Workbook
Name 변수H: 변수!$C$1:$AO$1
Name 환율: 변수!$C$6:$AO$13
Name BS연결H: BS연결!$C$1:$AO$1
Name BS연결: BS연결!$C$5:$AO$105
Name BS별도H: BS별도!$C$1:$AO$1
Name BS별도: BS별도!$C$5:$AO$91
Name SUBQH: subQ!$A$1:$AO$1
Name subQ: subQ!$A$5:$AO$41

Sheet README
A1: 한일철강(002220) 실적 모델 — ARGUS 한국조선
A2: 기준 분기 2026Q2 · 마지막 실적 2026Q2 · 생성 2026-10-13
A3: 모든 수치는 모델 산출값(DART 공개 재무제표 + 우리 추정)이다 — 목표주가·투자 추천 아님. 참고용 · 투자조언 아님.
A5: 시트
A6: 변수 가정 시계열. 환율 8행(ECB via frankfurter — L2 fx.json; 추정 분기 = 노란 가정), 추정 드라이버(노란 셀 = 모델값에서 역산한 가정, 바꾸면 재계산; 연녹 셀 = 3절 스칼라 참조 수식), 3절 스칼라 가정(세율·판관비율·지배주주비중·이자율·종가·PER 밴드·COE·외화 순노출·헤지비율)
A7: BS연결/BS별도 FnGuide 계정명 × 기간 값 덤프(백만원). 행1 분기라벨, 행4 YYYY.MM / YYYY.12A. 이름정의 BS연결H·BS연결(계정명 C열부터)
A8: subQ 분기 서브모델(억원 = 백만원/100). 확정 행: =IFERROR(VLOOKUP($D행,BS연결,MATCH(E$1,BS연결H,0),0)/100,"") 추정 행: 변수 시트 가정 셀 참조 수식. 외환손익·파생상품손익은 BS 계정 합·차, 기타금융손익은 잔차, OPM·EPS·BPS·PER·PBR 은 파생 수식
A9: SLS 선표(조선사만, sls json 있을 때): 요약 행(sls 저장값) + 계약별 스케줄(백만$) × (헤지비율 × 헤지환율 + (1−헤지비율) × 건조시점 환율[변수 원/달러(평균)]) → 원화 수식 블록 → 합계 행이 subQ 매출조선에 연결
A10: 시나리오 신규수주 보수/기준/낙관(forecast_panel 패널, 모델에 scenarios 가 있을 때만): 매출액·영업이익 = subQ 기준값 ± (시나리오 신규 − base 신규) × OPM. base 만 subQ 행에 포함, 나머지는 합산 안 함
A11: 분기/연간예상 subQ 를 이름(A열 key)으로 VLOOKUP 한 보고서 표(억원)
A12: TP PER 밴드 × 12M fwd EPS, PBR = ROE/COE × BPS — 모델 산출값 구간, 목표주가·추천 아님
A13: 외화 환율 QoQ, 외화 순노출 × Δ기말환율 → 환관련손익 추정
... A34: 백테스트: {"freeze": "2025Q2", "horizon": 4, "revenue_wape_pct": 20.5, "op_wape_pct": 88.9, "n": 4, "note": "단일 회사 4분기 — 통계 아님", "driver_at_freeze": "trend_seasonal", "selection_oos_at_freeze": null, "frozen_inputs": "fin(연결/별도)·고객 조선사 모델·지주 자회사 모델은 2025Q2 까지의 분기만; 선표는 체결일 ≤ 2025Q2 말일 계약(원장 최신 금액·코호트 등급, 환산 없음); 잔고는 yards_cache 2025Q2; 시세·환율 forward·prices·forecast_panel 신규수주 미사용. 고객 가중치(suppliers.json 언급 비중)와 합병 체인링크는 현재 지식; 고객 연동 채택은 동결 모델 안에서도 자기 la−4분기 OOS 규칙(selection_oos_at_freeze)", "detail": [{"q": "2025Q3", "rev_pred": 420.44, "rev_act": 508.41, "op_pred": 2.4, "op_act": 14.24}, {"q": "2025Q4", "rev_pred": 537.81, "rev_act": 456.95, "op_pred": 3.08, "op_act": 0.26}, {"q": "2026Q1", "rev_pred": 475.16, "rev_act": 618.74, "op_pred": 2.72, "op_act": 4.63}, {"q": "2026Q2", "rev_pred": 478.52, "rev_act": 617.57, "op_pred": 2.74, "op_act": 28.56}]}

Sheet 변수
C1: 이름: 변수H | E1: 4Q21 | F1: 2021 | G1: 1Q22 | H1: 2Q22 | I1: 3Q22 | J1: 4Q22 | K1: 2022 | L1: 1Q23 | M1: 2Q23 | N1: 3Q23 | O1: 4Q23 | P1: 2023 | Q1: 1Q24 | R1: 2Q24 | S1: 3Q24 | T1: 4Q24 | U1: 2024 | V1: 1Q25 | W1: 2Q25 | X1: 3Q25 | Y1: 4Q25 | Z1: 2025 | AA1: 1Q26 | AB1: 2Q26 | AC1: 3Q26 | AD1: 4Q26 | AE1: 2026 | AF1: 1Q27 | AG1: 2Q27 | AH1: 3Q27 | AI1: 4Q27 | AJ1: 2027 | AK1: 1Q28 | AL1: 2Q28 | AM1: 3Q28 | AN1: 4Q28 | AO1: 2028
A2: 가정 시계열 — 노란 셀은 추정 가정(모델값에서 역산), 연녹 셀은 3절 스칼라 참조 수식. 바꾸면 subQ·분기·연간예상·TP·시나리오가 재계산됩니다.
E3: 1 | F3: 2 | G3: 3 | H3: 4 | I3: 5 | J3: 6 | K3: 7 | L3: 8 | M3: 9 | N3: 10 | O3: 11 | P3: 12 | Q3: 13 | R3: 14 | S3: 15 | T3: 16 | U3: 17 | V3: 18 | W3: 19 | X3: 20 | Y3: 21 | Z3: 22 | AA3: 23 | AB3: 24 | AC3: 25 | AD3: 26 | AE3: 27 | AF3: 28 | AG3: 29 | AH3: 30 | AI3: 31 | AJ3: 32 | AK3: 33 | AL3: 34 | AM3: 35 | AN3: 36 | AO3: 37
E4: 2021.12 | F4: 2021.12A | G4: 2022.03 | H4: 2022.06 | I4: 2022.09 | J4: 2022.12 | K4: 2022.12A | L4: 2023.03 | M4: 2023.06 | N4: 2023.09 | O4: 2023.12 | P4: 2023.12A | Q4: 2024.03 | R4: 2024.06 | S4: 2024.09 | T4: 2024.12 | U4: 2024.12A | V4: 2025.03 | W4: 2025.06 | X4: 2025.09 | Y4: 2025.12 | Z4: 2025.12A | AA4: 2026.03 | AB4: 2026.06 | AC4: 2026.09 | AD4: 2026.12 | AE4: 2026.12A | AF4: 2027.03 | AG4: 2027.06 | AH4: 2027.09 | AI4: 2027.12 | AJ4: 2027.12A | AK4: 2028.03 | AL4: 2028.06 | AM4: 2028.09 | AN4: 2028.12 | AO4: 2028.12A
B5: 1. FX | C5: 이름: 환율
A6: USDKRW_avg | C6: 원/달러(평균) | E6: 1183.5 | F6: 1145.51 | G6: 1205.78 | H6: 1262.09 | I6: 1341.93 | J6: 1360.12 | K6: 1292.98 | L6: 1276.95 | M6: 1315.69 | N6: 1313.62 | O6: 1322.01 | P6: 1306.85 | Q6: 1330.14 | R6: 1371.28 | S6: 1356.22 | T6: 1396.3 | U6: 1363.53 | V6: 1452.28 | W6: 1398.52 | X6: 1386.95 | Y6: 1449.19 | Z6: 1421.52 | AA6: 1466.12 | AB6: 1501.75 | AC6: 1418.75 | AD6: 1343.63 | AE6: 1456.58 | AF6: 1333.09 | AG6: 1333.09 | AH6: 1333.09 | AI6: 1333.09 | AK6: 1333.09 | AL6: 1333.09 | AM6: 1333.09 | AN6: 1333.09
A7: USDKRW_end | C7: 원/달러(기말) | E7: 1188.75 | F7: 1188.75 | G7: 1213.74 | H7: 1301.24 | I7: 1436.9 | J7: 1260.16 | K7: 1260.16 | L7: 1305.99 | M7: 1321.44 | N7: 1345.35 | O7: 1297.43 | P7: 1297.43 | Q7: 1349.25 | R7: 1377.73 | S7: 1312.17 | T7: 1474.78 | U7: 1474.78 | V7: 1474.54 | W7: 1355.13 | X7: 1403.67 | Y7: 1444.2 | Z7: 1444.2 | AA7: 1524.8 | AB7: 1550.89 | AC7: 1355.4 | AD7: 1333.09 | AE7: 1333.09 | AF7: 1333.09 | AG7: 1333.09 | AH7: 1333.09 | AI7: 1333.09 | AK7: 1333.09 | AL7: 1333.09 | AM7: 1333.09 | AN7: 1333.09
A8: JPY100KRW_avg | C8: 원/100Y(평균) | E8: 1041.02 | F8: 1042.74 | G8: 1036.79 | H8: 972.23 | I8: 970.61 | J8: 961.03 | K8: 985.1 | L8: 964.89 | M8: 957.36 | N8: 909 | O8: 893.22 | P8: 931.11 | Q8: 896.29 | R8: 880.14 | S8: 909.35 | T8: 917.25 | U8: 900.92 | V8: 952.59 | W8: 967.92 | X8: 940.32 | Y8: 940.77 | Z8: 950.17 | AA8: 934.39 | AB8: 942.16 | AC8: 890.41 | AD8: 849.51 | AE8: 918.81 | AF8: 840.54 | AG8: 840.54 | AH8: 840.54 | AI8: 840.54 | AK8: 840.54 | AL8: 840.54 | AM8: 840.54 | AN8: 840.54
A9: JPY100KRW_end | C9: 원/100Y(기말) | E9: 1032.62 | F9: 1032.62 | G9: 996.83 | H9: 954.9 | I9: 993.29 | J9: 955.54 | K9: 955.54 | L9: 980.62 | M9: 913.67 | N9: 901.47 | O9: 917.04 | P9: 917.04 | Q9: 892.42 | R9: 857.76 | S9: 919.21 | T9: 939.65 | U9: 939.65 | V9: 986.84 | W9: 938.85 | X9: 948.49 | Y9: 921.81 | Z9: 921.81 | AA9: 955.99 | AB9: 954.75 | AC9: 863.31 | AD9: 840.54 | AE9: 840.54 | AF9: 840.54 | AG9: 840.54 | AH9: 840.54 | AI9: 840.54 | AK9: 840.54 | AL9: 840.54 | AM9: 840.54 | AN9: 840.54
A10: EURKRW_avg | C10: W/Euro(평균) | E10: 1353.32 | F10: 1354.06 | G10: 1352.29 | H10: 1343.31 | I10: 1350.63 | J10: 1386.07 | K10: 1358.07 | L10: 1369.93 | M10: 1432.41 | N10: 1429.41 | O10: 1420.91 | P10: 1412.88 | Q10: 1444.21 | R10: 1476.42 | S10: 1489.3 | T10: 1490.78 | U10: 1475.4 | V10: 1528.33 | W10: 1585.13 | X10: 1620.04 | Y10: 1686.02 | Z10: 1605.45 | AA10: 1715.47 | AB10: 1746.09 | AC10: 1631.97 | AD10: 1507.34 | AE10: 1688.95 | AF10: 1490.54 | AG10: 1490.54 | AH10: 1490.54 | AI10: 1490.54 | AK10: 1490.54 | AL10: 1490.54 | AM10: 1490.54 | AN10: 1490.54
A11: EURKRW_end | C11: W/Euro(기말) | E11: 1346.38 | F11: 1346.38 | G11: 1347.37 | H11: 1351.6 | I11: 1400.62 | J11: 1344.08 | K11: 1344.08 | L11: 1420.26 | M11: 1435.88 | N11: 1425.26 | O11: 1433.66 | P11: 1433.66 | Q11: 1458.68 | R11: 1474.86 | S11: 1469.1 | T11: 1532.14 | U11: 1532.14 | V11: 1594.72 | W11: 1588.22 | X11: 1648.04 | Y11: 1696.94 | Z11: 1696.94 | AA11: 1753.21 | AB11: 1767.09 | AC11: 1539.06 | AD11: 1490.54 | AE11: 1490.54 | AF11: 1490.54 | AG11: 1490.54 | AH11: 1490.54 | AI11: 1490.54 | AK11: 1490.54 | AL11: 1490.54 | AM11: 1490.54 | AN11: 1490.54
A12: CNYKRW_avg | C12: 원/중국원(평균) | E12: 185.14 | F12: 177.65 | G12: 189.93 | H12: 190.76 | I12: 195.79 | J12: 191.09 | K12: 191.93 | L12: 186.59 | M12: 187.45 | N12: 181.28 | O12: 182.86 | P12: 184.52 | Q12: 185.04 | R12: 189.35 | S12: 189.24 | T12: 194.24 | U12: 189.49 | V12: 199.63 | W12: 193.41 | X12: 193.79 | Y12: 204.38 | Z12: 197.8 | AA12: 211.75 | AB12: 220.8 | AC12: 210.43 | AD12: 200.5 | AE12: 213.68 | AF12: 199.18 | AG12: 199.18 | AH12: 199.18 | AI12: 199.18 | AK12: 199.18 | AL12: 199.18 | AM12: 199.18 | AN12: 199.18
A13: CNYKRW_end | C13: 원/중국원(기말) | E13: 187.13 | F13: 187.13 | G13: 191.38 | H13: 194.13 | I13: 201.92 | J13: 182.67 | K13: 182.67 | L13: 189.97 | M13: 181.8 | N13: 184.26 | O13: 182.61 | P13: 182.61 | Q13: 186.66 | R13: 189.7 | S13: 187.12 | T13: 202.04 | U13: 202.04 | V13: 203.3 | W13: 189.14 | X13: 197.16 | Y13: 206.28 | Z13: 206.28 | AA13: 220.97 | AB13: 228.56 | AC13: 202.16 | AD13: 199.18 | AE13: 199.18 | AF13: 199.18 | AG13: 199.18 | AH13: 199.18 | AI13: 199.18 | AK13: 199.18 | AL13: 199.18 | AM13: 199.18 | AN13: 199.18
B14: 1b. 종가
A15: price_close_end | C15: 종가(기말) | E15: 2675 | G15: 4050 | H15: 3785 | I15: 3335 | J15: 2815 | L15: 3060 | M15: 3375 | N15: 2720 | O15: 2390 | Q15: 2640 | R15: 2310 | S15: 2030 | T15: 1910 | V15: 1834 | W15: 2550 | X15: 3310 | Y15: 5070 | AA15: 3835 | AB15: 4205 | AC15: 2830 | AD15: 2900
A16: price_high | C16: 종가(최고) | E16: 3635 | G16: 4700 | H16: 6730 | I16: 4705 | J16: 3900 | L16: 3525 | M16: 4065 | N16: 3470 | O16: 2760 | Q16: 2890 | R16: 2765 | S16: 2305 | T16: 2190 | V16: 2025 | W16: 3060 | X16: 3600 | Y16: 5500 | AA16: 5700 | AB16: 6470 | AC16: 4770 | AD16: 3150
A17: price_low | C17: 종가(최저) | E17: 2495 | G17: 2675 | H17: 3400 | I17: 3275 | J17: 2755 | L17: 2640 | M17: 2970 | N17: 2635 | O17: 2245 | Q17: 2330 | R17: 2265 | S17: 1950 | T17: 1854 | V17: 1609 | W17: 1765 | X17: 2485 | Y17: 3190 | AA17: 3500 | AB17: 3810 | AC17: 2330 | AD17: 2725
A18: price_avg | C18: 종가(평균) | E18: 2948.2 | G18: 3349.1 | H18: 4652.4 | I18: 3941.8 | J18: 3124.7 | L18: 3078.4 | M18: 3248.4 | N18: 3082.1 | O18: 2531.2 | Q18: 2554.8 | R18: 2421.8 | S18: 2123.5 | T18: 1995.6 | V18: 1890.9 | W18: 2159.9 | X18: 2976 | Y18: 4424.1 | AA18: 4393.9 | AB18: 4846.3 | AC18: 3358.6 | AD18: 2882.9
B20: 2. 추정 드라이버 | C20: 실적 열 = subQ 실현값(수식), 추정 열 = 가정(노란 = 모델값 역산, 연녹 = 3절 스칼라 참조)
A21: drv:매출액 | B21: yoy | C21: 매출액 YoY | J21: =IFERROR(subQ!J5/subQ!E5-1,"") | L21: =IFERROR(subQ!L5/subQ!G5-1,"") | M21: =IFERROR(subQ!M5/subQ!H5-1,"") | N21: =IFERROR(subQ!N5/subQ!I5-1,"") | O21: =IFERROR(subQ!O5/subQ!J5-1,"") | Q21: =IFERROR(subQ!Q5/subQ!L5-1,"") | R21: =IFERROR(subQ!R5/subQ!M5-1,"") | S21: =IFERROR(subQ!S5/subQ!N5-1,"") | T21: =IFERROR(subQ!T5/subQ!O5-1,"") | V21: =IFERROR(subQ!V5/subQ!Q5-1,"") | W21: =IFERROR(subQ!W5/subQ!R5-1,"") | X21: =IFERROR(subQ!X5/subQ!S5-1,"") | Y21: =IFERROR(subQ!Y5/subQ!T5-1,"") | AA21: =IFERROR(subQ!AA5/subQ!V5-1,"") | AB21: =IFERROR(subQ!AB5/subQ!W5-1,"") | AC21: 0.099663008 | AD21: 0.099655981 | AF21: 0.099660534 | AG21: 0.099661432 | AH21: 0.04981398 | AI21: 0.049831837 | AK21: 0.049823633 | AL21: 0.049814466 | AM21: 0.024926311 | AN21: 0.024908536
A22: drv:판관비 | B22: ratio | C22: 판관비율(/매출) | E22: =IFERROR(subQ!E8/subQ!E5,"") | F22: =IFERROR(subQ!F8/subQ!F5,"") | G22: =IFERROR(subQ!G8/subQ!G5,"") | H22: =IFERROR(subQ!H8/subQ!H5,"") | I22: =IFERROR(subQ!I8/subQ!I5,"") | J22: =IFERROR(subQ!J8/subQ!J5,"") | K22: =IFERROR(subQ!K8/subQ!K5,"") | L22: =IFERROR(subQ!L8/subQ!L5,"") | ... AB22: =IFERROR(subQ!AB8/subQ!AB5,"") | AC22: =$D$50 | AD22: =$D$50 | AE22: =IFERROR(subQ!AE8/subQ!AE5,"") | AF22: =$D$50 | AG22: =$D$50 | AH22: =$D$50 | AI22: =$D$50 | AJ22: =IFERROR(subQ!AJ8/subQ!AJ5,"") | AK22: =$D$50 | AL22: =$D$50 | AM22: =$D$50 | AN22: =$D$50 | AO22: =IFERROR(subQ!AO8/subQ!AO5,"")
A23: drv:영업이익 | B23: ratio | C23: 영업이익률(OPM) | E23: =IFERROR(subQ!E9/subQ!E5,"") | F23: =IFERROR(subQ!F9/subQ!F5,"") | G23: =IFERROR(subQ!G9/subQ!G5,"") | H23: =IFERROR(subQ!H9/subQ!H5,"") | I23: =IFERROR(subQ!I9/subQ!I5,"") | J23: =IFERROR(subQ!J9/subQ!J5,"") | K23: =IFERROR(subQ!K9/subQ!K5,"") | L23: =IFERROR(subQ!L9/subQ!L5,"") | ... AB23: =IFERROR(subQ!AB9/subQ!AB5,"") | AC23: 0.005652143 | AD23: 0.005651854 | AE23: =IFERROR(subQ!AE9/subQ!AE5,"") | AF23: 0.005643739 | AG23: 0.005639651 | AH23: 0.005639514 | AI23: 0.005648968 | AJ23: =IFERROR(subQ!AJ9/subQ!AJ5,"") | AK23: 0.005641887 | AL23: 0.005638544 | AM23: 0.005651972 | AN23: 0.005641149 | AO23: =IFERROR(subQ!AO9/subQ!AO5,"")
A24: drv:외환손익 | B24: abs | C24: 외환손익 (가정, 억원) | E24: =subQ!E13 | F24: =subQ!F13 | G24: =subQ!G13 | H24: =subQ!H13 | I24: =subQ!I13 | J24: =subQ!J13 | K24: =subQ!K13 | L24: =subQ!L13 | ... AB24: =subQ!AB13 | AC24: 0 | AD24: 0 | AE24: =subQ!AE13 | AF24: 0 | AG24: 0 | AH24: 0 | AI24: 0 | AJ24: =subQ!AJ13 | AK24: 0 | AL24: 0 | AM24: 0 | AN24: 0 | AO24: =subQ!AO13
A25: drv:기타영업외손익 | B25: abs | C25: 기타영업외손익 (가정, 억원) | E25: =subQ!E14 | F25: =subQ!F14 | G25: =subQ!G14 | H25: =subQ!H14 | I25: =subQ!I14 | J25: =subQ!J14 | K25: =subQ!K14 | L25: =subQ!L14 | ... AB25: =subQ!AB14 | AC25: 0 | AD25: 0 | AE25: =subQ!AE14 | AF25: 0 | AG25: 0 | AH25: 0 | AI25: 0 | AJ25: =subQ!AJ14 | AK25: 0 | AL25: 0 | AM25: 0 | AN25: 0 | AO25: =subQ!AO14
A26: drv:지분법손익 | B26: abs | C26: 지분법손익 (가정, 억원) | E26: =subQ!E15 | F26: =subQ!F15 | G26: =subQ!G15 | H26: =subQ!H15 | I26: =subQ!I15 | J26: =subQ!J15 | K26: =subQ!K15 | L26: =subQ!L15 | ... AB26: =subQ!AB15 | AC26: 4.94 | AD26: 4.94 | AE26: =subQ!AE15 | AF26: 4.94 | AG26: 4.94 | AH26: 4.94 | AI26: 4.94 | AJ26: =subQ!AJ15 | AK26: 4.94 | AL26: 4.94 | AM26: 4.94 | AN26: 4.94 | AO26: =subQ!AO15
A27: drv:법인세비용 | B27: ratio | C27: 법인세율(/세전) | E27: =IFERROR(subQ!E17/subQ!E16,"") | F27: =IFERROR(subQ!F17/subQ!F16,"") | G27: =IFERROR(subQ!G17/subQ!G16,"") | H27: =IFERROR(subQ!H17/subQ!H16,"") | I27: =IFERROR(subQ!I17/subQ!I16,"") | J27: =IFERROR(subQ!J17/subQ!J16,"") | K27: =IFERROR(subQ!K17/subQ!K16,"") | L27: =IFERROR(subQ!L17/subQ!L16,"") | ... AB27: =IFERROR(subQ!AB17/subQ!AB16,"") | AC27: 0 | AD27: 0 | AE27: =IFERROR(subQ!AE17/subQ!AE16,"") | AF27: 0 | AG27: 0 | AH27: 0 | AI27: 0 | AJ27: =IFERROR(subQ!AJ17/subQ!AJ16,"") | AK27: 0 | AL27: 0 | AM27: 0 | AN27: 0 | AO27: =IFERROR(subQ!AO17/subQ!AO16,"")
A28: drv:지배주주순이익 | B28: ratio | C28: 지배주주 비중(/당기순이익) | E28: =IFERROR(subQ!E19/subQ!E18,"") | F28: =IFERROR(subQ!F19/subQ!F18,"") | G28: =IFERROR(subQ!G19/subQ!G18,"") | H28: =IFERROR(subQ!H19/subQ!H18,"") | I28: =IFERROR(subQ!I19/subQ!I18,"") | J28: =IFERROR(subQ!J19/subQ!J18,"") | K28: =IFERROR(subQ!K19/subQ!K18,"") | L28: =IFERROR(subQ!L19/subQ!L18,"") | ... AB28: =IFERROR(subQ!AB19/subQ!AB18,"") | AC28: =$D$51 | AD28: =$D$51 | AE28: =IFERROR(subQ!AE19/subQ!AE18,"") | AF28: =$D$51 | AG28: =$D$51 | AH28: =$D$51 | AI28: =$D$51 | AJ28: =IFERROR(subQ!AJ19/subQ!AJ18,"") | AK28: =$D$51 | AL28: =$D$51 | AM28: =$D$51 | AN28: =$D$51 | AO28: =IFERROR(subQ!AO19/subQ!AO18,"")
A29: drv:부채총계 | B29: qoq | C29: 부채총계 QoQ | G29: =IFERROR(subQ!G21/subQ!E21-1,"") | H29: =IFERROR(subQ!H21/subQ!G21-1,"") | I29: =IFERROR(subQ!I21/subQ!H21-1,"") | J29: =IFERROR(subQ!J21/subQ!I21-1,"") | L29: =IFERROR(subQ!L21/subQ!J21-1,"") | M29: =IFERROR(subQ!M21/subQ!L21-1,"") | N29: =IFERROR(subQ!N21/subQ!M21-1,"") | O29: =IFERROR(subQ!O21/subQ!N21-1,"") | Q29: =IFERROR(subQ!Q21/subQ!O21-1,"") | R29: =IFERROR(subQ!R21/subQ!Q21-1,"") | S29: =IFERROR(subQ!S21/subQ!R21-1,"") | T29: =IFERROR(subQ!T21/subQ!S21-1,"") | V29: =IFERROR(subQ!V21/subQ!T21-1,"") | W29: =IFERROR(subQ!W21/subQ!V21-1,"") | X29: =IFERROR(subQ!X21/subQ!W21-1,"") | Y29: =IFERROR(subQ!Y21/subQ!X21-1,"") | AA29: =IFERROR(subQ!AA21/subQ!Y21-1,"") | AB29: =IFERROR(subQ!AB21/subQ!AA21-1,"") | AC29: 3.43e-07 | AD29: 0 | AF29: 0 | AG29: 0 | AH29: 0 | AI29: 0 | AK29: 0 | AL29: 0 | AM29: 0 | AN29: 0
A30: drv:자본총계 | B30: roll | C30: 자본총계 기타변동(배당 등, 억원) | G30: =IFERROR(subQ!E22+subQ!G18-subQ!G22,"") | H30: =IFERROR(subQ!G22+subQ!H18-subQ!H22,"") | I30: =IFERROR(subQ!H22+subQ!I18-subQ!I22,"") | J30: =IFERROR(subQ!I22+subQ!J18-subQ!J22,"") | L30: =IFERROR(subQ!J22+subQ!L18-subQ!L22,"") | M30: =IFERROR(subQ!L22+subQ!M18-subQ!M22,"") | N30: =IFERROR(subQ!M22+subQ!N18-subQ!N22,"") | O30: =IFERROR(subQ!N22+subQ!O18-subQ!O22,"") | Q30: =IFERROR(subQ!O22+subQ!Q18-subQ!Q22,"") | R30: =IFERROR(subQ!Q22+subQ!R18-subQ!R22,"") | S30: =IFERROR(subQ!R22+subQ!S18-subQ!S22,"") | T30: =IFERROR(subQ!S22+subQ!T18-subQ!T22,"") | V30: =IFERROR(subQ!T22+subQ!V18-subQ!V22,"") | W30: =IFERROR(subQ!V22+subQ!W18-subQ!W22,"") | X30: =IFERROR(subQ!W22+subQ!X18-subQ!X22,"") | Y30: =IFERROR(subQ!X22+subQ!Y18-subQ!Y22,"") | AA30: =IFERROR(subQ!Y22+subQ!AA18-subQ!AA22,"") | AB30: =IFERROR(subQ!AA22+subQ!AB18-subQ!AB22,"") | AC30: 0.011097911 | AD30: 0.00012058 | AF30: -0.001880475 | AG30: 7.1235981 | AH30: -0.000760963 | AI30: 0.008484846 | AK30: 0.004156655 | AL30: 7.1178071 | AM30: 0.001536749 | AN30: 0.008039599
A31: drv:지배주주지분 | B31: roll | C31: 지배주주지분 기타변동(배당 등, 억원) | G31: =IFERROR(subQ!E23+subQ!G19-subQ!G23,"") | H31: =IFERROR(subQ!G23+subQ!H19-subQ!H23,"") | I31: =IFERROR(subQ!H23+subQ!I19-subQ!I23,"") | J31: =IFERROR(subQ!I23+subQ!J19-subQ!J23,"") | L31: =IFERROR(subQ!J23+subQ!L19-subQ!L23,"") | M31: =IFERROR(subQ!L23+subQ!M19-subQ!M23,"") | N31: =IFERROR(subQ!M23+subQ!N19-subQ!N23,"") | O31: =IFERROR(subQ!N23+subQ!O19-subQ!O23,"") | Q31: =IFERROR(subQ!O23+subQ!Q19-subQ!Q23,"") | R31: =IFERROR(subQ!Q23+subQ!R19-subQ!R23,"") | S31: =IFERROR(subQ!R23+subQ!S19-subQ!S23,"") | T31: =IFERROR(subQ!S23+subQ!T19-subQ!T23,"") | V31: =IFERROR(subQ!T23+subQ!V19-subQ!V23,"") | W31: =IFERROR(subQ!V23+subQ!W19-subQ!W23,"") | X31: =IFERROR(subQ!W23+subQ!X19-subQ!X23,"") | Y31: =IFERROR(subQ!X23+subQ!Y19-subQ!Y23,"") | AA31: =IFERROR(subQ!Y23+subQ!AA19-subQ!AA23,"") | AB31: =IFERROR(subQ!AA23+subQ!AB19-subQ!AB23,"") | AC31: 0.005397911 | AD31: 0.01012058 | AF31: -0.001880475 | AG31: 7.1235981 | AH31: -0.000760963 | AI31: -0.001515154 | AK31: 0.004156655 | AL31: 7.1178071 | AM31: 0.011536749 | AN31: -0.001960401
A32: drv:총차입금 | B32: qoq | C32: 총차입금 QoQ | G32: =IFERROR(subQ!G24/subQ!E24-1,"") | H32: =IFERROR(subQ!H24/subQ!G24-1,"") | I32: =IFERROR(subQ!I24/subQ!H24-1,"") | J32: =IFERROR(subQ!J24/subQ!I24-1,"") | L32: =IFERROR(subQ!L24/subQ!J24-1,"") | M32: =IFERROR(subQ!M24/subQ!L24-1,"") | N32: =IFERROR(subQ!N24/subQ!M24-1,"") | O32: =IFERROR(subQ!O24/subQ!N24-1,"") | Q32: =IFERROR(subQ!Q24/subQ!O24-1,"") | R32: =IFERROR(subQ!R24/subQ!Q24-1,"") | S32: =IFERROR(subQ!S24/subQ!R24-1,"") | T32: =IFERROR(subQ!T24/subQ!S24-1,"") | V32: =IFERROR(subQ!V24/subQ!T24-1,"") | W32: =IFERROR(subQ!W24/subQ!V24-1,"") | X32: =IFERROR(subQ!X24/subQ!W24-1,"") | Y32: =IFERROR(subQ!Y24/subQ!X24-1,"") | AA32: =IFERROR(subQ!AA24/subQ!Y24-1,"") | AB32: =IFERROR(subQ!AB24/subQ!AA24-1,"") | AC32: 4.089e-06 | AD32: 0 | AF32: 0 | AG32: 0 | AH32: 0 | AI32: 0 | AK32: 0 | AL32: 0 | AM32: 0 | AN32: 0
A33: drv:순차입금 | B33: qoq | C33: 순차입금 QoQ | G33: =IFERROR(subQ!G25/subQ!E25-1,"") | H33: =IFERROR(subQ!H25/subQ!G25-1,"") | I33: =IFERROR(subQ!I25/subQ!H25-1,"") | J33: =IFERROR(subQ!J25/subQ!I25-1,"") | L33: =IFERROR(subQ!L25/subQ!J25-1,"") | M33: =IFERROR(subQ!M25/subQ!L25-1,"") | N33: =IFERROR(subQ!N25/subQ!M25-1,"") | O33: =IFERROR(subQ!O25/subQ!N25-1,"") | Q33: =IFERROR(subQ!Q25/subQ!O25-1,"") | R33: =IFERROR(subQ!R25/subQ!Q25-1,"") | S33: =IFERROR(subQ!S25/subQ!R25-1,"") | T33: =IFERROR(subQ!T25/subQ!S25-1,"") | V33: =IFERROR(subQ!V25/subQ!T25-1,"") | W33: =IFERROR(subQ!W25/subQ!V25-1,"") | X33: =IFERROR(subQ!X25/subQ!W25-1,"") | Y33: =IFERROR(subQ!Y25/subQ!X25-1,"") | AA33: =IFERROR(subQ!AA25/subQ!Y25-1,"") | AB33: =IFERROR(subQ!AB25/subQ!AA25-1,"") | AC33: 0.014156745 | AD33: 0.014482704 | AF33: 0.013115304 | AG33: 0.022123218 | AH33: 0.013599342 | AI33: 0.013932916 | AK33: 0.012590277 | AL33: 0.021061953 | AM33: 0.013196911 | AN33: 0.013522424
A34: drv:이자발생자산 | B34: qoq | C34: 이자발생자산 QoQ | G34: =IFERROR(subQ!G26/subQ!E26-1,"") | H34: =IFERROR(subQ!H26/subQ!G26-1,"") | I34: =IFERROR(subQ!I26/subQ!H26-1,"") | J34: =IFERROR(subQ!J26/subQ!I26-1,"") | L34: =IFERROR(subQ!L26/subQ!J26-1,"") | M34: =IFERROR(subQ!M26/subQ!L26-1,"") | N34: =IFERROR(subQ!N26/subQ!M26-1,"") | O34: =IFERROR(subQ!O26/subQ!N26-1,"") | Q34: =IFERROR(subQ!Q26/subQ!O26-1,"") | R34: =IFERROR(subQ!R26/subQ!Q26-1,"") | S34: =IFERROR(subQ!S26/subQ!R26-1,"") | T34: =IFERROR(subQ!T26/subQ!S26-1,"") | V34: =IFERROR(subQ!V26/subQ!T26-1,"") | W34: =IFERROR(subQ!W26/subQ!V26-1,"") | X34: =IFERROR(subQ!X26/subQ!W26-1,"") | Y34: =IFERROR(subQ!Y26/subQ!X26-1,"") | AA34: =IFERROR(subQ!AA26/subQ!Y26-1,"") | AB34: =IFERROR(subQ!AB26/subQ!AA26-1,"") | AC34: -0.023105855 | AD34: -0.02453675 | AF34: -0.02310891 | AG34: -0.040402866 | AH34: -0.026469519 | AI34: -0.028259841 | AK34: -0.026621912 | AL34: -0.046329201 | AM34: -0.031052472 | AN34: -0.033329535
A35: drv:현금및현금성자산 | B35: qoq | C35: 현금및현금성자산 QoQ | G35: =IFERROR(subQ!G27/subQ!E27-1,"") | H35: =IFERROR(subQ!H27/subQ!G27-1,"") | I35: =IFERROR(subQ!I27/subQ!H27-1,"") | J35: =IFERROR(subQ!J27/subQ!I27-1,"") | L35: =IFERROR(subQ!L27/subQ!J27-1,"") | M35: =IFERROR(subQ!M27/subQ!L27-1,"") | N35: =IFERROR(subQ!N27/subQ!M27-1,"") | O35: =IFERROR(subQ!O27/subQ!N27-1,"") | Q35: =IFERROR(subQ!Q27/subQ!O27-1,"") | R35: =IFERROR(subQ!R27/subQ!Q27-1,"") | S35: =IFERROR(subQ!S27/subQ!R27-1,"") | T35: =IFERROR(subQ!T27/subQ!S27-1,"") | V35: =IFERROR(subQ!V27/subQ!T27-1,"") | W35: =IFERROR(subQ!W27/subQ!V27-1,"") | X35: =IFERROR(subQ!X27/subQ!W27-1,"") | Y35: =IFERROR(subQ!Y27/subQ!X27-1,"") | AA35: =IFERROR(subQ!AA27/subQ!Y27-1,"") | AB35: =IFERROR(subQ!AB27/subQ!AA27-1,"")
A36: drv:CAPEX | B36: yoy | C36: CAPEX YoY | J36: =IFERROR(subQ!J28/subQ!E28-1,"") | L36: =IFERROR(subQ!L28/subQ!G28-1,"") | M36: =IFERROR(subQ!M28/subQ!H28-1,"") | N36: =IFERROR(subQ!N28/subQ!I28-1,"") | O36: =IFERROR(subQ!O28/subQ!J28-1,"") | Q36: =IFERROR(subQ!Q28/subQ!L28-1,"") | R36: =IFERROR(subQ!R28/subQ!M28-1,"") | S36: =IFERROR(subQ!S28/subQ!N28-1,"") | T36: =IFERROR(subQ!T28/subQ!O28-1,"") | V36: =IFERROR(subQ!V28/subQ!Q28-1,"") | W36: =IFERROR(subQ!W28/subQ!R28-1,"") | X36: =IFERROR(subQ!X28/subQ!S28-1,"") | Y36: =IFERROR(subQ!Y28/subQ!T28-1,"") | AA36: =IFERROR(subQ!AA28/subQ!V28-1,"") | AB36: =IFERROR(subQ!AB28/subQ!W28-1,"") | AC36: 0.41411615 | AD36: -0.46536495 | AF36: 0.49450985 | AG36: -0.22634862 | AH36: 0 | AI36: 0 | AK36: 0 | AL36: 0 | AM36: 0 | AN36: 0
A37: drv:영업활동현금흐름 | B37: yoy | C37: 영업활동현금흐름 YoY | J37: =IFERROR(subQ!J29/subQ!E29-1,"") | L37: =IFERROR(subQ!L29/subQ!G29-1,"") | M37: =IFERROR(subQ!M29/subQ!H29-1,"") | N37: =IFERROR(subQ!N29/subQ!I29-1,"") | O37: =IFERROR(subQ!O29/subQ!J29-1,"") | Q37: =IFERROR(subQ!Q29/subQ!L29-1,"") | R37: =IFERROR(subQ!R29/subQ!M29-1,"") | S37: =IFERROR(subQ!S29/subQ!N29-1,"") | T37: =IFERROR(subQ!T29/subQ!O29-1,"") | V37: =IFERROR(subQ!V29/subQ!Q29-1,"") | W37: =IFERROR(subQ!W29/subQ!R29-1,"") | X37: =IFERROR(subQ!X29/subQ!S29-1,"") | Y37: =IFERROR(subQ!Y29/subQ!T29-1,"") | AA37: =IFERROR(subQ!AA29/subQ!V29-1,"") | AB37: =IFERROR(subQ!AB29/subQ!W29-1,"")
A38: drv:주식수 | B38: qoq | C38: 주식수 QoQ | G38: =IFERROR(subQ!G30/subQ!E30-1,"") | H38: =IFERROR(subQ!H30/subQ!G30-1,"") | I38: =IFERROR(subQ!I30/subQ!H30-1,"") | J38: =IFERROR(subQ!J30/subQ!I30-1,"") | L38: =IFERROR(subQ!L30/subQ!J30-1,"") | M38: =IFERROR(subQ!M30/subQ!L30-1,"") | N38: =IFERROR(subQ!N30/subQ!M30-1,"") | O38: =IFERROR(subQ!O30/subQ!N30-1,"") | Q38: =IFERROR(subQ!Q30/subQ!O30-1,"") | R38: =IFERROR(subQ!R30/subQ!Q30-1,"") | S38: =IFERROR(subQ!S30/subQ!R30-1,"") | T38: =IFERROR(subQ!T30/subQ!S30-1,"") | V38: =IFERROR(subQ!V30/subQ!T30-1,"") | W38: =IFERROR(subQ!W30/subQ!V30-1,"") | X38: =IFERROR(subQ!X30/subQ!W30-1,"") | Y38: =IFERROR(subQ!Y30/subQ!X30-1,"") | AA38: =IFERROR(subQ!AA30/subQ!Y30-1,"") | AB38: =IFERROR(subQ!AB30/subQ!AA30-1,"") | AC38: 0 | AD38: 0 | AF38: 0 | AG38: 0 | AH38: 0 | AI38: 0 | AK38: 0 | AL38: 0 | AM38: 0 | AN38: 0
A39: drv:DPS | B39: abs | C39: DPS (가정, 원) | E39: =subQ!E33 | F39: =subQ!F33 | G39: =subQ!G33 | H39: =subQ!H33 | I39: =subQ!I33 | J39: =subQ!J33 | K39: =subQ!K33 | L39: =subQ!L33 | ... AB39: =subQ!AB33 | AD39: 30 | AE39: =subQ!AE33 | AI39: 30 | AJ39: =subQ!AJ33 | AN39: 30 | AO39: =subQ!AO33
B41: 3. 밸류에이션·스칼라 | C41: 노란 셀 = 가정. '연결' 표시는 추정 전 분기 수식이 이 셀을 참조한다는 뜻
A42: sc:종가 | C42: 종가 | D42: 2900 | E42: 원 — 네이버 정규장 종가(aik 확정종가 대조 · aik 3,020원)
A43: sc:기준일 | C43: 기준일 | D43: 20261013 | E43: 종가 기준일
A44: sc:COE | C44: COE | D44: 0.09 | E44: 자기자본비용(가정) — TP 적정 PBR = ROE/COE
A45: sc:PER_lo | C45: PER_lo | D45: 10 | E45: PER 밴드 하단(배) — sector_default(레퍼런스 TP_PE PB 예시 10/15/20배; 과거 PER 중위 99.3배가 3~40 밖(턴어라운드 왜곡))
A46: sc:PER_mid | C46: PER_mid | D46: 15 | E46: PER 밴드 중단(배)
A47: sc:PER_hi | C47: PER_hi | D47: 20 | E47: PER 밴드 상단(배)
A48: sc:EPS_Y1가중 | C48: EPS_Y1가중 | D48: 0.5 | E48: 12M fwd EPS = FY(last_actual연도)E × w + FY+1E × (1−w) — 기준 분기 2Q 이면 0.5(가정)
A49: sc:세율 | C49: 세율 | D49: 0.1667 | E49: 참고(연결 안 됨: MAX(세전,0)×단일 세율로 재현 불가(지주 자회사 합산 등) → 분기별 역산) — 모델 assumptions 값 · 최근 12분기 세전 합 ≤ 0 → 클립 대신 최근 8분기 중 세전 > 0 인 2분기(2025Q2~2026Q2)의 법인세/세전 중위 16.7%
A50: sc:판관비율 | C50: 판관비율 | D50: 0.06019954 | E50: 연결 — 판관비 = 매출액 × 판관비율(역산, 재현 오차 ≤ 0.05억 · 모델 assumptions 0.0602)
A51: sc:지배주주비중 | C51: 지배주주비중 | D51: 1 | E51: 연결 — 지배주주순이익 = 당기순이익 × 비중(역산, 재현 오차 ≤ 0.05억)
A52: sc:이자율_자산 | C52: 이자율_자산 | D52: 0.033243344 | E52: 연결 — 이자손익 = (전분기 이자발생자산 × 자산이자율 − 전분기 총차입금 × 부채이자율)/4(역산, 재현 오차 ≤ 0.05억 · 모델 assumptions 0.0332)
A53: sc:이자율_부채 | C53: 이자율_부채 | D53: 0.077004894 | E53: 연결 — 같은 수식의 부채 쪽(총차입금 행이 없으면 0)(역산, 재현 오차 ≤ 0.05억 · 모델 assumptions 0.077)
A54: sc:배당성향 | C54: 배당성향 | E54: 배당성향(참고 — 모델은 직전 DPS 유지·Q2 지급 가정)
A55: sc:외화순노출_백만$ | C55: 외화순노출_백만$ | E55: 외화 순노출 × Δ기말환율 (외화 시트 방식) — 외화 순노출 미공시(face) → 0 + 표기
A56: sc:헤지비율 | C56: 헤지비율 | E56: sls 없음
A57: sc:헤지환율_약정 | C57: 헤지환율_약정 | E57: sls 없음

Sheet BS연결
B1: (백만원) | C1: 이름: BS연결H | E1: 4Q21 | F1: 2021 | G1: 1Q22 | H1: 2Q22 | I1: 3Q22 | J1: 4Q22 | K1: 2022 | L1: 1Q23 | M1: 2Q23 | N1: 3Q23 | O1: 4Q23 | P1: 2023 | Q1: 1Q24 | R1: 2Q24 | S1: 3Q24 | T1: 4Q24 | U1: 2024 | V1: 1Q25 | W1: 2Q25 | X1: 3Q25 | Y1: 4Q25 | Z1: 2025 | AA1: 1Q26 | AB1: 2Q26 | AC1: 3Q26 | AD1: 4Q26 | AE1: 2026 | AF1: 1Q27 | AG1: 2Q27 | AH1: 3Q27 | AI1: 4Q27 | AJ1: 2027 | AK1: 1Q28 | AL1: 2Q28 | AM1: 3Q28 | AN1: 4Q28 | AO1: 2028
B2: 연결 | D2: fin json(kship_fin.py)
B3: 한일철강(연) | C3: UPDATE: 26-10-13 | E3: 1 | F3: 2 | G3: 3 | H3: 4 | I3: 5 | J3: 6 | K3: 7 | L3: 8 | M3: 9 | N3: 10 | O3: 11 | P3: 12 | Q3: 13 | R3: 14 | S3: 15 | T3: 16 | U3: 17 | V3: 18 | W3: 19 | X3: 20 | Y3: 21 | Z3: 22 | AA3: 23 | AB3: 24 | AC3: 25 | AD3: 26 | AE3: 27 | AF3: 28 | AG3: 29 | AH3: 30 | AI3: 31 | AJ3: 32 | AK3: 33 | AL3: 34 | AM3: 35 | AN3: 36 | AO3: 37
B4: Account Code | C4: AccountNAME | E4: 2021.12 | F4: 2021.12A | G4: 2022.03 | H4: 2022.06 | I4: 2022.09 | J4: 2022.12 | K4: 2022.12A | L4: 2023.03 | M4: 2023.06 | N4: 2023.09 | O4: 2023.12 | P4: 2023.12A | Q4: 2024.03 | R4: 2024.06 | S4: 2024.09 | T4: 2024.12 | U4: 2024.12A | V4: 2025.03 | W4: 2025.06 | X4: 2025.09 | Y4: 2025.12 | Z4: 2025.12A | AA4: 2026.03 | AB4: 2026.06 | AC4: 2026.09 | AD4: 2026.12 | AE4: 2026.12A | AF4: 2027.03 | AG4: 2027.06 | AH4: 2027.09 | AI4: 2027.12 | AJ4: 2027.12A | AK4: 2028.03 | AL4: 2028.06 | AM4: 2028.09 | AN4: 2028.12 | AO4: 2028.12A
A5: 1 | C5: 유동자산 | E5: 109937.95 | F5: 109937.95 | G5: 118389.01 | H5: 124221.47 | I5: 120714.71 | J5: 105439.73 | K5: 105439.73 | L5: 100867.84 | M5: 103150.61 | N5: 109295.75 | O5: 96584.58 | P5: 96584.58 | Q5: 94917.36 | R5: 99915.72 | S5: 100005.89 | T5: 102427.18 | U5: 102427.18 | V5: 106184.2 | W5: 98415.96 | X5: 109120.87 | Y5: 97807.54 | Z5: 97807.54 | AA5: 103061.93 | AB5: 129882.74
A6: 1 | C6: 현금및현금성자산 | E6: 12776.01 | F6: 12776.01 | G6: 8489.31 | H6: 11125.59 | I6: 7570.64 | J6: 12401.56 | K6: 12401.56 | L6: 12008.24 | M6: 10418.08 | N6: 10507.76 | O6: 12942.53 | P6: 12942.53 | Q6: 6171.37 | R6: 8915.64 | S6: 14674.49 | T6: 11719.23 | U6: 11719.23 | V6: 13164.5 | W6: 10230.18 | X6: 9647.29 | Y6: 5890.6 | Z6: 5890.6 | AA6: 14534.04 | AB6: 14412.5
A7: 1 | C7: 단기금융상품 | E7: 15764.23 | F7: 15764.23 | G7: 23915.86 | J7: 28060 | K7: 28060 | L7: 18860 | M7: 18860 | N7: 16960 | O7: 16960 | P7: 16960 | Q7: 16460 | R7: 16460 | S7: 17460 | T7: 22260 | U7: 22260 | V7: 24260 | W7: 24260 | X7: 23410 | Y7: 23410 | Z7: 23410 | AA7: 21410 | AB7: 27610
A8: 1 | C8: 단기금융자산 | E8: 15764.23 | F8: 15764.23 | G8: 23915.86 | J8: 28060 | K8: 28060 | L8: 18860 | M8: 18860 | N8: 16960 | O8: 16960 | P8: 16960 | Q8: 16460 | R8: 16460 | S8: 17460 | T8: 22260 | U8: 22260 | V8: 24260 | W8: 24260 | X8: 23410 | Y8: 23410 | Z8: 23410 | AA8: 21410 | AB8: 27610
A9: 1 | C9: 매출채권및기타채권 | E9: 37085.46 | F9: 37085.46 | G9: 41100.6 | H9: 36743.63 | I9: 39143.39 | J9: 36796.2 | K9: 36796.2 | L9: 34123.23 | M9: 31403.44 | N9: 33549.25 | O9: 30795.01 | P9: 30795.01 | Q9: 30030.49 | R9: 31252.87 | S9: 24368.33 | T9: 31744.1 | U9: 31744.1 | V9: 29160.69 | W9: 26084.76 | X9: 30811.22 | Y9: 27655.13 | Z9: 27655.13 | AA9: 40017.83 | AB9: 39561.82
A10: 1 | C10: 기타유동자산 | E10: 2311.65 | F10: 2311.65 | G10: 1648.85 | H10: 321.66 | I10: 1403.57 | J10: 159.22 | K10: 159.22 | L10: 108.21 | M10: 268.95 | N10: 355.02 | O10: 195.94 | P10: 195.94 | Q10: 670.66 | R10: 1196.03 | S10: 304.9 | T10: 1209.62 | U10: 1209.62 | V10: 1101.65 | W10: 808.89 | X10: 1429.32 | AA10: 1004.28 | AB10: 1033.6
A11: 1 | C11: 기타유동금융자산 | E11: 853.93 | F11: 853.93 | G11: 1142.6 | H11: 27724.32 | I11: 29300.95 | J11: 0 | K11: 0 | L11: 0 | M11: 0 | N11: 0 | O11: 0 | P11: 0 | Q11: 0 | R11: 0 | S11: 0 | T11: 0 | U11: 0 | V11: 0 | W11: 0 | X11: 0
A12: 1 | C12: 재고자산 | E12: 41146.48 | F12: 41146.48 | G12: 42652.67 | H12: 47805.07 | I12: 42796.59 | J12: 27056.33 | K12: 27056.33 | L12: 35222.56 | M12: 41631.71 | N12: 47241.83 | O12: 35045.74 | P12: 35045.74 | Q12: 41370.67 | R12: 42064.67 | S12: 38097.63 | T12: 35354.35 | U12: 35354.35 | V12: 38462.11 | W12: 36970.98 | X12: 43702.79 | Y12: 39224.09 | Z12: 39224.09 | AA12: 26063.29 | AB12: 47225.02
A13: 1 | C13: 당기법인세자산(선급법인세) | E13: 0.2 | F13: 0.2 | G13: -560.88 | H13: 0 | I13: 0 | J13: 463.92 | K13: 463.92 | L13: 36.16 | M13: 56.91 | N13: 168.11 | O13: 117.08 | P13: 117.08 | Q13: -35.69 | R13: 26.52 | S13: 100.54 | T13: 139.88 | U13: 139.88 | V13: 35.25 | W13: 61.15 | X13: 120.26 | Y13: 153.12 | Z13: 153.12 | AA13: 32.49 | AB13: 39.81
A14: 1 | C14: 비유동자산 | E14: 228804.89 | F14: 228804.89 | G14: 230737.7 | H14: 231574.9 | I14: 235241.32 | J14: 233715.25 | K14: 233715.25 | L14: 232023.34 | M14: 231521.2 | N14: 233192.62 | O14: 234444.41 | P14: 234444.41 | Q14: 234992.25 | R14: 236204.63 | S14: 235904.86 | T14: 238024.87 | U14: 238024.87 | V14: 236992.17 | W14: 236534.3 | X14: 236131.59 | Y14: 238311.7 | Z14: 238311.7 | AA14: 237987.52 | AB14: 240223.41
A15: 1 | C15: 장기금융자산 | E15: 2022.2 | F15: 2022.2 | G15: 2024.1 | H15: 1001.97 | I15: 1001.97 | J15: 1019.08 | K15: 1019.08 | L15: 1006.13 | M15: 1010.81 | N15: 1020.81 | O15: 1021.24 | P15: 1021.24 | Q15: 1026.54 | R15: 1025.2 | S15: 1025.36 | T15: 1026.43 | U15: 1026.43 | V15: 1025.4 | W15: 1026.75 | X15: 269.28 | Y15: 4756.97 | Z15: 4756.97 | AA15: 4160.83 | AB15: 4160.6
A16: 1 | C16: 투자자산 | E16: 19410.42 | F16: 19410.42 | G16: 20341.59 | H16: 19607.94 | I16: 20439.76 | J16: 19901.21 | K16: 19901.21 | L16: 19914.05 | M16: 19730.23 | N16: 20023.5 | O16: 19963.51 | P16: 19963.51 | Q16: 19996.52 | R16: 19441.4 | S16: 19283.03 | T16: 19786.7 | U16: 19786.7 | V16: 19886.32 | W16: 19664.93 | X16: 18580.16 | Y16: 4756.97 | Z16: 4756.97 | AA16: 4160.83 | AB16: 4160.6
A17: 1 | C17: 종속기업및관계기업투자 | E17: 17388.22 | F17: 17388.22 | G17: 18317.49 | H17: 18605.97 | I17: 19437.79 | J17: 18882.13 | K17: 18882.13 | L17: 18907.92 | M17: 18719.42 | N17: 19002.69 | O17: 18942.27 | P17: 18942.27 | Q17: 18969.98 | R17: 18416.2 | S17: 18257.67 | T17: 18760.27 | U17: 18760.27 | V17: 18860.92 | W17: 18638.18 | X17: 18310.88
A18: 1 | C18: 투자부동산 | E18: 123818.87 | F18: 123818.87 | G18: 123772.16 | H18: 123725.45 | I18: 123678.75 | J18: 126970.6 | K18: 126970.6 | L18: 126917.2 | M18: 126864.93 | N18: 126812.67 | O18: 126760.4 | P18: 126760.4 | Q18: 126708.73 | R18: 126657.06 | S18: 127437.03 | T18: 129203.81 | U18: 129203.81 | V18: 129078.73 | W18: 129005.13 | X18: 128931.53 | Y18: 129028.38 | Z18: 129028.38 | AA18: 128953.32 | AB18: 128878.27
A19: 1 | C19: 유형자산 | E19: 83403.78 | F19: 83403.78 | G19: 84428.42 | H19: 83789.91 | I19: 86230.94 | J19: 81789.07 | K19: 81789.07 | L19: 80242.11 | M19: 79910.87 | N19: 81575.55 | O19: 82980.54 | P19: 82980.54 | Q19: 83904.66 | R19: 84168.14 | S19: 83457.65 | T19: 83201.22 | U19: 83201.22 | V19: 81479.21 | W19: 81112.24 | X19: 81461.88 | Y19: 82202.22 | Z19: 82202.22 | AA19: 82226.49
A20: 1 | C20: 무형자산 | E20: 2171.82 | F20: 2171.82 | G20: 2195.54 | H20: 2234.71 | I20: 2602.04 | J20: 2480.47 | K20: 2480.47 | L20: 2508.63 | M20: 2446.01 | N20: 2449.6 | O20: 2413.09 | P20: 2413.09 | Q20: 2427.41 | R20: 2439.6 | S20: 2414.72 | T20: 2471.27 | U20: 2471.27 | V20: 2475.03 | W20: 2389.78 | X20: 2417.63 | Y20: 3263.45 | Z20: 3263.45 | AA20: 3322.62 | AB20: 3420.56
A21: 1 | C21: 자산총계 | E21: 338742.84 | F21: 338742.84 | G21: 349126.71 | H21: 355796.37 | I21: 355956.03 | J21: 339154.97 | K21: 339154.97 | L21: 332891.18 | M21: 334671.81 | N21: 342488.37 | O21: 331029 | P21: 331029 | Q21: 329909.61 | R21: 336120.36 | S21: 335910.75 | T21: 340452.05 | U21: 340452.05 | V21: 343176.37 | W21: 334950.25 | X21: 345252.46 | Y21: 336119.24 | Z21: 336119.24 | AA21: 341049.45 | AB21: 370106.16
A22: 1 | C22: 유동부채 | E22: 89112.97 | F22: 89112.97 | G22: 116574.85 | H22: 132097.58 | I22: 130826.02 | J22: 112789.05 | K22: 112789.05 | L22: 116243.12 | M22: 114861.62 | N22: 128507.5 | O22: 121158.78 | P22: 121158.78 | Q22: 122286.13 | R22: 130229.48 | S22: 124334.16 | T22: 130607.4 | U22: 130607.4 | V22: 133771.7 | W22: 125461.37 | X22: 141760.88 | Y22: 134154.2 | Z22: 134154.2 | AA22: 140352.17 | AB22: 167169.41
A23: 1 | C23: 매입채무및기타채무 | E23: 11865.99 | F23: 11865.99 | G23: 14499.47 | J23: 14960.61 | K23: 14960.61 | L23: 13995.89 | M23: 19061.29 | N23: 26345.46 | O23: 17259.94 | P23: 17259.94 | Q23: 22385.8 | R23: 17874.15 | S23: 15613.39 | T23: 20092.91 | U23: 20092.91 | V23: 16094.37 | W23: 14780.91 | X23: 19530.68 | Y23: 17224.67 | Z23: 17224.67 | AA23: 23010.35 | AB23: 45474.98
A24: 1 | C24: 단기차입금 | E24: 71751.24 | F24: 71751.24 | G24: 96994.05 | H24: 110555.26 | I24: 99830.82 | J24: 93382.91 | K24: 93382.91 | L24: 97263.34 | M24: 81325.41 | N24: 80225.72 | O24: 79006.06 | P24: 79006.06 | Q24: 95514.09 | R24: 107988.29 | S24: 103875.06 | T24: 105141.35 | U24: 105141.35 | V24: 112136.48 | W24: 105858.38 | X24: 111772.67 | Y24: 111910.03 | Z24: 111910.03 | AA24: 112787.7 | AB24: 117391.52
A25: 1 | C25: 유동성장기부채 | E25: 0 | F25: 0 | G25: 0 | H25: 6464.5 | I25: 6464.5 | M25: 10494 | N25: 16494 | O25: 20494 | P25: 20494 | X25: 6000 | AB25: 0
A26: 1 | C26: 당기법인세부채(미지급법인세) | E26: 881.52 | F26: 881.52 | G26: 0 | H26: 513.91 | I26: 65.52 | J26: 3.35 | K26: 3.35 | L26: 0 | M26: 98.98 | N26: 98.98 | O26: 0 | P26: 0 | Q26: -62.83 | R26: 0 | S26: 0 | T26: 0 | U26: 0 | V26: 243.54 | W26: 0 | X26: 0 | Y26: 0.49 | Z26: 0.49 | AA26: 0.04 | AB26: 0
A27: 1 | C27: 기타유동금융부채 | E27: 2156.76 | F27: 2156.76 | G27: 2740.93 | H27: 5343.77 | I27: 8115.97 | J27: 1691 | K27: 1691 | L27: 1505 | M27: 1505 | N27: 1505 | O27: 1505 | P27: 1505 | Q27: 1505 | R27: 1505 | S27: 1605 | T27: 1605 | U27: 1605 | V27: 2305 | W27: 2290 | X27: 1990 | Y27: 1990 | Z27: 1990 | AA27: 1990 | AB27: 1990
A28: 1 | C28: 단기금융부채 | E28: 2156.76 | F28: 2156.76 | G28: 2740.93 | H28: 5343.77 | I28: 8115.97 | J28: 1961.29 | K28: 1961.29 | L28: 1800.75 | M28: 1714.46 | N28: 1826.51 | O28: 1828.92 | P28: 1828.92 | Q28: 1831.37 | R28: 1835.69 | S28: 1943.81 | T28: 1947.3 | U28: 1947.3 | V28: 2650.83 | W28: 2639.39 | X28: 2341.25 | Y28: 2344.42 | Z28: 2344.42 | AA28: 2347.62 | AB28: 2350.85
A29: 1 | C29: 기타유동부채 | E29: 2457.46 | F29: 2457.46 | G29: 2340.39 | H29: 2180.91 | I29: 2618 | J29: 2480.89 | K29: 2480.89 | L29: 3183.14 | M29: 2167.48 | N29: 3516.83 | O29: 2569.86 | P29: 2569.86 | Q29: 2617.7 | R29: 2531.35 | S29: 2901.9 | T29: 3425.84 | U29: 3425.84 | V29: 2646.48 | W29: 2182.69 | X29: 2116.29 | Y29: 2674.59 | Z29: 2674.59 | AA29: 2206.46 | AB29: 1952.06
A30: 1 | C30: 단기파생상품부채 | E30: 0 | F30: 0 | G30: 0
A31: 1 | C31: 비유동부채 | E31: 71869.08 | F31: 71869.08 | G31: 51629.61 | H31: 44371.91 | I31: 50439.46 | J31: 51833.29 | K31: 51833.29 | L31: 41227.03 | M31: 45324.58 | N31: 39578.38 | O31: 36300.81 | P31: 36300.81 | Q31: 36681.48 | R31: 36436.88 | S31: 42927.7 | T31: 41394.91 | U31: 41394.91 | V31: 41361.14 | W31: 41627.46 | X31: 35901.99 | Y31: 36858.97 | Z31: 36858.97 | AA31: 36768.36 | AB31: 36888.53
A32: 1 | C32: 장기차입금 | E32: 16421.5 | F32: 16421.5 | G32: 16548 | H32: 10494 | I32: 16494 | J32: 16494 | K32: 16494 | L32: 6000 | M32: 10000 | N32: 4000 | O32: 0 | P32: 0 | Q32: 0 | R32: 0 | S32: 6000 | T32: 6000 | U32: 6000 | V32: 6000 | W32: 6000 | X32: 0 | Y32: 0 | Z32: 0 | AB32: 0
A33: 1 | C33: 사채 | E33: 21317.19 | F33: 21317.19 | G33: 0 | H33: 0 | I33: 0 | J33: 0 | K33: 0 | L33: 0 | M33: 0 | N33: 0 | O33: 0 | P33: 0 | Q33: 0 | R33: 0 | S33: 0 | T33: 0 | U33: 0 | V33: 0 | W33: 0 | X33: 0
A34: 1 | C34: 확정급여부채 | E34: -36.18 | F34: -36.18 | G34: 710.59 | H34: 0 | I34: 0 | J34: 0 | K34: 0 | L34: 0 | M34: 0 | N34: 0 | O34: 0 | P34: 0 | Q34: 0 | R34: 0 | S34: 0 | T34: 0 | U34: 0 | V34: 138.85 | W34: 0 | X34: 2.67
A35: 1 | C35: 이연법인세부채 | E35: 34166.58 | F35: 34166.58 | G35: 34371.02 | H35: 33667.11 | I35: 33823.31 | J35: 35227.03 | K35: 35227.03 | L35: 35227.03 | M35: 35324.58 | N35: 35328.74 | O35: 36133.3 | P35: 36133.3 | Q35: 36597.17 | R35: 36436.88 | S35: 36664.32 | T35: 33712.52 | U35: 33712.52 | V35: 33627.69 | W35: 34121.57 | X35: 34121.57 | Y35: 35171.03 | Z35: 35171.03 | AA35: 35171.03 | AB35: 35382.63
A36: 1 | C36: 기타비유동금융부채 | E36: 0 | F36: 0 | G36: 0 | H36: 210.8 | I36: 122.15 | J36: 0 | K36: 0 | L36: 0 | M36: 0 | N36: 0 | O36: 0 | P36: 0 | Q36: 0 | R36: 0 | S36: 0 | T36: 1505.9 | U36: 1505.9 | V36: 1505.9 | W36: 1505.9 | X36: 1505.9 | Y36: 1505.9 | Z36: 1505.9 | AA36: 1505.9 | AB36: 1505.9
A37: 1 | C37: 장기금융부채 | E37: 0 | F37: 0 | G37: 0 | H37: 210.8 | I37: 122.15 | J37: 112.26 | K37: 112.26 | L37: 0 | M37: 0 | N37: 249.64 | O37: 167.52 | P37: 167.52 | Q37: 84.31 | R37: 0 | S37: 263.38 | T37: 1682.39 | U37: 1682.39 | V37: 1594.6 | W37: 1505.9 | X37: 1777.75 | Y37: 1687.95 | Z37: 1687.95 | AA37: 1597.33 | AB37: 1505.9
A38: 1 | C38: 장기파생상품부채 | E38: 0 | F38: 0 | G38: 0
A39: 1 | C39: 부채총계 | E39: 160982.05 | F39: 160982.05 | G39: 168204.46 | H39: 176469.49 | I39: 181265.48 | J39: 164622.34 | K39: 164622.34 | L39: 157470.15 | M39: 160186.2 | N39: 168085.88 | O39: 157459.59 | P39: 157459.59 | Q39: 158967.6 | R39: 166666.36 | S39: 167261.86 | T39: 172002.31 | U39: 172002.31 | V39: 175132.83 | W39: 167088.84 | X39: 177662.88 | Y39: 171013.17 | Z39: 171013.17 | AA39: 177120.53 | AB39: 204057.93
A40: 1 | C40: 지배주주지분 | E40: 175373.74 | F40: 175373.74 | G40: 178416.58 | H40: 176777.89 | I40: 172119.68 | J40: 172060.81 | K40: 172060.81 | L40: 172775.39 | M40: 172021.78 | N40: 171657.17 | O40: 170727.11 | P40: 170727.11 | Q40: 167995.92 | R40: 166292.58 | S40: 165362 | T40: 164663.51 | U40: 164663.51 | V40: 164234.34 | W40: 164359.13 | X40: 163915.81 | Y40: 161191.79 | Z40: 161191.79 | AA40: 159720.6 | AB40: 161791.65
A41: 1 | C41: 자본금 | E41: 13348.73 | F41: 13348.73 | G41: 13348.73 | H41: 13348.73 | I41: 13348.73 | J41: 13348.73 | K41: 13348.73 | L41: 13348.73 | M41: 13348.73 | N41: 13348.73 | O41: 13348.73 | P41: 13348.73 | Q41: 13348.73 | R41: 13348.73 | S41: 13348.73 | T41: 13348.73 | U41: 13348.73 | V41: 13348.73 | W41: 13348.73 | X41: 13348.73 | Y41: 13348.73 | Z41: 13348.73 | AA41: 13348.73 | AB41: 13348.73
A42: 1 | C42: 자본잉여금 | E42: 11140.41 | F42: 11140.41 | G42: 11140.41 | H42: 11140.41 | I42: 11140.41 | J42: 11140.41 | K42: 11140.41 | L42: 11140.41 | M42: 11140.41 | N42: 11140.41 | O42: 11140.41 | P42: 11140.41 | Q42: 11140.41 | R42: 11140.41 | S42: 11140.41 | T42: 11140.41 | U42: 11140.41 | V42: 11140.41 | W42: 9948.95 | X42: 9948.95 | Y42: 14513.78 | Z42: 14513.78 | AA42: 14513.78 | AB42: 14513.78
A43: 1 | C43: 이익잉여금 | E43: 150476.96 | F43: 150476.96 | G43: 153440.11 | H43: 151774.75 | I43: 146789.3 | J43: 147320.7 | K43: 147320.7 | L43: 147857.99 | M43: 147419.56 | N43: 146916.95 | O43: 146191.29 | P43: 146191.29 | Q43: 143353.14 | R43: 141563.66 | S43: 140761.21 | T43: 139672.54 | U43: 139672.54 | V43: 139243.12 | W43: 141103.11 | X43: 140191.41 | Y43: 139056.79 | Z43: 139056.79 | AA43: 136880.6 | AB43: 138716.01
A44: 1 | C44: 비지배주주지분 | E44: 2387.05 | F44: 2387.05 | G44: 2505.68 | H44: 2548.98 | I44: 2570.87 | J44: 2471.82 | K44: 2471.82 | L44: 2645.64 | M44: 2463.83 | N44: 2745.31 | O44: 2842.29 | P44: 2842.29 | Q44: 2946.08 | R44: 3161.42 | S44: 3286.89 | T44: 3786.22 | U44: 3786.22 | V44: 3809.19 | W44: 3502.28 | X44: 3673.78 | Y44: 3914.29 | Z44: 3914.29 | AA44: 4208.32 | AB44: 4256.57
A45: 1 | C45: 자본총계 | E45: 177760.79 | F45: 177760.79 | G45: 180922.26 | H45: 179326.88 | I45: 174690.55 | J45: 174532.63 | K45: 174532.63 | L45: 175421.03 | M45: 174485.61 | N45: 174402.49 | O45: 173569.4 | P45: 173569.4 | Q45: 170942.01 | R45: 169454 | S45: 168648.89 | T45: 168449.74 | U45: 168449.74 | V45: 168043.54 | W45: 167861.41 | X45: 167589.59 | Y45: 165106.07 | Z45: 165106.07 | AA45: 163928.93 | AB45: 166048.22
A46: 1 | C46: 부채와자본총계 | E46: 338742.84 | F46: 338742.84 | G46: 349126.71 | H46: 355796.37 | I46: 355956.03 | J46: 339154.97 | K46: 339154.97 | L46: 332891.18 | M46: 334671.81 | N46: 342488.37 | O46: 331029 | P46: 331029 | Q46: 329909.61 | R46: 336120.36 | S46: 335910.75 | T46: 340452.05 | U46: 340452.05 | V46: 343176.37 | W46: 334950.25 | X46: 345252.46 | Y46: 336119.24 | Z46: 336119.24 | AA46: 341049.45 | AB46: 370106.16
A47: 1 | C47: 총차입금 | E47: 109489.93 | F47: 109489.93 | G47: 113542.05 | H47: 127513.76 | I47: 122789.32 | J47: 109876.91 | K47: 109876.91 | L47: 103263.34 | M47: 101819.41 | N47: 100719.72 | O47: 99500.06 | P47: 99500.06 | Q47: 95514.09 | R47: 107988.29 | S47: 109875.06 | T47: 111141.35 | U47: 111141.35 | V47: 118136.48 | W47: 111858.38 | X47: 117772.67 | Y47: 111910.03 | Z47: 111910.03 | AA47: 112787.7 | AB47: 117391.52
A48: 1 | C48: 순차입금 | E48: 80949.69 | F48: 80949.69 | G48: 81136.88 | H48: 116388.17 | I48: 115218.68 | J48: 69415.35 | K48: 69415.35 | L48: 72395.1 | M48: 72541.33 | N48: 73251.96 | O48: 69597.53 | P48: 69597.53 | Q48: 72882.72 | R48: 82612.65 | S48: 77740.57 | T48: 77162.12 | U48: 77162.12 | V48: 80711.98 | W48: 77368.2 | X48: 84715.38 | Y48: 82609.43 | Z48: 82609.43 | AA48: 76843.66 | AB48: 75369.02
A49: 1 | C49: 이자발생자산 | E49: 30562.44 | F49: 30562.44 | G49: 34429.27 | H49: 12127.56 | I49: 8572.61 | J49: 41480.64 | K49: 41480.64 | L49: 31874.37 | M49: 30288.89 | N49: 28488.57 | O49: 30923.77 | P49: 30923.77 | Q49: 23657.91 | R49: 26400.84 | S49: 33159.85 | T49: 35005.66 | U49: 35005.66 | V49: 38449.9 | W49: 35516.93 | X49: 33326.57 | Y49: 34057.57 | Z49: 34057.57 | AA49: 40104.87 | AB49: 46183.1
A50: 1 | C50: 기타비유동자산 | H50: 492.57 | I50: 570.76 | J50: 841.2 | K50: 841.2 | L50: 707.81 | M50: 734.42 | N50: 601.04 | O50: 691.54 | P50: 691.54 | Q50: 547.76 | R50: 384.09 | S50: 230.8 | T50: 43.06 | U50: 43.06 | V50: 0 | W50: 179.24 | X50: 0 | Y50: 948.27 | Z50: 948.27 | AA50: 780.28 | AB50: 822.28
A51: 1 | C51: 기타포괄이익누계액 | H51: 514.01 | I51: 841.24 | Y51: -1268.64 | Z51: -1268.64 | AA51: -563.63 | AB51: -327.99
A52: 1 | C52: 단기투자자산(공정가치) | J52: 502.49 | K52: 502.49 | L52: 509.45 | M52: 511.52 | N52: 513.77 | O52: 528.29 | P52: 528.29 | Q52: 249.86 | R52: 0 | S52: 5000 | T52: 0 | U52: 0 | V52: 0 | W52: 0 | X52: 0 | Y52: 0.04 | Z52: 0.04 | AA52: 0 | AB52: 0
A53: 1 | C53: 유동리스부채 | J53: 270.29 | K53: 270.29 | L53: 295.75 | M53: 209.46 | N53: 321.51 | O53: 323.92 | P53: 323.92 | Q53: 326.37 | R53: 330.69 | S53: 338.81 | T53: 342.3 | U53: 342.3 | V53: 345.83 | W53: 349.39 | X53: 351.25 | Y53: 354.42 | Z53: 354.42 | AA53: 357.62 | AB53: 360.85
A54: 1 | C54: 리스부채 | J54: 382.55 | K54: 382.55 | L54: 295.75 | M54: 209.46 | N54: 571.15 | O54: 491.44 | P54: 491.44 | Q54: 410.68 | R54: 330.69 | S54: 602.19 | T54: 518.79 | U54: 518.79 | V54: 434.53 | W54: 349.39 | X54: 623.1 | Y54: 536.47 | Z54: 536.47 | AA54: 449.05 | AB54: 360.85
A55: 1 | C55: 비유동리스부채 | J55: 112.26 | K55: 112.26 | L55: 0 | M55: 0 | N55: 249.64 | O55: 167.52 | P55: 167.52 | Q55: 84.31 | R55: 0 | S55: 263.38 | T55: 176.49 | U55: 176.49 | V55: 88.7 | W55: 0 | X55: 271.85 | Y55: 182.05 | Z55: 182.05 | AA55: 91.43 | AB55: 0
A56: 1 | C56: 기타자본 | J56: 250.97 | K56: 250.97 | L56: 428.26 | M56: 113.08 | N56: 251.08 | O56: 46.68 | P56: 46.68 | Q56: 153.64 | R56: 239.78 | S56: 111.65 | T56: 501.83 | U56: 501.83 | V56: 502.08 | W56: -41.66 | X56: 426.72 | Y56: -4458.88 | Z56: -4458.88 | AA56: -4458.88 | AB56: -4458.88
A57: 1 | C57: 단기금융부채(face) | N57: 80225.72 | Y57: 111910.03 | Z57: 111910.03 | AA57: 112787.7
A58: 1 | C58: 기타비유동부채 | N58: 0 | O58: 0 | P58: 0 | Q58: 0 | R58: 0 | S58: 0 | T58: 0 | U58: 0 | V58: 0 | W58: 0 | X58: 0
A59: 1 | C59: 장기금융부채(face) | S59: 6000 | V59: 6000 | X59: 0 | Y59: 0 | Z59: 0
A60: 1 | C60: 매출액(수익) | E60: 68972.15 | G60: 72295.75 | H60: 60581.37 | I60: 63166.45 | J60: 59185.75 | K60: 255229.32 | L60: 60542.51 | M60: 51547.95 | N60: 53092.27 | O60: 51072.73 | P60: 216255.46 | Q60: 49991.04 | R60: 55504.69 | S60: 44028.11 | T60: 56318.4 | U60: 205842.24 | V60: 49758.06 | W60: 50110.08 | X60: 50841.03 | Y60: 45695.2 | Z60: 196404.37 | AA60: 61873.64 | AB60: 61757.19
A61: 1 | C61: 매출원가 | E61: 59271.5 | G61: 67728.53 | H61: 55838.34 | I61: 61631.2 | J61: 56472.84 | K61: 241670.91 | L61: 53902.99 | M61: 47634.08 | N61: 49124.99 | O61: 49228.29 | P61: 199890.35 | Q61: 45842.87 | R61: 51968.34 | S61: 41047.1 | T61: 52280.96 | U61: 191139.27 | V61: 46132.76 | W61: 45498.59 | X61: 46278.41 | Y61: 42474.7 | Z61: 180384.46 | AA61: 57857.85 | AB61: 55278.72
A62: 1 | C62: 매출총이익 | E62: 9700.65 | G62: 4567.22 | H62: 4743.03 | I62: 1535.25 | J62: 2712.91 | K62: 13558.41 | L62: 6639.52 | M62: 3913.87 | N62: 3967.28 | O62: 1844.44 | P62: 16365.11 | Q62: 4148.17 | R62: 3536.36 | S62: 2981.01 | T62: 4037.44 | U62: 14702.98 | V62: 3625.3 | W62: 4611.49 | X62: 4562.62 | Y62: 3220.49 | Z62: 16019.9 | AA62: 4015.79 | AB62: 6478.47
A63: 1 | C63: 판관비 | E63: 2393.41 | G63: 2581.49 | H63: 1587.55 | I63: 2275.26 | J63: 3082.37 | K63: 9526.67 | L63: 2938.67 | M63: 2712.19 | N63: 2462.02 | O63: 3392.44 | P63: 11505.32 | Q63: 3766.47 | R63: 3091.87 | S63: 3157.12 | T63: 4020.55 | U63: 14036.01 | V63: 3436.19 | W63: 3071.07 | X63: 3139.05 | Y63: 3194.51 | Z63: 12840.82 | AA63: 3552.51 | AB63: 3622.44
A64: 1 | C64: 영업이익 | E64: 7307.24 | G64: 1985.73 | H64: 3155.48 | I64: -740.01 | J64: -369.46 | K64: 4031.74 | L64: 3700.85 | M64: 1201.68 | N64: 1505.26 | O64: -1548 | P64: 4859.79 | Q64: 381.7 | R64: 444.49 | S64: -176.11 | T64: 16.88 | U64: 666.96 | V64: 189.11 | W64: 1540.42 | X64: 1423.57 | Y64: 25.98 | Z64: 3179.08 | AA64: 463.28 | AB64: 2856.03
A65: 1 | C65: 기타영업외손익 | E65: 602.01 | G65: 924.4 | H65: 140.92 | I65: -185.45 | J65: -60.2 | K65: 819.67 | L65: -213.5 | M65: -254.44 | N65: 138.37 | O65: 1206.82 | P65: 877.25 | Q65: 162.73 | R65: 347.23 | S65: -249.06 | T65: 587.13 | U65: 848.03 | V65: 440.83 | W65: -773.16 | X65: 304.57 | Y65: 148.83 | Z65: 121.07 | AA65: 69.77 | AB65: -24.83
A66: 1 | C66: 기타영업외비용 | E66: 540.78 | G66: 579.6 | L66: 1180.85 | M66: 640.42 | N66: 681.36 | O66: -504.59 | P66: 1998.04 | Q66: 707.73 | R66: 181.4 | S66: 960.17 | T66: 155.93 | U66: 2005.23 | V66: 692.82 | W66: 700.47 | X66: 376.62 | Y66: 635.16 | Z66: 2405.07 | AA66: 635.9 | AB66: 669.8
A67: 1 | C67: 금융수익 | E67: 3484.59 | G67: 399.64 | L67: 289.13 | M67: 383.73 | N67: -80.59 | O67: 1550.87 | P67: 2143.14 | Q67: 142.85 | R67: 151.98 | S67: 230.43 | T67: 649.17 | U67: 1174.43 | V67: 348.75 | W67: 2952.86 | X67: -1018.87 | Y67: -647.94 | Z67: 1634.8 | AA67: 293.61 | AB67: 308.42
A68: 1 | C68: 금융비용 | E68: 1583.77 | G68: 472.97 | L68: 2568.04 | M68: 1582.86 | N68: 2063.59 | O68: 453.84 | P68: 6668.33 | Q68: 2366.64 | R68: 2179.62 | S68: 34.99 | T68: 4821.97 | U68: 9403.22 | V68: 1300.38 | W68: 1276.74 | X68: 1231.7 | Y68: 1224.25 | Z68: 5033.07 | AA68: 2768.35 | AB68: 1709.87
A69: 1 | C69: 법인세비용차감전계속사업이익 | E69: 8898.05 | G69: 3222.71 | H69: -670.43 | I69: -4932.58 | J69: 2151.96 | K69: -228.34 | L69: 1310.94 | M69: -363.94 | N69: -237.62 | O69: 762.17 | P69: 1471.55 | Q69: -1642.29 | R69: -1751.8 | S69: -371.51 | T69: -3114.8 | U69: -6880.4 | V69: -233.33 | W69: 2360.95 | X69: -926.27 | Y69: -1989.93 | Z69: -788.58 | AA69: -1606.33 | AB69: 1926.99
A70: 1 | C70: 법인세비용 | E70: 1645.43 | G70: 212.05 | H70: -226.78 | I70: 118.14 | J70: 966.5 | K70: 1069.91 | L70: 1.5 | M70: 171.55 | N70: 38.45 | O70: 890.68 | P70: 1102.18 | Q70: 427.89 | R70: -108.39 | S70: 231.65 | T70: -2821.45 | U70: -2270.3 | V70: -92.77 | W70: 520.36 | X70: -14.6 | Y70: -765.87 | Z70: -352.88 | AA70: -18.35 | AB70: 217.71
A71: 1 | C71: 당기순이익 | E71: 7252.61 | G71: 3010.66 | H71: -443.65 | I71: -5050.72 | J71: 1185.46 | K71: -1298.25 | L71: 1309.44 | M71: -535.49 | N71: -276.07 | O71: -128.5 | P71: 369.38 | Q71: -2070.18 | R71: -1643.41 | S71: -603.16 | T71: -293.36 | U71: -4610.11 | V71: -140.56 | W71: 1840.59 | X71: -911.67 | Y71: -1224.07 | Z71: -435.71 | AA71: -1587.98 | AB71: 1709.28
A72: 1 | C72: 총포괄손익 | E72: 7240.65 | G72: 3161.47
A73: 1 | C73: 금융손익 | E73: 1900.82 | G73: -73.33 | H73: -4289.1 | I73: -4672.81 | J73: 2849.02 | K73: -6186.22 | L73: -2278.91 | M73: -1199.13 | N73: -2144.18 | O73: 1097.03 | P73: -4525.19 | Q73: -2223.79 | R73: -2027.64 | S73: 195.44 | T73: -4172.8 | U73: -8228.79 | V73: -951.63 | W73: 1676.12 | X73: -2250.57 | Y73: -1872.19 | Z73: -3398.27 | AA73: -2474.74 | AB73: -1401.45
A74: 1 | C74: (지배주주지분)당기순이익 | E74: 7252.61 | G74: 3010.66 | H74: -443.65 | I74: -5050.72 | J74: 1185.46 | K74: -1298.25
A75: 1 | C75: 계속사업이익 | E75: 7252.61 | G75: 3010.66 | H75: -443.65 | I75: -5050.72 | J75: 1185.46 | K75: -1298.25 | L75: 1309.44 | M75: -535.49 | N75: -276.07 | O75: -128.5 | P75: 369.38 | Q75: -2070.18 | R75: -1643.41 | S75: -603.16 | T75: -293.36 | U75: -4610.11 | V75: -140.56 | W75: 1840.59 | X75: -911.67 | Y75: -1224.07 | Z75: -435.71 | AA75: -1587.98 | AB75: 1709.28
A76: 1 | C76: 이자수익 | G76: 38.47 | H76: 61.82 | I76: 189.2 | J76: 301.99 | K76: 591.48 | L76: 228.6
A77: 1 | C77: 이자비용 | G77: 817.42 | H77: 932.62 | I77: 4693.5 | J77: 1498.57 | K77: 7942.11 | L77: 1797.75
A78: 1 | C78: 외화환산이익 | G78: 70.85 | L78: 19.21
A79: 1 | C79: 외화환산손실 | G79: -344.46 | L79: 698.76
A80: 1 | C80: 이자손익 | G80: -778.95 | H80: -870.8 | I80: -4504.3 | J80: -1196.58 | K80: -7350.63 | L80: -1569.15
A81: 1 | C81: 종속기업,공동지배기업및관계기업관련손익 | H81: 322.27 | I81: 665.69
A82: 1 | C82: 배당금수익 | H82: 121.83 | I82: 0 | L82: -60.89
A83: 1 | C83: 기타영업외수익 | L83: 967.35 | M83: 385.98 | N83: 819.73 | O83: 702.23 | P83: 2875.29 | Q83: 870.46 | R83: 528.63 | S83: 711.11 | T83: 743.06 | U83: 2853.26 | V83: 1133.65 | W83: -72.69 | X83: 681.19 | Y83: 783.99 | Z83: 2526.14 | AA83: 705.67 | AB83: 644.97
A84: 1 | C84: (비지배주주지분)당기순이익 | L84: 41.54 | M84: -36.17 | N84: 226.54 | O84: 197.62 | P84: 429.53 | Q84: 37.36 | R84: 146.07 | S84: 199.29 | T84: 266.01 | U84: 648.73 | V84: 45.32 | W84: -19.4 | X84: 0.03 | Y84: 92.18 | Z84: 118.13 | AA84: -124.06 | AB84: -126.13
A85: 1 | C85: 외환차익 | L85: 94.39
A86: 1 | C86: 외환차손 | L86: 71.53
A87: 1 | C87: 영업활동으로인한현금흐름 | E87: 9622.98 | G87: 803.41 | H87: -2837 | I87: 10177.55 | J87: 13224.59 | K87: 21368.55 | L87: -1917.88 | M87: 1628.53 | N87: 2595.32 | O87: 3415.51 | P87: 5721.48 | Q87: -1.75 | R87: -5617.4 | S87: 8728.22 | T87: 170.82 | U87: 3279.89 | V87: -4243.51 | W87: 4180.77 | X87: -4896.89 | Y87: 5551.62 | Z87: 591.99 | AA87: 9173.3 | AB87: 3154.04
A88: 1 | C88: 배당금수취(CF) | E88: -61 | I88: 0 | N88: 0 | S88: 0 | T88: 0 | X88: 0
A89: 1 | C89: 법인세납부(CF) | E89: -1628.14 | G89: -320.08 | H89: -515.28 | I89: -450.84 | J89: -6.05 | K89: -1292.25 | L89: 422.91 | M89: -19.25 | N89: -195.18 | O89: 63.52 | P89: 272 | Q89: 89.94 | R89: -13.56 | S89: -74.02 | T89: -38.71 | U89: -36.35 | V89: 104.63 | W89: -25.89 | X89: -59.12 | Y89: -32.86 | Z89: -13.24 | AA89: 120.64 | AB89: -7.33
A90: 1 | C90: 투자활동으로인한현금흐름 | E90: -1246.16 | G90: -9449.74 | H90: -4577 | I90: -4926.04 | J90: -456.24 | K90: -19409.02 | L90: 9118.08 | M90: -776.24 | N90: -996.34 | O90: -501.51 | P90: 6843.99 | Q90: -671.61 | R90: -3136.44 | S90: -6712.62 | T90: -2856.76 | U90: -13377.43 | V90: -2776.26 | W90: -887.07 | X90: -74.2 | Y90: -2559.02 | Z90: -6296.55 | AA90: 1790.08 | AB90: -7954.02
A91: 1 | C91: 무형자산의증가 | E91: 0 | I91: 340 | J91: 7.48 | L91: 0 | M91: 0 | N91: 0 | O91: 0 | P91: 0 | Q91: 0 | R91: 0 | S91: 0 | T91: 0 | U91: 0 | V91: 0 | W91: 0 | X91: 0 | Y91: 817.6 | Z91: 817.6
A92: 1 | C92: 재무활동으로인한현금흐름 | E92: -3631.66 | G92: 4309.18 | H92: 10020.44 | I92: -8918.16 | J92: -7691.82 | K92: -2280.36 | L92: -7695.17 | M92: -2342.28 | N92: -1556.26 | O92: -450.71 | P92: -12044.42 | Q92: -6135.24 | R92: 11787.63 | S92: 3428.2 | T92: -313.98 | U92: 8766.61 | V92: 7407.36 | W92: -5091.59 | X92: 4408.08 | Y92: -6606.46 | Z92: 117.39 | AA92: -1599.69 | AB92: 3911.8
A93: 1 | C93: 유동성장기부채의감소 | E93: 156.25 | I93: 0 | J93: 0 | L93: 0 | M93: 0 | N93: 4000 | Q93: 0 | R93: 0 | S93: 0 | T93: 0 | U93: 0 | V93: 0 | W93: 0 | X93: 0
A94: 1 | C94: 장기차입금의증가 | E94: 0 | G94: 20347.2 | Q94: 0 | R94: 0 | S94: 6000 | T94: 0 | U94: 6000 | V94: 0 | W94: 0 | X94: 0 | Y94: 0 | Z94: 0
A95: 1 | C95: 현금및현금성자산의증감 | E95: 4813.69 | G95: -4286.7 | H95: 2555.99 | I95: -3666.65 | J95: 5022.92 | K95: -374.44 | L95: -393.32 | M95: -1590.17 | N95: 89.69 | O95: 2434.76 | P95: 540.96 | Q95: -6771.16 | R95: 2744.28 | S95: 5758.84 | T95: -2955.25 | U95: -1223.29 | V95: 1445.27 | W95: -2934.32 | X95: -582.89 | Y95: -3756.69 | Z95: -5828.63 | AA95: 8643.44 | AB95: -121.54
A96: 1 | C96: 기말현금및현금성자산 | E96: 154.55 | G96: 8489.31 | H96: 2636.28 | I96: -3554.95 | J96: 4830.92 | K96: 12401.56 | L96: 12008.24 | M96: -1590.16 | N96: 89.68 | O96: 2434.77 | P96: 12942.53 | Q96: 6171.37 | R96: 2744.27 | S96: 5758.85 | T96: -2955.26 | U96: 11719.23 | V96: 13164.5 | W96: -2934.32 | X96: -582.89 | Y96: -3756.69 | Z96: 5890.6 | AA96: 14534.04 | AB96: -121.54
A97: 1 | C97: CAPEX | E97: 0 | G97: 1401.18 | H97: 1160.84 | I97: 2199.12 | J97: 2427.86 | K97: 7189 | L97: 159.22 | M97: 838 | N97: 2891.32 | O97: 1873.21 | P97: 5761.75 | Q97: 1744.42 | R97: 1633.23 | S97: 682.52 | T97: 2546.88 | U97: 6607.05 | V97: 26.26 | W97: 917.66 | X97: 959.61 | Y97: 2538.18 | Z97: 4441.71 | AA97: 907.99 | AB97: 1754.02
A98: 1 | C98: 유형자산의감소 | G98: 12.85 | I98: 244.98 | L98: 71.16 | M98: 0.84 | N98: 4 | O98: 0 | P98: 76 | Q98: 65.02 | S98: 0 | T98: 0 | V98: 0 | W98: 0 | X98: 0 | Y98: 0 | Z98: 0 | AA98: 57.36 | AB98: 0
A99: 1 | C99: 유형자산의증가 | G99: 1401.18 | H99: 1160.84 | I99: 1859.12 | J99: 2420.38 | K99: 6841.52 | L99: 159.22 | M99: 838 | N99: 2891.32 | O99: 1873.21 | P99: 5761.75 | Q99: 1744.42 | R99: 1633.23 | S99: 682.52 | T99: 2546.88 | U99: 6607.05 | V99: 26.26 | W99: 917.66 | X99: 959.61 | Y99: 1720.58 | Z99: 3624.11 | AA99: 907.99 | AB99: 1754.02
A100: 1 | C100: 단기차입금의증가 | G100: 24711.37 | H100: 40827.85 | L100: 7422.36 | M100: 5525.39 | N100: 1668.31 | O100: 180.28 | P100: 14796.34 | Q100: 5080.7 | R100: 38757.06 | T100: 17654.99 | V100: 8799.16 | W100: 10000 | X100: 11280.99 | AA100: 16300 | AB100: 4000
...

Sheet BS별도
B1: (백만원) | C1: 이름: BS별도H | E1: 4Q21 | F1: 2021 | G1: 1Q22 | H1: 2Q22 | I1: 3Q22 | J1: 4Q22 | K1: 2022 | L1: 1Q23 | M1: 2Q23 | N1: 3Q23 | O1: 4Q23 | P1: 2023 | Q1: 1Q24 | R1: 2Q24 | S1: 3Q24 | T1: 4Q24 | U1: 2024 | V1: 1Q25 | W1: 2Q25 | X1: 3Q25 | Y1: 4Q25 | Z1: 2025 | AA1: 1Q26 | AB1: 2Q26 | AC1: 3Q26 | AD1: 4Q26 | AE1: 2026 | AF1: 1Q27 | AG1: 2Q27 | AH1: 3Q27 | AI1: 4Q27 | AJ1: 2027 | AK1: 1Q28 | AL1: 2Q28 | AM1: 3Q28 | AN1: 4Q28 | AO1: 2028
B2: 별도 | D2: fin json(kship_fin.py)
B3: 한일철강(별) | C3: UPDATE: 26-10-13 | E3: 1 | F3: 2 | G3: 3 | H3: 4 | I3: 5 | J3: 6 | K3: 7 | L3: 8 | M3: 9 | N3: 10 | O3: 11 | P3: 12 | Q3: 13 | R3: 14 | S3: 15 | T3: 16 | U3: 17 | V3: 18 | W3: 19 | X3: 20 | Y3: 21 | Z3: 22 | AA3: 23 | AB3: 24 | AC3: 25 | AD3: 26 | AE3: 27 | AF3: 28 | AG3: 29 | AH3: 30 | AI3: 31 | AJ3: 32 | AK3: 33 | AL3: 34 | AM3: 35 | AN3: 36 | AO3: 37
B4: Account Code | C4: AccountNAME | E4: 2021.12 | F4: 2021.12A | G4: 2022.03 | H4: 2022.06 | I4: 2022.09 | J4: 2022.12 | K4: 2022.12A | L4: 2023.03 | M4: 2023.06 | N4: 2023.09 | O4: 2023.12 | P4: 2023.12A | Q4: 2024.03 | R4: 2024.06 | S4: 2024.09 | T4: 2024.12 | U4: 2024.12A | V4: 2025.03 | W4: 2025.06 | X4: 2025.09 | Y4: 2025.12 | Z4: 2025.12A | AA4: 2026.03 | AB4: 2026.06 | AC4: 2026.09 | AD4: 2026.12 | AE4: 2026.12A | AF4: 2027.03 | AG4: 2027.06 | AH4: 2027.09 | AI4: 2027.12 | AJ4: 2027.12A | AK4: 2028.03 | AL4: 2028.06 | AM4: 2028.09 | AN4: 2028.12 | AO4: 2028.12A
A5: 1 | C5: 유동자산 | E5: 100757.61 | F5: 100757.61 | G5: 109694.49 | H5: 115803.92 | I5: 111415.04 | J5: 97097.76 | K5: 97097.76 | L5: 93163.68 | M5: 95669.95 | N5: 100327.26 | O5: 88583.79 | P5: 88583.79 | Q5: 86581.44 | R5: 90750.88 | S5: 90620.84 | T5: 91087.56 | U5: 91087.56 | V5: 95796.32 | W5: 90092.83 | X5: 99580.08 | Y5: 87689.27 | Z5: 87689.27 | AA5: 92414.99 | AB5: 118854.64
A6: 1 | C6: 현금및현금성자산 | E6: 10446 | F6: 10446 | G6: 6078.01 | H6: 8350.23 | I6: 4642.59 | J6: 10051.2 | K6: 10051.2 | L6: 9359.84 | M6: 7952.02 | N6: 8582.24 | O6: 11500.72 | P6: 11500.72 | Q6: 4882.61 | R6: 7842.77 | S6: 13295.94 | T6: 10642.71 | U6: 10642.71 | V6: 12207.98 | W6: 8822.59 | X6: 8315.96 | Y6: 5100.11 | Z6: 5100.11 | AA6: 13604.18 | AB6: 13406.66
A7: 1 | C7: 단기금융상품 | E7: 15764.23 | F7: 15764.23 | G7: 23915.86 | J7: 28060 | K7: 28060 | L7: 18860 | M7: 18860 | N7: 16960 | O7: 16960 | P7: 16960 | Q7: 16460 | R7: 16460 | S7: 17460 | T7: 22260 | U7: 22260 | V7: 24260 | W7: 24260 | X7: 23410 | Y7: 23410 | Z7: 23410 | AA7: 21410 | AB7: 27610
A8: 1 | C8: 단기금융자산 | E8: 15764.23 | F8: 15764.23 | G8: 23915.86 | J8: 28060 | K8: 28060 | L8: 18860 | M8: 18860 | N8: 16960 | O8: 16960 | P8: 16960 | Q8: 16460 | R8: 16460 | S8: 17460 | T8: 22260 | U8: 22260 | V8: 24260 | W8: 24260 | X8: 23410 | Y8: 23410 | Z8: 23410 | AA8: 21410 | AB8: 27610
A9: 1 | C9: 매출채권및기타채권 | E9: 33674.87 | F9: 33674.87 | G9: 37446.69 | H9: 33382.63 | I9: 34950.15 | J9: 32939.3 | K9: 32939.3 | L9: 31261.88 | M9: 28341.76 | N9: 28785.92 | O9: 26576.18 | P9: 26576.18 | Q9: 25875.81 | R9: 25940.53 | S9: 18749.58 | T9: 24842.89 | U9: 24842.89 | V9: 23191.57 | W9: 22222.42 | X9: 25583.11 | Y9: 21243.36 | Z9: 21243.36 | AA9: 33824.43 | AB9: 33298.82
A10: 1 | C10: 기타유동자산 | E10: 1266.27 | F10: 1266.27 | G10: 1009.1 | H10: 207.8 | I10: 1224.4 | J10: 84.46 | K10: 84.46 | L10: 24.02 | M10: 209.47 | N10: 265.63 | O10: 110.58 | P10: 110.58 | Q10: 569.98 | R10: 1063.43 | S10: 162.85 | T10: 1123.6 | U10: 1123.6 | V10: 993.03 | W10: 744.38 | X10: 1325.08 | Y10: 1388.99 | Z10: 1388.99 | AA10: 734.33 | AB10: 685.74
A11: 1 | C11: 재고자산 | E11: 38752.31 | F11: 38752.31 | G11: 40102.23 | H11: 45636.11 | I11: 40797.23 | J11: 24996.52 | K11: 24996.52 | L11: 33112.48 | M11: 39738.38 | N11: 45051.74 | O11: 32791.14 | P11: 32791.14 | Q11: 38828.97 | R11: 39417.72 | S11: 35852.07 | T11: 32078.65 | U11: 32078.65 | V11: 35108.71 | W11: 33982.36 | X11: 40825.76 | Y11: 36393.77 | Z11: 36393.77 | AA11: 22809.72 | AB11: 43813.67
A12: 1 | C12: 당기법인세자산(선급법인세) | E12: 853.93 | F12: 853.93 | G12: 1142.6 | J12: 463.78 | K12: 463.78 | L12: 36.01 | M12: 56.8 | N12: 167.96 | O12: 116.89 | P12: 116.89 | Q12: -35.93 | R12: 26.43 | S12: 100.39 | T12: 139.7 | U12: 139.7 | V12: 35.03 | W12: 61.08 | X12: 120.16 | Y12: 152.99 | Z12: 152.99 | AA12: 32.32 | AB12: 39.75
A13: 1 | C13: 비유동자산 | E13: 227446.48 | F13: 227446.48 | G13: 228488.38 | H13: 229062.92 | I13: 231802.79 | J13: 231306.38 | K13: 231306.38 | L13: 229537.95 | M13: 229540.78 | N13: 230978.22 | O13: 231937.73 | P13: 231937.73 | Q13: 232416.09 | R13: 233876.77 | S13: 233890.5 | T13: 235331.54 | U13: 235331.54 | V13: 234341.28 | W13: 234468.68 | X13: 234369.48 | Y13: 236701.77 | Z13: 236701.77 | AA13: 235613.25 | AB13: 237197.05
A14: 1 | C14: 장기금융자산 | E14: 2022.2 | F14: 2022.2 | G14: 2024.1 | H14: 2701.97 | I14: 2701.97 | J14: 2751.77 | K14: 2751.77 | L14: 2739.68 | M14: 2845.54 | N14: 2751.07 | O14: 2406.71 | P14: 2406.71 | Q14: 2433.72 | R14: 3889.68 | S14: 3857.13 | T14: 4095.37 | U14: 4095.37 | V14: 4848.42 | W14: 4959.87 | X14: 4759.81 | Y14: 4507.1 | Z14: 4507.1 | AA14: 3910.97 | AB14: 3910.74
A15: 1 | C15: 투자자산 | E15: 23065.17 | F15: 23065.17 | G15: 23067.07 | H15: 23744.94 | I15: 23744.94 | J15: 23794.74 | K15: 23794.74 | L15: 23782.65 | M15: 23888.51 | N15: 23794.04 | O15: 23449.68 | P15: 23449.68 | Q15: 23476.69 | R15: 24932.65 | S15: 24900.1 | T15: 25138.34 | U15: 25138.34 | V15: 25891.39 | W15: 26002.84 | X15: 25802.78 | Y15: 25550.07 | Z15: 25550.07 | AA15: 24953.94 | AB15: 24953.71
A16: 1 | C16: 종속기업및관계기업투자 | E16: 21042.97 | F16: 21042.97 | G16: 21042.97 | H16: 21042.97 | I16: 21042.97 | J16: 21042.97 | K16: 21042.97 | L16: 21042.97 | M16: 21042.97 | N16: 21042.97 | O16: 21042.97 | P16: 21042.97 | Q16: 21042.97 | R16: 21042.97 | S16: 21042.97 | T16: 21042.97 | U16: 21042.97 | V16: 21042.97 | W16: 21042.97 | X16: 21042.97 | Y16: 21042.97 | Z16: 21042.97 | AA16: 21042.97 | AB16: 21042.97
A17: 1 | C17: 투자부동산 | E17: 123818.87 | F17: 123818.87 | G17: 123772.16 | H17: 123725.45 | I17: 123678.75 | J17: 126970.6 | K17: 126970.6 | L17: 126917.2 | M17: 126864.93 | N17: 126812.67 | O17: 126760.4 | P17: 126760.4 | Q17: 126708.73 | R17: 126657.06 | S17: 127437.03 | T17: 129203.81 | U17: 129203.81 | V17: 129078.73 | W17: 129005.13 | X17: 128931.53 | Y17: 129028.38 | Z17: 129028.38 | AA17: 128953.32 | AB17: 128878.27
A18: 1 | C18: 유형자산 | E18: 79576.93 | F18: 79576.93 | G18: 80663.64 | H18: 80090.14 | I18: 82463.76 | J18: 78366.85 | K18: 78366.85 | L18: 76797.3 | M18: 76719.92 | N18: 78437.49 | O18: 79703.13 | P18: 79703.13 | Q18: 80349.93 | R18: 80569.99 | S18: 79989.58 | T18: 79613.34 | U18: 79613.34 | V18: 78038.17 | W18: 77948.49 | X18: 78302.19 | Y18: 79024.46 | Z18: 79024.46 | AA18: 78775.13 | AB18: 80392.2
A19: 1 | C19: 무형자산 | E19: 985.51 | F19: 985.51 | G19: 985.51 | H19: 985.51 | I19: 1325.51 | J19: 1332.99 | K19: 1332.99 | L19: 1332.99 | M19: 1332.99 | N19: 1332.99 | O19: 1332.99 | P19: 1332.99 | Q19: 1332.99 | R19: 1332.99 | S19: 1332.99 | T19: 1332.99 | U19: 1332.99 | V19: 1332.99 | W19: 1332.99 | X19: 1332.99 | Y19: 2150.59 | Z19: 2150.59 | AA19: 2150.59 | AB19: 2150.59
A20: 1 | C20: 자산총계 | E20: 328204.09 | F20: 328204.09 | G20: 338182.87 | H20: 344866.84 | I20: 343217.83 | J20: 328404.14 | K20: 328404.14 | L20: 322701.63 | M20: 325210.72 | N20: 331305.48 | O20: 320521.52 | P20: 320521.52 | Q20: 318997.53 | R20: 324627.66 | S20: 324511.34 | T20: 326419.09 | U20: 326419.09 | V20: 330137.61 | W20: 324561.51 | X20: 333949.57 | Y20: 324391.04 | Z20: 324391.04 | AA20: 328028.24 | AB20: 356051.69
A21: 1 | C21: 유동부채 | E21: 83381.67 | F21: 83381.67 | G21: 111599.8 | H21: 127332.52 | I21: 125356.55 | J21: 108057.66 | K21: 108057.66 | L21: 112589.2 | M21: 111306.67 | N21: 124266.64 | O21: 117815.02 | P21: 117815.02 | Q21: 118931.95 | R21: 126325.31 | S21: 120571.21 | T21: 126126.23 | U21: 126126.23 | V21: 130437.25 | W21: 123617.41 | X21: 139174.27 | Y21: 131595.14 | Z21: 131595.14 | AA21: 137787.2 | AB21: 164199.8
A22: 1 | C22: 매입채무및기타채무 | E22: 10647.08 | F22: 10647.08 | G22: 13256.08 | J22: 13281.56 | K22: 13281.56 | L22: 12620.22 | M22: 17648.35 | N22: 23860.85 | O22: 15496.3 | P22: 15496.3 | Q22: 20538.31 | R22: 15120.43 | S22: 12816.33 | T22: 16179.18 | U22: 16179.18 | V22: 13331.37 | W22: 13166.01 | X22: 17296.07 | Y22: 15340.61 | Z22: 15340.61 | AA22: 20765.19 | AB22: 42765.12
A23: 1 | C23: 단기차입금 | E23: 68188.62 | F23: 68188.62 | G23: 93367.77 | H23: 106674.39 | I23: 102467.94 | J23: 90476.5 | K23: 90476.5 | L23: 95053.95 | M23: 79232.24 | N23: 95061.29 | O23: 98053.34 | P23: 98053.34 | Q23: 94213.84 | R23: 107036.14 | S23: 103686.32 | T23: 104940.08 | U23: 104940.08 | V23: 111934.8 | W23: 105669.22 | X23: 117575.85 | Y23: 111705.27 | Z23: 111705.27 | AA23: 112569 | AB23: 117164.55
A24: 1 | C24: 유동성장기부채 | E24: 0 | F24: 0 | G24: 0 | H24: 6464.5 | I24: 0 | M24: 10494 | N24: 0
A25: 1 | C25: 기타유동금융부채 | E25: 2157.76 | F25: 2157.76 | G25: 2741.93 | H25: 4977.18 | I25: 7671.2 | J25: 1692 | K25: 1692 | L25: 1506 | M25: 1506 | N25: 1506 | O25: 1506 | P25: 1506 | Q25: 1506 | R25: 1506 | S25: 1606 | T25: 1606 | U25: 1606 | V25: 2306 | W25: 2291 | X25: 1991 | Y25: 1991 | Z25: 1991 | AA25: 1991 | AB25: 1991
A26: 1 | C26: 단기금융부채 | E26: 2157.76 | F26: 2157.76 | G26: 2741.93 | H26: 4977.18 | I26: 7671.2 | J26: 1962.29 | K26: 1962.29 | L26: 1801.75 | M26: 1715.46 | N26: 1827.51 | O26: 1829.92 | P26: 1829.92 | Q26: 1832.37 | R26: 1836.69 | S26: 1944.81 | T26: 1948.3 | U26: 1948.3 | V26: 2651.83 | W26: 2640.39 | X26: 2342.25 | Y26: 2345.42 | Z26: 2345.42 | AA26: 2348.62 | AB26: 2351.85
A27: 1 | C27: 기타유동부채 | E27: 2388.2 | F27: 2388.2 | G27: 2234.03 | H27: 2138.98 | I27: 2548.84 | J27: 2333.97 | K27: 2333.97 | L27: 3113.29 | M27: 2117.64 | N27: 3418 | O27: 2435.45 | P27: 2435.45 | Q27: 2410.27 | R27: 2332.05 | S27: 2123.74 | T27: 3058.67 | U27: 3058.67 | V27: 2519.24 | W27: 2141.78 | X27: 1960.11 | Y27: 2203.36 | Z27: 2203.36 | AA27: 2104.34 | AB27: 1918.28
A28: 1 | C28: 비유동부채 | E28: 71484.77 | F28: 71484.77 | G28: 51040.86 | H28: 43719.69 | I28: 49631.04 | J28: 51402.38 | K28: 51402.38 | L28: 40796.12 | M28: 44880.1 | N28: 39129.74 | O28: 35180.47 | P28: 35180.47 | Q28: 35097.26 | R28: 35432.1 | S28: 41695.48 | T28: 40858.95 | U28: 40858.95 | V28: 40910.01 | W28: 41130.47 | X28: 35405 | Y28: 36361.98 | Z28: 36361.98 | AA28: 36271.36 | AB28: 36391.54
A29: 1 | C29: 장기차입금 | E29: 16421.5 | F29: 16421.5 | G29: 16548 | H29: 10494 | I29: 16494 | J29: 16494 | K29: 16494 | L29: 6000 | M29: 10000 | N29: 4000 | O29: 0 | P29: 0 | Q29: 0 | R29: 0 | S29: 6000 | T29: 6000 | U29: 6000 | V29: 6000 | W29: 6000 | X29: 0 | Y29: 0 | Z29: 0
A30: 1 | C30: 사채 | E30: 21317.19 | F30: 21317.19 | G30: 0 | H30: 0 | I30: 0 | J30: 0 | K30: 0 | L30: 0 | M30: 0 | N30: 0 | O30: 0 | P30: 0 | Q30: 0 | R30: 0 | S30: 0 | T30: 0 | U30: 0 | V30: 0 | W30: 0 | X30: 0
A31: 1 | C31: 확정급여부채 | E31: -36.18 | F31: -36.18 | G31: 710.59 | J31: 0 | K31: 0 | L31: 0 | M31: 0 | N31: 0 | O31: 0 | P31: 0 | Q31: 0 | R31: 0 | S31: 0 | T31: 0 | U31: 0 | V31: 138.85 | W31: 0 | X31: 2.67
A32: 1 | C32: 이연법인세부채 | E32: 33782.27 | F32: 33782.27 | G32: 33782.27 | H32: 33014.89 | I32: 33014.89 | J32: 34796.12 | K32: 34796.12 | L32: 34796.12 | M32: 34880.1 | N32: 34880.1 | O32: 35012.95 | P32: 35012.95 | Q32: 35012.95 | R32: 35432.1 | S32: 35432.1 | T32: 33176.57 | U32: 33176.57 | V32: 33176.57 | W32: 33624.58 | X32: 33624.58 | Y32: 34674.03 | Z32: 34674.03 | AA32: 34674.03 | AB32: 34885.64
A33: 1 | C33: 기타비유동금융부채 | E33: 0 | F33: 0 | G33: 0 | H33: 210.8 | I33: 122.15 | J33: 0 | K33: 0 | L33: 0 | M33: 0 | N33: 0 | O33: 0 | P33: 0 | Q33: 0 | R33: 0 | S33: 0 | T33: 1505.9 | U33: 1505.9 | V33: 1505.9 | W33: 1505.9 | X33: 1505.9 | Y33: 1505.9 | Z33: 1505.9 | AA33: 1505.9 | AB33: 1505.9
A34: 1 | C34: 장기금융부채 | E34: 0 | F34: 0 | G34: 0 | H34: 210.8 | I34: 122.15 | J34: 112.26 | K34: 112.26 | L34: 0 | M34: 0 | N34: 249.64 | O34: 167.52 | P34: 167.52 | Q34: 84.31 | R34: 0 | S34: 263.38 | T34: 1682.39 | U34: 1682.39 | V34: 1594.6 | W34: 1505.9 | X34: 1777.75 | Y34: 1687.95 | Z34: 1687.95 | AA34: 1597.33 | AB34: 1505.9
A35: 1 | C35: 부채총계 | E35: 154866.44 | F35: 154866.44 | G35: 162640.66 | H35: 171052.21 | I35: 174987.59 | J35: 159460.03 | K35: 159460.03 | L35: 153385.32 | M35: 156186.77 | N35: 163396.37 | O35: 152995.49 | P35: 152995.49 | Q35: 154029.21 | R35: 161757.41 | S35: 162266.69 | T35: 166985.18 | U35: 166985.18 | V35: 171347.25 | W35: 164747.88 | X35: 174579.27 | Y35: 167957.12 | Z35: 167957.12 | AA35: 174058.56 | AB35: 200591.34
A36: 1 | C36: 자본금 | E36: 13348.73 | F36: 13348.73 | G36: 13348.73 | H36: 13348.73 | I36: 13348.73 | J36: 13348.73 | K36: 13348.73 | L36: 13348.73 | M36: 13348.73 | N36: 13348.73 | O36: 13348.73 | P36: 13348.73 | Q36: 13348.73 | R36: 13348.73 | S36: 13348.73 | T36: 13348.73 | U36: 13348.73 | V36: 13348.73 | W36: 13348.73 | X36: 13348.73 | Y36: 13348.73 | Z36: 13348.73 | AA36: 13348.73 | AB36: 13348.73
A37: 1 | C37: 자본잉여금 | E37: 11140.41 | F37: 11140.41 | G37: 11140.41 | H37: 11140.41 | I37: 11140.41 | J37: 11140.41 | K37: 11140.41 | L37: 11140.41 | M37: 11140.41 | N37: 11140.41 | O37: 11140.41 | P37: 11140.41 | Q37: 11140.41 | R37: 11140.41 | S37: 11140.41 | T37: 11140.41 | U37: 11140.41 | V37: 11140.41 | W37: 9948.95 | X37: 9948.95 | Y37: 14513.78 | Z37: 14513.78 | AA37: 14513.78 | AB37: 14513.78
A38: 1 | C38: 이익잉여금 | E38: 148994.34 | F38: 148994.34 | G38: 151197.62 | H38: 149475.92 | I38: 143895.6 | J38: 144613 | K38: 144613 | L38: 144990.53 | M38: 144694.54 | N38: 143578.91 | O38: 143195.25 | P38: 143195.25 | Q38: 140633.35 | R38: 138536.34 | S38: 137914.57 | T38: 135102.98 | U38: 135102.98 | V38: 134460.23 | W38: 136673.91 | X38: 136081.32 | Y38: 135033 | Z38: 135033 | AA38: 132568.77 | AB38: 134059.44
A39: 1 | C39: 자본총계 | E39: 173337.65 | F39: 173337.65 | G39: 175542.21 | H39: 173814.63 | I39: 168230.23 | J39: 168944.1 | K39: 168944.1 | L39: 169316.31 | M39: 169023.96 | N39: 167909.1 | O39: 167526.03 | P39: 167526.03 | Q39: 164968.32 | R39: 162870.25 | S39: 162244.65 | T39: 159433.91 | U39: 159433.91 | V39: 158790.35 | W39: 159813.63 | X39: 159370.29 | Y39: 156433.92 | Z39: 156433.92 | AA39: 153969.68 | AB39: 155460.35
A40: 1 | C40: 부채와자본총계 | E40: 328204.09 | F40: 328204.09 | G40: 338182.87 | H40: 344866.84 | I40: 343217.83 | J40: 328404.14 | K40: 328404.14 | L40: 322701.63 | M40: 325210.72 | N40: 331305.48 | O40: 320521.52 | P40: 320521.52 | Q40: 318997.53 | R40: 324627.66 | S40: 324511.34 | T40: 326419.09 | U40: 326419.09 | V40: 330137.61 | W40: 324561.51 | X40: 333949.57 | Y40: 324391.04 | Z40: 324391.04 | AA40: 328028.24 | AB40: 356051.69
A41: 1 | C41: 지배주주지분 | E41: 173337.65 | F41: 173337.65 | G41: 175542.21 | H41: 173814.63 | I41: 168230.23 | J41: 168944.1 | K41: 168944.1 | L41: 169316.31 | M41: 169023.96 | N41: 167909.1 | O41: 167526.03 | P41: 167526.03 | Q41: 164968.32 | R41: 162870.25 | S41: 162244.65 | T41: 159433.91 | U41: 159433.91 | V41: 158790.35 | W41: 159813.63 | X41: 159370.29 | Y41: 156433.92 | Z41: 156433.92 | AA41: 153969.68 | AB41: 155460.35
A42: 1 | C42: 총차입금 | E42: 105927.31 | F42: 105927.31 | G42: 109915.77 | H42: 123632.89 | I42: 118961.94 | J42: 106970.5 | K42: 106970.5 | L42: 101053.95 | M42: 99726.24 | N42: 99061.29 | O42: 98053.34 | P42: 98053.34 | Q42: 94213.84 | R42: 107036.14 | S42: 109686.32 | T42: 110940.08 | U42: 110940.08 | V42: 117934.8 | W42: 111669.22 | X42: 117575.85 | Y42: 111705.27 | Z42: 111705.27 | AA42: 112569 | AB42: 117164.55
A43: 1 | C43: 순차입금 | E43: 79717.08 | F43: 79717.08 | G43: 79921.9 | H43: 115282.66 | I43: 114319.35 | J43: 68859.3 | K43: 68859.3 | L43: 72834.11 | M43: 72914.22 | N43: 73519.05 | O43: 69592.62 | P43: 69592.62 | Q43: 72871.23 | R43: 82733.37 | S43: 78930.38 | T43: 78037.37 | U43: 78037.37 | V43: 81466.82 | W43: 78586.63 | X43: 85849.89 | Y43: 83195.16 | Z43: 83195.16 | AA43: 77554.82 | AB43: 76147.89
A44: 1 | C44: 이자발생자산 | E44: 28232.43 | F44: 28232.43 | G44: 32017.97 | H44: 11052.2 | I44: 7344.56 | J44: 40862.97 | K44: 40862.97 | L44: 30959.52 | M44: 29657.56 | N44: 28293.31 | O44: 30867.43 | P44: 30867.43 | Q44: 23776.33 | R44: 28192.45 | S44: 34613.07 | T44: 36998.08 | U44: 36998.08 | V44: 41316.4 | W44: 38042.46 | X44: 36485.77 | Y44: 33017.21 | Z44: 33017.21 | AA44: 38925.15 | AB44: 44927.4
A45: 1 | C45: 기타유동금융자산 | H45: 27725.96 | I45: 29301.11 | J45: 0 | K45: 0 | L45: 0 | M45: 0 | N45: 0 | O45: 0 | P45: 0 | Q45: 0 | R45: 0 | S45: 0 | T45: 0 | U45: 0 | V45: 0 | W45: 0 | X45: 0
A46: 1 | C46: 단기투자자산(공정가치) | H46: 501.19 | I46: 499.57 | J46: 502.49 | K46: 502.49 | L46: 509.45 | M46: 511.52 | N46: 513.77 | O46: 528.29 | P46: 528.29 | Q46: 0 | R46: 0 | S46: 5000 | T46: 0 | U46: 0 | V46: 0 | X46: 0 | Y46: 0.04 | Z46: 0.04 | AA46: 0 | AB46: 0
A47: 1 | C47: 기타비유동자산 | H47: 492.57 | I47: 570.76 | J47: 841.2 | K47: 841.2 | L47: 707.81 | M47: 734.42 | N47: 601.04 | O47: 691.54 | P47: 691.54 | Q47: 547.76 | R47: 384.09 | S47: 230.8 | T47: 43.06 | U47: 43.06 | V47: 0 | W47: 179.24 | X47: 0 | Y47: 948.27 | Z47: 948.27 | AA47: 780.28 | AB47: 822.28
A48: 1 | C48: 당기법인세부채(미지급법인세) | H48: 513.98 | I48: 65.62 | J48: 3.35 | K48: 3.35 | L48: 0 | M48: 98.98 | N48: 98.98 | O48: 0 | P48: 0 | Q48: -62.83 | R48: 0 | S48: 0 | T48: 0 | U48: 0 | V48: 0 | W48: 0 | X48: 0 | Y48: 0.49 | Z48: 0.49 | AA48: 0.04 | AB48: 0
A49: 1 | C49: 기타자본 | H49: -150.43 | I49: -154.51 | J49: -158.04 | K49: -158.04 | L49: -163.36 | M49: -159.72 | N49: -158.95 | O49: -158.37 | P49: -158.37 | Q49: -154.17 | R49: -155.23 | S49: -159.06 | T49: -158.21 | U49: -158.21 | V49: -159.02 | W49: -157.96 | X49: -8.71 | Y49: -4564.83 | Z49: -4564.83 | AA49: -4564.83 | AB49: -4564.83
A50: 1 | C50: 유동리스부채 | J50: 270.29 | K50: 270.29 | L50: 295.75 | M50: 209.46 | N50: 321.51 | O50: 323.92 | P50: 323.92 | Q50: 326.37 | R50: 330.69 | S50: 338.81 | T50: 342.3 | U50: 342.3 | V50: 345.83 | W50: 349.39 | X50: 351.25 | Y50: 354.42 | Z50: 354.42 | AA50: 357.62 | AB50: 360.85
A51: 1 | C51: 리스부채 | J51: 382.55 | K51: 382.55 | L51: 295.75 | M51: 209.46 | N51: 571.15 | O51: 491.44 | P51: 491.44 | Q51: 410.68 | R51: 330.69 | S51: 602.19 | T51: 518.79 | U51: 518.79 | V51: 434.53 | W51: 349.39 | X51: 623.1 | Y51: 536.47 | Z51: 536.47 | AA51: 449.05 | AB51: 360.85
A52: 1 | C52: 비유동리스부채 | J52: 112.26 | K52: 112.26 | L52: 0 | M52: 0 | N52: 249.64 | O52: 167.52 | P52: 167.52 | Q52: 84.31 | R52: 0 | S52: 263.38 | T52: 176.49 | U52: 176.49 | V52: 88.7 | W52: 0 | X52: 271.85 | Y52: 182.05 | Z52: 182.05 | AA52: 91.43 | AB52: 0
A53: 1 | C53: 단기금융부채(face) | N53: 95061.29 | O53: 98053.34 | P53: 98053.34 | Q53: 94213.84 | R53: 107036.14 | S53: 103686.32 | T53: 104940.08 | U53: 104940.08 | V53: 111934.8 | W53: 105669.22 | X53: 117575.85 | Y53: 111705.27 | Z53: 111705.27 | AA53: 112569 | AB53: 117164.55
A54: 1 | C54: 기타비유동부채 | N54: 0 | O54: 0 | P54: 0 | Q54: 0 | R54: 0 | S54: 0 | T54: 0 | U54: 0 | V54: 0 | W54: 0 | X54: 0
A55: 1 | C55: 장기금융부채(face) | S55: 6000 | T55: 6000 | U55: 6000 | V55: 6000 | W55: 6000 | X55: 0 | Y55: 0 | Z55: 0
A56: 1 | C56: 기타포괄이익누계액 | Y56: -1896.77 | Z56: -1896.77 | AA56: -1896.77 | AB56: -1896.77
A57: 1 | C57: 매출액(수익) | E57: 66146.79 | G57: 69565.95 | H57: 58293.26 | I57: 59866.52 | J57: 54186.08 | K57: 241911.81 | L57: 57458.81 | M57: 48614.22 | N57: 48611.2 | O57: 46401.11 | P57: 201085.34 | Q57: 46198 | R57: 49841.3 | S57: 38203.5 | T57: 48723.46 | U57: 182966.26 | V57: 43671.02 | W57: 45976.78 | X57: 46050.96 | Y57: 40597.32 | Z57: 176296.08 | AA57: 57647.41 | AB57: 57497.5
A58: 1 | C58: 매출원가 | E58: 56793.96 | G58: 65319.72 | H58: 53679.31 | I58: 58757.1 | J58: 52720.96 | K58: 230477.09 | L58: 51256.22 | M58: 45082.43 | N58: 45625.48 | O58: 44904.75 | P58: 186868.88 | Q58: 42669.17 | R58: 47205.72 | S58: 36679.47 | T58: 45798.77 | U58: 172353.13 | V58: 41095.32 | W58: 42004.04 | X58: 42313.7 | Y58: 38357.31 | Z58: 163770.37 | AA58: 54347.59 | AB58: 51612.08
A59: 1 | C59: 매출총이익 | E59: 9352.83 | G59: 4246.24 | H59: 4613.95 | I59: 1109.42 | J59: 1465.12 | K59: 11434.73 | L59: 6202.59 | M59: 3531.79 | N59: 2985.72 | O59: 1496.36 | P59: 14216.46 | Q59: 3528.82 | R59: 2635.59 | S59: 1524.03 | T59: 2924.69 | U59: 10613.13 | V59: 2575.71 | W59: 3972.74 | X59: 3737.26 | Y59: 2240 | Z59: 12525.71 | AA59: 3299.82 | AB59: 5885.43
A60: 1 | C60: 판관비 | E60: 2194.02 | G60: 2298.5 | H60: 1351.15 | I60: 1968.17 | J60: 2167.3 | K60: 7785.12 | L60: 2611.09 | M60: 2427.33 | N60: 2201.76 | O60: 2836.79 | P60: 10076.97 | Q60: 3220.2 | R60: 2505.02 | S60: 2601.27 | T60: 3200.71 | U60: 11527.2 | V60: 2634.13 | W60: 2488.39 | X60: 2523.08 | Y60: 2563.48 | Z60: 10209.08 | AA60: 2782.56 | AB60: 2957.84
A61: 1 | C61: 영업이익 | E61: 7158.81 | G61: 1947.74 | H61: 3262.8 | I61: -858.75 | J61: -702.17 | K61: 3649.62 | L61: 3591.5 | M61: 1104.47 | N61: 783.96 | O61: -1340.43 | P61: 4139.5 | Q61: 308.62 | R61: 130.57 | S61: -1077.24 | T61: -276.02 | U61: -914.07 | V61: -58.42 | W61: 1484.35 | X61: 1214.19 | Y61: -323.48 | Z61: 2316.64 | AA61: 517.26 | AB61: 2927.59
A62: 1 | C62: 기타영업외손익 | E62: 17.67 | G62: 245.97 | H62: 212.35 | I62: 116.23 | J62: -81.77 | K62: 492.78 | L62: -283.7 | M62: -188.34 | N62: 188.1 | O62: 717.15 | P62: 433.21 | Q62: 59.5 | R62: 238.2 | S62: 249.44 | T62: 11.81 | U62: 558.95 | V62: 557.64 | W62: -535.15 | X62: 417.21 | Y62: 207.9 | Z62: 647.6 | AA62: 193.96 | AB62: 169.54
A63: 1 | C63: 금융수익 | E63: 3455.27 | G63: 474.35 | L63: 330.11 | M63: 400.7 | N63: -81.91 | O63: 1300.01 | P63: 1948.91 | Q63: 156.07 | R63: 131 | S63: 235.5 | T63: 630.24 | U63: 1152.81 | V63: 365.66 | W63: 2947.69 | X63: -1017.32 | Y63: -640.21 | Z63: 1655.82 | AA63: 304.09 | AB63: 313.36
A64: 1 | C64: 금융비용 | E64: 1571.73 | G64: 465.15 | L64: 2528.28 | M64: 1430.91 | N64: 2005.98 | O64: 454.57 | P64: 6419.74 | Q64: 2356.6 | R64: 2163.8 | S64: 28.46 | T64: 4764.25 | U64: 9313.11 | V64: 1263.87 | W64: 1235.48 | X64: 1206.67 | Y64: 1222.08 | Z64: 4928.1 | AA64: 2767.27 | AB64: 1708.22
A65: 1 | C65: 법인세비용차감전계속사업이익 | E65: 9060.02 | G65: 2202.92 | H65: -801.7 | I65: -5579.17 | J65: 2492.21 | K65: -1685.74 | L65: 1109.63 | M65: -114.08 | N65: -1115.83 | O65: 222.16 | P65: 101.88 | Q65: -1832.4 | R65: -1664.03 | S65: -620.77 | T65: -4398.21 | U65: -8515.41 | V65: -398.99 | W65: 2661.4 | X65: -592.58 | Y65: -1977.86 | Z65: -308.03 | AA65: -1751.96 | AB65: 1702.28
A66: 1 | C66: 법인세비용 | E66: 1727.11 | G66: -0.36 | H66: -298.41 | I66: 1.15 | J66: 1341.26 | K66: 1043.64 | L66: 1.5 | M66: 181.91 | N66: 0.21 | O66: 206.28 | P66: 389.9 | Q66: -1.11 | R66: 432.97 | S66: 1.01 | T66: -2115.9 | U66: -1683.03 | V66: -0.22 | W66: 447.73 | X66: 0 | Y66: -747.91 | Z66: -300.4 | AA66: 0 | AB66: 211.6
A67: 1 | C67: 당기순이익 | E67: 7332.91 | G67: 2203.28 | H67: -503.29 | I67: -5580.32 | J67: 1150.95 | K67: -2729.38 | L67: 1108.14 | M67: -295.99 | N67: -1115.63 | O67: 15.88 | P67: -287.6 | Q67: -1831.3 | R67: -2097.01 | S67: -621.78 | T67: -2282.3 | U67: -6832.39 | V67: -399.21 | W67: 2213.67 | X67: -592.58 | Y67: -1229.95 | Z67: -8.07 | AA67: -1751.96 | AB67: 1490.67
A68: 1 | C68: 총포괄손익 | E68: 7217.56 | G68: 2204.56 | H68: -509.17 | I68: -5584.4 | J68: 713.87 | K68: -3175.14 | L68: 1102.82 | M68: -292.36 | N68: -1114.85 | O68: -383.07 | P68: -687.46 | Q68: -1827.1 | R68: -2098.07 | S68: -625.6 | T68: -2810.75 | U68: -7361.52 | V68: -400.02 | W68: 2214.74 | X68: -443.34 | Y68: -2936.38 | Z68: -1565 | AA68: -1751.96 | AB68: 1490.67
A69: 1 | C69: 금융손익 | E69: 1883.54 | G69: 9.2 | H69: -4276.85 | I69: -4836.64 | J69: 3276.16 | K69: -5828.13 | L69: -2198.17 | M69: -1030.21 | N69: -2087.89 | O69: 845.44 | P69: -4470.83 | Q69: -2200.53 | R69: -2032.8 | S69: 207.04 | T69: -4134.01 | U69: -8160.3 | V69: -898.21 | W69: 1712.21 | X69: -2223.99 | Y69: -1862.29 | Z69: -3272.28 | AA69: -2463.18 | AB69: -1394.86
A70: 1 | C70: (지배주주지분)당기순이익 | E70: 7332.91 | G70: 2203.28 | H70: -503.29 | I70: -5580.32 | J70: 1150.95 | K70: -2729.38 | L70: 1108.14 | M70: -295.99 | N70: -1115.63 | O70: 15.88 | P70: -287.6 | Q70: -1831.3 | R70: -2097.01 | S70: -621.78 | T70: -2282.3 | U70: -6832.39 | V70: -399.21 | W70: 2213.67 | X70: -592.58 | Y70: -1229.95 | Z70: -8.07 | AA70: -1751.96 | AB70: 1490.67
A71: 1 | C71: 계속사업이익 | E71: 7332.91 | G71: 2203.28 | H71: -503.29 | I71: -5580.32 | J71: 1150.95 | K71: -2729.38 | L71: 1108.14 | M71: -295.99 | N71: -1115.63 | O71: 15.88 | P71: -287.6 | Q71: -1831.3 | R71: -2097.01 | S71: -621.78 | T71: -2282.3 | U71: -6832.39 | V71: -399.21 | W71: 2213.67 | X71: -592.58 | Y71: -1229.95 | Z71: -8.07 | AA71: -1751.96 | AB71: 1490.67
A72: 1 | C72: 기타영업외수익 | L72: 761.72 | M72: 280.46 | N72: 665.57 | O72: 665.37 | P72: 2373.12 | Q72: 660.57 | R72: 525.77 | S72: 693.25 | T72: 632.57 | U72: 2512.16 | V72: 1034.94 | W72: -71.28 | X72: 632.67 | Y72: 725.05 | Z72: 2321.38 | AA72: 699.42 | AB72: 645.09
A73: 1 | C73: 기타영업외비용 | L73: 1045.42 | M73: 468.8 | N73: 477.47 | O73: -51.78 | P73: 1939.91 | Q73: 601.07 | R73: 287.57 | S73: 443.81 | T73: 620.76 | U73: 1953.21 | V73: 477.3 | W73: 463.87 | X73: 215.46 | Y73: 517.15 | Z73: 1673.78 | AA73: 505.46 | AB73: 475.55
A74: 1 | C74: 영업활동으로인한현금흐름 | E74: 9069.93 | G74: 754.93 | H74: -2962.94 | I74: 9919.8 | J74: 12965.6 | K74: 20677.39 | L74: -2925.96 | M74: 1735.49 | N74: 2717.56 | O74: 3402.11 | P74: 4929.2 | Q74: -24.3 | R74: -6388.4 | S74: 8238.97 | T74: 185.24 | U74: 2011.51 | V74: -3092.03 | W74: 2560.29 | X74: -4836.31 | Y74: 5914.03 | Z74: 545.98 | AA74: 8300.14 | AB74: 3728.04
A75: 1 | C75: 배당금수취(CF) | E75: -61 | I75: 0 | J75: 0 | L75: 0 | M75: 60.92 | N75: 0 | O75: 0 | P75: 60.92 | Q75: 0 | R75: 30.46 | S75: 0 | T75: 0 | U75: 30.46 | V75: 0 | W75: 30.46 | X75: 0 | Y75: 0 | Z75: 30.46
A76: 1 | C76: 법인세납부(CF) | E76: -1628.13 | G76: -320.07 | H76: -515.51 | I76: -450.8 | J76: -6.01 | K76: -1292.39 | L76: 422.93 | M76: -19.3 | N76: -195.14 | O76: 63.57 | P76: 272.06 | Q76: 89.99 | R76: -13.71 | S76: -73.97 | T76: -38.67 | U76: -36.36 | V76: 104.67 | W76: -26.05 | X76: -59.08 | Y76: -32.83 | Z76: -13.29 | AA76: 120.67 | AB76: -7.42
A77: 1 | C77: 투자활동으로인한현금흐름 | E77: -1260.68 | G77: -9447.22 | H77: -4578.19 | I77: -4903.35 | J77: -468.6 | K77: -19397.36 | L77: 9122.17 | M77: -836.1 | N77: -996.39 | O77: -212.83 | P77: 7076.85 | Q77: -643.71 | R77: -2817.14 | S77: -6966.02 | T77: -2535.49 | U77: -12962.36 | V77: -2750 | W77: -853.51 | X77: -78.43 | Y77: -2523.39 | Z77: -6205.33 | AA77: 1793.07 | AB77: -7879.79
A78: 1 | C78: 무형자산의증가 | E78: 0 | I78: 340 | J78: 7.48 | L78: 0 | M78: 0 | N78: 0 | O78: 0 | P78: 0 | Q78: 0 | R78: 0 | S78: 0 | T78: 0 | U78: 0 | V78: 0 | W78: 0 | X78: 0 | Y78: 817.6 | Z78: 817.6
A79: 1 | C79: 재무활동으로인한현금흐름 | E79: -3574.2 | G79: 4324.87 | H79: 9813.39 | I79: -8734.93 | J79: -7088.25 | K79: -1684.92 | L79: -6888.11 | M79: -2316.89 | N79: -1091.89 | O79: -270.43 | P79: -10567.32 | Q79: -5950.74 | R79: 12163.17 | S79: 4180.94 | T79: -302.64 | U79: 10090.73 | V79: 7407.36 | W79: -5091.59 | X79: 4408.08 | Y79: -6606.46 | Z79: 117.39 | AA79: -1599.69 | AB79: 3911.8
A80: 1 | C80: 장기차입금의증가 | E80: 0 | G80: 20347.2 | O80: 4000 | Q80: 0 | R80: 0 | S80: 6000 | T80: 0 | U80: 6000 | V80: 0 | W80: 0 | X80: 0 | Y80: 0 | Z80: 0
A81: 1 | C81: 현금및현금성자산의증감 | E81: 4235 | G81: -4367.99 | H81: 2272.84 | I81: -3718.49 | J81: 5418.84 | K81: -394.8 | L81: -691.36 | M81: -1407.82 | N81: 630.22 | O81: 2918.48 | P81: 1449.52 | Q81: -6618.11 | R81: 2960.16 | S81: 5453.17 | T81: -2653.23 | U81: -858.01 | V81: 1565.26 | W81: -3385.38 | X81: -506.63 | Y81: -3215.85 | Z81: -5542.6 | AA81: 8504.07 | AB81: -197.52
A82: 1 | C82: 기말현금및현금성자산 | E82: 4235 | G82: 6078.01 | H82: 2272.22 | I82: -3707.64 | J82: 5408.61 | K82: 10051.2 | L82: 9359.84 | M82: -1407.82 | N82: 630.22 | O82: 2918.48 | P82: 11500.72 | Q82: 4882.61 | R82: 2960.16 | S82: 5453.17 | T82: -2653.23 | U82: 10642.71 | V82: 12207.98 | W82: -3385.39 | X82: -506.63 | Y82: -3215.85 | Z82: 5100.11 | AA82: 13604.18 | AB82: -197.52
A83: 1 | C83: CAPEX | E83: 0 | G83: 1398.66 | H83: 1162.02 | I83: 2144.96 | J83: 2312.69 | K83: 7018.33 | L83: 155.13 | M83: 836.94 | N83: 2891.37 | O83: 1584.54 | P83: 5467.98 | Q83: 1716.52 | R83: 1283.47 | S83: 935.92 | T83: 2225.61 | U83: 6161.52 | V83: 0 | W83: 853.65 | X83: 963.83 | Y83: 2502.54 | Z83: 4320.02 | AA83: 905 | AB83: 1679.79
A84: 1 | C84: 유형자산의감소 | G84: 12.85 | I84: 213.5 | L84: 71.16 | M84: 0.84 | N84: 4 | O84: 0 | P84: 76 | Q84: 65.02 | S84: 0 | T84: 0 | V84: 0 | W84: 0 | X84: 0 | Y84: 0 | Z84: 0 | AA84: 57.36 | AB84: 0
A85: 1 | C85: 유형자산의증가 | G85: 1398.66 | H85: 1162.02 | I85: 1804.96 | J85: 2305.21 | K85: 6670.85 | L85: 155.13 | M85: 836.94 | N85: 2891.37 | O85: 1584.54 | P85: 5467.98 | Q85: 1716.52 | R85: 1283.47 | S85: 935.92 | T85: 2225.61 | U85: 6161.52 | V85: 0 | W85: 853.65 | X85: 963.83 | Y85: 1684.94 | Z85: 3502.42 | AA85: 905 | AB85: 1679.79
A86: 1 | C86: 단기차입금의증가 | G86: 24727.06 | H86: 40620.8 | L86: 6615.31 | M86: 5500 | N86: 1203.93 | O86: 0 | P86: 13319.24 | Q86: 4896.2 | R86: 39501.6 | V86: 8799.16 | W86: 10000 | X86: 11280.99 | AA86: 16300 | AB86: 4000
A87: 1 | C87: 이자지급(CF) | I87: -1107.59
A88: 1 | C88: 배당금지급 | I88: 0 | J88: 0 | L88: 0 | M88: 730.61 | N88: 0 | O88: 0 | P88: 730.61 | Q88: 730.61 | R88: 0 | S88: 0 | T88: 0 | U88: 730.61 | V88: 243.54 | W88: 0 | X88: 0 | Y88: 0 | Z88: 243.54 | AA88: 712.28 | AB88: 0
A89: 1 | C89: 유동성장기부채의감소 | L89: 0 | M89: 0 | N89: 0 | O89: 0 | P89: 0 | Q89: 0 | R89: 0 | S89: 0 | T89: 0 | U89: 0 | V89: 0 | W89: 0 | X89: 0
A90: 1 | C90: 리스부채의상환 | L90: 86.8 | M90: 86.29 | O90: 270.43 | Q90: 323.92 | S90: 82.56 | T90: 83.4 | V90: 84.26 | W90: 85.14 | X90: 172.9 | Y90: 0 | Z90: 342.3 | AA90: 87.41 | AB90: 88.21
A91: 1 | C91: 단기차입금의감소 | V91: 1764 | W91: 13800 | X91: 6400 | AA91: 17100 | AB91: 0

Sheet subQ
A1: YQ | C1: subQ 분기 서브모델(억원, U=100) | E1: 4Q21 | F1: 2021 | G1: 1Q22 | H1: 2Q22 | I1: 3Q22 | J1: 4Q22 | K1: 2022 | L1: 1Q23 | M1: 2Q23 | N1: 3Q23 | O1: 4Q23 | P1: 2023 | Q1: 1Q24 | R1: 2Q24 | S1: 3Q24 | T1: 4Q24 | U1: 2024 | V1: 1Q25 | W1: 2Q25 | X1: 3Q25 | Y1: 4Q25 | Z1: 2025 | AA1: 1Q26 | AB1: 2Q26 | AC1: 3Q26 | AD1: 4Q26 | AE1: 2026 | AF1: 1Q27 | AG1: 2Q27 | AH1: 3Q27 | AI1: 4Q27 | AJ1: 2027 | AK1: 1Q28 | AL1: 2Q28 | AM1: 3Q28 | AN1: 4Q28 | AO1: 2028
A2: A=이름(key) B=그룹 C=단위 D=FnGuide 계정명(VLOOKUP 키). 확정=VLOOKUP(BS), 추정=변수 가정 참조
E3: 1 | F3: 2 | G3: 3 | H3: 4 | I3: 5 | J3: 6 | K3: 7 | L3: 8 | M3: 9 | N3: 10 | O3: 11 | P3: 12 | Q3: 13 | R3: 14 | S3: 15 | T3: 16 | U3: 17 | V3: 18 | W3: 19 | X3: 20 | Y3: 21 | Z3: 22 | AA3: 23 | AB3: 24 | AC3: 25 | AD3: 26 | AE3: 27 | AF3: 28 | AG3: 29 | AH3: 30 | AI3: 31 | AJ3: 32 | AK3: 33 | AL3: 34 | AM3: 35 | AN3: 36 | AO3: 37
E4: 2021.12 | F4: 2021.12A | G4: 2022.03 | H4: 2022.06 | I4: 2022.09 | J4: 2022.12 | K4: 2022.12A | L4: 2023.03 | M4: 2023.06 | N4: 2023.09 | O4: 2023.12 | P4: 2023.12A | Q4: 2024.03 | R4: 2024.06 | S4: 2024.09 | T4: 2024.12 | U4: 2024.12A | V4: 2025.03 | W4: 2025.06 | X4: 2025.09 | Y4: 2025.12 | Z4: 2025.12A | AA4: 2026.03 | AB4: 2026.06 | AC4: 2026.09 | AD4: 2026.12 | AE4: 2026.12A | AF4: 2027.03 | AG4: 2027.06 | AH4: 2027.09 | AI4: 2027.12 | AJ4: 2027.12A | AK4: 2028.03 | AL4: 2028.06 | AM4: 2028.09 | AN4: 2028.12 | AO4: 2028.12A
A5: 매출액 | B5: 손익 | C5: 억원 | D5: 매출액(수익) | E5: =IFERROR(VLOOKUP($D5,BS연결,MATCH(E$1,BS연결H,0),0)/100,"") | G5: =IFERROR(VLOOKUP($D5,BS연결,MATCH(G$1,BS연결H,0),0)/100,"") | H5: =IFERROR(VLOOKUP($D5,BS연결,MATCH(H$1,BS연결H,0),0)/100,"") | I5: =IFERROR(VLOOKUP($D5,BS연결,MATCH(I$1,BS연결H,0),0)/100,"") | J5: =IFERROR(VLOOKUP($D5,BS연결,MATCH(J$1,BS연결H,0),0)/100,"") | K5: =IFERROR(VLOOKUP($D5,BS연결,MATCH(K$1,BS연결H,0),0)/100,"") | L5: =IFERROR(VLOOKUP($D5,BS연결,MATCH(L$1,BS연결H,0),0)/100,"") | M5: =IFERROR(VLOOKUP($D5,BS연결,MATCH(M$1,BS연결H,0),0)/100,"") | N5: =IFERROR(VLOOKUP($D5,BS연결,MATCH(N$1,BS연결H,0),0)/100,"") | ... AB5: =IFERROR(VLOOKUP($D5,BS연결,MATCH(AB$1,BS연결H,0),0)/100,"") | AC5: =IFERROR(X5*(1+변수!AC21),"") | AD5: =IFERROR(Y5*(1+변수!AD21),"") | AE5: =SUM(AA5:AD5) | AF5: =IFERROR(AA5*(1+변수!AF21),"") | AG5: =IFERROR(AB5*(1+변수!AG21),"") | AH5: =IFERROR(AC5*(1+변수!AH21),"") | AI5: =IFERROR(AD5*(1+변수!AI21),"") | AJ5: =SUM(AF5:AI5) | AK5: =IFERROR(AF5*(1+변수!AK21),"") | AL5: =IFERROR(AG5*(1+변수!AL21),"") | AM5: =IFERROR(AH5*(1+변수!AM21),"") | AN5: =IFERROR(AI5*(1+변수!AN21),"") | AO5: =SUM(AK5:AN5)
A6: 매출원가 | B6: 손익 | C6: 억원 | D6: 매출원가 | E6: =IFERROR(VLOOKUP($D6,BS연결,MATCH(E$1,BS연결H,0),0)/100,"") | G6: =IFERROR(VLOOKUP($D6,BS연결,MATCH(G$1,BS연결H,0),0)/100,"") | H6: =IFERROR(VLOOKUP($D6,BS연결,MATCH(H$1,BS연결H,0),0)/100,"") | I6: =IFERROR(VLOOKUP($D6,BS연결,MATCH(I$1,BS연결H,0),0)/100,"") | J6: =IFERROR(VLOOKUP($D6,BS연결,MATCH(J$1,BS연결H,0),0)/100,"") | K6: =IFERROR(VLOOKUP($D6,BS연결,MATCH(K$1,BS연결H,0),0)/100,"") | L6: =IFERROR(VLOOKUP($D6,BS연결,MATCH(L$1,BS연결H,0),0)/100,"") | M6: =IFERROR(VLOOKUP($D6,BS연결,MATCH(M$1,BS연결H,0),0)/100,"") | N6: =IFERROR(VLOOKUP($D6,BS연결,MATCH(N$1,BS연결H,0),0)/100,"") | ... AB6: =IFERROR(VLOOKUP($D6,BS연결,MATCH(AB$1,BS연결H,0),0)/100,"") | AC6: =IFERROR(AC5-AC7,"") | AD6: =IFERROR(AD5-AD7,"") | AE6: =SUM(AA6:AD6) | AF6: =IFERROR(AF5-AF7,"") | AG6: =IFERROR(AG5-AG7,"") | AH6: =IFERROR(AH5-AH7,"") | AI6: =IFERROR(AI5-AI7,"") | AJ6: =SUM(AF6:AI6) | AK6: =IFERROR(AK5-AK7,"") | AL6: =IFERROR(AL5-AL7,"") | AM6: =IFERROR(AM5-AM7,"") | AN6: =IFERROR(AN5-AN7,"") | AO6: =SUM(AK6:AN6)
A7: 매출총이익 | B7: 손익 | C7: 억원 | D7: 매출총이익 | E7: =IFERROR(VLOOKUP($D7,BS연결,MATCH(E$1,BS연결H,0),0)/100,"") | G7: =IFERROR(VLOOKUP($D7,BS연결,MATCH(G$1,BS연결H,0),0)/100,"") | H7: =IFERROR(VLOOKUP($D7,BS연결,MATCH(H$1,BS연결H,0),0)/100,"") | I7: =IFERROR(VLOOKUP($D7,BS연결,MATCH(I$1,BS연결H,0),0)/100,"") | J7: =IFERROR(VLOOKUP($D7,BS연결,MATCH(J$1,BS연결H,0),0)/100,"") | K7: =IFERROR(VLOOKUP($D7,BS연결,MATCH(K$1,BS연결H,0),0)/100,"") | L7: =IFERROR(VLOOKUP($D7,BS연결,MATCH(L$1,BS연결H,0),0)/100,"") | M7: =IFERROR(VLOOKUP($D7,BS연결,MATCH(M$1,BS연결H,0),0)/100,"") | N7: =IFERROR(VLOOKUP($D7,BS연결,MATCH(N$1,BS연결H,0),0)/100,"") | ... AB7: =IFERROR(VLOOKUP($D7,BS연결,MATCH(AB$1,BS연결H,0),0)/100,"") | AC7: =IFERROR(AC9+AC8,"") | AD7: =IFERROR(AD9+AD8,"") | AE7: =SUM(AA7:AD7) | AF7: =IFERROR(AF9+AF8,"") | AG7: =IFERROR(AG9+AG8,"") | AH7: =IFERROR(AH9+AH8,"") | AI7: =IFERROR(AI9+AI8,"") | AJ7: =SUM(AF7:AI7) | AK7: =IFERROR(AK9+AK8,"") | AL7: =IFERROR(AL9+AL8,"") | AM7: =IFERROR(AM9+AM8,"") | AN7: =IFERROR(AN9+AN8,"") | AO7: =SUM(AK7:AN7)
A8: 판관비 | B8: 손익 | C8: 억원 | D8: 판관비 | E8: =IFERROR(VLOOKUP($D8,BS연결,MATCH(E$1,BS연결H,0),0)/100,"") | G8: =IFERROR(VLOOKUP($D8,BS연결,MATCH(G$1,BS연결H,0),0)/100,"") | H8: =IFERROR(VLOOKUP($D8,BS연결,MATCH(H$1,BS연결H,0),0)/100,"") | I8: =IFERROR(VLOOKUP($D8,BS연결,MATCH(I$1,BS연결H,0),0)/100,"") | J8: =IFERROR(VLOOKUP($D8,BS연결,MATCH(J$1,BS연결H,0),0)/100,"") | K8: =IFERROR(VLOOKUP($D8,BS연결,MATCH(K$1,BS연결H,0),0)/100,"") | L8: =IFERROR(VLOOKUP($D8,BS연결,MATCH(L$1,BS연결H,0),0)/100,"") | M8: =IFERROR(VLOOKUP($D8,BS연결,MATCH(M$1,BS연결H,0),0)/100,"") | N8: =IFERROR(VLOOKUP($D8,BS연결,MATCH(N$1,BS연결H,0),0)/100,"") | ... AB8: =IFERROR(VLOOKUP($D8,BS연결,MATCH(AB$1,BS연결H,0),0)/100,"") | AC8: =IFERROR(AC5*변수!AC22,"") | AD8: =IFERROR(AD5*변수!AD22,"") | AE8: =SUM(AA8:AD8) | AF8: =IFERROR(AF5*변수!AF22,"") | AG8: =IFERROR(AG5*변수!AG22,"") | AH8: =IFERROR(AH5*변수!AH22,"") | AI8: =IFERROR(AI5*변수!AI22,"") | AJ8: =SUM(AF8:AI8) | AK8: =IFERROR(AK5*변수!AK22,"") | AL8: =IFERROR(AL5*변수!AL22,"") | AM8: =IFERROR(AM5*변수!AM22,"") | AN8: =IFERROR(AN5*변수!AN22,"") | AO8: =SUM(AK8:AN8)
A9: 영업이익 | B9: 손익 | C9: 억원 | D9: 영업이익 | E9: =IFERROR(VLOOKUP($D9,BS연결,MATCH(E$1,BS연결H,0),0)/100,"") | G9: =IFERROR(VLOOKUP($D9,BS연결,MATCH(G$1,BS연결H,0),0)/100,"") | H9: =IFERROR(VLOOKUP($D9,BS연결,MATCH(H$1,BS연결H,0),0)/100,"") | I9: =IFERROR(VLOOKUP($D9,BS연결,MATCH(I$1,BS연결H,0),0)/100,"") | J9: =IFERROR(VLOOKUP($D9,BS연결,MATCH(J$1,BS연결H,0),0)/100,"") | K9: =IFERROR(VLOOKUP($D9,BS연결,MATCH(K$1,BS연결H,0),0)/100,"") | L9: =IFERROR(VLOOKUP($D9,BS연결,MATCH(L$1,BS연결H,0),0)/100,"") | M9: =IFERROR(VLOOKUP($D9,BS연결,MATCH(M$1,BS연결H,0),0)/100,"") | N9: =IFERROR(VLOOKUP($D9,BS연결,MATCH(N$1,BS연결H,0),0)/100,"") | ... AB9: =IFERROR(VLOOKUP($D9,BS연결,MATCH(AB$1,BS연결H,0),0)/100,"") | AC9: =IFERROR(AC5*변수!AC23,"") | AD9: =IFERROR(AD5*변수!AD23,"") | AE9: =SUM(AA9:AD9) | AF9: =IFERROR(AF5*변수!AF23,"") | AG9: =IFERROR(AG5*변수!AG23,"") | AH9: =IFERROR(AH5*변수!AH23,"") | AI9: =IFERROR(AI5*변수!AI23,"") | AJ9: =SUM(AF9:AI9) | AK9: =IFERROR(AK5*변수!AK23,"") | AL9: =IFERROR(AL5*변수!AL23,"") | AM9: =IFERROR(AM5*변수!AM23,"") | AN9: =IFERROR(AN5*변수!AN23,"") | AO9: =SUM(AK9:AN9)
A10: OPM | B10: 손익 | C10: % | D10: 영업이익률 | E10: =IFERROR(E9/E5,"") | G10: =IFERROR(G9/G5,"") | H10: =IFERROR(H9/H5,"") | I10: =IFERROR(I9/I5,"") | J10: =IFERROR(J9/J5,"") | K10: =IFERROR(K9/K5,"") | L10: =IFERROR(L9/L5,"") | M10: =IFERROR(M9/M5,"") | N10: =IFERROR(N9/N5,"") | ... AO10: =IFERROR(AO9/AO5,"")
A11: 금융손익 | B11: 손익 | C11: 억원 | D11: 금융손익 | E11: =IFERROR(VLOOKUP($D11,BS연결,MATCH(E$1,BS연결H,0),0)/100,"") | G11: =IFERROR(VLOOKUP($D11,BS연결,MATCH(G$1,BS연결H,0),0)/100,"") | H11: =IFERROR(VLOOKUP($D11,BS연결,MATCH(H$1,BS연결H,0),0)/100,"") | I11: =IFERROR(VLOOKUP($D11,BS연결,MATCH(I$1,BS연결H,0),0)/100,"") | J11: =IFERROR(VLOOKUP($D11,BS연결,MATCH(J$1,BS연결H,0),0)/100,"") | K11: =IFERROR(VLOOKUP($D11,BS연결,MATCH(K$1,BS연결H,0),0)/100,"") | L11: =IFERROR(VLOOKUP($D11,BS연결,MATCH(L$1,BS연결H,0),0)/100,"") | M11: =IFERROR(VLOOKUP($D11,BS연결,MATCH(M$1,BS연결H,0),0)/100,"") | N11: =IFERROR(VLOOKUP($D11,BS연결,MATCH(N$1,BS연결H,0),0)/100,"") | ... T11: =IFERROR(VLOOKUP($D11,BS연결,MATCH(T$1,BS연결H,0),0)/100,"") | U11: =SUM(Q11:T11) | V11: =IFERROR(VLOOKUP($D11,BS연결,MATCH(V$1,BS연결H,0),0)/100,"") | W11: =IFERROR(VLOOKUP($D11,BS연결,MATCH(W$1,BS연결H,0),0)/100,"") | X11: =IFERROR(VLOOKUP($D11,BS연결,MATCH(X$1,BS연결H,0),0)/100,"") | Y11: =IFERROR(VLOOKUP($D11,BS연결,MATCH(Y$1,BS연결H,0),0)/100,"") | Z11: =IFERROR(VLOOKUP($D11,BS연결,MATCH(Z$1,BS연결H,0),0)/100,"") | AA11: =IFERROR(VLOOKUP($D11,BS연결,MATCH(AA$1,BS연결H,0),0)/100,"") | AB11: =IFERROR(VLOOKUP($D11,BS연결,MATCH(AB$1,BS연결H,0),0)/100,"") | AC11: =IFERROR(AC12+AC13,"") | AD11: =IFERROR(AD12+AD13,"") | AE11: =SUM(AA11:AD11) | AF11: =IFERROR(AF12+AF13,"") | AG11: =IFERROR(AG12+AG13,"") | AH11: =IFERROR(AH12+AH13,"") | AI11: =IFERROR(AI12+AI13,"") | AJ11: =SUM(AF11:AI11) | AK11: =IFERROR(AK12+AK13,"") | AL11: =IFERROR(AL12+AL13,"") | AM11: =IFERROR(AM12+AM13,"") | AN11: =IFERROR(AN12+AN13,"") | AO11: =SUM(AK11:AN11)
A12: 이자손익 | B12: 손익 | C12: 억원 | D12: 이자손익 | G12: =IFERROR(VLOOKUP($D12,BS연결,MATCH(G$1,BS연결H,0),0)/100,"") | H12: =IFERROR(VLOOKUP($D12,BS연결,MATCH(H$1,BS연결H,0),0)/100,"") | I12: =IFERROR(VLOOKUP($D12,BS연결,MATCH(I$1,BS연결H,0),0)/100,"") | J12: =IFERROR(VLOOKUP($D12,BS연결,MATCH(J$1,BS연결H,0),0)/100,"") | K12: =IFERROR(VLOOKUP($D12,BS연결,MATCH(K$1,BS연결H,0),0)/100,"") | L12: =IFERROR(VLOOKUP($D12,BS연결,MATCH(L$1,BS연결H,0),0)/100,"") | P12: =SUM(L12:O12) | U12: =SUM(Q12:T12) | Z12: =SUM(V12:Y12) | AC12: =IFERROR((AB26*변수!$D$52-AB24*변수!$D$53)/4,"") | AD12: =IFERROR((AC26*변수!$D$52-AC24*변수!$D$53)/4,"") | AE12: =SUM(AA12:AD12) | AF12: =IFERROR((AD26*변수!$D$52-AD24*변수!$D$53)/4,"") | AG12: =IFERROR((AF26*변수!$D$52-AF24*변수!$D$53)/4,"") | AH12: =IFERROR((AG26*변수!$D$52-AG24*변수!$D$53)/4,"") | AI12: =IFERROR((AH26*변수!$D$52-AH24*변수!$D$53)/4,"") | AJ12: =SUM(AF12:AI12) | AK12: =IFERROR((AI26*변수!$D$52-AI24*변수!$D$53)/4,"") | AL12: =IFERROR((AK26*변수!$D$52-AK24*변수!$D$53)/4,"") | AM12: =IFERROR((AL26*변수!$D$52-AL24*변수!$D$53)/4,"") | AN12: =IFERROR((AM26*변수!$D$52-AM24*변수!$D$53)/4,"") | AO12: =SUM(AK12:AN12)
A13: 외환손익 | B13: 손익 | C13: 억원 | D13: 외환손익(실적만; 추정 환효과는 환관련손익) | K13: =SUM(G13:J13) | L13: =IFERROR((VLOOKUP("외환차익",BS연결,MATCH(L$1,BS연결H,0),0)-VLOOKUP("외환차손",BS연결,MATCH(L$1,BS연결H,0),0)+VLOOKUP("외화환산이익",BS연결,MATCH(L$1,BS연결H,0),0)-VLOOKUP("외화환산손실",BS연결,MATCH(L$1,BS연결H,0),0))/100,"") | P13: =SUM(L13:O13) | U13: =SUM(Q13:T13) | Z13: =SUM(V13:Y13) | AC13: =변수!AC24 | AD13: =변수!AD24 | AE13: =SUM(AA13:AD13) | AF13: =변수!AF24 | AG13: =변수!AG24 | AH13: =변수!AH24 | AI13: =변수!AI24 | AJ13: =SUM(AF13:AI13) | AK13: =변수!AK24 | AL13: =변수!AL24 | AM13: =변수!AM24 | AN13: =변수!AN24 | AO13: =SUM(AK13:AN13)
A14: 기타영업외손익 | B14: 손익 | C14: 억원 | D14: 기타영업외손익 | E14: =IFERROR(VLOOKUP($D14,BS연결,MATCH(E$1,BS연결H,0),0)/100,"") | G14: =IFERROR(VLOOKUP($D14,BS연결,MATCH(G$1,BS연결H,0),0)/100,"") | H14: =IFERROR(VLOOKUP($D14,BS연결,MATCH(H$1,BS연결H,0),0)/100,"") | I14: =IFERROR(VLOOKUP($D14,BS연결,MATCH(I$1,BS연결H,0),0)/100,"") | J14: =IFERROR(VLOOKUP($D14,BS연결,MATCH(J$1,BS연결H,0),0)/100,"") | K14: =IFERROR(VLOOKUP($D14,BS연결,MATCH(K$1,BS연결H,0),0)/100,"") | L14: =IFERROR(VLOOKUP($D14,BS연결,MATCH(L$1,BS연결H,0),0)/100,"") | M14: =IFERROR(VLOOKUP($D14,BS연결,MATCH(M$1,BS연결H,0),0)/100,"") | N14: =IFERROR(VLOOKUP($D14,BS연결,MATCH(N$1,BS연결H,0),0)/100,"") | ... AB14: =IFERROR(VLOOKUP($D14,BS연결,MATCH(AB$1,BS연결H,0),0)/100,"") | AC14: =변수!AC25 | AD14: =변수!AD25 | AE14: =SUM(AA14:AD14) | AF14: =변수!AF25 | AG14: =변수!AG25 | AH14: =변수!AH25 | AI14: =변수!AI25 | AJ14: =SUM(AF14:AI14) | AK14: =변수!AK25 | AL14: =변수!AL25 | AM14: =변수!AM25 | AN14: =변수!AN25 | AO14: =SUM(AK14:AN14)
A15: 지분법손익 | B15: 손익 | C15: 억원 | D15: 종속기업,공동지배기업및관계기업관련손익 | H15: =IFERROR(VLOOKUP($D15,BS연결,MATCH(H$1,BS연결H,0),0)/100,"") | I15: =IFERROR(VLOOKUP($D15,BS연결,MATCH(I$1,BS연결H,0),0)/100,"") | K15: =SUM(G15:J15) | P15: =SUM(L15:O15) | U15: =SUM(Q15:T15) | Z15: =SUM(V15:Y15) | AC15: =변수!AC26 | AD15: =변수!AD26 | AE15: =SUM(AA15:AD15) | AF15: =변수!AF26 | AG15: =변수!AG26 | AH15: =변수!AH26 | AI15: =변수!AI26 | AJ15: =SUM(AF15:AI15) | AK15: =변수!AK26 | AL15: =변수!AL26 | AM15: =변수!AM26 | AN15: =변수!AN26 | AO15: =SUM(AK15:AN15)
A16: 세전이익 | B16: 손익 | C16: 억원 | D16: 법인세비용차감전계속사업이익 | E16: =IFERROR(VLOOKUP($D16,BS연결,MATCH(E$1,BS연결H,0),0)/100,"") | G16: =IFERROR(VLOOKUP($D16,BS연결,MATCH(G$1,BS연결H,0),0)/100,"") | H16: =IFERROR(VLOOKUP($D16,BS연결,MATCH(H$1,BS연결H,0),0)/100,"") | I16: =IFERROR(VLOOKUP($D16,BS연결,MATCH(I$1,BS연결H,0),0)/100,"") | J16: =IFERROR(VLOOKUP($D16,BS연결,MATCH(J$1,BS연결H,0),0)/100,"") | K16: =IFERROR(VLOOKUP($D16,BS연결,MATCH(K$1,BS연결H,0),0)/100,"") | L16: =IFERROR(VLOOKUP($D16,BS연결,MATCH(L$1,BS연결H,0),0)/100,"") | M16: =IFERROR(VLOOKUP($D16,BS연결,MATCH(M$1,BS연결H,0),0)/100,"") | N16: =IFERROR(VLOOKUP($D16,BS연결,MATCH(N$1,BS연결H,0),0)/100,"") | ... AB16: =IFERROR(VLOOKUP($D16,BS연결,MATCH(AB$1,BS연결H,0),0)/100,"") | AC16: =IFERROR(AC9+AC11+AC14+AC15,"") | AD16: =IFERROR(AD9+AD11+AD14+AD15,"") | AE16: =SUM(AA16:AD16) | AF16: =IFERROR(AF9+AF11+AF14+AF15,"") | AG16: =IFERROR(AG9+AG11+AG14+AG15,"") | AH16: =IFERROR(AH9+AH11+AH14+AH15,"") | AI16: =IFERROR(AI9+AI11+AI14+AI15,"") | AJ16: =SUM(AF16:AI16) | AK16: =IFERROR(AK9+AK11+AK14+AK15,"") | AL16: =IFERROR(AL9+AL11+AL14+AL15,"") | AM16: =IFERROR(AM9+AM11+AM14+AM15,"") | AN16: =IFERROR(AN9+AN11+AN14+AN15,"") | AO16: =SUM(AK16:AN16)
A17: 법인세비용 | B17: 손익 | C17: 억원 | D17: 법인세비용 | E17: =IFERROR(VLOOKUP($D17,BS연결,MATCH(E$1,BS연결H,0),0)/100,"") | G17: =IFERROR(VLOOKUP($D17,BS연결,MATCH(G$1,BS연결H,0),0)/100,"") | H17: =IFERROR(VLOOKUP($D17,BS연결,MATCH(H$1,BS연결H,0),0)/100,"") | I17: =IFERROR(VLOOKUP($D17,BS연결,MATCH(I$1,BS연결H,0),0)/100,"") | J17: =IFERROR(VLOOKUP($D17,BS연결,MATCH(J$1,BS연결H,0),0)/100,"") | K17: =IFERROR(VLOOKUP($D17,BS연결,MATCH(K$1,BS연결H,0),0)/100,"") | L17: =IFERROR(VLOOKUP($D17,BS연결,MATCH(L$1,BS연결H,0),0)/100,"") | M17: =IFERROR(VLOOKUP($D17,BS연결,MATCH(M$1,BS연결H,0),0)/100,"") | N17: =IFERROR(VLOOKUP($D17,BS연결,MATCH(N$1,BS연결H,0),0)/100,"") | ... T17: =IFERROR(VLOOKUP($D17,BS연결,MATCH(T$1,BS연결H,0),0)/100,"") | U17: =SUM(Q17:T17) | V17: =IFERROR(VLOOKUP($D17,BS연결,MATCH(V$1,BS연결H,0),0)/100,"") | W17: =IFERROR(VLOOKUP($D17,BS연결,MATCH(W$1,BS연결H,0),0)/100,"") | X17: =IFERROR(VLOOKUP($D17,BS연결,MATCH(X$1,BS연결H,0),0)/100,"") | Y17: =IFERROR(VLOOKUP($D17,BS연결,MATCH(Y$1,BS연결H,0),0)/100,"") | Z17: =SUM(V17:Y17) | AA17: =IFERROR(VLOOKUP($D17,BS연결,MATCH(AA$1,BS연결H,0),0)/100,"") | AB17: =IFERROR(VLOOKUP($D17,BS연결,MATCH(AB$1,BS연결H,0),0)/100,"") | AC17: =IFERROR(AC16*변수!AC27,"") | AD17: =IFERROR(AD16*변수!AD27,"") | AE17: =SUM(AA17:AD17) | AF17: =IFERROR(AF16*변수!AF27,"") | AG17: =IFERROR(AG16*변수!AG27,"") | AH17: =IFERROR(AH16*변수!AH27,"") | AI17: =IFERROR(AI16*변수!AI27,"") | AJ17: =SUM(AF17:AI17) | AK17: =IFERROR(AK16*변수!AK27,"") | AL17: =IFERROR(AL16*변수!AL27,"") | AM17: =IFERROR(AM16*변수!AM27,"") | AN17: =IFERROR(AN16*변수!AN27,"") | AO17: =SUM(AK17:AN17)
A18: 당기순이익 | B18: 손익 | C18: 억원 | D18: 당기순이익 | E18: =IFERROR(VLOOKUP($D18,BS연결,MATCH(E$1,BS연결H,0),0)/100,"") | G18: =IFERROR(VLOOKUP($D18,BS연결,MATCH(G$1,BS연결H,0),0)/100,"") | H18: =IFERROR(VLOOKUP($D18,BS연결,MATCH(H$1,BS연결H,0),0)/100,"") | I18: =IFERROR(VLOOKUP($D18,BS연결,MATCH(I$1,BS연결H,0),0)/100,"") | J18: =IFERROR(VLOOKUP($D18,BS연결,MATCH(J$1,BS연결H,0),0)/100,"") | K18: =IFERROR(VLOOKUP($D18,BS연결,MATCH(K$1,BS연결H,0),0)/100,"") | L18: =IFERROR(VLOOKUP($D18,BS연결,MATCH(L$1,BS연결H,0),0)/100,"") | M18: =IFERROR(VLOOKUP($D18,BS연결,MATCH(M$1,BS연결H,0),0)/100,"") | N18: =IFERROR(VLOOKUP($D18,BS연결,MATCH(N$1,BS연결H,0),0)/100,"") | ... T18: =IFERROR(VLOOKUP($D18,BS연결,MATCH(T$1,BS연결H,0),0)/100,"") | U18: =SUM(Q18:T18) | V18: =IFERROR(VLOOKUP($D18,BS연결,MATCH(V$1,BS연결H,0),0)/100,"") | W18: =IFERROR(VLOOKUP($D18,BS연결,MATCH(W$1,BS연결H,0),0)/100,"") | X18: =IFERROR(VLOOKUP($D18,BS연결,MATCH(X$1,BS연결H,0),0)/100,"") | Y18: =IFERROR(VLOOKUP($D18,BS연결,MATCH(Y$1,BS연결H,0),0)/100,"") | Z18: =IFERROR(VLOOKUP($D18,BS연결,MATCH(Z$1,BS연결H,0),0)/100,"") | AA18: =IFERROR(VLOOKUP($D18,BS연결,MATCH(AA$1,BS연결H,0),0)/100,"") | AB18: =IFERROR(VLOOKUP($D18,BS연결,MATCH(AB$1,BS연결H,0),0)/100,"") | AC18: =IFERROR(AC16-AC17,"") | AD18: =IFERROR(AD16-AD17,"") | AE18: =SUM(AA18:AD18) | AF18: =IFERROR(AF16-AF17,"") | AG18: =IFERROR(AG16-AG17,"") | AH18: =IFERROR(AH16-AH17,"") | AI18: =IFERROR(AI16-AI17,"") | AJ18: =SUM(AF18:AI18) | AK18: =IFERROR(AK16-AK17,"") | AL18: =IFERROR(AL16-AL17,"") | AM18: =IFERROR(AM16-AM17,"") | AN18: =IFERROR(AN16-AN17,"") | AO18: =SUM(AK18:AN18)
A19: 지배주주순이익 | B19: 손익 | C19: 억원 | D19: (지배주주지분)당기순이익 | E19: =IFERROR(VLOOKUP($D19,BS연결,MATCH(E$1,BS연결H,0),0)/100,"") | G19: =IFERROR(VLOOKUP($D19,BS연결,MATCH(G$1,BS연결H,0),0)/100,"") | H19: =IFERROR(VLOOKUP($D19,BS연결,MATCH(H$1,BS연결H,0),0)/100,"") | I19: =IFERROR(VLOOKUP($D19,BS연결,MATCH(I$1,BS연결H,0),0)/100,"") | J19: =IFERROR(VLOOKUP($D19,BS연결,MATCH(J$1,BS연결H,0),0)/100,"") | K19: =IFERROR(VLOOKUP($D19,BS연결,MATCH(K$1,BS연결H,0),0)/100,"") | L19: 12.68 | M19: -4.99 | N19: -5.03 | O19: -3.26 | P19: =SUM(L19:O19) | Q19: -21.08 | R19: -17.89 | S19: -8.02 | T19: -5.59 | U19: =SUM(Q19:T19) | V19: -1.86 | W19: 18.6 | X19: -9.12 | Y19: -13.16 | Z19: =SUM(V19:Y19) | AA19: -14.64 | AB19: 18.35 | AC19: =IFERROR(AC18*변수!AC28,"") | AD19: =IFERROR(AD18*변수!AD28,"") | AE19: =SUM(AA19:AD19) | AF19: =IFERROR(AF18*변수!AF28,"") | AG19: =IFERROR(AG18*변수!AG28,"") | AH19: =IFERROR(AH18*변수!AH28,"") | AI19: =IFERROR(AI18*변수!AI28,"") | AJ19: =SUM(AF19:AI19) | AK19: =IFERROR(AK18*변수!AK28,"") | AL19: =IFERROR(AL18*변수!AL28,"") | AM19: =IFERROR(AM18*변수!AM28,"") | AN19: =IFERROR(AN18*변수!AN28,"") | AO19: =SUM(AK19:AN19)
A20: 자산총계 | B20: 재무상태 | C20: 억원 | D20: 자산총계 | E20: =IFERROR(VLOOKUP($D20,BS연결,MATCH(E$1,BS연결H,0),0)/100,"") | F20: =IFERROR(VLOOKUP($D20,BS연결,MATCH(F$1,BS연결H,0),0)/100,"") | G20: =IFERROR(VLOOKUP($D20,BS연결,MATCH(G$1,BS연결H,0),0)/100,"") | H20: =IFERROR(VLOOKUP($D20,BS연결,MATCH(H$1,BS연결H,0),0)/100,"") | I20: =IFERROR(VLOOKUP($D20,BS연결,MATCH(I$1,BS연결H,0),0)/100,"") | J20: =IFERROR(VLOOKUP($D20,BS연결,MATCH(J$1,BS연결H,0),0)/100,"") | K20: =IFERROR(VLOOKUP($D20,BS연결,MATCH(K$1,BS연결H,0),0)/100,"") | L20: =IFERROR(VLOOKUP($D20,BS연결,MATCH(L$1,BS연결H,0),0)/100,"") | ... AB20: =IFERROR(VLOOKUP($D20,BS연결,MATCH(AB$1,BS연결H,0),0)/100,"") | AC20: =IFERROR(AC21+AC22,"") | AD20: =IFERROR(AD21+AD22,"") | AE20: =AD20 | AF20: =IFERROR(AF21+AF22,"") | AG20: =IFERROR(AG21+AG22,"") | AH20: =IFERROR(AH21+AH22,"") | AI20: =IFERROR(AI21+AI22,"") | AJ20: =AI20 | AK20: =IFERROR(AK21+AK22,"") | AL20: =IFERROR(AL21+AL22,"") | AM20: =IFERROR(AM21+AM22,"") | AN20: =IFERROR(AN21+AN22,"") | AO20: =AN20
A21: 부채총계 | B21: 재무상태 | C21: 억원 | D21: 부채총계 | E21: =IFERROR(VLOOKUP($D21,BS연결,MATCH(E$1,BS연결H,0),0)/100,"") | F21: =IFERROR(VLOOKUP($D21,BS연결,MATCH(F$1,BS연결H,0),0)/100,"") | G21: =IFERROR(VLOOKUP($D21,BS연결,MATCH(G$1,BS연결H,0),0)/100,"") | H21: =IFERROR(VLOOKUP($D21,BS연결,MATCH(H$1,BS연결H,0),0)/100,"") | I21: =IFERROR(VLOOKUP($D21,BS연결,MATCH(I$1,BS연결H,0),0)/100,"") | J21: =IFERROR(VLOOKUP($D21,BS연결,MATCH(J$1,BS연결H,0),0)/100,"") | K21: =IFERROR(VLOOKUP($D21,BS연결,MATCH(K$1,BS연결H,0),0)/100,"") | L21: =IFERROR(VLOOKUP($D21,BS연결,MATCH(L$1,BS연결H,0),0)/100,"") | ... AB21: =IFERROR(VLOOKUP($D21,BS연결,MATCH(AB$1,BS연결H,0),0)/100,"") | AC21: =IFERROR(AB21*(1+변수!AC29),"") | AD21: =IFERROR(AC21*(1+변수!AD29),"") | AE21: =AD21 | AF21: =IFERROR(AD21*(1+변수!AF29),"") | AG21: =IFERROR(AF21*(1+변수!AG29),"") | AH21: =IFERROR(AG21*(1+변수!AH29),"") | AI21: =IFERROR(AH21*(1+변수!AI29),"") | AJ21: =AI21 | AK21: =IFERROR(AI21*(1+변수!AK29),"") | AL21: =IFERROR(AK21*(1+변수!AL29),"") | AM21: =IFERROR(AL21*(1+변수!AM29),"") | AN21: =IFERROR(AM21*(1+변수!AN29),"") | AO21: =AN21
A22: 자본총계 | B22: 재무상태 | C22: 억원 | D22: 자본총계 | E22: =IFERROR(VLOOKUP($D22,BS연결,MATCH(E$1,BS연결H,0),0)/100,"") | F22: =IFERROR(VLOOKUP($D22,BS연결,MATCH(F$1,BS연결H,0),0)/100,"") | G22: =IFERROR(VLOOKUP($D22,BS연결,MATCH(G$1,BS연결H,0),0)/100,"") | H22: =IFERROR(VLOOKUP($D22,BS연결,MATCH(H$1,BS연결H,0),0)/100,"") | I22: =IFERROR(VLOOKUP($D22,BS연결,MATCH(I$1,BS연결H,0),0)/100,"") | J22: =IFERROR(VLOOKUP($D22,BS연결,MATCH(J$1,BS연결H,0),0)/100,"") | K22: =IFERROR(VLOOKUP($D22,BS연결,MATCH(K$1,BS연결H,0),0)/100,"") | L22: =IFERROR(VLOOKUP($D22,BS연결,MATCH(L$1,BS연결H,0),0)/100,"") | ... AB22: =IFERROR(VLOOKUP($D22,BS연결,MATCH(AB$1,BS연결H,0),0)/100,"") | AC22: =IFERROR(AB22+AC18-변수!AC30,"") | AD22: =IFERROR(AC22+AD18-변수!AD30,"") | AE22: =AD22 | AF22: =IFERROR(AD22+AF18-변수!AF30,"") | AG22: =IFERROR(AF22+AG18-변수!AG30,"") | AH22: =IFERROR(AG22+AH18-변수!AH30,"") | AI22: =IFERROR(AH22+AI18-변수!AI30,"") | AJ22: =AI22 | AK22: =IFERROR(AI22+AK18-변수!AK30,"") | AL22: =IFERROR(AK22+AL18-변수!AL30,"") | AM22: =IFERROR(AL22+AM18-변수!AM30,"") | AN22: =IFERROR(AM22+AN18-변수!AN30,"") | AO22: =AN22
A23: 지배주주지분 | B23: 재무상태 | C23: 억원 | D23: 지배주주지분 | E23: =IFERROR(VLOOKUP($D23,BS연결,MATCH(E$1,BS연결H,0),0)/100,"") | F23: =IFERROR(VLOOKUP($D23,BS연결,MATCH(F$1,BS연결H,0),0)/100,"") | G23: =IFERROR(VLOOKUP($D23,BS연결,MATCH(G$1,BS연결H,0),0)/100,"") | H23: =IFERROR(VLOOKUP($D23,BS연결,MATCH(H$1,BS연결H,0),0)/100,"") | I23: =IFERROR(VLOOKUP($D23,BS연결,MATCH(I$1,BS연결H,0),0)/100,"") | J23: =IFERROR(VLOOKUP($D23,BS연결,MATCH(J$1,BS연결H,0),0)/100,"") | K23: =IFERROR(VLOOKUP($D23,BS연결,MATCH(K$1,BS연결H,0),0)/100,"") | L23: =IFERROR(VLOOKUP($D23,BS연결,MATCH(L$1,BS연결H,0),0)/100,"") | ... AB23: =IFERROR(VLOOKUP($D23,BS연결,MATCH(AB$1,BS연결H,0),0)/100,"") | AC23: =IFERROR(AB23+AC19-변수!AC31,"") | AD23: =IFERROR(AC23+AD19-변수!AD31,"") | AE23: =AD23 | AF23: =IFERROR(AD23+AF19-변수!AF31,"") | AG23: =IFERROR(AF23+AG19-변수!AG31,"") | AH23: =IFERROR(AG23+AH19-변수!AH31,"") | AI23: =IFERROR(AH23+AI19-변수!AI31,"") | AJ23: =AI23 | AK23: =IFERROR(AI23+AK19-변수!AK31,"") | AL23: =IFERROR(AK23+AL19-변수!AL31,"") | AM23: =IFERROR(AL23+AM19-변수!AM31,"") | AN23: =IFERROR(AM23+AN19-변수!AN31,"") | AO23: =AN23
A24: 총차입금 | B24: 재무상태 | C24: 억원 | D24: 총차입금 | E24: =IFERROR(VLOOKUP($D24,BS연결,MATCH(E$1,BS연결H,0),0)/100,"") | F24: =IFERROR(VLOOKUP($D24,BS연결,MATCH(F$1,BS연결H,0),0)/100,"") | G24: =IFERROR(VLOOKUP($D24,BS연결,MATCH(G$1,BS연결H,0),0)/100,"") | H24: =IFERROR(VLOOKUP($D24,BS연결,MATCH(H$1,BS연결H,0),0)/100,"") | I24: =IFERROR(VLOOKUP($D24,BS연결,MATCH(I$1,BS연결H,0),0)/100,"") | J24: =IFERROR(VLOOKUP($D24,BS연결,MATCH(J$1,BS연결H,0),0)/100,"") | K24: =IFERROR(VLOOKUP($D24,BS연결,MATCH(K$1,BS연결H,0),0)/100,"") | L24: =IFERROR(VLOOKUP($D24,BS연결,MATCH(L$1,BS연결H,0),0)/100,"") | ... AB24: =IFERROR(VLOOKUP($D24,BS연결,MATCH(AB$1,BS연결H,0),0)/100,"") | AC24: =IFERROR(AB24*(1+변수!AC32),"") | AD24: =IFERROR(AC24*(1+변수!AD32),"") | AE24: =AD24 | AF24: =IFERROR(AD24*(1+변수!AF32),"") | AG24: =IFERROR(AF24*(1+변수!AG32),"") | AH24: =IFERROR(AG24*(1+변수!AH32),"") | AI24: =IFERROR(AH24*(1+변수!AI32),"") | AJ24: =AI24 | AK24: =IFERROR(AI24*(1+변수!AK32),"") | AL24: =IFERROR(AK24*(1+변수!AL32),"") | AM24: =IFERROR(AL24*(1+변수!AM32),"") | AN24: =IFERROR(AM24*(1+변수!AN32),"") | AO24: =AN24
A25: 순차입금 | B25: 재무상태 | C25: 억원 | D25: 순차입금 | E25: =IFERROR(VLOOKUP($D25,BS연결,MATCH(E$1,BS연결H,0),0)/100,"") | F25: =IFERROR(VLOOKUP($D25,BS연결,MATCH(F$1,BS연결H,0),0)/100,"") | G25: =IFERROR(VLOOKUP($D25,BS연결,MATCH(G$1,BS연결H,0),0)/100,"") | H25: =IFERROR(VLOOKUP($D25,BS연결,MATCH(H$1,BS연결H,0),0)/100,"") | I25: =IFERROR(VLOOKUP($D25,BS연결,MATCH(I$1,BS연결H,0),0)/100,"") | J25: =IFERROR(VLOOKUP($D25,BS연결,MATCH(J$1,BS연결H,0),0)/100,"") | K25: =IFERROR(VLOOKUP($D25,BS연결,MATCH(K$1,BS연결H,0),0)/100,"") | L25: =IFERROR(VLOOKUP($D25,BS연결,MATCH(L$1,BS연결H,0),0)/100,"") | ... AB25: =IFERROR(VLOOKUP($D25,BS연결,MATCH(AB$1,BS연결H,0),0)/100,"") | AC25: =IFERROR(AB25*(1+변수!AC33),"") | AD25: =IFERROR(AC25*(1+변수!AD33),"") | AE25: =AD25 | AF25: =IFERROR(AD25*(1+변수!AF33),"") | AG25: =IFERROR(AF25*(1+변수!AG33),"") | AH25: =IFERROR(AG25*(1+변수!AH33),"") | AI25: =IFERROR(AH25*(1+변수!AI33),"") | AJ25: =AI25 | AK25: =IFERROR(AI25*(1+변수!AK33),"") | AL25: =IFERROR(AK25*(1+변수!AL33),"") | AM25: =IFERROR(AL25*(1+변수!AM33),"") | AN25: =IFERROR(AM25*(1+변수!AN33),"") | AO25: =AN25
A26: 이자발생자산 | B26: 재무상태 | C26: 억원 | D26: 이자발생자산 | E26: =IFERROR(VLOOKUP($D26,BS연결,MATCH(E$1,BS연결H,0),0)/100,"") | F26: =IFERROR(VLOOKUP($D26,BS연결,MATCH(F$1,BS연결H,0),0)/100,"") | G26: =IFERROR(VLOOKUP($D26,BS연결,MATCH(G$1,BS연결H,0),0)/100,"") | H26: =IFERROR(VLOOKUP($D26,BS연결,MATCH(H$1,BS연결H,0),0)/100,"") | I26: =IFERROR(VLOOKUP($D26,BS연결,MATCH(I$1,BS연결H,0),0)/100,"") | J26: =IFERROR(VLOOKUP($D26,BS연결,MATCH(J$1,BS연결H,0),0)/100,"") | K26: =IFERROR(VLOOKUP($D26,BS연결,MATCH(K$1,BS연결H,0),0)/100,"") | L26: =IFERROR(VLOOKUP($D26,BS연결,MATCH(L$1,BS연결H,0),0)/100,"") | ... AB26: =IFERROR(VLOOKUP($D26,BS연결,MATCH(AB$1,BS연결H,0),0)/100,"") | AC26: =IFERROR(AB26*(1+변수!AC34),"") | AD26: =IFERROR(AC26*(1+변수!AD34),"") | AE26: =AD26 | AF26: =IFERROR(AD26*(1+변수!AF34),"") | AG26: =IFERROR(AF26*(1+변수!AG34),"") | AH26: =IFERROR(AG26*(1+변수!AH34),"") | AI26: =IFERROR(AH26*(1+변수!AI34),"") | AJ26: =AI26 | AK26: =IFERROR(AI26*(1+변수!AK34),"") | AL26: =IFERROR(AK26*(1+변수!AL34),"") | AM26: =IFERROR(AL26*(1+변수!AM34),"") | AN26: =IFERROR(AM26*(1+변수!AN34),"") | AO26: =AN26
A27: 현금및현금성자산 | B27: 재무상태 | C27: 억원 | D27: 현금및현금성자산 | E27: =IFERROR(VLOOKUP($D27,BS연결,MATCH(E$1,BS연결H,0),0)/100,"") | F27: =IFERROR(VLOOKUP($D27,BS연결,MATCH(F$1,BS연결H,0),0)/100,"") | G27: =IFERROR(VLOOKUP($D27,BS연결,MATCH(G$1,BS연결H,0),0)/100,"") | H27: =IFERROR(VLOOKUP($D27,BS연결,MATCH(H$1,BS연결H,0),0)/100,"") | I27: =IFERROR(VLOOKUP($D27,BS연결,MATCH(I$1,BS연결H,0),0)/100,"") | J27: =IFERROR(VLOOKUP($D27,BS연결,MATCH(J$1,BS연결H,0),0)/100,"") | K27: =IFERROR(VLOOKUP($D27,BS연결,MATCH(K$1,BS연결H,0),0)/100,"") | L27: =IFERROR(VLOOKUP($D27,BS연결,MATCH(L$1,BS연결H,0),0)/100,"") | ... AB27: =IFERROR(VLOOKUP($D27,BS연결,MATCH(AB$1,BS연결H,0),0)/100,"") | AE27: =AD27 | AJ27: =AI27 | AO27: =AN27
A28: CAPEX | B28: 현금흐름 | C28: 억원 | D28: CAPEX | E28: =IFERROR(VLOOKUP($D28,BS연결,MATCH(E$1,BS연결H,0),0)/100,"") | G28: =IFERROR(VLOOKUP($D28,BS연결,MATCH(G$1,BS연결H,0),0)/100,"") | H28: =IFERROR(VLOOKUP($D28,BS연결,MATCH(H$1,BS연결H,0),0)/100,"") | I28: =IFERROR(VLOOKUP($D28,BS연결,MATCH(I$1,BS연결H,0),0)/100,"") | J28: =IFERROR(VLOOKUP($D28,BS연결,MATCH(J$1,BS연결H,0),0)/100,"") | K28: =IFERROR(VLOOKUP($D28,BS연결,MATCH(K$1,BS연결H,0),0)/100,"") | L28: =IFERROR(VLOOKUP($D28,BS연결,MATCH(L$1,BS연결H,0),0)/100,"") | M28: =IFERROR(VLOOKUP($D28,BS연결,MATCH(M$1,BS연결H,0),0)/100,"") | N28: =IFERROR(VLOOKUP($D28,BS연결,MATCH(N$1,BS연결H,0),0)/100,"") | ... AB28: =IFERROR(VLOOKUP($D28,BS연결,MATCH(AB$1,BS연결H,0),0)/100,"") | AC28: =IFERROR(X28*(1+변수!AC36),"") | AD28: =IFERROR(Y28*(1+변수!AD36),"") | AE28: =SUM(AA28:AD28) | AF28: =IFERROR(AA28*(1+변수!AF36),"") | AG28: =IFERROR(AB28*(1+변수!AG36),"") | AH28: =IFERROR(AC28*(1+변수!AH36),"") | AI28: =IFERROR(AD28*(1+변수!AI36),"") | AJ28: =SUM(AF28:AI28) | AK28: =IFERROR(AF28*(1+변수!AK36),"") | AL28: =IFERROR(AG28*(1+변수!AL36),"") | AM28: =IFERROR(AH28*(1+변수!AM36),"") | AN28: =IFERROR(AI28*(1+변수!AN36),"") | AO28: =SUM(AK28:AN28)
A29: 영업활동현금흐름 | B29: 현금흐름 | C29: 억원 | D29: 영업활동으로인한현금흐름 | E29: =IFERROR(VLOOKUP($D29,BS연결,MATCH(E$1,BS연결H,0),0)/100,"") | G29: =IFERROR(VLOOKUP($D29,BS연결,MATCH(G$1,BS연결H,0),0)/100,"") | H29: =IFERROR(VLOOKUP($D29,BS연결,MATCH(H$1,BS연결H,0),0)/100,"") | I29: =IFERROR(VLOOKUP($D29,BS연결,MATCH(I$1,BS연결H,0),0)/100,"") | J29: =IFERROR(VLOOKUP($D29,BS연결,MATCH(J$1,BS연결H,0),0)/100,"") | K29: =IFERROR(VLOOKUP($D29,BS연결,MATCH(K$1,BS연결H,0),0)/100,"") | L29: =IFERROR(VLOOKUP($D29,BS연결,MATCH(L$1,BS연결H,0),0)/100,"") | M29: =IFERROR(VLOOKUP($D29,BS연결,MATCH(M$1,BS연결H,0),0)/100,"") | N29: =IFERROR(VLOOKUP($D29,BS연결,MATCH(N$1,BS연결H,0),0)/100,"") | ... AB29: =IFERROR(VLOOKUP($D29,BS연결,MATCH(AB$1,BS연결H,0),0)/100,"") | AE29: =SUM(AA29:AD29) | AJ29: =SUM(AF29:AI29) | AO29: =SUM(AK29:AN29)
A30: 주식수 | B30: 주당 | C30: 백만주 | D30: 유통주식수 | E30: 24.354 | F30: =E30 | G30: 24.354 | H30: 24.354 | I30: 24.354 | J30: 24.354 | K30: =J30 | L30: 24.354 | M30: 24.354 | N30: 24.354 | O30: 24.354 | P30: =O30 | Q30: 24.354 | R30: 24.354 | S30: 24.354 | T30: 24.354 | U30: =T30 | V30: 24.173 | W30: 23.743 | X30: 23.743 | Y30: 23.743 | Z30: =Y30 | AA30: 23.743 | AB30: 23.743 | AC30: =IFERROR(AB30*(1+변수!AC38),"") | AD30: =IFERROR(AC30*(1+변수!AD38),"") | AE30: =AD30 | AF30: =IFERROR(AD30*(1+변수!AF38),"") | AG30: =IFERROR(AF30*(1+변수!AG38),"") | AH30: =IFERROR(AG30*(1+변수!AH38),"") | AI30: =IFERROR(AH30*(1+변수!AI38),"") | AJ30: =AI30 | AK30: =IFERROR(AI30*(1+변수!AK38),"") | AL30: =IFERROR(AK30*(1+변수!AL38),"") | AM30: =IFERROR(AL30*(1+변수!AM38),"") | AN30: =IFERROR(AM30*(1+변수!AN38),"") | AO30: =AN30
A31: EPS | B31: 주당 | C31: 원 | D31: EPS | E31: =IFERROR(E19*100/E30,"") | G31: =IFERROR(G19*100/G30,"") | H31: =IFERROR(H19*100/H30,"") | I31: =IFERROR(I19*100/I30,"") | J31: =IFERROR(J19*100/J30,"") | K31: =SUM(G31:J31) | L31: =IFERROR(L19*100/L30,"") | M31: =IFERROR(M19*100/M30,"") | N31: =IFERROR(N19*100/N30,"") | O31: =IFERROR(O19*100/O30,"") | P31: =SUM(L31:O31) | Q31: =IFERROR(Q19*100/Q30,"") | R31: =IFERROR(R19*100/R30,"") | S31: =IFERROR(S19*100/S30,"") | T31: =IFERROR(T19*100/T30,"") | U31: =SUM(Q31:T31) | V31: =IFERROR(V19*100/V30,"") | W31: =IFERROR(W19*100/W30,"") | X31: =IFERROR(X19*100/X30,"") | Y31: =IFERROR(Y19*100/Y30,"") | Z31: =SUM(V31:Y31) | AA31: =IFERROR(AA19*100/AA30,"") | AB31: =IFERROR(AB19*100/AB30,"") | AC31: =IFERROR(AC19*100/AC30,"") | AD31: =IFERROR(AD19*100/AD30,"") | AE31: =SUM(AA31:AD31) | AF31: =IFERROR(AF19*100/AF30,"") | AG31: =IFERROR(AG19*100/AG30,"") | AH31: =IFERROR(AH19*100/AH30,"") | AI31: =IFERROR(AI19*100/AI30,"") | AJ31: =SUM(AF31:AI31) | AK31: =IFERROR(AK19*100/AK30,"") | AL31: =IFERROR(AL19*100/AL30,"") | AM31: =IFERROR(AM19*100/AM30,"") | AN31: =IFERROR(AN19*100/AN30,"") | AO31: =SUM(AK31:AN31)
A32: BPS | B32: 주당 | C32: 원 | D32: BPS | E32: =IFERROR(E23*100/E30,"") | F32: =E32 | G32: =IFERROR(G23*100/G30,"") | H32: =IFERROR(H23*100/H30,"") | I32: =IFERROR(I23*100/I30,"") | J32: =IFERROR(J23*100/J30,"") | K32: =J32 | L32: =IFERROR(L23*100/L30,"") | M32: =IFERROR(M23*100/M30,"") | N32: =IFERROR(N23*100/N30,"") | O32: =IFERROR(O23*100/O30,"") | P32: =O32 | Q32: =IFERROR(Q23*100/Q30,"") | R32: =IFERROR(R23*100/R30,"") | S32: =IFERROR(S23*100/S30,"") | T32: =IFERROR(T23*100/T30,"") | U32: =T32 | V32: =IFERROR(V23*100/V30,"") | W32: =IFERROR(W23*100/W30,"") | X32: =IFERROR(X23*100/X30,"") | Y32: =IFERROR(Y23*100/Y30,"") | Z32: =Y32 | AA32: =IFERROR(AA23*100/AA30,"") | AB32: =IFERROR(AB23*100/AB30,"") | AC32: =IFERROR(AC23*100/AC30,"") | AD32: =IFERROR(AD23*100/AD30,"") | AE32: =AD32 | AF32: =IFERROR(AF23*100/AF30,"") | AG32: =IFERROR(AG23*100/AG30,"") | AH32: =IFERROR(AH23*100/AH30,"") | AI32: =IFERROR(AI23*100/AI30,"") | AJ32: =AI32 | AK32: =IFERROR(AK23*100/AK30,"") | AL32: =IFERROR(AL23*100/AL30,"") | AM32: =IFERROR(AM23*100/AM30,"") | AN32: =IFERROR(AN23*100/AN30,"") | AO32: =AN32
A33: DPS | B33: 주당 | C33: 원 | D33: DPS(보통주) | E33: 50 | F33: 50 | J33: 30 | K33: =SUM(G33:J33) | O33: 30 | P33: =SUM(L33:O33) | T33: 10 | U33: =SUM(Q33:T33) | Y33: 30 | Z33: =SUM(V33:Y33) | AD33: =변수!AD39 | AE33: =SUM(AA33:AD33) | AI33: =변수!AI39 | AJ33: =SUM(AF33:AI33) | AN33: =변수!AN39 | AO33: =SUM(AK33:AN33)
A34: PER | B34: 주당 | C34: 배 | D34: PER | F34: =E34 | I34: =IFERROR(변수!I18/(E31+G31+H31+I31),"") | K34: =J34 | N34: =IFERROR(변수!N18/(J31+L31+M31+N31),"") | P34: =O34 | U34: =T34 | W34: =IFERROR(변수!W18/(S31+T31+V31+W31),"") | X34: =IFERROR(변수!X18/(T31+V31+W31+X31),"") | Z34: =Y34 | AE34: =AD34 | AJ34: =AI34 | AO34: =AN34
A35: PBR | B35: 주당 | C35: 배 | D35: PBR | E35: =IFERROR(변수!E18/E32,"") | F35: =E35 | G35: =IFERROR(변수!G18/G32,"") | H35: =IFERROR(변수!H18/H32,"") | I35: =IFERROR(변수!I18/I32,"") | J35: =IFERROR(변수!J18/J32,"") | K35: =J35 | L35: =IFERROR(변수!L18/L32,"") | M35: =IFERROR(변수!M18/M32,"") | N35: =IFERROR(변수!N18/N32,"") | O35: =IFERROR(변수!O18/O32,"") | P35: =O35 | Q35: =IFERROR(변수!Q18/Q32,"") | R35: =IFERROR(변수!R18/R32,"") | S35: =IFERROR(변수!S18/S32,"") | T35: =IFERROR(변수!T18/T32,"") | U35: =T35 | V35: =IFERROR(변수!V18/V32,"") | W35: =IFERROR(변수!W18/W32,"") | X35: =IFERROR(변수!X18/X32,"") | Y35: =IFERROR(변수!Y18/Y32,"") | Z35: =Y35 | AA35: =IFERROR(변수!AA18/AA32,"") | AB35: =IFERROR(변수!AB18/AB32,"") | AC35: =IFERROR(변수!$D$42/AC32,"") | AD35: =IFERROR(변수!$D$42/AD32,"") | AE35: =AD35 | AF35: =IFERROR(변수!$D$42/AF32,"") | AG35: =IFERROR(변수!$D$42/AG32,"") | AH35: =IFERROR(변수!$D$42/AH32,"") | AI35: =IFERROR(변수!$D$42/AI32,"") | AJ35: =AI35 | AK35: =IFERROR(변수!$D$42/AK32,"") | AL35: =IFERROR(변수!$D$42/AL32,"") | AM35: =IFERROR(변수!$D$42/AM32,"") | AN35: =IFERROR(변수!$D$42/AN32,"") | AO35: =AN35
A36: 매출전사 | B36: 사업부 | C36: 억원 | D36: 매출 전사(부문 미분리) | E36: 689.72 | G36: 722.96 | H36: 605.81 | I36: 631.66 | J36: 591.86 | K36: =SUM(G36:J36) | L36: 605.43 | M36: 515.48 | N36: 530.92 | O36: 510.73 | P36: =SUM(L36:O36) | Q36: 499.91 | R36: 555.05 | S36: 440.28 | T36: 563.18 | U36: =SUM(Q36:T36) | V36: 497.58 | W36: 501.1 | X36: 508.41 | Y36: 456.95 | Z36: =SUM(V36:Y36) | AA36: 618.74 | AB36: 617.57 | AC36: =IFERROR(AC5,"") | AD36: =IFERROR(AD5,"") | AE36: =SUM(AA36:AD36) | AF36: =IFERROR(AF5,"") | AG36: =IFERROR(AG5,"") | AH36: =IFERROR(AH5,"") | AI36: =IFERROR(AI5,"") | AJ36: =SUM(AF36:AI36) | AK36: =IFERROR(AK5,"") | AL36: =IFERROR(AL5,"") | AM36: =IFERROR(AM5,"") | AN36: =IFERROR(AN5,"") | AO36: =SUM(AK36:AN36)
A37: OP전사 | B37: 사업부 | C37: 억원 | D37: OP 전사(부문 미분리) | E37: 73.07 | G37: 19.86 | H37: 31.55 | I37: -7.4 | J37: -3.69 | K37: =SUM(G37:J37) | L37: 37.01 | M37: 12.02 | N37: 15.05 | O37: -15.48 | P37: =SUM(L37:O37) | Q37: 3.82 | R37: 4.44 | S37: -1.76 | T37: 0.17 | U37: =SUM(Q37:T37) | V37: 1.89 | W37: 15.4 | X37: 14.24 | Y37: 0.26 | Z37: =SUM(V37:Y37) | AA37: 4.63 | AB37: 28.56 | AC37: =IFERROR(AC9,"") | AD37: =IFERROR(AD9,"") | AE37: =SUM(AA37:AD37) | AF37: =IFERROR(AF9,"") | AG37: =IFERROR(AG9,"") | AH37: =IFERROR(AH9,"") | AI37: =IFERROR(AI9,"") | AJ37: =SUM(AF37:AI37) | AK37: =IFERROR(AK9,"") | AL37: =IFERROR(AL9,"") | AM37: =IFERROR(AM9,"") | AN37: =IFERROR(AN9,"") | AO37: =SUM(AK37:AN37)
B38: 비율(참고)
A39: NPM | C39: % | D39: 지배주주순이익 / 매출액 | E39: =IFERROR(E19/E5,"") | F39: =IFERROR(F19/F5,"") | G39: =IFERROR(G19/G5,"") | H39: =IFERROR(H19/H5,"") | I39: =IFERROR(I19/I5,"") | J39: =IFERROR(J19/J5,"") | K39: =IFERROR(K19/K5,"") | L39: =IFERROR(L19/L5,"") | ... AO39: =IFERROR(AO19/AO5,"")
A40: 매출원가율 | C40: % | D40: 매출원가 / 매출액 | E40: =IFERROR(E6/E5,"") | F40: =IFERROR(F6/F5,"") | G40: =IFERROR(G6/G5,"") | H40: =IFERROR(H6/H5,"") | I40: =IFERROR(I6/I5,"") | J40: =IFERROR(J6/J5,"") | K40: =IFERROR(K6/K5,"") | L40: =IFERROR(L6/L5,"") | ... AO40: =IFERROR(AO6/AO5,"")
A41: 판관비율 | C41: % | D41: 판관비 / 매출액 | E41: =IFERROR(E8/E5,"") | F41: =IFERROR(F8/F5,"") | G41: =IFERROR(G8/G5,"") | H41: =IFERROR(H8/H5,"") | I41: =IFERROR(I8/I5,"") | J41: =IFERROR(J8/J5,"") | K41: =IFERROR(K8/K5,"") | L41: =IFERROR(L8/L5,"") | ... AO41: =IFERROR(AO8/AO5,"")

Sheet 분기
C1: 이름: 분기H — subQ 를 이름으로 VLOOKUP(억원) | E1: 4Q21 | F1: 1Q22 | G1: 2Q22 | H1: 3Q22 | I1: 4Q22 | J1: 1Q23 | K1: 2Q23 | L1: 3Q23 | M1: 4Q23 | N1: 1Q24 | O1: 2Q24 | P1: 3Q24 | Q1: 4Q24 | R1: 1Q25 | S1: 2Q25 | T1: 3Q25 | U1: 4Q25 | V1: 1Q26 | W1: 2Q26 | X1: 3Q26 | Y1: 4Q26 | Z1: 1Q27 | AA1: 2Q27 | AB1: 3Q27 | AC1: 4Q27 | AD1: 1Q28 | AE1: 2Q28 | AF1: 3Q28 | AG1: 4Q28
C2: 종가: | D2: =변수!D42
C3: 기준일: | D3: 20261013 | E3: 1 | F3: 2 | G3: 3 | H3: 4 | I3: 5 | J3: 6 | K3: 7 | L3: 8 | M3: 9 | N3: 10 | O3: 11 | P3: 12 | Q3: 13 | R3: 14 | S3: 15 | T3: 16 | U3: 17 | V3: 18 | W3: 19 | X3: 20 | Y3: 21 | Z3: 22 | AA3: 23 | AB3: 24 | AC3: 25 | AD3: 26 | AE3: 27 | AF3: 28 | AG3: 29
E4: 2021.12 | F4: 2022.03 | G4: 2022.06 | H4: 2022.09 | I4: 2022.12 | J4: 2023.03 | K4: 2023.06 | L4: 2023.09 | M4: 2023.12 | N4: 2024.03 | O4: 2024.06 | P4: 2024.09 | Q4: 2024.12 | R4: 2025.03 | S4: 2025.06 | T4: 2025.09 | U4: 2025.12 | V4: 2026.03 | W4: 2026.06 | X4: 2026.09 | Y4: 2026.12 | Z4: 2027.03 | AA4: 2027.06 | AB4: 2027.09 | AC4: 2027.12 | AD4: 2028.03 | AE4: 2028.06 | AF4: 2028.09 | AG4: 2028.12
A5: 매출액 | D5: 매출액 | E5: =IFERROR(VLOOKUP($A5,subQ,MATCH(E$1,SUBQH,0),0),"") | F5: =IFERROR(VLOOKUP($A5,subQ,MATCH(F$1,SUBQH,0),0),"") | G5: =IFERROR(VLOOKUP($A5,subQ,MATCH(G$1,SUBQH,0),0),"") | H5: =IFERROR(VLOOKUP($A5,subQ,MATCH(H$1,SUBQH,0),0),"") | I5: =IFERROR(VLOOKUP($A5,subQ,MATCH(I$1,SUBQH,0),0),"") | J5: =IFERROR(VLOOKUP($A5,subQ,MATCH(J$1,SUBQH,0),0),"") | K5: =IFERROR(VLOOKUP($A5,subQ,MATCH(K$1,SUBQH,0),0),"") | L5: =IFERROR(VLOOKUP($A5,subQ,MATCH(L$1,SUBQH,0),0),"") | ... AG5: =IFERROR(VLOOKUP($A5,subQ,MATCH(AG$1,SUBQH,0),0),"")
A6: 매출원가 | D6: 매출원가 | E6: =IFERROR(VLOOKUP($A6,subQ,MATCH(E$1,SUBQH,0),0),"") | F6: =IFERROR(VLOOKUP($A6,subQ,MATCH(F$1,SUBQH,0),0),"") | G6: =IFERROR(VLOOKUP($A6,subQ,MATCH(G$1,SUBQH,0),0),"") | H6: =IFERROR(VLOOKUP($A6,subQ,MATCH(H$1,SUBQH,0),0),"") | I6: =IFERROR(VLOOKUP($A6,subQ,MATCH(I$1,SUBQH,0),0),"") | J6: =IFERROR(VLOOKUP($A6,subQ,MATCH(J$1,SUBQH,0),0),"") | K6: =IFERROR(VLOOKUP($A6,subQ,MATCH(K$1,SUBQH,0),0),"") | L6: =IFERROR(VLOOKUP($A6,subQ,MATCH(L$1,SUBQH,0),0),"") | ... AG6: =IFERROR(VLOOKUP($A6,subQ,MATCH(AG$1,SUBQH,0),0),"")
A7: 매출총이익 | D7: 매출총이익 | E7: =IFERROR(VLOOKUP($A7,subQ,MATCH(E$1,SUBQH,0),0),"") | F7: =IFERROR(VLOOKUP($A7,subQ,MATCH(F$1,SUBQH,0),0),"") | G7: =IFERROR(VLOOKUP($A7,subQ,MATCH(G$1,SUBQH,0),0),"") | H7: =IFERROR(VLOOKUP($A7,subQ,MATCH(H$1,SUBQH,0),0),"") | I7: =IFERROR(VLOOKUP($A7,subQ,MATCH(I$1,SUBQH,0),0),"") | J7: =IFERROR(VLOOKUP($A7,subQ,MATCH(J$1,SUBQH,0),0),"") | K7: =IFERROR(VLOOKUP($A7,subQ,MATCH(K$1,SUBQH,0),0),"") | L7: =IFERROR(VLOOKUP($A7,subQ,MATCH(L$1,SUBQH,0),0),"") | ... AG7: =IFERROR(VLOOKUP($A7,subQ,MATCH(AG$1,SUBQH,0),0),"")
A8: 판관비 | D8: 판매비와관리비 | E8: =IFERROR(VLOOKUP($A8,subQ,MATCH(E$1,SUBQH,0),0),"") | F8: =IFERROR(VLOOKUP($A8,subQ,MATCH(F$1,SUBQH,0),0),"") | G8: =IFERROR(VLOOKUP($A8,subQ,MATCH(G$1,SUBQH,0),0),"") | H8: =IFERROR(VLOOKUP($A8,subQ,MATCH(H$1,SUBQH,0),0),"") | I8: =IFERROR(VLOOKUP($A8,subQ,MATCH(I$1,SUBQH,0),0),"") | J8: =IFERROR(VLOOKUP($A8,subQ,MATCH(J$1,SUBQH,0),0),"") | K8: =IFERROR(VLOOKUP($A8,subQ,MATCH(K$1,SUBQH,0),0),"") | L8: =IFERROR(VLOOKUP($A8,subQ,MATCH(L$1,SUBQH,0),0),"") | ... AG8: =IFERROR(VLOOKUP($A8,subQ,MATCH(AG$1,SUBQH,0),0),"")
A9: 영업이익 | D9: 영업이익 | E9: =IFERROR(VLOOKUP($A9,subQ,MATCH(E$1,SUBQH,0),0),"") | F9: =IFERROR(VLOOKUP($A9,subQ,MATCH(F$1,SUBQH,0),0),"") | G9: =IFERROR(VLOOKUP($A9,subQ,MATCH(G$1,SUBQH,0),0),"") | H9: =IFERROR(VLOOKUP($A9,subQ,MATCH(H$1,SUBQH,0),0),"") | I9: =IFERROR(VLOOKUP($A9,subQ,MATCH(I$1,SUBQH,0),0),"") | J9: =IFERROR(VLOOKUP($A9,subQ,MATCH(J$1,SUBQH,0),0),"") | K9: =IFERROR(VLOOKUP($A9,subQ,MATCH(K$1,SUBQH,0),0),"") | L9: =IFERROR(VLOOKUP($A9,subQ,MATCH(L$1,SUBQH,0),0),"") | ... AG9: =IFERROR(VLOOKUP($A9,subQ,MATCH(AG$1,SUBQH,0),0),"")
A10: OPM | D10: 영업이익률 | E10: =IFERROR(VLOOKUP($A10,subQ,MATCH(E$1,SUBQH,0),0),"") | F10: =IFERROR(VLOOKUP($A10,subQ,MATCH(F$1,SUBQH,0),0),"") | G10: =IFERROR(VLOOKUP($A10,subQ,MATCH(G$1,SUBQH,0),0),"") | H10: =IFERROR(VLOOKUP($A10,subQ,MATCH(H$1,SUBQH,0),0),"") | I10: =IFERROR(VLOOKUP($A10,subQ,MATCH(I$1,SUBQH,0),0),"") | J10: =IFERROR(VLOOKUP($A10,subQ,MATCH(J$1,SUBQH,0),0),"") | K10: =IFERROR(VLOOKUP($A10,subQ,MATCH(K$1,SUBQH,0),0),"") | L10: =IFERROR(VLOOKUP($A10,subQ,MATCH(L$1,SUBQH,0),0),"") | ... AG10: =IFERROR(VLOOKUP($A10,subQ,MATCH(AG$1,SUBQH,0),0),"")
A11: 금융손익 | D11: 금융손익(이자·환 포함) | E11: =IFERROR(VLOOKUP($A11,subQ,MATCH(E$1,SUBQH,0),0),"") | F11: =IFERROR(VLOOKUP($A11,subQ,MATCH(F$1,SUBQH,0),0),"") | G11: =IFERROR(VLOOKUP($A11,subQ,MATCH(G$1,SUBQH,0),0),"") | H11: =IFERROR(VLOOKUP($A11,subQ,MATCH(H$1,SUBQH,0),0),"") | I11: =IFERROR(VLOOKUP($A11,subQ,MATCH(I$1,SUBQH,0),0),"") | J11: =IFERROR(VLOOKUP($A11,subQ,MATCH(J$1,SUBQH,0),0),"") | K11: =IFERROR(VLOOKUP($A11,subQ,MATCH(K$1,SUBQH,0),0),"") | L11: =IFERROR(VLOOKUP($A11,subQ,MATCH(L$1,SUBQH,0),0),"") | ... AG11: =IFERROR(VLOOKUP($A11,subQ,MATCH(AG$1,SUBQH,0),0),"")
A12: 이자손익 | D12: 이자손익(이자수익 − 이자비용) | E12: =IFERROR(VLOOKUP($A12,subQ,MATCH(E$1,SUBQH,0),0),"") | F12: =IFERROR(VLOOKUP($A12,subQ,MATCH(F$1,SUBQH,0),0),"") | G12: =IFERROR(VLOOKUP($A12,subQ,MATCH(G$1,SUBQH,0),0),"") | H12: =IFERROR(VLOOKUP($A12,subQ,MATCH(H$1,SUBQH,0),0),"") | I12: =IFERROR(VLOOKUP($A12,subQ,MATCH(I$1,SUBQH,0),0),"") | J12: =IFERROR(VLOOKUP($A12,subQ,MATCH(J$1,SUBQH,0),0),"") | K12: =IFERROR(VLOOKUP($A12,subQ,MATCH(K$1,SUBQH,0),0),"") | L12: =IFERROR(VLOOKUP($A12,subQ,MATCH(L$1,SUBQH,0),0),"") | ... AG12: =IFERROR(VLOOKUP($A12,subQ,MATCH(AG$1,SUBQH,0),0),"")
A13: 외환손익 | D13: 외환손익(실적만; 추정 환효과는 환관련손익) | E13: =IFERROR(VLOOKUP($A13,subQ,MATCH(E$1,SUBQH,0),0),"") | F13: =IFERROR(VLOOKUP($A13,subQ,MATCH(F$1,SUBQH,0),0),"") | G13: =IFERROR(VLOOKUP($A13,subQ,MATCH(G$1,SUBQH,0),0),"") | H13: =IFERROR(VLOOKUP($A13,subQ,MATCH(H$1,SUBQH,0),0),"") | I13: =IFERROR(VLOOKUP($A13,subQ,MATCH(I$1,SUBQH,0),0),"") | J13: =IFERROR(VLOOKUP($A13,subQ,MATCH(J$1,SUBQH,0),0),"") | K13: =IFERROR(VLOOKUP($A13,subQ,MATCH(K$1,SUBQH,0),0),"") | L13: =IFERROR(VLOOKUP($A13,subQ,MATCH(L$1,SUBQH,0),0),"") | ... AG13: =IFERROR(VLOOKUP($A13,subQ,MATCH(AG$1,SUBQH,0),0),"")
A14: 기타영업외손익 | D14: 기타영업외손익 | E14: =IFERROR(VLOOKUP($A14,subQ,MATCH(E$1,SUBQH,0),0),"") | F14: =IFERROR(VLOOKUP($A14,subQ,MATCH(F$1,SUBQH,0),0),"") | G14: =IFERROR(VLOOKUP($A14,subQ,MATCH(G$1,SUBQH,0),0),"") | H14: =IFERROR(VLOOKUP($A14,subQ,MATCH(H$1,SUBQH,0),0),"") | I14: =IFERROR(VLOOKUP($A14,subQ,MATCH(I$1,SUBQH,0),0),"") | J14: =IFERROR(VLOOKUP($A14,subQ,MATCH(J$1,SUBQH,0),0),"") | K14: =IFERROR(VLOOKUP($A14,subQ,MATCH(K$1,SUBQH,0),0),"") | L14: =IFERROR(VLOOKUP($A14,subQ,MATCH(L$1,SUBQH,0),0),"") | ... AG14: =IFERROR(VLOOKUP($A14,subQ,MATCH(AG$1,SUBQH,0),0),"")
A15: 지분법손익 | D15: 지분법손익 | E15: =IFERROR(VLOOKUP($A15,subQ,MATCH(E$1,SUBQH,0),0),"") | F15: =IFERROR(VLOOKUP($A15,subQ,MATCH(F$1,SUBQH,0),0),"") | G15: =IFERROR(VLOOKUP($A15,subQ,MATCH(G$1,SUBQH,0),0),"") | H15: =IFERROR(VLOOKUP($A15,subQ,MATCH(H$1,SUBQH,0),0),"") | I15: =IFERROR(VLOOKUP($A15,subQ,MATCH(I$1,SUBQH,0),0),"") | J15: =IFERROR(VLOOKUP($A15,subQ,MATCH(J$1,SUBQH,0),0),"") | K15: =IFERROR(VLOOKUP($A15,subQ,MATCH(K$1,SUBQH,0),0),"") | L15: =IFERROR(VLOOKUP($A15,subQ,MATCH(L$1,SUBQH,0),0),"") | ... AG15: =IFERROR(VLOOKUP($A15,subQ,MATCH(AG$1,SUBQH,0),0),"")
A16: 세전이익 | D16: 법인세비용차감전이익 | E16: =IFERROR(VLOOKUP($A16,subQ,MATCH(E$1,SUBQH,0),0),"") | F16: =IFERROR(VLOOKUP($A16,subQ,MATCH(F$1,SUBQH,0),0),"") | G16: =IFERROR(VLOOKUP($A16,subQ,MATCH(G$1,SUBQH,0),0),"") | H16: =IFERROR(VLOOKUP($A16,subQ,MATCH(H$1,SUBQH,0),0),"") | I16: =IFERROR(VLOOKUP($A16,subQ,MATCH(I$1,SUBQH,0),0),"") | J16: =IFERROR(VLOOKUP($A16,subQ,MATCH(J$1,SUBQH,0),0),"") | K16: =IFERROR(VLOOKUP($A16,subQ,MATCH(K$1,SUBQH,0),0),"") | L16: =IFERROR(VLOOKUP($A16,subQ,MATCH(L$1,SUBQH,0),0),"") | ... AG16: =IFERROR(VLOOKUP($A16,subQ,MATCH(AG$1,SUBQH,0),0),"")
... A38: NPM | D38: NPM | E38: =IFERROR(VLOOKUP($A38,subQ,MATCH(E$1,SUBQH,0),0),"") | F38: =IFERROR(VLOOKUP($A38,subQ,MATCH(F$1,SUBQH,0),0),"") | G38: =IFERROR(VLOOKUP($A38,subQ,MATCH(G$1,SUBQH,0),0),"") | H38: =IFERROR(VLOOKUP($A38,subQ,MATCH(H$1,SUBQH,0),0),"") | I38: =IFERROR(VLOOKUP($A38,subQ,MATCH(I$1,SUBQH,0),0),"") | J38: =IFERROR(VLOOKUP($A38,subQ,MATCH(J$1,SUBQH,0),0),"") | K38: =IFERROR(VLOOKUP($A38,subQ,MATCH(K$1,SUBQH,0),0),"") | L38: =IFERROR(VLOOKUP($A38,subQ,MATCH(L$1,SUBQH,0),0),"") | ... AG38: =IFERROR(VLOOKUP($A38,subQ,MATCH(AG$1,SUBQH,0),0),"")
A39: 매출액 YoY | D39: 매출액 YoY | I39: =IFERROR(I5/E5-1,"") | J39: =IFERROR(J5/F5-1,"") | K39: =IFERROR(K5/G5-1,"") | L39: =IFERROR(L5/H5-1,"") | M39: =IFERROR(M5/I5-1,"") | N39: =IFERROR(N5/J5-1,"") | O39: =IFERROR(O5/K5-1,"") | P39: =IFERROR(P5/L5-1,"") | ... AG39: =IFERROR(AG5/AC5-1,"")
A40: 영업이익 YoY | D40: 영업이익 YoY | I40: =IFERROR(I9/E9-1,"") | J40: =IFERROR(J9/F9-1,"") | K40: =IFERROR(K9/G9-1,"") | L40: =IFERROR(L9/H9-1,"") | M40: =IFERROR(M9/I9-1,"") | N40: =IFERROR(N9/J9-1,"") | O40: =IFERROR(O9/K9-1,"") | P40: =IFERROR(P9/L9-1,"") | ... AG40: =IFERROR(AG9/AC9-1,"")
A41: 지배주주순이익 YoY | D41: 지배주주순이익 YoY | I41: =IFERROR(I19/E19-1,"") | J41: =IFERROR(J19/F19-1,"") | K41: =IFERROR(K19/G19-1,"") | L41: =IFERROR(L19/H19-1,"") | M41: =IFERROR(M19/I19-1,"") | N41: =IFERROR(N19/J19-1,"") | O41: =IFERROR(O19/K19-1,"") | P41: =IFERROR(P19/L19-1,"") | ... AG41: =IFERROR(AG19/AC19-1,"")

Sheet 연간예상
C1: 이름: 연간예상H — subQ 를 이름으로 VLOOKUP(억원) | E1: 2021 | F1: 2022 | G1: 2023 | H1: 2024 | I1: 2025 | J1: 2026 | K1: 2027 | L1: 2028
C2: 종가: | D2: =변수!D42
C3: 기준일: | D3: 20261013 | E3: 1 | F3: 2 | G3: 3 | H3: 4 | I3: 5 | J3: 6 | K3: 7 | L3: 8
E4: 2021.12A | F4: 2022.12A | G4: 2023.12A | H4: 2024.12A | I4: 2025.12A | J4: 2026.12A | K4: 2027.12A | L4: 2028.12A
A5: 매출액 | D5: 매출액 | E5: =IFERROR(VLOOKUP($A5,subQ,MATCH(E$1,SUBQH,0),0),"") | F5: =IFERROR(VLOOKUP($A5,subQ,MATCH(F$1,SUBQH,0),0),"") | G5: =IFERROR(VLOOKUP($A5,subQ,MATCH(G$1,SUBQH,0),0),"") | H5: =IFERROR(VLOOKUP($A5,subQ,MATCH(H$1,SUBQH,0),0),"") | I5: =IFERROR(VLOOKUP($A5,subQ,MATCH(I$1,SUBQH,0),0),"") | J5: =IFERROR(VLOOKUP($A5,subQ,MATCH(J$1,SUBQH,0),0),"") | K5: =IFERROR(VLOOKUP($A5,subQ,MATCH(K$1,SUBQH,0),0),"") | L5: =IFERROR(VLOOKUP($A5,subQ,MATCH(L$1,SUBQH,0),0),"")
A6: 매출원가 | D6: 매출원가 | E6: =IFERROR(VLOOKUP($A6,subQ,MATCH(E$1,SUBQH,0),0),"") | F6: =IFERROR(VLOOKUP($A6,subQ,MATCH(F$1,SUBQH,0),0),"") | G6: =IFERROR(VLOOKUP($A6,subQ,MATCH(G$1,SUBQH,0),0),"") | H6: =IFERROR(VLOOKUP($A6,subQ,MATCH(H$1,SUBQH,0),0),"") | I6: =IFERROR(VLOOKUP($A6,subQ,MATCH(I$1,SUBQH,0),0),"") | J6: =IFERROR(VLOOKUP($A6,subQ,MATCH(J$1,SUBQH,0),0),"") | K6: =IFERROR(VLOOKUP($A6,subQ,MATCH(K$1,SUBQH,0),0),"") | L6: =IFERROR(VLOOKUP($A6,subQ,MATCH(L$1,SUBQH,0),0),"")
A7: 매출총이익 | D7: 매출총이익 | E7: =IFERROR(VLOOKUP($A7,subQ,MATCH(E$1,SUBQH,0),0),"") | F7: =IFERROR(VLOOKUP($A7,subQ,MATCH(F$1,SUBQH,0),0),"") | G7: =IFERROR(VLOOKUP($A7,subQ,MATCH(G$1,SUBQH,0),0),"") | H7: =IFERROR(VLOOKUP($A7,subQ,MATCH(H$1,SUBQH,0),0),"") | I7: =IFERROR(VLOOKUP($A7,subQ,MATCH(I$1,SUBQH,0),0),"") | J7: =IFERROR(VLOOKUP($A7,subQ,MATCH(J$1,SUBQH,0),0),"") | K7: =IFERROR(VLOOKUP($A7,subQ,MATCH(K$1,SUBQH,0),0),"") | L7: =IFERROR(VLOOKUP($A7,subQ,MATCH(L$1,SUBQH,0),0),"")
A8: 판관비 | D8: 판매비와관리비 | E8: =IFERROR(VLOOKUP($A8,subQ,MATCH(E$1,SUBQH,0),0),"") | F8: =IFERROR(VLOOKUP($A8,subQ,MATCH(F$1,SUBQH,0),0),"") | G8: =IFERROR(VLOOKUP($A8,subQ,MATCH(G$1,SUBQH,0),0),"") | H8: =IFERROR(VLOOKUP($A8,subQ,MATCH(H$1,SUBQH,0),0),"") | I8: =IFERROR(VLOOKUP($A8,subQ,MATCH(I$1,SUBQH,0),0),"") | J8: =IFERROR(VLOOKUP($A8,subQ,MATCH(J$1,SUBQH,0),0),"") | K8: =IFERROR(VLOOKUP($A8,subQ,MATCH(K$1,SUBQH,0),0),"") | L8: =IFERROR(VLOOKUP($A8,subQ,MATCH(L$1,SUBQH,0),0),"")
A9: 영업이익 | D9: 영업이익 | E9: =IFERROR(VLOOKUP($A9,subQ,MATCH(E$1,SUBQH,0),0),"") | F9: =IFERROR(VLOOKUP($A9,subQ,MATCH(F$1,SUBQH,0),0),"") | G9: =IFERROR(VLOOKUP($A9,subQ,MATCH(G$1,SUBQH,0),0),"") | H9: =IFERROR(VLOOKUP($A9,subQ,MATCH(H$1,SUBQH,0),0),"") | I9: =IFERROR(VLOOKUP($A9,subQ,MATCH(I$1,SUBQH,0),0),"") | J9: =IFERROR(VLOOKUP($A9,subQ,MATCH(J$1,SUBQH,0),0),"") | K9: =IFERROR(VLOOKUP($A9,subQ,MATCH(K$1,SUBQH,0),0),"") | L9: =IFERROR(VLOOKUP($A9,subQ,MATCH(L$1,SUBQH,0),0),"")
A10: OPM | D10: 영업이익률 | E10: =IFERROR(VLOOKUP($A10,subQ,MATCH(E$1,SUBQH,0),0),"") | F10: =IFERROR(VLOOKUP($A10,subQ,MATCH(F$1,SUBQH,0),0),"") | G10: =IFERROR(VLOOKUP($A10,subQ,MATCH(G$1,SUBQH,0),0),"") | H10: =IFERROR(VLOOKUP($A10,subQ,MATCH(H$1,SUBQH,0),0),"") | I10: =IFERROR(VLOOKUP($A10,subQ,MATCH(I$1,SUBQH,0),0),"") | J10: =IFERROR(VLOOKUP($A10,subQ,MATCH(J$1,SUBQH,0),0),"") | K10: =IFERROR(VLOOKUP($A10,subQ,MATCH(K$1,SUBQH,0),0),"") | L10: =IFERROR(VLOOKUP($A10,subQ,MATCH(L$1,SUBQH,0),0),"")
A11: 금융손익 | D11: 금융손익(이자·환 포함) | E11: =IFERROR(VLOOKUP($A11,subQ,MATCH(E$1,SUBQH,0),0),"") | F11: =IFERROR(VLOOKUP($A11,subQ,MATCH(F$1,SUBQH,0),0),"") | G11: =IFERROR(VLOOKUP($A11,subQ,MATCH(G$1,SUBQH,0),0),"") | H11: =IFERROR(VLOOKUP($A11,subQ,MATCH(H$1,SUBQH,0),0),"") | I11: =IFERROR(VLOOKUP($A11,subQ,MATCH(I$1,SUBQH,0),0),"") | J11: =IFERROR(VLOOKUP($A11,subQ,MATCH(J$1,SUBQH,0),0),"") | K11: =IFERROR(VLOOKUP($A11,subQ,MATCH(K$1,SUBQH,0),0),"") | L11: =IFERROR(VLOOKUP($A11,subQ,MATCH(L$1,SUBQH,0),0),"")
A12: 이자손익 | D12: 이자손익(이자수익 − 이자비용) | E12: =IFERROR(VLOOKUP($A12,subQ,MATCH(E$1,SUBQH,0),0),"") | F12: =IFERROR(VLOOKUP($A12,subQ,MATCH(F$1,SUBQH,0),0),"") | G12: =IFERROR(VLOOKUP($A12,subQ,MATCH(G$1,SUBQH,0),0),"") | H12: =IFERROR(VLOOKUP($A12,subQ,MATCH(H$1,SUBQH,0),0),"") | I12: =IFERROR(VLOOKUP($A12,subQ,MATCH(I$1,SUBQH,0),0),"") | J12: =IFERROR(VLOOKUP($A12,subQ,MATCH(J$1,SUBQH,0),0),"") | K12: =IFERROR(VLOOKUP($A12,subQ,MATCH(K$1,SUBQH,0),0),"") | L12: =IFERROR(VLOOKUP($A12,subQ,MATCH(L$1,SUBQH,0),0),"")
A13: 외환손익 | D13: 외환손익(실적만; 추정 환효과는 환관련손익) | E13: =IFERROR(VLOOKUP($A13,subQ,MATCH(E$1,SUBQH,0),0),"") | F13: =IFERROR(VLOOKUP($A13,subQ,MATCH(F$1,SUBQH,0),0),"") | G13: =IFERROR(VLOOKUP($A13,subQ,MATCH(G$1,SUBQH,0),0),"") | H13: =IFERROR(VLOOKUP($A13,subQ,MATCH(H$1,SUBQH,0),0),"") | I13: =IFERROR(VLOOKUP($A13,subQ,MATCH(I$1,SUBQH,0),0),"") | J13: =IFERROR(VLOOKUP($A13,subQ,MATCH(J$1,SUBQH,0),0),"") | K13: =IFERROR(VLOOKUP($A13,subQ,MATCH(K$1,SUBQH,0),0),"") | L13: =IFERROR(VLOOKUP($A13,subQ,MATCH(L$1,SUBQH,0),0),"")
A14: 기타영업외손익 | D14: 기타영업외손익 | E14: =IFERROR(VLOOKUP($A14,subQ,MATCH(E$1,SUBQH,0),0),"") | F14: =IFERROR(VLOOKUP($A14,subQ,MATCH(F$1,SUBQH,0),0),"") | G14: =IFERROR(VLOOKUP($A14,subQ,MATCH(G$1,SUBQH,0),0),"") | H14: =IFERROR(VLOOKUP($A14,subQ,MATCH(H$1,SUBQH,0),0),"") | I14: =IFERROR(VLOOKUP($A14,subQ,MATCH(I$1,SUBQH,0),0),"") | J14: =IFERROR(VLOOKUP($A14,subQ,MATCH(J$1,SUBQH,0),0),"") | K14: =IFERROR(VLOOKUP($A14,subQ,MATCH(K$1,SUBQH,0),0),"") | L14: =IFERROR(VLOOKUP($A14,subQ,MATCH(L$1,SUBQH,0),0),"")
A15: 지분법손익 | D15: 지분법손익 | E15: =IFERROR(VLOOKUP($A15,subQ,MATCH(E$1,SUBQH,0),0),"") | F15: =IFERROR(VLOOKUP($A15,subQ,MATCH(F$1,SUBQH,0),0),"") | G15: =IFERROR(VLOOKUP($A15,subQ,MATCH(G$1,SUBQH,0),0),"") | H15: =IFERROR(VLOOKUP($A15,subQ,MATCH(H$1,SUBQH,0),0),"") | I15: =IFERROR(VLOOKUP($A15,subQ,MATCH(I$1,SUBQH,0),0),"") | J15: =IFERROR(VLOOKUP($A15,subQ,MATCH(J$1,SUBQH,0),0),"") | K15: =IFERROR(VLOOKUP($A15,subQ,MATCH(K$1,SUBQH,0),0),"") | L15: =IFERROR(VLOOKUP($A15,subQ,MATCH(L$1,SUBQH,0),0),"")
A16: 세전이익 | D16: 법인세비용차감전이익 | E16: =IFERROR(VLOOKUP($A16,subQ,MATCH(E$1,SUBQH,0),0),"") | F16: =IFERROR(VLOOKUP($A16,subQ,MATCH(F$1,SUBQH,0),0),"") | G16: =IFERROR(VLOOKUP($A16,subQ,MATCH(G$1,SUBQH,0),0),"") | H16: =IFERROR(VLOOKUP($A16,subQ,MATCH(H$1,SUBQH,0),0),"") | I16: =IFERROR(VLOOKUP($A16,subQ,MATCH(I$1,SUBQH,0),0),"") | J16: =IFERROR(VLOOKUP($A16,subQ,MATCH(J$1,SUBQH,0),0),"") | K16: =IFERROR(VLOOKUP($A16,subQ,MATCH(K$1,SUBQH,0),0),"") | L16: =IFERROR(VLOOKUP($A16,subQ,MATCH(L$1,SUBQH,0),0),"")
... A38: NPM | D38: NPM | E38: =IFERROR(VLOOKUP($A38,subQ,MATCH(E$1,SUBQH,0),0),"") | F38: =IFERROR(VLOOKUP($A38,subQ,MATCH(F$1,SUBQH,0),0),"") | G38: =IFERROR(VLOOKUP($A38,subQ,MATCH(G$1,SUBQH,0),0),"") | H38: =IFERROR(VLOOKUP($A38,subQ,MATCH(H$1,SUBQH,0),0),"") | I38: =IFERROR(VLOOKUP($A38,subQ,MATCH(I$1,SUBQH,0),0),"") | J38: =IFERROR(VLOOKUP($A38,subQ,MATCH(J$1,SUBQH,0),0),"") | K38: =IFERROR(VLOOKUP($A38,subQ,MATCH(K$1,SUBQH,0),0),"") | L38: =IFERROR(VLOOKUP($A38,subQ,MATCH(L$1,SUBQH,0),0),"")
A39: 매출액 YoY | D39: 매출액 YoY | F39: =IFERROR(F5/E5-1,"") | G39: =IFERROR(G5/F5-1,"") | H39: =IFERROR(H5/G5-1,"") | I39: =IFERROR(I5/H5-1,"") | J39: =IFERROR(J5/I5-1,"") | K39: =IFERROR(K5/J5-1,"") | L39: =IFERROR(L5/K5-1,"")
A40: 영업이익 YoY | D40: 영업이익 YoY | F40: =IFERROR(F9/E9-1,"") | G40: =IFERROR(G9/F9-1,"") | H40: =IFERROR(H9/G9-1,"") | I40: =IFERROR(I9/H9-1,"") | J40: =IFERROR(J9/I9-1,"") | K40: =IFERROR(K9/J9-1,"") | L40: =IFERROR(L9/K9-1,"")
A41: 지배주주순이익 YoY | D41: 지배주주순이익 YoY | F41: =IFERROR(F19/E19-1,"") | G41: =IFERROR(G19/F19-1,"") | H41: =IFERROR(H19/G19-1,"") | I41: =IFERROR(I19/H19-1,"") | J41: =IFERROR(J19/I19-1,"") | K41: =IFERROR(K19/J19-1,"") | L41: =IFERROR(L19/K19-1,"")

Sheet TP
B1: 종가 | C1: =변수!D42
B2: 기준일 | C2: =변수!D43
B3: 모델 산출값 — 목표주가·추천 아님. 밴드·COE 는 변수 시트 3절의 가정
C5: FY | D5: 2025 | E5: 2026 | F5: 2027 | G5: 2028
D6: A | E6: E | F6: E | G6: E
C7: EPS(원) | D7: =IFERROR(VLOOKUP("EPS",subQ,MATCH(D$5,SUBQH,0),0),"") | E7: =IFERROR(VLOOKUP("EPS",subQ,MATCH(E$5,SUBQH,0),0),"") | F7: =IFERROR(VLOOKUP("EPS",subQ,MATCH(F$5,SUBQH,0),0),"") | G7: =IFERROR(VLOOKUP("EPS",subQ,MATCH(G$5,SUBQH,0),0),"")
C8: BPS(원) | D8: =IFERROR(VLOOKUP("BPS",subQ,MATCH(D$5,SUBQH,0),0),"") | E8: =IFERROR(VLOOKUP("BPS",subQ,MATCH(E$5,SUBQH,0),0),"") | F8: =IFERROR(VLOOKUP("BPS",subQ,MATCH(F$5,SUBQH,0),0),"") | G8: =IFERROR(VLOOKUP("BPS",subQ,MATCH(G$5,SUBQH,0),0),"")
C9: 지배주주순이익(억원) | D9: =IFERROR(VLOOKUP("지배주주순이익",subQ,MATCH(D$5,SUBQH,0),0),"") | E9: =IFERROR(VLOOKUP("지배주주순이익",subQ,MATCH(E$5,SUBQH,0),0),"") | F9: =IFERROR(VLOOKUP("지배주주순이익",subQ,MATCH(F$5,SUBQH,0),0),"") | G9: =IFERROR(VLOOKUP("지배주주순이익",subQ,MATCH(G$5,SUBQH,0),0),"")
C10: 영업이익(억원) | D10: =IFERROR(VLOOKUP("영업이익",subQ,MATCH(D$5,SUBQH,0),0),"") | E10: =IFERROR(VLOOKUP("영업이익",subQ,MATCH(E$5,SUBQH,0),0),"") | F10: =IFERROR(VLOOKUP("영업이익",subQ,MATCH(F$5,SUBQH,0),0),"") | G10: =IFERROR(VLOOKUP("영업이익",subQ,MATCH(G$5,SUBQH,0),0),"")
C11: ROE(EPS/기초BPS) | E11: =IFERROR(E7/D8,"") | F11: =IFERROR(F7/E8,"") | G11: =IFERROR(G7/F8,"")
B13: PER
C14: 12M fwd EPS | D14: =IFERROR(E7*변수!D48+F7*(1-변수!D48),"")
C15: 적정가치 @PER_lo | D15: =변수!D45 | E15: =IFERROR(ROUND($D$14*D15,-2),"") | F15: =IFERROR(E15/$C$1-1,"") | G15: 배 · 원 · 종가 대비
C16: 적정가치 @PER_mid | D16: =변수!D46 | E16: =IFERROR(ROUND($D$14*D16,-2),"") | F16: =IFERROR(E16/$C$1-1,"") | G16: 배 · 원 · 종가 대비
C17: 적정가치 @PER_hi | D17: =변수!D47 | E17: =IFERROR(ROUND($D$14*D17,-2),"") | F17: =IFERROR(E17/$C$1-1,"") | G17: 배 · 원 · 종가 대비
C18: 현재 PER(종가/12M fwd EPS) | D18: =IFERROR($C$1/$D$14,"")
B20: PBR
C21: 최근 BPS(마지막 실적 분기) | D21: =IFERROR(VLOOKUP("BPS",subQ,MATCH("2Q26",SUBQH,0),0),"")
C22: ROE fwd(12M fwd EPS / BPS) | D22: =IFERROR($D$14/$D$21,"")
C23: COE | D23: =변수!D44
C24: 적정 PBR = ROE/COE | D24: =IFERROR(D22/D23,"")
C25: 적정가치(PBR) = BPS × 적정PBR | D25: =IFERROR(ROUND(D21*D24,-2),"") | E25: =IFERROR(D25/$C$1-1,"")
C26: 현재 PBR(종가/BPS) | D26: =IFERROR($C$1/D21,"")
B28: 모델 json valuation(참고)
C29: eps_fwd12m | D29: -177.5
C30: bps_latest | D30: 6814.4
C31: per_now
C32: pbr_now | D32: 0.43
C33: roe_fwd | D33: -0.026
C34: fair_pbr
C35: fair_value_pbr
C36: ev_ebitda
C37: note | D37: 모델 산출값 — 목표주가·추천 아님

Sheet 외화
C1: 이름: 외화QH — 환율 QoQ · 외화 순노출 × Δ기말환율 | E1: 4Q21 | F1: 1Q22 | G1: 2Q22 | H1: 3Q22 | I1: 4Q22 | J1: 1Q23 | K1: 2Q23 | L1: 3Q23 | M1: 4Q23 | N1: 1Q24 | O1: 2Q24 | P1: 3Q24 | Q1: 4Q24 | R1: 1Q25 | S1: 2Q25 | T1: 3Q25 | U1: 4Q25 | V1: 1Q26 | W1: 2Q26 | X1: 3Q26 | Y1: 4Q26 | Z1: 1Q27 | AA1: 2Q27 | AB1: 3Q27 | AC1: 4Q27 | AD1: 1Q28 | AE1: 2Q28 | AF1: 3Q28 | AG1: 4Q28
E3: 1 | F3: 2 | G3: 3 | H3: 4 | I3: 5 | J3: 6 | K3: 7 | L3: 8 | M3: 9 | N3: 10 | O3: 11 | P3: 12 | Q3: 13 | R3: 14 | S3: 15 | T3: 16 | U3: 17 | V3: 18 | W3: 19 | X3: 20 | Y3: 21 | Z3: 22 | AA3: 23 | AB3: 24 | AC3: 25 | AD3: 26 | AE3: 27 | AF3: 28 | AG3: 29
E4: 2021.12 | F4: 2022.03 | G4: 2022.06 | H4: 2022.09 | I4: 2022.12 | J4: 2023.03 | K4: 2023.06 | L4: 2023.09 | M4: 2023.12 | N4: 2024.03 | O4: 2024.06 | P4: 2024.09 | Q4: 2024.12 | R4: 2025.03 | S4: 2025.06 | T4: 2025.09 | U4: 2025.12 | V4: 2026.03 | W4: 2026.06 | X4: 2026.09 | Y4: 2026.12 | Z4: 2027.03 | AA4: 2027.06 | AB4: 2027.09 | AC4: 2027.12 | AD4: 2028.03 | AE4: 2028.06 | AF4: 2028.09 | AG4: 2028.12
D5: 원/달러(평균) | E5: =IFERROR(VLOOKUP($D5,환율,MATCH(E$1,변수H,0),0),"") | F5: =IFERROR(VLOOKUP($D5,환율,MATCH(F$1,변수H,0),0),"") | G5: =IFERROR(VLOOKUP($D5,환율,MATCH(G$1,변수H,0),0),"") | H5: =IFERROR(VLOOKUP($D5,환율,MATCH(H$1,변수H,0),0),"") | I5: =IFERROR(VLOOKUP($D5,환율,MATCH(I$1,변수H,0),0),"") | J5: =IFERROR(VLOOKUP($D5,환율,MATCH(J$1,변수H,0),0),"") | K5: =IFERROR(VLOOKUP($D5,환율,MATCH(K$1,변수H,0),0),"") | L5: =IFERROR(VLOOKUP($D5,환율,MATCH(L$1,변수H,0),0),"") | ... AG5: =IFERROR(VLOOKUP($D5,환율,MATCH(AG$1,변수H,0),0),"")
A6: 원/달러(평균) QoQ | F6: =IFERROR(F5/E5-1,"") | G6: =IFERROR(G5/F5-1,"") | H6: =IFERROR(H5/G5-1,"") | I6: =IFERROR(I5/H5-1,"") | J6: =IFERROR(J5/I5-1,"") | K6: =IFERROR(K5/J5-1,"") | L6: =IFERROR(L5/K5-1,"") | M6: =IFERROR(M5/L5-1,"") | ... AG6: =IFERROR(AG5/AF5-1,"")
D7: 원/달러(기말) | E7: =IFERROR(VLOOKUP($D7,환율,MATCH(E$1,변수H,0),0),"") | F7: =IFERROR(VLOOKUP($D7,환율,MATCH(F$1,변수H,0),0),"") | G7: =IFERROR(VLOOKUP($D7,환율,MATCH(G$1,변수H,0),0),"") | H7: =IFERROR(VLOOKUP($D7,환율,MATCH(H$1,변수H,0),0),"") | I7: =IFERROR(VLOOKUP($D7,환율,MATCH(I$1,변수H,0),0),"") | J7: =IFERROR(VLOOKUP($D7,환율,MATCH(J$1,변수H,0),0),"") | K7: =IFERROR(VLOOKUP($D7,환율,MATCH(K$1,변수H,0),0),"") | L7: =IFERROR(VLOOKUP($D7,환율,MATCH(L$1,변수H,0),0),"") | ... AG7: =IFERROR(VLOOKUP($D7,환율,MATCH(AG$1,변수H,0),0),"")
A8: 원/달러(기말) QoQ | F8: =IFERROR(F7/E7-1,"") | G8: =IFERROR(G7/F7-1,"") | H8: =IFERROR(H7/G7-1,"") | I8: =IFERROR(I7/H7-1,"") | J8: =IFERROR(J7/I7-1,"") | K8: =IFERROR(K7/J7-1,"") | L8: =IFERROR(L7/K7-1,"") | M8: =IFERROR(M7/L7-1,"") | ... AG8: =IFERROR(AG7/AF7-1,"")
D9: W/Euro(평균) | E9: =IFERROR(VLOOKUP($D9,환율,MATCH(E$1,변수H,0),0),"") | F9: =IFERROR(VLOOKUP($D9,환율,MATCH(F$1,변수H,0),0),"") | G9: =IFERROR(VLOOKUP($D9,환율,MATCH(G$1,변수H,0),0),"") | H9: =IFERROR(VLOOKUP($D9,환율,MATCH(H$1,변수H,0),0),"") | I9: =IFERROR(VLOOKUP($D9,환율,MATCH(I$1,변수H,0),0),"") | J9: =IFERROR(VLOOKUP($D9,환율,MATCH(J$1,변수H,0),0),"") | K9: =IFERROR(VLOOKUP($D9,환율,MATCH(K$1,변수H,0),0),"") | L9: =IFERROR(VLOOKUP($D9,환율,MATCH(L$1,변수H,0),0),"") | ... AG9: =IFERROR(VLOOKUP($D9,환율,MATCH(AG$1,변수H,0),0),"")
A10: W/Euro(평균) QoQ | F10: =IFERROR(F9/E9-1,"") | G10: =IFERROR(G9/F9-1,"") | H10: =IFERROR(H9/G9-1,"") | I10: =IFERROR(I9/H9-1,"") | J10: =IFERROR(J9/I9-1,"") | K10: =IFERROR(K9/J9-1,"") | L10: =IFERROR(L9/K9-1,"") | M10: =IFERROR(M9/L9-1,"") | ... AG10: =IFERROR(AG9/AF9-1,"")
D11: W/Euro(기말) | E11: =IFERROR(VLOOKUP($D11,환율,MATCH(E$1,변수H,0),0),"") | F11: =IFERROR(VLOOKUP($D11,환율,MATCH(F$1,변수H,0),0),"") | G11: =IFERROR(VLOOKUP($D11,환율,MATCH(G$1,변수H,0),0),"") | H11: =IFERROR(VLOOKUP($D11,환율,MATCH(H$1,변수H,0),0),"") | I11: =IFERROR(VLOOKUP($D11,환율,MATCH(I$1,변수H,0),0),"") | J11: =IFERROR(VLOOKUP($D11,환율,MATCH(J$1,변수H,0),0),"") | K11: =IFERROR(VLOOKUP($D11,환율,MATCH(K$1,변수H,0),0),"") | L11: =IFERROR(VLOOKUP($D11,환율,MATCH(L$1,변수H,0),0),"") | ... AG11: =IFERROR(VLOOKUP($D11,환율,MATCH(AG$1,변수H,0),0),"")
A12: W/Euro(기말) QoQ | F12: =IFERROR(F11/E11-1,"") | G12: =IFERROR(G11/F11-1,"") | H12: =IFERROR(H11/G11-1,"") | I12: =IFERROR(I11/H11-1,"") | J12: =IFERROR(J11/I11-1,"") | K12: =IFERROR(K11/J11-1,"") | L12: =IFERROR(L11/K11-1,"") | M12: =IFERROR(M11/L11-1,"") | ... AG12: =IFERROR(AG11/AF11-1,"")
D13: 원/100Y(기말) | E13: =IFERROR(VLOOKUP($D13,환율,MATCH(E$1,변수H,0),0),"") | F13: =IFERROR(VLOOKUP($D13,환율,MATCH(F$1,변수H,0),0),"") | G13: =IFERROR(VLOOKUP($D13,환율,MATCH(G$1,변수H,0),0),"") | H13: =IFERROR(VLOOKUP($D13,환율,MATCH(H$1,변수H,0),0),"") | I13: =IFERROR(VLOOKUP($D13,환율,MATCH(I$1,변수H,0),0),"") | J13: =IFERROR(VLOOKUP($D13,환율,MATCH(J$1,변수H,0),0),"") | K13: =IFERROR(VLOOKUP($D13,환율,MATCH(K$1,변수H,0),0),"") | L13: =IFERROR(VLOOKUP($D13,환율,MATCH(L$1,변수H,0),0),"") | ... AG13: =IFERROR(VLOOKUP($D13,환율,MATCH(AG$1,변수H,0),0),"")
A14: 원/100Y(기말) QoQ | F14: =IFERROR(F13/E13-1,"") | G14: =IFERROR(G13/F13-1,"") | H14: =IFERROR(H13/G13-1,"") | I14: =IFERROR(I13/H13-1,"") | J14: =IFERROR(J13/I13-1,"") | K14: =IFERROR(K13/J13-1,"") | L14: =IFERROR(L13/K13-1,"") | M14: =IFERROR(M13/L13-1,"") | ... AG14: =IFERROR(AG13/AF13-1,"")
A16: 외화순노출 | C16: 외화 순노출(백만$) | D16: =변수!D55 | E16: 외화 순노출 × Δ기말환율 (외화 시트 방식)
A17: 환관련손익추정 | C17: 환관련손익 추정(억원) = 순노출 × Δ원/달러(기말) / 100 | F17: =IFERROR($D$16*(F7-E7)/100,"") | G17: =IFERROR($D$16*(G7-F7)/100,"") | H17: =IFERROR($D$16*(H7-G7)/100,"") | I17: =IFERROR($D$16*(I7-H7)/100,"") | J17: =IFERROR($D$16*(J7-I7)/100,"") | K17: =IFERROR($D$16*(K7-J7)/100,"") | L17: =IFERROR($D$16*(L7-K7)/100,"") | M17: =IFERROR($D$16*(M7-L7)/100,"") | ... AG17: =IFERROR($D$16*(AG7-AF7)/100,"")
A18: fx_pnl.by_q | C18: 모델 fx_pnl.by_q(억원, 참고)
C19: 외화 순노출 미공시(face) → 0 + 표기
