Workbook
Name 변수H: 변수!$C$1:$AO$1
Name 환율: 변수!$C$6:$AO$13
Name BS연결H: BS연결!$C$1:$AO$1
Name BS연결: BS연결!$C$5:$AO$110
Name BS별도H: BS별도!$C$1:$AO$1
Name BS별도: BS별도!$C$5:$AO$94
Name SUBQH: subQ!$A$1:$AO$1
Name subQ: subQ!$A$5:$AO$47

Sheet README
A1: 케이씨씨(002380) 실적 모델 — ARGUS 한국조선
A2: 기준 분기 2026Q2 · 마지막 실적 2026Q2 · 생성 2026-10-12
A3: 모든 수치는 모델 산출값(DART 공개 재무제표 + 우리 추정)이다 — 목표주가·투자 추천 아님. 참고용 · 투자조언 아님.
A5: 시트
A6: 변수 가정 시계열. 환율 8행(ECB via frankfurter — L2 fx.json; 추정 분기 = 노란 가정), 추정 드라이버(노란 셀 = 모델값에서 역산한 가정, 바꾸면 재계산; 연녹 셀 = 3절 스칼라 참조 수식), 3절 스칼라 가정(세율·판관비율·지배주주비중·이자율·종가·PER 밴드·COE·외화 순노출·헤지비율)
A7: BS연결/BS별도 FnGuide 계정명 × 기간 값 덤프(백만원). 행1 분기라벨, 행4 YYYY.MM / YYYY.12A. 이름정의 BS연결H·BS연결(계정명 C열부터)
A8: subQ 분기 서브모델(억원 = 백만원/100). 확정 행: =IFERROR(VLOOKUP($D행,BS연결,MATCH(E$1,BS연결H,0),0)/100,"") 추정 행: 변수 시트 가정 셀 참조 수식. 외환손익·파생상품손익은 BS 계정 합·차, 기타금융손익은 잔차, OPM·EPS·BPS·PER·PBR 은 파생 수식, 조정EPS 는 EPS 참조(일회성 의심 분기만 산식 셀)
A9: SLS 선표(조선사만, sls json 있을 때): 요약 행(sls 저장값) + 계약별 스케줄(백만$) × (헤지비율 × 헤지환율 + (1−헤지비율) × 건조시점 환율[변수 원/달러(평균)]) → 원화 수식 블록 → 합계 행이 subQ 매출조선에 연결
A10: 시나리오 신규수주 보수/기준/낙관(forecast_panel 패널, 모델에 scenarios 가 있을 때만): 매출액·영업이익 = subQ 기준값 ± (시나리오 신규 − base 신규) × OPM. base 만 subQ 행에 포함, 나머지는 합산 안 함
A11: 분기/연간예상 subQ 를 이름(A열 key)으로 VLOOKUP 한 보고서 표(억원)
A12: TP PER 밴드 × 12M fwd EPS, PBR = ROE/COE × BPS — 모델 산출값 구간, 목표주가·추천 아님
A13: 외화 환율 QoQ, 외화 순노출 × Δ기말환율 → 환관련손익 추정
... A35: 백테스트: {"freeze": "2025Q2", "horizon": 4, "revenue_wape_pct": 32.2, "op_wape_pct": 43.9, "n": 4, "note": "단일 회사 4분기 — 통계 아님", "driver_at_freeze": "customer_yard_revenue_weighted", "selection_oos_at_freeze": {"freeze": "2024Q2", "n": 4, "wape_link": null, "wape_trend": 3.9, "adopted": "undetermined", "decision": "undetermined", "note": "현재 채택 조합(suppliers_mentions·시차 4·ma4·창 8)을 동결 데이터로 재적합할 수 없음(짝·고객 모델 부족) → 연동 WAPE 없음, undetermined(유의성 조건만으로 채택)"}, "frozen_inputs": "fin(연결/별도)·고객 조선사 모델·지주 자회사 모델은 2025Q2 까지의 분기만; 선표는 체결일 ≤ 2025Q2 말일 계약(원장 최신 금액·코호트 등급, 환산 없음); 잔고는 yards_cache 2025Q2; 시세·환율 forward·prices·forecast_panel 신규수주 미사용. 고객 가중치(suppliers.json 언급 비중)와 합병 체인링크는 현재 지식; 고객 연동 채택은 동결 모델 안에서도 자기 la−4분기 OOS 규칙(selection_oos_at_freeze)", "detail": [{"q": "2025Q3", "rev_pred": 20450.78, "rev_act": 16228.33, "op_pred": 1349.61, "op_act": 1172.64}, {"q": "2025Q4", "rev_pred": 21141.06, "rev_act": 15564.18, "op_pred": 1395.17, "op_act": 665.27}, {"q": "2026Q1", "rev_pred": 21947.17, "rev_act": 16264.0, "op_pred": 1448.37, "op_act": 881.28}, {"q": "2026Q2", "rev_pred": 23848.0, "rev_act": 18060.19, "op_pred": 1573.81, "op_act": 1288.84}]}

Sheet 변수
C1: 이름: 변수H | E1: 4Q21 | F1: 2021 | G1: 1Q22 | H1: 2Q22 | I1: 3Q22 | J1: 4Q22 | K1: 2022 | L1: 1Q23 | M1: 2Q23 | N1: 3Q23 | O1: 4Q23 | P1: 2023 | Q1: 1Q24 | R1: 2Q24 | S1: 3Q24 | T1: 4Q24 | U1: 2024 | V1: 1Q25 | W1: 2Q25 | X1: 3Q25 | Y1: 4Q25 | Z1: 2025 | AA1: 1Q26 | AB1: 2Q26 | AC1: 3Q26 | AD1: 4Q26 | AE1: 2026 | AF1: 1Q27 | AG1: 2Q27 | AH1: 3Q27 | AI1: 4Q27 | AJ1: 2027 | AK1: 1Q28 | AL1: 2Q28 | AM1: 3Q28 | AN1: 4Q28 | AO1: 2028
A2: 가정 시계열 — 노란 셀은 추정 가정(모델값에서 역산), 연녹 셀은 3절 스칼라 참조 수식. 바꾸면 subQ·분기·연간예상·TP·시나리오가 재계산됩니다.
E3: 1 | F3: 2 | G3: 3 | H3: 4 | I3: 5 | J3: 6 | K3: 7 | L3: 8 | M3: 9 | N3: 10 | O3: 11 | P3: 12 | Q3: 13 | R3: 14 | S3: 15 | T3: 16 | U3: 17 | V3: 18 | W3: 19 | X3: 20 | Y3: 21 | Z3: 22 | AA3: 23 | AB3: 24 | AC3: 25 | AD3: 26 | AE3: 27 | AF3: 28 | AG3: 29 | AH3: 30 | AI3: 31 | AJ3: 32 | AK3: 33 | AL3: 34 | AM3: 35 | AN3: 36 | AO3: 37
E4: 2021.12 | F4: 2021.12A | G4: 2022.03 | H4: 2022.06 | I4: 2022.09 | J4: 2022.12 | K4: 2022.12A | L4: 2023.03 | M4: 2023.06 | N4: 2023.09 | O4: 2023.12 | P4: 2023.12A | Q4: 2024.03 | R4: 2024.06 | S4: 2024.09 | T4: 2024.12 | U4: 2024.12A | V4: 2025.03 | W4: 2025.06 | X4: 2025.09 | Y4: 2025.12 | Z4: 2025.12A | AA4: 2026.03 | AB4: 2026.06 | AC4: 2026.09 | AD4: 2026.12 | AE4: 2026.12A | AF4: 2027.03 | AG4: 2027.06 | AH4: 2027.09 | AI4: 2027.12 | AJ4: 2027.12A | AK4: 2028.03 | AL4: 2028.06 | AM4: 2028.09 | AN4: 2028.12 | AO4: 2028.12A
B5: 1. FX | C5: 이름: 환율
A6: USDKRW_avg | C6: 원/달러(평균) | E6: 1183.5 | F6: 1145.51 | G6: 1205.78 | H6: 1262.09 | I6: 1341.93 | J6: 1360.12 | K6: 1292.98 | L6: 1276.95 | M6: 1315.69 | N6: 1313.62 | O6: 1322.01 | P6: 1306.85 | Q6: 1330.14 | R6: 1371.28 | S6: 1356.22 | T6: 1396.3 | U6: 1363.53 | V6: 1452.28 | W6: 1398.52 | X6: 1386.95 | Y6: 1449.19 | Z6: 1421.52 | AA6: 1466.12 | AB6: 1501.75 | AC6: 1418.75 | AD6: 1345.14 | AE6: 1457.21 | AF6: 1341.49 | AG6: 1341.49 | AH6: 1341.49 | AI6: 1341.49 | AK6: 1341.49 | AL6: 1341.49 | AM6: 1341.49 | AN6: 1341.49
A7: USDKRW_end | C7: 원/달러(기말) | E7: 1188.75 | F7: 1188.75 | G7: 1213.74 | H7: 1301.24 | I7: 1436.9 | J7: 1260.16 | K7: 1260.16 | L7: 1305.99 | M7: 1321.44 | N7: 1345.35 | O7: 1297.43 | P7: 1297.43 | Q7: 1349.25 | R7: 1377.73 | S7: 1312.17 | T7: 1474.78 | U7: 1474.78 | V7: 1474.54 | W7: 1355.13 | X7: 1403.67 | Y7: 1444.2 | Z7: 1444.2 | AA7: 1524.8 | AB7: 1550.89 | AC7: 1355.4 | AD7: 1341.49 | AE7: 1341.49 | AF7: 1341.49 | AG7: 1341.49 | AH7: 1341.49 | AI7: 1341.49 | AK7: 1341.49 | AL7: 1341.49 | AM7: 1341.49 | AN7: 1341.49
A8: JPY100KRW_avg | C8: 원/100Y(평균) | E8: 1041.02 | F8: 1042.74 | G8: 1036.79 | H8: 972.23 | I8: 970.61 | J8: 961.03 | K8: 985.1 | L8: 964.89 | M8: 957.36 | N8: 909 | O8: 893.22 | P8: 931.11 | Q8: 896.29 | R8: 880.14 | S8: 909.35 | T8: 917.25 | U8: 900.92 | V8: 952.59 | W8: 967.92 | X8: 940.32 | Y8: 940.77 | Z8: 950.17 | AA8: 934.39 | AB8: 942.16 | AC8: 890.41 | AD8: 850.79 | AE8: 919.21 | AF8: 847.7 | AG8: 847.7 | AH8: 847.7 | AI8: 847.7 | AK8: 847.7 | AL8: 847.7 | AM8: 847.7 | AN8: 847.7
A9: JPY100KRW_end | C9: 원/100Y(기말) | E9: 1032.62 | F9: 1032.62 | G9: 996.83 | H9: 954.9 | I9: 993.29 | J9: 955.54 | K9: 955.54 | L9: 980.62 | M9: 913.67 | N9: 901.47 | O9: 917.04 | P9: 917.04 | Q9: 892.42 | R9: 857.76 | S9: 919.21 | T9: 939.65 | U9: 939.65 | V9: 986.84 | W9: 938.85 | X9: 948.49 | Y9: 921.81 | Z9: 921.81 | AA9: 955.99 | AB9: 954.75 | AC9: 863.31 | AD9: 847.7 | AE9: 847.7 | AF9: 847.7 | AG9: 847.7 | AH9: 847.7 | AI9: 847.7 | AK9: 847.7 | AL9: 847.7 | AM9: 847.7 | AN9: 847.7
A10: EURKRW_avg | C10: W/Euro(평균) | E10: 1353.32 | F10: 1354.06 | G10: 1352.29 | H10: 1343.31 | I10: 1350.63 | J10: 1386.07 | K10: 1358.07 | L10: 1369.93 | M10: 1432.41 | N10: 1429.41 | O10: 1420.91 | P10: 1412.88 | Q10: 1444.21 | R10: 1476.42 | S10: 1489.3 | T10: 1490.78 | U10: 1475.4 | V10: 1528.33 | W10: 1585.13 | X10: 1620.04 | Y10: 1686.02 | Z10: 1605.45 | AA10: 1715.47 | AB10: 1746.09 | AC10: 1631.97 | AD10: 1509.74 | AE10: 1689.95 | AF10: 1503.27 | AG10: 1503.27 | AH10: 1503.27 | AI10: 1503.27 | AK10: 1503.27 | AL10: 1503.27 | AM10: 1503.27 | AN10: 1503.27
A11: EURKRW_end | C11: W/Euro(기말) | E11: 1346.38 | F11: 1346.38 | G11: 1347.37 | H11: 1351.6 | I11: 1400.62 | J11: 1344.08 | K11: 1344.08 | L11: 1420.26 | M11: 1435.88 | N11: 1425.26 | O11: 1433.66 | P11: 1433.66 | Q11: 1458.68 | R11: 1474.86 | S11: 1469.1 | T11: 1532.14 | U11: 1532.14 | V11: 1594.72 | W11: 1588.22 | X11: 1648.04 | Y11: 1696.94 | Z11: 1696.94 | AA11: 1753.21 | AB11: 1767.09 | AC11: 1539.06 | AD11: 1503.27 | AE11: 1503.27 | AF11: 1503.27 | AG11: 1503.27 | AH11: 1503.27 | AI11: 1503.27 | AK11: 1503.27 | AL11: 1503.27 | AM11: 1503.27 | AN11: 1503.27
A12: CNYKRW_avg | C12: 원/중국원(평균) | E12: 185.14 | F12: 177.65 | G12: 189.93 | H12: 190.76 | I12: 195.79 | J12: 191.09 | K12: 191.93 | L12: 186.59 | M12: 187.45 | N12: 181.28 | O12: 182.86 | P12: 184.52 | Q12: 185.04 | R12: 189.35 | S12: 189.24 | T12: 194.24 | U12: 189.49 | V12: 199.63 | W12: 193.41 | X12: 193.79 | Y12: 204.38 | Z12: 197.8 | AA12: 211.75 | AB12: 220.8 | AC12: 210.43 | AD12: 200.69 | AE12: 213.75 | AF12: 200.46 | AG12: 200.46 | AH12: 200.46 | AI12: 200.46 | AK12: 200.46 | AL12: 200.46 | AM12: 200.46 | AN12: 200.46
A13: CNYKRW_end | C13: 원/중국원(기말) | E13: 187.13 | F13: 187.13 | G13: 191.38 | H13: 194.13 | I13: 201.92 | J13: 182.67 | K13: 182.67 | L13: 189.97 | M13: 181.8 | N13: 184.26 | O13: 182.61 | P13: 182.61 | Q13: 186.66 | R13: 189.7 | S13: 187.12 | T13: 202.04 | U13: 202.04 | V13: 203.3 | W13: 189.14 | X13: 197.16 | Y13: 206.28 | Z13: 206.28 | AA13: 220.97 | AB13: 228.56 | AC13: 202.16 | AD13: 200.46 | AE13: 200.46 | AF13: 200.46 | AG13: 200.46 | AH13: 200.46 | AI13: 200.46 | AK13: 200.46 | AL13: 200.46 | AM13: 200.46 | AN13: 200.46
B14: 1b. 종가
A15: price_close_end | C15: 종가(기말) | E15: 315000 | G15: 342000 | H15: 287500 | I15: 231500 | J15: 204500 | L15: 222000 | M15: 196400 | N15: 246500 | O15: 228500 | Q15: 259500 | R15: 308500 | S15: 301500 | T15: 235500 | V15: 252500 | W15: 312000 | X15: 384000 | Y15: 420500 | AA15: 482000 | AB15: 486500 | AC15: 470500 | AD15: 455000
A16: price_high | C16: 종가(최고) | E16: 420500 | G16: 414500 | H16: 382500 | I16: 319500 | J16: 266000 | L16: 261500 | M16: 244500 | N16: 271500 | O16: 250500 | Q16: 294000 | R16: 327500 | S16: 345000 | T16: 306500 | V16: 289500 | W16: 344000 | X16: 441000 | Y16: 460000 | AA16: 692000 | AB16: 656000 | AC16: 514000 | AD16: 479000
A17: price_low | C17: 종가(최저) | E17: 271000 | G17: 296000 | H17: 268000 | I17: 227500 | J17: 203500 | L17: 191500 | M17: 192000 | N17: 186700 | O17: 207000 | Q17: 199900 | R17: 225000 | S17: 270500 | T17: 216500 | V17: 226500 | W17: 231000 | X17: 314000 | Y17: 367000 | AA17: 382500 | AB17: 452000 | AC17: 336000 | AD17: 452000
A18: price_avg | C18: 종가(평균) | E18: 328738.1 | G18: 348330.5 | H18: 329846.8 | I18: 284865.1 | J18: 239016.1 | L18: 229911.3 | M18: 215073.8 | N18: 216145.2 | O18: 229691.7 | Q18: 253950.8 | R18: 277025 | S18: 306096.8 | T18: 249426.2 | V18: 263310.3 | W18: 275991.7 | X18: 379915.4 | Y18: 415796.6 | AA18: 502076.3 | AB18: 534524.6 | AC18: 451483.9 | AD18: 466583.3
B20: 2. 추정 드라이버 | C20: 실적 열 = subQ 실현값(수식), 추정 열 = 가정(노란 = 모델값 역산, 연녹 = 3절 스칼라 참조)
A21: drv:매출액 | B21: yoy | C21: 매출액 YoY | J21: =IFERROR(subQ!J5/subQ!E5-1,"") | L21: =IFERROR(subQ!L5/subQ!G5-1,"") | M21: =IFERROR(subQ!M5/subQ!H5-1,"") | N21: =IFERROR(subQ!N5/subQ!I5-1,"") | O21: =IFERROR(subQ!O5/subQ!J5-1,"") | Q21: =IFERROR(subQ!Q5/subQ!L5-1,"") | R21: =IFERROR(subQ!R5/subQ!M5-1,"") | S21: =IFERROR(subQ!S5/subQ!N5-1,"") | T21: =IFERROR(subQ!T5/subQ!O5-1,"") | V21: =IFERROR(subQ!V5/subQ!Q5-1,"") | W21: =IFERROR(subQ!W5/subQ!R5-1,"") | X21: =IFERROR(subQ!X5/subQ!S5-1,"") | Y21: =IFERROR(subQ!Y5/subQ!T5-1,"") | AA21: =IFERROR(subQ!AA5/subQ!V5-1,"") | AB21: =IFERROR(subQ!AB5/subQ!W5-1,"") | AC21: 0.002340026 | AD21: 0.002340156 | AF21: 0.002340415 | AG21: 0.002340429 | AH21: 0.001170518 | AI21: 0.001170468 | AK21: 0.001169791 | AL21: 0.001170007 | AM21: 0.000584575 | AN21: 0.00058455
A22: drv:판관비 | B22: ratio | C22: 판관비율(/매출) | E22: =IFERROR(subQ!E8/subQ!E5,"") | F22: =IFERROR(subQ!F8/subQ!F5,"") | G22: =IFERROR(subQ!G8/subQ!G5,"") | H22: =IFERROR(subQ!H8/subQ!H5,"") | I22: =IFERROR(subQ!I8/subQ!I5,"") | J22: =IFERROR(subQ!J8/subQ!J5,"") | K22: =IFERROR(subQ!K8/subQ!K5,"") | L22: =IFERROR(subQ!L8/subQ!L5,"") | ... AB22: =IFERROR(subQ!AB8/subQ!AB5,"") | AC22: =$D$54 | AD22: =$D$54 | AE22: =IFERROR(subQ!AE8/subQ!AE5,"") | AF22: =$D$54 | AG22: =$D$54 | AH22: =$D$54 | AI22: =$D$54 | AJ22: =IFERROR(subQ!AJ8/subQ!AJ5,"") | AK22: =$D$54 | AL22: =$D$54 | AM22: =$D$54 | AN22: =$D$54 | AO22: =IFERROR(subQ!AO8/subQ!AO5,"")
A23: drv:영업이익 | B23: ratio | C23: 영업이익률(OPM) | E23: =IFERROR(subQ!E9/subQ!E5,"") | F23: =IFERROR(subQ!F9/subQ!F5,"") | G23: =IFERROR(subQ!G9/subQ!G5,"") | H23: =IFERROR(subQ!H9/subQ!H5,"") | I23: =IFERROR(subQ!I9/subQ!I5,"") | J23: =IFERROR(subQ!J9/subQ!J5,"") | K23: =IFERROR(subQ!K9/subQ!K5,"") | L23: =IFERROR(subQ!L9/subQ!L5,"") | ... AB23: =IFERROR(subQ!AB9/subQ!AB5,"") | AC23: 0.06802223 | AD23: 0.068022384 | AE23: =IFERROR(subQ!AE9/subQ!AE5,"") | AF23: 0.068022078 | AG23: 0.068022247 | AH23: 0.068021914 | AI23: 0.06802225 | AJ23: =IFERROR(subQ!AJ9/subQ!AJ5,"") | AK23: 0.068022251 | AL23: 0.068022207 | AM23: 0.068022063 | AN23: 0.068022183 | AO23: =IFERROR(subQ!AO9/subQ!AO5,"")
A24: drv:외환손익 | B24: abs | C24: 외환손익 (가정, 억원) | E24: =subQ!E13 | F24: =subQ!F13 | G24: =subQ!G13 | H24: =subQ!H13 | I24: =subQ!I13 | J24: =subQ!J13 | K24: =subQ!K13 | L24: =subQ!L13 | ... AB24: =subQ!AB13 | AC24: 0 | AD24: 0 | AE24: =subQ!AE13 | AF24: 0 | AG24: 0 | AH24: 0 | AI24: 0 | AJ24: =subQ!AJ13 | AK24: 0 | AL24: 0 | AM24: 0 | AN24: 0 | AO24: =subQ!AO13
A25: drv:파생상품손익 | B25: abs | C25: 파생상품손익 (가정, 억원) | E25: =subQ!E14 | F25: =subQ!F14 | G25: =subQ!G14 | H25: =subQ!H14 | I25: =subQ!I14 | J25: =subQ!J14 | K25: =subQ!K14 | L25: =subQ!L14 | ... AB25: =subQ!AB14 | AC25: 0 | AD25: 0 | AE25: =subQ!AE14 | AF25: 0 | AG25: 0 | AH25: 0 | AI25: 0 | AJ25: =subQ!AJ14 | AK25: 0 | AL25: 0 | AM25: 0 | AN25: 0 | AO25: =subQ!AO14
A26: drv:기타금융손익 | B26: abs | C26: 기타금융손익 (가정, 억원) | E26: =subQ!E15 | F26: =subQ!F15 | G26: =subQ!G15 | H26: =subQ!H15 | I26: =subQ!I15 | J26: =subQ!J15 | K26: =subQ!K15 | L26: =subQ!L15 | ... AB26: =subQ!AB15 | AC26: 0 | AD26: 0 | AE26: =subQ!AE15 | AF26: 0 | AG26: 0 | AH26: 0 | AI26: 0 | AJ26: =subQ!AJ15 | AK26: 0 | AL26: 0 | AM26: 0 | AN26: 0 | AO26: =subQ!AO15
A27: drv:기타영업외손익 | B27: abs | C27: 기타영업외손익 (가정, 억원) | E27: =subQ!E16 | F27: =subQ!F16 | G27: =subQ!G16 | H27: =subQ!H16 | I27: =subQ!I16 | J27: =subQ!J16 | K27: =subQ!K16 | L27: =subQ!L16 | ... AB27: =subQ!AB16 | AC27: 0 | AD27: 0 | AE27: =subQ!AE16 | AF27: 0 | AG27: 0 | AH27: 0 | AI27: 0 | AJ27: =subQ!AJ16 | AK27: 0 | AL27: 0 | AM27: 0 | AN27: 0 | AO27: =subQ!AO16
A28: drv:지분법손익 | B28: abs | C28: 지분법손익 (가정, 억원) | E28: =subQ!E17 | F28: =subQ!F17 | G28: =subQ!G17 | H28: =subQ!H17 | I28: =subQ!I17 | J28: =subQ!J17 | K28: =subQ!K17 | L28: =subQ!L17 | ... AB28: =subQ!AB17 | AC28: 26.09 | AD28: 26.09 | AE28: =subQ!AE17 | AF28: 26.09 | AG28: 26.09 | AH28: 26.09 | AI28: 26.09 | AJ28: =subQ!AJ17 | AK28: 26.09 | AL28: 26.09 | AM28: 26.09 | AN28: 26.09 | AO28: =subQ!AO17
A29: drv:법인세비용 | B29: tax | C29: 법인세율(/세전) — 법인세 = MAX(세전,0) × 세율 | E29: =IFERROR(subQ!E19/subQ!E18,"") | F29: =IFERROR(subQ!F19/subQ!F18,"") | G29: =IFERROR(subQ!G19/subQ!G18,"") | H29: =IFERROR(subQ!H19/subQ!H18,"") | I29: =IFERROR(subQ!I19/subQ!I18,"") | J29: =IFERROR(subQ!J19/subQ!J18,"") | K29: =IFERROR(subQ!K19/subQ!K18,"") | L29: =IFERROR(subQ!L19/subQ!L18,"") | ... AB29: =IFERROR(subQ!AB19/subQ!AB18,"") | AC29: =$D$53 | AD29: =$D$53 | AE29: =IFERROR(subQ!AE19/subQ!AE18,"") | AF29: =$D$53 | AG29: =$D$53 | AH29: =$D$53 | AI29: =$D$53 | AJ29: =IFERROR(subQ!AJ19/subQ!AJ18,"") | AK29: =$D$53 | AL29: =$D$53 | AM29: =$D$53 | AN29: =$D$53 | AO29: =IFERROR(subQ!AO19/subQ!AO18,"")
A30: drv:지배주주순이익 | B30: ratio | C30: 지배주주 비중(/당기순이익) | E30: =IFERROR(subQ!E21/subQ!E20,"") | F30: =IFERROR(subQ!F21/subQ!F20,"") | G30: =IFERROR(subQ!G21/subQ!G20,"") | H30: =IFERROR(subQ!H21/subQ!H20,"") | I30: =IFERROR(subQ!I21/subQ!I20,"") | J30: =IFERROR(subQ!J21/subQ!J20,"") | K30: =IFERROR(subQ!K21/subQ!K20,"") | L30: =IFERROR(subQ!L21/subQ!L20,"") | ... AB30: =IFERROR(subQ!AB21/subQ!AB20,"") | AC30: =$D$55 | AD30: =$D$55 | AE30: =IFERROR(subQ!AE21/subQ!AE20,"") | AF30: =$D$55 | AG30: =$D$55 | AH30: =$D$55 | AI30: =$D$55 | AJ30: =IFERROR(subQ!AJ21/subQ!AJ20,"") | AK30: =$D$55 | AL30: =$D$55 | AM30: =$D$55 | AN30: =$D$55 | AO30: =IFERROR(subQ!AO21/subQ!AO20,"")
A31: drv:중단사업이익 | B31: abs | C31: 중단사업이익 (가정, 억원) | E31: =subQ!E22 | F31: =subQ!F22 | G31: =subQ!G22 | H31: =subQ!H22 | I31: =subQ!I22 | J31: =subQ!J22 | K31: =subQ!K22 | L31: =subQ!L22 | ... AB31: =subQ!AB22 | AE31: =subQ!AE22 | AJ31: =subQ!AJ22 | AO31: =subQ!AO22
A32: drv:감가상각비 | B32: abs | C32: 감가상각비 (가정, 억원) | E32: =subQ!E23 | F32: =subQ!F23 | G32: =subQ!G23 | H32: =subQ!H23 | I32: =subQ!I23 | J32: =subQ!J23 | K32: =subQ!K23 | L32: =subQ!L23 | ... AB32: =subQ!AB23 | AC32: 927.98 | AD32: 927.98 | AE32: =subQ!AE23 | AF32: 927.98 | AG32: 927.98 | AH32: 927.98 | AI32: 927.98 | AJ32: =subQ!AJ23 | AK32: 927.98 | AL32: 927.98 | AM32: 927.98 | AN32: 927.98 | AO32: =subQ!AO23
A33: drv:부채총계 | B33: qoq | C33: 부채총계 QoQ | G33: =IFERROR(subQ!G26/subQ!E26-1,"") | H33: =IFERROR(subQ!H26/subQ!G26-1,"") | I33: =IFERROR(subQ!I26/subQ!H26-1,"") | J33: =IFERROR(subQ!J26/subQ!I26-1,"") | L33: =IFERROR(subQ!L26/subQ!J26-1,"") | M33: =IFERROR(subQ!M26/subQ!L26-1,"") | N33: =IFERROR(subQ!N26/subQ!M26-1,"") | O33: =IFERROR(subQ!O26/subQ!N26-1,"") | Q33: =IFERROR(subQ!Q26/subQ!O26-1,"") | R33: =IFERROR(subQ!R26/subQ!Q26-1,"") | S33: =IFERROR(subQ!S26/subQ!R26-1,"") | T33: =IFERROR(subQ!T26/subQ!S26-1,"") | V33: =IFERROR(subQ!V26/subQ!T26-1,"") | W33: =IFERROR(subQ!W26/subQ!V26-1,"") | X33: =IFERROR(subQ!X26/subQ!W26-1,"") | Y33: =IFERROR(subQ!Y26/subQ!X26-1,"") | AA33: =IFERROR(subQ!AA26/subQ!Y26-1,"") | AB33: =IFERROR(subQ!AB26/subQ!AA26-1,"") | AC33: 2.4e-08 | AD33: 0 | AF33: 0 | AG33: 0 | AH33: 0 | AI33: 0 | AK33: 0 | AL33: 0 | AM33: 0 | AN33: 0
A34: drv:자본총계 | B34: roll | C34: 자본총계 기타변동(배당 등, 억원) | G34: =IFERROR(subQ!E27+subQ!G20-subQ!G27,"") | H34: =IFERROR(subQ!G27+subQ!H20-subQ!H27,"") | I34: =IFERROR(subQ!H27+subQ!I20-subQ!I27,"") | J34: =IFERROR(subQ!I27+subQ!J20-subQ!J27,"") | L34: =IFERROR(subQ!J27+subQ!L20-subQ!L27,"") | M34: =IFERROR(subQ!L27+subQ!M20-subQ!M27,"") | N34: =IFERROR(subQ!M27+subQ!N20-subQ!N27,"") | O34: =IFERROR(subQ!N27+subQ!O20-subQ!O27,"") | Q34: =IFERROR(subQ!O27+subQ!Q20-subQ!Q27,"") | R34: =IFERROR(subQ!Q27+subQ!R20-subQ!R27,"") | S34: =IFERROR(subQ!R27+subQ!S20-subQ!S27,"") | T34: =IFERROR(subQ!S27+subQ!T20-subQ!T27,"") | V34: =IFERROR(subQ!T27+subQ!V20-subQ!V27,"") | W34: =IFERROR(subQ!V27+subQ!W20-subQ!W27,"") | X34: =IFERROR(subQ!W27+subQ!X20-subQ!X27,"") | Y34: =IFERROR(subQ!X27+subQ!Y20-subQ!Y27,"") | AA34: =IFERROR(subQ!Y27+subQ!AA20-subQ!AA27,"") | AB34: =IFERROR(subQ!AA27+subQ!AB20-subQ!AB27,"") | AC34: -0.005080478 | AD34: 0.003856558 | AF34: -0.004643765 | AG34: 1103.1314 | AH34: -0.009517324 | AI34: 0.00171645 | AK34: 0.0011091 | AL34: 1103.1275 | AM34: -0.008428075 | AN34: 0.000101345
A35: drv:지배주주지분 | B35: roll | C35: 지배주주지분 기타변동(배당 등, 억원) | G35: =IFERROR(subQ!E28+subQ!G21-subQ!G28,"") | H35: =IFERROR(subQ!G28+subQ!H21-subQ!H28,"") | I35: =IFERROR(subQ!H28+subQ!I21-subQ!I28,"") | J35: =IFERROR(subQ!I28+subQ!J21-subQ!J28,"") | L35: =IFERROR(subQ!J28+subQ!L21-subQ!L28,"") | M35: =IFERROR(subQ!L28+subQ!M21-subQ!M28,"") | N35: =IFERROR(subQ!M28+subQ!N21-subQ!N28,"") | O35: =IFERROR(subQ!N28+subQ!O21-subQ!O28,"") | Q35: =IFERROR(subQ!O28+subQ!Q21-subQ!Q28,"") | R35: =IFERROR(subQ!Q28+subQ!R21-subQ!R28,"") | S35: =IFERROR(subQ!R28+subQ!S21-subQ!S28,"") | T35: =IFERROR(subQ!S28+subQ!T21-subQ!T28,"") | V35: =IFERROR(subQ!T28+subQ!V21-subQ!V28,"") | W35: =IFERROR(subQ!V28+subQ!W21-subQ!W28,"") | X35: =IFERROR(subQ!W28+subQ!X21-subQ!X28,"") | Y35: =IFERROR(subQ!X28+subQ!Y21-subQ!Y28,"") | AA35: =IFERROR(subQ!Y28+subQ!AA21-subQ!AA28,"") | AB35: =IFERROR(subQ!AA28+subQ!AB21-subQ!AB28,"") | AC35: -0.005080478 | AD35: 0.003856558 | AF35: -0.004643765 | AG35: 1103.1314 | AH35: -0.009517324 | AI35: 0.00171645 | AK35: 0.0011091 | AL35: 1103.1275 | AM35: -0.008428075 | AN35: 0.000101345
A36: drv:총차입금 | B36: qoq | C36: 총차입금 QoQ | G36: =IFERROR(subQ!G29/subQ!E29-1,"") | H36: =IFERROR(subQ!H29/subQ!G29-1,"") | I36: =IFERROR(subQ!I29/subQ!H29-1,"") | J36: =IFERROR(subQ!J29/subQ!I29-1,"") | L36: =IFERROR(subQ!L29/subQ!J29-1,"") | M36: =IFERROR(subQ!M29/subQ!L29-1,"") | N36: =IFERROR(subQ!N29/subQ!M29-1,"") | O36: =IFERROR(subQ!O29/subQ!N29-1,"") | Q36: =IFERROR(subQ!Q29/subQ!O29-1,"") | R36: =IFERROR(subQ!R29/subQ!Q29-1,"") | S36: =IFERROR(subQ!S29/subQ!R29-1,"") | T36: =IFERROR(subQ!T29/subQ!S29-1,"") | V36: =IFERROR(subQ!V29/subQ!T29-1,"") | W36: =IFERROR(subQ!W29/subQ!V29-1,"") | X36: =IFERROR(subQ!X29/subQ!W29-1,"") | Y36: =IFERROR(subQ!Y29/subQ!X29-1,"") | AA36: =IFERROR(subQ!AA29/subQ!Y29-1,"") | AB36: =IFERROR(subQ!AB29/subQ!AA29-1,"") | AC36: -2.8e-08 | AD36: 0 | AF36: 0 | AG36: 0 | AH36: 0 | AI36: 0 | AK36: 0 | AL36: 0 | AM36: 0 | AN36: 0
A37: drv:순차입금 | B37: qoq | C37: 순차입금 QoQ | G37: =IFERROR(subQ!G30/subQ!E30-1,"") | H37: =IFERROR(subQ!H30/subQ!G30-1,"") | I37: =IFERROR(subQ!I30/subQ!H30-1,"") | J37: =IFERROR(subQ!J30/subQ!I30-1,"") | L37: =IFERROR(subQ!L30/subQ!J30-1,"") | M37: =IFERROR(subQ!M30/subQ!L30-1,"") | N37: =IFERROR(subQ!N30/subQ!M30-1,"") | O37: =IFERROR(subQ!O30/subQ!N30-1,"") | Q37: =IFERROR(subQ!Q30/subQ!O30-1,"") | R37: =IFERROR(subQ!R30/subQ!Q30-1,"") | S37: =IFERROR(subQ!S30/subQ!R30-1,"") | T37: =IFERROR(subQ!T30/subQ!S30-1,"") | V37: =IFERROR(subQ!V30/subQ!T30-1,"") | W37: =IFERROR(subQ!W30/subQ!V30-1,"") | X37: =IFERROR(subQ!X30/subQ!W30-1,"") | Y37: =IFERROR(subQ!Y30/subQ!X30-1,"") | AA37: =IFERROR(subQ!AA30/subQ!Y30-1,"") | AB37: =IFERROR(subQ!AB30/subQ!AA30-1,"") | AC37: -0.008628067 | AD37: -0.007833687 | AF37: -0.008833684 | AG37: 0.016519056 | AH37: -0.008739267 | AI37: -0.007937616 | AK37: -0.008948733 | AL37: 0.016637568 | AM37: -0.008840655 | AN37: -0.008032313
A38: drv:이자발생자산 | B38: qoq | C38: 이자발생자산 QoQ | G38: =IFERROR(subQ!G31/subQ!E31-1,"") | H38: =IFERROR(subQ!H31/subQ!G31-1,"") | I38: =IFERROR(subQ!I31/subQ!H31-1,"") | J38: =IFERROR(subQ!J31/subQ!I31-1,"") | L38: =IFERROR(subQ!L31/subQ!J31-1,"") | M38: =IFERROR(subQ!M31/subQ!L31-1,"") | N38: =IFERROR(subQ!N31/subQ!M31-1,"") | O38: =IFERROR(subQ!O31/subQ!N31-1,"") | Q38: =IFERROR(subQ!Q31/subQ!O31-1,"") | R38: =IFERROR(subQ!R31/subQ!Q31-1,"") | S38: =IFERROR(subQ!S31/subQ!R31-1,"") | T38: =IFERROR(subQ!T31/subQ!S31-1,"") | V38: =IFERROR(subQ!V31/subQ!T31-1,"") | W38: =IFERROR(subQ!W31/subQ!V31-1,"") | X38: =IFERROR(subQ!X31/subQ!W31-1,"") | Y38: =IFERROR(subQ!Y31/subQ!X31-1,"") | AA38: =IFERROR(subQ!AA31/subQ!Y31-1,"") | AB38: =IFERROR(subQ!AB31/subQ!AA31-1,"") | AC38: 0.003364731 | AD38: 0.003018382 | AF38: 0.003366768 | AG38: -0.006219407 | AH38: 0.003365566 | AI38: 0.00302005 | AK38: 0.003367653 | AL38: -0.006184141 | AM38: 0.003361509 | AN38: 0.003017008
A39: drv:현금및현금성자산 | B39: qoq | C39: 현금및현금성자산 QoQ | G39: =IFERROR(subQ!G32/subQ!E32-1,"") | H39: =IFERROR(subQ!H32/subQ!G32-1,"") | I39: =IFERROR(subQ!I32/subQ!H32-1,"") | J39: =IFERROR(subQ!J32/subQ!I32-1,"") | L39: =IFERROR(subQ!L32/subQ!J32-1,"") | M39: =IFERROR(subQ!M32/subQ!L32-1,"") | N39: =IFERROR(subQ!N32/subQ!M32-1,"") | O39: =IFERROR(subQ!O32/subQ!N32-1,"") | Q39: =IFERROR(subQ!Q32/subQ!O32-1,"") | R39: =IFERROR(subQ!R32/subQ!Q32-1,"") | S39: =IFERROR(subQ!S32/subQ!R32-1,"") | T39: =IFERROR(subQ!T32/subQ!S32-1,"") | V39: =IFERROR(subQ!V32/subQ!T32-1,"") | W39: =IFERROR(subQ!W32/subQ!V32-1,"") | X39: =IFERROR(subQ!X32/subQ!W32-1,"") | Y39: =IFERROR(subQ!Y32/subQ!X32-1,"") | AA39: =IFERROR(subQ!AA32/subQ!Y32-1,"") | AB39: =IFERROR(subQ!AB32/subQ!AA32-1,"")
A40: drv:CAPEX | B40: yoy | C40: CAPEX YoY | J40: =IFERROR(subQ!J33/subQ!E33-1,"") | L40: =IFERROR(subQ!L33/subQ!G33-1,"") | M40: =IFERROR(subQ!M33/subQ!H33-1,"") | N40: =IFERROR(subQ!N33/subQ!I33-1,"") | O40: =IFERROR(subQ!O33/subQ!J33-1,"") | Q40: =IFERROR(subQ!Q33/subQ!L33-1,"") | R40: =IFERROR(subQ!R33/subQ!M33-1,"") | S40: =IFERROR(subQ!S33/subQ!N33-1,"") | T40: =IFERROR(subQ!T33/subQ!O33-1,"") | V40: =IFERROR(subQ!V33/subQ!Q33-1,"") | W40: =IFERROR(subQ!W33/subQ!R33-1,"") | X40: =IFERROR(subQ!X33/subQ!S33-1,"") | Y40: =IFERROR(subQ!Y33/subQ!T33-1,"") | AA40: =IFERROR(subQ!AA33/subQ!V33-1,"") | AB40: =IFERROR(subQ!AB33/subQ!W33-1,"") | AC40: 0.1855448 | AD40: -0.21637063 | AF40: -0.055900001 | AG40: 0.062937285 | AH40: 0 | AI40: 0 | AK40: 0 | AL40: 0 | AM40: 0 | AN40: 0
A41: drv:영업활동현금흐름 | B41: yoy | C41: 영업활동현금흐름 YoY | J41: =IFERROR(subQ!J34/subQ!E34-1,"") | L41: =IFERROR(subQ!L34/subQ!G34-1,"") | M41: =IFERROR(subQ!M34/subQ!H34-1,"") | N41: =IFERROR(subQ!N34/subQ!I34-1,"") | O41: =IFERROR(subQ!O34/subQ!J34-1,"") | Q41: =IFERROR(subQ!Q34/subQ!L34-1,"") | R41: =IFERROR(subQ!R34/subQ!M34-1,"") | S41: =IFERROR(subQ!S34/subQ!N34-1,"") | T41: =IFERROR(subQ!T34/subQ!O34-1,"") | V41: =IFERROR(subQ!V34/subQ!Q34-1,"") | W41: =IFERROR(subQ!W34/subQ!R34-1,"") | X41: =IFERROR(subQ!X34/subQ!S34-1,"") | Y41: =IFERROR(subQ!Y34/subQ!T34-1,"") | AA41: =IFERROR(subQ!AA34/subQ!V34-1,"") | AB41: =IFERROR(subQ!AB34/subQ!W34-1,"")
A42: drv:주식수 | B42: qoq | C42: 주식수 QoQ | G42: =IFERROR(subQ!G35/subQ!E35-1,"") | H42: =IFERROR(subQ!H35/subQ!G35-1,"") | I42: =IFERROR(subQ!I35/subQ!H35-1,"") | J42: =IFERROR(subQ!J35/subQ!I35-1,"") | L42: =IFERROR(subQ!L35/subQ!J35-1,"") | M42: =IFERROR(subQ!M35/subQ!L35-1,"") | N42: =IFERROR(subQ!N35/subQ!M35-1,"") | O42: =IFERROR(subQ!O35/subQ!N35-1,"") | Q42: =IFERROR(subQ!Q35/subQ!O35-1,"") | R42: =IFERROR(subQ!R35/subQ!Q35-1,"") | S42: =IFERROR(subQ!S35/subQ!R35-1,"") | T42: =IFERROR(subQ!T35/subQ!S35-1,"") | V42: =IFERROR(subQ!V35/subQ!T35-1,"") | W42: =IFERROR(subQ!W35/subQ!V35-1,"") | X42: =IFERROR(subQ!X35/subQ!W35-1,"") | Y42: =IFERROR(subQ!Y35/subQ!X35-1,"") | AA42: =IFERROR(subQ!AA35/subQ!Y35-1,"") | AB42: =IFERROR(subQ!AB35/subQ!AA35-1,"") | AC42: 0 | AD42: 0 | AF42: 0 | AG42: 0 | AH42: 0 | AI42: 0 | AK42: 0 | AL42: 0 | AM42: 0 | AN42: 0
A43: drv:DPS | B43: abs | C43: DPS (가정, 원) | E43: =subQ!E39 | F43: =subQ!F39 | G43: =subQ!G39 | H43: =subQ!H39 | I43: =subQ!I39 | J43: =subQ!J39 | K43: =subQ!K39 | L43: =subQ!L39 | ... AB43: =subQ!AB39 | AD43: 15000 | AE43: =subQ!AE39 | AI43: 15000 | AJ43: =subQ!AJ39 | AN43: 15000 | AO43: =subQ!AO39
B45: 3. 밸류에이션·스칼라 | C45: 노란 셀 = 가정. '연결' 표시는 추정 전 분기 수식이 이 셀을 참조한다는 뜻
A46: sc:종가 | C46: 종가 | D46: 455000 | E46: 원 — 네이버 정규장 종가(aik 확정종가 대조 · aik 467,500원)
A47: sc:기준일 | C47: 기준일 | D47: 20261012 | E47: 종가 기준일
A48: sc:COE | C48: COE | D48: 0.09 | E48: 자기자본비용(가정) — TP 적정 PBR = ROE/COE
A49: sc:PER_lo | C49: PER_lo | D49: 10 | E49: PER 밴드 하단(배) — sector_default(레퍼런스 TP_PE PB 예시 10/15/20배; 과거 PER 중위 3.7배가 캡 5~30 밖 — 턴어라운드 초기 TTM EPS 왜곡)
A50: sc:PER_mid | C50: PER_mid | D50: 15 | E50: PER 밴드 중단(배)
A51: sc:PER_hi | C51: PER_hi | D51: 20 | E51: PER 밴드 상단(배)
A52: sc:EPS_Y1가중 | C52: EPS_Y1가중 | D52: 0.5 | E52: 12M fwd EPS = FY(last_actual연도)E × w + FY+1E × (1−w) — 기준 분기 2Q 이면 0.5(가정)
A53: sc:세율 | C53: 세율 | D53: 0.22000094 | E53: 연결 — 법인세 = MAX(세전,0) × 세율(역산, 재현 오차 ≤ 0.05억 · 모델 assumptions 0.22) · 최근 12분기 유효세율 29.8% 가 5~27% 밖; 세전 > 0 분기 중위 31.2% 도 5~27% 밖 → 법정세율 근사 22% 가정
A54: sc:판관비율 | C54: 판관비율 | D54: 0.18873975 | E54: 연결 — 판관비 = 매출액 × 판관비율(역산, 재현 오차 ≤ 0.05억 · 모델 assumptions 0.1887)
A55: sc:지배주주비중 | C55: 지배주주비중 | D55: 1 | E55: 연결 — 지배주주순이익 = 당기순이익 × 비중(역산, 재현 오차 ≤ 0.05억)
A56: sc:이자율_자산 | C56: 이자율_자산 | D56: 0.0043518021 | E56: 연결 — 이자손익 = (전분기 이자발생자산 × 자산이자율 − 전분기 총차입금 × 부채이자율)/4(역산, 재현 오차 ≤ 0.05억 · 모델 assumptions 0.0043)
A57: sc:이자율_부채 | C57: 이자율_부채 | D57: 0.063508668 | E57: 연결 — 같은 수식의 부채 쪽(총차입금 행이 없으면 0)(역산, 재현 오차 ≤ 0.05억 · 모델 assumptions 0.0635)
A58: sc:배당성향 | C58: 배당성향 | D58: 0.0717 | E58: 배당성향(참고 — 모델은 직전 DPS 유지·Q2 지급 가정)
A59: sc:외화순노출_백만$ | C59: 외화순노출_백만$ | E59: 외화 순노출 × Δ기말환율 (외화 시트 방식) — 외화 순노출 미공시(face) → 0 + 표기
A60: sc:헤지비율 | C60: 헤지비율 | E60: sls 없음
A61: sc:헤지환율_약정 | C61: 헤지환율_약정 | E61: sls 없음

Sheet BS연결
B1: (백만원) | C1: 이름: BS연결H | E1: 4Q21 | F1: 2021 | G1: 1Q22 | H1: 2Q22 | I1: 3Q22 | J1: 4Q22 | K1: 2022 | L1: 1Q23 | M1: 2Q23 | N1: 3Q23 | O1: 4Q23 | P1: 2023 | Q1: 1Q24 | R1: 2Q24 | S1: 3Q24 | T1: 4Q24 | U1: 2024 | V1: 1Q25 | W1: 2Q25 | X1: 3Q25 | Y1: 4Q25 | Z1: 2025 | AA1: 1Q26 | AB1: 2Q26 | AC1: 3Q26 | AD1: 4Q26 | AE1: 2026 | AF1: 1Q27 | AG1: 2Q27 | AH1: 3Q27 | AI1: 4Q27 | AJ1: 2027 | AK1: 1Q28 | AL1: 2Q28 | AM1: 3Q28 | AN1: 4Q28 | AO1: 2028
B2: 연결 | D2: fin json(kship_fin.py)
B3: 케이씨씨(연) | C3: UPDATE: 26-10-12 | E3: 1 | F3: 2 | G3: 3 | H3: 4 | I3: 5 | J3: 6 | K3: 7 | L3: 8 | M3: 9 | N3: 10 | O3: 11 | P3: 12 | Q3: 13 | R3: 14 | S3: 15 | T3: 16 | U3: 17 | V3: 18 | W3: 19 | X3: 20 | Y3: 21 | Z3: 22 | AA3: 23 | AB3: 24 | AC3: 25 | AD3: 26 | AE3: 27 | AF3: 28 | AG3: 29 | AH3: 30 | AI3: 31 | AJ3: 32 | AK3: 33 | AL3: 34 | AM3: 35 | AN3: 36 | AO3: 37
B4: Account Code | C4: AccountNAME | E4: 2021.12 | F4: 2021.12A | G4: 2022.03 | H4: 2022.06 | I4: 2022.09 | J4: 2022.12 | K4: 2022.12A | L4: 2023.03 | M4: 2023.06 | N4: 2023.09 | O4: 2023.12 | P4: 2023.12A | Q4: 2024.03 | R4: 2024.06 | S4: 2024.09 | T4: 2024.12 | U4: 2024.12A | V4: 2025.03 | W4: 2025.06 | X4: 2025.09 | Y4: 2025.12 | Z4: 2025.12A | AA4: 2026.03 | AB4: 2026.06 | AC4: 2026.09 | AD4: 2026.12 | AE4: 2026.12A | AF4: 2027.03 | AG4: 2027.06 | AH4: 2027.09 | AI4: 2027.12 | AJ4: 2027.12A | AK4: 2028.03 | AL4: 2028.06 | AM4: 2028.09 | AN4: 2028.12 | AO4: 2028.12A
A5: 1 | C5: 유동자산 | E5: 3668126.4 | F5: 3668126.4 | G5: 4388794.5 | H5: 4604773.5 | I5: 4303363.8 | J5: 4029782.8 | K5: 4029782.8 | L5: 4221561.5 | M5: 4296128.5 | N5: 4348879 | O5: 4178193 | P5: 4178193 | Q5: 4390977.8 | R5: 4398762 | S5: 4372544.2 | T5: 3994488.4 | U5: 3994488.4 | V5: 4495685 | W5: 4012252.1 | X5: 4018869.3 | Y5: 3982829.9 | Z5: 3982829.9 | AA5: 4548827.1 | AB5: 4351935.5
A6: 1 | C6: 현금및현금성자산 | E6: 541200.62 | F6: 541200.62 | G6: 328395.52 | H6: 394154.02 | I6: 467291.37 | J6: 776747.67 | K6: 776747.67 | L6: 830350.62 | M6: 973610.32 | N6: 1029439.4 | O6: 1045142.1 | P6: 1045142.1 | Q6: 1083647.9 | R6: 1072629.7 | S6: 1040909.6 | T6: 501329.76 | U6: 501329.76 | V6: 906545.13 | W6: 781684.86 | X6: 915207.59 | Y6: 1193612.4 | Z6: 1193612.4 | AA6: 1469494.9 | AB6: 1177380.3
A7: 1 | C7: 단기금융상품 | E7: 604744.65 | F7: 604744.65 | G7: 1125967 | H7: 1207028.9 | I7: 722731.82 | J7: 408423.84 | K7: 408423.84 | L7: 488875.35 | M7: 540229.59 | N7: 514967.23 | O7: 509868.88 | P7: 509868.88 | Q7: 548928.53 | R7: 436662.92 | S7: 486318.59 | T7: 510145.13 | U7: 510145.13 | V7: 531205.28 | W7: 374098.57 | X7: 216899.41 | Y7: 36838.55 | Z7: 36838.55 | AA7: 60084.28 | AB7: 25343.85
A8: 1 | C8: 단기금융자산 | E8: 604744.65 | F8: 604744.65 | G8: 1125967 | H8: 1207028.9 | I8: 722731.82 | J8: 408423.84 | K8: 408423.84 | L8: 488875.35 | M8: 540229.59 | N8: 514967.23 | O8: 509868.88 | P8: 509868.88 | Q8: 548928.53 | R8: 436662.92 | S8: 486318.59 | T8: 510145.13 | U8: 510145.13 | V8: 531205.28 | W8: 374098.57 | X8: 216899.41 | Y8: 36838.55 | Z8: 36838.55 | AA8: 60084.28 | AB8: 25343.85
A9: 1 | C9: 매출채권및기타채권 | E9: 1128138.5 | F9: 1128138.5 | G9: 1365742.9 | H9: 1337604.6 | I9: 1349237.7 | J9: 1201308.8 | K9: 1201308.8 | L9: 1251304.2 | M9: 1187458.7 | N9: 1189899.4 | O9: 1129052.8 | P9: 1129052.8 | Q9: 1262422.2 | R9: 1351795.6 | S9: 1287510.7 | T9: 1308739.7 | U9: 1308739.7 | V9: 1395653.1 | W9: 1291995.4 | X9: 1316162.4 | Y9: 1151524.4 | Z9: 1151524.4 | AA9: 1387502 | AB9: 1426533.1
A10: 1 | C10: 선급금 | E10: 21880.21 | F10: 21880.21 | G10: 20911.89 | H10: 26966.86 | I10: 24710.22 | J10: 16748.69 | K10: 16748.69 | L10: 17795.19 | M10: 20965.92 | N10: 16992.43 | O10: 16696.26 | P10: 16696.26 | Q10: 18973.96 | R10: 19135.57 | S10: 15662.25 | T10: 16911.15 | U10: 16911.15 | V10: 15380.8 | W10: 14394.72 | X10: 15964.33 | Y10: 20684.08 | Z10: 20684.08 | AA10: 11462.28 | AB10: 23789.06
A11: 1 | C11: 선급금등 | E11: 21880.21 | F11: 21880.21 | G11: 20911.89 | H11: 26966.86 | I11: 24710.22 | J11: 16748.69 | K11: 16748.69 | L11: 17795.19 | M11: 20965.92 | N11: 16992.43 | O11: 16696.26 | P11: 16696.26 | Q11: 18973.96 | R11: 19135.57 | S11: 15662.25 | T11: 16911.15 | U11: 16911.15 | V11: 15380.8 | W11: 14394.72 | X11: 15964.33 | Y11: 20684.08 | Z11: 20684.08 | AA11: 11462.28 | AB11: 23789.06
A12: 1 | C12: 기타유동자산 | E12: 61566.05 | F12: 61566.05 | G12: 96209.91 | H12: 68073.73 | I12: 74488.96 | J12: 60506.58 | K12: 60506.58 | L12: 59181.06 | M12: 55254.5 | N12: 57264.98 | O12: 61945.71 | P12: 61945.71 | Q12: 54900.67 | R12: 50923.01 | S12: 48941.01 | T12: 67473.09 | U12: 67473.09 | V12: 55718.2 | W12: 47145.6 | X12: 58209.21 | Y12: 67889.43 | Z12: 67889.43 | AA12: 46702.25 | AB12: 62995.36
A13: 1 | C13: 기타유동금융자산 | E13: 2441.16 | F13: 2441.16 | G13: 3064.61 | H13: 3882.13 | I13: 2942.33 | J13: 3839.8 | K13: 3839.8 | L13: 3404.55 | M13: 5060.48 | N13: 60182.83 | O13: 32224.01 | P13: 32224.01 | Q13: 21085.95 | R13: 18838.42 | S13: 16384.87 | T13: 21694.68 | U13: 21694.68 | V13: 3308.78 | W13: 2839.46 | X13: 1445.52 | Y13: 96.7 | Z13: 96.7 | AA13: 95.68 | AB13: 37.51
A14: 1 | C14: 당기법인세자산(선급법인세) | E14: 1131.35 | F14: 1131.35 | G14: 1694 | H14: 1435.97 | I14: 2525.43 | J14: 2855.83 | K14: 2855.83 | L14: 2618.99 | M14: 1256.31 | N14: 858.08 | O14: 959.7 | P14: 959.7 | Q14: 1147.54 | R14: 1253.98 | S14: 3237.56 | T14: 1870.04 | U14: 1870.04 | V14: 1931.28 | W14: 1468.67 | X14: 2716.73 | Y14: 2882.51 | Z14: 2882.51 | AA14: 3208.47 | AB14: 1728.72
A15: 1 | C15: 재고자산 | E15: 1306422 | F15: 1306422 | G15: 1445238.6 | H15: 1570112 | I15: 1661664.2 | J15: 1576100.2 | K15: 1576100.2 | L15: 1585826.8 | M15: 1533258.7 | N15: 1473785 | O15: 1398999.7 | P15: 1398999.7 | Q15: 1418845.1 | R15: 1466658.4 | S15: 1489241.9 | T15: 1583236 | U15: 1583236 | V15: 1601323.2 | W15: 1513019.5 | X15: 1508228.4 | Y15: 1529985.8 | Z15: 1529985.8 | AA15: 1581739.6 | AB15: 1657916.7
A16: 1 | C16: 비유동자산 | E16: 9210736.8 | F16: 9210736.8 | G16: 9030509.2 | H16: 9328258.7 | I16: 9284742.8 | J16: 9088703.5 | K16: 9088703.5 | L16: 9083349.5 | M16: 9108641.7 | N16: 9061670.2 | O16: 9175278.1 | P16: 9175278.1 | Q16: 9712507.6 | R16: 9245830.2 | S16: 9130814.9 | T16: 9114061.7 | U16: 9114061.7 | V16: 10570486 | W16: 11577430 | X16: 12193006 | Y16: 12820730 | Z16: 12820730 | AA16: 13074193 | AB16: 16770864
... A35: 1 | C35: 사채 | E35: 1168017.8 | F35: 1168017.8 | G35: 968354.81 | H35: 1117873.4 | I35: 1118099.2 | J35: 798493.51 | K35: 798493.51 | L35: 798672.52 | M35: 918134.68 | N35: 918321.73 | O35: 748637.26 | P35: 748637.26 | Q35: 1327305 | R35: 1057792.4 | S35: 1058013.4 | T35: 1307469.1 | U35: 1307469.1 | V35: 1561826.9 | W35: 1287383.7 | X35: 1287652.9 | Y35: 2097835.7 | Z35: 2097835.7 | AA35: 2167189.8 | AB35: 2151185.3
A36: 1 | C36: 기타비유동금융부채 | E36: 43512.69 | F36: 43512.69 | G36: 29627.88 | H36: 5566.21 | I36: 1607.17 | J36: 57445.32 | K36: 57445.32 | L36: 31577.61 | M36: 20696.72 | N36: 3749.29 | Y36: 11164.39 | Z36: 11164.39 | AA36: 7518.41 | AB36: 14633.96
A37: 1 | C37: 장기금융부채 | E37: 43512.69 | F37: 43512.69 | G37: 29627.88 | H37: 5566.21 | I37: 1607.17 | J37: 57445.32 | K37: 57445.32 | L37: 31577.61 | M37: 20696.72 | N37: 3749.29 | Y37: 11164.39 | Z37: 11164.39 | AA37: 7518.41 | AB37: 14633.96
A38: 1 | C38: 확정급여부채 | E38: 429025.14 | F38: 429025.14 | G38: 434418.07 | H38: 450907.6 | I38: 478463.69 | J38: 274253.73 | K38: 274253.73 | L38: 297962.49 | M38: 293544.05 | N38: 297047.35 | O38: 356537.68 | P38: 356537.68 | Q38: 372291.58 | R38: 372888.79 | S38: 369268.19 | T38: 366277.72 | U38: 366277.72 | V38: 371287.7 | W38: 367388.72 | X38: 383162.46 | Y38: 349309.9 | Z38: 349309.9 | AA38: 367217.75 | AB38: 373999.49
A39: 1 | C39: 장기충당부채 | E39: 16886.93 | F39: 16886.93 | G39: 17237.78 | H39: 17616.08 | I39: 19202.98 | J39: 14527.3 | K39: 14527.3 | L39: 15566.4 | M39: 26897.75 | N39: 20150.73 | O39: 21640.37 | P39: 21640.37 | Q39: 22140.19 | R39: 22358.91 | S39: 22724.52 | T39: 24331.4 | U39: 24331.4 | V39: 25673.97 | W39: 23374.57 | X39: 23857.48 | Y39: 24880.68 | Z39: 24880.68 | AA39: 26077.86 | AB39: 25560.83
A40: 1 | C40: 이연법인세부채 | E40: 587271.93 | F40: 587271.93 | G40: 554089.62 | H40: 595406.37 | I40: 499683.99 | J40: 448431.11 | K40: 448431.11 | L40: 487002.07 | M40: 504457.57 | N40: 507454.11 | O40: 497063.26 | P40: 497063.26 | Q40: 601509.36 | R40: 580081.85 | S40: 583884.87 | T40: 430851.84 | U40: 430851.84 | V40: 737437.77 | W40: 1081628.8 | X40: 1178925.3 | Y40: 1410256.4 | Z40: 1410256.4 | AA40: 1458153.1 | AB40: 2384318.6
A41: 1 | C41: 부채총계 | E41: 7502796.3 | F41: 7502796.3 | G41: 8061671.4 | H41: 8366463.3 | I41: 8164670.7 | J41: 7567347.8 | K41: 7567347.8 | L41: 7771258.7 | M41: 7879075.7 | N41: 7913369.2 | O41: 7905941.7 | P41: 7905941.7 | Q41: 8261675.1 | R41: 8535877.6 | S41: 8392005.6 | T41: 8069234.7 | U41: 8069234.7 | V41: 8805934.5 | W41: 8520441.4 | X41: 8761128.7 | Y41: 8979073.7 | Z41: 8979073.7 | AA41: 9523275.8 | AB41: 10106056
A42: 1 | C42: 지배주주지분 | E42: 5035301.2 | F42: 5035301.2 | G42: 4970965.3 | H42: 5160875.9 | I42: 4993943.9 | J42: 5117785.1 | K42: 5117785.1 | L42: 5119406.8 | M42: 5156838 | N42: 5179538 | O42: 5177363.2 | P42: 5177363.2 | Q42: 5605468.9 | R42: 5108714.6 | S42: 5111353.5 | T42: 5039315.4 | U42: 5039315.4 | V42: 6260236.2 | W42: 7069241 | X42: 7450746.4 | Y42: 7824485.7 | Z42: 7824485.7 | AA42: 8099744 | AB42: 11016744
A43: 1 | C43: 자본금 | E43: 48084.66 | F43: 48084.66 | G43: 48084.66 | H43: 48084.66 | I43: 48084.66 | J43: 48084.66 | K43: 48084.66 | L43: 48084.66 | M43: 48084.66 | N43: 48084.66 | O43: 48084.66 | P43: 48084.66 | Q43: 48084.66 | R43: 48084.66 | S43: 48084.66 | T43: 48084.66 | U43: 48084.66 | V43: 48084.66 | W43: 48084.66 | X43: 48084.66 | Y43: 48084.66 | Z43: 48084.66 | AA43: 48084.66 | AB43: 48084.66
A44: 1 | C44: 자본잉여금 | E44: 552912.6 | F44: 552912.6 | G44: 552912.6 | H44: 552912.6 | I44: 552912.6 | J44: 552912.6 | K44: 552912.6 | L44: 552912.6 | M44: 552912.6 | N44: 552912.6 | O44: 552912.6 | P44: 552912.6 | Q44: 552912.6 | R44: 349758.89 | S44: 349758.89 | T44: 349758.89 | U44: 349758.89 | V44: 349758.89 | W44: 349758.89 | X44: 349758.89 | Y44: 349758.89 | Z44: 349758.89 | AA44: 313103.99 | AB44: 313103.99
A45: 1 | C45: 기타자본 | E45: -204952.84 | F45: -204952.84 | G45: -286379.5 | H45: -304846.77 | I45: -304846.77 | J45: -304846.77 | K45: -304846.77 | L45: -304846.77 | M45: -304846.77 | N45: -304846.77 | O45: -304846.77 | P45: -304846.77 | Q45: -304846.77 | R45: -504350.31 | S45: -504350.31 | T45: -504350.31 | U45: -504350.31 | V45: -504350.31 | W45: -504350.31 | X45: -504350.31 | Y45: -504350.31 | Z45: -504350.31 | AA45: -504350.31 | AB45: -445944.44
A46: 1 | C46: 기타포괄이익누계액 | E46: -39155.72 | F46: -39155.72 | G46: 17601.15 | H46: 56623.62 | I46: 164890.87 | J46: 23231.82 | K46: 23231.82 | L46: 68771.61 | M46: 15208.9 | N46: -1701.23 | O46: -21227.45 | P46: -21227.45 | Q46: -12456.69 | R46: -73685.65 | S46: -21581.85 | T46: -20214.98 | U46: -20214.98 | V46: 995115.73 | W46: 910874.52 | X46: 971446.89 | Y46: 1004614.4 | Z46: 1004614.4 | AA46: 1165819.1 | AB46: 1243695.2
A47: 1 | C47: 이익잉여금 | E47: 4678412.5 | F47: 4678412.5 | G47: 4638746.4 | H47: 4808101.8 | I47: 4532902.5 | J47: 4798402.8 | K47: 4798402.8 | L47: 4754484.7 | M47: 4845478.7 | N47: 4885088.8 | O47: 4902440.2 | P47: 4902440.2 | Q47: 5321775.1 | R47: 5288907 | S47: 5239442.1 | T47: 5166037.2 | U47: 5166037.2 | V47: 5371627.2 | W47: 6264873.2 | X47: 6585806.3 | Y47: 6926378.1 | Z47: 6926378.1 | AA47: 7077086.6 | AB47: 9857804.6
A48: 1 | C48: 비지배주주지분 | E48: 340765.65 | F48: 340765.65 | G48: 386667 | H48: 405692.9 | I48: 429492.09 | J48: 433353.43 | K48: 433353.43 | L48: 414245.5 | M48: 368856.52 | N48: 317642.01 | O48: 270166.21 | P48: 270166.21 | Q48: 236341.47 | R48: 0 | S48: 0 | V48: 0
A49: 1 | C49: 자본총계 | E49: 5376066.9 | F49: 5376066.9 | G49: 5357632.3 | H49: 5566568.8 | I49: 5423436 | J49: 5551138.5 | K49: 5551138.5 | L49: 5533652.3 | M49: 5525694.6 | N49: 5497180 | O49: 5447529.4 | P49: 5447529.4 | Q49: 5841810.4 | R49: 5108714.6 | S49: 5111353.5 | T49: 5039315.4 | U49: 5039315.4 | V49: 6260236.2 | W49: 7069241 | X49: 7450746.4 | Y49: 7824485.7 | Z49: 7824485.7 | AA49: 8099744 | AB49: 11016744
A50: 1 | C50: 부채와자본총계 | E50: 12878863 | F50: 12878863 | G50: 13419304 | H50: 13933032 | I50: 13588107 | J50: 13118486 | K50: 13118486 | L50: 13304911 | M50: 13404770 | N50: 13410549 | O50: 13353471 | P50: 13353471 | Q50: 14103485 | R50: 13644592 | S50: 13503359 | T50: 13108550 | U50: 13108550 | V50: 15066171 | W50: 15589682 | X50: 16211875 | Y50: 16803559 | Z50: 16803559 | AA50: 17623020 | AB50: 21122800
A51: 1 | C51: 총차입금 | E51: 4588864.1 | F51: 4588864.1 | G51: 5066717.4 | H51: 5369417 | I51: 5176146.9 | J51: 4881670.2 | K51: 4881670.2 | L51: 5096574.5 | M51: 5280827.9 | N51: 5349823.7 | O51: 5150850.2 | P51: 5150850.2 | Q51: 5276565.5 | R51: 5592274.2 | S51: 5516006.9 | T51: 5186962.7 | U51: 5186962.7 | V51: 5642147.7 | W51: 5225879.1 | X51: 5059496.1 | Y51: 5010779.2 | Z51: 5010779.2 | AA51: 5437429.8 | AB51: 5265511.2
A52: 1 | C52: 순차입금 | E52: 3442918.8 | F52: 3442918.8 | G52: 3612354.9 | H52: 3768234.1 | I52: 3986123.7 | J52: 3696498.6 | K52: 3696498.6 | L52: 3777348.6 | M52: 3766988 | N52: 3805417 | O52: 3595839.2 | P52: 3595839.2 | Q52: 3643989.1 | R52: 4082981.6 | S52: 3988778.7 | T52: 4175487.8 | U52: 4175487.8 | V52: 4204397.2 | W52: 4070095.7 | X52: 3927389.1 | Y52: 3780328.2 | Z52: 3780328.2 | AA52: 3907850.6 | AB52: 4062787
A53: 1 | C53: 이자발생자산 | E53: 3821873.1 | F53: 3821873.1 | G53: 3897761.4 | H53: 4214292.1 | I53: 3439378.8 | J53: 3571612.5 | K53: 3571612.5 | L53: 3621406.2 | M53: 3887957.5 | N53: 3860407.7 | O53: 4278876.2 | P53: 4278876.2 | Q53: 4840020.8 | R53: 4557058.9 | S53: 4585312.2 | T53: 3778542.2 | U53: 3778542.2 | V53: 4173497.3 | W53: 5144842.3 | X53: 5662254.3 | Y53: 6689512.5 | Z53: 6689512.5 | AA53: 7068994.3 | AB53: 10418227
A54: 1 | C54: 기타유동금융부채 | O54: 164369.97 | P54: 164369.97 | Q54: 168939.66 | R54: 0 | S54: 0 | X54: 299131.33 | Y54: 275328.61 | Z54: 275328.61 | AA54: 168371.8 | AB54: 136569.19
A55: 1 | C55: 단기금융부채 | O55: 164369.97 | P55: 164369.97 | Q55: 168939.66 | R55: 0 | S55: 0 | X55: 299131.33 | Y55: 275328.61 | Z55: 275328.61 | AA55: 168371.8 | AB55: 136569.19
A56: 1 | C56: 매출액(수익) | E56: 1509740 | G56: 1637578.5 | H56: 1755882.4 | I56: 1740125.2 | J56: 1641207.6 | K56: 6774793.7 | L56: 1564942.8 | M56: 1588344.8 | N56: 1552724.5 | O56: 1582430.5 | P56: 6288442.6 | Q56: 1588371.7 | R56: 1778727.7 | S56: 1634207.7 | T56: 1657455.3 | U56: 6658762.4 | V56: 1599305.3 | W56: 1705264 | X56: 1622832.5 | Y56: 1556417.7 | Z56: 6483819.5 | AA56: 1626399.6 | AB56: 1806019.1
A57: 1 | C57: 매출원가 | E57: 1178077.7 | G57: 1253044.6 | H57: 1341496.8 | I57: 1382013.1 | J57: 1313330.4 | K57: 5289884.9 | L57: 1251543.3 | M57: 1241872.2 | N57: 1223040.4 | O57: 1243487 | P57: 4959942.8 | Q57: 1228576.5 | R57: 1348199.2 | S57: 1195391.8 | T57: 1255874 | U57: 5028041.5 | V57: 1204395.9 | W57: 1267996.2 | X57: 1206254.7 | Y57: 1167703.1 | Z57: 4846349.8 | AA57: 1224311 | AB57: 1348082.2
A58: 1 | C58: 매출총이익 | E58: 331662.29 | G58: 384533.86 | H58: 414385.65 | I58: 358112.1 | J58: 327877.15 | K58: 1484908.8 | L58: 313399.44 | M58: 346472.66 | N58: 329684.19 | O58: 338943.49 | P58: 1328499.8 | Q58: 359795.25 | R58: 430528.47 | S58: 438815.93 | T58: 401581.32 | U58: 1630721 | V58: 394909.4 | W58: 437267.75 | X58: 416577.85 | Y58: 388714.63 | Z58: 1637469.6 | AA58: 402088.56 | AB58: 457936.95
A59: 1 | C59: 판관비 | E59: 257272.17 | G59: 235126.09 | H59: 250152.01 | I59: 261732.55 | J59: 270236.58 | K59: 1017247.2 | L59: 237571.69 | M59: 256088.94 | N59: 241254.64 | O59: 281054.29 | P59: 1015969.6 | Q59: 252888.21 | R59: 289967.54 | S59: 313487.39 | T59: 303259.59 | U59: 1159602.7 | V59: 291465.55 | W59: 296887.06 | X59: 299314.3 | Y59: 322187.61 | Z59: 1209854.5 | AA59: 313960.45 | AB59: 329052.63
A60: 1 | C60: 영업이익 | E60: 74390.13 | G60: 149407.77 | H60: 164233.64 | I60: 96379.55 | J60: 57640.56 | K60: 467661.52 | L60: 75827.75 | M60: 90383.72 | N60: 88429.54 | O60: 57889.19 | P60: 312530.2 | Q60: 106907.04 | R60: 140560.93 | S60: 125328.54 | T60: 98321.73 | U60: 471118.24 | V60: 103443.84 | W60: 140380.69 | X60: 117263.55 | Y60: 66527.03 | Z60: 427615.11 | AA60: 88128.12 | AB60: 128884.32
A61: 1 | C61: 종속기업,공동지배기업및관계기업관련손익 | E61: -52803.61 | G61: 11768.32 | H61: 9700.92 | I61: -49.17 | J61: 3632.95 | K61: 25053.02 | L61: -14433.15 | M61: -4871.72 | N61: -14493.56 | O61: -166504.08 | P61: -200302.51 | Q61: -2633.1 | R61: 65671.25 | S61: 7178 | T61: 2118.68 | U61: 72334.83 | V61: 6099.35 | W61: 2784.63 | X61: -205.02 | Y61: -4864.31 | Z61: 3814.65 | AA61: 6589.4 | AB61: 5423.23
A62: 1 | C62: 지분법관련손익 | E62: -52803.61 | G62: 11768.32 | H62: 9700.92 | I62: -49.17 | J62: 3632.95 | K62: 25053.02 | L62: -14433.15 | M62: -4871.72 | N62: -14493.56 | O62: -166504.08 | P62: -200302.51 | Q62: -2633.1 | R62: 65671.25 | S62: 7178 | T62: 2118.68 | U62: 72334.83 | V62: 6099.35 | W62: 2784.63 | X62: -205.02 | Y62: -4864.31 | Z62: 3814.65 | AA62: 6589.4 | AB62: 5423.23
A63: 1 | C63: 금융손익 | E63: -141725.05 | G63: -77425.14 | H63: 120747.61 | I63: -396921.73 | J63: 50417.7 | K63: -303181.56 | L63: -36760.7 | M63: 43835.55 | N63: -9375.54 | O63: 171390.36 | P63: 169089.67 | Q63: 523045.66 | R63: -197808.06 | S63: -139073.87 | T63: -246624.07 | U63: -60460.34 | V63: -50669.57 | W63: 1129282.9 | X63: 364281.54 | Y63: 861021.84 | Z63: 2303916.7 | AA63: 201322.45 | AB63: 3636399.2
A64: 1 | C64: 금융수익 | E64: 60660.06 | G64: 172654.13 | H64: 232747.28 | I64: 94028.08 | J64: 25075.89 | K64: 524505.38 | L64: 194455.26 | M64: 250334.27 | N64: 107961.58 | O64: 205449.62 | P64: 758200.73 | Q64: 656804.14 | R64: 108580.97 | S64: -25469.22 | T64: 142914.91 | U64: 882830.8 | V64: 179435.72 | W64: 1327922.1 | X64: 542869.95 | Y64: 988843.73 | Z64: 3039071.5 | AA64: 562422.72 | AB64: 3764282.9
A65: 1 | C65: 금융비용 | E65: 202385.1 | G65: 250079.27 | H65: 111999.67 | I65: 490949.81 | J65: -25341.8 | K65: 827686.95 | L65: 231215.96 | M65: 206498.72 | N65: 117337.12 | O65: 34059.26 | P65: 589111.06 | Q65: 133758.48 | R65: 306389.03 | S65: 113604.65 | T65: 389538.98 | U65: 943291.14 | V65: 230105.29 | W65: 198639.25 | X65: 178588.41 | Y65: 127821.89 | Z65: 735154.84 | AA65: 361100.27 | AB65: 127883.72
A66: 1 | C66: 기타영업외손익 | E66: -108942.89 | G66: 1084.84 | H66: -14981.52 | I66: -2537.48 | J66: -61144.89 | K66: -77579.05 | L66: 3451.36 | M66: -10984.08 | N66: 407.65 | O66: -29756.53 | P66: -36881.6 | Q66: -257.94 | R66: -1097.36 | S66: -533.25 | T66: -11235.54 | U66: -13124.09 | V66: 16521.8 | W66: -5679.55 | X66: -1951.29 | Y66: -355408.02 | Z66: -346517.06 | AA66: 16442.05 | AB66: -11356.25
A67: 1 | C67: 기타영업외수익 | E67: 12171.04 | G67: 25510.56 | H67: 9367.77 | I67: 13187.44 | J67: 14604.47 | K67: 62670.24 | L67: 30735.66 | M67: 14801.95 | N67: 10562.11 | O67: 7375.83 | P67: 63475.55 | Q67: 9612.6 | R67: 11687.35 | S67: 9202.83 | T67: 12298.98 | U67: 42801.76 | V67: 44443.33 | W67: 11915.21 | X67: 10059.25 | Y67: 80021.19 | Z67: 146438.98 | AA67: 28958.96 | AB67: 14305.05
... A74: 1 | C74: (지배주주지분)당기순이익 | E74: -184616.89 | G74: 6580.39 | H74: 169357.94 | I74: -268008.68 | J74: 125933.34 | K74: 33862.99 | L74: 8136.88 | M74: 90992.96 | N74: 46964.03 | O74: 66568.91 | P74: 212662.78 | Q74: 472184.45 | R74: -32840.88 | S74: -42307.65 | T74: -86467.88 | U74: 310568.04 | V74: 44050.09 | W74: 893270.72 | X74: 326338.46 | Y74: 274837.01 | Z74: 1538496.3 | AA74: 216956.9 | AB74: 2839157.2
A75: 1 | C75: (비지배주주지분)당기순이익 | E75: -47564.22 | G75: 25616.91 | H75: 12841.39 | I75: 2667.33 | J75: -46326.96 | K75: -5201.33 | L75: -23588.9 | M75: -23669.08 | N75: -35726.07 | O75: -37176.12 | P75: -120160.17 | Q75: -17273.52 | R75: 0 | S75: 0 | T75: 0 | U75: -17273.52 | V75: 0
A76: 1 | C76: 이자수익 | G76: 1243.58 | H76: 1287.06 | I76: 2315.89 | J76: 5753.51 | K76: 10600.04 | L76: 6824.39 | M76: 7998.41 | N76: 9053.59 | O76: 9749.05 | P76: 33625.44 | Q76: 9658.65 | R76: 9246.04 | S76: 7984.59 | T76: 9140.56 | U76: 36029.84 | V76: 4696.69 | W76: 5184 | X76: 6840.08 | Y76: 6399.41 | Z76: 23120.18 | AA76: 9435.26 | AB76: 9730.05
A77: 1 | C77: 배당금수익 | G77: 76131.39 | H77: 143.99 | I77: 604.63 | J77: 7.94 | K77: 76887.95 | L77: 43826.68 | M77: 0 | N77: 458.48 | O77: 0 | P77: 44285.16 | Q77: 48061.81 | R77: 0 | S77: 458.48 | T77: 0 | U77: 48520.29 | V77: 62913.24 | W77: 0 | X77: 9216.45 | Y77: 110.77 | Z77: 72240.46 | AA77: 78278.22 | AB77: 475.31
A78: 1 | C78: 이자비용 | G78: 35914.99 | H78: 45070.25 | I78: 47540.95 | J78: 49805.16 | K78: 178331.35 | L78: 51779.3 | M78: 73501.45 | N78: 62995.28 | O78: 66368.49 | P78: 254644.52 | Q78: 66011.17 | R78: 92351.54 | S78: 94206.83 | T78: 95237.01 | U78: 347806.55 | V78: 78864.29 | W78: 78934.93 | X78: 90252.5 | Y78: 91793.28 | Z78: 339845 | AA78: 72288.52 | AB78: 75403.96
A79: 1 | C79: 외환차익 | G79: 18645.12 | H79: 37520.7 | I79: 44645.99 | J79: 36391.16 | K79: 137202.97 | L79: 26667.8 | M79: 26381.53 | N79: 19835.6 | O79: 25749.15 | P79: 98634.08 | Q79: 28985.2 | R79: 29021.28 | S79: 14401.43 | T79: 66663.8 | U79: 139071.71 | V79: 15900.6 | W79: 38399.63 | X79: 25574.32 | Y79: 33953.29 | Z79: 113827.84 | AA79: 21180.12 | AB79: 42412.63
A80: 1 | C80: 외환차손 | G80: 14682.41 | H80: 23109.87 | I80: 25429 | J80: 39700.82 | K80: 102922.1 | L80: 29261.05 | M80: 20398.24 | N80: 16061.95 | O80: 17418.38 | P80: 83139.62 | Q80: 11995.86 | R80: 10360.83 | S80: 23805.76 | T80: 16623.5 | U80: 62785.95 | V80: 19009.53 | W80: 35308.93 | X80: 31992.77 | Y80: 10033.54 | Z80: 96344.77 | AA80: 11180.82 | AB80: 18254.8
A81: 1 | C81: 외화환산이익 | G81: 51609.49 | H81: 25151.02 | I81: 10592 | J81: -47352.59 | K81: 39999.92 | L81: 38497.85 | M81: 61106.82 | N81: 46830.42 | O81: -106124.03 | P81: 40311.06 | Q81: 45192.81 | R81: 53139.72 | S81: -65314.42 | T81: 82531.74 | U81: 115549.85 | V81: 37598.45 | W81: 34797.71 | X81: -4647.71 | Y81: 13358.45 | Z81: 81106.9 | AA81: 68669.38 | AB81: 3281.19
A82: 1 | C82: 외화환산손실 | G82: 53177.18 | H82: 21345.24 | I82: 17103.1 | J82: -7234.39 | K82: 84391.13 | L82: 51826.15 | M82: 57681.44 | N82: 37136.92 | O82: -69979.13 | P82: 76665.38 | Q82: 34257.71 | R82: 38852.34 | S82: -11325.64 | T82: 28984.04 | U82: 90768.45 | V82: 49263.89 | W82: 79895.01 | X82: -18387.65 | Y82: 36312.17 | Z82: 147083.42 | AA82: 85101.69 | AB82: 27940.25
A83: 1 | C83: 파생상품이익 | G83: 15339.88 | H83: 13053.82 | I83: 16582.84 | J83: -19179.86 | K83: 25796.68 | L83: 31822.83 | M83: 19689.76 | N83: 21970.38 | O83: -47550.93 | P83: 25932.04 | Q83: 6756.51 | R83: 9901.81 | S83: -65.06 | T83: 6212.8 | U83: 22806.06 | V83: 5394.59 | W83: 1069.6 | X83: 5330.21 | Y83: 5064.25 | Z83: 16858.65 | AA83: 122157.76 | AB83: 51127.49
A84: 1 | C84: 파생상품손실 | G84: 2415.93 | H84: 1204.86 | I84: 1148.32 | J84: 38446.14 | K84: 43215.25 | L84: 3456.95 | M84: 470.21 | N84: 764.04 | O84: 112308.6 | P84: 116999.8 | Q84: 5403.71 | R84: 5059.23 | S84: 2882 | T84: 905.11 | U84: 14250.05 | V84: 1492.13 | W84: 163.96 | X84: 73656.4 | Y84: -19085.1 | Z84: 56227.39 | AA84: 13246.43 | AB84: 5429.36
A85: 1 | C85: 이자손익 | G85: -34671.41 | H85: -43783.19 | I85: -45225.06 | J85: -44051.65 | K85: -167731.31 | L85: -44954.91 | M85: -65503.04 | N85: -53941.69 | O85: -56619.44 | P85: -221019.08 | Q85: -56352.52 | R85: -83105.5 | S85: -86222.24 | T85: -86096.45 | U85: -311776.71 | V85: -74167.6 | W85: -73750.93 | X85: -83412.42 | Y85: -85393.87 | Z85: -316724.82 | AA85: -62853.26 | AB85: -65673.91
A86: 1 | C86: 중단사업이익 | AB86: -3631.75
A87: 1 | C87: 영업활동으로인한현금흐름 | E87: 189767.52 | G87: -76357.97 | H87: 36313.96 | I87: 206935.87 | J87: 217674.51 | K87: 384566.37 | L87: 19425.33 | M87: 265160.35 | N87: 176899.91 | O87: 326780.74 | P87: 788266.33 | Q87: 113737.76 | R87: 209889 | S87: 134088.68 | T87: 139085.85 | U87: 596801.29 | V87: 109138.48 | W87: 167174.14 | X87: 135288.72 | Y87: 377876.14 | Z87: 789477.48 | AA87: 85181.96 | AB87: 30910.52
A88: 1 | C88: 감가상각비 | E88: 7231.1 | G88: 6904.18 | H88: 6495.89 | I88: 6792.9 | J88: 7437.76 | K88: 27630.73 | L88: 7069.9 | M88: 7034.24 | N88: 7209.64 | O88: 10742.84 | P88: 32056.62 | Q88: 7059.71 | R88: 7315.32 | S88: 7351.83 | T88: 6808.32 | U88: 28535.18 | V88: 103182.77 | W88: 97615.25 | X88: -177546.86 | Y88: 386321.79 | Z88: 409572.95 | AA88: 93709.35 | AB88: 91886.07
A89: 1 | C89: 무형자산상각비 | E89: 10316.76 | G89: 9633.33 | H89: 10783.43 | I89: 11943.51 | J89: 11017.5 | K89: 43377.77 | L89: 15455.79 | M89: 11241.46 | N89: 11390.85 | O89: 8506.49 | P89: 46594.59 | Q89: 12560.41 | R89: 11918.19 | S89: 11597.57 | T89: 12238.65 | U89: 48314.82 | V89: 12507.98 | W89: 12137.41 | X89: 11921.41 | Y89: 12821.84 | Z89: 49388.64 | AA89: 11707.12 | AB89: 12427.34
A90: 1 | C90: 법인세납부(CF) | E90: 59809.67 | G90: -51434.55 | H90: -51879.03 | I90: -54912.15 | J90: -15171.01 | K90: -173396.74 | L90: -52806.03 | M90: -34801.84 | N90: -29351.47 | O90: -33724.33 | P90: -150683.67 | Q90: -25539.05 | R90: -41834.59 | S90: -37308.76 | T90: -28225.56 | U90: -132907.96 | V90: -96171.84 | W90: -83723.16 | X90: -53013.38 | Y90: -44772.23 | Z90: -277680.61 | AA90: -61617.87 | AB90: -9135.62
A91: 1 | C91: 투자활동으로인한현금흐름 | E91: 390031.95 | G91: -447113.88 | H91: -95715.22 | I91: 401282.92 | J91: 177631.35 | K91: 36085.17 | L91: -128460.36 | M91: -83739.69 | N91: -89760.59 | O91: -53380.52 | P91: -355341.16 | Q91: -72833.18 | R91: 507010.91 | S91: -105491.96 | T91: -47148.44 | U91: 281537.33 | V91: -89288.97 | W91: 146540.07 | X91: 105710.03 | Y91: 106421.83 | Z91: 269382.96 | AA91: -109480.52 | AB91: 67983.59
A92: 1 | C92: 유형자산의증가 | E92: 102819.66 | G92: 72229.7 | H92: 87111.85 | I92: 101693.09 | J92: 123706.92 | K92: 384741.56 | L92: 114720.08 | M92: 70988.73 | N92: 125619.7 | O92: 67680.85 | P92: 379009.36 | Q92: 55864.07 | R92: 72825.24 | S92: 64949.2 | T92: 64081.33 | U92: 257719.84 | V92: 91179.11 | W92: 46925.54 | X92: 73752.26 | Y92: 108048.61 | Z92: 319905.52 | AA92: 94238.32 | AB92: 83596.02
A93: 1 | C93: CAPEX | E93: 104133.59 | G93: 72627.46 | H93: 89907.98 | I93: 105056.71 | J93: 125439.45 | K93: 393031.6 | L93: 120787.53 | M93: 73053.43 | N93: 126554.27 | O93: 69451.98 | P93: 389847.21 | Q93: 57157.04 | R93: 74065.75 | S93: 65508.53 | T93: 68269.3 | U93: 265000.62 | V93: 92403.92 | W93: 48155.14 | X93: 75674.07 | Y93: 114486.52 | Z93: 330719.65 | AA93: 95027.01 | AB93: 84402.91
A94: 1 | C94: 무형자산의증가 | E94: 1313.93 | G94: 397.76 | H94: 2796.13 | I94: 3363.62 | J94: 1732.53 | K94: 8290.04 | L94: 6067.45 | M94: 2064.7 | N94: 934.57 | O94: 1771.13 | P94: 10837.85 | Q94: 1292.97 | R94: 1240.51 | S94: 559.33 | T94: 4187.97 | U94: 7280.78 | V94: 1224.81 | W94: 1229.6 | X94: 1921.81 | Y94: 6437.91 | Z94: 10814.13 | AA94: 788.69 | AB94: 806.89
A95: 1 | C95: 유형자산의감소 | E95: 806.04 | G95: 705.93 | H95: 2943.72 | I95: 508.07 | J95: 2019.59 | K95: 6177.31 | L95: 45146.72 | N95: 8482.85 | Q95: 788.05 | R95: 820.57 | S95: 1244.14 | T95: 4274.97 | U95: 7127.73 | V95: 336.63 | W95: 1113.85 | X95: 5295.68 | Y95: 25821.38 | Z95: 32567.54 | AA95: 1031.43 | AB95: 451.46
A96: 1 | C96: 무형자산의감소 | E96: 0 | G96: 0.22 | H96: 2150 | I96: 0 | J96: 0 | K96: 2150.22 | N96: 0.73 | O96: 8.32 | S96: 3 | T96: 5.84 | V96: 92.25 | X96: 208.14 | Y96: 75937.04 | AA96: 0.01 | AB96: 0.49
A97: 1 | C97: 이자수취(CF) | E97: -732.52 | G97: 530.49 | H97: 729.63 | I97: 1381.32 | J97: 3996.46 | K97: 6637.9 | L97: 9399.7 | M97: 7308.47 | N97: 8080.09 | O97: 10292.59 | P97: 35080.85 | Q97: 8656.63 | R97: 7100 | S97: 6164.48 | T97: 7190.6 | U97: 29111.71 | V97: 1182.95 | W97: 2246.77 | X97: 17202.97 | Y97: 3940.35 | Z97: 24573.04 | AA97: 5327.72 | AB97: 14843.15
A98: 1 | C98: 배당금수취(CF) | E98: 90.22 | G98: 9.24 | H98: 77797.63 | I98: 612.56 | J98: 0 | K98: 78419.43 | L98: 143.5 | M98: 44983.33 | N98: 458.48 | O98: 0 | P98: 45585.31 | Q98: 143.5 | R98: 126861.47 | S98: 458.48 | T98: 7751.17 | U98: 135214.62 | V98: 205 | W98: 64147 | X98: 9216.45 | Y98: 110.77 | Z98: 73679.22 | AA98: 205 | AB98: 91422.65
A99: 1 | C99: 재무활동으로인한현금흐름 | E99: -540076.34 | G99: 300042.19 | H99: 51526.02 | I99: -495251.75 | J99: -40442.19 | K99: -184125.73 | L99: 147518.35 | M99: -26619.29 | N99: -44782.37 | O99: -237858.81 | P99: -161742.12 | Q99: -19793.14 | R99: -731808.19 | S99: -44825.63 | T99: -657630.63 | U99: -1454057.6 | V99: 383428.87 | W99: -417154.8 | X99: -128890.42 | Y99: -199765.2 | Z99: -362381.55 | AA99: 256723.4 | AB99: -388537.8
A100: 1 | C100: 장기차입금의증가 | E100: 0 | G100: 371564.16 | H100: 0 | I100: 0 | J100: 0 | K100: 371564.16 | L100: 2154454.6 | M100: 32749.71 | N100: 9036.15 | S100: 4304.06 | V100: 100000 | W100: 100168 | X100: 0 | Y100: 0 | Z100: 200168
A101: 1 | C101: 사채의증가 | E101: 249261.26 | I101: 0 | J101: 0 | N101: 0 | O101: 0 | Q101: 578380.44 | R101: 0 | S101: 0 | T101: 299133.46 | U101: 877513.9 | V101: 398851.08 | W101: 0 | X101: 885072.27 | Y101: 945728.41 | Z101: 2229651.8 | AA101: 398861.36 | AB101: 0
A102: 1 | C102: 유동성장기부채의감소 | E102: 2482.56 | G102: 2522.89 | H102: 82628.41 | I102: 102778.2 | J102: 6160.89 | K102: 194090.39 | L102: 283.95 | M102: 3073.77 | N102: 8480.96 | Q102: 402822.96 | R102: 41594.42 | S102: 7193.09 | T102: 102606.24 | U102: 554216.71 | V102: 141407.31 | W102: 2247.14 | X102: 2937.79 | Y102: 12148.98 | Z102: 158741.22
A103: 1 | C103: 사채의감소 | E103: 280000 | L103: 200000 | M103: 150000 | N103: 0 | O103: 320000 | P103: 670000 | S103: 0 | T103: 170000 | X103: 0 | Y103: 50000 | AA103: 145000 | AB103: 275000
A104: 1 | C104: 리스부채의상환 | E104: 6519.81 | G104: 6289.61 | H104: 6144.73 | I104: 6579.13 | J104: 6539.68 | K104: 25553.15 | L104: 6312.66 | M104: 10488.22 | N104: 8313.53 | O104: 9634.78 | P104: 34749.19 | Q104: 8229.38 | R104: 8705.33 | S104: 8786.16 | T104: 8192.6 | U104: 33913.47 | V104: 9113.86 | W104: 8755.97 | X104: 8945.84 | Y104: 11242 | Z104: 38057.67 | AA104: 10304.71 | AB104: 9825.94
A105: 1 | C105: 이자지급(CF) | E105: -36812.03 | G105: -44471.1 | H105: -36900.94 | I105: -40517.01 | J105: -46861.4 | K105: -168750.45 | L105: -48830.07 | M105: -66047.4 | N105: -59192.81 | O105: -70323.56 | P105: -244393.84 | Q105: -50542.72 | R105: -85058.65 | S105: -85128.08 | T105: -78992.93 | U105: -299722.38 | V105: -72092.56 | W105: -74337.88 | X105: -47366.11 | Y105: -43950.96 | Z105: -237747.51 | AA105: -50624.16 | AB105: -46810.71
A106: 1 | C106: 배당금지급 | E106: 0 | I106: 7354.17 | J106: 0 | N106: 7354.17 | O106: 0 | S106: 7354.17 | T106: 0 | X106: 7354.17 | Y106: 0
A107: 1 | C107: 현금및현금성자산의증감 | E107: 39723.13 | G107: -223429.66 | H107: -7875.24 | I107: 112967.04 | J107: 354863.67 | K107: 236525.81 | L107: 38483.32 | M107: 154801.38 | N107: 42356.94 | O107: 35541.42 | P107: 271183.06 | Q107: 21111.44 | R107: -14908.28 | S107: -16228.9 | T107: -565693.23 | U107: -575718.97 | V107: 403278.38 | W107: -103440.58 | X107: 112108.32 | Y107: 284532.77 | Z107: 696478.89 | AA107: 232424.84 | AB107: -289643.7
A108: 1 | C108: 기말현금및현금성자산 | E108: 37910.82 | G108: 328395.52 | H108: 65758.5 | I108: 73137.35 | J108: 309456.3 | K108: 776747.67 | L108: 830350.62 | M108: 143259.7 | N108: 55829.09 | O108: 15702.7 | P108: 1045142.1 | Q108: 1083647.9 | R108: -11018.16 | S108: -31720.07 | T108: -539579.86 | U108: 501329.76 | V108: 906545.13 | W108: -124860.27 | X108: 133522.73 | Y108: 278404.85 | Z108: 1193612.4 | AA108: 1469494.9 | AB108: -292114.55
A109: 1 | C109: 자기주식의취득 | G109: 81426.66 | H109: 18467.27 | I109: 0 | J109: 0 | K109: 99893.93
A110: 1 | C110: 장기차입금의감소 | L110: 2106067.6 | M110: 71292.68 | O110: 6333.5 | S110: 0 | T110: 545592 | X110: 958481.46 | Y110: 787297.34

Sheet BS별도
B1: (백만원) | C1: 이름: BS별도H | E1: 4Q21 | F1: 2021 | G1: 1Q22 | H1: 2Q22 | I1: 3Q22 | J1: 4Q22 | K1: 2022 | L1: 1Q23 | M1: 2Q23 | N1: 3Q23 | O1: 4Q23 | P1: 2023 | Q1: 1Q24 | R1: 2Q24 | S1: 3Q24 | T1: 4Q24 | U1: 2024 | V1: 1Q25 | W1: 2Q25 | X1: 3Q25 | Y1: 4Q25 | Z1: 2025 | AA1: 1Q26 | AB1: 2Q26 | AC1: 3Q26 | AD1: 4Q26 | AE1: 2026 | AF1: 1Q27 | AG1: 2Q27 | AH1: 3Q27 | AI1: 4Q27 | AJ1: 2027 | AK1: 1Q28 | AL1: 2Q28 | AM1: 3Q28 | AN1: 4Q28 | AO1: 2028
B2: 별도 | D2: fin json(kship_fin.py)
B3: 케이씨씨(별) | C3: UPDATE: 26-10-12 | E3: 1 | F3: 2 | G3: 3 | H3: 4 | I3: 5 | J3: 6 | K3: 7 | L3: 8 | M3: 9 | N3: 10 | O3: 11 | P3: 12 | Q3: 13 | R3: 14 | S3: 15 | T3: 16 | U3: 17 | V3: 18 | W3: 19 | X3: 20 | Y3: 21 | Z3: 22 | AA3: 23 | AB3: 24 | AC3: 25 | AD3: 26 | AE3: 27 | AF3: 28 | AG3: 29 | AH3: 30 | AI3: 31 | AJ3: 32 | AK3: 33 | AL3: 34 | AM3: 35 | AN3: 36 | AO3: 37
B4: Account Code | C4: AccountNAME | E4: 2021.12 | F4: 2021.12A | G4: 2022.03 | H4: 2022.06 | I4: 2022.09 | J4: 2022.12 | K4: 2022.12A | L4: 2023.03 | M4: 2023.06 | N4: 2023.09 | O4: 2023.12 | P4: 2023.12A | Q4: 2024.03 | R4: 2024.06 | S4: 2024.09 | T4: 2024.12 | U4: 2024.12A | V4: 2025.03 | W4: 2025.06 | X4: 2025.09 | Y4: 2025.12 | Z4: 2025.12A | AA4: 2026.03 | AB4: 2026.06 | AC4: 2026.09 | AD4: 2026.12 | AE4: 2026.12A | AF4: 2027.03 | AG4: 2027.06 | AH4: 2027.09 | AI4: 2027.12 | AJ4: 2027.12A | AK4: 2028.03 | AL4: 2028.06 | AM4: 2028.09 | AN4: 2028.12 | AO4: 2028.12A
A5: 1 | C5: 유동자산 | E5: 1704546.3 | F5: 1704546.3 | G5: 2299643.5 | H5: 2395983.2 | I5: 2005126 | J5: 1971791.8 | K5: 1971791.8 | L5: 2158317.3 | M5: 2340728.5 | N5: 2401533.1 | O5: 2349590.5 | P5: 2349590.5 | Q5: 2448592.7 | R5: 2420739.4 | S5: 2467466.7 | T5: 1958625.2 | U5: 1958625.2 | V5: 2401953.5 | W5: 2041442.6 | X5: 2021694.7 | Y5: 1975270.4 | Z5: 1975270.4 | AA5: 2417429.1 | AB5: 1946447
A6: 1 | C6: 현금및현금성자산 | E6: 182739.8 | F6: 182739.8 | G6: 153638.74 | H6: 158022.61 | I6: 227730.27 | J6: 501584.85 | K6: 501584.85 | L6: 555886.47 | M6: 689533.03 | N6: 732684.37 | O6: 724453.17 | P6: 724453.17 | Q6: 730153.27 | R6: 794183.36 | S6: 855245.7 | T6: 276042.67 | U6: 276042.67 | V6: 699444.78 | W6: 561965.16 | X6: 684640.21 | Y6: 886036.62 | Z6: 886036.62 | AA6: 1218978.3 | AB6: 793299.59
A7: 1 | C7: 단기금융상품 | E7: 592331.14 | F7: 592331.14 | G7: 1101441.3 | H7: 1188377.8 | I7: 702058.35 | J7: 390186.83 | K7: 390186.83 | L7: 474572.4 | M7: 518738.49 | N7: 490438.22 | O7: 483239.54 | P7: 483239.54 | Q7: 526750.73 | R7: 415696.81 | S7: 461144.03 | T7: 481477.35 | U7: 481477.35 | V7: 509061.06 | W7: 349562.92 | X7: 194776.67 | Y7: 8501.55 | Z7: 8501.55 | AA7: 29584.01
A8: 1 | C8: 단기금융자산 | E8: 592331.14 | F8: 592331.14 | G8: 1101441.3 | H8: 1188377.8 | I8: 702058.35 | J8: 390186.83 | K8: 390186.83 | L8: 474572.4 | M8: 518738.49 | N8: 490438.22 | O8: 483239.54 | P8: 483239.54 | Q8: 526750.73 | R8: 415696.81 | S8: 461144.03 | T8: 481477.35 | U8: 481477.35 | V8: 509061.06 | W8: 349562.92 | X8: 194776.67 | Y8: 8501.55 | Z8: 8501.55 | AA8: 29584.01
A9: 1 | C9: 매출채권및기타채권 | E9: 501805.77 | F9: 501805.77 | G9: 583506.47 | H9: 563766.88 | I9: 584313.78 | J9: 599834.4 | K9: 599834.4 | L9: 633422.24 | M9: 606209.56 | N9: 622336.22 | O9: 598019.1 | P9: 598019.1 | Q9: 644551.23 | R9: 664776.34 | S9: 598688.34 | T9: 622823.1 | U9: 622823.1 | V9: 647886.29 | W9: 617084.63 | X9: 639817.24 | Y9: 566800.48 | Z9: 566800.48 | AA9: 659046.75 | AB9: 637404.65
A10: 1 | C10: 선급금 | E10: 4242.46 | F10: 4242.46 | G10: 4509.98 | H10: 9807.29 | I10: 5648.42 | J10: 4708.45 | K10: 4708.45 | L10: 5190.49 | M10: 6315.52 | N10: 6107.37 | O10: 6777.41 | P10: 6777.41 | Q10: 8053.49 | R10: 5878.91 | S10: 4082.63 | T10: 3795.33 | U10: 3795.33 | V10: 3157.26 | W10: 2966.02 | X10: 2722.44 | Y10: 2736.59 | Z10: 2736.59 | AA10: 1626.35 | AB10: 3171.69
A11: 1 | C11: 선급금등 | E11: 4242.46 | F11: 4242.46 | G11: 4509.98 | H11: 9807.29 | I11: 5648.42 | J11: 4708.45 | K11: 4708.45 | L11: 5190.49 | M11: 6315.52 | N11: 6107.37 | O11: 6777.41 | P11: 6777.41 | Q11: 8053.49 | R11: 5878.91 | S11: 4082.63 | T11: 3795.33 | U11: 3795.33 | V11: 3157.26 | W11: 2966.02 | X11: 2722.44 | Y11: 2736.59 | Z11: 2736.59 | AA11: 1626.35 | AB11: 3171.69
A12: 1 | C12: 기타유동자산 | E12: 14944.86 | F12: 14944.86 | G12: 21138.61 | H12: 24596.28 | I12: 18544.65 | J12: 19104.74 | K12: 19104.74 | L12: 18768.83 | M12: 18451.82 | N12: 16280.14 | O12: 21500.21 | P12: 21500.21 | Q12: 17557.59 | R12: 16353.17 | S12: 10432.9 | T12: 9863.51 | U12: 9863.51 | V12: 9264.79 | W12: 9035.85 | X12: 8027.34 | Y12: 7842.79 | Z12: 7842.79 | AA12: 7381.64 | AB12: 10453.14
A13: 1 | C13: 기타유동금융자산 | E13: 2441.16 | F13: 2441.16 | G13: 3064.61 | H13: 3882.13 | I13: 2942.33 | J13: 3839.8 | K13: 3839.8 | L13: 3404.55 | M13: 5060.48 | N13: 12529.82 | O13: 9768.36 | P13: 9768.36 | Q13: 21085.95 | R13: 18838.42 | S13: 16384.87 | T13: 21688.98 | U13: 21688.98 | V13: 3303.08 | W13: 2833.72 | X13: 1439.78 | Y13: 96.7 | Z13: 96.7 | AA13: 95.68 | AB13: 37.51
A14: 1 | C14: 재고자산 | E14: 387801.47 | F14: 387801.47 | G14: 414371.65 | H14: 434855.46 | I14: 447054.54 | J14: 457241.18 | K14: 457241.18 | L14: 472262.77 | M14: 502735.1 | N14: 504782.22 | O14: 512610.1 | P14: 512610.1 | Q14: 508493.9 | R14: 510891.27 | S14: 525570.91 | T14: 546729.6 | U14: 546729.6 | V14: 532993.45 | W14: 500960.31 | X14: 492993.48 | Y14: 505992.23 | Z14: 505992.23 | AA14: 502342.73 | AB14: 505252.08
A15: 1 | C15: 비유동자산 | E15: 7105826.2 | F15: 7105826.2 | G15: 6832549.8 | H15: 6961802 | I15: 6565494.5 | J15: 6831287.8 | K15: 6831287.8 | L15: 6802872.1 | M15: 6904157.7 | N15: 6915116.8 | O15: 7307682 | P15: 7307682 | Q15: 7904680.6 | R15: 8068423.9 | S15: 8056915.7 | T15: 8340919.6 | U15: 8340919.6 | V15: 9576913.9 | W15: 10814399 | X15: 12283420 | Y15: 13151278 | Z15: 13151278 | AA15: 13218320 | AB15: 17011650
A16: 1 | C16: 장기매출채권및기타채권 | E16: 46770.47 | F16: 46770.47 | G16: 44587.56 | H16: 43302.93 | I16: 42252.85 | J16: 40543.76 | K16: 40543.76 | L16: 879.82 | M16: 59020.73 | N16: 1529.85 | O16: 56418.12 | P16: 56418.12 | Q16: 189737.13 | R16: 194533.88 | S16: 186485.8 | T16: 197910.67 | U16: 197910.67 | V16: 198194.43 | W16: 189236.85 | X16: 37267.64 | Y16: 47834.76 | Z16: 47834.76 | AA16: 47607.35 | AB16: 45822.1
A17: 1 | C17: 기타비유동자산 | E17: 60933.36 | F17: 60933.36 | G17: 53039.26 | H17: 49310.5 | I17: 41197.55 | J17: 75656.75 | K17: 75656.75 | L17: 67797.53 | M17: 66474.25 | N17: 61613.59 | O17: 35849.4 | P17: 35849.4 | Q17: 28820.77 | R17: 31707.54 | S17: 29851.67 | T17: 43891.26 | U17: 43891.26 | V17: 37309.68 | W17: 32392.54 | X17: 30514.03 | Y17: 34851.46 | Z17: 34851.46 | AA17: 27679.67 | AB17: 24313.6
A18: 1 | C18: 장기금융자산 | E18: 2666973.7 | F18: 2666973.7 | G18: 2384359.1 | H18: 2530953.2 | I18: 2134304.4 | J18: 2287109 | K18: 2287109 | L18: 2220664 | M18: 2306180.1 | N18: 2315995.3 | O18: 2723859.5 | P18: 2723859.5 | Q18: 3207437.8 | R18: 3047759.6 | S18: 3058077.3 | T18: 2767066.4 | U18: 2767066.4 | V18: 2735746 | W18: 3989057.9 | X18: 4530146.4 | Y18: 5455561 | Z18: 5455561 | AA18: 5525797.7 | AB18: 9177343.9
A19: 1 | C19: 투자자산 | E19: 4743334.8 | F19: 4743334.8 | G19: 4486239.7 | H19: 4633222.6 | I19: 4238939 | J19: 4429827.2 | K19: 4429827.2 | L19: 4376954.4 | M19: 4473207.4 | N19: 4486013.4 | O19: 4898276.1 | P19: 4898276.1 | Q19: 5386811.5 | R19: 5548754.4 | S19: 5560133.1 | T19: 5846810.2 | U19: 5846810.2 | V19: 5815489.8 | W19: 7085790.2 | X19: 8731562.4 | Y19: 9656976.9 | Z19: 9656976.9 | AA19: 9728218.4 | AB19: 13535848
A20: 1 | C20: 종속기업및관계기업투자 | E20: 2076361.1 | F20: 2076361.1 | G20: 2101880.6 | H20: 2102269.5 | I20: 2104634.6 | J20: 2142718.2 | K20: 2142718.2 | L20: 2156290.4 | M20: 2167027.3 | N20: 2170018 | O20: 2174416.5 | P20: 2174416.5 | Q20: 2179373.8 | R20: 2500994.8 | S20: 2502055.8 | T20: 3079743.8 | U20: 3079743.8 | V20: 3079743.8 | W20: 3096732.3 | X20: 4201416 | Y20: 4201416 | Z20: 4201416 | AA20: 4202420.7 | AB20: 4358503.8
... A32: 1 | C32: 비유동부채 | E32: 2041225.4 | F32: 2041225.4 | G32: 2164830.5 | H32: 2341735.7 | I32: 2250087.4 | J32: 2018562.7 | K32: 2018562.7 | L32: 1495006.5 | M32: 1579191.9 | N32: 1572846.8 | O32: 1358330.7 | P32: 1358330.7 | Q32: 1916095.7 | R32: 2271867.9 | S32: 2269337 | T32: 2373548.5 | U32: 2373548.5 | V32: 2900929.4 | W32: 2959819.9 | X32: 3056512.6 | Y32: 3140683.5 | Z32: 3140683.5 | AA32: 3203626.8 | AB32: 3433354
A33: 1 | C33: 장기차입금 | E33: 434820.79 | F33: 434820.79 | G33: 807010.15 | H33: 809488.33 | I33: 819149.17 | J33: 809051.14 | K33: 809051.14 | L33: 266587.06 | M33: 228037.34 | N33: 227716.38 | O33: 128268.45 | P33: 128268.45 | Q33: 0 | R33: 644589.99 | S33: 644626.5 | T33: 644663.01 | U33: 644663.01 | V33: 644698.74 | W33: 644734.87 | X33: 644771.41 | Y33: 644807.96 | Z33: 644807.96 | AA33: 644843.73
A34: 1 | C34: 사채 | E34: 1168017.8 | F34: 1168017.8 | G34: 968354.81 | H34: 1117873.4 | I34: 1118099.2 | J34: 798493.51 | K34: 798493.51 | L34: 798672.52 | M34: 918134.68 | N34: 918321.73 | O34: 748637.26 | P34: 748637.26 | Q34: 1327305 | R34: 1057792.4 | S34: 1058013.4 | T34: 1307469.1 | U34: 1307469.1 | V34: 1561826.9 | W34: 1287383.7 | X34: 1287652.9 | Y34: 1128051.6 | Z34: 1128051.6 | AA34: 1147519.8 | AB34: 1117780.9
A35: 1 | C35: 기타비유동금융부채 | E35: 18940.58 | F35: 18940.58 | G35: 8621.14 | H35: 5566.21 | I35: 1607.17 | J35: 57445.32 | K35: 57445.32 | L35: 31577.61 | M35: 20696.72 | N35: 3749.29
A36: 1 | C36: 장기금융부채 | E36: 18940.58 | F36: 18940.58 | G36: 8621.14 | H36: 5566.21 | I36: 1607.17 | J36: 57445.32 | K36: 57445.32 | L36: 31577.61 | M36: 20696.72 | N36: 3749.29
A37: 1 | C37: 확정급여부채 | E37: 3662.09 | F37: 3662.09 | G37: 3663.42 | H37: 3583.57 | I37: 3529.66 | J37: 3850.89 | K37: 3850.89 | L37: 4086.22 | M37: 4137.5 | N37: 4312.39 | O37: 5569.62 | P37: 5569.62 | Q37: 5481.84 | R37: 6144.64 | S37: 11966.1 | T37: 7515.15 | U37: 7515.15 | V37: 7468.03 | W37: 9725.97 | X37: 15543.98 | Y37: 9931.4 | Z37: 9931.4 | AA37: 9862.46 | AB37: 9791.24
A38: 1 | C38: 장기충당부채 | E38: 688.12 | F38: 688.12 | G38: 693.27 | H38: 596.18 | I38: 608.09 | J38: 660.39 | K38: 660.39 | L38: 714.93 | M38: 724.29 | N38: 764.59 | O38: 787.65 | P38: 787.65 | Q38: 833.98 | R38: 856.55 | S38: 909.33 | T38: 923.57 | U38: 923.57 | V38: 967.2 | W38: 951.27 | X38: 1001.14 | Y38: 992.6 | Z38: 992.6 | AA38: 1055.97 | AB38: 1038.89
A39: 1 | C39: 이연법인세부채 | E39: 339243.99 | F39: 339243.99 | G39: 299512.84 | H39: 331373.93 | I39: 235605.99 | J39: 273884.26 | K39: 273884.26 | L39: 296835.38 | M39: 318147.33 | N39: 329454.99 | O39: 388026.54 | P39: 388026.54 | Q39: 484101.22 | R39: 464401.31 | S39: 468071.15 | T39: 323425.27 | U39: 323425.27 | V39: 590666.21 | W39: 931221.71 | X39: 1027604.8 | Y39: 1277184.5 | Z39: 1277184.5 | AA39: 1323531.9 | AB39: 2234715.1
A40: 1 | C40: 부채총계 | E40: 3756748.5 | F40: 3756748.5 | G40: 4244930.4 | H40: 4366626.1 | I40: 3867262.8 | J40: 3891107 | K40: 3891107 | L40: 4043873.3 | M40: 4190372.2 | N40: 4171018.5 | O40: 4298986.3 | P40: 4298986.3 | Q40: 4471412.3 | R40: 4587489.5 | S40: 4593214.2 | T40: 4435298.7 | U40: 4435298.7 | V40: 5080349.1 | W40: 5018778.6 | X40: 6113809.3 | Y40: 6272420 | Z40: 6272420 | AA40: 6661480.6 | AB40: 7153718.3
A41: 1 | C41: 자본금 | E41: 48084.66 | F41: 48084.66 | G41: 48084.66 | H41: 48084.66 | I41: 48084.66 | J41: 48084.66 | K41: 48084.66 | L41: 48084.66 | M41: 48084.66 | N41: 48084.66 | O41: 48084.66 | P41: 48084.66 | Q41: 48084.66 | R41: 48084.66 | S41: 48084.66 | T41: 48084.66 | U41: 48084.66 | V41: 48084.66 | W41: 48084.66 | X41: 48084.66 | Y41: 48084.66 | Z41: 48084.66 | AA41: 48084.66 | AB41: 48084.66
A42: 1 | C42: 자본잉여금 | E42: 553070.81 | F42: 553070.81 | G42: 553070.81 | H42: 553070.81 | I42: 553070.81 | J42: 553070.81 | K42: 553070.81 | L42: 553070.81 | M42: 553070.81 | N42: 553070.81 | O42: 553070.81 | P42: 553070.81 | Q42: 553070.81 | R42: 553070.81 | S42: 553070.81 | T42: 553070.81 | U42: 553070.81 | V42: 553070.81 | W42: 553070.81 | X42: 553070.81 | Y42: 553070.81 | Z42: 553070.81 | AA42: 516415.92 | AB42: 516415.92
A43: 1 | C43: 기타자본 | E43: -204952.84 | F43: -204952.84 | G43: -286379.5 | H43: -304846.77 | I43: -304846.77 | J43: -304846.77 | K43: -304846.77 | L43: -304846.77 | M43: -304846.77 | N43: -304846.77 | O43: -304846.77 | P43: -304846.77 | Q43: -304846.77 | R43: -304846.77 | S43: -304846.77 | T43: -304846.77 | U43: -304846.77 | V43: -304846.77 | W43: -304846.77 | X43: -304846.77 | Y43: -304846.77 | Z43: -304846.77 | AA43: -304846.77 | AB43: -246440.9
A44: 1 | C44: 기타포괄이익누계액 | E44: -22922.71 | F44: -22922.71 | G44: -21421.96 | H44: -27875.2 | I44: -31477 | J44: -33244.08 | K44: -33244.08 | L44: -32073.59 | M44: -29984.94 | N44: -31507.91 | O44: -31464.4 | P44: -31464.4 | Q44: -31972.32 | R44: -32214 | S44: -32214 | T44: -27839.89 | U44: -27839.89 | V44: 647600.41 | W44: 652205.16 | X44: 647316.71 | Y44: 628418.07 | Z44: 628418.07 | AA44: 629641.25 | AB44: 634175.67
A45: 1 | C45: 이익잉여금 | E45: 4680344 | F45: 4680344 | G45: 4593908.9 | H45: 4722725.5 | I45: 4438526 | J45: 4648908 | K45: 4648908 | L45: 4653080.9 | M45: 4788190.2 | N45: 4880830.6 | O45: 5093441.9 | P45: 5093441.9 | Q45: 5617524.6 | R45: 5637579 | S45: 5667073.6 | T45: 5595777.3 | U45: 5595777.3 | V45: 5954609.1 | W45: 6888548.9 | X45: 7247679.8 | Y45: 7929402.1 | Z45: 7929402.1 | AA45: 8084973.7 | AB45: 10852144
A46: 1 | C46: 자본총계 | E46: 5053623.9 | F46: 5053623.9 | G46: 4887262.9 | H46: 4991159.1 | I46: 4703357.7 | J46: 4911972.6 | K46: 4911972.6 | L46: 4917316 | M46: 5054514 | N46: 5145631.4 | O46: 5358286.2 | P46: 5358286.2 | Q46: 5881861 | R46: 5901673.7 | S46: 5931168.3 | T46: 5864246.1 | U46: 5864246.1 | V46: 6898518.2 | W46: 7837062.8 | X46: 8191305.2 | Y46: 8854128.9 | Z46: 8854128.9 | AA46: 8974268.7 | AB46: 11804379
A47: 1 | C47: 부채와자본총계 | E47: 8810372.4 | F47: 8810372.4 | G47: 9132193.3 | H47: 9357785.2 | I47: 8570620.5 | J47: 8803079.6 | K47: 8803079.6 | L47: 8961189.3 | M47: 9244886.2 | N47: 9316649.9 | O47: 9657272.5 | P47: 9657272.5 | Q47: 10353273 | R47: 10489163 | S47: 10524382 | T47: 10299545 | U47: 10299545 | V47: 11978867 | W47: 12855841 | X47: 14305114 | Y47: 15126549 | Z47: 15126549 | AA47: 15635749 | AB47: 18958097
A48: 1 | C48: 지배주주지분 | E48: 5053623.9 | F48: 5053623.9 | G48: 4887262.9 | H48: 4991159.1 | I48: 4703357.7 | J48: 4911972.6 | K48: 4911972.6 | L48: 4917316 | M48: 5054514 | N48: 5145631.4 | O48: 5358286.2 | P48: 5358286.2 | Q48: 5881861 | R48: 5901673.7 | S48: 5931168.3 | T48: 5864246.1 | U48: 5864246.1 | V48: 6898518.2 | W48: 7837062.8 | X48: 8191305.2 | Y48: 8854128.9 | Z48: 8854128.9 | AA48: 8974268.7 | AB48: 11804379
... A51: 1 | C51: 이자발생자산 | E51: 3442044.6 | F51: 3442044.6 | G51: 3639439.2 | H51: 3877353.5 | I51: 3064093.1 | J51: 3178880.7 | K51: 3178880.7 | L51: 3251122.9 | M51: 3514451.6 | N51: 3539117.9 | O51: 3931552.2 | P51: 3931552.2 | Q51: 4464341.8 | R51: 4257639.8 | S51: 4374467 | T51: 3524586.5 | U51: 3524586.5 | V51: 3944251.9 | W51: 4900586 | X51: 5409563.3 | Y51: 6350099.2 | Z51: 6350099.2 | AA51: 6774360 | AB51: 9970643.5
A52: 1 | C52: 기타유동금융부채 | O52: 164369.97 | P52: 164369.97 | Q52: 168939.66 | X52: 299131.33 | Y52: 275328.61 | Z52: 275328.61 | AA52: 168371.8 | AB52: 136569.19
A53: 1 | C53: 단기금융부채 | O53: 164369.97 | P53: 164369.97 | Q53: 168939.66 | X53: 299131.33 | Y53: 275328.61 | Z53: 275328.61 | AA53: 168371.8 | AB53: 136569.19
A54: 1 | C54: 매출액(수익) | E54: 630575.28 | G54: 591633.94 | H54: 691108.74 | I54: 685954.18 | J54: 733008.72 | K54: 2701705.6 | L54: 698957.77 | M54: 746470.85 | N54: 755998.44 | O54: 798089.54 | P54: 2999516.6 | Q54: 761600.28 | R54: 855758.96 | S54: 748529.62 | T54: 761041.63 | U54: 3126930.5 | V54: 700063.86 | W54: 782984.14 | X54: 746115.12 | Y54: 706560.75 | Z54: 2935723.9 | AA54: 700342.94 | AB54: 770047.69
A55: 1 | C55: 매출원가 | E55: 507378.36 | G55: 470560.92 | H55: 534116.8 | I55: 543545.48 | J55: 581791.18 | K55: 2130014.4 | L55: 553162.69 | M55: 541461.97 | N55: 546661.5 | O55: 587008.28 | P55: 2228294.4 | Q55: 570438.14 | R55: 638194.87 | S55: 564653.11 | T55: 569674.37 | U55: 2342960.5 | V55: 536699.19 | W55: 594586.73 | X55: 562215.33 | Y55: 535761.05 | Z55: 2229262.3 | AA55: 527331.83 | AB55: 584863.65
A56: 1 | C56: 매출총이익 | E56: 123196.91 | G56: 121073.02 | H56: 156991.94 | I56: 142408.7 | J56: 151217.53 | K56: 571691.19 | L56: 145795.07 | M56: 205008.88 | N56: 209336.93 | O56: 211081.26 | P56: 771222.14 | Q56: 191162.14 | R56: 217564.09 | S56: 183876.51 | T56: 191367.26 | U56: 783970 | V56: 163364.67 | W56: 188397.41 | X56: 183899.79 | Y56: 170799.7 | Z56: 706461.57 | AA56: 173011.11 | AB56: 185184.04
A57: 1 | C57: 판관비 | E57: 103182.21 | G57: 95815.65 | H57: 95848.57 | I57: 90805.56 | J57: 111430.06 | K57: 393899.84 | L57: 94556.38 | M57: 107361.67 | N57: 99067.66 | O57: 124953.6 | P57: 425939.31 | Q57: 102979.56 | R57: 115435 | S57: 107567.69 | T57: 120975.15 | U57: 446957.4 | V57: 101661.53 | W57: 105216.4 | X57: 105672.55 | Y57: 111076.58 | Z57: 423627.06 | AA57: 107374.68 | AB57: 107944.59
A58: 1 | C58: 영업이익 | E58: 20014.71 | G58: 25257.37 | H58: 61143.37 | I58: 51603.13 | J58: 39787.47 | K58: 177791.34 | L58: 51238.69 | M58: 97647.21 | N58: 110269.27 | O58: 86127.67 | P58: 345282.84 | Q58: 88182.58 | R58: 102129.09 | S58: 76308.82 | T58: 70392.11 | U58: 337012.6 | V58: 61703.14 | W58: 83181.02 | X58: 78227.23 | Y58: 59723.1 | Z58: 282834.49 | AA58: 65636.43 | AB58: 77239.45
A59: 1 | C59: 금융손익 | E59: -119146.63 | G59: -56442.96 | H59: 119717.86 | I59: -401686.64 | J59: 118680.8 | K59: -219730.94 | L59: 721.46 | M59: 81318.32 | N59: 17212.47 | O59: 227467.7 | P59: 326719.95 | Q59: 617436.2 | R59: -75179.35 | S59: -36503.12 | T59: -232867.64 | U59: 272886.09 | V59: 17367.57 | W59: 1195591.5 | X59: 397029.7 | Y59: 898787.41 | Z59: 2508776.2 | AA59: 203543.21 | AB59: 3635127.8
A60: 1 | C60: 금융수익 | E60: 20128.86 | G60: 114126.65 | H60: 191875.39 | I60: 70331.97 | J60: 35582.08 | K60: 411916.09 | L60: 145009.78 | M60: 171792.24 | N60: 54776.42 | O60: 275596.59 | P60: 647175.03 | Q60: 687489.22 | R60: 135197.42 | S60: 15993.77 | T60: 73901.48 | U60: 912581.89 | V60: 142894.84 | W60: 1277748.3 | X60: 544299.05 | Y60: 966146.05 | Z60: 2931088.2 | AA60: 510719.78 | AB60: 3730158.8
A61: 1 | C61: 금융비용 | E61: 139275.49 | G61: 170569.61 | H61: 72157.53 | I61: 472018.62 | J61: -83098.73 | K61: 631647.03 | L61: 144288.32 | M61: 90473.92 | N61: 37563.95 | O61: 48128.9 | P61: 320455.09 | Q61: 70053.03 | R61: 210376.77 | S61: 52496.89 | T61: 306769.12 | U61: 639695.81 | V61: 125527.27 | W61: 82156.75 | X61: 147269.35 | Y61: 67358.64 | Z61: 422312.01 | AA61: 307176.57 | AB61: 95030.92
A62: 1 | C62: 기타영업외손익 | E62: 73652.06 | G62: 4743 | H62: 3509.43 | I62: -300.31 | J62: 41906.39 | K62: 49858.51 | L62: 19719.72 | M62: -328.06 | N62: 9078.97 | O62: 4909.24 | P62: 33379.87 | Q62: 7074.07 | R62: 6620.77 | S62: 8801.7 | T62: 5948.41 | U62: 28444.95 | V62: 30044.02 | W62: 800.99 | X62: 10117.81 | Y62: -46210.73 | Z62: -5247.91 | AA62: 19692.88 | AB62: 1388.7
A63: 1 | C63: 기타영업외수익 | E63: 76741.7 | G63: 9238.58 | H63: 12838.18 | I63: 11281.15 | J63: 51720.32 | K63: 85078.23 | L63: 29164.63 | M63: 15711.25 | N63: 10759.17 | O63: 13467.46 | P63: 69102.51 | Q63: 10408.33 | R63: 14634.28 | S63: 11562.7 | T63: 14346.47 | U63: 50951.78 | V63: 43699.35 | W63: 12739.58 | X63: 14372.91 | Y63: 15162.62 | Z63: 85974.46 | AA63: 23348.48 | AB63: 15237.11
A64: 1 | C64: 기타영업외비용 | E64: 3089.64 | G64: 4495.57 | H64: 9328.74 | I64: 11581.46 | J64: 9813.95 | K64: 35219.72 | L64: 9444.91 | M64: 16039.31 | N64: 1680.21 | O64: 8558.22 | P64: 35722.65 | Q64: 3334.25 | R64: 8013.51 | S64: 2760.99 | T64: 8398.07 | U64: 22506.82 | V64: 13655.34 | W64: 11938.59 | X64: 4255.1 | Y64: 61373.35 | Z64: 91222.38 | AA64: 3655.59 | AB64: 13848.41
A65: 1 | C65: 법인세비용차감전계속사업이익 | E65: -25479.86 | G65: -26442.59 | H65: 184370.67 | I65: -350383.82 | J65: 200374.65 | K65: 7918.91 | L65: 71679.87 | M65: 178637.47 | N65: 136560.71 | O65: 318504.6 | P65: 705382.65 | Q65: 712692.84 | R65: 33570.51 | S65: 48607.4 | T65: -156527.12 | U65: 638343.63 | V65: 109114.73 | W65: 1279573.5 | X65: 485374.74 | Y65: 912299.78 | Z65: 2786362.8 | AA65: 288872.52 | AB65: 3713756
... A67: 1 | C67: 계속사업이익 | E67: -10754.59 | G67: -40486.14 | H67: 128816.66 | I67: -276845.36 | J67: 195857.61 | K67: 7342.77 | L67: 55652.12 | M67: 135109.29 | N67: 99994.53 | O67: 250073.51 | P67: 540829.45 | Q67: 575561.94 | R67: 20054.37 | S67: 36848.79 | T67: -61617.96 | U67: 570847.14 | V67: 106653.59 | W67: 933939.82 | X67: 366485.04 | Y67: 657816.33 | Z67: 2064894.8 | AA67: 221852.04 | AB67: 2829207.7
A68: 1 | C68: 중단사업이익 | E68: 284.9 | AB68: -3631.75
A69: 1 | C69: 당기순이익 | E69: -10469.68 | G69: -40486.14 | H69: 128816.66 | I69: -276845.36 | J69: 195857.61 | K69: 7342.77 | L69: 55652.12 | M69: 135109.29 | N69: 99994.53 | O69: 250073.51 | P69: 540829.45 | Q69: 575561.94 | R69: 20054.37 | S69: 36848.79 | T69: -61617.96 | U69: 570847.14 | V69: 106653.59 | W69: 933939.82 | X69: 366485.04 | Y69: 657816.33 | Z69: 2064894.8 | AA69: 221852.04 | AB69: 2825575.9
A70: 1 | C70: 총포괄손익 | E70: -14487.8 | G70: -38985.39 | H70: 122363.42 | I70: -280447.17 | J70: 208614.9 | K70: 11545.76 | L70: 56822.61 | M70: 137197.93 | N70: 98471.56 | O70: 212654.83 | P70: 505146.93 | Q70: 575054.02 | R70: 19812.69 | S70: 36848.79 | T70: -66922.22 | U70: 564793.28 | V70: 782093.89 | W70: 938544.57 | X70: 361596.59 | Y70: 662823.65 | Z70: 2745058.7 | AA70: 223098.26 | AB70: 2830110.3
A71: 1 | C71: (지배주주지분)당기순이익 | E71: -10469.68 | G71: -40486.14 | H71: 128816.66 | I71: -276845.36 | J71: 195857.61 | K71: 7342.77 | L71: 55652.12 | M71: 135109.29 | N71: 99994.53 | O71: 250073.51 | P71: 540829.45 | Q71: 575561.94 | R71: 20054.37 | S71: 36848.79 | T71: -61617.96 | U71: 570847.14 | V71: 106653.59 | W71: 933939.82 | X71: 366485.04 | Y71: 657816.33 | Z71: 2064894.8 | AA71: 221852.04 | AB71: 2825575.9
A72: 1 | C72: 영업활동으로인한현금흐름 | E72: 55262.03 | G72: 40549.7 | H72: 46685.51 | I72: 61101.3 | J72: 46341.16 | K72: 194677.67 | L72: 61146.89 | M72: 142577.1 | N72: 116191.4 | O72: 143487.23 | P72: 463402.62 | Q72: 88103.09 | R72: 145876.06 | S72: 110520.55 | T72: 100878.48 | U72: 445378.18 | V72: 108895.33 | W72: 77750.99 | X72: 68771.97 | Y72: 159471.63 | Z72: 414889.92 | AA72: 86881.58 | AB72: 57074.6
A73: 1 | C73: 감가상각비 | E73: 2700.6 | G73: 1595.29 | H73: 1435.81 | I73: 1521.73 | J73: 1735.28 | K73: 6288.11 | L73: 1747.1 | M73: 1663.29 | N73: 1710.02 | O73: 1927.27 | P73: 7047.68 | Q73: 1870.42 | R73: 2085.98 | S73: 2054.56 | T73: 2096.31 | U73: 8107.27 | V73: 36089.52 | W73: 35970.29 | X73: -65540.87 | Y73: 2177.14 | Z73: 8696.08 | AA73: 30148.76 | AB73: 28325.79
A74: 1 | C74: 무형자산상각비 | E74: 233.61 | G74: 265.79 | H74: 272.01 | I74: 279.46 | J74: 291.47 | K74: 1108.73 | L74: 311.5 | M74: 318.2 | N74: 332.73 | O74: 336.45 | P74: 1298.88 | Q74: 306.78 | R74: 294.28 | S74: 295.32 | T74: 300.54 | U74: 1196.92 | V74: 303.87 | W74: 386.78 | X74: 316.62 | Y74: 223.93 | Z74: 1231.2 | AA74: 219.23 | AB74: 275.37
A75: 1 | C75: 법인세납부(CF) | E75: -2014.92 | G75: -7577.65 | H75: -23116.63 | I75: -24518.95 | J75: -1551.75 | K75: -56764.98 | L75: -1220.77 | M75: -11024.21 | N75: -10666.34 | O75: -12055.52 | P75: -34966.84 | Q75: -3020.52 | R75: -24235.13 | S75: -10295.87 | T75: -10788.77 | U75: -48340.29 | V75: -49833.53 | W75: -60790.76 | X75: -22103.94 | Y75: -20064.1 | Z75: -152792.33 | AA75: -16641.51 | AB75: 12767.88
A76: 1 | C76: 투자활동으로인한현금흐름 | E76: 487807.47 | G76: -403500.26 | H76: -41200.89 | I76: 464642.68 | J76: 246974.87 | K76: 266916.4 | L76: -109839.3 | M76: -46355.64 | N76: -34459.7 | O76: -1837.63 | P76: -192492.27 | Q76: -110680.21 | R76: -259449.17 | S76: -56792.76 | T76: -579304.48 | U76: -1006226.6 | V76: -19778.95 | W76: 190156.65 | X76: -818078.14 | Y76: 178601.86 | Z76: -469098.58 | AA76: -46664.01 | AB76: -43977.87
A77: 1 | C77: 유형자산의증가 | E77: 25443.74 | G77: 30879.31 | H77: 24361.41 | I77: 41142.14 | J77: 49551.38 | K77: 145934.24 | L77: 56905.8 | M77: 50598.74 | N77: 60546.09 | O77: 23978.74 | P77: 192029.37 | Q77: 21543.7 | R77: 30565.81 | S77: 21436.25 | T77: 12580.7 | U77: 86126.46 | V77: 17729.21 | W77: 13172.56 | X77: 17958.43 | Y77: 37379.49 | Z77: 86239.69 | AA77: 30987.63 | AB77: 10565.74
A78: 1 | C78: CAPEX | E78: 26125.17 | G78: 31047.65 | H78: 26553.8 | I78: 41349.35 | J78: 50008.86 | K78: 148959.66 | L78: 57114.96 | M78: 50877.37 | N78: 60733.76 | O78: 24228.55 | P78: 192954.64 | Q78: 21910.92 | R78: 30801.43 | S78: 21646.68 | T78: 12885.41 | U78: 87244.44 | V78: 17953.67 | W78: 13532.35 | X78: 18043.55 | Y78: 37683.66 | Z78: 87213.23 | AA78: 31200.45 | AB78: 10769.98
A79: 1 | C79: 무형자산의증가 | E79: 681.43 | G79: 168.34 | H79: 2192.39 | I79: 207.21 | J79: 457.48 | K79: 3025.42 | L79: 209.16 | M79: 278.63 | N79: 187.67 | O79: 249.81 | P79: 925.27 | Q79: 367.22 | R79: 235.62 | S79: 210.43 | T79: 304.71 | U79: 1117.98 | V79: 224.46 | W79: 359.79 | X79: 85.12 | Y79: 304.17 | Z79: 973.54 | AA79: 212.82 | AB79: 204.24
A80: 1 | C80: 유형자산의감소 | E80: 865.95 | G80: 807.17 | H80: 2850.64 | I80: 361.18 | J80: 1388.14 | K80: 5407.13 | L80: 20736.11 | M80: 6559.39 | N80: 842.54 | O80: 1107.53 | P80: 29245.57 | Q80: 649.33 | R80: 759.27 | S80: 992.29 | T80: 4203.36 | U80: 6604.25 | V80: 251.05 | W80: 1103.02 | X80: 5100.63 | Y80: 25860.7 | Z80: 32315.4 | AA80: 186.35 | AB80: 420.98
A81: 1 | C81: 무형자산의감소 | E81: 0 | G81: 0.22 | H81: 2150 | I81: 0 | J81: 0 | K81: 2150.22 | N81: 0.73 | O81: 0 | T81: 5.85 | V81: 1.15 | W81: 0.24 | X81: 209.09 | Y81: 0 | Z81: 210.48
A82: 1 | C82: 이자수취(CF) | E82: 1987.14 | G82: 311.34 | H82: 395.08 | I82: 961.47 | J82: 3043.58 | K82: 4711.47 | L82: 4350.76 | M82: 5329.17 | N82: 6718.03 | O82: 8378.45 | P82: 24776.41 | Q82: 7188.55 | R82: 7636.26 | S82: 6764.26 | T82: 8165.82 | U82: 29754.89 | V82: 1908.06 | W82: 2777.28 | X82: 15710.58 | Y82: 4136.45 | Z82: 24532.37 | AA82: 4471.73 | AB82: 13438.65
A83: 1 | C83: 배당금수취(CF) | E83: 90.22 | G83: 152.74 | H83: 77654.13 | I83: 612.56 | J83: 0 | K83: 78419.43 | L83: 143.5 | M83: 44983.33 | N83: 458.48 | O83: 0 | P83: 45585.31 | Q83: 72625.92 | R83: 126861.47 | S83: 458.48 | T83: 0 | U83: 199945.87 | V83: 205 | W83: 64147 | X83: 9216.45 | Y83: 110.77 | Z83: 73679.22 | AA83: 205 | AB83: 79820.42
A84: 1 | C84: 재무활동으로인한현금흐름 | E84: -511388.9 | G84: 333582.22 | H84: -972.04 | I84: -462377.9 | J84: 2732.4 | K84: -127035.32 | L84: 97094.24 | M84: 41378.47 | N84: -48064.51 | O84: -137036.1 | P84: -46627.9 | Q84: 21205.85 | R84: 174088.76 | S84: 22366.67 | T84: -109995.62 | U84: 107665.66 | V84: 330986.87 | W84: -388864.99 | X84: 855895.03 | Y84: -130132.8 | Z84: 667884.11 | AA84: 263512.1 | AB84: -425948.17
A85: 1 | C85: 장기차입금의증가 | E85: 0 | G85: 371564.16 | H85: 0 | I85: 0 | J85: 0 | K85: 371564.16 | S85: 0 | T85: 0
A86: 1 | C86: 사채의증가 | E86: 249261.26 | I86: 0 | J86: 0 | N86: 0 | O86: 0 | Q86: 578380.44 | R86: 0 | S86: 0 | T86: 299133.46 | U86: 877513.9 | V86: 398851.08 | W86: 0 | X86: 885072.27 | Y86: 0 | Z86: 1283923.4 | AA86: 398861.36 | AB86: 0
A87: 1 | C87: 유동성장기부채의감소 | E87: 0 | I87: 100000 | J87: 0 | Q87: 400000 | R87: 238682 | S87: 0 | T87: 270000 | U87: 908682 | V87: 137585.7 | W87: 270000 | X87: 0
A88: 1 | C88: 사채의감소 | E88: 280000 | L88: 200000 | M88: 150000 | AA88: 145000 | AB88: 275000
A89: 1 | C89: 리스부채의상환 | E89: 2374.58 | G89: 1374.8 | H89: 1347.65 | I89: 1521.11 | J89: 1564.83 | K89: 5808.39 | L89: 1556.99 | M89: 2004.82 | N89: 1954.1 | O89: 2043.67 | P89: 7559.58 | Q89: 1987.4 | R89: 2218.97 | S89: 2348.56 | T89: 2230 | U89: 8784.93 | V89: 2322.56 | W89: 2314.88 | X89: 2445.55 | Y89: 2327.44 | Z89: 9410.43 | AA89: 2333.97 | AB89: 2110.26
A90: 1 | C90: 이자지급(CF) | E90: -13698.32 | G90: -23797.12 | H90: -12442.16 | I90: -14294.45 | J90: -17833.24 | K90: -68366.97 | L90: -18227.7 | M90: -18946.82 | N90: -22566.28 | O90: -32943.06 | P90: -92683.86 | Q90: -18437.81 | R90: -29567.42 | S90: -29042.57 | T90: -31428.48 | U90: -108476.28 | V90: -30469.07 | W90: -32825.28 | X90: -29441.59 | Y90: -29610.53 | Z90: -122346.47 | AA90: -37883.22 | AB90: -32205.73
A91: 1 | C91: 배당금지급 | E91: 0 | I91: 7354.17 | J91: 0 | N91: 7354.17 | O91: 0 | S91: 7354.17 | T91: 0 | X91: 7354.17 | Y91: 0
A92: 1 | C92: 현금및현금성자산의증감 | E92: 31680.61 | G92: -29368.34 | H92: 4512.58 | I92: 63366.07 | J92: 296048.44 | K92: 334558.75 | L92: 48401.82 | M92: 137599.94 | N92: 33667.19 | O92: 4613.49 | P92: 224282.44 | Q92: -1371.27 | R92: 60515.65 | S92: 76094.46 | T92: -588421.62 | U92: -453182.78 | V92: 420103.25 | W92: -120957.34 | X92: 106588.84 | Y92: 207940.71 | Z92: 613675.46 | AA92: 303729.67 | AB92: -412851.44
A93: 1 | C93: 기말현금및현금성자산 | E93: 30152.04 | G93: 153638.74 | H93: 4383.87 | I93: 69707.66 | J93: 273854.58 | K93: 501584.85 | L93: 555886.47 | M93: 133646.56 | N93: 43151.34 | O93: -8231.2 | P93: 724453.17 | Q93: 730153.27 | R93: 64030.09 | S93: 61062.34 | T93: -579203.03 | U93: 276042.67 | V93: 699444.78 | W93: -137479.62 | X93: 122675.05 | Y93: 201396.41 | Z93: 886036.62 | AA93: 1218978.3 | AB93: -425678.7
A94: 1 | C94: 자기주식의취득 | G94: 81426.66 | H94: 18467.27 | I94: 0 | J94: 0 | K94: 99893.93

Sheet subQ
A1: YQ | C1: subQ 분기 서브모델(억원, U=100) | E1: 4Q21 | F1: 2021 | G1: 1Q22 | H1: 2Q22 | I1: 3Q22 | J1: 4Q22 | K1: 2022 | L1: 1Q23 | M1: 2Q23 | N1: 3Q23 | O1: 4Q23 | P1: 2023 | Q1: 1Q24 | R1: 2Q24 | S1: 3Q24 | T1: 4Q24 | U1: 2024 | V1: 1Q25 | W1: 2Q25 | X1: 3Q25 | Y1: 4Q25 | Z1: 2025 | AA1: 1Q26 | AB1: 2Q26 | AC1: 3Q26 | AD1: 4Q26 | AE1: 2026 | AF1: 1Q27 | AG1: 2Q27 | AH1: 3Q27 | AI1: 4Q27 | AJ1: 2027 | AK1: 1Q28 | AL1: 2Q28 | AM1: 3Q28 | AN1: 4Q28 | AO1: 2028
A2: A=이름(key) B=그룹 C=단위 D=FnGuide 계정명(VLOOKUP 키). 확정=VLOOKUP(BS), 추정=변수 가정 참조
E3: 1 | F3: 2 | G3: 3 | H3: 4 | I3: 5 | J3: 6 | K3: 7 | L3: 8 | M3: 9 | N3: 10 | O3: 11 | P3: 12 | Q3: 13 | R3: 14 | S3: 15 | T3: 16 | U3: 17 | V3: 18 | W3: 19 | X3: 20 | Y3: 21 | Z3: 22 | AA3: 23 | AB3: 24 | AC3: 25 | AD3: 26 | AE3: 27 | AF3: 28 | AG3: 29 | AH3: 30 | AI3: 31 | AJ3: 32 | AK3: 33 | AL3: 34 | AM3: 35 | AN3: 36 | AO3: 37
E4: 2021.12 | F4: 2021.12A | G4: 2022.03 | H4: 2022.06 | I4: 2022.09 | J4: 2022.12 | K4: 2022.12A | L4: 2023.03 | M4: 2023.06 | N4: 2023.09 | O4: 2023.12 | P4: 2023.12A | Q4: 2024.03 | R4: 2024.06 | S4: 2024.09 | T4: 2024.12 | U4: 2024.12A | V4: 2025.03 | W4: 2025.06 | X4: 2025.09 | Y4: 2025.12 | Z4: 2025.12A | AA4: 2026.03 | AB4: 2026.06 | AC4: 2026.09 | AD4: 2026.12 | AE4: 2026.12A | AF4: 2027.03 | AG4: 2027.06 | AH4: 2027.09 | AI4: 2027.12 | AJ4: 2027.12A | AK4: 2028.03 | AL4: 2028.06 | AM4: 2028.09 | AN4: 2028.12 | AO4: 2028.12A
A5: 매출액 | B5: 손익 | C5: 억원 | D5: 매출액(수익) | E5: =IFERROR(VLOOKUP($D5,BS연결,MATCH(E$1,BS연결H,0),0)/100,"") | G5: =IFERROR(VLOOKUP($D5,BS연결,MATCH(G$1,BS연결H,0),0)/100,"") | H5: =IFERROR(VLOOKUP($D5,BS연결,MATCH(H$1,BS연결H,0),0)/100,"") | I5: =IFERROR(VLOOKUP($D5,BS연결,MATCH(I$1,BS연결H,0),0)/100,"") | J5: =IFERROR(VLOOKUP($D5,BS연결,MATCH(J$1,BS연결H,0),0)/100,"") | K5: =IFERROR(VLOOKUP($D5,BS연결,MATCH(K$1,BS연결H,0),0)/100,"") | L5: =IFERROR(VLOOKUP($D5,BS연결,MATCH(L$1,BS연결H,0),0)/100,"") | M5: =IFERROR(VLOOKUP($D5,BS연결,MATCH(M$1,BS연결H,0),0)/100,"") | N5: =IFERROR(VLOOKUP($D5,BS연결,MATCH(N$1,BS연결H,0),0)/100,"") | ... AB5: =IFERROR(VLOOKUP($D5,BS연결,MATCH(AB$1,BS연결H,0),0)/100,"") | AC5: =IFERROR(X5*(1+변수!AC21),"") | AD5: =IFERROR(Y5*(1+변수!AD21),"") | AE5: =SUM(AA5:AD5) | AF5: =IFERROR(AA5*(1+변수!AF21),"") | AG5: =IFERROR(AB5*(1+변수!AG21),"") | AH5: =IFERROR(AC5*(1+변수!AH21),"") | AI5: =IFERROR(AD5*(1+변수!AI21),"") | AJ5: =SUM(AF5:AI5) | AK5: =IFERROR(AF5*(1+변수!AK21),"") | AL5: =IFERROR(AG5*(1+변수!AL21),"") | AM5: =IFERROR(AH5*(1+변수!AM21),"") | AN5: =IFERROR(AI5*(1+변수!AN21),"") | AO5: =SUM(AK5:AN5)
A6: 매출원가 | B6: 손익 | C6: 억원 | D6: 매출원가 | E6: =IFERROR(VLOOKUP($D6,BS연결,MATCH(E$1,BS연결H,0),0)/100,"") | G6: =IFERROR(VLOOKUP($D6,BS연결,MATCH(G$1,BS연결H,0),0)/100,"") | H6: =IFERROR(VLOOKUP($D6,BS연결,MATCH(H$1,BS연결H,0),0)/100,"") | I6: =IFERROR(VLOOKUP($D6,BS연결,MATCH(I$1,BS연결H,0),0)/100,"") | J6: =IFERROR(VLOOKUP($D6,BS연결,MATCH(J$1,BS연결H,0),0)/100,"") | K6: =IFERROR(VLOOKUP($D6,BS연결,MATCH(K$1,BS연결H,0),0)/100,"") | L6: =IFERROR(VLOOKUP($D6,BS연결,MATCH(L$1,BS연결H,0),0)/100,"") | M6: =IFERROR(VLOOKUP($D6,BS연결,MATCH(M$1,BS연결H,0),0)/100,"") | N6: =IFERROR(VLOOKUP($D6,BS연결,MATCH(N$1,BS연결H,0),0)/100,"") | ... AB6: =IFERROR(VLOOKUP($D6,BS연결,MATCH(AB$1,BS연결H,0),0)/100,"") | AC6: =IFERROR(AC5-AC7,"") | AD6: =IFERROR(AD5-AD7,"") | AE6: =SUM(AA6:AD6) | AF6: =IFERROR(AF5-AF7,"") | AG6: =IFERROR(AG5-AG7,"") | AH6: =IFERROR(AH5-AH7,"") | AI6: =IFERROR(AI5-AI7,"") | AJ6: =SUM(AF6:AI6) | AK6: =IFERROR(AK5-AK7,"") | AL6: =IFERROR(AL5-AL7,"") | AM6: =IFERROR(AM5-AM7,"") | AN6: =IFERROR(AN5-AN7,"") | AO6: =SUM(AK6:AN6)
A7: 매출총이익 | B7: 손익 | C7: 억원 | D7: 매출총이익 | E7: =IFERROR(VLOOKUP($D7,BS연결,MATCH(E$1,BS연결H,0),0)/100,"") | G7: =IFERROR(VLOOKUP($D7,BS연결,MATCH(G$1,BS연결H,0),0)/100,"") | H7: =IFERROR(VLOOKUP($D7,BS연결,MATCH(H$1,BS연결H,0),0)/100,"") | I7: =IFERROR(VLOOKUP($D7,BS연결,MATCH(I$1,BS연결H,0),0)/100,"") | J7: =IFERROR(VLOOKUP($D7,BS연결,MATCH(J$1,BS연결H,0),0)/100,"") | K7: =IFERROR(VLOOKUP($D7,BS연결,MATCH(K$1,BS연결H,0),0)/100,"") | L7: =IFERROR(VLOOKUP($D7,BS연결,MATCH(L$1,BS연결H,0),0)/100,"") | M7: =IFERROR(VLOOKUP($D7,BS연결,MATCH(M$1,BS연결H,0),0)/100,"") | N7: =IFERROR(VLOOKUP($D7,BS연결,MATCH(N$1,BS연결H,0),0)/100,"") | ... AB7: =IFERROR(VLOOKUP($D7,BS연결,MATCH(AB$1,BS연결H,0),0)/100,"") | AC7: =IFERROR(AC9+AC8,"") | AD7: =IFERROR(AD9+AD8,"") | AE7: =SUM(AA7:AD7) | AF7: =IFERROR(AF9+AF8,"") | AG7: =IFERROR(AG9+AG8,"") | AH7: =IFERROR(AH9+AH8,"") | AI7: =IFERROR(AI9+AI8,"") | AJ7: =SUM(AF7:AI7) | AK7: =IFERROR(AK9+AK8,"") | AL7: =IFERROR(AL9+AL8,"") | AM7: =IFERROR(AM9+AM8,"") | AN7: =IFERROR(AN9+AN8,"") | AO7: =SUM(AK7:AN7)
A8: 판관비 | B8: 손익 | C8: 억원 | D8: 판관비 | E8: =IFERROR(VLOOKUP($D8,BS연결,MATCH(E$1,BS연결H,0),0)/100,"") | G8: =IFERROR(VLOOKUP($D8,BS연결,MATCH(G$1,BS연결H,0),0)/100,"") | H8: =IFERROR(VLOOKUP($D8,BS연결,MATCH(H$1,BS연결H,0),0)/100,"") | I8: =IFERROR(VLOOKUP($D8,BS연결,MATCH(I$1,BS연결H,0),0)/100,"") | J8: =IFERROR(VLOOKUP($D8,BS연결,MATCH(J$1,BS연결H,0),0)/100,"") | K8: =IFERROR(VLOOKUP($D8,BS연결,MATCH(K$1,BS연결H,0),0)/100,"") | L8: =IFERROR(VLOOKUP($D8,BS연결,MATCH(L$1,BS연결H,0),0)/100,"") | M8: =IFERROR(VLOOKUP($D8,BS연결,MATCH(M$1,BS연결H,0),0)/100,"") | N8: =IFERROR(VLOOKUP($D8,BS연결,MATCH(N$1,BS연결H,0),0)/100,"") | ... AB8: =IFERROR(VLOOKUP($D8,BS연결,MATCH(AB$1,BS연결H,0),0)/100,"") | AC8: =IFERROR(AC5*변수!AC22,"") | AD8: =IFERROR(AD5*변수!AD22,"") | AE8: =SUM(AA8:AD8) | AF8: =IFERROR(AF5*변수!AF22,"") | AG8: =IFERROR(AG5*변수!AG22,"") | AH8: =IFERROR(AH5*변수!AH22,"") | AI8: =IFERROR(AI5*변수!AI22,"") | AJ8: =SUM(AF8:AI8) | AK8: =IFERROR(AK5*변수!AK22,"") | AL8: =IFERROR(AL5*변수!AL22,"") | AM8: =IFERROR(AM5*변수!AM22,"") | AN8: =IFERROR(AN5*변수!AN22,"") | AO8: =SUM(AK8:AN8)
A9: 영업이익 | B9: 손익 | C9: 억원 | D9: 영업이익 | E9: =IFERROR(VLOOKUP($D9,BS연결,MATCH(E$1,BS연결H,0),0)/100,"") | G9: =IFERROR(VLOOKUP($D9,BS연결,MATCH(G$1,BS연결H,0),0)/100,"") | H9: =IFERROR(VLOOKUP($D9,BS연결,MATCH(H$1,BS연결H,0),0)/100,"") | I9: =IFERROR(VLOOKUP($D9,BS연결,MATCH(I$1,BS연결H,0),0)/100,"") | J9: =IFERROR(VLOOKUP($D9,BS연결,MATCH(J$1,BS연결H,0),0)/100,"") | K9: =IFERROR(VLOOKUP($D9,BS연결,MATCH(K$1,BS연결H,0),0)/100,"") | L9: =IFERROR(VLOOKUP($D9,BS연결,MATCH(L$1,BS연결H,0),0)/100,"") | M9: =IFERROR(VLOOKUP($D9,BS연결,MATCH(M$1,BS연결H,0),0)/100,"") | N9: =IFERROR(VLOOKUP($D9,BS연결,MATCH(N$1,BS연결H,0),0)/100,"") | ... AB9: =IFERROR(VLOOKUP($D9,BS연결,MATCH(AB$1,BS연결H,0),0)/100,"") | AC9: =IFERROR(AC5*변수!AC23,"") | AD9: =IFERROR(AD5*변수!AD23,"") | AE9: =SUM(AA9:AD9) | AF9: =IFERROR(AF5*변수!AF23,"") | AG9: =IFERROR(AG5*변수!AG23,"") | AH9: =IFERROR(AH5*변수!AH23,"") | AI9: =IFERROR(AI5*변수!AI23,"") | AJ9: =SUM(AF9:AI9) | AK9: =IFERROR(AK5*변수!AK23,"") | AL9: =IFERROR(AL5*변수!AL23,"") | AM9: =IFERROR(AM5*변수!AM23,"") | AN9: =IFERROR(AN5*변수!AN23,"") | AO9: =SUM(AK9:AN9)
A10: OPM | B10: 손익 | C10: % | D10: 영업이익률 | E10: =IFERROR(E9/E5,"") | G10: =IFERROR(G9/G5,"") | H10: =IFERROR(H9/H5,"") | I10: =IFERROR(I9/I5,"") | J10: =IFERROR(J9/J5,"") | K10: =IFERROR(K9/K5,"") | L10: =IFERROR(L9/L5,"") | M10: =IFERROR(M9/M5,"") | N10: =IFERROR(N9/N5,"") | ... AO10: =IFERROR(AO9/AO5,"")
A11: 금융손익 | B11: 손익 | C11: 억원 | D11: 금융손익 | E11: =IFERROR(VLOOKUP($D11,BS연결,MATCH(E$1,BS연결H,0),0)/100,"") | G11: =IFERROR(VLOOKUP($D11,BS연결,MATCH(G$1,BS연결H,0),0)/100,"") | H11: =IFERROR(VLOOKUP($D11,BS연결,MATCH(H$1,BS연결H,0),0)/100,"") | I11: =IFERROR(VLOOKUP($D11,BS연결,MATCH(I$1,BS연결H,0),0)/100,"") | J11: =IFERROR(VLOOKUP($D11,BS연결,MATCH(J$1,BS연결H,0),0)/100,"") | K11: =IFERROR(VLOOKUP($D11,BS연결,MATCH(K$1,BS연결H,0),0)/100,"") | L11: =IFERROR(VLOOKUP($D11,BS연결,MATCH(L$1,BS연결H,0),0)/100,"") | M11: =IFERROR(VLOOKUP($D11,BS연결,MATCH(M$1,BS연결H,0),0)/100,"") | N11: =IFERROR(VLOOKUP($D11,BS연결,MATCH(N$1,BS연결H,0),0)/100,"") | ... AB11: =IFERROR(VLOOKUP($D11,BS연결,MATCH(AB$1,BS연결H,0),0)/100,"") | AC11: =IFERROR(AC12+AC13+AC14+AC15,"") | AD11: =IFERROR(AD12+AD13+AD14+AD15,"") | AE11: =SUM(AA11:AD11) | AF11: =IFERROR(AF12+AF13+AF14+AF15,"") | AG11: =IFERROR(AG12+AG13+AG14+AG15,"") | AH11: =IFERROR(AH12+AH13+AH14+AH15,"") | AI11: =IFERROR(AI12+AI13+AI14+AI15,"") | AJ11: =SUM(AF11:AI11) | AK11: =IFERROR(AK12+AK13+AK14+AK15,"") | AL11: =IFERROR(AL12+AL13+AL14+AL15,"") | AM11: =IFERROR(AM12+AM13+AM14+AM15,"") | AN11: =IFERROR(AN12+AN13+AN14+AN15,"") | AO11: =SUM(AK11:AN11)
A12: 이자손익 | B12: 손익 | C12: 억원 | D12: 이자손익 | G12: =IFERROR(VLOOKUP($D12,BS연결,MATCH(G$1,BS연결H,0),0)/100,"") | H12: =IFERROR(VLOOKUP($D12,BS연결,MATCH(H$1,BS연결H,0),0)/100,"") | I12: =IFERROR(VLOOKUP($D12,BS연결,MATCH(I$1,BS연결H,0),0)/100,"") | J12: =IFERROR(VLOOKUP($D12,BS연결,MATCH(J$1,BS연결H,0),0)/100,"") | K12: =IFERROR(VLOOKUP($D12,BS연결,MATCH(K$1,BS연결H,0),0)/100,"") | L12: =IFERROR(VLOOKUP($D12,BS연결,MATCH(L$1,BS연결H,0),0)/100,"") | M12: =IFERROR(VLOOKUP($D12,BS연결,MATCH(M$1,BS연결H,0),0)/100,"") | N12: =IFERROR(VLOOKUP($D12,BS연결,MATCH(N$1,BS연결H,0),0)/100,"") | ... AB12: =IFERROR(VLOOKUP($D12,BS연결,MATCH(AB$1,BS연결H,0),0)/100,"") | AC12: =IFERROR((AB31*변수!$D$56-AB29*변수!$D$57)/4,"") | AD12: =IFERROR((AC31*변수!$D$56-AC29*변수!$D$57)/4,"") | AE12: =SUM(AA12:AD12) | AF12: =IFERROR((AD31*변수!$D$56-AD29*변수!$D$57)/4,"") | AG12: =IFERROR((AF31*변수!$D$56-AF29*변수!$D$57)/4,"") | AH12: =IFERROR((AG31*변수!$D$56-AG29*변수!$D$57)/4,"") | AI12: =IFERROR((AH31*변수!$D$56-AH29*변수!$D$57)/4,"") | AJ12: =SUM(AF12:AI12) | AK12: =IFERROR((AI31*변수!$D$56-AI29*변수!$D$57)/4,"") | AL12: =IFERROR((AK31*변수!$D$56-AK29*변수!$D$57)/4,"") | AM12: =IFERROR((AL31*변수!$D$56-AL29*변수!$D$57)/4,"") | AN12: =IFERROR((AM31*변수!$D$56-AM29*변수!$D$57)/4,"") | AO12: =SUM(AK12:AN12)
A13: 외환손익 | B13: 손익 | C13: 억원 | D13: 외환손익(실적만; 추정 환효과는 환관련손익) | G13: =IFERROR((VLOOKUP("외환차익",BS연결,MATCH(G$1,BS연결H,0),0)-VLOOKUP("외환차손",BS연결,MATCH(G$1,BS연결H,0),0)+VLOOKUP("외화환산이익",BS연결,MATCH(G$1,BS연결H,0),0)-VLOOKUP("외화환산손실",BS연결,MATCH(G$1,BS연결H,0),0))/100,"") | H13: =IFERROR((VLOOKUP("외환차익",BS연결,MATCH(H$1,BS연결H,0),0)-VLOOKUP("외환차손",BS연결,MATCH(H$1,BS연결H,0),0)+VLOOKUP("외화환산이익",BS연결,MATCH(H$1,BS연결H,0),0)-VLOOKUP("외화환산손실",BS연결,MATCH(H$1,BS연결H,0),0))/100,"") | I13: =IFERROR((VLOOKUP("외환차익",BS연결,MATCH(I$1,BS연결H,0),0)-VLOOKUP("외환차손",BS연결,MATCH(I$1,BS연결H,0),0)+VLOOKUP("외화환산이익",BS연결,MATCH(I$1,BS연결H,0),0)-VLOOKUP("외화환산손실",BS연결,MATCH(I$1,BS연결H,0),0))/100,"") | J13: =IFERROR((VLOOKUP("외환차익",BS연결,MATCH(J$1,BS연결H,0),0)-VLOOKUP("외환차손",BS연결,MATCH(J$1,BS연결H,0),0)+VLOOKUP("외화환산이익",BS연결,MATCH(J$1,BS연결H,0),0)-VLOOKUP("외화환산손실",BS연결,MATCH(J$1,BS연결H,0),0))/100,"") | K13: =SUM(G13:J13) | L13: =IFERROR((VLOOKUP("외환차익",BS연결,MATCH(L$1,BS연결H,0),0)-VLOOKUP("외환차손",BS연결,MATCH(L$1,BS연결H,0),0)+VLOOKUP("외화환산이익",BS연결,MATCH(L$1,BS연결H,0),0)-VLOOKUP("외화환산손실",BS연결,MATCH(L$1,BS연결H,0),0))/100,"") | M13: =IFERROR((VLOOKUP("외환차익",BS연결,MATCH(M$1,BS연결H,0),0)-VLOOKUP("외환차손",BS연결,MATCH(M$1,BS연결H,0),0)+VLOOKUP("외화환산이익",BS연결,MATCH(M$1,BS연결H,0),0)-VLOOKUP("외화환산손실",BS연결,MATCH(M$1,BS연결H,0),0))/100,"") | N13: =IFERROR((VLOOKUP("외환차익",BS연결,MATCH(N$1,BS연결H,0),0)-VLOOKUP("외환차손",BS연결,MATCH(N$1,BS연결H,0),0)+VLOOKUP("외화환산이익",BS연결,MATCH(N$1,BS연결H,0),0)-VLOOKUP("외화환산손실",BS연결,MATCH(N$1,BS연결H,0),0))/100,"") | O13: =IFERROR((VLOOKUP("외환차익",BS연결,MATCH(O$1,BS연결H,0),0)-VLOOKUP("외환차손",BS연결,MATCH(O$1,BS연결H,0),0)+VLOOKUP("외화환산이익",BS연결,MATCH(O$1,BS연결H,0),0)-VLOOKUP("외화환산손실",BS연결,MATCH(O$1,BS연결H,0),0))/100,"") | P13: =SUM(L13:O13) | Q13: =IFERROR((VLOOKUP("외환차익",BS연결,MATCH(Q$1,BS연결H,0),0)-VLOOKUP("외환차손",BS연결,MATCH(Q$1,BS연결H,0),0)+VLOOKUP("외화환산이익",BS연결,MATCH(Q$1,BS연결H,0),0)-VLOOKUP("외화환산손실",BS연결,MATCH(Q$1,BS연결H,0),0))/100,"") | R13: =IFERROR((VLOOKUP("외환차익",BS연결,MATCH(R$1,BS연결H,0),0)-VLOOKUP("외환차손",BS연결,MATCH(R$1,BS연결H,0),0)+VLOOKUP("외화환산이익",BS연결,MATCH(R$1,BS연결H,0),0)-VLOOKUP("외화환산손실",BS연결,MATCH(R$1,BS연결H,0),0))/100,"") | S13: =IFERROR((VLOOKUP("외환차익",BS연결,MATCH(S$1,BS연결H,0),0)-VLOOKUP("외환차손",BS연결,MATCH(S$1,BS연결H,0),0)+VLOOKUP("외화환산이익",BS연결,MATCH(S$1,BS연결H,0),0)-VLOOKUP("외화환산손실",BS연결,MATCH(S$1,BS연결H,0),0))/100,"") | T13: =IFERROR((VLOOKUP("외환차익",BS연결,MATCH(T$1,BS연결H,0),0)-VLOOKUP("외환차손",BS연결,MATCH(T$1,BS연결H,0),0)+VLOOKUP("외화환산이익",BS연결,MATCH(T$1,BS연결H,0),0)-VLOOKUP("외화환산손실",BS연결,MATCH(T$1,BS연결H,0),0))/100,"") | U13: =SUM(Q13:T13) | V13: =IFERROR((VLOOKUP("외환차익",BS연결,MATCH(V$1,BS연결H,0),0)-VLOOKUP("외환차손",BS연결,MATCH(V$1,BS연결H,0),0)+VLOOKUP("외화환산이익",BS연결,MATCH(V$1,BS연결H,0),0)-VLOOKUP("외화환산손실",BS연결,MATCH(V$1,BS연결H,0),0))/100,"") | W13: =IFERROR((VLOOKUP("외환차익",BS연결,MATCH(W$1,BS연결H,0),0)-VLOOKUP("외환차손",BS연결,MATCH(W$1,BS연결H,0),0)+VLOOKUP("외화환산이익",BS연결,MATCH(W$1,BS연결H,0),0)-VLOOKUP("외화환산손실",BS연결,MATCH(W$1,BS연결H,0),0))/100,"") | X13: =IFERROR((VLOOKUP("외환차익",BS연결,MATCH(X$1,BS연결H,0),0)-VLOOKUP("외환차손",BS연결,MATCH(X$1,BS연결H,0),0)+VLOOKUP("외화환산이익",BS연결,MATCH(X$1,BS연결H,0),0)-VLOOKUP("외화환산손실",BS연결,MATCH(X$1,BS연결H,0),0))/100,"") | Y13: =IFERROR((VLOOKUP("외환차익",BS연결,MATCH(Y$1,BS연결H,0),0)-VLOOKUP("외환차손",BS연결,MATCH(Y$1,BS연결H,0),0)+VLOOKUP("외화환산이익",BS연결,MATCH(Y$1,BS연결H,0),0)-VLOOKUP("외화환산손실",BS연결,MATCH(Y$1,BS연결H,0),0))/100,"") | Z13: =SUM(V13:Y13) | AA13: =IFERROR((VLOOKUP("외환차익",BS연결,MATCH(AA$1,BS연결H,0),0)-VLOOKUP("외환차손",BS연결,MATCH(AA$1,BS연결H,0),0)+VLOOKUP("외화환산이익",BS연결,MATCH(AA$1,BS연결H,0),0)-VLOOKUP("외화환산손실",BS연결,MATCH(AA$1,BS연결H,0),0))/100,"") | AB13: =IFERROR((VLOOKUP("외환차익",BS연결,MATCH(AB$1,BS연결H,0),0)-VLOOKUP("외환차손",BS연결,MATCH(AB$1,BS연결H,0),0)+VLOOKUP("외화환산이익",BS연결,MATCH(AB$1,BS연결H,0),0)-VLOOKUP("외화환산손실",BS연결,MATCH(AB$1,BS연결H,0),0))/100,"") | AC13: =변수!AC24 | AD13: =변수!AD24 | AE13: =SUM(AA13:AD13) | AF13: =변수!AF24 | AG13: =변수!AG24 | AH13: =변수!AH24 | AI13: =변수!AI24 | AJ13: =SUM(AF13:AI13) | AK13: =변수!AK24 | AL13: =변수!AL24 | AM13: =변수!AM24 | AN13: =변수!AN24 | AO13: =SUM(AK13:AN13)
A14: 파생상품손익 | B14: 손익 | C14: 억원 | D14: 파생상품손익 | G14: =IFERROR((VLOOKUP("파생상품이익",BS연결,MATCH(G$1,BS연결H,0),0)-VLOOKUP("파생상품손실",BS연결,MATCH(G$1,BS연결H,0),0))/100,"") | H14: =IFERROR((VLOOKUP("파생상품이익",BS연결,MATCH(H$1,BS연결H,0),0)-VLOOKUP("파생상품손실",BS연결,MATCH(H$1,BS연결H,0),0))/100,"") | I14: =IFERROR((VLOOKUP("파생상품이익",BS연결,MATCH(I$1,BS연결H,0),0)-VLOOKUP("파생상품손실",BS연결,MATCH(I$1,BS연결H,0),0))/100,"") | J14: =IFERROR((VLOOKUP("파생상품이익",BS연결,MATCH(J$1,BS연결H,0),0)-VLOOKUP("파생상품손실",BS연결,MATCH(J$1,BS연결H,0),0))/100,"") | K14: =SUM(G14:J14) | L14: =IFERROR((VLOOKUP("파생상품이익",BS연결,MATCH(L$1,BS연결H,0),0)-VLOOKUP("파생상품손실",BS연결,MATCH(L$1,BS연결H,0),0))/100,"") | M14: =IFERROR((VLOOKUP("파생상품이익",BS연결,MATCH(M$1,BS연결H,0),0)-VLOOKUP("파생상품손실",BS연결,MATCH(M$1,BS연결H,0),0))/100,"") | N14: =IFERROR((VLOOKUP("파생상품이익",BS연결,MATCH(N$1,BS연결H,0),0)-VLOOKUP("파생상품손실",BS연결,MATCH(N$1,BS연결H,0),0))/100,"") | O14: =IFERROR((VLOOKUP("파생상품이익",BS연결,MATCH(O$1,BS연결H,0),0)-VLOOKUP("파생상품손실",BS연결,MATCH(O$1,BS연결H,0),0))/100,"") | P14: =SUM(L14:O14) | Q14: =IFERROR((VLOOKUP("파생상품이익",BS연결,MATCH(Q$1,BS연결H,0),0)-VLOOKUP("파생상품손실",BS연결,MATCH(Q$1,BS연결H,0),0))/100,"") | R14: =IFERROR((VLOOKUP("파생상품이익",BS연결,MATCH(R$1,BS연결H,0),0)-VLOOKUP("파생상품손실",BS연결,MATCH(R$1,BS연결H,0),0))/100,"") | S14: =IFERROR((VLOOKUP("파생상품이익",BS연결,MATCH(S$1,BS연결H,0),0)-VLOOKUP("파생상품손실",BS연결,MATCH(S$1,BS연결H,0),0))/100,"") | T14: =IFERROR((VLOOKUP("파생상품이익",BS연결,MATCH(T$1,BS연결H,0),0)-VLOOKUP("파생상품손실",BS연결,MATCH(T$1,BS연결H,0),0))/100,"") | U14: =SUM(Q14:T14) | V14: =IFERROR((VLOOKUP("파생상품이익",BS연결,MATCH(V$1,BS연결H,0),0)-VLOOKUP("파생상품손실",BS연결,MATCH(V$1,BS연결H,0),0))/100,"") | W14: =IFERROR((VLOOKUP("파생상품이익",BS연결,MATCH(W$1,BS연결H,0),0)-VLOOKUP("파생상품손실",BS연결,MATCH(W$1,BS연결H,0),0))/100,"") | X14: =IFERROR((VLOOKUP("파생상품이익",BS연결,MATCH(X$1,BS연결H,0),0)-VLOOKUP("파생상품손실",BS연결,MATCH(X$1,BS연결H,0),0))/100,"") | Y14: =IFERROR((VLOOKUP("파생상품이익",BS연결,MATCH(Y$1,BS연결H,0),0)-VLOOKUP("파생상품손실",BS연결,MATCH(Y$1,BS연결H,0),0))/100,"") | Z14: =SUM(V14:Y14) | AA14: =IFERROR((VLOOKUP("파생상품이익",BS연결,MATCH(AA$1,BS연결H,0),0)-VLOOKUP("파생상품손실",BS연결,MATCH(AA$1,BS연결H,0),0))/100,"") | AB14: =IFERROR((VLOOKUP("파생상품이익",BS연결,MATCH(AB$1,BS연결H,0),0)-VLOOKUP("파생상품손실",BS연결,MATCH(AB$1,BS연결H,0),0))/100,"") | AC14: =변수!AC25 | AD14: =변수!AD25 | AE14: =SUM(AA14:AD14) | AF14: =변수!AF25 | AG14: =변수!AG25 | AH14: =변수!AH25 | AI14: =변수!AI25 | AJ14: =SUM(AF14:AI14) | AK14: =변수!AK25 | AL14: =변수!AL25 | AM14: =변수!AM25 | AN14: =변수!AN25 | AO14: =SUM(AK14:AN14)
A15: 기타금융손익 | B15: 손익 | C15: 억원 | D15: 기타금융손익(금융손익 잔차) | G15: =IFERROR(G11-G12-G13-G14,"") | H15: =IFERROR(H11-H12-H13-H14,"") | I15: =IFERROR(I11-I12-I13-I14,"") | J15: =IFERROR(J11-J12-J13-J14,"") | K15: =SUM(G15:J15) | L15: =IFERROR(L11-L12-L13-L14,"") | M15: =IFERROR(M11-M12-M13-M14,"") | N15: =IFERROR(N11-N12-N13-N14,"") | O15: =IFERROR(O11-O12-O13-O14,"") | P15: =SUM(L15:O15) | Q15: =IFERROR(Q11-Q12-Q13-Q14,"") | R15: =IFERROR(R11-R12-R13-R14,"") | S15: =IFERROR(S11-S12-S13-S14,"") | T15: =IFERROR(T11-T12-T13-T14,"") | U15: =SUM(Q15:T15) | V15: =IFERROR(V11-V12-V13-V14,"") | W15: =IFERROR(W11-W12-W13-W14,"") | X15: =IFERROR(X11-X12-X13-X14,"") | Y15: =IFERROR(Y11-Y12-Y13-Y14,"") | Z15: =SUM(V15:Y15) | AA15: =IFERROR(AA11-AA12-AA13-AA14,"") | AB15: =IFERROR(AB11-AB12-AB13-AB14,"") | AC15: =변수!AC26 | AD15: =변수!AD26 | AE15: =SUM(AA15:AD15) | AF15: =변수!AF26 | AG15: =변수!AG26 | AH15: =변수!AH26 | AI15: =변수!AI26 | AJ15: =SUM(AF15:AI15) | AK15: =변수!AK26 | AL15: =변수!AL26 | AM15: =변수!AM26 | AN15: =변수!AN26 | AO15: =SUM(AK15:AN15)
A16: 기타영업외손익 | B16: 손익 | C16: 억원 | D16: 기타영업외손익 | E16: =IFERROR(VLOOKUP($D16,BS연결,MATCH(E$1,BS연결H,0),0)/100,"") | G16: =IFERROR(VLOOKUP($D16,BS연결,MATCH(G$1,BS연결H,0),0)/100,"") | H16: =IFERROR(VLOOKUP($D16,BS연결,MATCH(H$1,BS연결H,0),0)/100,"") | I16: =IFERROR(VLOOKUP($D16,BS연결,MATCH(I$1,BS연결H,0),0)/100,"") | J16: =IFERROR(VLOOKUP($D16,BS연결,MATCH(J$1,BS연결H,0),0)/100,"") | K16: =IFERROR(VLOOKUP($D16,BS연결,MATCH(K$1,BS연결H,0),0)/100,"") | L16: =IFERROR(VLOOKUP($D16,BS연결,MATCH(L$1,BS연결H,0),0)/100,"") | M16: =IFERROR(VLOOKUP($D16,BS연결,MATCH(M$1,BS연결H,0),0)/100,"") | N16: =IFERROR(VLOOKUP($D16,BS연결,MATCH(N$1,BS연결H,0),0)/100,"") | ... AB16: =IFERROR(VLOOKUP($D16,BS연결,MATCH(AB$1,BS연결H,0),0)/100,"") | AC16: =변수!AC27 | AD16: =변수!AD27 | AE16: =SUM(AA16:AD16) | AF16: =변수!AF27 | AG16: =변수!AG27 | AH16: =변수!AH27 | AI16: =변수!AI27 | AJ16: =SUM(AF16:AI16) | AK16: =변수!AK27 | AL16: =변수!AL27 | AM16: =변수!AM27 | AN16: =변수!AN27 | AO16: =SUM(AK16:AN16)
A17: 지분법손익 | B17: 손익 | C17: 억원 | D17: 종속기업,공동지배기업및관계기업관련손익 | E17: =IFERROR(VLOOKUP($D17,BS연결,MATCH(E$1,BS연결H,0),0)/100,"") | G17: =IFERROR(VLOOKUP($D17,BS연결,MATCH(G$1,BS연결H,0),0)/100,"") | H17: =IFERROR(VLOOKUP($D17,BS연결,MATCH(H$1,BS연결H,0),0)/100,"") | I17: =IFERROR(VLOOKUP($D17,BS연결,MATCH(I$1,BS연결H,0),0)/100,"") | J17: =IFERROR(VLOOKUP($D17,BS연결,MATCH(J$1,BS연결H,0),0)/100,"") | K17: =IFERROR(VLOOKUP($D17,BS연결,MATCH(K$1,BS연결H,0),0)/100,"") | L17: =IFERROR(VLOOKUP($D17,BS연결,MATCH(L$1,BS연결H,0),0)/100,"") | M17: =IFERROR(VLOOKUP($D17,BS연결,MATCH(M$1,BS연결H,0),0)/100,"") | N17: =IFERROR(VLOOKUP($D17,BS연결,MATCH(N$1,BS연결H,0),0)/100,"") | ... AB17: =IFERROR(VLOOKUP($D17,BS연결,MATCH(AB$1,BS연결H,0),0)/100,"") | AC17: =변수!AC28 | AD17: =변수!AD28 | AE17: =SUM(AA17:AD17) | AF17: =변수!AF28 | AG17: =변수!AG28 | AH17: =변수!AH28 | AI17: =변수!AI28 | AJ17: =SUM(AF17:AI17) | AK17: =변수!AK28 | AL17: =변수!AL28 | AM17: =변수!AM28 | AN17: =변수!AN28 | AO17: =SUM(AK17:AN17)
A18: 세전이익 | B18: 손익 | C18: 억원 | D18: 법인세비용차감전계속사업이익 | E18: =IFERROR(VLOOKUP($D18,BS연결,MATCH(E$1,BS연결H,0),0)/100,"") | G18: =IFERROR(VLOOKUP($D18,BS연결,MATCH(G$1,BS연결H,0),0)/100,"") | H18: =IFERROR(VLOOKUP($D18,BS연결,MATCH(H$1,BS연결H,0),0)/100,"") | I18: =IFERROR(VLOOKUP($D18,BS연결,MATCH(I$1,BS연결H,0),0)/100,"") | J18: =IFERROR(VLOOKUP($D18,BS연결,MATCH(J$1,BS연결H,0),0)/100,"") | K18: =IFERROR(VLOOKUP($D18,BS연결,MATCH(K$1,BS연결H,0),0)/100,"") | L18: =IFERROR(VLOOKUP($D18,BS연결,MATCH(L$1,BS연결H,0),0)/100,"") | M18: =IFERROR(VLOOKUP($D18,BS연결,MATCH(M$1,BS연결H,0),0)/100,"") | N18: =IFERROR(VLOOKUP($D18,BS연결,MATCH(N$1,BS연결H,0),0)/100,"") | ... AB18: =IFERROR(VLOOKUP($D18,BS연결,MATCH(AB$1,BS연결H,0),0)/100,"") | AC18: =IFERROR(AC9+AC11+AC16+AC17,"") | AD18: =IFERROR(AD9+AD11+AD16+AD17,"") | AE18: =SUM(AA18:AD18) | AF18: =IFERROR(AF9+AF11+AF16+AF17,"") | AG18: =IFERROR(AG9+AG11+AG16+AG17,"") | AH18: =IFERROR(AH9+AH11+AH16+AH17,"") | AI18: =IFERROR(AI9+AI11+AI16+AI17,"") | AJ18: =SUM(AF18:AI18) | AK18: =IFERROR(AK9+AK11+AK16+AK17,"") | AL18: =IFERROR(AL9+AL11+AL16+AL17,"") | AM18: =IFERROR(AM9+AM11+AM16+AM17,"") | AN18: =IFERROR(AN9+AN11+AN16+AN17,"") | AO18: =SUM(AK18:AN18)
A19: 법인세비용 | B19: 손익 | C19: 억원 | D19: 법인세비용 | E19: =IFERROR(VLOOKUP($D19,BS연결,MATCH(E$1,BS연결H,0),0)/100,"") | G19: =IFERROR(VLOOKUP($D19,BS연결,MATCH(G$1,BS연결H,0),0)/100,"") | H19: =IFERROR(VLOOKUP($D19,BS연결,MATCH(H$1,BS연결H,0),0)/100,"") | I19: =IFERROR(VLOOKUP($D19,BS연결,MATCH(I$1,BS연결H,0),0)/100,"") | J19: =IFERROR(VLOOKUP($D19,BS연결,MATCH(J$1,BS연결H,0),0)/100,"") | K19: =IFERROR(VLOOKUP($D19,BS연결,MATCH(K$1,BS연결H,0),0)/100,"") | L19: =IFERROR(VLOOKUP($D19,BS연결,MATCH(L$1,BS연결H,0),0)/100,"") | M19: =IFERROR(VLOOKUP($D19,BS연결,MATCH(M$1,BS연결H,0),0)/100,"") | N19: =IFERROR(VLOOKUP($D19,BS연결,MATCH(N$1,BS연결H,0),0)/100,"") | ... AB19: =IFERROR(VLOOKUP($D19,BS연결,MATCH(AB$1,BS연결H,0),0)/100,"") | AC19: =IFERROR(MAX(AC18,0)*변수!AC29,"") | AD19: =IFERROR(MAX(AD18,0)*변수!AD29,"") | AE19: =SUM(AA19:AD19) | AF19: =IFERROR(MAX(AF18,0)*변수!AF29,"") | AG19: =IFERROR(MAX(AG18,0)*변수!AG29,"") | AH19: =IFERROR(MAX(AH18,0)*변수!AH29,"") | AI19: =IFERROR(MAX(AI18,0)*변수!AI29,"") | AJ19: =SUM(AF19:AI19) | AK19: =IFERROR(MAX(AK18,0)*변수!AK29,"") | AL19: =IFERROR(MAX(AL18,0)*변수!AL29,"") | AM19: =IFERROR(MAX(AM18,0)*변수!AM29,"") | AN19: =IFERROR(MAX(AN18,0)*변수!AN29,"") | AO19: =SUM(AK19:AN19)
A20: 당기순이익 | B20: 손익 | C20: 억원 | D20: 당기순이익 | E20: =IFERROR(VLOOKUP($D20,BS연결,MATCH(E$1,BS연결H,0),0)/100,"") | G20: =IFERROR(VLOOKUP($D20,BS연결,MATCH(G$1,BS연결H,0),0)/100,"") | H20: =IFERROR(VLOOKUP($D20,BS연결,MATCH(H$1,BS연결H,0),0)/100,"") | I20: =IFERROR(VLOOKUP($D20,BS연결,MATCH(I$1,BS연결H,0),0)/100,"") | J20: =IFERROR(VLOOKUP($D20,BS연결,MATCH(J$1,BS연결H,0),0)/100,"") | K20: =IFERROR(VLOOKUP($D20,BS연결,MATCH(K$1,BS연결H,0),0)/100,"") | L20: =IFERROR(VLOOKUP($D20,BS연결,MATCH(L$1,BS연결H,0),0)/100,"") | M20: =IFERROR(VLOOKUP($D20,BS연결,MATCH(M$1,BS연결H,0),0)/100,"") | N20: =IFERROR(VLOOKUP($D20,BS연결,MATCH(N$1,BS연결H,0),0)/100,"") | ... AB20: =IFERROR(VLOOKUP($D20,BS연결,MATCH(AB$1,BS연결H,0),0)/100,"") | AC20: =IFERROR(AC18-AC19,"") | AD20: =IFERROR(AD18-AD19,"") | AE20: =SUM(AA20:AD20) | AF20: =IFERROR(AF18-AF19,"") | AG20: =IFERROR(AG18-AG19,"") | AH20: =IFERROR(AH18-AH19,"") | AI20: =IFERROR(AI18-AI19,"") | AJ20: =SUM(AF20:AI20) | AK20: =IFERROR(AK18-AK19,"") | AL20: =IFERROR(AL18-AL19,"") | AM20: =IFERROR(AM18-AM19,"") | AN20: =IFERROR(AN18-AN19,"") | AO20: =SUM(AK20:AN20)
A21: 지배주주순이익 | B21: 손익 | C21: 억원 | D21: (지배주주지분)당기순이익 | E21: =IFERROR(VLOOKUP($D21,BS연결,MATCH(E$1,BS연결H,0),0)/100,"") | G21: =IFERROR(VLOOKUP($D21,BS연결,MATCH(G$1,BS연결H,0),0)/100,"") | H21: =IFERROR(VLOOKUP($D21,BS연결,MATCH(H$1,BS연결H,0),0)/100,"") | I21: =IFERROR(VLOOKUP($D21,BS연결,MATCH(I$1,BS연결H,0),0)/100,"") | J21: =IFERROR(VLOOKUP($D21,BS연결,MATCH(J$1,BS연결H,0),0)/100,"") | K21: =IFERROR(VLOOKUP($D21,BS연결,MATCH(K$1,BS연결H,0),0)/100,"") | L21: =IFERROR(VLOOKUP($D21,BS연결,MATCH(L$1,BS연결H,0),0)/100,"") | M21: =IFERROR(VLOOKUP($D21,BS연결,MATCH(M$1,BS연결H,0),0)/100,"") | N21: =IFERROR(VLOOKUP($D21,BS연결,MATCH(N$1,BS연결H,0),0)/100,"") | ... AB21: =IFERROR(VLOOKUP($D21,BS연결,MATCH(AB$1,BS연결H,0),0)/100,"") | AC21: =IFERROR(AC20*변수!AC30,"") | AD21: =IFERROR(AD20*변수!AD30,"") | AE21: =SUM(AA21:AD21) | AF21: =IFERROR(AF20*변수!AF30,"") | AG21: =IFERROR(AG20*변수!AG30,"") | AH21: =IFERROR(AH20*변수!AH30,"") | AI21: =IFERROR(AI20*변수!AI30,"") | AJ21: =SUM(AF21:AI21) | AK21: =IFERROR(AK20*변수!AK30,"") | AL21: =IFERROR(AL20*변수!AL30,"") | AM21: =IFERROR(AM20*변수!AM30,"") | AN21: =IFERROR(AN20*변수!AN30,"") | AO21: =SUM(AK21:AN21)
A22: 중단사업이익 | B22: 손익 | C22: 억원 | D22: 중단사업이익 | K22: =SUM(G22:J22) | P22: =SUM(L22:O22) | U22: =SUM(Q22:T22) | Z22: =SUM(V22:Y22) | AB22: =IFERROR(VLOOKUP($D22,BS연결,MATCH(AB$1,BS연결H,0),0)/100,"") | AE22: =SUM(AA22:AD22) | AJ22: =SUM(AF22:AI22) | AO22: =SUM(AK22:AN22)
A23: 감가상각비 | B23: 손익 | C23: 억원 | D23: 감가상각비 | E23: =IFERROR(VLOOKUP($D23,BS연결,MATCH(E$1,BS연결H,0),0)/100,"") | G23: =IFERROR(VLOOKUP($D23,BS연결,MATCH(G$1,BS연결H,0),0)/100,"") | H23: =IFERROR(VLOOKUP($D23,BS연결,MATCH(H$1,BS연결H,0),0)/100,"") | I23: =IFERROR(VLOOKUP($D23,BS연결,MATCH(I$1,BS연결H,0),0)/100,"") | J23: =IFERROR(VLOOKUP($D23,BS연결,MATCH(J$1,BS연결H,0),0)/100,"") | K23: =IFERROR(VLOOKUP($D23,BS연결,MATCH(K$1,BS연결H,0),0)/100,"") | L23: =IFERROR(VLOOKUP($D23,BS연결,MATCH(L$1,BS연결H,0),0)/100,"") | M23: =IFERROR(VLOOKUP($D23,BS연결,MATCH(M$1,BS연결H,0),0)/100,"") | N23: =IFERROR(VLOOKUP($D23,BS연결,MATCH(N$1,BS연결H,0),0)/100,"") | ... AB23: =IFERROR(VLOOKUP($D23,BS연결,MATCH(AB$1,BS연결H,0),0)/100,"") | AC23: =변수!AC32 | AD23: =변수!AD32 | AE23: =SUM(AA23:AD23) | AF23: =변수!AF32 | AG23: =변수!AG32 | AH23: =변수!AH32 | AI23: =변수!AI32 | AJ23: =SUM(AF23:AI23) | AK23: =변수!AK32 | AL23: =변수!AL32 | AM23: =변수!AM32 | AN23: =변수!AN32 | AO23: =SUM(AK23:AN23)
A24: EBITDA | B24: 손익 | C24: 억원 | D24: EBITDA | E24: 816.21 | G24: 1563.12 | H24: 1707.3 | I24: 1031.72 | J24: 650.78 | K24: =SUM(G24:J24) | L24: 828.98 | M24: 974.18 | N24: 956.39 | O24: 686.32 | P24: =SUM(L24:O24) | Q24: 1139.67 | R24: 1478.76 | S24: 1326.8 | T24: 1051.3 | U24: =SUM(Q24:T24) | V24: 2066.27 | W24: 2379.96 | X24: -602.83 | Y24: 4528.49 | Z24: =SUM(V24:Y24) | AA24: 1818.37 | AB24: 2207.7 | AC24: =IFERROR(AC9+AC23,"") | AD24: =IFERROR(AD9+AD23,"") | AE24: =SUM(AA24:AD24) | AF24: =IFERROR(AF9+AF23,"") | AG24: =IFERROR(AG9+AG23,"") | AH24: =IFERROR(AH9+AH23,"") | AI24: =IFERROR(AI9+AI23,"") | AJ24: =SUM(AF24:AI24) | AK24: =IFERROR(AK9+AK23,"") | AL24: =IFERROR(AL9+AL23,"") | AM24: =IFERROR(AM9+AM23,"") | AN24: =IFERROR(AN9+AN23,"") | AO24: =SUM(AK24:AN24)
A25: 자산총계 | B25: 재무상태 | C25: 억원 | D25: 자산총계 | E25: =IFERROR(VLOOKUP($D25,BS연결,MATCH(E$1,BS연결H,0),0)/100,"") | F25: =IFERROR(VLOOKUP($D25,BS연결,MATCH(F$1,BS연결H,0),0)/100,"") | G25: =IFERROR(VLOOKUP($D25,BS연결,MATCH(G$1,BS연결H,0),0)/100,"") | H25: =IFERROR(VLOOKUP($D25,BS연결,MATCH(H$1,BS연결H,0),0)/100,"") | I25: =IFERROR(VLOOKUP($D25,BS연결,MATCH(I$1,BS연결H,0),0)/100,"") | J25: =IFERROR(VLOOKUP($D25,BS연결,MATCH(J$1,BS연결H,0),0)/100,"") | K25: =IFERROR(VLOOKUP($D25,BS연결,MATCH(K$1,BS연결H,0),0)/100,"") | L25: =IFERROR(VLOOKUP($D25,BS연결,MATCH(L$1,BS연결H,0),0)/100,"") | ... AB25: =IFERROR(VLOOKUP($D25,BS연결,MATCH(AB$1,BS연결H,0),0)/100,"") | AC25: =IFERROR(AC26+AC27,"") | AD25: =IFERROR(AD26+AD27,"") | AE25: =AD25 | AF25: =IFERROR(AF26+AF27,"") | AG25: =IFERROR(AG26+AG27,"") | AH25: =IFERROR(AH26+AH27,"") | AI25: =IFERROR(AI26+AI27,"") | AJ25: =AI25 | AK25: =IFERROR(AK26+AK27,"") | AL25: =IFERROR(AL26+AL27,"") | AM25: =IFERROR(AM26+AM27,"") | AN25: =IFERROR(AN26+AN27,"") | AO25: =AN25
A26: 부채총계 | B26: 재무상태 | C26: 억원 | D26: 부채총계 | E26: =IFERROR(VLOOKUP($D26,BS연결,MATCH(E$1,BS연결H,0),0)/100,"") | F26: =IFERROR(VLOOKUP($D26,BS연결,MATCH(F$1,BS연결H,0),0)/100,"") | G26: =IFERROR(VLOOKUP($D26,BS연결,MATCH(G$1,BS연결H,0),0)/100,"") | H26: =IFERROR(VLOOKUP($D26,BS연결,MATCH(H$1,BS연결H,0),0)/100,"") | I26: =IFERROR(VLOOKUP($D26,BS연결,MATCH(I$1,BS연결H,0),0)/100,"") | J26: =IFERROR(VLOOKUP($D26,BS연결,MATCH(J$1,BS연결H,0),0)/100,"") | K26: =IFERROR(VLOOKUP($D26,BS연결,MATCH(K$1,BS연결H,0),0)/100,"") | L26: =IFERROR(VLOOKUP($D26,BS연결,MATCH(L$1,BS연결H,0),0)/100,"") | ... AB26: =IFERROR(VLOOKUP($D26,BS연결,MATCH(AB$1,BS연결H,0),0)/100,"") | AC26: =IFERROR(AB26*(1+변수!AC33),"") | AD26: =IFERROR(AC26*(1+변수!AD33),"") | AE26: =AD26 | AF26: =IFERROR(AD26*(1+변수!AF33),"") | AG26: =IFERROR(AF26*(1+변수!AG33),"") | AH26: =IFERROR(AG26*(1+변수!AH33),"") | AI26: =IFERROR(AH26*(1+변수!AI33),"") | AJ26: =AI26 | AK26: =IFERROR(AI26*(1+변수!AK33),"") | AL26: =IFERROR(AK26*(1+변수!AL33),"") | AM26: =IFERROR(AL26*(1+변수!AM33),"") | AN26: =IFERROR(AM26*(1+변수!AN33),"") | AO26: =AN26
A27: 자본총계 | B27: 재무상태 | C27: 억원 | D27: 자본총계 | E27: =IFERROR(VLOOKUP($D27,BS연결,MATCH(E$1,BS연결H,0),0)/100,"") | F27: =IFERROR(VLOOKUP($D27,BS연결,MATCH(F$1,BS연결H,0),0)/100,"") | G27: =IFERROR(VLOOKUP($D27,BS연결,MATCH(G$1,BS연결H,0),0)/100,"") | H27: =IFERROR(VLOOKUP($D27,BS연결,MATCH(H$1,BS연결H,0),0)/100,"") | I27: =IFERROR(VLOOKUP($D27,BS연결,MATCH(I$1,BS연결H,0),0)/100,"") | J27: =IFERROR(VLOOKUP($D27,BS연결,MATCH(J$1,BS연결H,0),0)/100,"") | K27: =IFERROR(VLOOKUP($D27,BS연결,MATCH(K$1,BS연결H,0),0)/100,"") | L27: =IFERROR(VLOOKUP($D27,BS연결,MATCH(L$1,BS연결H,0),0)/100,"") | ... AB27: =IFERROR(VLOOKUP($D27,BS연결,MATCH(AB$1,BS연결H,0),0)/100,"") | AC27: =IFERROR(AB27+AC20-변수!AC34,"") | AD27: =IFERROR(AC27+AD20-변수!AD34,"") | AE27: =AD27 | AF27: =IFERROR(AD27+AF20-변수!AF34,"") | AG27: =IFERROR(AF27+AG20-변수!AG34,"") | AH27: =IFERROR(AG27+AH20-변수!AH34,"") | AI27: =IFERROR(AH27+AI20-변수!AI34,"") | AJ27: =AI27 | AK27: =IFERROR(AI27+AK20-변수!AK34,"") | AL27: =IFERROR(AK27+AL20-변수!AL34,"") | AM27: =IFERROR(AL27+AM20-변수!AM34,"") | AN27: =IFERROR(AM27+AN20-변수!AN34,"") | AO27: =AN27
A28: 지배주주지분 | B28: 재무상태 | C28: 억원 | D28: 지배주주지분 | E28: =IFERROR(VLOOKUP($D28,BS연결,MATCH(E$1,BS연결H,0),0)/100,"") | F28: =IFERROR(VLOOKUP($D28,BS연결,MATCH(F$1,BS연결H,0),0)/100,"") | G28: =IFERROR(VLOOKUP($D28,BS연결,MATCH(G$1,BS연결H,0),0)/100,"") | H28: =IFERROR(VLOOKUP($D28,BS연결,MATCH(H$1,BS연결H,0),0)/100,"") | I28: =IFERROR(VLOOKUP($D28,BS연결,MATCH(I$1,BS연결H,0),0)/100,"") | J28: =IFERROR(VLOOKUP($D28,BS연결,MATCH(J$1,BS연결H,0),0)/100,"") | K28: =IFERROR(VLOOKUP($D28,BS연결,MATCH(K$1,BS연결H,0),0)/100,"") | L28: =IFERROR(VLOOKUP($D28,BS연결,MATCH(L$1,BS연결H,0),0)/100,"") | ... AB28: =IFERROR(VLOOKUP($D28,BS연결,MATCH(AB$1,BS연결H,0),0)/100,"") | AC28: =IFERROR(AB28+AC21-변수!AC35,"") | AD28: =IFERROR(AC28+AD21-변수!AD35,"") | AE28: =AD28 | AF28: =IFERROR(AD28+AF21-변수!AF35,"") | AG28: =IFERROR(AF28+AG21-변수!AG35,"") | AH28: =IFERROR(AG28+AH21-변수!AH35,"") | AI28: =IFERROR(AH28+AI21-변수!AI35,"") | AJ28: =AI28 | AK28: =IFERROR(AI28+AK21-변수!AK35,"") | AL28: =IFERROR(AK28+AL21-변수!AL35,"") | AM28: =IFERROR(AL28+AM21-변수!AM35,"") | AN28: =IFERROR(AM28+AN21-변수!AN35,"") | AO28: =AN28
A29: 총차입금 | B29: 재무상태 | C29: 억원 | D29: 총차입금 | E29: =IFERROR(VLOOKUP($D29,BS연결,MATCH(E$1,BS연결H,0),0)/100,"") | F29: =IFERROR(VLOOKUP($D29,BS연결,MATCH(F$1,BS연결H,0),0)/100,"") | G29: =IFERROR(VLOOKUP($D29,BS연결,MATCH(G$1,BS연결H,0),0)/100,"") | H29: =IFERROR(VLOOKUP($D29,BS연결,MATCH(H$1,BS연결H,0),0)/100,"") | I29: =IFERROR(VLOOKUP($D29,BS연결,MATCH(I$1,BS연결H,0),0)/100,"") | J29: =IFERROR(VLOOKUP($D29,BS연결,MATCH(J$1,BS연결H,0),0)/100,"") | K29: =IFERROR(VLOOKUP($D29,BS연결,MATCH(K$1,BS연결H,0),0)/100,"") | L29: =IFERROR(VLOOKUP($D29,BS연결,MATCH(L$1,BS연결H,0),0)/100,"") | ... AB29: =IFERROR(VLOOKUP($D29,BS연결,MATCH(AB$1,BS연결H,0),0)/100,"") | AC29: =IFERROR(AB29*(1+변수!AC36),"") | AD29: =IFERROR(AC29*(1+변수!AD36),"") | AE29: =AD29 | AF29: =IFERROR(AD29*(1+변수!AF36),"") | AG29: =IFERROR(AF29*(1+변수!AG36),"") | AH29: =IFERROR(AG29*(1+변수!AH36),"") | AI29: =IFERROR(AH29*(1+변수!AI36),"") | AJ29: =AI29 | AK29: =IFERROR(AI29*(1+변수!AK36),"") | AL29: =IFERROR(AK29*(1+변수!AL36),"") | AM29: =IFERROR(AL29*(1+변수!AM36),"") | AN29: =IFERROR(AM29*(1+변수!AN36),"") | AO29: =AN29
A30: 순차입금 | B30: 재무상태 | C30: 억원 | D30: 순차입금 | E30: =IFERROR(VLOOKUP($D30,BS연결,MATCH(E$1,BS연결H,0),0)/100,"") | F30: =IFERROR(VLOOKUP($D30,BS연결,MATCH(F$1,BS연결H,0),0)/100,"") | G30: =IFERROR(VLOOKUP($D30,BS연결,MATCH(G$1,BS연결H,0),0)/100,"") | H30: =IFERROR(VLOOKUP($D30,BS연결,MATCH(H$1,BS연결H,0),0)/100,"") | I30: =IFERROR(VLOOKUP($D30,BS연결,MATCH(I$1,BS연결H,0),0)/100,"") | J30: =IFERROR(VLOOKUP($D30,BS연결,MATCH(J$1,BS연결H,0),0)/100,"") | K30: =IFERROR(VLOOKUP($D30,BS연결,MATCH(K$1,BS연결H,0),0)/100,"") | L30: =IFERROR(VLOOKUP($D30,BS연결,MATCH(L$1,BS연결H,0),0)/100,"") | ... AB30: =IFERROR(VLOOKUP($D30,BS연결,MATCH(AB$1,BS연결H,0),0)/100,"") | AC30: =IFERROR(AB30*(1+변수!AC37),"") | AD30: =IFERROR(AC30*(1+변수!AD37),"") | AE30: =AD30 | AF30: =IFERROR(AD30*(1+변수!AF37),"") | AG30: =IFERROR(AF30*(1+변수!AG37),"") | AH30: =IFERROR(AG30*(1+변수!AH37),"") | AI30: =IFERROR(AH30*(1+변수!AI37),"") | AJ30: =AI30 | AK30: =IFERROR(AI30*(1+변수!AK37),"") | AL30: =IFERROR(AK30*(1+변수!AL37),"") | AM30: =IFERROR(AL30*(1+변수!AM37),"") | AN30: =IFERROR(AM30*(1+변수!AN37),"") | AO30: =AN30
A31: 이자발생자산 | B31: 재무상태 | C31: 억원 | D31: 이자발생자산 | E31: =IFERROR(VLOOKUP($D31,BS연결,MATCH(E$1,BS연결H,0),0)/100,"") | F31: =IFERROR(VLOOKUP($D31,BS연결,MATCH(F$1,BS연결H,0),0)/100,"") | G31: =IFERROR(VLOOKUP($D31,BS연결,MATCH(G$1,BS연결H,0),0)/100,"") | H31: =IFERROR(VLOOKUP($D31,BS연결,MATCH(H$1,BS연결H,0),0)/100,"") | I31: =IFERROR(VLOOKUP($D31,BS연결,MATCH(I$1,BS연결H,0),0)/100,"") | J31: =IFERROR(VLOOKUP($D31,BS연결,MATCH(J$1,BS연결H,0),0)/100,"") | K31: =IFERROR(VLOOKUP($D31,BS연결,MATCH(K$1,BS연결H,0),0)/100,"") | L31: =IFERROR(VLOOKUP($D31,BS연결,MATCH(L$1,BS연결H,0),0)/100,"") | ... AB31: =IFERROR(VLOOKUP($D31,BS연결,MATCH(AB$1,BS연결H,0),0)/100,"") | AC31: =IFERROR(AB31*(1+변수!AC38),"") | AD31: =IFERROR(AC31*(1+변수!AD38),"") | AE31: =AD31 | AF31: =IFERROR(AD31*(1+변수!AF38),"") | AG31: =IFERROR(AF31*(1+변수!AG38),"") | AH31: =IFERROR(AG31*(1+변수!AH38),"") | AI31: =IFERROR(AH31*(1+변수!AI38),"") | AJ31: =AI31 | AK31: =IFERROR(AI31*(1+변수!AK38),"") | AL31: =IFERROR(AK31*(1+변수!AL38),"") | AM31: =IFERROR(AL31*(1+변수!AM38),"") | AN31: =IFERROR(AM31*(1+변수!AN38),"") | AO31: =AN31
A32: 현금및현금성자산 | B32: 재무상태 | C32: 억원 | D32: 현금및현금성자산 | E32: =IFERROR(VLOOKUP($D32,BS연결,MATCH(E$1,BS연결H,0),0)/100,"") | F32: =IFERROR(VLOOKUP($D32,BS연결,MATCH(F$1,BS연결H,0),0)/100,"") | G32: =IFERROR(VLOOKUP($D32,BS연결,MATCH(G$1,BS연결H,0),0)/100,"") | H32: =IFERROR(VLOOKUP($D32,BS연결,MATCH(H$1,BS연결H,0),0)/100,"") | I32: =IFERROR(VLOOKUP($D32,BS연결,MATCH(I$1,BS연결H,0),0)/100,"") | J32: =IFERROR(VLOOKUP($D32,BS연결,MATCH(J$1,BS연결H,0),0)/100,"") | K32: =IFERROR(VLOOKUP($D32,BS연결,MATCH(K$1,BS연결H,0),0)/100,"") | L32: =IFERROR(VLOOKUP($D32,BS연결,MATCH(L$1,BS연결H,0),0)/100,"") | ... AB32: =IFERROR(VLOOKUP($D32,BS연결,MATCH(AB$1,BS연결H,0),0)/100,"") | AE32: =AD32 | AJ32: =AI32 | AO32: =AN32
A33: CAPEX | B33: 현금흐름 | C33: 억원 | D33: CAPEX | E33: =IFERROR(VLOOKUP($D33,BS연결,MATCH(E$1,BS연결H,0),0)/100,"") | G33: =IFERROR(VLOOKUP($D33,BS연결,MATCH(G$1,BS연결H,0),0)/100,"") | H33: =IFERROR(VLOOKUP($D33,BS연결,MATCH(H$1,BS연결H,0),0)/100,"") | I33: =IFERROR(VLOOKUP($D33,BS연결,MATCH(I$1,BS연결H,0),0)/100,"") | J33: =IFERROR(VLOOKUP($D33,BS연결,MATCH(J$1,BS연결H,0),0)/100,"") | K33: =IFERROR(VLOOKUP($D33,BS연결,MATCH(K$1,BS연결H,0),0)/100,"") | L33: =IFERROR(VLOOKUP($D33,BS연결,MATCH(L$1,BS연결H,0),0)/100,"") | M33: =IFERROR(VLOOKUP($D33,BS연결,MATCH(M$1,BS연결H,0),0)/100,"") | N33: =IFERROR(VLOOKUP($D33,BS연결,MATCH(N$1,BS연결H,0),0)/100,"") | ... AB33: =IFERROR(VLOOKUP($D33,BS연결,MATCH(AB$1,BS연결H,0),0)/100,"") | AC33: =IFERROR(X33*(1+변수!AC40),"") | AD33: =IFERROR(Y33*(1+변수!AD40),"") | AE33: =SUM(AA33:AD33) | AF33: =IFERROR(AA33*(1+변수!AF40),"") | AG33: =IFERROR(AB33*(1+변수!AG40),"") | AH33: =IFERROR(AC33*(1+변수!AH40),"") | AI33: =IFERROR(AD33*(1+변수!AI40),"") | AJ33: =SUM(AF33:AI33) | AK33: =IFERROR(AF33*(1+변수!AK40),"") | AL33: =IFERROR(AG33*(1+변수!AL40),"") | AM33: =IFERROR(AH33*(1+변수!AM40),"") | AN33: =IFERROR(AI33*(1+변수!AN40),"") | AO33: =SUM(AK33:AN33)
A34: 영업활동현금흐름 | B34: 현금흐름 | C34: 억원 | D34: 영업활동으로인한현금흐름 | E34: =IFERROR(VLOOKUP($D34,BS연결,MATCH(E$1,BS연결H,0),0)/100,"") | G34: =IFERROR(VLOOKUP($D34,BS연결,MATCH(G$1,BS연결H,0),0)/100,"") | H34: =IFERROR(VLOOKUP($D34,BS연결,MATCH(H$1,BS연결H,0),0)/100,"") | I34: =IFERROR(VLOOKUP($D34,BS연결,MATCH(I$1,BS연결H,0),0)/100,"") | J34: =IFERROR(VLOOKUP($D34,BS연결,MATCH(J$1,BS연결H,0),0)/100,"") | K34: =IFERROR(VLOOKUP($D34,BS연결,MATCH(K$1,BS연결H,0),0)/100,"") | L34: =IFERROR(VLOOKUP($D34,BS연결,MATCH(L$1,BS연결H,0),0)/100,"") | M34: =IFERROR(VLOOKUP($D34,BS연결,MATCH(M$1,BS연결H,0),0)/100,"") | N34: =IFERROR(VLOOKUP($D34,BS연결,MATCH(N$1,BS연결H,0),0)/100,"") | ... AB34: =IFERROR(VLOOKUP($D34,BS연결,MATCH(AB$1,BS연결H,0),0)/100,"") | AE34: =SUM(AA34:AD34) | AJ34: =SUM(AF34:AI34) | AO34: =SUM(AK34:AN34)
A35: 주식수 | B35: 주당 | C35: 백만주 | D35: 유통주식수 | E35: 7.658 | F35: =E35 | G35: 7.409 | H35: 7.354 | I35: 7.354 | J35: 7.354 | K35: =J35 | L35: 7.354 | M35: 7.354 | N35: 7.354 | O35: 7.354 | P35: =O35 | Q35: 7.354 | R35: 7.354 | S35: 7.354 | T35: 7.354 | U35: =T35 | V35: 7.354 | W35: 7.354 | X35: 7.354 | Y35: 7.354 | Z35: =Y35 | AA35: 7.354 | AB35: 7.354 | AC35: =IFERROR(AB35*(1+변수!AC42),"") | AD35: =IFERROR(AC35*(1+변수!AD42),"") | AE35: =AD35 | AF35: =IFERROR(AD35*(1+변수!AF42),"") | AG35: =IFERROR(AF35*(1+변수!AG42),"") | AH35: =IFERROR(AG35*(1+변수!AH42),"") | AI35: =IFERROR(AH35*(1+변수!AI42),"") | AJ35: =AI35 | AK35: =IFERROR(AI35*(1+변수!AK42),"") | AL35: =IFERROR(AK35*(1+변수!AL42),"") | AM35: =IFERROR(AL35*(1+변수!AM42),"") | AN35: =IFERROR(AM35*(1+변수!AN42),"") | AO35: =AN35
A36: EPS | B36: 주당 | C36: 원 | D36: EPS | E36: =IFERROR(E21*100/E35,"") | G36: =IFERROR(G21*100/G35,"") | H36: =IFERROR(H21*100/H35,"") | I36: =IFERROR(I21*100/I35,"") | J36: =IFERROR(J21*100/J35,"") | K36: =SUM(G36:J36) | L36: =IFERROR(L21*100/L35,"") | M36: =IFERROR(M21*100/M35,"") | N36: =IFERROR(N21*100/N35,"") | O36: =IFERROR(O21*100/O35,"") | P36: =SUM(L36:O36) | Q36: =IFERROR(Q21*100/Q35,"") | R36: =IFERROR(R21*100/R35,"") | S36: =IFERROR(S21*100/S35,"") | T36: =IFERROR(T21*100/T35,"") | U36: =SUM(Q36:T36) | V36: =IFERROR(V21*100/V35,"") | W36: =IFERROR(W21*100/W35,"") | X36: =IFERROR(X21*100/X35,"") | Y36: =IFERROR(Y21*100/Y35,"") | Z36: =SUM(V36:Y36) | AA36: =IFERROR(AA21*100/AA35,"") | AB36: =IFERROR(AB21*100/AB35,"") | AC36: =IFERROR(AC21*100/AC35,"") | AD36: =IFERROR(AD21*100/AD35,"") | AE36: =SUM(AA36:AD36) | AF36: =IFERROR(AF21*100/AF35,"") | AG36: =IFERROR(AG21*100/AG35,"") | AH36: =IFERROR(AH21*100/AH35,"") | AI36: =IFERROR(AI21*100/AI35,"") | AJ36: =SUM(AF36:AI36) | AK36: =IFERROR(AK21*100/AK35,"") | AL36: =IFERROR(AL21*100/AL35,"") | AM36: =IFERROR(AM21*100/AM35,"") | AN36: =IFERROR(AN21*100/AN35,"") | AO36: =SUM(AK36:AN36)
A37: 조정EPS | B37: 주당 | C37: 원 | D37: 조정 EPS(일회성 의심 분기의 초과 비영업손익 세후 차감 — 모델 추정) | E37: =IFERROR(E36,"") | G37: =IFERROR(G36,"") | H37: =IFERROR(H36,"") | I37: =IFERROR(I36,"") | J37: =IFERROR(J36,"") | K37: =SUM(G37:J37) | L37: =IFERROR(L36,"") | M37: =IFERROR(M36,"") | N37: =IFERROR(N36,"") | O37: =IFERROR(O36,"") | P37: =SUM(L37:O37) | Q37: =IFERROR(Q36,"") | R37: =IFERROR(R36,"") | S37: =IFERROR(S36,"") | T37: =IFERROR(T36,"") | U37: =SUM(Q37:T37) | V37: =IFERROR(V36,"") | W37: =IFERROR(W36,"") | X37: =IFERROR(X36,"") | Y37: =IFERROR(Y36,"") | Z37: =SUM(V37:Y37) | AA37: =IFERROR(AA36,"") | AB37: =IFERROR((AB21-(27630.69)*(1.0))*100/AB35,"") | AC37: =IFERROR(AC36,"") | AD37: =IFERROR(AD36,"") | AE37: =SUM(AA37:AD37) | AF37: =IFERROR(AF36,"") | AG37: =IFERROR(AG36,"") | AH37: =IFERROR(AH36,"") | AI37: =IFERROR(AI36,"") | AJ37: =SUM(AF37:AI37) | AK37: =IFERROR(AK36,"") | AL37: =IFERROR(AL36,"") | AM37: =IFERROR(AM36,"") | AN37: =IFERROR(AN36,"") | AO37: =SUM(AK37:AN37)
A38: BPS | B38: 주당 | C38: 원 | D38: BPS | E38: =IFERROR(E28*100/E35,"") | F38: =E38 | G38: =IFERROR(G28*100/G35,"") | H38: =IFERROR(H28*100/H35,"") | I38: =IFERROR(I28*100/I35,"") | J38: =IFERROR(J28*100/J35,"") | K38: =J38 | L38: =IFERROR(L28*100/L35,"") | M38: =IFERROR(M28*100/M35,"") | N38: =IFERROR(N28*100/N35,"") | O38: =IFERROR(O28*100/O35,"") | P38: =O38 | Q38: =IFERROR(Q28*100/Q35,"") | R38: =IFERROR(R28*100/R35,"") | S38: =IFERROR(S28*100/S35,"") | T38: =IFERROR(T28*100/T35,"") | U38: =T38 | V38: =IFERROR(V28*100/V35,"") | W38: =IFERROR(W28*100/W35,"") | X38: =IFERROR(X28*100/X35,"") | Y38: =IFERROR(Y28*100/Y35,"") | Z38: =Y38 | AA38: =IFERROR(AA28*100/AA35,"") | AB38: =IFERROR(AB28*100/AB35,"") | AC38: =IFERROR(AC28*100/AC35,"") | AD38: =IFERROR(AD28*100/AD35,"") | AE38: =AD38 | AF38: =IFERROR(AF28*100/AF35,"") | AG38: =IFERROR(AG28*100/AG35,"") | AH38: =IFERROR(AH28*100/AH35,"") | AI38: =IFERROR(AI28*100/AI35,"") | AJ38: =AI38 | AK38: =IFERROR(AK28*100/AK35,"") | AL38: =IFERROR(AL28*100/AL35,"") | AM38: =IFERROR(AM28*100/AM35,"") | AN38: =IFERROR(AN28*100/AN35,"") | AO38: =AN38
A39: DPS | B39: 주당 | C39: 원 | D39: DPS(보통주) | E39: 7000 | F39: 7000 | J39: 8000 | K39: =SUM(G39:J39) | O39: 8000 | P39: =SUM(L39:O39) | T39: 10000 | U39: =SUM(Q39:T39) | Y39: 15000 | Z39: =SUM(V39:Y39) | AD39: =변수!AD43 | AE39: =SUM(AA39:AD39) | AI39: =변수!AI43 | AJ39: =SUM(AF39:AI39) | AN39: =변수!AN43 | AO39: =SUM(AK39:AN39)
A40: PER | B40: 주당 | C40: 배 | D40: PER | F40: =E40 | J40: =IFERROR(변수!J18/(G36+H36+I36+J36),"") | K40: =J40 | L40: =IFERROR(변수!L18/(H36+I36+J36+L36),"") | N40: =IFERROR(변수!N18/(J36+L36+M36+N36),"") | O40: =IFERROR(변수!O18/(L36+M36+N36+O36),"") | P40: =O40 | Q40: =IFERROR(변수!Q18/(M36+N36+O36+Q36),"") | R40: =IFERROR(변수!R18/(N36+O36+Q36+R36),"") | S40: =IFERROR(변수!S18/(O36+Q36+R36+S36),"") | T40: =IFERROR(변수!T18/(Q36+R36+S36+T36),"") | U40: =T40 | W40: =IFERROR(변수!W18/(S36+T36+V36+W36),"") | X40: =IFERROR(변수!X18/(T36+V36+W36+X36),"") | Y40: =IFERROR(변수!Y18/(V36+W36+X36+Y36),"") | Z40: =Y40 | AA40: =IFERROR(변수!AA18/(W36+X36+Y36+AA36),"") | AB40: =IFERROR(변수!AB18/(X36+Y36+AA36+AB36),"") | AC40: =IFERROR(변수!$D$46/(Y36+AA36+AB36+AC36),"") | AD40: =IFERROR(변수!$D$46/(AA36+AB36+AC36+AD36),"") | AE40: =AD40 | AF40: =IFERROR(변수!$D$46/(AB36+AC36+AD36+AF36),"") | AG40: =IFERROR(변수!$D$46/(AC36+AD36+AF36+AG36),"") | AH40: =IFERROR(변수!$D$46/(AD36+AF36+AG36+AH36),"") | AI40: =IFERROR(변수!$D$46/(AF36+AG36+AH36+AI36),"") | AJ40: =AI40 | AK40: =IFERROR(변수!$D$46/(AG36+AH36+AI36+AK36),"") | AL40: =IFERROR(변수!$D$46/(AH36+AI36+AK36+AL36),"") | AM40: =IFERROR(변수!$D$46/(AI36+AK36+AL36+AM36),"") | AN40: =IFERROR(변수!$D$46/(AK36+AL36+AM36+AN36),"") | AO40: =AN40
A41: PBR | B41: 주당 | C41: 배 | D41: PBR | E41: =IFERROR(변수!E18/E38,"") | F41: =E41 | G41: =IFERROR(변수!G18/G38,"") | H41: =IFERROR(변수!H18/H38,"") | I41: =IFERROR(변수!I18/I38,"") | J41: =IFERROR(변수!J18/J38,"") | K41: =J41 | L41: =IFERROR(변수!L18/L38,"") | M41: =IFERROR(변수!M18/M38,"") | N41: =IFERROR(변수!N18/N38,"") | O41: =IFERROR(변수!O18/O38,"") | P41: =O41 | Q41: =IFERROR(변수!Q18/Q38,"") | R41: =IFERROR(변수!R18/R38,"") | S41: =IFERROR(변수!S18/S38,"") | T41: =IFERROR(변수!T18/T38,"") | U41: =T41 | V41: =IFERROR(변수!V18/V38,"") | W41: =IFERROR(변수!W18/W38,"") | X41: =IFERROR(변수!X18/X38,"") | Y41: =IFERROR(변수!Y18/Y38,"") | Z41: =Y41 | AA41: =IFERROR(변수!AA18/AA38,"") | AB41: =IFERROR(변수!AB18/AB38,"") | AC41: =IFERROR(변수!$D$46/AC38,"") | AD41: =IFERROR(변수!$D$46/AD38,"") | AE41: =AD41 | AF41: =IFERROR(변수!$D$46/AF38,"") | AG41: =IFERROR(변수!$D$46/AG38,"") | AH41: =IFERROR(변수!$D$46/AH38,"") | AI41: =IFERROR(변수!$D$46/AI38,"") | AJ41: =AI41 | AK41: =IFERROR(변수!$D$46/AK38,"") | AL41: =IFERROR(변수!$D$46/AL38,"") | AM41: =IFERROR(변수!$D$46/AM38,"") | AN41: =IFERROR(변수!$D$46/AN38,"") | AO41: =AN41
A42: 매출전사 | B42: 사업부 | C42: 억원 | D42: 매출 전사(부문 미분리) | E42: 15097.4 | G42: 16375.78 | H42: 17558.82 | I42: 17401.25 | J42: 16412.08 | K42: =SUM(G42:J42) | L42: 15649.43 | M42: 15883.45 | N42: 15527.25 | O42: 15824.3 | P42: =SUM(L42:O42) | Q42: 15883.72 | R42: 17787.28 | S42: 16342.08 | T42: 16574.55 | U42: =SUM(Q42:T42) | V42: 15993.05 | W42: 17052.64 | X42: 16228.33 | Y42: 15564.18 | Z42: =SUM(V42:Y42) | AA42: 16264 | AB42: 18060.19 | AC42: =IFERROR(AC5,"") | AD42: =IFERROR(AD5,"") | AE42: =SUM(AA42:AD42) | AF42: =IFERROR(AF5,"") | AG42: =IFERROR(AG5,"") | AH42: =IFERROR(AH5,"") | AI42: =IFERROR(AI5,"") | AJ42: =SUM(AF42:AI42) | AK42: =IFERROR(AK5,"") | AL42: =IFERROR(AL5,"") | AM42: =IFERROR(AM5,"") | AN42: =IFERROR(AN5,"") | AO42: =SUM(AK42:AN42)
A43: OP전사 | B43: 사업부 | C43: 억원 | D43: OP 전사(부문 미분리) | E43: 743.9 | G43: 1494.08 | H43: 1642.34 | I43: 963.8 | J43: 576.41 | K43: =SUM(G43:J43) | L43: 758.28 | M43: 903.84 | N43: 884.3 | O43: 578.89 | P43: =SUM(L43:O43) | Q43: 1069.07 | R43: 1405.61 | S43: 1253.29 | T43: 983.22 | U43: =SUM(Q43:T43) | V43: 1034.44 | W43: 1403.81 | X43: 1172.64 | Y43: 665.27 | Z43: =SUM(V43:Y43) | AA43: 881.28 | AB43: 1288.84 | AC43: =IFERROR(AC9,"") | AD43: =IFERROR(AD9,"") | AE43: =SUM(AA43:AD43) | AF43: =IFERROR(AF9,"") | AG43: =IFERROR(AG9,"") | AH43: =IFERROR(AH9,"") | AI43: =IFERROR(AI9,"") | AJ43: =SUM(AF43:AI43) | AK43: =IFERROR(AK9,"") | AL43: =IFERROR(AL9,"") | AM43: =IFERROR(AM9,"") | AN43: =IFERROR(AN9,"") | AO43: =SUM(AK43:AN43)
B44: 비율(참고)
A45: NPM | C45: % | D45: 지배주주순이익 / 매출액 | E45: =IFERROR(E21/E5,"") | F45: =IFERROR(F21/F5,"") | G45: =IFERROR(G21/G5,"") | H45: =IFERROR(H21/H5,"") | I45: =IFERROR(I21/I5,"") | J45: =IFERROR(J21/J5,"") | K45: =IFERROR(K21/K5,"") | L45: =IFERROR(L21/L5,"") | ... AO45: =IFERROR(AO21/AO5,"")
A46: 매출원가율 | C46: % | D46: 매출원가 / 매출액 | E46: =IFERROR(E6/E5,"") | F46: =IFERROR(F6/F5,"") | G46: =IFERROR(G6/G5,"") | H46: =IFERROR(H6/H5,"") | I46: =IFERROR(I6/I5,"") | J46: =IFERROR(J6/J5,"") | K46: =IFERROR(K6/K5,"") | L46: =IFERROR(L6/L5,"") | ... AO46: =IFERROR(AO6/AO5,"")
A47: 판관비율 | C47: % | D47: 판관비 / 매출액 | E47: =IFERROR(E8/E5,"") | F47: =IFERROR(F8/F5,"") | G47: =IFERROR(G8/G5,"") | H47: =IFERROR(H8/H5,"") | I47: =IFERROR(I8/I5,"") | J47: =IFERROR(J8/J5,"") | K47: =IFERROR(K8/K5,"") | L47: =IFERROR(L8/L5,"") | ... AO47: =IFERROR(AO8/AO5,"")

Sheet 분기
C1: 이름: 분기H — subQ 를 이름으로 VLOOKUP(억원) | E1: 4Q21 | F1: 1Q22 | G1: 2Q22 | H1: 3Q22 | I1: 4Q22 | J1: 1Q23 | K1: 2Q23 | L1: 3Q23 | M1: 4Q23 | N1: 1Q24 | O1: 2Q24 | P1: 3Q24 | Q1: 4Q24 | R1: 1Q25 | S1: 2Q25 | T1: 3Q25 | U1: 4Q25 | V1: 1Q26 | W1: 2Q26 | X1: 3Q26 | Y1: 4Q26 | Z1: 1Q27 | AA1: 2Q27 | AB1: 3Q27 | AC1: 4Q27 | AD1: 1Q28 | AE1: 2Q28 | AF1: 3Q28 | AG1: 4Q28
C2: 종가: | D2: =변수!D46
C3: 기준일: | D3: 20261012 | E3: 1 | F3: 2 | G3: 3 | H3: 4 | I3: 5 | J3: 6 | K3: 7 | L3: 8 | M3: 9 | N3: 10 | O3: 11 | P3: 12 | Q3: 13 | R3: 14 | S3: 15 | T3: 16 | U3: 17 | V3: 18 | W3: 19 | X3: 20 | Y3: 21 | Z3: 22 | AA3: 23 | AB3: 24 | AC3: 25 | AD3: 26 | AE3: 27 | AF3: 28 | AG3: 29
E4: 2021.12 | F4: 2022.03 | G4: 2022.06 | H4: 2022.09 | I4: 2022.12 | J4: 2023.03 | K4: 2023.06 | L4: 2023.09 | M4: 2023.12 | N4: 2024.03 | O4: 2024.06 | P4: 2024.09 | Q4: 2024.12 | R4: 2025.03 | S4: 2025.06 | T4: 2025.09 | U4: 2025.12 | V4: 2026.03 | W4: 2026.06 | X4: 2026.09 | Y4: 2026.12 | Z4: 2027.03 | AA4: 2027.06 | AB4: 2027.09 | AC4: 2027.12 | AD4: 2028.03 | AE4: 2028.06 | AF4: 2028.09 | AG4: 2028.12
A5: 매출액 | D5: 매출액 | E5: =IFERROR(VLOOKUP($A5,subQ,MATCH(E$1,SUBQH,0),0),"") | F5: =IFERROR(VLOOKUP($A5,subQ,MATCH(F$1,SUBQH,0),0),"") | G5: =IFERROR(VLOOKUP($A5,subQ,MATCH(G$1,SUBQH,0),0),"") | H5: =IFERROR(VLOOKUP($A5,subQ,MATCH(H$1,SUBQH,0),0),"") | I5: =IFERROR(VLOOKUP($A5,subQ,MATCH(I$1,SUBQH,0),0),"") | J5: =IFERROR(VLOOKUP($A5,subQ,MATCH(J$1,SUBQH,0),0),"") | K5: =IFERROR(VLOOKUP($A5,subQ,MATCH(K$1,SUBQH,0),0),"") | L5: =IFERROR(VLOOKUP($A5,subQ,MATCH(L$1,SUBQH,0),0),"") | ... AG5: =IFERROR(VLOOKUP($A5,subQ,MATCH(AG$1,SUBQH,0),0),"")
A6: 매출원가 | D6: 매출원가 | E6: =IFERROR(VLOOKUP($A6,subQ,MATCH(E$1,SUBQH,0),0),"") | F6: =IFERROR(VLOOKUP($A6,subQ,MATCH(F$1,SUBQH,0),0),"") | G6: =IFERROR(VLOOKUP($A6,subQ,MATCH(G$1,SUBQH,0),0),"") | H6: =IFERROR(VLOOKUP($A6,subQ,MATCH(H$1,SUBQH,0),0),"") | I6: =IFERROR(VLOOKUP($A6,subQ,MATCH(I$1,SUBQH,0),0),"") | J6: =IFERROR(VLOOKUP($A6,subQ,MATCH(J$1,SUBQH,0),0),"") | K6: =IFERROR(VLOOKUP($A6,subQ,MATCH(K$1,SUBQH,0),0),"") | L6: =IFERROR(VLOOKUP($A6,subQ,MATCH(L$1,SUBQH,0),0),"") | ... AG6: =IFERROR(VLOOKUP($A6,subQ,MATCH(AG$1,SUBQH,0),0),"")
A7: 매출총이익 | D7: 매출총이익 | E7: =IFERROR(VLOOKUP($A7,subQ,MATCH(E$1,SUBQH,0),0),"") | F7: =IFERROR(VLOOKUP($A7,subQ,MATCH(F$1,SUBQH,0),0),"") | G7: =IFERROR(VLOOKUP($A7,subQ,MATCH(G$1,SUBQH,0),0),"") | H7: =IFERROR(VLOOKUP($A7,subQ,MATCH(H$1,SUBQH,0),0),"") | I7: =IFERROR(VLOOKUP($A7,subQ,MATCH(I$1,SUBQH,0),0),"") | J7: =IFERROR(VLOOKUP($A7,subQ,MATCH(J$1,SUBQH,0),0),"") | K7: =IFERROR(VLOOKUP($A7,subQ,MATCH(K$1,SUBQH,0),0),"") | L7: =IFERROR(VLOOKUP($A7,subQ,MATCH(L$1,SUBQH,0),0),"") | ... AG7: =IFERROR(VLOOKUP($A7,subQ,MATCH(AG$1,SUBQH,0),0),"")
A8: 판관비 | D8: 판매비와관리비 | E8: =IFERROR(VLOOKUP($A8,subQ,MATCH(E$1,SUBQH,0),0),"") | F8: =IFERROR(VLOOKUP($A8,subQ,MATCH(F$1,SUBQH,0),0),"") | G8: =IFERROR(VLOOKUP($A8,subQ,MATCH(G$1,SUBQH,0),0),"") | H8: =IFERROR(VLOOKUP($A8,subQ,MATCH(H$1,SUBQH,0),0),"") | I8: =IFERROR(VLOOKUP($A8,subQ,MATCH(I$1,SUBQH,0),0),"") | J8: =IFERROR(VLOOKUP($A8,subQ,MATCH(J$1,SUBQH,0),0),"") | K8: =IFERROR(VLOOKUP($A8,subQ,MATCH(K$1,SUBQH,0),0),"") | L8: =IFERROR(VLOOKUP($A8,subQ,MATCH(L$1,SUBQH,0),0),"") | ... AG8: =IFERROR(VLOOKUP($A8,subQ,MATCH(AG$1,SUBQH,0),0),"")
A9: 영업이익 | D9: 영업이익 | E9: =IFERROR(VLOOKUP($A9,subQ,MATCH(E$1,SUBQH,0),0),"") | F9: =IFERROR(VLOOKUP($A9,subQ,MATCH(F$1,SUBQH,0),0),"") | G9: =IFERROR(VLOOKUP($A9,subQ,MATCH(G$1,SUBQH,0),0),"") | H9: =IFERROR(VLOOKUP($A9,subQ,MATCH(H$1,SUBQH,0),0),"") | I9: =IFERROR(VLOOKUP($A9,subQ,MATCH(I$1,SUBQH,0),0),"") | J9: =IFERROR(VLOOKUP($A9,subQ,MATCH(J$1,SUBQH,0),0),"") | K9: =IFERROR(VLOOKUP($A9,subQ,MATCH(K$1,SUBQH,0),0),"") | L9: =IFERROR(VLOOKUP($A9,subQ,MATCH(L$1,SUBQH,0),0),"") | ... AG9: =IFERROR(VLOOKUP($A9,subQ,MATCH(AG$1,SUBQH,0),0),"")
A10: OPM | D10: 영업이익률 | E10: =IFERROR(VLOOKUP($A10,subQ,MATCH(E$1,SUBQH,0),0),"") | F10: =IFERROR(VLOOKUP($A10,subQ,MATCH(F$1,SUBQH,0),0),"") | G10: =IFERROR(VLOOKUP($A10,subQ,MATCH(G$1,SUBQH,0),0),"") | H10: =IFERROR(VLOOKUP($A10,subQ,MATCH(H$1,SUBQH,0),0),"") | I10: =IFERROR(VLOOKUP($A10,subQ,MATCH(I$1,SUBQH,0),0),"") | J10: =IFERROR(VLOOKUP($A10,subQ,MATCH(J$1,SUBQH,0),0),"") | K10: =IFERROR(VLOOKUP($A10,subQ,MATCH(K$1,SUBQH,0),0),"") | L10: =IFERROR(VLOOKUP($A10,subQ,MATCH(L$1,SUBQH,0),0),"") | ... AG10: =IFERROR(VLOOKUP($A10,subQ,MATCH(AG$1,SUBQH,0),0),"")
A11: 금융손익 | D11: 금융손익(이자·환 포함) | E11: =IFERROR(VLOOKUP($A11,subQ,MATCH(E$1,SUBQH,0),0),"") | F11: =IFERROR(VLOOKUP($A11,subQ,MATCH(F$1,SUBQH,0),0),"") | G11: =IFERROR(VLOOKUP($A11,subQ,MATCH(G$1,SUBQH,0),0),"") | H11: =IFERROR(VLOOKUP($A11,subQ,MATCH(H$1,SUBQH,0),0),"") | I11: =IFERROR(VLOOKUP($A11,subQ,MATCH(I$1,SUBQH,0),0),"") | J11: =IFERROR(VLOOKUP($A11,subQ,MATCH(J$1,SUBQH,0),0),"") | K11: =IFERROR(VLOOKUP($A11,subQ,MATCH(K$1,SUBQH,0),0),"") | L11: =IFERROR(VLOOKUP($A11,subQ,MATCH(L$1,SUBQH,0),0),"") | ... AG11: =IFERROR(VLOOKUP($A11,subQ,MATCH(AG$1,SUBQH,0),0),"")
A12: 이자손익 | D12: 이자손익(이자수익 − 이자비용) | E12: =IFERROR(VLOOKUP($A12,subQ,MATCH(E$1,SUBQH,0),0),"") | F12: =IFERROR(VLOOKUP($A12,subQ,MATCH(F$1,SUBQH,0),0),"") | G12: =IFERROR(VLOOKUP($A12,subQ,MATCH(G$1,SUBQH,0),0),"") | H12: =IFERROR(VLOOKUP($A12,subQ,MATCH(H$1,SUBQH,0),0),"") | I12: =IFERROR(VLOOKUP($A12,subQ,MATCH(I$1,SUBQH,0),0),"") | J12: =IFERROR(VLOOKUP($A12,subQ,MATCH(J$1,SUBQH,0),0),"") | K12: =IFERROR(VLOOKUP($A12,subQ,MATCH(K$1,SUBQH,0),0),"") | L12: =IFERROR(VLOOKUP($A12,subQ,MATCH(L$1,SUBQH,0),0),"") | ... AG12: =IFERROR(VLOOKUP($A12,subQ,MATCH(AG$1,SUBQH,0),0),"")
A13: 외환손익 | D13: 외환손익(실적만; 추정 환효과는 환관련손익) | E13: =IFERROR(VLOOKUP($A13,subQ,MATCH(E$1,SUBQH,0),0),"") | F13: =IFERROR(VLOOKUP($A13,subQ,MATCH(F$1,SUBQH,0),0),"") | G13: =IFERROR(VLOOKUP($A13,subQ,MATCH(G$1,SUBQH,0),0),"") | H13: =IFERROR(VLOOKUP($A13,subQ,MATCH(H$1,SUBQH,0),0),"") | I13: =IFERROR(VLOOKUP($A13,subQ,MATCH(I$1,SUBQH,0),0),"") | J13: =IFERROR(VLOOKUP($A13,subQ,MATCH(J$1,SUBQH,0),0),"") | K13: =IFERROR(VLOOKUP($A13,subQ,MATCH(K$1,SUBQH,0),0),"") | L13: =IFERROR(VLOOKUP($A13,subQ,MATCH(L$1,SUBQH,0),0),"") | ... AG13: =IFERROR(VLOOKUP($A13,subQ,MATCH(AG$1,SUBQH,0),0),"")
A14: 파생상품손익 | D14: 파생상품손익 | E14: =IFERROR(VLOOKUP($A14,subQ,MATCH(E$1,SUBQH,0),0),"") | F14: =IFERROR(VLOOKUP($A14,subQ,MATCH(F$1,SUBQH,0),0),"") | G14: =IFERROR(VLOOKUP($A14,subQ,MATCH(G$1,SUBQH,0),0),"") | H14: =IFERROR(VLOOKUP($A14,subQ,MATCH(H$1,SUBQH,0),0),"") | I14: =IFERROR(VLOOKUP($A14,subQ,MATCH(I$1,SUBQH,0),0),"") | J14: =IFERROR(VLOOKUP($A14,subQ,MATCH(J$1,SUBQH,0),0),"") | K14: =IFERROR(VLOOKUP($A14,subQ,MATCH(K$1,SUBQH,0),0),"") | L14: =IFERROR(VLOOKUP($A14,subQ,MATCH(L$1,SUBQH,0),0),"") | ... AG14: =IFERROR(VLOOKUP($A14,subQ,MATCH(AG$1,SUBQH,0),0),"")
A15: 기타금융손익 | D15: 기타금융손익(금융손익 잔차) | E15: =IFERROR(VLOOKUP($A15,subQ,MATCH(E$1,SUBQH,0),0),"") | F15: =IFERROR(VLOOKUP($A15,subQ,MATCH(F$1,SUBQH,0),0),"") | G15: =IFERROR(VLOOKUP($A15,subQ,MATCH(G$1,SUBQH,0),0),"") | H15: =IFERROR(VLOOKUP($A15,subQ,MATCH(H$1,SUBQH,0),0),"") | I15: =IFERROR(VLOOKUP($A15,subQ,MATCH(I$1,SUBQH,0),0),"") | J15: =IFERROR(VLOOKUP($A15,subQ,MATCH(J$1,SUBQH,0),0),"") | K15: =IFERROR(VLOOKUP($A15,subQ,MATCH(K$1,SUBQH,0),0),"") | L15: =IFERROR(VLOOKUP($A15,subQ,MATCH(L$1,SUBQH,0),0),"") | ... AG15: =IFERROR(VLOOKUP($A15,subQ,MATCH(AG$1,SUBQH,0),0),"")
A16: 기타영업외손익 | D16: 기타영업외손익 | E16: =IFERROR(VLOOKUP($A16,subQ,MATCH(E$1,SUBQH,0),0),"") | F16: =IFERROR(VLOOKUP($A16,subQ,MATCH(F$1,SUBQH,0),0),"") | G16: =IFERROR(VLOOKUP($A16,subQ,MATCH(G$1,SUBQH,0),0),"") | H16: =IFERROR(VLOOKUP($A16,subQ,MATCH(H$1,SUBQH,0),0),"") | I16: =IFERROR(VLOOKUP($A16,subQ,MATCH(I$1,SUBQH,0),0),"") | J16: =IFERROR(VLOOKUP($A16,subQ,MATCH(J$1,SUBQH,0),0),"") | K16: =IFERROR(VLOOKUP($A16,subQ,MATCH(K$1,SUBQH,0),0),"") | L16: =IFERROR(VLOOKUP($A16,subQ,MATCH(L$1,SUBQH,0),0),"") | ... AG16: =IFERROR(VLOOKUP($A16,subQ,MATCH(AG$1,SUBQH,0),0),"")
... A44: NPM | D44: NPM | E44: =IFERROR(VLOOKUP($A44,subQ,MATCH(E$1,SUBQH,0),0),"") | F44: =IFERROR(VLOOKUP($A44,subQ,MATCH(F$1,SUBQH,0),0),"") | G44: =IFERROR(VLOOKUP($A44,subQ,MATCH(G$1,SUBQH,0),0),"") | H44: =IFERROR(VLOOKUP($A44,subQ,MATCH(H$1,SUBQH,0),0),"") | I44: =IFERROR(VLOOKUP($A44,subQ,MATCH(I$1,SUBQH,0),0),"") | J44: =IFERROR(VLOOKUP($A44,subQ,MATCH(J$1,SUBQH,0),0),"") | K44: =IFERROR(VLOOKUP($A44,subQ,MATCH(K$1,SUBQH,0),0),"") | L44: =IFERROR(VLOOKUP($A44,subQ,MATCH(L$1,SUBQH,0),0),"") | ... AG44: =IFERROR(VLOOKUP($A44,subQ,MATCH(AG$1,SUBQH,0),0),"")
A45: 매출액 YoY | D45: 매출액 YoY | I45: =IFERROR(I5/E5-1,"") | J45: =IFERROR(J5/F5-1,"") | K45: =IFERROR(K5/G5-1,"") | L45: =IFERROR(L5/H5-1,"") | M45: =IFERROR(M5/I5-1,"") | N45: =IFERROR(N5/J5-1,"") | O45: =IFERROR(O5/K5-1,"") | P45: =IFERROR(P5/L5-1,"") | ... AG45: =IFERROR(AG5/AC5-1,"")
A46: 영업이익 YoY | D46: 영업이익 YoY | I46: =IFERROR(I9/E9-1,"") | J46: =IFERROR(J9/F9-1,"") | K46: =IFERROR(K9/G9-1,"") | L46: =IFERROR(L9/H9-1,"") | M46: =IFERROR(M9/I9-1,"") | N46: =IFERROR(N9/J9-1,"") | O46: =IFERROR(O9/K9-1,"") | P46: =IFERROR(P9/L9-1,"") | ... AG46: =IFERROR(AG9/AC9-1,"")
A47: 지배주주순이익 YoY | D47: 지배주주순이익 YoY | I47: =IFERROR(I21/E21-1,"") | J47: =IFERROR(J21/F21-1,"") | K47: =IFERROR(K21/G21-1,"") | L47: =IFERROR(L21/H21-1,"") | M47: =IFERROR(M21/I21-1,"") | N47: =IFERROR(N21/J21-1,"") | O47: =IFERROR(O21/K21-1,"") | P47: =IFERROR(P21/L21-1,"") | ... AG47: =IFERROR(AG21/AC21-1,"")

Sheet 연간예상
C1: 이름: 연간예상H — subQ 를 이름으로 VLOOKUP(억원) | E1: 2021 | F1: 2022 | G1: 2023 | H1: 2024 | I1: 2025 | J1: 2026 | K1: 2027 | L1: 2028
C2: 종가: | D2: =변수!D46
C3: 기준일: | D3: 20261012 | E3: 1 | F3: 2 | G3: 3 | H3: 4 | I3: 5 | J3: 6 | K3: 7 | L3: 8
E4: 2021.12A | F4: 2022.12A | G4: 2023.12A | H4: 2024.12A | I4: 2025.12A | J4: 2026.12A | K4: 2027.12A | L4: 2028.12A
A5: 매출액 | D5: 매출액 | E5: =IFERROR(VLOOKUP($A5,subQ,MATCH(E$1,SUBQH,0),0),"") | F5: =IFERROR(VLOOKUP($A5,subQ,MATCH(F$1,SUBQH,0),0),"") | G5: =IFERROR(VLOOKUP($A5,subQ,MATCH(G$1,SUBQH,0),0),"") | H5: =IFERROR(VLOOKUP($A5,subQ,MATCH(H$1,SUBQH,0),0),"") | I5: =IFERROR(VLOOKUP($A5,subQ,MATCH(I$1,SUBQH,0),0),"") | J5: =IFERROR(VLOOKUP($A5,subQ,MATCH(J$1,SUBQH,0),0),"") | K5: =IFERROR(VLOOKUP($A5,subQ,MATCH(K$1,SUBQH,0),0),"") | L5: =IFERROR(VLOOKUP($A5,subQ,MATCH(L$1,SUBQH,0),0),"")
A6: 매출원가 | D6: 매출원가 | E6: =IFERROR(VLOOKUP($A6,subQ,MATCH(E$1,SUBQH,0),0),"") | F6: =IFERROR(VLOOKUP($A6,subQ,MATCH(F$1,SUBQH,0),0),"") | G6: =IFERROR(VLOOKUP($A6,subQ,MATCH(G$1,SUBQH,0),0),"") | H6: =IFERROR(VLOOKUP($A6,subQ,MATCH(H$1,SUBQH,0),0),"") | I6: =IFERROR(VLOOKUP($A6,subQ,MATCH(I$1,SUBQH,0),0),"") | J6: =IFERROR(VLOOKUP($A6,subQ,MATCH(J$1,SUBQH,0),0),"") | K6: =IFERROR(VLOOKUP($A6,subQ,MATCH(K$1,SUBQH,0),0),"") | L6: =IFERROR(VLOOKUP($A6,subQ,MATCH(L$1,SUBQH,0),0),"")
A7: 매출총이익 | D7: 매출총이익 | E7: =IFERROR(VLOOKUP($A7,subQ,MATCH(E$1,SUBQH,0),0),"") | F7: =IFERROR(VLOOKUP($A7,subQ,MATCH(F$1,SUBQH,0),0),"") | G7: =IFERROR(VLOOKUP($A7,subQ,MATCH(G$1,SUBQH,0),0),"") | H7: =IFERROR(VLOOKUP($A7,subQ,MATCH(H$1,SUBQH,0),0),"") | I7: =IFERROR(VLOOKUP($A7,subQ,MATCH(I$1,SUBQH,0),0),"") | J7: =IFERROR(VLOOKUP($A7,subQ,MATCH(J$1,SUBQH,0),0),"") | K7: =IFERROR(VLOOKUP($A7,subQ,MATCH(K$1,SUBQH,0),0),"") | L7: =IFERROR(VLOOKUP($A7,subQ,MATCH(L$1,SUBQH,0),0),"")
A8: 판관비 | D8: 판매비와관리비 | E8: =IFERROR(VLOOKUP($A8,subQ,MATCH(E$1,SUBQH,0),0),"") | F8: =IFERROR(VLOOKUP($A8,subQ,MATCH(F$1,SUBQH,0),0),"") | G8: =IFERROR(VLOOKUP($A8,subQ,MATCH(G$1,SUBQH,0),0),"") | H8: =IFERROR(VLOOKUP($A8,subQ,MATCH(H$1,SUBQH,0),0),"") | I8: =IFERROR(VLOOKUP($A8,subQ,MATCH(I$1,SUBQH,0),0),"") | J8: =IFERROR(VLOOKUP($A8,subQ,MATCH(J$1,SUBQH,0),0),"") | K8: =IFERROR(VLOOKUP($A8,subQ,MATCH(K$1,SUBQH,0),0),"") | L8: =IFERROR(VLOOKUP($A8,subQ,MATCH(L$1,SUBQH,0),0),"")
A9: 영업이익 | D9: 영업이익 | E9: =IFERROR(VLOOKUP($A9,subQ,MATCH(E$1,SUBQH,0),0),"") | F9: =IFERROR(VLOOKUP($A9,subQ,MATCH(F$1,SUBQH,0),0),"") | G9: =IFERROR(VLOOKUP($A9,subQ,MATCH(G$1,SUBQH,0),0),"") | H9: =IFERROR(VLOOKUP($A9,subQ,MATCH(H$1,SUBQH,0),0),"") | I9: =IFERROR(VLOOKUP($A9,subQ,MATCH(I$1,SUBQH,0),0),"") | J9: =IFERROR(VLOOKUP($A9,subQ,MATCH(J$1,SUBQH,0),0),"") | K9: =IFERROR(VLOOKUP($A9,subQ,MATCH(K$1,SUBQH,0),0),"") | L9: =IFERROR(VLOOKUP($A9,subQ,MATCH(L$1,SUBQH,0),0),"")
A10: OPM | D10: 영업이익률 | E10: =IFERROR(VLOOKUP($A10,subQ,MATCH(E$1,SUBQH,0),0),"") | F10: =IFERROR(VLOOKUP($A10,subQ,MATCH(F$1,SUBQH,0),0),"") | G10: =IFERROR(VLOOKUP($A10,subQ,MATCH(G$1,SUBQH,0),0),"") | H10: =IFERROR(VLOOKUP($A10,subQ,MATCH(H$1,SUBQH,0),0),"") | I10: =IFERROR(VLOOKUP($A10,subQ,MATCH(I$1,SUBQH,0),0),"") | J10: =IFERROR(VLOOKUP($A10,subQ,MATCH(J$1,SUBQH,0),0),"") | K10: =IFERROR(VLOOKUP($A10,subQ,MATCH(K$1,SUBQH,0),0),"") | L10: =IFERROR(VLOOKUP($A10,subQ,MATCH(L$1,SUBQH,0),0),"")
A11: 금융손익 | D11: 금융손익(이자·환 포함) | E11: =IFERROR(VLOOKUP($A11,subQ,MATCH(E$1,SUBQH,0),0),"") | F11: =IFERROR(VLOOKUP($A11,subQ,MATCH(F$1,SUBQH,0),0),"") | G11: =IFERROR(VLOOKUP($A11,subQ,MATCH(G$1,SUBQH,0),0),"") | H11: =IFERROR(VLOOKUP($A11,subQ,MATCH(H$1,SUBQH,0),0),"") | I11: =IFERROR(VLOOKUP($A11,subQ,MATCH(I$1,SUBQH,0),0),"") | J11: =IFERROR(VLOOKUP($A11,subQ,MATCH(J$1,SUBQH,0),0),"") | K11: =IFERROR(VLOOKUP($A11,subQ,MATCH(K$1,SUBQH,0),0),"") | L11: =IFERROR(VLOOKUP($A11,subQ,MATCH(L$1,SUBQH,0),0),"")
A12: 이자손익 | D12: 이자손익(이자수익 − 이자비용) | E12: =IFERROR(VLOOKUP($A12,subQ,MATCH(E$1,SUBQH,0),0),"") | F12: =IFERROR(VLOOKUP($A12,subQ,MATCH(F$1,SUBQH,0),0),"") | G12: =IFERROR(VLOOKUP($A12,subQ,MATCH(G$1,SUBQH,0),0),"") | H12: =IFERROR(VLOOKUP($A12,subQ,MATCH(H$1,SUBQH,0),0),"") | I12: =IFERROR(VLOOKUP($A12,subQ,MATCH(I$1,SUBQH,0),0),"") | J12: =IFERROR(VLOOKUP($A12,subQ,MATCH(J$1,SUBQH,0),0),"") | K12: =IFERROR(VLOOKUP($A12,subQ,MATCH(K$1,SUBQH,0),0),"") | L12: =IFERROR(VLOOKUP($A12,subQ,MATCH(L$1,SUBQH,0),0),"")
A13: 외환손익 | D13: 외환손익(실적만; 추정 환효과는 환관련손익) | E13: =IFERROR(VLOOKUP($A13,subQ,MATCH(E$1,SUBQH,0),0),"") | F13: =IFERROR(VLOOKUP($A13,subQ,MATCH(F$1,SUBQH,0),0),"") | G13: =IFERROR(VLOOKUP($A13,subQ,MATCH(G$1,SUBQH,0),0),"") | H13: =IFERROR(VLOOKUP($A13,subQ,MATCH(H$1,SUBQH,0),0),"") | I13: =IFERROR(VLOOKUP($A13,subQ,MATCH(I$1,SUBQH,0),0),"") | J13: =IFERROR(VLOOKUP($A13,subQ,MATCH(J$1,SUBQH,0),0),"") | K13: =IFERROR(VLOOKUP($A13,subQ,MATCH(K$1,SUBQH,0),0),"") | L13: =IFERROR(VLOOKUP($A13,subQ,MATCH(L$1,SUBQH,0),0),"")
A14: 파생상품손익 | D14: 파생상품손익 | E14: =IFERROR(VLOOKUP($A14,subQ,MATCH(E$1,SUBQH,0),0),"") | F14: =IFERROR(VLOOKUP($A14,subQ,MATCH(F$1,SUBQH,0),0),"") | G14: =IFERROR(VLOOKUP($A14,subQ,MATCH(G$1,SUBQH,0),0),"") | H14: =IFERROR(VLOOKUP($A14,subQ,MATCH(H$1,SUBQH,0),0),"") | I14: =IFERROR(VLOOKUP($A14,subQ,MATCH(I$1,SUBQH,0),0),"") | J14: =IFERROR(VLOOKUP($A14,subQ,MATCH(J$1,SUBQH,0),0),"") | K14: =IFERROR(VLOOKUP($A14,subQ,MATCH(K$1,SUBQH,0),0),"") | L14: =IFERROR(VLOOKUP($A14,subQ,MATCH(L$1,SUBQH,0),0),"")
A15: 기타금융손익 | D15: 기타금융손익(금융손익 잔차) | E15: =IFERROR(VLOOKUP($A15,subQ,MATCH(E$1,SUBQH,0),0),"") | F15: =IFERROR(VLOOKUP($A15,subQ,MATCH(F$1,SUBQH,0),0),"") | G15: =IFERROR(VLOOKUP($A15,subQ,MATCH(G$1,SUBQH,0),0),"") | H15: =IFERROR(VLOOKUP($A15,subQ,MATCH(H$1,SUBQH,0),0),"") | I15: =IFERROR(VLOOKUP($A15,subQ,MATCH(I$1,SUBQH,0),0),"") | J15: =IFERROR(VLOOKUP($A15,subQ,MATCH(J$1,SUBQH,0),0),"") | K15: =IFERROR(VLOOKUP($A15,subQ,MATCH(K$1,SUBQH,0),0),"") | L15: =IFERROR(VLOOKUP($A15,subQ,MATCH(L$1,SUBQH,0),0),"")
A16: 기타영업외손익 | D16: 기타영업외손익 | E16: =IFERROR(VLOOKUP($A16,subQ,MATCH(E$1,SUBQH,0),0),"") | F16: =IFERROR(VLOOKUP($A16,subQ,MATCH(F$1,SUBQH,0),0),"") | G16: =IFERROR(VLOOKUP($A16,subQ,MATCH(G$1,SUBQH,0),0),"") | H16: =IFERROR(VLOOKUP($A16,subQ,MATCH(H$1,SUBQH,0),0),"") | I16: =IFERROR(VLOOKUP($A16,subQ,MATCH(I$1,SUBQH,0),0),"") | J16: =IFERROR(VLOOKUP($A16,subQ,MATCH(J$1,SUBQH,0),0),"") | K16: =IFERROR(VLOOKUP($A16,subQ,MATCH(K$1,SUBQH,0),0),"") | L16: =IFERROR(VLOOKUP($A16,subQ,MATCH(L$1,SUBQH,0),0),"")
... A44: NPM | D44: NPM | E44: =IFERROR(VLOOKUP($A44,subQ,MATCH(E$1,SUBQH,0),0),"") | F44: =IFERROR(VLOOKUP($A44,subQ,MATCH(F$1,SUBQH,0),0),"") | G44: =IFERROR(VLOOKUP($A44,subQ,MATCH(G$1,SUBQH,0),0),"") | H44: =IFERROR(VLOOKUP($A44,subQ,MATCH(H$1,SUBQH,0),0),"") | I44: =IFERROR(VLOOKUP($A44,subQ,MATCH(I$1,SUBQH,0),0),"") | J44: =IFERROR(VLOOKUP($A44,subQ,MATCH(J$1,SUBQH,0),0),"") | K44: =IFERROR(VLOOKUP($A44,subQ,MATCH(K$1,SUBQH,0),0),"") | L44: =IFERROR(VLOOKUP($A44,subQ,MATCH(L$1,SUBQH,0),0),"")
A45: 매출액 YoY | D45: 매출액 YoY | F45: =IFERROR(F5/E5-1,"") | G45: =IFERROR(G5/F5-1,"") | H45: =IFERROR(H5/G5-1,"") | I45: =IFERROR(I5/H5-1,"") | J45: =IFERROR(J5/I5-1,"") | K45: =IFERROR(K5/J5-1,"") | L45: =IFERROR(L5/K5-1,"")
A46: 영업이익 YoY | D46: 영업이익 YoY | F46: =IFERROR(F9/E9-1,"") | G46: =IFERROR(G9/F9-1,"") | H46: =IFERROR(H9/G9-1,"") | I46: =IFERROR(I9/H9-1,"") | J46: =IFERROR(J9/I9-1,"") | K46: =IFERROR(K9/J9-1,"") | L46: =IFERROR(L9/K9-1,"")
A47: 지배주주순이익 YoY | D47: 지배주주순이익 YoY | F47: =IFERROR(F21/E21-1,"") | G47: =IFERROR(G21/F21-1,"") | H47: =IFERROR(H21/G21-1,"") | I47: =IFERROR(I21/H21-1,"") | J47: =IFERROR(J21/I21-1,"") | K47: =IFERROR(K21/J21-1,"") | L47: =IFERROR(L21/K21-1,"")

Sheet TP
B1: 종가 | C1: =변수!D46
B2: 기준일 | C2: =변수!D47
B3: 모델 산출값 — 목표주가·추천 아님. 밴드·COE 는 변수 시트 3절의 가정
C5: FY | D5: 2025 | E5: 2026 | F5: 2027 | G5: 2028
D6: A | E6: E | F6: E | G6: E
C7: EPS(원) | D7: =IFERROR(VLOOKUP("EPS",subQ,MATCH(D$5,SUBQH,0),0),"") | E7: =IFERROR(VLOOKUP("EPS",subQ,MATCH(E$5,SUBQH,0),0),"") | F7: =IFERROR(VLOOKUP("EPS",subQ,MATCH(F$5,SUBQH,0),0),"") | G7: =IFERROR(VLOOKUP("EPS",subQ,MATCH(G$5,SUBQH,0),0),"")
C8: BPS(원) | D8: =IFERROR(VLOOKUP("BPS",subQ,MATCH(D$5,SUBQH,0),0),"") | E8: =IFERROR(VLOOKUP("BPS",subQ,MATCH(E$5,SUBQH,0),0),"") | F8: =IFERROR(VLOOKUP("BPS",subQ,MATCH(F$5,SUBQH,0),0),"") | G8: =IFERROR(VLOOKUP("BPS",subQ,MATCH(G$5,SUBQH,0),0),"")
C9: 지배주주순이익(억원) | D9: =IFERROR(VLOOKUP("지배주주순이익",subQ,MATCH(D$5,SUBQH,0),0),"") | E9: =IFERROR(VLOOKUP("지배주주순이익",subQ,MATCH(E$5,SUBQH,0),0),"") | F9: =IFERROR(VLOOKUP("지배주주순이익",subQ,MATCH(F$5,SUBQH,0),0),"") | G9: =IFERROR(VLOOKUP("지배주주순이익",subQ,MATCH(G$5,SUBQH,0),0),"")
C10: 영업이익(억원) | D10: =IFERROR(VLOOKUP("영업이익",subQ,MATCH(D$5,SUBQH,0),0),"") | E10: =IFERROR(VLOOKUP("영업이익",subQ,MATCH(E$5,SUBQH,0),0),"") | F10: =IFERROR(VLOOKUP("영업이익",subQ,MATCH(F$5,SUBQH,0),0),"") | G10: =IFERROR(VLOOKUP("영업이익",subQ,MATCH(G$5,SUBQH,0),0),"")
C11: ROE(EPS/기초BPS) | E11: =IFERROR(E7/D8,"") | F11: =IFERROR(F7/E8,"") | G11: =IFERROR(G7/F8,"")
B13: PER
C14: 12M fwd EPS | D14: =IFERROR(E7*변수!D52+F7*(1-변수!D52),"")
C15: 적정가치 @PER_lo | D15: =변수!D49 | E15: =IFERROR(ROUND($D$14*D15,-2),"") | F15: =IFERROR(E15/$C$1-1,"") | G15: 배 · 원 · 종가 대비
C16: 적정가치 @PER_mid | D16: =변수!D50 | E16: =IFERROR(ROUND($D$14*D16,-2),"") | F16: =IFERROR(E16/$C$1-1,"") | G16: 배 · 원 · 종가 대비
C17: 적정가치 @PER_hi | D17: =변수!D51 | E17: =IFERROR(ROUND($D$14*D17,-2),"") | F17: =IFERROR(E17/$C$1-1,"") | G17: 배 · 원 · 종가 대비
C18: 현재 PER(종가/12M fwd EPS) | D18: =IFERROR($C$1/$D$14,"")
B20: PBR
C21: 최근 BPS(마지막 실적 분기) | D21: =IFERROR(VLOOKUP("BPS",subQ,MATCH("2Q26",SUBQH,0),0),"")
C22: ROE fwd(12M fwd EPS / BPS) | D22: =IFERROR($D$14/$D$21,"")
C23: COE | D23: =변수!D48
C24: 적정 PBR = ROE/COE | D24: =IFERROR(D22/D23,"")
C25: 적정가치(PBR) = BPS × 적정PBR | D25: =IFERROR(ROUND(D21*D24,-2),"") | E25: =IFERROR(D25/$C$1-1,"")
C26: 현재 PBR(종가/BPS) | D26: =IFERROR($C$1/D21,"")
B28: 모델 json valuation(참고)
C29: eps_fwd12m | D29: 18283.4
C30: bps_latest | D30: 1498026.6
C31: per_now | D31: 24.89
C32: pbr_now | D32: 0.3
C33: roe_fwd | D33: 0.0122
C34: fair_pbr | D34: 0.14
C35: fair_value_pbr | D35: 209700
C36: ev_ebitda | D36: 9.01
C37: note | D37: 모델 산출값 — 목표주가·추천 아님

Sheet 외화
C1: 이름: 외화QH — 환율 QoQ · 외화 순노출 × Δ기말환율 | E1: 4Q21 | F1: 1Q22 | G1: 2Q22 | H1: 3Q22 | I1: 4Q22 | J1: 1Q23 | K1: 2Q23 | L1: 3Q23 | M1: 4Q23 | N1: 1Q24 | O1: 2Q24 | P1: 3Q24 | Q1: 4Q24 | R1: 1Q25 | S1: 2Q25 | T1: 3Q25 | U1: 4Q25 | V1: 1Q26 | W1: 2Q26 | X1: 3Q26 | Y1: 4Q26 | Z1: 1Q27 | AA1: 2Q27 | AB1: 3Q27 | AC1: 4Q27 | AD1: 1Q28 | AE1: 2Q28 | AF1: 3Q28 | AG1: 4Q28
E3: 1 | F3: 2 | G3: 3 | H3: 4 | I3: 5 | J3: 6 | K3: 7 | L3: 8 | M3: 9 | N3: 10 | O3: 11 | P3: 12 | Q3: 13 | R3: 14 | S3: 15 | T3: 16 | U3: 17 | V3: 18 | W3: 19 | X3: 20 | Y3: 21 | Z3: 22 | AA3: 23 | AB3: 24 | AC3: 25 | AD3: 26 | AE3: 27 | AF3: 28 | AG3: 29
E4: 2021.12 | F4: 2022.03 | G4: 2022.06 | H4: 2022.09 | I4: 2022.12 | J4: 2023.03 | K4: 2023.06 | L4: 2023.09 | M4: 2023.12 | N4: 2024.03 | O4: 2024.06 | P4: 2024.09 | Q4: 2024.12 | R4: 2025.03 | S4: 2025.06 | T4: 2025.09 | U4: 2025.12 | V4: 2026.03 | W4: 2026.06 | X4: 2026.09 | Y4: 2026.12 | Z4: 2027.03 | AA4: 2027.06 | AB4: 2027.09 | AC4: 2027.12 | AD4: 2028.03 | AE4: 2028.06 | AF4: 2028.09 | AG4: 2028.12
D5: 원/달러(평균) | E5: =IFERROR(VLOOKUP($D5,환율,MATCH(E$1,변수H,0),0),"") | F5: =IFERROR(VLOOKUP($D5,환율,MATCH(F$1,변수H,0),0),"") | G5: =IFERROR(VLOOKUP($D5,환율,MATCH(G$1,변수H,0),0),"") | H5: =IFERROR(VLOOKUP($D5,환율,MATCH(H$1,변수H,0),0),"") | I5: =IFERROR(VLOOKUP($D5,환율,MATCH(I$1,변수H,0),0),"") | J5: =IFERROR(VLOOKUP($D5,환율,MATCH(J$1,변수H,0),0),"") | K5: =IFERROR(VLOOKUP($D5,환율,MATCH(K$1,변수H,0),0),"") | L5: =IFERROR(VLOOKUP($D5,환율,MATCH(L$1,변수H,0),0),"") | ... AG5: =IFERROR(VLOOKUP($D5,환율,MATCH(AG$1,변수H,0),0),"")
A6: 원/달러(평균) QoQ | F6: =IFERROR(F5/E5-1,"") | G6: =IFERROR(G5/F5-1,"") | H6: =IFERROR(H5/G5-1,"") | I6: =IFERROR(I5/H5-1,"") | J6: =IFERROR(J5/I5-1,"") | K6: =IFERROR(K5/J5-1,"") | L6: =IFERROR(L5/K5-1,"") | M6: =IFERROR(M5/L5-1,"") | ... AG6: =IFERROR(AG5/AF5-1,"")
D7: 원/달러(기말) | E7: =IFERROR(VLOOKUP($D7,환율,MATCH(E$1,변수H,0),0),"") | F7: =IFERROR(VLOOKUP($D7,환율,MATCH(F$1,변수H,0),0),"") | G7: =IFERROR(VLOOKUP($D7,환율,MATCH(G$1,변수H,0),0),"") | H7: =IFERROR(VLOOKUP($D7,환율,MATCH(H$1,변수H,0),0),"") | I7: =IFERROR(VLOOKUP($D7,환율,MATCH(I$1,변수H,0),0),"") | J7: =IFERROR(VLOOKUP($D7,환율,MATCH(J$1,변수H,0),0),"") | K7: =IFERROR(VLOOKUP($D7,환율,MATCH(K$1,변수H,0),0),"") | L7: =IFERROR(VLOOKUP($D7,환율,MATCH(L$1,변수H,0),0),"") | ... AG7: =IFERROR(VLOOKUP($D7,환율,MATCH(AG$1,변수H,0),0),"")
A8: 원/달러(기말) QoQ | F8: =IFERROR(F7/E7-1,"") | G8: =IFERROR(G7/F7-1,"") | H8: =IFERROR(H7/G7-1,"") | I8: =IFERROR(I7/H7-1,"") | J8: =IFERROR(J7/I7-1,"") | K8: =IFERROR(K7/J7-1,"") | L8: =IFERROR(L7/K7-1,"") | M8: =IFERROR(M7/L7-1,"") | ... AG8: =IFERROR(AG7/AF7-1,"")
D9: W/Euro(평균) | E9: =IFERROR(VLOOKUP($D9,환율,MATCH(E$1,변수H,0),0),"") | F9: =IFERROR(VLOOKUP($D9,환율,MATCH(F$1,변수H,0),0),"") | G9: =IFERROR(VLOOKUP($D9,환율,MATCH(G$1,변수H,0),0),"") | H9: =IFERROR(VLOOKUP($D9,환율,MATCH(H$1,변수H,0),0),"") | I9: =IFERROR(VLOOKUP($D9,환율,MATCH(I$1,변수H,0),0),"") | J9: =IFERROR(VLOOKUP($D9,환율,MATCH(J$1,변수H,0),0),"") | K9: =IFERROR(VLOOKUP($D9,환율,MATCH(K$1,변수H,0),0),"") | L9: =IFERROR(VLOOKUP($D9,환율,MATCH(L$1,변수H,0),0),"") | ... AG9: =IFERROR(VLOOKUP($D9,환율,MATCH(AG$1,변수H,0),0),"")
A10: W/Euro(평균) QoQ | F10: =IFERROR(F9/E9-1,"") | G10: =IFERROR(G9/F9-1,"") | H10: =IFERROR(H9/G9-1,"") | I10: =IFERROR(I9/H9-1,"") | J10: =IFERROR(J9/I9-1,"") | K10: =IFERROR(K9/J9-1,"") | L10: =IFERROR(L9/K9-1,"") | M10: =IFERROR(M9/L9-1,"") | ... AG10: =IFERROR(AG9/AF9-1,"")
D11: W/Euro(기말) | E11: =IFERROR(VLOOKUP($D11,환율,MATCH(E$1,변수H,0),0),"") | F11: =IFERROR(VLOOKUP($D11,환율,MATCH(F$1,변수H,0),0),"") | G11: =IFERROR(VLOOKUP($D11,환율,MATCH(G$1,변수H,0),0),"") | H11: =IFERROR(VLOOKUP($D11,환율,MATCH(H$1,변수H,0),0),"") | I11: =IFERROR(VLOOKUP($D11,환율,MATCH(I$1,변수H,0),0),"") | J11: =IFERROR(VLOOKUP($D11,환율,MATCH(J$1,변수H,0),0),"") | K11: =IFERROR(VLOOKUP($D11,환율,MATCH(K$1,변수H,0),0),"") | L11: =IFERROR(VLOOKUP($D11,환율,MATCH(L$1,변수H,0),0),"") | ... AG11: =IFERROR(VLOOKUP($D11,환율,MATCH(AG$1,변수H,0),0),"")
A12: W/Euro(기말) QoQ | F12: =IFERROR(F11/E11-1,"") | G12: =IFERROR(G11/F11-1,"") | H12: =IFERROR(H11/G11-1,"") | I12: =IFERROR(I11/H11-1,"") | J12: =IFERROR(J11/I11-1,"") | K12: =IFERROR(K11/J11-1,"") | L12: =IFERROR(L11/K11-1,"") | M12: =IFERROR(M11/L11-1,"") | ... AG12: =IFERROR(AG11/AF11-1,"")
D13: 원/100Y(기말) | E13: =IFERROR(VLOOKUP($D13,환율,MATCH(E$1,변수H,0),0),"") | F13: =IFERROR(VLOOKUP($D13,환율,MATCH(F$1,변수H,0),0),"") | G13: =IFERROR(VLOOKUP($D13,환율,MATCH(G$1,변수H,0),0),"") | H13: =IFERROR(VLOOKUP($D13,환율,MATCH(H$1,변수H,0),0),"") | I13: =IFERROR(VLOOKUP($D13,환율,MATCH(I$1,변수H,0),0),"") | J13: =IFERROR(VLOOKUP($D13,환율,MATCH(J$1,변수H,0),0),"") | K13: =IFERROR(VLOOKUP($D13,환율,MATCH(K$1,변수H,0),0),"") | L13: =IFERROR(VLOOKUP($D13,환율,MATCH(L$1,변수H,0),0),"") | ... AG13: =IFERROR(VLOOKUP($D13,환율,MATCH(AG$1,변수H,0),0),"")
A14: 원/100Y(기말) QoQ | F14: =IFERROR(F13/E13-1,"") | G14: =IFERROR(G13/F13-1,"") | H14: =IFERROR(H13/G13-1,"") | I14: =IFERROR(I13/H13-1,"") | J14: =IFERROR(J13/I13-1,"") | K14: =IFERROR(K13/J13-1,"") | L14: =IFERROR(L13/K13-1,"") | M14: =IFERROR(M13/L13-1,"") | ... AG14: =IFERROR(AG13/AF13-1,"")
A16: 외화순노출 | C16: 외화 순노출(백만$) | D16: =변수!D59 | E16: 외화 순노출 × Δ기말환율 (외화 시트 방식)
A17: 환관련손익추정 | C17: 환관련손익 추정(억원) = 순노출 × Δ원/달러(기말) / 100 | F17: =IFERROR($D$16*(F7-E7)/100,"") | G17: =IFERROR($D$16*(G7-F7)/100,"") | H17: =IFERROR($D$16*(H7-G7)/100,"") | I17: =IFERROR($D$16*(I7-H7)/100,"") | J17: =IFERROR($D$16*(J7-I7)/100,"") | K17: =IFERROR($D$16*(K7-J7)/100,"") | L17: =IFERROR($D$16*(L7-K7)/100,"") | M17: =IFERROR($D$16*(M7-L7)/100,"") | ... AG17: =IFERROR($D$16*(AG7-AF7)/100,"")
A18: fx_pnl.by_q | C18: 모델 fx_pnl.by_q(억원, 참고)
C19: 외화 순노출 미공시(face) → 0 + 표기
