Workbook
Name 변수H: 변수!$C$1:$AO$1
Name 환율: 변수!$C$6:$AO$13
Name BS연결H: BS연결!$C$1:$AO$1
Name BS연결: BS연결!$C$5:$AO$112
Name BS별도H: BS별도!$C$1:$AO$1
Name BS별도: BS별도!$C$5:$AO$95
Name SUBQH: subQ!$A$1:$AO$1
Name subQ: subQ!$A$5:$AO$43
Name SLS_H: SLS!$A$1:$BH$1

Sheet README
A1: HD한국조선해양(009540) 실적 모델 — ARGUS 한국조선
A2: 기준 분기 2026Q2 · 마지막 실적 2026Q2 · 생성 2026-10-12
A3: 모든 수치는 모델 산출값(DART 공개 재무제표 + 우리 추정)이다 — 목표주가·투자 추천 아님. 참고용 · 투자조언 아님.
A5: 시트
A6: 변수 가정 시계열. 환율 8행(ECB via frankfurter — L2 fx.json; 추정 분기 = 노란 가정), 추정 드라이버(노란 셀 = 모델값에서 역산한 가정, 바꾸면 재계산; 연녹 셀 = 3절 스칼라 참조 수식), 3절 스칼라 가정(세율·판관비율·지배주주비중·이자율·종가·PER 밴드·COE·외화 순노출·헤지비율)
A7: BS연결/BS별도 FnGuide 계정명 × 기간 값 덤프(백만원). 행1 분기라벨, 행4 YYYY.MM / YYYY.12A. 이름정의 BS연결H·BS연결(계정명 C열부터)
A8: subQ 분기 서브모델(억원 = 백만원/100). 확정 행: =IFERROR(VLOOKUP($D행,BS연결,MATCH(E$1,BS연결H,0),0)/100,"") 추정 행: 변수 시트 가정 셀 참조 수식. 외환손익·파생상품손익은 BS 계정 합·차, 기타금융손익은 잔차, OPM·EPS·BPS·PER·PBR 은 파생 수식
A9: SLS 선표(조선사만, sls json 있을 때): 요약 행(sls 저장값) + 계약별 스케줄(백만$) × (헤지비율 × 헤지환율 + (1−헤지비율) × 건조시점 환율[변수 원/달러(평균)]) → 원화 수식 블록 → 합계 행이 subQ 매출조선에 연결
A10: 시나리오 신규수주 보수/기준/낙관(forecast_panel 패널, 모델에 scenarios 가 있을 때만): 매출액·영업이익 = subQ 기준값 ± (시나리오 신규 − base 신규) × OPM. base 만 subQ 행에 포함, 나머지는 합산 안 함
A11: 분기/연간예상 subQ 를 이름(A열 key)으로 VLOOKUP 한 보고서 표(억원)
A12: TP PER 밴드 × 12M fwd EPS, PBR = ROE/COE × BPS — 모델 산출값 구간, 목표주가·추천 아님
A13: 외화 환율 QoQ, 외화 순노출 × Δ기말환율 → 환관련손익 추정
... A36: 백테스트: {"freeze": "2025Q2", "horizon": 4, "revenue_wape_pct": 9.8, "op_wape_pct": 40.8, "n": 4, "note": "단일 회사 4분기 — 통계 아님", "driver_at_freeze": "subsidiary_yard_scaled", "selection_oos_at_freeze": null, "frozen_inputs": "fin(연결/별도)·고객 조선사 모델·지주 자회사 모델은 2025Q2 까지의 분기만; 선표는 체결일 ≤ 2025Q2 말일 계약(원장 최신 금액·코호트 등급, 환산 없음); 잔고는 yards_cache 2025Q2; 시세·환율 forward·prices·forecast_panel 신규수주 미사용. 고객 가중치(suppliers.json 언급 비중)와 합병 체인링크는 현재 지식; 고객 연동 채택은 동결 모델 안에서도 자기 la−4분기 OOS 규칙(selection_oos_at_freeze)", "detail": [{"q": "2025Q3", "rev_pred": 74060.53, "rev_act": 75814.36, "op_pred": 7553.95, "op_act": 10537.75}, {"q": "2025Q4", "rev_pred": 74060.53, "rev_act": 81516.57, "op_pred": 7553.95, "op_act": 10379.19}, {"q": "2026Q1", "rev_pred": 73789.18, "rev_act": 81408.9, "op_pred": 7526.28, "op_act": 13559.7}, {"q": "2026Q2", "rev_pred": 73924.83, "rev_act": 89270.46, "op_pred": 7540.11, "op_act": 16451.46}]}

Sheet 변수
C1: 이름: 변수H | E1: 4Q21 | F1: 2021 | G1: 1Q22 | H1: 2Q22 | I1: 3Q22 | J1: 4Q22 | K1: 2022 | L1: 1Q23 | M1: 2Q23 | N1: 3Q23 | O1: 4Q23 | P1: 2023 | Q1: 1Q24 | R1: 2Q24 | S1: 3Q24 | T1: 4Q24 | U1: 2024 | V1: 1Q25 | W1: 2Q25 | X1: 3Q25 | Y1: 4Q25 | Z1: 2025 | AA1: 1Q26 | AB1: 2Q26 | AC1: 3Q26 | AD1: 4Q26 | AE1: 2026 | AF1: 1Q27 | AG1: 2Q27 | AH1: 3Q27 | AI1: 4Q27 | AJ1: 2027 | AK1: 1Q28 | AL1: 2Q28 | AM1: 3Q28 | AN1: 4Q28 | AO1: 2028
A2: 가정 시계열 — 노란 셀은 추정 가정(모델값에서 역산), 연녹 셀은 3절 스칼라 참조 수식. 바꾸면 subQ·분기·연간예상·TP·시나리오가 재계산됩니다.
E3: 1 | F3: 2 | G3: 3 | H3: 4 | I3: 5 | J3: 6 | K3: 7 | L3: 8 | M3: 9 | N3: 10 | O3: 11 | P3: 12 | Q3: 13 | R3: 14 | S3: 15 | T3: 16 | U3: 17 | V3: 18 | W3: 19 | X3: 20 | Y3: 21 | Z3: 22 | AA3: 23 | AB3: 24 | AC3: 25 | AD3: 26 | AE3: 27 | AF3: 28 | AG3: 29 | AH3: 30 | AI3: 31 | AJ3: 32 | AK3: 33 | AL3: 34 | AM3: 35 | AN3: 36 | AO3: 37
E4: 2021.12 | F4: 2021.12A | G4: 2022.03 | H4: 2022.06 | I4: 2022.09 | J4: 2022.12 | K4: 2022.12A | L4: 2023.03 | M4: 2023.06 | N4: 2023.09 | O4: 2023.12 | P4: 2023.12A | Q4: 2024.03 | R4: 2024.06 | S4: 2024.09 | T4: 2024.12 | U4: 2024.12A | V4: 2025.03 | W4: 2025.06 | X4: 2025.09 | Y4: 2025.12 | Z4: 2025.12A | AA4: 2026.03 | AB4: 2026.06 | AC4: 2026.09 | AD4: 2026.12 | AE4: 2026.12A | AF4: 2027.03 | AG4: 2027.06 | AH4: 2027.09 | AI4: 2027.12 | AJ4: 2027.12A | AK4: 2028.03 | AL4: 2028.06 | AM4: 2028.09 | AN4: 2028.12 | AO4: 2028.12A
B5: 1. FX | C5: 이름: 환율
A6: USDKRW_avg | C6: 원/달러(평균) | E6: 1183.5 | F6: 1145.51 | G6: 1205.78 | H6: 1262.09 | I6: 1341.93 | J6: 1360.12 | K6: 1292.98 | L6: 1276.95 | M6: 1315.69 | N6: 1313.62 | O6: 1322.01 | P6: 1306.85 | Q6: 1330.14 | R6: 1371.28 | S6: 1356.22 | T6: 1396.3 | U6: 1363.53 | V6: 1452.28 | W6: 1398.52 | X6: 1386.95 | Y6: 1449.19 | Z6: 1421.52 | AA6: 1466.12 | AB6: 1501.75 | AC6: 1418.75 | AD6: 1345.14 | AE6: 1457.21 | AF6: 1341.49 | AG6: 1341.49 | AH6: 1341.49 | AI6: 1341.49 | AK6: 1341.49 | AL6: 1341.49 | AM6: 1341.49 | AN6: 1341.49
A7: USDKRW_end | C7: 원/달러(기말) | E7: 1188.75 | F7: 1188.75 | G7: 1213.74 | H7: 1301.24 | I7: 1436.9 | J7: 1260.16 | K7: 1260.16 | L7: 1305.99 | M7: 1321.44 | N7: 1345.35 | O7: 1297.43 | P7: 1297.43 | Q7: 1349.25 | R7: 1377.73 | S7: 1312.17 | T7: 1474.78 | U7: 1474.78 | V7: 1474.54 | W7: 1355.13 | X7: 1403.67 | Y7: 1444.2 | Z7: 1444.2 | AA7: 1524.8 | AB7: 1550.89 | AC7: 1355.4 | AD7: 1341.49 | AE7: 1341.49 | AF7: 1341.49 | AG7: 1341.49 | AH7: 1341.49 | AI7: 1341.49 | AK7: 1341.49 | AL7: 1341.49 | AM7: 1341.49 | AN7: 1341.49
A8: JPY100KRW_avg | C8: 원/100Y(평균) | E8: 1041.02 | F8: 1042.74 | G8: 1036.79 | H8: 972.23 | I8: 970.61 | J8: 961.03 | K8: 985.1 | L8: 964.89 | M8: 957.36 | N8: 909 | O8: 893.22 | P8: 931.11 | Q8: 896.29 | R8: 880.14 | S8: 909.35 | T8: 917.25 | U8: 900.92 | V8: 952.59 | W8: 967.92 | X8: 940.32 | Y8: 940.77 | Z8: 950.17 | AA8: 934.39 | AB8: 942.16 | AC8: 890.41 | AD8: 850.79 | AE8: 919.21 | AF8: 847.7 | AG8: 847.7 | AH8: 847.7 | AI8: 847.7 | AK8: 847.7 | AL8: 847.7 | AM8: 847.7 | AN8: 847.7
A9: JPY100KRW_end | C9: 원/100Y(기말) | E9: 1032.62 | F9: 1032.62 | G9: 996.83 | H9: 954.9 | I9: 993.29 | J9: 955.54 | K9: 955.54 | L9: 980.62 | M9: 913.67 | N9: 901.47 | O9: 917.04 | P9: 917.04 | Q9: 892.42 | R9: 857.76 | S9: 919.21 | T9: 939.65 | U9: 939.65 | V9: 986.84 | W9: 938.85 | X9: 948.49 | Y9: 921.81 | Z9: 921.81 | AA9: 955.99 | AB9: 954.75 | AC9: 863.31 | AD9: 847.7 | AE9: 847.7 | AF9: 847.7 | AG9: 847.7 | AH9: 847.7 | AI9: 847.7 | AK9: 847.7 | AL9: 847.7 | AM9: 847.7 | AN9: 847.7
A10: EURKRW_avg | C10: W/Euro(평균) | E10: 1353.32 | F10: 1354.06 | G10: 1352.29 | H10: 1343.31 | I10: 1350.63 | J10: 1386.07 | K10: 1358.07 | L10: 1369.93 | M10: 1432.41 | N10: 1429.41 | O10: 1420.91 | P10: 1412.88 | Q10: 1444.21 | R10: 1476.42 | S10: 1489.3 | T10: 1490.78 | U10: 1475.4 | V10: 1528.33 | W10: 1585.13 | X10: 1620.04 | Y10: 1686.02 | Z10: 1605.45 | AA10: 1715.47 | AB10: 1746.09 | AC10: 1631.97 | AD10: 1509.74 | AE10: 1689.95 | AF10: 1503.27 | AG10: 1503.27 | AH10: 1503.27 | AI10: 1503.27 | AK10: 1503.27 | AL10: 1503.27 | AM10: 1503.27 | AN10: 1503.27
A11: EURKRW_end | C11: W/Euro(기말) | E11: 1346.38 | F11: 1346.38 | G11: 1347.37 | H11: 1351.6 | I11: 1400.62 | J11: 1344.08 | K11: 1344.08 | L11: 1420.26 | M11: 1435.88 | N11: 1425.26 | O11: 1433.66 | P11: 1433.66 | Q11: 1458.68 | R11: 1474.86 | S11: 1469.1 | T11: 1532.14 | U11: 1532.14 | V11: 1594.72 | W11: 1588.22 | X11: 1648.04 | Y11: 1696.94 | Z11: 1696.94 | AA11: 1753.21 | AB11: 1767.09 | AC11: 1539.06 | AD11: 1503.27 | AE11: 1503.27 | AF11: 1503.27 | AG11: 1503.27 | AH11: 1503.27 | AI11: 1503.27 | AK11: 1503.27 | AL11: 1503.27 | AM11: 1503.27 | AN11: 1503.27
A12: CNYKRW_avg | C12: 원/중국원(평균) | E12: 185.14 | F12: 177.65 | G12: 189.93 | H12: 190.76 | I12: 195.79 | J12: 191.09 | K12: 191.93 | L12: 186.59 | M12: 187.45 | N12: 181.28 | O12: 182.86 | P12: 184.52 | Q12: 185.04 | R12: 189.35 | S12: 189.24 | T12: 194.24 | U12: 189.49 | V12: 199.63 | W12: 193.41 | X12: 193.79 | Y12: 204.38 | Z12: 197.8 | AA12: 211.75 | AB12: 220.8 | AC12: 210.43 | AD12: 200.69 | AE12: 213.75 | AF12: 200.46 | AG12: 200.46 | AH12: 200.46 | AI12: 200.46 | AK12: 200.46 | AL12: 200.46 | AM12: 200.46 | AN12: 200.46
A13: CNYKRW_end | C13: 원/중국원(기말) | E13: 187.13 | F13: 187.13 | G13: 191.38 | H13: 194.13 | I13: 201.92 | J13: 182.67 | K13: 182.67 | L13: 189.97 | M13: 181.8 | N13: 184.26 | O13: 182.61 | P13: 182.61 | Q13: 186.66 | R13: 189.7 | S13: 187.12 | T13: 202.04 | U13: 202.04 | V13: 203.3 | W13: 189.14 | X13: 197.16 | Y13: 206.28 | Z13: 206.28 | AA13: 220.97 | AB13: 228.56 | AC13: 202.16 | AD13: 200.46 | AE13: 200.46 | AF13: 200.46 | AG13: 200.46 | AH13: 200.46 | AI13: 200.46 | AK13: 200.46 | AL13: 200.46 | AM13: 200.46 | AN13: 200.46
B14: 1b. 종가
A15: price_close_end | C15: 종가(기말) | E15: 94600 | G15: 88900 | H15: 93900 | I15: 72900 | J15: 70700 | L15: 77500 | M15: 116500 | N15: 111000 | O15: 120900 | Q15: 118400 | R15: 158800 | S15: 187700 | T15: 228000 | V15: 201000 | W15: 366000 | X15: 411000 | Y15: 407000 | AA15: 344000 | AB15: 350000 | AC15: 326500 | AD15: 279500
A16: price_high | C16: 종가(최고) | E16: 108500 | G16: 103500 | H16: 98200 | I16: 101500 | J16: 81000 | L16: 86500 | M16: 121900 | N16: 130000 | O16: 121400 | Q16: 129000 | R16: 160000 | S16: 213000 | T16: 238000 | V16: 253500 | W16: 398500 | X16: 438000 | Y16: 494500 | AA16: 474000 | AB16: 488000 | AC16: 412500 | AD16: 328500
A17: price_low | C17: 종가(최저) | E17: 87000 | G17: 76900 | H17: 80900 | I17: 72500 | J17: 68600 | L17: 68100 | M17: 75500 | N17: 110200 | O17: 89000 | Q17: 104000 | R17: 110800 | S17: 153600 | T17: 175500 | V17: 194400 | W17: 185700 | X17: 304500 | Y17: 396000 | AA17: 340500 | AB17: 338000 | AC17: 314000 | AD17: 276500
A18: price_avg | C18: 종가(평균) | E18: 97490.5 | G18: 89366.1 | H18: 89929 | I18: 87073 | J18: 74871 | L18: 78014.5 | M18: 94542.6 | N18: 120450 | O18: 103801.7 | Q18: 115870.5 | R18: 131518.3 | S18: 184258.1 | T18: 198872.1 | V18: 225800 | W18: 286443.3 | X18: 370384.6 | Y18: 430364.4 | AA18: 415415.3 | AB18: 412032.8 | AC18: 356596.8 | AD18: 307083.3
B20: 2. 추정 드라이버 | C20: 실적 열 = subQ 실현값(수식), 추정 열 = 가정(노란 = 모델값 역산, 연녹 = 3절 스칼라 참조)
A21: drv:매출액 | B21: yoy | C21: 매출액 YoY | J21: =IFERROR(subQ!J5/subQ!E5-1,"") | L21: =IFERROR(subQ!L5/subQ!G5-1,"") | M21: =IFERROR(subQ!M5/subQ!H5-1,"") | N21: =IFERROR(subQ!N5/subQ!I5-1,"") | O21: =IFERROR(subQ!O5/subQ!J5-1,"") | Q21: =IFERROR(subQ!Q5/subQ!L5-1,"") | R21: =IFERROR(subQ!R5/subQ!M5-1,"") | S21: =IFERROR(subQ!S5/subQ!N5-1,"") | T21: =IFERROR(subQ!T5/subQ!O5-1,"") | V21: =IFERROR(subQ!V5/subQ!Q5-1,"") | W21: =IFERROR(subQ!W5/subQ!R5-1,"") | X21: =IFERROR(subQ!X5/subQ!S5-1,"") | Y21: =IFERROR(subQ!Y5/subQ!T5-1,"") | AA21: =IFERROR(subQ!AA5/subQ!V5-1,"") | AB21: =IFERROR(subQ!AB5/subQ!W5-1,"") | AC21: 0.22636362 | AD21: 0.15508325 | AF21: 0.18688378 | AG21: 0.13838021 | AH21: 0.15339426 | AI21: 0.21060379 | AK21: 0.25269506 | AL21: 0.26398303 | AM21: 0.25295681 | AN21: 0.21587486
A22: drv:판관비 | B22: ratio | C22: 판관비율(/매출) | E22: =IFERROR(subQ!E8/subQ!E5,"") | F22: =IFERROR(subQ!F8/subQ!F5,"") | G22: =IFERROR(subQ!G8/subQ!G5,"") | H22: =IFERROR(subQ!H8/subQ!H5,"") | I22: =IFERROR(subQ!I8/subQ!I5,"") | J22: =IFERROR(subQ!J8/subQ!J5,"") | K22: =IFERROR(subQ!K8/subQ!K5,"") | L22: =IFERROR(subQ!L8/subQ!L5,"") | ... AB22: =IFERROR(subQ!AB8/subQ!AB5,"") | AC22: =$D$52 | AD22: =$D$52 | AE22: =IFERROR(subQ!AE8/subQ!AE5,"") | AF22: =$D$52 | AG22: =$D$52 | AH22: =$D$52 | AI22: =$D$52 | AJ22: =IFERROR(subQ!AJ8/subQ!AJ5,"") | AK22: =$D$52 | AL22: =$D$52 | AM22: =$D$52 | AN22: =$D$52 | AO22: =IFERROR(subQ!AO8/subQ!AO5,"")
A23: drv:영업이익 | B23: ratio | C23: 영업이익률(OPM) | E23: =IFERROR(subQ!E9/subQ!E5,"") | F23: =IFERROR(subQ!F9/subQ!F5,"") | G23: =IFERROR(subQ!G9/subQ!G5,"") | H23: =IFERROR(subQ!H9/subQ!H5,"") | I23: =IFERROR(subQ!I9/subQ!I5,"") | J23: =IFERROR(subQ!J9/subQ!J5,"") | K23: =IFERROR(subQ!K9/subQ!K5,"") | L23: =IFERROR(subQ!L9/subQ!L5,"") | ... AB23: =IFERROR(subQ!AB9/subQ!AB5,"") | AC23: 0.15719965 | AD23: 0.15749967 | AE23: =IFERROR(subQ!AE9/subQ!AE5,"") | AF23: 0.15749972 | AG23: 0.15752827 | AH23: 0.15761034 | AI23: 0.15767032 | AJ23: =IFERROR(subQ!AJ9/subQ!AJ5,"") | AK23: 0.15773036 | AL23: 0.15779038 | AM23: 0.15794199 | AN23: 0.15816302 | AO23: =IFERROR(subQ!AO9/subQ!AO5,"")
A24: drv:외환손익 | B24: abs | C24: 외환손익 (가정, 억원) | E24: =subQ!E13 | F24: =subQ!F13 | G24: =subQ!G13 | H24: =subQ!H13 | I24: =subQ!I13 | J24: =subQ!J13 | K24: =subQ!K13 | L24: =subQ!L13 | ... AB24: =subQ!AB13 | AC24: 0 | AD24: 0 | AE24: =subQ!AE13 | AF24: 0 | AG24: 0 | AH24: 0 | AI24: 0 | AJ24: =subQ!AJ13 | AK24: 0 | AL24: 0 | AM24: 0 | AN24: 0 | AO24: =subQ!AO13
A25: drv:파생상품손익 | B25: abs | C25: 파생상품손익 (가정, 억원) | E25: =subQ!E14 | F25: =subQ!F14 | G25: =subQ!G14 | H25: =subQ!H14 | I25: =subQ!I14 | J25: =subQ!J14 | K25: =subQ!K14 | L25: =subQ!L14 | ... AB25: =subQ!AB14 | AC25: 0 | AD25: 0 | AE25: =subQ!AE14 | AF25: 0 | AG25: 0 | AH25: 0 | AI25: 0 | AJ25: =subQ!AJ14 | AK25: 0 | AL25: 0 | AM25: 0 | AN25: 0 | AO25: =subQ!AO14
A26: drv:기타금융손익 | B26: abs | C26: 기타금융손익 (가정, 억원) | E26: =subQ!E15 | F26: =subQ!F15 | G26: =subQ!G15 | H26: =subQ!H15 | I26: =subQ!I15 | J26: =subQ!J15 | K26: =subQ!K15 | L26: =subQ!L15 | ... AB26: =subQ!AB15 | AC26: 0.85 | AD26: 0.85 | AE26: =subQ!AE15 | AF26: 0.85 | AG26: 0.85 | AH26: 0.85 | AI26: 0.85 | AJ26: =subQ!AJ15 | AK26: 0.85 | AL26: 0.85 | AM26: 0.85 | AN26: 0.85 | AO26: =subQ!AO15
A27: drv:기타영업외손익 | B27: abs | C27: 기타영업외손익 (가정, 억원) | E27: =subQ!E16 | F27: =subQ!F16 | G27: =subQ!G16 | H27: =subQ!H16 | I27: =subQ!I16 | J27: =subQ!J16 | K27: =subQ!K16 | L27: =subQ!L16 | ... AB27: =subQ!AB16 | AC27: 0 | AD27: 0 | AE27: =subQ!AE16 | AF27: 0 | AG27: 0 | AH27: 0 | AI27: 0 | AJ27: =subQ!AJ16 | AK27: 0 | AL27: 0 | AM27: 0 | AN27: 0 | AO27: =subQ!AO16
A28: drv:지분법손익 | B28: abs | C28: 지분법손익 (가정, 억원) | E28: =subQ!E17 | F28: =subQ!F17 | G28: =subQ!G17 | H28: =subQ!H17 | I28: =subQ!I17 | J28: =subQ!J17 | K28: =subQ!K17 | L28: =subQ!L17 | ... AB28: =subQ!AB17 | AC28: 0.11 | AD28: 0.11 | AE28: =subQ!AE17 | AF28: 0.11 | AG28: 0.11 | AH28: 0.11 | AI28: 0.11 | AJ28: =subQ!AJ17 | AK28: 0.11 | AL28: 0.11 | AM28: 0.11 | AN28: 0.11 | AO28: =subQ!AO17
A29: drv:법인세비용 | B29: tax | C29: 법인세율(/세전) — 법인세 = MAX(세전,0) × 세율 | E29: =IFERROR(subQ!E19/subQ!E18,"") | F29: =IFERROR(subQ!F19/subQ!F18,"") | G29: =IFERROR(subQ!G19/subQ!G18,"") | H29: =IFERROR(subQ!H19/subQ!H18,"") | I29: =IFERROR(subQ!I19/subQ!I18,"") | J29: =IFERROR(subQ!J19/subQ!J18,"") | K29: =IFERROR(subQ!K19/subQ!K18,"") | L29: =IFERROR(subQ!L19/subQ!L18,"") | ... AB29: =IFERROR(subQ!AB19/subQ!AB18,"") | AC29: =$D$51 | AD29: =$D$51 | AE29: =IFERROR(subQ!AE19/subQ!AE18,"") | AF29: =$D$51 | AG29: =$D$51 | AH29: =$D$51 | AI29: =$D$51 | AJ29: =IFERROR(subQ!AJ19/subQ!AJ18,"") | AK29: =$D$51 | AL29: =$D$51 | AM29: =$D$51 | AN29: =$D$51 | AO29: =IFERROR(subQ!AO19/subQ!AO18,"")
A30: drv:지배주주순이익 | B30: ratio | C30: 지배주주 비중(/당기순이익) | E30: =IFERROR(subQ!E21/subQ!E20,"") | F30: =IFERROR(subQ!F21/subQ!F20,"") | G30: =IFERROR(subQ!G21/subQ!G20,"") | H30: =IFERROR(subQ!H21/subQ!H20,"") | I30: =IFERROR(subQ!I21/subQ!I20,"") | J30: =IFERROR(subQ!J21/subQ!J20,"") | K30: =IFERROR(subQ!K21/subQ!K20,"") | L30: =IFERROR(subQ!L21/subQ!L20,"") | ... AB30: =IFERROR(subQ!AB21/subQ!AB20,"") | AC30: =$D$53 | AD30: =$D$53 | AE30: =IFERROR(subQ!AE21/subQ!AE20,"") | AF30: =$D$53 | AG30: =$D$53 | AH30: =$D$53 | AI30: =$D$53 | AJ30: =IFERROR(subQ!AJ21/subQ!AJ20,"") | AK30: =$D$53 | AL30: =$D$53 | AM30: =$D$53 | AN30: =$D$53 | AO30: =IFERROR(subQ!AO21/subQ!AO20,"")
A31: drv:부채총계 | B31: qoq | C31: 부채총계 QoQ | G31: =IFERROR(subQ!G23/subQ!E23-1,"") | H31: =IFERROR(subQ!H23/subQ!G23-1,"") | I31: =IFERROR(subQ!I23/subQ!H23-1,"") | J31: =IFERROR(subQ!J23/subQ!I23-1,"") | L31: =IFERROR(subQ!L23/subQ!J23-1,"") | M31: =IFERROR(subQ!M23/subQ!L23-1,"") | N31: =IFERROR(subQ!N23/subQ!M23-1,"") | O31: =IFERROR(subQ!O23/subQ!N23-1,"") | Q31: =IFERROR(subQ!Q23/subQ!O23-1,"") | R31: =IFERROR(subQ!R23/subQ!Q23-1,"") | S31: =IFERROR(subQ!S23/subQ!R23-1,"") | T31: =IFERROR(subQ!T23/subQ!S23-1,"") | V31: =IFERROR(subQ!V23/subQ!T23-1,"") | W31: =IFERROR(subQ!W23/subQ!V23-1,"") | X31: =IFERROR(subQ!X23/subQ!W23-1,"") | Y31: =IFERROR(subQ!Y23/subQ!X23-1,"") | AA31: =IFERROR(subQ!AA23/subQ!Y23-1,"") | AB31: =IFERROR(subQ!AB23/subQ!AA23-1,"") | AC31: -6e-09 | AD31: 0 | AF31: 0 | AG31: 0 | AH31: 0 | AI31: 0 | AK31: 0 | AL31: 0 | AM31: 0 | AN31: 0
A32: drv:자본총계 | B32: roll | C32: 자본총계 기타변동(배당 등, 억원) | G32: =IFERROR(subQ!E24+subQ!G20-subQ!G24,"") | H32: =IFERROR(subQ!G24+subQ!H20-subQ!H24,"") | I32: =IFERROR(subQ!H24+subQ!I20-subQ!I24,"") | J32: =IFERROR(subQ!I24+subQ!J20-subQ!J24,"") | L32: =IFERROR(subQ!J24+subQ!L20-subQ!L24,"") | M32: =IFERROR(subQ!L24+subQ!M20-subQ!M24,"") | N32: =IFERROR(subQ!M24+subQ!N20-subQ!N24,"") | O32: =IFERROR(subQ!N24+subQ!O20-subQ!O24,"") | Q32: =IFERROR(subQ!O24+subQ!Q20-subQ!Q24,"") | R32: =IFERROR(subQ!Q24+subQ!R20-subQ!R24,"") | S32: =IFERROR(subQ!R24+subQ!S20-subQ!S24,"") | T32: =IFERROR(subQ!S24+subQ!T20-subQ!T24,"") | V32: =IFERROR(subQ!T24+subQ!V20-subQ!V24,"") | W32: =IFERROR(subQ!V24+subQ!W20-subQ!W24,"") | X32: =IFERROR(subQ!W24+subQ!X20-subQ!X24,"") | Y32: =IFERROR(subQ!X24+subQ!Y20-subQ!Y24,"") | AA32: =IFERROR(subQ!Y24+subQ!AA20-subQ!AA24,"") | AB32: =IFERROR(subQ!AA24+subQ!AB20-subQ!AB24,"") | AC32: 0.002219706 | AD32: 0.001992804 | AF32: -0.00884461 | AG32: 8697.9045 | AH32: 0.004886995 | AI32: -0.001840368 | AK32: -0.001684756 | AL32: 8697.891 | AM32: -0.006822408 | AN32: 0.002582778
A33: drv:지배주주지분 | B33: roll | C33: 지배주주지분 기타변동(배당 등, 억원) | G33: =IFERROR(subQ!E25+subQ!G21-subQ!G25,"") | H33: =IFERROR(subQ!G25+subQ!H21-subQ!H25,"") | I33: =IFERROR(subQ!H25+subQ!I21-subQ!I25,"") | J33: =IFERROR(subQ!I25+subQ!J21-subQ!J25,"") | L33: =IFERROR(subQ!J25+subQ!L21-subQ!L25,"") | M33: =IFERROR(subQ!L25+subQ!M21-subQ!M25,"") | N33: =IFERROR(subQ!M25+subQ!N21-subQ!N25,"") | O33: =IFERROR(subQ!N25+subQ!O21-subQ!O25,"") | Q33: =IFERROR(subQ!O25+subQ!Q21-subQ!Q25,"") | R33: =IFERROR(subQ!Q25+subQ!R21-subQ!R25,"") | S33: =IFERROR(subQ!R25+subQ!S21-subQ!S25,"") | T33: =IFERROR(subQ!S25+subQ!T21-subQ!T25,"") | V33: =IFERROR(subQ!T25+subQ!V21-subQ!V25,"") | W33: =IFERROR(subQ!V25+subQ!W21-subQ!W25,"") | X33: =IFERROR(subQ!W25+subQ!X21-subQ!X25,"") | Y33: =IFERROR(subQ!X25+subQ!Y21-subQ!Y25,"") | AA33: =IFERROR(subQ!Y25+subQ!AA21-subQ!AA25,"") | AB33: =IFERROR(subQ!AA25+subQ!AB21-subQ!AB25,"") | AC33: 0.006392947 | AD33: -0.000733656 | AF33: 0.003949213 | AG33: 8697.9004 | AH33: -0.000320234 | AI33: 0.004160542 | AK33: -0.001710315 | AL33: 8697.9018 | AM33: 0.00551919 | AN33: -0.002624819
A34: drv:총차입금 | B34: qoq | C34: 총차입금 QoQ | G34: =IFERROR(subQ!G26/subQ!E26-1,"") | H34: =IFERROR(subQ!H26/subQ!G26-1,"") | I34: =IFERROR(subQ!I26/subQ!H26-1,"") | J34: =IFERROR(subQ!J26/subQ!I26-1,"") | L34: =IFERROR(subQ!L26/subQ!J26-1,"") | M34: =IFERROR(subQ!M26/subQ!L26-1,"") | N34: =IFERROR(subQ!N26/subQ!M26-1,"") | O34: =IFERROR(subQ!O26/subQ!N26-1,"") | Q34: =IFERROR(subQ!Q26/subQ!O26-1,"") | R34: =IFERROR(subQ!R26/subQ!Q26-1,"") | S34: =IFERROR(subQ!S26/subQ!R26-1,"") | T34: =IFERROR(subQ!T26/subQ!S26-1,"") | V34: =IFERROR(subQ!V26/subQ!T26-1,"") | W34: =IFERROR(subQ!W26/subQ!V26-1,"") | X34: =IFERROR(subQ!X26/subQ!W26-1,"") | Y34: =IFERROR(subQ!Y26/subQ!X26-1,"") | AA34: =IFERROR(subQ!AA26/subQ!Y26-1,"") | AB34: =IFERROR(subQ!AB26/subQ!AA26-1,"") | AC34: 1.04e-07 | AD34: 0 | AF34: 0 | AG34: 0 | AH34: 0 | AI34: 0 | AK34: 0 | AL34: 0 | AM34: 0 | AN34: 0
A35: drv:순차입금 | B35: qoq | C35: 순차입금 QoQ | G35: =IFERROR(subQ!G27/subQ!E27-1,"") | H35: =IFERROR(subQ!H27/subQ!G27-1,"") | I35: =IFERROR(subQ!I27/subQ!H27-1,"") | J35: =IFERROR(subQ!J27/subQ!I27-1,"") | L35: =IFERROR(subQ!L27/subQ!J27-1,"") | M35: =IFERROR(subQ!M27/subQ!L27-1,"") | N35: =IFERROR(subQ!N27/subQ!M27-1,"") | O35: =IFERROR(subQ!O27/subQ!N27-1,"") | Q35: =IFERROR(subQ!Q27/subQ!O27-1,"") | R35: =IFERROR(subQ!R27/subQ!Q27-1,"") | S35: =IFERROR(subQ!S27/subQ!R27-1,"") | T35: =IFERROR(subQ!T27/subQ!S27-1,"") | V35: =IFERROR(subQ!V27/subQ!T27-1,"") | W35: =IFERROR(subQ!W27/subQ!V27-1,"") | X35: =IFERROR(subQ!X27/subQ!W27-1,"") | Y35: =IFERROR(subQ!Y27/subQ!X27-1,"") | AA35: =IFERROR(subQ!AA27/subQ!Y27-1,"") | AB35: =IFERROR(subQ!AB27/subQ!AA27-1,"") | AC35: 0.098200296 | AD35: 0.091226089 | AF35: 0.086234479 | AG35: 0.028182823 | AH35: 0.08620475 | AI35: 0.084730354 | AK35: 0.083291442 | AL35: 0.039471625 | AM35: 0.082611647 | AN35: 0.079166414
A36: drv:이자발생자산 | B36: qoq | C36: 이자발생자산 QoQ | G36: =IFERROR(subQ!G28/subQ!E28-1,"") | H36: =IFERROR(subQ!H28/subQ!G28-1,"") | I36: =IFERROR(subQ!I28/subQ!H28-1,"") | J36: =IFERROR(subQ!J28/subQ!I28-1,"") | L36: =IFERROR(subQ!L28/subQ!J28-1,"") | M36: =IFERROR(subQ!M28/subQ!L28-1,"") | N36: =IFERROR(subQ!N28/subQ!M28-1,"") | O36: =IFERROR(subQ!O28/subQ!N28-1,"") | Q36: =IFERROR(subQ!Q28/subQ!O28-1,"") | R36: =IFERROR(subQ!R28/subQ!Q28-1,"") | S36: =IFERROR(subQ!S28/subQ!R28-1,"") | T36: =IFERROR(subQ!T28/subQ!S28-1,"") | V36: =IFERROR(subQ!V28/subQ!T28-1,"") | W36: =IFERROR(subQ!W28/subQ!V28-1,"") | X36: =IFERROR(subQ!X28/subQ!W28-1,"") | Y36: =IFERROR(subQ!Y28/subQ!X28-1,"") | AA36: =IFERROR(subQ!AA28/subQ!Y28-1,"") | AB36: =IFERROR(subQ!AB28/subQ!AA28-1,"") | AC36: 0.077852775 | AD36: 0.073688865 | AF36: 0.070794645 | AG36: 0.023470499 | AH36: 0.072121168 | AI36: 0.071818895 | AK36: 0.071449755 | AL36: 0.034234033 | AM36: 0.072012632 | AN36: 0.069691718
A37: drv:현금및현금성자산 | B37: qoq | C37: 현금및현금성자산 QoQ | G37: =IFERROR(subQ!G29/subQ!E29-1,"") | H37: =IFERROR(subQ!H29/subQ!G29-1,"") | I37: =IFERROR(subQ!I29/subQ!H29-1,"") | J37: =IFERROR(subQ!J29/subQ!I29-1,"") | L37: =IFERROR(subQ!L29/subQ!J29-1,"") | M37: =IFERROR(subQ!M29/subQ!L29-1,"") | N37: =IFERROR(subQ!N29/subQ!M29-1,"") | O37: =IFERROR(subQ!O29/subQ!N29-1,"") | Q37: =IFERROR(subQ!Q29/subQ!O29-1,"") | R37: =IFERROR(subQ!R29/subQ!Q29-1,"") | S37: =IFERROR(subQ!S29/subQ!R29-1,"") | T37: =IFERROR(subQ!T29/subQ!S29-1,"") | V37: =IFERROR(subQ!V29/subQ!T29-1,"") | W37: =IFERROR(subQ!W29/subQ!V29-1,"") | X37: =IFERROR(subQ!X29/subQ!W29-1,"") | Y37: =IFERROR(subQ!Y29/subQ!X29-1,"") | AA37: =IFERROR(subQ!AA29/subQ!Y29-1,"") | AB37: =IFERROR(subQ!AB29/subQ!AA29-1,"")
A38: drv:CAPEX | B38: yoy | C38: CAPEX YoY | J38: =IFERROR(subQ!J30/subQ!E30-1,"") | L38: =IFERROR(subQ!L30/subQ!G30-1,"") | M38: =IFERROR(subQ!M30/subQ!H30-1,"") | N38: =IFERROR(subQ!N30/subQ!I30-1,"") | O38: =IFERROR(subQ!O30/subQ!J30-1,"") | Q38: =IFERROR(subQ!Q30/subQ!L30-1,"") | R38: =IFERROR(subQ!R30/subQ!M30-1,"") | S38: =IFERROR(subQ!S30/subQ!N30-1,"") | T38: =IFERROR(subQ!T30/subQ!O30-1,"") | V38: =IFERROR(subQ!V30/subQ!Q30-1,"") | W38: =IFERROR(subQ!W30/subQ!R30-1,"") | X38: =IFERROR(subQ!X30/subQ!S30-1,"") | Y38: =IFERROR(subQ!Y30/subQ!T30-1,"") | AA38: =IFERROR(subQ!AA30/subQ!V30-1,"") | AB38: =IFERROR(subQ!AB30/subQ!W30-1,"") | AC38: -0.051399817 | AD38: -0.1170748 | AF38: 0.14586764 | AG38: 0.057287555 | AH38: 0 | AI38: 0 | AK38: 0 | AL38: 0 | AM38: 0 | AN38: 0
A39: drv:영업활동현금흐름 | B39: yoy | C39: 영업활동현금흐름 YoY | J39: =IFERROR(subQ!J31/subQ!E31-1,"") | L39: =IFERROR(subQ!L31/subQ!G31-1,"") | M39: =IFERROR(subQ!M31/subQ!H31-1,"") | N39: =IFERROR(subQ!N31/subQ!I31-1,"") | O39: =IFERROR(subQ!O31/subQ!J31-1,"") | Q39: =IFERROR(subQ!Q31/subQ!L31-1,"") | R39: =IFERROR(subQ!R31/subQ!M31-1,"") | S39: =IFERROR(subQ!S31/subQ!N31-1,"") | T39: =IFERROR(subQ!T31/subQ!O31-1,"") | V39: =IFERROR(subQ!V31/subQ!Q31-1,"") | W39: =IFERROR(subQ!W31/subQ!R31-1,"") | X39: =IFERROR(subQ!X31/subQ!S31-1,"") | Y39: =IFERROR(subQ!Y31/subQ!T31-1,"") | AA39: =IFERROR(subQ!AA31/subQ!V31-1,"") | AB39: =IFERROR(subQ!AB31/subQ!W31-1,"")
A40: drv:주식수 | B40: qoq | C40: 주식수 QoQ | G40: =IFERROR(subQ!G32/subQ!E32-1,"") | H40: =IFERROR(subQ!H32/subQ!G32-1,"") | I40: =IFERROR(subQ!I32/subQ!H32-1,"") | J40: =IFERROR(subQ!J32/subQ!I32-1,"") | L40: =IFERROR(subQ!L32/subQ!J32-1,"") | M40: =IFERROR(subQ!M32/subQ!L32-1,"") | N40: =IFERROR(subQ!N32/subQ!M32-1,"") | O40: =IFERROR(subQ!O32/subQ!N32-1,"") | Q40: =IFERROR(subQ!Q32/subQ!O32-1,"") | R40: =IFERROR(subQ!R32/subQ!Q32-1,"") | S40: =IFERROR(subQ!S32/subQ!R32-1,"") | T40: =IFERROR(subQ!T32/subQ!S32-1,"") | V40: =IFERROR(subQ!V32/subQ!T32-1,"") | W40: =IFERROR(subQ!W32/subQ!V32-1,"") | X40: =IFERROR(subQ!X32/subQ!W32-1,"") | Y40: =IFERROR(subQ!Y32/subQ!X32-1,"") | AA40: =IFERROR(subQ!AA32/subQ!Y32-1,"") | AB40: =IFERROR(subQ!AB32/subQ!AA32-1,"") | AC40: 0 | AD40: 0 | AF40: 0 | AG40: 0 | AH40: 0 | AI40: 0 | AK40: 0 | AL40: 0 | AM40: 0 | AN40: 0
A41: drv:DPS | B41: abs | C41: DPS (가정, 원) | E41: =subQ!E35 | F41: =subQ!F35 | G41: =subQ!G35 | H41: =subQ!H35 | I41: =subQ!I35 | J41: =subQ!J35 | K41: =subQ!K35 | L41: =subQ!L35 | ... AB41: =subQ!AB35 | AD41: 12300 | AE41: =subQ!AE35 | AI41: 12300 | AJ41: =subQ!AJ35 | AN41: 12300 | AO41: =subQ!AO35
B43: 3. 밸류에이션·스칼라 | C43: 노란 셀 = 가정. '연결' 표시는 추정 전 분기 수식이 이 셀을 참조한다는 뜻
A44: sc:종가 | C44: 종가 | D44: 279500 | E44: 원 — 네이버 정규장 종가(aik 확정종가 대조 · aik 301,500원)
A45: sc:기준일 | C45: 기준일 | D45: 20261012 | E45: 종가 기준일
A46: sc:COE | C46: COE | D46: 0.09 | E46: 자기자본비용(가정) — TP 적정 PBR = ROE/COE
A47: sc:PER_lo | C47: PER_lo | D47: 11.7 | E47: PER 밴드 하단(배) — hist_quarterly(분기 평균가 ÷ TTM EPS, 13분기, 25/50/75 백분위)
A48: sc:PER_mid | C48: PER_mid | D48: 13.1 | E48: PER 밴드 중단(배)
A49: sc:PER_hi | C49: PER_hi | D49: 21.5 | E49: PER 밴드 상단(배)
A50: sc:EPS_Y1가중 | C50: EPS_Y1가중 | D50: 0.5 | E50: 12M fwd EPS = FY(last_actual연도)E × w + FY+1E × (1−w) — 기준 분기 2Q 이면 0.5(가정)
A51: sc:세율 | C51: 세율 | D51: 0.19892701 | E51: 연결 — 법인세 = MAX(세전,0) × 세율(역산, 재현 오차 ≤ 0.05억 · 모델 assumptions 0.1989) · 최근 12분기 유효세율 19.9%(5~27% 안 — 그대로)
A52: sc:판관비율 | C52: 판관비율 | D52: 0.048429844 | E52: 연결 — 판관비 = 매출액 × 판관비율(역산, 재현 오차 ≤ 0.05억 · 모델 assumptions 0.0484)
A53: sc:지배주주비중 | C53: 지배주주비중 | D53: 0.76002778 | E53: 연결 — 지배주주순이익 = 당기순이익 × 비중(역산, 재현 오차 ≤ 0.05억)
A54: sc:이자율_자산 | C54: 이자율_자산 | D54: 0.028167872 | E54: 연결 — 이자손익 = (전분기 이자발생자산 × 자산이자율 − 전분기 총차입금 × 부채이자율)/4(역산, 재현 오차 ≤ 0.05억 · 모델 assumptions 0.0282)
A55: sc:이자율_부채 | C55: 이자율_부채 | D55: 0.13116192 | E55: 연결 — 같은 수식의 부채 쪽(총차입금 행이 없으면 0)(역산, 재현 오차 ≤ 0.05억 · 모델 assumptions 0.1312)
A56: sc:배당성향 | C56: 배당성향 | D56: 0.4011 | E56: 배당성향(참고 — 모델은 직전 DPS 유지·Q2 지급 가정)
A57: sc:외화순노출_백만$ | C57: 외화순노출_백만$ | E57: 외화 순노출 × Δ기말환율 (외화 시트 방식) — 외화 순노출 미공시(face) → 0 + 표기
A58: sc:헤지비율 | C58: 헤지비율 | D58: 0.7 | E58: SLS 원화 = Σ 스케줄 × (헤지비율 × 헤지환율 + (1−헤지비율) × 건조시점 환율[원/달러(평균)]) — estimate · 통화선도 공시 없음 → HEDGE 70% 가정(레퍼런스 SLS 시트 HEDGE 행은 미포 65%·삼성重 100% — 그 사이에 둔 설정값). hedge_rate 는 계약별 수주시점 환율로 대체
A59: sc:헤지환율_약정 | C59: 헤지환율_약정 | E59: 정기보고서 평균 약정환율(measured) — 비어 있으면 계약별 수주시점 환율(fx_at_sign)을 쓴다

Sheet BS연결
B1: (백만원) | C1: 이름: BS연결H | E1: 4Q21 | F1: 2021 | G1: 1Q22 | H1: 2Q22 | I1: 3Q22 | J1: 4Q22 | K1: 2022 | L1: 1Q23 | M1: 2Q23 | N1: 3Q23 | O1: 4Q23 | P1: 2023 | Q1: 1Q24 | R1: 2Q24 | S1: 3Q24 | T1: 4Q24 | U1: 2024 | V1: 1Q25 | W1: 2Q25 | X1: 3Q25 | Y1: 4Q25 | Z1: 2025 | AA1: 1Q26 | AB1: 2Q26 | AC1: 3Q26 | AD1: 4Q26 | AE1: 2026 | AF1: 1Q27 | AG1: 2Q27 | AH1: 3Q27 | AI1: 4Q27 | AJ1: 2027 | AK1: 1Q28 | AL1: 2Q28 | AM1: 3Q28 | AN1: 4Q28 | AO1: 2028
B2: 연결 | D2: fin json(kship_fin.py)
B3: HD한국조선해양(연) | C3: UPDATE: 26-10-12 | E3: 1 | F3: 2 | G3: 3 | H3: 4 | I3: 5 | J3: 6 | K3: 7 | L3: 8 | M3: 9 | N3: 10 | O3: 11 | P3: 12 | Q3: 13 | R3: 14 | S3: 15 | T3: 16 | U3: 17 | V3: 18 | W3: 19 | X3: 20 | Y3: 21 | Z3: 22 | AA3: 23 | AB3: 24 | AC3: 25 | AD3: 26 | AE3: 27 | AF3: 28 | AG3: 29 | AH3: 30 | AI3: 31 | AJ3: 32 | AK3: 33 | AL3: 34 | AM3: 35 | AN3: 36 | AO3: 37
B4: Account Code | C4: AccountNAME | E4: 2021.12 | F4: 2021.12A | G4: 2022.03 | H4: 2022.06 | I4: 2022.09 | J4: 2022.12 | K4: 2022.12A | L4: 2023.03 | M4: 2023.06 | N4: 2023.09 | O4: 2023.12 | P4: 2023.12A | Q4: 2024.03 | R4: 2024.06 | S4: 2024.09 | T4: 2024.12 | U4: 2024.12A | V4: 2025.03 | W4: 2025.06 | X4: 2025.09 | Y4: 2025.12 | Z4: 2025.12A | AA4: 2026.03 | AB4: 2026.06 | AC4: 2026.09 | AD4: 2026.12 | AE4: 2026.12A | AF4: 2027.03 | AG4: 2027.06 | AH4: 2027.09 | AI4: 2027.12 | AJ4: 2027.12A | AK4: 2028.03 | AL4: 2028.06 | AM4: 2028.09 | AN4: 2028.12 | AO4: 2028.12A
A5: 1 | C5: 유동자산 | E5: 14562196 | F5: 14562196 | G5: 15055674 | H5: 16265600 | I5: 18102306 | J5: 15775914 | K5: 15775914 | L5: 16219644 | M5: 17381113 | N5: 18479102 | O5: 17735127 | P5: 17735127 | Q5: 17895153 | R5: 18247451 | S5: 17264688 | T5: 20431356 | U5: 20431356 | V5: 23289377 | W5: 22015176 | X5: 23057853 | Y5: 23424478 | Z5: 23424478 | AA5: 25710146 | AB5: 30170024
A6: 1 | C6: 현금및현금성자산 | E6: 4567468.1 | F6: 4567468.1 | G6: 4532301.5 | H6: 4752961.1 | I6: 3634472.2 | J6: 2697222.9 | K6: 2697222.9 | L6: 2852572.6 | M6: 4270309.7 | N6: 4035501.8 | O6: 3018391 | P6: 3018391 | Q6: 3669603.9 | R6: 3397850.3 | S6: 2543376.7 | T6: 3717319 | U6: 3717319 | V6: 5600443.1 | W6: 5513834 | X6: 4709370.9 | Y6: 3742015.5 | Z6: 3742015.5 | AA6: 6468672.8 | AB6: 10995975
A7: 1 | C7: 단기금융상품 | E7: 660027.77 | F7: 660027.77 | G7: 754500.51 | H7: 628361.61 | I7: 1443706 | J7: 1304041.5 | K7: 1304041.5 | L7: 1170875.3 | M7: 341542.35 | N7: 1057491.3 | O7: 1595618.7 | P7: 1595618.7 | Q7: 983649.16 | R7: 1815275.1 | S7: 1764395.1 | T7: 1922179.2 | U7: 1922179.2 | V7: 2454897.5 | W7: 2705949.6 | Y7: 4434581.4 | Z7: 4434581.4 | AA7: 3267664.3 | AB7: 2596829.4
A8: 1 | C8: 단기금융자산 | E8: 848060.65 | F8: 848060.65 | G8: 1023391.7 | H8: 1212233.1 | I8: 2701185.8 | J8: 1818718 | K8: 1818718 | L8: 1747798.9 | M8: 908706.84 | N8: 1735702.7 | O8: 2025013.7 | P8: 2025013.7 | Q8: 1570842.6 | R8: 2558446.5 | S8: 2204130 | T8: 3115653.6 | U8: 3115653.6 | V8: 3472603.2 | W8: 3153286.3 | Y8: 5125708 | Z8: 5125708 | AA8: 4427782.3 | AB8: 3984024
A9: 1 | C9: 매출채권및기타채권 | E9: 1067698 | F9: 1067698 | G9: 1055271 | H9: 1573082 | I9: 1344506.2 | J9: 1026706.3 | K9: 1026706.3 | L9: 1132897.1 | M9: 1112498.9 | N9: 1320685.2 | O9: 1460128.9 | P9: 1460128.9 | Q9: 1444969.5 | R9: 1458522.8 | S9: 1555797 | T9: 1640342.8 | U9: 1640342.8 | V9: 2061517.4 | W9: 1643448.5 | Y9: 1812029.6 | Z9: 1812029.6 | AA9: 1768844.4 | AB9: 1829787.4
A10: 1 | C10: 계약자산 | E10: 5502878.4 | F10: 5502878.4 | G10: 5712921.8 | H10: 5787753.5 | I10: 6879969.6 | J10: 6435957.2 | K10: 6435957.2 | L10: 6404863.5 | M10: 7005608 | N10: 7080262.7 | O10: 7156818.3 | P10: 7156818.3 | Q10: 6962382.6 | R10: 6693699.4 | S10: 6527921.7 | T10: 7503003.9 | U10: 7503003.9 | V10: 7050616.6 | W10: 6667632.2 | Y10: 7738830.4 | Z10: 7738830.4 | AA10: 8059754 | AB10: 8242620
A11: 1 | C11: 재고자산 | E11: 1554136.7 | F11: 1554136.7 | G11: 1626869.9 | H11: 1750576.8 | I11: 2176607 | J11: 2203316.6 | K11: 2203316.6 | L11: 2229702.4 | M11: 2141559 | N11: 2174245.4 | O11: 2005664.7 | P11: 2005664.7 | Q11: 2216194 | R11: 2128191.8 | S11: 2337487.5 | T11: 2232067 | U11: 2232067 | V11: 2368177.5 | W11: 2477601.5 | Y11: 2765843.2 | Z11: 2765843.2 | AA11: 2943570.7 | AB11: 3168879.3
A12: 1 | C12: 유동파생상품자산 | E12: 14528.49 | F12: 14528.49 | G12: 40303.62 | H12: 69900.57 | I12: 131143.12 | J12: 169837.01 | K12: 169837.01 | L12: 130245.86 | M12: 122965.27 | N12: 112831.45 | O12: 143267.3 | P12: 143267.3 | Q12: 36191.34 | R12: 5407.3 | S12: 98613.01 | T12: 1162.39 | U12: 1162.39 | V12: 2661.44 | W12: 93986.32 | Y12: 13602.67 | Z12: 13602.67 | AA12: 89255.86 | AB12: 99637.62
A13: 1 | C13: 유동확정계약자산 | E13: 173504.39 | F13: 173504.39 | G13: 228587.54 | H13: 513970.96 | I13: 1126336.7 | J13: 344839.51 | K13: 344839.51 | L13: 446677.76 | M13: 444199.22 | N13: 565379.94 | O13: 286127.7 | P13: 286127.7 | Q13: 551002.12 | R13: 737764.03 | S13: 341121.84 | T13: 1192312 | U13: 1192312 | V13: 1015044.2 | W13: 353350.45 | Y13: 677523.87 | Z13: 677523.87 | AA13: 1070862.1 | AB13: 1287557
A14: 1 | C14: 당기법인세자산(선급법인세) | E14: 7762.97 | F14: 7762.97 | G14: 9212.23 | H14: 3680.53 | I14: 6557.67 | J14: 12589.48 | K14: 12589.48 | L14: 18492.13 | M14: 12413.62 | N14: 18160.32 | O14: 22350.22 | P14: 22350.22 | Q14: 29131.28 | R14: 7152.74 | S14: 8924.7 | T14: 6101.77 | U14: 6101.77 | V14: 6733.31 | W14: 1280.41 | X14: 1801.9 | Y14: 657.63 | Z14: 657.63 | AA14: 937.65 | AB14: 4935.35
A15: 1 | C15: 매각예정비유동자산및처분자산 | E15: 13082.98 | F15: 13082.98 | O15: 0 | P15: 0 | T15: 63000.19 | U15: 63000.19 | V15: 0 | W15: 4626.85 | X15: 4626.85 | Y15: 0 | Z15: 0
A16: 1 | C16: 기타유동자산 | E16: 1001108.2 | F16: 1001108.2 | G16: 1095706.1 | H16: 1185313.4 | I16: 1359007.1 | J16: 1581403.8 | K16: 1581403.8 | L16: 1833316.8 | M16: 1930017.4 | N16: 2114544.3 | O16: 2046760.4 | P16: 2046760.4 | Q16: 2002029.1 | R16: 2003587.1 | S16: 2087050.3 | T16: 2153868.2 | U16: 2153868.2 | V16: 2729285.8 | W16: 2553466.2 | X16: 2296629.1 | Y16: 2239393.5 | Z16: 2239393.5 | AA16: 2040584.5 | AB16: 1943802.9
A17: 1 | C17: 비유동자산 | E17: 12730898 | F17: 12730898 | G17: 12885645 | H17: 13656117 | I17: 15015790 | J17: 14107562 | K17: 14107562 | L17: 14226195 | M17: 14255866 | N17: 14754484 | O17: 14507441 | P17: 14507441 | Q17: 14614725 | R17: 14898039 | S17: 14761399 | T17: 16287781 | U17: 16287781 | V17: 16198822 | W17: 15258250 | X17: 15369660 | Y17: 16117735 | Z17: 16117735 | AA17: 16494705 | AB17: 16554812
A18: 1 | C18: 종속기업및관계기업투자 | E18: 321972.07 | F18: 321972.07 | G18: 282267.2 | H18: 281742.73 | I18: 281165.27 | J18: 269723.77 | K18: 269723.77 | L18: 267612.72 | M18: 251483.65 | N18: 264976.49 | O18: 308959.16 | P18: 308959.16 | Q18: 307392.06 | R18: 315049.24 | S18: 298341.77 | T18: 256615.05 | U18: 256615.05 | V18: 255282.18 | W18: 202951.54 | X18: 205915.58 | Y18: 206177.77 | Z18: 206177.77 | AA18: 210058.58 | AB18: 241306.88
A19: 1 | C19: 투자자산 | E19: 801835.8 | F19: 801835.8 | G19: 802175.67 | H19: 1408967.6 | I19: 2676341.8 | J19: 1152709.6 | K19: 1152709.6 | L19: 1197562.3 | M19: 1102008.5 | N19: 1245718.7 | O19: 970881.11 | P19: 970881.11 | Q19: 1076455.8 | R19: 1361295.8 | S19: 872964.91 | T19: 2164452.7 | U19: 2164452.7 | V19: 2109994.4 | W19: 1034095.4 | X19: 1261608.8 | Y19: 1591674.3 | Z19: 1591674.3 | AA19: 2312047.5 | AB19: 2393703.1
A20: 1 | C20: 장기금융자산 | E20: 194920.08 | F20: 194920.08 | G20: 235680.99 | H20: 208361.52 | I20: 177758.22 | J20: 201294.94 | K20: 201294.94 | L20: 215008.15 | M20: 237145.51 | N20: 219067.27 | O20: 232714.3 | P20: 232714.3 | Q20: 137208.8 | R20: 133134.52 | S20: 138455.85 | T20: 141591.46 | U20: 141591.46 | V20: 141428.37 | W20: 147247.45 | X20: 126454.09 | Y20: 139177.02 | Z20: 139177.02 | AA20: 145896.86 | AB20: 148784.66
A21: 1 | C21: 장기매출채권및기타채권 | E21: 150019.08 | F21: 150019.08 | G21: 195653.54 | H21: 236188.38 | I21: 313969.69 | J21: 250490.03 | K21: 250490.03 | L21: 285803.88 | M21: 280599.39 | N21: 302394.19 | O21: 252258.03 | P21: 252258.03 | Q21: 268320.59 | R21: 257891.23 | S21: 225234.83 | T21: 192697.65 | U21: 192697.65 | V21: 161356.45 | W21: 143599.44 | X21: 161208.64 | Y21: 119081.38 | Z21: 119081.38 | AA21: 117875.42 | AB21: 119370.5
A22: 1 | C22: 투자부동산 | E22: 231498.68 | F22: 231498.68 | G22: 225622.29 | H22: 224549.19 | I22: 223488.64 | J22: 222373.89 | K22: 222373.89 | L22: 221330.1 | M22: 220618.67 | N22: 219477.79 | O22: 218330.34 | P22: 218330.34 | Q22: 217398.32 | R22: 218390.88 | S22: 303038.83 | T22: 216566.15 | U22: 216566.15 | V22: 215397.29 | W22: 209622.31 | X22: 208545.68 | Y22: 130204.19 | Z22: 130204.19 | AA22: 129671.2 | AB22: 129057.01
A23: 1 | C23: 유형자산 | E23: 9872012 | F23: 9872012 | G23: 9879817.2 | H23: 9957200 | I23: 10083239 | J23: 10143113 | K23: 10143113 | L23: 10201693 | M23: 10321642 | N23: 10432116 | O23: 10503503 | P23: 10503503 | Q23: 10565402 | R23: 10687802 | S23: 10912699 | T23: 11110890 | U23: 11110890 | V23: 11299189 | W23: 11703121 | X23: 11816084 | Y23: 12025455 | Z23: 12025455 | AA23: 12036472 | AB23: 12153874
A24: 1 | C24: 사용권자산 | E24: 51714.13 | F24: 51714.13 | G24: 51765.05 | H24: 52033.52 | I24: 50187.03 | J24: 108493.82 | K24: 108493.82 | L24: 105249.25 | M24: 101373.99 | N24: 101968.75 | O24: 100432.71 | P24: 100432.71 | Q24: 98673.55 | R24: 93883.53 | S24: 87771.76 | T24: 484619.59 | U24: 484619.59 | V24: 480902.57 | W24: 443820.01 | X24: 449018.49 | Y24: 444896.48 | Z24: 444896.48 | AA24: 466872.33 | AB24: 463343.92
A25: 1 | C25: 기타비유동자산 | E25: 112078.03 | F25: 112078.03 | G25: 132621.87 | H25: 132318.96 | I25: 107703.57 | J25: 674090.26 | K25: 674090.26 | L25: 653237.61 | M25: 665461.79 | N25: 649765.75 | O25: 646909.4 | P25: 646909.4 | Q25: 620001.9 | R25: 623381.95 | S25: 604777.8 | T25: 843653.05 | U25: 843653.05 | V25: 790617.88 | W25: 719843.18 | X25: 692160.01 | Y25: 1012788 | Z25: 1012788 | AA25: 1003419.4 | AB25: 973342.54
A26: 1 | C26: 무형자산 | E26: 133535.87 | F26: 133535.87 | G26: 136254.92 | H26: 138643.79 | I26: 149354.67 | J26: 163697.16 | K26: 163697.16 | L26: 170964.98 | M26: 178935.63 | N26: 193535.36 | O26: 190793.08 | P26: 190793.08 | Q26: 195077.65 | R26: 201972.64 | S26: 322022.47 | T26: 374650.95 | U26: 374650.95 | V26: 384210.88 | W26: 391727.87 | X26: 395543.78 | Y26: 519011.46 | Z26: 519011.46 | AA26: 531927.3 | AB26: 539665.72
A27: 1 | C27: 비유동파생상품자산 | E27: 44764.33 | F27: 44764.33 | G27: 66274.52 | H27: 89606.57 | I27: 168984.18 | J27: 388939.41 | K27: 388939.41 | L27: 191238.26 | M27: 213250.54 | N27: 122759.99 | O27: 250805.05 | P27: 250805.05 | Q27: 84685.04 | R27: 54772.17 | S27: 138915.2 | T27: 64055.7 | U27: 64055.7 | V27: 66263.49 | W27: 316839.19 | X27: 110578.23 | Y27: 102577.92 | Z27: 102577.92 | AA27: 2877.08 | AB27: 8557.09
... A48: 1 | C48: 장기매입채무및기타채무 | E48: 9250.1 | F48: 9250.1 | G48: 8831.59 | H48: 8781.95 | I48: 8858.45 | J48: 9225.66 | K48: 9225.66 | L48: 9211.51 | M48: 9584.18 | N48: 20102.28 | O48: 25747.46 | P48: 25747.46 | Q48: 25232.09 | R48: 26760.8 | S48: 28666.04 | T48: 34511.49 | U48: 34511.49 | V48: 36016.99 | W48: 38222.24 | X48: 39955.89 | Y48: 47062.97 | Z48: 47062.97 | AA48: 51962.92 | AB48: 55137.06
A49: 1 | C49: 확정급여부채 | E49: 59562.11 | F49: 59562.11 | G49: 61543.54 | H49: 63183.42 | I49: 69800.12 | J49: 52628.12 | K49: 52628.12 | L49: 53467.39 | M49: 53546.75 | N49: 55321.96 | O49: 55801.68 | P49: 55801.68 | Q49: 55680.39 | R49: 56114.38 | S49: 57783.47 | T49: 58441.45 | U49: 58441.45 | V49: 49324.45 | X49: 55801.36 | Y49: 44333.5 | Z49: 44333.5 | AA49: 45958.51 | AB49: 46936.6
A50: 1 | C50: 장기충당부채 | E50: 319090.17 | F50: 319090.17 | G50: 331684.26 | H50: 347164.85 | I50: 373963.69 | J50: 321790.6 | K50: 321790.6 | L50: 284280.93 | M50: 305307.22 | N50: 310159.9 | O50: 84658.17 | P50: 84658.17 | Q50: 85260.02 | R50: 96962.37 | S50: 105491.03 | T50: 102619.02 | U50: 102619.02 | V50: 108322.92 | W50: 104717.99 | X50: 103721.5 | Y50: 111316.77 | Z50: 111316.77 | AA50: 116754.78 | AB50: 115934.98
A51: 1 | C51: 장기파생상품부채 | E51: 247054.35 | F51: 247054.35 | G51: 255840.72 | H51: 839810.35 | I51: 2055965.3 | J51: 620301.51 | K51: 620301.51 | L51: 696697.59 | M51: 598464.87 | N51: 737100.8 | O51: 420577.57 | P51: 420577.57 | Q51: 607755.24 | R51: 875928.12 | S51: 411294.18 | T51: 1702277.5 | U51: 1702277.5 | V51: 1650110.6 | W51: 650880.45 | X51: 886912.66 | Y51: 1191846.7 | Z51: 1191846.7 | AA51: 1975136.2 | AB51: 2023765.8
A52: 1 | C52: 이연법인세부채 | E52: 59054.29 | F52: 59054.29 | G52: 66758.77 | H52: 77088.05 | I52: 59882.13 | J52: 1271.5 | K52: 1271.5 | L52: 1275.13 | M52: 1269.4 | N52: 830.74 | O52: 1478.77 | P52: 1478.77 | Q52: 1480.35 | R52: 4856.14 | S52: 20961.24 | T52: 1192.62 | U52: 1192.62 | V52: 1955.34 | W52: 1236.06 | X52: 5608.62 | Y52: 4532.74 | Z52: 4532.74 | AA52: 13819.71 | AB52: 158187.18
A53: 1 | C53: 부채총계 | E53: 14879339 | F53: 14879339 | G53: 15772766 | H53: 17715884 | I53: 20603881 | J53: 17571346 | K53: 17571346 | L53: 18180091 | M53: 19346745 | N53: 20615317 | O53: 19872465 | P53: 19872465 | Q53: 19951678 | R53: 19926316 | S53: 18454669 | T53: 22563324 | U53: 22563324 | V53: 25016945 | W53: 21968154 | X53: 22475233 | Y53: 22633860 | Z53: 22633860 | AA53: 24888295 | AB53: 27800917
A54: 1 | C54: 지배주주지분 | E54: 9856559.1 | F54: 9856559.1 | G54: 9659384.5 | H54: 9587848.4 | I54: 9801730.9 | J54: 9714919.2 | K54: 9714919.2 | L54: 9682086.6 | M54: 9728327.2 | N54: 10048549 | O54: 9903690.5 | P54: 9903690.5 | Q54: 10086862 | R54: 10518174 | S54: 10671554 | T54: 11099427 | U54: 11099427 | V54: 11369215 | W54: 11994279 | X54: 12437819 | Y54: 13286078 | Z54: 13286078 | AA54: 13549753 | AB54: 14829924
A55: 1 | C55: 자본금 | E55: 353865.58 | F55: 353865.58 | G55: 353865.58 | H55: 353865.58 | I55: 353865.58 | J55: 353865.58 | K55: 353865.58 | L55: 353865.58 | M55: 353865.58 | N55: 353865.58 | O55: 353865.58 | P55: 353865.58 | Q55: 353865.58 | R55: 353865.58 | S55: 353865.58 | T55: 353865.58 | U55: 353865.58 | V55: 353865.58 | W55: 353865.58 | X55: 353865.58 | Y55: 353865.58 | Z55: 353865.58 | AA55: 353865.58 | AB55: 353865.58
A56: 1 | C56: 자본잉여금 | E56: 2400507.2 | F56: 2400507.2 | G56: 2400507.2 | H56: 2467505.9 | I56: 2467505.9 | J56: 2467505.9 | K56: 2467505.9 | L56: 2466883.3 | M56: 2461903.5 | N56: 2459463.7 | O56: 2459694.6 | P56: 2459694.6 | Q56: 2458941.5 | R56: 2599805.7 | S56: 2599768.7 | T56: 2599782.4 | U56: 2599782.4 | V56: 2599782.2 | W56: 2722590.6 | X56: 2762402.1 | Y56: 3016775.3 | Z56: 3016775.3 | AA56: 3043385 | AB56: 3026446.4
A57: 1 | C57: 기타자본 | E57: -8697362.6 | F57: -8697362.6 | G57: -8703261.5 | H57: -8703261.5 | I57: -8703261.5 | J57: -8703261.5 | K57: -8703261.5 | L57: -8608510 | M57: -8608510 | N57: -8609897.3 | O57: -8609897.2 | P57: -8609897.2 | Q57: -8609897.2 | R57: -8609897.2 | S57: -8609184.6 | T57: -8609021.4 | U57: -8609021.4 | V57: -8488512.3 | W57: -8526891.1 | X57: -8541364.9 | Y57: -8608784.6 | Z57: -8608784.6 | AA57: -8608763.7 | AB57: -8615335.2
A58: 1 | C58: 기타포괄이익누계액 | E58: 1332378.6 | F58: 1332378.6 | G58: 1340687.2 | H58: 1324023.6 | I58: 1307202.8 | J58: 1296442.4 | K58: 1296442.4 | L58: 1307514.1 | M58: 1329368.2 | N58: 1315646.3 | O58: 1325567.8 | P58: 1325567.8 | Q58: 1652051.9 | R58: 1649300.6 | S58: 1650953.5 | T58: 1670921 | U58: 1670921 | V58: 1684934.6 | W58: 1867347.2 | X58: 1886836.1 | Y58: 1856691.8 | Z58: 1856691.8 | AA58: 1892972.7 | AB58: 1906187.6
A59: 1 | C59: 이익잉여금 | E59: 14467170 | F59: 14467170 | G59: 14267586 | H59: 14145715 | I59: 14376418 | J59: 14300367 | K59: 14300367 | L59: 14162334 | M59: 14191700 | N59: 14529471 | O59: 14374460 | P59: 14374460 | Q59: 14231900 | R59: 14525099 | S59: 14676151 | T59: 15083879 | U59: 15083879 | V59: 15219145 | W59: 15577366 | X59: 15976080 | Y59: 16667530 | Z59: 16667530 | AA59: 16868293 | AB59: 18158759
A60: 1 | C60: 비지배주주지분 | E60: 2557196.2 | F60: 2557196.2 | G60: 2509168 | H60: 2617984.7 | I60: 2712483.6 | J60: 2597210.6 | K60: 2597210.6 | L60: 2583661.1 | M60: 2561907.6 | N60: 2569720.5 | O60: 2466412.4 | P60: 2466412.4 | Q60: 2471338.2 | R60: 2700999.5 | S60: 2899864.4 | T60: 3056386.1 | U60: 3056386.1 | V60: 3102040.3 | W60: 3310993.3 | X60: 3514460.7 | Y60: 3622275.1 | Z60: 3622275.1 | AA60: 3766804.1 | AB60: 4093996.1
A61: 1 | C61: 자본총계 | E61: 12413755 | F61: 12413755 | G61: 12168552 | H61: 12205833 | I61: 12514215 | J61: 12312130 | K61: 12312130 | L61: 12265748 | M61: 12290235 | N61: 12618270 | O61: 12370103 | P61: 12370103 | Q61: 12558200 | R61: 13219174 | S61: 13571419 | T61: 14155813 | U61: 14155813 | V61: 14471255 | W61: 15305272 | X61: 15952280 | Y61: 16908353 | Z61: 16908353 | AA61: 17316557 | AB61: 18923920
... A65: 1 | C65: 이자발생자산 | E65: 5610448.8 | F65: 5610448.8 | G65: 5791374.1 | H65: 6173555.7 | I65: 6513416.2 | J65: 4717235.8 | K65: 4717235.8 | L65: 4815379.7 | M65: 5416162.1 | N65: 5990271.8 | O65: 5276118.9 | P65: 5276118.9 | Q65: 5377655.3 | R65: 6089431.2 | S65: 4885962.5 | T65: 6974564 | U65: 6974564 | V65: 9214474.7 | W65: 8814367.8 | X65: 4835825 | Y65: 9006900.5 | Z65: 9006900.5 | AA65: 11042352 | AB65: 15128784
A66: 1 | C66: 유동성장기부채 | E66: 1155256.6 | F66: 1155256.6 | G66: 1457139.7 | H66: 1929332 | I66: 2202204.9 | L66: 1595927.1 | M66: 1133826.8 | N66: 1025888.8 | O66: 1293920 | P66: 1293920 | Q66: 1121558.2 | R66: 578527.95 | S66: 579223.51 | T66: 375439.96 | U66: 375439.96 | V66: 389333.68 | W66: 335430.93 | X66: 258565.73 | Y66: 154967.44 | Z66: 154967.44
A67: 1 | C67: 단기금융부채(face) | J67: 2700995.4 | K67: 2700995.4 | AA67: 983399.58 | AB67: 2927467.7
A68: 1 | C68: 매출액(수익) | E68: 4456648.7 | G68: 3907727.9 | H68: 4188606.5 | I68: 4264415.3 | J68: 4941270.5 | K68: 17302020 | L68: 4842359.5 | M68: 5453640 | N68: 5011205.9 | O68: 5989000.2 | P68: 21296206 | Q68: 5515626 | R68: 6615483.7 | S68: 6245755.8 | T68: 7161711.9 | U68: 25538577 | V68: 6771705.9 | W68: 7428417 | X68: 7581435.7 | Y68: 8151656.6 | Z68: 29933215 | AA68: 8140889.8 | AB68: 8927046.5
A69: 1 | C69: 매출원가 | E69: 4826101 | G69: 4081812.9 | H69: 4242899 | I69: 3853876.4 | J69: 4756992.3 | K69: 16935581 | L69: 4638593.8 | M69: 5170910.7 | N69: 4714261.3 | O69: 5724412.7 | P69: 20248178 | Q69: 5165675.4 | R69: 5906289.6 | S69: 5539033.5 | T69: 6332211.4 | U69: 22943210 | V69: 5609799.7 | W69: 6126416.4 | X69: 6183788.9 | Y69: 6684789.3 | Z69: 24604794 | AA69: 6396263.4 | AB69: 6843417.4
A70: 1 | C70: 매출총이익 | E70: -369452.26 | G70: -174084.94 | H70: -54292.6 | I70: 410538.95 | J70: 184278.14 | K70: 366439.55 | L70: 203765.7 | M70: 282729.32 | N70: 296944.56 | O70: 264587.57 | P70: 1048027.2 | Q70: 349950.6 | R70: 709194.09 | S70: 706722.25 | T70: 829500.49 | U70: 2595367.4 | V70: 1161906.2 | W70: 1302000.7 | X70: 1397646.9 | Y70: 1466867.3 | Z70: 5328421 | AA70: 1744626.4 | AB70: 2083629.1
A71: 1 | C71: 판관비 | E71: 327305.99 | G71: 222310.89 | H71: 210792.41 | I71: 221802.67 | J71: 67094.19 | K71: 722000.16 | L71: 222809.96 | M71: 211472.72 | N71: 227987.2 | O71: 103496.54 | P71: 765766.42 | Q71: 189788.02 | R71: 332729.09 | S71: 308314.67 | T71: 330445.16 | U71: 1161276.9 | V71: 302751.78 | W71: 348359.63 | X71: 343871.63 | Y71: 428948.43 | Z71: 1423931.5 | AA71: 388656.27 | AB71: 438482.73
A72: 1 | C72: 영업이익 | E72: -696758.26 | G72: -396395.83 | H72: -265085 | I72: 188736.28 | J72: 117183.96 | K72: -355560.59 | L72: -19044.26 | M72: 71256.6 | N72: 68957.35 | O72: 161091.03 | P72: 282260.72 | Q72: 160162.57 | R72: 376465 | S72: 398407.58 | T72: 499055.34 | U72: 1434090.5 | V72: 859154.45 | W72: 953641.03 | X72: 1053775.2 | Y72: 1037918.9 | Z72: 3904489.6 | AA72: 1355970.1 | AB72: 1645146.4
A73: 1 | C73: 금융수익 | E73: 99675.03 | G73: 302131.07 | H73: 674396.92 | I73: 1105446.9 | J73: 84883.87 | K73: 2166858.7 | L73: 486109.7 | M73: 295877.12 | N73: 381594.4 | O73: 109828.84 | P73: 1273410.1 | Q73: 562301.87 | R73: 411062.03 | S73: 1436944.4 | T73: 782980.02 | U73: 3193288.4 | V73: 321348.43 | W73: 2599835.4 | X73: 731596.12 | Y73: -140290.99 | Z73: 3512488.9 | AA73: 849230.39 | AB73: 1074421.3
A74: 1 | C74: 금융비용 | E74: 113466.04 | G74: 365911.48 | H74: 1677729.7 | I74: 2986823.2 | J74: -2192068.2 | K74: 2838396.1 | L74: 1259596.4 | M74: 389157.89 | N74: 978487.19 | O74: -487653.74 | P74: 2139587.7 | Q74: 1466661.7 | R74: 1168172.9 | S74: 715575.95 | T74: 3144413.4 | U74: 6494824 | V74: 547228.71 | W74: 949013.33 | X74: 1719400.7 | Y74: 667698.05 | Z74: 3883340.8 | AA74: 2229311 | AB74: 1289073.1
A75: 1 | C75: 기타영업외수익 | E75: 14205.93 | G75: 148724.27 | H75: 1158851.6 | I75: 2276886.2 | J75: -2219020.5 | K75: 1365441.5 | L75: 737265.25 | M75: 116488.52 | N75: 677647.13 | O75: -612388.82 | P75: 919012.08 | Q75: 1082684.6 | R75: 863504.14 | S75: 26009.55 | T75: 2765121.4 | U75: 4737319.7 | V75: 239842.36 | W75: 36143.85 | X75: 1126875.1 | Y75: 508596.43 | Z75: 1911457.7 | AA75: 1709624.4 | AB75: 779789.55
A76: 1 | C76: 기타영업외비용 | E76: 307190.98 | G76: 71416.94 | H76: 41618.98 | I76: 179216.98 | J76: 475695.26 | K76: 767948.16 | L76: 92296.57 | M76: 43014.44 | N76: 24879.55 | O76: 183029.24 | P76: 343219.8 | Q76: 89172.46 | R76: 26988.92 | S76: 928897.94 | T76: 2012.94 | U76: 1047072.3 | V76: 74061.5 | W76: 2094746.7 | X76: 53837.35 | Y76: -343651.61 | Z76: 1878993.9 | AA76: 117625.14 | AB76: 47688.9
A77: 1 | C77: 종속기업,공동지배기업및관계기업관련손익 | E77: -174.16 | G77: -41.21 | H77: -146.54 | I77: -15.37 | J77: -1287.46 | K77: -1490.58 | L77: 22 | M77: -18.18 | N77: 25.48 | O77: 49.67 | P77: 78.97 | Q77: -196.08 | R77: 27.23 | S77: 9.26 | T77: 20.32 | U77: -139.27 | V77: 100.38 | W77: 74.99 | X77: 63.8 | Y77: -34.16 | Z77: 205.01 | AA77: 15.87 | AB77: 6.83
A78: 1 | C78: 지분법관련손익 | E78: -174.16 | G78: -41.21 | H78: -146.54 | I78: -15.37 | J78: -1287.46 | K78: -1490.58 | L78: 22 | M78: -18.18 | N78: 25.48 | O78: 49.67 | P78: 78.97 | Q78: -196.08 | R78: 27.23 | S78: 9.26 | T78: 20.32 | U78: -139.27 | V78: 100.38 | W78: 74.99 | X78: 63.8 | Y78: -34.16 | Z78: 205.01 | AA78: 15.87 | AB78: 6.83
A79: 1 | C79: 법인세비용차감전계속사업이익 | E79: -1003708.5 | G79: -382910.12 | H79: -151331.7 | I79: 405013.74 | J79: -301867.16 | K79: -431095.24 | L79: -147540.24 | M79: 51431.72 | N79: 124857.62 | O79: -36794.78 | P79: -8045.68 | Q79: 249118.8 | R79: 455896.62 | S79: 216896.95 | T79: 900750.69 | U79: 1822663.1 | V79: 799155.42 | W79: 545935.22 | X79: 1139072.2 | Y79: 1082143.7 | Z79: 3566306.6 | AA79: 1567904.7 | AB79: 2162602.1
... A82: 1 | C82: 총포괄손익 | E82: -708042.54 | G82: -242252.97 | H82: -124255.82 | I82: 308381.38 | J82: -202084.75 | K82: -260212.16 | L82: -138057.14 | M82: 40512.07 | N82: 333812.57 | O82: -247335.56 | P82: -11068.06 | Q82: 190028.74 | R82: 357713.77 | S82: 177876.61 | T82: 549216.62 | U82: 1274835.7 | V82: 629032.12 | W82: 710535.82 | X82: 888107.52 | Y82: 968531.85 | Z82: 3196207.3 | AA82: 1178885 | AB82: 1609242.5
A83: 1 | C83: (지배주주지분)당기순이익 | E83: -519774.03 | G83: -231682.21 | H83: -116620.8 | I83: 227971.18 | J83: -96617.79 | K83: -216949.62 | L83: -139792.81 | M83: 49779.53 | N83: 336995.34 | O83: -25271.07 | P83: 221710.99 | Q83: 188946.85 | R83: 292130.85 | S83: 151043.57 | T83: 540214.68 | U83: 1172335.9 | W83: 356438.68 | X83: 633303.12 | Y83: 683273.43 | AB83: 1287492.2
A84: 1 | C84: (비지배주주지분)당기순이익 | E84: -155515.74 | G84: -61477.84 | H84: 11021.26 | I84: 87860.44 | J84: -115631.35 | K84: -78227.49 | L84: -12056.17 | M84: -10370.55 | N84: 8896.84 | O84: -63250.85 | P84: -76780.73 | Q84: 4398.83 | R84: 65648.12 | S84: 25341.44 | T84: 186855.76 | U84: 282244.15 | V84: 116228.08 | W84: 90634.37 | X84: 243394.32 | Y84: 309726.07 | Z84: 759982.84 | AA84: 297157.14 | AB84: 306661.58
A85: 1 | C85: 금융손익 | E85: -13791.01 | G85: -63780.41 | H85: -1003332.8 | I85: -1881376.4 | J85: 2276952.1 | K85: -671537.42 | L85: -773486.68 | M85: -93280.77 | N85: -596892.79 | O85: 597482.58 | P85: -866177.66 | Q85: -904359.83 | R85: -757110.83 | S85: 721368.5 | T85: -2361433.4 | U85: -3301535.6 | V85: -225880.28 | W85: 1650822 | X85: -987804.55 | Y85: -807989.04 | Z85: -370851.83 | AA85: -1380080.6 | AB85: -214651.75
A86: 1 | C86: 기타영업외손익 | E86: -292985.05 | G86: 77307.33 | H86: 1117232.6 | I86: 2097669.2 | J86: -2694715.8 | K86: 597493.36 | L86: 644968.68 | M86: 73474.08 | N86: 652767.58 | O86: -795418.06 | P86: 575792.28 | Q86: 993512.13 | R86: 836515.22 | S86: -902888.39 | T86: 2763108.5 | U86: 3690247.4 | V86: 165780.86 | W86: -2058602.8 | X86: 1073037.7 | Y86: 852248.04 | Z86: 32463.8 | AA86: 1591999.3 | AB86: 732100.65
A87: 1 | C87: 계속사업이익 | E87: -675289.77 | G87: -293160.04 | H87: -105599.54 | I87: 315831.63 | J87: -212249.15 | K87: -295177.1 | L87: -151848.97 | M87: 39408.99 | N87: 345892.18 | O87: -88521.92 | P87: 144930.28 | Q87: 193345.68 | R87: 357778.97 | S87: 176385.02 | T87: 727070.44 | U87: 1454580.1 | V87: 611625.28 | W87: 447073.04 | X87: 876697.44 | Y87: 992999.51 | Z87: 2928395.3 | AA87: 1141412.1 | AB87: 1594153.8
A88: 1 | C88: 이자수익 | G88: 19787 | H88: 26428 | I88: 38678 | J88: 49190 | K88: 134083 | L88: 45641 | M88: 45862 | N88: 50756 | O88: 59699 | P88: 201958 | Q88: 53146 | R88: 51184 | S88: 49722 | T88: 59022 | U88: 213074 | V88: 57847 | W88: 66767 | X88: 66049 | Y88: 64327 | Z88: 254990 | AA88: 66391 | AB88: 85010
A89: 1 | C89: 배당금수익 | G89: 3043 | H89: 61 | I89: 14 | J89: 4 | K89: 3122 | L89: 5993 | M89: 30 | N89: 13 | O89: 4 | P89: 6040 | Q89: 3591 | R89: 26 | S89: 12 | T89: 3 | U89: 3632 | V89: 170 | W89: 3 | X89: 65 | Y89: 7 | Z89: 245 | AA89: 268 | AB89: 6
A90: 1 | C90: 이자비용 | G90: 37274 | H90: 41383 | I90: 44895 | J90: 42294 | K90: 165846 | L90: 49032 | M90: 55437 | N90: 59397 | O90: 30013 | P90: 193879 | Q90: 60072 | R90: 53985 | S90: 44262 | T90: 48003 | U90: 206322 | V90: 39703 | W90: 44880 | X90: 44101 | Y90: 30078 | Z90: 158762 | AA90: 38616 | AB90: 92377
A91: 1 | C91: 외환차익 | G91: 118432 | H91: 274720 | I91: 389411 | J91: 442449 | K91: 1225012 | L91: 169088 | M91: 195142 | N91: 182709 | O91: 172623 | P91: 719562 | Q91: 203433 | R91: 302238 | S91: 155388 | T91: 285849 | U91: 946908 | V91: 162258 | W91: 241900 | X91: 176052 | Y91: 233393 | Z91: 813603 | AA91: 364975 | AB91: 448403
A92: 1 | C92: 외환차손 | G92: 82004 | H92: 127890 | I92: 155572 | J92: 346753 | K92: 712219 | L92: 162231 | M92: 114338 | N92: 112360 | O92: 147961 | P92: 536890 | Q92: 98554 | R92: 121808 | S92: 143996 | T92: 116315 | U92: 480673 | V92: 236630 | W92: 472913 | X92: 282773 | Y92: 162019 | Z92: 1154335 | AA92: 217365 | AB92: 254597
A93: 1 | C93: 외화환산이익 | G93: 96615 | H93: 274744 | I93: 510436 | J93: -785382 | K93: 96413 | L93: 181716 | M93: 1 | N93: 116834 | O93: -232029 | P93: 66522 | Q93: 241717 | R93: 45241 | S93: 0 | T93: 530784 | U93: 817742 | V93: 52531 | W93: 52397 | X93: 334500 | Y93: 51326 | Z93: 490754 | AA93: 381838 | AB93: 135499
A94: 1 | C94: 외화환산손실 | G94: 55420 | H94: 169680 | I94: 302658 | J94: -89492 | K94: 438266 | L94: 66574 | M94: 40232 | N94: 46779 | O94: 46200 | P94: 199785 | Q94: 74042 | R94: 26859 | S94: 345213 | T94: -20614 | U94: 425500 | V94: 27360 | W94: 410728 | X94: 0 | Y94: -10246 | Z94: 427842 | AA94: 91407 | AB94: 142777
A95: 1 | C95: 파생상품이익 | G95: 61226 | H95: 96386 | I95: 165783 | J95: 369626 | K95: 693021 | L95: 79888 | M95: 54731 | N95: 26643 | O95: 109137 | P95: 270399 | Q95: 59757 | R95: 10889 | S95: 1230188 | T95: -91936 | U95: 1208898 | V95: 48443 | W95: 2232287 | X95: 154810 | Y95: -488050 | Z95: 1947490 | AA95: 35563 | AB95: 24996
A96: 1 | C96: 파생상품손실 | G96: 190965 | H96: 1326157 | I96: 2447648 | J96: -2489684 | K96: 1475086 | L96: 829138 | M96: 173207 | N96: 758543 | O96: -713014 | P96: 1047874 | Q96: 1233915 | R96: 965463 | S96: 182105 | T96: 3000352 | U96: 5381835 | V96: 243285 | W96: 10711 | X96: 1392245 | Y96: 462356 | Z96: 2108597 | AA96: 1881727 | AB96: 799209
A97: 1 | C97: 이자손익 | G97: -17487 | H97: -14955 | I97: -6217 | J97: 6896 | K97: -31763 | L97: -3391 | M97: -9575 | N97: -8641 | O97: 29686 | P97: 8079 | Q97: -6926 | R97: -2801 | S97: 5460 | T97: 11019 | U97: 6752 | V97: 18144 | W97: 21887 | X97: 21948 | Y97: 34249 | Z97: 96228 | AA97: 27775 | AB97: -7367
A98: 1 | C98: 영업활동으로인한현금흐름 | E98: -441452.68 | G98: 19429.74 | H98: 208403.68 | I98: 191575.98 | J98: 42836.37 | K98: 462245.77 | L98: 762750.93 | M98: 542991.39 | N98: 944715.27 | O98: -168866.66 | P98: 2081590.9 | Q98: 755596.45 | R98: 1526057.8 | S98: 119321.75 | T98: 1887684.2 | U98: 4288660.2 | V98: 2184544 | W98: 1082950.2 | X98: 1702441.7 | Y98: -547885.25 | Z98: 4422050.6 | AA98: 1775559.4 | AB98: 2603951.4
A99: 1 | C99: 이자수취(CF) | E99: 16996.82 | G99: 18414.8 | H99: 22974.54 | I99: 31343.76 | J99: 51703.69 | K99: 124436.79 | L99: 47765.21 | M99: 41450.99 | N99: 37646.93 | O99: 61566.25 | P99: 188429.38 | Q99: 65644.19 | R99: 50606.21 | S99: 48306.57 | T99: 51513.17 | U99: 216070.14 | V99: 48068.96 | W99: 69575.62 | X99: 61388.33 | Y99: 46506.68 | Z99: 225539.59 | AA99: 62709.95 | AB99: 89592.68
A100: 1 | C100: 이자지급(CF) | E100: -33999.42 | G100: -29831.84 | H100: -31392.63 | I100: -34973.1 | J100: -32004.07 | K100: -128201.64 | L100: -46093.64 | M100: -37699.81 | N100: -41720.64 | O100: -52044.08 | P100: -177558.17 | Q100: -62119.68 | R100: -30188.56 | S100: -41195.57 | T100: -18127.61 | U100: -151631.42 | V100: -24354.76 | W100: -9728.43 | X100: -18560.29 | Y100: -27062.5 | Z100: -79705.98 | AA100: -15370.69 | AB100: -2490.84
A101: 1 | C101: 배당금수취(CF) | E101: 40737.12 | G101: 172.75 | H101: 6258.74 | I101: 13.91 | J101: 4 | K101: 6449.4 | L101: 170.25 | M101: 6771.23 | N101: 12.81 | O101: 4 | P101: 6958.29 | Q101: 54.78 | R101: 3706.77 | S101: 12.41 | T101: 27838.71 | U101: 31612.67 | V101: 37.05 | W101: 1020.28 | X101: 64.84 | Y101: 6.42 | Z101: 1128.59 | AA101: 76.19 | AB101: 1304.09
A102: 1 | C102: 법인세납부(CF) | E102: 655.01 | G102: -3175.4 | H102: 4117.76 | I102: -10400.97 | J102: -9209.02 | K102: -18667.63 | L102: -8706.12 | M102: -1843.93 | N102: -6611.94 | O102: -7857 | P102: -25018.99 | Q102: -7286.07 | T102: -8961.69 | V102: -12467.11 | Y102: -8551.04 | AA102: -23026.9 | AB102: -63819.1
A103: 1 | C103: 투자활동으로인한현금흐름 | E103: 167889.63 | G103: -199318.38 | H103: -19669.57 | I103: -1039801.3 | J103: -80681.37 | K103: -1339470.7 | L103: -21313.82 | M103: 586275.47 | N103: -994862.94 | O103: -836988.26 | P103: -1266889.6 | Q103: 510535.87 | R103: -1093407.1 | S103: -261909.31 | T103: -388020.87 | U103: -1232801.4 | V103: -753976.56 | W103: -464113.62 | X103: -2107227 | Y103: -278523.19 | Z103: -3603840.3 | AA103: 975569.45 | AB103: 446610.35
A104: 1 | C104: 유형자산의감소 | E104: 7674.54 | G104: 2878.08 | H104: 7116.78 | I104: 10419.17 | J104: 3217.02 | K104: 23631.05 | L104: 2904.18 | M104: 4930.15 | N104: 3602.49 | O104: 12225.01 | P104: 23661.83 | Q104: 8761.56 | R104: 8415.43 | S104: 5498.76 | T104: 1820.38 | U104: 24496.13 | V104: 4219.63 | W104: 15773.93 | X104: 2713.72 | Y104: 9218.65 | Z104: 31925.93 | AA104: 1952.13 | AB104: 9804.36
A105: 1 | C105: 무형자산의감소 | E105: 300 | I105: 0 | J105: 0 | T105: 0 | V105: 11.21 | W105: 0 | X105: 985.91 | Y105: 3282.05 | Z105: 4279.17 | AA105: 0 | AB105: 0
A106: 1 | C106: 유형자산의증가 | E106: 111586.14 | G106: 92408.15 | H106: 154627.4 | I106: 211326.34 | J106: 208529.12 | K106: 666891.01 | L106: 146046.52 | M106: 222061.34 | N106: 227623.87 | O106: 226221.37 | P106: 821953.1 | Q106: 184798.26 | R106: 237755 | S106: 242961.79 | T106: 225473.99 | U106: 890989.04 | V106: 305401.7 | W106: 192975.17 | X106: 223086.15 | Y106: 225371.71 | Z106: 946834.73 | AA106: 184515.63 | AB106: 195858.74
A107: 1 | C107: CAPEX | E107: 128443.33 | G107: 97553.85 | H107: 161857.65 | I107: 223384.89 | J107: 224603.23 | K107: 707399.62 | L107: 156070.01 | M107: 233127.78 | N107: 243738.95 | O107: 249103.02 | P107: 882039.76 | Q107: 195556.18 | R107: 248185.1 | S107: 253555.15 | T107: 251745.24 | U107: 949041.67 | V107: 312531.22 | W107: 206038.33 | X107: 233867.76 | Y107: 251263.64 | Z107: 1003700.9 | AA107: 193606.13 | AB107: 209826.55
A108: 1 | C108: 무형자산의증가 | E108: 16857.19 | G108: 5145.7 | H108: 7230.25 | I108: 12058.55 | J108: 16074.11 | K108: 40508.61 | L108: 10023.49 | M108: 11066.44 | N108: 16115.08 | O108: 22881.65 | P108: 60086.66 | Q108: 10757.92 | R108: 10430.1 | S108: 10593.36 | T108: 26271.25 | U108: 58052.63 | V108: 7129.52 | W108: 13063.16 | X108: 10781.61 | Y108: 25891.93 | Z108: 56866.22 | AA108: 9090.5 | AB108: 13967.81
A109: 1 | C109: 재무활동으로인한현금흐름 | E109: -717845.88 | G109: 144143.98 | H109: 27273.1 | I109: -273298.21 | J109: -875389.25 | K109: -977270.38 | L109: -591077.39 | M109: 292019.11 | N109: -184404.76 | O109: -1745.74 | P109: -485208.78 | Q109: -611991.71 | R109: -709438.28 | S109: -708473.34 | T109: -329064.71 | U109: -2358968 | V109: 451391.26 | W109: -699760.55 | X109: -391971.29 | Y109: -151935.43 | Z109: -792276.01 | AA109: -46384.23 | AB109: 1392171.2
A110: 1 | C110: 리스부채의상환 | E110: 5109.03 | G110: 4285.59 | H110: 5277.07 | I110: 4540.93 | J110: 6517.29 | K110: 20620.88 | L110: 7182.17 | M110: 9107.54 | N110: 8584.69 | O110: 8135.68 | P110: 33010.08 | Q110: 8944.6 | R110: 9994.8 | S110: 9147.51 | T110: 7139.79 | U110: 35226.7 | V110: 8127.99 | W110: 9213.49 | X110: 9317.61 | Y110: 10689.65 | Z110: 37348.74 | AA110: 9043.38 | AB110: 9937.71
A111: 1 | C111: 현금및현금성자산의증감 | E111: -991955.35 | G111: -35166.64 | H111: 220659.62 | I111: -1118488.9 | J111: -937249.29 | K111: -1870245.2 | L111: 155349.75 | M111: 1417737.1 | N111: -234807.94 | O111: -1017110.8 | P111: 321168.1 | Q111: 651212.95 | R111: -271753.66 | S111: -854473.53 | T111: 1173942.2 | U111: 698927.99 | V111: 1883124.1 | W111: -86609.06 | X111: 187588.87 | Y111: -1959407.4 | Z111: 24696.59 | AA111: 2726657.2 | AB111: 4527302.7
A112: 1 | C112: 기말현금및현금성자산 | E112: -991955.35 | G112: 4532301.5 | H112: 220659.62 | I112: -1118488.9 | J112: -937249.29 | K112: 2697222.9 | L112: 2852572.6 | M112: 1417737.1 | N112: -234807.95 | O112: -1017110.8 | P112: 3018391 | Q112: 3669603.9 | R112: -271753.66 | S112: -854473.54 | T112: 1173942.2 | U112: 3717319 | V112: 5600443.1 | W112: -86609.06 | X112: 3904907.8 | Y112: -5676726.3 | Z112: 3742015.5 | AA112: 6468672.8 | AB112: 4527302.7

Sheet BS별도
B1: (백만원) | C1: 이름: BS별도H | E1: 4Q21 | F1: 2021 | G1: 1Q22 | H1: 2Q22 | I1: 3Q22 | J1: 4Q22 | K1: 2022 | L1: 1Q23 | M1: 2Q23 | N1: 3Q23 | O1: 4Q23 | P1: 2023 | Q1: 1Q24 | R1: 2Q24 | S1: 3Q24 | T1: 4Q24 | U1: 2024 | V1: 1Q25 | W1: 2Q25 | X1: 3Q25 | Y1: 4Q25 | Z1: 2025 | AA1: 1Q26 | AB1: 2Q26 | AC1: 3Q26 | AD1: 4Q26 | AE1: 2026 | AF1: 1Q27 | AG1: 2Q27 | AH1: 3Q27 | AI1: 4Q27 | AJ1: 2027 | AK1: 1Q28 | AL1: 2Q28 | AM1: 3Q28 | AN1: 4Q28 | AO1: 2028
B2: 별도 | D2: fin json(kship_fin.py)
B3: HD한국조선해양(별) | C3: UPDATE: 26-10-12 | E3: 1 | F3: 2 | G3: 3 | H3: 4 | I3: 5 | J3: 6 | K3: 7 | L3: 8 | M3: 9 | N3: 10 | O3: 11 | P3: 12 | Q3: 13 | R3: 14 | S3: 15 | T3: 16 | U3: 17 | V3: 18 | W3: 19 | X3: 20 | Y3: 21 | Z3: 22 | AA3: 23 | AB3: 24 | AC3: 25 | AD3: 26 | AE3: 27 | AF3: 28 | AG3: 29 | AH3: 30 | AI3: 31 | AJ3: 32 | AK3: 33 | AL3: 34 | AM3: 35 | AN3: 36 | AO3: 37
B4: Account Code | C4: AccountNAME | E4: 2021.12 | F4: 2021.12A | G4: 2022.03 | H4: 2022.06 | I4: 2022.09 | J4: 2022.12 | K4: 2022.12A | L4: 2023.03 | M4: 2023.06 | N4: 2023.09 | O4: 2023.12 | P4: 2023.12A | Q4: 2024.03 | R4: 2024.06 | S4: 2024.09 | T4: 2024.12 | U4: 2024.12A | V4: 2025.03 | W4: 2025.06 | X4: 2025.09 | Y4: 2025.12 | Z4: 2025.12A | AA4: 2026.03 | AB4: 2026.06 | AC4: 2026.09 | AD4: 2026.12 | AE4: 2026.12A | AF4: 2027.03 | AG4: 2027.06 | AH4: 2027.09 | AI4: 2027.12 | AJ4: 2027.12A | AK4: 2028.03 | AL4: 2028.06 | AM4: 2028.09 | AN4: 2028.12 | AO4: 2028.12A
A5: 1 | C5: 유동자산 | E5: 1840381.4 | F5: 1840381.4 | G5: 1856263.8 | H5: 2050674.6 | I5: 2087178.4 | J5: 2118469.8 | K5: 2118469.8 | L5: 1727843.4 | M5: 1672166.8 | N5: 1677075.3 | O5: 1654502 | P5: 1654502 | Q5: 1712155.7 | R5: 2109640.5 | S5: 1966992.4 | T5: 2027133.8 | U5: 2027133.8 | V5: 3018511.1 | W5: 2817273 | X5: 2882373.3 | Y5: 2835643.6 | Z5: 2835643.6 | AA5: 3338945.9 | AB5: 5422003.5
A6: 1 | C6: 현금및현금성자산 | E6: 1449872.8 | F6: 1449872.8 | G6: 1326479.7 | H6: 1775968.1 | I6: 901998.02 | J6: 987479.94 | K6: 987479.94 | L6: 689692.8 | M6: 1418830.9 | N6: 676696.94 | O6: 505091.26 | P6: 505091.26 | Q6: 1002357.4 | R6: 642852.35 | S6: 512854.16 | T6: 762696.86 | U6: 762696.86 | V6: 1042446.7 | W6: 925455.71 | X6: 781737.44 | Y6: 523688.18 | Z6: 523688.18 | AA6: 761392.15 | AB6: 3145869
A7: 1 | C7: 단기금융상품 | E7: 350500 | F7: 350500 | G7: 490500 | H7: 240500 | I7: 1132793.3 | J7: 1061789.8 | K7: 1061789.8 | L7: 942071.23 | M7: 140500 | N7: 850510.21 | O7: 950500 | P7: 950500 | Q7: 540500 | R7: 1246862.1 | S7: 1249327.4 | T7: 980500 | U7: 980500 | V7: 1230000 | W7: 1420000 | X7: 1610000 | Y7: 1530000 | Z7: 1530000 | AA7: 1050000 | AB7: 1151027
A8: 1 | C8: 단기금융자산 | E8: 350500 | F8: 350500 | G8: 490500 | H8: 240500 | I8: 1132793.3 | J8: 1061789.8 | K8: 1061789.8 | L8: 942071.23 | M8: 140500 | N8: 850510.21 | O8: 950500 | P8: 950500 | Q8: 540500 | R8: 1246862.1 | S8: 1249327.4 | T8: 980500 | U8: 980500 | V8: 1230000 | W8: 1420000 | X8: 1610000 | Y8: 1530000 | Z8: 1530000 | AA8: 1050000 | AB8: 1151027
A9: 1 | C9: 매출채권및기타채권 | E9: 27520.26 | F9: 27520.26 | G9: 25121.81 | H9: 21390.79 | I9: 39034.75 | J9: 52635.81 | K9: 52635.81 | L9: 59789.2 | M9: 57352.16 | N9: 75781.77 | O9: 105934.61 | P9: 105934.61 | Q9: 55247.88 | R9: 110808.05 | S9: 73075.22 | T9: 142205.89 | U9: 142205.89 | V9: 537659.34 | W9: 174536.58 | X9: 158454.22 | Y9: 345911.87 | Z9: 345911.87 | AA9: 912986.66 | AB9: 375257.14
A10: 1 | C10: 계약자산 | E10: 904.65 | F10: 904.65 | G10: 9190 | H10: 10220.26 | I10: 10655.27 | J10: 850.84 | K10: 850.84 | L10: 16121.93 | M10: 15084.44 | N10: 16467.08 | O10: 974.29 | P10: 974.29 | Q10: 17369.15 | R10: 17128.01 | S10: 22643.12 | T10: 556.29 | U10: 556.29 | V10: 22416.01 | W10: 22969.34 | X10: 23422.85 | Y10: 7781.49 | Z10: 7781.49 | AA10: 44341.11 | AB10: 89841.59
A11: 1 | C11: 재고자산 | E11: 729.68 | F11: 729.68 | G11: 774.19 | H11: 780.85 | I11: 992.62 | J11: 2280.75 | K11: 2280.75 | L11: 4144.05 | M11: 7006.13 | N11: 14791.62 | O11: 31510.6 | P11: 31510.6 | Q11: 34155.35 | R11: 45304.64 | S11: 66535.88 | T11: 71499.27 | U11: 71499.27 | V11: 95225.95 | W11: 144353.14 | X11: 166017.02 | Y11: 199477.5 | Z11: 199477.5 | AA11: 253389.6 | AB11: 345137.7
A12: 1 | C12: 당기법인세자산(선급법인세) | E12: 1621.06 | F12: 1621.06 | G12: 1704.74 | I12: 157.42 | J12: 3081.69 | K12: 3081.69 | L12: 5899.01 | M12: 5672.61 | N12: 7752.59 | O12: 9413.78 | P12: 9413.78 | Q12: 12094.7 | R12: 5119.07 | S12: 5991.76 | T12: 2214.65 | U12: 2214.65 | V12: 2305.31 | W12: 0 | X12: 0 | Y12: 0 | Z12: 0
A13: 1 | C13: 매각예정비유동자산및처분자산 | E13: 8363.67 | F13: 8363.67 | J13: 2871.72 | K13: 2871.72 | O13: 8637.81 | P13: 8637.81 | Q13: 0 | R13: 0 | S13: 0 | T13: 0 | U13: 0 | W13: 4626.85 | X13: 4626.85 | Y13: 0 | Z13: 0
A14: 1 | C14: 기타유동자산 | E14: 869.32 | F14: 869.32 | G14: 2493.37 | H14: 1814.55 | I14: 1547.09 | J14: 7479.3 | K14: 7479.3 | L14: 10125.13 | M14: 27720.53 | N14: 35075.1 | O14: 42439.69 | P14: 42439.69 | Q14: 50431.24 | R14: 41566.26 | S14: 36564.88 | T14: 67460.78 | U14: 67460.78 | V14: 88457.83 | W14: 125331.34 | X14: 138114.96 | Y14: 228784.56 | Z14: 228784.56 | AA14: 316836.38 | AB14: 314871.12
A15: 1 | C15: 비유동자산 | E15: 9268756.9 | F15: 9268756.9 | G15: 9307104.2 | H15: 9159581 | I15: 9111342.6 | J15: 9311699.9 | K15: 9311699.9 | L15: 9743843.7 | M15: 9784157.6 | N15: 10054933 | O15: 10119748 | P15: 10119748 | Q15: 10048488 | R15: 9761246 | S15: 9956471.7 | T15: 10030124 | U15: 10030124 | V15: 10085273 | W15: 10011893 | X15: 10009464 | Y15: 10065482 | Z15: 10065482 | AA15: 10067659 | AB15: 10096282
A16: 1 | C16: 종속기업및관계기업투자 | E16: 8298137.4 | F16: 8298137.4 | G16: 8283702.4 | H16: 8165548.3 | I16: 8149415.3 | J16: 8349068.3 | K16: 8349068.3 | L16: 8764495.4 | M16: 8803081.1 | N16: 8832251.2 | O16: 8883881.6 | P16: 8883881.6 | Q16: 8883810.8 | R16: 8694162.6 | S16: 8922041.2 | T16: 9012227.6 | U16: 9012227.6 | V16: 9067495.7 | W16: 9035213.8 | X16: 9065809.2 | Y16: 9235911.6 | Z16: 9235911.6 | AA16: 9260450.7 | AB16: 9290755.9
A17: 1 | C17: 투자자산 | E17: 8423562.8 | F17: 8423562.8 | G17: 8445715.7 | H17: 8307040.2 | I17: 8269787.6 | J17: 8470131 | K17: 8470131 | L17: 8897521.5 | M17: 8938661.1 | N17: 8952660.2 | O17: 9014455.1 | P17: 9014455.1 | Q17: 8946462.1 | R17: 8751453.9 | S17: 8979296.7 | T17: 9068618.7 | U17: 9068618.7 | V17: 9123941.4 | W17: 9091919 | X17: 9100095.8 | Y17: 9275982 | Z17: 9275982 | AA17: 9305361 | AB17: 9343852
A18: 1 | C18: 장기금융자산 | E18: 125425.34 | F18: 125425.34 | G18: 162013.29 | H18: 141491.84 | I18: 120372.33 | J18: 121062.65 | K18: 121062.65 | L18: 133026.02 | M18: 135580 | N18: 120408.96 | O18: 130573.46 | P18: 130573.46 | Q18: 62651.38 | R18: 57291.28 | S18: 57255.52 | T18: 56391.05 | U18: 56391.05 | V18: 56445.74 | W18: 56705.16 | X18: 34286.61 | Y18: 40070.37 | Z18: 40070.37 | AA18: 43682.04 | AB18: 45378.16
A19: 1 | C19: 장기매출채권및기타채권 | E19: 40576.9 | F19: 40576.9 | G19: 63250.05 | H19: 58897.65 | I19: 58967.42 | J19: 16848.99 | K19: 16848.99 | L19: 18713.07 | M19: 19247.17 | N19: 19528.07 | O19: 29452.38 | P19: 29452.38 | Q19: 28081 | R19: 28076.4 | S19: 17927.72 | T19: 5987.56 | U19: 5987.56 | V19: 7906.94 | W19: 8165.59 | X19: 37132.28 | Y19: 8389.86 | Z19: 8389.86 | AA19: 8517.53 | AB19: 8882.35
A20: 1 | C20: 투자부동산 | E20: 145515.41 | F20: 145515.41 | G20: 142410.88 | H20: 141676.9 | I20: 140942.92 | J20: 140208.95 | K20: 140208.95 | L20: 139474.97 | M20: 138740.99 | N20: 138007.01 | O20: 137273.04 | P20: 137273.04 | Q20: 136548.3 | R20: 141233.27 | S20: 140467.35 | T20: 139778.31 | U20: 139778.31 | V20: 139011.7 | W20: 133609.98 | X20: 132877.71 | Y20: 54604.37 | Z20: 54604.37 | AA20: 54397.2 | AB20: 54190.04
A21: 1 | C21: 유형자산 | E21: 623510.77 | F21: 623510.77 | G21: 621545.75 | H21: 621587.14 | I21: 613069.08 | J21: 609038.84 | K21: 609038.84 | L21: 609109.97 | M21: 612731.61 | N21: 613111.7 | O21: 598210.1 | P21: 598210.1 | Q21: 601827.4 | R21: 595607.44 | S21: 595673.04 | T21: 600537.64 | U21: 600537.64 | V21: 600149.91 | W21: 616110.64 | X21: 622059.04 | Y21: 624978.37 | Z21: 624978.37 | AA21: 628318.47 | AB21: 625612.66
A22: 1 | C22: 사용권자산 | E22: 7469.48 | F22: 7469.48 | G22: 6247.36 | H22: 4480.51 | I22: 3511.95 | J22: 24390.29 | K22: 24390.29 | L22: 25860.17 | M22: 23939.56 | N22: 23081.84 | O22: 25116.38 | P22: 25116.38 | Q22: 23706.64 | R22: 22844.83 | S22: 20856.29 | T22: 18740.89 | U22: 18740.89 | V22: 23946.91 | W22: 21401.16 | X22: 18281.39 | Y22: 13586.9 | Z22: 13586.9 | AA22: 11929.53 | AB22: 9761.06
A23: 1 | C23: 기타비유동자산 | E23: 11688.94 | F23: 11688.94 | G23: 9650.11 | H23: 6145.55 | I23: 4248.41 | J23: 29934.92 | K23: 29934.92 | L23: 29555.37 | M23: 25118.39 | N23: 23789.13 | O23: 41687.67 | P23: 41687.67 | Q23: 36587.96 | R23: 33125.45 | S23: 27742.95 | T23: 23578.53 | U23: 23578.53 | V23: 25557.49 | W23: 22057.41 | X23: 18930.35 | Y23: 40237.08 | Z23: 40237.08 | AA23: 32584.82 | AB23: 24445.86
A24: 1 | C24: 무형자산 | E24: 23902.15 | F24: 23902.15 | G24: 24531.72 | H24: 24233.56 | I24: 24327.17 | J24: 24353.83 | K24: 24353.83 | L24: 26026.1 | M24: 28901.46 | N24: 33764.11 | O24: 38762.72 | P24: 38762.72 | Q24: 40452.49 | R24: 42379.58 | S24: 44236.73 | T24: 47459.99 | U24: 47459.99 | V24: 47989.77 | W24: 47650.5 | X24: 48757.85 | Y24: 38422.08 | Z24: 38422.08 | AA24: 38479.53 | AB24: 39299.07
A25: 1 | C25: 자산총계 | E25: 11109138 | F25: 11109138 | G25: 11163368 | H25: 11210256 | I25: 11198521 | J25: 11430170 | K25: 11430170 | L25: 11471687 | M25: 11456324 | N25: 11732008 | O25: 11774250 | P25: 11774250 | Q25: 11760644 | R25: 11870887 | S25: 11923464 | T25: 12057257 | U25: 12057257 | V25: 13103784 | W25: 12829166 | X25: 12891838 | Y25: 12901126 | Z25: 12901126 | AA25: 13406604 | AB25: 15518286
A26: 1 | C26: 유동부채 | E26: 221237.07 | F26: 221237.07 | G26: 208402.63 | H26: 215794.97 | I26: 219455.58 | J26: 258944.57 | K26: 258944.57 | L26: 160027.99 | M26: 127675.02 | N26: 153107.1 | O26: 196119.73 | P26: 196119.73 | Q26: 173854.55 | R26: 177586.86 | S26: 225138 | T26: 331705.96 | U26: 331705.96 | V26: 1312526.8 | W26: 1015876.2 | X26: 990818.33 | Y26: 1116053.7 | Z26: 1116053.7 | AA26: 1677198.3 | AB26: 3431358.8
A27: 1 | C27: 단기차입금 | E27: 170.81 | F27: 170.81 | G27: 174.45 | H27: 186.28 | I27: 206.73 | J27: 4860.97 | K27: 4860.97 | O27: 0 | P27: 0 | R27: 1072.2 | T27: 0 | U27: 0 | V27: 597623.66 | W27: 522979.29 | X27: 495339.36 | Y27: 473565.66 | Z27: 473565.66 | AA27: 427437.86 | AB27: 2549642.4
A28: 1 | C28: 단기금융부채(face) | E28: 170.81 | F28: 170.81 | G28: 174.45 | H28: 186.28 | I28: 206.73 | J28: 4860.97 | K28: 4860.97 | O28: 0 | P28: 0 | R28: 1072.2 | T28: 0 | U28: 0 | V28: 597623.66 | W28: 522979.29 | X28: 495339.36 | Y28: 473565.66 | Z28: 473565.66 | AA28: 427437.86 | AB28: 2549642.4
A29: 1 | C29: 유동리스부채 | E29: 4773.53 | F29: 4773.53 | G29: 4234.11 | H29: 3147.86 | I29: 2477.75 | J29: 7641.23 | K29: 7641.23 | L29: 8853.82 | M29: 8613.49 | N29: 8690.88 | O29: 9005.9 | P29: 9005.9 | Q29: 8912.06 | R29: 9116.42 | S29: 8880.42 | T29: 8601.86 | U29: 8601.86 | V29: 12781.87 | W29: 13013.22 | X29: 12881.53 | Y29: 10330.51 | Z29: 10330.51 | AA29: 8106.05 | AB29: 6121.32
A30: 1 | C30: 리스부채 | E30: 7739.67 | F30: 7739.67 | G30: 6519.27 | H30: 4605.94 | I30: 3649.8 | J30: 23697.51 | K30: 23697.51 | L30: 25284.18 | M30: 23553.35 | N30: 22787.65 | O30: 24874.82 | P30: 24874.82 | Q30: 23583.98 | R30: 22824.64 | S30: 20974.69 | T30: 18929.81 | U30: 18929.81 | V30: 24220.35 | W30: 21790.97 | X30: 18794.22 | Y30: 13946.19 | Z30: 13946.19 | AA30: 12259.1 | AB30: 9995.5
A31: 1 | C31: 단기금융부채 | E31: 4773.53 | F31: 4773.53 | G31: 4234.11 | H31: 3147.86 | I31: 2477.75 | J31: 7641.23 | K31: 7641.23 | L31: 8853.82 | M31: 8613.49 | N31: 8690.88 | O31: 9005.9 | P31: 9005.9 | Q31: 8912.06 | R31: 9116.42 | S31: 8880.42 | T31: 8601.86 | U31: 8601.86 | V31: 12781.87 | W31: 13013.22 | X31: 12881.53 | Y31: 10330.51 | Z31: 10330.51 | AA31: 8106.05 | AB31: 6121.32
A32: 1 | C32: 매입채무및기타채무 | E32: 178306.07 | F32: 178306.07 | G32: 162665.02 | H32: 168161.42 | I32: 167123.34 | J32: 186935.61 | K32: 186935.61 | L32: 96691.03 | M32: 51219.14 | N32: 47192.2 | O32: 85026.14 | P32: 85026.14 | Q32: 49753.04 | R32: 55293.11 | S32: 63751.58 | T32: 113963.38 | U32: 113963.38 | V32: 439385.05 | W32: 127698.87 | X32: 128454.06 | Y32: 230562.83 | Z32: 230562.83 | AA32: 818457.19 | AB32: 204950.33
A33: 1 | C33: 계약부채 | E33: 4827.19 | F33: 4827.19 | G33: 8220.73 | H33: 8347.62 | I33: 17061.47 | J33: 26788.46 | K33: 26788.46 | L33: 49885.1 | M33: 66994.02 | N33: 96563.15 | O33: 101407.84 | P33: 101407.84 | Q33: 114394.6 | R33: 107893.01 | S33: 151121.4 | T33: 207481.7 | U33: 207481.7 | V33: 245980.03 | W33: 319326.78 | X33: 343949.27 | Y33: 380304.5 | Z33: 380304.5 | AA33: 385027.65 | AB33: 638920.62
A34: 1 | C34: 선수금 | E34: 1528.17 | F34: 1528.17 | O34: 0 | P34: 0
A35: 1 | C35: 기타유동부채 | E35: 1567.55 | F35: 1567.55 | G35: 39.38 | H35: 79.38 | I35: 79.38 | J35: 79.38 | K35: 79.38 | L35: 16.48 | M35: 56.48 | N35: 55.21 | O35: 32.04 | P35: 32.04 | Q35: 32.04 | R35: 32.04 | S35: 32.04 | T35: 32.04 | U35: 32.04 | V35: 32.04 | W35: 0 | X35: 0 | Y35: 0 | Z35: 0
A36: 1 | C36: 단기충당부채 | E36: 31591.92 | F36: 31591.92 | G36: 31858.92 | H36: 32112.92 | I36: 32377.92 | J36: 32638.92 | K36: 32638.92 | L36: 4581.57 | M36: 791.89 | N36: 605.66 | O36: 647.8 | P36: 647.8 | Q36: 762.8 | R36: 1134.68 | S36: 1352.55 | T36: 1626.99 | U36: 1626.99 | V36: 1775.15 | W36: 1913.68 | X36: 2360.95 | Y36: 2831.3 | Z36: 2831.3 | AA36: 3345.01 | AB36: 4548.16
A37: 1 | C37: 비유동부채 | E37: 110885.36 | F37: 110885.36 | G37: 116241.82 | H37: 114312.1 | I37: 92741.2 | J37: 46736.42 | K37: 46736.42 | L37: 49537.79 | M37: 51464.86 | N37: 48921.73 | O37: 48531.88 | P37: 48531.88 | Q37: 47544.3 | R37: 45574.45 | S37: 43907.99 | T37: 45017.39 | U37: 45017.39 | V37: 47011.69 | W37: 47028.71 | X37: 49024.36 | Y37: 44084.22 | Z37: 44084.22 | AA37: 62450.17 | AB37: 212795.6
A38: 1 | C38: 장기차입금 | E38: 44141.67 | F38: 44141.67 | G38: 35924.5 | H38: 25931.23 | I38: 21287.71 | J38: 11977.28 | K38: 11977.28 | L38: 14482.59 | M38: 17851.91 | N38: 13932.86 | O38: 12901.87 | P38: 12901.87 | Q38: 12893.13 | R38: 11163.46 | S38: 10604.16 | T38: 11812.76 | U38: 11812.76 | V38: 11784.63 | W38: 10899.88 | X38: 11267.92 | Y38: 11530.7 | Z38: 11530.7 | AA38: 12161.51 | AB38: 12387.32
A39: 1 | C39: 장기금융부채(face) | E39: 44141.67 | F39: 44141.67 | G39: 35924.5 | H39: 25931.23 | I39: 21287.71 | J39: 11977.28 | K39: 11977.28 | L39: 14482.59 | M39: 17851.91 | N39: 13932.86 | O39: 12901.87 | P39: 12901.87 | Q39: 12893.13 | R39: 11163.46 | S39: 10604.16 | T39: 11812.76 | U39: 11812.76 | V39: 11784.63 | W39: 10899.88 | X39: 11267.92 | Y39: 11530.7 | Z39: 11530.7 | AA39: 12161.51 | AB39: 12387.32
A40: 1 | C40: 비유동리스부채 | E40: 2966.14 | F40: 2966.14 | G40: 2285.16 | H40: 1458.08 | I40: 1172.05 | J40: 16056.28 | K40: 16056.28 | L40: 16430.36 | M40: 14939.86 | N40: 14096.77 | O40: 15868.92 | P40: 15868.92 | Q40: 14671.92 | R40: 13708.22 | S40: 12094.27 | T40: 10327.95 | U40: 10327.95 | V40: 11438.48 | W40: 8777.75 | X40: 5912.69 | Y40: 3615.68 | Z40: 3615.68 | AA40: 4153.05 | AB40: 3874.18
A41: 1 | C41: 장기금융부채 | E41: 2966.14 | F41: 2966.14 | G41: 2285.16 | H41: 1458.08 | I41: 1172.05 | J41: 16056.28 | K41: 16056.28 | L41: 16430.36 | M41: 14939.86 | N41: 14096.77 | O41: 15868.92 | P41: 15868.92 | Q41: 14671.92 | R41: 13708.22 | S41: 12094.27 | T41: 10327.95 | U41: 10327.95 | V41: 11438.48 | W41: 8777.75 | X41: 5912.69 | Y41: 3615.68 | Z41: 3615.68 | AA41: 5381.26 | AB41: 11845.98
A42: 1 | C42: 장기매입채무및기타채무 | E42: 6291.46 | F42: 6291.46 | G42: 6294.08 | H42: 6070.86 | I42: 6110.93 | J42: 6387.3 | K42: 6387.3 | L42: 6397.71 | M42: 6459.48 | N42: 6525.61 | O42: 8129.35 | P42: 8129.35 | Q42: 8151.49 | R42: 8732.05 | S42: 9145.5 | T42: 10591.83 | U42: 10591.83 | V42: 11104.17 | W42: 12105.3 | X42: 12636.22 | Y42: 13748.83 | Z42: 13748.83 | AA42: 14374.74 | AB42: 15226.2
A43: 1 | C43: 확정급여부채 | E43: 729.7 | F43: 729.7 | G43: 729.7 | H43: 729.7 | I43: 4971.04 | J43: 1060.42 | K43: 1060.42 | L43: 1060.42 | M43: 1060.42 | N43: 2923.97 | O43: 84.4 | P43: 84.4 | Q43: 84.4 | R43: 84.4 | S43: 84.4 | T43: 119.76 | U43: 119.76 | V43: 119.76 | W43: 2483.22 | X43: 6373.53 | Y43: 201.55 | Z43: 201.55 | AA43: 201.55 | AB43: 202.22
A44: 1 | C44: 부채총계 | E44: 332122.43 | F44: 332122.43 | G44: 324644.46 | H44: 330107.07 | I44: 312196.78 | J44: 305680.98 | K44: 305680.98 | L44: 209565.78 | M44: 179139.89 | N44: 202028.83 | O44: 244651.62 | P44: 244651.62 | Q44: 221398.85 | R44: 223161.31 | S44: 269045.99 | T44: 376723.35 | U44: 376723.35 | V44: 1359538.5 | W44: 1062904.9 | X44: 1039842.7 | Y44: 1160137.9 | Z44: 1160137.9 | AA44: 1739648.5 | AB44: 3644154.4
A45: 1 | C45: 자본금 | E45: 353865.58 | F45: 353865.58 | G45: 353865.58 | H45: 353865.58 | I45: 353865.58 | J45: 353865.58 | K45: 353865.58 | L45: 353865.58 | M45: 353865.58 | N45: 353865.58 | O45: 353865.58 | P45: 353865.58 | Q45: 353865.58 | R45: 353865.58 | S45: 353865.58 | T45: 353865.58 | U45: 353865.58 | V45: 353865.58 | W45: 353865.58 | X45: 353865.58 | Y45: 353865.58 | Z45: 353865.58 | AA45: 353865.58 | AB45: 353865.58
A46: 1 | C46: 자본잉여금 | E46: 2352915 | F46: 2352915 | G46: 2352915 | H46: 2352915 | I46: 2352915 | J46: 2352915 | K46: 2352915 | L46: 2352915 | M46: 2352915 | N46: 2352915 | O46: 2353534.3 | P46: 2353534.3 | Q46: 2353534.3 | R46: 2353534.3 | S46: 2353534.3 | T46: 2353534.3 | U46: 2353534.3 | V46: 2353534.3 | W46: 2353534.3 | X46: 2353534.3 | Y46: 2353534.3 | Z46: 2353534.3 | AA46: 2353534.3 | AB46: 2353534.3
A47: 1 | C47: 기타자본 | E47: -8153905.2 | F47: -8153905.2 | G47: -8153905.2 | H47: -8153905.2 | I47: -8153905.2 | J47: -8153905.2 | K47: -8153905.2 | L47: -8059153.6 | M47: -8060193.6 | N47: -8060450.5 | O47: -8060450.5 | P47: -8060450.5 | Q47: -8060450.5 | R47: -8060450.5 | S47: -8060450.5 | T47: -8060450.5 | U47: -8060450.5 | V47: -8060450.5 | W47: -8060450.5 | X47: -8060450.5 | Y47: -8060450.5 | Z47: -8060450.5 | AA47: -8060450.5 | AB47: -8060450.5
... A55: 1 | C55: 이자발생자산 | E55: 1925798.1 | F55: 1925798.1 | G55: 1978993 | H55: 2157959.9 | I55: 2155163.6 | J55: 2170332.3 | K55: 2170332.3 | L55: 1764790.1 | M55: 1694910.9 | N55: 1647616.1 | O55: 1586164.7 | P55: 1586164.7 | Q55: 1605508.8 | R55: 1947005.7 | S55: 1819437.1 | T55: 1799587.9 | U55: 1799587.9 | V55: 2328892.4 | W55: 2402160.9 | X55: 2426024 | Y55: 2093758.6 | Z55: 2093758.6 | AA55: 1855074.2 | AB55: 4342274.2
A56: 1 | C56: 당기법인세부채(미지급법인세) | G56: 1210.02 | H56: 3759.48 | I56: 128.99 | R56: 3045.39 | V56: 14949 | W56: 30944.33 | X56: 7833.15 | Y56: 18458.91 | Z56: 18458.91 | AA56: 34824.58 | AB56: 27175.99
A57: 1 | C57: 이연법인세자산 | J57: 21183.38 | K57: 21183.38 | L57: 23442.69 | M57: 20756.85 | N57: 274072.4 | O57: 259906.96 | P57: 259906.96 | Q57: 258529.11 | R57: 169370.03 | S57: 151127.18 | T57: 144162.97 | U57: 144162.97 | V57: 140715.92 | W57: 92380.38 | X57: 49611.39 | Y57: 22868.36 | Z57: 22868.36 | AA57: 0 | AB57: 0
A58: 1 | C58: 장기충당부채 | M58: 74.91 | N58: 452.88 | O58: 646.36 | P58: 646.36 | Q58: 932.92 | R58: 1166.67 | S58: 1351.01 | T58: 1959.86 | U58: 1959.86 | V58: 2449.97 | W58: 2738.65 | X58: 2901.08 | Y58: 5145.54 | Z58: 5145.54 | AA58: 5953.04 | AB58: 6297.04
A59: 1 | C59: 이연법인세부채 | O59: 0 | P59: 0 | AA59: 14629.12 | AB59: 157181.1
A60: 1 | C60: 비유동확정계약자산 | AA60: 1228.21 | AB60: 7442.24
A61: 1 | C61: 장기파생상품부채 | AA61: 1228.21 | AB61: 7971.8
A62: 1 | C62: 비유동파생상품자산 | AB62: 275.69
A63: 1 | C63: 매출액(수익) | E63: 80420.24 | G63: 46052.19 | H63: 38861.81 | I63: 42855.82 | J63: 52730.65 | K63: 180500.47 | L63: 53512.93 | M63: 56555.94 | N63: 60687.11 | O63: 99151.68 | P63: 269907.66 | Q63: 104106.37 | R63: 106013.26 | S63: 112806.17 | T63: 193870.54 | U63: 516796.34 | V63: 551782.29 | W63: 140273.39 | X63: 480102.28 | Y63: 321595.87 | Z63: 1493753.8 | AA63: 790716.34 | AB63: 345446.84
A64: 1 | C64: 매출원가 | E64: 35065.64 | G64: 33909.79 | H64: 33276.08 | I64: 37359.33 | J64: 46756.45 | K64: 151301.65 | L64: 43389.36 | M64: 50029.24 | N64: 53982.42 | O64: 86791.22 | P64: 234192.24 | Q64: 88529.52 | R64: 94076.23 | S64: 100171.69 | T64: 142863.97 | U64: 425641.41 | V64: 114589.9 | W64: 123306.17 | X64: 163264.82 | Y64: 279166.18 | Z64: 680327.07 | AA64: 232189.67 | AB64: 303222.7
A65: 1 | C65: 매출총이익 | E65: 45354.6 | G65: 12142.4 | H65: 5585.73 | I65: 5496.49 | J65: 5974.2 | K65: 29198.82 | L65: 10123.57 | M65: 6526.7 | N65: 6704.69 | O65: 12360.46 | P65: 35715.42 | Q65: 15576.84 | R65: 11937.02 | S65: 12634.49 | T65: 51006.58 | U65: 91154.93 | V65: 437192.39 | W65: 16967.22 | X65: 316837.47 | Y65: 42429.68 | Z65: 813426.76 | AA65: 558526.67 | AB65: 42224.14
A66: 1 | C66: 판관비 | E66: 25653.04 | G66: 6495.27 | H66: 12693.65 | I66: 11699.31 | J66: 16595.61 | K66: 47483.84 | L66: 7229.97 | M66: 8883.8 | N66: 12937.15 | O66: 18247.68 | P66: 47298.6 | Q66: 14578.12 | R66: 16435.56 | S66: 20410.98 | T66: 22471.98 | U66: 73896.64 | V66: 20993.85 | W66: 26175.02 | X66: 27402.16 | Y66: 38206.51 | Z66: 112777.54 | AA66: 30009.81 | AB66: 42409.89
A67: 1 | C67: 영업이익 | E67: 19701.56 | G67: 5647.13 | H67: -7107.92 | I67: -6202.82 | J67: -10621.4 | K67: -18285.01 | L67: 2893.6 | M67: -2357.1 | N67: -6232.46 | O67: -5887.22 | P67: -11583.18 | Q67: 998.72 | R67: -4498.53 | V67: 416198.54 | W67: -9207.8 | X67: 289435.31 | Y67: 4223.17 | Z67: 700649.22 | AA67: 528516.86 | AB67: -185.75
A68: 1 | C68: 금융수익 | E68: 8464.44 | G68: 17892.37 | H68: 19961.73 | I68: 21274.8 | J68: 23342 | K68: 82470.9 | L68: 31656.14 | M68: 17611.17 | N68: 20514.4 | O68: 15727.94 | P68: 85509.65 | Q68: 18685.23 | R68: 17729.91 | S68: 19194.74 | T68: 22462.14 | U68: 78072.02 | V68: 20692.5 | W68: 32053.78 | X68: 17090.27 | Y68: 23364.39 | Z68: 93200.94 | AA68: 55826.64 | AB68: 597215.98
A69: 1 | C69: 금융비용 | E69: 273.06 | G69: 663.45 | H69: 1077.07 | I69: 13369.39 | J69: -3740.77 | K69: 11369.14 | L69: 4241.5 | M69: 7247.7 | N69: 1697.7 | O69: 2147.15 | P69: 15334.05 | Q69: 2343.82 | R69: 2338.91 | S69: 2132.74 | T69: 6130.95 | U69: 12946.42 | V69: 6872.65 | W69: 143378.17 | X69: 56913.96 | Y69: 400.06 | Z69: 207564.84 | AA69: 17095.87 | AB69: 324849.47
A70: 1 | C70: 기타영업외수익 | E70: 12194.3 | G70: 50811.09 | H70: 63985.11 | I70: 7003.01 | J70: 166023.13 | K70: 287822.34 | L70: 1954.89 | M70: 1027.28 | N70: 1749.44 | O70: 3890.9 | P70: 8622.51 | Q70: 383 | R70: 138366.58 | S70: 189.99 | T70: 431.58 | U70: 139371.15 | V70: 543.13 | W70: 156991.09 | X70: 66803.24 | Y70: 20760.65 | Z70: 245098.11 | AA70: 16069.8 | AB70: 7355.03
A71: 1 | C71: 기타영업외비용 | E71: 8907.97 | G71: 1233.89 | H71: 1439.45 | I71: 979.09 | J71: 15445.96 | K71: 19098.39 | L71: 3607.93 | M71: 402.48 | N71: 343.3 | O71: 1253.73 | P71: 5607.44 | Q71: 1216.81 | R71: 928.66 | S71: 586.31 | T71: 4337.34 | U71: 7069.12 | V71: 2370.83 | W71: 64421.1 | X71: 465.15 | Y71: 218276.63 | Z71: 285533.71 | AA71: 1216.49 | AB71: 1244.02
A72: 1 | C72: 법인세비용차감전계속사업이익 | E72: 31179.27 | G72: 72453.25 | H72: 74322.4 | I72: 7726.52 | J72: 167038.53 | K72: 321540.7 | L72: 28655.2 | M72: 8631.17 | N72: 13990.39 | O72: 10330.74 | P72: 61607.5 | Q72: 16506.33 | R72: 148330.39 | S72: 8889.19 | T72: 40960.01 | U72: 214685.92 | V72: 428190.69 | W72: -27962.2 | X72: 315949.72 | Y72: -170328.5 | Z72: 545849.71 | AA72: 582100.94 | AB72: 278291.78
A73: 1 | C73: 법인세비용 | E73: -62455.25 | G73: 15101.74 | H73: 16550.02 | I73: -14623.75 | J73: -70958.23 | K73: -53930.22 | L73: -5025.91 | M73: 620.27 | N73: -250042.46 | O73: 14598.62 | P73: -239849.48 | Q73: 2683.58 | R73: 35753.08 | S73: 2168.96 | T73: 8482.32 | U73: 49087.94 | V73: 3876.07 | W73: -12724.55 | X73: 2851.79 | Y73: -62488.45 | Z73: -68485.14 | AA73: 12853.94 | AB73: 71123.9
A74: 1 | C74: 당기순이익 | E74: 93634.52 | G74: 57351.51 | H74: 57772.38 | I74: 22350.27 | J74: 237996.78 | K74: 375470.94 | L74: 33681.11 | M74: 8010.9 | N74: 264032.85 | O74: -4267.89 | P74: 301456.97 | Q74: 13822.75 | R74: 112577.31 | S74: 6720.23 | T74: 32477.69 | U74: 165597.98 | V74: 424314.62 | W74: -15237.65 | X74: 313097.93 | Y74: -107840.03 | Z74: 614334.87 | AA74: 569246.99 | AB74: 207167.88
A75: 1 | C75: 총포괄손익 | E75: 71599.81 | G75: 61707.59 | H75: 41424.97 | I75: 6175.77 | J75: 238164.46 | K75: 347472.79 | L75: 42880.93 | M75: 16103.25 | N75: 253051.49 | O75: -1000.01 | P75: 311035.66 | Q75: 9646.94 | R75: 108479.93 | S75: 6692.94 | T75: 26115.91 | U75: 150935.72 | V75: 424356.35 | W75: 22015.73 | X75: 312020.3 | Y75: -111007.25 | Z75: 647385.13 | AA75: 569471.28 | AB75: 207175.24
A76: 1 | C76: 금융손익 | E76: 8191.38 | G76: 17228.92 | H76: 18884.66 | I76: 7905.41 | J76: 27082.77 | K76: 71101.76 | L76: 27414.64 | M76: 10363.47 | N76: 18816.7 | O76: 13580.79 | P76: 70175.6 | Q76: 16341.41 | R76: 15391 | S76: 17062 | T76: 16331.19 | U76: 65125.6 | V76: 13819.85 | W76: -111324.39 | X76: -39823.69 | Y76: 22964.33 | Z76: -114363.9 | AA76: 38730.77 | AB76: 272366.51
A77: 1 | C77: 기타영업외손익 | E77: 3286.33 | G77: 49577.2 | H77: 62545.66 | I77: 6023.92 | J77: 150577.17 | K77: 268723.95 | L77: -1653.04 | M77: 624.8 | N77: 1406.14 | O77: 2637.17 | P77: 3015.07 | Q77: -833.81 | R77: 137437.92 | S77: -396.32 | T77: -3905.76 | U77: 132302.03 | V77: -1827.7 | W77: 92569.99 | X77: 66338.09 | Y77: -197515.98 | Z77: -40435.6 | AA77: 14853.31 | AB77: 6111.01
A78: 1 | C78: (지배주주지분)당기순이익 | E78: 93634.52 | G78: 57351.51 | H78: 57772.38 | I78: 22350.27 | J78: 237996.78 | K78: 375470.94 | L78: 33681.11 | M78: 8010.9 | N78: 264032.85 | O78: -4267.89 | P78: 301456.97 | Q78: 13822.75 | R78: 112577.31 | S78: 6720.23 | T78: 32477.69 | U78: 165597.98 | V78: 424314.62 | W78: -15237.65 | X78: 313097.93 | Y78: -107840.03 | Z78: 614334.87 | AA78: 569246.99 | AB78: 207167.88
A79: 1 | C79: 계속사업이익 | E79: 93634.52 | G79: 57351.51 | H79: 57772.38 | I79: 22350.27 | J79: 237996.78 | K79: 375470.94 | L79: 33681.11 | M79: 8010.9 | N79: 264032.85 | O79: -4267.89 | P79: 301456.97 | Q79: 13822.75 | R79: 112577.31 | S79: 6720.23 | T79: 32477.69 | U79: 165597.98 | V79: 424314.62 | W79: -15237.65 | X79: 313097.93 | Y79: -107840.03 | Z79: 614334.87 | AA79: 569246.99 | AB79: 207167.88
... A83: 1 | C83: 배당금수취(CF) | E83: 41513.22 | G83: 155 | H83: 10194.78 | I83: 9.91 | J83: 0 | K83: 10359.69 | L83: 165 | M83: 8496.23 | N83: 8.95 | O83: 0 | P83: 8670.18 | Q83: 49 | R83: 8065.62 | S83: 8.95 | T83: 27835.29 | U83: 35958.86 | V83: 24 | W83: 417562.01 | X83: 298998.52 | Y83: 0 | Z83: 716584.53 | AA83: 12 | AB83: 532027.78
A84: 1 | C84: 법인세납부(CF) | E84: -971.85 | G84: -968.17 | H84: 564.48 | I84: -5059.5 | J84: -2513.73 | K84: -7976.92 | L84: -2814.25 | M84: 539.09 | N84: -2054.37 | O84: -1701.07 | P84: -6030.6 | Q84: -2689.58 | R84: 6545.21 | S84: -1601.4 | V84: -1502.87 | W84: -3693.8 | X84: -3008.8 | Y84: 7896.07 | Z84: -309.4 | AA84: -1674.43 | AB84: -23147.75
A85: 1 | C85: 투자활동으로인한현금흐름 | E85: 143745.62 | G85: -122174.93 | H85: 433865.03 | I85: -877050.23 | J85: 77922.73 | K85: -487437.4 | L85: -296098.3 | M85: 767594.77 | N85: -753350.63 | O85: -154556.08 | P85: -436410.24 | Q85: 471403.11 | R85: -383281.4 | S85: -226664.08 | T85: 179476.58 | U85: 40934.21 | V85: -310773.85 | W85: -231060.41 | X85: -256408.61 | Y85: -196298.47 | Z85: -994541.34 | AA85: 441164.73 | AB85: -137114.03
A86: 1 | C86: 유형자산의감소 | E86: 2036.48 | I86: 7324.26 | J86: 1991.71 | L86: 0.72 | M86: 0.78 | N86: 1319.82 | O86: 9755.27 | P86: 11076.59 | Q86: 5.91 | R86: 5758.49 | T86: 366.27 | V86: 2047.6 | W86: 30781.86 | AA86: 8.68 | AB86: 7029.79
A87: 1 | C87: 무형자산의감소 | E87: 0 | I87: 0 | J87: 0 | T87: 0 | Y87: 0
A88: 1 | C88: 유형자산의증가 | E88: 990.85 | G88: 701.05 | H88: 2947.57 | I88: 2834.53 | J88: 3216.44 | K88: 9699.59 | L88: 3590.05 | M88: 5786.18 | N88: 4304.63 | O88: 7766.22 | P88: 21447.08 | Q88: 7473.67 | R88: 6725.13 | S88: 4057.82 | T88: 7061.44 | U88: 25318.06 | V88: 7016.89 | W88: 8385.86 | X88: 11475.29 | Y88: 6613.39 | Z88: 33491.43 | AA88: 8168.65 | AB88: 9746.38
A89: 1 | C89: CAPEX | E89: 990.85 | G89: 1330.62 | H89: 4029.11 | I89: 2928.13 | J89: 3243.11 | K89: 11530.97 | L89: 5264.92 | M89: 6561.38 | N89: 6643.97 | O89: 13002.51 | P89: 31472.78 | Q89: 9496.4 | R89: 8985.2 | S89: 7018.94 | T89: 10617.67 | U89: 36118.21 | V89: 7963.14 | W89: 8976.54 | X89: 11954.84 | Y89: 11647.99 | Z89: 40542.51 | AA89: 8659.93 | AB89: 10999.76
A90: 1 | C90: 무형자산의증가 | E90: 0 | G90: 629.57 | H90: 1081.54 | I90: 93.6 | J90: 26.67 | K90: 1831.38 | L90: 1674.87 | M90: 775.2 | N90: 2339.34 | O90: 5236.29 | P90: 10025.7 | Q90: 2022.73 | R90: 2260.07 | S90: 2961.12 | T90: 3556.23 | U90: 10800.15 | V90: 946.25 | W90: 590.68 | X90: 479.55 | Y90: 5034.6 | Z90: 7051.08 | AA90: 491.28 | AB90: 1253.38
A91: 1 | C91: 재무활동으로인한현금흐름 | E91: -1293.99 | G91: -1248.41 | H91: -1191.68 | I91: -1127.24 | J91: -1314.21 | K91: -4881.54 | L91: -46808.77 | M91: -2013.36 | N91: -2100.22 | O91: -2267.61 | P91: -53189.96 | Q91: -2041.54 | R91: -2116.32 | S91: -2158.11 | T91: -2225.81 | U91: -8541.78 | V91: 597242.12 | W91: -363819.18 | X91: -229216.8 | Y91: -3165.84 | Z91: 1040.3 | AA91: -2815.93 | AB91: 1635388.5
A92: 1 | C92: 현금및현금성자산의증감 | E92: 181225.29 | G92: -123393.13 | H92: 449488.43 | I92: -873970.08 | J92: 85481.92 | K92: -462392.86 | L92: -297787.15 | M92: 729138.16 | N92: -742134.02 | O92: -171605.67 | P92: -482388.68 | Q92: 497266.16 | R92: -359505.06 | S92: -129998.2 | T92: 249842.71 | U92: 257605.61 | V92: 279749.83 | W92: -116990.99 | X92: -143718.27 | Y92: -258049.25 | Z92: -239008.68 | AA92: 237703.97 | AB92: 2384476.8
A93: 1 | C93: 기말현금및현금성자산 | E93: 181225.3 | G93: 1326479.7 | H93: 449488.43 | I93: -873970.08 | J93: 85481.92 | K93: 987479.94 | L93: 689692.8 | M93: 729138.15 | N93: -742134.01 | O93: -171605.68 | P93: 505091.26 | Q93: 1002357.4 | R93: -359505.07 | S93: -129998.19 | T93: 249842.7 | U93: 762696.86 | V93: 1042446.7 | W93: -116990.98 | X93: -143718.27 | Y93: -258049.26 | Z93: 523688.18 | AA93: 761392.15 | AB93: 2384476.8
A94: 1 | C94: 리스부채의상환 | L94: 1803.53
A95: 1 | C95: 배당금지급 | X95: 226267.58 | Y95: 0

Sheet subQ
A1: YQ | C1: subQ 분기 서브모델(억원, U=100) | E1: 4Q21 | F1: 2021 | G1: 1Q22 | H1: 2Q22 | I1: 3Q22 | J1: 4Q22 | K1: 2022 | L1: 1Q23 | M1: 2Q23 | N1: 3Q23 | O1: 4Q23 | P1: 2023 | Q1: 1Q24 | R1: 2Q24 | S1: 3Q24 | T1: 4Q24 | U1: 2024 | V1: 1Q25 | W1: 2Q25 | X1: 3Q25 | Y1: 4Q25 | Z1: 2025 | AA1: 1Q26 | AB1: 2Q26 | AC1: 3Q26 | AD1: 4Q26 | AE1: 2026 | AF1: 1Q27 | AG1: 2Q27 | AH1: 3Q27 | AI1: 4Q27 | AJ1: 2027 | AK1: 1Q28 | AL1: 2Q28 | AM1: 3Q28 | AN1: 4Q28 | AO1: 2028
A2: A=이름(key) B=그룹 C=단위 D=FnGuide 계정명(VLOOKUP 키). 확정=VLOOKUP(BS), 추정=변수 가정 참조
E3: 1 | F3: 2 | G3: 3 | H3: 4 | I3: 5 | J3: 6 | K3: 7 | L3: 8 | M3: 9 | N3: 10 | O3: 11 | P3: 12 | Q3: 13 | R3: 14 | S3: 15 | T3: 16 | U3: 17 | V3: 18 | W3: 19 | X3: 20 | Y3: 21 | Z3: 22 | AA3: 23 | AB3: 24 | AC3: 25 | AD3: 26 | AE3: 27 | AF3: 28 | AG3: 29 | AH3: 30 | AI3: 31 | AJ3: 32 | AK3: 33 | AL3: 34 | AM3: 35 | AN3: 36 | AO3: 37
E4: 2021.12 | F4: 2021.12A | G4: 2022.03 | H4: 2022.06 | I4: 2022.09 | J4: 2022.12 | K4: 2022.12A | L4: 2023.03 | M4: 2023.06 | N4: 2023.09 | O4: 2023.12 | P4: 2023.12A | Q4: 2024.03 | R4: 2024.06 | S4: 2024.09 | T4: 2024.12 | U4: 2024.12A | V4: 2025.03 | W4: 2025.06 | X4: 2025.09 | Y4: 2025.12 | Z4: 2025.12A | AA4: 2026.03 | AB4: 2026.06 | AC4: 2026.09 | AD4: 2026.12 | AE4: 2026.12A | AF4: 2027.03 | AG4: 2027.06 | AH4: 2027.09 | AI4: 2027.12 | AJ4: 2027.12A | AK4: 2028.03 | AL4: 2028.06 | AM4: 2028.09 | AN4: 2028.12 | AO4: 2028.12A
A5: 매출액 | B5: 손익 | C5: 억원 | D5: 매출액(수익) | E5: =IFERROR(VLOOKUP($D5,BS연결,MATCH(E$1,BS연결H,0),0)/100,"") | G5: =IFERROR(VLOOKUP($D5,BS연결,MATCH(G$1,BS연결H,0),0)/100,"") | H5: =IFERROR(VLOOKUP($D5,BS연결,MATCH(H$1,BS연결H,0),0)/100,"") | I5: =IFERROR(VLOOKUP($D5,BS연결,MATCH(I$1,BS연결H,0),0)/100,"") | J5: =IFERROR(VLOOKUP($D5,BS연결,MATCH(J$1,BS연결H,0),0)/100,"") | K5: =IFERROR(VLOOKUP($D5,BS연결,MATCH(K$1,BS연결H,0),0)/100,"") | L5: =IFERROR(VLOOKUP($D5,BS연결,MATCH(L$1,BS연결H,0),0)/100,"") | M5: =IFERROR(VLOOKUP($D5,BS연결,MATCH(M$1,BS연결H,0),0)/100,"") | N5: =IFERROR(VLOOKUP($D5,BS연결,MATCH(N$1,BS연결H,0),0)/100,"") | ... AB5: =IFERROR(VLOOKUP($D5,BS연결,MATCH(AB$1,BS연결H,0),0)/100,"") | AC5: =IFERROR(X5*(1+변수!AC21),"") | AD5: =IFERROR(Y5*(1+변수!AD21),"") | AE5: =SUM(AA5:AD5) | AF5: =IFERROR(AA5*(1+변수!AF21),"") | AG5: =IFERROR(AB5*(1+변수!AG21),"") | AH5: =IFERROR(AC5*(1+변수!AH21),"") | AI5: =IFERROR(AD5*(1+변수!AI21),"") | AJ5: =SUM(AF5:AI5) | AK5: =IFERROR(AF5*(1+변수!AK21),"") | AL5: =IFERROR(AG5*(1+변수!AL21),"") | AM5: =IFERROR(AH5*(1+변수!AM21),"") | AN5: =IFERROR(AI5*(1+변수!AN21),"") | AO5: =SUM(AK5:AN5)
A6: 매출원가 | B6: 손익 | C6: 억원 | D6: 매출원가 | E6: =IFERROR(VLOOKUP($D6,BS연결,MATCH(E$1,BS연결H,0),0)/100,"") | G6: =IFERROR(VLOOKUP($D6,BS연결,MATCH(G$1,BS연결H,0),0)/100,"") | H6: =IFERROR(VLOOKUP($D6,BS연결,MATCH(H$1,BS연결H,0),0)/100,"") | I6: =IFERROR(VLOOKUP($D6,BS연결,MATCH(I$1,BS연결H,0),0)/100,"") | J6: =IFERROR(VLOOKUP($D6,BS연결,MATCH(J$1,BS연결H,0),0)/100,"") | K6: =IFERROR(VLOOKUP($D6,BS연결,MATCH(K$1,BS연결H,0),0)/100,"") | L6: =IFERROR(VLOOKUP($D6,BS연결,MATCH(L$1,BS연결H,0),0)/100,"") | M6: =IFERROR(VLOOKUP($D6,BS연결,MATCH(M$1,BS연결H,0),0)/100,"") | N6: =IFERROR(VLOOKUP($D6,BS연결,MATCH(N$1,BS연결H,0),0)/100,"") | ... AB6: =IFERROR(VLOOKUP($D6,BS연결,MATCH(AB$1,BS연결H,0),0)/100,"") | AC6: =IFERROR(AC5-AC7,"") | AD6: =IFERROR(AD5-AD7,"") | AE6: =SUM(AA6:AD6) | AF6: =IFERROR(AF5-AF7,"") | AG6: =IFERROR(AG5-AG7,"") | AH6: =IFERROR(AH5-AH7,"") | AI6: =IFERROR(AI5-AI7,"") | AJ6: =SUM(AF6:AI6) | AK6: =IFERROR(AK5-AK7,"") | AL6: =IFERROR(AL5-AL7,"") | AM6: =IFERROR(AM5-AM7,"") | AN6: =IFERROR(AN5-AN7,"") | AO6: =SUM(AK6:AN6)
A7: 매출총이익 | B7: 손익 | C7: 억원 | D7: 매출총이익 | E7: =IFERROR(VLOOKUP($D7,BS연결,MATCH(E$1,BS연결H,0),0)/100,"") | G7: =IFERROR(VLOOKUP($D7,BS연결,MATCH(G$1,BS연결H,0),0)/100,"") | H7: =IFERROR(VLOOKUP($D7,BS연결,MATCH(H$1,BS연결H,0),0)/100,"") | I7: =IFERROR(VLOOKUP($D7,BS연결,MATCH(I$1,BS연결H,0),0)/100,"") | J7: =IFERROR(VLOOKUP($D7,BS연결,MATCH(J$1,BS연결H,0),0)/100,"") | K7: =IFERROR(VLOOKUP($D7,BS연결,MATCH(K$1,BS연결H,0),0)/100,"") | L7: =IFERROR(VLOOKUP($D7,BS연결,MATCH(L$1,BS연결H,0),0)/100,"") | M7: =IFERROR(VLOOKUP($D7,BS연결,MATCH(M$1,BS연결H,0),0)/100,"") | N7: =IFERROR(VLOOKUP($D7,BS연결,MATCH(N$1,BS연결H,0),0)/100,"") | ... AB7: =IFERROR(VLOOKUP($D7,BS연결,MATCH(AB$1,BS연결H,0),0)/100,"") | AC7: =IFERROR(AC9+AC8,"") | AD7: =IFERROR(AD9+AD8,"") | AE7: =SUM(AA7:AD7) | AF7: =IFERROR(AF9+AF8,"") | AG7: =IFERROR(AG9+AG8,"") | AH7: =IFERROR(AH9+AH8,"") | AI7: =IFERROR(AI9+AI8,"") | AJ7: =SUM(AF7:AI7) | AK7: =IFERROR(AK9+AK8,"") | AL7: =IFERROR(AL9+AL8,"") | AM7: =IFERROR(AM9+AM8,"") | AN7: =IFERROR(AN9+AN8,"") | AO7: =SUM(AK7:AN7)
A8: 판관비 | B8: 손익 | C8: 억원 | D8: 판관비 | E8: =IFERROR(VLOOKUP($D8,BS연결,MATCH(E$1,BS연결H,0),0)/100,"") | G8: =IFERROR(VLOOKUP($D8,BS연결,MATCH(G$1,BS연결H,0),0)/100,"") | H8: =IFERROR(VLOOKUP($D8,BS연결,MATCH(H$1,BS연결H,0),0)/100,"") | I8: =IFERROR(VLOOKUP($D8,BS연결,MATCH(I$1,BS연결H,0),0)/100,"") | J8: =IFERROR(VLOOKUP($D8,BS연결,MATCH(J$1,BS연결H,0),0)/100,"") | K8: =IFERROR(VLOOKUP($D8,BS연결,MATCH(K$1,BS연결H,0),0)/100,"") | L8: =IFERROR(VLOOKUP($D8,BS연결,MATCH(L$1,BS연결H,0),0)/100,"") | M8: =IFERROR(VLOOKUP($D8,BS연결,MATCH(M$1,BS연결H,0),0)/100,"") | N8: =IFERROR(VLOOKUP($D8,BS연결,MATCH(N$1,BS연결H,0),0)/100,"") | ... AB8: =IFERROR(VLOOKUP($D8,BS연결,MATCH(AB$1,BS연결H,0),0)/100,"") | AC8: =IFERROR(AC5*변수!AC22,"") | AD8: =IFERROR(AD5*변수!AD22,"") | AE8: =SUM(AA8:AD8) | AF8: =IFERROR(AF5*변수!AF22,"") | AG8: =IFERROR(AG5*변수!AG22,"") | AH8: =IFERROR(AH5*변수!AH22,"") | AI8: =IFERROR(AI5*변수!AI22,"") | AJ8: =SUM(AF8:AI8) | AK8: =IFERROR(AK5*변수!AK22,"") | AL8: =IFERROR(AL5*변수!AL22,"") | AM8: =IFERROR(AM5*변수!AM22,"") | AN8: =IFERROR(AN5*변수!AN22,"") | AO8: =SUM(AK8:AN8)
A9: 영업이익 | B9: 손익 | C9: 억원 | D9: 영업이익 | E9: =IFERROR(VLOOKUP($D9,BS연결,MATCH(E$1,BS연결H,0),0)/100,"") | G9: =IFERROR(VLOOKUP($D9,BS연결,MATCH(G$1,BS연결H,0),0)/100,"") | H9: =IFERROR(VLOOKUP($D9,BS연결,MATCH(H$1,BS연결H,0),0)/100,"") | I9: =IFERROR(VLOOKUP($D9,BS연결,MATCH(I$1,BS연결H,0),0)/100,"") | J9: =IFERROR(VLOOKUP($D9,BS연결,MATCH(J$1,BS연결H,0),0)/100,"") | K9: =IFERROR(VLOOKUP($D9,BS연결,MATCH(K$1,BS연결H,0),0)/100,"") | L9: =IFERROR(VLOOKUP($D9,BS연결,MATCH(L$1,BS연결H,0),0)/100,"") | M9: =IFERROR(VLOOKUP($D9,BS연결,MATCH(M$1,BS연결H,0),0)/100,"") | N9: =IFERROR(VLOOKUP($D9,BS연결,MATCH(N$1,BS연결H,0),0)/100,"") | ... AB9: =IFERROR(VLOOKUP($D9,BS연결,MATCH(AB$1,BS연결H,0),0)/100,"") | AC9: =IFERROR(AC5*변수!AC23,"") | AD9: =IFERROR(AD5*변수!AD23,"") | AE9: =SUM(AA9:AD9) | AF9: =IFERROR(AF5*변수!AF23,"") | AG9: =IFERROR(AG5*변수!AG23,"") | AH9: =IFERROR(AH5*변수!AH23,"") | AI9: =IFERROR(AI5*변수!AI23,"") | AJ9: =SUM(AF9:AI9) | AK9: =IFERROR(AK5*변수!AK23,"") | AL9: =IFERROR(AL5*변수!AL23,"") | AM9: =IFERROR(AM5*변수!AM23,"") | AN9: =IFERROR(AN5*변수!AN23,"") | AO9: =SUM(AK9:AN9)
A10: OPM | B10: 손익 | C10: % | D10: 영업이익률 | E10: =IFERROR(E9/E5,"") | G10: =IFERROR(G9/G5,"") | H10: =IFERROR(H9/H5,"") | I10: =IFERROR(I9/I5,"") | J10: =IFERROR(J9/J5,"") | K10: =IFERROR(K9/K5,"") | L10: =IFERROR(L9/L5,"") | M10: =IFERROR(M9/M5,"") | N10: =IFERROR(N9/N5,"") | ... AO10: =IFERROR(AO9/AO5,"")
A11: 금융손익 | B11: 손익 | C11: 억원 | D11: 금융손익 | E11: =IFERROR(VLOOKUP($D11,BS연결,MATCH(E$1,BS연결H,0),0)/100,"") | G11: =IFERROR(VLOOKUP($D11,BS연결,MATCH(G$1,BS연결H,0),0)/100,"") | H11: =IFERROR(VLOOKUP($D11,BS연결,MATCH(H$1,BS연결H,0),0)/100,"") | I11: =IFERROR(VLOOKUP($D11,BS연결,MATCH(I$1,BS연결H,0),0)/100,"") | J11: =IFERROR(VLOOKUP($D11,BS연결,MATCH(J$1,BS연결H,0),0)/100,"") | K11: =IFERROR(VLOOKUP($D11,BS연결,MATCH(K$1,BS연결H,0),0)/100,"") | L11: =IFERROR(VLOOKUP($D11,BS연결,MATCH(L$1,BS연결H,0),0)/100,"") | M11: =IFERROR(VLOOKUP($D11,BS연결,MATCH(M$1,BS연결H,0),0)/100,"") | N11: =IFERROR(VLOOKUP($D11,BS연결,MATCH(N$1,BS연결H,0),0)/100,"") | ... AB11: =IFERROR(VLOOKUP($D11,BS연결,MATCH(AB$1,BS연결H,0),0)/100,"") | AC11: =IFERROR(AC12+AC13+AC14+AC15,"") | AD11: =IFERROR(AD12+AD13+AD14+AD15,"") | AE11: =SUM(AA11:AD11) | AF11: =IFERROR(AF12+AF13+AF14+AF15,"") | AG11: =IFERROR(AG12+AG13+AG14+AG15,"") | AH11: =IFERROR(AH12+AH13+AH14+AH15,"") | AI11: =IFERROR(AI12+AI13+AI14+AI15,"") | AJ11: =SUM(AF11:AI11) | AK11: =IFERROR(AK12+AK13+AK14+AK15,"") | AL11: =IFERROR(AL12+AL13+AL14+AL15,"") | AM11: =IFERROR(AM12+AM13+AM14+AM15,"") | AN11: =IFERROR(AN12+AN13+AN14+AN15,"") | AO11: =SUM(AK11:AN11)
A12: 이자손익 | B12: 손익 | C12: 억원 | D12: 이자손익 | G12: =IFERROR(VLOOKUP($D12,BS연결,MATCH(G$1,BS연결H,0),0)/100,"") | H12: =IFERROR(VLOOKUP($D12,BS연결,MATCH(H$1,BS연결H,0),0)/100,"") | I12: =IFERROR(VLOOKUP($D12,BS연결,MATCH(I$1,BS연결H,0),0)/100,"") | J12: =IFERROR(VLOOKUP($D12,BS연결,MATCH(J$1,BS연결H,0),0)/100,"") | K12: =IFERROR(VLOOKUP($D12,BS연결,MATCH(K$1,BS연결H,0),0)/100,"") | L12: =IFERROR(VLOOKUP($D12,BS연결,MATCH(L$1,BS연결H,0),0)/100,"") | M12: =IFERROR(VLOOKUP($D12,BS연결,MATCH(M$1,BS연결H,0),0)/100,"") | N12: =IFERROR(VLOOKUP($D12,BS연결,MATCH(N$1,BS연결H,0),0)/100,"") | ... AB12: =IFERROR(VLOOKUP($D12,BS연결,MATCH(AB$1,BS연결H,0),0)/100,"") | AC12: =IFERROR((AB28*변수!$D$54-AB26*변수!$D$55)/4,"") | AD12: =IFERROR((AC28*변수!$D$54-AC26*변수!$D$55)/4,"") | AE12: =SUM(AA12:AD12) | AF12: =IFERROR((AD28*변수!$D$54-AD26*변수!$D$55)/4,"") | AG12: =IFERROR((AF28*변수!$D$54-AF26*변수!$D$55)/4,"") | AH12: =IFERROR((AG28*변수!$D$54-AG26*변수!$D$55)/4,"") | AI12: =IFERROR((AH28*변수!$D$54-AH26*변수!$D$55)/4,"") | AJ12: =SUM(AF12:AI12) | AK12: =IFERROR((AI28*변수!$D$54-AI26*변수!$D$55)/4,"") | AL12: =IFERROR((AK28*변수!$D$54-AK26*변수!$D$55)/4,"") | AM12: =IFERROR((AL28*변수!$D$54-AL26*변수!$D$55)/4,"") | AN12: =IFERROR((AM28*변수!$D$54-AM26*변수!$D$55)/4,"") | AO12: =SUM(AK12:AN12)
A13: 외환손익 | B13: 손익 | C13: 억원 | D13: 외환손익(실적만; 추정 환효과는 환관련손익) | G13: =IFERROR((VLOOKUP("외환차익",BS연결,MATCH(G$1,BS연결H,0),0)-VLOOKUP("외환차손",BS연결,MATCH(G$1,BS연결H,0),0)+VLOOKUP("외화환산이익",BS연결,MATCH(G$1,BS연결H,0),0)-VLOOKUP("외화환산손실",BS연결,MATCH(G$1,BS연결H,0),0))/100,"") | H13: =IFERROR((VLOOKUP("외환차익",BS연결,MATCH(H$1,BS연결H,0),0)-VLOOKUP("외환차손",BS연결,MATCH(H$1,BS연결H,0),0)+VLOOKUP("외화환산이익",BS연결,MATCH(H$1,BS연결H,0),0)-VLOOKUP("외화환산손실",BS연결,MATCH(H$1,BS연결H,0),0))/100,"") | I13: =IFERROR((VLOOKUP("외환차익",BS연결,MATCH(I$1,BS연결H,0),0)-VLOOKUP("외환차손",BS연결,MATCH(I$1,BS연결H,0),0)+VLOOKUP("외화환산이익",BS연결,MATCH(I$1,BS연결H,0),0)-VLOOKUP("외화환산손실",BS연결,MATCH(I$1,BS연결H,0),0))/100,"") | J13: =IFERROR((VLOOKUP("외환차익",BS연결,MATCH(J$1,BS연결H,0),0)-VLOOKUP("외환차손",BS연결,MATCH(J$1,BS연결H,0),0)+VLOOKUP("외화환산이익",BS연결,MATCH(J$1,BS연결H,0),0)-VLOOKUP("외화환산손실",BS연결,MATCH(J$1,BS연결H,0),0))/100,"") | K13: =SUM(G13:J13) | L13: =IFERROR((VLOOKUP("외환차익",BS연결,MATCH(L$1,BS연결H,0),0)-VLOOKUP("외환차손",BS연결,MATCH(L$1,BS연결H,0),0)+VLOOKUP("외화환산이익",BS연결,MATCH(L$1,BS연결H,0),0)-VLOOKUP("외화환산손실",BS연결,MATCH(L$1,BS연결H,0),0))/100,"") | M13: =IFERROR((VLOOKUP("외환차익",BS연결,MATCH(M$1,BS연결H,0),0)-VLOOKUP("외환차손",BS연결,MATCH(M$1,BS연결H,0),0)+VLOOKUP("외화환산이익",BS연결,MATCH(M$1,BS연결H,0),0)-VLOOKUP("외화환산손실",BS연결,MATCH(M$1,BS연결H,0),0))/100,"") | N13: =IFERROR((VLOOKUP("외환차익",BS연결,MATCH(N$1,BS연결H,0),0)-VLOOKUP("외환차손",BS연결,MATCH(N$1,BS연결H,0),0)+VLOOKUP("외화환산이익",BS연결,MATCH(N$1,BS연결H,0),0)-VLOOKUP("외화환산손실",BS연결,MATCH(N$1,BS연결H,0),0))/100,"") | O13: =IFERROR((VLOOKUP("외환차익",BS연결,MATCH(O$1,BS연결H,0),0)-VLOOKUP("외환차손",BS연결,MATCH(O$1,BS연결H,0),0)+VLOOKUP("외화환산이익",BS연결,MATCH(O$1,BS연결H,0),0)-VLOOKUP("외화환산손실",BS연결,MATCH(O$1,BS연결H,0),0))/100,"") | P13: =SUM(L13:O13) | Q13: =IFERROR((VLOOKUP("외환차익",BS연결,MATCH(Q$1,BS연결H,0),0)-VLOOKUP("외환차손",BS연결,MATCH(Q$1,BS연결H,0),0)+VLOOKUP("외화환산이익",BS연결,MATCH(Q$1,BS연결H,0),0)-VLOOKUP("외화환산손실",BS연결,MATCH(Q$1,BS연결H,0),0))/100,"") | R13: =IFERROR((VLOOKUP("외환차익",BS연결,MATCH(R$1,BS연결H,0),0)-VLOOKUP("외환차손",BS연결,MATCH(R$1,BS연결H,0),0)+VLOOKUP("외화환산이익",BS연결,MATCH(R$1,BS연결H,0),0)-VLOOKUP("외화환산손실",BS연결,MATCH(R$1,BS연결H,0),0))/100,"") | S13: =IFERROR((VLOOKUP("외환차익",BS연결,MATCH(S$1,BS연결H,0),0)-VLOOKUP("외환차손",BS연결,MATCH(S$1,BS연결H,0),0)+VLOOKUP("외화환산이익",BS연결,MATCH(S$1,BS연결H,0),0)-VLOOKUP("외화환산손실",BS연결,MATCH(S$1,BS연결H,0),0))/100,"") | T13: =IFERROR((VLOOKUP("외환차익",BS연결,MATCH(T$1,BS연결H,0),0)-VLOOKUP("외환차손",BS연결,MATCH(T$1,BS연결H,0),0)+VLOOKUP("외화환산이익",BS연결,MATCH(T$1,BS연결H,0),0)-VLOOKUP("외화환산손실",BS연결,MATCH(T$1,BS연결H,0),0))/100,"") | U13: =SUM(Q13:T13) | V13: =IFERROR((VLOOKUP("외환차익",BS연결,MATCH(V$1,BS연결H,0),0)-VLOOKUP("외환차손",BS연결,MATCH(V$1,BS연결H,0),0)+VLOOKUP("외화환산이익",BS연결,MATCH(V$1,BS연결H,0),0)-VLOOKUP("외화환산손실",BS연결,MATCH(V$1,BS연결H,0),0))/100,"") | W13: =IFERROR((VLOOKUP("외환차익",BS연결,MATCH(W$1,BS연결H,0),0)-VLOOKUP("외환차손",BS연결,MATCH(W$1,BS연결H,0),0)+VLOOKUP("외화환산이익",BS연결,MATCH(W$1,BS연결H,0),0)-VLOOKUP("외화환산손실",BS연결,MATCH(W$1,BS연결H,0),0))/100,"") | X13: =IFERROR((VLOOKUP("외환차익",BS연결,MATCH(X$1,BS연결H,0),0)-VLOOKUP("외환차손",BS연결,MATCH(X$1,BS연결H,0),0)+VLOOKUP("외화환산이익",BS연결,MATCH(X$1,BS연결H,0),0)-VLOOKUP("외화환산손실",BS연결,MATCH(X$1,BS연결H,0),0))/100,"") | Y13: =IFERROR((VLOOKUP("외환차익",BS연결,MATCH(Y$1,BS연결H,0),0)-VLOOKUP("외환차손",BS연결,MATCH(Y$1,BS연결H,0),0)+VLOOKUP("외화환산이익",BS연결,MATCH(Y$1,BS연결H,0),0)-VLOOKUP("외화환산손실",BS연결,MATCH(Y$1,BS연결H,0),0))/100,"") | Z13: =SUM(V13:Y13) | AA13: =IFERROR((VLOOKUP("외환차익",BS연결,MATCH(AA$1,BS연결H,0),0)-VLOOKUP("외환차손",BS연결,MATCH(AA$1,BS연결H,0),0)+VLOOKUP("외화환산이익",BS연결,MATCH(AA$1,BS연결H,0),0)-VLOOKUP("외화환산손실",BS연결,MATCH(AA$1,BS연결H,0),0))/100,"") | AB13: =IFERROR((VLOOKUP("외환차익",BS연결,MATCH(AB$1,BS연결H,0),0)-VLOOKUP("외환차손",BS연결,MATCH(AB$1,BS연결H,0),0)+VLOOKUP("외화환산이익",BS연결,MATCH(AB$1,BS연결H,0),0)-VLOOKUP("외화환산손실",BS연결,MATCH(AB$1,BS연결H,0),0))/100,"") | AC13: =변수!AC24 | AD13: =변수!AD24 | AE13: =SUM(AA13:AD13) | AF13: =변수!AF24 | AG13: =변수!AG24 | AH13: =변수!AH24 | AI13: =변수!AI24 | AJ13: =SUM(AF13:AI13) | AK13: =변수!AK24 | AL13: =변수!AL24 | AM13: =변수!AM24 | AN13: =변수!AN24 | AO13: =SUM(AK13:AN13)
A14: 파생상품손익 | B14: 손익 | C14: 억원 | D14: 파생상품손익 | G14: =IFERROR((VLOOKUP("파생상품이익",BS연결,MATCH(G$1,BS연결H,0),0)-VLOOKUP("파생상품손실",BS연결,MATCH(G$1,BS연결H,0),0))/100,"") | H14: =IFERROR((VLOOKUP("파생상품이익",BS연결,MATCH(H$1,BS연결H,0),0)-VLOOKUP("파생상품손실",BS연결,MATCH(H$1,BS연결H,0),0))/100,"") | I14: =IFERROR((VLOOKUP("파생상품이익",BS연결,MATCH(I$1,BS연결H,0),0)-VLOOKUP("파생상품손실",BS연결,MATCH(I$1,BS연결H,0),0))/100,"") | J14: =IFERROR((VLOOKUP("파생상품이익",BS연결,MATCH(J$1,BS연결H,0),0)-VLOOKUP("파생상품손실",BS연결,MATCH(J$1,BS연결H,0),0))/100,"") | K14: =SUM(G14:J14) | L14: =IFERROR((VLOOKUP("파생상품이익",BS연결,MATCH(L$1,BS연결H,0),0)-VLOOKUP("파생상품손실",BS연결,MATCH(L$1,BS연결H,0),0))/100,"") | M14: =IFERROR((VLOOKUP("파생상품이익",BS연결,MATCH(M$1,BS연결H,0),0)-VLOOKUP("파생상품손실",BS연결,MATCH(M$1,BS연결H,0),0))/100,"") | N14: =IFERROR((VLOOKUP("파생상품이익",BS연결,MATCH(N$1,BS연결H,0),0)-VLOOKUP("파생상품손실",BS연결,MATCH(N$1,BS연결H,0),0))/100,"") | O14: =IFERROR((VLOOKUP("파생상품이익",BS연결,MATCH(O$1,BS연결H,0),0)-VLOOKUP("파생상품손실",BS연결,MATCH(O$1,BS연결H,0),0))/100,"") | P14: =SUM(L14:O14) | Q14: =IFERROR((VLOOKUP("파생상품이익",BS연결,MATCH(Q$1,BS연결H,0),0)-VLOOKUP("파생상품손실",BS연결,MATCH(Q$1,BS연결H,0),0))/100,"") | R14: =IFERROR((VLOOKUP("파생상품이익",BS연결,MATCH(R$1,BS연결H,0),0)-VLOOKUP("파생상품손실",BS연결,MATCH(R$1,BS연결H,0),0))/100,"") | S14: =IFERROR((VLOOKUP("파생상품이익",BS연결,MATCH(S$1,BS연결H,0),0)-VLOOKUP("파생상품손실",BS연결,MATCH(S$1,BS연결H,0),0))/100,"") | T14: =IFERROR((VLOOKUP("파생상품이익",BS연결,MATCH(T$1,BS연결H,0),0)-VLOOKUP("파생상품손실",BS연결,MATCH(T$1,BS연결H,0),0))/100,"") | U14: =SUM(Q14:T14) | V14: =IFERROR((VLOOKUP("파생상품이익",BS연결,MATCH(V$1,BS연결H,0),0)-VLOOKUP("파생상품손실",BS연결,MATCH(V$1,BS연결H,0),0))/100,"") | W14: =IFERROR((VLOOKUP("파생상품이익",BS연결,MATCH(W$1,BS연결H,0),0)-VLOOKUP("파생상품손실",BS연결,MATCH(W$1,BS연결H,0),0))/100,"") | X14: =IFERROR((VLOOKUP("파생상품이익",BS연결,MATCH(X$1,BS연결H,0),0)-VLOOKUP("파생상품손실",BS연결,MATCH(X$1,BS연결H,0),0))/100,"") | Y14: =IFERROR((VLOOKUP("파생상품이익",BS연결,MATCH(Y$1,BS연결H,0),0)-VLOOKUP("파생상품손실",BS연결,MATCH(Y$1,BS연결H,0),0))/100,"") | Z14: =SUM(V14:Y14) | AA14: =IFERROR((VLOOKUP("파생상품이익",BS연결,MATCH(AA$1,BS연결H,0),0)-VLOOKUP("파생상품손실",BS연결,MATCH(AA$1,BS연결H,0),0))/100,"") | AB14: =IFERROR((VLOOKUP("파생상품이익",BS연결,MATCH(AB$1,BS연결H,0),0)-VLOOKUP("파생상품손실",BS연결,MATCH(AB$1,BS연결H,0),0))/100,"") | AC14: =변수!AC25 | AD14: =변수!AD25 | AE14: =SUM(AA14:AD14) | AF14: =변수!AF25 | AG14: =변수!AG25 | AH14: =변수!AH25 | AI14: =변수!AI25 | AJ14: =SUM(AF14:AI14) | AK14: =변수!AK25 | AL14: =변수!AL25 | AM14: =변수!AM25 | AN14: =변수!AN25 | AO14: =SUM(AK14:AN14)
A15: 기타금융손익 | B15: 손익 | C15: 억원 | D15: 기타금융손익(금융손익 잔차) | G15: =IFERROR(G11-G12-G13-G14,"") | H15: =IFERROR(H11-H12-H13-H14,"") | I15: =IFERROR(I11-I12-I13-I14,"") | J15: =IFERROR(J11-J12-J13-J14,"") | K15: =SUM(G15:J15) | L15: =IFERROR(L11-L12-L13-L14,"") | M15: =IFERROR(M11-M12-M13-M14,"") | N15: =IFERROR(N11-N12-N13-N14,"") | O15: =IFERROR(O11-O12-O13-O14,"") | P15: =SUM(L15:O15) | Q15: =IFERROR(Q11-Q12-Q13-Q14,"") | R15: =IFERROR(R11-R12-R13-R14,"") | S15: =IFERROR(S11-S12-S13-S14,"") | T15: =IFERROR(T11-T12-T13-T14,"") | U15: =SUM(Q15:T15) | V15: =IFERROR(V11-V12-V13-V14,"") | W15: =IFERROR(W11-W12-W13-W14,"") | X15: =IFERROR(X11-X12-X13-X14,"") | Y15: =IFERROR(Y11-Y12-Y13-Y14,"") | Z15: =SUM(V15:Y15) | AA15: =IFERROR(AA11-AA12-AA13-AA14,"") | AB15: =IFERROR(AB11-AB12-AB13-AB14,"") | AC15: =변수!AC26 | AD15: =변수!AD26 | AE15: =SUM(AA15:AD15) | AF15: =변수!AF26 | AG15: =변수!AG26 | AH15: =변수!AH26 | AI15: =변수!AI26 | AJ15: =SUM(AF15:AI15) | AK15: =변수!AK26 | AL15: =변수!AL26 | AM15: =변수!AM26 | AN15: =변수!AN26 | AO15: =SUM(AK15:AN15)
A16: 기타영업외손익 | B16: 손익 | C16: 억원 | D16: 기타영업외손익 | E16: =IFERROR(VLOOKUP($D16,BS연결,MATCH(E$1,BS연결H,0),0)/100,"") | G16: =IFERROR(VLOOKUP($D16,BS연결,MATCH(G$1,BS연결H,0),0)/100,"") | H16: =IFERROR(VLOOKUP($D16,BS연결,MATCH(H$1,BS연결H,0),0)/100,"") | I16: =IFERROR(VLOOKUP($D16,BS연결,MATCH(I$1,BS연결H,0),0)/100,"") | J16: =IFERROR(VLOOKUP($D16,BS연결,MATCH(J$1,BS연결H,0),0)/100,"") | K16: =IFERROR(VLOOKUP($D16,BS연결,MATCH(K$1,BS연결H,0),0)/100,"") | L16: =IFERROR(VLOOKUP($D16,BS연결,MATCH(L$1,BS연결H,0),0)/100,"") | M16: =IFERROR(VLOOKUP($D16,BS연결,MATCH(M$1,BS연결H,0),0)/100,"") | N16: =IFERROR(VLOOKUP($D16,BS연결,MATCH(N$1,BS연결H,0),0)/100,"") | ... AB16: =IFERROR(VLOOKUP($D16,BS연결,MATCH(AB$1,BS연결H,0),0)/100,"") | AC16: =변수!AC27 | AD16: =변수!AD27 | AE16: =SUM(AA16:AD16) | AF16: =변수!AF27 | AG16: =변수!AG27 | AH16: =변수!AH27 | AI16: =변수!AI27 | AJ16: =SUM(AF16:AI16) | AK16: =변수!AK27 | AL16: =변수!AL27 | AM16: =변수!AM27 | AN16: =변수!AN27 | AO16: =SUM(AK16:AN16)
A17: 지분법손익 | B17: 손익 | C17: 억원 | D17: 종속기업,공동지배기업및관계기업관련손익 | E17: =IFERROR(VLOOKUP($D17,BS연결,MATCH(E$1,BS연결H,0),0)/100,"") | G17: =IFERROR(VLOOKUP($D17,BS연결,MATCH(G$1,BS연결H,0),0)/100,"") | H17: =IFERROR(VLOOKUP($D17,BS연결,MATCH(H$1,BS연결H,0),0)/100,"") | I17: =IFERROR(VLOOKUP($D17,BS연결,MATCH(I$1,BS연결H,0),0)/100,"") | J17: =IFERROR(VLOOKUP($D17,BS연결,MATCH(J$1,BS연결H,0),0)/100,"") | K17: =IFERROR(VLOOKUP($D17,BS연결,MATCH(K$1,BS연결H,0),0)/100,"") | L17: =IFERROR(VLOOKUP($D17,BS연결,MATCH(L$1,BS연결H,0),0)/100,"") | M17: =IFERROR(VLOOKUP($D17,BS연결,MATCH(M$1,BS연결H,0),0)/100,"") | N17: =IFERROR(VLOOKUP($D17,BS연결,MATCH(N$1,BS연결H,0),0)/100,"") | ... AB17: =IFERROR(VLOOKUP($D17,BS연결,MATCH(AB$1,BS연결H,0),0)/100,"") | AC17: =변수!AC28 | AD17: =변수!AD28 | AE17: =SUM(AA17:AD17) | AF17: =변수!AF28 | AG17: =변수!AG28 | AH17: =변수!AH28 | AI17: =변수!AI28 | AJ17: =SUM(AF17:AI17) | AK17: =변수!AK28 | AL17: =변수!AL28 | AM17: =변수!AM28 | AN17: =변수!AN28 | AO17: =SUM(AK17:AN17)
A18: 세전이익 | B18: 손익 | C18: 억원 | D18: 법인세비용차감전계속사업이익 | E18: =IFERROR(VLOOKUP($D18,BS연결,MATCH(E$1,BS연결H,0),0)/100,"") | G18: =IFERROR(VLOOKUP($D18,BS연결,MATCH(G$1,BS연결H,0),0)/100,"") | H18: =IFERROR(VLOOKUP($D18,BS연결,MATCH(H$1,BS연결H,0),0)/100,"") | I18: =IFERROR(VLOOKUP($D18,BS연결,MATCH(I$1,BS연결H,0),0)/100,"") | J18: =IFERROR(VLOOKUP($D18,BS연결,MATCH(J$1,BS연결H,0),0)/100,"") | K18: =IFERROR(VLOOKUP($D18,BS연결,MATCH(K$1,BS연결H,0),0)/100,"") | L18: =IFERROR(VLOOKUP($D18,BS연결,MATCH(L$1,BS연결H,0),0)/100,"") | M18: =IFERROR(VLOOKUP($D18,BS연결,MATCH(M$1,BS연결H,0),0)/100,"") | N18: =IFERROR(VLOOKUP($D18,BS연결,MATCH(N$1,BS연결H,0),0)/100,"") | ... AB18: =IFERROR(VLOOKUP($D18,BS연결,MATCH(AB$1,BS연결H,0),0)/100,"") | AC18: =IFERROR(AC9+AC11+AC16+AC17,"") | AD18: =IFERROR(AD9+AD11+AD16+AD17,"") | AE18: =SUM(AA18:AD18) | AF18: =IFERROR(AF9+AF11+AF16+AF17,"") | AG18: =IFERROR(AG9+AG11+AG16+AG17,"") | AH18: =IFERROR(AH9+AH11+AH16+AH17,"") | AI18: =IFERROR(AI9+AI11+AI16+AI17,"") | AJ18: =SUM(AF18:AI18) | AK18: =IFERROR(AK9+AK11+AK16+AK17,"") | AL18: =IFERROR(AL9+AL11+AL16+AL17,"") | AM18: =IFERROR(AM9+AM11+AM16+AM17,"") | AN18: =IFERROR(AN9+AN11+AN16+AN17,"") | AO18: =SUM(AK18:AN18)
A19: 법인세비용 | B19: 손익 | C19: 억원 | D19: 법인세비용 | E19: =IFERROR(VLOOKUP($D19,BS연결,MATCH(E$1,BS연결H,0),0)/100,"") | G19: =IFERROR(VLOOKUP($D19,BS연결,MATCH(G$1,BS연결H,0),0)/100,"") | H19: =IFERROR(VLOOKUP($D19,BS연결,MATCH(H$1,BS연결H,0),0)/100,"") | I19: =IFERROR(VLOOKUP($D19,BS연결,MATCH(I$1,BS연결H,0),0)/100,"") | J19: =IFERROR(VLOOKUP($D19,BS연결,MATCH(J$1,BS연결H,0),0)/100,"") | K19: =IFERROR(VLOOKUP($D19,BS연결,MATCH(K$1,BS연결H,0),0)/100,"") | L19: =IFERROR(VLOOKUP($D19,BS연결,MATCH(L$1,BS연결H,0),0)/100,"") | M19: =IFERROR(VLOOKUP($D19,BS연결,MATCH(M$1,BS연결H,0),0)/100,"") | N19: =IFERROR(VLOOKUP($D19,BS연결,MATCH(N$1,BS연결H,0),0)/100,"") | ... AB19: =IFERROR(VLOOKUP($D19,BS연결,MATCH(AB$1,BS연결H,0),0)/100,"") | AC19: =IFERROR(MAX(AC18,0)*변수!AC29,"") | AD19: =IFERROR(MAX(AD18,0)*변수!AD29,"") | AE19: =SUM(AA19:AD19) | AF19: =IFERROR(MAX(AF18,0)*변수!AF29,"") | AG19: =IFERROR(MAX(AG18,0)*변수!AG29,"") | AH19: =IFERROR(MAX(AH18,0)*변수!AH29,"") | AI19: =IFERROR(MAX(AI18,0)*변수!AI29,"") | AJ19: =SUM(AF19:AI19) | AK19: =IFERROR(MAX(AK18,0)*변수!AK29,"") | AL19: =IFERROR(MAX(AL18,0)*변수!AL29,"") | AM19: =IFERROR(MAX(AM18,0)*변수!AM29,"") | AN19: =IFERROR(MAX(AN18,0)*변수!AN29,"") | AO19: =SUM(AK19:AN19)
A20: 당기순이익 | B20: 손익 | C20: 억원 | D20: 당기순이익 | E20: =IFERROR(VLOOKUP($D20,BS연결,MATCH(E$1,BS연결H,0),0)/100,"") | G20: =IFERROR(VLOOKUP($D20,BS연결,MATCH(G$1,BS연결H,0),0)/100,"") | H20: =IFERROR(VLOOKUP($D20,BS연결,MATCH(H$1,BS연결H,0),0)/100,"") | I20: =IFERROR(VLOOKUP($D20,BS연결,MATCH(I$1,BS연결H,0),0)/100,"") | J20: =IFERROR(VLOOKUP($D20,BS연결,MATCH(J$1,BS연결H,0),0)/100,"") | K20: =IFERROR(VLOOKUP($D20,BS연결,MATCH(K$1,BS연결H,0),0)/100,"") | L20: =IFERROR(VLOOKUP($D20,BS연결,MATCH(L$1,BS연결H,0),0)/100,"") | M20: =IFERROR(VLOOKUP($D20,BS연결,MATCH(M$1,BS연결H,0),0)/100,"") | N20: =IFERROR(VLOOKUP($D20,BS연결,MATCH(N$1,BS연결H,0),0)/100,"") | ... AB20: =IFERROR(VLOOKUP($D20,BS연결,MATCH(AB$1,BS연결H,0),0)/100,"") | AC20: =IFERROR(AC18-AC19,"") | AD20: =IFERROR(AD18-AD19,"") | AE20: =SUM(AA20:AD20) | AF20: =IFERROR(AF18-AF19,"") | AG20: =IFERROR(AG18-AG19,"") | AH20: =IFERROR(AH18-AH19,"") | AI20: =IFERROR(AI18-AI19,"") | AJ20: =SUM(AF20:AI20) | AK20: =IFERROR(AK18-AK19,"") | AL20: =IFERROR(AL18-AL19,"") | AM20: =IFERROR(AM18-AM19,"") | AN20: =IFERROR(AN18-AN19,"") | AO20: =SUM(AK20:AN20)
A21: 지배주주순이익 | B21: 손익 | C21: 억원 | D21: (지배주주지분)당기순이익 | E21: =IFERROR(VLOOKUP($D21,BS연결,MATCH(E$1,BS연결H,0),0)/100,"") | G21: =IFERROR(VLOOKUP($D21,BS연결,MATCH(G$1,BS연결H,0),0)/100,"") | H21: =IFERROR(VLOOKUP($D21,BS연결,MATCH(H$1,BS연결H,0),0)/100,"") | I21: =IFERROR(VLOOKUP($D21,BS연결,MATCH(I$1,BS연결H,0),0)/100,"") | J21: =IFERROR(VLOOKUP($D21,BS연결,MATCH(J$1,BS연결H,0),0)/100,"") | K21: =IFERROR(VLOOKUP($D21,BS연결,MATCH(K$1,BS연결H,0),0)/100,"") | L21: =IFERROR(VLOOKUP($D21,BS연결,MATCH(L$1,BS연결H,0),0)/100,"") | M21: =IFERROR(VLOOKUP($D21,BS연결,MATCH(M$1,BS연결H,0),0)/100,"") | N21: =IFERROR(VLOOKUP($D21,BS연결,MATCH(N$1,BS연결H,0),0)/100,"") | ... U21: =IFERROR(VLOOKUP($D21,BS연결,MATCH(U$1,BS연결H,0),0)/100,"") | V21: 4953.97 | W21: =IFERROR(VLOOKUP($D21,BS연결,MATCH(W$1,BS연결H,0),0)/100,"") | X21: =IFERROR(VLOOKUP($D21,BS연결,MATCH(X$1,BS연결H,0),0)/100,"") | Y21: =IFERROR(VLOOKUP($D21,BS연결,MATCH(Y$1,BS연결H,0),0)/100,"") | Z21: =SUM(V21:Y21) | AA21: 8442.55 | AB21: =IFERROR(VLOOKUP($D21,BS연결,MATCH(AB$1,BS연결H,0),0)/100,"") | AC21: =IFERROR(AC20*변수!AC30,"") | AD21: =IFERROR(AD20*변수!AD30,"") | AE21: =SUM(AA21:AD21) | AF21: =IFERROR(AF20*변수!AF30,"") | AG21: =IFERROR(AG20*변수!AG30,"") | AH21: =IFERROR(AH20*변수!AH30,"") | AI21: =IFERROR(AI20*변수!AI30,"") | AJ21: =SUM(AF21:AI21) | AK21: =IFERROR(AK20*변수!AK30,"") | AL21: =IFERROR(AL20*변수!AL30,"") | AM21: =IFERROR(AM20*변수!AM30,"") | AN21: =IFERROR(AN20*변수!AN30,"") | AO21: =SUM(AK21:AN21)
A22: 자산총계 | B22: 재무상태 | C22: 억원 | D22: 자산총계 | E22: =IFERROR(VLOOKUP($D22,BS연결,MATCH(E$1,BS연결H,0),0)/100,"") | F22: =IFERROR(VLOOKUP($D22,BS연결,MATCH(F$1,BS연결H,0),0)/100,"") | G22: =IFERROR(VLOOKUP($D22,BS연결,MATCH(G$1,BS연결H,0),0)/100,"") | H22: =IFERROR(VLOOKUP($D22,BS연결,MATCH(H$1,BS연결H,0),0)/100,"") | I22: =IFERROR(VLOOKUP($D22,BS연결,MATCH(I$1,BS연결H,0),0)/100,"") | J22: =IFERROR(VLOOKUP($D22,BS연결,MATCH(J$1,BS연결H,0),0)/100,"") | K22: =IFERROR(VLOOKUP($D22,BS연결,MATCH(K$1,BS연결H,0),0)/100,"") | L22: =IFERROR(VLOOKUP($D22,BS연결,MATCH(L$1,BS연결H,0),0)/100,"") | ... AB22: =IFERROR(VLOOKUP($D22,BS연결,MATCH(AB$1,BS연결H,0),0)/100,"") | AC22: =IFERROR(AC23+AC24,"") | AD22: =IFERROR(AD23+AD24,"") | AE22: =AD22 | AF22: =IFERROR(AF23+AF24,"") | AG22: =IFERROR(AG23+AG24,"") | AH22: =IFERROR(AH23+AH24,"") | AI22: =IFERROR(AI23+AI24,"") | AJ22: =AI22 | AK22: =IFERROR(AK23+AK24,"") | AL22: =IFERROR(AL23+AL24,"") | AM22: =IFERROR(AM23+AM24,"") | AN22: =IFERROR(AN23+AN24,"") | AO22: =AN22
A23: 부채총계 | B23: 재무상태 | C23: 억원 | D23: 부채총계 | E23: =IFERROR(VLOOKUP($D23,BS연결,MATCH(E$1,BS연결H,0),0)/100,"") | F23: =IFERROR(VLOOKUP($D23,BS연결,MATCH(F$1,BS연결H,0),0)/100,"") | G23: =IFERROR(VLOOKUP($D23,BS연결,MATCH(G$1,BS연결H,0),0)/100,"") | H23: =IFERROR(VLOOKUP($D23,BS연결,MATCH(H$1,BS연결H,0),0)/100,"") | I23: =IFERROR(VLOOKUP($D23,BS연결,MATCH(I$1,BS연결H,0),0)/100,"") | J23: =IFERROR(VLOOKUP($D23,BS연결,MATCH(J$1,BS연결H,0),0)/100,"") | K23: =IFERROR(VLOOKUP($D23,BS연결,MATCH(K$1,BS연결H,0),0)/100,"") | L23: =IFERROR(VLOOKUP($D23,BS연결,MATCH(L$1,BS연결H,0),0)/100,"") | ... AB23: =IFERROR(VLOOKUP($D23,BS연결,MATCH(AB$1,BS연결H,0),0)/100,"") | AC23: =IFERROR(AB23*(1+변수!AC31),"") | AD23: =IFERROR(AC23*(1+변수!AD31),"") | AE23: =AD23 | AF23: =IFERROR(AD23*(1+변수!AF31),"") | AG23: =IFERROR(AF23*(1+변수!AG31),"") | AH23: =IFERROR(AG23*(1+변수!AH31),"") | AI23: =IFERROR(AH23*(1+변수!AI31),"") | AJ23: =AI23 | AK23: =IFERROR(AI23*(1+변수!AK31),"") | AL23: =IFERROR(AK23*(1+변수!AL31),"") | AM23: =IFERROR(AL23*(1+변수!AM31),"") | AN23: =IFERROR(AM23*(1+변수!AN31),"") | AO23: =AN23
A24: 자본총계 | B24: 재무상태 | C24: 억원 | D24: 자본총계 | E24: =IFERROR(VLOOKUP($D24,BS연결,MATCH(E$1,BS연결H,0),0)/100,"") | F24: =IFERROR(VLOOKUP($D24,BS연결,MATCH(F$1,BS연결H,0),0)/100,"") | G24: =IFERROR(VLOOKUP($D24,BS연결,MATCH(G$1,BS연결H,0),0)/100,"") | H24: =IFERROR(VLOOKUP($D24,BS연결,MATCH(H$1,BS연결H,0),0)/100,"") | I24: =IFERROR(VLOOKUP($D24,BS연결,MATCH(I$1,BS연결H,0),0)/100,"") | J24: =IFERROR(VLOOKUP($D24,BS연결,MATCH(J$1,BS연결H,0),0)/100,"") | K24: =IFERROR(VLOOKUP($D24,BS연결,MATCH(K$1,BS연결H,0),0)/100,"") | L24: =IFERROR(VLOOKUP($D24,BS연결,MATCH(L$1,BS연결H,0),0)/100,"") | ... AB24: =IFERROR(VLOOKUP($D24,BS연결,MATCH(AB$1,BS연결H,0),0)/100,"") | AC24: =IFERROR(AB24+AC20-변수!AC32,"") | AD24: =IFERROR(AC24+AD20-변수!AD32,"") | AE24: =AD24 | AF24: =IFERROR(AD24+AF20-변수!AF32,"") | AG24: =IFERROR(AF24+AG20-변수!AG32,"") | AH24: =IFERROR(AG24+AH20-변수!AH32,"") | AI24: =IFERROR(AH24+AI20-변수!AI32,"") | AJ24: =AI24 | AK24: =IFERROR(AI24+AK20-변수!AK32,"") | AL24: =IFERROR(AK24+AL20-변수!AL32,"") | AM24: =IFERROR(AL24+AM20-변수!AM32,"") | AN24: =IFERROR(AM24+AN20-변수!AN32,"") | AO24: =AN24
A25: 지배주주지분 | B25: 재무상태 | C25: 억원 | D25: 지배주주지분 | E25: =IFERROR(VLOOKUP($D25,BS연결,MATCH(E$1,BS연결H,0),0)/100,"") | F25: =IFERROR(VLOOKUP($D25,BS연결,MATCH(F$1,BS연결H,0),0)/100,"") | G25: =IFERROR(VLOOKUP($D25,BS연결,MATCH(G$1,BS연결H,0),0)/100,"") | H25: =IFERROR(VLOOKUP($D25,BS연결,MATCH(H$1,BS연결H,0),0)/100,"") | I25: =IFERROR(VLOOKUP($D25,BS연결,MATCH(I$1,BS연결H,0),0)/100,"") | J25: =IFERROR(VLOOKUP($D25,BS연결,MATCH(J$1,BS연결H,0),0)/100,"") | K25: =IFERROR(VLOOKUP($D25,BS연결,MATCH(K$1,BS연결H,0),0)/100,"") | L25: =IFERROR(VLOOKUP($D25,BS연결,MATCH(L$1,BS연결H,0),0)/100,"") | ... AB25: =IFERROR(VLOOKUP($D25,BS연결,MATCH(AB$1,BS연결H,0),0)/100,"") | AC25: =IFERROR(AB25+AC21-변수!AC33,"") | AD25: =IFERROR(AC25+AD21-변수!AD33,"") | AE25: =AD25 | AF25: =IFERROR(AD25+AF21-변수!AF33,"") | AG25: =IFERROR(AF25+AG21-변수!AG33,"") | AH25: =IFERROR(AG25+AH21-변수!AH33,"") | AI25: =IFERROR(AH25+AI21-변수!AI33,"") | AJ25: =AI25 | AK25: =IFERROR(AI25+AK21-변수!AK33,"") | AL25: =IFERROR(AK25+AL21-변수!AL33,"") | AM25: =IFERROR(AL25+AM21-변수!AM33,"") | AN25: =IFERROR(AM25+AN21-변수!AN33,"") | AO25: =AN25
A26: 총차입금 | B26: 재무상태 | C26: 억원 | D26: 총차입금 | E26: =IFERROR(VLOOKUP($D26,BS연결,MATCH(E$1,BS연결H,0),0)/100,"") | F26: =IFERROR(VLOOKUP($D26,BS연결,MATCH(F$1,BS연결H,0),0)/100,"") | G26: =IFERROR(VLOOKUP($D26,BS연결,MATCH(G$1,BS연결H,0),0)/100,"") | H26: =IFERROR(VLOOKUP($D26,BS연결,MATCH(H$1,BS연결H,0),0)/100,"") | I26: =IFERROR(VLOOKUP($D26,BS연결,MATCH(I$1,BS연결H,0),0)/100,"") | J26: =IFERROR(VLOOKUP($D26,BS연결,MATCH(J$1,BS연결H,0),0)/100,"") | K26: =IFERROR(VLOOKUP($D26,BS연결,MATCH(K$1,BS연결H,0),0)/100,"") | L26: =IFERROR(VLOOKUP($D26,BS연결,MATCH(L$1,BS연결H,0),0)/100,"") | ... AB26: =IFERROR(VLOOKUP($D26,BS연결,MATCH(AB$1,BS연결H,0),0)/100,"") | AC26: =IFERROR(AB26*(1+변수!AC34),"") | AD26: =IFERROR(AC26*(1+변수!AD34),"") | AE26: =AD26 | AF26: =IFERROR(AD26*(1+변수!AF34),"") | AG26: =IFERROR(AF26*(1+변수!AG34),"") | AH26: =IFERROR(AG26*(1+변수!AH34),"") | AI26: =IFERROR(AH26*(1+변수!AI34),"") | AJ26: =AI26 | AK26: =IFERROR(AI26*(1+변수!AK34),"") | AL26: =IFERROR(AK26*(1+변수!AL34),"") | AM26: =IFERROR(AL26*(1+변수!AM34),"") | AN26: =IFERROR(AM26*(1+변수!AN34),"") | AO26: =AN26
A27: 순차입금 | B27: 재무상태 | C27: 억원 | D27: 순차입금 | E27: =IFERROR(VLOOKUP($D27,BS연결,MATCH(E$1,BS연결H,0),0)/100,"") | F27: =IFERROR(VLOOKUP($D27,BS연결,MATCH(F$1,BS연결H,0),0)/100,"") | G27: =IFERROR(VLOOKUP($D27,BS연결,MATCH(G$1,BS연결H,0),0)/100,"") | H27: =IFERROR(VLOOKUP($D27,BS연결,MATCH(H$1,BS연결H,0),0)/100,"") | I27: =IFERROR(VLOOKUP($D27,BS연결,MATCH(I$1,BS연결H,0),0)/100,"") | J27: =IFERROR(VLOOKUP($D27,BS연결,MATCH(J$1,BS연결H,0),0)/100,"") | K27: =IFERROR(VLOOKUP($D27,BS연결,MATCH(K$1,BS연결H,0),0)/100,"") | L27: =IFERROR(VLOOKUP($D27,BS연결,MATCH(L$1,BS연결H,0),0)/100,"") | ... AB27: =IFERROR(VLOOKUP($D27,BS연결,MATCH(AB$1,BS연결H,0),0)/100,"") | AC27: =IFERROR(AB27*(1+변수!AC35),"") | AD27: =IFERROR(AC27*(1+변수!AD35),"") | AE27: =AD27 | AF27: =IFERROR(AD27*(1+변수!AF35),"") | AG27: =IFERROR(AF27*(1+변수!AG35),"") | AH27: =IFERROR(AG27*(1+변수!AH35),"") | AI27: =IFERROR(AH27*(1+변수!AI35),"") | AJ27: =AI27 | AK27: =IFERROR(AI27*(1+변수!AK35),"") | AL27: =IFERROR(AK27*(1+변수!AL35),"") | AM27: =IFERROR(AL27*(1+변수!AM35),"") | AN27: =IFERROR(AM27*(1+변수!AN35),"") | AO27: =AN27
A28: 이자발생자산 | B28: 재무상태 | C28: 억원 | D28: 이자발생자산 | E28: =IFERROR(VLOOKUP($D28,BS연결,MATCH(E$1,BS연결H,0),0)/100,"") | F28: =IFERROR(VLOOKUP($D28,BS연결,MATCH(F$1,BS연결H,0),0)/100,"") | G28: =IFERROR(VLOOKUP($D28,BS연결,MATCH(G$1,BS연결H,0),0)/100,"") | H28: =IFERROR(VLOOKUP($D28,BS연결,MATCH(H$1,BS연결H,0),0)/100,"") | I28: =IFERROR(VLOOKUP($D28,BS연결,MATCH(I$1,BS연결H,0),0)/100,"") | J28: =IFERROR(VLOOKUP($D28,BS연결,MATCH(J$1,BS연결H,0),0)/100,"") | K28: =IFERROR(VLOOKUP($D28,BS연결,MATCH(K$1,BS연결H,0),0)/100,"") | L28: =IFERROR(VLOOKUP($D28,BS연결,MATCH(L$1,BS연결H,0),0)/100,"") | ... AB28: =IFERROR(VLOOKUP($D28,BS연결,MATCH(AB$1,BS연결H,0),0)/100,"") | AC28: =IFERROR(AB28*(1+변수!AC36),"") | AD28: =IFERROR(AC28*(1+변수!AD36),"") | AE28: =AD28 | AF28: =IFERROR(AD28*(1+변수!AF36),"") | AG28: =IFERROR(AF28*(1+변수!AG36),"") | AH28: =IFERROR(AG28*(1+변수!AH36),"") | AI28: =IFERROR(AH28*(1+변수!AI36),"") | AJ28: =AI28 | AK28: =IFERROR(AI28*(1+변수!AK36),"") | AL28: =IFERROR(AK28*(1+변수!AL36),"") | AM28: =IFERROR(AL28*(1+변수!AM36),"") | AN28: =IFERROR(AM28*(1+변수!AN36),"") | AO28: =AN28
A29: 현금및현금성자산 | B29: 재무상태 | C29: 억원 | D29: 현금및현금성자산 | E29: =IFERROR(VLOOKUP($D29,BS연결,MATCH(E$1,BS연결H,0),0)/100,"") | F29: =IFERROR(VLOOKUP($D29,BS연결,MATCH(F$1,BS연결H,0),0)/100,"") | G29: =IFERROR(VLOOKUP($D29,BS연결,MATCH(G$1,BS연결H,0),0)/100,"") | H29: =IFERROR(VLOOKUP($D29,BS연결,MATCH(H$1,BS연결H,0),0)/100,"") | I29: =IFERROR(VLOOKUP($D29,BS연결,MATCH(I$1,BS연결H,0),0)/100,"") | J29: =IFERROR(VLOOKUP($D29,BS연결,MATCH(J$1,BS연결H,0),0)/100,"") | K29: =IFERROR(VLOOKUP($D29,BS연결,MATCH(K$1,BS연결H,0),0)/100,"") | L29: =IFERROR(VLOOKUP($D29,BS연결,MATCH(L$1,BS연결H,0),0)/100,"") | ... AB29: =IFERROR(VLOOKUP($D29,BS연결,MATCH(AB$1,BS연결H,0),0)/100,"") | AE29: =AD29 | AJ29: =AI29 | AO29: =AN29
A30: CAPEX | B30: 현금흐름 | C30: 억원 | D30: CAPEX | E30: =IFERROR(VLOOKUP($D30,BS연결,MATCH(E$1,BS연결H,0),0)/100,"") | G30: =IFERROR(VLOOKUP($D30,BS연결,MATCH(G$1,BS연결H,0),0)/100,"") | H30: =IFERROR(VLOOKUP($D30,BS연결,MATCH(H$1,BS연결H,0),0)/100,"") | I30: =IFERROR(VLOOKUP($D30,BS연결,MATCH(I$1,BS연결H,0),0)/100,"") | J30: =IFERROR(VLOOKUP($D30,BS연결,MATCH(J$1,BS연결H,0),0)/100,"") | K30: =IFERROR(VLOOKUP($D30,BS연결,MATCH(K$1,BS연결H,0),0)/100,"") | L30: =IFERROR(VLOOKUP($D30,BS연결,MATCH(L$1,BS연결H,0),0)/100,"") | M30: =IFERROR(VLOOKUP($D30,BS연결,MATCH(M$1,BS연결H,0),0)/100,"") | N30: =IFERROR(VLOOKUP($D30,BS연결,MATCH(N$1,BS연결H,0),0)/100,"") | ... AB30: =IFERROR(VLOOKUP($D30,BS연결,MATCH(AB$1,BS연결H,0),0)/100,"") | AC30: =IFERROR(X30*(1+변수!AC38),"") | AD30: =IFERROR(Y30*(1+변수!AD38),"") | AE30: =SUM(AA30:AD30) | AF30: =IFERROR(AA30*(1+변수!AF38),"") | AG30: =IFERROR(AB30*(1+변수!AG38),"") | AH30: =IFERROR(AC30*(1+변수!AH38),"") | AI30: =IFERROR(AD30*(1+변수!AI38),"") | AJ30: =SUM(AF30:AI30) | AK30: =IFERROR(AF30*(1+변수!AK38),"") | AL30: =IFERROR(AG30*(1+변수!AL38),"") | AM30: =IFERROR(AH30*(1+변수!AM38),"") | AN30: =IFERROR(AI30*(1+변수!AN38),"") | AO30: =SUM(AK30:AN30)
A31: 영업활동현금흐름 | B31: 현금흐름 | C31: 억원 | D31: 영업활동으로인한현금흐름 | E31: =IFERROR(VLOOKUP($D31,BS연결,MATCH(E$1,BS연결H,0),0)/100,"") | G31: =IFERROR(VLOOKUP($D31,BS연결,MATCH(G$1,BS연결H,0),0)/100,"") | H31: =IFERROR(VLOOKUP($D31,BS연결,MATCH(H$1,BS연결H,0),0)/100,"") | I31: =IFERROR(VLOOKUP($D31,BS연결,MATCH(I$1,BS연결H,0),0)/100,"") | J31: =IFERROR(VLOOKUP($D31,BS연결,MATCH(J$1,BS연결H,0),0)/100,"") | K31: =IFERROR(VLOOKUP($D31,BS연결,MATCH(K$1,BS연결H,0),0)/100,"") | L31: =IFERROR(VLOOKUP($D31,BS연결,MATCH(L$1,BS연결H,0),0)/100,"") | M31: =IFERROR(VLOOKUP($D31,BS연결,MATCH(M$1,BS연결H,0),0)/100,"") | N31: =IFERROR(VLOOKUP($D31,BS연결,MATCH(N$1,BS연결H,0),0)/100,"") | ... AB31: =IFERROR(VLOOKUP($D31,BS연결,MATCH(AB$1,BS연결H,0),0)/100,"") | AE31: =SUM(AA31:AD31) | AJ31: =SUM(AF31:AI31) | AO31: =SUM(AK31:AN31)
A32: 주식수 | B32: 주당 | C32: 백만주 | D32: 유통주식수 | E32: 70.715 | F32: =E32 | G32: 70.715 | H32: 70.715 | I32: 70.715 | J32: 70.715 | K32: =J32 | L32: 70.715 | M32: 70.715 | N32: 70.715 | O32: 70.715 | P32: =O32 | Q32: 70.715 | R32: 70.715 | S32: 70.715 | T32: 70.715 | U32: =T32 | V32: 70.715 | W32: 70.715 | X32: 70.715 | Y32: 70.715 | Z32: =Y32 | AA32: 70.715 | AB32: 70.715 | AC32: =IFERROR(AB32*(1+변수!AC40),"") | AD32: =IFERROR(AC32*(1+변수!AD40),"") | AE32: =AD32 | AF32: =IFERROR(AD32*(1+변수!AF40),"") | AG32: =IFERROR(AF32*(1+변수!AG40),"") | AH32: =IFERROR(AG32*(1+변수!AH40),"") | AI32: =IFERROR(AH32*(1+변수!AI40),"") | AJ32: =AI32 | AK32: =IFERROR(AI32*(1+변수!AK40),"") | AL32: =IFERROR(AK32*(1+변수!AL40),"") | AM32: =IFERROR(AL32*(1+변수!AM40),"") | AN32: =IFERROR(AM32*(1+변수!AN40),"") | AO32: =AN32
A33: EPS | B33: 주당 | C33: 원 | D33: EPS | E33: =IFERROR(E21*100/E32,"") | G33: =IFERROR(G21*100/G32,"") | H33: =IFERROR(H21*100/H32,"") | I33: =IFERROR(I21*100/I32,"") | J33: =IFERROR(J21*100/J32,"") | K33: =SUM(G33:J33) | L33: =IFERROR(L21*100/L32,"") | M33: =IFERROR(M21*100/M32,"") | N33: =IFERROR(N21*100/N32,"") | O33: =IFERROR(O21*100/O32,"") | P33: =SUM(L33:O33) | Q33: =IFERROR(Q21*100/Q32,"") | R33: =IFERROR(R21*100/R32,"") | S33: =IFERROR(S21*100/S32,"") | T33: =IFERROR(T21*100/T32,"") | U33: =SUM(Q33:T33) | V33: =IFERROR(V21*100/V32,"") | W33: =IFERROR(W21*100/W32,"") | X33: =IFERROR(X21*100/X32,"") | Y33: =IFERROR(Y21*100/Y32,"") | Z33: =SUM(V33:Y33) | AA33: =IFERROR(AA21*100/AA32,"") | AB33: =IFERROR(AB21*100/AB32,"") | AC33: =IFERROR(AC21*100/AC32,"") | AD33: =IFERROR(AD21*100/AD32,"") | AE33: =SUM(AA33:AD33) | AF33: =IFERROR(AF21*100/AF32,"") | AG33: =IFERROR(AG21*100/AG32,"") | AH33: =IFERROR(AH21*100/AH32,"") | AI33: =IFERROR(AI21*100/AI32,"") | AJ33: =SUM(AF33:AI33) | AK33: =IFERROR(AK21*100/AK32,"") | AL33: =IFERROR(AL21*100/AL32,"") | AM33: =IFERROR(AM21*100/AM32,"") | AN33: =IFERROR(AN21*100/AN32,"") | AO33: =SUM(AK33:AN33)
A34: BPS | B34: 주당 | C34: 원 | D34: BPS | E34: =IFERROR(E25*100/E32,"") | F34: =E34 | G34: =IFERROR(G25*100/G32,"") | H34: =IFERROR(H25*100/H32,"") | I34: =IFERROR(I25*100/I32,"") | J34: =IFERROR(J25*100/J32,"") | K34: =J34 | L34: =IFERROR(L25*100/L32,"") | M34: =IFERROR(M25*100/M32,"") | N34: =IFERROR(N25*100/N32,"") | O34: =IFERROR(O25*100/O32,"") | P34: =O34 | Q34: =IFERROR(Q25*100/Q32,"") | R34: =IFERROR(R25*100/R32,"") | S34: =IFERROR(S25*100/S32,"") | T34: =IFERROR(T25*100/T32,"") | U34: =T34 | V34: =IFERROR(V25*100/V32,"") | W34: =IFERROR(W25*100/W32,"") | X34: =IFERROR(X25*100/X32,"") | Y34: =IFERROR(Y25*100/Y32,"") | Z34: =Y34 | AA34: =IFERROR(AA25*100/AA32,"") | AB34: =IFERROR(AB25*100/AB32,"") | AC34: =IFERROR(AC25*100/AC32,"") | AD34: =IFERROR(AD25*100/AD32,"") | AE34: =AD34 | AF34: =IFERROR(AF25*100/AF32,"") | AG34: =IFERROR(AG25*100/AG32,"") | AH34: =IFERROR(AH25*100/AH32,"") | AI34: =IFERROR(AI25*100/AI32,"") | AJ34: =AI34 | AK34: =IFERROR(AK25*100/AK32,"") | AL34: =IFERROR(AL25*100/AL32,"") | AM34: =IFERROR(AM25*100/AM32,"") | AN34: =IFERROR(AN25*100/AN32,"") | AO34: =AN34
A35: DPS | B35: 주당 | C35: 원 | D35: DPS(보통주) | E35: 0 | F35: 0 | J35: 0 | K35: =SUM(G35:J35) | O35: 0 | P35: =SUM(L35:O35) | T35: 5100 | U35: =SUM(Q35:T35) | Y35: 12300 | Z35: =SUM(V35:Y35) | AD35: =변수!AD41 | AE35: =SUM(AA35:AD35) | AI35: =변수!AI41 | AJ35: =SUM(AF35:AI35) | AN35: =변수!AN41 | AO35: =SUM(AK35:AN35)
A36: PER | B36: 주당 | C36: 배 | D36: PER | F36: =E36 | K36: =J36 | M36: =IFERROR(변수!M18/(I33+J33+L33+M33),"") | N36: =IFERROR(변수!N18/(J33+L33+M33+N33),"") | O36: =IFERROR(변수!O18/(L33+M33+N33+O33),"") | P36: =O36 | Q36: =IFERROR(변수!Q18/(M33+N33+O33+Q33),"") | R36: =IFERROR(변수!R18/(N33+O33+Q33+R33),"") | S36: =IFERROR(변수!S18/(O33+Q33+R33+S33),"") | T36: =IFERROR(변수!T18/(Q33+R33+S33+T33),"") | U36: =T36 | V36: =IFERROR(변수!V18/(R33+S33+T33+V33),"") | W36: =IFERROR(변수!W18/(S33+T33+V33+W33),"") | X36: =IFERROR(변수!X18/(T33+V33+W33+X33),"") | Y36: =IFERROR(변수!Y18/(V33+W33+X33+Y33),"") | Z36: =Y36 | AA36: =IFERROR(변수!AA18/(W33+X33+Y33+AA33),"") | AB36: =IFERROR(변수!AB18/(X33+Y33+AA33+AB33),"") | AC36: =IFERROR(변수!$D$44/(Y33+AA33+AB33+AC33),"") | AD36: =IFERROR(변수!$D$44/(AA33+AB33+AC33+AD33),"") | AE36: =AD36 | AF36: =IFERROR(변수!$D$44/(AB33+AC33+AD33+AF33),"") | AG36: =IFERROR(변수!$D$44/(AC33+AD33+AF33+AG33),"") | AH36: =IFERROR(변수!$D$44/(AD33+AF33+AG33+AH33),"") | AI36: =IFERROR(변수!$D$44/(AF33+AG33+AH33+AI33),"") | AJ36: =AI36 | AK36: =IFERROR(변수!$D$44/(AG33+AH33+AI33+AK33),"") | AL36: =IFERROR(변수!$D$44/(AH33+AI33+AK33+AL33),"") | AM36: =IFERROR(변수!$D$44/(AI33+AK33+AL33+AM33),"") | AN36: =IFERROR(변수!$D$44/(AK33+AL33+AM33+AN33),"") | AO36: =AN36
A37: PBR | B37: 주당 | C37: 배 | D37: PBR | E37: =IFERROR(변수!E18/E34,"") | F37: =E37 | G37: =IFERROR(변수!G18/G34,"") | H37: =IFERROR(변수!H18/H34,"") | I37: =IFERROR(변수!I18/I34,"") | J37: =IFERROR(변수!J18/J34,"") | K37: =J37 | L37: =IFERROR(변수!L18/L34,"") | M37: =IFERROR(변수!M18/M34,"") | N37: =IFERROR(변수!N18/N34,"") | O37: =IFERROR(변수!O18/O34,"") | P37: =O37 | Q37: =IFERROR(변수!Q18/Q34,"") | R37: =IFERROR(변수!R18/R34,"") | S37: =IFERROR(변수!S18/S34,"") | T37: =IFERROR(변수!T18/T34,"") | U37: =T37 | V37: =IFERROR(변수!V18/V34,"") | W37: =IFERROR(변수!W18/W34,"") | X37: =IFERROR(변수!X18/X34,"") | Y37: =IFERROR(변수!Y18/Y34,"") | Z37: =Y37 | AA37: =IFERROR(변수!AA18/AA34,"") | AB37: =IFERROR(변수!AB18/AB34,"") | AC37: =IFERROR(변수!$D$44/AC34,"") | AD37: =IFERROR(변수!$D$44/AD34,"") | AE37: =AD37 | AF37: =IFERROR(변수!$D$44/AF34,"") | AG37: =IFERROR(변수!$D$44/AG34,"") | AH37: =IFERROR(변수!$D$44/AH34,"") | AI37: =IFERROR(변수!$D$44/AI34,"") | AJ37: =AI37 | AK37: =IFERROR(변수!$D$44/AK34,"") | AL37: =IFERROR(변수!$D$44/AL34,"") | AM37: =IFERROR(변수!$D$44/AM34,"") | AN37: =IFERROR(변수!$D$44/AN34,"") | AO37: =AN37
A38: 매출전사 | B38: 사업부 | C38: 억원 | D38: 매출 전사(부문 미분리) | E38: 44566.49 | G38: 39077.28 | H38: 41886.06 | I38: 42644.15 | J38: 49412.7 | K38: =SUM(G38:J38) | L38: 48423.59 | M38: 54536.4 | N38: 50112.06 | O38: 59890 | P38: =SUM(L38:O38) | Q38: 55156.26 | R38: 66154.84 | S38: 62457.56 | T38: 71617.12 | U38: =SUM(Q38:T38) | V38: 67717.06 | W38: 74284.17 | X38: 75814.36 | Y38: 81516.57 | Z38: =SUM(V38:Y38) | AA38: 81408.9 | AB38: 89270.46 | AC38: =IFERROR(AC5,"") | AD38: =IFERROR(AD5,"") | AE38: =SUM(AA38:AD38) | AF38: =IFERROR(AF5,"") | AG38: =IFERROR(AG5,"") | AH38: =IFERROR(AH5,"") | AI38: =IFERROR(AI5,"") | AJ38: =SUM(AF38:AI38) | AK38: =IFERROR(AK5,"") | AL38: =IFERROR(AL5,"") | AM38: =IFERROR(AM5,"") | AN38: =IFERROR(AN5,"") | AO38: =SUM(AK38:AN38)
A39: OP전사 | B39: 사업부 | C39: 억원 | D39: OP 전사(부문 미분리) | E39: -6967.58 | G39: -3963.96 | H39: -2650.85 | I39: 1887.36 | J39: 1171.84 | K39: =SUM(G39:J39) | L39: -190.44 | M39: 712.57 | N39: 689.57 | O39: 1610.91 | P39: =SUM(L39:O39) | Q39: 1601.63 | R39: 3764.65 | S39: 3984.08 | T39: 4990.55 | U39: =SUM(Q39:T39) | V39: 8591.54 | W39: 9536.41 | X39: 10537.75 | Y39: 10379.19 | Z39: =SUM(V39:Y39) | AA39: 13559.7 | AB39: 16451.46 | AC39: =IFERROR(AC9,"") | AD39: =IFERROR(AD9,"") | AE39: =SUM(AA39:AD39) | AF39: =IFERROR(AF9,"") | AG39: =IFERROR(AG9,"") | AH39: =IFERROR(AH9,"") | AI39: =IFERROR(AI9,"") | AJ39: =SUM(AF39:AI39) | AK39: =IFERROR(AK9,"") | AL39: =IFERROR(AL9,"") | AM39: =IFERROR(AM9,"") | AN39: =IFERROR(AN9,"") | AO39: =SUM(AK39:AN39)
B40: 비율(참고)
A41: NPM | C41: % | D41: 지배주주순이익 / 매출액 | E41: =IFERROR(E21/E5,"") | F41: =IFERROR(F21/F5,"") | G41: =IFERROR(G21/G5,"") | H41: =IFERROR(H21/H5,"") | I41: =IFERROR(I21/I5,"") | J41: =IFERROR(J21/J5,"") | K41: =IFERROR(K21/K5,"") | L41: =IFERROR(L21/L5,"") | ... AO41: =IFERROR(AO21/AO5,"")
A42: 매출원가율 | C42: % | D42: 매출원가 / 매출액 | E42: =IFERROR(E6/E5,"") | F42: =IFERROR(F6/F5,"") | G42: =IFERROR(G6/G5,"") | H42: =IFERROR(H6/H5,"") | I42: =IFERROR(I6/I5,"") | J42: =IFERROR(J6/J5,"") | K42: =IFERROR(K6/K5,"") | L42: =IFERROR(L6/L5,"") | ... AO42: =IFERROR(AO6/AO5,"")
A43: 판관비율 | C43: % | D43: 판관비 / 매출액 | E43: =IFERROR(E8/E5,"") | F43: =IFERROR(F8/F5,"") | G43: =IFERROR(G8/G5,"") | H43: =IFERROR(H8/H5,"") | I43: =IFERROR(I8/I5,"") | J43: =IFERROR(J8/J5,"") | K43: =IFERROR(K8/K5,"") | L43: =IFERROR(L8/L5,"") | ... AO43: =IFERROR(AO8/AO5,"")

Sheet SLS
C1: 이름: SLS_H · 선표 매출인식(백만$) — sls json origin 2026Q2 | E1: 3Q19 | F1: 4Q19 | G1: 1Q20 | H1: 2Q20 | I1: 3Q20 | J1: 4Q20 | K1: 1Q21 | L1: 2Q21 | M1: 3Q21 | N1: 4Q21 | O1: 1Q22 | P1: 2Q22 | Q1: 3Q22 | R1: 4Q22 | S1: 1Q23 | T1: 2Q23 | U1: 3Q23 | V1: 4Q23 | W1: 1Q24 | X1: 2Q24 | Y1: 3Q24 | Z1: 4Q24 | AA1: 1Q25 | AB1: 2Q25 | AC1: 3Q25 | AD1: 4Q25 | AE1: 1Q26 | AF1: 2Q26 | AG1: 3Q26 | AH1: 4Q26 | AI1: 1Q27 | AJ1: 2Q27 | AK1: 3Q27 | AL1: 4Q27 | AM1: 1Q28 | AN1: 2Q28 | AO1: 3Q28 | AP1: 4Q28 | AQ1: 1Q29 | AR1: 2Q29 | AS1: 3Q29 | AT1: 4Q29 | AU1: 1Q30 | AV1: 2Q30 | AW1: 2019 | AX1: 2020 | AY1: 2021 | AZ1: 2022 | BA1: 2023 | BB1: 2024 | BC1: 2025 | BD1: 2026 | BE1: 2027 | BF1: 2028 | BG1: 2029 | BH1: 2030
A2: 코호트 표(레퍼런스 실측 캘리브레이션): ①적자 −1.1% ②BEP 1% ③중마진 4.3% ④호황 5.4% ⑤초호황 10.8% — 회사별 캘리브레이션은 target_opm.basis 참조 · 코호트 모드 reference_anchor(대안 ledger_relative) · 잔고 캡 미적용
E3: 1 | F3: 2 | G3: 3 | H3: 4 | I3: 5 | J3: 6 | K3: 7 | L3: 8 | M3: 9 | N3: 10 | O3: 11 | P3: 12 | Q3: 13 | R3: 14 | S3: 15 | T3: 16 | U3: 17 | V3: 18 | W3: 19 | X3: 20 | Y3: 21 | Z3: 22 | AA3: 23 | AB3: 24 | AC3: 25 | AD3: 26 | AE3: 27 | AF3: 28 | AG3: 29 | AH3: 30 | AI3: 31 | AJ3: 32 | AK3: 33 | AL3: 34 | AM3: 35 | AN3: 36 | AO3: 37 | AP3: 38 | AQ3: 39 | AR3: 40 | AS3: 41 | AT3: 42 | AU3: 43 | AV3: 44 | AW3: 45 | AX3: 46 | AY3: 47 | AZ3: 48 | BA3: 49 | BB3: 50 | BC3: 51 | BD3: 52 | BE3: 53 | BF3: 54 | BG3: 55 | BH3: 56
E4: 2019.09 | F4: 2019.12 | G4: 2020.03 | H4: 2020.06 | I4: 2020.09 | J4: 2020.12 | K4: 2021.03 | L4: 2021.06 | M4: 2021.09 | N4: 2021.12 | O4: 2022.03 | P4: 2022.06 | Q4: 2022.09 | R4: 2022.12 | S4: 2023.03 | T4: 2023.06 | U4: 2023.09 | V4: 2023.12 | W4: 2024.03 | X4: 2024.06 | Y4: 2024.09 | Z4: 2024.12 | AA4: 2025.03 | AB4: 2025.06 | AC4: 2025.09 | AD4: 2025.12 | AE4: 2026.03 | AF4: 2026.06 | AG4: 2026.09 | AH4: 2026.12 | AI4: 2027.03 | AJ4: 2027.06 | AK4: 2027.09 | AL4: 2027.12 | AM4: 2028.03 | AN4: 2028.06 | AO4: 2028.09 | AP4: 2028.12 | AQ4: 2029.03 | AR4: 2029.06 | AS4: 2029.09 | AT4: 2029.12 | AU4: 2030.03 | AV4: 2030.06 | AW4: 2019.12A | AX4: 2020.12A | AY4: 2021.12A | AZ4: 2022.12A | BA4: 2023.12A | BB4: 2024.12A | BC4: 2025.12A | BD4: 2026.12A | BE4: 2027.12A | BF4: 2028.12A | BG4: 2029.12A | BH4: 2030.12A
A5: usd_m | D5: 매출인식 합계(백만$) | E5: 1.437 | F5: 4.722 | G5: 4.671 | H5: 4.671 | I5: 4.722 | J5: 4.722 | K5: 4.619 | L5: 34.199 | M5: 58.893 | N5: 67.289 | O5: 65.826 | P5: 66.557 | Q5: 67.289 | R5: 67.289 | S5: 65.826 | T5: 66.557 | U5: 67.289 | V5: 67.289 | W5: 66.557 | X5: 66.557 | Y5: 67.289 | Z5: 67.289 | AA5: 65.826 | AB5: 24.091 | AC5: 70.694 | AD5: 140.261 | AE5: 306.79 | AF5: 459.926 | AG5: 554.32 | AH5: 556.754 | AI5: 544.651 | AJ5: 550.702 | AK5: 552.756 | AL5: 544.494 | AM5: 538.576 | AN5: 534.432 | AO5: 506.379 | AP5: 466.438 | AQ5: 349.912 | AR5: 244.248 | AS5: 155.825 | AT5: 86.689 | AU5: 24.339 | AV5: 16.497 | AW5: 6.159 | AX5: 18.786 | AY5: 165 | AZ5: 266.961 | BA5: 266.961 | BB5: 267.692 | BC5: 300.872 | BD5: 1877.79 | BE5: 2192.603 | BF5: 2045.825 | BG5: 836.674 | BH5: 40.836
A6: marine_usd_m | D6: 해양(type≠OTHER) 합계(백만$) | E6: 0 | F6: 0 | G6: 0 | H6: 0 | I6: 0 | J6: 0 | K6: 0 | L6: 29.528 | M6: 50.307 | N6: 50.307 | O6: 49.213 | P6: 49.76 | Q6: 50.307 | R6: 50.307 | S6: 49.213 | T6: 49.76 | U6: 50.307 | V6: 50.307 | W6: 49.76 | X6: 49.76 | Y6: 50.307 | Z6: 50.307 | AA6: 49.213 | AB6: 7.294 | AC6: 53.713 | AD6: 124.101 | AE6: 294.797 | AF6: 447.8 | AG6: 542.06 | AH6: 544.494 | AI6: 532.658 | AJ6: 538.576 | AK6: 544.494 | AL6: 544.494 | AM6: 538.576 | AN6: 534.432 | AO6: 506.379 | AP6: 466.438 | AQ6: 349.912 | AR6: 244.248 | AS6: 155.825 | AT6: 86.689 | AU6: 24.339 | AV6: 16.497 | AW6: 0 | AX6: 0 | AY6: 130.142 | AZ6: 199.587 | BA6: 199.587 | BB6: 200.134 | BC6: 234.321 | BD6: 1829.151 | BE6: 2160.222 | BF6: 2045.825 | BG6: 836.674 | BH6: 40.836
A7: type:OTHER | D7: 선종 OTHER | E7: 1.437 | F7: 4.722 | G7: 4.671 | H7: 4.671 | I7: 4.722 | J7: 4.722 | K7: 4.619 | L7: 4.671 | M7: 8.586 | N7: 16.982 | O7: 16.612 | P7: 16.797 | Q7: 16.982 | R7: 16.982 | S7: 16.612 | T7: 16.797 | U7: 16.982 | V7: 16.982 | W7: 16.797 | X7: 16.797 | Y7: 16.982 | Z7: 16.982 | AA7: 16.612 | AB7: 16.797 | AC7: 16.982 | AD7: 16.16 | AE7: 11.993 | AF7: 12.126 | AG7: 12.26 | AH7: 12.26 | AI7: 11.993 | AJ7: 12.126 | AK7: 8.262 | AW7: 6.159 | AX7: 18.786 | AY7: 34.858 | AZ7: 67.373 | BA7: 67.373 | BB7: 67.558 | BC7: 66.551 | BD7: 48.639 | BE7: 32.381
A8: type:OFFSH | D8: 선종 OFFSH | L8: 29.528 | M8: 50.307 | N8: 50.307 | O8: 49.213 | P8: 49.76 | Q8: 50.307 | R8: 50.307 | S8: 49.213 | T8: 49.76 | U8: 50.307 | V8: 50.307 | W8: 49.76 | X8: 49.76 | Y8: 50.307 | Z8: 50.307 | AA8: 49.213 | AB8: 4.375 | AY8: 130.142 | AZ8: 199.587 | BA8: 199.587 | BB8: 200.134 | BC8: 53.588
A9: type:LNGC | D9: 선종 LNGC | AB9: 2.919 | AC9: 53.713 | AD9: 60.682 | AE9: 89.625 | AF9: 154.335 | AG9: 176.152 | AH9: 176.152 | AI9: 172.322 | AJ9: 174.237 | AK9: 176.152 | AL9: 176.152 | AM9: 174.237 | AN9: 174.237 | AO9: 150.746 | AP9: 150.746 | AQ9: 93.956 | AR9: 75.519 | AS9: 46.123 | BC9: 117.314 | BD9: 596.264 | BE9: 698.863 | BF9: 649.966 | BG9: 215.598
A10: type:CONT | D10: 선종 CONT | AD10: 42.327 | AE10: 119.295 | AF10: 120.621 | AG10: 121.946 | AH10: 121.946 | AI10: 119.295 | AJ10: 120.621 | AK10: 121.946 | AL10: 121.946 | AM10: 120.621 | AN10: 120.621 | AO10: 121.946 | AP10: 103.696 | AQ10: 79.233 | AR10: 26.411 | BC10: 42.327 | BD10: 483.808 | BE10: 483.808 | BF10: 466.884 | BG10: 105.644
A11: type:VLCC | D11: 선종 VLCC | AD11: 21.092 | AE11: 70.181 | AF11: 80.62 | AG11: 81.506 | AH11: 81.506 | AI11: 79.734 | AJ11: 80.62 | AK11: 81.506 | AL11: 81.506 | AM11: 80.62 | AN11: 80.62 | AO11: 81.506 | AP11: 60.267 | AQ11: 48.398 | AR11: 44.387 | AS11: 16.99 | BC11: 21.092 | BD11: 313.813 | BE11: 323.366 | BF11: 303.013 | BG11: 109.775
A12: type:VLGC | D12: 선종 VLGC | AE12: 15.695 | AF12: 92.225 | AG12: 162.457 | AH12: 164.891 | AI12: 161.306 | AJ12: 163.099 | AK12: 164.891 | AL12: 164.891 | AM12: 163.099 | AN12: 158.955 | AO12: 152.182 | AP12: 151.73 | AQ12: 128.326 | AR12: 97.931 | AS12: 92.713 | AT12: 86.689 | AU12: 24.339 | AV12: 16.497 | BD12: 435.268 | BE12: 654.187 | BF12: 625.966 | BG12: 405.659 | BH12: 40.836
A13: cohort:등급없음 | D13: 코호트 등급없음 | E13: 1.437 | F13: 4.722 | G13: 4.671 | H13: 4.671 | I13: 4.722 | J13: 4.722 | K13: 4.619 | L13: 4.671 | M13: 8.586 | N13: 16.982 | O13: 16.612 | P13: 16.797 | Q13: 16.982 | R13: 16.982 | S13: 16.612 | T13: 16.797 | U13: 16.982 | V13: 16.982 | W13: 16.797 | X13: 16.797 | Y13: 16.982 | Z13: 16.982 | AA13: 16.612 | AB13: 16.797 | AC13: 16.982 | AD13: 16.16 | AE13: 11.993 | AF13: 12.126 | AG13: 12.26 | AH13: 12.26 | AI13: 11.993 | AJ13: 12.126 | AK13: 8.262 | AW13: 6.159 | AX13: 18.786 | AY13: 34.858 | AZ13: 67.373 | BA13: 67.373 | BB13: 67.558 | BC13: 66.551 | BD13: 48.639 | BE13: 32.381
A14: cohort:④호황 | D14: 코호트 ④호황 | L14: 29.528 | M14: 50.307 | N14: 50.307 | O14: 49.213 | P14: 49.76 | Q14: 50.307 | R14: 50.307 | S14: 49.213 | T14: 49.76 | U14: 50.307 | V14: 50.307 | W14: 49.76 | X14: 49.76 | Y14: 50.307 | Z14: 50.307 | AA14: 49.213 | AB14: 4.375 | AY14: 130.142 | AZ14: 199.587 | BA14: 199.587 | BB14: 200.134 | BC14: 53.588
A15: cohort:⑤초호황 | D15: 코호트 ⑤초호황 | AB15: 2.919 | AC15: 53.713 | AD15: 124.101 | AE15: 294.797 | AF15: 447.8 | AG15: 542.06 | AH15: 544.494 | AI15: 532.658 | AJ15: 538.576 | AK15: 544.494 | AL15: 544.494 | AM15: 538.576 | AN15: 534.432 | AO15: 506.379 | AP15: 466.438 | AQ15: 349.912 | AR15: 244.248 | AS15: 155.825 | AT15: 86.689 | AU15: 24.339 | AV15: 16.497 | BC15: 180.733 | BD15: 1829.151 | BE15: 2160.222 | BF15: 2045.825 | BG15: 836.674 | BH15: 40.836
A16: hedge_ratio | D16: 헤지비율 | E16: 0.7 | F16: 0.7 | G16: 0.7 | H16: 0.7 | I16: 0.7 | J16: 0.7 | K16: 0.7 | L16: 0.7 | M16: 0.7 | N16: 0.7 | O16: 0.7 | P16: 0.7 | Q16: 0.7 | R16: 0.7 | S16: 0.7 | T16: 0.7 | U16: 0.7 | V16: 0.7 | W16: 0.7 | X16: 0.7 | Y16: 0.7 | Z16: 0.7 | AA16: 0.7 | AB16: 0.7 | AC16: 0.7 | AD16: 0.7 | AE16: 0.7 | AF16: 0.7 | AG16: 0.7 | AH16: 0.7 | AI16: 0.7 | AJ16: 0.7 | AK16: 0.7 | AL16: 0.7 | AM16: 0.7 | AN16: 0.7 | AO16: 0.7 | AP16: 0.7 | AQ16: 0.7 | AR16: 0.7 | AS16: 0.7 | AT16: 0.7 | AU16: 0.7 | AV16: 0.7
A17: hedge_rate | D17: 헤지환율(가중) | E17: 1193.96 | F17: 1193.96 | G17: 1193.96 | H17: 1193.96 | I17: 1193.96 | J17: 1193.96 | K17: 1193.96 | L17: 1131.31 | M17: 1129.74 | N17: 1133.51 | O17: 1133.51 | P17: 1133.51 | Q17: 1133.51 | R17: 1133.51 | S17: 1133.51 | T17: 1133.51 | U17: 1133.51 | V17: 1133.51 | W17: 1133.51 | X17: 1133.51 | Y17: 1133.51 | Z17: 1133.51 | AA17: 1133.51 | AB17: 1183.87 | AC17: 1314.89 | AD17: 1383 | AE17: 1424.78 | AF17: 1447.13 | AG17: 1452.57 | AH17: 1452.42 | AI17: 1452.42 | AJ17: 1452.42 | AK17: 1454.54 | AL17: 1459.01 | AM17: 1459.01 | AN17: 1458.95 | AO17: 1458.47 | AP17: 1459.25 | AQ17: 1469.71 | AR17: 1478.79 | AS17: 1482.77 | AT17: 1477.93 | AU17: 1418.75 | AV17: 1418.75
A18: spot_assumed | D18: 건조시점 환율(sls 가정) | E18: 1193.96 | F18: 1176.23 | G18: 1193.92 | H18: 1219.69 | I18: 1187.81 | J18: 1117.97 | K18: 1114.99 | L18: 1121.13 | M18: 1159.91 | N18: 1183.5 | O18: 1205.78 | P18: 1262.09 | Q18: 1341.93 | R18: 1360.12 | S18: 1276.95 | T18: 1315.69 | U18: 1313.62 | V18: 1322.01 | W18: 1330.14 | X18: 1371.28 | Y18: 1356.22 | Z18: 1396.3 | AA18: 1452.28 | AB18: 1398.52 | AC18: 1386.95 | AD18: 1449.19 | AE18: 1466.12 | AF18: 1501.75 | AG18: 1418.75 | AH18: 1345.14 | AI18: 1341.49 | AJ18: 1341.49 | AK18: 1341.49 | AL18: 1341.49 | AM18: 1341.49 | AN18: 1341.49 | AO18: 1341.49 | AP18: 1341.49 | AQ18: 1341.49 | AR18: 1341.49 | AS18: 1341.49 | AT18: 1341.49 | AU18: 1341.49 | AV18: 1341.49
A19: applied_rate | D19: 적용환율 | E19: 1193.96 | F19: 1188.64 | G19: 1193.95 | H19: 1201.68 | I19: 1192.12 | J19: 1171.16 | K19: 1170.27 | L19: 1128.26 | M19: 1138.79 | N19: 1148.51 | O19: 1155.19 | P19: 1172.08 | Q19: 1196.03 | R19: 1201.49 | S19: 1176.54 | T19: 1188.16 | U19: 1187.54 | V19: 1190.06 | W19: 1192.5 | X19: 1204.84 | Y19: 1200.32 | Z19: 1212.35 | AA19: 1229.14 | AB19: 1248.27 | AC19: 1336.51 | AD19: 1402.85 | AE19: 1437.18 | AF19: 1463.51 | AG19: 1442.42 | AH19: 1420.24 | AI19: 1419.14 | AJ19: 1419.14 | AK19: 1420.62 | AL19: 1423.75 | AM19: 1423.75 | AN19: 1423.71 | AO19: 1423.38 | AP19: 1423.92 | AQ19: 1431.24 | AR19: 1437.6 | AS19: 1440.38 | AT19: 1437 | AU19: 1395.57 | AV19: 1395.57
A20: hedged_krw_m | D20: 헤지적용 원화매출(백만원) | E20: 1715.9 | F20: 5612.7 | G20: 5576.5 | H20: 5612.6 | I20: 5629.1 | J20: 5530.2 | K20: 5405.8 | L20: 38584.8 | M20: 67067.4 | N20: 77281.3 | O20: 76041.2 | P20: 78010.5 | Q20: 80479.5 | R20: 80846.6 | S20: 77446.7 | T20: 79080.7 | U20: 79908 | V20: 80077.3 | W20: 79369.3 | X20: 80190.7 | Y20: 80767.9 | Z20: 81577 | AA20: 80909.1 | AB20: 30071.6 | AC20: 94483.5 | AD20: 196766.5 | AE20: 440913.4 | AF20: 673108 | AG20: 799564 | AH20: 790722.4 | AI20: 772936.4 | AJ20: 781524.5 | AK20: 785258 | AL20: 775224.8 | AM20: 766798.4 | AN20: 760877.4 | AO20: 720768.7 | AP20: 664171.2 | AQ20: 500809.6 | AR20: 351131.5 | AS20: 224447.8 | AT20: 124571.1 | AU20: 33967.5 | AV20: 23022.4 | AW20: 7328.6 | AX20: 22348.4 | AY20: 188339.3 | AZ20: 315377.8 | BA20: 316512.7 | BB20: 321904.9 | BC20: 402230.7 | BD20: 2704307.8 | BE20: 3114943.7 | BF20: 2912615.7 | BG20: 1200960 | BH20: 56989.9
A21: marine_hedged_krw_m | D21: 해양 원화(백만원) | E21: 0 | F21: 0 | G21: 0 | H21: 0 | I21: 0 | J21: 0 | K21: 0 | L21: 33110.3 | M21: 56995.4 | N21: 57351.5 | O21: 56433.6 | P21: 57901.3 | Q21: 59742.5 | R21: 60017 | S21: 57484.4 | T21: 58701.4 | U21: 59315.2 | V21: 59441.9 | W21: 58917.1 | X21: 59531.3 | Y21: 59958.2 | Z21: 60563.1 | AA21: 60073 | AB21: 9274.9 | AC21: 73517.2 | AD21: 176526.4 | AE21: 425900.7 | AF21: 657798.9 | AG21: 784391.9 | AH21: 775821 | AI21: 758372.1 | AJ21: 766798.4 | AK21: 775224.8 | AL21: 775224.8 | AM21: 766798.4 | AN21: 760877.4 | AO21: 720768.7 | AP21: 664171.2 | AQ21: 500809.6 | AR21: 351131.5 | AS21: 224447.8 | AT21: 124571.1 | AU21: 33967.5 | AV21: 23022.4 | AW21: 0 | AX21: 0 | AY21: 147457.2 | AZ21: 234094.4 | BA21: 234942.9 | BB21: 238969.7 | BC21: 319391.5 | BD21: 2643912.5 | BE21: 3075620.1 | BF21: 2912615.7 | BG21: 1200960 | BH21: 56989.9
A22: marine_hedged_krw_m_signed_by_origin | D22: 해양 원화 — origin 분기말까지 체결분(백만원) | E22: 0 | F22: 0 | G22: 0 | H22: 0 | I22: 0 | J22: 0 | K22: 0 | L22: 33110.3 | M22: 56995.4 | N22: 57351.5 | O22: 56433.6 | P22: 57901.3 | Q22: 59742.5 | R22: 60017 | S22: 57484.4 | T22: 58701.4 | U22: 59315.2 | V22: 59441.9 | W22: 58917.1 | X22: 59531.3 | Y22: 59958.2 | Z22: 60563.1 | AA22: 60073 | AB22: 9274.9 | AC22: 73517.2 | AD22: 176526.4 | AE22: 425900.7 | AF22: 657798.9 | AG22: 752546.1 | AH22: 741071.4 | AI22: 724404.6 | AJ22: 732453.5 | AK22: 740502.4 | AL22: 740502.4 | AM22: 732453.5 | AN22: 726532.4 | AO22: 686046.4 | AP22: 629448.8 | AQ22: 466842.1 | AR22: 316786.6 | AS22: 189725.5 | AT22: 89848.8 | AU22: 0 | AV22: 0
A23: marine_hedged_krw_m_post_origin | D23: 해양 원화 — origin 이후 체결분(백만원) | E23: 0 | F23: 0 | G23: 0 | H23: 0 | I23: 0 | J23: 0 | K23: 0 | L23: 0 | M23: 0 | N23: 0 | O23: 0 | P23: 0 | Q23: 0 | R23: 0 | S23: 0 | T23: 0 | U23: 0 | V23: 0 | W23: 0 | X23: 0 | Y23: 0 | Z23: 0 | AA23: 0 | AB23: 0 | AC23: 0 | AD23: 0 | AE23: 0 | AF23: 0 | AG23: 31845.9 | AH23: 34749.6 | AI23: 33967.5 | AJ23: 34344.9 | AK23: 34722.3 | AL23: 34722.3 | AM23: 34344.9 | AN23: 34344.9 | AO23: 34722.3 | AP23: 34722.3 | AQ23: 33967.5 | AR23: 34344.9 | AS23: 34722.3 | AT23: 34722.3 | AU23: 33967.5 | AV23: 23022.4
A24: target_opm | D24: 타겟 OPM(코호트) | L24: 0.054 | M24: 0.054 | N24: 0.054 | O24: 0.054 | P24: 0.054 | Q24: 0.054 | R24: 0.054 | S24: 0.054 | T24: 0.054 | U24: 0.054 | V24: 0.054 | W24: 0.054 | X24: 0.054 | Y24: 0.054 | Z24: 0.054 | AA24: 0.054 | AB24: 0.0756 | AC24: 0.108 | AD24: 0.108 | AE24: 0.108 | AF24: 0.108 | AG24: 0.108 | AH24: 0.108 | AI24: 0.108 | AJ24: 0.108 | AK24: 0.108 | AL24: 0.108 | AM24: 0.108 | AN24: 0.108 | AO24: 0.108 | AP24: 0.108 | AQ24: 0.108 | AR24: 0.108 | AS24: 0.108 | AT24: 0.108 | AU24: 0.108 | AV24: 0.108
A26: 선표 연결(수식) — 원화(백만원) = 스케줄(백만$) × 포함 × (1 + (캡배율 − 1) × origin 이후) × (헤지비율 × 헤지환율 + (1 − 헤지비율) × 건조시점 환율) | J26: subQ 매출조선에 연결되지 않음()
A27: 헤지비율 | D27: =변수!$D$58 | E27: 변수 3절 '헤지비율' 참조 — 통화선도 공시 없음 → HEDGE 70% 가정(레퍼런스 SLS 시트 HEDGE 행은 미포 65%·삼성重 100% — 그 사이에 둔 설정값). hedge_rate 는 계약별 수주시점 환율로 대체
A28: 헤지환율 방식 | D28: 계약별 수주시점 환율(fx_at_sign)
A29: spot_krw | D29: 건조시점 원/달러(평균) — 변수 환율 행 참조, 변수 범위 밖 분기는 sls spot_assumed | E29: =IFERROR(VLOOKUP(" 원/달러(평균)",환율,MATCH(E$1,변수H,0),0),1193.96) | F29: =IFERROR(VLOOKUP(" 원/달러(평균)",환율,MATCH(F$1,변수H,0),0),1176.23) | G29: =IFERROR(VLOOKUP(" 원/달러(평균)",환율,MATCH(G$1,변수H,0),0),1193.92) | H29: =IFERROR(VLOOKUP(" 원/달러(평균)",환율,MATCH(H$1,변수H,0),0),1219.69) | I29: =IFERROR(VLOOKUP(" 원/달러(평균)",환율,MATCH(I$1,변수H,0),0),1187.81) | J29: =IFERROR(VLOOKUP(" 원/달러(평균)",환율,MATCH(J$1,변수H,0),0),1117.97) | K29: =IFERROR(VLOOKUP(" 원/달러(평균)",환율,MATCH(K$1,변수H,0),0),1114.99) | L29: =IFERROR(VLOOKUP(" 원/달러(평균)",환율,MATCH(L$1,변수H,0),0),1121.13) | M29: =IFERROR(VLOOKUP(" 원/달러(평균)",환율,MATCH(M$1,변수H,0),0),1159.91) | N29: =IFERROR(VLOOKUP(" 원/달러(평균)",환율,MATCH(N$1,변수H,0),0),1183.5) | O29: =IFERROR(VLOOKUP(" 원/달러(평균)",환율,MATCH(O$1,변수H,0),0),1205.78) | P29: =IFERROR(VLOOKUP(" 원/달러(평균)",환율,MATCH(P$1,변수H,0),0),1262.09) | Q29: =IFERROR(VLOOKUP(" 원/달러(평균)",환율,MATCH(Q$1,변수H,0),0),1341.93) | R29: =IFERROR(VLOOKUP(" 원/달러(평균)",환율,MATCH(R$1,변수H,0),0),1360.12) | S29: =IFERROR(VLOOKUP(" 원/달러(평균)",환율,MATCH(S$1,변수H,0),0),1276.95) | T29: =IFERROR(VLOOKUP(" 원/달러(평균)",환율,MATCH(T$1,변수H,0),0),1315.69) | U29: =IFERROR(VLOOKUP(" 원/달러(평균)",환율,MATCH(U$1,변수H,0),0),1313.62) | V29: =IFERROR(VLOOKUP(" 원/달러(평균)",환율,MATCH(V$1,변수H,0),0),1322.01) | W29: =IFERROR(VLOOKUP(" 원/달러(평균)",환율,MATCH(W$1,변수H,0),0),1330.14) | X29: =IFERROR(VLOOKUP(" 원/달러(평균)",환율,MATCH(X$1,변수H,0),0),1371.28) | Y29: =IFERROR(VLOOKUP(" 원/달러(평균)",환율,MATCH(Y$1,변수H,0),0),1356.22) | Z29: =IFERROR(VLOOKUP(" 원/달러(평균)",환율,MATCH(Z$1,변수H,0),0),1396.3) | AA29: =IFERROR(VLOOKUP(" 원/달러(평균)",환율,MATCH(AA$1,변수H,0),0),1452.28) | AB29: =IFERROR(VLOOKUP(" 원/달러(평균)",환율,MATCH(AB$1,변수H,0),0),1398.52) | AC29: =IFERROR(VLOOKUP(" 원/달러(평균)",환율,MATCH(AC$1,변수H,0),0),1386.95) | AD29: =IFERROR(VLOOKUP(" 원/달러(평균)",환율,MATCH(AD$1,변수H,0),0),1449.19) | AE29: =IFERROR(VLOOKUP(" 원/달러(평균)",환율,MATCH(AE$1,변수H,0),0),1466.12) | AF29: =IFERROR(VLOOKUP(" 원/달러(평균)",환율,MATCH(AF$1,변수H,0),0),1501.75) | AG29: =IFERROR(VLOOKUP(" 원/달러(평균)",환율,MATCH(AG$1,변수H,0),0),1418.75) | AH29: =IFERROR(VLOOKUP(" 원/달러(평균)",환율,MATCH(AH$1,변수H,0),0),1345.14) | AI29: =IFERROR(VLOOKUP(" 원/달러(평균)",환율,MATCH(AI$1,변수H,0),0),1341.49) | AJ29: =IFERROR(VLOOKUP(" 원/달러(평균)",환율,MATCH(AJ$1,변수H,0),0),1341.49) | AK29: =IFERROR(VLOOKUP(" 원/달러(평균)",환율,MATCH(AK$1,변수H,0),0),1341.49) | AL29: =IFERROR(VLOOKUP(" 원/달러(평균)",환율,MATCH(AL$1,변수H,0),0),1341.49) | AM29: =IFERROR(VLOOKUP(" 원/달러(평균)",환율,MATCH(AM$1,변수H,0),0),1341.49) | AN29: =IFERROR(VLOOKUP(" 원/달러(평균)",환율,MATCH(AN$1,변수H,0),0),1341.49) | AO29: =IFERROR(VLOOKUP(" 원/달러(평균)",환율,MATCH(AO$1,변수H,0),0),1341.49) | AP29: =IFERROR(VLOOKUP(" 원/달러(평균)",환율,MATCH(AP$1,변수H,0),0),1341.49) | ... AV29: =IFERROR(VLOOKUP(" 원/달러(평균)",환율,MATCH(AV$1,변수H,0),0),1341.49)
A30: after_origin | D30: origin(2026Q2) 이후 분기 = 1 (잔고 캡 배율 적용 구간) | E30: 0 | F30: 0 | G30: 0 | H30: 0 | I30: 0 | J30: 0 | K30: 0 | L30: 0 | M30: 0 | N30: 0 | O30: 0 | P30: 0 | Q30: 0 | R30: 0 | S30: 0 | T30: 0 | U30: 0 | V30: 0 | W30: 0 | X30: 0 | Y30: 0 | Z30: 0 | AA30: 0 | AB30: 0 | AC30: 0 | AD30: 0 | AE30: 0 | AF30: 0 | AG30: 1 | AH30: 1 | AI30: 1 | AJ30: 1 | AK30: 1 | AL30: 1 | AM30: 1 | AN30: 1 | AO30: 1 | AP30: 1 | AQ30: 1 | AR30: 1 | AS30: 1 | AT30: 1 | AU30: 1 | AV30: 1
A32: ① 계약별 매출인식 스케줄(백만$, sls 저장값) | B32: type | C32: ships | D32: name | BJ32: 포함(1/0) | BK32: 헤지환율 | BL32: 캡배율 | BM32: 체결일 | BN32: origin이내 | BO32: 코호트 | BP32: 계약액(백만$) | BQ32: 종료
A33: 20251121800424 | B33: VLCC | C33: 4 | D33: VLCC 4척 | AD33: 16.217 | AE33: 34.752 | AF33: 35.138 | AG33: 35.524 | AH33: 35.524 | AI33: 34.752 | AJ33: 35.138 | AK33: 35.524 | AL33: 35.524 | AM33: 35.138 | AN33: 35.138 | AO33: 35.524 | AP33: 35.524 | AQ33: 34.752 | AR33: 35.138 | AS33: 16.987 | BJ33: 1 | BK33: 1449.19 | BL33: 1 | BM33: 2025-11-20 | BN33: 1 | BO33: ⑤초호황 | BP33: 526.294 | BQ33: 2029-08-13
A34: 20251124800131 | B34: CONT | C34: 6 | D34: 컨테이너선 6척 | AD34: 36.095 | AE34: 79.233 | AF34: 80.113 | AG34: 80.994 | AH34: 80.994 | AI34: 79.233 | AJ34: 80.113 | AK34: 80.994 | AL34: 80.994 | AM34: 80.113 | AN34: 80.113 | AO34: 80.994 | AP34: 80.994 | AQ34: 79.233 | AR34: 26.408 | BJ34: 1 | BK34: 1449.19 | BL34: 1 | BM34: 2025-11-21 | BN34: 1 | BO34: ⑤초호황 | BP34: 1106.618 | BQ34: 2029-04-30
A35: 20251202800104 | B35: LNGC | C35: 1 | D35: LNGC 1척 | AD35: 6.97 | AE35: 20.235 | AF35: 20.459 | AG35: 20.684 | AH35: 20.684 | AI35: 20.235 | AJ35: 20.459 | AK35: 20.684 | AL35: 20.684 | AM35: 20.459 | AN35: 20.459 | AO35: 20.684 | AP35: 20.687 | BJ35: 1 | BK35: 1449.19 | BL35: 1 | BM35: 2025-12-01 | BN35: 1 | BO35: ⑤초호황 | BP35: 253.383 | BQ35: 2028-12-31
A36: 20251215800970 | B36: OTHER | D36: 태안화력 5~8호기 저탄장 옥내화 공사 | E36: 1.437 | F36: 4.722 | G36: 4.671 | H36: 4.671 | I36: 4.722 | J36: 4.722 | K36: 4.619 | L36: 4.671 | M36: 4.722 | N36: 4.722 | O36: 4.619 | P36: 4.671 | Q36: 4.722 | R36: 4.722 | S36: 4.619 | T36: 4.671 | U36: 4.722 | V36: 4.722 | W36: 4.671 | X36: 4.671 | Y36: 4.722 | Z36: 4.722 | AA36: 4.619 | AB36: 4.671 | AC36: 4.722 | AD36: 3.898 | BJ36: 0 | BK36: 1193.96 | BL36: 1 | BM36: 2019-09-03 | BN36: 1 | BP36: 117.843 | BQ36: 2025-12-15
A37: 20251219800421 | B37: LNGC | C37: 3 | D37: LNGC 3척 | AB37: 2.919 | AC37: 53.713 | AD37: 53.713 | AE37: 52.545 | AF37: 53.129 | AG37: 53.713 | AH37: 53.713 | AI37: 52.545 | AJ37: 53.129 | AK37: 53.713 | AL37: 53.713 | AM37: 53.129 | AN37: 53.129 | AO37: 53.713 | AP37: 53.713 | AQ37: 19.262 | BJ37: 1 | BK37: 1360.9 | BL37: 1 | BM37: 2025-06-26 | BN37: 1 | BO37: ⑤초호황 | BP37: 769.491 | BQ37: 2029-02-02
A38: 20251219800433 | B38: CONT | C38: 4 | D38: 컨테이너선 4척 | AD38: 6.232 | AE38: 40.062 | AF38: 40.508 | AG38: 40.953 | AH38: 40.953 | AI38: 40.062 | AJ38: 40.508 | AK38: 40.953 | AL38: 40.953 | AM38: 40.508 | AN38: 40.508 | AO38: 40.953 | AP38: 22.699 | BJ38: 1 | BK38: 1449.19 | BL38: 1 | BM38: 2025-12-18 | BN38: 1 | BO38: ⑤초호황 | BP38: 475.852 | BQ38: 2028-11-20
A39: 20260116800207 | B39: VLGC | C39: 1 | D39: VLGC 1척 | AE39: 10.499 | AF39: 12.571 | AG39: 12.709 | AH39: 12.709 | AI39: 12.433 | AJ39: 12.571 | AK39: 12.709 | AL39: 12.709 | AM39: 12.571 | AN39: 8.427 | BJ39: 1 | BK39: 1466.12 | BL39: 1 | BM39: 2026-01-15 | BN39: 1 | BO39: ⑤초호황 | BP39: 119.908 | BQ39: 2028-05-31
A40: 20260202800947 | B40: LNGC | C40: 1 | D40: LNGC 1척 | AE40: 16.845 | AF40: 25.13 | AG40: 25.406 | AH40: 25.406 | AI40: 24.854 | AJ40: 25.13 | AK40: 25.406 | AL40: 25.406 | AM40: 25.13 | AN40: 25.128 | BJ40: 1 | BK40: 1466.12 | BL40: 1 | BM40: 2026-01-30 | BN40: 1 | BO40: ⑤초호황 | BP40: 243.841 | BQ40: 2028-06-30
A41: 20260304800002 | B41: VLCC | C41: 4 | D41: 157,000 DWT 원유운반선 4척 | AD41: 4.874 | AE41: 31.336 | AF41: 31.684 | AG41: 32.032 | AH41: 32.032 | AI41: 31.336 | AJ41: 31.684 | AK41: 32.032 | AL41: 32.032 | AM41: 31.684 | AN41: 31.684 | AO41: 32.032 | AP41: 10.797 | BJ41: 1 | BK41: 1449.19 | BL41: 1 | BM41: 2025-12-18 | BN41: 1 | BO41: ⑤초호황 | BP41: 365.239 | BQ41: 2028-10-31
A42: 20260306800225 | B42: VLCC | C42: 2 | D42: 157,000 DWT 원유운반선 2척 | AE42: 4.094 | AF42: 13.798 | AG42: 13.949 | AH42: 13.949 | AI42: 13.646 | AJ42: 13.798 | AK42: 13.949 | AL42: 13.949 | AM42: 13.798 | AN42: 13.798 | AO42: 13.949 | AP42: 13.949 | AQ42: 13.646 | AR42: 9.249 | BJ42: 1 | BK42: 1466.12 | BL42: 1 | BM42: 2026-03-05 | BN42: 1 | BO42: ⑤초호황 | BP42: 179.521 | BQ42: 2029-05-31
A43: 20260310800414 | B43: VLGC | C43: 2 | D43: LPGC 2척 | AE43: 5.197 | AF43: 20.561 | AG43: 20.787 | AH43: 20.787 | AI43: 20.335 | AJ43: 20.561 | AK43: 20.787 | AL43: 20.787 | AM43: 20.561 | AN43: 20.561 | AO43: 20.787 | AP43: 20.33 | BJ43: 1 | BK43: 1466.12 | BL43: 1 | BM43: 2026-03-09 | BN43: 1 | BO43: ⑤초호황 | BP43: 232.041 | BQ43: 2028-12-29
A44: 20260403800582 | B44: VLGC | C44: 2 | D44: LPGC 2척 | AF44: 19.162 | AG44: 19.588 | AH44: 19.588 | AI44: 19.162 | AJ44: 19.375 | AK44: 19.588 | AL44: 19.588 | AM44: 19.375 | AN44: 19.375 | AO44: 19.588 | AP44: 19.588 | AQ44: 18.951 | BJ44: 1 | BK44: 1501.75 | BL44: 1 | BM44: 2026-04-02 | BN44: 1 | BO44: ⑤초호황 | BP44: 232.928 | BQ44: 2029-03-30
A45: 20260408800703 | B45: LNGC | C45: 2 | D45: LNGC 2척 | AF45: 34.299 | AG45: 37.123 | AH45: 37.123 | AI45: 36.316 | AJ45: 36.72 | AK45: 37.123 | AL45: 37.123 | AM45: 36.72 | AN45: 36.72 | AO45: 37.123 | AP45: 37.123 | AQ45: 36.316 | AR45: 36.72 | AS45: 36.319 | BJ45: 1 | BK45: 1501.75 | BL45: 1 | BM45: 2026-04-07 | BN45: 1 | BO45: ⑤초호황 | BP45: 512.868 | BQ45: 2029-09-28
A46: 20260416800167 | B46: VLGC | C46: 2 | D46: LPGC 2척 | AF46: 15.981 | AG46: 19.095 | AH46: 19.095 | AI46: 18.68 | AJ46: 18.887 | AK46: 19.095 | AL46: 19.095 | AM46: 18.887 | AN46: 18.887 | AO46: 19.095 | AP46: 19.095 | AQ46: 18.68 | AR46: 6.225 | BJ46: 1 | BK46: 1501.75 | BL46: 1 | BM46: 2026-04-15 | BN46: 1 | BO46: ⑤초호황 | BP46: 230.797 | BQ46: 2029-04-30
A47: 20260513800195 | B47: LNGC | C47: 2 | D47: LNGC 2척 | AF47: 21.318 | AG47: 39.225 | AH47: 39.225 | AI47: 38.373 | AJ47: 38.799 | AK47: 39.225 | AL47: 39.225 | AM47: 38.799 | AN47: 38.799 | AO47: 39.225 | AP47: 39.225 | AQ47: 38.373 | AR47: 38.799 | AS47: 9.809 | BJ47: 1 | BK47: 1501.75 | BL47: 1 | BM47: 2026-05-12 | BN47: 1 | BO47: ⑤초호황 | BP47: 498.419 | BQ47: 2029-07-23
A48: 20260521800360 | B48: VLGC | C48: 6 | D48: VLAC 6척 | AF48: 23.001 | AG48: 50.383 | AH48: 50.383 | AI48: 49.288 | AJ48: 49.836 | AK48: 50.383 | AL48: 50.383 | AM48: 49.836 | AN48: 49.836 | AO48: 50.383 | AP48: 50.383 | AQ48: 49.288 | AR48: 49.836 | AS48: 50.383 | AT48: 44.36 | BJ48: 1 | BK48: 1501.75 | BL48: 1 | BM48: 2026-05-20 | BN48: 1 | BO48: ⑤초호황 | BP48: 717.962 | BQ48: 2029-12-20
A49: 20260629800351 | B49: VLGC | C49: 2 | D49: LPGC 2척 | AF49: 0.948 | AG49: 17.449 | AH49: 17.449 | AI49: 17.07 | AJ49: 17.259 | AK49: 17.449 | AL49: 17.449 | AM49: 17.259 | AN49: 17.259 | AO49: 17.449 | AP49: 17.449 | AQ49: 17.07 | AR49: 17.259 | AS49: 17.449 | AT49: 17.449 | BJ49: 1 | BK49: 1501.75 | BL49: 1 | BM49: 2026-06-26 | BN49: 1 | BO49: ⑤초호황 | BP49: 243.716 | BQ49: 2029-12-31
A50: 20260713800202 | B50: VLGC | C50: 3 | D50: VLAC 3척 | AG50: 22.446 | AH50: 24.88 | AI50: 24.339 | AJ50: 24.61 | AK50: 24.88 | AL50: 24.88 | AM50: 24.61 | AN50: 24.61 | AO50: 24.88 | AP50: 24.88 | AQ50: 24.339 | AR50: 24.61 | AS50: 24.88 | AT50: 24.88 | AU50: 24.339 | AV50: 16.501 | BJ50: 0 | BK50: 1418.75 | BL50: 1 | BM50: 2026-07-10 | BN50: 0 | BO50: ⑤초호황 | BP50: 384.564 | BQ50: 2030-05-31
A51: 20260903800523 | B51: OFFSH | C51: 1 | D51: FPSO Hull 1기 | L51: 29.528 | M51: 50.307 | N51: 50.307 | O51: 49.213 | P51: 49.76 | Q51: 50.307 | R51: 50.307 | S51: 49.213 | T51: 49.76 | U51: 50.307 | V51: 50.307 | W51: 49.76 | X51: 49.76 | Y51: 50.307 | Z51: 50.307 | AA51: 49.213 | AB51: 4.376 | BJ51: 1 | BK51: 1121.4 | BL51: 1 | BM51: 2021-05-10 | BN51: 1 | BO51: ④호황 | BP51: 783.039 | BQ51: 2025-04-08
A52: 20261006800410 | B52: OTHER | D52: 보령화력 1~8호기 저탄장 옥내화 공사 | M52: 3.864 | N52: 12.26 | O52: 11.993 | P52: 12.126 | Q52: 12.26 | R52: 12.26 | S52: 11.993 | T52: 12.126 | U52: 12.26 | V52: 12.26 | W52: 12.126 | X52: 12.126 | Y52: 12.26 | Z52: 12.26 | AA52: 11.993 | AB52: 12.126 | AC52: 12.26 | AD52: 12.26 | AE52: 11.993 | AF52: 12.126 | AG52: 12.26 | AH52: 12.26 | AI52: 11.993 | AJ52: 12.126 | AK52: 8.262 | BJ52: 0 | BK52: 1159.91 | BL52: 1 | BM52: 2021-09-02 | BN52: 1 | BP52: 291.833 | BQ52: 2027-08-31
A54: ② 계약별 원화(백만원, 수식) | B54: type | C54: ships | D54: name
A55: 20251121800424 | B55: VLCC | C55: 4 | D55: VLCC 4척 | AD55: =IFERROR(AD33*$BJ33*(1+($BL33-1)*AD$30)*($D$27*$BK33+(1-$D$27)*AD$29),"") | AE55: =IFERROR(AE33*$BJ33*(1+($BL33-1)*AE$30)*($D$27*$BK33+(1-$D$27)*AE$29),"") | AF55: =IFERROR(AF33*$BJ33*(1+($BL33-1)*AF$30)*($D$27*$BK33+(1-$D$27)*AF$29),"") | AG55: =IFERROR(AG33*$BJ33*(1+($BL33-1)*AG$30)*($D$27*$BK33+(1-$D$27)*AG$29),"") | AH55: =IFERROR(AH33*$BJ33*(1+($BL33-1)*AH$30)*($D$27*$BK33+(1-$D$27)*AH$29),"") | AI55: =IFERROR(AI33*$BJ33*(1+($BL33-1)*AI$30)*($D$27*$BK33+(1-$D$27)*AI$29),"") | AJ55: =IFERROR(AJ33*$BJ33*(1+($BL33-1)*AJ$30)*($D$27*$BK33+(1-$D$27)*AJ$29),"") | AK55: =IFERROR(AK33*$BJ33*(1+($BL33-1)*AK$30)*($D$27*$BK33+(1-$D$27)*AK$29),"") | ... AS55: =IFERROR(AS33*$BJ33*(1+($BL33-1)*AS$30)*($D$27*$BK33+(1-$D$27)*AS$29),"")
A56: 20251124800131 | B56: CONT | C56: 6 | D56: 컨테이너선 6척 | AD56: =IFERROR(AD34*$BJ34*(1+($BL34-1)*AD$30)*($D$27*$BK34+(1-$D$27)*AD$29),"") | AE56: =IFERROR(AE34*$BJ34*(1+($BL34-1)*AE$30)*($D$27*$BK34+(1-$D$27)*AE$29),"") | AF56: =IFERROR(AF34*$BJ34*(1+($BL34-1)*AF$30)*($D$27*$BK34+(1-$D$27)*AF$29),"") | AG56: =IFERROR(AG34*$BJ34*(1+($BL34-1)*AG$30)*($D$27*$BK34+(1-$D$27)*AG$29),"") | AH56: =IFERROR(AH34*$BJ34*(1+($BL34-1)*AH$30)*($D$27*$BK34+(1-$D$27)*AH$29),"") | AI56: =IFERROR(AI34*$BJ34*(1+($BL34-1)*AI$30)*($D$27*$BK34+(1-$D$27)*AI$29),"") | AJ56: =IFERROR(AJ34*$BJ34*(1+($BL34-1)*AJ$30)*($D$27*$BK34+(1-$D$27)*AJ$29),"") | AK56: =IFERROR(AK34*$BJ34*(1+($BL34-1)*AK$30)*($D$27*$BK34+(1-$D$27)*AK$29),"") | ... AR56: =IFERROR(AR34*$BJ34*(1+($BL34-1)*AR$30)*($D$27*$BK34+(1-$D$27)*AR$29),"")
A57: 20251202800104 | B57: LNGC | C57: 1 | D57: LNGC 1척 | AD57: =IFERROR(AD35*$BJ35*(1+($BL35-1)*AD$30)*($D$27*$BK35+(1-$D$27)*AD$29),"") | AE57: =IFERROR(AE35*$BJ35*(1+($BL35-1)*AE$30)*($D$27*$BK35+(1-$D$27)*AE$29),"") | AF57: =IFERROR(AF35*$BJ35*(1+($BL35-1)*AF$30)*($D$27*$BK35+(1-$D$27)*AF$29),"") | AG57: =IFERROR(AG35*$BJ35*(1+($BL35-1)*AG$30)*($D$27*$BK35+(1-$D$27)*AG$29),"") | AH57: =IFERROR(AH35*$BJ35*(1+($BL35-1)*AH$30)*($D$27*$BK35+(1-$D$27)*AH$29),"") | AI57: =IFERROR(AI35*$BJ35*(1+($BL35-1)*AI$30)*($D$27*$BK35+(1-$D$27)*AI$29),"") | AJ57: =IFERROR(AJ35*$BJ35*(1+($BL35-1)*AJ$30)*($D$27*$BK35+(1-$D$27)*AJ$29),"") | AK57: =IFERROR(AK35*$BJ35*(1+($BL35-1)*AK$30)*($D$27*$BK35+(1-$D$27)*AK$29),"") | ... AP57: =IFERROR(AP35*$BJ35*(1+($BL35-1)*AP$30)*($D$27*$BK35+(1-$D$27)*AP$29),"")
A58: 20251215800970 | B58: OTHER | D58: 태안화력 5~8호기 저탄장 옥내화 공사 | E58: =IFERROR(E36*$BJ36*(1+($BL36-1)*E$30)*($D$27*$BK36+(1-$D$27)*E$29),"") | F58: =IFERROR(F36*$BJ36*(1+($BL36-1)*F$30)*($D$27*$BK36+(1-$D$27)*F$29),"") | G58: =IFERROR(G36*$BJ36*(1+($BL36-1)*G$30)*($D$27*$BK36+(1-$D$27)*G$29),"") | H58: =IFERROR(H36*$BJ36*(1+($BL36-1)*H$30)*($D$27*$BK36+(1-$D$27)*H$29),"") | I58: =IFERROR(I36*$BJ36*(1+($BL36-1)*I$30)*($D$27*$BK36+(1-$D$27)*I$29),"") | J58: =IFERROR(J36*$BJ36*(1+($BL36-1)*J$30)*($D$27*$BK36+(1-$D$27)*J$29),"") | K58: =IFERROR(K36*$BJ36*(1+($BL36-1)*K$30)*($D$27*$BK36+(1-$D$27)*K$29),"") | L58: =IFERROR(L36*$BJ36*(1+($BL36-1)*L$30)*($D$27*$BK36+(1-$D$27)*L$29),"") | ... AD58: =IFERROR(AD36*$BJ36*(1+($BL36-1)*AD$30)*($D$27*$BK36+(1-$D$27)*AD$29),"")
A59: 20251219800421 | B59: LNGC | C59: 3 | D59: LNGC 3척 | AB59: =IFERROR(AB37*$BJ37*(1+($BL37-1)*AB$30)*($D$27*$BK37+(1-$D$27)*AB$29),"") | AC59: =IFERROR(AC37*$BJ37*(1+($BL37-1)*AC$30)*($D$27*$BK37+(1-$D$27)*AC$29),"") | AD59: =IFERROR(AD37*$BJ37*(1+($BL37-1)*AD$30)*($D$27*$BK37+(1-$D$27)*AD$29),"") | AE59: =IFERROR(AE37*$BJ37*(1+($BL37-1)*AE$30)*($D$27*$BK37+(1-$D$27)*AE$29),"") | AF59: =IFERROR(AF37*$BJ37*(1+($BL37-1)*AF$30)*($D$27*$BK37+(1-$D$27)*AF$29),"") | AG59: =IFERROR(AG37*$BJ37*(1+($BL37-1)*AG$30)*($D$27*$BK37+(1-$D$27)*AG$29),"") | AH59: =IFERROR(AH37*$BJ37*(1+($BL37-1)*AH$30)*($D$27*$BK37+(1-$D$27)*AH$29),"") | AI59: =IFERROR(AI37*$BJ37*(1+($BL37-1)*AI$30)*($D$27*$BK37+(1-$D$27)*AI$29),"") | ... AQ59: =IFERROR(AQ37*$BJ37*(1+($BL37-1)*AQ$30)*($D$27*$BK37+(1-$D$27)*AQ$29),"")
A60: 20251219800433 | B60: CONT | C60: 4 | D60: 컨테이너선 4척 | AD60: =IFERROR(AD38*$BJ38*(1+($BL38-1)*AD$30)*($D$27*$BK38+(1-$D$27)*AD$29),"") | AE60: =IFERROR(AE38*$BJ38*(1+($BL38-1)*AE$30)*($D$27*$BK38+(1-$D$27)*AE$29),"") | AF60: =IFERROR(AF38*$BJ38*(1+($BL38-1)*AF$30)*($D$27*$BK38+(1-$D$27)*AF$29),"") | AG60: =IFERROR(AG38*$BJ38*(1+($BL38-1)*AG$30)*($D$27*$BK38+(1-$D$27)*AG$29),"") | AH60: =IFERROR(AH38*$BJ38*(1+($BL38-1)*AH$30)*($D$27*$BK38+(1-$D$27)*AH$29),"") | AI60: =IFERROR(AI38*$BJ38*(1+($BL38-1)*AI$30)*($D$27*$BK38+(1-$D$27)*AI$29),"") | AJ60: =IFERROR(AJ38*$BJ38*(1+($BL38-1)*AJ$30)*($D$27*$BK38+(1-$D$27)*AJ$29),"") | AK60: =IFERROR(AK38*$BJ38*(1+($BL38-1)*AK$30)*($D$27*$BK38+(1-$D$27)*AK$29),"") | ... AP60: =IFERROR(AP38*$BJ38*(1+($BL38-1)*AP$30)*($D$27*$BK38+(1-$D$27)*AP$29),"")
A61: 20260116800207 | B61: VLGC | C61: 1 | D61: VLGC 1척 | AE61: =IFERROR(AE39*$BJ39*(1+($BL39-1)*AE$30)*($D$27*$BK39+(1-$D$27)*AE$29),"") | AF61: =IFERROR(AF39*$BJ39*(1+($BL39-1)*AF$30)*($D$27*$BK39+(1-$D$27)*AF$29),"") | AG61: =IFERROR(AG39*$BJ39*(1+($BL39-1)*AG$30)*($D$27*$BK39+(1-$D$27)*AG$29),"") | AH61: =IFERROR(AH39*$BJ39*(1+($BL39-1)*AH$30)*($D$27*$BK39+(1-$D$27)*AH$29),"") | AI61: =IFERROR(AI39*$BJ39*(1+($BL39-1)*AI$30)*($D$27*$BK39+(1-$D$27)*AI$29),"") | AJ61: =IFERROR(AJ39*$BJ39*(1+($BL39-1)*AJ$30)*($D$27*$BK39+(1-$D$27)*AJ$29),"") | AK61: =IFERROR(AK39*$BJ39*(1+($BL39-1)*AK$30)*($D$27*$BK39+(1-$D$27)*AK$29),"") | AL61: =IFERROR(AL39*$BJ39*(1+($BL39-1)*AL$30)*($D$27*$BK39+(1-$D$27)*AL$29),"") | ... AN61: =IFERROR(AN39*$BJ39*(1+($BL39-1)*AN$30)*($D$27*$BK39+(1-$D$27)*AN$29),"")
A62: 20260202800947 | B62: LNGC | C62: 1 | D62: LNGC 1척 | AE62: =IFERROR(AE40*$BJ40*(1+($BL40-1)*AE$30)*($D$27*$BK40+(1-$D$27)*AE$29),"") | AF62: =IFERROR(AF40*$BJ40*(1+($BL40-1)*AF$30)*($D$27*$BK40+(1-$D$27)*AF$29),"") | AG62: =IFERROR(AG40*$BJ40*(1+($BL40-1)*AG$30)*($D$27*$BK40+(1-$D$27)*AG$29),"") | AH62: =IFERROR(AH40*$BJ40*(1+($BL40-1)*AH$30)*($D$27*$BK40+(1-$D$27)*AH$29),"") | AI62: =IFERROR(AI40*$BJ40*(1+($BL40-1)*AI$30)*($D$27*$BK40+(1-$D$27)*AI$29),"") | AJ62: =IFERROR(AJ40*$BJ40*(1+($BL40-1)*AJ$30)*($D$27*$BK40+(1-$D$27)*AJ$29),"") | AK62: =IFERROR(AK40*$BJ40*(1+($BL40-1)*AK$30)*($D$27*$BK40+(1-$D$27)*AK$29),"") | AL62: =IFERROR(AL40*$BJ40*(1+($BL40-1)*AL$30)*($D$27*$BK40+(1-$D$27)*AL$29),"") | ... AN62: =IFERROR(AN40*$BJ40*(1+($BL40-1)*AN$30)*($D$27*$BK40+(1-$D$27)*AN$29),"")
A63: 20260304800002 | B63: VLCC | C63: 4 | D63: 157,000 DWT 원유운반선 4척 | AD63: =IFERROR(AD41*$BJ41*(1+($BL41-1)*AD$30)*($D$27*$BK41+(1-$D$27)*AD$29),"") | AE63: =IFERROR(AE41*$BJ41*(1+($BL41-1)*AE$30)*($D$27*$BK41+(1-$D$27)*AE$29),"") | AF63: =IFERROR(AF41*$BJ41*(1+($BL41-1)*AF$30)*($D$27*$BK41+(1-$D$27)*AF$29),"") | AG63: =IFERROR(AG41*$BJ41*(1+($BL41-1)*AG$30)*($D$27*$BK41+(1-$D$27)*AG$29),"") | AH63: =IFERROR(AH41*$BJ41*(1+($BL41-1)*AH$30)*($D$27*$BK41+(1-$D$27)*AH$29),"") | AI63: =IFERROR(AI41*$BJ41*(1+($BL41-1)*AI$30)*($D$27*$BK41+(1-$D$27)*AI$29),"") | AJ63: =IFERROR(AJ41*$BJ41*(1+($BL41-1)*AJ$30)*($D$27*$BK41+(1-$D$27)*AJ$29),"") | AK63: =IFERROR(AK41*$BJ41*(1+($BL41-1)*AK$30)*($D$27*$BK41+(1-$D$27)*AK$29),"") | ... AP63: =IFERROR(AP41*$BJ41*(1+($BL41-1)*AP$30)*($D$27*$BK41+(1-$D$27)*AP$29),"")
A64: 20260306800225 | B64: VLCC | C64: 2 | D64: 157,000 DWT 원유운반선 2척 | AE64: =IFERROR(AE42*$BJ42*(1+($BL42-1)*AE$30)*($D$27*$BK42+(1-$D$27)*AE$29),"") | AF64: =IFERROR(AF42*$BJ42*(1+($BL42-1)*AF$30)*($D$27*$BK42+(1-$D$27)*AF$29),"") | AG64: =IFERROR(AG42*$BJ42*(1+($BL42-1)*AG$30)*($D$27*$BK42+(1-$D$27)*AG$29),"") | AH64: =IFERROR(AH42*$BJ42*(1+($BL42-1)*AH$30)*($D$27*$BK42+(1-$D$27)*AH$29),"") | AI64: =IFERROR(AI42*$BJ42*(1+($BL42-1)*AI$30)*($D$27*$BK42+(1-$D$27)*AI$29),"") | AJ64: =IFERROR(AJ42*$BJ42*(1+($BL42-1)*AJ$30)*($D$27*$BK42+(1-$D$27)*AJ$29),"") | AK64: =IFERROR(AK42*$BJ42*(1+($BL42-1)*AK$30)*($D$27*$BK42+(1-$D$27)*AK$29),"") | AL64: =IFERROR(AL42*$BJ42*(1+($BL42-1)*AL$30)*($D$27*$BK42+(1-$D$27)*AL$29),"") | ... AR64: =IFERROR(AR42*$BJ42*(1+($BL42-1)*AR$30)*($D$27*$BK42+(1-$D$27)*AR$29),"")
A65: 20260310800414 | B65: VLGC | C65: 2 | D65: LPGC 2척 | AE65: =IFERROR(AE43*$BJ43*(1+($BL43-1)*AE$30)*($D$27*$BK43+(1-$D$27)*AE$29),"") | AF65: =IFERROR(AF43*$BJ43*(1+($BL43-1)*AF$30)*($D$27*$BK43+(1-$D$27)*AF$29),"") | AG65: =IFERROR(AG43*$BJ43*(1+($BL43-1)*AG$30)*($D$27*$BK43+(1-$D$27)*AG$29),"") | AH65: =IFERROR(AH43*$BJ43*(1+($BL43-1)*AH$30)*($D$27*$BK43+(1-$D$27)*AH$29),"") | AI65: =IFERROR(AI43*$BJ43*(1+($BL43-1)*AI$30)*($D$27*$BK43+(1-$D$27)*AI$29),"") | AJ65: =IFERROR(AJ43*$BJ43*(1+($BL43-1)*AJ$30)*($D$27*$BK43+(1-$D$27)*AJ$29),"") | AK65: =IFERROR(AK43*$BJ43*(1+($BL43-1)*AK$30)*($D$27*$BK43+(1-$D$27)*AK$29),"") | AL65: =IFERROR(AL43*$BJ43*(1+($BL43-1)*AL$30)*($D$27*$BK43+(1-$D$27)*AL$29),"") | ... AP65: =IFERROR(AP43*$BJ43*(1+($BL43-1)*AP$30)*($D$27*$BK43+(1-$D$27)*AP$29),"")
A66: 20260403800582 | B66: VLGC | C66: 2 | D66: LPGC 2척 | AF66: =IFERROR(AF44*$BJ44*(1+($BL44-1)*AF$30)*($D$27*$BK44+(1-$D$27)*AF$29),"") | AG66: =IFERROR(AG44*$BJ44*(1+($BL44-1)*AG$30)*($D$27*$BK44+(1-$D$27)*AG$29),"") | AH66: =IFERROR(AH44*$BJ44*(1+($BL44-1)*AH$30)*($D$27*$BK44+(1-$D$27)*AH$29),"") | AI66: =IFERROR(AI44*$BJ44*(1+($BL44-1)*AI$30)*($D$27*$BK44+(1-$D$27)*AI$29),"") | AJ66: =IFERROR(AJ44*$BJ44*(1+($BL44-1)*AJ$30)*($D$27*$BK44+(1-$D$27)*AJ$29),"") | AK66: =IFERROR(AK44*$BJ44*(1+($BL44-1)*AK$30)*($D$27*$BK44+(1-$D$27)*AK$29),"") | AL66: =IFERROR(AL44*$BJ44*(1+($BL44-1)*AL$30)*($D$27*$BK44+(1-$D$27)*AL$29),"") | AM66: =IFERROR(AM44*$BJ44*(1+($BL44-1)*AM$30)*($D$27*$BK44+(1-$D$27)*AM$29),"") | ... AQ66: =IFERROR(AQ44*$BJ44*(1+($BL44-1)*AQ$30)*($D$27*$BK44+(1-$D$27)*AQ$29),"")
A67: 20260408800703 | B67: LNGC | C67: 2 | D67: LNGC 2척 | AF67: =IFERROR(AF45*$BJ45*(1+($BL45-1)*AF$30)*($D$27*$BK45+(1-$D$27)*AF$29),"") | AG67: =IFERROR(AG45*$BJ45*(1+($BL45-1)*AG$30)*($D$27*$BK45+(1-$D$27)*AG$29),"") | AH67: =IFERROR(AH45*$BJ45*(1+($BL45-1)*AH$30)*($D$27*$BK45+(1-$D$27)*AH$29),"") | AI67: =IFERROR(AI45*$BJ45*(1+($BL45-1)*AI$30)*($D$27*$BK45+(1-$D$27)*AI$29),"") | AJ67: =IFERROR(AJ45*$BJ45*(1+($BL45-1)*AJ$30)*($D$27*$BK45+(1-$D$27)*AJ$29),"") | AK67: =IFERROR(AK45*$BJ45*(1+($BL45-1)*AK$30)*($D$27*$BK45+(1-$D$27)*AK$29),"") | AL67: =IFERROR(AL45*$BJ45*(1+($BL45-1)*AL$30)*($D$27*$BK45+(1-$D$27)*AL$29),"") | AM67: =IFERROR(AM45*$BJ45*(1+($BL45-1)*AM$30)*($D$27*$BK45+(1-$D$27)*AM$29),"") | ... AS67: =IFERROR(AS45*$BJ45*(1+($BL45-1)*AS$30)*($D$27*$BK45+(1-$D$27)*AS$29),"")
A68: 20260416800167 | B68: VLGC | C68: 2 | D68: LPGC 2척 | AF68: =IFERROR(AF46*$BJ46*(1+($BL46-1)*AF$30)*($D$27*$BK46+(1-$D$27)*AF$29),"") | AG68: =IFERROR(AG46*$BJ46*(1+($BL46-1)*AG$30)*($D$27*$BK46+(1-$D$27)*AG$29),"") | AH68: =IFERROR(AH46*$BJ46*(1+($BL46-1)*AH$30)*($D$27*$BK46+(1-$D$27)*AH$29),"") | AI68: =IFERROR(AI46*$BJ46*(1+($BL46-1)*AI$30)*($D$27*$BK46+(1-$D$27)*AI$29),"") | AJ68: =IFERROR(AJ46*$BJ46*(1+($BL46-1)*AJ$30)*($D$27*$BK46+(1-$D$27)*AJ$29),"") | AK68: =IFERROR(AK46*$BJ46*(1+($BL46-1)*AK$30)*($D$27*$BK46+(1-$D$27)*AK$29),"") | AL68: =IFERROR(AL46*$BJ46*(1+($BL46-1)*AL$30)*($D$27*$BK46+(1-$D$27)*AL$29),"") | AM68: =IFERROR(AM46*$BJ46*(1+($BL46-1)*AM$30)*($D$27*$BK46+(1-$D$27)*AM$29),"") | ... AR68: =IFERROR(AR46*$BJ46*(1+($BL46-1)*AR$30)*($D$27*$BK46+(1-$D$27)*AR$29),"")
A69: 20260513800195 | B69: LNGC | C69: 2 | D69: LNGC 2척 | AF69: =IFERROR(AF47*$BJ47*(1+($BL47-1)*AF$30)*($D$27*$BK47+(1-$D$27)*AF$29),"") | AG69: =IFERROR(AG47*$BJ47*(1+($BL47-1)*AG$30)*($D$27*$BK47+(1-$D$27)*AG$29),"") | AH69: =IFERROR(AH47*$BJ47*(1+($BL47-1)*AH$30)*($D$27*$BK47+(1-$D$27)*AH$29),"") | AI69: =IFERROR(AI47*$BJ47*(1+($BL47-1)*AI$30)*($D$27*$BK47+(1-$D$27)*AI$29),"") | AJ69: =IFERROR(AJ47*$BJ47*(1+($BL47-1)*AJ$30)*($D$27*$BK47+(1-$D$27)*AJ$29),"") | AK69: =IFERROR(AK47*$BJ47*(1+($BL47-1)*AK$30)*($D$27*$BK47+(1-$D$27)*AK$29),"") | AL69: =IFERROR(AL47*$BJ47*(1+($BL47-1)*AL$30)*($D$27*$BK47+(1-$D$27)*AL$29),"") | AM69: =IFERROR(AM47*$BJ47*(1+($BL47-1)*AM$30)*($D$27*$BK47+(1-$D$27)*AM$29),"") | ... AS69: =IFERROR(AS47*$BJ47*(1+($BL47-1)*AS$30)*($D$27*$BK47+(1-$D$27)*AS$29),"")
A70: 20260521800360 | B70: VLGC | C70: 6 | D70: VLAC 6척 | AF70: =IFERROR(AF48*$BJ48*(1+($BL48-1)*AF$30)*($D$27*$BK48+(1-$D$27)*AF$29),"") | AG70: =IFERROR(AG48*$BJ48*(1+($BL48-1)*AG$30)*($D$27*$BK48+(1-$D$27)*AG$29),"") | AH70: =IFERROR(AH48*$BJ48*(1+($BL48-1)*AH$30)*($D$27*$BK48+(1-$D$27)*AH$29),"") | AI70: =IFERROR(AI48*$BJ48*(1+($BL48-1)*AI$30)*($D$27*$BK48+(1-$D$27)*AI$29),"") | AJ70: =IFERROR(AJ48*$BJ48*(1+($BL48-1)*AJ$30)*($D$27*$BK48+(1-$D$27)*AJ$29),"") | AK70: =IFERROR(AK48*$BJ48*(1+($BL48-1)*AK$30)*($D$27*$BK48+(1-$D$27)*AK$29),"") | AL70: =IFERROR(AL48*$BJ48*(1+($BL48-1)*AL$30)*($D$27*$BK48+(1-$D$27)*AL$29),"") | AM70: =IFERROR(AM48*$BJ48*(1+($BL48-1)*AM$30)*($D$27*$BK48+(1-$D$27)*AM$29),"") | ... AT70: =IFERROR(AT48*$BJ48*(1+($BL48-1)*AT$30)*($D$27*$BK48+(1-$D$27)*AT$29),"")
A71: 20260629800351 | B71: VLGC | C71: 2 | D71: LPGC 2척 | AF71: =IFERROR(AF49*$BJ49*(1+($BL49-1)*AF$30)*($D$27*$BK49+(1-$D$27)*AF$29),"") | AG71: =IFERROR(AG49*$BJ49*(1+($BL49-1)*AG$30)*($D$27*$BK49+(1-$D$27)*AG$29),"") | AH71: =IFERROR(AH49*$BJ49*(1+($BL49-1)*AH$30)*($D$27*$BK49+(1-$D$27)*AH$29),"") | AI71: =IFERROR(AI49*$BJ49*(1+($BL49-1)*AI$30)*($D$27*$BK49+(1-$D$27)*AI$29),"") | AJ71: =IFERROR(AJ49*$BJ49*(1+($BL49-1)*AJ$30)*($D$27*$BK49+(1-$D$27)*AJ$29),"") | AK71: =IFERROR(AK49*$BJ49*(1+($BL49-1)*AK$30)*($D$27*$BK49+(1-$D$27)*AK$29),"") | AL71: =IFERROR(AL49*$BJ49*(1+($BL49-1)*AL$30)*($D$27*$BK49+(1-$D$27)*AL$29),"") | AM71: =IFERROR(AM49*$BJ49*(1+($BL49-1)*AM$30)*($D$27*$BK49+(1-$D$27)*AM$29),"") | ... AT71: =IFERROR(AT49*$BJ49*(1+($BL49-1)*AT$30)*($D$27*$BK49+(1-$D$27)*AT$29),"")
A72: 20260713800202 | B72: VLGC | C72: 3 | D72: VLAC 3척 | AG72: =IFERROR(AG50*$BJ50*(1+($BL50-1)*AG$30)*($D$27*$BK50+(1-$D$27)*AG$29),"") | AH72: =IFERROR(AH50*$BJ50*(1+($BL50-1)*AH$30)*($D$27*$BK50+(1-$D$27)*AH$29),"") | AI72: =IFERROR(AI50*$BJ50*(1+($BL50-1)*AI$30)*($D$27*$BK50+(1-$D$27)*AI$29),"") | AJ72: =IFERROR(AJ50*$BJ50*(1+($BL50-1)*AJ$30)*($D$27*$BK50+(1-$D$27)*AJ$29),"") | AK72: =IFERROR(AK50*$BJ50*(1+($BL50-1)*AK$30)*($D$27*$BK50+(1-$D$27)*AK$29),"") | AL72: =IFERROR(AL50*$BJ50*(1+($BL50-1)*AL$30)*($D$27*$BK50+(1-$D$27)*AL$29),"") | AM72: =IFERROR(AM50*$BJ50*(1+($BL50-1)*AM$30)*($D$27*$BK50+(1-$D$27)*AM$29),"") | AN72: =IFERROR(AN50*$BJ50*(1+($BL50-1)*AN$30)*($D$27*$BK50+(1-$D$27)*AN$29),"") | ... AV72: =IFERROR(AV50*$BJ50*(1+($BL50-1)*AV$30)*($D$27*$BK50+(1-$D$27)*AV$29),"")
A73: 20260903800523 | B73: OFFSH | C73: 1 | D73: FPSO Hull 1기 | L73: =IFERROR(L51*$BJ51*(1+($BL51-1)*L$30)*($D$27*$BK51+(1-$D$27)*L$29),"") | M73: =IFERROR(M51*$BJ51*(1+($BL51-1)*M$30)*($D$27*$BK51+(1-$D$27)*M$29),"") | N73: =IFERROR(N51*$BJ51*(1+($BL51-1)*N$30)*($D$27*$BK51+(1-$D$27)*N$29),"") | O73: =IFERROR(O51*$BJ51*(1+($BL51-1)*O$30)*($D$27*$BK51+(1-$D$27)*O$29),"") | P73: =IFERROR(P51*$BJ51*(1+($BL51-1)*P$30)*($D$27*$BK51+(1-$D$27)*P$29),"") | Q73: =IFERROR(Q51*$BJ51*(1+($BL51-1)*Q$30)*($D$27*$BK51+(1-$D$27)*Q$29),"") | R73: =IFERROR(R51*$BJ51*(1+($BL51-1)*R$30)*($D$27*$BK51+(1-$D$27)*R$29),"") | S73: =IFERROR(S51*$BJ51*(1+($BL51-1)*S$30)*($D$27*$BK51+(1-$D$27)*S$29),"") | ... AB73: =IFERROR(AB51*$BJ51*(1+($BL51-1)*AB$30)*($D$27*$BK51+(1-$D$27)*AB$29),"")
A74: 20261006800410 | B74: OTHER | D74: 보령화력 1~8호기 저탄장 옥내화 공사 | M74: =IFERROR(M52*$BJ52*(1+($BL52-1)*M$30)*($D$27*$BK52+(1-$D$27)*M$29),"") | N74: =IFERROR(N52*$BJ52*(1+($BL52-1)*N$30)*($D$27*$BK52+(1-$D$27)*N$29),"") | O74: =IFERROR(O52*$BJ52*(1+($BL52-1)*O$30)*($D$27*$BK52+(1-$D$27)*O$29),"") | P74: =IFERROR(P52*$BJ52*(1+($BL52-1)*P$30)*($D$27*$BK52+(1-$D$27)*P$29),"") | Q74: =IFERROR(Q52*$BJ52*(1+($BL52-1)*Q$30)*($D$27*$BK52+(1-$D$27)*Q$29),"") | R74: =IFERROR(R52*$BJ52*(1+($BL52-1)*R$30)*($D$27*$BK52+(1-$D$27)*R$29),"") | S74: =IFERROR(S52*$BJ52*(1+($BL52-1)*S$30)*($D$27*$BK52+(1-$D$27)*S$29),"") | T74: =IFERROR(T52*$BJ52*(1+($BL52-1)*T$30)*($D$27*$BK52+(1-$D$27)*T$29),"") | ... AK74: =IFERROR(AK52*$BJ52*(1+($BL52-1)*AK$30)*($D$27*$BK52+(1-$D$27)*AK$29),"")
A75: usd_incl | D75: 포함 계약 스케줄 합(백만$, 캡 배율 전) | E75: =SUMPRODUCT(E33:E52,$BJ$33:$BJ$52) | F75: =SUMPRODUCT(F33:F52,$BJ$33:$BJ$52) | G75: =SUMPRODUCT(G33:G52,$BJ$33:$BJ$52) | H75: =SUMPRODUCT(H33:H52,$BJ$33:$BJ$52) | I75: =SUMPRODUCT(I33:I52,$BJ$33:$BJ$52) | J75: =SUMPRODUCT(J33:J52,$BJ$33:$BJ$52) | K75: =SUMPRODUCT(K33:K52,$BJ$33:$BJ$52) | L75: =SUMPRODUCT(L33:L52,$BJ$33:$BJ$52) | ... AV75: =SUMPRODUCT(AV33:AV52,$BJ$33:$BJ$52)
A76: krw_link | D76: 원화 합계(백만원) — subQ 연결 행 | E76: =SUM(E55:E74) | F76: =SUM(F55:F74) | G76: =SUM(G55:G74) | H76: =SUM(H55:H74) | I76: =SUM(I55:I74) | J76: =SUM(J55:J74) | K76: =SUM(K55:K74) | L76: =SUM(L55:L74) | ... AV76: =SUM(AV55:AV74)
A78: 계약 원장(contracts.json 기반 — counted 아닌 계약 포함)
A79: rcp | B79: type | C79: ships | D79: amt_krw_m | E79: amt_usd_m | F79: fx_at_sign | G79: signed | H79: start | I79: end | J79: cohort | K79: cohort_alt | L79: curve | M79: counted | N79: signed_by_origin | O79: estimated_series
A80: 20251121800424 | B80: VLCC | C80: 4 | D80: 762700 | E80: 526.294 | F80: 1449.19 | G80: 2025-11-20 | H80: 2025-11-20 | I80: 2029-08-13 | J80: ⑤초호황 | K80: ④호황 | L80: linear_progress | M80: TRUE | N80: TRUE | O80: TRUE
A81: 20251124800131 | B81: CONT | C81: 6 | D81: 1603700 | E81: 1106.618 | F81: 1449.19 | G81: 2025-11-21 | H81: 2025-11-21 | I81: 2029-04-30 | J81: ⑤초호황 | K81: ③중마진 | L81: linear_progress | M81: TRUE | N81: TRUE | O81: TRUE
A82: 20251124800132 | B82: CONT | C82: 2 | D82: 534600 | E82: 368.896 | F82: 1449.19 | G82: 2025-11-21 | H82: 2025-11-21 | I82: 2028-07-14 | L82: linear_progress | M82: FALSE | N82: TRUE | O82: TRUE
A83: 20251202800104 | B83: LNGC | C83: 1 | D83: 367200 | E83: 253.383 | F83: 1449.19 | G83: 2025-12-01 | H83: 2025-12-01 | I83: 2028-12-31 | J83: ⑤초호황 | K83: ③중마진 | L83: linear_progress | M83: TRUE | N83: TRUE | O83: FALSE
A84: 20251215800970 | B84: OTHER | D84: 140700 | E84: 117.843 | F84: 1193.96 | G84: 2019-09-03 | H84: 2019-09-03 | I84: 2025-12-15 | L84: linear_progress | M84: TRUE | N84: TRUE | O84: FALSE
A85: 20251219800421 | B85: LNGC | C85: 3 | D85: 1047200 | E85: 769.491 | F85: 1360.9 | G85: 2025-06-26 | H85: 2025-06-26 | I85: 2029-02-02 | J85: ⑤초호황 | K85: ③중마진 | L85: linear_progress | M85: TRUE | N85: TRUE | O85: FALSE
A86: 20251219800433 | B86: CONT | C86: 4 | D86: 689600 | E86: 475.852 | F86: 1449.19 | G86: 2025-12-18 | H86: 2025-12-18 | I86: 2028-11-20 | J86: ⑤초호황 | K86: ②BEP | L86: linear_progress | M86: TRUE | N86: TRUE | O86: TRUE
A87: 20251224800162 | B87: PC | C87: 5 | D87: 375000 | E87: 258.765 | F87: 1449.19 | G87: 2025-12-23 | H87: 2025-12-23 | I87: 2028-07-31 | L87: linear_progress | M87: FALSE | N87: TRUE | O87: TRUE
A88: 20251226800855 | B88: NAVAL | C88: 2 | D88: 844700 | E88: 582.877 | F88: 1449.19 | G88: 2025-12-26 | H88: 2025-12-26 | I88: 2029-12-20 | L88: linear_progress | M88: FALSE | N88: TRUE | O88: FALSE
A89: 20260106800156 | B89: LNGC | C89: 4 | D89: 1499300 | E89: 1022.631 | F89: 1466.12 | G89: 2026-01-05 | H89: 2026-01-05 | I89: 2029-03-27 | L89: linear_progress | M89: FALSE | N89: TRUE | O89: TRUE
A90: 20260116800207 | B90: VLGC | C90: 1 | D90: 175800 | E90: 119.908 | F90: 1466.12 | G90: 2026-01-15 | H90: 2026-01-15 | I90: 2028-05-31 | J90: ⑤초호황 | K90: ③중마진 | L90: linear_progress | M90: TRUE | N90: TRUE | O90: FALSE
A91: 20260120800211 | B91: VLCC | C91: 2 | D91: 481600 | E91: 328.486 | F91: 1466.12 | G91: 2026-01-19 | H91: 2026-01-19 | I91: 2029-06-30 | L91: linear_progress | M91: FALSE | N91: TRUE | O91: FALSE
A92: 20260202800947 | B92: LNGC | C92: 1 | D92: 357500 | E92: 243.841 | F92: 1466.12 | G92: 2026-01-30 | H92: 2026-01-30 | I92: 2028-06-30 | J92: ⑤초호황 | K92: ③중마진 | L92: linear_progress | M92: TRUE | N92: TRUE | O92: TRUE
A93: 20260226800208 | B93: LNGC | C93: 1 | D93: 367800 | E93: 250.866 | F93: 1466.12 | G93: 2026-02-25 | H93: 2026-02-25 | I93: 2028-09-29 | L93: linear_progress | M93: FALSE | N93: TRUE | O93: TRUE
A94: 20260227800230 | B94: CONT | C94: 6 | D94: 372400 | E94: 254.004 | F94: 1466.12 | G94: 2026-02-26 | H94: 2026-02-26 | I94: 2028-06-30 | L94: linear_progress | M94: FALSE | N94: TRUE | O94: TRUE
A95: 20260304800002 | B95: VLCC | C95: 4 | D95: 529300 | E95: 365.239 | F95: 1449.19 | G95: 2025-12-18 | H95: 2025-12-18 | I95: 2028-10-31 | J95: ⑤초호황 | K95: ③중마진 | L95: linear_progress | M95: TRUE | N95: TRUE | O95: TRUE
A96: 20260305800849 | B96: LNGC | C96: 4 | D96: 1487200 | E96: 1014.378 | F96: 1466.12 | G96: 2026-03-04 | H96: 2026-03-04 | I96: 2029-11-30 | L96: linear_progress | M96: FALSE | N96: TRUE | O96: TRUE
A97: 20260306800225 | B97: VLCC | C97: 2 | D97: 263200 | E97: 179.521 | F97: 1466.12 | G97: 2026-03-05 | H97: 2026-03-05 | I97: 2029-05-31 | J97: ⑤초호황 | K97: ③중마진 | L97: linear_progress | M97: TRUE | N97: TRUE | O97: FALSE
A98: 20260310800414 | B98: VLGC | C98: 2 | D98: 340200 | E98: 232.041 | F98: 1466.12 | G98: 2026-03-09 | H98: 2026-03-09 | I98: 2028-12-29 | J98: ⑤초호황 | K98: ③중마진 | L98: linear_progress | M98: TRUE | N98: TRUE | O98: TRUE
A99: 20260316800234 | B99: CONT | C99: 10 | D99: 823700 | E99: 561.823 | F99: 1466.12 | G99: 2026-03-13 | H99: 2026-03-13 | I99: 2028-12-31 | L99: linear_progress | M99: FALSE | N99: TRUE | O99: TRUE
A100: 20260403800582 | B100: VLGC | C100: 2 | D100: 349800 | E100: 232.928 | F100: 1501.75 | G100: 2026-04-02 | H100: 2026-04-02 | I100: 2029-03-30 | J100: ⑤초호황 | K100: ③중마진 | L100: linear_progress | M100: TRUE | N100: TRUE | O100: FALSE
A101: 20260403800587 | B101: PC | C101: 8 | D101: 611700 | E101: 407.325 | F101: 1501.75 | G101: 2026-04-02 | H101: 2026-04-02 | I101: 2029-05-31 | L101: linear_progress | M101: FALSE | N101: TRUE | O101: TRUE
A102: 20260408800703 | B102: LNGC | C102: 2 | D102: 770200 | E102: 512.868 | F102: 1501.75 | G102: 2026-04-07 | H102: 2026-04-07 | I102: 2029-09-28 | J102: ⑤초호황 | K102: ③중마진 | L102: linear_progress | M102: TRUE | N102: TRUE | O102: TRUE
A103: 20260416800167 | B103: VLGC | C103: 2 | D103: 346600 | E103: 230.797 | F103: 1501.75 | G103: 2026-04-15 | H103: 2026-04-15 | I103: 2029-04-30 | J103: ⑤초호황 | K103: ③중마진 | L103: linear_progress | M103: TRUE | N103: TRUE | O103: TRUE
A104: 20260417800196 | B104: VLGC | C104: 4 | D104: 674700 | E104: 449.276 | F104: 1501.75 | G104: 2026-04-16 | H104: 2026-04-16 | I104: 2029-11-30 | L104: linear_progress | M104: FALSE | N104: TRUE | O104: TRUE
...

Sheet 시나리오
C1: 신규수주 시나리오(억원) — subQ 기준값 ± (시나리오 신규 − base 신규) × OPM | E1: 3Q26 | F1: 4Q26 | G1: 2026 | H1: 1Q27 | I1: 2Q27 | J1: 3Q27 | K1: 4Q27 | L1: 2027 | M1: 1Q28 | N1: 2Q28 | O1: 3Q28 | P1: 4Q28 | Q1: 2028
A2: 출처: HD현대重(329180) 모델 scenarios 의 new_order_revenue × 연결/자회사 비율 1.410 · calibrated=False · 행(subQ)에 포함된 시나리오: base. 보수/낙관/기존만 은 합산하지 않는다. 모델 산출값 — 목표주가·추천 아님
A3: 매출 = 기존(선표+잔고 소진+기타) + 시나리오 신규수주 매출; 영업이익 = 행 영업이익 + (시나리오 신규 − base 신규) × base OPM 경로. 보수/낙관·existing_only 는 행에 합산하지 않음(base 는 행과 동일). 모델 산출값 — 목표주가·추천 아님 | E3: 1 | F3: 2 | G3: 3 | H3: 4 | I3: 5 | J3: 6 | K3: 7 | L3: 8 | M3: 9 | N3: 10 | O3: 11 | P3: 12 | Q3: 13
E4: 2026.09 | F4: 2026.12 | G4: 2026.12A | H4: 2027.03 | I4: 2027.06 | J4: 2027.09 | K4: 2027.12 | L4: 2027.12A | M4: 2028.03 | N4: 2028.06 | O4: 2028.09 | P4: 2028.12 | Q4: 2028.12A
A5: base | D5: 기준(base — subQ 행에 포함) — 행에 포함
A6: scn:base:신규수주매출 | C6: 억원 | D6: 신규수주 매출(억원) — 패널 값(노란, 가정) | E6: 0 | F6: 1006.48 | G6: =SUM(E6:F6) | H6: 4164.54 | I6: 9391.61 | J6: 16168.84 | K6: 23977.29 | L6: =SUM(H6:K6) | M6: 32298.09 | N6: 40612.33 | O6: 48401.1 | P6: 55145.52 | Q6: =SUM(M6:P6)
A7: scn:base:매출액 | C7: 억원 | D7: 매출액 = subQ 매출액 − base 신규 + 이 시나리오 신규 | E7: =IFERROR(subQ!AC5-E6+E6,"") | F7: =IFERROR(subQ!AD5-F6+F6,"") | G7: =IFERROR(SUM(E7:F7)+subQ!AA5+subQ!AB5,"") | H7: =IFERROR(subQ!AF5-H6+H6,"") | I7: =IFERROR(subQ!AG5-I6+I6,"") | J7: =IFERROR(subQ!AH5-J6+J6,"") | K7: =IFERROR(subQ!AI5-K6+K6,"") | L7: =IFERROR(SUM(H7:K7),"") | M7: =IFERROR(subQ!AK5-M6+M6,"") | N7: =IFERROR(subQ!AL5-N6+N6,"") | O7: =IFERROR(subQ!AM5-O6+O6,"") | P7: =IFERROR(subQ!AN5-P6+P6,"") | Q7: =IFERROR(SUM(M7:P7),"")
A8: scn:base:영업이익 | C8: 억원 | D8: 영업이익 = subQ 영업이익 + (이 시나리오 신규 − base 신규) × OPM(변수 드라이버) | E8: =IFERROR(subQ!AC9+(E6-E6)*변수!AC23,"") | F8: =IFERROR(subQ!AD9+(F6-F6)*변수!AD23,"") | G8: =IFERROR(SUM(E8:F8)+subQ!AA9+subQ!AB9,"") | H8: =IFERROR(subQ!AF9+(H6-H6)*변수!AF23,"") | I8: =IFERROR(subQ!AG9+(I6-I6)*변수!AG23,"") | J8: =IFERROR(subQ!AH9+(J6-J6)*변수!AH23,"") | K8: =IFERROR(subQ!AI9+(K6-K6)*변수!AI23,"") | L8: =IFERROR(SUM(H8:K8),"") | M8: =IFERROR(subQ!AK9+(M6-M6)*변수!AK23,"") | N8: =IFERROR(subQ!AL9+(N6-N6)*변수!AL23,"") | O8: =IFERROR(subQ!AM9+(O6-O6)*변수!AM23,"") | P8: =IFERROR(subQ!AN9+(P6-P6)*변수!AN23,"") | Q8: =IFERROR(SUM(M8:P8),"")
A9: scn:base:OPM | C9: % | D9: OPM | E9: =IFERROR(E8/E7,"") | F9: =IFERROR(F8/F7,"") | G9: =IFERROR(G8/G7,"") | H9: =IFERROR(H8/H7,"") | I9: =IFERROR(I8/I7,"") | J9: =IFERROR(J8/J7,"") | K9: =IFERROR(K8/K7,"") | L9: =IFERROR(L8/L7,"") | ... Q9: =IFERROR(Q8/Q7,"")
A11: existing_only | D11: 기존 잔고만(신규수주 0)
A12: scn:existing_only:신규수주매출 | C12: 억원 | D12: 신규수주 매출(억원) — 패널 값(노란, 가정) | E12: 0 | F12: 0 | G12: =SUM(E12:F12) | H12: 0 | I12: 0 | J12: 0 | K12: 0 | L12: =SUM(H12:K12) | M12: 0 | N12: 0 | O12: 0 | P12: 0 | Q12: =SUM(M12:P12)
A13: scn:existing_only:매출액 | C13: 억원 | D13: 매출액 = subQ 매출액 − base 신규 + 이 시나리오 신규 | E13: =IFERROR(subQ!AC5-E6+E12,"") | F13: =IFERROR(subQ!AD5-F6+F12,"") | G13: =IFERROR(SUM(E13:F13)+subQ!AA5+subQ!AB5,"") | H13: =IFERROR(subQ!AF5-H6+H12,"") | I13: =IFERROR(subQ!AG5-I6+I12,"") | J13: =IFERROR(subQ!AH5-J6+J12,"") | K13: =IFERROR(subQ!AI5-K6+K12,"") | L13: =IFERROR(SUM(H13:K13),"") | M13: =IFERROR(subQ!AK5-M6+M12,"") | N13: =IFERROR(subQ!AL5-N6+N12,"") | O13: =IFERROR(subQ!AM5-O6+O12,"") | P13: =IFERROR(subQ!AN5-P6+P12,"") | Q13: =IFERROR(SUM(M13:P13),"")
A14: scn:existing_only:영업이익 | C14: 억원 | D14: 영업이익 = subQ 영업이익 + (이 시나리오 신규 − base 신규) × OPM(변수 드라이버) | E14: =IFERROR(subQ!AC9+(E12-E6)*변수!AC23,"") | F14: =IFERROR(subQ!AD9+(F12-F6)*변수!AD23,"") | G14: =IFERROR(SUM(E14:F14)+subQ!AA9+subQ!AB9,"") | H14: =IFERROR(subQ!AF9+(H12-H6)*변수!AF23,"") | I14: =IFERROR(subQ!AG9+(I12-I6)*변수!AG23,"") | J14: =IFERROR(subQ!AH9+(J12-J6)*변수!AH23,"") | K14: =IFERROR(subQ!AI9+(K12-K6)*변수!AI23,"") | L14: =IFERROR(SUM(H14:K14),"") | M14: =IFERROR(subQ!AK9+(M12-M6)*변수!AK23,"") | N14: =IFERROR(subQ!AL9+(N12-N6)*변수!AL23,"") | O14: =IFERROR(subQ!AM9+(O12-O6)*변수!AM23,"") | P14: =IFERROR(subQ!AN9+(P12-P6)*변수!AN23,"") | Q14: =IFERROR(SUM(M14:P14),"")
A15: scn:existing_only:OPM | C15: % | D15: OPM | E15: =IFERROR(E14/E13,"") | F15: =IFERROR(F14/F13,"") | G15: =IFERROR(G14/G13,"") | H15: =IFERROR(H14/H13,"") | I15: =IFERROR(I14/I13,"") | J15: =IFERROR(J14/J13,"") | K15: =IFERROR(K14/K13,"") | L15: =IFERROR(L14/L13,"") | ... Q15: =IFERROR(Q14/Q13,"")
A17: conservative | D17: 보수
A18: scn:conservative:신규수주매출 | C18: 억원 | D18: 신규수주 매출(억원) — 패널 값(노란, 가정) | E18: 0 | F18: 614.73 | G18: =SUM(E18:F18) | H18: 2695.64 | I18: 6306.65 | J18: 11074.16 | K18: 16624.54 | L18: =SUM(H18:K18) | M18: 22584.18 | N18: 28579.5 | O18: 34236.87 | P18: 39182.67 | Q18: =SUM(M18:P18)
A19: scn:conservative:매출액 | C19: 억원 | D19: 매출액 = subQ 매출액 − base 신규 + 이 시나리오 신규 | E19: =IFERROR(subQ!AC5-E6+E18,"") | F19: =IFERROR(subQ!AD5-F6+F18,"") | G19: =IFERROR(SUM(E19:F19)+subQ!AA5+subQ!AB5,"") | H19: =IFERROR(subQ!AF5-H6+H18,"") | I19: =IFERROR(subQ!AG5-I6+I18,"") | J19: =IFERROR(subQ!AH5-J6+J18,"") | K19: =IFERROR(subQ!AI5-K6+K18,"") | L19: =IFERROR(SUM(H19:K19),"") | M19: =IFERROR(subQ!AK5-M6+M18,"") | N19: =IFERROR(subQ!AL5-N6+N18,"") | O19: =IFERROR(subQ!AM5-O6+O18,"") | P19: =IFERROR(subQ!AN5-P6+P18,"") | Q19: =IFERROR(SUM(M19:P19),"")
A20: scn:conservative:영업이익 | C20: 억원 | D20: 영업이익 = subQ 영업이익 + (이 시나리오 신규 − base 신규) × OPM(변수 드라이버) | E20: =IFERROR(subQ!AC9+(E18-E6)*변수!AC23,"") | F20: =IFERROR(subQ!AD9+(F18-F6)*변수!AD23,"") | G20: =IFERROR(SUM(E20:F20)+subQ!AA9+subQ!AB9,"") | H20: =IFERROR(subQ!AF9+(H18-H6)*변수!AF23,"") | I20: =IFERROR(subQ!AG9+(I18-I6)*변수!AG23,"") | J20: =IFERROR(subQ!AH9+(J18-J6)*변수!AH23,"") | K20: =IFERROR(subQ!AI9+(K18-K6)*변수!AI23,"") | L20: =IFERROR(SUM(H20:K20),"") | M20: =IFERROR(subQ!AK9+(M18-M6)*변수!AK23,"") | N20: =IFERROR(subQ!AL9+(N18-N6)*변수!AL23,"") | O20: =IFERROR(subQ!AM9+(O18-O6)*변수!AM23,"") | P20: =IFERROR(subQ!AN9+(P18-P6)*변수!AN23,"") | Q20: =IFERROR(SUM(M20:P20),"")
A21: scn:conservative:OPM | C21: % | D21: OPM | E21: =IFERROR(E20/E19,"") | F21: =IFERROR(F20/F19,"") | G21: =IFERROR(G20/G19,"") | H21: =IFERROR(H20/H19,"") | I21: =IFERROR(I20/I19,"") | J21: =IFERROR(J20/J19,"") | K21: =IFERROR(K20/K19,"") | L21: =IFERROR(L20/L19,"") | ... Q21: =IFERROR(Q20/Q19,"")
A23: optimistic | D23: 낙관
A24: scn:optimistic:신규수주매출 | C24: 억원 | D24: 신규수주 매출(억원) — 패널 값(노란, 가정) | E24: 0 | F24: 1762.6 | G24: =SUM(E24:F24) | H24: 7000.62 | I24: 15350.03 | J24: 26011.72 | K24: 38186.66 | L24: =SUM(H24:K24) | M24: 51075.78 | N24: 63880.01 | O24: 75800.27 | P24: 86037.53 | Q24: =SUM(M24:P24)
A25: scn:optimistic:매출액 | C25: 억원 | D25: 매출액 = subQ 매출액 − base 신규 + 이 시나리오 신규 | E25: =IFERROR(subQ!AC5-E6+E24,"") | F25: =IFERROR(subQ!AD5-F6+F24,"") | G25: =IFERROR(SUM(E25:F25)+subQ!AA5+subQ!AB5,"") | H25: =IFERROR(subQ!AF5-H6+H24,"") | I25: =IFERROR(subQ!AG5-I6+I24,"") | J25: =IFERROR(subQ!AH5-J6+J24,"") | K25: =IFERROR(subQ!AI5-K6+K24,"") | L25: =IFERROR(SUM(H25:K25),"") | M25: =IFERROR(subQ!AK5-M6+M24,"") | N25: =IFERROR(subQ!AL5-N6+N24,"") | O25: =IFERROR(subQ!AM5-O6+O24,"") | P25: =IFERROR(subQ!AN5-P6+P24,"") | Q25: =IFERROR(SUM(M25:P25),"")
A26: scn:optimistic:영업이익 | C26: 억원 | D26: 영업이익 = subQ 영업이익 + (이 시나리오 신규 − base 신규) × OPM(변수 드라이버) | E26: =IFERROR(subQ!AC9+(E24-E6)*변수!AC23,"") | F26: =IFERROR(subQ!AD9+(F24-F6)*변수!AD23,"") | G26: =IFERROR(SUM(E26:F26)+subQ!AA9+subQ!AB9,"") | H26: =IFERROR(subQ!AF9+(H24-H6)*변수!AF23,"") | I26: =IFERROR(subQ!AG9+(I24-I6)*변수!AG23,"") | J26: =IFERROR(subQ!AH9+(J24-J6)*변수!AH23,"") | K26: =IFERROR(subQ!AI9+(K24-K6)*변수!AI23,"") | L26: =IFERROR(SUM(H26:K26),"") | M26: =IFERROR(subQ!AK9+(M24-M6)*변수!AK23,"") | N26: =IFERROR(subQ!AL9+(N24-N6)*변수!AL23,"") | O26: =IFERROR(subQ!AM9+(O24-O6)*변수!AM23,"") | P26: =IFERROR(subQ!AN9+(P24-P6)*변수!AN23,"") | Q26: =IFERROR(SUM(M26:P26),"")
A27: scn:optimistic:OPM | C27: % | D27: OPM | E27: =IFERROR(E26/E25,"") | F27: =IFERROR(F26/F25,"") | G27: =IFERROR(G26/G25,"") | H27: =IFERROR(H26/H25,"") | I27: =IFERROR(I26/I25,"") | J27: =IFERROR(J26/J25,"") | K27: =IFERROR(K26/K25,"") | L27: =IFERROR(L26/L25,"") | ... Q27: =IFERROR(Q26/Q25,"")

Sheet 분기
C1: 이름: 분기H — subQ 를 이름으로 VLOOKUP(억원) | E1: 4Q21 | F1: 1Q22 | G1: 2Q22 | H1: 3Q22 | I1: 4Q22 | J1: 1Q23 | K1: 2Q23 | L1: 3Q23 | M1: 4Q23 | N1: 1Q24 | O1: 2Q24 | P1: 3Q24 | Q1: 4Q24 | R1: 1Q25 | S1: 2Q25 | T1: 3Q25 | U1: 4Q25 | V1: 1Q26 | W1: 2Q26 | X1: 3Q26 | Y1: 4Q26 | Z1: 1Q27 | AA1: 2Q27 | AB1: 3Q27 | AC1: 4Q27 | AD1: 1Q28 | AE1: 2Q28 | AF1: 3Q28 | AG1: 4Q28
C2: 종가: | D2: =변수!D44
C3: 기준일: | D3: 20261012 | E3: 1 | F3: 2 | G3: 3 | H3: 4 | I3: 5 | J3: 6 | K3: 7 | L3: 8 | M3: 9 | N3: 10 | O3: 11 | P3: 12 | Q3: 13 | R3: 14 | S3: 15 | T3: 16 | U3: 17 | V3: 18 | W3: 19 | X3: 20 | Y3: 21 | Z3: 22 | AA3: 23 | AB3: 24 | AC3: 25 | AD3: 26 | AE3: 27 | AF3: 28 | AG3: 29
E4: 2021.12 | F4: 2022.03 | G4: 2022.06 | H4: 2022.09 | I4: 2022.12 | J4: 2023.03 | K4: 2023.06 | L4: 2023.09 | M4: 2023.12 | N4: 2024.03 | O4: 2024.06 | P4: 2024.09 | Q4: 2024.12 | R4: 2025.03 | S4: 2025.06 | T4: 2025.09 | U4: 2025.12 | V4: 2026.03 | W4: 2026.06 | X4: 2026.09 | Y4: 2026.12 | Z4: 2027.03 | AA4: 2027.06 | AB4: 2027.09 | AC4: 2027.12 | AD4: 2028.03 | AE4: 2028.06 | AF4: 2028.09 | AG4: 2028.12
A5: 매출액 | D5: 매출액 | E5: =IFERROR(VLOOKUP($A5,subQ,MATCH(E$1,SUBQH,0),0),"") | F5: =IFERROR(VLOOKUP($A5,subQ,MATCH(F$1,SUBQH,0),0),"") | G5: =IFERROR(VLOOKUP($A5,subQ,MATCH(G$1,SUBQH,0),0),"") | H5: =IFERROR(VLOOKUP($A5,subQ,MATCH(H$1,SUBQH,0),0),"") | I5: =IFERROR(VLOOKUP($A5,subQ,MATCH(I$1,SUBQH,0),0),"") | J5: =IFERROR(VLOOKUP($A5,subQ,MATCH(J$1,SUBQH,0),0),"") | K5: =IFERROR(VLOOKUP($A5,subQ,MATCH(K$1,SUBQH,0),0),"") | L5: =IFERROR(VLOOKUP($A5,subQ,MATCH(L$1,SUBQH,0),0),"") | ... AG5: =IFERROR(VLOOKUP($A5,subQ,MATCH(AG$1,SUBQH,0),0),"")
A6: 매출원가 | D6: 매출원가 | E6: =IFERROR(VLOOKUP($A6,subQ,MATCH(E$1,SUBQH,0),0),"") | F6: =IFERROR(VLOOKUP($A6,subQ,MATCH(F$1,SUBQH,0),0),"") | G6: =IFERROR(VLOOKUP($A6,subQ,MATCH(G$1,SUBQH,0),0),"") | H6: =IFERROR(VLOOKUP($A6,subQ,MATCH(H$1,SUBQH,0),0),"") | I6: =IFERROR(VLOOKUP($A6,subQ,MATCH(I$1,SUBQH,0),0),"") | J6: =IFERROR(VLOOKUP($A6,subQ,MATCH(J$1,SUBQH,0),0),"") | K6: =IFERROR(VLOOKUP($A6,subQ,MATCH(K$1,SUBQH,0),0),"") | L6: =IFERROR(VLOOKUP($A6,subQ,MATCH(L$1,SUBQH,0),0),"") | ... AG6: =IFERROR(VLOOKUP($A6,subQ,MATCH(AG$1,SUBQH,0),0),"")
A7: 매출총이익 | D7: 매출총이익 | E7: =IFERROR(VLOOKUP($A7,subQ,MATCH(E$1,SUBQH,0),0),"") | F7: =IFERROR(VLOOKUP($A7,subQ,MATCH(F$1,SUBQH,0),0),"") | G7: =IFERROR(VLOOKUP($A7,subQ,MATCH(G$1,SUBQH,0),0),"") | H7: =IFERROR(VLOOKUP($A7,subQ,MATCH(H$1,SUBQH,0),0),"") | I7: =IFERROR(VLOOKUP($A7,subQ,MATCH(I$1,SUBQH,0),0),"") | J7: =IFERROR(VLOOKUP($A7,subQ,MATCH(J$1,SUBQH,0),0),"") | K7: =IFERROR(VLOOKUP($A7,subQ,MATCH(K$1,SUBQH,0),0),"") | L7: =IFERROR(VLOOKUP($A7,subQ,MATCH(L$1,SUBQH,0),0),"") | ... AG7: =IFERROR(VLOOKUP($A7,subQ,MATCH(AG$1,SUBQH,0),0),"")
A8: 판관비 | D8: 판매비와관리비 | E8: =IFERROR(VLOOKUP($A8,subQ,MATCH(E$1,SUBQH,0),0),"") | F8: =IFERROR(VLOOKUP($A8,subQ,MATCH(F$1,SUBQH,0),0),"") | G8: =IFERROR(VLOOKUP($A8,subQ,MATCH(G$1,SUBQH,0),0),"") | H8: =IFERROR(VLOOKUP($A8,subQ,MATCH(H$1,SUBQH,0),0),"") | I8: =IFERROR(VLOOKUP($A8,subQ,MATCH(I$1,SUBQH,0),0),"") | J8: =IFERROR(VLOOKUP($A8,subQ,MATCH(J$1,SUBQH,0),0),"") | K8: =IFERROR(VLOOKUP($A8,subQ,MATCH(K$1,SUBQH,0),0),"") | L8: =IFERROR(VLOOKUP($A8,subQ,MATCH(L$1,SUBQH,0),0),"") | ... AG8: =IFERROR(VLOOKUP($A8,subQ,MATCH(AG$1,SUBQH,0),0),"")
A9: 영업이익 | D9: 영업이익 | E9: =IFERROR(VLOOKUP($A9,subQ,MATCH(E$1,SUBQH,0),0),"") | F9: =IFERROR(VLOOKUP($A9,subQ,MATCH(F$1,SUBQH,0),0),"") | G9: =IFERROR(VLOOKUP($A9,subQ,MATCH(G$1,SUBQH,0),0),"") | H9: =IFERROR(VLOOKUP($A9,subQ,MATCH(H$1,SUBQH,0),0),"") | I9: =IFERROR(VLOOKUP($A9,subQ,MATCH(I$1,SUBQH,0),0),"") | J9: =IFERROR(VLOOKUP($A9,subQ,MATCH(J$1,SUBQH,0),0),"") | K9: =IFERROR(VLOOKUP($A9,subQ,MATCH(K$1,SUBQH,0),0),"") | L9: =IFERROR(VLOOKUP($A9,subQ,MATCH(L$1,SUBQH,0),0),"") | ... AG9: =IFERROR(VLOOKUP($A9,subQ,MATCH(AG$1,SUBQH,0),0),"")
A10: OPM | D10: 영업이익률 | E10: =IFERROR(VLOOKUP($A10,subQ,MATCH(E$1,SUBQH,0),0),"") | F10: =IFERROR(VLOOKUP($A10,subQ,MATCH(F$1,SUBQH,0),0),"") | G10: =IFERROR(VLOOKUP($A10,subQ,MATCH(G$1,SUBQH,0),0),"") | H10: =IFERROR(VLOOKUP($A10,subQ,MATCH(H$1,SUBQH,0),0),"") | I10: =IFERROR(VLOOKUP($A10,subQ,MATCH(I$1,SUBQH,0),0),"") | J10: =IFERROR(VLOOKUP($A10,subQ,MATCH(J$1,SUBQH,0),0),"") | K10: =IFERROR(VLOOKUP($A10,subQ,MATCH(K$1,SUBQH,0),0),"") | L10: =IFERROR(VLOOKUP($A10,subQ,MATCH(L$1,SUBQH,0),0),"") | ... AG10: =IFERROR(VLOOKUP($A10,subQ,MATCH(AG$1,SUBQH,0),0),"")
A11: 금융손익 | D11: 금융손익(이자·환 포함) | E11: =IFERROR(VLOOKUP($A11,subQ,MATCH(E$1,SUBQH,0),0),"") | F11: =IFERROR(VLOOKUP($A11,subQ,MATCH(F$1,SUBQH,0),0),"") | G11: =IFERROR(VLOOKUP($A11,subQ,MATCH(G$1,SUBQH,0),0),"") | H11: =IFERROR(VLOOKUP($A11,subQ,MATCH(H$1,SUBQH,0),0),"") | I11: =IFERROR(VLOOKUP($A11,subQ,MATCH(I$1,SUBQH,0),0),"") | J11: =IFERROR(VLOOKUP($A11,subQ,MATCH(J$1,SUBQH,0),0),"") | K11: =IFERROR(VLOOKUP($A11,subQ,MATCH(K$1,SUBQH,0),0),"") | L11: =IFERROR(VLOOKUP($A11,subQ,MATCH(L$1,SUBQH,0),0),"") | ... AG11: =IFERROR(VLOOKUP($A11,subQ,MATCH(AG$1,SUBQH,0),0),"")
A12: 이자손익 | D12: 이자손익(이자수익 − 이자비용) | E12: =IFERROR(VLOOKUP($A12,subQ,MATCH(E$1,SUBQH,0),0),"") | F12: =IFERROR(VLOOKUP($A12,subQ,MATCH(F$1,SUBQH,0),0),"") | G12: =IFERROR(VLOOKUP($A12,subQ,MATCH(G$1,SUBQH,0),0),"") | H12: =IFERROR(VLOOKUP($A12,subQ,MATCH(H$1,SUBQH,0),0),"") | I12: =IFERROR(VLOOKUP($A12,subQ,MATCH(I$1,SUBQH,0),0),"") | J12: =IFERROR(VLOOKUP($A12,subQ,MATCH(J$1,SUBQH,0),0),"") | K12: =IFERROR(VLOOKUP($A12,subQ,MATCH(K$1,SUBQH,0),0),"") | L12: =IFERROR(VLOOKUP($A12,subQ,MATCH(L$1,SUBQH,0),0),"") | ... AG12: =IFERROR(VLOOKUP($A12,subQ,MATCH(AG$1,SUBQH,0),0),"")
A13: 외환손익 | D13: 외환손익(실적만; 추정 환효과는 환관련손익) | E13: =IFERROR(VLOOKUP($A13,subQ,MATCH(E$1,SUBQH,0),0),"") | F13: =IFERROR(VLOOKUP($A13,subQ,MATCH(F$1,SUBQH,0),0),"") | G13: =IFERROR(VLOOKUP($A13,subQ,MATCH(G$1,SUBQH,0),0),"") | H13: =IFERROR(VLOOKUP($A13,subQ,MATCH(H$1,SUBQH,0),0),"") | I13: =IFERROR(VLOOKUP($A13,subQ,MATCH(I$1,SUBQH,0),0),"") | J13: =IFERROR(VLOOKUP($A13,subQ,MATCH(J$1,SUBQH,0),0),"") | K13: =IFERROR(VLOOKUP($A13,subQ,MATCH(K$1,SUBQH,0),0),"") | L13: =IFERROR(VLOOKUP($A13,subQ,MATCH(L$1,SUBQH,0),0),"") | ... AG13: =IFERROR(VLOOKUP($A13,subQ,MATCH(AG$1,SUBQH,0),0),"")
A14: 파생상품손익 | D14: 파생상품손익 | E14: =IFERROR(VLOOKUP($A14,subQ,MATCH(E$1,SUBQH,0),0),"") | F14: =IFERROR(VLOOKUP($A14,subQ,MATCH(F$1,SUBQH,0),0),"") | G14: =IFERROR(VLOOKUP($A14,subQ,MATCH(G$1,SUBQH,0),0),"") | H14: =IFERROR(VLOOKUP($A14,subQ,MATCH(H$1,SUBQH,0),0),"") | I14: =IFERROR(VLOOKUP($A14,subQ,MATCH(I$1,SUBQH,0),0),"") | J14: =IFERROR(VLOOKUP($A14,subQ,MATCH(J$1,SUBQH,0),0),"") | K14: =IFERROR(VLOOKUP($A14,subQ,MATCH(K$1,SUBQH,0),0),"") | L14: =IFERROR(VLOOKUP($A14,subQ,MATCH(L$1,SUBQH,0),0),"") | ... AG14: =IFERROR(VLOOKUP($A14,subQ,MATCH(AG$1,SUBQH,0),0),"")
A15: 기타금융손익 | D15: 기타금융손익(금융손익 잔차) | E15: =IFERROR(VLOOKUP($A15,subQ,MATCH(E$1,SUBQH,0),0),"") | F15: =IFERROR(VLOOKUP($A15,subQ,MATCH(F$1,SUBQH,0),0),"") | G15: =IFERROR(VLOOKUP($A15,subQ,MATCH(G$1,SUBQH,0),0),"") | H15: =IFERROR(VLOOKUP($A15,subQ,MATCH(H$1,SUBQH,0),0),"") | I15: =IFERROR(VLOOKUP($A15,subQ,MATCH(I$1,SUBQH,0),0),"") | J15: =IFERROR(VLOOKUP($A15,subQ,MATCH(J$1,SUBQH,0),0),"") | K15: =IFERROR(VLOOKUP($A15,subQ,MATCH(K$1,SUBQH,0),0),"") | L15: =IFERROR(VLOOKUP($A15,subQ,MATCH(L$1,SUBQH,0),0),"") | ... AG15: =IFERROR(VLOOKUP($A15,subQ,MATCH(AG$1,SUBQH,0),0),"")
A16: 기타영업외손익 | D16: 기타영업외손익 | E16: =IFERROR(VLOOKUP($A16,subQ,MATCH(E$1,SUBQH,0),0),"") | F16: =IFERROR(VLOOKUP($A16,subQ,MATCH(F$1,SUBQH,0),0),"") | G16: =IFERROR(VLOOKUP($A16,subQ,MATCH(G$1,SUBQH,0),0),"") | H16: =IFERROR(VLOOKUP($A16,subQ,MATCH(H$1,SUBQH,0),0),"") | I16: =IFERROR(VLOOKUP($A16,subQ,MATCH(I$1,SUBQH,0),0),"") | J16: =IFERROR(VLOOKUP($A16,subQ,MATCH(J$1,SUBQH,0),0),"") | K16: =IFERROR(VLOOKUP($A16,subQ,MATCH(K$1,SUBQH,0),0),"") | L16: =IFERROR(VLOOKUP($A16,subQ,MATCH(L$1,SUBQH,0),0),"") | ... AG16: =IFERROR(VLOOKUP($A16,subQ,MATCH(AG$1,SUBQH,0),0),"")
... A40: NPM | D40: NPM | E40: =IFERROR(VLOOKUP($A40,subQ,MATCH(E$1,SUBQH,0),0),"") | F40: =IFERROR(VLOOKUP($A40,subQ,MATCH(F$1,SUBQH,0),0),"") | G40: =IFERROR(VLOOKUP($A40,subQ,MATCH(G$1,SUBQH,0),0),"") | H40: =IFERROR(VLOOKUP($A40,subQ,MATCH(H$1,SUBQH,0),0),"") | I40: =IFERROR(VLOOKUP($A40,subQ,MATCH(I$1,SUBQH,0),0),"") | J40: =IFERROR(VLOOKUP($A40,subQ,MATCH(J$1,SUBQH,0),0),"") | K40: =IFERROR(VLOOKUP($A40,subQ,MATCH(K$1,SUBQH,0),0),"") | L40: =IFERROR(VLOOKUP($A40,subQ,MATCH(L$1,SUBQH,0),0),"") | ... AG40: =IFERROR(VLOOKUP($A40,subQ,MATCH(AG$1,SUBQH,0),0),"")
A41: 매출액 YoY | D41: 매출액 YoY | I41: =IFERROR(I5/E5-1,"") | J41: =IFERROR(J5/F5-1,"") | K41: =IFERROR(K5/G5-1,"") | L41: =IFERROR(L5/H5-1,"") | M41: =IFERROR(M5/I5-1,"") | N41: =IFERROR(N5/J5-1,"") | O41: =IFERROR(O5/K5-1,"") | P41: =IFERROR(P5/L5-1,"") | ... AG41: =IFERROR(AG5/AC5-1,"")
A42: 영업이익 YoY | D42: 영업이익 YoY | I42: =IFERROR(I9/E9-1,"") | J42: =IFERROR(J9/F9-1,"") | K42: =IFERROR(K9/G9-1,"") | L42: =IFERROR(L9/H9-1,"") | M42: =IFERROR(M9/I9-1,"") | N42: =IFERROR(N9/J9-1,"") | O42: =IFERROR(O9/K9-1,"") | P42: =IFERROR(P9/L9-1,"") | ... AG42: =IFERROR(AG9/AC9-1,"")
A43: 지배주주순이익 YoY | D43: 지배주주순이익 YoY | I43: =IFERROR(I21/E21-1,"") | J43: =IFERROR(J21/F21-1,"") | K43: =IFERROR(K21/G21-1,"") | L43: =IFERROR(L21/H21-1,"") | M43: =IFERROR(M21/I21-1,"") | N43: =IFERROR(N21/J21-1,"") | O43: =IFERROR(O21/K21-1,"") | P43: =IFERROR(P21/L21-1,"") | ... AG43: =IFERROR(AG21/AC21-1,"")

Sheet 연간예상
C1: 이름: 연간예상H — subQ 를 이름으로 VLOOKUP(억원) | E1: 2021 | F1: 2022 | G1: 2023 | H1: 2024 | I1: 2025 | J1: 2026 | K1: 2027 | L1: 2028
C2: 종가: | D2: =변수!D44
C3: 기준일: | D3: 20261012 | E3: 1 | F3: 2 | G3: 3 | H3: 4 | I3: 5 | J3: 6 | K3: 7 | L3: 8
E4: 2021.12A | F4: 2022.12A | G4: 2023.12A | H4: 2024.12A | I4: 2025.12A | J4: 2026.12A | K4: 2027.12A | L4: 2028.12A
A5: 매출액 | D5: 매출액 | E5: =IFERROR(VLOOKUP($A5,subQ,MATCH(E$1,SUBQH,0),0),"") | F5: =IFERROR(VLOOKUP($A5,subQ,MATCH(F$1,SUBQH,0),0),"") | G5: =IFERROR(VLOOKUP($A5,subQ,MATCH(G$1,SUBQH,0),0),"") | H5: =IFERROR(VLOOKUP($A5,subQ,MATCH(H$1,SUBQH,0),0),"") | I5: =IFERROR(VLOOKUP($A5,subQ,MATCH(I$1,SUBQH,0),0),"") | J5: =IFERROR(VLOOKUP($A5,subQ,MATCH(J$1,SUBQH,0),0),"") | K5: =IFERROR(VLOOKUP($A5,subQ,MATCH(K$1,SUBQH,0),0),"") | L5: =IFERROR(VLOOKUP($A5,subQ,MATCH(L$1,SUBQH,0),0),"")
A6: 매출원가 | D6: 매출원가 | E6: =IFERROR(VLOOKUP($A6,subQ,MATCH(E$1,SUBQH,0),0),"") | F6: =IFERROR(VLOOKUP($A6,subQ,MATCH(F$1,SUBQH,0),0),"") | G6: =IFERROR(VLOOKUP($A6,subQ,MATCH(G$1,SUBQH,0),0),"") | H6: =IFERROR(VLOOKUP($A6,subQ,MATCH(H$1,SUBQH,0),0),"") | I6: =IFERROR(VLOOKUP($A6,subQ,MATCH(I$1,SUBQH,0),0),"") | J6: =IFERROR(VLOOKUP($A6,subQ,MATCH(J$1,SUBQH,0),0),"") | K6: =IFERROR(VLOOKUP($A6,subQ,MATCH(K$1,SUBQH,0),0),"") | L6: =IFERROR(VLOOKUP($A6,subQ,MATCH(L$1,SUBQH,0),0),"")
A7: 매출총이익 | D7: 매출총이익 | E7: =IFERROR(VLOOKUP($A7,subQ,MATCH(E$1,SUBQH,0),0),"") | F7: =IFERROR(VLOOKUP($A7,subQ,MATCH(F$1,SUBQH,0),0),"") | G7: =IFERROR(VLOOKUP($A7,subQ,MATCH(G$1,SUBQH,0),0),"") | H7: =IFERROR(VLOOKUP($A7,subQ,MATCH(H$1,SUBQH,0),0),"") | I7: =IFERROR(VLOOKUP($A7,subQ,MATCH(I$1,SUBQH,0),0),"") | J7: =IFERROR(VLOOKUP($A7,subQ,MATCH(J$1,SUBQH,0),0),"") | K7: =IFERROR(VLOOKUP($A7,subQ,MATCH(K$1,SUBQH,0),0),"") | L7: =IFERROR(VLOOKUP($A7,subQ,MATCH(L$1,SUBQH,0),0),"")
A8: 판관비 | D8: 판매비와관리비 | E8: =IFERROR(VLOOKUP($A8,subQ,MATCH(E$1,SUBQH,0),0),"") | F8: =IFERROR(VLOOKUP($A8,subQ,MATCH(F$1,SUBQH,0),0),"") | G8: =IFERROR(VLOOKUP($A8,subQ,MATCH(G$1,SUBQH,0),0),"") | H8: =IFERROR(VLOOKUP($A8,subQ,MATCH(H$1,SUBQH,0),0),"") | I8: =IFERROR(VLOOKUP($A8,subQ,MATCH(I$1,SUBQH,0),0),"") | J8: =IFERROR(VLOOKUP($A8,subQ,MATCH(J$1,SUBQH,0),0),"") | K8: =IFERROR(VLOOKUP($A8,subQ,MATCH(K$1,SUBQH,0),0),"") | L8: =IFERROR(VLOOKUP($A8,subQ,MATCH(L$1,SUBQH,0),0),"")
A9: 영업이익 | D9: 영업이익 | E9: =IFERROR(VLOOKUP($A9,subQ,MATCH(E$1,SUBQH,0),0),"") | F9: =IFERROR(VLOOKUP($A9,subQ,MATCH(F$1,SUBQH,0),0),"") | G9: =IFERROR(VLOOKUP($A9,subQ,MATCH(G$1,SUBQH,0),0),"") | H9: =IFERROR(VLOOKUP($A9,subQ,MATCH(H$1,SUBQH,0),0),"") | I9: =IFERROR(VLOOKUP($A9,subQ,MATCH(I$1,SUBQH,0),0),"") | J9: =IFERROR(VLOOKUP($A9,subQ,MATCH(J$1,SUBQH,0),0),"") | K9: =IFERROR(VLOOKUP($A9,subQ,MATCH(K$1,SUBQH,0),0),"") | L9: =IFERROR(VLOOKUP($A9,subQ,MATCH(L$1,SUBQH,0),0),"")
A10: OPM | D10: 영업이익률 | E10: =IFERROR(VLOOKUP($A10,subQ,MATCH(E$1,SUBQH,0),0),"") | F10: =IFERROR(VLOOKUP($A10,subQ,MATCH(F$1,SUBQH,0),0),"") | G10: =IFERROR(VLOOKUP($A10,subQ,MATCH(G$1,SUBQH,0),0),"") | H10: =IFERROR(VLOOKUP($A10,subQ,MATCH(H$1,SUBQH,0),0),"") | I10: =IFERROR(VLOOKUP($A10,subQ,MATCH(I$1,SUBQH,0),0),"") | J10: =IFERROR(VLOOKUP($A10,subQ,MATCH(J$1,SUBQH,0),0),"") | K10: =IFERROR(VLOOKUP($A10,subQ,MATCH(K$1,SUBQH,0),0),"") | L10: =IFERROR(VLOOKUP($A10,subQ,MATCH(L$1,SUBQH,0),0),"")
A11: 금융손익 | D11: 금융손익(이자·환 포함) | E11: =IFERROR(VLOOKUP($A11,subQ,MATCH(E$1,SUBQH,0),0),"") | F11: =IFERROR(VLOOKUP($A11,subQ,MATCH(F$1,SUBQH,0),0),"") | G11: =IFERROR(VLOOKUP($A11,subQ,MATCH(G$1,SUBQH,0),0),"") | H11: =IFERROR(VLOOKUP($A11,subQ,MATCH(H$1,SUBQH,0),0),"") | I11: =IFERROR(VLOOKUP($A11,subQ,MATCH(I$1,SUBQH,0),0),"") | J11: =IFERROR(VLOOKUP($A11,subQ,MATCH(J$1,SUBQH,0),0),"") | K11: =IFERROR(VLOOKUP($A11,subQ,MATCH(K$1,SUBQH,0),0),"") | L11: =IFERROR(VLOOKUP($A11,subQ,MATCH(L$1,SUBQH,0),0),"")
