Workbook
Name 변수H: 변수!$C$1:$AO$1
Name 환율: 변수!$C$6:$AO$13
Name BS연결H: BS연결!$C$1:$AO$1
Name BS연결: BS연결!$C$5:$AO$122
Name BS별도H: BS별도!$C$1:$AO$1
Name BS별도: BS별도!$C$5:$AO$106
Name SUBQH: subQ!$A$1:$AO$1
Name subQ: subQ!$A$5:$AO$47
Name SLS_H: SLS!$A$1:$AV$1

Sheet README
A1: 삼성중공업(010140) 실적 모델 — ARGUS 한국조선
A2: 기준 분기 2026Q2 · 마지막 실적 2026Q2 · 생성 2026-10-19
A3: 모든 수치는 모델 산출값(DART 공개 재무제표 + 우리 추정)이다 — 목표주가·투자 추천 아님. 참고용 · 투자조언 아님.
A5: 시트
A6: 변수 가정 시계열. 환율 8행(ECB via frankfurter — L2 fx.json; 추정 분기 = 노란 가정), 추정 드라이버(노란 셀 = 모델값에서 역산한 가정, 바꾸면 재계산; 연녹 셀 = 3절 스칼라 참조 수식), 3절 스칼라 가정(세율·판관비율·지배주주비중·이자율·종가·PER 밴드·COE·외화 순노출·헤지비율)
A7: BS연결/BS별도 FnGuide 계정명 × 기간 값 덤프(백만원). 행1 분기라벨, 행4 YYYY.MM / YYYY.12A. 이름정의 BS연결H·BS연결(계정명 C열부터)
A8: subQ 분기 서브모델(억원 = 백만원/100). 확정 행: =IFERROR(VLOOKUP($D행,BS연결,MATCH(E$1,BS연결H,0),0)/100,"") 추정 행: 변수 시트 가정 셀 참조 수식. 외환손익·파생상품손익은 BS 계정 합·차, 기타금융손익은 잔차, OPM·EPS·BPS·PER·PBR 은 파생 수식
A9: SLS 선표(조선사만, sls json 있을 때): 요약 행(sls 저장값) + 계약별 스케줄(백만$) × (헤지비율 × 헤지환율 + (1−헤지비율) × 건조시점 환율[변수 원/달러(평균)]) → 원화 수식 블록 → 합계 행이 subQ 매출조선에 연결
A10: 시나리오 신규수주 보수/기준/낙관(forecast_panel 패널, 모델에 scenarios 가 있을 때만): 매출액·영업이익 = subQ 기준값 ± (시나리오 신규 − base 신규) × OPM. base 만 subQ 행에 포함, 나머지는 합산 안 함
A11: 분기/연간예상 subQ 를 이름(A열 key)으로 VLOOKUP 한 보고서 표(억원)
A12: TP PER 밴드 × 12M fwd EPS, PBR = ROE/COE × BPS — 모델 산출값 구간, 목표주가·추천 아님
A13: 외화 환율 QoQ, 외화 순노출 × Δ기말환율 → 환관련손익 추정
... A36: 백테스트: {"freeze": "2025Q2", "horizon": 4, "revenue_wape_pct": 6.5, "op_wape_pct": 39.7, "n": 4, "note": "단일 회사 4분기 — 통계 아님", "driver_at_freeze": "sls_marine_plus_uncovered_backlog_runoff", "selection_oos_at_freeze": null, "frozen_inputs": "fin(연결/별도)·고객 조선사 모델·지주 자회사 모델은 2025Q2 까지의 분기만; 선표는 체결일 ≤ 2025Q2 말일 계약(원장 최신 금액·코호트 등급, 환산 없음); 잔고는 yards_cache 2025Q2; 시세·환율 forward·prices·forecast_panel 신규수주 미사용. 고객 가중치(suppliers.json 언급 비중)와 합병 체인링크는 현재 지식; 고객 연동 채택은 동결 모델 안에서도 자기 la−4분기 OOS 규칙(selection_oos_at_freeze)", "detail": [{"q": "2025Q3", "rev_pred": 29660.89, "rev_act": 26348.19, "op_pred": 1722.17, "op_act": 2380.82}, {"q": "2025Q4", "rev_pred": 29381.56, "rev_act": 28379.29, "op_pred": 1705.95, "op_act": 2962.35}, {"q": "2026Q1", "rev_pred": 29237.07, "rev_act": 29022.51, "op_pred": 1697.56, "op_act": 2731.18}, {"q": "2026Q2", "rev_pred": 29309.33, "rev_act": 32307.12, "op_pred": 1701.76, "op_act": 3250.24}]}

Sheet 변수
C1: 이름: 변수H | E1: 4Q21 | F1: 2021 | G1: 1Q22 | H1: 2Q22 | I1: 3Q22 | J1: 4Q22 | K1: 2022 | L1: 1Q23 | M1: 2Q23 | N1: 3Q23 | O1: 4Q23 | P1: 2023 | Q1: 1Q24 | R1: 2Q24 | S1: 3Q24 | T1: 4Q24 | U1: 2024 | V1: 1Q25 | W1: 2Q25 | X1: 3Q25 | Y1: 4Q25 | Z1: 2025 | AA1: 1Q26 | AB1: 2Q26 | AC1: 3Q26 | AD1: 4Q26 | AE1: 2026 | AF1: 1Q27 | AG1: 2Q27 | AH1: 3Q27 | AI1: 4Q27 | AJ1: 2027 | AK1: 1Q28 | AL1: 2Q28 | AM1: 3Q28 | AN1: 4Q28 | AO1: 2028
A2: 가정 시계열 — 노란 셀은 추정 가정(모델값에서 역산), 연녹 셀은 3절 스칼라 참조 수식. 바꾸면 subQ·분기·연간예상·TP·시나리오가 재계산됩니다.
E3: 1 | F3: 2 | G3: 3 | H3: 4 | I3: 5 | J3: 6 | K3: 7 | L3: 8 | M3: 9 | N3: 10 | O3: 11 | P3: 12 | Q3: 13 | R3: 14 | S3: 15 | T3: 16 | U3: 17 | V3: 18 | W3: 19 | X3: 20 | Y3: 21 | Z3: 22 | AA3: 23 | AB3: 24 | AC3: 25 | AD3: 26 | AE3: 27 | AF3: 28 | AG3: 29 | AH3: 30 | AI3: 31 | AJ3: 32 | AK3: 33 | AL3: 34 | AM3: 35 | AN3: 36 | AO3: 37
E4: 2021.12 | F4: 2021.12A | G4: 2022.03 | H4: 2022.06 | I4: 2022.09 | J4: 2022.12 | K4: 2022.12A | L4: 2023.03 | M4: 2023.06 | N4: 2023.09 | O4: 2023.12 | P4: 2023.12A | Q4: 2024.03 | R4: 2024.06 | S4: 2024.09 | T4: 2024.12 | U4: 2024.12A | V4: 2025.03 | W4: 2025.06 | X4: 2025.09 | Y4: 2025.12 | Z4: 2025.12A | AA4: 2026.03 | AB4: 2026.06 | AC4: 2026.09 | AD4: 2026.12 | AE4: 2026.12A | AF4: 2027.03 | AG4: 2027.06 | AH4: 2027.09 | AI4: 2027.12 | AJ4: 2027.12A | AK4: 2028.03 | AL4: 2028.06 | AM4: 2028.09 | AN4: 2028.12 | AO4: 2028.12A
B5: 1. FX | C5: 이름: 환율
A6: USDKRW_avg | C6: 원/달러(평균) | E6: 1183.5 | F6: 1145.51 | G6: 1205.78 | H6: 1262.09 | I6: 1341.93 | J6: 1360.12 | K6: 1292.98 | L6: 1276.95 | M6: 1315.69 | N6: 1313.62 | O6: 1322.01 | P6: 1306.85 | Q6: 1330.14 | R6: 1371.28 | S6: 1356.22 | T6: 1396.3 | U6: 1363.53 | V6: 1452.28 | W6: 1398.52 | X6: 1386.95 | Y6: 1449.19 | Z6: 1421.52 | AA6: 1466.12 | AB6: 1501.75 | AC6: 1418.75 | AD6: 1342.11 | AE6: 1454.27 | AF6: 1332.1 | AG6: 1332.1 | AH6: 1332.1 | AI6: 1332.1 | AK6: 1332.1 | AL6: 1332.1 | AM6: 1332.1 | AN6: 1332.1
A7: USDKRW_end | C7: 원/달러(기말) | E7: 1188.75 | F7: 1188.75 | G7: 1213.74 | H7: 1301.24 | I7: 1436.9 | J7: 1260.16 | K7: 1260.16 | L7: 1305.99 | M7: 1321.44 | N7: 1345.35 | O7: 1297.43 | P7: 1297.43 | Q7: 1349.25 | R7: 1377.73 | S7: 1312.17 | T7: 1474.78 | U7: 1474.78 | V7: 1474.54 | W7: 1355.13 | X7: 1403.67 | Y7: 1444.2 | Z7: 1444.2 | AA7: 1524.8 | AB7: 1550.89 | AC7: 1355.4 | AD7: 1332.1 | AE7: 1332.1 | AF7: 1332.1 | AG7: 1332.1 | AH7: 1332.1 | AI7: 1332.1 | AK7: 1332.1 | AL7: 1332.1 | AM7: 1332.1 | AN7: 1332.1
A8: JPY100KRW_avg | C8: 원/100Y(평균) | E8: 1041.02 | F8: 1042.74 | G8: 1036.79 | H8: 972.23 | I8: 970.61 | J8: 961.03 | K8: 985.1 | L8: 964.89 | M8: 957.36 | N8: 909 | O8: 893.22 | P8: 931.11 | Q8: 896.29 | R8: 880.14 | S8: 909.35 | T8: 917.25 | U8: 900.92 | V8: 952.59 | W8: 967.92 | X8: 940.32 | Y8: 940.77 | Z8: 950.17 | AA8: 934.39 | AB8: 942.16 | AC8: 890.41 | AD8: 848.59 | AE8: 917.39 | AF8: 842.99 | AG8: 842.99 | AH8: 842.99 | AI8: 842.99 | AK8: 842.99 | AL8: 842.99 | AM8: 842.99 | AN8: 842.99
A9: JPY100KRW_end | C9: 원/100Y(기말) | E9: 1032.62 | F9: 1032.62 | G9: 996.83 | H9: 954.9 | I9: 993.29 | J9: 955.54 | K9: 955.54 | L9: 980.62 | M9: 913.67 | N9: 901.47 | O9: 917.04 | P9: 917.04 | Q9: 892.42 | R9: 857.76 | S9: 919.21 | T9: 939.65 | U9: 939.65 | V9: 986.84 | W9: 938.85 | X9: 948.49 | Y9: 921.81 | Z9: 921.81 | AA9: 955.99 | AB9: 954.75 | AC9: 863.31 | AD9: 842.99 | AE9: 842.99 | AF9: 842.99 | AG9: 842.99 | AH9: 842.99 | AI9: 842.99 | AK9: 842.99 | AL9: 842.99 | AM9: 842.99 | AN9: 842.99
A10: EURKRW_avg | C10: W/Euro(평균) | E10: 1353.32 | F10: 1354.06 | G10: 1352.29 | H10: 1343.31 | I10: 1350.63 | J10: 1386.07 | K10: 1358.07 | L10: 1369.93 | M10: 1432.41 | N10: 1429.41 | O10: 1420.91 | P10: 1412.88 | Q10: 1444.21 | R10: 1476.42 | S10: 1489.3 | T10: 1490.78 | U10: 1475.4 | V10: 1528.33 | W10: 1585.13 | X10: 1620.04 | Y10: 1686.02 | Z10: 1605.45 | AA10: 1715.47 | AB10: 1746.09 | AC10: 1631.97 | AD10: 1505.3 | AE10: 1685.25 | AF10: 1499.02 | AG10: 1499.02 | AH10: 1499.02 | AI10: 1499.02 | AK10: 1499.02 | AL10: 1499.02 | AM10: 1499.02 | AN10: 1499.02
A11: EURKRW_end | C11: W/Euro(기말) | E11: 1346.38 | F11: 1346.38 | G11: 1347.37 | H11: 1351.6 | I11: 1400.62 | J11: 1344.08 | K11: 1344.08 | L11: 1420.26 | M11: 1435.88 | N11: 1425.26 | O11: 1433.66 | P11: 1433.66 | Q11: 1458.68 | R11: 1474.86 | S11: 1469.1 | T11: 1532.14 | U11: 1532.14 | V11: 1594.72 | W11: 1588.22 | X11: 1648.04 | Y11: 1696.94 | Z11: 1696.94 | AA11: 1753.21 | AB11: 1767.09 | AC11: 1539.06 | AD11: 1499.02 | AE11: 1499.02 | AF11: 1499.02 | AG11: 1499.02 | AH11: 1499.02 | AI11: 1499.02 | AK11: 1499.02 | AL11: 1499.02 | AM11: 1499.02 | AN11: 1499.02
A12: CNYKRW_avg | C12: 원/중국원(평균) | E12: 185.14 | F12: 177.65 | G12: 189.93 | H12: 190.76 | I12: 195.79 | J12: 191.09 | K12: 191.93 | L12: 186.59 | M12: 187.45 | N12: 181.28 | O12: 182.86 | P12: 184.52 | Q12: 185.04 | R12: 189.35 | S12: 189.24 | T12: 194.24 | U12: 189.49 | V12: 199.63 | W12: 193.41 | X12: 193.79 | Y12: 204.38 | Z12: 197.8 | AA12: 211.75 | AB12: 220.8 | AC12: 210.43 | AD12: 200.38 | AE12: 213.41 | AF12: 199.23 | AG12: 199.23 | AH12: 199.23 | AI12: 199.23 | AK12: 199.23 | AL12: 199.23 | AM12: 199.23 | AN12: 199.23
A13: CNYKRW_end | C13: 원/중국원(기말) | E13: 187.13 | F13: 187.13 | G13: 191.38 | H13: 194.13 | I13: 201.92 | J13: 182.67 | K13: 182.67 | L13: 189.97 | M13: 181.8 | N13: 184.26 | O13: 182.61 | P13: 182.61 | Q13: 186.66 | R13: 189.7 | S13: 187.12 | T13: 202.04 | U13: 202.04 | V13: 203.3 | W13: 189.14 | X13: 197.16 | Y13: 206.28 | Z13: 206.28 | AA13: 220.97 | AB13: 228.56 | AC13: 202.16 | AD13: 199.23 | AE13: 199.23 | AF13: 199.23 | AG13: 199.23 | AH13: 199.23 | AI13: 199.23 | AK13: 199.23 | AL13: 199.23 | AM13: 199.23 | AN13: 199.23
B14: 1b. 종가
A15: price_close_end | C15: 종가(기말) | E15: 5670 | G15: 5680 | H15: 6070 | I15: 5310 | J15: 5110 | L15: 5170 | M15: 6670 | N15: 7840 | O15: 7750 | Q15: 8560 | R15: 9350 | S15: 10030 | T15: 11300 | V15: 13480 | W15: 16760 | X15: 21900 | Y15: 24100 | AA15: 24450 | AB15: 23300 | AC15: 19840 | AD15: 18300
A16: price_high | C16: 종가(최고) | E16: 6740 | G16: 6180 | H16: 6450 | I16: 6310 | J16: 5570 | L16: 5950 | M16: 6990 | N16: 9470 | O16: 8300 | Q16: 9390 | R16: 10300 | S16: 12280 | T16: 12290 | V16: 15840 | W16: 18550 | X16: 22800 | Y16: 32500 | AA16: 32000 | AB16: 35350 | AC16: 24500 | AD16: 20150
A17: price_low | C17: 종가(최저) | E17: 5070 | G17: 5020 | H17: 5400 | I17: 5180 | J17: 5000 | L17: 4790 | M17: 5130 | N17: 6600 | O17: 6810 | Q17: 6980 | R17: 8290 | S17: 9290 | T17: 9330 | V17: 11220 | W17: 12650 | X17: 15610 | Y17: 20850 | AA17: 23000 | AB17: 22200 | AC17: 18440 | AD17: 17210
A18: price_avg | C18: 종가(평균) | E18: 5806 | G18: 5619 | H18: 5817.7 | I18: 5694.6 | J18: 5218.2 | L18: 5307.1 | M18: 5952.8 | N18: 8334.2 | O18: 7583.2 | Q18: 7732 | R18: 9306.5 | S18: 10491.9 | T18: 10783 | V18: 13524.5 | W18: 15345.3 | X18: 19674.6 | Y18: 25321.2 | AA18: 28202.5 | AB18: 28704.1 | AC18: 21422.3 | AD18: 18892.7
B20: 2. 추정 드라이버 | C20: 실적 열 = subQ 실현값(수식), 추정 열 = 가정(노란 = 모델값 역산, 연녹 = 3절 스칼라 참조)
A21: drv:판관비 | B21: ratio | C21: 판관비율(/매출) | E21: =IFERROR(subQ!E8/subQ!E5,"") | F21: =IFERROR(subQ!F8/subQ!F5,"") | G21: =IFERROR(subQ!G8/subQ!G5,"") | H21: =IFERROR(subQ!H8/subQ!H5,"") | I21: =IFERROR(subQ!I8/subQ!I5,"") | J21: =IFERROR(subQ!J8/subQ!J5,"") | K21: =IFERROR(subQ!K8/subQ!K5,"") | L21: =IFERROR(subQ!L8/subQ!L5,"") | ... AB21: =IFERROR(subQ!AB8/subQ!AB5,"") | AC21: =$D$55 | AD21: =$D$55 | AE21: =IFERROR(subQ!AE8/subQ!AE5,"") | AF21: =$D$55 | AG21: =$D$55 | AH21: =$D$55 | AI21: =$D$55 | AJ21: =IFERROR(subQ!AJ8/subQ!AJ5,"") | AK21: =$D$55 | AL21: =$D$55 | AM21: =$D$55 | AN21: =$D$55 | AO21: =IFERROR(subQ!AO8/subQ!AO5,"")
A22: drv:외환손익 | B22: abs | C22: 외환손익 (가정, 억원) | E22: =subQ!E13 | F22: =subQ!F13 | G22: =subQ!G13 | H22: =subQ!H13 | I22: =subQ!I13 | J22: =subQ!J13 | K22: =subQ!K13 | L22: =subQ!L13 | ... AB22: =subQ!AB13 | AC22: 0 | AD22: 0 | AE22: =subQ!AE13 | AF22: 0 | AG22: 0 | AH22: 0 | AI22: 0 | AJ22: =subQ!AJ13 | AK22: 0 | AL22: 0 | AM22: 0 | AN22: 0 | AO22: =subQ!AO13
A23: drv:파생상품손익 | B23: abs | C23: 파생상품손익 (가정, 억원) | E23: =subQ!E14 | F23: =subQ!F14 | G23: =subQ!G14 | H23: =subQ!H14 | I23: =subQ!I14 | J23: =subQ!J14 | K23: =subQ!K14 | L23: =subQ!L14 | ... AB23: =subQ!AB14 | AC23: 0 | AD23: 0 | AE23: =subQ!AE14 | AF23: 0 | AG23: 0 | AH23: 0 | AI23: 0 | AJ23: =subQ!AJ14 | AK23: 0 | AL23: 0 | AM23: 0 | AN23: 0 | AO23: =subQ!AO14
A24: drv:기타금융손익 | B24: abs | C24: 기타금융손익 (가정, 억원) | E24: =subQ!E15 | F24: =subQ!F15 | G24: =subQ!G15 | H24: =subQ!H15 | I24: =subQ!I15 | J24: =subQ!J15 | K24: =subQ!K15 | L24: =subQ!L15 | ... AB24: =subQ!AB15 | AC24: -0.01 | AD24: -0.01 | AE24: =subQ!AE15 | AF24: -0.01 | AG24: -0.01 | AH24: -0.01 | AI24: -0.01 | AJ24: =subQ!AJ15 | AK24: -0.01 | AL24: -0.01 | AM24: -0.01 | AN24: -0.01 | AO24: =subQ!AO15
A25: drv:기타영업외손익 | B25: abs | C25: 기타영업외손익 (가정, 억원) | E25: =subQ!E16 | F25: =subQ!F16 | G25: =subQ!G16 | H25: =subQ!H16 | I25: =subQ!I16 | J25: =subQ!J16 | K25: =subQ!K16 | L25: =subQ!L16 | ... AB25: =subQ!AB16 | AC25: 0 | AD25: 0 | AE25: =subQ!AE16 | AF25: 0 | AG25: 0 | AH25: 0 | AI25: 0 | AJ25: =subQ!AJ16 | AK25: 0 | AL25: 0 | AM25: 0 | AN25: 0 | AO25: =subQ!AO16
A26: drv:지분법손익 | B26: abs | C26: 지분법손익 (가정, 억원) | E26: =subQ!E17 | F26: =subQ!F17 | G26: =subQ!G17 | H26: =subQ!H17 | I26: =subQ!I17 | J26: =subQ!J17 | K26: =subQ!K17 | L26: =subQ!L17 | ... AB26: =subQ!AB17 | AC26: 0 | AD26: 0 | AE26: =subQ!AE17 | AF26: 0 | AG26: 0 | AH26: 0 | AI26: 0 | AJ26: =subQ!AJ17 | AK26: 0 | AL26: 0 | AM26: 0 | AN26: 0 | AO26: =subQ!AO17
A27: drv:법인세비용 | B27: tax | C27: 법인세율(/세전) — 법인세 = MAX(세전,0) × 세율 | E27: =IFERROR(subQ!E19/subQ!E18,"") | F27: =IFERROR(subQ!F19/subQ!F18,"") | G27: =IFERROR(subQ!G19/subQ!G18,"") | H27: =IFERROR(subQ!H19/subQ!H18,"") | I27: =IFERROR(subQ!I19/subQ!I18,"") | J27: =IFERROR(subQ!J19/subQ!J18,"") | K27: =IFERROR(subQ!K19/subQ!K18,"") | L27: =IFERROR(subQ!L19/subQ!L18,"") | ... AB27: =IFERROR(subQ!AB19/subQ!AB18,"") | AC27: =$D$54 | AD27: =$D$54 | AE27: =IFERROR(subQ!AE19/subQ!AE18,"") | AF27: =$D$54 | AG27: =$D$54 | AH27: =$D$54 | AI27: =$D$54 | AJ27: =IFERROR(subQ!AJ19/subQ!AJ18,"") | AK27: =$D$54 | AL27: =$D$54 | AM27: =$D$54 | AN27: =$D$54 | AO27: =IFERROR(subQ!AO19/subQ!AO18,"")
A28: drv:지배주주순이익 | B28: ratio | C28: 지배주주 비중(/당기순이익) | E28: =IFERROR(subQ!E21/subQ!E20,"") | F28: =IFERROR(subQ!F21/subQ!F20,"") | G28: =IFERROR(subQ!G21/subQ!G20,"") | H28: =IFERROR(subQ!H21/subQ!H20,"") | I28: =IFERROR(subQ!I21/subQ!I20,"") | J28: =IFERROR(subQ!J21/subQ!J20,"") | K28: =IFERROR(subQ!K21/subQ!K20,"") | L28: =IFERROR(subQ!L21/subQ!L20,"") | ... AB28: =IFERROR(subQ!AB21/subQ!AB20,"") | AC28: =$D$56 | AD28: =$D$56 | AE28: =IFERROR(subQ!AE21/subQ!AE20,"") | AF28: =$D$56 | AG28: =$D$56 | AH28: =$D$56 | AI28: =$D$56 | AJ28: =IFERROR(subQ!AJ21/subQ!AJ20,"") | AK28: =$D$56 | AL28: =$D$56 | AM28: =$D$56 | AN28: =$D$56 | AO28: =IFERROR(subQ!AO21/subQ!AO20,"")
A29: drv:부채총계 | B29: qoq | C29: 부채총계 QoQ | G29: =IFERROR(subQ!G23/subQ!E23-1,"") | H29: =IFERROR(subQ!H23/subQ!G23-1,"") | I29: =IFERROR(subQ!I23/subQ!H23-1,"") | J29: =IFERROR(subQ!J23/subQ!I23-1,"") | L29: =IFERROR(subQ!L23/subQ!J23-1,"") | M29: =IFERROR(subQ!M23/subQ!L23-1,"") | N29: =IFERROR(subQ!N23/subQ!M23-1,"") | O29: =IFERROR(subQ!O23/subQ!N23-1,"") | Q29: =IFERROR(subQ!Q23/subQ!O23-1,"") | R29: =IFERROR(subQ!R23/subQ!Q23-1,"") | S29: =IFERROR(subQ!S23/subQ!R23-1,"") | T29: =IFERROR(subQ!T23/subQ!S23-1,"") | V29: =IFERROR(subQ!V23/subQ!T23-1,"") | W29: =IFERROR(subQ!W23/subQ!V23-1,"") | X29: =IFERROR(subQ!X23/subQ!W23-1,"") | Y29: =IFERROR(subQ!Y23/subQ!X23-1,"") | AA29: =IFERROR(subQ!AA23/subQ!Y23-1,"") | AB29: =IFERROR(subQ!AB23/subQ!AA23-1,"") | AC29: 1.5e-08 | AD29: 0 | AF29: 0 | AG29: 0 | AH29: 0 | AI29: 0 | AK29: 0 | AL29: 0 | AM29: 0 | AN29: 0
A30: drv:자본총계 | B30: roll | C30: 자본총계 기타변동(배당 등, 억원) | G30: =IFERROR(subQ!E24+subQ!G20-subQ!G24,"") | H30: =IFERROR(subQ!G24+subQ!H20-subQ!H24,"") | I30: =IFERROR(subQ!H24+subQ!I20-subQ!I24,"") | J30: =IFERROR(subQ!I24+subQ!J20-subQ!J24,"") | L30: =IFERROR(subQ!J24+subQ!L20-subQ!L24,"") | M30: =IFERROR(subQ!L24+subQ!M20-subQ!M24,"") | N30: =IFERROR(subQ!M24+subQ!N20-subQ!N24,"") | O30: =IFERROR(subQ!N24+subQ!O20-subQ!O24,"") | Q30: =IFERROR(subQ!O24+subQ!Q20-subQ!Q24,"") | R30: =IFERROR(subQ!Q24+subQ!R20-subQ!R24,"") | S30: =IFERROR(subQ!R24+subQ!S20-subQ!S24,"") | T30: =IFERROR(subQ!S24+subQ!T20-subQ!T24,"") | V30: =IFERROR(subQ!T24+subQ!V20-subQ!V24,"") | W30: =IFERROR(subQ!V24+subQ!W20-subQ!W24,"") | X30: =IFERROR(subQ!W24+subQ!X20-subQ!X24,"") | Y30: =IFERROR(subQ!X24+subQ!Y20-subQ!Y24,"") | AA30: =IFERROR(subQ!Y24+subQ!AA20-subQ!AA24,"") | AB30: =IFERROR(subQ!AA24+subQ!AB20-subQ!AB24,"") | AC30: -0.00437145 | AD30: -0.008110109 | AF30: 0.006996103 | AG30: 0.00698306 | AH30: 0.005801761 | AI30: -0.007028072 | AK30: -0.00143717 | AL30: 0.006252531 | AM30: -0.003588791 | AN30: 0.002485498
A31: drv:지배주주지분 | B31: roll | C31: 지배주주지분 기타변동(배당 등, 억원) | G31: =IFERROR(subQ!E25+subQ!G21-subQ!G25,"") | H31: =IFERROR(subQ!G25+subQ!H21-subQ!H25,"") | I31: =IFERROR(subQ!H25+subQ!I21-subQ!I25,"") | J31: =IFERROR(subQ!I25+subQ!J21-subQ!J25,"") | L31: =IFERROR(subQ!J25+subQ!L21-subQ!L25,"") | M31: =IFERROR(subQ!L25+subQ!M21-subQ!M25,"") | N31: =IFERROR(subQ!M25+subQ!N21-subQ!N25,"") | O31: =IFERROR(subQ!N25+subQ!O21-subQ!O25,"") | Q31: =IFERROR(subQ!O25+subQ!Q21-subQ!Q25,"") | R31: =IFERROR(subQ!Q25+subQ!R21-subQ!R25,"") | S31: =IFERROR(subQ!R25+subQ!S21-subQ!S25,"") | T31: =IFERROR(subQ!S25+subQ!T21-subQ!T25,"") | V31: =IFERROR(subQ!T25+subQ!V21-subQ!V25,"") | W31: =IFERROR(subQ!V25+subQ!W21-subQ!W25,"") | X31: =IFERROR(subQ!W25+subQ!X21-subQ!X25,"") | Y31: =IFERROR(subQ!X25+subQ!Y21-subQ!Y25,"") | AA31: =IFERROR(subQ!Y25+subQ!AA21-subQ!AA25,"") | AB31: =IFERROR(subQ!AA25+subQ!AB21-subQ!AB25,"") | AC31: -0.00437145 | AD31: -0.008110109 | AF31: 0.006996103 | AG31: 0.00698306 | AH31: 0.005801761 | AI31: -0.007028072 | AK31: -0.00143717 | AL31: 0.006252531 | AM31: -0.003588791 | AN31: 0.002485498
A32: drv:총차입금 | B32: qoq | C32: 총차입금 QoQ | G32: =IFERROR(subQ!G26/subQ!E26-1,"") | H32: =IFERROR(subQ!H26/subQ!G26-1,"") | I32: =IFERROR(subQ!I26/subQ!H26-1,"") | J32: =IFERROR(subQ!J26/subQ!I26-1,"") | L32: =IFERROR(subQ!L26/subQ!J26-1,"") | M32: =IFERROR(subQ!M26/subQ!L26-1,"") | N32: =IFERROR(subQ!N26/subQ!M26-1,"") | O32: =IFERROR(subQ!O26/subQ!N26-1,"") | Q32: =IFERROR(subQ!Q26/subQ!O26-1,"") | R32: =IFERROR(subQ!R26/subQ!Q26-1,"") | S32: =IFERROR(subQ!S26/subQ!R26-1,"") | T32: =IFERROR(subQ!T26/subQ!S26-1,"") | V32: =IFERROR(subQ!V26/subQ!T26-1,"") | W32: =IFERROR(subQ!W26/subQ!V26-1,"") | X32: =IFERROR(subQ!X26/subQ!W26-1,"") | Y32: =IFERROR(subQ!Y26/subQ!X26-1,"") | AA32: =IFERROR(subQ!AA26/subQ!Y26-1,"") | AB32: =IFERROR(subQ!AB26/subQ!AA26-1,"") | AC32: -2.81e-07 | AD32: 0 | AF32: 0 | AG32: 0 | AH32: 0 | AI32: 0 | AK32: 0 | AL32: 0 | AM32: 0 | AN32: 0
A33: drv:순차입금 | B33: qoq | C33: 순차입금 QoQ | G33: =IFERROR(subQ!G27/subQ!E27-1,"") | H33: =IFERROR(subQ!H27/subQ!G27-1,"") | I33: =IFERROR(subQ!I27/subQ!H27-1,"") | J33: =IFERROR(subQ!J27/subQ!I27-1,"") | L33: =IFERROR(subQ!L27/subQ!J27-1,"") | M33: =IFERROR(subQ!M27/subQ!L27-1,"") | N33: =IFERROR(subQ!N27/subQ!M27-1,"") | O33: =IFERROR(subQ!O27/subQ!N27-1,"") | Q33: =IFERROR(subQ!Q27/subQ!O27-1,"") | R33: =IFERROR(subQ!R27/subQ!Q27-1,"") | S33: =IFERROR(subQ!S27/subQ!R27-1,"") | T33: =IFERROR(subQ!T27/subQ!S27-1,"") | V33: =IFERROR(subQ!V27/subQ!T27-1,"") | W33: =IFERROR(subQ!W27/subQ!V27-1,"") | X33: =IFERROR(subQ!X27/subQ!W27-1,"") | Y33: =IFERROR(subQ!Y27/subQ!X27-1,"") | AA33: =IFERROR(subQ!AA27/subQ!Y27-1,"") | AB33: =IFERROR(subQ!AB27/subQ!AA27-1,"") | AC33: 0.12516996 | AD33: 0.11764612 | AF33: 0.10570743 | AG33: 0.10020086 | AH33: 0.096259049 | AI33: 0.095440652 | AK33: 0.088755933 | AL33: 0.086346121 | AM33: 0.085386994 | AN33: 0.080805279
A34: drv:이자발생자산 | B34: qoq | C34: 이자발생자산 QoQ | G34: =IFERROR(subQ!G28/subQ!E28-1,"") | H34: =IFERROR(subQ!H28/subQ!G28-1,"") | I34: =IFERROR(subQ!I28/subQ!H28-1,"") | J34: =IFERROR(subQ!J28/subQ!I28-1,"") | L34: =IFERROR(subQ!L28/subQ!J28-1,"") | M34: =IFERROR(subQ!M28/subQ!L28-1,"") | N34: =IFERROR(subQ!N28/subQ!M28-1,"") | O34: =IFERROR(subQ!O28/subQ!N28-1,"") | Q34: =IFERROR(subQ!Q28/subQ!O28-1,"") | R34: =IFERROR(subQ!R28/subQ!Q28-1,"") | S34: =IFERROR(subQ!S28/subQ!R28-1,"") | T34: =IFERROR(subQ!T28/subQ!S28-1,"") | V34: =IFERROR(subQ!V28/subQ!T28-1,"") | W34: =IFERROR(subQ!W28/subQ!V28-1,"") | X34: =IFERROR(subQ!X28/subQ!W28-1,"") | Y34: =IFERROR(subQ!Y28/subQ!X28-1,"") | AA34: =IFERROR(subQ!AA28/subQ!Y28-1,"") | AB34: =IFERROR(subQ!AB28/subQ!AA28-1,"") | AC34: 0.077124403 | AD34: 0.075721495 | AF34: 0.070689214 | AG34: 0.06919837 | AH34: 0.068403715 | AI34: 0.069590609 | AK34: 0.066280122 | AL34: 0.065840098 | AM34: 0.066361038 | AN34: 0.06392103
A35: drv:현금및현금성자산 | B35: qoq | C35: 현금및현금성자산 QoQ | G35: =IFERROR(subQ!G29/subQ!E29-1,"") | H35: =IFERROR(subQ!H29/subQ!G29-1,"") | I35: =IFERROR(subQ!I29/subQ!H29-1,"") | J35: =IFERROR(subQ!J29/subQ!I29-1,"") | L35: =IFERROR(subQ!L29/subQ!J29-1,"") | M35: =IFERROR(subQ!M29/subQ!L29-1,"") | N35: =IFERROR(subQ!N29/subQ!M29-1,"") | O35: =IFERROR(subQ!O29/subQ!N29-1,"") | Q35: =IFERROR(subQ!Q29/subQ!O29-1,"") | R35: =IFERROR(subQ!R29/subQ!Q29-1,"") | S35: =IFERROR(subQ!S29/subQ!R29-1,"") | T35: =IFERROR(subQ!T29/subQ!S29-1,"") | V35: =IFERROR(subQ!V29/subQ!T29-1,"") | W35: =IFERROR(subQ!W29/subQ!V29-1,"") | X35: =IFERROR(subQ!X29/subQ!W29-1,"") | Y35: =IFERROR(subQ!Y29/subQ!X29-1,"") | AA35: =IFERROR(subQ!AA29/subQ!Y29-1,"") | AB35: =IFERROR(subQ!AB29/subQ!AA29-1,"")
A36: drv:CAPEX | B36: yoy | C36: CAPEX YoY | J36: =IFERROR(subQ!J30/subQ!E30-1,"") | L36: =IFERROR(subQ!L30/subQ!G30-1,"") | M36: =IFERROR(subQ!M30/subQ!H30-1,"") | N36: =IFERROR(subQ!N30/subQ!I30-1,"") | O36: =IFERROR(subQ!O30/subQ!J30-1,"") | Q36: =IFERROR(subQ!Q30/subQ!L30-1,"") | R36: =IFERROR(subQ!R30/subQ!M30-1,"") | S36: =IFERROR(subQ!S30/subQ!N30-1,"") | T36: =IFERROR(subQ!T30/subQ!O30-1,"") | V36: =IFERROR(subQ!V30/subQ!Q30-1,"") | W36: =IFERROR(subQ!W30/subQ!R30-1,"") | X36: =IFERROR(subQ!X30/subQ!S30-1,"") | Y36: =IFERROR(subQ!Y30/subQ!T30-1,"") | AA36: =IFERROR(subQ!AA30/subQ!V30-1,"") | AB36: =IFERROR(subQ!AB30/subQ!W30-1,"") | AC36: 0.036122998 | AD36: -0.0336799 | AF36: 0.50377999 | AG36: -0.12017348 | AH36: 0 | AI36: 0 | AK36: 0 | AL36: 0 | AM36: 0 | AN36: 0
A37: drv:영업활동현금흐름 | B37: yoy | C37: 영업활동현금흐름 YoY | J37: =IFERROR(subQ!J31/subQ!E31-1,"") | L37: =IFERROR(subQ!L31/subQ!G31-1,"") | M37: =IFERROR(subQ!M31/subQ!H31-1,"") | N37: =IFERROR(subQ!N31/subQ!I31-1,"") | O37: =IFERROR(subQ!O31/subQ!J31-1,"") | Q37: =IFERROR(subQ!Q31/subQ!L31-1,"") | R37: =IFERROR(subQ!R31/subQ!M31-1,"") | S37: =IFERROR(subQ!S31/subQ!N31-1,"") | T37: =IFERROR(subQ!T31/subQ!O31-1,"") | V37: =IFERROR(subQ!V31/subQ!Q31-1,"") | W37: =IFERROR(subQ!W31/subQ!R31-1,"") | X37: =IFERROR(subQ!X31/subQ!S31-1,"") | Y37: =IFERROR(subQ!Y31/subQ!T31-1,"") | AA37: =IFERROR(subQ!AA31/subQ!V31-1,"") | AB37: =IFERROR(subQ!AB31/subQ!W31-1,"")
A38: drv:주식수 | B38: qoq | C38: 주식수 QoQ | G38: =IFERROR(subQ!G32/subQ!E32-1,"") | H38: =IFERROR(subQ!H32/subQ!G32-1,"") | I38: =IFERROR(subQ!I32/subQ!H32-1,"") | J38: =IFERROR(subQ!J32/subQ!I32-1,"") | L38: =IFERROR(subQ!L32/subQ!J32-1,"") | M38: =IFERROR(subQ!M32/subQ!L32-1,"") | N38: =IFERROR(subQ!N32/subQ!M32-1,"") | O38: =IFERROR(subQ!O32/subQ!N32-1,"") | Q38: =IFERROR(subQ!Q32/subQ!O32-1,"") | R38: =IFERROR(subQ!R32/subQ!Q32-1,"") | S38: =IFERROR(subQ!S32/subQ!R32-1,"") | T38: =IFERROR(subQ!T32/subQ!S32-1,"") | V38: =IFERROR(subQ!V32/subQ!T32-1,"") | W38: =IFERROR(subQ!W32/subQ!V32-1,"") | X38: =IFERROR(subQ!X32/subQ!W32-1,"") | Y38: =IFERROR(subQ!Y32/subQ!X32-1,"") | AA38: =IFERROR(subQ!AA32/subQ!Y32-1,"") | AB38: =IFERROR(subQ!AB32/subQ!AA32-1,"") | AC38: 0 | AD38: 0 | AF38: 0 | AG38: 0 | AH38: 0 | AI38: 0 | AK38: 0 | AL38: 0 | AM38: 0 | AN38: 0
A39: drv:DPS | B39: abs | C39: DPS (가정, 원) | E39: =subQ!E35 | F39: =subQ!F35 | G39: =subQ!G35 | H39: =subQ!H35 | I39: =subQ!I35 | J39: =subQ!J35 | K39: =subQ!K35 | L39: =subQ!L35 | ... AB39: =subQ!AB35 | AD39: 0 | AE39: =subQ!AE35 | AI39: 0 | AJ39: =subQ!AJ35 | AN39: 0 | AO39: =subQ!AO35
A40: drv:매출조선 | B40: sls_link | C40: 원장 밖 잔고 소진(억원) — 매출조선 = SLS 원화/100 + 이 행 + 매출조선신규 | G40: =IFERROR(subQ!G38-SLS!E141/100,"") | H40: =IFERROR(subQ!H38-SLS!F141/100,"") | I40: =IFERROR(subQ!I38-SLS!G141/100,"") | J40: =IFERROR(subQ!J38-SLS!H141/100,"") | L40: =IFERROR(subQ!L38-SLS!I141/100,"") | M40: =IFERROR(subQ!M38-SLS!J141/100,"") | N40: =IFERROR(subQ!N38-SLS!K141/100,"") | O40: =IFERROR(subQ!O38-SLS!L141/100,"") | Q40: =IFERROR(subQ!Q38-SLS!M141/100,"") | R40: =IFERROR(subQ!R38-SLS!N141/100,"") | S40: =IFERROR(subQ!S38-SLS!O141/100,"") | T40: =IFERROR(subQ!T38-SLS!P141/100,"") | V40: =IFERROR(subQ!V38-SLS!Q141/100,"") | W40: =IFERROR(subQ!W38-SLS!R141/100,"") | X40: =IFERROR(subQ!X38-SLS!S141/100,"") | Y40: =IFERROR(subQ!Y38-SLS!T141/100,"") | AA40: =IFERROR(subQ!AA38-SLS!U141/100,"") | AB40: =IFERROR(subQ!AB38-SLS!V141/100,"") | AC40: 11046.035 | AD40: 13154.383 | AF40: 13085.926 | AG40: 13120.064 | AH40: 13154.419 | AI40: 13154.433 | AK40: 13120.252 | AL40: 13120.142 | AM40: 13154.505 | AN40: 13133.981
A41: drv:매출조선신규 | B41: abs | C41: 매출조선신규 (forecast_panel base · 공시 상계 신규수주 매출, 억원 — 가정) | E41: =subQ!E39 | F41: =subQ!F39 | G41: =subQ!G39 | H41: =subQ!H39 | I41: =subQ!I39 | J41: =subQ!J39 | K41: =subQ!K39 | L41: =subQ!L39 | ... AB41: =subQ!AB39 | AC41: 0 | AD41: 54.41 | AE41: =subQ!AE39 | AF41: 693.57 | AG41: 2393.86 | AH41: 5034.28 | AI41: 8331.89 | AJ41: =subQ!AJ39 | AK41: 12015.39 | AL41: 15897.92 | AM41: 19805.34 | AN41: 23529.12 | AO41: =subQ!AO39
A42: drv:OP조선 | B42: ratio | C42: OP조선 마진(/매출조선) | E42: =IFERROR(subQ!E40/subQ!E38,"") | F42: =IFERROR(subQ!F40/subQ!F38,"") | G42: =IFERROR(subQ!G40/subQ!G38,"") | H42: =IFERROR(subQ!H40/subQ!H38,"") | I42: =IFERROR(subQ!I40/subQ!I38,"") | J42: =IFERROR(subQ!J40/subQ!J38,"") | K42: =IFERROR(subQ!K40/subQ!K38,"") | L42: =IFERROR(subQ!L40/subQ!L38,"") | ... AB42: =IFERROR(subQ!AB40/subQ!AB38,"") | AC42: 0.099410028 | AD42: 0.099458957 | AE42: =IFERROR(subQ!AE40/subQ!AE38,"") | AF42: 0.09945904 | AG42: 0.099690182 | AH42: 0.099805097 | AI42: 0.099804897 | AJ42: =IFERROR(subQ!AJ40/subQ!AJ38,"") | AK42: 0.099980688 | AL42: 0.09998074 | AM42: 0.099980597 | AN42: 0.099980568 | AO42: =IFERROR(subQ!AO40/subQ!AO38,"")
A43: drv:매출기타 | B43: yoy | C43: 매출기타 YoY | J43: =IFERROR(subQ!J42/subQ!E42-1,"") | L43: =IFERROR(subQ!L42/subQ!G42-1,"") | M43: =IFERROR(subQ!M42/subQ!H42-1,"") | N43: =IFERROR(subQ!N42/subQ!I42-1,"") | O43: =IFERROR(subQ!O42/subQ!J42-1,"") | Q43: =IFERROR(subQ!Q42/subQ!L42-1,"") | R43: =IFERROR(subQ!R42/subQ!M42-1,"") | S43: =IFERROR(subQ!S42/subQ!N42-1,"") | T43: =IFERROR(subQ!T42/subQ!O42-1,"") | V43: =IFERROR(subQ!V42/subQ!Q42-1,"") | W43: =IFERROR(subQ!W42/subQ!R42-1,"") | X43: =IFERROR(subQ!X42/subQ!S42-1,"") | Y43: =IFERROR(subQ!Y42/subQ!T42-1,"") | AA43: =IFERROR(subQ!AA42/subQ!V42-1,"") | AB43: =IFERROR(subQ!AB42/subQ!W42-1,"") | AC43: -0.78193459 | AD43: 0.93633805 | AF43: 0.24127238 | AG43: -0.16274816 | AH43: 0 | AI43: 0 | AK43: 0 | AL43: 0 | AM43: 0 | AN43: 0
A44: drv:OP기타 | B44: ratio | C44: OP기타 마진(/매출기타) | E44: =IFERROR(subQ!E43/subQ!E42,"") | F44: =IFERROR(subQ!F43/subQ!F42,"") | G44: =IFERROR(subQ!G43/subQ!G42,"") | H44: =IFERROR(subQ!H43/subQ!H42,"") | I44: =IFERROR(subQ!I43/subQ!I42,"") | J44: =IFERROR(subQ!J43/subQ!J42,"") | K44: =IFERROR(subQ!K43/subQ!K42,"") | L44: =IFERROR(subQ!L43/subQ!L42,"") | ... AB44: =IFERROR(subQ!AB43/subQ!AB42,"") | AC44: 0.099407213 | AD44: 0.099459441 | AE44: =IFERROR(subQ!AE43/subQ!AE42,"") | AF44: 0.099459441 | AG44: 0.099694466 | AH44: 0.099807627 | AI44: 0.099807627 | AJ44: =IFERROR(subQ!AJ43/subQ!AJ42,"") | AK44: 0.09998172 | AL44: 0.09998172 | AM44: 0.09998172 | AN44: 0.09998172 | AO44: =IFERROR(subQ!AO43/subQ!AO42,"")
B46: 3. 밸류에이션·스칼라 | C46: 노란 셀 = 가정. '연결' 표시는 추정 전 분기 수식이 이 셀을 참조한다는 뜻
A47: sc:종가 | C47: 종가 | D47: 18300 | E47: 원 — 네이버 정규장 종가(aik 확정종가 대조 · aik 18,170원)
A48: sc:기준일 | C48: 기준일 | D48: 20261019 | E48: 종가 기준일
A49: sc:COE | C49: COE | D49: 0.09 | E49: 자기자본비용(가정) — TP 적정 PBR = ROE/COE
A50: sc:PER_lo | C50: PER_lo | D50: 10 | E50: PER 밴드 하단(배) — sector_default(레퍼런스 TP_PE PB 예시 10/15/20배; 과거 PER 중위 46.2배가 3~40 밖(턴어라운드 왜곡))
A51: sc:PER_mid | C51: PER_mid | D51: 15 | E51: PER 밴드 중단(배)
A52: sc:PER_hi | C52: PER_hi | D52: 20 | E52: PER 밴드 상단(배)
A53: sc:EPS_Y1가중 | C53: EPS_Y1가중 | D53: 0.5 | E53: 12M fwd EPS = FY(last_actual연도)E × w + FY+1E × (1−w) — 기준 분기 2Q 이면 0.5(가정)
A54: sc:세율 | C54: 세율 | D54: 0.21999996 | E54: 연결 — 법인세 = MAX(세전,0) × 세율(역산, 재현 오차 ≤ 0.05억 · 모델 assumptions 0.22) · 최근 12분기 유효세율 -65.5% 가 5~27% 밖; 세전 > 0 분기 중위 1.0% 도 5~27% 밖 → 법정세율 근사 22% 가정
A55: sc:판관비율 | C55: 판관비율 | D55: 0.044638481 | E55: 연결 — 판관비 = 매출액 × 판관비율(역산, 재현 오차 ≤ 0.05억 · 모델 assumptions 0.0446)
A56: sc:지배주주비중 | C56: 지배주주비중 | D56: 1 | E56: 연결 — 지배주주순이익 = 당기순이익 × 비중(역산, 재현 오차 ≤ 0.05억)
A57: sc:이자율_자산 | C57: 이자율_자산 | D57: 0.012297081 | E57: 연결 — 이자손익 = (전분기 이자발생자산 × 자산이자율 − 전분기 총차입금 × 부채이자율)/4(역산, 재현 오차 ≤ 0.05억 · 모델 assumptions 0.0123)
A58: sc:이자율_부채 | C58: 이자율_부채 | D58: 0.055768094 | E58: 연결 — 같은 수식의 부채 쪽(총차입금 행이 없으면 0)(역산, 재현 오차 ≤ 0.05억 · 모델 assumptions 0.0558)
A59: sc:배당성향 | C59: 배당성향 | D59: 0 | E59: 배당성향(참고 — 모델은 직전 DPS 유지·Q2 지급 가정)
A60: sc:외화순노출_백만$ | C60: 외화순노출_백만$ | E60: 외화 순노출 × Δ기말환율 (외화 시트 방식) — 외화 순노출 미공시(face) → 0 + 표기
A61: sc:헤지비율 | C61: 헤지비율 | D61: 0.7 | E61: SLS 원화 = Σ 스케줄 × (헤지비율 × 헤지환율 + (1−헤지비율) × 건조시점 환율[원/달러(평균)]) — estimate · 약정환율 미공시 → HEDGE 70% 가정(레퍼런스 SLS 시트 HEDGE 행은 미포 65%·삼성重 100% — 그 사이에 둔 설정값). hedge_rate 는 계약별 수주시점 환율로 대체
A62: sc:헤지환율_약정 | C62: 헤지환율_약정 | E62: 정기보고서 평균 약정환율(measured) — 비어 있으면 계약별 수주시점 환율(fx_at_sign)을 쓴다

Sheet BS연결
B1: (백만원) | C1: 이름: BS연결H | E1: 4Q21 | F1: 2021 | G1: 1Q22 | H1: 2Q22 | I1: 3Q22 | J1: 4Q22 | K1: 2022 | L1: 1Q23 | M1: 2Q23 | N1: 3Q23 | O1: 4Q23 | P1: 2023 | Q1: 1Q24 | R1: 2Q24 | S1: 3Q24 | T1: 4Q24 | U1: 2024 | V1: 1Q25 | W1: 2Q25 | X1: 3Q25 | Y1: 4Q25 | Z1: 2025 | AA1: 1Q26 | AB1: 2Q26 | AC1: 3Q26 | AD1: 4Q26 | AE1: 2026 | AF1: 1Q27 | AG1: 2Q27 | AH1: 3Q27 | AI1: 4Q27 | AJ1: 2027 | AK1: 1Q28 | AL1: 2Q28 | AM1: 3Q28 | AN1: 4Q28 | AO1: 2028
B2: 연결 | D2: fin json(kship_fin.py)
B3: 삼성중공업(연) | C3: UPDATE: 26-10-19 | E3: 1 | F3: 2 | G3: 3 | H3: 4 | I3: 5 | J3: 6 | K3: 7 | L3: 8 | M3: 9 | N3: 10 | O3: 11 | P3: 12 | Q3: 13 | R3: 14 | S3: 15 | T3: 16 | U3: 17 | V3: 18 | W3: 19 | X3: 20 | Y3: 21 | Z3: 22 | AA3: 23 | AB3: 24 | AC3: 25 | AD3: 26 | AE3: 27 | AF3: 28 | AG3: 29 | AH3: 30 | AI3: 31 | AJ3: 32 | AK3: 33 | AL3: 34 | AM3: 35 | AN3: 36 | AO3: 37
B4: Account Code | C4: AccountNAME | E4: 2021.12 | F4: 2021.12A | G4: 2022.03 | H4: 2022.06 | I4: 2022.09 | J4: 2022.12 | K4: 2022.12A | L4: 2023.03 | M4: 2023.06 | N4: 2023.09 | O4: 2023.12 | P4: 2023.12A | Q4: 2024.03 | R4: 2024.06 | S4: 2024.09 | T4: 2024.12 | U4: 2024.12A | V4: 2025.03 | W4: 2025.06 | X4: 2025.09 | Y4: 2025.12 | Z4: 2025.12A | AA4: 2026.03 | AB4: 2026.06 | AC4: 2026.09 | AD4: 2026.12 | AE4: 2026.12A | AF4: 2027.03 | AG4: 2027.06 | AH4: 2027.09 | AI4: 2027.12 | AJ4: 2027.12A | AK4: 2028.03 | AL4: 2028.06 | AM4: 2028.09 | AN4: 2028.12 | AO4: 2028.12A
A5: 1 | C5: 유동자산 | E5: 5593582.9 | F5: 5593582.9 | G5: 5770158.4 | H5: 7127608.9 | I5: 9502252.7 | J5: 8411943.5 | K5: 8411943.5 | L5: 8604416.6 | M5: 8950612.6 | N5: 10617374 | O5: 9245491.7 | P5: 9245491.7 | Q5: 9803428.6 | R5: 9931850.9 | S5: 8569496 | T5: 9369985.1 | U5: 9369985.1 | V5: 8642748.8 | W5: 7000349.9 | X5: 7324552.7 | Y5: 7407076.8 | Z5: 7407076.8 | AA5: 8264307.3 | AB5: 9684057.2
A6: 1 | C6: 현금및현금성자산 | E6: 571214.29 | F6: 571214.29 | G6: 674797.03 | H6: 915384 | I6: 827177.36 | J6: 919191.7 | K6: 919191.7 | L6: 287073.93 | M6: 651449.18 | N6: 493848.92 | O6: 583811.7 | P6: 583811.7 | Q6: 789036.13 | R6: 325535.34 | S6: 630473.16 | T6: 955961.85 | U6: 955961.85 | V6: 519674.1 | W6: 596771.16 | X6: 1403023 | Y6: 772614.65 | Z6: 772614.65 | AA6: 1038042.8 | AB6: 807415.28
A7: 1 | C7: 단기금융상품 | E7: 599476.18 | F7: 599476.18 | G7: 196247.24 | H7: 349164.39 | I7: 105679.94 | J7: 113168.77 | K7: 113168.77 | L7: 374474.41 | M7: 306317.63 | N7: 179305.37 | O7: 155368.15 | P7: 155368.15 | Q7: 92235.25 | R7: 86844.71 | S7: 52682.26 | T7: 47755.09 | U7: 47755.09 | V7: 45612 | W7: 69708.61 | X7: 266258.93 | Y7: 311797 | Z7: 311797 | AA7: 608399.54 | AB7: 726657.43
A8: 1 | C8: 단기금융자산 | E8: 1037314.2 | F8: 1037314.2 | G8: 886645.09 | H8: 2125512.8 | I8: 3705580.7 | J8: 2026903.3 | K8: 2026903.3 | L8: 2401333.2 | M8: 2223202.4 | N8: 2794106.3 | O8: 1534347.5 | P8: 1534347.5 | Q8: 2087189.8 | R8: 2488058 | S8: 1507853.6 | T8: 2098941.2 | U8: 2098941.2 | V8: 1841864.8 | W8: 1132440.8 | X8: 1159064.8 | Y8: 1356867.8 | Z8: 1356867.8 | AA8: 2056992.8 | AB8: 2356775.7
A9: 1 | C9: 매출채권및기타채권 | E9: 146050.59 | F9: 146050.59 | G9: 206468.68 | H9: 150443.92 | I9: 262997.63 | J9: 770435.61 | K9: 770435.61 | L9: 536078.64 | M9: 408678.54 | N9: 978717.2 | O9: 541144.14 | P9: 541144.14 | Q9: 640813.36 | R9: 531626.93 | S9: 439394.87 | T9: 1185653.6 | U9: 1185653.6 | V9: 976833.49 | W9: 535100.23 | X9: 385245.66 | Y9: 1418753.4 | Z9: 1418753.4 | AA9: 678802.85 | AB9: 678786.06
A10: 1 | C10: 계약자산 | E10: 1532623.8 | F10: 1532623.8 | G10: 1636704.1 | H10: 1652085 | I10: 2296810.5 | J10: 2319153.1 | K10: 2319153.1 | L10: 2369921.3 | M10: 2914358.6 | N10: 3497798.6 | O10: 3783888.8 | P10: 3783888.8 | Q10: 4039461.9 | R10: 4568227.4 | S10: 3916158.6 | T10: 3572702.9 | U10: 3572702.9 | V10: 3461667.3 | W10: 3143533.6 | X10: 2757869.3 | Y10: 2176503 | Z10: 2176503 | AA10: 2673891.9 | AB10: 3335138.2
A11: 1 | C11: 선급금 | E11: 380271.13 | F11: 380271.13 | G11: 414557.9 | H11: 457741.86 | I11: 536309.36 | J11: 546864.92 | K11: 546864.92 | L11: 610370.64 | M11: 683985.56 | N11: 696749.11 | O11: 782581.09 | P11: 782581.09 | Q11: 784169.84 | R11: 824377.36 | S11: 851667.01 | T11: 880646.88 | U11: 880646.88 | V11: 952542.38 | W11: 819761.38 | X11: 859787.58 | Y11: 899488 | Z11: 899488 | AA11: 829881.75 | AB11: 959947.18
A12: 1 | C12: 선급금등 | E12: 380271.13 | F12: 380271.13 | G12: 414557.9 | H12: 457741.86 | I12: 536309.36 | J12: 546864.92 | K12: 546864.92 | L12: 610370.64 | M12: 683985.56 | N12: 696749.11 | O12: 782581.09 | P12: 782581.09 | Q12: 784169.84 | R12: 824377.36 | S12: 851667.01 | T12: 880646.88 | U12: 880646.88 | V12: 952542.38 | W12: 819761.38 | X12: 859787.58 | Y12: 899488 | Z12: 899488 | AA12: 829881.75 | AB12: 959947.18
A13: 1 | C13: 기타유동자산 | E13: 524219.16 | F13: 524219.16 | G13: 572165.86 | H13: 647195.94 | I13: 719448.08 | J13: 713578.07 | K13: 713578.07 | L13: 845765.22 | M13: 900819.2 | N13: 926097.36 | O13: 984183.18 | P13: 984183.18 | Q13: 997444.05 | R13: 1031966.6 | S13: 1076792.6 | T13: 1032127 | U13: 1032127 | V13: 1140212.6 | W13: 1023707.8 | X13: 1085580.9 | Y13: 1121950.9 | Z13: 1121950.9 | AA13: 1067327.3 | AB13: 1201255.2
A14: 1 | C14: 유동파생상품자산 | E14: 157360.32 | F14: 157360.32 | G14: 234481.53 | H14: 449552.93 | I14: 925051.78 | J14: 852661.8 | K14: 852661.8 | L14: 546299.73 | M14: 393147.66 | N14: 499261.69 | O14: 265825.97 | P14: 265825.97 | Q14: 309901.32 | R14: 373077.69 | S14: 237510.23 | T14: 630502.42 | U14: 630502.42 | V14: 428417.24 | W14: 529470.32 | X14: 241363.2 | Y14: 358110.48 | Z14: 358110.48 | AA14: 459157.53 | AB14: 548727.3
A15: 1 | C15: 유동확정계약자산 | E15: 280477.68 | F15: 280477.68 | G15: 455916.32 | H15: 1326795.5 | I15: 2674849 | J15: 1061072.8 | K15: 1061072.8 | L15: 1480559.1 | M15: 1523737.1 | N15: 2115539.2 | O15: 1113153.4 | P15: 1113153.4 | Q15: 1685053.2 | R15: 2028135.6 | S15: 1217661.1 | T15: 1420683.7 | U15: 1420683.7 | V15: 1367835.6 | W15: 533261.85 | X15: 651442.67 | Y15: 686960.31 | Z15: 686960.31 | AA15: 989435.75 | AB15: 1081391
A16: 1 | C16: 재고자산 | E16: 1487633.6 | F16: 1487633.6 | G16: 1549255.3 | H16: 1546715.8 | I16: 1601466.5 | J16: 1573509.7 | K16: 1573509.7 | L16: 1722224.7 | M16: 1763087.5 | N16: 1838285 | O16: 1729150.3 | P16: 1729150.3 | Q16: 1162977.1 | R16: 904171.77 | S16: 919122.63 | T16: 452452.89 | U16: 452452.89 | V16: 499653.81 | W16: 500284.61 | X16: 463223.2 | Y16: 489645.27 | Z16: 489645.27 | AA16: 677272.38 | AB16: 497750.84
... A18: 1 | C18: 기타유동금융자산 | E18: 77503.31 | F18: 77503.31 | G18: 77444.4 | H18: 79162.44 | I18: 76909.37 | J18: 77681.13 | K18: 77681.13 | L18: 77791.29 | M18: 77904.86 | N18: 74737.3 | O18: 74387.67 | P18: 74387.67 | Q18: 72561.05 | R18: 72158.06 | S18: 69561.11 | T18: 62127.39 | U18: 62127.39 | V18: 192678.45 | W18: 63117.63 | X18: 64448.28 | Y18: 66751.36 | Z18: 66751.36 | AA18: 67766.39 | AB18: 802498.99
A19: 1 | C19: 매각예정비유동자산및처분자산 | E19: 190409.1 | F19: 190409.1 | G19: 154397.03
A20: 1 | C20: 비유동자산 | E20: 6545013.1 | F20: 6545013.1 | G20: 6516720.9 | H20: 6668840.5 | I20: 7358807.6 | J20: 6079754.5 | K20: 6079754.5 | L20: 6047471.7 | M20: 6030569.2 | N20: 5981824.8 | O20: 6347897.4 | P20: 6347897.4 | Q20: 6555576.8 | R20: 6846397 | S20: 6506473.1 | T20: 7824652 | U20: 7824652 | V20: 7638407.2 | W20: 6941369.6 | X20: 7214897 | Y20: 7541794.3 | Z20: 7541794.3 | AA20: 8304415.6 | AB20: 8275325
A21: 1 | C21: 장기금융자산 | E21: 45675.73 | F21: 45675.73 | G21: 46431.26 | H21: 46357.6 | I21: 46000.34 | J21: 85746 | K21: 85746 | L21: 85772.36 | M21: 85997.98 | N21: 85924.4 | O21: 87302.1 | P21: 87302.1 | Q21: 87591.22 | R21: 87461.09 | S21: 88424.58 | T21: 102341.44 | U21: 102341.44 | V21: 119960.07 | W21: 119983.32 | X21: 176895.16 | Y21: 168378.3 | Z21: 168378.3 | AA21: 165783.22 | AB21: 182438.21
A22: 1 | C22: 투자자산 | E22: 559853.24 | F22: 559853.24 | G22: 544073 | H22: 835696.1 | I22: 1666349.2 | J22: 384139.02 | K22: 384139.02 | L22: 367452.94 | M22: 365553.34 | N22: 367095.25 | O22: 460924.51 | P22: 460924.51 | Q22: 689950.46 | R22: 1024559.9 | S22: 653424.89 | T22: 1679662.2 | U22: 1679662.2 | V22: 1535372.1 | W22: 768416.09 | X22: 1112203.9 | Y22: 1531860.2 | Z22: 1531860.2 | AA22: 2376022.3 | AB22: 2443685.3
A23: 1 | C23: 종속기업및관계기업투자 | E23: 933.53 | F23: 933.53 | G23: 835.3 | H23: 735.4 | I23: 599.61 | J23: 120.27 | K23: 120.27 | L23: 80.62 | M23: 68.65 | N23: 57.99 | O23: 53.63 | P23: 53.63 | Q23: 62.42 | R23: 63.15 | S23: 54.07 | T23: 51.4 | U23: 51.4 | V23: 66.71 | W23: 66.79 | X23: 65.24 | Y23: 69.76 | Z23: 69.76 | AA23: 71.97 | AB23: 77.38
A24: 1 | C24: 유형자산 | E24: 5613735.2 | F24: 5613735.2 | G24: 5588616.6 | H24: 5551065.3 | I24: 5548467 | J24: 5235398.8 | K24: 5235398.8 | L24: 5232765.6 | M24: 5219108.6 | N24: 5227209.7 | O24: 5208721.7 | P24: 5208721.7 | Q24: 5200152.8 | R24: 5201568.9 | S24: 5184646.3 | T24: 5115872.2 | U24: 5115872.2 | V24: 5082731.5 | W24: 5073650.8 | X24: 5089571.7 | Y24: 5107108.3 | Z24: 5107108.3 | AA24: 5113631.4 | AB24: 5130883.2
A25: 1 | C25: 사용권자산 | E25: 38511.42 | F25: 38511.42 | G25: 55189.54 | H25: 65576.87 | I25: 68785.33 | J25: 100697.39 | K25: 100697.39 | L25: 128057.68 | M25: 116542.37 | N25: 106903.78 | O25: 174483.14 | P25: 174483.14 | Q25: 247877.06 | R25: 262129.67 | S25: 237311.3 | T25: 259254.49 | U25: 259254.49 | V25: 249835.04 | W25: 225889.61 | X25: 214881.42 | Y25: 194996.63 | Z25: 194996.63 | AA25: 206532.19 | AB25: 181398.02
A26: 1 | C26: 기타비유동자산 | E26: 82337.36 | F26: 82337.36 | G26: 102854.14 | H26: 102595.02 | I26: 107414.62 | J26: 228106.95 | K26: 228106.95 | L26: 251804.84 | M26: 244270.25 | N26: 229706.53 | O26: 304846.98 | P26: 304846.98 | Q26: 368345.2 | R26: 373491.22 | S26: 338043.19 | T26: 354214.93 | U26: 354214.93 | V26: 330072.99 | W26: 289107.72 | X26: 261085.6 | Y26: 287174.4 | Z26: 287174.4 | AA26: 289735.71 | AB26: 231607.88
A27: 1 | C27: 투자부동산 | E27: 17616.35 | F27: 17616.35 | G27: 17576.88 | H27: 276.71 | I27: 275.67 | J27: 274.64 | K27: 274.64 | L27: 273.6 | O27: 0 | P27: 0 | T27: 0 | U27: 0
A28: 1 | C28: 무형자산 | E28: 24422.52 | F28: 24422.52 | G28: 24818.85 | H28: 23874.94 | I28: 23889.11 | J28: 26426.7 | K28: 26426.7 | L28: 26800.51 | M28: 26925.69 | N28: 27003.04 | O28: 26973.12 | P28: 26973.12 | Q28: 26864.83 | R28: 26927 | S28: 27782.86 | T28: 27842.41 | U28: 27842.41 | V28: 32982.37 | W28: 32201.14 | X28: 32048.09 | Y28: 32017.07 | Z28: 32017.07 | AA28: 35744.31 | AB28: 38340.32
A29: 1 | C29: 비유동파생상품자산 | E29: 145141.39 | F29: 145141.39 | G29: 139065.54 | H29: 244581.2 | I29: 375130.81 | J29: 83310.77 | K29: 83310.77 | L29: 57634.16 | M29: 51230.65 | N29: 33177.76 | O29: 95504.63 | P29: 95504.63 | Q29: 60902.38 | R29: 114313.77 | S29: 101646.1 | T29: 276472.07 | U29: 276472.07 | V29: 246317.46 | W29: 235830.96 | X29: 156941.09 | Y29: 242790.83 | Z29: 242790.83 | AA29: 436336.76 | AB29: 454061.37
A30: 1 | C30: 비유동확정계약자산 | E30: 368102.59 | F30: 368102.59 | G30: 357740.9 | H30: 544021.9 | I30: 1244618.5 | J30: 214961.98 | K30: 214961.98 | L30: 223965.8 | M30: 228256.06 | N30: 247935.1 | O30: 278064.15 | P30: 278064.15 | Q30: 541394.44 | R30: 822721.89 | S30: 463300.14 | T30: 1300797.3 | U30: 1300797.3 | V30: 1169027.8 | W30: 412535.02 | X30: 778302.39 | Y30: 1120621.3 | Z30: 1120621.3 | AA30: 1773830.4 | AB30: 1807108.3
A31: 1 | C31: 장기매출채권및기타채권 | E31: 10411.32 | F31: 10411.32 | G31: 13418.35
A32: 1 | C32: 이연법인세자산 | E32: 236637.08 | F32: 236637.08 | G32: 225363.02 | H32: 155332.48 | I32: 12412.04 | J32: 205408.47 | K32: 205408.47 | L32: 168374.12 | M32: 174711.38 | N32: 130810.22 | O32: 346431.15 | P32: 346431.15 | Q32: 270263.54 | R32: 219850 | S32: 302575.91 | T32: 647060.27 | U32: 647060.27 | V32: 657248.25 | W32: 777993.91 | X32: 719987.74 | Y32: 583634.39 | Z32: 583634.39 | AA32: 489281.94 | AB32: 430808.32
A33: 1 | C33: 자산총계 | E33: 12138596 | F33: 12138596 | G33: 12286879 | H33: 13796449 | I33: 16861060 | J33: 14491698 | K33: 14491698 | L33: 14651888 | M33: 14981182 | N33: 16599199 | O33: 15593389 | P33: 15593389 | Q33: 16359005 | R33: 16778248 | S33: 15075969 | T33: 17194637 | U33: 17194637 | V33: 16281156 | W33: 13941719 | X33: 14539450 | Y33: 14948871 | Z33: 14948871 | AA33: 16568723 | AB33: 17959382
A34: 1 | C34: 유동부채 | E34: 7058249.8 | F34: 7058249.8 | G34: 7256585.7 | H34: 7863958.3 | I34: 9950723.9 | J34: 9216046.8 | K34: 9216046.8 | L34: 9456073.2 | M34: 9734832.9 | N34: 11443466 | O34: 11231917 | P34: 11231917 | Q34: 11809118 | R34: 11960243 | S34: 10839831 | T34: 12029242 | U34: 12029242 | V34: 11181335 | W34: 9559551.2 | X34: 9474581.3 | Y34: 9422232.4 | Z34: 9422232.4 | AA34: 9998876.3 | AB34: 11034660
A35: 1 | C35: 매입채무및기타채무 | E35: 821003.26 | F35: 821003.26 | G35: 829920.43 | H35: 894953.33 | I35: 951053.57 | J35: 1004203.1 | K35: 1004203.1 | L35: 950845.5 | M35: 1029500 | N35: 1103401.9 | O35: 1147302.2 | P35: 1147302.2 | Q35: 1605934.3 | R35: 1037074.4 | S35: 873392.08 | T35: 945568.69 | U35: 945568.69 | V35: 890592.14 | W35: 887132.56 | X35: 855541.54 | Y35: 1022545 | Z35: 1022545 | AA35: 1121859.6 | AB35: 1435233.3
A36: 1 | C36: 단기차입금 | E36: 922449.41 | F36: 922449.41 | G36: 817743.18 | H36: 744625.3 | I36: 1621413.4 | J36: 1407408.4 | K36: 1407408.4 | L36: 1218289.4 | M36: 1465934.4 | N36: 1664104.8 | O36: 1849594.5 | P36: 1849594.5 | Q36: 2075109.7 | R36: 2190689.1 | S36: 2441203 | T36: 2155829.6 | U36: 2155829.6 | V36: 2122745 | W36: 1860047.3 | X36: 1684765 | Y36: 1454489.6 | Z36: 1454489.6 | AA36: 766450.94 | AB36: 789943.13
A37: 1 | C37: 계약부채 | E37: 2628389.4 | F37: 2628389.4 | G37: 2838350.1 | H37: 2749450.1 | I37: 2797222.5 | J37: 3757436.2 | K37: 3757436.2 | L37: 4213136.7 | M37: 4369453.8 | N37: 5170088.6 | O37: 4992172.5 | P37: 4992172.5 | Q37: 5277724.7 | R37: 5527670.4 | S37: 5309287.3 | T37: 5463032.3 | U37: 5463032.3 | V37: 5510132.1 | W37: 5071009.6 | X37: 5367795.8 | Y37: 4580473.4 | Z37: 4580473.4 | AA37: 4950716.7 | AB37: 5433923.9
A38: 1 | C38: 당기법인세부채(미지급법인세) | E38: 4072.8 | F38: 4072.8 | G38: 3673.81 | H38: 75575.88 | I38: 4637.68 | J38: 5170.17 | K38: 5170.17 | L38: 3019.36 | M38: 3442.46 | N38: 3564.09 | O38: 3967.11 | P38: 3967.11 | Q38: 6475.18 | R38: 3528.17 | S38: 2365.07 | T38: 0 | U38: 0 | V38: 676.47 | W38: 848.35 | X38: 313.97 | Y38: 12159.39 | Z38: 12159.39 | AA38: 20190.34 | AB38: 35968.34
A39: 1 | C39: 단기파생상품부채 | E39: 369828.37 | F39: 369828.37 | G39: 491157.58 | H39: 1102591.1 | I39: 2669046.3 | J39: 1094132.8 | K39: 1094132.8 | L39: 1174517.6 | M39: 1151054.2 | N39: 1720315.3 | O39: 719442.42 | P39: 719442.42 | Q39: 984974.04 | R39: 1272684.3 | S39: 377136.67 | T39: 2065507 | U39: 2065507 | V39: 1236269.9 | W39: 406352.66 | X39: 619570 | Y39: 799606.05 | Z39: 799606.05 | AA39: 1393515.9 | AB39: 1693887
A40: 1 | C40: 단기금융부채 | E40: 383652.73 | F40: 383652.73 | G40: 517621.65 | H40: 1129416.5 | I40: 2684835.9 | J40: 1126732.7 | K40: 1126732.7 | L40: 1224792.3 | M40: 1195801.4 | N40: 1757362.3 | O40: 750762.11 | P40: 750762.11 | Q40: 1070044.9 | R40: 1355767.6 | S40: 454297.35 | T40: 2130546.3 | U40: 2130546.3 | V40: 1317706 | W40: 480261.68 | X40: 693758.54 | Y40: 863773.82 | Z40: 863773.82 | AA40: 1463133 | AB40: 1747334.1
A41: 1 | C41: 유동성장기부채 | E41: 927141.09 | F41: 927141.09 | G41: 856555.67 | H41: 774345.18 | I41: 552595.28 | J41: 519288.55 | K41: 519288.55 | L41: 627235.39 | M41: 593940.55 | N41: 815922.36 | O41: 1185307.4 | P41: 1185307.4 | Q41: 1028629.2 | R41: 1154913.9 | S41: 1203982.3 | T41: 925634.84 | U41: 925634.84 | V41: 901182.55 | W41: 852965.56 | X41: 459548.14 | Y41: 277372.89 | Z41: 277372.89 | AA41: 125060.87 | AB41: 5138.33
A42: 1 | C42: 유동리스부채 | E42: 13824.36 | F42: 13824.36 | G42: 26464.07 | H42: 26825.37 | I42: 15789.6 | J42: 32599.83 | K42: 32599.83 | L42: 50274.64 | M42: 43465.61 | N42: 36616.95 | O42: 31277.32 | P42: 31277.32 | Q42: 85070.84 | R42: 83083.36 | S42: 77160.68 | T42: 65037.53 | U42: 65037.53 | V42: 81434.32 | W42: 73907.33 | X42: 74186.79 | Y42: 64167.77 | Z42: 64167.77 | AA42: 69617.09 | AB42: 53447.08
A43: 1 | C43: 리스부채 | E43: 25215.05 | F43: 25215.05 | G43: 34277.29 | H43: 30231.44 | I43: 19265.64 | J43: 56243.82 | K43: 56243.82 | L43: 80671.7 | M43: 69567.98 | N43: 59561.41 | O43: 130102.62 | P43: 130102.62 | Q43: 201892.65 | R43: 218445.16 | S43: 197369.24 | T43: 325399.52 | U43: 325399.52 | V43: 310697.65 | W43: 291773.47 | X43: 280331.2 | Y43: 258735.49 | Z43: 258735.49 | AA43: 261234.15 | AB43: 233158.14
... A53: 1 | C53: 기타비유동금융부채 | E53: 50790.34 | F53: 50790.34 | G53: 50575.1 | H53: 210609.78 | I53: 210218.39 | J53: 217910.57 | K53: 217910.57 | L53: 223307.27 | M53: 224656.46 | N53: 227484.3 | O53: 187385.9 | P53: 187385.9 | Q53: 59372.26 | R53: 59560.36 | S53: 59304.63 | T53: 62349.58 | U53: 62349.58 | V53: 65391.06 | W53: 65575.52 | X53: 65699.24 | Y53: 81941.27 | Z53: 81941.27 | AA53: 82726.27 | AB53: 83201.1
A54: 1 | C54: 이연법인세부채 | E54: 27179.19 | F54: 27179.19 | G54: 28165.52 | H54: 29960.34 | I54: 33253.84 | J54: 21861.69 | K54: 21861.69 | L54: 18007.91 | M54: 17697.11 | N54: 14050.09 | O54: 14086.42 | P54: 14086.42 | Q54: 0 | R54: 0 | S54: 0 | T54: 0 | U54: 0 | Y54: 0 | Z54: 0
A55: 1 | C55: 부채총계 | E55: 8041328.9 | F55: 8041328.9 | G55: 8253315.2 | H55: 9570294.3 | I55: 12369443 | J55: 10919761 | K55: 10919761 | L55: 10931420 | M55: 11272755 | N55: 12727073 | O55: 12184182 | P55: 12184182 | Q55: 12687134 | R55: 12859746 | S55: 11344792 | T55: 13445186 | U55: 13445186 | V55: 12473198 | W55: 10332762 | X55: 10594104 | Y55: 10853831 | Z55: 10853831 | AA55: 12113230 | AB55: 13249029
A56: 1 | C56: 지배주주지분 | E56: 4111044 | F56: 4111044 | G56: 4048489.7 | H56: 4244211.2 | I56: 4514542.3 | J56: 3594491.1 | K56: 3594491.1 | L56: 3745865.3 | M56: 3736371.9 | N56: 3903339.2 | O56: 3439345 | P56: 3439345 | Q56: 3705485.5 | R56: 3955772.1 | S56: 3769079.4 | T56: 3794593 | U56: 3794593 | V56: 3854995.3 | W56: 3654160.4 | X56: 3993852.3 | Y56: 4148939.3 | Z56: 4148939.3 | AA56: 4513941.8 | AB56: 4771398.4
A57: 1 | C57: 자본금 | E57: 880114.84 | F57: 880114.84 | G57: 880114.84 | H57: 880114.84 | I57: 880114.84 | J57: 880114.84 | K57: 880114.84 | L57: 880114.84 | M57: 880114.84 | N57: 880114.84 | O57: 880114.84 | P57: 880114.84 | Q57: 880114.84 | R57: 880114.84 | S57: 880114.84 | T57: 880114.84 | U57: 880114.84 | V57: 880114.84 | W57: 880114.84 | X57: 880114.84 | Y57: 880114.84 | Z57: 880114.84 | AA57: 880114.84 | AB57: 880114.84
A58: 1 | C58: 보통주자본금 | E58: 880000 | F58: 880000 | G58: 880000 | H58: 880000 | I58: 880000 | J58: 880000 | K58: 880000 | L58: 880000 | M58: 880000 | N58: 880000 | O58: 880000 | P58: 880000 | Q58: 880000 | R58: 880000 | S58: 880000 | T58: 880000 | U58: 880000 | V58: 880000 | W58: 880000 | X58: 880000 | Y58: 880000 | Z58: 880000 | AA58: 880000 | AB58: 880000
A59: 1 | C59: 우선주자본금 | E59: 114.84 | F59: 114.84 | G59: 114.84 | H59: 114.84 | I59: 114.84 | J59: 114.84 | K59: 114.84 | L59: 114.84 | M59: 114.84 | N59: 114.84 | O59: 114.84 | P59: 114.84 | Q59: 114.84 | R59: 114.84 | S59: 114.84 | T59: 114.84 | U59: 114.84 | V59: 114.84 | W59: 114.84 | X59: 114.84 | Y59: 114.84 | Z59: 114.84 | AA59: 114.84 | AB59: 114.84
A60: 1 | C60: 자본잉여금 | E60: 1969727.2 | F60: 1969727.2 | G60: 1969727.2 | H60: 1969727.2 | I60: 1969727.2 | J60: 1969727.2 | K60: 1969727.2 | L60: 1969727.2 | M60: 1969727.2 | N60: 1969727.2 | O60: 1969727.2 | P60: 1969727.2 | Q60: 1969727.2 | R60: 1969727.2 | S60: 1969727.2 | T60: 1969727.2 | U60: 1969727.2 | V60: 1969727.2 | W60: 1969727.2 | X60: 1969727.2 | Y60: 1969727.2 | Z60: 1969727.2 | AA60: 1969727.2 | AB60: 1969727.2
A61: 1 | C61: 기타포괄이익누계액 | E61: 1060330.6 | F61: 1060330.6 | G61: 1100811.8 | H61: 1333501.1 | I61: 1802788.1 | J61: 1147530.9 | K61: 1147530.9 | L61: 1287480.9 | M61: 1252379.4 | N61: 1381235.9 | O61: 1202135.8 | P61: 1202135.8 | Q61: 1458329.3 | R61: 1632059.6 | S61: 1371387.3 | T61: 1524733 | U61: 1524733 | V61: 1493039.6 | W61: 1078085.4 | X61: 1273381.8 | Y61: 1345897.4 | Z61: 1345897.4 | AA61: 1609315.9 | AB61: 1642440
A62: 1 | C62: 기타자본 | E62: 1556045.1 | F62: 1556045.1 | G62: 1556045.1 | H62: 1556045.1 | I62: 1556045.1 | J62: 1556045.1 | K62: 1556045.1 | L62: 1556045.1 | M62: 1556045.1 | N62: 1556045.1 | O62: 1556045.1 | P62: 1556045.1 | Q62: 1556045.1 | R62: 1556045.1 | S62: 1556045.1 | T62: 1556045.1 | U62: 1556045.1 | V62: 1556045.1 | W62: 1556045.1 | X62: 1556045.1 | Y62: 1556045.1 | Z62: 1556045.1 | AA62: 1556045.1 | AB62: 1556045.1
A63: 1 | C63: 이익잉여금 | E63: -1355173.8 | F63: -1355173.8 | G63: -1458209.3 | H63: -1495176.9 | I63: -1694132.9 | J63: -1958927 | K63: -1958927 | L63: -1947502.7 | M63: -1921894.6 | N63: -1883783.8 | O63: -2168677.9 | P63: -2168677.9 | Q63: -2158730.9 | R63: -2082174.6 | S63: -2008195.1 | T63: -2136027.1 | U63: -2136027.1 | V63: -2043931.4 | W63: -1829812.1 | X63: -1685416.7 | Y63: -1602845.2 | Z63: -1602845.2 | AA63: -1501261.3 | AB63: -1276928.7
A64: 1 | C64: 비지배주주지분 | E64: -13776.85 | F64: -13776.85 | G64: -14925.61 | H64: -18056.08 | I64: -22924.9 | J64: -22553.68 | K64: -22553.68 | L64: -25397.45 | M64: -27945.27 | N64: -31213.01 | O64: -30137.4 | P64: -30137.4 | Q64: -33614.48 | R64: -37270.51 | S64: -37902.17 | T64: -45141.84 | U64: -45141.84 | V64: -47036.82 | W64: -45203.09 | X64: -48506.35 | Y64: -53899.37 | Z64: -53899.37 | AA64: -58448.98 | AB64: -61044.99
A65: 1 | C65: 자본총계 | E65: 4097267.1 | F65: 4097267.1 | G65: 4033564.1 | H65: 4226155.1 | I65: 4491617.4 | J65: 3571937.4 | K65: 3571937.4 | L65: 3720467.9 | M65: 3708426.6 | N65: 3872126.2 | O65: 3409207.6 | P65: 3409207.6 | Q65: 3671871 | R65: 3918501.6 | S65: 3731177.2 | T65: 3749451.1 | U65: 3749451.1 | V65: 3807958.5 | W65: 3608957.3 | X65: 3945345.9 | Y65: 4095039.9 | Z65: 4095039.9 | AA65: 4455492.8 | AB65: 4710353.4
A66: 1 | C66: 부채와자본총계 | E66: 12138596 | F66: 12138596 | G66: 12286879 | H66: 13796449 | I66: 16861060 | J66: 14491698 | K66: 14491698 | L66: 14651888 | M66: 14981182 | N66: 16599199 | O66: 15593389 | P66: 15593389 | Q66: 16359005 | R66: 16778248 | S66: 15075969 | T66: 17194637 | U66: 17194637 | V66: 16281156 | W66: 13941719 | X66: 14539450 | Y66: 14948871 | Z66: 14948871 | AA66: 16568723 | AB66: 17959382
... A69: 1 | C69: 이자발생자산 | E69: 1654204.2 | F69: 1654204.2 | G69: 1607873.4 | H69: 3087254.4 | I69: 4578758.4 | J69: 3031841 | K69: 3031841 | L69: 2774179.5 | M69: 2960649.6 | N69: 3373879.6 | O69: 2205461.3 | P69: 2205461.3 | Q69: 2963817.1 | R69: 2901054.5 | S69: 2226751.3 | T69: 3157244.5 | U69: 3157244.5 | V69: 2481499 | W69: 1849195.3 | X69: 2738983 | Y69: 2297860.7 | Z69: 2297860.7 | AA69: 3260818.8 | AB69: 3346629.2
A70: 1 | C70: 확정급여부채 | I70: 3156.24
A71: 1 | C71: 단기투자자산(공정가치) | L71: 353997.77
A72: 1 | C72: 기타유동금융부채 | M72: 1281.62 | N72: 430.04 | O72: 42.37 | P72: 42.37 | Q72: 0 | R72: 0 | S72: 0 | T72: 1.83 | U72: 1.83 | V72: 1.83 | W72: 1.69 | X72: 1.75 | Y72: 0 | Z72: 0
A73: 1 | C73: 매출액(수익) | E73: 1846514.7 | G73: 1483846 | H73: 1426146.3 | I73: 1400129.1 | J73: 1634546.1 | K73: 5944667.5 | L73: 1605052 | M73: 1945786.6 | N73: 2025430.3 | O73: 2433161 | P73: 8009429.9 | Q73: 2347795.5 | R73: 2531955 | S73: 2322956.4 | T73: 2700371 | U73: 9903077.9 | V73: 2494285.9 | W73: 2682977.4 | X73: 2634818.8 | Y73: 2837928.6 | Z73: 10650011 | AA73: 2902250.6 | AB73: 3230712
A74: 1 | C74: 매출원가 | E74: 2010626.5 | G74: 1472935.6 | H74: 1599594.9 | I74: 1470457.9 | J74: 1863899.1 | K74: 6406887.4 | L74: 1496189.7 | M74: 1793369.9 | N74: 1838803.4 | O74: 2235593.2 | P74: 7363956.2 | Q74: 2183182.1 | R74: 2298993 | S74: 2095592.2 | T74: 2404748.5 | U74: 8982515.9 | V74: 2256680 | W74: 2357747 | X74: 2281437.6 | Y74: 2379819.9 | Z74: 9275684.6 | AA74: 2504199.1 | AB74: 2758634.9
A75: 1 | C75: 매출총이익 | E75: -164111.84 | G75: 10910.44 | H75: -173448.58 | I75: -70328.88 | J75: -229352.95 | K75: -462219.97 | L75: 108862.26 | M75: 152416.64 | N75: 186626.99 | O75: 197567.88 | P75: 645473.77 | Q75: 164613.46 | R75: 232961.99 | S75: 227364.11 | T75: 295622.49 | U75: 920562.05 | V75: 237605.87 | W75: 325230.37 | X75: 353381.19 | Y75: 458108.71 | Z75: 1374326.1 | AA75: 398051.54 | AB75: 472077.14
A76: 1 | C76: 판관비 | E76: 92967.25 | G76: 105818.78 | H76: 82293.32 | I76: 97589.93 | J76: 106498.97 | K76: 392201 | L76: 89305.2 | M76: 93502.3 | N76: 110752.7 | O76: 118568.8 | P76: 412129 | Q76: 86746.52 | R76: 102233.05 | S76: 107494.78 | T76: 121389.01 | U76: 417863.36 | V76: 114528.9 | W76: 120414.13 | X76: 115298.73 | Y76: 161873.5 | Z76: 512115.26 | AA76: 124933.06 | AB76: 147053.32
A77: 1 | C77: 영업이익 | E77: -257079.09 | G77: -94908.34 | H77: -255741.9 | I77: -167918.8 | J77: -335851.92 | K77: -854420.96 | L77: 19557.06 | M77: 58914.34 | N77: 75874.29 | O77: 78999.08 | P77: 233344.77 | Q77: 77866.94 | R77: 130728.94 | S77: 119869.33 | T77: 174233.47 | U77: 502698.68 | V77: 123076.97 | W77: 204816.24 | X77: 238082.46 | Y77: 296235.21 | Z77: 862210.88 | AA77: 273118.47 | AB77: 325023.82
A78: 1 | C78: 기타영업외수익 | E78: 118764.77 | G78: 369947.44 | H78: 1696122.7 | I78: 2518036.8 | J78: -1459281.7 | K78: 3124825.3 | L78: 997460.48 | M78: 362343.68 | N78: 973218.89 | O78: -545777.92 | P78: 1787245.1 | Q78: 1414239.4 | R78: 1109687.5 | S78: -692289.33 | T78: 3593578.5 | U78: 5425216.1 | V78: 348019.85 | W78: 1611255.6 | X78: -682190.01 | Y78: 189039.21 | Z78: 1466124.7 | AA78: 1701453.3 | AB78: 648223.55
A79: 1 | C79: 기타영업외비용 | E79: 81167.12 | G79: 359342.56 | H79: 1390390.5 | I79: 2538608.1 | J79: -1543560.3 | K79: 2744780.9 | L79: 962854.46 | M79: 367736.36 | N79: 973449.86 | O79: -134338.58 | P79: 2169702.1 | Q79: 1442637.4 | R79: 1124182.5 | S79: -692130.68 | T79: 4189354.8 | U79: 6064044 | V79: 398517.88 | W79: 1795075.3 | X79: -676001.65 | Y79: 204070.02 | Z79: 1721661.5 | AA79: 1710179.3 | AB79: 643851.68
A80: 1 | C80: 금융수익 | E80: 10806.6 | G80: 22578.79 | H80: 55816.92 | I80: 67052.68 | J80: 31702.51 | K80: 177150.9 | L80: 54080.7 | M80: 36681.61 | N80: 18883.17 | O80: 33362.3 | P80: 143007.78 | Q80: 58898.94 | R80: 86160.99 | S80: -42751 | T80: 80157.21 | U80: 182466.14 | V80: 157247.58 | W80: 333450.5 | X80: -22850.82 | Y80: 173333.64 | Z80: 641180.9 | AA80: 221234.39 | AB80: 123413.3
A81: 1 | C81: 금융비용 | E81: 35244.17 | G81: 40452.1 | H81: 73526.16 | I81: 113524.67 | J81: 29145.8 | K81: 256648.73 | L81: 102312.54 | M81: 65060.12 | N81: 63487.95 | O81: 58694.25 | P81: 289554.86 | Q81: 93127.26 | R81: 126435.8 | S81: 5261.89 | T81: 137019.36 | U81: 361844.31 | V81: 138943.95 | W81: 139932.04 | X81: 67878.3 | Y81: 250614.51 | Z81: 597368.8 | AA81: 356049.07 | AB81: 152787.27
A82: 1 | C82: 종속기업,공동지배기업및관계기업관련손익 | E82: -138.1 | G82: -98.23 | H82: -200.56 | I82: -176.08 | J82: -362 | K82: -836.87 | L82: -40.78 | M82: -2.58 | N82: -4.48 | O82: -5.3 | P82: -53.14 | Q82: 1.14 | R82: 3.66 | S82: -0.45 | T82: 0.86 | U82: 5.21 | V82: -2.46 | W82: -3.03 | X82: -0.84 | Y82: -1.17 | Z82: -7.5 | AA82: 5.73 | AB82: 0.14
A83: 1 | C83: 지분법관련손익 | E83: -138.1 | G83: -98.23 | H83: -200.56 | I83: -176.08 | J83: -362 | K83: -836.87 | L83: -40.78 | M83: -2.58 | N83: -4.48 | O83: -5.3 | P83: -53.14 | Q83: 1.14 | R83: 3.66 | S83: -0.45 | T83: 0.86 | U83: 5.21 | V83: -2.46 | W83: -3.03 | X83: -0.84 | Y83: -1.17 | Z83: -7.5 | AA83: 5.73 | AB83: 0.14
A84: 1 | C84: 법인세비용차감전계속사업이익 | E84: -244057.13 | G84: -102275 | H84: 32080.46 | I84: -235138.14 | J84: -249378.59 | K84: -554711.27 | L84: 5890.46 | M84: 25140.56 | N84: 31034.06 | O84: -357777.51 | P84: -295712.43 | Q84: 15241.68 | R84: 75962.84 | S84: 71697.33 | T84: -478404.07 | U84: -315502.22 | V84: 90880.11 | W84: 214512 | X84: 141164.14 | Y84: 203922.35 | Z84: 650478.6 | AA84: 129583.56 | AB84: 300021.86
... A92: 1 | C92: 총포괄손익 | E92: -168907.08 | G92: -63703.04 | H92: 192591.08 | I92: 265462.22 | J92: -919679.96 | K92: -525329.7 | L92: 148530.45 | M92: -12041.25 | N92: 163699.63 | O92: -462918.63 | P92: -162729.8 | Q92: 262663.39 | R92: 246630.6 | S92: -187324.4 | T92: 18273.92 | U92: 340243.51 | V92: 58507.4 | W92: -199021.17 | X92: 336388.59 | Y92: 149674.01 | Z92: 345548.83 | AA92: 360452.85 | AB92: 254840.62
A93: 1 | C93: 이자수익 | G93: 2446.48 | H93: 3299.61 | I93: 5349.96 | J93: 4771.55 | K93: 15867.6 | L93: 7638.78 | M93: 8019.89 | N93: 5525.98 | O93: 11674.09 | P93: 32858.74 | Q93: 4771.22 | R93: 7842.24 | S93: 3647.92 | T93: 4845.49 | U93: 21106.87 | V93: 4235.77 | W93: 3092.74 | X93: 3673.32 | Y93: 13928.03 | Z93: 24929.86 | AA93: 7622.71 | AB93: 10573.07
A94: 1 | C94: 이자비용 | G94: 15691.35 | H94: 16146.71 | I94: 25753.11 | J94: 42136.55 | K94: 99727.72 | L94: 39091.75 | M94: 41651.18 | N94: 46321.93 | O94: 51516.8 | P94: 178581.66 | Q94: 52254.22 | R94: 54278.54 | S94: 53815.31 | T94: 52898.58 | U94: 213246.65 | V94: 43191.45 | W94: 36942.59 | X94: 32231.19 | Y94: 27858 | Z94: 140223.23 | AA94: 19448.85 | AB94: 15343.95
A95: 1 | C95: 외환차익 | G95: 1296.91 | H95: 2524.58 | I95: 2381.14 | J95: 5041.23 | K95: 11243.86 | L95: 6068.69 | M95: 1673.63 | N95: 686.71 | O95: 4547.28 | P95: 12976.31 | Q95: 1630.75 | R95: 8740.08 | S95: 277.89 | T95: 2518.32 | U95: 13167.04 | V95: 3991.72 | W95: 8945.5 | X95: 5482.06 | Y95: 2264.02 | Z95: 20683.3 | AA95: 1209.67 | AB95: 3973.4
A96: 1 | C96: 외환차손 | G96: 2917.59 | H96: 6592.69 | I96: 12046.25 | J96: 16665.16 | K96: 38221.69 | L96: 12276.66 | M96: 7119.73 | N96: 5139.52 | O96: 4852.54 | P96: 29388.45 | Q96: 6683.21 | R96: 13993.17 | S96: 8981.13 | T96: 11455.82 | U96: 41113.33 | V96: 1367.88 | W96: 5402.58 | X96: 2636.42 | Y96: 2645.01 | Z96: 12051.89 | AA96: 3445.23 | AB96: 9687.51
A97: 1 | C97: 외화환산이익 | G97: 1044.19 | H97: 859.95 | I97: 4351.56 | J97: 23741.63 | K97: 29997.33 | L97: 148.52 | M97: 869.38 | N97: -103.19 | O97: 9195.02 | P97: 10109.73 | Q97: 7848.83 | R97: -7588.69 | S97: 17201.13 | T97: -15642.52 | U97: 1818.75 | V97: 2574.58 | W97: 20248.6 | X97: -13465.18 | Y97: -4297.71 | Z97: 5060.29 | AA97: 3173.54 | AB97: 4099.38
A98: 1 | C98: 외화환산손실 | G98: 7389.8 | H98: 18413.15 | I98: 37674.1 | J98: -48642.73 | K98: 14834.32 | L98: 14455.96 | M98: 4846.18 | N98: 4409.83 | O98: -12120.31 | P98: 11591.66 | Q98: 19128.83 | R98: 6840.82 | S98: -21917.15 | T98: 38031.29 | U98: 42083.79 | V98: 6760.62 | W98: -615.44 | X98: 3915.08 | Y98: 5180.66 | Z98: 15240.92 | AA98: 22326.35 | AB98: 4777.52
A99: 1 | C99: 파생상품이익 | G99: 17791.22 | H99: 49132.8 | I99: 54970.03 | J99: -1851.89 | K99: 120042.16 | L99: 40224.72 | M99: 26118.72 | N99: 12773.68 | O99: 7945.9 | P99: 87063.02 | Q99: 44648.14 | R99: 77167.37 | S99: -63877.94 | T99: 88435.94 | U99: 146373.51 | V99: 146445.51 | W99: 301163.67 | X99: -18541.01 | Y99: 161439.29 | Z99: 590507.46 | AA99: 209228.48 | AB99: 104767.46
A100: 1 | C100: 파생상품손실 | G100: 14453.37 | H100: 32373.6 | I100: 38051.21 | J100: 10713.02 | K100: 95591.2 | L100: 33087.85 | M100: 7885.07 | N100: 4133.9 | O100: 10226.15 | P100: 55332.97 | Q100: 14802.14 | R100: 51018.75 | S100: -35868.07 | T100: -2969.52 | U100: 26983.3 | V100: 87359.13 | W100: 98071.83 | X100: 29194.95 | Y100: 214521.84 | Z100: 429147.75 | AA100: 310828.63 | AB100: 122978.29
A101: 1 | C101: 이자손익 | G101: -13244.87 | H101: -12847.1 | I101: -20403.15 | J101: -37365 | K101: -83860.12 | L101: -31452.97 | M101: -33631.29 | N101: -40795.95 | O101: -39842.71 | P101: -145722.92 | Q101: -47483 | R101: -46436.3 | S101: -50167.39 | T101: -48053.09 | U101: -192139.78 | V101: -38955.68 | W101: -33849.85 | X101: -28557.87 | Y101: -13929.97 | Z101: -115293.37 | AA101: -11826.14 | AB101: -4770.88
A102: 1 | C102: 영업활동으로인한현금흐름 | E102: 73090.05 | G102: -195503.4 | H102: -117297.68 | I102: -1159537.2 | J102: -220682.46 | K102: -1693020.7 | L102: 280015.58 | M102: -325934.21 | N102: -408677.03 | O102: -61870.9 | P102: -516466.56 | Q102: 299282.43 | R102: -435255.69 | S102: 100661.91 | T102: 689831.29 | U102: 654519.94 | V102: -131050.83 | W102: 401494.8 | X102: 1367889.1 | Y102: -75484.3 | Z102: 1562848.8 | AA102: 1488808.6 | AB102: 818125.83
A103: 1 | C103: 이자수취(CF) | E103: 24028.25 | G103: 10317.76 | H103: 12349.83 | I103: 11519.3 | J103: -1869.9 | K103: 32316.99 | L103: 12466.36 | M103: 8780.48 | N103: 13185.23 | O103: 13498.97 | P103: 47931.04 | Q103: 18272.57 | R103: 9984.21 | S103: 6345.51 | T103: 6768.07 | U103: 41370.36 | V103: 7356.31 | W103: 6381.38 | X103: 6611.83 | Y103: 10288.29 | Z103: 30637.81 | AA103: 10011.24 | AB103: 9872.68
A104: 1 | C104: 이자지급(CF) | E104: -39539.07 | G104: -24558.99 | H104: -16854.85 | I104: -22936.52 | J104: -28162.47 | K104: -92512.83 | L104: -26000.8 | M104: -52785.78 | N104: -43706.08 | O104: -60935.51 | P104: -183428.17 | Q104: -74156.66 | R104: -59938.66 | S104: -50700.9 | T104: -82384.98 | U104: -267181.2 | V104: -47326.54 | W104: -43244.7 | X104: -32996.68 | Y104: -46398.47 | Z104: -169966.39 | AA104: -24199.24 | AB104: -14702.43
A105: 1 | C105: 배당금수취(CF) | E105: 0 | I105: 0 | J105: 0 | N105: -0.21 | O105: 0 | S105: 0 | T105: 0 | X105: 0 | Y105: 0 | AA105: 246.84 | AB105: 682.67
A106: 1 | C106: 법인세납부(CF) | E106: 11290.53 | G106: 8055.68 | H106: 7491.26 | I106: -36190.91 | J106: -10504.01 | K106: -31147.98 | N106: -1187.31 | O106: -2594.71 | Q106: -4012.81 | R106: -1210.86 | S106: -1860.38 | T106: -958.79 | U106: -8042.84 | V106: -267.44 | W106: 2467.73 | X106: -1532.34 | Y106: -2758.61 | Z106: -2090.66 | AA106: -6700.74 | AB106: -10806.16
A107: 1 | C107: 투자활동으로인한현금흐름 | E107: -87857.6 | G107: 409903.94 | H107: 227288.32 | I107: 237106.74 | J107: 227768.05 | K107: 1102067.1 | L107: -640775.89 | M107: 378685.81 | N107: 83125.49 | O107: -15779.9 | P107: -194744.49 | Q107: 34292.81 | R107: -30865.52 | S107: -13103.59 | T107: 320203.66 | U107: 310527.36 | V107: -170854.7 | W107: 36977.32 | X107: -240693.62 | Y107: -105808.87 | Z107: -480379.87 | AA107: -330587.3 | AB107: -938806.23
A108: 1 | C108: 유형자산의증가 | E108: 6215.37 | G108: 17466.06 | H108: 14586.68 | I108: 9456.49 | J108: 20900.76 | K108: 62409.99 | L108: 26244.76 | M108: 42229.93 | N108: 45027.13 | O108: 39918.11 | P108: 153419.93 | Q108: 28467.26 | R108: 35507.25 | S108: 43971.29 | T108: 65449.16 | U108: 173394.96 | V108: 41791.51 | W108: 66823.74 | X108: 51943.64 | Y108: 55695.83 | Z108: 216254.72 | AA108: 35789.81 | AB108: 61171.15
A109: 1 | C109: CAPEX | E109: 6215.37 | G109: 17466.06 | H109: 14586.68 | I109: 9456.49 | J109: 20900.76 | K109: 62409.99 | L109: 26244.76 | M109: 42229.93 | N109: 45067.8 | O109: 39917.98 | P109: 153460.47 | Q109: 28482.94 | R109: 35507.44 | S109: 43971.36 | T109: 65453.08 | U109: 173414.82 | V109: 41791.51 | W109: 66823.74 | X109: 51943.64 | Y109: 55695.83 | Z109: 216254.72 | AA109: 35789.81 | AB109: 61171.15
A110: 1 | C110: 유형자산의감소 | E110: 138495.94 | G110: 5944.07 | H110: 23475.18 | J110: 297766.99 | L110: 39.3 | M110: 970.33 | N110: 180.96 | O110: 503.83 | P110: 1694.42 | Q110: 399.8 | R110: 662.53 | S110: 173.24 | T110: 382480.37 | U110: 383715.94 | V110: 18505.89 | W110: 295.92 | X110: 499.2 | Y110: 2326.03 | Z110: 21627.04 | AA110: 507.98 | AB110: 334.53
A111: 1 | C111: 무형자산의감소 | E111: 0 | I111: 10.97 | J111: -0.91
A112: 1 | C112: 재무활동으로인한현금흐름 | E112: -572668.07 | G112: -131800.92 | H112: 123199.84 | I112: 838202.92 | J112: 117207.9 | K112: 946809.74 | L112: -273036.63 | M112: 313328.34 | N112: 167118.79 | O112: 168589.2 | P112: 375999.7 | Q112: -137462.25 | R112: 9263.79 | S112: 219287.87 | T112: -690305.09 | U112: -599215.68 | V112: -134240.53 | W112: -358878.94 | X112: -321042.86 | Y112: -452353.85 | Z112: -1266516.2 | AA112: -896453.12 | AB112: -113016
A113: 1 | C113: 단기차입금의증가 | E113: 233841.15 | G113: 172835.71 | H113: 424867.94 | I113: 941183.2 | J113: 301254.04 | K113: 1840140.9 | L113: 552455.7 | M113: 428462.83 | N113: 676363.71 | O113: 516942.92 | P113: 2174225.2 | Q113: 1010071.6 | R113: 865604.85 | S113: 979079.1 | T113: 626139.28 | U113: 3480894.8 | V113: 749564.59 | W113: 481342.71 | X113: 580886.7 | Y113: 184765.85 | Z113: 1996559.9 | AA113: 146391.58 | AB113: 182068.51
A114: 1 | C114: 단기차입금의감소 | E114: 1006718.2 | G114: 286966.15 | H114: 509245.4 | I114: 115510.54 | J114: 422545.09 | K114: 1334267.2 | L114: 761234.42 | M114: 177333.3 | N114: 484470.61 | O114: 306608.99 | P114: 1729647.3 | Q114: 807134.12 | R114: 760031.59 | S114: 688720.68 | T114: 983191.98 | U114: 3239078.4 | V114: 788760.36 | W114: 714152.22 | X114: 778178.14 | Y114: 430410.95 | Z114: 2711501.7 | AA114: 862182.78 | AB114: 167365.29
A115: 1 | C115: 유동성장기부채의감소 | E115: 1169979 | G115: 117791 | H115: 317138 | I115: 170650 | J115: 30000 | K115: 635579 | L115: 94314.53 | M115: 679585.73 | O115: 0 | Q115: 315644 | R115: 180110 | S115: 247676 | T115: 388753 | U115: 1132183 | V115: 78961 | W115: 302284 | X115: 399177 | Y115: 182185 | Z115: 962607 | AA115: 164865.01 | AB115: 117502.27
A116: 1 | C116: 사채의증가 | E116: 0 | I116: 0 | J116: 79539.16 | L116: 44909.51 | M116: 179638.2 | N116: 0 | O116: 0 | P116: 224547.71 | Q116: 0 | R116: 0 | S116: 0 | T116: 0 | U116: 0 | Y116: 0
A117: 1 | C117: 장기차입금의증가 | E117: 100000 | G117: 110145 | H117: 361407 | I117: 194447.54 | J117: 205001.19 | K117: 871000.73 | N117: 0 | O117: 117530 | Q117: 107012.16 | R117: 105319.33 | S117: 198041.69 | T117: 76345.47 | U117: 486718.65 | V117: 1656.09 | W117: 195583.36 | AA117: 0 | AB117: 0
A118: 1 | C118: 리스부채의상환 | E118: 5486.85 | G118: 10024.48 | H118: 16751.48 | I118: 11267.28 | J118: 16041.39 | K118: 54084.63 | L118: 15805.12 | M118: 19196.43 | N118: 14105.85 | O118: 14775.23 | P118: 63882.63 | Q118: 20849.73 | R118: 21496.91 | S118: 21436.23 | T118: 20823.64 | U118: 84606.51 | V118: 17739.85 | W118: 19368.79 | X118: 22221.57 | Y118: 22861.36 | Z118: 82191.57 | AA118: 15796.91 | AB118: 10236.95
A119: 1 | C119: 현금및현금성자산의증감 | E119: -587435.63 | G119: 82599.62 | H119: 233190.47 | I119: -84227.51 | J119: 124293.51 | K119: 355856.09 | L119: -633796.94 | M119: 366079.94 | N119: -158432.75 | O119: 90938.4 | P119: -335211.35 | Q119: 196112.99 | R119: -456857.41 | S119: 306846.19 | T119: 319729.84 | U119: 365831.61 | V119: -436146.06 | W119: 79593.17 | X119: 806152.62 | Y119: -633647.01 | Z119: -184047.28 | AA119: 261768.16 | AB119: -233696.4
...

Sheet BS별도
B1: (백만원) | C1: 이름: BS별도H | E1: 4Q21 | F1: 2021 | G1: 1Q22 | H1: 2Q22 | I1: 3Q22 | J1: 4Q22 | K1: 2022 | L1: 1Q23 | M1: 2Q23 | N1: 3Q23 | O1: 4Q23 | P1: 2023 | Q1: 1Q24 | R1: 2Q24 | S1: 3Q24 | T1: 4Q24 | U1: 2024 | V1: 1Q25 | W1: 2Q25 | X1: 3Q25 | Y1: 4Q25 | Z1: 2025 | AA1: 1Q26 | AB1: 2Q26 | AC1: 3Q26 | AD1: 4Q26 | AE1: 2026 | AF1: 1Q27 | AG1: 2Q27 | AH1: 3Q27 | AI1: 4Q27 | AJ1: 2027 | AK1: 1Q28 | AL1: 2Q28 | AM1: 3Q28 | AN1: 4Q28 | AO1: 2028
B2: 별도 | D2: fin json(kship_fin.py)
B3: 삼성중공업(별) | C3: UPDATE: 26-10-19 | E3: 1 | F3: 2 | G3: 3 | H3: 4 | I3: 5 | J3: 6 | K3: 7 | L3: 8 | M3: 9 | N3: 10 | O3: 11 | P3: 12 | Q3: 13 | R3: 14 | S3: 15 | T3: 16 | U3: 17 | V3: 18 | W3: 19 | X3: 20 | Y3: 21 | Z3: 22 | AA3: 23 | AB3: 24 | AC3: 25 | AD3: 26 | AE3: 27 | AF3: 28 | AG3: 29 | AH3: 30 | AI3: 31 | AJ3: 32 | AK3: 33 | AL3: 34 | AM3: 35 | AN3: 36 | AO3: 37
B4: Account Code | C4: AccountNAME | E4: 2021.12 | F4: 2021.12A | G4: 2022.03 | H4: 2022.06 | I4: 2022.09 | J4: 2022.12 | K4: 2022.12A | L4: 2023.03 | M4: 2023.06 | N4: 2023.09 | O4: 2023.12 | P4: 2023.12A | Q4: 2024.03 | R4: 2024.06 | S4: 2024.09 | T4: 2024.12 | U4: 2024.12A | V4: 2025.03 | W4: 2025.06 | X4: 2025.09 | Y4: 2025.12 | Z4: 2025.12A | AA4: 2026.03 | AB4: 2026.06 | AC4: 2026.09 | AD4: 2026.12 | AE4: 2026.12A | AF4: 2027.03 | AG4: 2027.06 | AH4: 2027.09 | AI4: 2027.12 | AJ4: 2027.12A | AK4: 2028.03 | AL4: 2028.06 | AM4: 2028.09 | AN4: 2028.12 | AO4: 2028.12A
A5: 1 | C5: 유동자산 | E5: 5381314 | F5: 5381314 | G5: 5591731.4 | H5: 6745400 | I5: 9179954.6 | J5: 8080046.7 | K5: 8080046.7 | L5: 8432823.1 | M5: 8816102.5 | N5: 10528799 | O5: 9106451.4 | P5: 9106451.4 | Q5: 9696673.3 | R5: 9876070.3 | S5: 8480249.6 | T5: 9329871 | U5: 9329871 | V5: 8632608.6 | W5: 6961978.7 | X5: 7269760.7 | Y5: 7338656.9 | Z5: 7338656.9 | AA5: 8261589.8 | AB5: 9656586.2
A6: 1 | C6: 현금및현금성자산 | E6: 514394.69 | F6: 514394.69 | G6: 614926.47 | H6: 489414.73 | I6: 419090.75 | J6: 514997.41 | K6: 514997.41 | L6: 212662.85 | M6: 592953.89 | N6: 389818.56 | O6: 519631.73 | P6: 519631.73 | Q6: 765620.16 | R6: 272322.38 | S6: 567800.38 | T6: 888448.68 | U6: 888448.68 | V6: 471581.61 | W6: 566760.97 | X6: 1346737.8 | Y6: 685976.42 | Z6: 685976.42 | AA6: 1004973.8 | AB6: 758888.15
A7: 1 | C7: 단기금융상품 | E7: 569031.92 | F7: 569031.92 | G7: 167199.94 | H7: 318436.04 | I7: 70607.48 | J7: 84557.13 | K7: 84557.13 | L7: 348914.05 | M7: 288916.6 | N7: 163843.33 | O7: 136908.15 | P7: 136908.15 | Q7: 86908.95 | R7: 58774.68 | S7: 33976.92 | T7: 33851.15 | U7: 33851.15 | V7: 36804.68 | W7: 36830.1 | X7: 236937.39 | Y7: 287050.93 | Z7: 287050.93 | AA7: 586672.09 | AB7: 716570.94
A8: 1 | C8: 단기금융자산 | E8: 1006869.9 | F8: 1006869.9 | G8: 857597.79 | H8: 2092704.4 | I8: 3663628.9 | J8: 1993508.2 | K8: 1993508.2 | L8: 2373603 | M8: 2199548.2 | N8: 2772081.9 | O8: 1511350.7 | P8: 1511350.7 | Q8: 2079864 | R8: 2457514.8 | S8: 1488990.9 | T8: 2082031.4 | U8: 2082031.4 | V8: 1832210.6 | W8: 1099234.3 | X8: 1129633.7 | Y8: 1332121.7 | Z8: 1332121.7 | AA8: 2035265.4 | AB8: 2346689.2
A9: 1 | C9: 매출채권및기타채권 | E9: 126417.22 | F9: 126417.22 | G9: 179496 | H9: 226529.09 | I9: 233311.61 | J9: 896928.79 | K9: 896928.79 | L9: 496705.52 | M9: 346862.25 | N9: 998045.75 | O9: 512517.29 | P9: 512517.29 | Q9: 569171.21 | R9: 557381.04 | S9: 439410.15 | T9: 1239581.9 | U9: 1239581.9 | V9: 1024362.4 | W9: 570927.8 | X9: 427663.12 | Y9: 1483387.4 | Z9: 1483387.4 | AA9: 699595.36 | AB9: 692857.16
A10: 1 | C10: 계약자산 | E10: 1626474.6 | F10: 1626474.6 | G10: 1740955.5 | H10: 1749710.4 | I10: 2449946.2 | J10: 2319153.1 | K10: 2319153.1 | L10: 2369921.3 | M10: 2934565.5 | N10: 3497798.6 | O10: 3783888.8 | P10: 3783888.8 | Q10: 4039461.9 | R10: 4568227.4 | S10: 3916158.6 | T10: 3572702.9 | U10: 3572702.9 | V10: 3461667.3 | W10: 3143533.6 | X10: 2757869.3 | Y10: 2176503 | Z10: 2176503 | AA10: 2673891.9 | AB10: 3335138.2
A11: 1 | C11: 선급금 | E11: 383604.15 | F11: 383604.15 | G11: 413476.26 | H11: 477250.63 | I11: 552039.34 | J11: 551406.55 | K11: 551406.55 | L11: 612029.97 | M11: 689282.85 | N11: 700986.09 | O11: 786319.82 | P11: 786319.82 | Q11: 787269.12 | R11: 827461.17 | S11: 854406.76 | T11: 882532.54 | U11: 882532.54 | V11: 962464.18 | W11: 828167.66 | X11: 868252.95 | Y11: 904168.57 | Z11: 904168.57 | AA11: 838022.29 | AB11: 969608.02
A12: 1 | C12: 선급금등 | E12: 383604.15 | F12: 383604.15 | G12: 413476.26 | H12: 477250.63 | I12: 552039.34 | J12: 551406.55 | K12: 551406.55 | L12: 612029.97 | M12: 689282.85 | N12: 700986.09 | O12: 786319.82 | P12: 786319.82 | Q12: 787269.12 | R12: 827461.17 | S12: 854406.76 | T12: 882532.54 | U12: 882532.54 | V12: 962464.18 | W12: 828167.66 | X12: 868252.95 | Y12: 904168.57 | Z12: 904168.57 | AA12: 838022.29 | AB12: 969608.02
A13: 1 | C13: 기타유동자산 | E13: 521869.02 | F13: 521869.02 | G13: 565714.07 | H13: 555998.7 | I13: 725568.98 | J13: 709864.87 | K13: 709864.87 | L13: 829091.86 | M13: 887052.81 | N13: 913515.25 | O13: 971787.39 | P13: 971787.39 | Q13: 984196.96 | R13: 1025482.5 | S13: 1070601.2 | T13: 1029667.2 | U13: 1029667.2 | V13: 1145074.5 | W13: 1025782.2 | X13: 1087759.5 | Y13: 1119489.4 | Z13: 1119489.4 | AA13: 1066424.8 | AB13: 1201568.4
A14: 1 | C14: 유동파생상품자산 | E14: 157360.32 | F14: 157360.32 | G14: 234481.53 | H14: 447472.85 | I14: 918172.42 | J14: 847878.35 | K14: 847878.35 | L14: 544129.89 | M14: 386894.49 | N14: 492699.28 | O14: 261289.15 | P14: 261289.15 | Q14: 307901.87 | R14: 370604.47 | S14: 237352.87 | T14: 627496.48 | U14: 627496.48 | V14: 427570.29 | W14: 529142.31 | X14: 241253.64 | Y14: 358110.48 | Z14: 358110.48 | AA14: 459157.53 | AB14: 548727.3
A15: 1 | C15: 유동확정계약자산 | E15: 280477.68 | F15: 280477.68 | G15: 455916.32 | H15: 1326795.5 | I15: 2674849 | J15: 1061072.8 | K15: 1061072.8 | L15: 1480559.1 | M15: 1523737.1 | N15: 2115539.2 | O15: 1113153.4 | P15: 1113153.4 | Q15: 1685053.2 | R15: 2028135.6 | S15: 1217661.1 | T15: 1420683.7 | U15: 1420683.7 | V15: 1367835.6 | W15: 533261.85 | X15: 651442.67 | Y15: 686960.31 | Z15: 686960.31 | AA15: 989435.75 | AB15: 1081391
A16: 1 | C16: 재고자산 | E16: 1483010.1 | F16: 1483010.1 | G16: 1545048.8 | H16: 1541992.6 | I16: 1596910.3 | J16: 1569405.5 | K16: 1569405.5 | L16: 1718239.3 | M16: 1773731 | N16: 1875278.9 | O16: 1727875.7 | P16: 1727875.7 | Q16: 1178079.2 | R16: 917790.68 | S16: 920617.91 | T16: 450129.4 | U16: 450129.4 | V16: 497313.26 | W16: 486923.95 | X16: 447773.89 | Y16: 474335.77 | Z16: 474335.77 | AA16: 683622.64 | AB16: 496015.75
A17: 1 | C17: 당기법인세자산(선급법인세) | E17: 1725.44 | F17: 1725.44 | G17: 554.37 | H17: 994.23 | I17: 1597.75 | J17: 2316.49 | K17: 2316.49 | L17: 1078.95 | M17: 2066.78 | N17: 3465.43 | O17: 4858.18 | P17: 4858.18 | Q17: 6364.4 | R17: 2746.2 | S17: 3420.95 | T17: 4118.13 | U17: 4118.13 | V17: 4936.12 | W17: 1513.35 | X17: 2116.62 | Y17: 0 | Z17: 0 | AB17: 2.74
A18: 1 | C18: 기타유동금융자산 | E18: 85604.13 | F18: 85604.13 | G18: 87438.35 | H18: 88055.89 | I18: 89900.19 | J18: 73872.21 | K18: 73872.21 | L18: 77522.5 | M18: 79322.07 | N18: 78794.2 | O18: 74541.61 | P18: 74541.61 | Q18: 73915.34 | R18: 74605.3 | S18: 73249.46 | T18: 63191.45 | U18: 63191.45 | V18: 195462.85 | W18: 67302.61 | X18: 70206.74 | Y18: 66843.2 | Z18: 66843.2 | AA18: 97815.82 | AB18: 825426.61
A19: 1 | C19: 매각예정비유동자산및처분자산 | E19: 14948.88 | F19: 14948.88
A20: 1 | C20: 비유동자산 | E20: 6510823.6 | F20: 6510823.6 | G20: 6470973 | H20: 7215958.6 | I20: 7882184.1 | J20: 6659327 | K20: 6659327 | L20: 6450685.2 | M20: 6450084.6 | N20: 6398646.7 | O20: 6785527.3 | P20: 6785527.3 | Q20: 6644185.1 | R20: 6831606 | S20: 6508097.2 | T20: 7667982.7 | U20: 7667982.7 | V20: 7481500.8 | W20: 6855938 | X20: 7118134.9 | Y20: 7436031.5 | Z20: 7436031.5 | AA20: 8174325.3 | AB20: 8141604.9
A21: 1 | C21: 장기금융자산 | E21: 45407.88 | F21: 45407.88 | G21: 46210.92 | H21: 46062.7 | I21: 45702.02 | J21: 85516.68 | K21: 85516.68 | L21: 85540.04 | M21: 85776.98 | N21: 85711.42 | O21: 86920.34 | P21: 86920.34 | Q21: 87199.19 | R21: 108044.74 | S21: 107939.26 | T21: 124061.82 | U21: 124061.82 | V21: 141630.07 | W21: 173935.46 | X21: 232676.82 | Y21: 223462.59 | Z21: 223462.59 | AA21: 224002.96 | AB21: 239773.31
A22: 1 | C22: 투자자산 | E22: 992461.37 | F22: 992461.37 | G22: 976826.87 | H22: 1858475.3 | I22: 2689260.8 | J22: 1405108.9 | K22: 1405108.9 | L22: 1220649.4 | M22: 1218773.1 | N22: 1220333.7 | O22: 1313998.5 | P22: 1313998.5 | Q22: 1207440.3 | R22: 1444273.9 | S22: 1072079 | T22: 1973587.7 | U22: 1973587.7 | V22: 1838323.8 | W22: 1105629.9 | X22: 1451248.7 | Y22: 1872182.5 | Z22: 1872182.5 | AA22: 2719477.9 | AB22: 2789722.6
A23: 1 | C23: 종속기업및관계기업투자 | E23: 433809.51 | F23: 433809.51 | G23: 433809.51 | H23: 1023809.5 | I23: 1023809.5 | J23: 1021319.5 | K23: 1021319.5 | L23: 853509.41 | M23: 853509.41 | N23: 853509.41 | O23: 853509.41 | P23: 853509.41 | Q23: 517944.31 | R23: 399193.53 | S23: 399193.53 | T23: 272256.49 | U23: 272256.49 | V23: 281348.42 | W23: 283328.42 | X23: 283328.42 | Y23: 285307.83 | Z23: 285307.83 | AA23: 285307.83 | AB23: 288779.63
A24: 1 | C24: 유형자산 | E24: 5187279.1 | F24: 5187279.1 | G24: 5160256.6 | H24: 5135923.5 | I24: 5110971 | J24: 4848270.8 | K24: 4848270.8 | L24: 4837204.9 | M24: 4836165.3 | N24: 4841477.5 | O24: 4841052.2 | P24: 4841052.2 | Q24: 4824013.6 | R24: 4819229.6 | S24: 4817534.2 | T24: 4715386.9 | U24: 4715386.9 | V24: 4680159 | W24: 4702737.4 | X24: 4706809.4 | Y24: 4716240.8 | Z24: 4716240.8 | AA24: 4703190.5 | AB24: 4714297.4
A25: 1 | C25: 투자부동산 | E25: 17616.35 | F25: 17616.35 | G25: 17576.88 | H25: 276.71 | I25: 275.67 | J25: 274.64 | K25: 274.64 | L25: 273.6 | O25: 0 | P25: 0 | T25: 0 | U25: 0
A26: 1 | C26: 무형자산 | E26: 22877.29 | F26: 22877.29 | G26: 23260.26 | H26: 23479.77 | I26: 23498.52 | J26: 26088.79 | K26: 26088.79 | L26: 26466.04 | M26: 26622.51 | N26: 26671.9 | O26: 26666.12 | P26: 26666.12 | Q26: 26552.44 | R26: 26626.08 | S26: 27503.76 | T26: 27561.3 | U26: 27561.3 | V26: 32721.26 | W26: 31975.54 | X26: 31833.44 | Y26: 31797.93 | Z26: 31797.93 | AA26: 35329.76 | AB26: 37939.08
A27: 1 | C27: 기타비유동자산 | E27: 43741.81 | F27: 43741.81 | G27: 54472.31 | H27: 42677.2 | I27: 45993.28 | J27: 174372.93 | K27: 174372.93 | L27: 197922.05 | M27: 194296.44 | N27: 180272.29 | O27: 258131.99 | P27: 258131.99 | Q27: 316447.13 | R27: 322110.92 | S27: 288993.02 | T27: 306563.1 | U27: 306563.1 | V27: 275413.13 | W27: 239853.87 | X27: 209866.95 | Y27: 235393.65 | Z27: 235393.65 | AA27: 230184.01 | AB27: 172133.96
A28: 1 | C28: 비유동파생상품자산 | E28: 145141.39 | F28: 145141.39 | G28: 139065.54 | H28: 244581.2 | I28: 375130.81 | J28: 83310.77 | K28: 83310.77 | L28: 57634.16 | M28: 51230.65 | N28: 33177.76 | O28: 95504.63 | P28: 95504.63 | Q28: 60902.38 | R28: 114313.77 | S28: 101646.1 | T28: 276472.07 | U28: 276472.07 | V28: 246317.46 | W28: 235830.96 | X28: 156941.09 | Y28: 242790.83 | Z28: 242790.83 | AA28: 436336.76 | AB28: 454061.37
A29: 1 | C29: 비유동확정계약자산 | E29: 368102.59 | F29: 368102.59 | G29: 357740.9 | H29: 544021.9 | I29: 1244618.5 | J29: 214961.98 | K29: 214961.98 | L29: 223965.8 | M29: 228256.06 | N29: 247935.1 | O29: 278064.15 | P29: 278064.15 | Q29: 541394.44 | R29: 822721.89 | S29: 463300.14 | T29: 1300797.3 | U29: 1300797.3 | V29: 1169027.8 | W29: 412535.02 | X29: 778302.39 | Y29: 1120621.3 | Z29: 1120621.3 | AA29: 1773830.4 | AB29: 1807108.3
A30: 1 | C30: 장기매출채권및기타채권 | E30: 10411.32 | F30: 10411.32 | G30: 13418.35
A31: 1 | C31: 이연법인세자산 | E31: 236436.33 | F31: 236436.33 | G31: 225161.76 | H31: 155126.05 | I31: 12184.82 | J31: 205210.92 | K31: 205210.92 | L31: 168169.22 | M31: 174227.28 | N31: 129891.39 | O31: 345678.47 | P31: 345678.47 | Q31: 269731.65 | R31: 219365.47 | S31: 301987.23 | T31: 644883.75 | U31: 644883.75 | V31: 654883.63 | W31: 775741.34 | X31: 718376.42 | Y31: 580416.56 | Z31: 580416.56 | AA31: 486143.2 | AB31: 427511.9
A32: 1 | C32: 자산총계 | E32: 11892138 | F32: 11892138 | G32: 12062704 | H32: 13961359 | I32: 17062139 | J32: 14739374 | K32: 14739374 | L32: 14883508 | M32: 15266187 | N32: 16927445 | O32: 15891979 | P32: 15891979 | Q32: 16340858 | R32: 16707676 | S32: 14988347 | T32: 16997854 | U32: 16997854 | V32: 16114109 | W32: 13817917 | X32: 14387896 | Y32: 14774688 | Z32: 14774688 | AA32: 16435915 | AB32: 17798191
A33: 1 | C33: 유동부채 | E33: 6731070.9 | F33: 6731070.9 | G33: 6938717.9 | H33: 7603021.1 | I33: 9776618.6 | J33: 9494896.2 | K33: 9494896.2 | L33: 9892309.1 | M33: 9959821.3 | N33: 11936723 | O33: 11659137 | P33: 11659137 | Q33: 11860797 | R33: 11979132 | S33: 10851241 | T33: 11878027 | U33: 11878027 | V33: 11049769 | W33: 9455032.3 | X33: 9345607.2 | Y33: 9295708.1 | Z33: 9295708.1 | AA33: 9899119.7 | AB33: 10914452
A34: 1 | C34: 매입채무및기타채무 | E34: 804437.68 | F34: 804437.68 | G34: 821915.14 | H34: 885826.7 | I34: 947143.77 | J34: 1004306.1 | K34: 1004306.1 | L34: 908956.78 | M34: 1017163.8 | N34: 1093903 | O34: 1120716 | P34: 1120716 | Q34: 1584271.1 | R34: 1017611.5 | S34: 856168.13 | T34: 924606.3 | U34: 924606.3 | V34: 878041.55 | W34: 872010.25 | X34: 830448.09 | Y34: 1017053.7 | Z34: 1017053.7 | AA34: 1099461.9 | AB34: 1408096.6
A35: 1 | C35: 단기차입금 | E35: 802069.76 | F35: 802069.76 | G35: 707074.8 | H35: 637305.8 | I35: 1491442.8 | J35: 1284231.3 | K35: 1284231.3 | L35: 1068100.8 | M35: 1295121.2 | N35: 1540149.7 | O35: 1717150.1 | P35: 1717150.1 | Q35: 1941809.1 | R35: 2092596.7 | S35: 2338458.6 | T35: 2032630.1 | U35: 2032630.1 | V35: 2020967.3 | W35: 1783280.6 | X35: 1587251.7 | Y35: 1343121.6 | Z35: 1343121.6 | AA35: 695805.56 | AB35: 706848.25
A36: 1 | C36: 계약부채 | E36: 2458884.6 | F36: 2458884.6 | G36: 2661272.3 | H36: 2693974.6 | I36: 2783246.6 | J36: 3644426 | K36: 3644426 | L36: 4077260.4 | M36: 4024848.7 | N36: 4776546.2 | O36: 4558317 | P36: 4558317 | Q36: 5001661.2 | R36: 5428904.8 | S36: 5203133.6 | T36: 5462956.8 | U36: 5462956.8 | V36: 5509860.5 | W36: 5070288 | X36: 5367437 | Y36: 4576789.8 | Z36: 4576789.8 | AA36: 4950344.8 | AB36: 5433599.9
A37: 1 | C37: 단기파생상품부채 | E37: 369510.68 | F37: 369510.68 | G37: 489325.36 | H37: 1102591.1 | I37: 2669046.3 | J37: 1094132.8 | K37: 1094132.8 | L37: 1174497.7 | M37: 1151054.2 | N37: 1720295.8 | O37: 719442.42 | P37: 719442.42 | Q37: 984974.04 | R37: 1272684.3 | S37: 377136.67 | T37: 2065507 | U37: 2065507 | V37: 1236269.9 | W37: 406352.66 | X37: 619570 | Y37: 798883.58 | Z37: 798883.58 | AA37: 1393515.9 | AB37: 1693887
A38: 1 | C38: 단기금융부채 | E38: 382945.78 | F38: 382945.78 | G38: 506329.52 | H38: 1119328.8 | I38: 2684562.4 | J38: 1126516.8 | K38: 1126516.8 | L38: 1224772.3 | M38: 1194519.8 | N38: 1756912.8 | O38: 750719.74 | P38: 750719.74 | Q38: 1070044.9 | R38: 1355767.6 | S38: 454297.35 | T38: 2130544.5 | U38: 2130544.5 | V38: 1317704.2 | W38: 480259.99 | X38: 693756.79 | Y38: 863051.35 | Z38: 863051.35 | AA38: 1463133 | AB38: 1747334.1
A39: 1 | C39: 유동성장기부채 | E39: 927141.09 | F39: 927141.09 | G39: 856555.67 | H39: 774345.18 | I39: 552595.28 | J39: 1059424.7 | K39: 1059424.7 | L39: 1417303.4 | M39: 1384008.6 | N39: 1855922.4 | O39: 2225307.4 | P39: 2225307.4 | Q39: 1528493.1 | R39: 1404845.8 | S39: 1453914.3 | T39: 925634.84 | U39: 925634.84 | V39: 901182.55 | W39: 852965.56 | X39: 459548.14 | Y39: 277372.89 | Z39: 277372.89 | AA39: 114971.54 | AB39: 0
A40: 1 | C40: 유동리스부채 | E40: 13435.1 | F40: 13435.1 | G40: 17004.16 | H40: 16737.64 | I40: 15516.04 | J40: 32383.96 | K40: 32383.96 | L40: 50274.64 | M40: 43465.61 | N40: 36616.95 | O40: 31277.32 | P40: 31277.32 | Q40: 85070.84 | R40: 83083.36 | S40: 77160.68 | T40: 65037.53 | U40: 65037.53 | V40: 81434.32 | W40: 73907.33 | X40: 74186.79 | Y40: 64167.77 | Z40: 64167.77 | AA40: 69617.09 | AB40: 53447.08
A41: 1 | C41: 리스부채 | E41: 24825.79 | F41: 24825.79 | G41: 24817.38 | H41: 20143.71 | I41: 18992.08 | J41: 56027.95 | K41: 56027.95 | L41: 80671.7 | M41: 69567.98 | N41: 59561.41 | O41: 130102.62 | P41: 130102.62 | Q41: 201892.65 | R41: 218445.16 | S41: 197369.24 | T41: 325399.52 | U41: 325399.52 | V41: 310697.65 | W41: 291773.47 | X41: 280331.2 | Y41: 258735.49 | Z41: 258735.49 | AA41: 261234.15 | AB41: 233158.14
A42: 1 | C42: 단기충당부채 | E42: 1279102.5 | F42: 1279102.5 | G42: 1309369.3 | H42: 1370138.2 | I42: 1199745.3 | J42: 1286044.2 | K42: 1286044.2 | L42: 1119785.9 | M42: 992699.55 | N42: 806726.46 | O42: 1081565.5 | P42: 1081565.5 | Q42: 520462.66 | R42: 476855.36 | S42: 345925.5 | T42: 283375.89 | U42: 283375.89 | V42: 244904.66 | W42: 287245.11 | X42: 286591.56 | Y42: 1090396.6 | Z42: 1090396.6 | AA42: 1092818.9 | AB42: 1101003.6
... A45: 1 | C45: 사채 | E45: 173763.28 | F45: 173763.28 | G45: 124853.73 | H45: 39938.2 | I45: 39945.69 | J45: 119521.36 | K45: 119521.36 | L45: 149505.1 | M45: 304255.01 | N45: 304353.38 | O45: 204687.39 | P45: 204687.39 | Q45: 169758.68 | R45: 74888.85 | S45: 74897.86 | T45: 74907.01 | U45: 74907.01 | V45: 64922.88 | W45: 0 | X45: 299105.81 | Y45: 299189.22 | Z45: 299189.22 | AA45: 299272.37 | AB45: 299355.35
A46: 1 | C46: 장기차입금 | E46: 223710 | F46: 223710 | G46: 334361 | H46: 1300145 | I46: 1521885 | J46: 1195651.9 | K46: 1195651.9 | L46: 806363.94 | M46: 976073.94 | N46: 506408 | O46: 292231 | P46: 292231 | Q46: 272697 | R46: 169460 | S46: 65477 | T46: 44720 | U46: 44720 | V46: 0 | W46: 0 | X46: 0 | Y46: 0 | Z46: 0
A47: 1 | C47: 비유동리스부채 | E47: 11390.69 | F47: 11390.69 | G47: 7813.22 | H47: 3406.07 | I47: 3476.04 | J47: 23643.99 | K47: 23643.99 | L47: 30397.06 | M47: 26102.37 | N47: 22944.46 | O47: 98825.3 | P47: 98825.3 | Q47: 116821.81 | R47: 135361.8 | S47: 120208.56 | T47: 260361.99 | U47: 260361.99 | V47: 229263.33 | W47: 217866.14 | X47: 206144.41 | Y47: 194567.72 | Z47: 194567.72 | AA47: 191617.06 | AB47: 179711.06
A48: 1 | C48: 장기금융부채 | E48: 479089.84 | F48: 479089.84 | G48: 452918.94 | H48: 839257.29 | I48: 1330963.6 | J48: 347495.09 | K48: 347495.09 | L48: 268670.88 | M48: 215812.93 | N48: 196576.95 | O48: 262487.58 | P48: 262487.58 | Q48: 375087.08 | R48: 588591.04 | S48: 300027.7 | T48: 1235598 | U48: 1235598 | V48: 1157555.3 | W48: 704888.55 | X48: 746038.3 | Y48: 1048424.2 | Z48: 1048424.2 | AA48: 1737565 | AB48: 1823299.3
A49: 1 | C49: 장기충당부채 | E49: 61798.56 | F49: 61798.56 | G49: 39429.58 | H49: 38828.65 | I49: 26244.24 | J49: 28986.64 | K49: 28986.64 | L49: 19466.9 | M49: 23514.47 | N49: 26846.31 | O49: 29982.69 | P49: 29982.69 | Q49: 32456.13 | R49: 37544.47 | S49: 36915.02 | T49: 41757.36 | U49: 41757.36 | V49: 50425.78 | W49: 50444.32 | X49: 55319.83 | Y49: 63230.31 | Z49: 63230.31 | AA49: 67623.4 | AB49: 78883.57
A50: 1 | C50: 장기파생상품부채 | E50: 417699.39 | F50: 417699.39 | G50: 395352.66 | H50: 786612.71 | I50: 1279017.6 | J50: 274626.53 | K50: 274626.53 | L50: 188154.52 | M50: 139650.81 | N50: 124205.26 | O50: 105724.86 | P50: 105724.86 | Q50: 199974.85 | R50: 394904.27 | S50: 121765.91 | T50: 914698.45 | U50: 914698.45 | V50: 864750.74 | W50: 423500.26 | X50: 476332.47 | Y50: 775354.91 | Z50: 775354.91 | AA50: 1467463.8 | AB50: 1564892.9
A51: 1 | C51: 기타비유동금융부채 | E51: 49999.76 | F51: 49999.76 | G51: 49753.06 | H51: 49238.51 | I51: 48469.97 | J51: 49224.57 | K51: 49224.57 | L51: 50119.3 | M51: 50059.75 | N51: 49427.23 | O51: 57937.42 | P51: 57937.42 | Q51: 58290.42 | R51: 58324.97 | S51: 58053.23 | T51: 60537.59 | U51: 60537.59 | V51: 63541.2 | W51: 63522.15 | X51: 63561.42 | Y51: 78501.55 | Z51: 78501.55 | AA51: 78484.1 | AB51: 78695.37
A52: 1 | C52: 부채총계 | E52: 7669432.6 | F52: 7669432.6 | G52: 7890281.2 | H52: 9821190.2 | I52: 12698813 | J52: 11186551 | K52: 11186551 | L52: 11136316 | M52: 11479478 | N52: 12970908 | O52: 12448526 | P52: 12448526 | Q52: 12710796 | R52: 12849617 | S52: 11328558 | T52: 13275009 | U52: 13275009 | V52: 12322673 | W52: 10210365 | X52: 10446071 | Y52: 10706552 | Z52: 10706552 | AA52: 12003580 | AB52: 13115990
A53: 1 | C53: 자본금 | E53: 880114.84 | F53: 880114.84 | G53: 880114.84 | H53: 880114.84 | I53: 880114.84 | J53: 880114.84 | K53: 880114.84 | L53: 880114.84 | M53: 880114.84 | N53: 880114.84 | O53: 880114.84 | P53: 880114.84 | Q53: 880114.84 | R53: 880114.84 | S53: 880114.84 | T53: 880114.84 | U53: 880114.84 | V53: 880114.84 | W53: 880114.84 | X53: 880114.84 | Y53: 880114.84 | Z53: 880114.84 | AA53: 880114.84 | AB53: 880114.84
A54: 1 | C54: 보통주자본금 | E54: 880000 | F54: 880000 | G54: 880000 | H54: 880000 | I54: 880000 | J54: 880000 | K54: 880000 | L54: 880000 | M54: 880000 | N54: 880000 | O54: 880000 | P54: 880000 | Q54: 880000 | R54: 880000 | S54: 880000 | T54: 880000 | U54: 880000 | V54: 880000 | W54: 880000 | X54: 880000 | Y54: 880000 | Z54: 880000 | AA54: 880000 | AB54: 880000
A55: 1 | C55: 우선주자본금 | E55: 114.84 | F55: 114.84 | G55: 114.84 | H55: 114.84 | I55: 114.84 | J55: 114.84 | K55: 114.84 | L55: 114.84 | M55: 114.84 | N55: 114.84 | O55: 114.84 | P55: 114.84 | Q55: 114.84 | R55: 114.84 | S55: 114.84 | T55: 114.84 | U55: 114.84 | V55: 114.84 | W55: 114.84 | X55: 114.84 | Y55: 114.84 | Z55: 114.84 | AA55: 114.84 | AB55: 114.84
A56: 1 | C56: 자본잉여금 | E56: 1969727.2 | F56: 1969727.2 | G56: 1969727.2 | H56: 1969727.2 | I56: 1969727.2 | J56: 1969727.2 | K56: 1969727.2 | L56: 1969727.2 | M56: 1969727.2 | N56: 1969727.2 | O56: 1969727.2 | P56: 1969727.2 | Q56: 1969727.2 | R56: 1969727.2 | S56: 1969727.2 | T56: 1969727.2 | U56: 1969727.2 | V56: 1969727.2 | W56: 1969727.2 | X56: 1969727.2 | Y56: 1969727.2 | Z56: 1969727.2 | AA56: 1969727.2 | AB56: 1969727.2
A57: 1 | C57: 기타포괄이익누계액 | E57: 1173140.8 | F57: 1173140.8 | G57: 1208455.4 | H57: 1427756.7 | I57: 1875453.6 | J57: 1267458.6 | K57: 1267458.6 | L57: 1390770.6 | M57: 1370585.9 | N57: 1518179.3 | O57: 1308612 | P57: 1308612 | Q57: 1561439.3 | R57: 1729108.6 | S57: 1454060.3 | T57: 1603542.2 | U57: 1603542.2 | V57: 1570252.5 | W57: 1167907 | X57: 1356493.1 | Y57: 1420867.5 | Z57: 1420867.5 | AA57: 1669663 | AB57: 1694099.1
A58: 1 | C58: 기타자본 | E58: 1556045.1 | F58: 1556045.1 | G58: 1556045.1 | H58: 1556045.1 | I58: 1556045.1 | J58: 1556045.1 | K58: 1556045.1 | L58: 1556045.1 | M58: 1556045.1 | N58: 1556045.1 | O58: 1556045.1 | P58: 1556045.1 | Q58: 1556045.1 | R58: 1556045.1 | S58: 1556045.1 | T58: 1556045.1 | U58: 1556045.1 | V58: 1556045.1 | W58: 1556045.1 | X58: 1556045.1 | Y58: 1556045.1 | Z58: 1556045.1 | AA58: 1556045.1 | AB58: 1556045.1
... A65: 1 | C65: 이자발생자산 | E65: 1566672.5 | F65: 1566672.5 | G65: 1518735.2 | H65: 2628181.8 | I65: 4128421.6 | J65: 2594022.3 | K65: 2594022.3 | L65: 2671805.9 | M65: 2878279.1 | N65: 3247611.8 | O65: 2117902.8 | P65: 2117902.8 | Q65: 2932683.4 | R65: 2837881.9 | S65: 2164730.5 | T65: 3094541.9 | U65: 3094541.9 | V65: 2445422.2 | W65: 1839930.7 | X65: 2709048.4 | Y65: 2241560.7 | Z65: 2241560.7 | AA65: 3264242.1 | AB65: 3345350.7
A66: 1 | C66: 사용권자산 | G66: 6872.69 | H66: 5705.09 | I66: 7436.78 | J66: 47000.66 | K66: 47000.66 | L66: 74199.03 | M66: 66576.9 | N66: 57470.06 | O66: 127772.18 | P66: 127772.18 | Q66: 195986.43 | R66: 210758.81 | S66: 188268.89 | T66: 211609.24 | U66: 211609.24 | V66: 195180.18 | W66: 176638.97 | X66: 165683.35 | Y66: 145255.68 | Z66: 145255.68 | AA66: 149095.69 | AB66: 124052.11
A67: 1 | C67: 확정급여부채 | I67: 3156.24
A68: 1 | C68: 단기투자자산(공정가치) | L68: 353997.77
A69: 1 | C69: 당기법인세부채(미지급법인세) | Y69: 12159.39 | Z69: 12159.39 | AA69: 19577.86 | AB69: 35531.28
A70: 1 | C70: 매출액(수익) | E70: 1824114.6 | G70: 1469234.8 | H70: 1404803 | I70: 1388306.6 | J70: 1593863.1 | K70: 5856207.5 | L70: 1574714.1 | M70: 1926308 | N70: 2016460 | O70: 2389765.1 | P70: 7907247.2 | Q70: 2321766.5 | R70: 2527599.3 | S70: 2320247.5 | T70: 2697815.6 | U70: 9867428.9 | V70: 2490274 | W70: 2678494.6 | X70: 2631922 | Y70: 2834262.2 | Z70: 10634953 | AA70: 2899873.8 | AB70: 3224937.5
A71: 1 | C71: 매출원가 | E71: 1986502.3 | G71: 1471439.2 | H71: 1587741.8 | I71: 1465049.6 | J71: 1832974.3 | K71: 6357204.9 | L71: 1428201.8 | M71: 1770312.8 | N71: 1840350.9 | O71: 2254318 | P71: 7293183.6 | Q71: 2222356 | R71: 2316678.6 | S71: 2114172.9 | T71: 2389582.9 | U71: 9042790.4 | V71: 2260247.4 | W71: 2361613.6 | X71: 2283922 | Y71: 2379841.7 | Z71: 9285624.7 | AA71: 2499042 | AB71: 2764534
A72: 1 | C72: 매출총이익 | E72: -162387.73 | G72: -2204.43 | H72: -182938.83 | I72: -76742.92 | J72: -239111.22 | K72: -500997.4 | L72: 146512.29 | M72: 155995.26 | N72: 176109.09 | O72: 135447.06 | P72: 614063.7 | Q72: 99410.49 | R72: 210920.68 | S72: 206074.59 | T72: 308232.71 | U72: 824638.47 | V72: 230026.66 | W72: 316881 | X72: 347999.97 | Y72: 454420.52 | Z72: 1349328.1 | AA72: 400831.82 | AB72: 460403.46
A73: 1 | C73: 판관비 | E73: 67898.28 | G73: 79386.32 | H73: 63850.88 | I73: 80694.63 | J73: 190172.36 | K73: 414104.19 | L73: 76561.87 | M73: 78159.41 | N73: 95013.42 | O73: 107379.7 | P73: 357114.4 | Q73: 72384.53 | R73: 91661.21 | S73: 96599.92 | T73: 110069.99 | U73: 370715.65 | V73: 104344.75 | W73: 109647.73 | X73: 103965.84 | Y73: 164309.52 | Z73: 482267.84 | AA73: 114647.37 | AB73: 136068.78
A74: 1 | C74: 영업이익 | E74: -230286.01 | G74: -81590.75 | H74: -246789.71 | I74: -157437.54 | J74: -429283.59 | K74: -915101.59 | L74: 69950.41 | M74: 77835.85 | N74: 81095.67 | O74: 28067.35 | P74: 256949.28 | Q74: 27025.96 | R74: 119259.47 | S74: 109474.67 | T74: 198162.73 | U74: 453922.83 | V74: 125681.91 | W74: 207233.26 | X74: 244034.14 | Y74: 290111 | Z74: 867060.31 | AA74: 286184.45 | AB74: 324334.68
A75: 1 | C75: 기타영업외수익 | E75: 118565.02 | G75: 358223.38 | H75: 1389923 | I75: 2513116.6 | J75: -1317798.6 | K75: 2943464.4 | L75: 993391.73 | M75: 371567.54 | N75: 972677.24 | O75: -545087.6 | P75: 1792548.9 | Q75: 1413589.3 | R75: 1108474.3 | S75: -693990.43 | T75: 3591947.2 | U75: 5420020.3 | V75: 345955.31 | W75: 1609424.3 | X75: -683554.55 | Y75: 192017.82 | Z75: 1463842.8 | AA75: 1700219.2 | AB75: 646247.06
A76: 1 | C76: 기타영업외비용 | E76: 78926.2 | G76: 347522.1 | H76: 1378946.3 | I76: 2536504 | J76: -1542475.7 | K76: 2720496.8 | L76: 961058.23 | M76: 364709.16 | N76: 969908.84 | O76: -128173.42 | P76: 2167502.8 | Q76: 1437245.3 | R76: 1121243.2 | S76: -693719.9 | T76: 4180223.8 | U76: 6044992.5 | V76: 391065.58 | W76: 1794908.1 | X76: -670673.14 | Y76: 212405.72 | Z76: 1727706.3 | AA76: 1709168.8 | AB76: 642626.37
A77: 1 | C77: 금융수익 | E77: 9025.2 | G77: 22756.35 | H77: 53534.2 | I77: 58085.99 | J77: 33881.91 | K77: 168258.45 | L77: 51395.21 | M77: 35178.49 | N77: 20135.01 | O77: 35074.42 | P77: 141783.13 | Q77: 56287.81 | R77: 38685.87 | S77: 17214.26 | T77: 64666.52 | U77: 176854.46 | V77: 155882.55 | W77: 334524.35 | X77: -21825.12 | Y77: 166821.3 | Z77: 635403.08 | AA77: 221143.97 | AB77: 124455.2
A78: 1 | C78: 금융비용 | E78: 32232.8 | G78: 37463.18 | H78: 69344.08 | I78: 101828.91 | J78: 15392.24 | K78: 224028.41 | L78: 82621.34 | M78: 60177.02 | N78: 81776.58 | O78: 22610.54 | P78: 247185.48 | Q78: 125875.33 | R78: 84848.54 | S78: 49641.42 | T78: 108172.61 | U78: 368537.9 | V78: 134572.31 | W78: 137822.93 | X78: 66022.78 | Y78: 247426.96 | Z78: 585844.98 | AA78: 354118.83 | AB78: 151801.76
A79: 1 | C79: 법인세비용차감전계속사업이익 | E79: -213854.8 | G79: -85596.31 | H79: -251622.91 | I79: -224567.9 | J79: -186116.86 | K79: -747903.98 | L79: 71057.78 | M79: 59695.7 | N79: 22222.51 | O79: -376382.94 | P79: -223406.95 | Q79: -66217.62 | R79: 60327.87 | S79: 76776.97 | T79: -433620 | U79: -362732.78 | V79: 101881.88 | W79: 218450.79 | X79: 143304.82 | Y79: 189117.43 | Z79: 652754.92 | AA79: 144260 | AB79: 300608.81
A80: 1 | C80: 당기순이익 | E80: -260758.11 | G80: -85596.31 | H80: -251622.91 | I80: -224567.9 | J80: -218098.26 | K80: -779885.38 | L80: 71057.78 | M80: 59693.09 | N80: 22225.12 | O80: -242020.75 | P80: -89044.76 | Q80: -66217.62 | R80: 60327.87 | S80: 76776.97 | T80: -55200.46 | U80: 15686.76 | V80: 101881.88 | W80: 218450.79 | X80: 143304.82 | Y80: 76686.96 | Z80: 540324.45 | AA80: 115402.55 | AB80: 225430.48
A81: 1 | C81: 금융손익 | E81: -23207.6 | G81: -14706.83 | H81: -15809.88 | I81: -43742.92 | J81: 18489.67 | K81: -55769.96 | L81: -31226.13 | M81: -24998.53 | N81: -61641.57 | O81: 12463.88 | P81: -105402.35 | Q81: -69587.52 | R81: -46162.67 | S81: -32427.16 | T81: -43506.09 | U81: -191683.44 | V81: 21310.24 | W81: 196701.42 | X81: -87847.9 | Y81: -80605.66 | Z81: 49558.1 | AA81: -132974.86 | AB81: -27346.56
... A85: 1 | C85: 총포괄손익 | E85: -82071.28 | G85: -50281.75 | H85: -32254.87 | I85: 223157.13 | J85: -810502.95 | K85: -669882.44 | L85: 194369.77 | M85: 39517.11 | N85: 169828.14 | O85: -513084.55 | P85: -109369.53 | Q85: 186609.67 | R85: 227997.11 | S85: -198271.25 | T85: 63055.82 | U85: 279391.35 | V85: 68592.24 | W85: -183885.04 | X85: 334272.87 | Y85: 126312.12 | Z85: 345292.19 | AA85: 364198.02 | AB85: 249866.55
A86: 1 | C86: 법인세비용 | M86: 2.61 | N86: -2.61 | R86: 0 | V86: 0 | W86: 0 | X86: 0 | Y86: 112430.47 | Z86: 112430.47 | AA86: 28857.46 | AB86: 75178.33
A87: 1 | C87: 영업활동으로인한현금흐름 | E87: 111568.36 | G87: -174831.9 | H87: -112434.24 | I87: -1121188 | J87: -262212.25 | K87: -1670666.4 | L87: 422342.25 | M87: -494897.63 | N87: -512044.53 | O87: -100784.39 | P87: -685384.3 | Q87: -94375.94 | R87: 164722.37 | S87: 100186.79 | T87: 823202.38 | U87: 993735.6 | V87: -127046.44 | W87: 407903.37 | X87: 1360952.1 | Y87: -96570.16 | Z87: 1545238.8 | AA87: 1500354.6 | AB87: 817523.82
A88: 1 | C88: 이자수취(CF) | E88: 15341.95 | G88: 5241.16 | H88: 7136.16 | I88: 7534.35 | J88: 4047.81 | K88: 23959.48 | L88: 11107.64 | M88: 7661.56 | N88: 13366.6 | O88: 10135.54 | P88: 42271.34 | Q88: 17695.88 | R88: 9500.01 | S88: 5679.04 | T88: 6119.28 | U88: 38994.21 | V88: 6835.95 | W88: 6065.82 | X88: 5899.32 | Y88: 8259.09 | Z88: 27060.18 | AA88: 9519.47 | AB88: 9448.31
A89: 1 | C89: 이자지급(CF) | E89: -30216.55 | G89: -19909.95 | H89: -17837.74 | I89: -16218.12 | J89: -30101.63 | K89: -84067.44 | L89: -32318.67 | M89: -43396.98 | N89: -29893.24 | O89: -50327.98 | P89: -155936.87 | Q89: -53052.91 | R89: -54063.39 | S89: -43804.43 | T89: -49759.92 | U89: -200680.65 | V89: -45353.24 | W89: -38155.77 | X89: -31276.35 | Y89: -24975.83 | Z89: -139761.19 | AA89: -19500.48 | AB89: -14189.6
A90: 1 | C90: 배당금수취(CF) | E90: 0 | I90: 0 | J90: 0 | N90: 0 | O90: 0 | Q90: 0 | R90: 224.43 | S90: 0 | T90: 0 | U90: 224.43 | X90: 0 | Y90: 859.74 | AA90: 246.84 | AB90: 682.67
A91: 1 | C91: 법인세납부(CF) | E91: -720.62 | G91: 1171.07 | H91: -439.86 | I91: -603.53 | J91: -11270.99 | K91: -11143.31 | N91: -1398.65 | O91: -1392.75 | Q91: -1506.22 | R91: 3618.2 | S91: -674.75 | T91: -697.18 | U91: 740.05 | V91: -817.99 | W91: 3422.77 | X91: -603.28 | Y91: -1184.86 | Z91: 816.64 | AA91: -6596.38 | AB91: -8397.84
A92: 1 | C92: 투자활동으로인한현금흐름 | E92: -90863.57 | G92: 389525.34 | H92: -717056.51 | I92: 238161.72 | J92: 230910.48 | K92: 141541.03 | L92: -476176.08 | M92: 373732.37 | N92: 83158.95 | O92: -11791.29 | P92: -31076.05 | Q92: 362762.81 | R92: 91761.87 | S92: -17004.48 | T92: 435654.07 | U92: 873174.27 | V92: -175532.57 | W92: 27689.65 | X92: -244098.33 | Y92: -103721.57 | Z92: -495662.82 | AA92: -333546.81 | AB92: -944672.51
A93: 1 | C93: 유형자산의증가 | E93: 9408.07 | G93: 11575.9 | H93: 13603.91 | I93: 12627.42 | J93: 22955.39 | K93: 60762.62 | L93: 26192.13 | M93: 42166.77 | N93: 42290.63 | O93: 39359.67 | P93: 150009.2 | Q93: 23215.88 | R93: 34847.09 | S93: 42062.45 | T93: 64452.76 | U93: 164578.18 | V93: 35891.69 | W93: 64797.12 | X93: 47790.66 | Y93: 52998.55 | Z93: 201478.02 | AA93: 34537.08 | AB93: 60115.21
A94: 1 | C94: CAPEX | E94: 9408.07 | G94: 11575.9 | H94: 13603.91 | I94: 12627.42 | J94: 22955.39 | K94: 60762.62 | L94: 26192.13 | M94: 42166.77 | N94: 42290.63 | O94: 39359.67 | P94: 150009.2 | Q94: 23215.88 | R94: 34847.09 | S94: 42062.45 | T94: 64452.76 | U94: 164578.18 | V94: 35891.69 | W94: 64797.12 | X94: 47790.66 | Y94: 52998.55 | Z94: 201478.02 | AA94: 34537.08 | AB94: 60115.21
A95: 1 | C95: 유형자산의감소 | E95: 137595.21 | G95: 545.37 | H95: 204.52 | I95: 512.42 | J95: 301493.71 | K95: 302756.02 | L95: 38.56 | M95: 933.76 | N95: 97.05 | O95: 498.7 | P95: 1568.07 | Q95: 322.22 | R95: 450.93 | S95: 158.37 | T95: 382478.63 | U95: 383410.15 | V95: 17895.86 | W95: 250.02 | X95: 483.47 | Y95: 2301.06 | Z95: 20930.41 | AA95: 494.19 | AB95: 307.68
A96: 1 | C96: 무형자산의감소 | E96: 0
A97: 1 | C97: 재무활동으로인한현금흐름 | E97: -531763.48 | G97: -114501.65 | H97: 704318.11 | I97: 812663.89 | J97: 127237.52 | K97: 1529717.9 | L97: -248515.42 | M97: 501491.78 | N97: 225755.48 | O97: 242404.37 | P97: 721136.21 | Q97: -30094.47 | R97: -742132.48 | S97: 212307.59 | T97: -938806.15 | U97: -1498725.5 | V97: -114299.22 | W97: -340369.88 | X97: -336896.9 | Y97: -460479.96 | Z97: -1252046 | AA97: -847839.2 | AB97: -118954.69
A98: 1 | C98: 단기차입금의증가 | E98: 212333.43 | G98: 94140.72 | H98: 424593.47 | I98: 933712.22 | J98: 274921.07 | K98: 1727367.5 | L98: 453926.9 | M98: 401276.14 | N98: 669451.14 | O98: 523511.8 | P98: 2048166 | Q98: 914139.14 | R98: 857619.56 | S98: 1037889.3 | T98: 539353.4 | U98: 3349001.4 | V98: 739905 | W98: 349361.43 | X98: 551522.17 | Y98: 157351.26 | Z98: 1798139.9 | AA98: 144443.59 | AB98: 170411.62
A99: 1 | C99: 단기차입금의감소 | E99: 944535.06 | G99: 196139.83 | H99: 499937.51 | I99: 120915.7 | J99: 403959.06 | K99: 1220952.1 | L99: 683498.94 | M99: 171373.55 | N99: 429439.17 | O99: 325867.21 | P99: 1610178.9 | Q99: 708110.88 | R99: 713290.07 | S99: 754004.5 | T99: 897706.97 | U99: 3073112.4 | V99: 757503.38 | W99: 562691.51 | X99: 767020.49 | Y99: 412784.88 | Z99: 2500000.3 | AA99: 814057.88 | AB99: 164129.35
A100: 1 | C100: 유동성장기부채의감소 | E100: 1169979 | G100: 117791 | H100: 317138 | I100: 170650 | J100: 30000 | K100: 635579 | L100: 49000 | M100: 470346 | N100: 0 | O100: 0 | P100: 519346 | Q100: 315644 | R100: 970178.06 | S100: 247676 | T100: 638684.94 | U100: 2172183 | V100: 78961 | W100: 302284 | X100: 399177 | Y100: 182185 | Z100: 962607 | AA100: 162428 | AB100: 115000
A101: 1 | C101: 사채의증가 | E101: 0 | I101: 0 | J101: 79539.16 | L101: 44909.51 | M101: 179638.2 | N101: 0 | O101: 0 | P101: 224547.71 | Q101: 0 | R101: 0 | S101: 0 | T101: 0 | U101: 0 | Y101: 0
A102: 1 | C102: 장기차입금의증가 | E102: 100000 | G102: 110145 | H102: 1081407 | I102: 175438 | J102: 222278 | K102: 1589268 | N102: 0 | O102: 117530 | Q102: 100371 | R102: 105213 | S102: 197535 | T102: 79056 | U102: 482175 | V102: 0 | W102: 194613 | X102: 0 | Y102: 0 | Z102: 194613
A103: 1 | C103: 리스부채의상환 | E103: 5257.66 | G103: 4856.54 | H103: 4566.63 | I103: 4920.63 | J103: 15541.65 | K103: 29885.45 | L103: 15805.12 | M103: 19045.79 | N103: 14256.49 | O103: 14552.21 | P103: 63659.61 | Q103: 20849.73 | R103: 21496.91 | S103: 21436.23 | T103: 20823.64 | U103: 84606.51 | V103: 17739.85 | W103: 19368.79 | X103: 22221.57 | Y103: 22861.36 | Z103: 82191.57 | AA103: 15796.91 | AB103: 10236.95
A104: 1 | C104: 현금및현금성자산의증감 | E104: -511058.68 | G104: 100191.79 | H104: -125172.63 | I104: -70362.37 | J104: 95935.77 | K104: 592.56 | L104: -302349.25 | M104: 380326.51 | N104: -203130.09 | O104: 129828.69 | P104: 4675.86 | Q104: 238292.39 | R104: -485648.23 | S104: 295489.89 | T104: 320050.32 | U104: 368184.37 | V104: -416878.23 | W104: 95223.15 | X104: 779956.82 | Y104: -660771.7 | Z104: -202469.96 | AA104: 318968.56 | AB104: -246103.37
A105: 1 | C105: 기말현금및현금성자산 | E105: -511054.09 | G105: 614926.47 | H105: -125511.74 | I105: -70323.98 | J105: 95906.66 | K105: 514997.41 | L105: 212662.85 | M105: 380291.04 | N105: -203135.33 | O105: 129813.17 | P105: 519631.73 | Q105: 765620.16 | R105: -493297.78 | S105: 295478 | T105: 320648.3 | U105: 888448.68 | V105: 471581.61 | W105: 95179.36 | X105: 779976.86 | Y105: -660761.41 | Z105: 685976.42 | AA105: 1004973.8 | AB105: -246085.66
A106: 1 | C106: 장기차입금의감소 | N106: 0 | O106: 58218 | S106: 0 | T106: 0

Sheet subQ
A1: YQ | C1: subQ 분기 서브모델(억원, U=100) | E1: 4Q21 | F1: 2021 | G1: 1Q22 | H1: 2Q22 | I1: 3Q22 | J1: 4Q22 | K1: 2022 | L1: 1Q23 | M1: 2Q23 | N1: 3Q23 | O1: 4Q23 | P1: 2023 | Q1: 1Q24 | R1: 2Q24 | S1: 3Q24 | T1: 4Q24 | U1: 2024 | V1: 1Q25 | W1: 2Q25 | X1: 3Q25 | Y1: 4Q25 | Z1: 2025 | AA1: 1Q26 | AB1: 2Q26 | AC1: 3Q26 | AD1: 4Q26 | AE1: 2026 | AF1: 1Q27 | AG1: 2Q27 | AH1: 3Q27 | AI1: 4Q27 | AJ1: 2027 | AK1: 1Q28 | AL1: 2Q28 | AM1: 3Q28 | AN1: 4Q28 | AO1: 2028
A2: A=이름(key) B=그룹 C=단위 D=FnGuide 계정명(VLOOKUP 키). 확정=VLOOKUP(BS), 추정=변수 가정 참조
E3: 1 | F3: 2 | G3: 3 | H3: 4 | I3: 5 | J3: 6 | K3: 7 | L3: 8 | M3: 9 | N3: 10 | O3: 11 | P3: 12 | Q3: 13 | R3: 14 | S3: 15 | T3: 16 | U3: 17 | V3: 18 | W3: 19 | X3: 20 | Y3: 21 | Z3: 22 | AA3: 23 | AB3: 24 | AC3: 25 | AD3: 26 | AE3: 27 | AF3: 28 | AG3: 29 | AH3: 30 | AI3: 31 | AJ3: 32 | AK3: 33 | AL3: 34 | AM3: 35 | AN3: 36 | AO3: 37
E4: 2021.12 | F4: 2021.12A | G4: 2022.03 | H4: 2022.06 | I4: 2022.09 | J4: 2022.12 | K4: 2022.12A | L4: 2023.03 | M4: 2023.06 | N4: 2023.09 | O4: 2023.12 | P4: 2023.12A | Q4: 2024.03 | R4: 2024.06 | S4: 2024.09 | T4: 2024.12 | U4: 2024.12A | V4: 2025.03 | W4: 2025.06 | X4: 2025.09 | Y4: 2025.12 | Z4: 2025.12A | AA4: 2026.03 | AB4: 2026.06 | AC4: 2026.09 | AD4: 2026.12 | AE4: 2026.12A | AF4: 2027.03 | AG4: 2027.06 | AH4: 2027.09 | AI4: 2027.12 | AJ4: 2027.12A | AK4: 2028.03 | AL4: 2028.06 | AM4: 2028.09 | AN4: 2028.12 | AO4: 2028.12A
A5: 매출액 | B5: 손익 | C5: 억원 | D5: 매출액(수익) | E5: =IFERROR(VLOOKUP($D5,BS연결,MATCH(E$1,BS연결H,0),0)/100,"") | G5: =IFERROR(VLOOKUP($D5,BS연결,MATCH(G$1,BS연결H,0),0)/100,"") | H5: =IFERROR(VLOOKUP($D5,BS연결,MATCH(H$1,BS연결H,0),0)/100,"") | I5: =IFERROR(VLOOKUP($D5,BS연결,MATCH(I$1,BS연결H,0),0)/100,"") | J5: =IFERROR(VLOOKUP($D5,BS연결,MATCH(J$1,BS연결H,0),0)/100,"") | K5: =IFERROR(VLOOKUP($D5,BS연결,MATCH(K$1,BS연결H,0),0)/100,"") | L5: =IFERROR(VLOOKUP($D5,BS연결,MATCH(L$1,BS연결H,0),0)/100,"") | M5: =IFERROR(VLOOKUP($D5,BS연결,MATCH(M$1,BS연결H,0),0)/100,"") | N5: =IFERROR(VLOOKUP($D5,BS연결,MATCH(N$1,BS연결H,0),0)/100,"") | ... AB5: =IFERROR(VLOOKUP($D5,BS연결,MATCH(AB$1,BS연결H,0),0)/100,"") | AC5: =IFERROR(AC38+AC42,"") | AD5: =IFERROR(AD38+AD42,"") | AE5: =SUM(AA5:AD5) | AF5: =IFERROR(AF38+AF42,"") | AG5: =IFERROR(AG38+AG42,"") | AH5: =IFERROR(AH38+AH42,"") | AI5: =IFERROR(AI38+AI42,"") | AJ5: =SUM(AF5:AI5) | AK5: =IFERROR(AK38+AK42,"") | AL5: =IFERROR(AL38+AL42,"") | AM5: =IFERROR(AM38+AM42,"") | AN5: =IFERROR(AN38+AN42,"") | AO5: =SUM(AK5:AN5)
A6: 매출원가 | B6: 손익 | C6: 억원 | D6: 매출원가 | E6: =IFERROR(VLOOKUP($D6,BS연결,MATCH(E$1,BS연결H,0),0)/100,"") | G6: =IFERROR(VLOOKUP($D6,BS연결,MATCH(G$1,BS연결H,0),0)/100,"") | H6: =IFERROR(VLOOKUP($D6,BS연결,MATCH(H$1,BS연결H,0),0)/100,"") | I6: =IFERROR(VLOOKUP($D6,BS연결,MATCH(I$1,BS연결H,0),0)/100,"") | J6: =IFERROR(VLOOKUP($D6,BS연결,MATCH(J$1,BS연결H,0),0)/100,"") | K6: =IFERROR(VLOOKUP($D6,BS연결,MATCH(K$1,BS연결H,0),0)/100,"") | L6: =IFERROR(VLOOKUP($D6,BS연결,MATCH(L$1,BS연결H,0),0)/100,"") | M6: =IFERROR(VLOOKUP($D6,BS연결,MATCH(M$1,BS연결H,0),0)/100,"") | N6: =IFERROR(VLOOKUP($D6,BS연결,MATCH(N$1,BS연결H,0),0)/100,"") | ... AB6: =IFERROR(VLOOKUP($D6,BS연결,MATCH(AB$1,BS연결H,0),0)/100,"") | AC6: =IFERROR(AC5-AC7,"") | AD6: =IFERROR(AD5-AD7,"") | AE6: =SUM(AA6:AD6) | AF6: =IFERROR(AF5-AF7,"") | AG6: =IFERROR(AG5-AG7,"") | AH6: =IFERROR(AH5-AH7,"") | AI6: =IFERROR(AI5-AI7,"") | AJ6: =SUM(AF6:AI6) | AK6: =IFERROR(AK5-AK7,"") | AL6: =IFERROR(AL5-AL7,"") | AM6: =IFERROR(AM5-AM7,"") | AN6: =IFERROR(AN5-AN7,"") | AO6: =SUM(AK6:AN6)
A7: 매출총이익 | B7: 손익 | C7: 억원 | D7: 매출총이익 | E7: =IFERROR(VLOOKUP($D7,BS연결,MATCH(E$1,BS연결H,0),0)/100,"") | G7: =IFERROR(VLOOKUP($D7,BS연결,MATCH(G$1,BS연결H,0),0)/100,"") | H7: =IFERROR(VLOOKUP($D7,BS연결,MATCH(H$1,BS연결H,0),0)/100,"") | I7: =IFERROR(VLOOKUP($D7,BS연결,MATCH(I$1,BS연결H,0),0)/100,"") | J7: =IFERROR(VLOOKUP($D7,BS연결,MATCH(J$1,BS연결H,0),0)/100,"") | K7: =IFERROR(VLOOKUP($D7,BS연결,MATCH(K$1,BS연결H,0),0)/100,"") | L7: =IFERROR(VLOOKUP($D7,BS연결,MATCH(L$1,BS연결H,0),0)/100,"") | M7: =IFERROR(VLOOKUP($D7,BS연결,MATCH(M$1,BS연결H,0),0)/100,"") | N7: =IFERROR(VLOOKUP($D7,BS연결,MATCH(N$1,BS연결H,0),0)/100,"") | ... AB7: =IFERROR(VLOOKUP($D7,BS연결,MATCH(AB$1,BS연결H,0),0)/100,"") | AC7: =IFERROR(AC9+AC8,"") | AD7: =IFERROR(AD9+AD8,"") | AE7: =SUM(AA7:AD7) | AF7: =IFERROR(AF9+AF8,"") | AG7: =IFERROR(AG9+AG8,"") | AH7: =IFERROR(AH9+AH8,"") | AI7: =IFERROR(AI9+AI8,"") | AJ7: =SUM(AF7:AI7) | AK7: =IFERROR(AK9+AK8,"") | AL7: =IFERROR(AL9+AL8,"") | AM7: =IFERROR(AM9+AM8,"") | AN7: =IFERROR(AN9+AN8,"") | AO7: =SUM(AK7:AN7)
A8: 판관비 | B8: 손익 | C8: 억원 | D8: 판관비 | E8: =IFERROR(VLOOKUP($D8,BS연결,MATCH(E$1,BS연결H,0),0)/100,"") | G8: =IFERROR(VLOOKUP($D8,BS연결,MATCH(G$1,BS연결H,0),0)/100,"") | H8: =IFERROR(VLOOKUP($D8,BS연결,MATCH(H$1,BS연결H,0),0)/100,"") | I8: =IFERROR(VLOOKUP($D8,BS연결,MATCH(I$1,BS연결H,0),0)/100,"") | J8: =IFERROR(VLOOKUP($D8,BS연결,MATCH(J$1,BS연결H,0),0)/100,"") | K8: =IFERROR(VLOOKUP($D8,BS연결,MATCH(K$1,BS연결H,0),0)/100,"") | L8: =IFERROR(VLOOKUP($D8,BS연결,MATCH(L$1,BS연결H,0),0)/100,"") | M8: =IFERROR(VLOOKUP($D8,BS연결,MATCH(M$1,BS연결H,0),0)/100,"") | N8: =IFERROR(VLOOKUP($D8,BS연결,MATCH(N$1,BS연결H,0),0)/100,"") | ... AB8: =IFERROR(VLOOKUP($D8,BS연결,MATCH(AB$1,BS연결H,0),0)/100,"") | AC8: =IFERROR(AC5*변수!AC21,"") | AD8: =IFERROR(AD5*변수!AD21,"") | AE8: =SUM(AA8:AD8) | AF8: =IFERROR(AF5*변수!AF21,"") | AG8: =IFERROR(AG5*변수!AG21,"") | AH8: =IFERROR(AH5*변수!AH21,"") | AI8: =IFERROR(AI5*변수!AI21,"") | AJ8: =SUM(AF8:AI8) | AK8: =IFERROR(AK5*변수!AK21,"") | AL8: =IFERROR(AL5*변수!AL21,"") | AM8: =IFERROR(AM5*변수!AM21,"") | AN8: =IFERROR(AN5*변수!AN21,"") | AO8: =SUM(AK8:AN8)
A9: 영업이익 | B9: 손익 | C9: 억원 | D9: 영업이익 | E9: =IFERROR(VLOOKUP($D9,BS연결,MATCH(E$1,BS연결H,0),0)/100,"") | G9: =IFERROR(VLOOKUP($D9,BS연결,MATCH(G$1,BS연결H,0),0)/100,"") | H9: =IFERROR(VLOOKUP($D9,BS연결,MATCH(H$1,BS연결H,0),0)/100,"") | I9: =IFERROR(VLOOKUP($D9,BS연결,MATCH(I$1,BS연결H,0),0)/100,"") | J9: =IFERROR(VLOOKUP($D9,BS연결,MATCH(J$1,BS연결H,0),0)/100,"") | K9: =IFERROR(VLOOKUP($D9,BS연결,MATCH(K$1,BS연결H,0),0)/100,"") | L9: =IFERROR(VLOOKUP($D9,BS연결,MATCH(L$1,BS연결H,0),0)/100,"") | M9: =IFERROR(VLOOKUP($D9,BS연결,MATCH(M$1,BS연결H,0),0)/100,"") | N9: =IFERROR(VLOOKUP($D9,BS연결,MATCH(N$1,BS연결H,0),0)/100,"") | ... AB9: =IFERROR(VLOOKUP($D9,BS연결,MATCH(AB$1,BS연결H,0),0)/100,"") | AC9: =IFERROR(AC40+AC43,"") | AD9: =IFERROR(AD40+AD43,"") | AE9: =SUM(AA9:AD9) | AF9: =IFERROR(AF40+AF43,"") | AG9: =IFERROR(AG40+AG43,"") | AH9: =IFERROR(AH40+AH43,"") | AI9: =IFERROR(AI40+AI43,"") | AJ9: =SUM(AF9:AI9) | AK9: =IFERROR(AK40+AK43,"") | AL9: =IFERROR(AL40+AL43,"") | AM9: =IFERROR(AM40+AM43,"") | AN9: =IFERROR(AN40+AN43,"") | AO9: =SUM(AK9:AN9)
A10: OPM | B10: 손익 | C10: % | D10: 영업이익률 | E10: =IFERROR(E9/E5,"") | G10: =IFERROR(G9/G5,"") | H10: =IFERROR(H9/H5,"") | I10: =IFERROR(I9/I5,"") | J10: =IFERROR(J9/J5,"") | K10: =IFERROR(K9/K5,"") | L10: =IFERROR(L9/L5,"") | M10: =IFERROR(M9/M5,"") | N10: =IFERROR(N9/N5,"") | ... AO10: =IFERROR(AO9/AO5,"")
A11: 금융손익 | B11: 손익 | C11: 억원 | D11: 금융손익 | E11: =IFERROR(VLOOKUP($D11,BS연결,MATCH(E$1,BS연결H,0),0)/100,"") | G11: =IFERROR(VLOOKUP($D11,BS연결,MATCH(G$1,BS연결H,0),0)/100,"") | H11: =IFERROR(VLOOKUP($D11,BS연결,MATCH(H$1,BS연결H,0),0)/100,"") | I11: =IFERROR(VLOOKUP($D11,BS연결,MATCH(I$1,BS연결H,0),0)/100,"") | J11: =IFERROR(VLOOKUP($D11,BS연결,MATCH(J$1,BS연결H,0),0)/100,"") | K11: =IFERROR(VLOOKUP($D11,BS연결,MATCH(K$1,BS연결H,0),0)/100,"") | L11: =IFERROR(VLOOKUP($D11,BS연결,MATCH(L$1,BS연결H,0),0)/100,"") | M11: =IFERROR(VLOOKUP($D11,BS연결,MATCH(M$1,BS연결H,0),0)/100,"") | N11: =IFERROR(VLOOKUP($D11,BS연결,MATCH(N$1,BS연결H,0),0)/100,"") | ... AB11: =IFERROR(VLOOKUP($D11,BS연결,MATCH(AB$1,BS연결H,0),0)/100,"") | AC11: =IFERROR(AC12+AC13+AC14+AC15,"") | AD11: =IFERROR(AD12+AD13+AD14+AD15,"") | AE11: =SUM(AA11:AD11) | AF11: =IFERROR(AF12+AF13+AF14+AF15,"") | AG11: =IFERROR(AG12+AG13+AG14+AG15,"") | AH11: =IFERROR(AH12+AH13+AH14+AH15,"") | AI11: =IFERROR(AI12+AI13+AI14+AI15,"") | AJ11: =SUM(AF11:AI11) | AK11: =IFERROR(AK12+AK13+AK14+AK15,"") | AL11: =IFERROR(AL12+AL13+AL14+AL15,"") | AM11: =IFERROR(AM12+AM13+AM14+AM15,"") | AN11: =IFERROR(AN12+AN13+AN14+AN15,"") | AO11: =SUM(AK11:AN11)
A12: 이자손익 | B12: 손익 | C12: 억원 | D12: 이자손익 | G12: =IFERROR(VLOOKUP($D12,BS연결,MATCH(G$1,BS연결H,0),0)/100,"") | H12: =IFERROR(VLOOKUP($D12,BS연결,MATCH(H$1,BS연결H,0),0)/100,"") | I12: =IFERROR(VLOOKUP($D12,BS연결,MATCH(I$1,BS연결H,0),0)/100,"") | J12: =IFERROR(VLOOKUP($D12,BS연결,MATCH(J$1,BS연결H,0),0)/100,"") | K12: =IFERROR(VLOOKUP($D12,BS연결,MATCH(K$1,BS연결H,0),0)/100,"") | L12: =IFERROR(VLOOKUP($D12,BS연결,MATCH(L$1,BS연결H,0),0)/100,"") | M12: =IFERROR(VLOOKUP($D12,BS연결,MATCH(M$1,BS연결H,0),0)/100,"") | N12: =IFERROR(VLOOKUP($D12,BS연결,MATCH(N$1,BS연결H,0),0)/100,"") | ... AB12: =IFERROR(VLOOKUP($D12,BS연결,MATCH(AB$1,BS연결H,0),0)/100,"") | AC12: =IFERROR((AB28*변수!$D$57-AB26*변수!$D$58)/4,"") | AD12: =IFERROR((AC28*변수!$D$57-AC26*변수!$D$58)/4,"") | AE12: =SUM(AA12:AD12) | AF12: =IFERROR((AD28*변수!$D$57-AD26*변수!$D$58)/4,"") | AG12: =IFERROR((AF28*변수!$D$57-AF26*변수!$D$58)/4,"") | AH12: =IFERROR((AG28*변수!$D$57-AG26*변수!$D$58)/4,"") | AI12: =IFERROR((AH28*변수!$D$57-AH26*변수!$D$58)/4,"") | AJ12: =SUM(AF12:AI12) | AK12: =IFERROR((AI28*변수!$D$57-AI26*변수!$D$58)/4,"") | AL12: =IFERROR((AK28*변수!$D$57-AK26*변수!$D$58)/4,"") | AM12: =IFERROR((AL28*변수!$D$57-AL26*변수!$D$58)/4,"") | AN12: =IFERROR((AM28*변수!$D$57-AM26*변수!$D$58)/4,"") | AO12: =SUM(AK12:AN12)
A13: 외환손익 | B13: 손익 | C13: 억원 | D13: 외환손익(실적만; 추정 환효과는 환관련손익) | G13: =IFERROR((VLOOKUP("외환차익",BS연결,MATCH(G$1,BS연결H,0),0)-VLOOKUP("외환차손",BS연결,MATCH(G$1,BS연결H,0),0)+VLOOKUP("외화환산이익",BS연결,MATCH(G$1,BS연결H,0),0)-VLOOKUP("외화환산손실",BS연결,MATCH(G$1,BS연결H,0),0))/100,"") | H13: =IFERROR((VLOOKUP("외환차익",BS연결,MATCH(H$1,BS연결H,0),0)-VLOOKUP("외환차손",BS연결,MATCH(H$1,BS연결H,0),0)+VLOOKUP("외화환산이익",BS연결,MATCH(H$1,BS연결H,0),0)-VLOOKUP("외화환산손실",BS연결,MATCH(H$1,BS연결H,0),0))/100,"") | I13: =IFERROR((VLOOKUP("외환차익",BS연결,MATCH(I$1,BS연결H,0),0)-VLOOKUP("외환차손",BS연결,MATCH(I$1,BS연결H,0),0)+VLOOKUP("외화환산이익",BS연결,MATCH(I$1,BS연결H,0),0)-VLOOKUP("외화환산손실",BS연결,MATCH(I$1,BS연결H,0),0))/100,"") | J13: =IFERROR((VLOOKUP("외환차익",BS연결,MATCH(J$1,BS연결H,0),0)-VLOOKUP("외환차손",BS연결,MATCH(J$1,BS연결H,0),0)+VLOOKUP("외화환산이익",BS연결,MATCH(J$1,BS연결H,0),0)-VLOOKUP("외화환산손실",BS연결,MATCH(J$1,BS연결H,0),0))/100,"") | K13: =SUM(G13:J13) | L13: =IFERROR((VLOOKUP("외환차익",BS연결,MATCH(L$1,BS연결H,0),0)-VLOOKUP("외환차손",BS연결,MATCH(L$1,BS연결H,0),0)+VLOOKUP("외화환산이익",BS연결,MATCH(L$1,BS연결H,0),0)-VLOOKUP("외화환산손실",BS연결,MATCH(L$1,BS연결H,0),0))/100,"") | M13: =IFERROR((VLOOKUP("외환차익",BS연결,MATCH(M$1,BS연결H,0),0)-VLOOKUP("외환차손",BS연결,MATCH(M$1,BS연결H,0),0)+VLOOKUP("외화환산이익",BS연결,MATCH(M$1,BS연결H,0),0)-VLOOKUP("외화환산손실",BS연결,MATCH(M$1,BS연결H,0),0))/100,"") | N13: =IFERROR((VLOOKUP("외환차익",BS연결,MATCH(N$1,BS연결H,0),0)-VLOOKUP("외환차손",BS연결,MATCH(N$1,BS연결H,0),0)+VLOOKUP("외화환산이익",BS연결,MATCH(N$1,BS연결H,0),0)-VLOOKUP("외화환산손실",BS연결,MATCH(N$1,BS연결H,0),0))/100,"") | O13: =IFERROR((VLOOKUP("외환차익",BS연결,MATCH(O$1,BS연결H,0),0)-VLOOKUP("외환차손",BS연결,MATCH(O$1,BS연결H,0),0)+VLOOKUP("외화환산이익",BS연결,MATCH(O$1,BS연결H,0),0)-VLOOKUP("외화환산손실",BS연결,MATCH(O$1,BS연결H,0),0))/100,"") | P13: =SUM(L13:O13) | Q13: =IFERROR((VLOOKUP("외환차익",BS연결,MATCH(Q$1,BS연결H,0),0)-VLOOKUP("외환차손",BS연결,MATCH(Q$1,BS연결H,0),0)+VLOOKUP("외화환산이익",BS연결,MATCH(Q$1,BS연결H,0),0)-VLOOKUP("외화환산손실",BS연결,MATCH(Q$1,BS연결H,0),0))/100,"") | R13: =IFERROR((VLOOKUP("외환차익",BS연결,MATCH(R$1,BS연결H,0),0)-VLOOKUP("외환차손",BS연결,MATCH(R$1,BS연결H,0),0)+VLOOKUP("외화환산이익",BS연결,MATCH(R$1,BS연결H,0),0)-VLOOKUP("외화환산손실",BS연결,MATCH(R$1,BS연결H,0),0))/100,"") | S13: =IFERROR((VLOOKUP("외환차익",BS연결,MATCH(S$1,BS연결H,0),0)-VLOOKUP("외환차손",BS연결,MATCH(S$1,BS연결H,0),0)+VLOOKUP("외화환산이익",BS연결,MATCH(S$1,BS연결H,0),0)-VLOOKUP("외화환산손실",BS연결,MATCH(S$1,BS연결H,0),0))/100,"") | T13: =IFERROR((VLOOKUP("외환차익",BS연결,MATCH(T$1,BS연결H,0),0)-VLOOKUP("외환차손",BS연결,MATCH(T$1,BS연결H,0),0)+VLOOKUP("외화환산이익",BS연결,MATCH(T$1,BS연결H,0),0)-VLOOKUP("외화환산손실",BS연결,MATCH(T$1,BS연결H,0),0))/100,"") | U13: =SUM(Q13:T13) | V13: =IFERROR((VLOOKUP("외환차익",BS연결,MATCH(V$1,BS연결H,0),0)-VLOOKUP("외환차손",BS연결,MATCH(V$1,BS연결H,0),0)+VLOOKUP("외화환산이익",BS연결,MATCH(V$1,BS연결H,0),0)-VLOOKUP("외화환산손실",BS연결,MATCH(V$1,BS연결H,0),0))/100,"") | W13: =IFERROR((VLOOKUP("외환차익",BS연결,MATCH(W$1,BS연결H,0),0)-VLOOKUP("외환차손",BS연결,MATCH(W$1,BS연결H,0),0)+VLOOKUP("외화환산이익",BS연결,MATCH(W$1,BS연결H,0),0)-VLOOKUP("외화환산손실",BS연결,MATCH(W$1,BS연결H,0),0))/100,"") | X13: =IFERROR((VLOOKUP("외환차익",BS연결,MATCH(X$1,BS연결H,0),0)-VLOOKUP("외환차손",BS연결,MATCH(X$1,BS연결H,0),0)+VLOOKUP("외화환산이익",BS연결,MATCH(X$1,BS연결H,0),0)-VLOOKUP("외화환산손실",BS연결,MATCH(X$1,BS연결H,0),0))/100,"") | Y13: =IFERROR((VLOOKUP("외환차익",BS연결,MATCH(Y$1,BS연결H,0),0)-VLOOKUP("외환차손",BS연결,MATCH(Y$1,BS연결H,0),0)+VLOOKUP("외화환산이익",BS연결,MATCH(Y$1,BS연결H,0),0)-VLOOKUP("외화환산손실",BS연결,MATCH(Y$1,BS연결H,0),0))/100,"") | Z13: =SUM(V13:Y13) | AA13: =IFERROR((VLOOKUP("외환차익",BS연결,MATCH(AA$1,BS연결H,0),0)-VLOOKUP("외환차손",BS연결,MATCH(AA$1,BS연결H,0),0)+VLOOKUP("외화환산이익",BS연결,MATCH(AA$1,BS연결H,0),0)-VLOOKUP("외화환산손실",BS연결,MATCH(AA$1,BS연결H,0),0))/100,"") | AB13: =IFERROR((VLOOKUP("외환차익",BS연결,MATCH(AB$1,BS연결H,0),0)-VLOOKUP("외환차손",BS연결,MATCH(AB$1,BS연결H,0),0)+VLOOKUP("외화환산이익",BS연결,MATCH(AB$1,BS연결H,0),0)-VLOOKUP("외화환산손실",BS연결,MATCH(AB$1,BS연결H,0),0))/100,"") | AC13: =변수!AC22 | AD13: =변수!AD22 | AE13: =SUM(AA13:AD13) | AF13: =변수!AF22 | AG13: =변수!AG22 | AH13: =변수!AH22 | AI13: =변수!AI22 | AJ13: =SUM(AF13:AI13) | AK13: =변수!AK22 | AL13: =변수!AL22 | AM13: =변수!AM22 | AN13: =변수!AN22 | AO13: =SUM(AK13:AN13)
A14: 파생상품손익 | B14: 손익 | C14: 억원 | D14: 파생상품손익 | G14: =IFERROR((VLOOKUP("파생상품이익",BS연결,MATCH(G$1,BS연결H,0),0)-VLOOKUP("파생상품손실",BS연결,MATCH(G$1,BS연결H,0),0))/100,"") | H14: =IFERROR((VLOOKUP("파생상품이익",BS연결,MATCH(H$1,BS연결H,0),0)-VLOOKUP("파생상품손실",BS연결,MATCH(H$1,BS연결H,0),0))/100,"") | I14: =IFERROR((VLOOKUP("파생상품이익",BS연결,MATCH(I$1,BS연결H,0),0)-VLOOKUP("파생상품손실",BS연결,MATCH(I$1,BS연결H,0),0))/100,"") | J14: =IFERROR((VLOOKUP("파생상품이익",BS연결,MATCH(J$1,BS연결H,0),0)-VLOOKUP("파생상품손실",BS연결,MATCH(J$1,BS연결H,0),0))/100,"") | K14: =SUM(G14:J14) | L14: =IFERROR((VLOOKUP("파생상품이익",BS연결,MATCH(L$1,BS연결H,0),0)-VLOOKUP("파생상품손실",BS연결,MATCH(L$1,BS연결H,0),0))/100,"") | M14: =IFERROR((VLOOKUP("파생상품이익",BS연결,MATCH(M$1,BS연결H,0),0)-VLOOKUP("파생상품손실",BS연결,MATCH(M$1,BS연결H,0),0))/100,"") | N14: =IFERROR((VLOOKUP("파생상품이익",BS연결,MATCH(N$1,BS연결H,0),0)-VLOOKUP("파생상품손실",BS연결,MATCH(N$1,BS연결H,0),0))/100,"") | O14: =IFERROR((VLOOKUP("파생상품이익",BS연결,MATCH(O$1,BS연결H,0),0)-VLOOKUP("파생상품손실",BS연결,MATCH(O$1,BS연결H,0),0))/100,"") | P14: =SUM(L14:O14) | Q14: =IFERROR((VLOOKUP("파생상품이익",BS연결,MATCH(Q$1,BS연결H,0),0)-VLOOKUP("파생상품손실",BS연결,MATCH(Q$1,BS연결H,0),0))/100,"") | R14: =IFERROR((VLOOKUP("파생상품이익",BS연결,MATCH(R$1,BS연결H,0),0)-VLOOKUP("파생상품손실",BS연결,MATCH(R$1,BS연결H,0),0))/100,"") | S14: =IFERROR((VLOOKUP("파생상품이익",BS연결,MATCH(S$1,BS연결H,0),0)-VLOOKUP("파생상품손실",BS연결,MATCH(S$1,BS연결H,0),0))/100,"") | T14: =IFERROR((VLOOKUP("파생상품이익",BS연결,MATCH(T$1,BS연결H,0),0)-VLOOKUP("파생상품손실",BS연결,MATCH(T$1,BS연결H,0),0))/100,"") | U14: =SUM(Q14:T14) | V14: =IFERROR((VLOOKUP("파생상품이익",BS연결,MATCH(V$1,BS연결H,0),0)-VLOOKUP("파생상품손실",BS연결,MATCH(V$1,BS연결H,0),0))/100,"") | W14: =IFERROR((VLOOKUP("파생상품이익",BS연결,MATCH(W$1,BS연결H,0),0)-VLOOKUP("파생상품손실",BS연결,MATCH(W$1,BS연결H,0),0))/100,"") | X14: =IFERROR((VLOOKUP("파생상품이익",BS연결,MATCH(X$1,BS연결H,0),0)-VLOOKUP("파생상품손실",BS연결,MATCH(X$1,BS연결H,0),0))/100,"") | Y14: =IFERROR((VLOOKUP("파생상품이익",BS연결,MATCH(Y$1,BS연결H,0),0)-VLOOKUP("파생상품손실",BS연결,MATCH(Y$1,BS연결H,0),0))/100,"") | Z14: =SUM(V14:Y14) | AA14: =IFERROR((VLOOKUP("파생상품이익",BS연결,MATCH(AA$1,BS연결H,0),0)-VLOOKUP("파생상품손실",BS연결,MATCH(AA$1,BS연결H,0),0))/100,"") | AB14: =IFERROR((VLOOKUP("파생상품이익",BS연결,MATCH(AB$1,BS연결H,0),0)-VLOOKUP("파생상품손실",BS연결,MATCH(AB$1,BS연결H,0),0))/100,"") | AC14: =변수!AC23 | AD14: =변수!AD23 | AE14: =SUM(AA14:AD14) | AF14: =변수!AF23 | AG14: =변수!AG23 | AH14: =변수!AH23 | AI14: =변수!AI23 | AJ14: =SUM(AF14:AI14) | AK14: =변수!AK23 | AL14: =변수!AL23 | AM14: =변수!AM23 | AN14: =변수!AN23 | AO14: =SUM(AK14:AN14)
A15: 기타금융손익 | B15: 손익 | C15: 억원 | D15: 기타금융손익(금융손익 잔차) | G15: =IFERROR(G11-G12-G13-G14,"") | H15: =IFERROR(H11-H12-H13-H14,"") | I15: =IFERROR(I11-I12-I13-I14,"") | J15: =IFERROR(J11-J12-J13-J14,"") | K15: =SUM(G15:J15) | L15: =IFERROR(L11-L12-L13-L14,"") | M15: =IFERROR(M11-M12-M13-M14,"") | N15: =IFERROR(N11-N12-N13-N14,"") | O15: =IFERROR(O11-O12-O13-O14,"") | P15: =SUM(L15:O15) | Q15: =IFERROR(Q11-Q12-Q13-Q14,"") | R15: =IFERROR(R11-R12-R13-R14,"") | S15: =IFERROR(S11-S12-S13-S14,"") | T15: =IFERROR(T11-T12-T13-T14,"") | U15: =SUM(Q15:T15) | V15: =IFERROR(V11-V12-V13-V14,"") | W15: =IFERROR(W11-W12-W13-W14,"") | X15: =IFERROR(X11-X12-X13-X14,"") | Y15: =IFERROR(Y11-Y12-Y13-Y14,"") | Z15: =SUM(V15:Y15) | AA15: =IFERROR(AA11-AA12-AA13-AA14,"") | AB15: =IFERROR(AB11-AB12-AB13-AB14,"") | AC15: =변수!AC24 | AD15: =변수!AD24 | AE15: =SUM(AA15:AD15) | AF15: =변수!AF24 | AG15: =변수!AG24 | AH15: =변수!AH24 | AI15: =변수!AI24 | AJ15: =SUM(AF15:AI15) | AK15: =변수!AK24 | AL15: =변수!AL24 | AM15: =변수!AM24 | AN15: =변수!AN24 | AO15: =SUM(AK15:AN15)
A16: 기타영업외손익 | B16: 손익 | C16: 억원 | D16: 기타영업외손익 | E16: =IFERROR(VLOOKUP($D16,BS연결,MATCH(E$1,BS연결H,0),0)/100,"") | G16: =IFERROR(VLOOKUP($D16,BS연결,MATCH(G$1,BS연결H,0),0)/100,"") | H16: =IFERROR(VLOOKUP($D16,BS연결,MATCH(H$1,BS연결H,0),0)/100,"") | I16: =IFERROR(VLOOKUP($D16,BS연결,MATCH(I$1,BS연결H,0),0)/100,"") | J16: =IFERROR(VLOOKUP($D16,BS연결,MATCH(J$1,BS연결H,0),0)/100,"") | K16: =IFERROR(VLOOKUP($D16,BS연결,MATCH(K$1,BS연결H,0),0)/100,"") | L16: =IFERROR(VLOOKUP($D16,BS연결,MATCH(L$1,BS연결H,0),0)/100,"") | M16: =IFERROR(VLOOKUP($D16,BS연결,MATCH(M$1,BS연결H,0),0)/100,"") | N16: =IFERROR(VLOOKUP($D16,BS연결,MATCH(N$1,BS연결H,0),0)/100,"") | ... AB16: =IFERROR(VLOOKUP($D16,BS연결,MATCH(AB$1,BS연결H,0),0)/100,"") | AC16: =변수!AC25 | AD16: =변수!AD25 | AE16: =SUM(AA16:AD16) | AF16: =변수!AF25 | AG16: =변수!AG25 | AH16: =변수!AH25 | AI16: =변수!AI25 | AJ16: =SUM(AF16:AI16) | AK16: =변수!AK25 | AL16: =변수!AL25 | AM16: =변수!AM25 | AN16: =변수!AN25 | AO16: =SUM(AK16:AN16)
A17: 지분법손익 | B17: 손익 | C17: 억원 | D17: 종속기업,공동지배기업및관계기업관련손익 | E17: =IFERROR(VLOOKUP($D17,BS연결,MATCH(E$1,BS연결H,0),0)/100,"") | G17: =IFERROR(VLOOKUP($D17,BS연결,MATCH(G$1,BS연결H,0),0)/100,"") | H17: =IFERROR(VLOOKUP($D17,BS연결,MATCH(H$1,BS연결H,0),0)/100,"") | I17: =IFERROR(VLOOKUP($D17,BS연결,MATCH(I$1,BS연결H,0),0)/100,"") | J17: =IFERROR(VLOOKUP($D17,BS연결,MATCH(J$1,BS연결H,0),0)/100,"") | K17: =IFERROR(VLOOKUP($D17,BS연결,MATCH(K$1,BS연결H,0),0)/100,"") | L17: =IFERROR(VLOOKUP($D17,BS연결,MATCH(L$1,BS연결H,0),0)/100,"") | M17: =IFERROR(VLOOKUP($D17,BS연결,MATCH(M$1,BS연결H,0),0)/100,"") | N17: =IFERROR(VLOOKUP($D17,BS연결,MATCH(N$1,BS연결H,0),0)/100,"") | ... AB17: =IFERROR(VLOOKUP($D17,BS연결,MATCH(AB$1,BS연결H,0),0)/100,"") | AC17: =변수!AC26 | AD17: =변수!AD26 | AE17: =SUM(AA17:AD17) | AF17: =변수!AF26 | AG17: =변수!AG26 | AH17: =변수!AH26 | AI17: =변수!AI26 | AJ17: =SUM(AF17:AI17) | AK17: =변수!AK26 | AL17: =변수!AL26 | AM17: =변수!AM26 | AN17: =변수!AN26 | AO17: =SUM(AK17:AN17)
A18: 세전이익 | B18: 손익 | C18: 억원 | D18: 법인세비용차감전계속사업이익 | E18: =IFERROR(VLOOKUP($D18,BS연결,MATCH(E$1,BS연결H,0),0)/100,"") | G18: =IFERROR(VLOOKUP($D18,BS연결,MATCH(G$1,BS연결H,0),0)/100,"") | H18: =IFERROR(VLOOKUP($D18,BS연결,MATCH(H$1,BS연결H,0),0)/100,"") | I18: =IFERROR(VLOOKUP($D18,BS연결,MATCH(I$1,BS연결H,0),0)/100,"") | J18: =IFERROR(VLOOKUP($D18,BS연결,MATCH(J$1,BS연결H,0),0)/100,"") | K18: =IFERROR(VLOOKUP($D18,BS연결,MATCH(K$1,BS연결H,0),0)/100,"") | L18: =IFERROR(VLOOKUP($D18,BS연결,MATCH(L$1,BS연결H,0),0)/100,"") | M18: =IFERROR(VLOOKUP($D18,BS연결,MATCH(M$1,BS연결H,0),0)/100,"") | N18: =IFERROR(VLOOKUP($D18,BS연결,MATCH(N$1,BS연결H,0),0)/100,"") | ... AB18: =IFERROR(VLOOKUP($D18,BS연결,MATCH(AB$1,BS연결H,0),0)/100,"") | AC18: =IFERROR(AC9+AC11+AC16+AC17,"") | AD18: =IFERROR(AD9+AD11+AD16+AD17,"") | AE18: =SUM(AA18:AD18) | AF18: =IFERROR(AF9+AF11+AF16+AF17,"") | AG18: =IFERROR(AG9+AG11+AG16+AG17,"") | AH18: =IFERROR(AH9+AH11+AH16+AH17,"") | AI18: =IFERROR(AI9+AI11+AI16+AI17,"") | AJ18: =SUM(AF18:AI18) | AK18: =IFERROR(AK9+AK11+AK16+AK17,"") | AL18: =IFERROR(AL9+AL11+AL16+AL17,"") | AM18: =IFERROR(AM9+AM11+AM16+AM17,"") | AN18: =IFERROR(AN9+AN11+AN16+AN17,"") | AO18: =SUM(AK18:AN18)
A19: 법인세비용 | B19: 손익 | C19: 억원 | D19: 법인세비용 | E19: =IFERROR(VLOOKUP($D19,BS연결,MATCH(E$1,BS연결H,0),0)/100,"") | G19: =IFERROR(VLOOKUP($D19,BS연결,MATCH(G$1,BS연결H,0),0)/100,"") | H19: =IFERROR(VLOOKUP($D19,BS연결,MATCH(H$1,BS연결H,0),0)/100,"") | I19: =IFERROR(VLOOKUP($D19,BS연결,MATCH(I$1,BS연결H,0),0)/100,"") | J19: =IFERROR(VLOOKUP($D19,BS연결,MATCH(J$1,BS연결H,0),0)/100,"") | K19: =IFERROR(VLOOKUP($D19,BS연결,MATCH(K$1,BS연결H,0),0)/100,"") | L19: =IFERROR(VLOOKUP($D19,BS연결,MATCH(L$1,BS연결H,0),0)/100,"") | M19: =IFERROR(VLOOKUP($D19,BS연결,MATCH(M$1,BS연결H,0),0)/100,"") | N19: =IFERROR(VLOOKUP($D19,BS연결,MATCH(N$1,BS연결H,0),0)/100,"") | ... AB19: =IFERROR(VLOOKUP($D19,BS연결,MATCH(AB$1,BS연결H,0),0)/100,"") | AC19: =IFERROR(MAX(AC18,0)*변수!AC27,"") | AD19: =IFERROR(MAX(AD18,0)*변수!AD27,"") | AE19: =SUM(AA19:AD19) | AF19: =IFERROR(MAX(AF18,0)*변수!AF27,"") | AG19: =IFERROR(MAX(AG18,0)*변수!AG27,"") | AH19: =IFERROR(MAX(AH18,0)*변수!AH27,"") | AI19: =IFERROR(MAX(AI18,0)*변수!AI27,"") | AJ19: =SUM(AF19:AI19) | AK19: =IFERROR(MAX(AK18,0)*변수!AK27,"") | AL19: =IFERROR(MAX(AL18,0)*변수!AL27,"") | AM19: =IFERROR(MAX(AM18,0)*변수!AM27,"") | AN19: =IFERROR(MAX(AN18,0)*변수!AN27,"") | AO19: =SUM(AK19:AN19)
A20: 당기순이익 | B20: 손익 | C20: 억원 | D20: 당기순이익 | E20: =IFERROR(VLOOKUP($D20,BS연결,MATCH(E$1,BS연결H,0),0)/100,"") | G20: =IFERROR(VLOOKUP($D20,BS연결,MATCH(G$1,BS연결H,0),0)/100,"") | H20: =IFERROR(VLOOKUP($D20,BS연결,MATCH(H$1,BS연결H,0),0)/100,"") | I20: =IFERROR(VLOOKUP($D20,BS연결,MATCH(I$1,BS연결H,0),0)/100,"") | J20: =IFERROR(VLOOKUP($D20,BS연결,MATCH(J$1,BS연결H,0),0)/100,"") | K20: =IFERROR(VLOOKUP($D20,BS연결,MATCH(K$1,BS연결H,0),0)/100,"") | L20: =IFERROR(VLOOKUP($D20,BS연결,MATCH(L$1,BS연결H,0),0)/100,"") | M20: =IFERROR(VLOOKUP($D20,BS연결,MATCH(M$1,BS연결H,0),0)/100,"") | N20: =IFERROR(VLOOKUP($D20,BS연결,MATCH(N$1,BS연결H,0),0)/100,"") | ... AB20: =IFERROR(VLOOKUP($D20,BS연결,MATCH(AB$1,BS연결H,0),0)/100,"") | AC20: =IFERROR(AC18-AC19,"") | AD20: =IFERROR(AD18-AD19,"") | AE20: =SUM(AA20:AD20) | AF20: =IFERROR(AF18-AF19,"") | AG20: =IFERROR(AG18-AG19,"") | AH20: =IFERROR(AH18-AH19,"") | AI20: =IFERROR(AI18-AI19,"") | AJ20: =SUM(AF20:AI20) | AK20: =IFERROR(AK18-AK19,"") | AL20: =IFERROR(AL18-AL19,"") | AM20: =IFERROR(AM18-AM19,"") | AN20: =IFERROR(AN18-AN19,"") | AO20: =SUM(AK20:AN20)
A21: 지배주주순이익 | B21: 손익 | C21: 억원 | D21: (지배주주지분)당기순이익 | E21: =IFERROR(VLOOKUP($D21,BS연결,MATCH(E$1,BS연결H,0),0)/100,"") | G21: =IFERROR(VLOOKUP($D21,BS연결,MATCH(G$1,BS연결H,0),0)/100,"") | H21: =IFERROR(VLOOKUP($D21,BS연결,MATCH(H$1,BS연결H,0),0)/100,"") | I21: =IFERROR(VLOOKUP($D21,BS연결,MATCH(I$1,BS연결H,0),0)/100,"") | J21: =IFERROR(VLOOKUP($D21,BS연결,MATCH(J$1,BS연결H,0),0)/100,"") | K21: =IFERROR(VLOOKUP($D21,BS연결,MATCH(K$1,BS연결H,0),0)/100,"") | L21: =IFERROR(VLOOKUP($D21,BS연결,MATCH(L$1,BS연결H,0),0)/100,"") | M21: =IFERROR(VLOOKUP($D21,BS연결,MATCH(M$1,BS연결H,0),0)/100,"") | N21: =IFERROR(VLOOKUP($D21,BS연결,MATCH(N$1,BS연결H,0),0)/100,"") | O21: =IFERROR(VLOOKUP($D21,BS연결,MATCH(O$1,BS연결H,0),0)/100,"") | P21: =SUM(L21:O21) | Q21: =IFERROR(VLOOKUP($D21,BS연결,MATCH(Q$1,BS연결H,0),0)/100,"") | R21: =IFERROR(VLOOKUP($D21,BS연결,MATCH(R$1,BS연결H,0),0)/100,"") | S21: =IFERROR(VLOOKUP($D21,BS연결,MATCH(S$1,BS연결H,0),0)/100,"") | T21: =IFERROR(VLOOKUP($D21,BS연결,MATCH(T$1,BS연결H,0),0)/100,"") | U21: =IFERROR(VLOOKUP($D21,BS연결,MATCH(U$1,BS연결H,0),0)/100,"") | V21: =IFERROR(VLOOKUP($D21,BS연결,MATCH(V$1,BS연결H,0),0)/100,"") | W21: =IFERROR(VLOOKUP($D21,BS연결,MATCH(W$1,BS연결H,0),0)/100,"") | X21: =IFERROR(VLOOKUP($D21,BS연결,MATCH(X$1,BS연결H,0),0)/100,"") | ... AB21: =IFERROR(VLOOKUP($D21,BS연결,MATCH(AB$1,BS연결H,0),0)/100,"") | AC21: =IFERROR(AC20*변수!AC28,"") | AD21: =IFERROR(AD20*변수!AD28,"") | AE21: =SUM(AA21:AD21) | AF21: =IFERROR(AF20*변수!AF28,"") | AG21: =IFERROR(AG20*변수!AG28,"") | AH21: =IFERROR(AH20*변수!AH28,"") | AI21: =IFERROR(AI20*변수!AI28,"") | AJ21: =SUM(AF21:AI21) | AK21: =IFERROR(AK20*변수!AK28,"") | AL21: =IFERROR(AL20*변수!AL28,"") | AM21: =IFERROR(AM20*변수!AM28,"") | AN21: =IFERROR(AN20*변수!AN28,"") | AO21: =SUM(AK21:AN21)
A22: 자산총계 | B22: 재무상태 | C22: 억원 | D22: 자산총계 | E22: =IFERROR(VLOOKUP($D22,BS연결,MATCH(E$1,BS연결H,0),0)/100,"") | F22: =IFERROR(VLOOKUP($D22,BS연결,MATCH(F$1,BS연결H,0),0)/100,"") | G22: =IFERROR(VLOOKUP($D22,BS연결,MATCH(G$1,BS연결H,0),0)/100,"") | H22: =IFERROR(VLOOKUP($D22,BS연결,MATCH(H$1,BS연결H,0),0)/100,"") | I22: =IFERROR(VLOOKUP($D22,BS연결,MATCH(I$1,BS연결H,0),0)/100,"") | J22: =IFERROR(VLOOKUP($D22,BS연결,MATCH(J$1,BS연결H,0),0)/100,"") | K22: =IFERROR(VLOOKUP($D22,BS연결,MATCH(K$1,BS연결H,0),0)/100,"") | L22: =IFERROR(VLOOKUP($D22,BS연결,MATCH(L$1,BS연결H,0),0)/100,"") | ... AB22: =IFERROR(VLOOKUP($D22,BS연결,MATCH(AB$1,BS연결H,0),0)/100,"") | AC22: =IFERROR(AC23+AC24,"") | AD22: =IFERROR(AD23+AD24,"") | AE22: =AD22 | AF22: =IFERROR(AF23+AF24,"") | AG22: =IFERROR(AG23+AG24,"") | AH22: =IFERROR(AH23+AH24,"") | AI22: =IFERROR(AI23+AI24,"") | AJ22: =AI22 | AK22: =IFERROR(AK23+AK24,"") | AL22: =IFERROR(AL23+AL24,"") | AM22: =IFERROR(AM23+AM24,"") | AN22: =IFERROR(AN23+AN24,"") | AO22: =AN22
A23: 부채총계 | B23: 재무상태 | C23: 억원 | D23: 부채총계 | E23: =IFERROR(VLOOKUP($D23,BS연결,MATCH(E$1,BS연결H,0),0)/100,"") | F23: =IFERROR(VLOOKUP($D23,BS연결,MATCH(F$1,BS연결H,0),0)/100,"") | G23: =IFERROR(VLOOKUP($D23,BS연결,MATCH(G$1,BS연결H,0),0)/100,"") | H23: =IFERROR(VLOOKUP($D23,BS연결,MATCH(H$1,BS연결H,0),0)/100,"") | I23: =IFERROR(VLOOKUP($D23,BS연결,MATCH(I$1,BS연결H,0),0)/100,"") | J23: =IFERROR(VLOOKUP($D23,BS연결,MATCH(J$1,BS연결H,0),0)/100,"") | K23: =IFERROR(VLOOKUP($D23,BS연결,MATCH(K$1,BS연결H,0),0)/100,"") | L23: =IFERROR(VLOOKUP($D23,BS연결,MATCH(L$1,BS연결H,0),0)/100,"") | ... AB23: =IFERROR(VLOOKUP($D23,BS연결,MATCH(AB$1,BS연결H,0),0)/100,"") | AC23: =IFERROR(AB23*(1+변수!AC29),"") | AD23: =IFERROR(AC23*(1+변수!AD29),"") | AE23: =AD23 | AF23: =IFERROR(AD23*(1+변수!AF29),"") | AG23: =IFERROR(AF23*(1+변수!AG29),"") | AH23: =IFERROR(AG23*(1+변수!AH29),"") | AI23: =IFERROR(AH23*(1+변수!AI29),"") | AJ23: =AI23 | AK23: =IFERROR(AI23*(1+변수!AK29),"") | AL23: =IFERROR(AK23*(1+변수!AL29),"") | AM23: =IFERROR(AL23*(1+변수!AM29),"") | AN23: =IFERROR(AM23*(1+변수!AN29),"") | AO23: =AN23
A24: 자본총계 | B24: 재무상태 | C24: 억원 | D24: 자본총계 | E24: =IFERROR(VLOOKUP($D24,BS연결,MATCH(E$1,BS연결H,0),0)/100,"") | F24: =IFERROR(VLOOKUP($D24,BS연결,MATCH(F$1,BS연결H,0),0)/100,"") | G24: =IFERROR(VLOOKUP($D24,BS연결,MATCH(G$1,BS연결H,0),0)/100,"") | H24: =IFERROR(VLOOKUP($D24,BS연결,MATCH(H$1,BS연결H,0),0)/100,"") | I24: =IFERROR(VLOOKUP($D24,BS연결,MATCH(I$1,BS연결H,0),0)/100,"") | J24: =IFERROR(VLOOKUP($D24,BS연결,MATCH(J$1,BS연결H,0),0)/100,"") | K24: =IFERROR(VLOOKUP($D24,BS연결,MATCH(K$1,BS연결H,0),0)/100,"") | L24: =IFERROR(VLOOKUP($D24,BS연결,MATCH(L$1,BS연결H,0),0)/100,"") | ... AB24: =IFERROR(VLOOKUP($D24,BS연결,MATCH(AB$1,BS연결H,0),0)/100,"") | AC24: =IFERROR(AB24+AC20-변수!AC30,"") | AD24: =IFERROR(AC24+AD20-변수!AD30,"") | AE24: =AD24 | AF24: =IFERROR(AD24+AF20-변수!AF30,"") | AG24: =IFERROR(AF24+AG20-변수!AG30,"") | AH24: =IFERROR(AG24+AH20-변수!AH30,"") | AI24: =IFERROR(AH24+AI20-변수!AI30,"") | AJ24: =AI24 | AK24: =IFERROR(AI24+AK20-변수!AK30,"") | AL24: =IFERROR(AK24+AL20-변수!AL30,"") | AM24: =IFERROR(AL24+AM20-변수!AM30,"") | AN24: =IFERROR(AM24+AN20-변수!AN30,"") | AO24: =AN24
A25: 지배주주지분 | B25: 재무상태 | C25: 억원 | D25: 지배주주지분 | E25: =IFERROR(VLOOKUP($D25,BS연결,MATCH(E$1,BS연결H,0),0)/100,"") | F25: =IFERROR(VLOOKUP($D25,BS연결,MATCH(F$1,BS연결H,0),0)/100,"") | G25: =IFERROR(VLOOKUP($D25,BS연결,MATCH(G$1,BS연결H,0),0)/100,"") | H25: =IFERROR(VLOOKUP($D25,BS연결,MATCH(H$1,BS연결H,0),0)/100,"") | I25: =IFERROR(VLOOKUP($D25,BS연결,MATCH(I$1,BS연결H,0),0)/100,"") | J25: =IFERROR(VLOOKUP($D25,BS연결,MATCH(J$1,BS연결H,0),0)/100,"") | K25: =IFERROR(VLOOKUP($D25,BS연결,MATCH(K$1,BS연결H,0),0)/100,"") | L25: =IFERROR(VLOOKUP($D25,BS연결,MATCH(L$1,BS연결H,0),0)/100,"") | ... AB25: =IFERROR(VLOOKUP($D25,BS연결,MATCH(AB$1,BS연결H,0),0)/100,"") | AC25: =IFERROR(AB25+AC21-변수!AC31,"") | AD25: =IFERROR(AC25+AD21-변수!AD31,"") | AE25: =AD25 | AF25: =IFERROR(AD25+AF21-변수!AF31,"") | AG25: =IFERROR(AF25+AG21-변수!AG31,"") | AH25: =IFERROR(AG25+AH21-변수!AH31,"") | AI25: =IFERROR(AH25+AI21-변수!AI31,"") | AJ25: =AI25 | AK25: =IFERROR(AI25+AK21-변수!AK31,"") | AL25: =IFERROR(AK25+AL21-변수!AL31,"") | AM25: =IFERROR(AL25+AM21-변수!AM31,"") | AN25: =IFERROR(AM25+AN21-변수!AN31,"") | AO25: =AN25
A26: 총차입금 | B26: 재무상태 | C26: 억원 | D26: 총차입금 | E26: =IFERROR(VLOOKUP($D26,BS연결,MATCH(E$1,BS연결H,0),0)/100,"") | F26: =IFERROR(VLOOKUP($D26,BS연결,MATCH(F$1,BS연결H,0),0)/100,"") | G26: =IFERROR(VLOOKUP($D26,BS연결,MATCH(G$1,BS연결H,0),0)/100,"") | H26: =IFERROR(VLOOKUP($D26,BS연결,MATCH(H$1,BS연결H,0),0)/100,"") | I26: =IFERROR(VLOOKUP($D26,BS연결,MATCH(I$1,BS연결H,0),0)/100,"") | J26: =IFERROR(VLOOKUP($D26,BS연결,MATCH(J$1,BS연결H,0),0)/100,"") | K26: =IFERROR(VLOOKUP($D26,BS연결,MATCH(K$1,BS연결H,0),0)/100,"") | L26: =IFERROR(VLOOKUP($D26,BS연결,MATCH(L$1,BS연결H,0),0)/100,"") | ... AB26: =IFERROR(VLOOKUP($D26,BS연결,MATCH(AB$1,BS연결H,0),0)/100,"") | AC26: =IFERROR(AB26*(1+변수!AC32),"") | AD26: =IFERROR(AC26*(1+변수!AD32),"") | AE26: =AD26 | AF26: =IFERROR(AD26*(1+변수!AF32),"") | AG26: =IFERROR(AF26*(1+변수!AG32),"") | AH26: =IFERROR(AG26*(1+변수!AH32),"") | AI26: =IFERROR(AH26*(1+변수!AI32),"") | AJ26: =AI26 | AK26: =IFERROR(AI26*(1+변수!AK32),"") | AL26: =IFERROR(AK26*(1+변수!AL32),"") | AM26: =IFERROR(AL26*(1+변수!AM32),"") | AN26: =IFERROR(AM26*(1+변수!AN32),"") | AO26: =AN26
A27: 순차입금 | B27: 재무상태 | C27: 억원 | D27: 순차입금 | E27: =IFERROR(VLOOKUP($D27,BS연결,MATCH(E$1,BS연결H,0),0)/100,"") | F27: =IFERROR(VLOOKUP($D27,BS연결,MATCH(F$1,BS연결H,0),0)/100,"") | G27: =IFERROR(VLOOKUP($D27,BS연결,MATCH(G$1,BS연결H,0),0)/100,"") | H27: =IFERROR(VLOOKUP($D27,BS연결,MATCH(H$1,BS연결H,0),0)/100,"") | I27: =IFERROR(VLOOKUP($D27,BS연결,MATCH(I$1,BS연결H,0),0)/100,"") | J27: =IFERROR(VLOOKUP($D27,BS연결,MATCH(J$1,BS연결H,0),0)/100,"") | K27: =IFERROR(VLOOKUP($D27,BS연결,MATCH(K$1,BS연결H,0),0)/100,"") | L27: =IFERROR(VLOOKUP($D27,BS연결,MATCH(L$1,BS연결H,0),0)/100,"") | ... AB27: =IFERROR(VLOOKUP($D27,BS연결,MATCH(AB$1,BS연결H,0),0)/100,"") | AC27: =IFERROR(AB27*(1+변수!AC33),"") | AD27: =IFERROR(AC27*(1+변수!AD33),"") | AE27: =AD27 | AF27: =IFERROR(AD27*(1+변수!AF33),"") | AG27: =IFERROR(AF27*(1+변수!AG33),"") | AH27: =IFERROR(AG27*(1+변수!AH33),"") | AI27: =IFERROR(AH27*(1+변수!AI33),"") | AJ27: =AI27 | AK27: =IFERROR(AI27*(1+변수!AK33),"") | AL27: =IFERROR(AK27*(1+변수!AL33),"") | AM27: =IFERROR(AL27*(1+변수!AM33),"") | AN27: =IFERROR(AM27*(1+변수!AN33),"") | AO27: =AN27
A28: 이자발생자산 | B28: 재무상태 | C28: 억원 | D28: 이자발생자산 | E28: =IFERROR(VLOOKUP($D28,BS연결,MATCH(E$1,BS연결H,0),0)/100,"") | F28: =IFERROR(VLOOKUP($D28,BS연결,MATCH(F$1,BS연결H,0),0)/100,"") | G28: =IFERROR(VLOOKUP($D28,BS연결,MATCH(G$1,BS연결H,0),0)/100,"") | H28: =IFERROR(VLOOKUP($D28,BS연결,MATCH(H$1,BS연결H,0),0)/100,"") | I28: =IFERROR(VLOOKUP($D28,BS연결,MATCH(I$1,BS연결H,0),0)/100,"") | J28: =IFERROR(VLOOKUP($D28,BS연결,MATCH(J$1,BS연결H,0),0)/100,"") | K28: =IFERROR(VLOOKUP($D28,BS연결,MATCH(K$1,BS연결H,0),0)/100,"") | L28: =IFERROR(VLOOKUP($D28,BS연결,MATCH(L$1,BS연결H,0),0)/100,"") | ... AB28: =IFERROR(VLOOKUP($D28,BS연결,MATCH(AB$1,BS연결H,0),0)/100,"") | AC28: =IFERROR(AB28*(1+변수!AC34),"") | AD28: =IFERROR(AC28*(1+변수!AD34),"") | AE28: =AD28 | AF28: =IFERROR(AD28*(1+변수!AF34),"") | AG28: =IFERROR(AF28*(1+변수!AG34),"") | AH28: =IFERROR(AG28*(1+변수!AH34),"") | AI28: =IFERROR(AH28*(1+변수!AI34),"") | AJ28: =AI28 | AK28: =IFERROR(AI28*(1+변수!AK34),"") | AL28: =IFERROR(AK28*(1+변수!AL34),"") | AM28: =IFERROR(AL28*(1+변수!AM34),"") | AN28: =IFERROR(AM28*(1+변수!AN34),"") | AO28: =AN28
A29: 현금및현금성자산 | B29: 재무상태 | C29: 억원 | D29: 현금및현금성자산 | E29: =IFERROR(VLOOKUP($D29,BS연결,MATCH(E$1,BS연결H,0),0)/100,"") | F29: =IFERROR(VLOOKUP($D29,BS연결,MATCH(F$1,BS연결H,0),0)/100,"") | G29: =IFERROR(VLOOKUP($D29,BS연결,MATCH(G$1,BS연결H,0),0)/100,"") | H29: =IFERROR(VLOOKUP($D29,BS연결,MATCH(H$1,BS연결H,0),0)/100,"") | I29: =IFERROR(VLOOKUP($D29,BS연결,MATCH(I$1,BS연결H,0),0)/100,"") | J29: =IFERROR(VLOOKUP($D29,BS연결,MATCH(J$1,BS연결H,0),0)/100,"") | K29: =IFERROR(VLOOKUP($D29,BS연결,MATCH(K$1,BS연결H,0),0)/100,"") | L29: =IFERROR(VLOOKUP($D29,BS연결,MATCH(L$1,BS연결H,0),0)/100,"") | ... AB29: =IFERROR(VLOOKUP($D29,BS연결,MATCH(AB$1,BS연결H,0),0)/100,"") | AE29: =AD29 | AJ29: =AI29 | AO29: =AN29
A30: CAPEX | B30: 현금흐름 | C30: 억원 | D30: CAPEX | E30: =IFERROR(VLOOKUP($D30,BS연결,MATCH(E$1,BS연결H,0),0)/100,"") | G30: =IFERROR(VLOOKUP($D30,BS연결,MATCH(G$1,BS연결H,0),0)/100,"") | H30: =IFERROR(VLOOKUP($D30,BS연결,MATCH(H$1,BS연결H,0),0)/100,"") | I30: =IFERROR(VLOOKUP($D30,BS연결,MATCH(I$1,BS연결H,0),0)/100,"") | J30: =IFERROR(VLOOKUP($D30,BS연결,MATCH(J$1,BS연결H,0),0)/100,"") | K30: =IFERROR(VLOOKUP($D30,BS연결,MATCH(K$1,BS연결H,0),0)/100,"") | L30: =IFERROR(VLOOKUP($D30,BS연결,MATCH(L$1,BS연결H,0),0)/100,"") | M30: =IFERROR(VLOOKUP($D30,BS연결,MATCH(M$1,BS연결H,0),0)/100,"") | N30: =IFERROR(VLOOKUP($D30,BS연결,MATCH(N$1,BS연결H,0),0)/100,"") | ... AB30: =IFERROR(VLOOKUP($D30,BS연결,MATCH(AB$1,BS연결H,0),0)/100,"") | AC30: =IFERROR(X30*(1+변수!AC36),"") | AD30: =IFERROR(Y30*(1+변수!AD36),"") | AE30: =SUM(AA30:AD30) | AF30: =IFERROR(AA30*(1+변수!AF36),"") | AG30: =IFERROR(AB30*(1+변수!AG36),"") | AH30: =IFERROR(AC30*(1+변수!AH36),"") | AI30: =IFERROR(AD30*(1+변수!AI36),"") | AJ30: =SUM(AF30:AI30) | AK30: =IFERROR(AF30*(1+변수!AK36),"") | AL30: =IFERROR(AG30*(1+변수!AL36),"") | AM30: =IFERROR(AH30*(1+변수!AM36),"") | AN30: =IFERROR(AI30*(1+변수!AN36),"") | AO30: =SUM(AK30:AN30)
A31: 영업활동현금흐름 | B31: 현금흐름 | C31: 억원 | D31: 영업활동으로인한현금흐름 | E31: =IFERROR(VLOOKUP($D31,BS연결,MATCH(E$1,BS연결H,0),0)/100,"") | G31: =IFERROR(VLOOKUP($D31,BS연결,MATCH(G$1,BS연결H,0),0)/100,"") | H31: =IFERROR(VLOOKUP($D31,BS연결,MATCH(H$1,BS연결H,0),0)/100,"") | I31: =IFERROR(VLOOKUP($D31,BS연결,MATCH(I$1,BS연결H,0),0)/100,"") | J31: =IFERROR(VLOOKUP($D31,BS연결,MATCH(J$1,BS연결H,0),0)/100,"") | K31: =IFERROR(VLOOKUP($D31,BS연결,MATCH(K$1,BS연결H,0),0)/100,"") | L31: =IFERROR(VLOOKUP($D31,BS연결,MATCH(L$1,BS연결H,0),0)/100,"") | M31: =IFERROR(VLOOKUP($D31,BS연결,MATCH(M$1,BS연결H,0),0)/100,"") | N31: =IFERROR(VLOOKUP($D31,BS연결,MATCH(N$1,BS연결H,0),0)/100,"") | ... AB31: =IFERROR(VLOOKUP($D31,BS연결,MATCH(AB$1,BS연결H,0),0)/100,"") | AE31: =SUM(AA31:AD31) | AJ31: =SUM(AF31:AI31) | AO31: =SUM(AK31:AN31)
A32: 주식수 | B32: 주당 | C32: 백만주 | D32: 유통주식수 | E32: 854.036 | F32: =E32 | G32: 854.036 | H32: 854.036 | I32: 854.036 | J32: 854.036 | K32: =J32 | L32: 854.036 | M32: 854.036 | N32: 854.036 | O32: 854.036 | P32: =O32 | Q32: 854.036 | R32: 854.036 | S32: 854.036 | T32: 854.036 | U32: =T32 | V32: 854.036 | W32: 854.036 | X32: 854.036 | Y32: 854.036 | Z32: =Y32 | AA32: 854.036 | AB32: 854.036 | AC32: =IFERROR(AB32*(1+변수!AC38),"") | AD32: =IFERROR(AC32*(1+변수!AD38),"") | AE32: =AD32 | AF32: =IFERROR(AD32*(1+변수!AF38),"") | AG32: =IFERROR(AF32*(1+변수!AG38),"") | AH32: =IFERROR(AG32*(1+변수!AH38),"") | AI32: =IFERROR(AH32*(1+변수!AI38),"") | AJ32: =AI32 | AK32: =IFERROR(AI32*(1+변수!AK38),"") | AL32: =IFERROR(AK32*(1+변수!AL38),"") | AM32: =IFERROR(AL32*(1+변수!AM38),"") | AN32: =IFERROR(AM32*(1+변수!AN38),"") | AO32: =AN32
A33: EPS | B33: 주당 | C33: 원 | D33: EPS | E33: =IFERROR(E21*100/E32,"") | G33: =IFERROR(G21*100/G32,"") | H33: =IFERROR(H21*100/H32,"") | I33: =IFERROR(I21*100/I32,"") | J33: =IFERROR(J21*100/J32,"") | K33: =SUM(G33:J33) | L33: =IFERROR(L21*100/L32,"") | M33: =IFERROR(M21*100/M32,"") | N33: =IFERROR(N21*100/N32,"") | O33: =IFERROR(O21*100/O32,"") | P33: =SUM(L33:O33) | Q33: =IFERROR(Q21*100/Q32,"") | R33: =IFERROR(R21*100/R32,"") | S33: =IFERROR(S21*100/S32,"") | T33: =IFERROR(T21*100/T32,"") | U33: =SUM(Q33:T33) | V33: =IFERROR(V21*100/V32,"") | W33: =IFERROR(W21*100/W32,"") | X33: =IFERROR(X21*100/X32,"") | Y33: =IFERROR(Y21*100/Y32,"") | Z33: =SUM(V33:Y33) | AA33: =IFERROR(AA21*100/AA32,"") | AB33: =IFERROR(AB21*100/AB32,"") | AC33: =IFERROR(AC21*100/AC32,"") | AD33: =IFERROR(AD21*100/AD32,"") | AE33: =SUM(AA33:AD33) | AF33: =IFERROR(AF21*100/AF32,"") | AG33: =IFERROR(AG21*100/AG32,"") | AH33: =IFERROR(AH21*100/AH32,"") | AI33: =IFERROR(AI21*100/AI32,"") | AJ33: =SUM(AF33:AI33) | AK33: =IFERROR(AK21*100/AK32,"") | AL33: =IFERROR(AL21*100/AL32,"") | AM33: =IFERROR(AM21*100/AM32,"") | AN33: =IFERROR(AN21*100/AN32,"") | AO33: =SUM(AK33:AN33)
A34: BPS | B34: 주당 | C34: 원 | D34: BPS | E34: =IFERROR(E25*100/E32,"") | F34: =E34 | G34: =IFERROR(G25*100/G32,"") | H34: =IFERROR(H25*100/H32,"") | I34: =IFERROR(I25*100/I32,"") | J34: =IFERROR(J25*100/J32,"") | K34: =J34 | L34: =IFERROR(L25*100/L32,"") | M34: =IFERROR(M25*100/M32,"") | N34: =IFERROR(N25*100/N32,"") | O34: =IFERROR(O25*100/O32,"") | P34: =O34 | Q34: =IFERROR(Q25*100/Q32,"") | R34: =IFERROR(R25*100/R32,"") | S34: =IFERROR(S25*100/S32,"") | T34: =IFERROR(T25*100/T32,"") | U34: =T34 | V34: =IFERROR(V25*100/V32,"") | W34: =IFERROR(W25*100/W32,"") | X34: =IFERROR(X25*100/X32,"") | Y34: =IFERROR(Y25*100/Y32,"") | Z34: =Y34 | AA34: =IFERROR(AA25*100/AA32,"") | AB34: =IFERROR(AB25*100/AB32,"") | AC34: =IFERROR(AC25*100/AC32,"") | AD34: =IFERROR(AD25*100/AD32,"") | AE34: =AD34 | AF34: =IFERROR(AF25*100/AF32,"") | AG34: =IFERROR(AG25*100/AG32,"") | AH34: =IFERROR(AH25*100/AH32,"") | AI34: =IFERROR(AI25*100/AI32,"") | AJ34: =AI34 | AK34: =IFERROR(AK25*100/AK32,"") | AL34: =IFERROR(AL25*100/AL32,"") | AM34: =IFERROR(AM25*100/AM32,"") | AN34: =IFERROR(AN25*100/AN32,"") | AO34: =AN34
A35: DPS | B35: 주당 | C35: 원 | D35: DPS(보통주) | E35: 0 | F35: 0 | J35: 0 | K35: =SUM(G35:J35) | O35: 0 | P35: =SUM(L35:O35) | T35: 0 | U35: =SUM(Q35:T35) | Y35: 0 | Z35: =SUM(V35:Y35) | AD35: =변수!AD39 | AE35: =SUM(AA35:AD35) | AI35: =변수!AI39 | AJ35: =SUM(AF35:AI35) | AN35: =변수!AN39 | AO35: =SUM(AK35:AN35)
A36: PER | B36: 주당 | C36: 배 | D36: PER | F36: =E36 | K36: =J36 | P36: =O36 | T36: =IFERROR(변수!T18/(Q33+R33+S33+T33),"") | U36: =T36 | V36: =IFERROR(변수!V18/(R33+S33+T33+V33),"") | W36: =IFERROR(변수!W18/(S33+T33+V33+W33),"") | X36: =IFERROR(변수!X18/(T33+V33+W33+X33),"") | Y36: =IFERROR(변수!Y18/(V33+W33+X33+Y33),"") | Z36: =Y36 | AA36: =IFERROR(변수!AA18/(W33+X33+Y33+AA33),"") | AB36: =IFERROR(변수!AB18/(X33+Y33+AA33+AB33),"") | AC36: =IFERROR(변수!$D$47/(Y33+AA33+AB33+AC33),"") | AD36: =IFERROR(변수!$D$47/(AA33+AB33+AC33+AD33),"") | AE36: =AD36 | AF36: =IFERROR(변수!$D$47/(AB33+AC33+AD33+AF33),"") | AG36: =IFERROR(변수!$D$47/(AC33+AD33+AF33+AG33),"") | AH36: =IFERROR(변수!$D$47/(AD33+AF33+AG33+AH33),"") | AI36: =IFERROR(변수!$D$47/(AF33+AG33+AH33+AI33),"") | AJ36: =AI36 | AK36: =IFERROR(변수!$D$47/(AG33+AH33+AI33+AK33),"") | AL36: =IFERROR(변수!$D$47/(AH33+AI33+AK33+AL33),"") | AM36: =IFERROR(변수!$D$47/(AI33+AK33+AL33+AM33),"") | AN36: =IFERROR(변수!$D$47/(AK33+AL33+AM33+AN33),"") | AO36: =AN36
A37: PBR | B37: 주당 | C37: 배 | D37: PBR | E37: =IFERROR(변수!E18/E34,"") | F37: =E37 | G37: =IFERROR(변수!G18/G34,"") | H37: =IFERROR(변수!H18/H34,"") | I37: =IFERROR(변수!I18/I34,"") | J37: =IFERROR(변수!J18/J34,"") | K37: =J37 | L37: =IFERROR(변수!L18/L34,"") | M37: =IFERROR(변수!M18/M34,"") | N37: =IFERROR(변수!N18/N34,"") | O37: =IFERROR(변수!O18/O34,"") | P37: =O37 | Q37: =IFERROR(변수!Q18/Q34,"") | R37: =IFERROR(변수!R18/R34,"") | S37: =IFERROR(변수!S18/S34,"") | T37: =IFERROR(변수!T18/T34,"") | U37: =T37 | V37: =IFERROR(변수!V18/V34,"") | W37: =IFERROR(변수!W18/W34,"") | X37: =IFERROR(변수!X18/X34,"") | Y37: =IFERROR(변수!Y18/Y34,"") | Z37: =Y37 | AA37: =IFERROR(변수!AA18/AA34,"") | AB37: =IFERROR(변수!AB18/AB34,"") | AC37: =IFERROR(변수!$D$47/AC34,"") | AD37: =IFERROR(변수!$D$47/AD34,"") | AE37: =AD37 | AF37: =IFERROR(변수!$D$47/AF34,"") | AG37: =IFERROR(변수!$D$47/AG34,"") | AH37: =IFERROR(변수!$D$47/AH34,"") | AI37: =IFERROR(변수!$D$47/AI34,"") | AJ37: =AI37 | AK37: =IFERROR(변수!$D$47/AK34,"") | AL37: =IFERROR(변수!$D$47/AL34,"") | AM37: =IFERROR(변수!$D$47/AM34,"") | AN37: =IFERROR(변수!$D$47/AN34,"") | AO37: =AN37
A38: 매출조선 | B38: 사업부 | C38: 억원 | D38: 매출 조선·해양(조선해양) | G38: 14972 | H38: 14022 | I38: 12974 | J38: 14356 | K38: =SUM(G38:J38) | L38: 14522 | M38: 18157 | N38: 19278 | O38: 22382 | P38: =SUM(L38:O38) | Q38: 22122 | R38: 22532 | S38: 22638 | T38: 25808 | U38: =SUM(Q38:T38) | V38: 23988 | W38: 31509 | X38: 21080 | Y38: 27786 | Z38: =SUM(V38:Y38) | AA38: 28097 | AB38: 30935 | AC38: =IFERROR(SLS!W141/100+변수!AC40+AC39,"") | AD38: =IFERROR(SLS!X141/100+변수!AD40+AD39,"") | AE38: =SUM(AA38:AD38) | AF38: =IFERROR(SLS!Y141/100+변수!AF40+AF39,"") | AG38: =IFERROR(SLS!Z141/100+변수!AG40+AG39,"") | AH38: =IFERROR(SLS!AA141/100+변수!AH40+AH39,"") | AI38: =IFERROR(SLS!AB141/100+변수!AI40+AI39,"") | AJ38: =SUM(AF38:AI38) | AK38: =IFERROR(SLS!AC141/100+변수!AK40+AK39,"") | AL38: =IFERROR(SLS!AD141/100+변수!AL40+AL39,"") | AM38: =IFERROR(SLS!AE141/100+변수!AM40+AM39,"") | AN38: =IFERROR(SLS!AF141/100+변수!AN40+AN39,"") | AO38: =SUM(AK38:AN38)
A39: 매출조선신규 | B39: 사업부 | C39: 억원 | D39: 매출 조선·해양(조선해양) 신규수주(forecast_panel base(공시 상계) — 매출조선에 포함) | K39: =SUM(G39:J39) | P39: =SUM(L39:O39) | U39: =SUM(Q39:T39) | Z39: =SUM(V39:Y39) | AA39: 0 | AB39: 0 | AC39: =변수!AC41 | AD39: =변수!AD41 | AE39: =SUM(AA39:AD39) | AF39: =변수!AF41 | AG39: =변수!AG41 | AH39: =변수!AH41 | AI39: =변수!AI41 | AJ39: =SUM(AF39:AI39) | AK39: =변수!AK41 | AL39: =변수!AL41 | AM39: =변수!AM41 | AN39: =변수!AN41 | AO39: =SUM(AK39:AN39)
A40: OP조선 | B40: 사업부 | C40: 억원 | D40: OP 조선·해양(조선해양) | K40: =SUM(G40:J40) | P40: =SUM(L40:O40) | U40: =SUM(Q40:T40) | Z40: =SUM(V40:Y40) | AC40: =IFERROR(AC38*변수!AC42,"") | AD40: =IFERROR(AD38*변수!AD42,"") | AE40: =SUM(AA40:AD40) | AF40: =IFERROR(AF38*변수!AF42,"") | AG40: =IFERROR(AG38*변수!AG42,"") | AH40: =IFERROR(AH38*변수!AH42,"") | AI40: =IFERROR(AI38*변수!AI42,"") | AJ40: =SUM(AF40:AI40) | AK40: =IFERROR(AK38*변수!AK42,"") | AL40: =IFERROR(AL38*변수!AL42,"") | AM40: =IFERROR(AM38*변수!AM42,"") | AN40: =IFERROR(AN38*변수!AN42,"") | AO40: =SUM(AK40:AN40)
A41: OP조선신규 | B41: 사업부 | C41: 억원 | D41: OP 조선·해양(조선해양) 신규수주(매출조선신규 × OPM — OP조선에 포함) | K41: =SUM(G41:J41) | P41: =SUM(L41:O41) | U41: =SUM(Q41:T41) | Z41: =SUM(V41:Y41) | AA41: 0 | AB41: 0 | AC41: =IFERROR(AC39*변수!AC42,"") | AD41: =IFERROR(AD39*변수!AD42,"") | AE41: =SUM(AA41:AD41) | AF41: =IFERROR(AF39*변수!AF42,"") | AG41: =IFERROR(AG39*변수!AG42,"") | AH41: =IFERROR(AH39*변수!AH42,"") | AI41: =IFERROR(AI39*변수!AI42,"") | AJ41: =SUM(AF41:AI41) | AK41: =IFERROR(AK39*변수!AK42,"") | AL41: =IFERROR(AL39*변수!AL42,"") | AM41: =IFERROR(AM39*변수!AM42,"") | AN41: =IFERROR(AN39*변수!AN42,"") | AO41: =SUM(AK41:AN41)
A42: 매출기타 | B42: 사업부 | C42: 억원 | D42: 매출 기타 부문(총매출 − 조선) | G42: 0 | H42: 239.46 | I42: 1027.29 | J42: 1989.46 | K42: =SUM(G42:J42) | L42: 1528.52 | M42: 1300.87 | N42: 976.3 | O42: 1949.61 | P42: =SUM(L42:O42) | Q42: 1355.96 | R42: 2787.55 | S42: 591.56 | T42: 1195.71 | U42: =SUM(Q42:T42) | V42: 954.86 | W42: 0 | X42: 5268.19 | Y42: 593.29 | Z42: =SUM(V42:Y42) | AA42: 925.51 | AB42: 1372.12 | AC42: =IFERROR(X42*(1+변수!AC43),"") | AD42: =IFERROR(Y42*(1+변수!AD43),"") | AE42: =SUM(AA42:AD42) | AF42: =IFERROR(AA42*(1+변수!AF43),"") | AG42: =IFERROR(AB42*(1+변수!AG43),"") | AH42: =IFERROR(AC42*(1+변수!AH43),"") | AI42: =IFERROR(AD42*(1+변수!AI43),"") | AJ42: =SUM(AF42:AI42) | AK42: =IFERROR(AF42*(1+변수!AK43),"") | AL42: =IFERROR(AG42*(1+변수!AL43),"") | AM42: =IFERROR(AH42*(1+변수!AM43),"") | AN42: =IFERROR(AI42*(1+변수!AN43),"") | AO42: =SUM(AK42:AN42)
A43: OP기타 | B43: 사업부 | C43: 억원 | D43: OP 기타 부문(총매출 − 조선) | K43: =SUM(G43:J43) | P43: =SUM(L43:O43) | U43: =SUM(Q43:T43) | Z43: =SUM(V43:Y43) | AC43: =IFERROR(AC42*변수!AC44,"") | AD43: =IFERROR(AD42*변수!AD44,"") | AE43: =SUM(AA43:AD43) | AF43: =IFERROR(AF42*변수!AF44,"") | AG43: =IFERROR(AG42*변수!AG44,"") | AH43: =IFERROR(AH42*변수!AH44,"") | AI43: =IFERROR(AI42*변수!AI44,"") | AJ43: =SUM(AF43:AI43) | AK43: =IFERROR(AK42*변수!AK44,"") | AL43: =IFERROR(AL42*변수!AL44,"") | AM43: =IFERROR(AM42*변수!AM44,"") | AN43: =IFERROR(AN42*변수!AN44,"") | AO43: =SUM(AK43:AN43)
B44: 비율(참고)
A45: NPM | C45: % | D45: 지배주주순이익 / 매출액 | E45: =IFERROR(E21/E5,"") | F45: =IFERROR(F21/F5,"") | G45: =IFERROR(G21/G5,"") | H45: =IFERROR(H21/H5,"") | I45: =IFERROR(I21/I5,"") | J45: =IFERROR(J21/J5,"") | K45: =IFERROR(K21/K5,"") | L45: =IFERROR(L21/L5,"") | ... AO45: =IFERROR(AO21/AO5,"")
A46: 매출원가율 | C46: % | D46: 매출원가 / 매출액 | E46: =IFERROR(E6/E5,"") | F46: =IFERROR(F6/F5,"") | G46: =IFERROR(G6/G5,"") | H46: =IFERROR(H6/H5,"") | I46: =IFERROR(I6/I5,"") | J46: =IFERROR(J6/J5,"") | K46: =IFERROR(K6/K5,"") | L46: =IFERROR(L6/L5,"") | ... AO46: =IFERROR(AO6/AO5,"")
A47: 판관비율 | C47: % | D47: 판관비 / 매출액 | E47: =IFERROR(E8/E5,"") | F47: =IFERROR(F8/F5,"") | G47: =IFERROR(G8/G5,"") | H47: =IFERROR(H8/H5,"") | I47: =IFERROR(I8/I5,"") | J47: =IFERROR(J8/J5,"") | K47: =IFERROR(K8/K5,"") | L47: =IFERROR(L8/L5,"") | ... AO47: =IFERROR(AO8/AO5,"")

Sheet SLS
C1: 이름: SLS_H · 선표 매출인식(백만$) — sls json origin 2026Q2 | E1: 1Q22 | F1: 2Q22 | G1: 3Q22 | H1: 4Q22 | I1: 1Q23 | J1: 2Q23 | K1: 3Q23 | L1: 4Q23 | M1: 1Q24 | N1: 2Q24 | O1: 3Q24 | P1: 4Q24 | Q1: 1Q25 | R1: 2Q25 | S1: 3Q25 | T1: 4Q25 | U1: 1Q26 | V1: 2Q26 | W1: 3Q26 | X1: 4Q26 | Y1: 1Q27 | Z1: 2Q27 | AA1: 3Q27 | AB1: 4Q27 | AC1: 1Q28 | AD1: 2Q28 | AE1: 3Q28 | AF1: 4Q28 | AG1: 1Q29 | AH1: 2Q29 | AI1: 3Q29 | AJ1: 4Q29 | AK1: 1Q30 | AL1: 2Q30 | AM1: 3Q30 | AN1: 2022 | AO1: 2023 | AP1: 2024 | AQ1: 2025 | AR1: 2026 | AS1: 2027 | AT1: 2028 | AU1: 2029 | AV1: 2030
A2: 코호트 표(레퍼런스 실측 캘리브레이션): ①적자 −1.1% ②BEP 1% ③중마진 4.3% ④호황 5.4% ⑤초호황 10.8% — 회사별 캘리브레이션은 target_opm.basis 참조 · 코호트 모드 reference_anchor(대안 ledger_relative) · 잔고 캡 미적용
E3: 1 | F3: 2 | G3: 3 | H3: 4 | I3: 5 | J3: 6 | K3: 7 | L3: 8 | M3: 9 | N3: 10 | O3: 11 | P3: 12 | Q3: 13 | R3: 14 | S3: 15 | T3: 16 | U3: 17 | V3: 18 | W3: 19 | X3: 20 | Y3: 21 | Z3: 22 | AA3: 23 | AB3: 24 | AC3: 25 | AD3: 26 | AE3: 27 | AF3: 28 | AG3: 29 | AH3: 30 | AI3: 31 | AJ3: 32 | AK3: 33 | AL3: 34 | AM3: 35 | AN3: 36 | AO3: 37 | AP3: 38 | AQ3: 39 | AR3: 40 | AS3: 41 | AT3: 42 | AU3: 43 | AV3: 44
E4: 2022.03 | F4: 2022.06 | G4: 2022.09 | H4: 2022.12 | I4: 2023.03 | J4: 2023.06 | K4: 2023.09 | L4: 2023.12 | M4: 2024.03 | N4: 2024.06 | O4: 2024.09 | P4: 2024.12 | Q4: 2025.03 | R4: 2025.06 | S4: 2025.09 | T4: 2025.12 | U4: 2026.03 | V4: 2026.06 | W4: 2026.09 | X4: 2026.12 | Y4: 2027.03 | Z4: 2027.06 | AA4: 2027.09 | AB4: 2027.12 | AC4: 2028.03 | AD4: 2028.06 | AE4: 2028.09 | AF4: 2028.12 | AG4: 2029.03 | AH4: 2029.06 | AI4: 2029.09 | AJ4: 2029.12 | AK4: 2030.03 | AL4: 2030.06 | AM4: 2030.09 | AN4: 2022.12A | AO4: 2023.12A | AP4: 2024.12A | AQ4: 2025.12A | AR4: 2026.12A | AS4: 2027.12A | AT4: 2028.12A | AU4: 2029.12A | AV4: 2030.12A
A5: usd_m | D5: 매출인식 합계(백만$) | E5: 3.771 | F5: 74.08 | G5: 82.492 | H5: 101.949 | I5: 141.599 | J5: 157.447 | K5: 218.403 | L5: 222.557 | M5: 220.138 | N5: 230.966 | O5: 353.028 | P5: 467.093 | Q5: 590.955 | R5: 672.269 | S5: 1075.051 | T5: 1199.784 | U5: 1314.155 | V5: 1567.71 | W5: 1663.4 | X5: 1817.47 | Y5: 1778.463 | Z5: 1724.872 | AA5: 1656.256 | AB5: 1656.256 | AC5: 1406.999 | AD5: 1305.612 | AE5: 1260.857 | AF5: 1081.789 | AG5: 757.11 | AH5: 589.757 | AI5: 431.834 | AJ5: 257.369 | AK5: 182.091 | AL5: 173.766 | AM5: 36.281 | AN5: 262.292 | AO5: 740.006 | AP5: 1271.225 | AQ5: 3538.059 | AR5: 6362.735 | AS5: 6815.847 | AT5: 5055.257 | AU5: 2036.07 | AV5: 392.138
A6: marine_usd_m | D6: 해양(type≠OTHER) 합계(백만$) | E6: 3.771 | F6: 49.028 | G6: 49.567 | H6: 49.567 | I6: 48.489 | J6: 63.303 | K6: 100.077 | L6: 100.077 | M6: 98.989 | N6: 99.678 | O6: 163.917 | P6: 277.982 | Q6: 405.955 | R6: 555.451 | S6: 906.541 | T6: 1023.47 | U6: 1226.957 | V6: 1479.544 | W6: 1574.265 | X6: 1728.334 | Y6: 1691.265 | Z6: 1677.704 | AA6: 1628.955 | AB6: 1628.955 | AC6: 1406.999 | AD6: 1305.612 | AE6: 1260.857 | AF6: 1081.789 | AG6: 757.11 | AH6: 589.757 | AI6: 431.834 | AJ6: 257.369 | AK6: 182.091 | AL6: 173.766 | AM6: 36.281 | AN6: 151.933 | AO6: 311.946 | AP6: 640.566 | AQ6: 2891.417 | AR6: 6009.1 | AS6: 6626.879 | AT6: 5055.257 | AU6: 2036.07 | AV6: 392.138
A7: type:CONT | D7: 선종 CONT | E7: 3.771 | F7: 49.028 | G7: 49.567 | H7: 49.567 | I7: 48.489 | J7: 49.028 | K7: 49.567 | L7: 49.567 | M7: 49.028 | N7: 49.028 | O7: 49.567 | P7: 77.293 | Q7: 110.872 | R7: 138.705 | S7: 123.462 | T7: 139.011 | U7: 198.83 | V7: 216.959 | W7: 231.831 | X7: 253.134 | Y7: 247.631 | Z7: 250.383 | AA7: 253.134 | AB7: 253.134 | AC7: 163.485 | AD7: 127.561 | AE7: 116.626 | AF7: 115.157 | AG7: 81.034 | AH7: 81.934 | AI7: 82.835 | AJ7: 54.923 | AN7: 151.933 | AO7: 196.651 | AP7: 224.916 | AQ7: 512.05 | AR7: 900.754 | AS7: 1004.282 | AT7: 522.829 | AU7: 300.726
A8: type:OTHER | D8: 선종 OTHER | F8: 25.052 | G8: 32.925 | H8: 52.382 | I8: 93.11 | J8: 94.144 | K8: 118.325 | L8: 122.48 | M8: 121.149 | N8: 131.288 | O8: 189.112 | P8: 189.112 | Q8: 185.001 | R8: 116.817 | S8: 168.51 | T8: 176.314 | U8: 87.198 | V8: 88.167 | W8: 89.136 | X8: 89.136 | Y8: 87.198 | Z8: 47.168 | AA8: 27.301 | AB8: 27.301 | AN8: 110.359 | AO8: 428.059 | AP8: 630.661 | AQ8: 646.642 | AR8: 353.637 | AS8: 188.968
A9: type:OFFSH | D9: 선종 OFFSH | J9: 14.275 | K9: 50.511 | L9: 50.511 | M9: 49.962 | N9: 49.962 | O9: 50.511 | P9: 50.511 | Q9: 49.412 | R9: 49.962 | S9: 343.784 | T9: 353.67 | U9: 345.982 | V9: 334.617 | W9: 226.186 | X9: 226.186 | Y9: 221.269 | Z9: 223.727 | AA9: 226.186 | AB9: 226.186 | AC9: 223.727 | AD9: 223.727 | AE9: 226.186 | AF9: 226.186 | AG9: 221.269 | AH9: 223.727 | AI9: 226.186 | AJ9: 175.675 | AK9: 171.856 | AL9: 173.766 | AM9: 36.281 | AO9: 115.297 | AP9: 200.946 | AQ9: 796.828 | AR9: 1132.971 | AS9: 897.368 | AT9: 899.826 | AU9: 846.857 | AV9: 381.903
A10: type:LNGC | D10: 선종 LNGC | N10: 0.688 | O10: 63.839 | P10: 128.696 | Q10: 154.982 | R10: 161.429 | S10: 230.163 | T10: 299.063 | U10: 422.404 | V10: 606.339 | W10: 722.163 | X10: 833.139 | Y10: 815.531 | Z10: 792.239 | AA10: 733.76 | AB10: 733.76 | AC10: 691.863 | AD10: 665.298 | AE10: 625.842 | AF10: 448.244 | AG10: 315.92 | AH10: 199.998 | AI10: 80.166 | AP10: 193.223 | AQ10: 845.637 | AR10: 2584.045 | AS10: 3075.29 | AT10: 2431.247 | AU10: 596.084
A11: type:VLCC | D11: 선종 VLCC | P11: 17.627 | Q11: 42.858 | R11: 134.46 | S11: 137.456 | T11: 160.05 | U11: 172.086 | V11: 201.372 | W11: 262.303 | X11: 268.481 | Y11: 262.645 | Z11: 265.563 | AA11: 268.481 | AB11: 268.481 | AC11: 235.197 | AD11: 214.131 | AE11: 216.484 | AF11: 216.484 | AG11: 85.131 | AH11: 39.895 | AI11: 10.383 | AP11: 17.627 | AQ11: 474.824 | AR11: 904.242 | AS11: 1065.17 | AT11: 882.296 | AU11: 135.409
A12: type:VLGC | D12: 선종 VLGC | P12: 3.855 | Q12: 47.83 | R12: 70.896 | S12: 71.676 | T12: 71.676 | U12: 87.655 | V12: 120.258 | W12: 131.781 | X12: 147.393 | Y12: 144.189 | Z12: 145.791 | AA12: 147.393 | AB12: 147.393 | AC12: 92.725 | AD12: 74.895 | AE12: 75.718 | AF12: 75.718 | AG12: 53.756 | AH12: 44.202 | AI12: 32.264 | AJ12: 26.77 | AK12: 10.235 | AP12: 3.855 | AQ12: 262.078 | AR12: 487.087 | AS12: 584.766 | AT12: 319.056 | AU12: 156.992 | AV12: 10.235
A13: cohort:⑤초호황 | D13: 코호트 ⑤초호황 | E13: 3.771 | F13: 49.028 | G13: 49.567 | H13: 49.567 | I13: 48.489 | J13: 63.303 | K13: 100.077 | L13: 100.077 | M13: 98.989 | N13: 99.678 | O13: 163.917 | P13: 277.982 | Q13: 405.955 | R13: 555.451 | S13: 613.267 | T13: 720.311 | U13: 930.388 | V13: 1252.174 | W13: 1574.265 | X13: 1728.334 | Y13: 1691.265 | Z13: 1677.704 | AA13: 1628.955 | AB13: 1628.955 | AC13: 1406.999 | AD13: 1305.612 | AE13: 1260.857 | AF13: 1081.789 | AG13: 757.11 | AH13: 589.757 | AI13: 431.834 | AJ13: 257.369 | AK13: 182.091 | AL13: 173.766 | AM13: 36.281 | AN13: 151.933 | AO13: 311.946 | AP13: 640.566 | AQ13: 2294.984 | AR13: 5485.161 | AS13: 6626.879 | AT13: 5055.257 | AU13: 2036.07 | AV13: 392.138
A14: cohort:등급없음 | D14: 코호트 등급없음 | F14: 25.052 | G14: 32.925 | H14: 52.382 | I14: 93.11 | J14: 94.144 | K14: 118.325 | L14: 122.48 | M14: 121.149 | N14: 131.288 | O14: 189.112 | P14: 189.112 | Q14: 185.001 | R14: 116.817 | S14: 461.783 | T14: 479.474 | U14: 383.767 | V14: 315.536 | W14: 89.136 | X14: 89.136 | Y14: 87.198 | Z14: 47.168 | AA14: 27.301 | AB14: 27.301 | AN14: 110.359 | AO14: 428.059 | AP14: 630.661 | AQ14: 1243.075 | AR14: 877.575 | AS14: 188.968
A15: hedge_ratio | D15: 헤지비율 | E15: 0.7 | F15: 0.7 | G15: 0.7 | H15: 0.7 | I15: 0.7 | J15: 0.7 | K15: 0.7 | L15: 0.7 | M15: 0.7 | N15: 0.7 | O15: 0.7 | P15: 0.7 | Q15: 0.7 | R15: 0.7 | S15: 0.7 | T15: 0.7 | U15: 0.7 | V15: 0.7 | W15: 0.7 | X15: 0.7 | Y15: 0.7 | Z15: 0.7 | AA15: 0.7 | AB15: 0.7 | AC15: 0.7 | AD15: 0.7 | AE15: 0.7 | AF15: 0.7 | AG15: 0.7 | AH15: 0.7 | AI15: 0.7 | AJ15: 0.7 | AK15: 0.7 | AL15: 0.7 | AM15: 0.7
A16: hedge_rate | D16: 헤지환율(가중) | E16: 1205.78 | F16: 1257.97 | G16: 1267.38 | H16: 1285.08 | I16: 1307.27 | J16: 1324.9 | K16: 1353.81 | L16: 1353.21 | M16: 1353.21 | N16: 1354.06 | O16: 1359.87 | P16: 1364.62 | Q16: 1375.91 | R16: 1390.2 | S16: 1393.58 | T16: 1399.86 | U16: 1411.59 | V16: 1427.29 | W16: 1442.98 | X16: 1438.95 | Y16: 1438.93 | Z16: 1441.71 | AA16: 1443.71 | AB16: 1443.71 | AC16: 1452.41 | AD16: 1452.66 | AE16: 1453.69 | AF16: 1457.41 | AG16: 1463 | AH16: 1465.55 | AI16: 1471.2 | AJ16: 1485.39 | AK16: 1497.08 | AL16: 1501.75 | AM16: 1501.75
A17: spot_assumed | D17: 건조시점 환율(sls 가정) | E17: 1205.78 | F17: 1262.09 | G17: 1341.93 | H17: 1360.12 | I17: 1276.95 | J17: 1315.69 | K17: 1313.62 | L17: 1322.01 | M17: 1330.14 | N17: 1371.28 | O17: 1356.22 | P17: 1396.3 | Q17: 1452.28 | R17: 1398.52 | S17: 1386.95 | T17: 1449.19 | U17: 1466.12 | V17: 1501.75 | W17: 1418.75 | X17: 1342.11 | Y17: 1332.1 | Z17: 1332.1 | AA17: 1332.1 | AB17: 1332.1 | AC17: 1332.1 | AD17: 1332.1 | AE17: 1332.1 | AF17: 1332.1 | AG17: 1332.1 | AH17: 1332.1 | AI17: 1332.1 | AJ17: 1332.1 | AK17: 1332.1 | AL17: 1332.1 | AM17: 1332.1
A18: applied_rate | D18: 적용환율 | E18: 1205.78 | F18: 1259.21 | G18: 1289.75 | H18: 1307.59 | I18: 1298.17 | J18: 1322.14 | K18: 1341.75 | L18: 1343.85 | M18: 1346.29 | N18: 1359.23 | O18: 1358.77 | P18: 1374.13 | Q18: 1398.82 | R18: 1392.7 | S18: 1391.59 | T18: 1414.66 | U18: 1427.95 | V18: 1449.63 | W18: 1435.71 | X18: 1409.9 | Y18: 1406.88 | Z18: 1408.83 | AA18: 1410.23 | AB18: 1410.23 | AC18: 1416.32 | AD18: 1416.49 | AE18: 1417.21 | AF18: 1419.82 | AG18: 1423.73 | AH18: 1425.52 | AI18: 1429.47 | AJ18: 1439.4 | AK18: 1447.59 | AL18: 1450.86 | AM18: 1450.86
A19: hedged_krw_m | D19: 헤지적용 원화매출(백만원) | E19: 4547.5 | F19: 93281.8 | G19: 106393.6 | H19: 133307.3 | I19: 183819.8 | J19: 208166.5 | K19: 293042.3 | L19: 299084.3 | M19: 296370.3 | N19: 313935.2 | O19: 479685.9 | P19: 641845.5 | Q19: 826642.1 | R19: 936268 | S19: 1496028.1 | T19: 1697287.6 | U19: 1876550.8 | V19: 2272592.2 | W19: 2388165.2 | X19: 2562450.9 | Y19: 2502080.6 | Z19: 2430049.5 | AA19: 2335697.1 | AB19: 2335697.1 | AC19: 1992758.4 | AD19: 1849390.4 | AE19: 1786898.2 | AF19: 1535944.9 | AG19: 1077920.6 | AH19: 840707.4 | AI19: 617293.3 | AJ19: 370457.1 | AK19: 263593.6 | AL19: 252109.2 | AM19: 52638.2 | AN19: 337530.2 | AO19: 984112.9 | AP19: 1731836.9 | AQ19: 4956225.8 | AR19: 9099759.1 | AS19: 9603524.3 | AT19: 7164991.9 | AU19: 2906378.4 | AV19: 568341
A20: marine_hedged_krw_m | D20: 해양 원화(백만원) | E20: 4547.5 | F20: 59945.2 | G20: 61791.1 | H20: 62061.6 | I20: 59502.6 | J20: 81373.8 | K20: 134373.6 | L20: 134625.5 | M20: 133403.6 | N20: 135569 | O20: 222900.3 | P20: 382786.1 | Q20: 570107.5 | R20: 776242.2 | S20: 1264739.6 | T20: 1451842.6 | U20: 1754754.8 | V20: 2148500.4 | W20: 2264929.3 | X20: 2441264.4 | Y20: 2383790.4 | Z20: 2366633.8 | AA20: 2299522 | AB20: 2299522 | AC20: 1992758.4 | AD20: 1849390.4 | AE20: 1786898.2 | AF20: 1535944.9 | AG20: 1077920.6 | AH20: 840707.4 | AI20: 617293.3 | AJ20: 370457.1 | AK20: 263593.6 | AL20: 252109.2 | AM20: 52638.2 | AN20: 188345.4 | AO20: 409875.5 | AP20: 874659 | AQ20: 4062931.9 | AR20: 8609448.9 | AS20: 9349468.2 | AT20: 7164991.9 | AU20: 2906378.4 | AV20: 568341
A21: marine_hedged_krw_m_signed_by_origin | D21: 해양 원화 — origin 분기말까지 체결분(백만원) | E21: 4547.5 | F21: 59945.2 | G21: 61791.1 | H21: 62061.6 | I21: 59502.6 | J21: 81373.8 | K21: 134373.6 | L21: 134625.5 | M21: 133403.6 | N21: 135569 | O21: 222900.3 | P21: 382786.1 | Q21: 570107.5 | R21: 776242.2 | S21: 1264739.6 | T21: 1451842.6 | U21: 1754754.8 | V21: 2148500.4 | W21: 2160295.9 | X21: 2125796.1 | Y21: 2075175 | Z21: 2054589.3 | AA21: 1984048.5 | AB21: 1984048.5 | AC21: 1680713.9 | AD21: 1537346 | AE21: 1471424.7 | AF21: 1222517.6 | AG21: 815345.1 | AH21: 608216.7 | AI21: 468952.5 | AJ21: 348229.1 | AK21: 249338.8 | AL21: 252109.2 | AM21: 52638.2
A22: marine_hedged_krw_m_post_origin | D22: 해양 원화 — origin 이후 체결분(백만원) | E22: 0 | F22: 0 | G22: 0 | H22: 0 | I22: 0 | J22: 0 | K22: 0 | L22: 0 | M22: 0 | N22: 0 | O22: 0 | P22: 0 | Q22: 0 | R22: 0 | S22: 0 | T22: 0 | U22: 0 | V22: 0 | W22: 104633.4 | X22: 315468.4 | Y22: 308615.4 | Z22: 312044.5 | AA22: 315473.5 | AB22: 315473.5 | AC22: 312044.5 | AD22: 312044.5 | AE22: 315473.5 | AF22: 313427.3 | AG22: 262575.5 | AH22: 232490.7 | AI22: 148340.7 | AJ22: 22227.9 | AK22: 14254.9 | AL22: 0 | AM22: 0
A23: target_opm | D23: 타겟 OPM(코호트) | E23: 0.108 | F23: 0.108 | G23: 0.108 | H23: 0.108 | I23: 0.108 | J23: 0.108 | K23: 0.108 | L23: 0.108 | M23: 0.108 | N23: 0.108 | O23: 0.108 | P23: 0.108 | Q23: 0.108 | R23: 0.108 | S23: 0.108 | T23: 0.108 | U23: 0.108 | V23: 0.108 | W23: 0.108 | X23: 0.108 | Y23: 0.108 | Z23: 0.108 | AA23: 0.108 | AB23: 0.108 | AC23: 0.108 | AD23: 0.108 | AE23: 0.108 | AF23: 0.108 | AG23: 0.108 | AH23: 0.108 | AI23: 0.108 | AJ23: 0.108 | AK23: 0.108 | AL23: 0.108 | AM23: 0.108
A25: 선표 연결(수식) — 원화(백만원) = 스케줄(백만$) × 포함 × (1 + (캡배율 − 1) × origin 이후) × (헤지비율 × 헤지환율 + (1 − 헤지비율) × 건조시점 환율) | J25: subQ 매출조선 = 합계/100 + 변수 잔고 소진 + 매출조선신규
A26: 헤지비율 | D26: =변수!$D$61 | E26: 변수 3절 '헤지비율' 참조 — 약정환율 미공시 → HEDGE 70% 가정(레퍼런스 SLS 시트 HEDGE 행은 미포 65%·삼성重 100% — 그 사이에 둔 설정값). hedge_rate 는 계약별 수주시점 환율로 대체
A27: 헤지환율 방식 | D27: 계약별 수주시점 환율(fx_at_sign)
A28: spot_krw | D28: 건조시점 원/달러(평균) — 변수 환율 행 참조, 변수 범위 밖 분기는 sls spot_assumed | E28: =IFERROR(VLOOKUP(" 원/달러(평균)",환율,MATCH(E$1,변수H,0),0),1205.78) | F28: =IFERROR(VLOOKUP(" 원/달러(평균)",환율,MATCH(F$1,변수H,0),0),1262.09) | G28: =IFERROR(VLOOKUP(" 원/달러(평균)",환율,MATCH(G$1,변수H,0),0),1341.93) | H28: =IFERROR(VLOOKUP(" 원/달러(평균)",환율,MATCH(H$1,변수H,0),0),1360.12) | I28: =IFERROR(VLOOKUP(" 원/달러(평균)",환율,MATCH(I$1,변수H,0),0),1276.95) | J28: =IFERROR(VLOOKUP(" 원/달러(평균)",환율,MATCH(J$1,변수H,0),0),1315.69) | K28: =IFERROR(VLOOKUP(" 원/달러(평균)",환율,MATCH(K$1,변수H,0),0),1313.62) | L28: =IFERROR(VLOOKUP(" 원/달러(평균)",환율,MATCH(L$1,변수H,0),0),1322.01) | M28: =IFERROR(VLOOKUP(" 원/달러(평균)",환율,MATCH(M$1,변수H,0),0),1330.14) | N28: =IFERROR(VLOOKUP(" 원/달러(평균)",환율,MATCH(N$1,변수H,0),0),1371.28) | O28: =IFERROR(VLOOKUP(" 원/달러(평균)",환율,MATCH(O$1,변수H,0),0),1356.22) | P28: =IFERROR(VLOOKUP(" 원/달러(평균)",환율,MATCH(P$1,변수H,0),0),1396.3) | Q28: =IFERROR(VLOOKUP(" 원/달러(평균)",환율,MATCH(Q$1,변수H,0),0),1452.28) | R28: =IFERROR(VLOOKUP(" 원/달러(평균)",환율,MATCH(R$1,변수H,0),0),1398.52) | S28: =IFERROR(VLOOKUP(" 원/달러(평균)",환율,MATCH(S$1,변수H,0),0),1386.95) | T28: =IFERROR(VLOOKUP(" 원/달러(평균)",환율,MATCH(T$1,변수H,0),0),1449.19) | U28: =IFERROR(VLOOKUP(" 원/달러(평균)",환율,MATCH(U$1,변수H,0),0),1466.12) | V28: =IFERROR(VLOOKUP(" 원/달러(평균)",환율,MATCH(V$1,변수H,0),0),1501.75) | W28: =IFERROR(VLOOKUP(" 원/달러(평균)",환율,MATCH(W$1,변수H,0),0),1418.75) | X28: =IFERROR(VLOOKUP(" 원/달러(평균)",환율,MATCH(X$1,변수H,0),0),1342.11) | Y28: =IFERROR(VLOOKUP(" 원/달러(평균)",환율,MATCH(Y$1,변수H,0),0),1332.1) | Z28: =IFERROR(VLOOKUP(" 원/달러(평균)",환율,MATCH(Z$1,변수H,0),0),1332.1) | AA28: =IFERROR(VLOOKUP(" 원/달러(평균)",환율,MATCH(AA$1,변수H,0),0),1332.1) | AB28: =IFERROR(VLOOKUP(" 원/달러(평균)",환율,MATCH(AB$1,변수H,0),0),1332.1) | AC28: =IFERROR(VLOOKUP(" 원/달러(평균)",환율,MATCH(AC$1,변수H,0),0),1332.1) | AD28: =IFERROR(VLOOKUP(" 원/달러(평균)",환율,MATCH(AD$1,변수H,0),0),1332.1) | AE28: =IFERROR(VLOOKUP(" 원/달러(평균)",환율,MATCH(AE$1,변수H,0),0),1332.1) | AF28: =IFERROR(VLOOKUP(" 원/달러(평균)",환율,MATCH(AF$1,변수H,0),0),1332.1) | ... AM28: =IFERROR(VLOOKUP(" 원/달러(평균)",환율,MATCH(AM$1,변수H,0),0),1332.1)
A29: after_origin | D29: origin(2026Q2) 이후 분기 = 1 (잔고 캡 배율 적용 구간) | E29: 0 | F29: 0 | G29: 0 | H29: 0 | I29: 0 | J29: 0 | K29: 0 | L29: 0 | M29: 0 | N29: 0 | O29: 0 | P29: 0 | Q29: 0 | R29: 0 | S29: 0 | T29: 0 | U29: 0 | V29: 0 | W29: 1 | X29: 1 | Y29: 1 | Z29: 1 | AA29: 1 | AB29: 1 | AC29: 1 | AD29: 1 | AE29: 1 | AF29: 1 | AG29: 1 | AH29: 1 | AI29: 1 | AJ29: 1 | AK29: 1 | AL29: 1 | AM29: 1
A31: ① 계약별 매출인식 스케줄(백만$, sls 저장값) | B31: type | C31: ships | D31: name | AX31: 포함(1/0) | AY31: 헤지환율 | AZ31: 캡배율 | BA31: 체결일 | BB31: origin이내 | BC31: 코호트 | BD31: 계약액(백만$) | BE31: 종료
A32: 20240701800160 | B32: LNGC | C32: 4 | D32: LNG 운반선 4척 | N32: 0.688 | O32: 63.309 | P32: 63.309 | Q32: 61.933 | R32: 62.621 | S32: 63.309 | T32: 63.309 | U32: 61.933 | V32: 62.621 | W32: 63.309 | X32: 63.309 | Y32: 61.933 | Z32: 62.621 | AA32: 63.309 | AB32: 63.309 | AC32: 62.621 | AD32: 62.621 | AE32: 42.664 | AX32: 1 | AY32: 1371.28 | AZ32: 1 | BA32: 2024-06-30 | BB32: 1 | BC32: ⑤초호황 | BD32: 1048.728 | BE32: 2028-08-31
A33: 20241002800072 | B33: LNGC | C33: 2 | D33: LNG 운반선 2척 | O33: 0.53 | P33: 48.794 | Q33: 47.733 | R33: 48.264 | S33: 48.794 | T33: 48.794 | U33: 47.733 | V33: 48.264 | W33: 48.794 | X33: 48.794 | Y33: 47.733 | Z33: 15.913 | AX33: 1 | AY33: 1356.22 | AZ33: 1 | BA33: 2024-09-30 | BB33: 1 | BC33: ⑤초호황 | BD33: 500.14 | BE33: 2027-04-30
A34: 20241031800038 | B34: LNGC | C34: 1 | D34: LNG 운반선 1척 | P34: 16.593 | Q34: 23.704 | R34: 23.968 | S34: 24.231 | T34: 24.231 | U34: 23.704 | V34: 23.968 | W34: 24.231 | X34: 24.231 | Y34: 23.704 | Z34: 23.97 | AX34: 1 | AY34: 1396.3 | AZ34: 1 | BA34: 2024-10-30 | BB34: 1 | BC34: ⑤초호황 | BD34: 256.535 | BE34: 2027-06-30
A35: 20241101800164 | B35: VLCC | C35: 4 | D35: 유조선 4척 | P35: 17.627 | Q35: 25.587 | R35: 25.872 | S35: 26.156 | T35: 26.156 | U35: 25.587 | V35: 25.872 | W35: 26.156 | X35: 26.156 | Y35: 25.587 | Z35: 25.872 | AA35: 26.156 | AB35: 26.157 | AX35: 1 | AY35: 1396.3 | AZ35: 1 | BA35: 2024-10-31 | BB35: 1 | BC35: ⑤초호황 | BD35: 328.941 | BE35: 2027-12-31
A36: 20241125800093 | B36: CONT | C36: 4 | D36: 컨테이너선 4척 | P36: 27.726 | Q36: 62.383 | R36: 63.076 | S36: 63.77 | T36: 63.77 | U36: 62.383 | V36: 63.076 | W36: 63.77 | X36: 63.77 | Y36: 62.383 | Z36: 63.076 | AA36: 63.77 | AB36: 63.769 | AX36: 1 | AY36: 1396.3 | AZ36: 1 | BA36: 2024-11-22 | BB36: 1 | BC36: ⑤초호황 | BD36: 786.722 | BE36: 2027-12-31
A37: 20241230800259 | B37: OTHER | D37: [P3 Ph3]FAB동 마감공사 | F37: 25.052 | G37: 32.925 | H37: 32.925 | I37: 32.209 | J37: 32.567 | K37: 32.925 | L37: 32.925 | M37: 32.567 | N37: 32.567 | O37: 32.925 | P37: 32.925 | Q37: 32.211 | AX37: 0 | AY37: 1360.12 | AZ37: 1 | BA37: 2022-11-28 | BB37: 1 | BD37: 384.723 | BE37: 2025-03-31
A38: 20241230800261 | B38: OTHER | D38: [P3 Ph4]FAB동 마감공사 | H38: 19.457 | I38: 37.258 | J38: 37.672 | K38: 38.086 | L38: 38.086 | M38: 37.672 | N38: 37.672 | O38: 38.086 | P38: 38.086 | Q38: 37.254 | AX38: 0 | AY38: 1360.12 | AZ38: 1 | BA38: 2022-11-10 | BB38: 1 | BD38: 359.329 | BE38: 2025-03-31
A39: 20250120800318 | B39: LNGC | C39: 1 | D39: LNG 운반선 1척 | Q39: 21.611 | R39: 26.576 | S39: 26.868 | T39: 26.868 | U39: 26.284 | V39: 26.576 | W39: 26.868 | X39: 26.868 | Y39: 26.284 | Z39: 26.579 | AX39: 1 | AY39: 1452.28 | AZ39: 1 | BA39: 2025-01-17 | BB39: 1 | BC39: ⑤초호황 | BD39: 261.382 | BE39: 2027-06-30
A40: 20250123800869 | B40: VLGC | C40: 3 | D40: 에탄운반선 3척 | P40: 3.855 | Q40: 43.372 | R40: 43.854 | S40: 44.336 | T40: 44.336 | U40: 43.372 | V40: 43.854 | W40: 44.336 | X40: 44.336 | Y40: 43.372 | Z40: 43.854 | AA40: 44.336 | AB40: 44.335 | AX40: 1 | AY40: 1396.3 | AZ40: 1 | BA40: 2024-12-24 | BB40: 1 | BC40: ⑤초호황 | BD40: 531.548 | BE40: 2027-12-31
A41: 20250317800118 | B41: VLCC | C41: 9 | D41: 셔틀탱커 9척 | Q41: 17.271 | R41: 87.314 | S41: 88.273 | T41: 88.273 | U41: 86.354 | V41: 87.314 | W41: 88.273 | X41: 88.273 | Y41: 86.354 | Z41: 87.314 | AA41: 88.273 | AB41: 88.273 | AC41: 87.314 | AD41: 87.314 | AE41: 88.273 | AF41: 88.272 | AX41: 1 | AY41: 1452.28 | AZ41: 1 | BA41: 2025-03-14 | BB41: 1 | BC41: ⑤초호황 | BD41: 1332.732 | BE41: 2028-12-31
A42: 20250318800145 | B42: VLGC | C42: 2 | D42: 에탄운반선 2척 | Q42: 4.458 | R42: 27.043 | S42: 27.34 | T42: 27.34 | U42: 26.745 | V42: 27.043 | W42: 27.34 | X42: 27.34 | Y42: 26.745 | Z42: 27.043 | AA42: 27.34 | AB42: 27.34 | AC42: 17.827 | AX42: 1 | AY42: 1452.28 | AZ42: 1 | BA42: 2025-03-17 | BB42: 1 | BC42: ⑤초호황 | BD42: 320.944 | BE42: 2028-02-29
A43: 20250408800489 | B43: VLCC | C43: 4 | D43: 유조선 4척 | R43: 21.275 | S43: 23.027 | T43: 23.027 | U43: 22.526 | V43: 22.776 | W43: 23.027 | X43: 23.027 | Y43: 22.526 | Z43: 22.776 | AA43: 23.027 | AB43: 23.027 | AC43: 22.776 | AD43: 22.776 | AE43: 23.027 | AF43: 23.027 | AX43: 1 | AY43: 1398.52 | AZ43: 1 | BA43: 2025-04-07 | BB43: 1 | BC43: ⑤초호황 | BD43: 341.647 | BE43: 2028-12-31
A44: 20250425800546 | B44: CONT | C44: 5 | D44: 컨테이너선 5척 | E44: 3.771 | F44: 49.028 | G44: 49.567 | H44: 49.567 | I44: 48.489 | J44: 49.028 | K44: 49.567 | L44: 49.567 | M44: 49.028 | N44: 49.028 | O44: 49.567 | P44: 49.567 | Q44: 48.489 | R44: 49.028 | S44: 23.166 | AX44: 1 | AY44: 1205.78 | AZ44: 1 | BA44: 2022-03-25 | BB44: 1 | BC44: ⑤초호황 | BD44: 666.457 | BE44: 2025-08-12
A45: 20250428800076 | B45: CONT | C45: 2 | D45: 컨테이너선 2척 | R45: 26.6 | S45: 36.526 | T45: 36.526 | U45: 35.732 | V45: 36.129 | W45: 36.526 | X45: 36.526 | Y45: 35.732 | Z45: 36.129 | AA45: 36.526 | AB45: 36.526 | AC45: 12.304 | AX45: 1 | AY45: 1398.52 | AZ45: 1 | BA45: 2025-04-25 | BB45: 1 | BC45: ⑤초호황 | BD45: 401.782 | BE45: 2028-01-31
A46: 20250618800387 | B46: OTHER | D46: 블록, 기자재 및 설계 | AX46: 0 | AY46: 1183.5 | AZ46: 1 | BA46: 2021-10-15 | BB46: 1 | BE46: 2026-04-09
A47: 20250618800388 | B47: OTHER | D47: 블록 및 기자재 | AX47: 0 | AY47: 1117.97 | AZ47: 1 | BA47: 2020-11-20 | BB47: 1 | BE47: 2025-05-15
A48: 20250818800096 | B48: LNGC | C48: 2 | D48: LNG운반선 2척 | S48: 26.571 | T48: 52.012 | U48: 50.881 | V48: 51.447 | W48: 52.012 | X48: 52.012 | Y48: 50.881 | Z48: 51.447 | AA48: 52.012 | AB48: 52.012 | AC48: 17.527 | AX48: 1 | AY48: 1386.95 | AZ48: 1 | BA48: 2025-08-15 | BB48: 1 | BC48: ⑤초호황 | BD48: 508.814 | BE48: 2028-01-31
A49: 20250818800098 | B49: LNGC | C49: 4 | D49: LNG운반선 4척 | S49: 40.389 | T49: 79.059 | U49: 77.34 | V49: 78.2 | W49: 79.059 | X49: 79.059 | Y49: 77.34 | Z49: 78.2 | AA49: 79.059 | AB49: 79.059 | AC49: 78.2 | AD49: 78.2 | AE49: 79.059 | AF49: 52.421 | AX49: 1 | AY49: 1386.95 | AZ49: 1 | BA49: 2025-08-15 | BB49: 1 | BC49: ⑤초호황 | BD49: 1034.644 | BE49: 2028-11-30
A50: 20251107800084 | B50: VLCC | C50: 2 | D50: 유조선 2척 | T50: 9.476 | U50: 15.229 | V50: 15.399 | W50: 15.568 | X50: 15.568 | Y50: 15.229 | Z50: 15.399 | AA50: 15.568 | AB50: 15.568 | AC50: 15.399 | AD50: 15.399 | AE50: 15.568 | AF50: 15.568 | AG50: 5.243 | AX50: 1 | AY50: 1449.19 | AZ50: 1 | BA50: 2025-11-06 | BB50: 1 | BC50: ⑤초호황 | BD50: 200.181 | BE50: 2029-01-31
A51: 20251120800137 | B51: CONT | C51: 7 | D51: 컨테이너선 7척 | T51: 38.716 | U51: 81.034 | V51: 81.934 | W51: 82.835 | X51: 82.835 | Y51: 81.034 | Z51: 81.934 | AA51: 82.835 | AB51: 82.835 | AC51: 81.934 | AD51: 81.934 | AE51: 82.835 | AF51: 82.835 | AG51: 81.034 | AH51: 81.934 | AI51: 82.835 | AJ51: 54.925 | AX51: 1 | AY51: 1449.19 | AZ51: 1 | BA51: 2025-11-19 | BB51: 1 | BC51: ⑤초호황 | BD51: 1326.258 | BE51: 2029-11-30
A52: 20251212800879 | B52: OTHER | D52: [P4 Ph1] FAB동 마감공사 | I52: 23.643 | J52: 23.905 | K52: 24.168 | L52: 24.168 | M52: 23.905 | N52: 23.905 | O52: 24.168 | P52: 24.168 | Q52: 23.643 | R52: 23.905 | S52: 24.168 | T52: 24.17 | AX52: 0 | AY52: 1360.12 | AZ52: 1 | BA52: 2022-12-23 | BB52: 1 | BD52: 287.916 | BE52: 2025-12-31
A53: 20251223800127 | B53: LNGC | C53: 2 | D53: LNG운반선 2척 | T53: 4.287 | U53: 38.581 | V53: 39.01 | W53: 39.438 | X53: 39.438 | Y53: 38.581 | Z53: 39.01 | AA53: 39.438 | AB53: 39.438 | AC53: 39.01 | AD53: 39.01 | AE53: 39.438 | AF53: 39.438 | AG53: 38.583 | AX53: 1 | AY53: 1449.19 | AZ53: 1 | BA53: 2025-12-22 | BB53: 1 | BC53: ⑤초호황 | BD53: 512.7 | BE53: 2029-03-31
A54: 20251226800865 | B54: OTHER | D54: [P4 Ph3(상서)]FAB동 마감공사 | N54: 10.14 | O54: 66.632 | P54: 66.632 | Q54: 65.183 | R54: 65.907 | S54: 66.632 | T54: 63.01 | AX54: 0 | AY54: 1371.28 | AZ54: 1 | BA54: 2024-06-14 | BB54: 1 | BD54: 404.136 | BE54: 2025-12-26
A55: 20260102800222 | B55: LNGC | C55: 2 | D55: LNG운반선 2척 | T55: 0.503 | U55: 45.235 | V55: 45.738 | W55: 46.241 | X55: 46.241 | Y55: 45.235 | Z55: 45.738 | AA55: 46.241 | AB55: 46.241 | AC55: 45.738 | AD55: 45.738 | AE55: 38.699 | AX55: 1 | AY55: 1449.19 | AZ55: 1 | BA55: 2025-12-31 | BB55: 1 | BC55: ⑤초호황 | BD55: 497.588 | BE55: 2028-09-15
A56: 20260128800216 | B56: VLGC | C56: 2 | D56: 에탄운반선 2척 | U56: 17.336 | V56: 24.65 | W56: 24.921 | X56: 24.921 | Y56: 24.379 | Z56: 24.65 | AA56: 24.921 | AB56: 24.921 | AC56: 24.65 | AD56: 24.65 | AE56: 24.921 | AF56: 24.921 | AG56: 4.064 | AX56: 1 | AY56: 1466.12 | AZ56: 1 | BA56: 2026-01-27 | BB56: 1 | BC56: ⑤초호황 | BD56: 293.905 | BE56: 2029-01-15
A57: 20260128800218 | B57: LNGC | C57: 2 | D57: LNG운반선 2척 | U57: 28.832 | V57: 40.996 | W57: 41.446 | X57: 41.446 | Y57: 40.545 | Z57: 40.996 | AA57: 41.446 | AB57: 41.446 | AC57: 40.996 | AD57: 40.996 | AE57: 41.446 | AF57: 41.446 | AG57: 13.966 | AX57: 1 | AY57: 1466.12 | AZ57: 1 | BA57: 2026-01-27 | BB57: 1 | BC57: ⑤초호황 | BD57: 496.003 | BE57: 2029-01-31
A58: 20260211800232 | B58: CONT | C58: 2 | D58: 컨테이너선 2척 | U58: 19.681 | V58: 35.819 | W58: 36.213 | X58: 36.213 | Y58: 35.426 | Z58: 35.819 | AA58: 36.213 | AB58: 36.213 | AC58: 35.819 | AD58: 12.203 | AX58: 1 | AY58: 1466.12 | AZ58: 1 | BA58: 2026-02-10 | BB58: 1 | BC58: ⑤초호황 | BD58: 319.619 | BE58: 2028-05-01
A59: 20260220800213 | B59: LNGC | C59: 1 | D59: LNG운반선 1척 | U59: 12.354 | V59: 27.42 | W59: 27.722 | X59: 27.722 | Y59: 27.119 | Z59: 27.42 | AA59: 27.722 | AB59: 27.722 | AC59: 27.42 | AD59: 18.382 | AX59: 1 | AY59: 1466.12 | AZ59: 1 | BA59: 2026-02-19 | BB59: 1 | BC59: ⑤초호황 | BD59: 251.003 | BE59: 2028-05-31
A60: 20260310800545 | B60: VLCC | C60: 3 | D60: 유조선 3척 | U60: 5.523 | V60: 22.846 | W60: 23.097 | X60: 23.097 | Y60: 22.595 | Z60: 22.846 | AA60: 23.097 | AB60: 23.097 | AC60: 22.846 | AD60: 22.846 | AE60: 23.097 | AF60: 23.097 | AG60: 14.813 | AX60: 1 | AY60: 1466.12 | AZ60: 1 | BA60: 2026-03-10 | BB60: 1 | BC60: ⑤초호황 | BD60: 272.897 | BE60: 2029-02-28
A61: 20260316801038 | B61: VLCC | C61: 1 | D61: 원유운반선 1척 | AX61: 1 | AY61: 1315.69 | AZ61: 1 | BA61: 2023-06-02 | BB61: 1 | BE61: 2026-07-03
A62: 20260320800106 | B62: LNGC | C62: 1 | D62: LNG운반선 1척 | U62: 2.718 | V62: 20.611 | W62: 20.838 | X62: 20.838 | Y62: 20.385 | Z62: 20.611 | AA62: 20.838 | AB62: 20.838 | AC62: 20.611 | AD62: 20.611 | AE62: 20.838 | AF62: 20.838 | AG62: 20.385 | AH62: 6.795 | AX62: 1 | AY62: 1466.12 | AZ62: 1 | BA62: 2026-03-20 | BB62: 1 | BC62: ⑤초호황 | BD62: 257.755 | BE62: 2029-04-30
A63: 20260323800137 | B63: LNGC | C63: 2 | D63: LNG운반선 2척 | U63: 6.807 | V63: 51.619 | W63: 52.186 | X63: 52.186 | Y63: 51.052 | Z63: 51.619 | AA63: 52.186 | AB63: 52.186 | AC63: 51.619 | AD63: 51.619 | AE63: 52.185 | AX63: 1 | AY63: 1466.12 | AZ63: 1 | BA63: 2026-03-20 | BB63: 1 | BC63: ⑤초호황 | BD63: 525.264 | BE63: 2028-09-30
A64: 20260401800243 | B64: VLGC | C64: 2 | D64: VLGC 2척 | U64: 0.201 | V64: 18.331 | W64: 18.533 | X64: 18.533 | Y64: 18.13 | Z64: 18.331 | AA64: 18.533 | AB64: 18.533 | AC64: 18.331 | AD64: 18.331 | AE64: 18.533 | AF64: 18.533 | AG64: 18.13 | AH64: 12.286 | AX64: 1 | AY64: 1466.12 | AZ64: 1 | BA64: 2026-03-31 | BB64: 1 | BC64: ⑤초호황 | BD64: 233.269 | BE64: 2029-05-31
A65: 20260504800254 | B65: LNGC | C65: 1 | D65: FSRU 1척 | V65: 19.565 | W65: 29.032 | X65: 29.032 | Y65: 28.401 | Z65: 28.716 | AA65: 29.032 | AB65: 29.032 | AC65: 28.716 | AD65: 28.716 | AE65: 29.032 | AF65: 29.032 | AG65: 14.517 | AX65: 1 | AY65: 1501.75 | AZ65: 1 | BA65: 2026-04-30 | BB65: 1 | BC65: ⑤초호황 | BD65: 322.823 | BE65: 2029-02-15
A66: 20260514800296 | B66: LNGC | C66: 2 | D66: LNG운반선 2척 | V66: 21.387 | W66: 40.155 | X66: 40.155 | Y66: 39.282 | Z66: 39.718 | AA66: 40.155 | AB66: 40.155 | AC66: 39.718 | AD66: 39.718 | AE66: 40.155 | AF66: 40.155 | AG66: 39.282 | AH66: 39.715 | AX66: 1 | AY66: 1501.75 | AZ66: 1 | BA66: 2026-05-13 | BB66: 1 | BC66: ⑤초호황 | BD66: 499.75 | BE66: 2029-06-30
A67: 20260518800216 | B67: LNGC | C67: 3 | D67: LNG운반선 3척 | V67: 31.612 | W67: 61.878 | X67: 61.878 | Y67: 60.533 | Z67: 61.206 | AA67: 61.878 | AB67: 61.878 | AC67: 61.206 | AD67: 61.206 | AE67: 61.878 | AF67: 61.878 | AG67: 60.533 | AH67: 41.029 | AX67: 1 | AY67: 1501.75 | AZ67: 1 | BA67: 2026-05-15 | BB67: 1 | BC67: ⑤초호황 | BD67: 748.593 | BE67: 2029-05-31
A68: 20260527800188 | B68: LNGC | C68: 1 | D68: LNG운반선 1척 | V68: 10.273 | W68: 26.253 | X68: 26.253 | Y68: 25.682 | Z68: 25.968 | AA68: 26.253 | AB68: 26.253 | AC68: 25.968 | AD68: 25.968 | AE68: 26.253 | AF68: 8.846 | AX68: 1 | AY68: 1501.75 | AZ68: 1 | BA68: 2026-05-26 | BB68: 1 | BC68: ⑤초호황 | BD68: 253.97 | BE68: 2028-10-31
A69: 20260527800189 | B69: VLGC | C69: 2 | D69: VLGC 2척 | V69: 6.38 | W69: 16.305 | X69: 16.305 | Y69: 15.95 | Z69: 16.127 | AA69: 16.305 | AB69: 16.305 | AC69: 16.127 | AD69: 16.127 | AE69: 16.305 | AF69: 16.305 | AG69: 15.95 | AH69: 16.127 | AI69: 16.305 | AJ69: 10.811 | AX69: 1 | AY69: 1501.75 | AZ69: 1 | BA69: 2026-05-26 | BB69: 1 | BC69: ⑤초호황 | BD69: 227.734 | BE69: 2029-11-30
A70: 20260527800191 | B70: VLCC | C70: 2 | D70: 유조선 2척 | V70: 10.112 | W70: 25.841 | X70: 25.841 | Y70: 25.28 | Z70: 25.561 | AA70: 25.841 | AB70: 25.841 | AC70: 21.067 | AX70: 1 | AY70: 1501.75 | AZ70: 1 | BA70: 2026-05-26 | BB70: 1 | BC70: ⑤초호황 | BD70: 185.384 | BE70: 2028-03-15
A71: 20260604800001 | B71: OFFSH | C71: 1 | D71: 해양생산설비 1기 | V71: 57.285 | W71: 175.675 | X71: 175.675 | Y71: 171.856 | Z71: 173.766 | AA71: 175.675 | AB71: 175.675 | AC71: 173.766 | AD71: 173.766 | AE71: 175.675 | AF71: 175.675 | AG71: 171.856 | AH71: 173.766 | AI71: 175.675 | AJ71: 175.675 | AK71: 171.856 | AL71: 173.766 | AM71: 36.286 | AX71: 1 | AY71: 1501.75 | AZ71: 1 | BA71: 2026-06-01 | BB71: 1 | BC71: ⑤초호황 | BD71: 2883.369 | BE71: 2030-07-19
A72: 20260608800137 | B72: LNGC | C72: 1 | D72: LNG운반선 1척 | V72: 7.033 | W72: 24.886 | X72: 24.886 | Y72: 24.345 | Z72: 24.615 | AA72: 24.886 | AB72: 24.886 | AC72: 24.615 | AD72: 24.615 | AE72: 24.886 | AF72: 24.886 | AG72: 2.162 | AX72: 1 | AY72: 1501.75 | AZ72: 1 | BA72: 2026-06-05 | BB72: 1 | BC72: ⑤초호황 | BD72: 256.701 | BE72: 2029-01-08
A73: 20260608800714 | B73: OFFSH | C73: 1 | D73: 해양생산설비 1기 | J73: 14.275 | K73: 50.511 | L73: 50.511 | M73: 49.962 | N73: 49.962 | O73: 50.511 | P73: 50.511 | Q73: 49.412 | R73: 49.962 | S73: 50.511 | T73: 50.511 | U73: 49.412 | V73: 49.962 | W73: 50.511 | X73: 50.511 | Y73: 49.412 | Z73: 49.962 | AA73: 50.511 | AB73: 50.511 | AC73: 49.962 | AD73: 49.962 | AE73: 50.511 | AF73: 50.511 | AG73: 49.412 | AH73: 49.962 | AI73: 50.503 | AX73: 1 | AY73: 1501.75 | AZ73: 1 | BA73: 2026-06-06 | BB73: 1 | BC73: ⑤초호황 | BD73: 1268.254 | BE73: 2029-09-30
A74: 20260608800716 | B74: OFFSH | D74: 해양생산설비 본 계약 체결전 예비 작업 | S74: 293.274 | T74: 303.159 | U74: 296.569 | V74: 227.37 | AX74: 1 | AY74: 1386.95 | AZ74: 1 | BA74: 2025-07-04 | BB74: 1 | BD74: 1120.372 | BE74: 2026-06-08
A75: 20260702800158 | B75: VLCC | C75: 2 | D75: 유조선 2척 | W75: 16.176 | X75: 16.176 | Y75: 15.824 | Z75: 16 | AA75: 16.176 | AB75: 16.176 | AC75: 16 | AD75: 16 | AE75: 16.176 | AF75: 16.176 | AG75: 15.824 | AH75: 16.001 | AX75: 0 | AY75: 1418.75 | AZ75: 1 | BA75: 2026-07-01 | BB75: 0 | BC75: ⑤초호황 | BD75: 192.705 | BE75: 2029-06-30
A76: 20260708800164 | B76: VLCC | C76: 2 | D76: 유조선 2척 | W76: 16.542 | X76: 17.696 | Y76: 17.311 | Z76: 17.504 | AA76: 17.696 | AB76: 17.696 | AC76: 17.504 | AD76: 17.504 | AE76: 17.696 | AF76: 17.696 | AG76: 17.311 | AH76: 8.655 | AX76: 0 | AY76: 1418.75 | AZ76: 1 | BA76: 2026-07-07 | BB76: 0 | BC76: ⑤초호황 | BD76: 200.811 | BE76: 2029-05-15
A77: 20260728800579 | B77: OTHER | D77: P4 Ph4(상동) 마감공사 | S77: 50.409 | T77: 61.834 | U77: 60.49 | V77: 61.162 | W77: 61.834 | X77: 61.834 | Y77: 60.49 | Z77: 20.165 | AX77: 0 | AY77: 1386.95 | AZ77: 1 | BA77: 2025-07-18 | BB77: 1 | BD77: 438.218 | BE77: 2027-04-30
A78: 20260803800398 | B78: VLCC | C78: 2 | D78: 유조선 2척 | W78: 10.383 | X78: 15.407 | Y78: 15.072 | Z78: 15.239 | AA78: 15.407 | AB78: 15.407 | AC78: 15.239 | AD78: 15.239 | AE78: 15.407 | AF78: 15.407 | AG78: 15.072 | AH78: 15.239 | AI78: 10.381 | AX78: 0 | AY78: 1418.75 | AZ78: 1 | BA78: 2026-07-31 | BB78: 0 | BC78: ⑤초호황 | BD78: 188.899 | BE78: 2029-08-31
A79: 20260831800071 | B79: CONT | C79: 2 | D79: 컨테이너선 2척 | W79: 12.488 | X79: 33.791 | Y79: 33.057 | Z79: 33.424 | AA79: 33.791 | AB79: 33.791 | AC79: 33.424 | AD79: 33.424 | AE79: 33.791 | AF79: 32.323 | AX79: 0 | AY79: 1418.75 | AZ79: 1 | BA79: 2026-08-28 | BB79: 0 | BC79: ⑤초호황 | BD79: 313.304 | BE79: 2028-12-27
A80: 20260831800178 | B80: OTHER | D80: [P4 Ph2(하동)] FAB동 마감공사 | K80: 23.147 | L80: 27.301 | M80: 27.004 | N80: 27.004 | O80: 27.301 | P80: 27.301 | Q80: 26.708 | R80: 27.004 | S80: 27.301 | T80: 27.301 | U80: 26.708 | V80: 27.004 | W80: 27.301 | X80: 27.301 | Y80: 26.708 | Z80: 27.004 | AA80: 27.301 | AB80: 27.303 | AX80: 0 | AY80: 1322.01 | AZ80: 1 | BA80: 2023-12-13 | BB80: 1 | BD80: 484.002 | BE80: 2027-12-31
A81: 20260911800485 | B81: VLCC | C81: 3 | D81: 유조선 3척 | T81: 13.118 | U81: 16.866 | V81: 17.053 | W81: 17.241 | X81: 17.241 | Y81: 16.866 | Z81: 17.053 | AA81: 17.241 | AB81: 17.241 | AC81: 17.053 | AD81: 17.053 | AE81: 17.241 | AF81: 17.241 | AG81: 16.865 | AX81: 1 | AY81: 1449.19 | AZ81: 1 | BA81: 2025-10-23 | BB81: 1 | BC81: ⑤초호황 | BD81: 235.373 | BE81: 2029-03-31
A82: 20260914800075 | B82: LNGC | C82: 4 | D82: LNG운반선 4척 | W82: 17.815 | X82: 81.948 | Y82: 80.166 | Z82: 81.057 | AA82: 81.948 | AB82: 81.948 | AC82: 81.057 | AD82: 81.057 | AE82: 81.948 | AF82: 81.948 | AG82: 80.166 | AH82: 81.057 | AI82: 80.167 | AX82: 0 | AY82: 1418.75 | AZ82: 1 | BA82: 2026-09-11 | BB82: 0 | BC82: ⑤초호황 | BD82: 992.282 | BE82: 2029-09-28
A83: 20260930800054 | B83: VLGC | C83: 2 | D83: VLGC 2척 | W83: 0.347 | X83: 15.96 | Y83: 15.613 | Z83: 15.786 | AA83: 15.96 | AB83: 15.96 | AC83: 15.786 | AD83: 15.786 | AE83: 15.96 | AF83: 15.96 | AG83: 15.613 | AH83: 15.786 | AI83: 15.96 | AJ83: 15.96 | AK83: 10.233 | AX83: 0 | AY83: 1418.75 | AZ83: 1 | BA83: 2026-09-29 | BB83: 0 | BC83: ⑤초호황 | BD83: 216.67 | BE83: 2030-02-28
A84: 20261002800245 | B84: LNGC | C84: 2 | D84: LNG운반선 2척 | X84: 46.842 | Y84: 46.328 | Z84: 46.842 | AA84: 47.357 | AB84: 47.357 | AC84: 46.842 | AD84: 46.842 | AE84: 47.357 | AF84: 47.357 | AG84: 46.328 | AH84: 31.401 | AX84: 0 | AY84: 1342.11 | AZ84: 1 | BA84: 2026-10-02 | BB84: 0 | BC84: ⑤초호황 | BD84: 500.853 | BE84: 2029-05-31
A86: ② 계약별 원화(백만원, 수식) | B86: type | C86: ships | D86: name
A87: 20240701800160 | B87: LNGC | C87: 4 | D87: LNG 운반선 4척 | N87: =IFERROR(N32*$AX32*(1+($AZ32-1)*N$29)*($D$26*$AY32+(1-$D$26)*N$28),"") | O87: =IFERROR(O32*$AX32*(1+($AZ32-1)*O$29)*($D$26*$AY32+(1-$D$26)*O$28),"") | P87: =IFERROR(P32*$AX32*(1+($AZ32-1)*P$29)*($D$26*$AY32+(1-$D$26)*P$28),"") | Q87: =IFERROR(Q32*$AX32*(1+($AZ32-1)*Q$29)*($D$26*$AY32+(1-$D$26)*Q$28),"") | R87: =IFERROR(R32*$AX32*(1+($AZ32-1)*R$29)*($D$26*$AY32+(1-$D$26)*R$28),"") | S87: =IFERROR(S32*$AX32*(1+($AZ32-1)*S$29)*($D$26*$AY32+(1-$D$26)*S$28),"") | T87: =IFERROR(T32*$AX32*(1+($AZ32-1)*T$29)*($D$26*$AY32+(1-$D$26)*T$28),"") | U87: =IFERROR(U32*$AX32*(1+($AZ32-1)*U$29)*($D$26*$AY32+(1-$D$26)*U$28),"") | ... AE87: =IFERROR(AE32*$AX32*(1+($AZ32-1)*AE$29)*($D$26*$AY32+(1-$D$26)*AE$28),"")
A88: 20241002800072 | B88: LNGC | C88: 2 | D88: LNG 운반선 2척 | O88: =IFERROR(O33*$AX33*(1+($AZ33-1)*O$29)*($D$26*$AY33+(1-$D$26)*O$28),"") | P88: =IFERROR(P33*$AX33*(1+($AZ33-1)*P$29)*($D$26*$AY33+(1-$D$26)*P$28),"") | Q88: =IFERROR(Q33*$AX33*(1+($AZ33-1)*Q$29)*($D$26*$AY33+(1-$D$26)*Q$28),"") | R88: =IFERROR(R33*$AX33*(1+($AZ33-1)*R$29)*($D$26*$AY33+(1-$D$26)*R$28),"") | S88: =IFERROR(S33*$AX33*(1+($AZ33-1)*S$29)*($D$26*$AY33+(1-$D$26)*S$28),"") | T88: =IFERROR(T33*$AX33*(1+($AZ33-1)*T$29)*($D$26*$AY33+(1-$D$26)*T$28),"") | U88: =IFERROR(U33*$AX33*(1+($AZ33-1)*U$29)*($D$26*$AY33+(1-$D$26)*U$28),"") | V88: =IFERROR(V33*$AX33*(1+($AZ33-1)*V$29)*($D$26*$AY33+(1-$D$26)*V$28),"") | ... Z88: =IFERROR(Z33*$AX33*(1+($AZ33-1)*Z$29)*($D$26*$AY33+(1-$D$26)*Z$28),"")
A89: 20241031800038 | B89: LNGC | C89: 1 | D89: LNG 운반선 1척 | P89: =IFERROR(P34*$AX34*(1+($AZ34-1)*P$29)*($D$26*$AY34+(1-$D$26)*P$28),"") | Q89: =IFERROR(Q34*$AX34*(1+($AZ34-1)*Q$29)*($D$26*$AY34+(1-$D$26)*Q$28),"") | R89: =IFERROR(R34*$AX34*(1+($AZ34-1)*R$29)*($D$26*$AY34+(1-$D$26)*R$28),"") | S89: =IFERROR(S34*$AX34*(1+($AZ34-1)*S$29)*($D$26*$AY34+(1-$D$26)*S$28),"") | T89: =IFERROR(T34*$AX34*(1+($AZ34-1)*T$29)*($D$26*$AY34+(1-$D$26)*T$28),"") | U89: =IFERROR(U34*$AX34*(1+($AZ34-1)*U$29)*($D$26*$AY34+(1-$D$26)*U$28),"") | V89: =IFERROR(V34*$AX34*(1+($AZ34-1)*V$29)*($D$26*$AY34+(1-$D$26)*V$28),"") | W89: =IFERROR(W34*$AX34*(1+($AZ34-1)*W$29)*($D$26*$AY34+(1-$D$26)*W$28),"") | ... Z89: =IFERROR(Z34*$AX34*(1+($AZ34-1)*Z$29)*($D$26*$AY34+(1-$D$26)*Z$28),"")
A90: 20241101800164 | B90: VLCC | C90: 4 | D90: 유조선 4척 | P90: =IFERROR(P35*$AX35*(1+($AZ35-1)*P$29)*($D$26*$AY35+(1-$D$26)*P$28),"") | Q90: =IFERROR(Q35*$AX35*(1+($AZ35-1)*Q$29)*($D$26*$AY35+(1-$D$26)*Q$28),"") | R90: =IFERROR(R35*$AX35*(1+($AZ35-1)*R$29)*($D$26*$AY35+(1-$D$26)*R$28),"") | S90: =IFERROR(S35*$AX35*(1+($AZ35-1)*S$29)*($D$26*$AY35+(1-$D$26)*S$28),"") | T90: =IFERROR(T35*$AX35*(1+($AZ35-1)*T$29)*($D$26*$AY35+(1-$D$26)*T$28),"") | U90: =IFERROR(U35*$AX35*(1+($AZ35-1)*U$29)*($D$26*$AY35+(1-$D$26)*U$28),"") | V90: =IFERROR(V35*$AX35*(1+($AZ35-1)*V$29)*($D$26*$AY35+(1-$D$26)*V$28),"") | W90: =IFERROR(W35*$AX35*(1+($AZ35-1)*W$29)*($D$26*$AY35+(1-$D$26)*W$28),"") | ... AB90: =IFERROR(AB35*$AX35*(1+($AZ35-1)*AB$29)*($D$26*$AY35+(1-$D$26)*AB$28),"")
A91: 20241125800093 | B91: CONT | C91: 4 | D91: 컨테이너선 4척 | P91: =IFERROR(P36*$AX36*(1+($AZ36-1)*P$29)*($D$26*$AY36+(1-$D$26)*P$28),"") | Q91: =IFERROR(Q36*$AX36*(1+($AZ36-1)*Q$29)*($D$26*$AY36+(1-$D$26)*Q$28),"") | R91: =IFERROR(R36*$AX36*(1+($AZ36-1)*R$29)*($D$26*$AY36+(1-$D$26)*R$28),"") | S91: =IFERROR(S36*$AX36*(1+($AZ36-1)*S$29)*($D$26*$AY36+(1-$D$26)*S$28),"") | T91: =IFERROR(T36*$AX36*(1+($AZ36-1)*T$29)*($D$26*$AY36+(1-$D$26)*T$28),"") | U91: =IFERROR(U36*$AX36*(1+($AZ36-1)*U$29)*($D$26*$AY36+(1-$D$26)*U$28),"") | V91: =IFERROR(V36*$AX36*(1+($AZ36-1)*V$29)*($D$26*$AY36+(1-$D$26)*V$28),"") | W91: =IFERROR(W36*$AX36*(1+($AZ36-1)*W$29)*($D$26*$AY36+(1-$D$26)*W$28),"") | ... AB91: =IFERROR(AB36*$AX36*(1+($AZ36-1)*AB$29)*($D$26*$AY36+(1-$D$26)*AB$28),"")
A92: 20241230800259 | B92: OTHER | D92: [P3 Ph3]FAB동 마감공사 | F92: =IFERROR(F37*$AX37*(1+($AZ37-1)*F$29)*($D$26*$AY37+(1-$D$26)*F$28),"") | G92: =IFERROR(G37*$AX37*(1+($AZ37-1)*G$29)*($D$26*$AY37+(1-$D$26)*G$28),"") | H92: =IFERROR(H37*$AX37*(1+($AZ37-1)*H$29)*($D$26*$AY37+(1-$D$26)*H$28),"") | I92: =IFERROR(I37*$AX37*(1+($AZ37-1)*I$29)*($D$26*$AY37+(1-$D$26)*I$28),"") | J92: =IFERROR(J37*$AX37*(1+($AZ37-1)*J$29)*($D$26*$AY37+(1-$D$26)*J$28),"") | K92: =IFERROR(K37*$AX37*(1+($AZ37-1)*K$29)*($D$26*$AY37+(1-$D$26)*K$28),"") | L92: =IFERROR(L37*$AX37*(1+($AZ37-1)*L$29)*($D$26*$AY37+(1-$D$26)*L$28),"") | M92: =IFERROR(M37*$AX37*(1+($AZ37-1)*M$29)*($D$26*$AY37+(1-$D$26)*M$28),"") | ... Q92: =IFERROR(Q37*$AX37*(1+($AZ37-1)*Q$29)*($D$26*$AY37+(1-$D$26)*Q$28),"")
A93: 20241230800261 | B93: OTHER | D93: [P3 Ph4]FAB동 마감공사 | H93: =IFERROR(H38*$AX38*(1+($AZ38-1)*H$29)*($D$26*$AY38+(1-$D$26)*H$28),"") | I93: =IFERROR(I38*$AX38*(1+($AZ38-1)*I$29)*($D$26*$AY38+(1-$D$26)*I$28),"") | J93: =IFERROR(J38*$AX38*(1+($AZ38-1)*J$29)*($D$26*$AY38+(1-$D$26)*J$28),"") | K93: =IFERROR(K38*$AX38*(1+($AZ38-1)*K$29)*($D$26*$AY38+(1-$D$26)*K$28),"") | L93: =IFERROR(L38*$AX38*(1+($AZ38-1)*L$29)*($D$26*$AY38+(1-$D$26)*L$28),"") | M93: =IFERROR(M38*$AX38*(1+($AZ38-1)*M$29)*($D$26*$AY38+(1-$D$26)*M$28),"") | N93: =IFERROR(N38*$AX38*(1+($AZ38-1)*N$29)*($D$26*$AY38+(1-$D$26)*N$28),"") | O93: =IFERROR(O38*$AX38*(1+($AZ38-1)*O$29)*($D$26*$AY38+(1-$D$26)*O$28),"") | ... Q93: =IFERROR(Q38*$AX38*(1+($AZ38-1)*Q$29)*($D$26*$AY38+(1-$D$26)*Q$28),"")
A94: 20250120800318 | B94: LNGC | C94: 1 | D94: LNG 운반선 1척 | Q94: =IFERROR(Q39*$AX39*(1+($AZ39-1)*Q$29)*($D$26*$AY39+(1-$D$26)*Q$28),"") | R94: =IFERROR(R39*$AX39*(1+($AZ39-1)*R$29)*($D$26*$AY39+(1-$D$26)*R$28),"") | S94: =IFERROR(S39*$AX39*(1+($AZ39-1)*S$29)*($D$26*$AY39+(1-$D$26)*S$28),"") | T94: =IFERROR(T39*$AX39*(1+($AZ39-1)*T$29)*($D$26*$AY39+(1-$D$26)*T$28),"") | U94: =IFERROR(U39*$AX39*(1+($AZ39-1)*U$29)*($D$26*$AY39+(1-$D$26)*U$28),"") | V94: =IFERROR(V39*$AX39*(1+($AZ39-1)*V$29)*($D$26*$AY39+(1-$D$26)*V$28),"") | W94: =IFERROR(W39*$AX39*(1+($AZ39-1)*W$29)*($D$26*$AY39+(1-$D$26)*W$28),"") | X94: =IFERROR(X39*$AX39*(1+($AZ39-1)*X$29)*($D$26*$AY39+(1-$D$26)*X$28),"") | ... Z94: =IFERROR(Z39*$AX39*(1+($AZ39-1)*Z$29)*($D$26*$AY39+(1-$D$26)*Z$28),"")
A95: 20250123800869 | B95: VLGC | C95: 3 | D95: 에탄운반선 3척 | P95: =IFERROR(P40*$AX40*(1+($AZ40-1)*P$29)*($D$26*$AY40+(1-$D$26)*P$28),"") | Q95: =IFERROR(Q40*$AX40*(1+($AZ40-1)*Q$29)*($D$26*$AY40+(1-$D$26)*Q$28),"") | R95: =IFERROR(R40*$AX40*(1+($AZ40-1)*R$29)*($D$26*$AY40+(1-$D$26)*R$28),"") | S95: =IFERROR(S40*$AX40*(1+($AZ40-1)*S$29)*($D$26*$AY40+(1-$D$26)*S$28),"") | T95: =IFERROR(T40*$AX40*(1+($AZ40-1)*T$29)*($D$26*$AY40+(1-$D$26)*T$28),"") | U95: =IFERROR(U40*$AX40*(1+($AZ40-1)*U$29)*($D$26*$AY40+(1-$D$26)*U$28),"") | V95: =IFERROR(V40*$AX40*(1+($AZ40-1)*V$29)*($D$26*$AY40+(1-$D$26)*V$28),"") | W95: =IFERROR(W40*$AX40*(1+($AZ40-1)*W$29)*($D$26*$AY40+(1-$D$26)*W$28),"") | ... AB95: =IFERROR(AB40*$AX40*(1+($AZ40-1)*AB$29)*($D$26*$AY40+(1-$D$26)*AB$28),"")
A96: 20250317800118 | B96: VLCC | C96: 9 | D96: 셔틀탱커 9척 | Q96: =IFERROR(Q41*$AX41*(1+($AZ41-1)*Q$29)*($D$26*$AY41+(1-$D$26)*Q$28),"") | R96: =IFERROR(R41*$AX41*(1+($AZ41-1)*R$29)*($D$26*$AY41+(1-$D$26)*R$28),"") | S96: =IFERROR(S41*$AX41*(1+($AZ41-1)*S$29)*($D$26*$AY41+(1-$D$26)*S$28),"") | T96: =IFERROR(T41*$AX41*(1+($AZ41-1)*T$29)*($D$26*$AY41+(1-$D$26)*T$28),"") | U96: =IFERROR(U41*$AX41*(1+($AZ41-1)*U$29)*($D$26*$AY41+(1-$D$26)*U$28),"") | V96: =IFERROR(V41*$AX41*(1+($AZ41-1)*V$29)*($D$26*$AY41+(1-$D$26)*V$28),"") | W96: =IFERROR(W41*$AX41*(1+($AZ41-1)*W$29)*($D$26*$AY41+(1-$D$26)*W$28),"") | X96: =IFERROR(X41*$AX41*(1+($AZ41-1)*X$29)*($D$26*$AY41+(1-$D$26)*X$28),"") | ... AF96: =IFERROR(AF41*$AX41*(1+($AZ41-1)*AF$29)*($D$26*$AY41+(1-$D$26)*AF$28),"")
A97: 20250318800145 | B97: VLGC | C97: 2 | D97: 에탄운반선 2척 | Q97: =IFERROR(Q42*$AX42*(1+($AZ42-1)*Q$29)*($D$26*$AY42+(1-$D$26)*Q$28),"") | R97: =IFERROR(R42*$AX42*(1+($AZ42-1)*R$29)*($D$26*$AY42+(1-$D$26)*R$28),"") | S97: =IFERROR(S42*$AX42*(1+($AZ42-1)*S$29)*($D$26*$AY42+(1-$D$26)*S$28),"") | T97: =IFERROR(T42*$AX42*(1+($AZ42-1)*T$29)*($D$26*$AY42+(1-$D$26)*T$28),"") | U97: =IFERROR(U42*$AX42*(1+($AZ42-1)*U$29)*($D$26*$AY42+(1-$D$26)*U$28),"") | V97: =IFERROR(V42*$AX42*(1+($AZ42-1)*V$29)*($D$26*$AY42+(1-$D$26)*V$28),"") | W97: =IFERROR(W42*$AX42*(1+($AZ42-1)*W$29)*($D$26*$AY42+(1-$D$26)*W$28),"") | X97: =IFERROR(X42*$AX42*(1+($AZ42-1)*X$29)*($D$26*$AY42+(1-$D$26)*X$28),"") | ... AC97: =IFERROR(AC42*$AX42*(1+($AZ42-1)*AC$29)*($D$26*$AY42+(1-$D$26)*AC$28),"")
A98: 20250408800489 | B98: VLCC | C98: 4 | D98: 유조선 4척 | R98: =IFERROR(R43*$AX43*(1+($AZ43-1)*R$29)*($D$26*$AY43+(1-$D$26)*R$28),"") | S98: =IFERROR(S43*$AX43*(1+($AZ43-1)*S$29)*($D$26*$AY43+(1-$D$26)*S$28),"") | T98: =IFERROR(T43*$AX43*(1+($AZ43-1)*T$29)*($D$26*$AY43+(1-$D$26)*T$28),"") | U98: =IFERROR(U43*$AX43*(1+($AZ43-1)*U$29)*($D$26*$AY43+(1-$D$26)*U$28),"") | V98: =IFERROR(V43*$AX43*(1+($AZ43-1)*V$29)*($D$26*$AY43+(1-$D$26)*V$28),"") | W98: =IFERROR(W43*$AX43*(1+($AZ43-1)*W$29)*($D$26*$AY43+(1-$D$26)*W$28),"") | X98: =IFERROR(X43*$AX43*(1+($AZ43-1)*X$29)*($D$26*$AY43+(1-$D$26)*X$28),"") | Y98: =IFERROR(Y43*$AX43*(1+($AZ43-1)*Y$29)*($D$26*$AY43+(1-$D$26)*Y$28),"") | ... AF98: =IFERROR(AF43*$AX43*(1+($AZ43-1)*AF$29)*($D$26*$AY43+(1-$D$26)*AF$28),"")
A99: 20250425800546 | B99: CONT | C99: 5 | D99: 컨테이너선 5척 | E99: =IFERROR(E44*$AX44*(1+($AZ44-1)*E$29)*($D$26*$AY44+(1-$D$26)*E$28),"") | F99: =IFERROR(F44*$AX44*(1+($AZ44-1)*F$29)*($D$26*$AY44+(1-$D$26)*F$28),"") | G99: =IFERROR(G44*$AX44*(1+($AZ44-1)*G$29)*($D$26*$AY44+(1-$D$26)*G$28),"") | H99: =IFERROR(H44*$AX44*(1+($AZ44-1)*H$29)*($D$26*$AY44+(1-$D$26)*H$28),"") | I99: =IFERROR(I44*$AX44*(1+($AZ44-1)*I$29)*($D$26*$AY44+(1-$D$26)*I$28),"") | J99: =IFERROR(J44*$AX44*(1+($AZ44-1)*J$29)*($D$26*$AY44+(1-$D$26)*J$28),"") | K99: =IFERROR(K44*$AX44*(1+($AZ44-1)*K$29)*($D$26*$AY44+(1-$D$26)*K$28),"") | L99: =IFERROR(L44*$AX44*(1+($AZ44-1)*L$29)*($D$26*$AY44+(1-$D$26)*L$28),"") | ... S99: =IFERROR(S44*$AX44*(1+($AZ44-1)*S$29)*($D$26*$AY44+(1-$D$26)*S$28),"")
A100: 20250428800076 | B100: CONT | C100: 2 | D100: 컨테이너선 2척 | R100: =IFERROR(R45*$AX45*(1+($AZ45-1)*R$29)*($D$26*$AY45+(1-$D$26)*R$28),"") | S100: =IFERROR(S45*$AX45*(1+($AZ45-1)*S$29)*($D$26*$AY45+(1-$D$26)*S$28),"") | T100: =IFERROR(T45*$AX45*(1+($AZ45-1)*T$29)*($D$26*$AY45+(1-$D$26)*T$28),"") | U100: =IFERROR(U45*$AX45*(1+($AZ45-1)*U$29)*($D$26*$AY45+(1-$D$26)*U$28),"") | V100: =IFERROR(V45*$AX45*(1+($AZ45-1)*V$29)*($D$26*$AY45+(1-$D$26)*V$28),"") | W100: =IFERROR(W45*$AX45*(1+($AZ45-1)*W$29)*($D$26*$AY45+(1-$D$26)*W$28),"") | X100: =IFERROR(X45*$AX45*(1+($AZ45-1)*X$29)*($D$26*$AY45+(1-$D$26)*X$28),"") | Y100: =IFERROR(Y45*$AX45*(1+($AZ45-1)*Y$29)*($D$26*$AY45+(1-$D$26)*Y$28),"") | ... AC100: =IFERROR(AC45*$AX45*(1+($AZ45-1)*AC$29)*($D$26*$AY45+(1-$D$26)*AC$28),"")
A101: 20250618800387 | B101: OTHER | D101: 블록, 기자재 및 설계
A102: 20250618800388 | B102: OTHER | D102: 블록 및 기자재
A103: 20250818800096 | B103: LNGC | C103: 2 | D103: LNG운반선 2척 | S103: =IFERROR(S48*$AX48*(1+($AZ48-1)*S$29)*($D$26*$AY48+(1-$D$26)*S$28),"") | T103: =IFERROR(T48*$AX48*(1+($AZ48-1)*T$29)*($D$26*$AY48+(1-$D$26)*T$28),"") | U103: =IFERROR(U48*$AX48*(1+($AZ48-1)*U$29)*($D$26*$AY48+(1-$D$26)*U$28),"") | V103: =IFERROR(V48*$AX48*(1+($AZ48-1)*V$29)*($D$26*$AY48+(1-$D$26)*V$28),"") | W103: =IFERROR(W48*$AX48*(1+($AZ48-1)*W$29)*($D$26*$AY48+(1-$D$26)*W$28),"") | X103: =IFERROR(X48*$AX48*(1+($AZ48-1)*X$29)*($D$26*$AY48+(1-$D$26)*X$28),"") | Y103: =IFERROR(Y48*$AX48*(1+($AZ48-1)*Y$29)*($D$26*$AY48+(1-$D$26)*Y$28),"") | Z103: =IFERROR(Z48*$AX48*(1+($AZ48-1)*Z$29)*($D$26*$AY48+(1-$D$26)*Z$28),"") | ... AC103: =IFERROR(AC48*$AX48*(1+($AZ48-1)*AC$29)*($D$26*$AY48+(1-$D$26)*AC$28),"")
...

Sheet 시나리오
C1: 신규수주 시나리오(억원) — subQ 기준값 ± (시나리오 신규 − base 신규) × OPM | E1: 3Q26 | F1: 4Q26 | G1: 2026 | H1: 1Q27 | I1: 2Q27 | J1: 3Q27 | K1: 4Q27 | L1: 2027 | M1: 1Q28 | N1: 2Q28 | O1: 3Q28 | P1: 4Q28 | Q1: 2028
A2: 출처: forecast_panel.json.gz scenarios.{conservative,base,optimistic}.quarterly[].new_order_revenue (KRW_million → 억원 ÷100) — 공시 수주 체결 분기별 상계 후(net_panel) · calibrated=False · 행(subQ)에 포함된 시나리오: base. 보수/낙관/기존만 은 합산하지 않는다. 모델 산출값 — 목표주가·추천 아님
A3: 매출 = 기존(선표+잔고 소진+기타) + 시나리오 신규수주 매출; 영업이익 = 행 영업이익 + (시나리오 신규 − base 신규) × base OPM 경로. 보수/낙관·existing_only 는 행에 합산하지 않음(base 는 행과 동일). 모델 산출값 — 목표주가·추천 아님 | E3: 1 | F3: 2 | G3: 3 | H3: 4 | I3: 5 | J3: 6 | K3: 7 | L3: 8 | M3: 9 | N3: 10 | O3: 11 | P3: 12 | Q3: 13
E4: 2026.09 | F4: 2026.12 | G4: 2026.12A | H4: 2027.03 | I4: 2027.06 | J4: 2027.09 | K4: 2027.12 | L4: 2027.12A | M4: 2028.03 | N4: 2028.06 | O4: 2028.09 | P4: 2028.12 | Q4: 2028.12A
A5: base | D5: 기준(base — subQ 행에 포함) — 행에 포함
A6: scn:base:신규수주매출 | C6: 억원 | D6: 신규수주 매출(억원) — subQ 매출조선신규 참조 | E6: =subQ!AC39 | F6: =subQ!AD39 | G6: =SUM(E6:F6) | H6: =subQ!AF39 | I6: =subQ!AG39 | J6: =subQ!AH39 | K6: =subQ!AI39 | L6: =SUM(H6:K6) | M6: =subQ!AK39 | N6: =subQ!AL39 | O6: =subQ!AM39 | P6: =subQ!AN39 | Q6: =SUM(M6:P6)
A7: scn:base:매출액 | C7: 억원 | D7: 매출액 = subQ 매출액 − base 신규 + 이 시나리오 신규 | E7: =IFERROR(subQ!AC5-E6+E6,"") | F7: =IFERROR(subQ!AD5-F6+F6,"") | G7: =IFERROR(SUM(E7:F7)+subQ!AA5+subQ!AB5,"") | H7: =IFERROR(subQ!AF5-H6+H6,"") | I7: =IFERROR(subQ!AG5-I6+I6,"") | J7: =IFERROR(subQ!AH5-J6+J6,"") | K7: =IFERROR(subQ!AI5-K6+K6,"") | L7: =IFERROR(SUM(H7:K7),"") | M7: =IFERROR(subQ!AK5-M6+M6,"") | N7: =IFERROR(subQ!AL5-N6+N6,"") | O7: =IFERROR(subQ!AM5-O6+O6,"") | P7: =IFERROR(subQ!AN5-P6+P6,"") | Q7: =IFERROR(SUM(M7:P7),"")
A8: scn:base:영업이익 | C8: 억원 | D8: 영업이익 = subQ 영업이익 + (이 시나리오 신규 − base 신규) × OPM(변수 드라이버) | E8: =IFERROR(subQ!AC9+(E6-E6)*변수!AC42,"") | F8: =IFERROR(subQ!AD9+(F6-F6)*변수!AD42,"") | G8: =IFERROR(SUM(E8:F8)+subQ!AA9+subQ!AB9,"") | H8: =IFERROR(subQ!AF9+(H6-H6)*변수!AF42,"") | I8: =IFERROR(subQ!AG9+(I6-I6)*변수!AG42,"") | J8: =IFERROR(subQ!AH9+(J6-J6)*변수!AH42,"") | K8: =IFERROR(subQ!AI9+(K6-K6)*변수!AI42,"") | L8: =IFERROR(SUM(H8:K8),"") | M8: =IFERROR(subQ!AK9+(M6-M6)*변수!AK42,"") | N8: =IFERROR(subQ!AL9+(N6-N6)*변수!AL42,"") | O8: =IFERROR(subQ!AM9+(O6-O6)*변수!AM42,"") | P8: =IFERROR(subQ!AN9+(P6-P6)*변수!AN42,"") | Q8: =IFERROR(SUM(M8:P8),"")
A9: scn:base:OPM | C9: % | D9: OPM | E9: =IFERROR(E8/E7,"") | F9: =IFERROR(F8/F7,"") | G9: =IFERROR(G8/G7,"") | H9: =IFERROR(H8/H7,"") | I9: =IFERROR(I8/I7,"") | J9: =IFERROR(J8/J7,"") | K9: =IFERROR(K8/K7,"") | L9: =IFERROR(L8/L7,"") | ... Q9: =IFERROR(Q8/Q7,"")
A11: existing_only | D11: 기존 잔고만(신규수주 0)
A12: scn:existing_only:신규수주매출 | C12: 억원 | D12: 신규수주 매출(억원) — 패널 값(노란, 가정) | E12: 0 | F12: 0 | G12: =SUM(E12:F12) | H12: 0 | I12: 0 | J12: 0 | K12: 0 | L12: =SUM(H12:K12) | M12: 0 | N12: 0 | O12: 0 | P12: 0 | Q12: =SUM(M12:P12)
A13: scn:existing_only:매출액 | C13: 억원 | D13: 매출액 = subQ 매출액 − base 신규 + 이 시나리오 신규 | E13: =IFERROR(subQ!AC5-E6+E12,"") | F13: =IFERROR(subQ!AD5-F6+F12,"") | G13: =IFERROR(SUM(E13:F13)+subQ!AA5+subQ!AB5,"") | H13: =IFERROR(subQ!AF5-H6+H12,"") | I13: =IFERROR(subQ!AG5-I6+I12,"") | J13: =IFERROR(subQ!AH5-J6+J12,"") | K13: =IFERROR(subQ!AI5-K6+K12,"") | L13: =IFERROR(SUM(H13:K13),"") | M13: =IFERROR(subQ!AK5-M6+M12,"") | N13: =IFERROR(subQ!AL5-N6+N12,"") | O13: =IFERROR(subQ!AM5-O6+O12,"") | P13: =IFERROR(subQ!AN5-P6+P12,"") | Q13: =IFERROR(SUM(M13:P13),"")
A14: scn:existing_only:영업이익 | C14: 억원 | D14: 영업이익 = subQ 영업이익 + (이 시나리오 신규 − base 신규) × OPM(변수 드라이버) | E14: =IFERROR(subQ!AC9+(E12-E6)*변수!AC42,"") | F14: =IFERROR(subQ!AD9+(F12-F6)*변수!AD42,"") | G14: =IFERROR(SUM(E14:F14)+subQ!AA9+subQ!AB9,"") | H14: =IFERROR(subQ!AF9+(H12-H6)*변수!AF42,"") | I14: =IFERROR(subQ!AG9+(I12-I6)*변수!AG42,"") | J14: =IFERROR(subQ!AH9+(J12-J6)*변수!AH42,"") | K14: =IFERROR(subQ!AI9+(K12-K6)*변수!AI42,"") | L14: =IFERROR(SUM(H14:K14),"") | M14: =IFERROR(subQ!AK9+(M12-M6)*변수!AK42,"") | N14: =IFERROR(subQ!AL9+(N12-N6)*변수!AL42,"") | O14: =IFERROR(subQ!AM9+(O12-O6)*변수!AM42,"") | P14: =IFERROR(subQ!AN9+(P12-P6)*변수!AN42,"") | Q14: =IFERROR(SUM(M14:P14),"")
A15: scn:existing_only:OPM | C15: % | D15: OPM | E15: =IFERROR(E14/E13,"") | F15: =IFERROR(F14/F13,"") | G15: =IFERROR(G14/G13,"") | H15: =IFERROR(H14/H13,"") | I15: =IFERROR(I14/I13,"") | J15: =IFERROR(J14/J13,"") | K15: =IFERROR(K14/K13,"") | L15: =IFERROR(L14/L13,"") | ... Q15: =IFERROR(Q14/Q13,"")
A17: conservative | D17: 보수
A18: scn:conservative:신규수주매출 | C18: 억원 | D18: 신규수주 매출(억원) — 패널 값(노란, 가정) | E18: 0 | F18: 0 | G18: =SUM(E18:F18) | H18: 202.96 | I18: 896.53 | J18: 2105.95 | K18: 3703.88 | L18: =SUM(H18:K18) | M18: 5563.38 | N18: 7572.18 | O18: 9626.3 | P18: 11615.32 | Q18: =SUM(M18:P18)
A19: scn:conservative:매출액 | C19: 억원 | D19: 매출액 = subQ 매출액 − base 신규 + 이 시나리오 신규 | E19: =IFERROR(subQ!AC5-E6+E18,"") | F19: =IFERROR(subQ!AD5-F6+F18,"") | G19: =IFERROR(SUM(E19:F19)+subQ!AA5+subQ!AB5,"") | H19: =IFERROR(subQ!AF5-H6+H18,"") | I19: =IFERROR(subQ!AG5-I6+I18,"") | J19: =IFERROR(subQ!AH5-J6+J18,"") | K19: =IFERROR(subQ!AI5-K6+K18,"") | L19: =IFERROR(SUM(H19:K19),"") | M19: =IFERROR(subQ!AK5-M6+M18,"") | N19: =IFERROR(subQ!AL5-N6+N18,"") | O19: =IFERROR(subQ!AM5-O6+O18,"") | P19: =IFERROR(subQ!AN5-P6+P18,"") | Q19: =IFERROR(SUM(M19:P19),"")
A20: scn:conservative:영업이익 | C20: 억원 | D20: 영업이익 = subQ 영업이익 + (이 시나리오 신규 − base 신규) × OPM(변수 드라이버) | E20: =IFERROR(subQ!AC9+(E18-E6)*변수!AC42,"") | F20: =IFERROR(subQ!AD9+(F18-F6)*변수!AD42,"") | G20: =IFERROR(SUM(E20:F20)+subQ!AA9+subQ!AB9,"") | H20: =IFERROR(subQ!AF9+(H18-H6)*변수!AF42,"") | I20: =IFERROR(subQ!AG9+(I18-I6)*변수!AG42,"") | J20: =IFERROR(subQ!AH9+(J18-J6)*변수!AH42,"") | K20: =IFERROR(subQ!AI9+(K18-K6)*변수!AI42,"") | L20: =IFERROR(SUM(H20:K20),"") | M20: =IFERROR(subQ!AK9+(M18-M6)*변수!AK42,"") | N20: =IFERROR(subQ!AL9+(N18-N6)*변수!AL42,"") | O20: =IFERROR(subQ!AM9+(O18-O6)*변수!AM42,"") | P20: =IFERROR(subQ!AN9+(P18-P6)*변수!AN42,"") | Q20: =IFERROR(SUM(M20:P20),"")
A21: scn:conservative:OPM | C21: % | D21: OPM | E21: =IFERROR(E20/E19,"") | F21: =IFERROR(F20/F19,"") | G21: =IFERROR(G20/G19,"") | H21: =IFERROR(H20/H19,"") | I21: =IFERROR(I20/I19,"") | J21: =IFERROR(J20/J19,"") | K21: =IFERROR(K20/K19,"") | L21: =IFERROR(L20/L19,"") | ... Q21: =IFERROR(Q20/Q19,"")
A23: optimistic | D23: 낙관
A24: scn:optimistic:신규수주매출 | C24: 억원 | D24: 신규수주 매출(억원) — 패널 값(노란, 가정) | E24: 0 | F24: 381.61 | G24: =SUM(E24:F24) | H24: 1961.25 | I24: 5087.17 | J24: 9398.88 | K24: 14349.92 | L24: =SUM(H24:K24) | M24: 19559.68 | N24: 24868.49 | O24: 30101.56 | P24: 34988.72 | Q24: =SUM(M24:P24)
A25: scn:optimistic:매출액 | C25: 억원 | D25: 매출액 = subQ 매출액 − base 신규 + 이 시나리오 신규 | E25: =IFERROR(subQ!AC5-E6+E24,"") | F25: =IFERROR(subQ!AD5-F6+F24,"") | G25: =IFERROR(SUM(E25:F25)+subQ!AA5+subQ!AB5,"") | H25: =IFERROR(subQ!AF5-H6+H24,"") | I25: =IFERROR(subQ!AG5-I6+I24,"") | J25: =IFERROR(subQ!AH5-J6+J24,"") | K25: =IFERROR(subQ!AI5-K6+K24,"") | L25: =IFERROR(SUM(H25:K25),"") | M25: =IFERROR(subQ!AK5-M6+M24,"") | N25: =IFERROR(subQ!AL5-N6+N24,"") | O25: =IFERROR(subQ!AM5-O6+O24,"") | P25: =IFERROR(subQ!AN5-P6+P24,"") | Q25: =IFERROR(SUM(M25:P25),"")
A26: scn:optimistic:영업이익 | C26: 억원 | D26: 영업이익 = subQ 영업이익 + (이 시나리오 신규 − base 신규) × OPM(변수 드라이버) | E26: =IFERROR(subQ!AC9+(E24-E6)*변수!AC42,"") | F26: =IFERROR(subQ!AD9+(F24-F6)*변수!AD42,"") | G26: =IFERROR(SUM(E26:F26)+subQ!AA9+subQ!AB9,"") | H26: =IFERROR(subQ!AF9+(H24-H6)*변수!AF42,"") | I26: =IFERROR(subQ!AG9+(I24-I6)*변수!AG42,"") | J26: =IFERROR(subQ!AH9+(J24-J6)*변수!AH42,"") | K26: =IFERROR(subQ!AI9+(K24-K6)*변수!AI42,"") | L26: =IFERROR(SUM(H26:K26),"") | M26: =IFERROR(subQ!AK9+(M24-M6)*변수!AK42,"") | N26: =IFERROR(subQ!AL9+(N24-N6)*변수!AL42,"") | O26: =IFERROR(subQ!AM9+(O24-O6)*변수!AM42,"") | P26: =IFERROR(subQ!AN9+(P24-P6)*변수!AN42,"") | Q26: =IFERROR(SUM(M26:P26),"")
A27: scn:optimistic:OPM | C27: % | D27: OPM | E27: =IFERROR(E26/E25,"") | F27: =IFERROR(F26/F25,"") | G27: =IFERROR(G26/G25,"") | H27: =IFERROR(H26/H25,"") | I27: =IFERROR(I26/I25,"") | J27: =IFERROR(J26/J25,"") | K27: =IFERROR(K26/K25,"") | L27: =IFERROR(L26/L25,"") | ... Q27: =IFERROR(Q26/Q25,"")

Sheet 분기
C1: 이름: 분기H — subQ 를 이름으로 VLOOKUP(억원) | E1: 4Q21 | F1: 1Q22 | G1: 2Q22 | H1: 3Q22 | I1: 4Q22 | J1: 1Q23 | K1: 2Q23 | L1: 3Q23 | M1: 4Q23 | N1: 1Q24 | O1: 2Q24 | P1: 3Q24 | Q1: 4Q24 | R1: 1Q25 | S1: 2Q25 | T1: 3Q25 | U1: 4Q25 | V1: 1Q26 | W1: 2Q26 | X1: 3Q26 | Y1: 4Q26 | Z1: 1Q27 | AA1: 2Q27 | AB1: 3Q27 | AC1: 4Q27 | AD1: 1Q28 | AE1: 2Q28 | AF1: 3Q28 | AG1: 4Q28
C2: 종가: | D2: =변수!D47
C3: 기준일: | D3: 20261019 | E3: 1 | F3: 2 | G3: 3 | H3: 4 | I3: 5 | J3: 6 | K3: 7 | L3: 8 | M3: 9 | N3: 10 | O3: 11 | P3: 12 | Q3: 13 | R3: 14 | S3: 15 | T3: 16 | U3: 17 | V3: 18 | W3: 19 | X3: 20 | Y3: 21 | Z3: 22 | AA3: 23 | AB3: 24 | AC3: 25 | AD3: 26 | AE3: 27 | AF3: 28 | AG3: 29
E4: 2021.12 | F4: 2022.03 | G4: 2022.06 | H4: 2022.09 | I4: 2022.12 | J4: 2023.03 | K4: 2023.06 | L4: 2023.09 | M4: 2023.12 | N4: 2024.03 | O4: 2024.06 | P4: 2024.09 | Q4: 2024.12 | R4: 2025.03 | S4: 2025.06 | T4: 2025.09 | U4: 2025.12 | V4: 2026.03 | W4: 2026.06 | X4: 2026.09 | Y4: 2026.12 | Z4: 2027.03 | AA4: 2027.06 | AB4: 2027.09 | AC4: 2027.12 | AD4: 2028.03 | AE4: 2028.06 | AF4: 2028.09 | AG4: 2028.12
A5: 매출액 | D5: 매출액 | E5: =IFERROR(VLOOKUP($A5,subQ,MATCH(E$1,SUBQH,0),0),"") | F5: =IFERROR(VLOOKUP($A5,subQ,MATCH(F$1,SUBQH,0),0),"") | G5: =IFERROR(VLOOKUP($A5,subQ,MATCH(G$1,SUBQH,0),0),"") | H5: =IFERROR(VLOOKUP($A5,subQ,MATCH(H$1,SUBQH,0),0),"") | I5: =IFERROR(VLOOKUP($A5,subQ,MATCH(I$1,SUBQH,0),0),"") | J5: =IFERROR(VLOOKUP($A5,subQ,MATCH(J$1,SUBQH,0),0),"") | K5: =IFERROR(VLOOKUP($A5,subQ,MATCH(K$1,SUBQH,0),0),"") | L5: =IFERROR(VLOOKUP($A5,subQ,MATCH(L$1,SUBQH,0),0),"") | ... AG5: =IFERROR(VLOOKUP($A5,subQ,MATCH(AG$1,SUBQH,0),0),"")
