Workbook
Name 변수H: 변수!$C$1:$AO$1
Name 환율: 변수!$C$6:$AO$13
Name BS연결H: BS연결!$C$1:$AO$1
Name BS연결: BS연결!$C$5:$AO$104
Name BS별도H: BS별도!$C$1:$AO$1
Name BS별도: BS별도!$C$5:$AO$92
Name SUBQH: subQ!$A$1:$AO$1
Name subQ: subQ!$A$5:$AO$40

Sheet README
A1: HD현대미포(010620) 실적 모델 — ARGUS 한국조선
A2: 기준 분기 2025Q3 · 마지막 실적 2025Q3 · 생성 2026-10-11
A3: 모든 수치는 모델 산출값(DART 공개 재무제표 + 우리 추정)이다 — 목표주가·투자 추천 아님. 참고용 · 투자조언 아님.
A5: 시트
A6: 변수 가정 시계열. 환율 8행(ECB via frankfurter — L2 fx.json; 추정 분기 = 노란 가정), 추정 드라이버(노란 셀 = 모델값에서 역산한 가정, 바꾸면 재계산; 연녹 셀 = 3절 스칼라 참조 수식), 3절 스칼라 가정(세율·판관비율·지배주주비중·이자율·종가·PER 밴드·COE·외화 순노출·헤지비율)
A7: BS연결/BS별도 FnGuide 계정명 × 기간 값 덤프(백만원). 행1 분기라벨, 행4 YYYY.MM / YYYY.12A. 이름정의 BS연결H·BS연결(계정명 C열부터)
A8: subQ 분기 서브모델(억원 = 백만원/100). 확정 행: =IFERROR(VLOOKUP($D행,BS연결,MATCH(E$1,BS연결H,0),0)/100,"") 추정 행: 변수 시트 가정 셀 참조 수식. 외환손익·파생상품손익은 BS 계정 합·차, 기타금융손익은 잔차, OPM·EPS·BPS·PER·PBR 은 파생 수식
A9: SLS 선표(조선사만, sls json 있을 때): 요약 행(sls 저장값) + 계약별 스케줄(백만$) × (헤지비율 × 헤지환율 + (1−헤지비율) × 건조시점 환율[변수 원/달러(평균)]) → 원화 수식 블록 → 합계 행이 subQ 매출조선에 연결
A10: 시나리오 신규수주 보수/기준/낙관(forecast_panel 패널, 모델에 scenarios 가 있을 때만): 매출액·영업이익 = subQ 기준값 ± (시나리오 신규 − base 신규) × OPM. base 만 subQ 행에 포함, 나머지는 합산 안 함
A11: 분기/연간예상 subQ 를 이름(A열 key)으로 VLOOKUP 한 보고서 표(억원)
A12: TP PER 밴드 × 12M fwd EPS, PBR = ROE/COE × BPS — 모델 산출값 구간, 목표주가·추천 아님
A13: 외화 환율 QoQ, 외화 순노출 × Δ기말환율 → 환관련손익 추정
... A34: 백테스트: {"freeze": "2025Q2", "horizon": 4, "revenue_wape_pct": 3.5, "op_wape_pct": 85.0, "n": 1, "note": "실측 1분기만 비교(나머지는 실적 없음 — 추정 vs 추정은 세지 않음) · 단일 회사 — 통계 아님", "driver_at_freeze": "trend_seasonal", "selection_oos_at_freeze": null, "frozen_inputs": "fin(연결/별도)·고객 조선사 모델·지주 자회사 모델은 2025Q2 까지의 분기만; 선표는 체결일 ≤ 2025Q2 말일 계약(원장 최신 금액·코호트 등급, 환산 없음); 잔고는 yards_cache 2025Q2; 시세·환율 forward·prices·forecast_panel 신규수주 미사용. 고객 가중치(suppliers.json 언급 비중)와 합병 체인링크는 현재 지식; 고객 연동 채택은 동결 모델 안에서도 자기 la−4분기 OOS 규칙(selection_oos_at_freeze)", "detail": [{"q": "2025Q3", "rev_pred": 12543.01, "rev_act": 13003.49, "op_pred": 301.93, "op_act": 2008.07}]}

Sheet 변수
C1: 이름: 변수H | E1: 4Q21 | F1: 2021 | G1: 1Q22 | H1: 2Q22 | I1: 3Q22 | J1: 4Q22 | K1: 2022 | L1: 1Q23 | M1: 2Q23 | N1: 3Q23 | O1: 4Q23 | P1: 2023 | Q1: 1Q24 | R1: 2Q24 | S1: 3Q24 | T1: 4Q24 | U1: 2024 | V1: 1Q25 | W1: 2Q25 | X1: 3Q25 | Y1: 4Q25 | Z1: 2025 | AA1: 1Q26 | AB1: 2Q26 | AC1: 3Q26 | AD1: 4Q26 | AE1: 2026 | AF1: 1Q27 | AG1: 2Q27 | AH1: 3Q27 | AI1: 4Q27 | AJ1: 2027 | AK1: 1Q28 | AL1: 2Q28 | AM1: 3Q28 | AN1: 4Q28 | AO1: 2028
A2: 가정 시계열 — 노란 셀은 추정 가정(모델값에서 역산), 연녹 셀은 3절 스칼라 참조 수식. 바꾸면 subQ·분기·연간예상·TP·시나리오가 재계산됩니다.
E3: 1 | F3: 2 | G3: 3 | H3: 4 | I3: 5 | J3: 6 | K3: 7 | L3: 8 | M3: 9 | N3: 10 | O3: 11 | P3: 12 | Q3: 13 | R3: 14 | S3: 15 | T3: 16 | U3: 17 | V3: 18 | W3: 19 | X3: 20 | Y3: 21 | Z3: 22 | AA3: 23 | AB3: 24 | AC3: 25 | AD3: 26 | AE3: 27 | AF3: 28 | AG3: 29 | AH3: 30 | AI3: 31 | AJ3: 32 | AK3: 33 | AL3: 34 | AM3: 35 | AN3: 36 | AO3: 37
E4: 2021.12 | F4: 2021.12A | G4: 2022.03 | H4: 2022.06 | I4: 2022.09 | J4: 2022.12 | K4: 2022.12A | L4: 2023.03 | M4: 2023.06 | N4: 2023.09 | O4: 2023.12 | P4: 2023.12A | Q4: 2024.03 | R4: 2024.06 | S4: 2024.09 | T4: 2024.12 | U4: 2024.12A | V4: 2025.03 | W4: 2025.06 | X4: 2025.09 | Y4: 2025.12 | Z4: 2025.12A | AA4: 2026.03 | AB4: 2026.06 | AC4: 2026.09 | AD4: 2026.12 | AE4: 2026.12A | AF4: 2027.03 | AG4: 2027.06 | AH4: 2027.09 | AI4: 2027.12 | AJ4: 2027.12A | AK4: 2028.03 | AL4: 2028.06 | AM4: 2028.09 | AN4: 2028.12 | AO4: 2028.12A
B5: 1. FX | C5: 이름: 환율
A6: USDKRW_avg | C6: 원/달러(평균) | E6: 1183.5 | F6: 1145.51 | G6: 1205.78 | H6: 1262.09 | I6: 1341.93 | J6: 1360.12 | K6: 1292.98 | L6: 1276.95 | M6: 1315.69 | N6: 1313.62 | O6: 1322.01 | P6: 1306.85 | Q6: 1330.14 | R6: 1371.28 | S6: 1356.22 | T6: 1396.3 | U6: 1363.53 | V6: 1452.28 | W6: 1398.52 | X6: 1386.95 | Y6: 1449.19 | Z6: 1421.52 | AA6: 1466.12 | AB6: 1501.75 | AC6: 1418.75 | AD6: 1345.14 | AE6: 1457.21 | AF6: 1341.49 | AG6: 1341.49 | AH6: 1341.49 | AI6: 1341.49 | AK6: 1341.49 | AL6: 1341.49 | AM6: 1341.49 | AN6: 1341.49
A7: USDKRW_end | C7: 원/달러(기말) | E7: 1188.75 | F7: 1188.75 | G7: 1213.74 | H7: 1301.24 | I7: 1436.9 | J7: 1260.16 | K7: 1260.16 | L7: 1305.99 | M7: 1321.44 | N7: 1345.35 | O7: 1297.43 | P7: 1297.43 | Q7: 1349.25 | R7: 1377.73 | S7: 1312.17 | T7: 1474.78 | U7: 1474.78 | V7: 1474.54 | W7: 1355.13 | X7: 1403.67 | Y7: 1444.2 | Z7: 1444.2 | AA7: 1524.8 | AB7: 1550.89 | AC7: 1355.4 | AD7: 1341.49 | AE7: 1341.49 | AF7: 1341.49 | AG7: 1341.49 | AH7: 1341.49 | AI7: 1341.49 | AK7: 1341.49 | AL7: 1341.49 | AM7: 1341.49 | AN7: 1341.49
A8: JPY100KRW_avg | C8: 원/100Y(평균) | E8: 1041.02 | F8: 1042.74 | G8: 1036.79 | H8: 972.23 | I8: 970.61 | J8: 961.03 | K8: 985.1 | L8: 964.89 | M8: 957.36 | N8: 909 | O8: 893.22 | P8: 931.11 | Q8: 896.29 | R8: 880.14 | S8: 909.35 | T8: 917.25 | U8: 900.92 | V8: 952.59 | W8: 967.92 | X8: 940.32 | Y8: 940.77 | Z8: 950.17 | AA8: 934.39 | AB8: 942.16 | AC8: 890.41 | AD8: 850.79 | AE8: 919.21 | AF8: 847.7 | AG8: 847.7 | AH8: 847.7 | AI8: 847.7 | AK8: 847.7 | AL8: 847.7 | AM8: 847.7 | AN8: 847.7
A9: JPY100KRW_end | C9: 원/100Y(기말) | E9: 1032.62 | F9: 1032.62 | G9: 996.83 | H9: 954.9 | I9: 993.29 | J9: 955.54 | K9: 955.54 | L9: 980.62 | M9: 913.67 | N9: 901.47 | O9: 917.04 | P9: 917.04 | Q9: 892.42 | R9: 857.76 | S9: 919.21 | T9: 939.65 | U9: 939.65 | V9: 986.84 | W9: 938.85 | X9: 948.49 | Y9: 921.81 | Z9: 921.81 | AA9: 955.99 | AB9: 954.75 | AC9: 863.31 | AD9: 847.7 | AE9: 847.7 | AF9: 847.7 | AG9: 847.7 | AH9: 847.7 | AI9: 847.7 | AK9: 847.7 | AL9: 847.7 | AM9: 847.7 | AN9: 847.7
A10: EURKRW_avg | C10: W/Euro(평균) | E10: 1353.32 | F10: 1354.06 | G10: 1352.29 | H10: 1343.31 | I10: 1350.63 | J10: 1386.07 | K10: 1358.07 | L10: 1369.93 | M10: 1432.41 | N10: 1429.41 | O10: 1420.91 | P10: 1412.88 | Q10: 1444.21 | R10: 1476.42 | S10: 1489.3 | T10: 1490.78 | U10: 1475.4 | V10: 1528.33 | W10: 1585.13 | X10: 1620.04 | Y10: 1686.02 | Z10: 1605.45 | AA10: 1715.47 | AB10: 1746.09 | AC10: 1631.97 | AD10: 1509.74 | AE10: 1689.95 | AF10: 1503.27 | AG10: 1503.27 | AH10: 1503.27 | AI10: 1503.27 | AK10: 1503.27 | AL10: 1503.27 | AM10: 1503.27 | AN10: 1503.27
A11: EURKRW_end | C11: W/Euro(기말) | E11: 1346.38 | F11: 1346.38 | G11: 1347.37 | H11: 1351.6 | I11: 1400.62 | J11: 1344.08 | K11: 1344.08 | L11: 1420.26 | M11: 1435.88 | N11: 1425.26 | O11: 1433.66 | P11: 1433.66 | Q11: 1458.68 | R11: 1474.86 | S11: 1469.1 | T11: 1532.14 | U11: 1532.14 | V11: 1594.72 | W11: 1588.22 | X11: 1648.04 | Y11: 1696.94 | Z11: 1696.94 | AA11: 1753.21 | AB11: 1767.09 | AC11: 1539.06 | AD11: 1503.27 | AE11: 1503.27 | AF11: 1503.27 | AG11: 1503.27 | AH11: 1503.27 | AI11: 1503.27 | AK11: 1503.27 | AL11: 1503.27 | AM11: 1503.27 | AN11: 1503.27
A12: CNYKRW_avg | C12: 원/중국원(평균) | E12: 185.14 | F12: 177.65 | G12: 189.93 | H12: 190.76 | I12: 195.79 | J12: 191.09 | K12: 191.93 | L12: 186.59 | M12: 187.45 | N12: 181.28 | O12: 182.86 | P12: 184.52 | Q12: 185.04 | R12: 189.35 | S12: 189.24 | T12: 194.24 | U12: 189.49 | V12: 199.63 | W12: 193.41 | X12: 193.79 | Y12: 204.38 | Z12: 197.8 | AA12: 211.75 | AB12: 220.8 | AC12: 210.43 | AD12: 200.69 | AE12: 213.75 | AF12: 200.46 | AG12: 200.46 | AH12: 200.46 | AI12: 200.46 | AK12: 200.46 | AL12: 200.46 | AM12: 200.46 | AN12: 200.46
A13: CNYKRW_end | C13: 원/중국원(기말) | E13: 187.13 | F13: 187.13 | G13: 191.38 | H13: 194.13 | I13: 201.92 | J13: 182.67 | K13: 182.67 | L13: 189.97 | M13: 181.8 | N13: 184.26 | O13: 182.61 | P13: 182.61 | Q13: 186.66 | R13: 189.7 | S13: 187.12 | T13: 202.04 | U13: 202.04 | V13: 203.3 | W13: 189.14 | X13: 197.16 | Y13: 206.28 | Z13: 206.28 | AA13: 220.97 | AB13: 228.56 | AC13: 202.16 | AD13: 200.46 | AE13: 200.46 | AF13: 200.46 | AG13: 200.46 | AH13: 200.46 | AI13: 200.46 | AK13: 200.46 | AL13: 200.46 | AM13: 200.46 | AN13: 200.46
B15: 2. 추정 드라이버 | C15: 실적 열 = subQ 실현값(수식), 추정 열 = 가정(노란 = 모델값 역산, 연녹 = 3절 스칼라 참조)
A16: drv:매출액 | B16: yoy | C16: 매출액 YoY | J16: =IFERROR(subQ!J5/subQ!E5-1,"") | L16: =IFERROR(subQ!L5/subQ!G5-1,"") | M16: =IFERROR(subQ!M5/subQ!H5-1,"") | N16: =IFERROR(subQ!N5/subQ!I5-1,"") | O16: =IFERROR(subQ!O5/subQ!J5-1,"") | Q16: =IFERROR(subQ!Q5/subQ!L5-1,"") | R16: =IFERROR(subQ!R5/subQ!M5-1,"") | S16: =IFERROR(subQ!S5/subQ!N5-1,"") | T16: =IFERROR(subQ!T5/subQ!O5-1,"") | V16: =IFERROR(subQ!V5/subQ!Q5-1,"") | W16: =IFERROR(subQ!W5/subQ!R5-1,"") | X16: =IFERROR(subQ!X5/subQ!S5-1,"") | Y16: 0.19292305 | AA16: 0.19292325 | AB16: 0.1929231 | AC16: 0.19292266 | AD16: 0.096461424 | AF16: 0.096460866 | AG16: 0.09646123 | AH16: 0.096461744 | AI16: 0.048230378 | AK16: 0.048230695 | AL16: 0.048230856 | AM16: 0.048230619 | AN16: 0.024115673
A17: drv:판관비 | B17: ratio | C17: 판관비율(/매출) | E17: =IFERROR(subQ!E8/subQ!E5,"") | F17: =IFERROR(subQ!F8/subQ!F5,"") | G17: =IFERROR(subQ!G8/subQ!G5,"") | H17: =IFERROR(subQ!H8/subQ!H5,"") | I17: =IFERROR(subQ!I8/subQ!I5,"") | J17: =IFERROR(subQ!J8/subQ!J5,"") | K17: =IFERROR(subQ!K8/subQ!K5,"") | L17: =IFERROR(subQ!L8/subQ!L5,"") | ... X17: =IFERROR(subQ!X8/subQ!X5,"") | Y17: =$D$46 | Z17: =IFERROR(subQ!Z8/subQ!Z5,"") | AA17: =$D$46 | AB17: =$D$46 | AC17: =$D$46 | AD17: =$D$46 | AE17: =IFERROR(subQ!AE8/subQ!AE5,"") | AF17: =$D$46 | AG17: =$D$46 | AH17: =$D$46 | AI17: =$D$46 | AJ17: =IFERROR(subQ!AJ8/subQ!AJ5,"") | AK17: =$D$46 | AL17: =$D$46 | AM17: =$D$46 | AN17: =$D$46 | AO17: =IFERROR(subQ!AO8/subQ!AO5,"")
A18: drv:영업이익 | B18: ratio | C18: 영업이익률(OPM) | E18: =IFERROR(subQ!E9/subQ!E5,"") | F18: =IFERROR(subQ!F9/subQ!F5,"") | G18: =IFERROR(subQ!G9/subQ!G5,"") | H18: =IFERROR(subQ!H9/subQ!H5,"") | I18: =IFERROR(subQ!I9/subQ!I5,"") | J18: =IFERROR(subQ!J9/subQ!J5,"") | K18: =IFERROR(subQ!K9/subQ!K5,"") | L18: =IFERROR(subQ!L9/subQ!L5,"") | ... X18: =IFERROR(subQ!X9/subQ!X5,"") | Y18: 0.032835274 | Z18: =IFERROR(subQ!Z9/subQ!Z5,"") | AA18: 0.03283506 | AB18: 0.032835077 | AC18: 0.03283553 | AD18: 0.03283528 | AE18: =IFERROR(subQ!AE9/subQ!AE5,"") | AF18: 0.032835131 | AG18: 0.032834959 | AH18: 0.032835366 | AI18: 0.032835146 | AJ18: =IFERROR(subQ!AJ9/subQ!AJ5,"") | AK18: 0.032835012 | AL18: 0.032834927 | AM18: 0.032835039 | AN18: 0.032835282 | AO18: =IFERROR(subQ!AO9/subQ!AO5,"")
A19: drv:외환손익 | B19: abs | C19: 외환손익 (가정, 억원) | E19: =subQ!E13 | F19: =subQ!F13 | G19: =subQ!G13 | H19: =subQ!H13 | I19: =subQ!I13 | J19: =subQ!J13 | K19: =subQ!K13 | L19: =subQ!L13 | ... X19: =subQ!X13 | Y19: 0 | Z19: =subQ!Z13 | AA19: 0 | AB19: 0 | AC19: 0 | AD19: 0 | AE19: =subQ!AE13 | AF19: 0 | AG19: 0 | AH19: 0 | AI19: 0 | AJ19: =subQ!AJ13 | AK19: 0 | AL19: 0 | AM19: 0 | AN19: 0 | AO19: =subQ!AO13
A20: drv:파생상품손익 | B20: abs | C20: 파생상품손익 (가정, 억원) | E20: =subQ!E14 | F20: =subQ!F14 | G20: =subQ!G14 | H20: =subQ!H14 | I20: =subQ!I14 | J20: =subQ!J14 | K20: =subQ!K14 | L20: =subQ!L14 | ... X20: =subQ!X14 | Y20: 0 | Z20: =subQ!Z14 | AA20: 0 | AB20: 0 | AC20: 0 | AD20: 0 | AE20: =subQ!AE14 | AF20: 0 | AG20: 0 | AH20: 0 | AI20: 0 | AJ20: =subQ!AJ14 | AK20: 0 | AL20: 0 | AM20: 0 | AN20: 0 | AO20: =subQ!AO14
A21: drv:기타금융손익 | B21: abs | C21: 기타금융손익 (가정, 억원) | E21: =subQ!E15 | F21: =subQ!F15 | G21: =subQ!G15 | H21: =subQ!H15 | I21: =subQ!I15 | J21: =subQ!J15 | K21: =subQ!K15 | L21: =subQ!L15 | ... X21: =subQ!X15 | Y21: 0 | Z21: =subQ!Z15 | AA21: 0 | AB21: 0 | AC21: 0 | AD21: 0 | AE21: =subQ!AE15 | AF21: 0 | AG21: 0 | AH21: 0 | AI21: 0 | AJ21: =subQ!AJ15 | AK21: 0 | AL21: 0 | AM21: 0 | AN21: 0 | AO21: =subQ!AO15
A22: drv:기타영업외손익 | B22: abs | C22: 기타영업외손익 (가정, 억원) | E22: =subQ!E16 | F22: =subQ!F16 | G22: =subQ!G16 | H22: =subQ!H16 | I22: =subQ!I16 | J22: =subQ!J16 | K22: =subQ!K16 | L22: =subQ!L16 | ... X22: =subQ!X16 | Y22: 0 | Z22: =subQ!Z16 | AA22: 0 | AB22: 0 | AC22: 0 | AD22: 0 | AE22: =subQ!AE16 | AF22: 0 | AG22: 0 | AH22: 0 | AI22: 0 | AJ22: =subQ!AJ16 | AK22: 0 | AL22: 0 | AM22: 0 | AN22: 0 | AO22: =subQ!AO16
A23: drv:법인세비용 | B23: tax | C23: 법인세율(/세전) — 법인세 = MAX(세전,0) × 세율 | E23: =IFERROR(subQ!E18/subQ!E17,"") | F23: =IFERROR(subQ!F18/subQ!F17,"") | G23: =IFERROR(subQ!G18/subQ!G17,"") | H23: =IFERROR(subQ!H18/subQ!H17,"") | I23: =IFERROR(subQ!I18/subQ!I17,"") | J23: =IFERROR(subQ!J18/subQ!J17,"") | K23: =IFERROR(subQ!K18/subQ!K17,"") | L23: =IFERROR(subQ!L18/subQ!L17,"") | ... X23: =IFERROR(subQ!X18/subQ!X17,"") | Y23: =$D$45 | Z23: =IFERROR(subQ!Z18/subQ!Z17,"") | AA23: =$D$45 | AB23: =$D$45 | AC23: =$D$45 | AD23: =$D$45 | AE23: =IFERROR(subQ!AE18/subQ!AE17,"") | AF23: =$D$45 | AG23: =$D$45 | AH23: =$D$45 | AI23: =$D$45 | AJ23: =IFERROR(subQ!AJ18/subQ!AJ17,"") | AK23: =$D$45 | AL23: =$D$45 | AM23: =$D$45 | AN23: =$D$45 | AO23: =IFERROR(subQ!AO18/subQ!AO17,"")
A24: drv:지배주주순이익 | B24: ratio | C24: 지배주주 비중(/당기순이익) | E24: =IFERROR(subQ!E20/subQ!E19,"") | F24: =IFERROR(subQ!F20/subQ!F19,"") | G24: =IFERROR(subQ!G20/subQ!G19,"") | H24: =IFERROR(subQ!H20/subQ!H19,"") | I24: =IFERROR(subQ!I20/subQ!I19,"") | J24: =IFERROR(subQ!J20/subQ!J19,"") | K24: =IFERROR(subQ!K20/subQ!K19,"") | L24: =IFERROR(subQ!L20/subQ!L19,"") | ... X24: =IFERROR(subQ!X20/subQ!X19,"") | Y24: =$D$47 | Z24: =IFERROR(subQ!Z20/subQ!Z19,"") | AA24: =$D$47 | AB24: =$D$47 | AC24: =$D$47 | AD24: =$D$47 | AE24: =IFERROR(subQ!AE20/subQ!AE19,"") | AF24: =$D$47 | AG24: =$D$47 | AH24: =$D$47 | AI24: =$D$47 | AJ24: =IFERROR(subQ!AJ20/subQ!AJ19,"") | AK24: =$D$47 | AL24: =$D$47 | AM24: =$D$47 | AN24: =$D$47 | AO24: =IFERROR(subQ!AO20/subQ!AO19,"")
A25: drv:부채총계 | B25: qoq | C25: 부채총계 QoQ | G25: =IFERROR(subQ!G22/subQ!E22-1,"") | H25: =IFERROR(subQ!H22/subQ!G22-1,"") | I25: =IFERROR(subQ!I22/subQ!H22-1,"") | J25: =IFERROR(subQ!J22/subQ!I22-1,"") | L25: =IFERROR(subQ!L22/subQ!J22-1,"") | M25: =IFERROR(subQ!M22/subQ!L22-1,"") | N25: =IFERROR(subQ!N22/subQ!M22-1,"") | O25: =IFERROR(subQ!O22/subQ!N22-1,"") | Q25: =IFERROR(subQ!Q22/subQ!O22-1,"") | R25: =IFERROR(subQ!R22/subQ!Q22-1,"") | S25: =IFERROR(subQ!S22/subQ!R22-1,"") | T25: =IFERROR(subQ!T22/subQ!S22-1,"") | V25: =IFERROR(subQ!V22/subQ!T22-1,"") | W25: =IFERROR(subQ!W22/subQ!V22-1,"") | X25: =IFERROR(subQ!X22/subQ!W22-1,"") | Y25: -2.5e-08 | AA25: 0 | AB25: 0 | AC25: 0 | AD25: 0 | AF25: 0 | AG25: 0 | AH25: 0 | AI25: 0 | AK25: 0 | AL25: 0 | AM25: 0 | AN25: 0
A26: drv:자본총계 | B26: roll | C26: 자본총계 기타변동(배당 등, 억원) | G26: =IFERROR(subQ!E23+subQ!G19-subQ!G23,"") | H26: =IFERROR(subQ!G23+subQ!H19-subQ!H23,"") | I26: =IFERROR(subQ!H23+subQ!I19-subQ!I23,"") | J26: =IFERROR(subQ!I23+subQ!J19-subQ!J23,"") | L26: =IFERROR(subQ!J23+subQ!L19-subQ!L23,"") | M26: =IFERROR(subQ!L23+subQ!M19-subQ!M23,"") | N26: =IFERROR(subQ!M23+subQ!N19-subQ!N23,"") | O26: =IFERROR(subQ!N23+subQ!O19-subQ!O23,"") | Q26: =IFERROR(subQ!O23+subQ!Q19-subQ!Q23,"") | R26: =IFERROR(subQ!Q23+subQ!R19-subQ!R23,"") | S26: =IFERROR(subQ!R23+subQ!S19-subQ!S23,"") | T26: =IFERROR(subQ!S23+subQ!T19-subQ!T23,"") | V26: =IFERROR(subQ!T23+subQ!V19-subQ!V23,"") | W26: =IFERROR(subQ!V23+subQ!W19-subQ!W23,"") | X26: =IFERROR(subQ!W23+subQ!X19-subQ!X23,"") | Y26: 0.002806108 | AA26: -0.001078958 | AB26: 283.17689 | AC26: 0.005629916 | AD26: 0.001086456 | AF26: 0.001173254 | AG26: 283.17455 | AH26: 0.004787964 | AI26: -0.004284398 | AK26: -0.003726089 | AL26: 283.17879 | AM26: -0.006460781 | AN26: 0.002151024
A27: drv:지배주주지분 | B27: roll | C27: 지배주주지분 기타변동(배당 등, 억원) | G27: =IFERROR(subQ!E24+subQ!G20-subQ!G24,"") | H27: =IFERROR(subQ!G24+subQ!H20-subQ!H24,"") | I27: =IFERROR(subQ!H24+subQ!I20-subQ!I24,"") | J27: =IFERROR(subQ!I24+subQ!J20-subQ!J24,"") | L27: =IFERROR(subQ!J24+subQ!L20-subQ!L24,"") | M27: =IFERROR(subQ!L24+subQ!M20-subQ!M24,"") | N27: =IFERROR(subQ!M24+subQ!N20-subQ!N24,"") | O27: =IFERROR(subQ!N24+subQ!O20-subQ!O24,"") | Q27: =IFERROR(subQ!O24+subQ!Q20-subQ!Q24,"") | R27: =IFERROR(subQ!Q24+subQ!R20-subQ!R24,"") | S27: =IFERROR(subQ!R24+subQ!S20-subQ!S24,"") | T27: =IFERROR(subQ!S24+subQ!T20-subQ!T24,"") | V27: =IFERROR(subQ!T24+subQ!V20-subQ!V24,"") | W27: =IFERROR(subQ!V24+subQ!W20-subQ!W24,"") | X27: =IFERROR(subQ!W24+subQ!X20-subQ!X24,"") | Y27: -0.003836385 | AA27: 0.00150822 | AB27: 283.17506 | AC27: -0.003643787 | AD27: 0.002376847 | AF27: -0.000156885 | AG27: 283.1697 | AH27: 0.001394517 | AI27: -0.00070735 | AK27: -0.006595615 | AL27: 283.17535 | AM27: -0.002641363 | AN27: -0.007052824
A28: drv:총차입금 | B28: qoq | C28: 총차입금 QoQ | G28: =IFERROR(subQ!G25/subQ!E25-1,"") | H28: =IFERROR(subQ!H25/subQ!G25-1,"") | I28: =IFERROR(subQ!I25/subQ!H25-1,"") | J28: =IFERROR(subQ!J25/subQ!I25-1,"") | L28: =IFERROR(subQ!L25/subQ!J25-1,"") | M28: =IFERROR(subQ!M25/subQ!L25-1,"") | N28: =IFERROR(subQ!N25/subQ!M25-1,"") | O28: =IFERROR(subQ!O25/subQ!N25-1,"") | Q28: =IFERROR(subQ!Q25/subQ!O25-1,"") | R28: =IFERROR(subQ!R25/subQ!Q25-1,"") | S28: =IFERROR(subQ!S25/subQ!R25-1,"") | T28: =IFERROR(subQ!T25/subQ!S25-1,"") | V28: =IFERROR(subQ!V25/subQ!T25-1,"") | W28: =IFERROR(subQ!W25/subQ!V25-1,"") | X28: =IFERROR(subQ!X25/subQ!W25-1,"") | Y28: 3.766e-06 | AA28: 0 | AB28: 0 | AC28: 0 | AD28: 0 | AF28: 0 | AG28: 0 | AH28: 0 | AI28: 0 | AK28: 0 | AL28: 0 | AM28: 0 | AN28: 0
A29: drv:순차입금 | B29: qoq | C29: 순차입금 QoQ | G29: =IFERROR(subQ!G26/subQ!E26-1,"") | H29: =IFERROR(subQ!H26/subQ!G26-1,"") | I29: =IFERROR(subQ!I26/subQ!H26-1,"") | J29: =IFERROR(subQ!J26/subQ!I26-1,"") | L29: =IFERROR(subQ!L26/subQ!J26-1,"") | M29: =IFERROR(subQ!M26/subQ!L26-1,"") | N29: =IFERROR(subQ!N26/subQ!M26-1,"") | O29: =IFERROR(subQ!O26/subQ!N26-1,"") | Q29: =IFERROR(subQ!Q26/subQ!O26-1,"") | R29: =IFERROR(subQ!R26/subQ!Q26-1,"") | S29: =IFERROR(subQ!S26/subQ!R26-1,"") | T29: =IFERROR(subQ!T26/subQ!S26-1,"") | V29: =IFERROR(subQ!V26/subQ!T26-1,"") | W29: =IFERROR(subQ!W26/subQ!V26-1,"") | X29: =IFERROR(subQ!X26/subQ!W26-1,"") | Y29: 0.1023188 | AA29: 0.078361537 | AB29: 0.025950686 | AC29: 0.077932569 | AD29: 0.086312002 | AF29: 0.067220142 | AG29: 0.026804075 | AH29: 0.067440209 | AI29: 0.072169434 | AK29: 0.057091116 | AL29: 0.024995617 | AM29: 0.057862798 | AN29: 0.061044144
A30: drv:이자발생자산 | B30: qoq | C30: 이자발생자산 QoQ | G30: =IFERROR(subQ!G27/subQ!E27-1,"") | H30: =IFERROR(subQ!H27/subQ!G27-1,"") | I30: =IFERROR(subQ!I27/subQ!H27-1,"") | J30: =IFERROR(subQ!J27/subQ!I27-1,"") | L30: =IFERROR(subQ!L27/subQ!J27-1,"") | M30: =IFERROR(subQ!M27/subQ!L27-1,"") | N30: =IFERROR(subQ!N27/subQ!M27-1,"") | O30: =IFERROR(subQ!O27/subQ!N27-1,"") | Q30: =IFERROR(subQ!Q27/subQ!O27-1,"") | R30: =IFERROR(subQ!R27/subQ!Q27-1,"") | S30: =IFERROR(subQ!S27/subQ!R27-1,"") | T30: =IFERROR(subQ!T27/subQ!S27-1,"") | V30: =IFERROR(subQ!V27/subQ!T27-1,"") | W30: =IFERROR(subQ!W27/subQ!V27-1,"") | X30: =IFERROR(subQ!X27/subQ!W27-1,"") | Y30: 0.079925717 | AA30: 0.062480722 | AB30: 0.021000772 | AC30: 0.063373229 | AD30: 0.071148197 | AF30: 0.056194932 | AG30: 0.022641672 | AH30: 0.057199294 | AI30: 0.061803313 | AK30: 0.049368091 | AL30: 0.021773399 | AM30: 0.050562579 | AN30: 0.053713223
A31: drv:현금및현금성자산 | B31: qoq | C31: 현금및현금성자산 QoQ | G31: =IFERROR(subQ!G28/subQ!E28-1,"") | H31: =IFERROR(subQ!H28/subQ!G28-1,"") | I31: =IFERROR(subQ!I28/subQ!H28-1,"") | J31: =IFERROR(subQ!J28/subQ!I28-1,"") | L31: =IFERROR(subQ!L28/subQ!J28-1,"") | M31: =IFERROR(subQ!M28/subQ!L28-1,"") | N31: =IFERROR(subQ!N28/subQ!M28-1,"") | O31: =IFERROR(subQ!O28/subQ!N28-1,"") | Q31: =IFERROR(subQ!Q28/subQ!O28-1,"") | R31: =IFERROR(subQ!R28/subQ!Q28-1,"") | S31: =IFERROR(subQ!S28/subQ!R28-1,"") | T31: =IFERROR(subQ!T28/subQ!S28-1,"") | V31: =IFERROR(subQ!V28/subQ!T28-1,"") | W31: =IFERROR(subQ!W28/subQ!V28-1,"") | X31: =IFERROR(subQ!X28/subQ!W28-1,"")
A32: drv:CAPEX | B32: yoy | C32: CAPEX YoY | J32: =IFERROR(subQ!J29/subQ!E29-1,"") | L32: =IFERROR(subQ!L29/subQ!G29-1,"") | M32: =IFERROR(subQ!M29/subQ!H29-1,"") | N32: =IFERROR(subQ!N29/subQ!I29-1,"") | O32: =IFERROR(subQ!O29/subQ!J29-1,"") | Q32: =IFERROR(subQ!Q29/subQ!L29-1,"") | R32: =IFERROR(subQ!R29/subQ!M29-1,"") | S32: =IFERROR(subQ!S29/subQ!N29-1,"") | T32: =IFERROR(subQ!T29/subQ!O29-1,"") | V32: =IFERROR(subQ!V29/subQ!Q29-1,"") | W32: =IFERROR(subQ!W29/subQ!R29-1,"") | X32: =IFERROR(subQ!X29/subQ!S29-1,"") | Y32: 0.089245143 | AA32: 0.13968947 | AB32: -0.075724154 | AC32: -0.24308534 | AD32: 0 | AF32: 0 | AG32: 0 | AH32: 0 | AI32: 0 | AK32: 0 | AL32: 0 | AM32: 0 | AN32: 0
A33: drv:영업활동현금흐름 | B33: yoy | C33: 영업활동현금흐름 YoY | J33: =IFERROR(subQ!J30/subQ!E30-1,"") | L33: =IFERROR(subQ!L30/subQ!G30-1,"") | M33: =IFERROR(subQ!M30/subQ!H30-1,"") | N33: =IFERROR(subQ!N30/subQ!I30-1,"") | O33: =IFERROR(subQ!O30/subQ!J30-1,"") | Q33: =IFERROR(subQ!Q30/subQ!L30-1,"") | R33: =IFERROR(subQ!R30/subQ!M30-1,"") | S33: =IFERROR(subQ!S30/subQ!N30-1,"") | T33: =IFERROR(subQ!T30/subQ!O30-1,"") | V33: =IFERROR(subQ!V30/subQ!Q30-1,"") | W33: =IFERROR(subQ!W30/subQ!R30-1,"") | X33: =IFERROR(subQ!X30/subQ!S30-1,"")
A34: drv:주식수 | B34: qoq | C34: 주식수 QoQ | G34: =IFERROR(subQ!G31/subQ!E31-1,"") | H34: =IFERROR(subQ!H31/subQ!G31-1,"") | I34: =IFERROR(subQ!I31/subQ!H31-1,"") | J34: =IFERROR(subQ!J31/subQ!I31-1,"") | L34: =IFERROR(subQ!L31/subQ!J31-1,"") | M34: =IFERROR(subQ!M31/subQ!L31-1,"") | N34: =IFERROR(subQ!N31/subQ!M31-1,"") | O34: =IFERROR(subQ!O31/subQ!N31-1,"") | Q34: =IFERROR(subQ!Q31/subQ!O31-1,"") | R34: =IFERROR(subQ!R31/subQ!Q31-1,"") | S34: =IFERROR(subQ!S31/subQ!R31-1,"") | T34: =IFERROR(subQ!T31/subQ!S31-1,"") | V34: =IFERROR(subQ!V31/subQ!T31-1,"") | W34: =IFERROR(subQ!W31/subQ!V31-1,"") | X34: =IFERROR(subQ!X31/subQ!W31-1,"") | Y34: 0 | AA34: 0 | AB34: 0 | AC34: 0 | AD34: 0 | AF34: 0 | AG34: 0 | AH34: 0 | AI34: 0 | AK34: 0 | AL34: 0 | AM34: 0 | AN34: 0
A35: drv:DPS | B35: abs | C35: DPS (가정, 원) | E35: =subQ!E34 | F35: =subQ!F34 | G35: =subQ!G34 | H35: =subQ!H34 | I35: =subQ!I34 | J35: =subQ!J34 | K35: =subQ!K34 | L35: =subQ!L34 | ... X35: =subQ!X34 | Y35: 710 | Z35: =subQ!Z34 | AD35: 710 | AE35: =subQ!AE34 | AI35: 710 | AJ35: =subQ!AJ34 | AN35: 710 | AO35: =subQ!AO34
B37: 3. 밸류에이션·스칼라 | C37: 노란 셀 = 가정. '연결' 표시는 추정 전 분기 수식이 이 셀을 참조한다는 뜻
A38: sc:종가 | C38: 종가 | E38: 원 — aikstockdata.com(금융위 확정종가 T+1)
A39: sc:기준일 | C39: 기준일 | E39: 종가 기준일
A40: sc:COE | C40: COE | D40: 0.09 | E40: 자기자본비용(가정) — TP 적정 PBR = ROE/COE
A41: sc:PER_lo | C41: PER_lo | D41: 10 | E41: PER 밴드 하단(배) — sector_default(레퍼런스 TP_PE PB 예시 10/15/20배; 과거 양(+)EPS 분기 0개 < 4)
A42: sc:PER_mid | C42: PER_mid | D42: 15 | E42: PER 밴드 중단(배)
A43: sc:PER_hi | C43: PER_hi | D43: 20 | E43: PER 밴드 상단(배)
A44: sc:EPS_Y1가중 | C44: EPS_Y1가중 | D44: 0.5 | E44: 12M fwd EPS = FY(last_actual연도)E × w + FY+1E × (1−w) — 기준 분기 2Q 이면 0.5(가정)
A45: sc:세율 | C45: 세율 | D45: 0.16169209 | E45: 연결 — 법인세 = MAX(세전,0) × 세율(역산, 재현 오차 ≤ 0.05억 · 모델 assumptions 0.1617) · 최근 12분기 유효세율 16.2%(5~27% 안 — 그대로)
A46: sc:판관비율 | C46: 판관비율 | D46: 0.033708049 | E46: 연결 — 판관비 = 매출액 × 판관비율(역산, 재현 오차 ≤ 0.05억 · 모델 assumptions 0.0337)
A47: sc:지배주주비중 | C47: 지배주주비중 | D47: 0.93546489 | E47: 연결 — 지배주주순이익 = 당기순이익 × 비중(역산, 재현 오차 ≤ 0.05억)
A48: sc:이자율_자산 | C48: 이자율_자산 | D48: 0.02546209 | E48: 연결 — 이자손익 = (전분기 이자발생자산 × 자산이자율 − 전분기 총차입금 × 부채이자율)/4(역산, 재현 오차 ≤ 0.05억 · 모델 assumptions 0.0255)
A49: sc:이자율_부채 | C49: 이자율_부채 | D49: 0.050454703 | E49: 연결 — 같은 수식의 부채 쪽(총차입금 행이 없으면 0)(역산, 재현 오차 ≤ 0.05억 · 모델 assumptions 0.0504)
A50: sc:배당성향 | C50: 배당성향 | D50: 0.2683 | E50: 배당성향(참고 — 모델은 직전 DPS 유지·Q2 지급 가정)
A51: sc:외화순노출_백만$ | C51: 외화순노출_백만$ | E51: 외화 순노출 × Δ기말환율 (외화 시트 방식) — 외화 순노출 미공시(face) → 0 + 표기
A52: sc:헤지비율 | C52: 헤지비율 | E52: sls 없음
A53: sc:헤지환율_약정 | C53: 헤지환율_약정 | E53: sls 없음

Sheet BS연결
B1: (백만원) | C1: 이름: BS연결H | E1: 4Q21 | F1: 2021 | G1: 1Q22 | H1: 2Q22 | I1: 3Q22 | J1: 4Q22 | K1: 2022 | L1: 1Q23 | M1: 2Q23 | N1: 3Q23 | O1: 4Q23 | P1: 2023 | Q1: 1Q24 | R1: 2Q24 | S1: 3Q24 | T1: 4Q24 | U1: 2024 | V1: 1Q25 | W1: 2Q25 | X1: 3Q25 | Y1: 4Q25 | Z1: 2025 | AA1: 1Q26 | AB1: 2Q26 | AC1: 3Q26 | AD1: 4Q26 | AE1: 2026 | AF1: 1Q27 | AG1: 2Q27 | AH1: 3Q27 | AI1: 4Q27 | AJ1: 2027 | AK1: 1Q28 | AL1: 2Q28 | AM1: 3Q28 | AN1: 4Q28 | AO1: 2028
B2: 연결 | D2: fin json(kship_fin.py)
B3: HD현대미포(연) | C3: UPDATE: 26-10-11 | E3: 1 | F3: 2 | G3: 3 | H3: 4 | I3: 5 | J3: 6 | K3: 7 | L3: 8 | M3: 9 | N3: 10 | O3: 11 | P3: 12 | Q3: 13 | R3: 14 | S3: 15 | T3: 16 | U3: 17 | V3: 18 | W3: 19 | X3: 20 | Y3: 21 | Z3: 22 | AA3: 23 | AB3: 24 | AC3: 25 | AD3: 26 | AE3: 27 | AF3: 28 | AG3: 29 | AH3: 30 | AI3: 31 | AJ3: 32 | AK3: 33 | AL3: 34 | AM3: 35 | AN3: 36 | AO3: 37
B4: Account Code | C4: AccountNAME | E4: 2021.12 | F4: 2021.12A | G4: 2022.03 | H4: 2022.06 | I4: 2022.09 | J4: 2022.12 | K4: 2022.12A | L4: 2023.03 | M4: 2023.06 | N4: 2023.09 | O4: 2023.12 | P4: 2023.12A | Q4: 2024.03 | R4: 2024.06 | S4: 2024.09 | T4: 2024.12 | U4: 2024.12A | V4: 2025.03 | W4: 2025.06 | X4: 2025.09 | Y4: 2025.12 | Z4: 2025.12A | AA4: 2026.03 | AB4: 2026.06 | AC4: 2026.09 | AD4: 2026.12 | AE4: 2026.12A | AF4: 2027.03 | AG4: 2027.06 | AH4: 2027.09 | AI4: 2027.12 | AJ4: 2027.12A | AK4: 2028.03 | AL4: 2028.06 | AM4: 2028.09 | AN4: 2028.12 | AO4: 2028.12A
A5: 1 | C5: 유동자산 | E5: 2046698.2 | F5: 2046698.2 | G5: 2342578.1 | H5: 2480297.2 | I5: 3049846.1 | J5: 2724476.1 | K5: 2724476.1 | L5: 2698711.6 | M5: 2638052.2 | N5: 2720335.7 | O5: 2799391.8 | P5: 2799391.8 | Q5: 2611902.6 | R5: 2556143.1 | S5: 2410367.3 | T5: 2786547.4 | U5: 2786547.4 | V5: 2898372.1 | W5: 2897881.1 | X5: 2891331.8
A6: 1 | C6: 현금및현금성자산 | E6: 400370.96 | F6: 400370.96 | G6: 615588.03 | H6: 577796.92 | I6: 426258.03 | J6: 490143.85 | K6: 490143.85 | L6: 364792.08 | M6: 381085.43 | N6: 424198.32 | O6: 310040.89 | P6: 310040.89 | Q6: 418212.43 | R6: 420994.36 | S6: 396603.6 | T6: 165096.21 | U6: 165096.21 | V6: 434009.49 | W6: 512816.28 | X6: 473564.11
A7: 1 | C7: 단기금융상품 | E7: 124527.77 | F7: 124527.77 | G7: 84000.51 | H7: 177001.29 | I7: 129001.48 | J7: 53001.73 | K7: 53001.73 | L7: 39554.07 | M7: 43042.35 | N7: 45990.68 | O7: 39080.73 | P7: 39080.73 | Q7: 33696.22 | R7: 38913.03 | S7: 42592.16 | T7: 38367.96 | U7: 38367.96 | V7: 34300.19 | W7: 41949.56 | X7: 47115.45
A8: 1 | C8: 단기금융자산 | E8: 154979.73 | F8: 154979.73 | G8: 125218.75 | H8: 255829.72 | I8: 284390.78 | J8: 125597.49 | K8: 125597.49 | L8: 107822.77 | M8: 101436.31 | N8: 111327.16 | O8: 87872.77 | P8: 87872.77 | Q8: 92807.27 | R8: 125317.45 | S8: 82253.71 | T8: 174224.62 | U8: 174224.62 | V8: 152810.05 | W8: 86446.08 | X8: 121971.47
A9: 1 | C9: 매출채권및기타채권 | E9: 47534.35 | F9: 47534.35 | G9: 189966.36 | H9: 103537.07 | I9: 241966.56 | J9: 87030.57 | K9: 87030.57 | L9: 77889.3 | M9: 49605.65 | N9: 79112.24 | O9: 164823.67 | P9: 164823.67 | Q9: 146455.76 | R9: 117121.82 | S9: 63301.88 | T9: 131232.52 | U9: 131232.52 | V9: 100782.8 | W9: 114511.86 | X9: 110957.5
A10: 1 | C10: 계약자산 | E10: 900692.64 | F10: 900692.64 | G10: 871255.87 | H10: 984525.23 | I10: 1356661.7 | J10: 1301215.9 | K10: 1301215.9 | L10: 1356700 | M10: 1322929.4 | N10: 1318559.9 | O10: 1442687.1 | P10: 1442687.1 | Q10: 1166462 | R10: 1011783.8 | S10: 940068.68 | T10: 1488564 | U10: 1488564 | V10: 1368532.1 | W10: 1249564.2 | X10: 1249293.1
A11: 1 | C11: 유동파생상품자산 | E11: 1664.05 | F11: 1664.05 | G11: 540.83 | H11: 2.69 | I11: 2.57 | J11: 29527.19 | K11: 29527.19 | L11: 11801.01 | M11: 10449.82 | N11: 3789.3 | O11: 15804.99 | P11: 15804.99 | Q11: 2382.6 | R11: 206.53 | S11: 10028.66 | T11: 185.35 | U11: 185.35 | V11: 16.69 | W11: 7654.67 | X11: 2577.2
A12: 1 | C12: 유동확정계약자산 | E12: 28787.91 | F12: 28787.91 | G12: 40677.41 | H12: 78825.74 | I12: 155386.73 | J12: 43068.57 | K12: 43068.57 | L12: 56467.69 | M12: 47944.14 | N12: 61547.18 | O12: 32987.05 | P12: 32987.05 | Q12: 56728.45 | R12: 86197.89 | S12: 29632.89 | T12: 135671.31 | U12: 135671.31 | V12: 118493.17 | W12: 36841.85 | X12: 72278.82
A13: 1 | C13: 재고자산 | E13: 265534.01 | F13: 265534.01 | G13: 268954.88 | H13: 251077.48 | I13: 324082.25 | J13: 292593.55 | K13: 292593.55 | L13: 294033.49 | M13: 276675.46 | N13: 234517.92 | O13: 230175.93 | P13: 230175.93 | Q13: 264411.92 | R13: 281611.38 | S13: 276882.83 | T13: 270834.34 | U13: 270834.34 | V13: 266344.85 | W13: 255118.38 | X13: 277576.08
A14: 1 | C14: 기타유동자산 | E14: 277586.48 | F14: 277586.48 | G14: 271594.23 | H14: 307530.82 | I14: 416486.78 | J14: 427894.77 | K14: 427894.77 | L14: 497474.01 | M14: 506319.97 | N14: 552620.16 | O14: 563791.49 | P14: 563791.49 | Q14: 523553.2 | R14: 599314.26 | S14: 651256.6 | T14: 556595.69 | U14: 556595.69 | V14: 575892.78 | W14: 679424.3 | X14: 657969.54
A15: 1 | C15: 비유동자산 | E15: 1831622.1 | F15: 1831622.1 | G15: 1855833.6 | H15: 1922888.8 | I15: 2019039 | J15: 2023769.4 | K15: 2023769.4 | L15: 2035377.6 | M15: 2068971.2 | N15: 2105433.4 | O15: 2109679.6 | P15: 2109679.6 | Q15: 2136680.4 | R15: 2197709.4 | S15: 2162629.8 | T15: 2322319.9 | U15: 2322319.9 | V15: 2299160.5 | W15: 2247239.1 | X15: 2223214.4
A16: 1 | C16: 장기금융자산 | E16: 13354.46 | F16: 13354.46 | G16: 14125.09 | H16: 14145.49 | I16: 14167.27 | J16: 15458.98 | K16: 15458.98 | L16: 15474.36 | M16: 15486.65 | N16: 15498.59 | O16: 14457.66 | P16: 14457.66 | Q16: 14470.66 | R16: 14484 | S16: 14483.93 | T16: 14001.12 | U16: 14001.12 | V16: 13904.25 | W16: 13894.83 | X16: 13894.3
... A22: 1 | C22: 기타비유동자산 | E22: 22996.01 | F22: 22996.01 | G22: 22829.08 | H22: 18884.61 | I22: 15434.44 | J22: 110317.92 | K22: 110317.92 | L22: 107881.04 | M22: 103882.1 | N22: 104182.19 | O22: 111761.67 | P22: 111761.67 | Q22: 107797.11 | R22: 103592.78 | S22: 97095.67 | T22: 78148.94 | U22: 78148.94 | V22: 71035.39 | W22: 61884.77 | X22: 54831.15
A23: 1 | C23: 비유동파생상품자산 | E23: 1247.58 | F23: 1247.58 | G23: 2856.12 | J23: 19316.97 | K23: 19316.97 | L23: 10750.01 | M23: 13448.73 | N23: 4016.89 | O23: 15623.77 | P23: 15623.77 | Q23: 954.44 | R23: 0 | S23: 14890.81 | T23: 0 | U23: 0 | W23: 47644.26 | X23: 10048.05
A24: 1 | C24: 비유동확정계약자산 | E24: 31692.05 | F24: 31692.05 | G24: 27599.9 | H24: 81004.24 | I24: 174527.51 | J24: 24761.83 | K24: 24761.83 | L24: 35792.49 | M24: 31436.13 | N24: 56188.95 | O24: 13771.64 | P24: 13771.64 | Q24: 43201.07 | R24: 82197.45 | S24: 20269.95 | T24: 187895.67 | U24: 187895.67 | V24: 172863.09 | W24: 29769.79 | X24: 64009.3
A25: 1 | C25: 이연법인세자산 | E25: 117765.29 | F25: 117765.29 | G25: 127290.04 | H25: 114200.15 | I25: 79950.66 | J25: 135722.09 | K25: 135722.09 | L25: 136778.98 | M25: 150403.05 | N25: 146994.7 | O25: 172186.42 | P25: 172186.42 | Q25: 171652.18 | R25: 164867.08 | S25: 165595.9 | T25: 152541.9 | U25: 152541.9 | V25: 146864.09 | W25: 130020.56 | X25: 94883.22
A26: 1 | C26: 자산총계 | E26: 3878320.3 | F26: 3878320.3 | G26: 4198411.7 | H26: 4403186.1 | I26: 5068885.1 | J26: 4748245.5 | K26: 4748245.5 | L26: 4734089.2 | M26: 4707023.4 | N26: 4825769.1 | O26: 4909071.4 | P26: 4909071.4 | Q26: 4748583 | R26: 4753852.6 | S26: 4572997.1 | T26: 5108867.3 | U26: 5108867.3 | V26: 5197532.6 | W26: 5145120.3 | X26: 5114546.1
A27: 1 | C27: 유동부채 | E27: 1612004.4 | F27: 1612004.4 | G27: 1968685.7 | H27: 2080370.4 | I27: 2533506.9 | J27: 2499086.9 | K27: 2499086.9 | L27: 2484394.5 | M27: 2492321.3 | N27: 2580232.9 | O27: 2735399.7 | P27: 2735399.7 | Q27: 2492849.5 | R27: 2448496.6 | S27: 2379286.5 | T27: 2705577.9 | U27: 2705577.9 | V27: 2870461 | W27: 2845940 | X27: 2649454.3
A28: 1 | C28: 단기차입금 | E28: 169155.8 | F28: 169155.8 | G28: 202029.85 | H28: 193066.4 | I28: 163444.1 | J28: 107721.17 | K28: 107721.17 | L28: 173678.08 | M28: 285828.23 | N28: 362946.64 | O28: 478561.15 | P28: 478561.15 | Q28: 276982.09 | R28: 180481.47 | S28: 94568.63 | T28: 159198.21 | U28: 159198.21 | V28: 158819.16 | W28: 121172.19 | X28: 119484.55
A29: 1 | C29: 단기금융부채(face) | E29: 169155.8 | F29: 169155.8 | G29: 202029.85 | H29: 193066.4 | I29: 163444.1 | J29: 107721.17 | K29: 107721.17 | L29: 173678.08 | M29: 285828.23 | N29: 362946.64 | O29: 478561.15 | P29: 478561.15 | Q29: 276982.09 | R29: 180481.47 | S29: 94568.63 | T29: 159198.21 | U29: 159198.21 | V29: 158819.16 | W29: 121172.19 | X29: 119484.55
A30: 1 | C30: 매입채무및기타채무 | E30: 519472.56 | F30: 519472.56 | G30: 435136.91 | H30: 583904.61 | I30: 625537.42 | J30: 687506.08 | K30: 687506.08 | L30: 651644.76 | M30: 614360.64 | N30: 516996.7 | O30: 567411.38 | P30: 567411.38 | Q30: 620815.94 | R30: 669370.09 | S30: 587647.98 | T30: 753608.85 | U30: 753608.85 | V30: 708798.85 | W30: 776124.43 | X30: 731594.83
A31: 1 | C31: 계약부채 | E31: 602513.94 | F31: 602513.94 | G31: 974873.75 | H31: 982481.76 | I31: 1352571.3 | J31: 1454465.3 | K31: 1454465.3 | L31: 1498006.9 | M31: 1463662.1 | N31: 1551498.7 | O31: 1557774.4 | P31: 1557774.4 | Q31: 1479867 | R31: 1455255.7 | S31: 1628960.5 | T31: 1588626.4 | U31: 1588626.4 | V31: 1816119.6 | W31: 1851368.9 | X31: 1662890.3
A32: 1 | C32: 단기충당부채 | E32: 272843.11 | F32: 272843.11 | G32: 288817.34 | H32: 189206.2 | I32: 123756.54 | J32: 144586.98 | K32: 144586.98 | L32: 49742.78 | M32: 29462.42 | N32: 36587.81 | O32: 74195.6 | P32: 74195.6 | Q32: 35945.67 | R32: 26630.11 | S32: 15566.98 | T32: 11216.9 | U32: 11216.9 | V32: 12003.85 | W32: 26936.98 | X32: 12716.65
A33: 1 | C33: 유동리스부채 | E33: 1454.35 | F33: 1454.35 | G33: 1507.08 | H33: 1231.99 | I33: 1151.79 | J33: 1716.81 | K33: 1716.81 | L33: 1932.27 | M33: 2000.36 | N33: 3816.51 | O33: 4239.09 | P33: 4239.09 | Q33: 4577.01 | R33: 4574.83 | S33: 4174.22 | T33: 4870.32 | U33: 4870.32 | V33: 4527.22 | W33: 4644.92 | X33: 4326.21
A34: 1 | C34: 리스부채 | E34: 10008.11 | F34: 10008.11 | G34: 10081.63 | H34: 9788.94 | I34: 9357.15 | J34: 11558.32 | K34: 11558.32 | L34: 11921.09 | M34: 12152.18 | N34: 18224.38 | O34: 18094.16 | P34: 18094.16 | Q34: 18238.25 | R34: 17886.84 | S34: 16630.34 | T34: 16521.33 | U34: 16521.33 | V34: 15765.97 | W34: 15418.18 | X34: 14240.48
A35: 1 | C35: 단기금융부채 | E35: 47931.26 | F35: 47931.26 | G35: 67794.49 | H35: 131670.24 | I35: 268038.57 | J35: 104637.45 | K35: 104637.45 | L35: 111196.55 | M35: 98852.73 | N35: 111814.46 | O35: 57457.06 | P35: 57457.06 | Q35: 78915.3 | R35: 116135.51 | S35: 51140.21 | T35: 190727.97 | U35: 190727.97 | V35: 172545.39 | W35: 67447.54 | X35: 113433.63
... A57: 1 | C57: 이자발생자산 | E57: 568705.15 | F57: 568705.15 | G57: 754931.87 | H57: 847772.13 | I57: 724816.08 | J57: 631200.32 | K57: 631200.32 | L57: 488089.21 | M57: 498008.39 | N57: 551024.07 | O57: 412371.32 | P57: 412371.32 | Q57: 525490.36 | R57: 560795.81 | S57: 493341.24 | T57: 353321.95 | U57: 353321.95 | V57: 600723.79 | W57: 613157.19 | X57: 609429.88
A58: 1 | C58: 이연법인세부채 | M58: 1194.72 | N58: 1194.72 | O58: 1405.56 | P58: 1405.56 | Q58: 1405.56 | R58: 1405.56 | S58: 1405.56 | T58: 910.44 | U58: 910.44 | V58: 910.44 | W58: 0 | X58: 910.44
A59: 1 | C59: 장기차입금 | O59: 95671.5 | P59: 95671.5 | Q59: 160000 | R59: 140000 | S59: 80000 | T59: 80000 | U59: 80000 | V59: 0 | W59: 0 | X59: 0
A60: 1 | C60: 장기금융부채(face) | O60: 95671.5 | P60: 95671.5 | Q60: 160000 | R60: 140000 | S60: 80000 | T60: 80000 | U60: 80000 | V60: 0 | W60: 0 | X60: 0
A61: 1 | C61: 매출액(수익) | E61: 860545.88 | G61: 875958.75 | H61: 935436.14 | I61: 882268.57 | J61: 1023197.5 | K61: 3716860.9 | L61: 909161.3 | M61: 1033370.8 | N61: 993800.53 | O61: 1102733.1 | P61: 4039065.7 | Q61: 1000493.6 | R61: 1129062.9 | S61: 1077667 | T61: 1422825.2 | U61: 4630048.8 | V61: 1183823 | W61: 1234448.4 | X61: 1300349.2
A62: 1 | C62: 매출원가 | E62: 904118.38 | G62: 910119.27 | H62: 912937.13 | I62: 837566.97 | J62: 1043382.9 | K62: 3704006.3 | L62: 916503.53 | M62: 1055211.1 | N62: 968931.18 | O62: 1129092.3 | P62: 4069738.1 | Q62: 973253.53 | R62: 1073429.9 | S62: 1003389.3 | T62: 1332063.9 | U62: 4382136.7 | V62: 1076844.9 | W62: 1101947.6 | X62: 1050007
A63: 1 | C63: 매출총이익 | E63: -43572.51 | G63: -34160.52 | H63: 22499.01 | I63: 44701.59 | J63: -20185.4 | K63: 12854.68 | L63: -7342.24 | M63: -21840.3 | N63: 24869.35 | O63: -26359.17 | P63: -30672.36 | Q63: 27240.1 | R63: 55632.92 | S63: 74277.7 | T63: 90761.35 | U63: 247912.07 | V63: 106978.08 | W63: 132500.75 | X63: 250342.17
A64: 1 | C64: 판관비 | E64: 33434.36 | G64: 27674.49 | H64: 29099.78 | I64: 30633.25 | J64: 34513.27 | K64: 121920.79 | L64: 20070.5 | M64: 30627.65 | N64: 32725.63 | O64: 38820.2 | P64: 122243.98 | Q64: 38284.07 | R64: 38208.52 | S64: 39027.39 | T64: 43864.18 | U64: 159384.16 | V64: 38493.99 | W64: 43081.52 | X64: 49534.75
A65: 1 | C65: 영업이익 | E65: -77006.86 | G65: -61835.01 | H65: -6600.78 | I65: 14068.34 | J65: -54698.67 | K65: -109066.12 | L65: -27412.73 | M65: -52467.95 | N65: -7856.29 | O65: -65179.38 | P65: -152916.35 | Q65: -11043.97 | R65: 17424.4 | S65: 35250.31 | T65: 46897.16 | U65: 88527.9 | V65: 68484.09 | W65: 89419.23 | X65: 200807.42
A66: 1 | C66: 금융수익 | E66: 1195.07 | G66: 53668.16 | H66: 104555.76 | I66: 189143.77 | J66: 15041.13 | K66: 362408.82 | L66: 96006.47 | M66: 58463.62 | N66: 66725.12 | O66: 25449.53 | P66: 246644.74 | Q66: 96732.18 | R66: 75761.3 | S66: 197846.34 | T66: 111172.08 | U66: 481511.9 | V66: 45383.44 | W66: 336070.62 | X66: 126873.65
A67: 1 | C67: 금융비용 | E67: 4460.13 | G67: 66730.04 | H67: 195716.47 | I67: 317517.92 | J67: -140005 | K67: 439959.43 | L67: 132242.95 | M67: 64766.54 | N67: 130225.19 | O67: -16833.39 | P67: 310401.29 | Q67: 176351.15 | R67: 155883.22 | S67: 114720.45 | T67: 388132.17 | U67: 835086.99 | V67: 72937.35 | W67: 149070.35 | X67: 226429.97
A68: 1 | C68: 기타영업외수익 | E68: 285.48 | G68: 30870.54 | H68: 151072.65 | I68: 284603.73 | J68: -249360.06 | K68: 217186.86 | L68: 67092.05 | M68: 22391.99 | N68: 90055.83 | O68: -66761.22 | P68: 112778.65 | Q68: 107249.15 | R68: 103563.63 | S68: 847.11 | T68: 333631.87 | U68: 545291.76 | V68: 28986.59 | W68: 500.66 | X68: 136763.59
A69: 1 | C69: 기타영업외비용 | E69: 23192.57 | G69: 5630.29 | H69: 2474.16 | I69: 28300.93 | J69: 57412.41 | K69: 93817.79 | L69: 8258.3 | M69: 9968.09 | N69: 5080.01 | O69: 29685.92 | P69: 52992.32 | Q69: 13284.14 | R69: 5274.82 | S69: 116381.47 | T69: -903.7 | U69: 134036.73 | V69: 10106.06 | W69: 249025.31 | X69: 7236.62
A70: 1 | C70: 법인세비용차감전계속사업이익 | E70: -103179.03 | G70: -49656.65 | H70: 50837.01 | I70: 141996.99 | J70: -206425.01 | K70: -63247.66 | L70: -4815.46 | M70: -46346.97 | N70: 13619.47 | O70: -119343.61 | P70: -156886.57 | Q70: 3302.06 | R70: 35591.29 | S70: 2841.83 | T70: 104472.65 | U70: 146207.83 | V70: 59810.7 | W70: 27894.84 | X70: 230778.08
A71: 1 | C71: 법인세비용 | E71: -24812.81 | G71: -10198.24 | H71: 13368.58 | I71: 34717.31 | J71: -57368.52 | K71: -19480.87 | L71: -445.95 | M71: -11399.12 | N71: 3886.5 | O71: -9975.28 | P71: -17933.85 | Q71: 1165.49 | R71: 6662.5 | S71: 237.49 | T71: 24894 | U71: 32959.48 | V71: 8113.35 | W71: 2685.97 | X71: 47936.06
A72: 1 | C72: 당기순이익 | E72: -78366.22 | G72: -39458.41 | H72: 37468.43 | I72: 107279.69 | J72: -149056.49 | K72: -43766.78 | L72: -4369.51 | M72: -34947.84 | N72: 9732.97 | O72: -109368.33 | P72: -138952.71 | Q72: 2136.57 | R72: 28928.79 | S72: 2604.35 | T72: 79578.64 | U72: 113248.35 | V72: 51697.35 | W72: 25208.87 | X72: 182842.03
... A78: 1 | C78: 계속사업이익 | E78: -78366.22 | G78: -39458.41 | H78: 37468.43 | I78: 107279.69 | J78: -149056.49 | K78: -43766.78 | L78: -4369.51 | M78: -34947.84 | N78: 9732.97 | O78: -109368.33 | P78: -138952.71 | Q78: 2136.57 | R78: 28928.79 | S78: 2604.35 | T78: 79578.64 | U78: 113248.35 | V78: 51697.35 | W78: 25208.87 | X78: 182842.03
A79: 1 | C79: 이자수익 | G79: 1721 | H79: 2717 | I79: 4028 | J79: 5073 | K79: 13539 | L79: 4039 | M79: 3835 | N79: 3965 | O79: 4081 | P79: 15920 | Q79: 4357 | R79: 3987 | S79: 4372 | T79: 3542 | U79: 16258 | V79: 2662 | W79: 3356 | X79: 4295
A80: 1 | C80: 배당금수익 | G80: 37 | H80: 0 | I80: 0 | J80: 0 | K80: 37 | L80: 42 | M80: 0 | N80: 0 | O80: 0 | P80: 42 | Q80: 62 | R80: 0 | S80: 0 | T80: 0 | U80: 62 | V80: 62 | W80: 0 | X80: 0
A81: 1 | C81: 이자비용 | G81: 821 | H81: 1213 | I81: 1509 | J81: 1518 | K81: 5061 | L81: 1517 | M81: 3171 | N81: 3949 | O81: 5196 | P81: 13833 | Q81: 6913 | R81: 5247 | S81: 4547 | T81: 2756 | U81: 19463 | V81: 3218 | W81: 945 | X81: 1136
A82: 1 | C82: 외환차익 | G82: 38996 | H82: 58814 | I82: 86354 | J82: 87300 | K82: 271464 | L82: 52556 | M82: 46704 | N82: 41098 | O82: 28852 | P82: 169210 | Q82: 55680 | R82: 70776 | S82: 38658 | T82: 49739 | U82: 214853 | V82: 25945 | W82: 42459 | X82: 52535
A83: 1 | C83: 외환차손 | G83: 23277 | H83: 20508 | I83: 18165 | J83: 70742 | K83: 132692 | L83: 38078 | M83: 23420 | N83: 22862 | O83: 34179 | P83: 118539 | Q83: 23076 | R83: 25167 | S83: 48578 | T83: 20919 | U83: 117740 | V83: 32246 | W83: 82351 | X83: 59961
A84: 1 | C84: 외화환산이익 | G84: 9518 | H84: 42793 | I84: 98762 | J84: -132785 | K84: 18288 | L84: 34361 | M84: -12185 | N84: 16611 | O84: -31125 | P84: 7662 | Q84: 35797 | R84: 0 | S84: 0 | T84: 77825 | U84: 113622 | V84: 9870 | W84: 11049 | X84: 56424
A85: 1 | C85: 외화환산손실 | G85: 6962 | H85: 11922 | I85: 21824 | J85: 56309 | K85: 97017 | L85: 9266 | M85: 9146 | N85: 6293 | O85: 17985 | P85: 42690 | Q85: 10002 | R85: 11048 | S85: 38628 | T85: 4848 | U85: 64526 | V85: 6229 | W85: 64400 | X85: 0
A86: 1 | C86: 파생상품이익 | G86: 3259 | H86: 232 | I86: -151 | J86: 55453 | K86: 58793 | L86: 5008 | M86: 7925 | N86: 5051 | O86: 23641 | P86: 41625 | Q86: 836 | R86: 998 | S86: 154816 | T86: -19934 | U86: 136716 | V86: 6844 | W86: 279207 | X86: 13620
A87: 1 | C87: 파생상품손실 | G87: 35670 | H87: 162073 | I87: 276020 | J87: -268575 | K87: 205188 | L87: 83382 | M87: 29030 | N87: 97121 | O87: -74201 | P87: 135332 | Q87: 136360 | R87: 114421 | S87: 22967 | T87: 359609 | U87: 633357 | V87: 31244 | W87: 1374 | X87: 165333
A88: 1 | C88: 이자손익 | G88: 900 | H88: 1504 | I88: 2519 | J88: 3555 | K88: 8478 | L88: 2522 | M88: 664 | N88: 16 | O88: -1115 | P88: 2087 | Q88: -2556 | R88: -1260 | S88: -175 | T88: 786 | U88: -3205 | V88: -556 | W88: 2411 | X88: 3159
A89: 1 | C89: 영업활동으로인한현금흐름 | E89: -277126.05 | G89: 170813.3 | H89: 104465.44 | I89: -125000.98 | J89: 58129.01 | K89: 208406.77 | L89: -188211.1 | M89: -53555.39 | N89: 11244.77 | O89: -302762.84 | P89: -533284.56 | Q89: 273016.62 | R89: 173229.52 | S89: 177754.72 | T89: -263100.88 | U89: 360899.98 | V89: 373397.19 | W89: 185990.07 | X89: 33364.41
A90: 1 | C90: 이자수취(CF) | E90: 4282.45 | G90: 1706.76 | H90: 2481.35 | I90: 3695.38 | J90: 5564.86 | K90: 13448.35 | L90: 4357.71 | M90: 3827.73 | N90: 3783.54 | O90: 4127.83 | P90: 16096.81 | Q90: 4101.74 | R90: 4261.59 | S90: 4566.95 | T90: 3566.37 | U90: 16496.65 | V90: 2607.4 | W90: 3185.5 | X90: 4529.74
A91: 1 | C91: 이자지급(CF) | E91: -794.54 | G91: -893.52 | H91: -1319.03 | I91: -1626.76 | J91: -1579.31 | K91: -5418.62 | L91: -1516.71 | M91: -2761.78 | N91: -3720.91 | O91: -4621.86 | P91: -12621.26 | Q91: -7512.68 | R91: -4709.32 | S91: -5689.37 | T91: -2725.01 | U91: -20636.38 | V91: -3253.48 | W91: -980.22 | X91: -1138.26
A92: 1 | C92: 배당금수취(CF) | E92: 0 | I92: 0 | J92: 0 | N92: 0 | O92: 0 | S92: 0 | T92: 0 | X92: 0
A93: 1 | C93: 법인세납부(CF) | E93: 998.06 | G93: -708.73 | H93: 134.1 | I93: -855.9 | J93: -754.63 | K93: -2185.16 | L93: -1603.51 | M93: 436.18 | N93: -908.67 | O93: -891.87 | P93: -2967.87 | Q93: -769.06 | R93: 2243.11 | S93: -1015.08 | T93: -1671.63 | U93: -1212.66 | V93: -2780.83 | W93: 93.32 | X93: -4789.56
A94: 1 | C94: 투자활동으로인한현금흐름 | E94: 59163.3 | G94: 14323.61 | H94: -122026.47 | I94: 11195.65 | J94: 49239.81 | K94: -47267.4 | L94: -164.79 | M94: -41967.79 | N94: -41352.56 | O94: -28139.68 | P94: -111624.82 | Q94: -20168.17 | R94: -46989.31 | S94: -57535.23 | T94: -24467.08 | U94: -149159.79 | V94: -24053.75 | W94: -43203.86 | X94: -47602.35
A95: 1 | C95: 유형자산의감소 | E95: 81.07 | G95: 152.44 | H95: 144.29 | I95: 379.52 | J95: 143.01 | K95: 819.26 | L95: 96.27 | M95: 156.54 | N95: 1122.85 | O95: 59.91 | P95: 1435.57 | Q95: 21.15 | R95: 56.87 | S95: 57.98 | T95: 100.04 | U95: 236.04 | V95: 75.95 | W95: 32.1 | X95: 155.04
A96: 1 | C96: 무형자산의감소 | E96: 300
A97: 1 | C97: 유형자산의증가 | E97: 24549.79 | G97: 25778.59 | H97: 27979.13 | I97: 35363.12 | J97: 24697.17 | K97: 113818.01 | L97: 12709.68 | M97: 36541.6 | N97: 37058.97 | O97: 31051.26 | P97: 117361.51 | Q97: 25245.76 | R97: 40674.65 | S97: 52329.86 | T97: 26366.14 | U97: 144616.41 | V97: 27973.91 | W97: 34297.34 | X97: 42028.58
A98: 1 | C98: CAPEX | E98: 24756.66 | G98: 26483.58 | H98: 29160.3 | I98: 37179.8 | J98: 25944.91 | K98: 118768.59 | L98: 14294.11 | M98: 38862.7 | N98: 39913.4 | O98: 34557.88 | P98: 127628.09 | Q98: 25987.84 | R98: 42005.73 | S98: 53479.73 | T98: 29797.7 | U98: 151271 | V98: 28478.81 | W98: 35116.14 | X98: 42880.66
A99: 1 | C99: 무형자산의증가 | E99: 206.87 | G99: 704.99 | H99: 1181.17 | I99: 1816.68 | J99: 1247.74 | K99: 4950.58 | L99: 1584.43 | M99: 2321.1 | N99: 2854.43 | O99: 3506.62 | P99: 10266.58 | Q99: 742.08 | R99: 1331.08 | S99: 1149.87 | T99: 3431.56 | U99: 6654.59 | V99: 504.9 | W99: 818.8 | X99: 852.08
A100: 1 | C100: 재무활동으로인한현금흐름 | E100: -19803.01 | G100: 29459.88 | H100: -22849.06 | I100: -41952.08 | J100: -36271.62 | K100: -71612.88 | L100: 61195.62 | M100: 112168.78 | N100: 72702.5 | O100: 217579.95 | P100: 463646.85 | Q100: -145772.01 | R100: -124965.07 | S100: -140452.34 | T100: 48048.03 | U100: -363141.39 | V100: -80956.35 | W100: -58905.22 | X100: -26092.23
A101: 1 | C101: 리스부채의상환 | E101: 488.69 | G101: 277.53 | H101: 292.48 | I101: 478.95 | J101: 460.06 | K101: 1509.02 | L101: 298.33 | M101: 369.84 | N101: 591.82 | O101: 404.48 | P101: 1664.47 | Q101: 1671.26 | R101: 1472.54 | S101: 1346.52 | T101: 1299.29 | U101: 5789.61 | V101: 956.35 | W101: 1012.32 | X101: 1412.31
A102: 1 | C102: 현금및현금성자산의증감 | E102: -237877.95 | G102: 215217.07 | H102: -37791.11 | I102: -151538.89 | J102: 63885.83 | K102: 89772.9 | L102: -125351.78 | M102: 16293.35 | N102: 43112.89 | O102: -114157.42 | P102: -180102.96 | Q102: 108171.53 | R102: 2781.94 | S102: -24390.76 | T102: -231507.39 | U102: -144944.68 | V102: 268913.28 | W102: 78806.79 | X102: -39252.17
A103: 1 | C103: 기말현금및현금성자산 | E103: -237877.95 | G103: 615588.03 | H103: -37791.11 | I103: -151538.89 | J103: 63885.82 | K103: 490143.85 | L103: 364792.08 | M103: 16293.35 | N103: 43112.89 | O103: -114157.43 | P103: 310040.89 | Q103: 418212.43 | R103: 2781.93 | S103: -24390.76 | T103: -231507.39 | U103: 165096.21 | V103: 434009.49 | W103: 78806.79 | X103: -39252.17
A104: 1 | C104: 배당금지급 | X104: 19144.46

Sheet BS별도
B1: (백만원) | C1: 이름: BS별도H | E1: 4Q21 | F1: 2021 | G1: 1Q22 | H1: 2Q22 | I1: 3Q22 | J1: 4Q22 | K1: 2022 | L1: 1Q23 | M1: 2Q23 | N1: 3Q23 | O1: 4Q23 | P1: 2023 | Q1: 1Q24 | R1: 2Q24 | S1: 3Q24 | T1: 4Q24 | U1: 2024 | V1: 1Q25 | W1: 2Q25 | X1: 3Q25 | Y1: 4Q25 | Z1: 2025 | AA1: 1Q26 | AB1: 2Q26 | AC1: 3Q26 | AD1: 4Q26 | AE1: 2026 | AF1: 1Q27 | AG1: 2Q27 | AH1: 3Q27 | AI1: 4Q27 | AJ1: 2027 | AK1: 1Q28 | AL1: 2Q28 | AM1: 3Q28 | AN1: 4Q28 | AO1: 2028
B2: 별도 | D2: fin json(kship_fin.py)
B3: HD현대미포(별) | C3: UPDATE: 26-10-11 | E3: 1 | F3: 2 | G3: 3 | H3: 4 | I3: 5 | J3: 6 | K3: 7 | L3: 8 | M3: 9 | N3: 10 | O3: 11 | P3: 12 | Q3: 13 | R3: 14 | S3: 15 | T3: 16 | U3: 17 | V3: 18 | W3: 19 | X3: 20 | Y3: 21 | Z3: 22 | AA3: 23 | AB3: 24 | AC3: 25 | AD3: 26 | AE3: 27 | AF3: 28 | AG3: 29 | AH3: 30 | AI3: 31 | AJ3: 32 | AK3: 33 | AL3: 34 | AM3: 35 | AN3: 36 | AO3: 37
B4: Account Code | C4: AccountNAME | E4: 2021.12 | F4: 2021.12A | G4: 2022.03 | H4: 2022.06 | I4: 2022.09 | J4: 2022.12 | K4: 2022.12A | L4: 2023.03 | M4: 2023.06 | N4: 2023.09 | O4: 2023.12 | P4: 2023.12A | Q4: 2024.03 | R4: 2024.06 | S4: 2024.09 | T4: 2024.12 | U4: 2024.12A | V4: 2025.03 | W4: 2025.06 | X4: 2025.09 | Y4: 2025.12 | Z4: 2025.12A | AA4: 2026.03 | AB4: 2026.06 | AC4: 2026.09 | AD4: 2026.12 | AE4: 2026.12A | AF4: 2027.03 | AG4: 2027.06 | AH4: 2027.09 | AI4: 2027.12 | AJ4: 2027.12A | AK4: 2028.03 | AL4: 2028.06 | AM4: 2028.09 | AN4: 2028.12 | AO4: 2028.12A
A5: 1 | C5: 유동자산 | E5: 2158881.4 | F5: 2158881.4 | G5: 2440189.8 | H5: 2661217.7 | I5: 3288166.8 | J5: 2945101.9 | K5: 2945101.9 | L5: 2838712.1 | M5: 2917547.3 | N5: 2948429.7 | O5: 3017901 | P5: 3017901 | Q5: 2820329.5 | R5: 2772843.2 | S5: 2560872.1 | T5: 2972534.5 | U5: 2972534.5 | V5: 3035855 | W5: 3074800.6 | X5: 3049804.9
A6: 1 | C6: 현금및현금성자산 | E6: 372686.92 | F6: 372686.92 | G6: 544188.39 | H6: 515417.73 | I6: 363000.29 | J6: 431836.62 | K6: 431836.62 | L6: 290430.89 | M6: 351336.78 | N6: 396957.6 | O6: 273524.46 | P6: 273524.46 | Q6: 390726.17 | R6: 364074.92 | S6: 288905.78 | T6: 83492.25 | U6: 83492.25 | V6: 283730.83 | W6: 451431.26 | X6: 325015.53
A7: 1 | C7: 단기금융상품 | E7: 123027.77 | F7: 123027.77 | G7: 83000.51 | H7: 173001.29 | I7: 123001.48 | J7: 53001.73 | K7: 53001.73 | L7: 23001.44 | M7: 23001.59 | N7: 23001.83 | O7: 23002.07 | P7: 23002.07 | Q7: 23000.13 | R7: 23000.15 | S7: 23000.17 | T7: 24122.31 | U7: 24122.31 | V7: 24112.89 | W7: 24612.96 | X7: 25107.54
A8: 1 | C8: 단기금융자산 | E8: 153479.73 | F8: 153479.73 | G8: 124218.75 | H8: 251829.72 | I8: 278390.78 | J8: 125597.49 | K8: 125597.49 | L8: 91270.14 | M8: 81395.55 | N8: 88338.31 | O8: 71794.11 | P8: 71794.11 | Q8: 82111.18 | R8: 109404.57 | S8: 62661.72 | T8: 159978.97 | U8: 159978.97 | V8: 142622.75 | W8: 69109.48 | X8: 99963.56
A9: 1 | C9: 매출채권및기타채권 | E9: 198948.55 | F9: 198948.55 | G9: 386967.32 | H9: 362527.03 | I9: 557870.48 | J9: 363163.72 | K9: 363163.72 | L9: 139891.3 | M9: 168468.5 | N9: 180146.63 | O9: 248076.57 | P9: 248076.57 | Q9: 222220.27 | R9: 290569.17 | S9: 122466.39 | T9: 171819.32 | U9: 171819.32 | V9: 147599.3 | W9: 156620.22 | X9: 184845.7
A10: 1 | C10: 계약자산 | E10: 900681.06 | F10: 900681.06 | G10: 871197.85 | H10: 984461.79 | I10: 1356660.9 | J10: 1301185.5 | K10: 1301185.5 | L10: 1356660 | M10: 1337028.8 | N10: 1318559.9 | O10: 1442687.1 | P10: 1442687.1 | Q10: 1166462 | R10: 1011783.8 | S10: 936957.46 | T10: 1488564 | U10: 1488564 | V10: 1368532.1 | W10: 1249564.2 | X10: 1248566.8
A11: 1 | C11: 유동파생상품자산 | E11: 1664.05 | F11: 1664.05 | G11: 540.83 | H11: 2.69 | I11: 2.57 | J11: 29527.19 | K11: 29527.19 | L11: 11801.01 | M11: 10449.82 | N11: 3789.3 | O11: 15804.99 | P11: 15804.99 | Q11: 2382.6 | R11: 206.53 | S11: 10028.66 | T11: 185.35 | U11: 185.35 | V11: 16.69 | W11: 7654.67 | X11: 2577.2
A12: 1 | C12: 유동확정계약자산 | E12: 28787.91 | F12: 28787.91 | G12: 40677.41 | H12: 78825.74 | I12: 155386.73 | J12: 43068.57 | K12: 43068.57 | L12: 56467.69 | M12: 47944.14 | N12: 61547.18 | O12: 32987.05 | P12: 32987.05 | Q12: 56728.45 | R12: 86197.89 | S12: 29632.89 | T12: 135671.31 | U12: 135671.31 | V12: 118493.17 | W12: 36841.85 | X12: 72278.82
A13: 1 | C13: 재고자산 | E13: 198966.89 | F13: 198966.89 | G13: 189257.67 | H13: 187865.86 | I13: 253988.21 | J13: 253733.47 | K13: 253733.47 | L13: 222679.27 | M13: 217087.52 | N13: 167972.41 | O13: 154750.48 | P13: 154750.48 | Q13: 195753.14 | R13: 198279.92 | S13: 201987.08 | T13: 188896.95 | U13: 188896.95 | V13: 165632.48 | W13: 153212.5 | X13: 174826.28
A14: 1 | C14: 기타유동자산 | E14: 334118.22 | F14: 334118.22 | G14: 324359.82 | H14: 359115.61 | I14: 478256.23 | J14: 469585.1 | K14: 469585.1 | L14: 737780.52 | M14: 762230.12 | N14: 796454.86 | O14: 827068.39 | P14: 827068.39 | Q14: 763056.77 | R14: 798730.75 | S14: 947893.7 | T14: 879782.98 | U14: 879782.98 | V14: 927737.52 | W14: 994862.86 | X14: 1016587.1
A15: 1 | C15: 비유동자산 | E15: 1699092 | F15: 1699092 | G15: 1705976.7 | H15: 1756041.7 | I15: 1822221.8 | J15: 1835597.4 | K15: 1835597.4 | L15: 1840141.5 | M15: 1872509.8 | N15: 1904043.4 | O15: 1914824.4 | P15: 1914824.4 | Q15: 1934068.4 | R15: 1985061.9 | S15: 1963877.5 | T15: 2095219.8 | U15: 2095219.8 | V15: 2076619.4 | W15: 2046535.9 | X15: 2015474.4
A16: 1 | C16: 장기금융자산 | E16: 13040.01 | F16: 13040.01 | G16: 13798.02 | H16: 13798.02 | I16: 13797.02 | J16: 15099.67 | K16: 15099.67 | L16: 15099.68 | M16: 15099.69 | N16: 15099.69 | O16: 14212.79 | P16: 14212.79 | Q16: 14212.79 | R16: 14212.79 | S16: 14199.29 | T16: 13702.75 | U16: 13702.75 | V16: 13702.75 | W16: 13700.25 | X16: 13700.25
... A23: 1 | C23: 기타비유동자산 | E23: 17646.82 | F23: 17646.82 | G23: 17394.16 | H23: 13125.07 | I23: 9129.74 | J23: 93639.32 | K23: 93639.32 | L23: 91165.39 | M23: 88605.25 | N23: 91566.21 | O23: 93469.73 | P23: 93469.73 | Q23: 89332.65 | R23: 84881.72 | S23: 79329.12 | T23: 55746.49 | U23: 55746.49 | V23: 49700.72 | W23: 42898.02 | X23: 36867.39
A24: 1 | C24: 비유동파생상품자산 | E24: 1247.58 | F24: 1247.58 | G24: 2856.12 | J24: 19316.97 | K24: 19316.97 | L24: 10750.01 | M24: 13448.73 | N24: 4016.89 | O24: 15623.77 | P24: 15623.77 | Q24: 954.44 | R24: 0 | S24: 14890.81 | T24: 0 | U24: 0 | W24: 47644.26 | X24: 10048.05
A25: 1 | C25: 비유동확정계약자산 | E25: 31692.05 | F25: 31692.05 | G25: 27599.9 | H25: 81004.24 | I25: 174527.51 | J25: 24761.83 | K25: 24761.83 | L25: 35792.49 | M25: 31436.13 | N25: 56188.95 | O25: 13771.64 | P25: 13771.64 | Q25: 43201.07 | R25: 82197.45 | S25: 20269.95 | T25: 187895.67 | U25: 187895.67 | V25: 172863.09 | W25: 29769.79 | X25: 64009.3
A26: 1 | C26: 이연법인세자산 | E26: 124055.97 | F26: 124055.97 | G26: 133345.88 | H26: 119022.48 | I26: 85208.44 | J26: 136572.07 | K26: 136572.07 | L26: 137185.54 | M26: 149466.43 | N26: 145960.6 | O26: 171091.53 | P26: 171091.53 | Q26: 170464.55 | R26: 163676.04 | S26: 164530.1 | T26: 151128.26 | U26: 151128.26 | V26: 145399.14 | W26: 129662.63 | X26: 93668.89
A27: 1 | C27: 자산총계 | E27: 3857973.4 | F27: 3857973.4 | G27: 4146166.5 | H27: 4417259.4 | I27: 5110388.7 | J27: 4780699.2 | K27: 4780699.2 | L27: 4678853.6 | M27: 4790057.1 | N27: 4852473.1 | O27: 4932725.4 | P27: 4932725.4 | Q27: 4754397.9 | R27: 4757905.1 | S27: 4524749.6 | T27: 5067754.2 | U27: 5067754.2 | V27: 5112474.4 | W27: 5121336.5 | X27: 5065279.3
A28: 1 | C28: 유동부채 | E28: 1647347.9 | F28: 1647347.9 | G28: 1963791.4 | H28: 2141888.2 | I28: 2635601.2 | J28: 2592825.6 | K28: 2592825.6 | L28: 2492545.8 | M28: 2643994.8 | N28: 2678281.1 | O28: 2826952.8 | P28: 2826952.8 | Q28: 2570211.4 | R28: 2532025.6 | S28: 2410804.1 | T28: 2759395.9 | U28: 2759395.9 | V28: 2881950.5 | W28: 2916366.4 | X28: 2706436.5
A29: 1 | C29: 단기차입금 | E29: 89727.3 | F29: 89727.3 | G29: 62389.81 | H29: 39303.43 | I29: 9919.74 | M29: 159000 | N29: 209000 | O29: 314328.5 | P29: 314328.5 | Q29: 159818.88 | R29: 45695.78 | S29: 0 | T29: 0 | U29: 0
A30: 1 | C30: 단기금융부채(face) | E30: 89727.3 | F30: 89727.3 | G30: 62389.81 | H30: 39303.43 | I30: 9919.74 | M30: 159000 | N30: 209000 | O30: 314328.5 | P30: 314328.5 | Q30: 159818.88 | R30: 45695.78 | S30: 0 | T30: 0 | U30: 0
A31: 1 | C31: 매입채무및기타채무 | E31: 630994.44 | F31: 630994.44 | G31: 567647.94 | H31: 799312.04 | I31: 878596.62 | J31: 886514.65 | K31: 886514.65 | L31: 831756.1 | M31: 877663.34 | N31: 768766.33 | O31: 822925.57 | P31: 822925.57 | Q31: 815639.32 | R31: 888283.54 | S31: 715189.88 | T31: 968882.14 | U31: 968882.14 | V31: 881053.28 | W31: 969874.49 | X31: 909920.47
A32: 1 | C32: 계약부채 | E32: 602513.94 | F32: 602513.94 | G32: 974873.75 | H32: 982481.76 | I32: 1352571.3 | J32: 1454465.3 | K32: 1454465.3 | L32: 1498006.9 | M32: 1477761.5 | N32: 1551498.7 | O32: 1557774.4 | P32: 1557774.4 | Q32: 1479867 | R32: 1455255.7 | S32: 1628960.5 | T32: 1588626.4 | U32: 1588626.4 | V32: 1816119.6 | W32: 1851368.9 | X32: 1662890.3
A33: 1 | C33: 단기충당부채 | E33: 276008.65 | F33: 276008.65 | G33: 290997.07 | H33: 189012.93 | I33: 126374.79 | J33: 147142.75 | K33: 147142.75 | L33: 51519.43 | M33: 30729.31 | N33: 37230.16 | O33: 74528.12 | P33: 74528.12 | Q33: 36024.12 | R33: 26716.2 | S33: 15566.99 | T33: 11216.9 | U33: 11216.9 | V33: 12003.85 | W33: 26936.98 | X33: 12716.65
A34: 1 | C34: 유동리스부채 | E34: 1434.63 | F34: 1434.63 | G34: 1477.57 | H34: 1194.33 | I34: 1116.17 | J34: 1676.15 | K34: 1676.15 | L34: 1895.6 | M34: 1972.52 | N34: 3787.92 | O34: 4178.21 | P34: 4178.21 | Q34: 4523.78 | R34: 4513.64 | S34: 4120.81 | T34: 4812.8 | U34: 4812.8 | V34: 4470.17 | W34: 4618.03 | X34: 4312.46
A35: 1 | C35: 리스부채 | E35: 9968.53 | F35: 9968.53 | G35: 10012.97 | H35: 9699.1 | I35: 9277.3 | J35: 11465.14 | K35: 11465.14 | L35: 11821.43 | M35: 12061.34 | N35: 18112.81 | O35: 17993.38 | P35: 17993.38 | Q35: 18145.12 | R35: 17751.7 | S35: 16502.98 | T35: 16419.95 | U35: 16419.95 | V35: 15655.16 | W35: 15337.53 | X35: 14172.97
A36: 1 | C36: 단기금융부채 | E36: 47911.54 | F36: 47911.54 | G36: 67764.98 | H36: 131632.58 | I36: 268002.95 | J36: 104596.79 | K36: 104596.79 | L36: 111159.88 | M36: 98824.89 | N36: 111785.87 | O36: 57396.18 | P36: 57396.18 | Q36: 78862.07 | R36: 116074.32 | S36: 51086.8 | T36: 190670.45 | U36: 190670.45 | V36: 172488.34 | W36: 67420.65 | X36: 113419.88
A37: 1 | C37: 단기파생상품부채 | E37: 46476.91 | F37: 46476.91 | G37: 66287.41 | H37: 130438.25 | I37: 266886.78 | J37: 102920.64 | K37: 102920.64 | L37: 109264.28 | M37: 96852.37 | N37: 107997.95 | O37: 53217.97 | P37: 53217.97 | Q37: 74338.29 | R37: 111560.68 | S37: 46965.99 | T37: 185857.65 | U37: 185857.65 | V37: 168018.17 | W37: 62802.62 | X37: 109107.42
A38: 1 | C38: 기타유동부채 | E38: 192.07 | F38: 192.07 | G38: 117.9 | H38: 145.5 | I38: 135.75 | J38: 106.1 | K38: 106.1 | L38: 103.47 | M38: 15.74 | T38: 0 | U38: 0 | V38: 285.51 | W38: 765.42 | X38: 7489.22
A39: 1 | C39: 비유동부채 | E39: 54428.39 | F39: 54428.39 | G39: 53965.21 | H39: 102698.84 | I39: 196722.34 | J39: 66728.11 | K39: 66728.11 | L39: 68791.25 | M39: 67288.15 | N39: 86575.43 | O39: 151512.56 | P39: 151512.56 | Q39: 227995.09 | R39: 245761.62 | S39: 137058.69 | T39: 291443.76 | U39: 291443.76 | V39: 194374.24 | W39: 98374.65 | X39: 95341.31
A40: 1 | C40: 장기매입채무및기타채무 | E40: 41.19 | F40: 41.19 | G40: 5.72 | H40: 5.72 | I40: 5.72 | J40: 5.72 | K40: 5.72 | L40: 3.28 | M40: 1.78 | N40: 1.78 | O40: 71.78 | P40: 71.78 | Q40: 71.78 | R40: 71.78 | S40: 71.78 | T40: 689.3 | U40: 689.3 | V40: 608.18 | W40: 608.18 | X40: 608.18
A41: 1 | C41: 확정급여부채 | E41: 8254.86 | F41: 8254.86 | G41: 8254.86 | H41: 8254.86 | I41: 8952.46 | J41: 7470.24 | K41: 7470.24 | L41: 7470.24 | M41: 7470.24 | N41: 7470.24 | O41: 8288.36 | P41: 8288.36 | Q41: 5946.58 | R41: 5946.58 | S41: 5946.58 | T41: 6289.27 | U41: 6289.27 | V41: 6289.27 | W41: 6289.27 | X41: 7544.59
A42: 1 | C42: 장기충당부채 | E42: 4658.81 | F42: 4658.81 | G42: 6713.2 | H42: 4929.24 | I42: 5075.51 | J42: 5384.36 | K42: 5384.36 | L42: 4849.4 | M42: 4842.46 | N42: 4572.69 | O42: 4270.35 | P42: 4270.35 | Q42: 4199.89 | R42: 4158.85 | S42: 3497.41 | T42: 4962.38 | U42: 4962.38 | V42: 3428.72 | W42: 3343.65 | X42: 3270.68
A43: 1 | C43: 비유동리스부채 | E43: 8533.9 | F43: 8533.9 | G43: 8535.4 | H43: 8504.77 | I43: 8161.13 | J43: 9788.99 | K43: 9788.99 | L43: 9925.83 | M43: 10088.82 | N43: 14324.89 | O43: 13815.17 | P43: 13815.17 | Q43: 13621.34 | R43: 13238.06 | S43: 12382.17 | T43: 11607.15 | U43: 11607.15 | V43: 11184.99 | W43: 10719.5 | X43: 9860.51
A44: 1 | C44: 장기금융부채 | E44: 41473.53 | F44: 41473.53 | G44: 38991.42 | H44: 89509.01 | I44: 182688.64 | J44: 53867.79 | K44: 53867.79 | L44: 56468.33 | M44: 54973.68 | N44: 74530.73 | O44: 43210.58 | P44: 43210.58 | Q44: 57776.85 | R44: 95584.42 | S44: 47542.93 | T44: 199502.82 | U44: 199502.82 | V44: 184048.08 | W44: 88133.55 | X44: 83917.86
A45: 1 | C45: 장기파생상품부채 | E45: 32939.63 | F45: 32939.63 | G45: 30456.02 | H45: 81004.24 | I45: 174527.51 | J45: 44078.8 | K45: 44078.8 | L45: 46542.5 | M45: 44884.86 | N45: 60205.84 | O45: 29395.41 | P45: 29395.41 | Q45: 44155.51 | R45: 82346.36 | S45: 35160.76 | T45: 187895.67 | U45: 187895.67 | V45: 172863.09 | W45: 77414.05 | X45: 74057.35
A46: 1 | C46: 부채총계 | E46: 1701776.3 | F46: 1701776.3 | G46: 2017756.7 | H46: 2244587.1 | I46: 2832323.5 | J46: 2659553.7 | K46: 2659553.7 | L46: 2561337 | M46: 2711283 | N46: 2764856.5 | O46: 2978465.3 | P46: 2978465.3 | Q46: 2798206.5 | R46: 2777787.2 | S46: 2547862.8 | T46: 3050839.7 | U46: 3050839.7 | V46: 3076324.8 | W46: 3014741 | X46: 2801777.8
A47: 1 | C47: 자본금 | E47: 199710.74 | F47: 199710.74 | G47: 199710.74 | H47: 199710.74 | I47: 199710.74 | J47: 199710.74 | K47: 199710.74 | L47: 199710.74 | M47: 199710.74 | N47: 199710.74 | O47: 199710.74 | P47: 199710.74 | Q47: 199710.74 | R47: 199710.74 | S47: 199710.74 | T47: 199710.74 | U47: 199710.74 | V47: 199710.74 | W47: 199710.74 | X47: 199710.74
A48: 1 | C48: 자본잉여금 | E48: 81745.92 | F48: 81745.92 | G48: 81745.92 | H48: 81745.92 | I48: 81745.92 | J48: 81745.92 | K48: 81745.92 | L48: 81745.92 | M48: 81745.92 | N48: 81745.92 | O48: 81745.92 | P48: 81745.92 | Q48: 81745.92 | R48: 81745.92 | S48: 81745.92 | T48: 81745.92 | U48: 81745.92 | V48: 81745.92 | W48: 81745.92 | X48: 81745.92
A49: 1 | C49: 기타자본 | E49: -12349.05 | F49: -12349.05 | G49: -12349.05 | H49: -12349.05 | I49: -12349.05 | J49: -12349.05 | K49: -12349.05 | L49: -12349.05 | M49: -12349.05 | N49: -12349.05 | O49: -12349.05 | P49: -12349.05 | Q49: -12349.05 | R49: -12349.05 | S49: -12349.05 | T49: -12349.05 | U49: -12349.05 | V49: -12349.05 | W49: -12349.05 | X49: -12349.05
A50: 1 | C50: 기타포괄이익누계액 | E50: 289436.37 | F50: 289436.37 | G50: 290010.93 | H50: 290010.93 | I50: 289956.76 | J50: 290944.16 | K50: 290944.16 | L50: 290944.16 | M50: 290944.16 | N50: 290944.16 | O50: 296792.74 | P50: 296792.74 | Q50: 296792.74 | R50: 296466.16 | S50: 296792.74 | T50: 296407.92 | U50: 296407.92 | V50: 296407.92 | W50: 350681.92 | X50: 350681.92
... A54: 1 | C54: 지배주주지분 | E54: 2156197 | F54: 2156197 | G54: 2128409.8 | H54: 2172672.3 | I54: 2278065.1 | J54: 2121145.6 | K54: 2121145.6 | L54: 2117516.6 | M54: 2078774.1 | N54: 2087616.6 | O54: 1954260.1 | P54: 1954260.1 | Q54: 1956191.5 | R54: 1980117.9 | S54: 1976886.8 | T54: 2016914.6 | U54: 2016914.6 | V54: 2036149.6 | W54: 2106595.5 | X54: 2263501.5
A55: 1 | C55: 총차입금 | E55: 89727.3 | F55: 89727.3 | G55: 62389.81 | H55: 39303.43 | I55: 9919.74 | M55: 159000 | N55: 209000 | O55: 410000 | P55: 410000 | Q55: 319818.88 | R55: 185695.78 | S55: 80000 | T55: 80000 | U55: 80000 | V55: 0 | W55: 0 | X55: 0
A56: 1 | C56: 순차입금 | E56: -436439.35 | F56: -436439.35 | G56: -606017.33 | H56: -727944.02 | I56: -631471.33 | M56: -273732.33 | N56: -276295.91 | O56: 64681.43 | P56: 64681.43 | Q56: -153018.47 | R56: -287783.71 | S56: -271567.5 | T56: -163471.22 | U56: -163471.22 | V56: -426353.58 | W56: -520540.74 | X56: -424979.09
A57: 1 | C57: 이자발생자산 | E57: 539206.66 | F57: 539206.66 | G57: 682205.16 | H57: 781045.47 | I57: 655188.09 | J57: 572533.78 | K57: 572533.78 | L57: 396800.71 | M57: 447832.02 | N57: 500395.6 | O57: 359531.36 | P57: 359531.36 | Q57: 487050.14 | R57: 487692.28 | S57: 365766.79 | T57: 257173.97 | U57: 257173.97 | V57: 440056.33 | W57: 534240.99 | X57: 438679.34
A58: 1 | C58: 장기차입금 | O58: 95671.5 | P58: 95671.5 | Q58: 160000 | R58: 140000 | S58: 80000 | T58: 80000 | U58: 80000 | V58: 0 | W58: 0 | X58: 0
A59: 1 | C59: 장기금융부채(face) | O59: 95671.5 | P59: 95671.5 | Q59: 160000 | R59: 140000 | S59: 80000 | T59: 80000 | U59: 80000 | V59: 0 | W59: 0 | X59: 0
A60: 1 | C60: 매출액(수익) | E60: 853585.77 | G60: 871221.8 | H60: 930654.47 | I60: 876541.78 | J60: 1017379.8 | K60: 3695797.9 | L60: 897635.23 | M60: 1023179.5 | N60: 986317.19 | O60: 1094159.8 | P60: 4001291.7 | Q60: 987722.21 | R60: 1114417.8 | S60: 1061614.2 | T60: 1408812.4 | U60: 4572566.6 | V60: 1166665.3 | W60: 1211425.4 | X60: 1278505.7
A61: 1 | C61: 매출원가 | E61: 901143.68 | G61: 907001.91 | H61: 905192.78 | I61: 838871.9 | J61: 1050620.7 | K61: 3701687.3 | L61: 908411.39 | M61: 1053860.7 | N61: 966701.21 | O61: 1127209.8 | P61: 4056183 | Q61: 966654.54 | R61: 1068882.7 | S61: 997939.85 | T61: 1330224.2 | U61: 4363701.2 | V61: 1072742.5 | W61: 1093852 | X61: 1041878.8
A62: 1 | C62: 매출총이익 | E62: -47557.91 | G62: -35780.11 | H62: 25461.69 | I62: 37669.88 | J62: -33240.9 | K62: -5889.44 | L62: -10776.15 | M62: -30681.2 | N62: 19615.97 | O62: -33049.99 | P62: -54891.37 | Q62: 21067.67 | R62: 45535.11 | S62: 63674.35 | T62: 78588.24 | U62: 208865.37 | V62: 93922.79 | W62: 117573.38 | X62: 236626.86
A63: 1 | C63: 판관비 | E63: 31184.87 | G63: 25666.16 | H63: 26850.61 | I63: 28377.23 | J63: 31609.05 | K63: 112503.05 | L63: 17795 | M63: 27818.7 | N63: 30161.92 | O63: 35547.95 | P63: 111323.57 | Q63: 35537.02 | R63: 35212.76 | S63: 36214.33 | T63: 41763.78 | U63: 148727.89 | V63: 35193.23 | W63: 39694.45 | X63: 46158.62
A64: 1 | C64: 영업이익 | E64: -78742.78 | G64: -61446.28 | H64: -1388.92 | I64: 9292.65 | J64: -64849.95 | K64: -118392.5 | L64: -28571.15 | M64: -58499.9 | N64: -10545.95 | O64: -68597.94 | P64: -166214.94 | Q64: -14469.35 | R64: 10322.35 | S64: 27460.02 | T64: 36824.46 | U64: 60137.48 | V64: 58729.56 | W64: 77878.93 | X64: 190468.24
A65: 1 | C65: 금융수익 | E65: 947.09 | G65: 60810.26 | H65: 104236.82 | I65: 188666.83 | J65: 13960.27 | K65: 367674.18 | L65: 94970.14 | M65: 57863.18 | N65: 65544.53 | O65: 24246.88 | P65: 242624.73 | Q65: 97580.22 | R65: 74935.39 | S65: 196585.53 | T65: 110402.67 | U65: 479503.81 | V65: 47260.04 | W65: 334551.34 | X65: 126126.8
A66: 1 | C66: 금융비용 | E66: 3806.01 | G66: 65995.33 | H66: 194521.33 | I66: 315820.57 | J66: -142461.69 | K66: 433875.54 | L66: 130379.38 | M66: 62819.25 | N66: 127495.4 | O66: -19110.6 | P66: 301583.43 | Q66: 174063.47 | R66: 153784.16 | S66: 113023.25 | T66: 386524.09 | U66: 827394.97 | V66: 70866.55 | W66: 146962.72 | X66: 224792.18
A67: 1 | C67: 기타영업외수익 | E67: 1055.41 | G67: 30159.9 | H67: 152659.55 | I67: 285408.44 | J67: -246424.78 | K67: 221803.11 | L67: 68075.62 | M67: 22400 | N67: 90037.26 | O67: -67747.27 | P67: 112765.61 | Q67: 106947.43 | R67: 103641.84 | S67: 948.8 | T67: 333240.88 | U67: 544778.95 | V67: 28679.44 | W67: 242.34 | X67: 136438.38
A68: 1 | C68: 기타영업외비용 | E68: 23135.64 | G68: 5623.41 | H68: 2281.94 | I68: 28212.7 | J68: 56006.07 | K68: 92124.12 | L68: 8204.16 | M68: 9822.44 | N68: 5051.58 | O68: 28903.41 | P68: 51981.59 | Q68: 13259.39 | R68: 5212.8 | S68: 116311.97 | T68: -1083.57 | U68: 133700.59 | V68: 10007.86 | W68: 248876.31 | X68: 6094.8
A69: 1 | C69: 법인세비용차감전계속사업이익 | E69: -103681.94 | G69: -42094.86 | H69: 58704.19 | I69: 139334.65 | J69: -210858.84 | K69: -54914.86 | L69: -4108.93 | M69: -50878.42 | N69: 12488.85 | O69: -121891.15 | P69: -164389.65 | Q69: 2735.43 | R69: 29902.62 | S69: -4340.86 | T69: 95027.5 | U69: 123324.69 | V69: 53794.63 | W69: 16833.57 | X69: 222146.44
A70: 1 | C70: 법인세비용 | E70: -24581.49 | G70: -10327.58 | H70: 14441.67 | I70: 33941.83 | J70: -51439.86 | K70: -13383.94 | L70: -479.98 | M70: -12135.89 | N70: 3646.37 | O70: -10234.97 | P70: -19204.47 | Q70: 804.06 | R70: 5649.59 | S70: -783.16 | T70: 22888.58 | U70: 28559.07 | V70: 6241.72 | W70: 661.76 | X70: 46095.97
A71: 1 | C71: 당기순이익 | E71: -79100.44 | G71: -31767.28 | H71: 44262.51 | I71: 105392.83 | J71: -159418.98 | K71: -41530.92 | L71: -3628.95 | M71: -38742.53 | N71: 8842.48 | O71: -111656.18 | P71: -145185.18 | Q71: 1931.38 | R71: 24253.03 | S71: -3557.7 | T71: 72138.91 | U71: 94765.62 | V71: 47552.91 | W71: 16171.81 | X71: 176050.47
... A79: 1 | C79: 이자지급(CF) | E79: -263.48 | G79: -252.02 | H79: -256.75 | I79: -214.91 | J79: -141.41 | K79: -865.09 | L79: -96.7 | M79: -1089.7 | N79: -2398.07 | O79: -3021.53 | P79: -6606 | Q79: -6038.22 | R79: -3621.7 | S79: -4586.09 | T79: -1656.04 | U79: -15902.05 | V79: -1867.04 | W79: -163.41 | X79: -160.39
A80: 1 | C80: 배당금수취(CF) | E80: 4291.2 | I80: 0 | J80: 0 | N80: 0 | O80: 0 | S80: 0 | T80: 0 | X80: 0
A81: 1 | C81: 법인세납부(CF) | E81: -358.55 | G81: -475.76 | H81: 129.45 | I81: -648.46 | J81: -413.81 | K81: -1408.58 | L81: -1306.53 | M81: 1278.17 | N81: -662.24 | O81: -757.74 | P81: -1448.34 | Q81: -755.91 | R81: 2906.52 | S81: -788.51 | T81: -662.7 | U81: 699.4 | V81: -551.78 | W81: 1698.82 | X81: -2639.05
A82: 1 | C82: 투자활동으로인한현금흐름 | E82: 68512.8 | G82: 30468.41 | H82: -112931.99 | I82: 23248.94 | J82: 54217.7 | K82: -4996.94 | L82: 22348.4 | M82: -33334.42 | N82: -31331.76 | O82: -30777.45 | P82: -73095.23 | Q82: -23168.09 | R82: -35197.56 | S82: -46981.23 | T82: -27186.78 | U82: -132533.66 | V82: -24553.55 | W82: -28626.94 | X82: -37419.78
A83: 1 | C83: 유형자산의감소 | E83: 58.78 | G83: 29.55 | H83: 83.25 | I83: 280.07 | J83: 210.79 | K83: 603.66 | L83: 1318.53 | M83: 516.25 | N83: 1073.96 | O83: 45.83 | P83: 2954.57 | Q83: 8.59 | R83: 1039.97 | S83: 46.09 | T83: 55.27 | U83: 1149.92 | V83: 21.03 | W83: 22.99 | X83: 106.32
A84: 1 | C84: 무형자산의감소 | E84: 300
A85: 1 | C85: 유형자산의증가 | E85: 11890.55 | G85: 9024.03 | H85: 21848.45 | I85: 25321.31 | J85: 13829.27 | K85: 70023.06 | L85: 7649.1 | M85: 31925.96 | N85: 29640.04 | O85: 27866.58 | P85: 97081.68 | Q85: 22262.22 | R85: 35014.99 | S85: 45888.13 | T85: 22694.09 | U85: 125859.43 | V85: 24301.16 | W85: 27527.86 | X85: 36187.93
A86: 1 | C86: CAPEX | E86: 11890.55 | G86: 9717.13 | H86: 23014.46 | I86: 27031.93 | J86: 15044.99 | K86: 74808.51 | L86: 9225.4 | M86: 34235.52 | N86: 32465.48 | O86: 30877.24 | P86: 106803.64 | Q86: 23000.19 | R86: 36028.51 | S86: 47035.81 | T86: 26117.9 | U86: 132182.41 | V86: 24790.83 | W86: 28344.36 | X86: 37040.01
A87: 1 | C87: 재무활동으로인한현금흐름 | E87: -16287.89 | G87: -28768.51 | H87: -25000 | I87: -28673.72 | J87: -8760.04 | K87: -91202.27 | L87: -289.57 | M87: 158638.99 | N87: 49416.14 | O87: 200619.51 | P87: 408385.07 | Q87: -92124.75 | R87: -136287.44 | S87: -106054.98 | T87: -1249.36 | U87: -335716.53 | V87: -80951.31 | W87: -29300 | X87: -20543.63
A88: 1 | C88: 리스부채의상환 | E88: 484.56 | G88: 272.2 | H88: 284.43 | I88: 468.96 | J88: 449.38 | K88: 1474.97 | L88: 289.57 | M88: 361.01 | N88: 583.86 | O88: 380.49 | P88: 1614.93 | Q88: 1663.62 | R88: 1464.82 | S88: 1338.74 | T88: 1249.35 | U88: 5716.53 | V88: 951.31 | W88: 982.15 | X88: 1399.17
A89: 1 | C89: 현금및현금성자산의증감 | E89: -226871.33 | G89: 171501.47 | H89: -28770.66 | I89: -152417.44 | J89: 68836.33 | K89: 59149.7 | L89: -141405.74 | M89: 60905.89 | N89: 45620.82 | O89: -123433.13 | P89: -158312.16 | Q89: 117201.71 | R89: -26651.25 | S89: -75169.14 | T89: -205413.53 | U89: -190032.21 | V89: 200238.58 | W89: 167700.43 | X89: -126415.73
A90: 1 | C90: 기말현금및현금성자산 | E90: -226871.33 | G90: 544188.39 | H90: -28770.66 | I90: -152417.44 | J90: 68836.33 | K90: 431836.62 | L90: 290430.89 | M90: 60905.89 | N90: 45620.82 | O90: -123433.14 | P90: 273524.46 | Q90: 390726.17 | R90: -26651.25 | S90: -75169.14 | T90: -205413.53 | U90: 83492.25 | V90: 283730.83 | W90: 167700.43 | X90: -126415.73
A91: 1 | C91: 무형자산의증가 | G91: 693.1 | H91: 1166.01 | I91: 1710.62 | J91: 1215.72 | K91: 4785.45 | L91: 1576.3 | M91: 2309.56 | N91: 2825.44 | O91: 3010.66 | P91: 9721.96 | Q91: 737.97 | R91: 1013.52 | S91: 1147.68 | T91: 3423.81 | U91: 6322.98 | V91: 489.67 | W91: 816.5 | X91: 852.08
A92: 1 | C92: 배당금지급 | X92: 19144.46

Sheet subQ
A1: YQ | C1: subQ 분기 서브모델(억원, U=100) | E1: 4Q21 | F1: 2021 | G1: 1Q22 | H1: 2Q22 | I1: 3Q22 | J1: 4Q22 | K1: 2022 | L1: 1Q23 | M1: 2Q23 | N1: 3Q23 | O1: 4Q23 | P1: 2023 | Q1: 1Q24 | R1: 2Q24 | S1: 3Q24 | T1: 4Q24 | U1: 2024 | V1: 1Q25 | W1: 2Q25 | X1: 3Q25 | Y1: 4Q25 | Z1: 2025 | AA1: 1Q26 | AB1: 2Q26 | AC1: 3Q26 | AD1: 4Q26 | AE1: 2026 | AF1: 1Q27 | AG1: 2Q27 | AH1: 3Q27 | AI1: 4Q27 | AJ1: 2027 | AK1: 1Q28 | AL1: 2Q28 | AM1: 3Q28 | AN1: 4Q28 | AO1: 2028
A2: A=이름(key) B=그룹 C=단위 D=FnGuide 계정명(VLOOKUP 키). 확정=VLOOKUP(BS), 추정=변수 가정 참조
E3: 1 | F3: 2 | G3: 3 | H3: 4 | I3: 5 | J3: 6 | K3: 7 | L3: 8 | M3: 9 | N3: 10 | O3: 11 | P3: 12 | Q3: 13 | R3: 14 | S3: 15 | T3: 16 | U3: 17 | V3: 18 | W3: 19 | X3: 20 | Y3: 21 | Z3: 22 | AA3: 23 | AB3: 24 | AC3: 25 | AD3: 26 | AE3: 27 | AF3: 28 | AG3: 29 | AH3: 30 | AI3: 31 | AJ3: 32 | AK3: 33 | AL3: 34 | AM3: 35 | AN3: 36 | AO3: 37
E4: 2021.12 | F4: 2021.12A | G4: 2022.03 | H4: 2022.06 | I4: 2022.09 | J4: 2022.12 | K4: 2022.12A | L4: 2023.03 | M4: 2023.06 | N4: 2023.09 | O4: 2023.12 | P4: 2023.12A | Q4: 2024.03 | R4: 2024.06 | S4: 2024.09 | T4: 2024.12 | U4: 2024.12A | V4: 2025.03 | W4: 2025.06 | X4: 2025.09 | Y4: 2025.12 | Z4: 2025.12A | AA4: 2026.03 | AB4: 2026.06 | AC4: 2026.09 | AD4: 2026.12 | AE4: 2026.12A | AF4: 2027.03 | AG4: 2027.06 | AH4: 2027.09 | AI4: 2027.12 | AJ4: 2027.12A | AK4: 2028.03 | AL4: 2028.06 | AM4: 2028.09 | AN4: 2028.12 | AO4: 2028.12A
A5: 매출액 | B5: 손익 | C5: 억원 | D5: 매출액(수익) | E5: =IFERROR(VLOOKUP($D5,BS연결,MATCH(E$1,BS연결H,0),0)/100,"") | G5: =IFERROR(VLOOKUP($D5,BS연결,MATCH(G$1,BS연결H,0),0)/100,"") | H5: =IFERROR(VLOOKUP($D5,BS연결,MATCH(H$1,BS연결H,0),0)/100,"") | I5: =IFERROR(VLOOKUP($D5,BS연결,MATCH(I$1,BS연결H,0),0)/100,"") | J5: =IFERROR(VLOOKUP($D5,BS연결,MATCH(J$1,BS연결H,0),0)/100,"") | K5: =IFERROR(VLOOKUP($D5,BS연결,MATCH(K$1,BS연결H,0),0)/100,"") | L5: =IFERROR(VLOOKUP($D5,BS연결,MATCH(L$1,BS연결H,0),0)/100,"") | M5: =IFERROR(VLOOKUP($D5,BS연결,MATCH(M$1,BS연결H,0),0)/100,"") | N5: =IFERROR(VLOOKUP($D5,BS연결,MATCH(N$1,BS연결H,0),0)/100,"") | ... X5: =IFERROR(VLOOKUP($D5,BS연결,MATCH(X$1,BS연결H,0),0)/100,"") | Y5: =IFERROR(T5*(1+변수!Y16),"") | Z5: =SUM(V5:Y5) | AA5: =IFERROR(V5*(1+변수!AA16),"") | AB5: =IFERROR(W5*(1+변수!AB16),"") | AC5: =IFERROR(X5*(1+변수!AC16),"") | AD5: =IFERROR(Y5*(1+변수!AD16),"") | AE5: =SUM(AA5:AD5) | AF5: =IFERROR(AA5*(1+변수!AF16),"") | AG5: =IFERROR(AB5*(1+변수!AG16),"") | AH5: =IFERROR(AC5*(1+변수!AH16),"") | AI5: =IFERROR(AD5*(1+변수!AI16),"") | AJ5: =SUM(AF5:AI5) | AK5: =IFERROR(AF5*(1+변수!AK16),"") | AL5: =IFERROR(AG5*(1+변수!AL16),"") | AM5: =IFERROR(AH5*(1+변수!AM16),"") | AN5: =IFERROR(AI5*(1+변수!AN16),"") | AO5: =SUM(AK5:AN5)
A6: 매출원가 | B6: 손익 | C6: 억원 | D6: 매출원가 | E6: =IFERROR(VLOOKUP($D6,BS연결,MATCH(E$1,BS연결H,0),0)/100,"") | G6: =IFERROR(VLOOKUP($D6,BS연결,MATCH(G$1,BS연결H,0),0)/100,"") | H6: =IFERROR(VLOOKUP($D6,BS연결,MATCH(H$1,BS연결H,0),0)/100,"") | I6: =IFERROR(VLOOKUP($D6,BS연결,MATCH(I$1,BS연결H,0),0)/100,"") | J6: =IFERROR(VLOOKUP($D6,BS연결,MATCH(J$1,BS연결H,0),0)/100,"") | K6: =IFERROR(VLOOKUP($D6,BS연결,MATCH(K$1,BS연결H,0),0)/100,"") | L6: =IFERROR(VLOOKUP($D6,BS연결,MATCH(L$1,BS연결H,0),0)/100,"") | M6: =IFERROR(VLOOKUP($D6,BS연결,MATCH(M$1,BS연결H,0),0)/100,"") | N6: =IFERROR(VLOOKUP($D6,BS연결,MATCH(N$1,BS연결H,0),0)/100,"") | ... X6: =IFERROR(VLOOKUP($D6,BS연결,MATCH(X$1,BS연결H,0),0)/100,"") | Y6: =IFERROR(Y5-Y7,"") | Z6: =SUM(V6:Y6) | AA6: =IFERROR(AA5-AA7,"") | AB6: =IFERROR(AB5-AB7,"") | AC6: =IFERROR(AC5-AC7,"") | AD6: =IFERROR(AD5-AD7,"") | AE6: =SUM(AA6:AD6) | AF6: =IFERROR(AF5-AF7,"") | AG6: =IFERROR(AG5-AG7,"") | AH6: =IFERROR(AH5-AH7,"") | AI6: =IFERROR(AI5-AI7,"") | AJ6: =SUM(AF6:AI6) | AK6: =IFERROR(AK5-AK7,"") | AL6: =IFERROR(AL5-AL7,"") | AM6: =IFERROR(AM5-AM7,"") | AN6: =IFERROR(AN5-AN7,"") | AO6: =SUM(AK6:AN6)
A7: 매출총이익 | B7: 손익 | C7: 억원 | D7: 매출총이익 | E7: =IFERROR(VLOOKUP($D7,BS연결,MATCH(E$1,BS연결H,0),0)/100,"") | G7: =IFERROR(VLOOKUP($D7,BS연결,MATCH(G$1,BS연결H,0),0)/100,"") | H7: =IFERROR(VLOOKUP($D7,BS연결,MATCH(H$1,BS연결H,0),0)/100,"") | I7: =IFERROR(VLOOKUP($D7,BS연결,MATCH(I$1,BS연결H,0),0)/100,"") | J7: =IFERROR(VLOOKUP($D7,BS연결,MATCH(J$1,BS연결H,0),0)/100,"") | K7: =IFERROR(VLOOKUP($D7,BS연결,MATCH(K$1,BS연결H,0),0)/100,"") | L7: =IFERROR(VLOOKUP($D7,BS연결,MATCH(L$1,BS연결H,0),0)/100,"") | M7: =IFERROR(VLOOKUP($D7,BS연결,MATCH(M$1,BS연결H,0),0)/100,"") | N7: =IFERROR(VLOOKUP($D7,BS연결,MATCH(N$1,BS연결H,0),0)/100,"") | ... X7: =IFERROR(VLOOKUP($D7,BS연결,MATCH(X$1,BS연결H,0),0)/100,"") | Y7: =IFERROR(Y9+Y8,"") | Z7: =SUM(V7:Y7) | AA7: =IFERROR(AA9+AA8,"") | AB7: =IFERROR(AB9+AB8,"") | AC7: =IFERROR(AC9+AC8,"") | AD7: =IFERROR(AD9+AD8,"") | AE7: =SUM(AA7:AD7) | AF7: =IFERROR(AF9+AF8,"") | AG7: =IFERROR(AG9+AG8,"") | AH7: =IFERROR(AH9+AH8,"") | AI7: =IFERROR(AI9+AI8,"") | AJ7: =SUM(AF7:AI7) | AK7: =IFERROR(AK9+AK8,"") | AL7: =IFERROR(AL9+AL8,"") | AM7: =IFERROR(AM9+AM8,"") | AN7: =IFERROR(AN9+AN8,"") | AO7: =SUM(AK7:AN7)
A8: 판관비 | B8: 손익 | C8: 억원 | D8: 판관비 | E8: =IFERROR(VLOOKUP($D8,BS연결,MATCH(E$1,BS연결H,0),0)/100,"") | G8: =IFERROR(VLOOKUP($D8,BS연결,MATCH(G$1,BS연결H,0),0)/100,"") | H8: =IFERROR(VLOOKUP($D8,BS연결,MATCH(H$1,BS연결H,0),0)/100,"") | I8: =IFERROR(VLOOKUP($D8,BS연결,MATCH(I$1,BS연결H,0),0)/100,"") | J8: =IFERROR(VLOOKUP($D8,BS연결,MATCH(J$1,BS연결H,0),0)/100,"") | K8: =IFERROR(VLOOKUP($D8,BS연결,MATCH(K$1,BS연결H,0),0)/100,"") | L8: =IFERROR(VLOOKUP($D8,BS연결,MATCH(L$1,BS연결H,0),0)/100,"") | M8: =IFERROR(VLOOKUP($D8,BS연결,MATCH(M$1,BS연결H,0),0)/100,"") | N8: =IFERROR(VLOOKUP($D8,BS연결,MATCH(N$1,BS연결H,0),0)/100,"") | ... X8: =IFERROR(VLOOKUP($D8,BS연결,MATCH(X$1,BS연결H,0),0)/100,"") | Y8: =IFERROR(Y5*변수!Y17,"") | Z8: =SUM(V8:Y8) | AA8: =IFERROR(AA5*변수!AA17,"") | AB8: =IFERROR(AB5*변수!AB17,"") | AC8: =IFERROR(AC5*변수!AC17,"") | AD8: =IFERROR(AD5*변수!AD17,"") | AE8: =SUM(AA8:AD8) | AF8: =IFERROR(AF5*변수!AF17,"") | AG8: =IFERROR(AG5*변수!AG17,"") | AH8: =IFERROR(AH5*변수!AH17,"") | AI8: =IFERROR(AI5*변수!AI17,"") | AJ8: =SUM(AF8:AI8) | AK8: =IFERROR(AK5*변수!AK17,"") | AL8: =IFERROR(AL5*변수!AL17,"") | AM8: =IFERROR(AM5*변수!AM17,"") | AN8: =IFERROR(AN5*변수!AN17,"") | AO8: =SUM(AK8:AN8)
A9: 영업이익 | B9: 손익 | C9: 억원 | D9: 영업이익 | E9: =IFERROR(VLOOKUP($D9,BS연결,MATCH(E$1,BS연결H,0),0)/100,"") | G9: =IFERROR(VLOOKUP($D9,BS연결,MATCH(G$1,BS연결H,0),0)/100,"") | H9: =IFERROR(VLOOKUP($D9,BS연결,MATCH(H$1,BS연결H,0),0)/100,"") | I9: =IFERROR(VLOOKUP($D9,BS연결,MATCH(I$1,BS연결H,0),0)/100,"") | J9: =IFERROR(VLOOKUP($D9,BS연결,MATCH(J$1,BS연결H,0),0)/100,"") | K9: =IFERROR(VLOOKUP($D9,BS연결,MATCH(K$1,BS연결H,0),0)/100,"") | L9: =IFERROR(VLOOKUP($D9,BS연결,MATCH(L$1,BS연결H,0),0)/100,"") | M9: =IFERROR(VLOOKUP($D9,BS연결,MATCH(M$1,BS연결H,0),0)/100,"") | N9: =IFERROR(VLOOKUP($D9,BS연결,MATCH(N$1,BS연결H,0),0)/100,"") | ... X9: =IFERROR(VLOOKUP($D9,BS연결,MATCH(X$1,BS연결H,0),0)/100,"") | Y9: =IFERROR(Y5*변수!Y18,"") | Z9: =SUM(V9:Y9) | AA9: =IFERROR(AA5*변수!AA18,"") | AB9: =IFERROR(AB5*변수!AB18,"") | AC9: =IFERROR(AC5*변수!AC18,"") | AD9: =IFERROR(AD5*변수!AD18,"") | AE9: =SUM(AA9:AD9) | AF9: =IFERROR(AF5*변수!AF18,"") | AG9: =IFERROR(AG5*변수!AG18,"") | AH9: =IFERROR(AH5*변수!AH18,"") | AI9: =IFERROR(AI5*변수!AI18,"") | AJ9: =SUM(AF9:AI9) | AK9: =IFERROR(AK5*변수!AK18,"") | AL9: =IFERROR(AL5*변수!AL18,"") | AM9: =IFERROR(AM5*변수!AM18,"") | AN9: =IFERROR(AN5*변수!AN18,"") | AO9: =SUM(AK9:AN9)
A10: OPM | B10: 손익 | C10: % | D10: 영업이익률 | E10: =IFERROR(E9/E5,"") | G10: =IFERROR(G9/G5,"") | H10: =IFERROR(H9/H5,"") | I10: =IFERROR(I9/I5,"") | J10: =IFERROR(J9/J5,"") | K10: =IFERROR(K9/K5,"") | L10: =IFERROR(L9/L5,"") | M10: =IFERROR(M9/M5,"") | N10: =IFERROR(N9/N5,"") | ... AO10: =IFERROR(AO9/AO5,"")
A11: 금융손익 | B11: 손익 | C11: 억원 | D11: 금융손익 | E11: =IFERROR(VLOOKUP($D11,BS연결,MATCH(E$1,BS연결H,0),0)/100,"") | G11: =IFERROR(VLOOKUP($D11,BS연결,MATCH(G$1,BS연결H,0),0)/100,"") | H11: =IFERROR(VLOOKUP($D11,BS연결,MATCH(H$1,BS연결H,0),0)/100,"") | I11: =IFERROR(VLOOKUP($D11,BS연결,MATCH(I$1,BS연결H,0),0)/100,"") | J11: =IFERROR(VLOOKUP($D11,BS연결,MATCH(J$1,BS연결H,0),0)/100,"") | K11: =IFERROR(VLOOKUP($D11,BS연결,MATCH(K$1,BS연결H,0),0)/100,"") | L11: =IFERROR(VLOOKUP($D11,BS연결,MATCH(L$1,BS연결H,0),0)/100,"") | M11: =IFERROR(VLOOKUP($D11,BS연결,MATCH(M$1,BS연결H,0),0)/100,"") | N11: =IFERROR(VLOOKUP($D11,BS연결,MATCH(N$1,BS연결H,0),0)/100,"") | ... X11: =IFERROR(VLOOKUP($D11,BS연결,MATCH(X$1,BS연결H,0),0)/100,"") | Y11: =IFERROR(Y12+Y13+Y14+Y15,"") | Z11: =SUM(V11:Y11) | AA11: =IFERROR(AA12+AA13+AA14+AA15,"") | AB11: =IFERROR(AB12+AB13+AB14+AB15,"") | AC11: =IFERROR(AC12+AC13+AC14+AC15,"") | AD11: =IFERROR(AD12+AD13+AD14+AD15,"") | AE11: =SUM(AA11:AD11) | AF11: =IFERROR(AF12+AF13+AF14+AF15,"") | AG11: =IFERROR(AG12+AG13+AG14+AG15,"") | AH11: =IFERROR(AH12+AH13+AH14+AH15,"") | AI11: =IFERROR(AI12+AI13+AI14+AI15,"") | AJ11: =SUM(AF11:AI11) | AK11: =IFERROR(AK12+AK13+AK14+AK15,"") | AL11: =IFERROR(AL12+AL13+AL14+AL15,"") | AM11: =IFERROR(AM12+AM13+AM14+AM15,"") | AN11: =IFERROR(AN12+AN13+AN14+AN15,"") | AO11: =SUM(AK11:AN11)
A12: 이자손익 | B12: 손익 | C12: 억원 | D12: 이자손익 | G12: =IFERROR(VLOOKUP($D12,BS연결,MATCH(G$1,BS연결H,0),0)/100,"") | H12: =IFERROR(VLOOKUP($D12,BS연결,MATCH(H$1,BS연결H,0),0)/100,"") | I12: =IFERROR(VLOOKUP($D12,BS연결,MATCH(I$1,BS연결H,0),0)/100,"") | J12: =IFERROR(VLOOKUP($D12,BS연결,MATCH(J$1,BS연결H,0),0)/100,"") | K12: =IFERROR(VLOOKUP($D12,BS연결,MATCH(K$1,BS연결H,0),0)/100,"") | L12: =IFERROR(VLOOKUP($D12,BS연결,MATCH(L$1,BS연결H,0),0)/100,"") | M12: =IFERROR(VLOOKUP($D12,BS연결,MATCH(M$1,BS연결H,0),0)/100,"") | N12: =IFERROR(VLOOKUP($D12,BS연결,MATCH(N$1,BS연결H,0),0)/100,"") | ... X12: =IFERROR(VLOOKUP($D12,BS연결,MATCH(X$1,BS연결H,0),0)/100,"") | Y12: =IFERROR((X27*변수!$D$48-X25*변수!$D$49)/4,"") | Z12: =SUM(V12:Y12) | AA12: =IFERROR((Y27*변수!$D$48-Y25*변수!$D$49)/4,"") | AB12: =IFERROR((AA27*변수!$D$48-AA25*변수!$D$49)/4,"") | AC12: =IFERROR((AB27*변수!$D$48-AB25*변수!$D$49)/4,"") | AD12: =IFERROR((AC27*변수!$D$48-AC25*변수!$D$49)/4,"") | AE12: =SUM(AA12:AD12) | AF12: =IFERROR((AD27*변수!$D$48-AD25*변수!$D$49)/4,"") | AG12: =IFERROR((AF27*변수!$D$48-AF25*변수!$D$49)/4,"") | AH12: =IFERROR((AG27*변수!$D$48-AG25*변수!$D$49)/4,"") | AI12: =IFERROR((AH27*변수!$D$48-AH25*변수!$D$49)/4,"") | AJ12: =SUM(AF12:AI12) | AK12: =IFERROR((AI27*변수!$D$48-AI25*변수!$D$49)/4,"") | AL12: =IFERROR((AK27*변수!$D$48-AK25*변수!$D$49)/4,"") | AM12: =IFERROR((AL27*변수!$D$48-AL25*변수!$D$49)/4,"") | AN12: =IFERROR((AM27*변수!$D$48-AM25*변수!$D$49)/4,"") | AO12: =SUM(AK12:AN12)
A13: 외환손익 | B13: 손익 | C13: 억원 | D13: 외환손익(실적만; 추정 환효과는 환관련손익) | G13: =IFERROR((VLOOKUP("외환차익",BS연결,MATCH(G$1,BS연결H,0),0)-VLOOKUP("외환차손",BS연결,MATCH(G$1,BS연결H,0),0)+VLOOKUP("외화환산이익",BS연결,MATCH(G$1,BS연결H,0),0)-VLOOKUP("외화환산손실",BS연결,MATCH(G$1,BS연결H,0),0))/100,"") | H13: =IFERROR((VLOOKUP("외환차익",BS연결,MATCH(H$1,BS연결H,0),0)-VLOOKUP("외환차손",BS연결,MATCH(H$1,BS연결H,0),0)+VLOOKUP("외화환산이익",BS연결,MATCH(H$1,BS연결H,0),0)-VLOOKUP("외화환산손실",BS연결,MATCH(H$1,BS연결H,0),0))/100,"") | I13: =IFERROR((VLOOKUP("외환차익",BS연결,MATCH(I$1,BS연결H,0),0)-VLOOKUP("외환차손",BS연결,MATCH(I$1,BS연결H,0),0)+VLOOKUP("외화환산이익",BS연결,MATCH(I$1,BS연결H,0),0)-VLOOKUP("외화환산손실",BS연결,MATCH(I$1,BS연결H,0),0))/100,"") | J13: =IFERROR((VLOOKUP("외환차익",BS연결,MATCH(J$1,BS연결H,0),0)-VLOOKUP("외환차손",BS연결,MATCH(J$1,BS연결H,0),0)+VLOOKUP("외화환산이익",BS연결,MATCH(J$1,BS연결H,0),0)-VLOOKUP("외화환산손실",BS연결,MATCH(J$1,BS연결H,0),0))/100,"") | K13: =SUM(G13:J13) | L13: =IFERROR((VLOOKUP("외환차익",BS연결,MATCH(L$1,BS연결H,0),0)-VLOOKUP("외환차손",BS연결,MATCH(L$1,BS연결H,0),0)+VLOOKUP("외화환산이익",BS연결,MATCH(L$1,BS연결H,0),0)-VLOOKUP("외화환산손실",BS연결,MATCH(L$1,BS연결H,0),0))/100,"") | M13: =IFERROR((VLOOKUP("외환차익",BS연결,MATCH(M$1,BS연결H,0),0)-VLOOKUP("외환차손",BS연결,MATCH(M$1,BS연결H,0),0)+VLOOKUP("외화환산이익",BS연결,MATCH(M$1,BS연결H,0),0)-VLOOKUP("외화환산손실",BS연결,MATCH(M$1,BS연결H,0),0))/100,"") | N13: =IFERROR((VLOOKUP("외환차익",BS연결,MATCH(N$1,BS연결H,0),0)-VLOOKUP("외환차손",BS연결,MATCH(N$1,BS연결H,0),0)+VLOOKUP("외화환산이익",BS연결,MATCH(N$1,BS연결H,0),0)-VLOOKUP("외화환산손실",BS연결,MATCH(N$1,BS연결H,0),0))/100,"") | O13: =IFERROR((VLOOKUP("외환차익",BS연결,MATCH(O$1,BS연결H,0),0)-VLOOKUP("외환차손",BS연결,MATCH(O$1,BS연결H,0),0)+VLOOKUP("외화환산이익",BS연결,MATCH(O$1,BS연결H,0),0)-VLOOKUP("외화환산손실",BS연결,MATCH(O$1,BS연결H,0),0))/100,"") | P13: =SUM(L13:O13) | Q13: =IFERROR((VLOOKUP("외환차익",BS연결,MATCH(Q$1,BS연결H,0),0)-VLOOKUP("외환차손",BS연결,MATCH(Q$1,BS연결H,0),0)+VLOOKUP("외화환산이익",BS연결,MATCH(Q$1,BS연결H,0),0)-VLOOKUP("외화환산손실",BS연결,MATCH(Q$1,BS연결H,0),0))/100,"") | R13: =IFERROR((VLOOKUP("외환차익",BS연결,MATCH(R$1,BS연결H,0),0)-VLOOKUP("외환차손",BS연결,MATCH(R$1,BS연결H,0),0)+VLOOKUP("외화환산이익",BS연결,MATCH(R$1,BS연결H,0),0)-VLOOKUP("외화환산손실",BS연결,MATCH(R$1,BS연결H,0),0))/100,"") | S13: =IFERROR((VLOOKUP("외환차익",BS연결,MATCH(S$1,BS연결H,0),0)-VLOOKUP("외환차손",BS연결,MATCH(S$1,BS연결H,0),0)+VLOOKUP("외화환산이익",BS연결,MATCH(S$1,BS연결H,0),0)-VLOOKUP("외화환산손실",BS연결,MATCH(S$1,BS연결H,0),0))/100,"") | T13: =IFERROR((VLOOKUP("외환차익",BS연결,MATCH(T$1,BS연결H,0),0)-VLOOKUP("외환차손",BS연결,MATCH(T$1,BS연결H,0),0)+VLOOKUP("외화환산이익",BS연결,MATCH(T$1,BS연결H,0),0)-VLOOKUP("외화환산손실",BS연결,MATCH(T$1,BS연결H,0),0))/100,"") | U13: =SUM(Q13:T13) | V13: =IFERROR((VLOOKUP("외환차익",BS연결,MATCH(V$1,BS연결H,0),0)-VLOOKUP("외환차손",BS연결,MATCH(V$1,BS연결H,0),0)+VLOOKUP("외화환산이익",BS연결,MATCH(V$1,BS연결H,0),0)-VLOOKUP("외화환산손실",BS연결,MATCH(V$1,BS연결H,0),0))/100,"") | W13: =IFERROR((VLOOKUP("외환차익",BS연결,MATCH(W$1,BS연결H,0),0)-VLOOKUP("외환차손",BS연결,MATCH(W$1,BS연결H,0),0)+VLOOKUP("외화환산이익",BS연결,MATCH(W$1,BS연결H,0),0)-VLOOKUP("외화환산손실",BS연결,MATCH(W$1,BS연결H,0),0))/100,"") | X13: =IFERROR((VLOOKUP("외환차익",BS연결,MATCH(X$1,BS연결H,0),0)-VLOOKUP("외환차손",BS연결,MATCH(X$1,BS연결H,0),0)+VLOOKUP("외화환산이익",BS연결,MATCH(X$1,BS연결H,0),0)-VLOOKUP("외화환산손실",BS연결,MATCH(X$1,BS연결H,0),0))/100,"") | Y13: =변수!Y19 | Z13: =SUM(V13:Y13) | AA13: =변수!AA19 | AB13: =변수!AB19 | AC13: =변수!AC19 | AD13: =변수!AD19 | AE13: =SUM(AA13:AD13) | AF13: =변수!AF19 | AG13: =변수!AG19 | AH13: =변수!AH19 | AI13: =변수!AI19 | AJ13: =SUM(AF13:AI13) | AK13: =변수!AK19 | AL13: =변수!AL19 | AM13: =변수!AM19 | AN13: =변수!AN19 | AO13: =SUM(AK13:AN13)
A14: 파생상품손익 | B14: 손익 | C14: 억원 | D14: 파생상품손익 | G14: =IFERROR((VLOOKUP("파생상품이익",BS연결,MATCH(G$1,BS연결H,0),0)-VLOOKUP("파생상품손실",BS연결,MATCH(G$1,BS연결H,0),0))/100,"") | H14: =IFERROR((VLOOKUP("파생상품이익",BS연결,MATCH(H$1,BS연결H,0),0)-VLOOKUP("파생상품손실",BS연결,MATCH(H$1,BS연결H,0),0))/100,"") | I14: =IFERROR((VLOOKUP("파생상품이익",BS연결,MATCH(I$1,BS연결H,0),0)-VLOOKUP("파생상품손실",BS연결,MATCH(I$1,BS연결H,0),0))/100,"") | J14: =IFERROR((VLOOKUP("파생상품이익",BS연결,MATCH(J$1,BS연결H,0),0)-VLOOKUP("파생상품손실",BS연결,MATCH(J$1,BS연결H,0),0))/100,"") | K14: =SUM(G14:J14) | L14: =IFERROR((VLOOKUP("파생상품이익",BS연결,MATCH(L$1,BS연결H,0),0)-VLOOKUP("파생상품손실",BS연결,MATCH(L$1,BS연결H,0),0))/100,"") | M14: =IFERROR((VLOOKUP("파생상품이익",BS연결,MATCH(M$1,BS연결H,0),0)-VLOOKUP("파생상품손실",BS연결,MATCH(M$1,BS연결H,0),0))/100,"") | N14: =IFERROR((VLOOKUP("파생상품이익",BS연결,MATCH(N$1,BS연결H,0),0)-VLOOKUP("파생상품손실",BS연결,MATCH(N$1,BS연결H,0),0))/100,"") | O14: =IFERROR((VLOOKUP("파생상품이익",BS연결,MATCH(O$1,BS연결H,0),0)-VLOOKUP("파생상품손실",BS연결,MATCH(O$1,BS연결H,0),0))/100,"") | P14: =SUM(L14:O14) | Q14: =IFERROR((VLOOKUP("파생상품이익",BS연결,MATCH(Q$1,BS연결H,0),0)-VLOOKUP("파생상품손실",BS연결,MATCH(Q$1,BS연결H,0),0))/100,"") | R14: =IFERROR((VLOOKUP("파생상품이익",BS연결,MATCH(R$1,BS연결H,0),0)-VLOOKUP("파생상품손실",BS연결,MATCH(R$1,BS연결H,0),0))/100,"") | S14: =IFERROR((VLOOKUP("파생상품이익",BS연결,MATCH(S$1,BS연결H,0),0)-VLOOKUP("파생상품손실",BS연결,MATCH(S$1,BS연결H,0),0))/100,"") | T14: =IFERROR((VLOOKUP("파생상품이익",BS연결,MATCH(T$1,BS연결H,0),0)-VLOOKUP("파생상품손실",BS연결,MATCH(T$1,BS연결H,0),0))/100,"") | U14: =SUM(Q14:T14) | V14: =IFERROR((VLOOKUP("파생상품이익",BS연결,MATCH(V$1,BS연결H,0),0)-VLOOKUP("파생상품손실",BS연결,MATCH(V$1,BS연결H,0),0))/100,"") | W14: =IFERROR((VLOOKUP("파생상품이익",BS연결,MATCH(W$1,BS연결H,0),0)-VLOOKUP("파생상품손실",BS연결,MATCH(W$1,BS연결H,0),0))/100,"") | X14: =IFERROR((VLOOKUP("파생상품이익",BS연결,MATCH(X$1,BS연결H,0),0)-VLOOKUP("파생상품손실",BS연결,MATCH(X$1,BS연결H,0),0))/100,"") | Y14: =변수!Y20 | Z14: =SUM(V14:Y14) | AA14: =변수!AA20 | AB14: =변수!AB20 | AC14: =변수!AC20 | AD14: =변수!AD20 | AE14: =SUM(AA14:AD14) | AF14: =변수!AF20 | AG14: =변수!AG20 | AH14: =변수!AH20 | AI14: =변수!AI20 | AJ14: =SUM(AF14:AI14) | AK14: =변수!AK20 | AL14: =변수!AL20 | AM14: =변수!AM20 | AN14: =변수!AN20 | AO14: =SUM(AK14:AN14)
A15: 기타금융손익 | B15: 손익 | C15: 억원 | D15: 기타금융손익(금융손익 잔차) | G15: =IFERROR(G11-G12-G13-G14,"") | H15: =IFERROR(H11-H12-H13-H14,"") | I15: =IFERROR(I11-I12-I13-I14,"") | J15: =IFERROR(J11-J12-J13-J14,"") | K15: =SUM(G15:J15) | L15: =IFERROR(L11-L12-L13-L14,"") | M15: =IFERROR(M11-M12-M13-M14,"") | N15: =IFERROR(N11-N12-N13-N14,"") | O15: =IFERROR(O11-O12-O13-O14,"") | P15: =SUM(L15:O15) | Q15: =IFERROR(Q11-Q12-Q13-Q14,"") | R15: =IFERROR(R11-R12-R13-R14,"") | S15: =IFERROR(S11-S12-S13-S14,"") | T15: =IFERROR(T11-T12-T13-T14,"") | U15: =SUM(Q15:T15) | V15: =IFERROR(V11-V12-V13-V14,"") | W15: =IFERROR(W11-W12-W13-W14,"") | X15: =IFERROR(X11-X12-X13-X14,"") | Y15: =변수!Y21 | Z15: =SUM(V15:Y15) | AA15: =변수!AA21 | AB15: =변수!AB21 | AC15: =변수!AC21 | AD15: =변수!AD21 | AE15: =SUM(AA15:AD15) | AF15: =변수!AF21 | AG15: =변수!AG21 | AH15: =변수!AH21 | AI15: =변수!AI21 | AJ15: =SUM(AF15:AI15) | AK15: =변수!AK21 | AL15: =변수!AL21 | AM15: =변수!AM21 | AN15: =변수!AN21 | AO15: =SUM(AK15:AN15)
A16: 기타영업외손익 | B16: 손익 | C16: 억원 | D16: 기타영업외손익 | E16: =IFERROR(VLOOKUP($D16,BS연결,MATCH(E$1,BS연결H,0),0)/100,"") | G16: =IFERROR(VLOOKUP($D16,BS연결,MATCH(G$1,BS연결H,0),0)/100,"") | H16: =IFERROR(VLOOKUP($D16,BS연결,MATCH(H$1,BS연결H,0),0)/100,"") | I16: =IFERROR(VLOOKUP($D16,BS연결,MATCH(I$1,BS연결H,0),0)/100,"") | J16: =IFERROR(VLOOKUP($D16,BS연결,MATCH(J$1,BS연결H,0),0)/100,"") | K16: =IFERROR(VLOOKUP($D16,BS연결,MATCH(K$1,BS연결H,0),0)/100,"") | L16: =IFERROR(VLOOKUP($D16,BS연결,MATCH(L$1,BS연결H,0),0)/100,"") | M16: =IFERROR(VLOOKUP($D16,BS연결,MATCH(M$1,BS연결H,0),0)/100,"") | N16: =IFERROR(VLOOKUP($D16,BS연결,MATCH(N$1,BS연결H,0),0)/100,"") | ... X16: =IFERROR(VLOOKUP($D16,BS연결,MATCH(X$1,BS연결H,0),0)/100,"") | Y16: =변수!Y22 | Z16: =SUM(V16:Y16) | AA16: =변수!AA22 | AB16: =변수!AB22 | AC16: =변수!AC22 | AD16: =변수!AD22 | AE16: =SUM(AA16:AD16) | AF16: =변수!AF22 | AG16: =변수!AG22 | AH16: =변수!AH22 | AI16: =변수!AI22 | AJ16: =SUM(AF16:AI16) | AK16: =변수!AK22 | AL16: =변수!AL22 | AM16: =변수!AM22 | AN16: =변수!AN22 | AO16: =SUM(AK16:AN16)
A17: 세전이익 | B17: 손익 | C17: 억원 | D17: 법인세비용차감전계속사업이익 | E17: =IFERROR(VLOOKUP($D17,BS연결,MATCH(E$1,BS연결H,0),0)/100,"") | G17: =IFERROR(VLOOKUP($D17,BS연결,MATCH(G$1,BS연결H,0),0)/100,"") | H17: =IFERROR(VLOOKUP($D17,BS연결,MATCH(H$1,BS연결H,0),0)/100,"") | I17: =IFERROR(VLOOKUP($D17,BS연결,MATCH(I$1,BS연결H,0),0)/100,"") | J17: =IFERROR(VLOOKUP($D17,BS연결,MATCH(J$1,BS연결H,0),0)/100,"") | K17: =IFERROR(VLOOKUP($D17,BS연결,MATCH(K$1,BS연결H,0),0)/100,"") | L17: =IFERROR(VLOOKUP($D17,BS연결,MATCH(L$1,BS연결H,0),0)/100,"") | M17: =IFERROR(VLOOKUP($D17,BS연결,MATCH(M$1,BS연결H,0),0)/100,"") | N17: =IFERROR(VLOOKUP($D17,BS연결,MATCH(N$1,BS연결H,0),0)/100,"") | ... X17: =IFERROR(VLOOKUP($D17,BS연결,MATCH(X$1,BS연결H,0),0)/100,"") | Y17: =IFERROR(Y9+Y11+Y16,"") | Z17: =SUM(V17:Y17) | AA17: =IFERROR(AA9+AA11+AA16,"") | AB17: =IFERROR(AB9+AB11+AB16,"") | AC17: =IFERROR(AC9+AC11+AC16,"") | AD17: =IFERROR(AD9+AD11+AD16,"") | AE17: =SUM(AA17:AD17) | AF17: =IFERROR(AF9+AF11+AF16,"") | AG17: =IFERROR(AG9+AG11+AG16,"") | AH17: =IFERROR(AH9+AH11+AH16,"") | AI17: =IFERROR(AI9+AI11+AI16,"") | AJ17: =SUM(AF17:AI17) | AK17: =IFERROR(AK9+AK11+AK16,"") | AL17: =IFERROR(AL9+AL11+AL16,"") | AM17: =IFERROR(AM9+AM11+AM16,"") | AN17: =IFERROR(AN9+AN11+AN16,"") | AO17: =SUM(AK17:AN17)
A18: 법인세비용 | B18: 손익 | C18: 억원 | D18: 법인세비용 | E18: =IFERROR(VLOOKUP($D18,BS연결,MATCH(E$1,BS연결H,0),0)/100,"") | G18: =IFERROR(VLOOKUP($D18,BS연결,MATCH(G$1,BS연결H,0),0)/100,"") | H18: =IFERROR(VLOOKUP($D18,BS연결,MATCH(H$1,BS연결H,0),0)/100,"") | I18: =IFERROR(VLOOKUP($D18,BS연결,MATCH(I$1,BS연결H,0),0)/100,"") | J18: =IFERROR(VLOOKUP($D18,BS연결,MATCH(J$1,BS연결H,0),0)/100,"") | K18: =IFERROR(VLOOKUP($D18,BS연결,MATCH(K$1,BS연결H,0),0)/100,"") | L18: =IFERROR(VLOOKUP($D18,BS연결,MATCH(L$1,BS연결H,0),0)/100,"") | M18: =IFERROR(VLOOKUP($D18,BS연결,MATCH(M$1,BS연결H,0),0)/100,"") | N18: =IFERROR(VLOOKUP($D18,BS연결,MATCH(N$1,BS연결H,0),0)/100,"") | ... T18: =IFERROR(VLOOKUP($D18,BS연결,MATCH(T$1,BS연결H,0),0)/100,"") | U18: =SUM(Q18:T18) | V18: =IFERROR(VLOOKUP($D18,BS연결,MATCH(V$1,BS연결H,0),0)/100,"") | W18: =IFERROR(VLOOKUP($D18,BS연결,MATCH(W$1,BS연결H,0),0)/100,"") | X18: =IFERROR(VLOOKUP($D18,BS연결,MATCH(X$1,BS연결H,0),0)/100,"") | Y18: =IFERROR(MAX(Y17,0)*변수!Y23,"") | Z18: =SUM(V18:Y18) | AA18: =IFERROR(MAX(AA17,0)*변수!AA23,"") | AB18: =IFERROR(MAX(AB17,0)*변수!AB23,"") | AC18: =IFERROR(MAX(AC17,0)*변수!AC23,"") | AD18: =IFERROR(MAX(AD17,0)*변수!AD23,"") | AE18: =SUM(AA18:AD18) | AF18: =IFERROR(MAX(AF17,0)*변수!AF23,"") | AG18: =IFERROR(MAX(AG17,0)*변수!AG23,"") | AH18: =IFERROR(MAX(AH17,0)*변수!AH23,"") | AI18: =IFERROR(MAX(AI17,0)*변수!AI23,"") | AJ18: =SUM(AF18:AI18) | AK18: =IFERROR(MAX(AK17,0)*변수!AK23,"") | AL18: =IFERROR(MAX(AL17,0)*변수!AL23,"") | AM18: =IFERROR(MAX(AM17,0)*변수!AM23,"") | AN18: =IFERROR(MAX(AN17,0)*변수!AN23,"") | AO18: =SUM(AK18:AN18)
A19: 당기순이익 | B19: 손익 | C19: 억원 | D19: 당기순이익 | E19: =IFERROR(VLOOKUP($D19,BS연결,MATCH(E$1,BS연결H,0),0)/100,"") | G19: =IFERROR(VLOOKUP($D19,BS연결,MATCH(G$1,BS연결H,0),0)/100,"") | H19: =IFERROR(VLOOKUP($D19,BS연결,MATCH(H$1,BS연결H,0),0)/100,"") | I19: =IFERROR(VLOOKUP($D19,BS연결,MATCH(I$1,BS연결H,0),0)/100,"") | J19: =IFERROR(VLOOKUP($D19,BS연결,MATCH(J$1,BS연결H,0),0)/100,"") | K19: =IFERROR(VLOOKUP($D19,BS연결,MATCH(K$1,BS연결H,0),0)/100,"") | L19: =IFERROR(VLOOKUP($D19,BS연결,MATCH(L$1,BS연결H,0),0)/100,"") | M19: =IFERROR(VLOOKUP($D19,BS연결,MATCH(M$1,BS연결H,0),0)/100,"") | N19: =IFERROR(VLOOKUP($D19,BS연결,MATCH(N$1,BS연결H,0),0)/100,"") | ... X19: =IFERROR(VLOOKUP($D19,BS연결,MATCH(X$1,BS연결H,0),0)/100,"") | Y19: =IFERROR(Y17-Y18,"") | Z19: =SUM(V19:Y19) | AA19: =IFERROR(AA17-AA18,"") | AB19: =IFERROR(AB17-AB18,"") | AC19: =IFERROR(AC17-AC18,"") | AD19: =IFERROR(AD17-AD18,"") | AE19: =SUM(AA19:AD19) | AF19: =IFERROR(AF17-AF18,"") | AG19: =IFERROR(AG17-AG18,"") | AH19: =IFERROR(AH17-AH18,"") | AI19: =IFERROR(AI17-AI18,"") | AJ19: =SUM(AF19:AI19) | AK19: =IFERROR(AK17-AK18,"") | AL19: =IFERROR(AL17-AL18,"") | AM19: =IFERROR(AM17-AM18,"") | AN19: =IFERROR(AN17-AN18,"") | AO19: =SUM(AK19:AN19)
A20: 지배주주순이익 | B20: 손익 | C20: 억원 | D20: (지배주주지분)당기순이익 | E20: =IFERROR(VLOOKUP($D20,BS연결,MATCH(E$1,BS연결H,0),0)/100,"") | G20: =IFERROR(VLOOKUP($D20,BS연결,MATCH(G$1,BS연결H,0),0)/100,"") | H20: =IFERROR(VLOOKUP($D20,BS연결,MATCH(H$1,BS연결H,0),0)/100,"") | I20: =IFERROR(VLOOKUP($D20,BS연결,MATCH(I$1,BS연결H,0),0)/100,"") | J20: =IFERROR(VLOOKUP($D20,BS연결,MATCH(J$1,BS연결H,0),0)/100,"") | K20: =IFERROR(VLOOKUP($D20,BS연결,MATCH(K$1,BS연결H,0),0)/100,"") | L20: =IFERROR(VLOOKUP($D20,BS연결,MATCH(L$1,BS연결H,0),0)/100,"") | M20: =IFERROR(VLOOKUP($D20,BS연결,MATCH(M$1,BS연결H,0),0)/100,"") | N20: =IFERROR(VLOOKUP($D20,BS연결,MATCH(N$1,BS연결H,0),0)/100,"") | ... X20: =IFERROR(VLOOKUP($D20,BS연결,MATCH(X$1,BS연결H,0),0)/100,"") | Y20: =IFERROR(Y19*변수!Y24,"") | Z20: =SUM(V20:Y20) | AA20: =IFERROR(AA19*변수!AA24,"") | AB20: =IFERROR(AB19*변수!AB24,"") | AC20: =IFERROR(AC19*변수!AC24,"") | AD20: =IFERROR(AD19*변수!AD24,"") | AE20: =SUM(AA20:AD20) | AF20: =IFERROR(AF19*변수!AF24,"") | AG20: =IFERROR(AG19*변수!AG24,"") | AH20: =IFERROR(AH19*변수!AH24,"") | AI20: =IFERROR(AI19*변수!AI24,"") | AJ20: =SUM(AF20:AI20) | AK20: =IFERROR(AK19*변수!AK24,"") | AL20: =IFERROR(AL19*변수!AL24,"") | AM20: =IFERROR(AM19*변수!AM24,"") | AN20: =IFERROR(AN19*변수!AN24,"") | AO20: =SUM(AK20:AN20)
A21: 자산총계 | B21: 재무상태 | C21: 억원 | D21: 자산총계 | E21: =IFERROR(VLOOKUP($D21,BS연결,MATCH(E$1,BS연결H,0),0)/100,"") | F21: =IFERROR(VLOOKUP($D21,BS연결,MATCH(F$1,BS연결H,0),0)/100,"") | G21: =IFERROR(VLOOKUP($D21,BS연결,MATCH(G$1,BS연결H,0),0)/100,"") | H21: =IFERROR(VLOOKUP($D21,BS연결,MATCH(H$1,BS연결H,0),0)/100,"") | I21: =IFERROR(VLOOKUP($D21,BS연결,MATCH(I$1,BS연결H,0),0)/100,"") | J21: =IFERROR(VLOOKUP($D21,BS연결,MATCH(J$1,BS연결H,0),0)/100,"") | K21: =IFERROR(VLOOKUP($D21,BS연결,MATCH(K$1,BS연결H,0),0)/100,"") | L21: =IFERROR(VLOOKUP($D21,BS연결,MATCH(L$1,BS연결H,0),0)/100,"") | ... X21: =IFERROR(VLOOKUP($D21,BS연결,MATCH(X$1,BS연결H,0),0)/100,"") | Y21: =IFERROR(Y22+Y23,"") | Z21: =Y21 | AA21: =IFERROR(AA22+AA23,"") | AB21: =IFERROR(AB22+AB23,"") | AC21: =IFERROR(AC22+AC23,"") | AD21: =IFERROR(AD22+AD23,"") | AE21: =AD21 | AF21: =IFERROR(AF22+AF23,"") | AG21: =IFERROR(AG22+AG23,"") | AH21: =IFERROR(AH22+AH23,"") | AI21: =IFERROR(AI22+AI23,"") | AJ21: =AI21 | AK21: =IFERROR(AK22+AK23,"") | AL21: =IFERROR(AL22+AL23,"") | AM21: =IFERROR(AM22+AM23,"") | AN21: =IFERROR(AN22+AN23,"") | AO21: =AN21
A22: 부채총계 | B22: 재무상태 | C22: 억원 | D22: 부채총계 | E22: =IFERROR(VLOOKUP($D22,BS연결,MATCH(E$1,BS연결H,0),0)/100,"") | F22: =IFERROR(VLOOKUP($D22,BS연결,MATCH(F$1,BS연결H,0),0)/100,"") | G22: =IFERROR(VLOOKUP($D22,BS연결,MATCH(G$1,BS연결H,0),0)/100,"") | H22: =IFERROR(VLOOKUP($D22,BS연결,MATCH(H$1,BS연결H,0),0)/100,"") | I22: =IFERROR(VLOOKUP($D22,BS연결,MATCH(I$1,BS연결H,0),0)/100,"") | J22: =IFERROR(VLOOKUP($D22,BS연결,MATCH(J$1,BS연결H,0),0)/100,"") | K22: =IFERROR(VLOOKUP($D22,BS연결,MATCH(K$1,BS연결H,0),0)/100,"") | L22: =IFERROR(VLOOKUP($D22,BS연결,MATCH(L$1,BS연결H,0),0)/100,"") | ... X22: =IFERROR(VLOOKUP($D22,BS연결,MATCH(X$1,BS연결H,0),0)/100,"") | Y22: =IFERROR(X22*(1+변수!Y25),"") | Z22: =Y22 | AA22: =IFERROR(Y22*(1+변수!AA25),"") | AB22: =IFERROR(AA22*(1+변수!AB25),"") | AC22: =IFERROR(AB22*(1+변수!AC25),"") | AD22: =IFERROR(AC22*(1+변수!AD25),"") | AE22: =AD22 | AF22: =IFERROR(AD22*(1+변수!AF25),"") | AG22: =IFERROR(AF22*(1+변수!AG25),"") | AH22: =IFERROR(AG22*(1+변수!AH25),"") | AI22: =IFERROR(AH22*(1+변수!AI25),"") | AJ22: =AI22 | AK22: =IFERROR(AI22*(1+변수!AK25),"") | AL22: =IFERROR(AK22*(1+변수!AL25),"") | AM22: =IFERROR(AL22*(1+변수!AM25),"") | AN22: =IFERROR(AM22*(1+변수!AN25),"") | AO22: =AN22
A23: 자본총계 | B23: 재무상태 | C23: 억원 | D23: 자본총계 | E23: =IFERROR(VLOOKUP($D23,BS연결,MATCH(E$1,BS연결H,0),0)/100,"") | F23: =IFERROR(VLOOKUP($D23,BS연결,MATCH(F$1,BS연결H,0),0)/100,"") | G23: =IFERROR(VLOOKUP($D23,BS연결,MATCH(G$1,BS연결H,0),0)/100,"") | H23: =IFERROR(VLOOKUP($D23,BS연결,MATCH(H$1,BS연결H,0),0)/100,"") | I23: =IFERROR(VLOOKUP($D23,BS연결,MATCH(I$1,BS연결H,0),0)/100,"") | J23: =IFERROR(VLOOKUP($D23,BS연결,MATCH(J$1,BS연결H,0),0)/100,"") | K23: =IFERROR(VLOOKUP($D23,BS연결,MATCH(K$1,BS연결H,0),0)/100,"") | L23: =IFERROR(VLOOKUP($D23,BS연결,MATCH(L$1,BS연결H,0),0)/100,"") | ... X23: =IFERROR(VLOOKUP($D23,BS연결,MATCH(X$1,BS연결H,0),0)/100,"") | Y23: =IFERROR(X23+Y19-변수!Y26,"") | Z23: =Y23 | AA23: =IFERROR(Y23+AA19-변수!AA26,"") | AB23: =IFERROR(AA23+AB19-변수!AB26,"") | AC23: =IFERROR(AB23+AC19-변수!AC26,"") | AD23: =IFERROR(AC23+AD19-변수!AD26,"") | AE23: =AD23 | AF23: =IFERROR(AD23+AF19-변수!AF26,"") | AG23: =IFERROR(AF23+AG19-변수!AG26,"") | AH23: =IFERROR(AG23+AH19-변수!AH26,"") | AI23: =IFERROR(AH23+AI19-변수!AI26,"") | AJ23: =AI23 | AK23: =IFERROR(AI23+AK19-변수!AK26,"") | AL23: =IFERROR(AK23+AL19-변수!AL26,"") | AM23: =IFERROR(AL23+AM19-변수!AM26,"") | AN23: =IFERROR(AM23+AN19-변수!AN26,"") | AO23: =AN23
A24: 지배주주지분 | B24: 재무상태 | C24: 억원 | D24: 지배주주지분 | E24: =IFERROR(VLOOKUP($D24,BS연결,MATCH(E$1,BS연결H,0),0)/100,"") | F24: =IFERROR(VLOOKUP($D24,BS연결,MATCH(F$1,BS연결H,0),0)/100,"") | G24: =IFERROR(VLOOKUP($D24,BS연결,MATCH(G$1,BS연결H,0),0)/100,"") | H24: =IFERROR(VLOOKUP($D24,BS연결,MATCH(H$1,BS연결H,0),0)/100,"") | I24: =IFERROR(VLOOKUP($D24,BS연결,MATCH(I$1,BS연결H,0),0)/100,"") | J24: =IFERROR(VLOOKUP($D24,BS연결,MATCH(J$1,BS연결H,0),0)/100,"") | K24: =IFERROR(VLOOKUP($D24,BS연결,MATCH(K$1,BS연결H,0),0)/100,"") | L24: =IFERROR(VLOOKUP($D24,BS연결,MATCH(L$1,BS연결H,0),0)/100,"") | ... X24: =IFERROR(VLOOKUP($D24,BS연결,MATCH(X$1,BS연결H,0),0)/100,"") | Y24: =IFERROR(X24+Y20-변수!Y27,"") | Z24: =Y24 | AA24: =IFERROR(Y24+AA20-변수!AA27,"") | AB24: =IFERROR(AA24+AB20-변수!AB27,"") | AC24: =IFERROR(AB24+AC20-변수!AC27,"") | AD24: =IFERROR(AC24+AD20-변수!AD27,"") | AE24: =AD24 | AF24: =IFERROR(AD24+AF20-변수!AF27,"") | AG24: =IFERROR(AF24+AG20-변수!AG27,"") | AH24: =IFERROR(AG24+AH20-변수!AH27,"") | AI24: =IFERROR(AH24+AI20-변수!AI27,"") | AJ24: =AI24 | AK24: =IFERROR(AI24+AK20-변수!AK27,"") | AL24: =IFERROR(AK24+AL20-변수!AL27,"") | AM24: =IFERROR(AL24+AM20-변수!AM27,"") | AN24: =IFERROR(AM24+AN20-변수!AN27,"") | AO24: =AN24
A25: 총차입금 | B25: 재무상태 | C25: 억원 | D25: 총차입금 | E25: =IFERROR(VLOOKUP($D25,BS연결,MATCH(E$1,BS연결H,0),0)/100,"") | F25: =IFERROR(VLOOKUP($D25,BS연결,MATCH(F$1,BS연결H,0),0)/100,"") | G25: =IFERROR(VLOOKUP($D25,BS연결,MATCH(G$1,BS연결H,0),0)/100,"") | H25: =IFERROR(VLOOKUP($D25,BS연결,MATCH(H$1,BS연결H,0),0)/100,"") | I25: =IFERROR(VLOOKUP($D25,BS연결,MATCH(I$1,BS연결H,0),0)/100,"") | J25: =IFERROR(VLOOKUP($D25,BS연결,MATCH(J$1,BS연결H,0),0)/100,"") | K25: =IFERROR(VLOOKUP($D25,BS연결,MATCH(K$1,BS연결H,0),0)/100,"") | L25: =IFERROR(VLOOKUP($D25,BS연결,MATCH(L$1,BS연결H,0),0)/100,"") | ... X25: =IFERROR(VLOOKUP($D25,BS연결,MATCH(X$1,BS연결H,0),0)/100,"") | Y25: =IFERROR(X25*(1+변수!Y28),"") | Z25: =Y25 | AA25: =IFERROR(Y25*(1+변수!AA28),"") | AB25: =IFERROR(AA25*(1+변수!AB28),"") | AC25: =IFERROR(AB25*(1+변수!AC28),"") | AD25: =IFERROR(AC25*(1+변수!AD28),"") | AE25: =AD25 | AF25: =IFERROR(AD25*(1+변수!AF28),"") | AG25: =IFERROR(AF25*(1+변수!AG28),"") | AH25: =IFERROR(AG25*(1+변수!AH28),"") | AI25: =IFERROR(AH25*(1+변수!AI28),"") | AJ25: =AI25 | AK25: =IFERROR(AI25*(1+변수!AK28),"") | AL25: =IFERROR(AK25*(1+변수!AL28),"") | AM25: =IFERROR(AL25*(1+변수!AM28),"") | AN25: =IFERROR(AM25*(1+변수!AN28),"") | AO25: =AN25
A26: 순차입금 | B26: 재무상태 | C26: 억원 | D26: 순차입금 | E26: =IFERROR(VLOOKUP($D26,BS연결,MATCH(E$1,BS연결H,0),0)/100,"") | F26: =IFERROR(VLOOKUP($D26,BS연결,MATCH(F$1,BS연결H,0),0)/100,"") | G26: =IFERROR(VLOOKUP($D26,BS연결,MATCH(G$1,BS연결H,0),0)/100,"") | H26: =IFERROR(VLOOKUP($D26,BS연결,MATCH(H$1,BS연결H,0),0)/100,"") | I26: =IFERROR(VLOOKUP($D26,BS연결,MATCH(I$1,BS연결H,0),0)/100,"") | J26: =IFERROR(VLOOKUP($D26,BS연결,MATCH(J$1,BS연결H,0),0)/100,"") | K26: =IFERROR(VLOOKUP($D26,BS연결,MATCH(K$1,BS연결H,0),0)/100,"") | L26: =IFERROR(VLOOKUP($D26,BS연결,MATCH(L$1,BS연결H,0),0)/100,"") | ... X26: =IFERROR(VLOOKUP($D26,BS연결,MATCH(X$1,BS연결H,0),0)/100,"") | Y26: =IFERROR(X26*(1+변수!Y29),"") | Z26: =Y26 | AA26: =IFERROR(Y26*(1+변수!AA29),"") | AB26: =IFERROR(AA26*(1+변수!AB29),"") | AC26: =IFERROR(AB26*(1+변수!AC29),"") | AD26: =IFERROR(AC26*(1+변수!AD29),"") | AE26: =AD26 | AF26: =IFERROR(AD26*(1+변수!AF29),"") | AG26: =IFERROR(AF26*(1+변수!AG29),"") | AH26: =IFERROR(AG26*(1+변수!AH29),"") | AI26: =IFERROR(AH26*(1+변수!AI29),"") | AJ26: =AI26 | AK26: =IFERROR(AI26*(1+변수!AK29),"") | AL26: =IFERROR(AK26*(1+변수!AL29),"") | AM26: =IFERROR(AL26*(1+변수!AM29),"") | AN26: =IFERROR(AM26*(1+변수!AN29),"") | AO26: =AN26
A27: 이자발생자산 | B27: 재무상태 | C27: 억원 | D27: 이자발생자산 | E27: =IFERROR(VLOOKUP($D27,BS연결,MATCH(E$1,BS연결H,0),0)/100,"") | F27: =IFERROR(VLOOKUP($D27,BS연결,MATCH(F$1,BS연결H,0),0)/100,"") | G27: =IFERROR(VLOOKUP($D27,BS연결,MATCH(G$1,BS연결H,0),0)/100,"") | H27: =IFERROR(VLOOKUP($D27,BS연결,MATCH(H$1,BS연결H,0),0)/100,"") | I27: =IFERROR(VLOOKUP($D27,BS연결,MATCH(I$1,BS연결H,0),0)/100,"") | J27: =IFERROR(VLOOKUP($D27,BS연결,MATCH(J$1,BS연결H,0),0)/100,"") | K27: =IFERROR(VLOOKUP($D27,BS연결,MATCH(K$1,BS연결H,0),0)/100,"") | L27: =IFERROR(VLOOKUP($D27,BS연결,MATCH(L$1,BS연결H,0),0)/100,"") | ... X27: =IFERROR(VLOOKUP($D27,BS연결,MATCH(X$1,BS연결H,0),0)/100,"") | Y27: =IFERROR(X27*(1+변수!Y30),"") | Z27: =Y27 | AA27: =IFERROR(Y27*(1+변수!AA30),"") | AB27: =IFERROR(AA27*(1+변수!AB30),"") | AC27: =IFERROR(AB27*(1+변수!AC30),"") | AD27: =IFERROR(AC27*(1+변수!AD30),"") | AE27: =AD27 | AF27: =IFERROR(AD27*(1+변수!AF30),"") | AG27: =IFERROR(AF27*(1+변수!AG30),"") | AH27: =IFERROR(AG27*(1+변수!AH30),"") | AI27: =IFERROR(AH27*(1+변수!AI30),"") | AJ27: =AI27 | AK27: =IFERROR(AI27*(1+변수!AK30),"") | AL27: =IFERROR(AK27*(1+변수!AL30),"") | AM27: =IFERROR(AL27*(1+변수!AM30),"") | AN27: =IFERROR(AM27*(1+변수!AN30),"") | AO27: =AN27
A28: 현금및현금성자산 | B28: 재무상태 | C28: 억원 | D28: 현금및현금성자산 | E28: =IFERROR(VLOOKUP($D28,BS연결,MATCH(E$1,BS연결H,0),0)/100,"") | F28: =IFERROR(VLOOKUP($D28,BS연결,MATCH(F$1,BS연결H,0),0)/100,"") | G28: =IFERROR(VLOOKUP($D28,BS연결,MATCH(G$1,BS연결H,0),0)/100,"") | H28: =IFERROR(VLOOKUP($D28,BS연결,MATCH(H$1,BS연결H,0),0)/100,"") | I28: =IFERROR(VLOOKUP($D28,BS연결,MATCH(I$1,BS연결H,0),0)/100,"") | J28: =IFERROR(VLOOKUP($D28,BS연결,MATCH(J$1,BS연결H,0),0)/100,"") | K28: =IFERROR(VLOOKUP($D28,BS연결,MATCH(K$1,BS연결H,0),0)/100,"") | L28: =IFERROR(VLOOKUP($D28,BS연결,MATCH(L$1,BS연결H,0),0)/100,"") | ... X28: =IFERROR(VLOOKUP($D28,BS연결,MATCH(X$1,BS연결H,0),0)/100,"") | Z28: =Y28 | AE28: =AD28 | AJ28: =AI28 | AO28: =AN28
A29: CAPEX | B29: 현금흐름 | C29: 억원 | D29: CAPEX | E29: =IFERROR(VLOOKUP($D29,BS연결,MATCH(E$1,BS연결H,0),0)/100,"") | G29: =IFERROR(VLOOKUP($D29,BS연결,MATCH(G$1,BS연결H,0),0)/100,"") | H29: =IFERROR(VLOOKUP($D29,BS연결,MATCH(H$1,BS연결H,0),0)/100,"") | I29: =IFERROR(VLOOKUP($D29,BS연결,MATCH(I$1,BS연결H,0),0)/100,"") | J29: =IFERROR(VLOOKUP($D29,BS연결,MATCH(J$1,BS연결H,0),0)/100,"") | K29: =IFERROR(VLOOKUP($D29,BS연결,MATCH(K$1,BS연결H,0),0)/100,"") | L29: =IFERROR(VLOOKUP($D29,BS연결,MATCH(L$1,BS연결H,0),0)/100,"") | M29: =IFERROR(VLOOKUP($D29,BS연결,MATCH(M$1,BS연결H,0),0)/100,"") | N29: =IFERROR(VLOOKUP($D29,BS연결,MATCH(N$1,BS연결H,0),0)/100,"") | ... X29: =IFERROR(VLOOKUP($D29,BS연결,MATCH(X$1,BS연결H,0),0)/100,"") | Y29: =IFERROR(T29*(1+변수!Y32),"") | Z29: =SUM(V29:Y29) | AA29: =IFERROR(V29*(1+변수!AA32),"") | AB29: =IFERROR(W29*(1+변수!AB32),"") | AC29: =IFERROR(X29*(1+변수!AC32),"") | AD29: =IFERROR(Y29*(1+변수!AD32),"") | AE29: =SUM(AA29:AD29) | AF29: =IFERROR(AA29*(1+변수!AF32),"") | AG29: =IFERROR(AB29*(1+변수!AG32),"") | AH29: =IFERROR(AC29*(1+변수!AH32),"") | AI29: =IFERROR(AD29*(1+변수!AI32),"") | AJ29: =SUM(AF29:AI29) | AK29: =IFERROR(AF29*(1+변수!AK32),"") | AL29: =IFERROR(AG29*(1+변수!AL32),"") | AM29: =IFERROR(AH29*(1+변수!AM32),"") | AN29: =IFERROR(AI29*(1+변수!AN32),"") | AO29: =SUM(AK29:AN29)
A30: 영업활동현금흐름 | B30: 현금흐름 | C30: 억원 | D30: 영업활동으로인한현금흐름 | E30: =IFERROR(VLOOKUP($D30,BS연결,MATCH(E$1,BS연결H,0),0)/100,"") | G30: =IFERROR(VLOOKUP($D30,BS연결,MATCH(G$1,BS연결H,0),0)/100,"") | H30: =IFERROR(VLOOKUP($D30,BS연결,MATCH(H$1,BS연결H,0),0)/100,"") | I30: =IFERROR(VLOOKUP($D30,BS연결,MATCH(I$1,BS연결H,0),0)/100,"") | J30: =IFERROR(VLOOKUP($D30,BS연결,MATCH(J$1,BS연결H,0),0)/100,"") | K30: =IFERROR(VLOOKUP($D30,BS연결,MATCH(K$1,BS연결H,0),0)/100,"") | L30: =IFERROR(VLOOKUP($D30,BS연결,MATCH(L$1,BS연결H,0),0)/100,"") | M30: =IFERROR(VLOOKUP($D30,BS연결,MATCH(M$1,BS연결H,0),0)/100,"") | N30: =IFERROR(VLOOKUP($D30,BS연결,MATCH(N$1,BS연결H,0),0)/100,"") | ... X30: =IFERROR(VLOOKUP($D30,BS연결,MATCH(X$1,BS연결H,0),0)/100,"") | Z30: =SUM(V30:Y30) | AE30: =SUM(AA30:AD30) | AJ30: =SUM(AF30:AI30) | AO30: =SUM(AK30:AN30)
A31: 주식수 | B31: 주당 | C31: 백만주 | D31: 유통주식수 | E31: 39.884 | F31: =E31 | G31: 39.884 | H31: 39.884 | I31: 39.884 | J31: 39.884 | K31: =J31 | L31: 39.884 | M31: 39.884 | N31: 39.884 | O31: 39.884 | P31: =O31 | Q31: 39.884 | R31: 39.884 | S31: 39.884 | T31: 39.884 | U31: =T31 | V31: 39.884 | W31: 39.884 | X31: 39.884 | Y31: =IFERROR(X31*(1+변수!Y34),"") | Z31: =Y31 | AA31: =IFERROR(Y31*(1+변수!AA34),"") | AB31: =IFERROR(AA31*(1+변수!AB34),"") | AC31: =IFERROR(AB31*(1+변수!AC34),"") | AD31: =IFERROR(AC31*(1+변수!AD34),"") | AE31: =AD31 | AF31: =IFERROR(AD31*(1+변수!AF34),"") | AG31: =IFERROR(AF31*(1+변수!AG34),"") | AH31: =IFERROR(AG31*(1+변수!AH34),"") | AI31: =IFERROR(AH31*(1+변수!AI34),"") | AJ31: =AI31 | AK31: =IFERROR(AI31*(1+변수!AK34),"") | AL31: =IFERROR(AK31*(1+변수!AL34),"") | AM31: =IFERROR(AL31*(1+변수!AM34),"") | AN31: =IFERROR(AM31*(1+변수!AN34),"") | AO31: =AN31
A32: EPS | B32: 주당 | C32: 원 | D32: EPS | E32: =IFERROR(E20*100/E31,"") | G32: =IFERROR(G20*100/G31,"") | H32: =IFERROR(H20*100/H31,"") | I32: =IFERROR(I20*100/I31,"") | J32: =IFERROR(J20*100/J31,"") | K32: =SUM(G32:J32) | L32: =IFERROR(L20*100/L31,"") | M32: =IFERROR(M20*100/M31,"") | N32: =IFERROR(N20*100/N31,"") | O32: =IFERROR(O20*100/O31,"") | P32: =SUM(L32:O32) | Q32: =IFERROR(Q20*100/Q31,"") | R32: =IFERROR(R20*100/R31,"") | S32: =IFERROR(S20*100/S31,"") | T32: =IFERROR(T20*100/T31,"") | U32: =SUM(Q32:T32) | V32: =IFERROR(V20*100/V31,"") | W32: =IFERROR(W20*100/W31,"") | X32: =IFERROR(X20*100/X31,"") | Y32: =IFERROR(Y20*100/Y31,"") | Z32: =SUM(V32:Y32) | AA32: =IFERROR(AA20*100/AA31,"") | AB32: =IFERROR(AB20*100/AB31,"") | AC32: =IFERROR(AC20*100/AC31,"") | AD32: =IFERROR(AD20*100/AD31,"") | AE32: =SUM(AA32:AD32) | AF32: =IFERROR(AF20*100/AF31,"") | AG32: =IFERROR(AG20*100/AG31,"") | AH32: =IFERROR(AH20*100/AH31,"") | AI32: =IFERROR(AI20*100/AI31,"") | AJ32: =SUM(AF32:AI32) | AK32: =IFERROR(AK20*100/AK31,"") | AL32: =IFERROR(AL20*100/AL31,"") | AM32: =IFERROR(AM20*100/AM31,"") | AN32: =IFERROR(AN20*100/AN31,"") | AO32: =SUM(AK32:AN32)
A33: BPS | B33: 주당 | C33: 원 | D33: BPS | E33: =IFERROR(E24*100/E31,"") | F33: =E33 | G33: =IFERROR(G24*100/G31,"") | H33: =IFERROR(H24*100/H31,"") | I33: =IFERROR(I24*100/I31,"") | J33: =IFERROR(J24*100/J31,"") | K33: =J33 | L33: =IFERROR(L24*100/L31,"") | M33: =IFERROR(M24*100/M31,"") | N33: =IFERROR(N24*100/N31,"") | O33: =IFERROR(O24*100/O31,"") | P33: =O33 | Q33: =IFERROR(Q24*100/Q31,"") | R33: =IFERROR(R24*100/R31,"") | S33: =IFERROR(S24*100/S31,"") | T33: =IFERROR(T24*100/T31,"") | U33: =T33 | V33: =IFERROR(V24*100/V31,"") | W33: =IFERROR(W24*100/W31,"") | X33: =IFERROR(X24*100/X31,"") | Y33: =IFERROR(Y24*100/Y31,"") | Z33: =Y33 | AA33: =IFERROR(AA24*100/AA31,"") | AB33: =IFERROR(AB24*100/AB31,"") | AC33: =IFERROR(AC24*100/AC31,"") | AD33: =IFERROR(AD24*100/AD31,"") | AE33: =AD33 | AF33: =IFERROR(AF24*100/AF31,"") | AG33: =IFERROR(AG24*100/AG31,"") | AH33: =IFERROR(AH24*100/AH31,"") | AI33: =IFERROR(AI24*100/AI31,"") | AJ33: =AI33 | AK33: =IFERROR(AK24*100/AK31,"") | AL33: =IFERROR(AL24*100/AL31,"") | AM33: =IFERROR(AM24*100/AM31,"") | AN33: =IFERROR(AN24*100/AN31,"") | AO33: =AN33
A34: DPS | B34: 주당 | C34: 원 | D34: DPS(보통주) | E34: 0 | F34: 0 | J34: 0 | K34: =SUM(G34:J34) | O34: 0 | P34: =SUM(L34:O34) | T34: 710 | U34: =SUM(Q34:T34) | Y34: =변수!Y35 | Z34: =SUM(V34:Y34) | AD34: =변수!AD35 | AE34: =SUM(AA34:AD34) | AI34: =변수!AI35 | AJ34: =SUM(AF34:AI34) | AN34: =변수!AN35 | AO34: =SUM(AK34:AN34)
A35: 매출전사 | B35: 사업부 | C35: 억원 | D35: 매출 전사(부문 미분리) | E35: 8605.46 | G35: 8759.59 | H35: 9354.36 | I35: 8822.69 | J35: 10231.97 | K35: =SUM(G35:J35) | L35: 9091.61 | M35: 10333.71 | N35: 9938.01 | O35: 11027.33 | P35: =SUM(L35:O35) | Q35: 10004.94 | R35: 11290.63 | S35: 10776.67 | T35: 14228.25 | U35: =SUM(Q35:T35) | V35: 11838.23 | W35: 12344.48 | X35: 13003.49 | Y35: =IFERROR(Y5,"") | Z35: =SUM(V35:Y35) | AA35: =IFERROR(AA5,"") | AB35: =IFERROR(AB5,"") | AC35: =IFERROR(AC5,"") | AD35: =IFERROR(AD5,"") | AE35: =SUM(AA35:AD35) | AF35: =IFERROR(AF5,"") | AG35: =IFERROR(AG5,"") | AH35: =IFERROR(AH5,"") | AI35: =IFERROR(AI5,"") | AJ35: =SUM(AF35:AI35) | AK35: =IFERROR(AK5,"") | AL35: =IFERROR(AL5,"") | AM35: =IFERROR(AM5,"") | AN35: =IFERROR(AN5,"") | AO35: =SUM(AK35:AN35)
A36: OP전사 | B36: 사업부 | C36: 억원 | D36: OP 전사(부문 미분리) | E36: -770.07 | G36: -618.35 | H36: -66.01 | I36: 140.68 | J36: -546.99 | K36: =SUM(G36:J36) | L36: -274.13 | M36: -524.68 | N36: -78.56 | O36: -651.79 | P36: =SUM(L36:O36) | Q36: -110.44 | R36: 174.24 | S36: 352.5 | T36: 468.97 | U36: =SUM(Q36:T36) | V36: 684.84 | W36: 894.19 | X36: 2008.07 | Y36: =IFERROR(Y9,"") | Z36: =SUM(V36:Y36) | AA36: =IFERROR(AA9,"") | AB36: =IFERROR(AB9,"") | AC36: =IFERROR(AC9,"") | AD36: =IFERROR(AD9,"") | AE36: =SUM(AA36:AD36) | AF36: =IFERROR(AF9,"") | AG36: =IFERROR(AG9,"") | AH36: =IFERROR(AH9,"") | AI36: =IFERROR(AI9,"") | AJ36: =SUM(AF36:AI36) | AK36: =IFERROR(AK9,"") | AL36: =IFERROR(AL9,"") | AM36: =IFERROR(AM9,"") | AN36: =IFERROR(AN9,"") | AO36: =SUM(AK36:AN36)
B37: 비율(참고)
A38: NPM | C38: % | D38: 지배주주순이익 / 매출액 | E38: =IFERROR(E20/E5,"") | F38: =IFERROR(F20/F5,"") | G38: =IFERROR(G20/G5,"") | H38: =IFERROR(H20/H5,"") | I38: =IFERROR(I20/I5,"") | J38: =IFERROR(J20/J5,"") | K38: =IFERROR(K20/K5,"") | L38: =IFERROR(L20/L5,"") | ... AO38: =IFERROR(AO20/AO5,"")
A39: 매출원가율 | C39: % | D39: 매출원가 / 매출액 | E39: =IFERROR(E6/E5,"") | F39: =IFERROR(F6/F5,"") | G39: =IFERROR(G6/G5,"") | H39: =IFERROR(H6/H5,"") | I39: =IFERROR(I6/I5,"") | J39: =IFERROR(J6/J5,"") | K39: =IFERROR(K6/K5,"") | L39: =IFERROR(L6/L5,"") | ... AO39: =IFERROR(AO6/AO5,"")
A40: 판관비율 | C40: % | D40: 판관비 / 매출액 | E40: =IFERROR(E8/E5,"") | F40: =IFERROR(F8/F5,"") | G40: =IFERROR(G8/G5,"") | H40: =IFERROR(H8/H5,"") | I40: =IFERROR(I8/I5,"") | J40: =IFERROR(J8/J5,"") | K40: =IFERROR(K8/K5,"") | L40: =IFERROR(L8/L5,"") | ... AO40: =IFERROR(AO8/AO5,"")

Sheet 분기
C1: 이름: 분기H — subQ 를 이름으로 VLOOKUP(억원) | E1: 4Q21 | F1: 1Q22 | G1: 2Q22 | H1: 3Q22 | I1: 4Q22 | J1: 1Q23 | K1: 2Q23 | L1: 3Q23 | M1: 4Q23 | N1: 1Q24 | O1: 2Q24 | P1: 3Q24 | Q1: 4Q24 | R1: 1Q25 | S1: 2Q25 | T1: 3Q25 | U1: 4Q25 | V1: 1Q26 | W1: 2Q26 | X1: 3Q26 | Y1: 4Q26 | Z1: 1Q27 | AA1: 2Q27 | AB1: 3Q27 | AC1: 4Q27 | AD1: 1Q28 | AE1: 2Q28 | AF1: 3Q28 | AG1: 4Q28
C2: 종가: | D2: =변수!D38
C3: 기준일: | E3: 1 | F3: 2 | G3: 3 | H3: 4 | I3: 5 | J3: 6 | K3: 7 | L3: 8 | M3: 9 | N3: 10 | O3: 11 | P3: 12 | Q3: 13 | R3: 14 | S3: 15 | T3: 16 | U3: 17 | V3: 18 | W3: 19 | X3: 20 | Y3: 21 | Z3: 22 | AA3: 23 | AB3: 24 | AC3: 25 | AD3: 26 | AE3: 27 | AF3: 28 | AG3: 29
E4: 2021.12 | F4: 2022.03 | G4: 2022.06 | H4: 2022.09 | I4: 2022.12 | J4: 2023.03 | K4: 2023.06 | L4: 2023.09 | M4: 2023.12 | N4: 2024.03 | O4: 2024.06 | P4: 2024.09 | Q4: 2024.12 | R4: 2025.03 | S4: 2025.06 | T4: 2025.09 | U4: 2025.12 | V4: 2026.03 | W4: 2026.06 | X4: 2026.09 | Y4: 2026.12 | Z4: 2027.03 | AA4: 2027.06 | AB4: 2027.09 | AC4: 2027.12 | AD4: 2028.03 | AE4: 2028.06 | AF4: 2028.09 | AG4: 2028.12
A5: 매출액 | D5: 매출액 | E5: =IFERROR(VLOOKUP($A5,subQ,MATCH(E$1,SUBQH,0),0),"") | F5: =IFERROR(VLOOKUP($A5,subQ,MATCH(F$1,SUBQH,0),0),"") | G5: =IFERROR(VLOOKUP($A5,subQ,MATCH(G$1,SUBQH,0),0),"") | H5: =IFERROR(VLOOKUP($A5,subQ,MATCH(H$1,SUBQH,0),0),"") | I5: =IFERROR(VLOOKUP($A5,subQ,MATCH(I$1,SUBQH,0),0),"") | J5: =IFERROR(VLOOKUP($A5,subQ,MATCH(J$1,SUBQH,0),0),"") | K5: =IFERROR(VLOOKUP($A5,subQ,MATCH(K$1,SUBQH,0),0),"") | L5: =IFERROR(VLOOKUP($A5,subQ,MATCH(L$1,SUBQH,0),0),"") | ... AG5: =IFERROR(VLOOKUP($A5,subQ,MATCH(AG$1,SUBQH,0),0),"")
A6: 매출원가 | D6: 매출원가 | E6: =IFERROR(VLOOKUP($A6,subQ,MATCH(E$1,SUBQH,0),0),"") | F6: =IFERROR(VLOOKUP($A6,subQ,MATCH(F$1,SUBQH,0),0),"") | G6: =IFERROR(VLOOKUP($A6,subQ,MATCH(G$1,SUBQH,0),0),"") | H6: =IFERROR(VLOOKUP($A6,subQ,MATCH(H$1,SUBQH,0),0),"") | I6: =IFERROR(VLOOKUP($A6,subQ,MATCH(I$1,SUBQH,0),0),"") | J6: =IFERROR(VLOOKUP($A6,subQ,MATCH(J$1,SUBQH,0),0),"") | K6: =IFERROR(VLOOKUP($A6,subQ,MATCH(K$1,SUBQH,0),0),"") | L6: =IFERROR(VLOOKUP($A6,subQ,MATCH(L$1,SUBQH,0),0),"") | ... AG6: =IFERROR(VLOOKUP($A6,subQ,MATCH(AG$1,SUBQH,0),0),"")
A7: 매출총이익 | D7: 매출총이익 | E7: =IFERROR(VLOOKUP($A7,subQ,MATCH(E$1,SUBQH,0),0),"") | F7: =IFERROR(VLOOKUP($A7,subQ,MATCH(F$1,SUBQH,0),0),"") | G7: =IFERROR(VLOOKUP($A7,subQ,MATCH(G$1,SUBQH,0),0),"") | H7: =IFERROR(VLOOKUP($A7,subQ,MATCH(H$1,SUBQH,0),0),"") | I7: =IFERROR(VLOOKUP($A7,subQ,MATCH(I$1,SUBQH,0),0),"") | J7: =IFERROR(VLOOKUP($A7,subQ,MATCH(J$1,SUBQH,0),0),"") | K7: =IFERROR(VLOOKUP($A7,subQ,MATCH(K$1,SUBQH,0),0),"") | L7: =IFERROR(VLOOKUP($A7,subQ,MATCH(L$1,SUBQH,0),0),"") | ... AG7: =IFERROR(VLOOKUP($A7,subQ,MATCH(AG$1,SUBQH,0),0),"")
A8: 판관비 | D8: 판매비와관리비 | E8: =IFERROR(VLOOKUP($A8,subQ,MATCH(E$1,SUBQH,0),0),"") | F8: =IFERROR(VLOOKUP($A8,subQ,MATCH(F$1,SUBQH,0),0),"") | G8: =IFERROR(VLOOKUP($A8,subQ,MATCH(G$1,SUBQH,0),0),"") | H8: =IFERROR(VLOOKUP($A8,subQ,MATCH(H$1,SUBQH,0),0),"") | I8: =IFERROR(VLOOKUP($A8,subQ,MATCH(I$1,SUBQH,0),0),"") | J8: =IFERROR(VLOOKUP($A8,subQ,MATCH(J$1,SUBQH,0),0),"") | K8: =IFERROR(VLOOKUP($A8,subQ,MATCH(K$1,SUBQH,0),0),"") | L8: =IFERROR(VLOOKUP($A8,subQ,MATCH(L$1,SUBQH,0),0),"") | ... AG8: =IFERROR(VLOOKUP($A8,subQ,MATCH(AG$1,SUBQH,0),0),"")
A9: 영업이익 | D9: 영업이익 | E9: =IFERROR(VLOOKUP($A9,subQ,MATCH(E$1,SUBQH,0),0),"") | F9: =IFERROR(VLOOKUP($A9,subQ,MATCH(F$1,SUBQH,0),0),"") | G9: =IFERROR(VLOOKUP($A9,subQ,MATCH(G$1,SUBQH,0),0),"") | H9: =IFERROR(VLOOKUP($A9,subQ,MATCH(H$1,SUBQH,0),0),"") | I9: =IFERROR(VLOOKUP($A9,subQ,MATCH(I$1,SUBQH,0),0),"") | J9: =IFERROR(VLOOKUP($A9,subQ,MATCH(J$1,SUBQH,0),0),"") | K9: =IFERROR(VLOOKUP($A9,subQ,MATCH(K$1,SUBQH,0),0),"") | L9: =IFERROR(VLOOKUP($A9,subQ,MATCH(L$1,SUBQH,0),0),"") | ... AG9: =IFERROR(VLOOKUP($A9,subQ,MATCH(AG$1,SUBQH,0),0),"")
A10: OPM | D10: 영업이익률 | E10: =IFERROR(VLOOKUP($A10,subQ,MATCH(E$1,SUBQH,0),0),"") | F10: =IFERROR(VLOOKUP($A10,subQ,MATCH(F$1,SUBQH,0),0),"") | G10: =IFERROR(VLOOKUP($A10,subQ,MATCH(G$1,SUBQH,0),0),"") | H10: =IFERROR(VLOOKUP($A10,subQ,MATCH(H$1,SUBQH,0),0),"") | I10: =IFERROR(VLOOKUP($A10,subQ,MATCH(I$1,SUBQH,0),0),"") | J10: =IFERROR(VLOOKUP($A10,subQ,MATCH(J$1,SUBQH,0),0),"") | K10: =IFERROR(VLOOKUP($A10,subQ,MATCH(K$1,SUBQH,0),0),"") | L10: =IFERROR(VLOOKUP($A10,subQ,MATCH(L$1,SUBQH,0),0),"") | ... AG10: =IFERROR(VLOOKUP($A10,subQ,MATCH(AG$1,SUBQH,0),0),"")
A11: 금융손익 | D11: 금융손익(이자·환 포함) | E11: =IFERROR(VLOOKUP($A11,subQ,MATCH(E$1,SUBQH,0),0),"") | F11: =IFERROR(VLOOKUP($A11,subQ,MATCH(F$1,SUBQH,0),0),"") | G11: =IFERROR(VLOOKUP($A11,subQ,MATCH(G$1,SUBQH,0),0),"") | H11: =IFERROR(VLOOKUP($A11,subQ,MATCH(H$1,SUBQH,0),0),"") | I11: =IFERROR(VLOOKUP($A11,subQ,MATCH(I$1,SUBQH,0),0),"") | J11: =IFERROR(VLOOKUP($A11,subQ,MATCH(J$1,SUBQH,0),0),"") | K11: =IFERROR(VLOOKUP($A11,subQ,MATCH(K$1,SUBQH,0),0),"") | L11: =IFERROR(VLOOKUP($A11,subQ,MATCH(L$1,SUBQH,0),0),"") | ... AG11: =IFERROR(VLOOKUP($A11,subQ,MATCH(AG$1,SUBQH,0),0),"")
A12: 이자손익 | D12: 이자손익(이자수익 − 이자비용) | E12: =IFERROR(VLOOKUP($A12,subQ,MATCH(E$1,SUBQH,0),0),"") | F12: =IFERROR(VLOOKUP($A12,subQ,MATCH(F$1,SUBQH,0),0),"") | G12: =IFERROR(VLOOKUP($A12,subQ,MATCH(G$1,SUBQH,0),0),"") | H12: =IFERROR(VLOOKUP($A12,subQ,MATCH(H$1,SUBQH,0),0),"") | I12: =IFERROR(VLOOKUP($A12,subQ,MATCH(I$1,SUBQH,0),0),"") | J12: =IFERROR(VLOOKUP($A12,subQ,MATCH(J$1,SUBQH,0),0),"") | K12: =IFERROR(VLOOKUP($A12,subQ,MATCH(K$1,SUBQH,0),0),"") | L12: =IFERROR(VLOOKUP($A12,subQ,MATCH(L$1,SUBQH,0),0),"") | ... AG12: =IFERROR(VLOOKUP($A12,subQ,MATCH(AG$1,SUBQH,0),0),"")
A13: 외환손익 | D13: 외환손익(실적만; 추정 환효과는 환관련손익) | E13: =IFERROR(VLOOKUP($A13,subQ,MATCH(E$1,SUBQH,0),0),"") | F13: =IFERROR(VLOOKUP($A13,subQ,MATCH(F$1,SUBQH,0),0),"") | G13: =IFERROR(VLOOKUP($A13,subQ,MATCH(G$1,SUBQH,0),0),"") | H13: =IFERROR(VLOOKUP($A13,subQ,MATCH(H$1,SUBQH,0),0),"") | I13: =IFERROR(VLOOKUP($A13,subQ,MATCH(I$1,SUBQH,0),0),"") | J13: =IFERROR(VLOOKUP($A13,subQ,MATCH(J$1,SUBQH,0),0),"") | K13: =IFERROR(VLOOKUP($A13,subQ,MATCH(K$1,SUBQH,0),0),"") | L13: =IFERROR(VLOOKUP($A13,subQ,MATCH(L$1,SUBQH,0),0),"") | ... AG13: =IFERROR(VLOOKUP($A13,subQ,MATCH(AG$1,SUBQH,0),0),"")
A14: 파생상품손익 | D14: 파생상품손익 | E14: =IFERROR(VLOOKUP($A14,subQ,MATCH(E$1,SUBQH,0),0),"") | F14: =IFERROR(VLOOKUP($A14,subQ,MATCH(F$1,SUBQH,0),0),"") | G14: =IFERROR(VLOOKUP($A14,subQ,MATCH(G$1,SUBQH,0),0),"") | H14: =IFERROR(VLOOKUP($A14,subQ,MATCH(H$1,SUBQH,0),0),"") | I14: =IFERROR(VLOOKUP($A14,subQ,MATCH(I$1,SUBQH,0),0),"") | J14: =IFERROR(VLOOKUP($A14,subQ,MATCH(J$1,SUBQH,0),0),"") | K14: =IFERROR(VLOOKUP($A14,subQ,MATCH(K$1,SUBQH,0),0),"") | L14: =IFERROR(VLOOKUP($A14,subQ,MATCH(L$1,SUBQH,0),0),"") | ... AG14: =IFERROR(VLOOKUP($A14,subQ,MATCH(AG$1,SUBQH,0),0),"")
A15: 기타금융손익 | D15: 기타금융손익(금융손익 잔차) | E15: =IFERROR(VLOOKUP($A15,subQ,MATCH(E$1,SUBQH,0),0),"") | F15: =IFERROR(VLOOKUP($A15,subQ,MATCH(F$1,SUBQH,0),0),"") | G15: =IFERROR(VLOOKUP($A15,subQ,MATCH(G$1,SUBQH,0),0),"") | H15: =IFERROR(VLOOKUP($A15,subQ,MATCH(H$1,SUBQH,0),0),"") | I15: =IFERROR(VLOOKUP($A15,subQ,MATCH(I$1,SUBQH,0),0),"") | J15: =IFERROR(VLOOKUP($A15,subQ,MATCH(J$1,SUBQH,0),0),"") | K15: =IFERROR(VLOOKUP($A15,subQ,MATCH(K$1,SUBQH,0),0),"") | L15: =IFERROR(VLOOKUP($A15,subQ,MATCH(L$1,SUBQH,0),0),"") | ... AG15: =IFERROR(VLOOKUP($A15,subQ,MATCH(AG$1,SUBQH,0),0),"")
A16: 기타영업외손익 | D16: 기타영업외손익 | E16: =IFERROR(VLOOKUP($A16,subQ,MATCH(E$1,SUBQH,0),0),"") | F16: =IFERROR(VLOOKUP($A16,subQ,MATCH(F$1,SUBQH,0),0),"") | G16: =IFERROR(VLOOKUP($A16,subQ,MATCH(G$1,SUBQH,0),0),"") | H16: =IFERROR(VLOOKUP($A16,subQ,MATCH(H$1,SUBQH,0),0),"") | I16: =IFERROR(VLOOKUP($A16,subQ,MATCH(I$1,SUBQH,0),0),"") | J16: =IFERROR(VLOOKUP($A16,subQ,MATCH(J$1,SUBQH,0),0),"") | K16: =IFERROR(VLOOKUP($A16,subQ,MATCH(K$1,SUBQH,0),0),"") | L16: =IFERROR(VLOOKUP($A16,subQ,MATCH(L$1,SUBQH,0),0),"") | ... AG16: =IFERROR(VLOOKUP($A16,subQ,MATCH(AG$1,SUBQH,0),0),"")
... A37: NPM | D37: NPM | E37: =IFERROR(VLOOKUP($A37,subQ,MATCH(E$1,SUBQH,0),0),"") | F37: =IFERROR(VLOOKUP($A37,subQ,MATCH(F$1,SUBQH,0),0),"") | G37: =IFERROR(VLOOKUP($A37,subQ,MATCH(G$1,SUBQH,0),0),"") | H37: =IFERROR(VLOOKUP($A37,subQ,MATCH(H$1,SUBQH,0),0),"") | I37: =IFERROR(VLOOKUP($A37,subQ,MATCH(I$1,SUBQH,0),0),"") | J37: =IFERROR(VLOOKUP($A37,subQ,MATCH(J$1,SUBQH,0),0),"") | K37: =IFERROR(VLOOKUP($A37,subQ,MATCH(K$1,SUBQH,0),0),"") | L37: =IFERROR(VLOOKUP($A37,subQ,MATCH(L$1,SUBQH,0),0),"") | ... AG37: =IFERROR(VLOOKUP($A37,subQ,MATCH(AG$1,SUBQH,0),0),"")
A38: 매출액 YoY | D38: 매출액 YoY | I38: =IFERROR(I5/E5-1,"") | J38: =IFERROR(J5/F5-1,"") | K38: =IFERROR(K5/G5-1,"") | L38: =IFERROR(L5/H5-1,"") | M38: =IFERROR(M5/I5-1,"") | N38: =IFERROR(N5/J5-1,"") | O38: =IFERROR(O5/K5-1,"") | P38: =IFERROR(P5/L5-1,"") | ... AG38: =IFERROR(AG5/AC5-1,"")
A39: 영업이익 YoY | D39: 영업이익 YoY | I39: =IFERROR(I9/E9-1,"") | J39: =IFERROR(J9/F9-1,"") | K39: =IFERROR(K9/G9-1,"") | L39: =IFERROR(L9/H9-1,"") | M39: =IFERROR(M9/I9-1,"") | N39: =IFERROR(N9/J9-1,"") | O39: =IFERROR(O9/K9-1,"") | P39: =IFERROR(P9/L9-1,"") | ... AG39: =IFERROR(AG9/AC9-1,"")
A40: 지배주주순이익 YoY | D40: 지배주주순이익 YoY | I40: =IFERROR(I20/E20-1,"") | J40: =IFERROR(J20/F20-1,"") | K40: =IFERROR(K20/G20-1,"") | L40: =IFERROR(L20/H20-1,"") | M40: =IFERROR(M20/I20-1,"") | N40: =IFERROR(N20/J20-1,"") | O40: =IFERROR(O20/K20-1,"") | P40: =IFERROR(P20/L20-1,"") | ... AG40: =IFERROR(AG20/AC20-1,"")

Sheet 연간예상
C1: 이름: 연간예상H — subQ 를 이름으로 VLOOKUP(억원) | E1: 2021 | F1: 2022 | G1: 2023 | H1: 2024 | I1: 2025 | J1: 2026 | K1: 2027 | L1: 2028
C2: 종가: | D2: =변수!D38
C3: 기준일: | E3: 1 | F3: 2 | G3: 3 | H3: 4 | I3: 5 | J3: 6 | K3: 7 | L3: 8
E4: 2021.12A | F4: 2022.12A | G4: 2023.12A | H4: 2024.12A | I4: 2025.12A | J4: 2026.12A | K4: 2027.12A | L4: 2028.12A
A5: 매출액 | D5: 매출액 | E5: =IFERROR(VLOOKUP($A5,subQ,MATCH(E$1,SUBQH,0),0),"") | F5: =IFERROR(VLOOKUP($A5,subQ,MATCH(F$1,SUBQH,0),0),"") | G5: =IFERROR(VLOOKUP($A5,subQ,MATCH(G$1,SUBQH,0),0),"") | H5: =IFERROR(VLOOKUP($A5,subQ,MATCH(H$1,SUBQH,0),0),"") | I5: =IFERROR(VLOOKUP($A5,subQ,MATCH(I$1,SUBQH,0),0),"") | J5: =IFERROR(VLOOKUP($A5,subQ,MATCH(J$1,SUBQH,0),0),"") | K5: =IFERROR(VLOOKUP($A5,subQ,MATCH(K$1,SUBQH,0),0),"") | L5: =IFERROR(VLOOKUP($A5,subQ,MATCH(L$1,SUBQH,0),0),"")
A6: 매출원가 | D6: 매출원가 | E6: =IFERROR(VLOOKUP($A6,subQ,MATCH(E$1,SUBQH,0),0),"") | F6: =IFERROR(VLOOKUP($A6,subQ,MATCH(F$1,SUBQH,0),0),"") | G6: =IFERROR(VLOOKUP($A6,subQ,MATCH(G$1,SUBQH,0),0),"") | H6: =IFERROR(VLOOKUP($A6,subQ,MATCH(H$1,SUBQH,0),0),"") | I6: =IFERROR(VLOOKUP($A6,subQ,MATCH(I$1,SUBQH,0),0),"") | J6: =IFERROR(VLOOKUP($A6,subQ,MATCH(J$1,SUBQH,0),0),"") | K6: =IFERROR(VLOOKUP($A6,subQ,MATCH(K$1,SUBQH,0),0),"") | L6: =IFERROR(VLOOKUP($A6,subQ,MATCH(L$1,SUBQH,0),0),"")
A7: 매출총이익 | D7: 매출총이익 | E7: =IFERROR(VLOOKUP($A7,subQ,MATCH(E$1,SUBQH,0),0),"") | F7: =IFERROR(VLOOKUP($A7,subQ,MATCH(F$1,SUBQH,0),0),"") | G7: =IFERROR(VLOOKUP($A7,subQ,MATCH(G$1,SUBQH,0),0),"") | H7: =IFERROR(VLOOKUP($A7,subQ,MATCH(H$1,SUBQH,0),0),"") | I7: =IFERROR(VLOOKUP($A7,subQ,MATCH(I$1,SUBQH,0),0),"") | J7: =IFERROR(VLOOKUP($A7,subQ,MATCH(J$1,SUBQH,0),0),"") | K7: =IFERROR(VLOOKUP($A7,subQ,MATCH(K$1,SUBQH,0),0),"") | L7: =IFERROR(VLOOKUP($A7,subQ,MATCH(L$1,SUBQH,0),0),"")
A8: 판관비 | D8: 판매비와관리비 | E8: =IFERROR(VLOOKUP($A8,subQ,MATCH(E$1,SUBQH,0),0),"") | F8: =IFERROR(VLOOKUP($A8,subQ,MATCH(F$1,SUBQH,0),0),"") | G8: =IFERROR(VLOOKUP($A8,subQ,MATCH(G$1,SUBQH,0),0),"") | H8: =IFERROR(VLOOKUP($A8,subQ,MATCH(H$1,SUBQH,0),0),"") | I8: =IFERROR(VLOOKUP($A8,subQ,MATCH(I$1,SUBQH,0),0),"") | J8: =IFERROR(VLOOKUP($A8,subQ,MATCH(J$1,SUBQH,0),0),"") | K8: =IFERROR(VLOOKUP($A8,subQ,MATCH(K$1,SUBQH,0),0),"") | L8: =IFERROR(VLOOKUP($A8,subQ,MATCH(L$1,SUBQH,0),0),"")
A9: 영업이익 | D9: 영업이익 | E9: =IFERROR(VLOOKUP($A9,subQ,MATCH(E$1,SUBQH,0),0),"") | F9: =IFERROR(VLOOKUP($A9,subQ,MATCH(F$1,SUBQH,0),0),"") | G9: =IFERROR(VLOOKUP($A9,subQ,MATCH(G$1,SUBQH,0),0),"") | H9: =IFERROR(VLOOKUP($A9,subQ,MATCH(H$1,SUBQH,0),0),"") | I9: =IFERROR(VLOOKUP($A9,subQ,MATCH(I$1,SUBQH,0),0),"") | J9: =IFERROR(VLOOKUP($A9,subQ,MATCH(J$1,SUBQH,0),0),"") | K9: =IFERROR(VLOOKUP($A9,subQ,MATCH(K$1,SUBQH,0),0),"") | L9: =IFERROR(VLOOKUP($A9,subQ,MATCH(L$1,SUBQH,0),0),"")
A10: OPM | D10: 영업이익률 | E10: =IFERROR(VLOOKUP($A10,subQ,MATCH(E$1,SUBQH,0),0),"") | F10: =IFERROR(VLOOKUP($A10,subQ,MATCH(F$1,SUBQH,0),0),"") | G10: =IFERROR(VLOOKUP($A10,subQ,MATCH(G$1,SUBQH,0),0),"") | H10: =IFERROR(VLOOKUP($A10,subQ,MATCH(H$1,SUBQH,0),0),"") | I10: =IFERROR(VLOOKUP($A10,subQ,MATCH(I$1,SUBQH,0),0),"") | J10: =IFERROR(VLOOKUP($A10,subQ,MATCH(J$1,SUBQH,0),0),"") | K10: =IFERROR(VLOOKUP($A10,subQ,MATCH(K$1,SUBQH,0),0),"") | L10: =IFERROR(VLOOKUP($A10,subQ,MATCH(L$1,SUBQH,0),0),"")
A11: 금융손익 | D11: 금융손익(이자·환 포함) | E11: =IFERROR(VLOOKUP($A11,subQ,MATCH(E$1,SUBQH,0),0),"") | F11: =IFERROR(VLOOKUP($A11,subQ,MATCH(F$1,SUBQH,0),0),"") | G11: =IFERROR(VLOOKUP($A11,subQ,MATCH(G$1,SUBQH,0),0),"") | H11: =IFERROR(VLOOKUP($A11,subQ,MATCH(H$1,SUBQH,0),0),"") | I11: =IFERROR(VLOOKUP($A11,subQ,MATCH(I$1,SUBQH,0),0),"") | J11: =IFERROR(VLOOKUP($A11,subQ,MATCH(J$1,SUBQH,0),0),"") | K11: =IFERROR(VLOOKUP($A11,subQ,MATCH(K$1,SUBQH,0),0),"") | L11: =IFERROR(VLOOKUP($A11,subQ,MATCH(L$1,SUBQH,0),0),"")
A12: 이자손익 | D12: 이자손익(이자수익 − 이자비용) | E12: =IFERROR(VLOOKUP($A12,subQ,MATCH(E$1,SUBQH,0),0),"") | F12: =IFERROR(VLOOKUP($A12,subQ,MATCH(F$1,SUBQH,0),0),"") | G12: =IFERROR(VLOOKUP($A12,subQ,MATCH(G$1,SUBQH,0),0),"") | H12: =IFERROR(VLOOKUP($A12,subQ,MATCH(H$1,SUBQH,0),0),"") | I12: =IFERROR(VLOOKUP($A12,subQ,MATCH(I$1,SUBQH,0),0),"") | J12: =IFERROR(VLOOKUP($A12,subQ,MATCH(J$1,SUBQH,0),0),"") | K12: =IFERROR(VLOOKUP($A12,subQ,MATCH(K$1,SUBQH,0),0),"") | L12: =IFERROR(VLOOKUP($A12,subQ,MATCH(L$1,SUBQH,0),0),"")
A13: 외환손익 | D13: 외환손익(실적만; 추정 환효과는 환관련손익) | E13: =IFERROR(VLOOKUP($A13,subQ,MATCH(E$1,SUBQH,0),0),"") | F13: =IFERROR(VLOOKUP($A13,subQ,MATCH(F$1,SUBQH,0),0),"") | G13: =IFERROR(VLOOKUP($A13,subQ,MATCH(G$1,SUBQH,0),0),"") | H13: =IFERROR(VLOOKUP($A13,subQ,MATCH(H$1,SUBQH,0),0),"") | I13: =IFERROR(VLOOKUP($A13,subQ,MATCH(I$1,SUBQH,0),0),"") | J13: =IFERROR(VLOOKUP($A13,subQ,MATCH(J$1,SUBQH,0),0),"") | K13: =IFERROR(VLOOKUP($A13,subQ,MATCH(K$1,SUBQH,0),0),"") | L13: =IFERROR(VLOOKUP($A13,subQ,MATCH(L$1,SUBQH,0),0),"")
A14: 파생상품손익 | D14: 파생상품손익 | E14: =IFERROR(VLOOKUP($A14,subQ,MATCH(E$1,SUBQH,0),0),"") | F14: =IFERROR(VLOOKUP($A14,subQ,MATCH(F$1,SUBQH,0),0),"") | G14: =IFERROR(VLOOKUP($A14,subQ,MATCH(G$1,SUBQH,0),0),"") | H14: =IFERROR(VLOOKUP($A14,subQ,MATCH(H$1,SUBQH,0),0),"") | I14: =IFERROR(VLOOKUP($A14,subQ,MATCH(I$1,SUBQH,0),0),"") | J14: =IFERROR(VLOOKUP($A14,subQ,MATCH(J$1,SUBQH,0),0),"") | K14: =IFERROR(VLOOKUP($A14,subQ,MATCH(K$1,SUBQH,0),0),"") | L14: =IFERROR(VLOOKUP($A14,subQ,MATCH(L$1,SUBQH,0),0),"")
A15: 기타금융손익 | D15: 기타금융손익(금융손익 잔차) | E15: =IFERROR(VLOOKUP($A15,subQ,MATCH(E$1,SUBQH,0),0),"") | F15: =IFERROR(VLOOKUP($A15,subQ,MATCH(F$1,SUBQH,0),0),"") | G15: =IFERROR(VLOOKUP($A15,subQ,MATCH(G$1,SUBQH,0),0),"") | H15: =IFERROR(VLOOKUP($A15,subQ,MATCH(H$1,SUBQH,0),0),"") | I15: =IFERROR(VLOOKUP($A15,subQ,MATCH(I$1,SUBQH,0),0),"") | J15: =IFERROR(VLOOKUP($A15,subQ,MATCH(J$1,SUBQH,0),0),"") | K15: =IFERROR(VLOOKUP($A15,subQ,MATCH(K$1,SUBQH,0),0),"") | L15: =IFERROR(VLOOKUP($A15,subQ,MATCH(L$1,SUBQH,0),0),"")
A16: 기타영업외손익 | D16: 기타영업외손익 | E16: =IFERROR(VLOOKUP($A16,subQ,MATCH(E$1,SUBQH,0),0),"") | F16: =IFERROR(VLOOKUP($A16,subQ,MATCH(F$1,SUBQH,0),0),"") | G16: =IFERROR(VLOOKUP($A16,subQ,MATCH(G$1,SUBQH,0),0),"") | H16: =IFERROR(VLOOKUP($A16,subQ,MATCH(H$1,SUBQH,0),0),"") | I16: =IFERROR(VLOOKUP($A16,subQ,MATCH(I$1,SUBQH,0),0),"") | J16: =IFERROR(VLOOKUP($A16,subQ,MATCH(J$1,SUBQH,0),0),"") | K16: =IFERROR(VLOOKUP($A16,subQ,MATCH(K$1,SUBQH,0),0),"") | L16: =IFERROR(VLOOKUP($A16,subQ,MATCH(L$1,SUBQH,0),0),"")
... A37: NPM | D37: NPM | E37: =IFERROR(VLOOKUP($A37,subQ,MATCH(E$1,SUBQH,0),0),"") | F37: =IFERROR(VLOOKUP($A37,subQ,MATCH(F$1,SUBQH,0),0),"") | G37: =IFERROR(VLOOKUP($A37,subQ,MATCH(G$1,SUBQH,0),0),"") | H37: =IFERROR(VLOOKUP($A37,subQ,MATCH(H$1,SUBQH,0),0),"") | I37: =IFERROR(VLOOKUP($A37,subQ,MATCH(I$1,SUBQH,0),0),"") | J37: =IFERROR(VLOOKUP($A37,subQ,MATCH(J$1,SUBQH,0),0),"") | K37: =IFERROR(VLOOKUP($A37,subQ,MATCH(K$1,SUBQH,0),0),"") | L37: =IFERROR(VLOOKUP($A37,subQ,MATCH(L$1,SUBQH,0),0),"")
A38: 매출액 YoY | D38: 매출액 YoY | F38: =IFERROR(F5/E5-1,"") | G38: =IFERROR(G5/F5-1,"") | H38: =IFERROR(H5/G5-1,"") | I38: =IFERROR(I5/H5-1,"") | J38: =IFERROR(J5/I5-1,"") | K38: =IFERROR(K5/J5-1,"") | L38: =IFERROR(L5/K5-1,"")
A39: 영업이익 YoY | D39: 영업이익 YoY | F39: =IFERROR(F9/E9-1,"") | G39: =IFERROR(G9/F9-1,"") | H39: =IFERROR(H9/G9-1,"") | I39: =IFERROR(I9/H9-1,"") | J39: =IFERROR(J9/I9-1,"") | K39: =IFERROR(K9/J9-1,"") | L39: =IFERROR(L9/K9-1,"")
A40: 지배주주순이익 YoY | D40: 지배주주순이익 YoY | F40: =IFERROR(F20/E20-1,"") | G40: =IFERROR(G20/F20-1,"") | H40: =IFERROR(H20/G20-1,"") | I40: =IFERROR(I20/H20-1,"") | J40: =IFERROR(J20/I20-1,"") | K40: =IFERROR(K20/J20-1,"") | L40: =IFERROR(L20/K20-1,"")

Sheet TP
B1: 종가 | C1: =변수!D38
B2: 기준일 | C2: =변수!D39
B3: 모델 산출값 — 목표주가·추천 아님. 밴드·COE 는 변수 시트 3절의 가정
C5: FY | D5: 2024 | E5: 2025 | F5: 2026 | G5: 2027
D6: A | E6: E | F6: E | G6: E
C7: EPS(원) | D7: =IFERROR(VLOOKUP("EPS",subQ,MATCH(D$5,SUBQH,0),0),"") | E7: =IFERROR(VLOOKUP("EPS",subQ,MATCH(E$5,SUBQH,0),0),"") | F7: =IFERROR(VLOOKUP("EPS",subQ,MATCH(F$5,SUBQH,0),0),"") | G7: =IFERROR(VLOOKUP("EPS",subQ,MATCH(G$5,SUBQH,0),0),"")
C8: BPS(원) | D8: =IFERROR(VLOOKUP("BPS",subQ,MATCH(D$5,SUBQH,0),0),"") | E8: =IFERROR(VLOOKUP("BPS",subQ,MATCH(E$5,SUBQH,0),0),"") | F8: =IFERROR(VLOOKUP("BPS",subQ,MATCH(F$5,SUBQH,0),0),"") | G8: =IFERROR(VLOOKUP("BPS",subQ,MATCH(G$5,SUBQH,0),0),"")
C9: 지배주주순이익(억원) | D9: =IFERROR(VLOOKUP("지배주주순이익",subQ,MATCH(D$5,SUBQH,0),0),"") | E9: =IFERROR(VLOOKUP("지배주주순이익",subQ,MATCH(E$5,SUBQH,0),0),"") | F9: =IFERROR(VLOOKUP("지배주주순이익",subQ,MATCH(F$5,SUBQH,0),0),"") | G9: =IFERROR(VLOOKUP("지배주주순이익",subQ,MATCH(G$5,SUBQH,0),0),"")
C10: 영업이익(억원) | D10: =IFERROR(VLOOKUP("영업이익",subQ,MATCH(D$5,SUBQH,0),0),"") | E10: =IFERROR(VLOOKUP("영업이익",subQ,MATCH(E$5,SUBQH,0),0),"") | F10: =IFERROR(VLOOKUP("영업이익",subQ,MATCH(F$5,SUBQH,0),0),"") | G10: =IFERROR(VLOOKUP("영업이익",subQ,MATCH(G$5,SUBQH,0),0),"")
C11: ROE(EPS/기초BPS) | E11: =IFERROR(E7/D8,"") | F11: =IFERROR(F7/E8,"") | G11: =IFERROR(G7/F8,"")
B13: PER
C14: 12M fwd EPS | D14: =IFERROR(E7*변수!D44+F7*(1-변수!D44),"")
C15: 적정가치 @PER_lo | D15: =변수!D41 | E15: =IFERROR(ROUND($D$14*D15,-2),"") | F15: =IFERROR(E15/$C$1-1,"") | G15: 배 · 원 · 종가 대비
C16: 적정가치 @PER_mid | D16: =변수!D42 | E16: =IFERROR(ROUND($D$14*D16,-2),"") | F16: =IFERROR(E16/$C$1-1,"") | G16: 배 · 원 · 종가 대비
C17: 적정가치 @PER_hi | D17: =변수!D43 | E17: =IFERROR(ROUND($D$14*D17,-2),"") | F17: =IFERROR(E17/$C$1-1,"") | G17: 배 · 원 · 종가 대비
C18: 현재 PER(종가/12M fwd EPS) | D18: =IFERROR($C$1/$D$14,"")
B20: PBR
C21: 최근 BPS(마지막 실적 분기) | D21: =IFERROR(VLOOKUP("BPS",subQ,MATCH("3Q25",SUBQH,0),0),"")
C22: ROE fwd(12M fwd EPS / BPS) | D22: =IFERROR($D$14/$D$21,"")
C23: COE | D23: =변수!D40
C24: 적정 PBR = ROE/COE | D24: =IFERROR(D22/D23,"")
C25: 적정가치(PBR) = BPS × 적정PBR | D25: =IFERROR(ROUND(D21*D24,-2),"") | E25: =IFERROR(D25/$C$1-1,"")
C26: 현재 PBR(종가/BPS) | D26: =IFERROR($C$1/D21,"")
B28: 모델 json valuation(참고)
C29: eps_fwd12m | D29: 4176.8
C30: bps_latest | D30: 57756.3
C31: per_now
C32: pbr_now
C33: roe_fwd | D33: 0.0723
C34: fair_pbr | D34: 0.8
C35: fair_value_pbr | D35: 46200
C36: ev_ebitda
C37: note | D37: 모델 산출값 — 목표주가·추천 아님

Sheet 외화
C1: 이름: 외화QH — 환율 QoQ · 외화 순노출 × Δ기말환율 | E1: 4Q21 | F1: 1Q22 | G1: 2Q22 | H1: 3Q22 | I1: 4Q22 | J1: 1Q23 | K1: 2Q23 | L1: 3Q23 | M1: 4Q23 | N1: 1Q24 | O1: 2Q24 | P1: 3Q24 | Q1: 4Q24 | R1: 1Q25 | S1: 2Q25 | T1: 3Q25 | U1: 4Q25 | V1: 1Q26 | W1: 2Q26 | X1: 3Q26 | Y1: 4Q26 | Z1: 1Q27 | AA1: 2Q27 | AB1: 3Q27 | AC1: 4Q27 | AD1: 1Q28 | AE1: 2Q28 | AF1: 3Q28 | AG1: 4Q28
E3: 1 | F3: 2 | G3: 3 | H3: 4 | I3: 5 | J3: 6 | K3: 7 | L3: 8 | M3: 9 | N3: 10 | O3: 11 | P3: 12 | Q3: 13 | R3: 14 | S3: 15 | T3: 16 | U3: 17 | V3: 18 | W3: 19 | X3: 20 | Y3: 21 | Z3: 22 | AA3: 23 | AB3: 24 | AC3: 25 | AD3: 26 | AE3: 27 | AF3: 28 | AG3: 29
E4: 2021.12 | F4: 2022.03 | G4: 2022.06 | H4: 2022.09 | I4: 2022.12 | J4: 2023.03 | K4: 2023.06 | L4: 2023.09 | M4: 2023.12 | N4: 2024.03 | O4: 2024.06 | P4: 2024.09 | Q4: 2024.12 | R4: 2025.03 | S4: 2025.06 | T4: 2025.09 | U4: 2025.12 | V4: 2026.03 | W4: 2026.06 | X4: 2026.09 | Y4: 2026.12 | Z4: 2027.03 | AA4: 2027.06 | AB4: 2027.09 | AC4: 2027.12 | AD4: 2028.03 | AE4: 2028.06 | AF4: 2028.09 | AG4: 2028.12
D5: 원/달러(평균) | E5: =IFERROR(VLOOKUP($D5,환율,MATCH(E$1,변수H,0),0),"") | F5: =IFERROR(VLOOKUP($D5,환율,MATCH(F$1,변수H,0),0),"") | G5: =IFERROR(VLOOKUP($D5,환율,MATCH(G$1,변수H,0),0),"") | H5: =IFERROR(VLOOKUP($D5,환율,MATCH(H$1,변수H,0),0),"") | I5: =IFERROR(VLOOKUP($D5,환율,MATCH(I$1,변수H,0),0),"") | J5: =IFERROR(VLOOKUP($D5,환율,MATCH(J$1,변수H,0),0),"") | K5: =IFERROR(VLOOKUP($D5,환율,MATCH(K$1,변수H,0),0),"") | L5: =IFERROR(VLOOKUP($D5,환율,MATCH(L$1,변수H,0),0),"") | ... AG5: =IFERROR(VLOOKUP($D5,환율,MATCH(AG$1,변수H,0),0),"")
A6: 원/달러(평균) QoQ | F6: =IFERROR(F5/E5-1,"") | G6: =IFERROR(G5/F5-1,"") | H6: =IFERROR(H5/G5-1,"") | I6: =IFERROR(I5/H5-1,"") | J6: =IFERROR(J5/I5-1,"") | K6: =IFERROR(K5/J5-1,"") | L6: =IFERROR(L5/K5-1,"") | M6: =IFERROR(M5/L5-1,"") | ... AG6: =IFERROR(AG5/AF5-1,"")
D7: 원/달러(기말) | E7: =IFERROR(VLOOKUP($D7,환율,MATCH(E$1,변수H,0),0),"") | F7: =IFERROR(VLOOKUP($D7,환율,MATCH(F$1,변수H,0),0),"") | G7: =IFERROR(VLOOKUP($D7,환율,MATCH(G$1,변수H,0),0),"") | H7: =IFERROR(VLOOKUP($D7,환율,MATCH(H$1,변수H,0),0),"") | I7: =IFERROR(VLOOKUP($D7,환율,MATCH(I$1,변수H,0),0),"") | J7: =IFERROR(VLOOKUP($D7,환율,MATCH(J$1,변수H,0),0),"") | K7: =IFERROR(VLOOKUP($D7,환율,MATCH(K$1,변수H,0),0),"") | L7: =IFERROR(VLOOKUP($D7,환율,MATCH(L$1,변수H,0),0),"") | ... AG7: =IFERROR(VLOOKUP($D7,환율,MATCH(AG$1,변수H,0),0),"")
A8: 원/달러(기말) QoQ | F8: =IFERROR(F7/E7-1,"") | G8: =IFERROR(G7/F7-1,"") | H8: =IFERROR(H7/G7-1,"") | I8: =IFERROR(I7/H7-1,"") | J8: =IFERROR(J7/I7-1,"") | K8: =IFERROR(K7/J7-1,"") | L8: =IFERROR(L7/K7-1,"") | M8: =IFERROR(M7/L7-1,"") | ... AG8: =IFERROR(AG7/AF7-1,"")
D9: W/Euro(평균) | E9: =IFERROR(VLOOKUP($D9,환율,MATCH(E$1,변수H,0),0),"") | F9: =IFERROR(VLOOKUP($D9,환율,MATCH(F$1,변수H,0),0),"") | G9: =IFERROR(VLOOKUP($D9,환율,MATCH(G$1,변수H,0),0),"") | H9: =IFERROR(VLOOKUP($D9,환율,MATCH(H$1,변수H,0),0),"") | I9: =IFERROR(VLOOKUP($D9,환율,MATCH(I$1,변수H,0),0),"") | J9: =IFERROR(VLOOKUP($D9,환율,MATCH(J$1,변수H,0),0),"") | K9: =IFERROR(VLOOKUP($D9,환율,MATCH(K$1,변수H,0),0),"") | L9: =IFERROR(VLOOKUP($D9,환율,MATCH(L$1,변수H,0),0),"") | ... AG9: =IFERROR(VLOOKUP($D9,환율,MATCH(AG$1,변수H,0),0),"")
A10: W/Euro(평균) QoQ | F10: =IFERROR(F9/E9-1,"") | G10: =IFERROR(G9/F9-1,"") | H10: =IFERROR(H9/G9-1,"") | I10: =IFERROR(I9/H9-1,"") | J10: =IFERROR(J9/I9-1,"") | K10: =IFERROR(K9/J9-1,"") | L10: =IFERROR(L9/K9-1,"") | M10: =IFERROR(M9/L9-1,"") | ... AG10: =IFERROR(AG9/AF9-1,"")
D11: W/Euro(기말) | E11: =IFERROR(VLOOKUP($D11,환율,MATCH(E$1,변수H,0),0),"") | F11: =IFERROR(VLOOKUP($D11,환율,MATCH(F$1,변수H,0),0),"") | G11: =IFERROR(VLOOKUP($D11,환율,MATCH(G$1,변수H,0),0),"") | H11: =IFERROR(VLOOKUP($D11,환율,MATCH(H$1,변수H,0),0),"") | I11: =IFERROR(VLOOKUP($D11,환율,MATCH(I$1,변수H,0),0),"") | J11: =IFERROR(VLOOKUP($D11,환율,MATCH(J$1,변수H,0),0),"") | K11: =IFERROR(VLOOKUP($D11,환율,MATCH(K$1,변수H,0),0),"") | L11: =IFERROR(VLOOKUP($D11,환율,MATCH(L$1,변수H,0),0),"") | ... AG11: =IFERROR(VLOOKUP($D11,환율,MATCH(AG$1,변수H,0),0),"")
A12: W/Euro(기말) QoQ | F12: =IFERROR(F11/E11-1,"") | G12: =IFERROR(G11/F11-1,"") | H12: =IFERROR(H11/G11-1,"") | I12: =IFERROR(I11/H11-1,"") | J12: =IFERROR(J11/I11-1,"") | K12: =IFERROR(K11/J11-1,"") | L12: =IFERROR(L11/K11-1,"") | M12: =IFERROR(M11/L11-1,"") | ... AG12: =IFERROR(AG11/AF11-1,"")
D13: 원/100Y(기말) | E13: =IFERROR(VLOOKUP($D13,환율,MATCH(E$1,변수H,0),0),"") | F13: =IFERROR(VLOOKUP($D13,환율,MATCH(F$1,변수H,0),0),"") | G13: =IFERROR(VLOOKUP($D13,환율,MATCH(G$1,변수H,0),0),"") | H13: =IFERROR(VLOOKUP($D13,환율,MATCH(H$1,변수H,0),0),"") | I13: =IFERROR(VLOOKUP($D13,환율,MATCH(I$1,변수H,0),0),"") | J13: =IFERROR(VLOOKUP($D13,환율,MATCH(J$1,변수H,0),0),"") | K13: =IFERROR(VLOOKUP($D13,환율,MATCH(K$1,변수H,0),0),"") | L13: =IFERROR(VLOOKUP($D13,환율,MATCH(L$1,변수H,0),0),"") | ... AG13: =IFERROR(VLOOKUP($D13,환율,MATCH(AG$1,변수H,0),0),"")
A14: 원/100Y(기말) QoQ | F14: =IFERROR(F13/E13-1,"") | G14: =IFERROR(G13/F13-1,"") | H14: =IFERROR(H13/G13-1,"") | I14: =IFERROR(I13/H13-1,"") | J14: =IFERROR(J13/I13-1,"") | K14: =IFERROR(K13/J13-1,"") | L14: =IFERROR(L13/K13-1,"") | M14: =IFERROR(M13/L13-1,"") | ... AG14: =IFERROR(AG13/AF13-1,"")
A16: 외화순노출 | C16: 외화 순노출(백만$) | D16: =변수!D51 | E16: 외화 순노출 × Δ기말환율 (외화 시트 방식)
A17: 환관련손익추정 | C17: 환관련손익 추정(억원) = 순노출 × Δ원/달러(기말) / 100 | F17: =IFERROR($D$16*(F7-E7)/100,"") | G17: =IFERROR($D$16*(G7-F7)/100,"") | H17: =IFERROR($D$16*(H7-G7)/100,"") | I17: =IFERROR($D$16*(I7-H7)/100,"") | J17: =IFERROR($D$16*(J7-I7)/100,"") | K17: =IFERROR($D$16*(K7-J7)/100,"") | L17: =IFERROR($D$16*(L7-K7)/100,"") | M17: =IFERROR($D$16*(M7-L7)/100,"") | ... AG17: =IFERROR($D$16*(AG7-AF7)/100,"")
A18: fx_pnl.by_q | C18: 모델 fx_pnl.by_q(억원, 참고)
C19: 외화 순노출 미공시(face) → 0 + 표기
