Workbook
Name 변수H: 변수!$C$1:$AO$1
Name 환율: 변수!$C$6:$AO$13
Name BS연결H: BS연결!$C$1:$AO$1
Name BS연결: BS연결!$C$5:$AO$95
Name BS별도H: BS별도!$C$1:$AO$1
Name BS별도: BS별도!$C$5:$AO$84
Name SUBQH: subQ!$A$1:$AO$1
Name subQ: subQ!$A$5:$AO$39

Sheet README
A1: 한신기계공업(011700) 실적 모델 — ARGUS 한국조선
A2: 기준 분기 2026Q2 · 마지막 실적 2026Q2 · 생성 2026-10-13
A3: 모든 수치는 모델 산출값(DART 공개 재무제표 + 우리 추정)이다 — 목표주가·투자 추천 아님. 참고용 · 투자조언 아님.
A5: 시트
A6: 변수 가정 시계열. 환율 8행(ECB via frankfurter — L2 fx.json; 추정 분기 = 노란 가정), 추정 드라이버(노란 셀 = 모델값에서 역산한 가정, 바꾸면 재계산; 연녹 셀 = 3절 스칼라 참조 수식), 3절 스칼라 가정(세율·판관비율·지배주주비중·이자율·종가·PER 밴드·COE·외화 순노출·헤지비율)
A7: BS연결/BS별도 FnGuide 계정명 × 기간 값 덤프(백만원). 행1 분기라벨, 행4 YYYY.MM / YYYY.12A. 이름정의 BS연결H·BS연결(계정명 C열부터)
A8: subQ 분기 서브모델(억원 = 백만원/100). 확정 행: =IFERROR(VLOOKUP($D행,BS연결,MATCH(E$1,BS연결H,0),0)/100,"") 추정 행: 변수 시트 가정 셀 참조 수식. 외환손익·파생상품손익은 BS 계정 합·차, 기타금융손익은 잔차, OPM·EPS·BPS·PER·PBR 은 파생 수식
A9: SLS 선표(조선사만, sls json 있을 때): 요약 행(sls 저장값) + 계약별 스케줄(백만$) × (헤지비율 × 헤지환율 + (1−헤지비율) × 건조시점 환율[변수 원/달러(평균)]) → 원화 수식 블록 → 합계 행이 subQ 매출조선에 연결
A10: 시나리오 신규수주 보수/기준/낙관(forecast_panel 패널, 모델에 scenarios 가 있을 때만): 매출액·영업이익 = subQ 기준값 ± (시나리오 신규 − base 신규) × OPM. base 만 subQ 행에 포함, 나머지는 합산 안 함
A11: 분기/연간예상 subQ 를 이름(A열 key)으로 VLOOKUP 한 보고서 표(억원)
A12: TP PER 밴드 × 12M fwd EPS, PBR = ROE/COE × BPS — 모델 산출값 구간, 목표주가·추천 아님
A13: 외화 환율 QoQ, 외화 순노출 × Δ기말환율 → 환관련손익 추정
... A34: 백테스트: {"freeze": "2025Q2", "horizon": 4, "revenue_wape_pct": 39.9, "op_wape_pct": 99.1, "n": 4, "note": "단일 회사 4분기 — 통계 아님", "driver_at_freeze": "trend_seasonal", "selection_oos_at_freeze": null, "frozen_inputs": "fin(연결/별도)·고객 조선사 모델·지주 자회사 모델은 2025Q2 까지의 분기만; 선표는 체결일 ≤ 2025Q2 말일 계약(원장 최신 금액·코호트 등급, 환산 없음); 잔고는 yards_cache 2025Q2; 시세·환율 forward·prices·forecast_panel 신규수주 미사용. 고객 가중치(suppliers.json 언급 비중)와 합병 체인링크는 현재 지식; 고객 연동 채택은 동결 모델 안에서도 자기 la−4분기 OOS 규칙(selection_oos_at_freeze)", "detail": [{"q": "2025Q3", "rev_pred": 173.53, "rev_act": 137.05, "op_pred": -1.18, "op_act": 11.6}, {"q": "2025Q4", "rev_pred": 303.02, "rev_act": 165.06, "op_pred": -2.06, "op_act": -18.69}, {"q": "2026Q1", "rev_pred": 100.73, "rev_act": 75.62, "op_pred": -0.68, "op_act": -16.05}, {"q": "2026Q2", "rev_pred": 151.69, "rev_act": 143.5, "op_pred": -1.03, "op_act": 11.18}]}

Sheet 변수
C1: 이름: 변수H | E1: 4Q21 | F1: 2021 | G1: 1Q22 | H1: 2Q22 | I1: 3Q22 | J1: 4Q22 | K1: 2022 | L1: 1Q23 | M1: 2Q23 | N1: 3Q23 | O1: 4Q23 | P1: 2023 | Q1: 1Q24 | R1: 2Q24 | S1: 3Q24 | T1: 4Q24 | U1: 2024 | V1: 1Q25 | W1: 2Q25 | X1: 3Q25 | Y1: 4Q25 | Z1: 2025 | AA1: 1Q26 | AB1: 2Q26 | AC1: 3Q26 | AD1: 4Q26 | AE1: 2026 | AF1: 1Q27 | AG1: 2Q27 | AH1: 3Q27 | AI1: 4Q27 | AJ1: 2027 | AK1: 1Q28 | AL1: 2Q28 | AM1: 3Q28 | AN1: 4Q28 | AO1: 2028
A2: 가정 시계열 — 노란 셀은 추정 가정(모델값에서 역산), 연녹 셀은 3절 스칼라 참조 수식. 바꾸면 subQ·분기·연간예상·TP·시나리오가 재계산됩니다.
E3: 1 | F3: 2 | G3: 3 | H3: 4 | I3: 5 | J3: 6 | K3: 7 | L3: 8 | M3: 9 | N3: 10 | O3: 11 | P3: 12 | Q3: 13 | R3: 14 | S3: 15 | T3: 16 | U3: 17 | V3: 18 | W3: 19 | X3: 20 | Y3: 21 | Z3: 22 | AA3: 23 | AB3: 24 | AC3: 25 | AD3: 26 | AE3: 27 | AF3: 28 | AG3: 29 | AH3: 30 | AI3: 31 | AJ3: 32 | AK3: 33 | AL3: 34 | AM3: 35 | AN3: 36 | AO3: 37
E4: 2021.12 | F4: 2021.12A | G4: 2022.03 | H4: 2022.06 | I4: 2022.09 | J4: 2022.12 | K4: 2022.12A | L4: 2023.03 | M4: 2023.06 | N4: 2023.09 | O4: 2023.12 | P4: 2023.12A | Q4: 2024.03 | R4: 2024.06 | S4: 2024.09 | T4: 2024.12 | U4: 2024.12A | V4: 2025.03 | W4: 2025.06 | X4: 2025.09 | Y4: 2025.12 | Z4: 2025.12A | AA4: 2026.03 | AB4: 2026.06 | AC4: 2026.09 | AD4: 2026.12 | AE4: 2026.12A | AF4: 2027.03 | AG4: 2027.06 | AH4: 2027.09 | AI4: 2027.12 | AJ4: 2027.12A | AK4: 2028.03 | AL4: 2028.06 | AM4: 2028.09 | AN4: 2028.12 | AO4: 2028.12A
B5: 1. FX | C5: 이름: 환율
A6: USDKRW_avg | C6: 원/달러(평균) | E6: 1183.5 | F6: 1145.51 | G6: 1205.78 | H6: 1262.09 | I6: 1341.93 | J6: 1360.12 | K6: 1292.98 | L6: 1276.95 | M6: 1315.69 | N6: 1313.62 | O6: 1322.01 | P6: 1306.85 | Q6: 1330.14 | R6: 1371.28 | S6: 1356.22 | T6: 1396.3 | U6: 1363.53 | V6: 1452.28 | W6: 1398.52 | X6: 1386.95 | Y6: 1449.19 | Z6: 1421.52 | AA6: 1466.12 | AB6: 1501.75 | AC6: 1418.75 | AD6: 1343.63 | AE6: 1456.58 | AF6: 1333.09 | AG6: 1333.09 | AH6: 1333.09 | AI6: 1333.09 | AK6: 1333.09 | AL6: 1333.09 | AM6: 1333.09 | AN6: 1333.09
A7: USDKRW_end | C7: 원/달러(기말) | E7: 1188.75 | F7: 1188.75 | G7: 1213.74 | H7: 1301.24 | I7: 1436.9 | J7: 1260.16 | K7: 1260.16 | L7: 1305.99 | M7: 1321.44 | N7: 1345.35 | O7: 1297.43 | P7: 1297.43 | Q7: 1349.25 | R7: 1377.73 | S7: 1312.17 | T7: 1474.78 | U7: 1474.78 | V7: 1474.54 | W7: 1355.13 | X7: 1403.67 | Y7: 1444.2 | Z7: 1444.2 | AA7: 1524.8 | AB7: 1550.89 | AC7: 1355.4 | AD7: 1333.09 | AE7: 1333.09 | AF7: 1333.09 | AG7: 1333.09 | AH7: 1333.09 | AI7: 1333.09 | AK7: 1333.09 | AL7: 1333.09 | AM7: 1333.09 | AN7: 1333.09
A8: JPY100KRW_avg | C8: 원/100Y(평균) | E8: 1041.02 | F8: 1042.74 | G8: 1036.79 | H8: 972.23 | I8: 970.61 | J8: 961.03 | K8: 985.1 | L8: 964.89 | M8: 957.36 | N8: 909 | O8: 893.22 | P8: 931.11 | Q8: 896.29 | R8: 880.14 | S8: 909.35 | T8: 917.25 | U8: 900.92 | V8: 952.59 | W8: 967.92 | X8: 940.32 | Y8: 940.77 | Z8: 950.17 | AA8: 934.39 | AB8: 942.16 | AC8: 890.41 | AD8: 849.51 | AE8: 918.81 | AF8: 840.54 | AG8: 840.54 | AH8: 840.54 | AI8: 840.54 | AK8: 840.54 | AL8: 840.54 | AM8: 840.54 | AN8: 840.54
A9: JPY100KRW_end | C9: 원/100Y(기말) | E9: 1032.62 | F9: 1032.62 | G9: 996.83 | H9: 954.9 | I9: 993.29 | J9: 955.54 | K9: 955.54 | L9: 980.62 | M9: 913.67 | N9: 901.47 | O9: 917.04 | P9: 917.04 | Q9: 892.42 | R9: 857.76 | S9: 919.21 | T9: 939.65 | U9: 939.65 | V9: 986.84 | W9: 938.85 | X9: 948.49 | Y9: 921.81 | Z9: 921.81 | AA9: 955.99 | AB9: 954.75 | AC9: 863.31 | AD9: 840.54 | AE9: 840.54 | AF9: 840.54 | AG9: 840.54 | AH9: 840.54 | AI9: 840.54 | AK9: 840.54 | AL9: 840.54 | AM9: 840.54 | AN9: 840.54
A10: EURKRW_avg | C10: W/Euro(평균) | E10: 1353.32 | F10: 1354.06 | G10: 1352.29 | H10: 1343.31 | I10: 1350.63 | J10: 1386.07 | K10: 1358.07 | L10: 1369.93 | M10: 1432.41 | N10: 1429.41 | O10: 1420.91 | P10: 1412.88 | Q10: 1444.21 | R10: 1476.42 | S10: 1489.3 | T10: 1490.78 | U10: 1475.4 | V10: 1528.33 | W10: 1585.13 | X10: 1620.04 | Y10: 1686.02 | Z10: 1605.45 | AA10: 1715.47 | AB10: 1746.09 | AC10: 1631.97 | AD10: 1507.34 | AE10: 1688.95 | AF10: 1490.54 | AG10: 1490.54 | AH10: 1490.54 | AI10: 1490.54 | AK10: 1490.54 | AL10: 1490.54 | AM10: 1490.54 | AN10: 1490.54
A11: EURKRW_end | C11: W/Euro(기말) | E11: 1346.38 | F11: 1346.38 | G11: 1347.37 | H11: 1351.6 | I11: 1400.62 | J11: 1344.08 | K11: 1344.08 | L11: 1420.26 | M11: 1435.88 | N11: 1425.26 | O11: 1433.66 | P11: 1433.66 | Q11: 1458.68 | R11: 1474.86 | S11: 1469.1 | T11: 1532.14 | U11: 1532.14 | V11: 1594.72 | W11: 1588.22 | X11: 1648.04 | Y11: 1696.94 | Z11: 1696.94 | AA11: 1753.21 | AB11: 1767.09 | AC11: 1539.06 | AD11: 1490.54 | AE11: 1490.54 | AF11: 1490.54 | AG11: 1490.54 | AH11: 1490.54 | AI11: 1490.54 | AK11: 1490.54 | AL11: 1490.54 | AM11: 1490.54 | AN11: 1490.54
A12: CNYKRW_avg | C12: 원/중국원(평균) | E12: 185.14 | F12: 177.65 | G12: 189.93 | H12: 190.76 | I12: 195.79 | J12: 191.09 | K12: 191.93 | L12: 186.59 | M12: 187.45 | N12: 181.28 | O12: 182.86 | P12: 184.52 | Q12: 185.04 | R12: 189.35 | S12: 189.24 | T12: 194.24 | U12: 189.49 | V12: 199.63 | W12: 193.41 | X12: 193.79 | Y12: 204.38 | Z12: 197.8 | AA12: 211.75 | AB12: 220.8 | AC12: 210.43 | AD12: 200.5 | AE12: 213.68 | AF12: 199.18 | AG12: 199.18 | AH12: 199.18 | AI12: 199.18 | AK12: 199.18 | AL12: 199.18 | AM12: 199.18 | AN12: 199.18
A13: CNYKRW_end | C13: 원/중국원(기말) | E13: 187.13 | F13: 187.13 | G13: 191.38 | H13: 194.13 | I13: 201.92 | J13: 182.67 | K13: 182.67 | L13: 189.97 | M13: 181.8 | N13: 184.26 | O13: 182.61 | P13: 182.61 | Q13: 186.66 | R13: 189.7 | S13: 187.12 | T13: 202.04 | U13: 202.04 | V13: 203.3 | W13: 189.14 | X13: 197.16 | Y13: 206.28 | Z13: 206.28 | AA13: 220.97 | AB13: 228.56 | AC13: 202.16 | AD13: 199.18 | AE13: 199.18 | AF13: 199.18 | AG13: 199.18 | AH13: 199.18 | AI13: 199.18 | AK13: 199.18 | AL13: 199.18 | AM13: 199.18 | AN13: 199.18
B14: 1b. 종가
A15: price_close_end | C15: 종가(기말) | E15: 3640 | G15: 8240 | H15: 9450 | I15: 6320 | J15: 6400 | L15: 6450 | M15: 5550 | N15: 4910 | O15: 4870 | Q15: 4865 | R15: 4500 | S15: 3350 | T15: 2700 | V15: 2735 | W15: 4135 | X15: 3360 | Y15: 3055 | AA15: 4265 | AB15: 2505 | AC15: 2455 | AD15: 2290
A16: price_high | C16: 종가(최고) | E16: 5180 | G16: 9400 | H16: 14950 | I16: 10100 | J16: 8440 | L16: 7640 | M16: 7490 | N16: 6410 | O16: 5480 | Q16: 5950 | R16: 6170 | S16: 5400 | T16: 3975 | V16: 3775 | W16: 5230 | X16: 4140 | Y16: 3895 | AA16: 5910 | AB16: 5880 | AC16: 2960 | AD16: 2850
A17: price_low | C17: 종가(최저) | E17: 2850 | G17: 2995 | H17: 8370 | I17: 6100 | J17: 5690 | L17: 5760 | M17: 5430 | N17: 4140 | O17: 3940 | Q17: 4755 | R17: 4040 | S17: 3030 | T17: 2560 | V17: 2685 | W17: 2360 | X17: 3165 | Y17: 2895 | AA17: 2965 | AB17: 2265 | AC17: 1767 | AD17: 2235
A18: price_avg | C18: 종가(평균) | E18: 3906.9 | G18: 4746.4 | H18: 10852.3 | I18: 8458.7 | J18: 6960.5 | L18: 6529.4 | M18: 6127.7 | N18: 4998.9 | O18: 4462.8 | Q18: 5180.3 | R18: 4725.5 | S18: 3860.9 | T18: 3275.2 | V18: 3154.1 | W18: 3239 | X18: 3631.2 | Y18: 3255 | AA18: 4289 | AB18: 3744.5 | AC18: 2421.5 | AD18: 2474.3
B20: 2. 추정 드라이버 | C20: 실적 열 = subQ 실현값(수식), 추정 열 = 가정(노란 = 모델값 역산, 연녹 = 3절 스칼라 참조)
A21: drv:매출액 | B21: yoy | C21: 매출액 YoY | J21: =IFERROR(subQ!J5/subQ!E5-1,"") | L21: =IFERROR(subQ!L5/subQ!G5-1,"") | M21: =IFERROR(subQ!M5/subQ!H5-1,"") | N21: =IFERROR(subQ!N5/subQ!I5-1,"") | O21: =IFERROR(subQ!O5/subQ!J5-1,"") | Q21: =IFERROR(subQ!Q5/subQ!L5-1,"") | R21: =IFERROR(subQ!R5/subQ!M5-1,"") | S21: =IFERROR(subQ!S5/subQ!N5-1,"") | T21: =IFERROR(subQ!T5/subQ!O5-1,"") | V21: =IFERROR(subQ!V5/subQ!Q5-1,"") | W21: =IFERROR(subQ!W5/subQ!R5-1,"") | X21: =IFERROR(subQ!X5/subQ!S5-1,"") | Y21: =IFERROR(subQ!Y5/subQ!T5-1,"") | AA21: =IFERROR(subQ!AA5/subQ!V5-1,"") | AB21: =IFERROR(subQ!AB5/subQ!W5-1,"") | AC21: -0.19811049 | AD21: -0.19810395 | AF21: -0.19812119 | AG21: -0.19809611 | AH21: -0.099090082 | AI21: -0.099048051 | AK21: -0.099109499 | AL21: -0.099070131 | AM21: -0.049489951 | AN21: -0.049559748
A22: drv:판관비 | B22: ratio | C22: 판관비율(/매출) | E22: =IFERROR(subQ!E8/subQ!E5,"") | F22: =IFERROR(subQ!F8/subQ!F5,"") | G22: =IFERROR(subQ!G8/subQ!G5,"") | H22: =IFERROR(subQ!H8/subQ!H5,"") | I22: =IFERROR(subQ!I8/subQ!I5,"") | J22: =IFERROR(subQ!J8/subQ!J5,"") | K22: =IFERROR(subQ!K8/subQ!K5,"") | L22: =IFERROR(subQ!L8/subQ!L5,"") | ... AB22: =IFERROR(subQ!AB8/subQ!AB5,"") | AC22: =$D$48 | AD22: =$D$48 | AE22: =IFERROR(subQ!AE8/subQ!AE5,"") | AF22: =$D$48 | AG22: =$D$48 | AH22: =$D$48 | AI22: =$D$48 | AJ22: =IFERROR(subQ!AJ8/subQ!AJ5,"") | AK22: =$D$48 | AL22: =$D$48 | AM22: =$D$48 | AN22: =$D$48 | AO22: =IFERROR(subQ!AO8/subQ!AO5,"")
A23: drv:영업이익 | B23: ratio | C23: 영업이익률(OPM) | E23: =IFERROR(subQ!E9/subQ!E5,"") | F23: =IFERROR(subQ!F9/subQ!F5,"") | G23: =IFERROR(subQ!G9/subQ!G5,"") | H23: =IFERROR(subQ!H9/subQ!H5,"") | I23: =IFERROR(subQ!I9/subQ!I5,"") | J23: =IFERROR(subQ!J9/subQ!J5,"") | K23: =IFERROR(subQ!K9/subQ!K5,"") | L23: =IFERROR(subQ!L9/subQ!L5,"") | ... AB23: =IFERROR(subQ!AB9/subQ!AB5,"") | AC23: -0.038307552 | AD23: -0.038304624 | AE23: =IFERROR(subQ!AE9/subQ!AE5,"") | AF23: -0.038258575 | AG23: -0.038324498 | AH23: -0.038278962 | AI23: -0.038322851 | AJ23: =IFERROR(subQ!AJ9/subQ!AJ5,"") | AK23: -0.038257368 | AL23: -0.038294589 | AM23: -0.038253108 | AN23: -0.038291865 | AO23: =IFERROR(subQ!AO9/subQ!AO5,"")
A24: drv:외환손익 | B24: abs | C24: 외환손익 (가정, 억원) | E24: =subQ!E13 | F24: =subQ!F13 | G24: =subQ!G13 | H24: =subQ!H13 | I24: =subQ!I13 | J24: =subQ!J13 | K24: =subQ!K13 | L24: =subQ!L13 | ... AB24: =subQ!AB13 | AC24: 0 | AD24: 0 | AE24: =subQ!AE13 | AF24: 0 | AG24: 0 | AH24: 0 | AI24: 0 | AJ24: =subQ!AJ13 | AK24: 0 | AL24: 0 | AM24: 0 | AN24: 0 | AO24: =subQ!AO13
A25: drv:기타영업외손익 | B25: abs | C25: 기타영업외손익 (가정, 억원) | E25: =subQ!E14 | F25: =subQ!F14 | G25: =subQ!G14 | H25: =subQ!H14 | I25: =subQ!I14 | J25: =subQ!J14 | K25: =subQ!K14 | L25: =subQ!L14 | ... AB25: =subQ!AB14 | AC25: 0 | AD25: 0 | AE25: =subQ!AE14 | AF25: 0 | AG25: 0 | AH25: 0 | AI25: 0 | AJ25: =subQ!AJ14 | AK25: 0 | AL25: 0 | AM25: 0 | AN25: 0 | AO25: =subQ!AO14
A26: drv:법인세비용 | B26: ratio | C26: 법인세율(/세전) | E26: =IFERROR(subQ!E16/subQ!E15,"") | F26: =IFERROR(subQ!F16/subQ!F15,"") | G26: =IFERROR(subQ!G16/subQ!G15,"") | H26: =IFERROR(subQ!H16/subQ!H15,"") | I26: =IFERROR(subQ!I16/subQ!I15,"") | J26: =IFERROR(subQ!J16/subQ!J15,"") | K26: =IFERROR(subQ!K16/subQ!K15,"") | L26: =IFERROR(subQ!L16/subQ!L15,"") | ... AB26: =IFERROR(subQ!AB16/subQ!AB15,"") | AC26: 0 | AD26: 0 | AE26: =IFERROR(subQ!AE16/subQ!AE15,"") | AF26: 0 | AG26: 0 | AH26: 0 | AI26: 0 | AJ26: =IFERROR(subQ!AJ16/subQ!AJ15,"") | AK26: 0 | AL26: 0 | AM26: 0 | AN26: 0 | AO26: =IFERROR(subQ!AO16/subQ!AO15,"")
A27: drv:지배주주순이익 | B27: ratio | C27: 지배주주 비중(/당기순이익) | E27: =IFERROR(subQ!E18/subQ!E17,"") | F27: =IFERROR(subQ!F18/subQ!F17,"") | G27: =IFERROR(subQ!G18/subQ!G17,"") | H27: =IFERROR(subQ!H18/subQ!H17,"") | I27: =IFERROR(subQ!I18/subQ!I17,"") | J27: =IFERROR(subQ!J18/subQ!J17,"") | K27: =IFERROR(subQ!K18/subQ!K17,"") | L27: =IFERROR(subQ!L18/subQ!L17,"") | ... AB27: =IFERROR(subQ!AB18/subQ!AB17,"") | AC27: =$D$49 | AD27: =$D$49 | AE27: =IFERROR(subQ!AE18/subQ!AE17,"") | AF27: =$D$49 | AG27: =$D$49 | AH27: =$D$49 | AI27: =$D$49 | AJ27: =IFERROR(subQ!AJ18/subQ!AJ17,"") | AK27: =$D$49 | AL27: =$D$49 | AM27: =$D$49 | AN27: =$D$49 | AO27: =IFERROR(subQ!AO18/subQ!AO17,"")
A28: drv:부채총계 | B28: qoq | C28: 부채총계 QoQ | G28: =IFERROR(subQ!G20/subQ!E20-1,"") | H28: =IFERROR(subQ!H20/subQ!G20-1,"") | I28: =IFERROR(subQ!I20/subQ!H20-1,"") | J28: =IFERROR(subQ!J20/subQ!I20-1,"") | L28: =IFERROR(subQ!L20/subQ!J20-1,"") | M28: =IFERROR(subQ!M20/subQ!L20-1,"") | N28: =IFERROR(subQ!N20/subQ!M20-1,"") | O28: =IFERROR(subQ!O20/subQ!N20-1,"") | Q28: =IFERROR(subQ!Q20/subQ!O20-1,"") | R28: =IFERROR(subQ!R20/subQ!Q20-1,"") | S28: =IFERROR(subQ!S20/subQ!R20-1,"") | T28: =IFERROR(subQ!T20/subQ!S20-1,"") | V28: =IFERROR(subQ!V20/subQ!T20-1,"") | W28: =IFERROR(subQ!W20/subQ!V20-1,"") | X28: =IFERROR(subQ!X20/subQ!W20-1,"") | Y28: =IFERROR(subQ!Y20/subQ!X20-1,"") | AA28: =IFERROR(subQ!AA20/subQ!Y20-1,"") | AB28: =IFERROR(subQ!AB20/subQ!AA20-1,"") | AC28: -1.1729e-05 | AD28: 0 | AF28: 0 | AG28: 0 | AH28: 0 | AI28: 0 | AK28: 0 | AL28: 0 | AM28: 0 | AN28: 0
A29: drv:자본총계 | B29: roll | C29: 자본총계 기타변동(배당 등, 억원) | G29: =IFERROR(subQ!E21+subQ!G17-subQ!G21,"") | H29: =IFERROR(subQ!G21+subQ!H17-subQ!H21,"") | I29: =IFERROR(subQ!H21+subQ!I17-subQ!I21,"") | J29: =IFERROR(subQ!I21+subQ!J17-subQ!J21,"") | L29: =IFERROR(subQ!J21+subQ!L17-subQ!L21,"") | M29: =IFERROR(subQ!L21+subQ!M17-subQ!M21,"") | N29: =IFERROR(subQ!M21+subQ!N17-subQ!N21,"") | O29: =IFERROR(subQ!N21+subQ!O17-subQ!O21,"") | Q29: =IFERROR(subQ!O21+subQ!Q17-subQ!Q21,"") | R29: =IFERROR(subQ!Q21+subQ!R17-subQ!R21,"") | S29: =IFERROR(subQ!R21+subQ!S17-subQ!S21,"") | T29: =IFERROR(subQ!S21+subQ!T17-subQ!T21,"") | V29: =IFERROR(subQ!T21+subQ!V17-subQ!V21,"") | W29: =IFERROR(subQ!V21+subQ!W17-subQ!W21,"") | X29: =IFERROR(subQ!W21+subQ!X17-subQ!X21,"") | Y29: =IFERROR(subQ!X21+subQ!Y17-subQ!Y21,"") | AA29: =IFERROR(subQ!Y21+subQ!AA17-subQ!AA21,"") | AB29: =IFERROR(subQ!AA21+subQ!AB17-subQ!AB21,"") | AC29: -0.003807554 | AD29: -0.003857632 | AF29: 0.001929552 | AG29: 6.4704115 | AH29: -0.003225667 | AI29: -0.008024344 | AK29: 0.000368462 | AL29: 6.4691866 | AM29: 0.007650895 | AN29: 0.002768129
A30: drv:지배주주지분 | B30: roll | C30: 지배주주지분 기타변동(배당 등, 억원) | G30: =IFERROR(subQ!E22+subQ!G18-subQ!G22,"") | H30: =IFERROR(subQ!G22+subQ!H18-subQ!H22,"") | I30: =IFERROR(subQ!H22+subQ!I18-subQ!I22,"") | J30: =IFERROR(subQ!I22+subQ!J18-subQ!J22,"") | L30: =IFERROR(subQ!J22+subQ!L18-subQ!L22,"") | M30: =IFERROR(subQ!L22+subQ!M18-subQ!M22,"") | N30: =IFERROR(subQ!M22+subQ!N18-subQ!N22,"") | O30: =IFERROR(subQ!N22+subQ!O18-subQ!O22,"") | Q30: =IFERROR(subQ!O22+subQ!Q18-subQ!Q22,"") | R30: =IFERROR(subQ!Q22+subQ!R18-subQ!R22,"") | S30: =IFERROR(subQ!R22+subQ!S18-subQ!S22,"") | T30: =IFERROR(subQ!S22+subQ!T18-subQ!T22,"") | V30: =IFERROR(subQ!T22+subQ!V18-subQ!V22,"") | W30: =IFERROR(subQ!V22+subQ!W18-subQ!W22,"") | X30: =IFERROR(subQ!W22+subQ!X18-subQ!X22,"") | Y30: =IFERROR(subQ!X22+subQ!Y18-subQ!Y22,"") | AA30: =IFERROR(subQ!Y22+subQ!AA18-subQ!AA22,"") | AB30: =IFERROR(subQ!AA22+subQ!AB18-subQ!AB22,"") | AC30: -0.004807554 | AD30: -0.003857632 | AF30: 0.001929552 | AG30: 6.4704115 | AH30: -0.003225667 | AI30: -0.008024344 | AK30: 0.000368462 | AL30: 6.4691866 | AM30: 0.007650895 | AN30: 0.002768129
A31: drv:총차입금 | B31: qoq | C31: 총차입금 QoQ | G31: =IFERROR(subQ!G23/subQ!E23-1,"") | H31: =IFERROR(subQ!H23/subQ!G23-1,"") | I31: =IFERROR(subQ!I23/subQ!H23-1,"") | J31: =IFERROR(subQ!J23/subQ!I23-1,"") | L31: =IFERROR(subQ!L23/subQ!J23-1,"") | M31: =IFERROR(subQ!M23/subQ!L23-1,"") | N31: =IFERROR(subQ!N23/subQ!M23-1,"") | O31: =IFERROR(subQ!O23/subQ!N23-1,"") | Q31: =IFERROR(subQ!Q23/subQ!O23-1,"") | R31: =IFERROR(subQ!R23/subQ!Q23-1,"") | S31: =IFERROR(subQ!S23/subQ!R23-1,"") | T31: =IFERROR(subQ!T23/subQ!S23-1,"") | V31: =IFERROR(subQ!V23/subQ!T23-1,"") | W31: =IFERROR(subQ!W23/subQ!V23-1,"") | X31: =IFERROR(subQ!X23/subQ!W23-1,"") | Y31: =IFERROR(subQ!Y23/subQ!X23-1,"") | AA31: =IFERROR(subQ!AA23/subQ!Y23-1,"") | AB31: =IFERROR(subQ!AB23/subQ!AA23-1,"") | AC31: -1.9221e-05 | AD31: 0 | AF31: 0 | AG31: 0 | AH31: 0 | AI31: 0 | AK31: 0 | AL31: 0 | AM31: 0 | AN31: 0
A32: drv:순차입금 | B32: qoq | C32: 순차입금 QoQ | G32: =IFERROR(subQ!G24/subQ!E24-1,"") | H32: =IFERROR(subQ!H24/subQ!G24-1,"") | I32: =IFERROR(subQ!I24/subQ!H24-1,"") | J32: =IFERROR(subQ!J24/subQ!I24-1,"") | L32: =IFERROR(subQ!L24/subQ!J24-1,"") | M32: =IFERROR(subQ!M24/subQ!L24-1,"") | N32: =IFERROR(subQ!N24/subQ!M24-1,"") | O32: =IFERROR(subQ!O24/subQ!N24-1,"") | Q32: =IFERROR(subQ!Q24/subQ!O24-1,"") | R32: =IFERROR(subQ!R24/subQ!Q24-1,"") | S32: =IFERROR(subQ!S24/subQ!R24-1,"") | T32: =IFERROR(subQ!T24/subQ!S24-1,"") | V32: =IFERROR(subQ!V24/subQ!T24-1,"") | W32: =IFERROR(subQ!W24/subQ!V24-1,"") | X32: =IFERROR(subQ!X24/subQ!W24-1,"") | Y32: =IFERROR(subQ!Y24/subQ!X24-1,"") | AA32: =IFERROR(subQ!AA24/subQ!Y24-1,"") | AB32: =IFERROR(subQ!AB24/subQ!AA24-1,"") | AC32: 0.035566994 | AD32: 0.041407542 | AF32: 0.019351425 | AG32: 0.082610308 | AH32: 0.028358107 | AI32: 0.032971425 | AK32: 0.016249678 | AL32: 0.069098985 | AM32: 0.024630542 | AN32: 0.02849861
A33: drv:이자발생자산 | B33: qoq | C33: 이자발생자산 QoQ | G33: =IFERROR(subQ!G25/subQ!E25-1,"") | H33: =IFERROR(subQ!H25/subQ!G25-1,"") | I33: =IFERROR(subQ!I25/subQ!H25-1,"") | J33: =IFERROR(subQ!J25/subQ!I25-1,"") | L33: =IFERROR(subQ!L25/subQ!J25-1,"") | M33: =IFERROR(subQ!M25/subQ!L25-1,"") | N33: =IFERROR(subQ!N25/subQ!M25-1,"") | O33: =IFERROR(subQ!O25/subQ!N25-1,"") | Q33: =IFERROR(subQ!Q25/subQ!O25-1,"") | R33: =IFERROR(subQ!R25/subQ!Q25-1,"") | S33: =IFERROR(subQ!S25/subQ!R25-1,"") | T33: =IFERROR(subQ!T25/subQ!S25-1,"") | V33: =IFERROR(subQ!V25/subQ!T25-1,"") | W33: =IFERROR(subQ!W25/subQ!V25-1,"") | X33: =IFERROR(subQ!X25/subQ!W25-1,"") | Y33: =IFERROR(subQ!Y25/subQ!X25-1,"") | AA33: =IFERROR(subQ!AA25/subQ!Y25-1,"") | AB33: =IFERROR(subQ!AB25/subQ!AA25-1,"") | AC33: -0.032340794 | AD33: -0.040291076 | AF33: -0.020432596 | AG33: -0.090768353 | AH33: -0.037100099 | AI33: -0.046067939 | AK33: -0.024585366 | AL33: -0.10892178 | AM33: -0.046582108 | AN33: -0.05792324
A34: drv:현금및현금성자산 | B34: qoq | C34: 현금및현금성자산 QoQ | G34: =IFERROR(subQ!G26/subQ!E26-1,"") | H34: =IFERROR(subQ!H26/subQ!G26-1,"") | I34: =IFERROR(subQ!I26/subQ!H26-1,"") | J34: =IFERROR(subQ!J26/subQ!I26-1,"") | L34: =IFERROR(subQ!L26/subQ!J26-1,"") | M34: =IFERROR(subQ!M26/subQ!L26-1,"") | N34: =IFERROR(subQ!N26/subQ!M26-1,"") | O34: =IFERROR(subQ!O26/subQ!N26-1,"") | Q34: =IFERROR(subQ!Q26/subQ!O26-1,"") | R34: =IFERROR(subQ!R26/subQ!Q26-1,"") | S34: =IFERROR(subQ!S26/subQ!R26-1,"") | T34: =IFERROR(subQ!T26/subQ!S26-1,"") | V34: =IFERROR(subQ!V26/subQ!T26-1,"") | W34: =IFERROR(subQ!W26/subQ!V26-1,"") | X34: =IFERROR(subQ!X26/subQ!W26-1,"") | Y34: =IFERROR(subQ!Y26/subQ!X26-1,"") | AA34: =IFERROR(subQ!AA26/subQ!Y26-1,"") | AB34: =IFERROR(subQ!AB26/subQ!AA26-1,"")
A35: drv:영업활동현금흐름 | B35: yoy | C35: 영업활동현금흐름 YoY | J35: =IFERROR(subQ!J27/subQ!E27-1,"") | L35: =IFERROR(subQ!L27/subQ!G27-1,"") | M35: =IFERROR(subQ!M27/subQ!H27-1,"") | N35: =IFERROR(subQ!N27/subQ!I27-1,"") | O35: =IFERROR(subQ!O27/subQ!J27-1,"") | Q35: =IFERROR(subQ!Q27/subQ!L27-1,"") | R35: =IFERROR(subQ!R27/subQ!M27-1,"") | S35: =IFERROR(subQ!S27/subQ!N27-1,"") | T35: =IFERROR(subQ!T27/subQ!O27-1,"") | V35: =IFERROR(subQ!V27/subQ!Q27-1,"") | W35: =IFERROR(subQ!W27/subQ!R27-1,"") | X35: =IFERROR(subQ!X27/subQ!S27-1,"") | Y35: =IFERROR(subQ!Y27/subQ!T27-1,"") | AA35: =IFERROR(subQ!AA27/subQ!V27-1,"") | AB35: =IFERROR(subQ!AB27/subQ!W27-1,"")
A36: drv:주식수 | B36: qoq | C36: 주식수 QoQ | G36: =IFERROR(subQ!G28/subQ!E28-1,"") | H36: =IFERROR(subQ!H28/subQ!G28-1,"") | I36: =IFERROR(subQ!I28/subQ!H28-1,"") | J36: =IFERROR(subQ!J28/subQ!I28-1,"") | L36: =IFERROR(subQ!L28/subQ!J28-1,"") | M36: =IFERROR(subQ!M28/subQ!L28-1,"") | N36: =IFERROR(subQ!N28/subQ!M28-1,"") | O36: =IFERROR(subQ!O28/subQ!N28-1,"") | Q36: =IFERROR(subQ!Q28/subQ!O28-1,"") | R36: =IFERROR(subQ!R28/subQ!Q28-1,"") | S36: =IFERROR(subQ!S28/subQ!R28-1,"") | T36: =IFERROR(subQ!T28/subQ!S28-1,"") | V36: =IFERROR(subQ!V28/subQ!T28-1,"") | W36: =IFERROR(subQ!W28/subQ!V28-1,"") | X36: =IFERROR(subQ!X28/subQ!W28-1,"") | Y36: =IFERROR(subQ!Y28/subQ!X28-1,"") | AA36: =IFERROR(subQ!AA28/subQ!Y28-1,"") | AB36: =IFERROR(subQ!AB28/subQ!AA28-1,"") | AC36: 0 | AD36: 0 | AF36: 0 | AG36: 0 | AH36: 0 | AI36: 0 | AK36: 0 | AL36: 0 | AM36: 0 | AN36: 0
A37: drv:DPS | B37: abs | C37: DPS (가정, 원) | E37: =subQ!E31 | F37: =subQ!F31 | G37: =subQ!G31 | H37: =subQ!H31 | I37: =subQ!I31 | J37: =subQ!J31 | K37: =subQ!K31 | L37: =subQ!L31 | ... AB37: =subQ!AB31 | AD37: 20 | AE37: =subQ!AE31 | AI37: 20 | AJ37: =subQ!AJ31 | AN37: 20 | AO37: =subQ!AO31
B39: 3. 밸류에이션·스칼라 | C39: 노란 셀 = 가정. '연결' 표시는 추정 전 분기 수식이 이 셀을 참조한다는 뜻
A40: sc:종가 | C40: 종가 | D40: 2290 | E40: 원 — 네이버 정규장 종가(aik 확정종가 대조 · aik 2,495원)
A41: sc:기준일 | C41: 기준일 | D41: 20261013 | E41: 종가 기준일
A42: sc:COE | C42: COE | D42: 0.09 | E42: 자기자본비용(가정) — TP 적정 PBR = ROE/COE
A43: sc:PER_lo | C43: PER_lo | D43: 10 | E43: PER 밴드 하단(배) — sector_default(레퍼런스 TP_PE PB 예시 10/15/20배; 과거 PER 중위 58.2배가 3~40 밖(턴어라운드 왜곡))
A44: sc:PER_mid | C44: PER_mid | D44: 15 | E44: PER 밴드 중단(배)
A45: sc:PER_hi | C45: PER_hi | D45: 20 | E45: PER 밴드 상단(배)
A46: sc:EPS_Y1가중 | C46: EPS_Y1가중 | D46: 0.5 | E46: 12M fwd EPS = FY(last_actual연도)E × w + FY+1E × (1−w) — 기준 분기 2Q 이면 0.5(가정)
A47: sc:세율 | C47: 세율 | D47: 0.193 | E47: 참고(연결 안 됨: MAX(세전,0)×단일 세율로 재현 불가(지주 자회사 합산 등) → 분기별 역산) — 모델 assumptions 값 · 최근 12분기 유효세율 58.1% 가 5~27% 밖 → 클립 대신 최근 8분기 중 세전 > 0 인 5분기(2024Q3~2026Q2)의 법인세/세전 중위 19.3%
A48: sc:판관비율 | C48: 판관비율 | D48: 0.23299866 | E48: 연결 — 판관비 = 매출액 × 판관비율(역산, 재현 오차 ≤ 0.05억 · 모델 assumptions 0.233)
A49: sc:지배주주비중 | C49: 지배주주비중 | D49: 1 | E49: 연결 — 지배주주순이익 = 당기순이익 × 비중(역산, 재현 오차 ≤ 0.05억)
A50: sc:이자율_자산 | C50: 이자율_자산 | D50: 0.033621951 | E50: 연결 — 이자손익 = (전분기 이자발생자산 × 자산이자율 − 전분기 총차입금 × 부채이자율)/4(역산, 재현 오차 ≤ 0.05억 · 모델 assumptions 0.0337)
A51: sc:이자율_부채 | C51: 이자율_부채 | D51: 0.023636337 | E51: 연결 — 같은 수식의 부채 쪽(총차입금 행이 없으면 0)(역산, 재현 오차 ≤ 0.05억 · 모델 assumptions 0.0236)
A52: sc:배당성향 | C52: 배당성향 | E52: 배당성향(참고 — 모델은 직전 DPS 유지·Q2 지급 가정)
A53: sc:외화순노출_백만$ | C53: 외화순노출_백만$ | E53: 외화 순노출 × Δ기말환율 (외화 시트 방식) — 외화 순노출 미공시(face) → 0 + 표기
A54: sc:헤지비율 | C54: 헤지비율 | E54: sls 없음
A55: sc:헤지환율_약정 | C55: 헤지환율_약정 | E55: sls 없음

Sheet BS연결
B1: (백만원) | C1: 이름: BS연결H | E1: 4Q21 | F1: 2021 | G1: 1Q22 | H1: 2Q22 | I1: 3Q22 | J1: 4Q22 | K1: 2022 | L1: 1Q23 | M1: 2Q23 | N1: 3Q23 | O1: 4Q23 | P1: 2023 | Q1: 1Q24 | R1: 2Q24 | S1: 3Q24 | T1: 4Q24 | U1: 2024 | V1: 1Q25 | W1: 2Q25 | X1: 3Q25 | Y1: 4Q25 | Z1: 2025 | AA1: 1Q26 | AB1: 2Q26 | AC1: 3Q26 | AD1: 4Q26 | AE1: 2026 | AF1: 1Q27 | AG1: 2Q27 | AH1: 3Q27 | AI1: 4Q27 | AJ1: 2027 | AK1: 1Q28 | AL1: 2Q28 | AM1: 3Q28 | AN1: 4Q28 | AO1: 2028
B2: 연결 | D2: fin json(kship_fin.py)
B3: 한신기계공업(연) | C3: UPDATE: 26-10-13 | E3: 1 | F3: 2 | G3: 3 | H3: 4 | I3: 5 | J3: 6 | K3: 7 | L3: 8 | M3: 9 | N3: 10 | O3: 11 | P3: 12 | Q3: 13 | R3: 14 | S3: 15 | T3: 16 | U3: 17 | V3: 18 | W3: 19 | X3: 20 | Y3: 21 | Z3: 22 | AA3: 23 | AB3: 24 | AC3: 25 | AD3: 26 | AE3: 27 | AF3: 28 | AG3: 29 | AH3: 30 | AI3: 31 | AJ3: 32 | AK3: 33 | AL3: 34 | AM3: 35 | AN3: 36 | AO3: 37
B4: Account Code | C4: AccountNAME | E4: 2021.12 | F4: 2021.12A | G4: 2022.03 | H4: 2022.06 | I4: 2022.09 | J4: 2022.12 | K4: 2022.12A | L4: 2023.03 | M4: 2023.06 | N4: 2023.09 | O4: 2023.12 | P4: 2023.12A | Q4: 2024.03 | R4: 2024.06 | S4: 2024.09 | T4: 2024.12 | U4: 2024.12A | V4: 2025.03 | W4: 2025.06 | X4: 2025.09 | Y4: 2025.12 | Z4: 2025.12A | AA4: 2026.03 | AB4: 2026.06 | AC4: 2026.09 | AD4: 2026.12 | AE4: 2026.12A | AF4: 2027.03 | AG4: 2027.06 | AH4: 2027.09 | AI4: 2027.12 | AJ4: 2027.12A | AK4: 2028.03 | AL4: 2028.06 | AM4: 2028.09 | AN4: 2028.12 | AO4: 2028.12A
A5: 1 | C5: 유동자산 | E5: 69346.21 | F5: 69346.21 | G5: 67268.15 | H5: 72146.61 | I5: 76362.58 | J5: 68795.51 | K5: 68795.51 | L5: 80482.57 | M5: 73163.48 | N5: 74245.16 | O5: 67028.09 | P5: 67028.09 | Q5: 67082.79 | R5: 70989.6 | S5: 76974.63 | T5: 72877.25 | U5: 72877.25 | V5: 61910.08 | W5: 60003.52 | X5: 60502.46 | Y5: 55070.88 | Z5: 55070.88 | AA5: 50804.8 | AB5: 55398.57
A6: 1 | C6: 현금및현금성자산 | E6: 9854.43 | F6: 9854.43 | G6: 7749.02 | H6: 8628.16 | I6: 18599.67 | J6: 15607.7 | K6: 15607.7 | L6: 16872.49 | M6: 10484.28 | N6: 8225.27 | O6: 8957.04 | P6: 8957.04 | Q6: 7049.78 | R6: 18474.78 | S6: 20872.14 | T6: 32815.56 | U6: 32815.56 | V6: 21293.64 | W6: 17663.54 | X6: 12974.02 | Y6: 17140.3 | Z6: 17140.3 | AA6: 11180.48 | AB6: 8525.98
A7: 1 | C7: 단기금융상품 | E7: 7.82 | F7: 7.82 | G7: 8.18 | H7: 6.78 | I7: 7.24 | J7: 7.69 | K7: 7.69 | L7: 7.7 | M7: 266.78 | N7: 125.24 | O7: 18.24 | P7: 18.24 | Q7: 15.51 | R7: 428.83 | S7: 191.72 | T7: 147.95 | U7: 147.95 | V7: 94.57 | W7: 78.05 | X7: 81.53 | Y7: 83.99 | Z7: 83.99 | AA7: 54.5 | AB7: 59.07
A8: 1 | C8: 단기금융자산 | E8: 3235.58 | F8: 3235.58 | G8: 2042.3 | H8: 7539.13 | I8: 23.46 | J8: 7.69 | K8: 7.69 | L8: 3509.95 | M8: 4593.93 | N8: 125.24 | O8: 18.24 | P8: 18.24 | Q8: 15.51 | R8: 428.83 | S8: 191.72 | T8: 3272.15 | U8: 3272.15 | V8: 3036.97 | W8: 2360.89 | X8: 1235.37 | Y8: 994.48 | Z8: 994.48 | AA8: 404.05 | AB8: 1058.73
A9: 1 | C9: 단기투자자산(공정가치) | E9: 10219.93 | F9: 10219.93 | G9: 10871.41 | H9: 9295.81 | I9: 9581.51 | J9: 9246.79 | K9: 9246.79 | L9: 9831.62 | M9: 10620.17 | N9: 10383.19 | O9: 21056.56 | P9: 21056.56 | Q9: 23676.22 | R9: 14045.48 | S9: 15216.76 | T9: 526.25 | U9: 526.25 | V9: 4374.12 | W9: 7021.18 | X9: 9034.77 | Y9: 4439.93 | Z9: 4439.93 | AA9: 7693.21 | AB9: 10437.67
A10: 1 | C10: 매출채권및기타채권 | E10: 28205 | F10: 28205 | G10: 25350.72 | H10: 26056.56 | I10: 26305.71 | J10: 26123.98 | K10: 26123.98 | L10: 28840.98 | M10: 26957.11 | N10: 27305.72 | O10: 20976.55 | P10: 20976.55 | Q10: 19818.57 | R10: 18838.27 | S10: 20844.55 | T10: 21727.37 | U10: 21727.37 | V10: 15652.76 | W10: 16479.66 | X10: 18366.89 | Y10: 18885.1 | Z10: 18885.1 | AA10: 15409.77 | AB10: 16468.85
A11: 1 | C11: 재고자산 | E11: 16867.71 | F11: 16867.71 | G11: 19418.62 | H11: 18903.37 | I11: 19629.27 | J11: 12752.34 | K11: 12752.34 | L11: 18907.64 | M11: 18478.48 | N11: 20149.39 | O11: 12885.1 | P11: 12885.1 | Q11: 13512.02 | R11: 17446.18 | S11: 16988.14 | T11: 12946.85 | U11: 12946.85 | V11: 15334.13 | W11: 14191.42 | X11: 16280.89 | Y11: 12174.6 | Z11: 12174.6 | AA11: 14533.53 | AB11: 16238.21
A12: 1 | C12: 기타유동자산 | E12: 963.55 | F12: 963.55 | G12: 1836.1 | H12: 1723.57 | I12: 2222.97 | J12: 1554.76 | K12: 1554.76 | L12: 2519.9 | M12: 2029.5 | N12: 1916.25 | O12: 2915.06 | P12: 2915.06 | Q12: 2687.32 | R12: 1536.89 | S12: 2642.14 | T12: 1344.54 | U12: 1344.54 | V12: 688.85 | W12: 738.96 | X12: 1047.17 | Y12: 1417.27 | Z12: 1417.27 | AA12: 1546.71 | AB12: 1840.72
A13: 1 | C13: 비유동자산 | E13: 31802.81 | F13: 31802.81 | G13: 31762.93 | H13: 41433.42 | I13: 41298.57 | J13: 42985.98 | K13: 42985.98 | L13: 41826.29 | M13: 41438.44 | N13: 42402.36 | O13: 48827.45 | P13: 48827.45 | Q13: 49323.29 | R13: 48986.3 | S13: 48886.84 | T13: 53681.88 | U13: 53681.88 | V13: 56172.74 | W13: 56082.5 | X13: 67245.5 | Y13: 65098.19 | Z13: 65098.19 | AA13: 65883.18 | AB13: 64470.16
A14: 1 | C14: 장기금융자산 | E14: 18.25 | F14: 18.25 | G14: 19.91 | H14: 20.66 | I14: 21.56 | J14: 22.46 | K14: 22.46 | L14: 23.66 | M14: 12.43 | N14: 13.48 | O14: 9.8 | P14: 9.8 | Q14: 13.33 | R14: 14.05 | S14: 14.5 | T14: 16.95 | U14: 16.95 | V14: 17.48 | W14: 117.85 | X14: 118.31 | Y14: 118.71 | Z14: 118.71 | AA14: 119.22 | AB14: 3906.61
A15: 1 | C15: 투자자산 | E15: 18.25 | F15: 18.25 | G15: 19.91 | H15: 20.66 | I15: 21.56 | J15: 22.46 | K15: 22.46 | L15: 23.66 | M15: 12.43 | N15: 13.48 | O15: 9.8 | P15: 9.8 | Q15: 13.33 | R15: 14.05 | S15: 14.5 | T15: 16.95 | U15: 16.95 | V15: 17.48 | W15: 117.85 | X15: 118.31 | Y15: 118.71 | Z15: 118.71 | AA15: 119.22 | AB15: 3906.61
A16: 1 | C16: 장기매출채권및기타채권 | E16: 733.38 | F16: 733.38 | G16: 794.23 | H16: 813.41 | I16: 825.8 | L16: 881.16 | M16: 836.98 | N16: 823.53 | AB16: 1110.46
A17: 1 | C17: 투자부동산 | E17: 4093.44 | F17: 4093.44 | G17: 4070.09 | H17: 13742.86 | I17: 13709.75 | J17: 13676.64 | K17: 13676.64 | L17: 13646.79 | M17: 13580.22 | N17: 13585.58 | O17: 13544.21 | P17: 13544.21 | Q17: 13509.81 | R17: 13476.54 | S17: 13442.8 | T17: 13442.8 | U17: 13442.8 | V17: 13409.69 | W17: 13809.16 | X17: 13774.7 | Y17: 31026.91 | Z17: 31026.91 | AA17: 32645.35 | AB17: 32626.52
A18: 1 | C18: 유형자산 | E18: 26370.3 | F18: 26370.3 | G18: 26270.38 | H18: 26232.08 | I18: 26018.07 | J18: 25488.4 | K18: 25488.4 | L18: 25516.5 | M18: 25607.9 | N18: 26749.66 | O18: 33084.92 | P18: 33084.92 | Q18: 33166.67 | R18: 33383.07 | S18: 33676.08 | T18: 33030.49 | U18: 33030.49 | V18: 33244.06 | W18: 32993.17 | X18: 44170.54 | Y18: 26786.27 | Z18: 26786.27 | AA18: 25880.76 | AB18: 25757.28
A19: 1 | C19: 무형자산 | E19: 587.44 | F19: 587.44 | G19: 608.32 | H19: 624.42 | I19: 723.4 | J19: 999.15 | K19: 999.15 | L19: 991.23 | M19: 975.87 | O19: 900.17 | P19: 900.17 | Q19: 852.96 | R19: 1146.35 | S19: 828.3 | T19: 729.31 | U19: 729.31 | V19: 702.94 | W19: 695.34 | X19: 688.81 | Y19: 615.07 | Z19: 615.07 | AA19: 589.09 | AB19: 563.12
A20: 1 | C20: 자산총계 | E20: 101149.02 | F20: 101149.02 | G20: 99031.09 | H20: 113580.03 | I20: 117661.16 | J20: 111781.49 | K20: 111781.49 | L20: 122308.86 | M20: 114601.92 | N20: 116647.51 | O20: 115855.54 | P20: 115855.54 | Q20: 116406.08 | R20: 119975.9 | S20: 125861.48 | T20: 126559.13 | U20: 126559.13 | V20: 118082.82 | W20: 116086.02 | X20: 127747.95 | Y20: 120169.07 | Z20: 120169.07 | AA20: 116687.98 | AB20: 119868.72
A21: 1 | C21: 유동부채 | E21: 10890.43 | F21: 10890.43 | G21: 9775.81 | H21: 11923.85 | I21: 14752.56 | J21: 21936.67 | K21: 21936.67 | L21: 25945.25 | M21: 21695.91 | N21: 21825.37 | O21: 14800.97 | P21: 14800.97 | Q21: 19207.76 | R21: 19686.23 | S21: 23790.5 | T21: 26595.44 | U21: 26595.44 | V21: 17750.88 | W21: 16141.81 | X21: 18585.79 | Y21: 24104.92 | Z21: 24104.92 | AA21: 22559.26 | AB21: 23422.25
A22: 1 | C22: 매입채무및기타채무 | E22: 7599.17 | F22: 7599.17 | G22: 6403.23 | H22: 5841.22 | I22: 5542.57 | J22: 7939.53 | K22: 7939.53 | L22: 12026.89 | M22: 6249.1 | N22: 12603.86 | O22: 5917.89 | P22: 5917.89 | Q22: 5639.84 | R22: 5236.76 | S22: 7961.26 | T22: 7299.6 | U22: 7299.6 | V22: 4314.26 | W22: 5372.66 | X22: 6032.67 | Y22: 7311.37 | Z22: 7311.37 | AA22: 5034.07 | AB22: 6511.6
A23: 1 | C23: 단기차입금 | E23: 230.28 | F23: 230.28 | G23: 280.63 | H23: 384.69 | I23: 3270.05 | J23: 6641.54 | K23: 6641.54 | L23: 6640.13 | M23: 9728.41 | N23: 1040.46 | O23: 7027.72 | P23: 7027.72 | Q23: 8952.37 | R23: 8543.49 | S23: 8658.59 | T23: 12250.08 | U23: 12250.08 | V23: 9867.05 | W23: 7988.32 | X23: 9813.31 | Y23: 7826.07 | Z23: 7826.07 | AA23: 8455.19 | AB23: 7571.72
A24: 1 | C24: 당기법인세부채(미지급법인세) | E24: 891.71 | F24: 891.71 | G24: 500.39 | H24: 2497.93 | I24: 3721.85 | J24: 2322.73 | K24: 2322.73 | L24: 1287.65 | M24: 0 | N24: 0 | O24: 0.1 | P24: 0.1 | Q24: 0 | S24: 1.74 | T24: 2854.76 | U24: 2854.76 | V24: 650.25 | W24: 5.16 | X24: -33.44 | Y24: 449.51 | Z24: 449.51 | AA24: 265.87 | AB24: 446.72
A25: 1 | C25: 기타유동부채 | E25: 2169.27 | F25: 2169.27 | G25: 2591.56 | H25: 3200.01 | I25: 2218.08 | J25: 3782.86 | K25: 3782.86 | L25: 5990.59 | M25: 4818.4 | N25: 7281.04 | O25: 1855.26 | P25: 1855.26 | Q25: 4615.55 | R25: 5905.98 | S25: 7168.91 | T25: 509.05 | U25: 509.05 | V25: 490.49 | W25: 596.94 | X25: 732.46 | Y25: 974.25 | Z25: 974.25 | AA25: 547.42 | AB25: 461.2
A26: 1 | C26: 비유동부채 | E26: 4196.02 | F26: 4196.02 | G26: 4435.31 | H26: 5280.91 | I26: 5556.54 | J26: 838.66 | K26: 838.66 | L26: 2268.66 | M26: 1364.21 | N26: 1364.21 | O26: 8490.27 | P26: 8490.27 | Q26: 8138.33 | R26: 9094.21 | S26: 9789.53 | T26: 10368.13 | U26: 10368.13 | V26: 10983.87 | W26: 10451.04 | X26: 17703 | Y26: 8505.73 | Z26: 8505.73 | AA26: 8789.59 | AB26: 8977.13
A27: 1 | C27: 장기매입채무및기타채무 | E27: 582.4 | F27: 582.4 | G27: 572.9 | H27: 811.77 | I27: 823.95 | J27: 830.46 | K27: 830.46 | L27: 1010.46 | M27: 1010.46 | N27: 1010.46 | O27: 909.96 | P27: 909.96 | Q27: 724.96 | R27: 1337.08 | S27: 1277.14 | T27: 1269.88 | U27: 1269.88 | V27: 1270.95 | W27: 1272.02 | X27: 1156.09 | Y27: 1232.68 | Z27: 1232.68 | AA27: 1228.99 | AB27: 1221.06
A28: 1 | C28: 장기차입금 | E28: 2750 | F28: 2750 | G28: 2750 | H28: 2750 | I28: 2750 | J28: 0 | K28: 0 | L28: 1250 | M28: 350 | N28: 350 | O28: 7580.31 | P28: 7580.31 | Q28: 7413.37 | R28: 7209.38 | S28: 7751.17 | T28: 7852.93 | U28: 7852.93 | V28: 8237.77 | W28: 7524.18 | X28: 14599.5 | Y28: 6515.17 | Z28: 6515.17 | AA28: 6722.4 | AB28: 6759.06
A29: 1 | C29: 기타비유동부채 | E29: 24.05 | F29: 24.05 | G29: 18.85 | H29: 13.61 | I29: 13.49 | J29: 8.2 | K29: 8.2 | L29: 8.2 | M29: 3.75 | N29: 3.75 | O29: 0 | P29: 0 | T29: 0 | U29: 0 | X29: 114.1 | Y29: 104.66 | Z29: 104.66 | AA29: 95.09 | AB29: 85.41
A30: 1 | C30: 이연법인세부채 | E30: 803.23 | F30: 803.23 | G30: 803.23 | H30: 1171.72 | I30: 1171.72 | J30: 0 | K30: 0 | L30: 0 | O30: 0 | P30: 0 | R30: 547.75 | S30: 547.75 | T30: 0 | U30: 0
A31: 1 | C31: 부채총계 | E31: 15086.45 | F31: 15086.45 | G31: 14211.11 | H31: 17204.76 | I31: 20309.1 | J31: 22775.32 | K31: 22775.32 | L31: 28213.91 | M31: 23060.12 | N31: 23189.58 | O31: 23291.24 | P31: 23291.24 | Q31: 27346.09 | R31: 28780.44 | S31: 33580.03 | T31: 36963.57 | U31: 36963.57 | V31: 28734.75 | W31: 26592.85 | X31: 36288.79 | Y31: 32610.65 | Z31: 32610.65 | AA31: 31348.85 | AB31: 32399.38
A32: 1 | C32: 지배주주지분 | E32: 85929.86 | F32: 85929.86 | G32: 84686.56 | H32: 96241.94 | I32: 97218.7 | J32: 88872.56 | K32: 88872.56 | L32: 93961.1 | M32: 91407.95 | N32: 93324.38 | O32: 92430.84 | P32: 92430.84 | Q32: 88926.37 | R32: 91060.61 | S32: 92146.62 | T32: 89460.78 | U32: 89460.78 | V32: 89213.21 | W32: 89358.38 | X32: 91324.38 | Y32: 87423.68 | Z32: 87423.68 | AA32: 85203.87 | AB32: 87334.24
A33: 1 | C33: 자본금 | E33: 16223.08 | F33: 16223.08 | G33: 16223.08 | H33: 16223.08 | I33: 16223.08 | J33: 16223.08 | K33: 16223.08 | L33: 16223.08 | M33: 16223.08 | N33: 16223.08 | O33: 16223.08 | P33: 16223.08 | Q33: 16223.08 | R33: 16223.08 | S33: 16223.08 | T33: 16223.08 | U33: 16223.08 | V33: 16223.08 | W33: 16223.08 | X33: 16223.08 | Y33: 16223.08 | Z33: 16223.08 | AA33: 16223.08 | AB33: 16223.08
A34: 1 | C34: 자본잉여금 | E34: 8439.1 | F34: 8439.1 | G34: 8439.1 | H34: 19275.7 | I34: 19275.7 | J34: 19275.7 | K34: 19275.7 | L34: 19275.7 | M34: 19275.7 | N34: 19275.7 | O34: 19275.7 | P34: 19275.7 | Q34: 19275.7 | R34: 19275.7 | S34: 19275.7 | T34: 19275.7 | U34: 19275.7 | V34: 19275.7 | W34: 19275.7 | X34: 19275.7 | Y34: 19275.7 | Z34: 19275.7 | AA34: 19275.7 | AB34: 19275.7
A35: 1 | C35: 기타자본 | E35: -2088.3 | F35: -2088.3 | G35: -2062.54 | H35: -463.96 | I35: -437.62 | J35: -411.29 | K35: -411.29 | L35: -385.53 | M35: -941.1 | N35: -941.1 | O35: -386.1 | P35: -386.1 | Q35: -386.1 | R35: -836.1 | S35: -836.1 | T35: -836.1 | U35: -836.1 | V35: -836.1 | W35: -836.1 | X35: -836.1 | Y35: -836.1 | Z35: -836.1 | AA35: -836.1 | AB35: -836.1
A36: 1 | C36: 기타포괄이익누계액 | E36: 845.69 | F36: 845.69 | G36: 911.73 | H36: 958.52 | I36: 1078.57 | J36: 792.19 | K36: 792.19 | L36: 909.21 | M36: 780.01 | N36: 827.47 | O36: 784.25 | P36: 784.25 | Q36: 852.91 | R36: 921.27 | S36: 887.46 | T36: 971.2 | U36: 971.2 | V36: 968.73 | W36: 891.91 | X36: 1014.47 | Y36: 680.3 | Z36: 680.3 | AA36: 610.46 | AB36: 593.65
A37: 1 | C37: 이익잉여금 | E37: 62510.3 | F37: 62510.3 | G37: 61175.19 | H37: 60248.59 | I37: 61078.98 | J37: 52992.88 | K37: 52992.88 | L37: 57938.64 | M37: 56070.27 | N37: 57939.23 | O37: 56533.91 | P37: 56533.91 | Q37: 52960.79 | R37: 55476.66 | S37: 56596.49 | T37: 53826.9 | U37: 53826.9 | V37: 53581.81 | W37: 53803.79 | X37: 55647.23 | Y37: 52080.71 | Z37: 52080.71 | AA37: 49930.74 | AB37: 52077.91
A38: 1 | C38: 비지배주주지분 | E38: 132.71 | F38: 132.71 | G38: 133.42 | H38: 133.34 | I38: 133.36 | J38: 133.61 | K38: 133.61 | L38: 133.85 | M38: 133.85 | N38: 133.55 | O38: 133.46 | P38: 133.46 | Q38: 133.62 | R38: 134.85 | S38: 134.82 | T38: 134.78 | U38: 134.78 | V38: 134.86 | W38: 134.78 | X38: 134.78 | Y38: 134.74 | Z38: 134.74 | AA38: 135.25 | AB38: 135.1
A39: 1 | C39: 자본총계 | E39: 86062.57 | F39: 86062.57 | G39: 84819.97 | H39: 96375.28 | I39: 97352.06 | J39: 89006.17 | K39: 89006.17 | L39: 94094.95 | M39: 91541.8 | N39: 93457.93 | O39: 92564.3 | P39: 92564.3 | Q39: 89059.99 | R39: 91195.46 | S39: 92281.44 | T39: 89595.56 | U39: 89595.56 | V39: 89348.07 | W39: 89493.17 | X39: 91459.16 | Y39: 87558.43 | Z39: 87558.43 | AA39: 85339.13 | AB39: 87469.34
A40: 1 | C40: 부채와자본총계 | E40: 101149.02 | F40: 101149.02 | G40: 99031.09 | H40: 113580.03 | I40: 117661.16 | J40: 111781.49 | K40: 111781.49 | L40: 122308.86 | M40: 114601.92 | N40: 116647.51 | O40: 115855.54 | P40: 115855.54 | Q40: 116406.08 | R40: 119975.9 | S40: 125861.48 | T40: 126559.13 | U40: 126559.13 | V40: 118082.82 | W40: 116086.02 | X40: 127747.95 | Y40: 120169.07 | Z40: 120169.07 | AA40: 116687.98 | AB40: 119868.72
A41: 1 | C41: 총차입금 | E41: 2980.28 | F41: 2980.28 | G41: 3030.63 | H41: 3134.69 | I41: 6020.05 | J41: 7891.54 | K41: 7891.54 | L41: 7890.13 | M41: 10978.41 | N41: 2290.46 | O41: 14608.03 | P41: 14608.03 | Q41: 16365.74 | R41: 15752.87 | S41: 16409.76 | T41: 20103.01 | U41: 20103.01 | V41: 18104.82 | W41: 16412.5 | X41: 24412.81 | Y41: 21590.52 | Z41: 21590.52 | AA41: 22656.76 | AB41: 21851.42
A42: 1 | C42: 순차입금 | E42: -10109.73 | F42: -10109.73 | G42: -6760.69 | H42: -13032.6 | I42: -12603.08 | J42: -7723.85 | K42: -7723.85 | L42: -12492.31 | M42: -4099.8 | N42: -6060.05 | O42: 5632.75 | P42: 5632.75 | Q42: 9300.45 | R42: -3150.74 | S42: -4654.1 | T42: -15984.7 | U42: -15984.7 | V42: -6225.79 | W42: -3611.93 | X42: 10203.42 | Y42: 3455.74 | Z42: 3455.74 | AA42: 11072.23 | AB42: 12266.71
A43: 1 | C43: 이자발생자산 | E43: 13108.26 | F43: 13108.26 | G43: 9811.23 | H43: 16187.95 | I43: 18644.69 | J43: 15637.85 | K43: 15637.85 | L43: 20406.1 | M43: 15090.64 | N43: 8363.99 | O43: 8985.08 | P43: 8985.08 | Q43: 7078.62 | R43: 18917.66 | S43: 21078.36 | T43: 36104.66 | U43: 36104.66 | V43: 24348.09 | W43: 20142.28 | X43: 14327.7 | Y43: 18253.49 | Z43: 18253.49 | AA43: 11703.75 | AB43: 13491.32
A44: 1 | C44: 기타비유동자산 | J44: 91.24 | K44: 91.24 | L44: 79.7 | M44: 64.55 | N44: 54.75 | O44: 49.71 | P44: 49.71 | Q44: 49.93 | R44: 64.03 | S44: 49.3 | T44: 9.04 | U44: 9.04 | V44: 51.97 | W44: 28.12 | X44: 64.94 | Y44: 46.81 | Z44: 46.81 | AA44: 45.51 | AB44: 42.97
A45: 1 | C45: 이연법인세자산 | J45: 1123.84 | K45: 1123.84 | L45: 76.44 | M45: 76.08 | N45: 76.08 | O45: 239.4 | P45: 239.4 | Q45: 450.57 | S45: 0 | T45: 2242.04 | U45: 2242.04 | V45: 2242.04 | W45: 1936.1 | X45: 1936.1 | Y45: 621.14 | Z45: 621.14 | AA45: 479.03 | AB45: 463.2
A46: 1 | C46: 유동성장기부채 | J46: 1250 | K46: 1250 | L46: 0 | M46: 900 | N46: 900 | O46: 0 | P46: 0 | T46: 0 | U46: 0 | W46: 900 | Y46: 7249.28 | Z46: 7249.28 | AA46: 7479.17 | AB46: 7520.64
A47: 1 | C47: 장기금융부채(face) | J47: 0 | K47: 0 | W47: 7524.18 | X47: 14599.5 | Y47: 6515.17 | Z47: 6515.17
A48: 1 | C48: 종속기업및관계기업투자 | L48: 0
A49: 1 | C49: 유동확정계약자산 | T49: 3124.2 | U49: 3124.2 | V49: 2942.4 | W49: 2282.84 | X49: 1153.84 | Y49: 910.49 | Z49: 910.49 | AA49: 349.55
A50: 1 | C50: 당기법인세자산(선급법인세) | T50: 1.62 | U50: 1.62 | V50: 29.12 | W50: 46.45 | X50: 61.94 | Y50: 19.22 | Z50: 19.22 | AA50: 37.05 | AB50: 21.82
A51: 1 | C51: 단기파생상품부채 | T51: 3681.95 | U51: 3681.95 | V51: 2428.83 | W51: 1278.71 | X51: 2040.79 | Y51: 294.45 | Z51: 294.45 | AA51: 777.54
A52: 1 | C52: 단기금융부채 | T52: 3681.95 | U52: 3681.95 | V52: 2428.83 | W52: 1278.71 | X52: 2040.79 | Y52: 294.45 | Z52: 294.45 | AA52: 777.54
A53: 1 | C53: 계약자산 | AB53: 806.58
A54: 1 | C54: 계약부채 | AB54: 910.37
A55: 1 | C55: 확정급여부채 | AB55: 911.6
A56: 1 | C56: 매출액(수익) | E56: 18181.35 | G56: 10892.05 | H56: 12820.92 | I56: 12647.07 | J56: 19679.92 | K56: 56039.96 | L56: 9723.56 | M56: 14165.97 | N56: 15617.49 | O56: 21747.81 | P56: 61254.83 | Q56: 9381.21 | R56: 11211.82 | S56: 15472.8 | T56: 27019.43 | U56: 63085.26 | V56: 8981.83 | W56: 13526.02 | X56: 13705.13 | Y56: 16505.88 | Z56: 52718.86 | AA56: 7562.24 | AB56: 14349.6
A57: 1 | C57: 매출원가 | E57: 13810.38 | G57: 8588.62 | H57: 11810.63 | I57: 10674.08 | J57: 21108.52 | K57: 52181.85 | L57: 7990.98 | M57: 12759.19 | N57: 12607.37 | O57: 20293.82 | P57: 53651.36 | Q57: 10085.49 | R57: 7307.12 | S57: 14667.04 | T57: 18724.48 | U57: 50784.13 | V57: 6896.67 | W57: 11971.48 | X57: 10390.88 | Y57: 13120.58 | Z57: 42379.61 | AA57: 6932.73 | AB57: 10785.16
A58: 1 | C58: 매출총이익 | E58: 4370.96 | G58: 2303.43 | H58: 1010.29 | I58: 1972.99 | J58: -1428.6 | K58: 3858.11 | L58: 1732.58 | M58: 1406.78 | N58: 3010.13 | O58: 1454 | P58: 7603.49 | Q58: -704.28 | R58: 3904.7 | S58: 805.77 | T58: 8294.95 | U58: 12301.14 | V58: 2085.16 | W58: 1554.54 | X58: 3314.24 | Y58: 3385.3 | Z58: 10339.24 | AA58: 629.5 | AB58: 3564.44
A59: 1 | C59: 판관비 | E59: 1378 | G59: 1800.68 | H59: 1423.69 | I59: 2062.64 | J59: 7654.59 | K59: 12941.6 | L59: 1675.03 | M59: 2698.96 | N59: 1919.47 | O59: 1366.6 | P59: 7660.06 | Q59: 2033.09 | R59: 1853.93 | S59: 2114.52 | T59: 6867 | U59: 12868.54 | V59: 2614.97 | W59: 1792.79 | X59: 2154.52 | Y59: 5254.5 | Z59: 11816.78 | AA59: 2234.89 | AB59: 2446.06
A60: 1 | C60: 영업이익 | E60: 2992.96 | G60: 502.75 | H60: -413.4 | I60: -89.65 | J60: -9083.19 | K60: -9083.49 | L60: 57.55 | M60: -1292.18 | N60: 1090.66 | O60: 87.4 | P60: -56.57 | Q60: -2737.37 | R60: 2050.76 | S60: -1308.75 | T60: 1427.96 | U60: -567.4 | V60: -529.81 | W60: -238.25 | X60: 1159.73 | Y60: -1869.19 | Z60: -1477.52 | AA60: -1605.38 | AB60: 1118.38
A61: 1 | C61: 기타영업외수익 | E61: 19.99 | G61: 29.39 | H61: 68.51 | I61: 105.88 | J61: 109.75 | K61: 313.53 | L61: 347.74 | M61: 101.82 | N61: 318.68 | O61: 318.31 | P61: 1086.55 | Q61: 133.85 | R61: 244.61 | S61: 894.48 | T61: -627.73 | U61: 645.21 | V61: 695.57 | W61: 225.68 | X61: 160.17 | Y61: 1056.56 | Z61: 2137.98 | AA61: 244.33 | AB61: 277.81
A62: 1 | C62: 기타영업외비용 | E62: 686.74 | G62: 62.28 | H62: 86.47 | I62: 108.12 | J62: 1264.8 | K62: 1521.67 | L62: 66.69 | M62: 247.74 | N62: -44.88 | O62: -9.05 | P62: 260.5 | Q62: 109.5 | R62: 42.85 | S62: 47.86 | T62: 1026.22 | U62: 1226.43 | V62: 60.44 | W62: 73.79 | X62: 69.83 | Y62: 129.48 | Z62: 333.54 | AA62: 58.99 | AB62: 189.29
A63: 1 | C63: 금융수익 | E63: 276.3 | G63: 464.6 | H63: 549.53 | I63: 1458.99 | J63: -215.11 | K63: 2258.01 | L63: 1015.94 | M63: 1893.7 | N63: 1359.13 | O63: 1454.58 | P63: 5723.35 | Q63: 1519.15 | R63: 1088.33 | S63: 2245.18 | T63: 70.86 | U63: 4923.52 | V63: 1101.41 | W63: 1263.51 | X63: 894.92 | Y63: 1044.1 | Z63: 4303.94 | AA63: 1677.81 | AB63: 2135.84
A64: 1 | C64: 금융비용 | E64: 300 | G64: 867.75 | H64: 1215.02 | I64: 529.26 | J64: 162.37 | K64: 2774.4 | L64: 348.71 | M64: 1997.22 | N64: 943.62 | O64: -1372.64 | P64: 1916.91 | Q64: 1093.17 | R64: 529.06 | S64: -113.27 | T64: 3050.39 | U64: 4559.35 | V64: 966.37 | W64: 521.7 | X64: 300.71 | Y64: 699.92 | Z64: 2488.7 | AA64: 1617.87 | AB64: 682.35
A65: 1 | C65: 법인세비용차감전계속사업이익 | E65: 2302.52 | G65: 66.7 | H65: -1096.85 | I65: 837.83 | J65: -10615.72 | K65: -10808.04 | L65: 1005.83 | M65: -1541.62 | N65: 1869.74 | O65: 3241.98 | P65: 4575.93 | Q65: -2287.05 | R65: 2811.79 | S65: 1896.32 | T65: -3205.52 | U65: -784.46 | V65: 240.36 | W65: 655.45 | X65: 1844.27 | Y65: -597.94 | Z65: 2142.14 | AA65: -1360.11 | AB65: 2660.39
A66: 1 | C66: 법인세비용 | E66: 641.3 | G66: 15.73 | H66: -170.18 | I66: 7.42 | J66: -1987.32 | K66: -2134.35 | L66: 0.08 | M66: 2.28 | N66: 1.08 | O66: 841.91 | P66: 845.35 | Q66: 0.01 | R66: 294.69 | S66: 776.52 | T66: -644.5 | U66: 426.72 | V66: 0.19 | W66: 433.54 | X66: 0.84 | Y66: 2156.29 | Z66: 2590.86 | AA66: 142.42 | AB66: 513.37
A67: 1 | C67: 당기순이익 | E67: 1661.22 | G67: 50.97 | H67: -926.68 | I67: 830.4 | J67: -8628.4 | K67: -8673.71 | L67: 1005.76 | M67: -1543.9 | N67: 1868.66 | O67: 2400.06 | P67: 3730.58 | Q67: -2287.05 | R67: 2517.11 | S67: 1119.8 | T67: -2561.01 | U67: -1211.15 | V67: 240.17 | W67: 221.91 | X67: 1843.43 | Y67: -2754.23 | Z67: -448.72 | AA67: -1502.53 | AB67: 2147.02
... A73: 1 | C73: 계속사업이익 | E73: 1661.22 | G73: 50.97 | H73: -926.68 | I73: 830.4 | J73: -8628.4 | K73: -8673.71 | L73: 1005.76 | M73: -1543.9 | N73: 1868.66 | O73: 2400.06 | P73: 3730.58 | Q73: -2287.05 | R73: 2517.11 | S73: 1119.8 | T73: -2561.01 | U73: -1211.15 | V73: 240.17 | W73: 221.91 | X73: 1843.43 | Y73: -2754.23 | Z73: -448.72 | AA73: -1502.53 | AB73: 2147.02
A74: 1 | C74: 이자수익 | G74: 35.72 | H74: 54.9 | I74: 105.09 | J74: 129.06 | K74: 324.77 | L74: 113.44 | M74: 101.3 | N74: 32.67 | O74: 918.94 | P74: 1166.35 | Q74: 135.71 | R74: 143.12 | S74: 82.64 | T74: 163.46 | U74: 524.93 | V74: 524.92 | W74: 135.37 | X74: 190.38 | Y74: -105.66 | Z74: 745.01 | AA74: 122.71 | AB74: 67.8
A75: 1 | C75: 배당금수익 | G75: 32.07 | H75: 84.82 | I75: 50.16 | J75: 38.75 | K75: 205.8 | L75: 21.4 | M75: 112.97 | N75: 46.65 | O75: 38.65 | P75: 219.67 | Q75: 30.3 | R75: 87.77 | S75: 55.62 | T75: 40.53 | U75: 214.22 | V75: 214.22 | W75: 50.52 | X75: 49.18 | Y75: 56.82 | Z75: 370.74 | AA75: 7.07 | AB75: 64.59
A76: 1 | C76: 이자비용 | G76: 20.92 | H76: 19.82 | I76: 59.35 | J76: 108.24 | K76: 208.33 | L76: 16.85 | M76: 171.07 | N76: 141.49 | O76: 241.08 | P76: 570.49 | Q76: 309.78 | R76: 177.46 | S76: 150.96 | T76: 147.47 | U76: 785.67 | V76: 170.95 | W76: 144.88 | X76: 163.77 | Y76: 33.28 | Z76: 512.88 | AA76: 165.12 | AB76: 172.73
A77: 1 | C77: 외환차익 | G77: 36.01 | H77: 148.8 | I77: 79.91 | J77: 320.66 | K77: 585.38 | L77: 66.92 | M77: 285.01 | N77: 96.36 | O77: 1691.02 | P77: 2139.31 | Q77: 37.04 | R77: 71.89 | S77: 171.61 | T77: 52.42 | U77: 332.96 | V77: 332.97 | W77: 281.04 | X77: 93.47 | Y77: 145.04 | Z77: 852.52 | AA77: 50.03 | AB77: 40.01
A78: 1 | C78: 외환차손 | G78: 73.3 | H78: 62.16 | I78: 45.71 | J78: 125.05 | K78: 306.22 | L78: 13.92 | M78: 1309.89 | N78: 186.81 | O78: -652.82 | P78: 857.8 | Q78: 97.53 | R78: 161.5 | S78: 35.92 | T78: 582.73 | U78: 877.68 | V78: 140.48 | W78: 27.91 | X78: 74.49 | Y78: 162.08 | Z78: 404.96 | AA78: 136.15 | AB78: 178.77
A79: 1 | C79: 외화환산이익 | G79: 171.19 | H79: 318.56 | I79: 753.05 | J79: -704.7 | K79: 538.1 | M79: 326.02 | N79: 169.54 | O79: -185.45 | Q79: 196.5 | R79: 179.86 | S79: 136.1 | T79: 331.47 | U79: 843.93 | V79: 843.93 | W79: 438.72 | X79: -273.42 | Y79: -148.96 | Z79: 860.27 | AA79: 239.96 | AB79: 72.68
A80: 1 | C80: 외화환산손실 | G80: 32.9 | H80: 60.54 | M80: 107.13 | N80: 123.02 | O80: -123.07 | Q80: 360.86 | R80: 91.27 | S80: -342.26 | T80: 859.75 | U80: 969.62 | V80: 440.77 | W80: 337.28 | X80: -10.97 | Y80: 155.58 | Z80: 922.66 | AA80: 340.95 | AB80: 0.43
A81: 1 | C81: 이자손익 | G81: 14.8 | H81: 35.08 | I81: 45.74 | J81: 20.82 | K81: 116.44 | L81: 96.59 | M81: -69.77 | N81: -108.82 | O81: 677.86 | P81: 595.86 | Q81: -174.07 | R81: -34.34 | S81: -68.32 | T81: 15.99 | U81: -260.74 | V81: 353.97 | W81: -9.51 | X81: 26.61 | Y81: -138.94 | Z81: 232.13 | AA81: -42.41 | AB81: -104.93
A82: 1 | C82: 영업활동으로인한현금흐름 | E82: 1515.62 | G82: -2478.67 | H82: 1233.73 | I82: 243.59 | J82: -1616.68 | K82: -2618.03 | L82: 1366.3 | M82: -8053.69 | N82: 0 | O82: -906.9 | P82: -7594.29 | Q82: -2952.85 | R82: 13364.2 | S82: 1013.16 | T82: -9070.15 | U82: 2354.36 | V82: -1916.89 | W82: 596.22 | X82: 122.79 | Y82: -288.14 | Z82: -1486.02 | AA82: -2344.34 | AB82: -656.4
A83: 1 | C83: 배당금수취(CF) | E83: 34.61 | G83: 32.07 | H83: 84.82 | I83: 50.16 | J83: 38.75 | K83: 205.8 | L83: 21.4 | M83: 112.97 | N83: 0 | O83: 85.3 | P83: 219.67 | Q83: 30.3 | R83: 87.77 | S83: 55.62 | T83: 40.53 | U83: 214.22 | V83: 13.86 | W83: 50.52 | X83: 49.18 | Y83: 56.82 | Z83: 170.38 | AA83: 7.07 | AB83: 64.59
A84: 1 | C84: 법인세납부(CF) | E84: -161.43 | G84: -407.05 | H84: -520.27 | I84: -287.27 | J84: -343.48 | K84: -1558.07 | L84: -1035.08 | M84: -1342.91 | N84: 0 | O84: 37 | P84: -2340.99 | Q84: -9.34 | R84: 746.82 | S84: -824.43 | T84: 779.66 | U84: 692.71 | V84: -2204.85 | W84: -817.39 | X84: -15.84 | Y84: -133.13 | Z84: -3171.21 | AA84: -326.09 | AB84: -208.64
A85: 1 | C85: 투자활동으로인한현금흐름 | E85: -1505.4 | G85: 277.14 | H85: -14751.81 | I85: 7200.15 | J85: -3435.34 | K85: -10709.86 | L85: -97.43 | M85: -903.32 | N85: 0 | O85: -4830.91 | P85: -5831.66 | Q85: -626.7 | R85: -610.53 | S85: 549.46 | T85: 18067.73 | U85: 17379.96 | V85: -6868.64 | W85: -3166.04 | X85: -12526.06 | Y85: 7076.69 | Z85: -15484.05 | AA85: -3421.34 | AB85: -1086.18
A86: 1 | C86: 재무활동으로인한현금흐름 | E86: 1472.76 | G86: 48.34 | H86: 14413.22 | I86: 2404.05 | J86: 2396.75 | K86: 19262.36 | L86: -6.9 | M86: 2726.42 | N86: 0 | O86: 4047.55 | P86: 6767.07 | Q86: 1703.41 | R86: -979.19 | S86: 580.4 | T86: 2761.24 | U86: 4065.86 | V86: -2870.47 | W86: -819.98 | X86: 7691.35 | Y86: -2538.49 | Z86: 1462.41 | AA86: -328.72 | AB86: -890.45
A87: 1 | C87: 단기차입금의증가 | E87: 152.65 | G87: 141.83 | H87: 254.75 | I87: 11217.06 | J87: 3664.29 | K87: 15277.93 | L87: 2142.05 | M87: 5614.67 | N87: 0 | Q87: 7713.51 | S87: 1525.62 | T87: 10035.62 | V87: 1899.57 | W87: 2142.91 | X87: 2292.8 | Y87: 2385.56 | Z87: 8720.84 | AA87: 3269.34 | AB87: 1674.58
A88: 1 | C88: 단기차입금의감소 | E88: 55.84 | G88: 78.5 | H88: 151.78 | I88: 8581.53 | L88: 2143.47 | M88: 2558.29 | N88: 0 | O88: 2014.05 | P88: 6715.81 | Q88: 5527.85 | S88: 1018.1 | T88: 7285.3 | V88: 4284.84 | W88: 2962.89 | X88: 1356.35 | Y88: 4959.18 | Z88: 13563.26 | AA88: 2942.62 | AB88: 2555.22
A89: 1 | C89: 자기주식의취득 | E89: 0 | G89: 0 | H89: 0 | I89: 0 | J89: 0 | K89: 0 | L89: 0 | M89: 0
A90: 1 | C90: 장기차입금의감소 | E90: 0 | G90: 0 | H90: 0 | I90: 0 | J90: 1500 | K90: 1500 | L90: 0 | M90: 0 | N90: 0 | O90: 0 | P90: 0
A91: 1 | C91: 배당금지급 | E91: 0 | G91: 0 | H91: 1385.37 | I91: 0 | J91: 0 | K91: 1385.37 | L91: 0 | M91: 324.46 | N91: 0 | O91: 0 | P91: 324.46 | Q91: 486.69 | R91: 0 | S91: 0 | T91: 0 | U91: 486.69 | V91: 485.19 | W91: 0 | X91: 0 | Y91: 0 | Z91: 485.19 | AA91: 646.92 | AB91: 0
A92: 1 | C92: 현금및현금성자산의증감 | E92: 2943.88 | G92: -4258.6 | H92: 1774.28 | I92: 19819.3 | J92: -5647.25 | K92: 11687.73 | L92: 2526.76 | M92: -12618.79 | N92: -204.17 | O92: -3013.34 | P92: -13309.54 | Q92: -3783.39 | R92: 13301.13 | S92: 14438.71 | T92: 23702.26 | U92: 47658.71 | V92: -23177.92 | W92: -7019.9 | X92: -9401.43 | Y92: 8416.33 | Z92: -31182.92 | AA92: -12054.22
A93: 1 | C93: 기말현금및현금성자산 | E93: 1460.9 | G93: 7749.02 | H93: 879.14 | I93: 9971.51 | J93: -2991.97 | K93: 15607.7 | L93: 16872.49 | M93: -6388.21 | N93: -2259.01 | O93: 731.77 | P93: 8957.04 | Q93: 7049.78 | R93: 11425 | S93: 2397.36 | T93: 11943.42 | U93: 32815.56 | V93: 21293.64 | W93: -3630.1 | X93: -4689.52 | Y93: 4166.28 | Z93: 17140.3 | AA93: 11180.48 | AB93: -2654.5
A94: 1 | C94: 장기차입금의증가 | G94: 0 | H94: 0 | I94: 0 | J94: 0 | K94: 0 | L94: 0 | M94: 0 | T94: 10.95 | Y94: 45.91 | AA94: 2.27
A95: 1 | C95: 이자수취(CF) | O95: 838.28 | Q95: 135.59 | R95: 75.8 | S95: 664.32 | T95: 88.7 | U95: 964.41 | V95: 179.67 | W95: 47.98 | X95: 118.05 | Y95: -161.09 | Z95: 184.61 | AA95: 105.71 | AB95: -93.98

Sheet BS별도
B1: (백만원) | C1: 이름: BS별도H | E1: 4Q21 | F1: 2021 | G1: 1Q22 | H1: 2Q22 | I1: 3Q22 | J1: 4Q22 | K1: 2022 | L1: 1Q23 | M1: 2Q23 | N1: 3Q23 | O1: 4Q23 | P1: 2023 | Q1: 1Q24 | R1: 2Q24 | S1: 3Q24 | T1: 4Q24 | U1: 2024 | V1: 1Q25 | W1: 2Q25 | X1: 3Q25 | Y1: 4Q25 | Z1: 2025 | AA1: 1Q26 | AB1: 2Q26 | AC1: 3Q26 | AD1: 4Q26 | AE1: 2026 | AF1: 1Q27 | AG1: 2Q27 | AH1: 3Q27 | AI1: 4Q27 | AJ1: 2027 | AK1: 1Q28 | AL1: 2Q28 | AM1: 3Q28 | AN1: 4Q28 | AO1: 2028
B2: 별도 | D2: fin json(kship_fin.py)
B3: 한신기계공업(별) | C3: UPDATE: 26-10-13 | E3: 1 | F3: 2 | G3: 3 | H3: 4 | I3: 5 | J3: 6 | K3: 7 | L3: 8 | M3: 9 | N3: 10 | O3: 11 | P3: 12 | Q3: 13 | R3: 14 | S3: 15 | T3: 16 | U3: 17 | V3: 18 | W3: 19 | X3: 20 | Y3: 21 | Z3: 22 | AA3: 23 | AB3: 24 | AC3: 25 | AD3: 26 | AE3: 27 | AF3: 28 | AG3: 29 | AH3: 30 | AI3: 31 | AJ3: 32 | AK3: 33 | AL3: 34 | AM3: 35 | AN3: 36 | AO3: 37
B4: Account Code | C4: AccountNAME | E4: 2021.12 | F4: 2021.12A | G4: 2022.03 | H4: 2022.06 | I4: 2022.09 | J4: 2022.12 | K4: 2022.12A | L4: 2023.03 | M4: 2023.06 | N4: 2023.09 | O4: 2023.12 | P4: 2023.12A | Q4: 2024.03 | R4: 2024.06 | S4: 2024.09 | T4: 2024.12 | U4: 2024.12A | V4: 2025.03 | W4: 2025.06 | X4: 2025.09 | Y4: 2025.12 | Z4: 2025.12A | AA4: 2026.03 | AB4: 2026.06 | AC4: 2026.09 | AD4: 2026.12 | AE4: 2026.12A | AF4: 2027.03 | AG4: 2027.06 | AH4: 2027.09 | AI4: 2027.12 | AJ4: 2027.12A | AK4: 2028.03 | AL4: 2028.06 | AM4: 2028.09 | AN4: 2028.12 | AO4: 2028.12A
A5: 1 | C5: 유동자산 | E5: 67206.22 | F5: 67206.22 | G5: 64955.68 | H5: 70108.03 | I5: 74855.82 | J5: 65515.27 | K5: 65515.27 | L5: 79412.51 | M5: 72457.97 | N5: 73862.41 | O5: 64828.34 | P5: 64828.34 | Q5: 65532.06 | R5: 68544.4 | S5: 75142.01 | T5: 72257.26 | U5: 72257.26 | V5: 61864.77 | W5: 58766.39 | X5: 58402.47 | Y5: 53948.4 | Z5: 53948.4 | AA5: 49124 | AB5: 54246.57
A6: 1 | C6: 현금및현금성자산 | E6: 9660.35 | F6: 9660.35 | G6: 7502.48 | H6: 8372.32 | I6: 18444.47 | J6: 15007.4 | K6: 15007.4 | L6: 16457.63 | M6: 10077.81 | N6: 7601.12 | O6: 7996.36 | P6: 7996.36 | Q6: 6378.78 | R6: 16493.77 | S6: 19504.4 | T6: 31383.67 | U6: 31383.67 | V6: 20073.74 | W6: 16609.6 | X6: 11034 | Y6: 15452.46 | Z6: 15452.46 | AA6: 9257.89 | AB6: 6649.77
A7: 1 | C7: 단기금융상품 | E7: 6.42 | F7: 6.42 | G7: 6.77 | H7: 5.37 | I7: 5.82 | J7: 6.27 | K7: 6.27 | L7: 6.27 | M7: 13.16 | N7: 13.16 | O7: 16.77 | P7: 16.77 | Q7: 14.04 | R7: 4.37 | S7: 3.4 | T7: 3.55 | U7: 3.55 | V7: 3.65 | W7: 3.65 | X7: 3.65 | Y7: 3.65 | Z7: 3.65 | AA7: 3.65 | AB7: 7.95
A8: 1 | C8: 단기금융자산 | E8: 3234.18 | F8: 3234.18 | G8: 2040.89 | H8: 7537.72 | I8: 22.04 | J8: 6.27 | K8: 6.27 | L8: 3508.52 | M8: 4340.31 | N8: 13.16 | O8: 16.77 | P8: 16.77 | Q8: 14.04 | R8: 4.37 | S8: 3.4 | T8: 3127.75 | U8: 3127.75 | V8: 2946.05 | W8: 2286.49 | X8: 1157.49 | Y8: 914.14 | Z8: 914.14 | AA8: 353.2 | AB8: 1007.61
A9: 1 | C9: 단기투자자산(공정가치) | E9: 10219.93 | F9: 10219.93 | G9: 10871.41 | H9: 9295.81 | I9: 9581.51 | J9: 9246.79 | K9: 9246.79 | L9: 9831.62 | M9: 10620.17 | N9: 10383.19 | O9: 21056.56 | P9: 21056.56 | Q9: 23676.22 | R9: 14045.48 | S9: 15216.76 | T9: 526.25 | U9: 526.25 | V9: 4374.12 | W9: 7021.18 | X9: 9034.77 | Y9: 4439.93 | Z9: 4439.93 | AA9: 7693.21 | AB9: 10437.67
A10: 1 | C10: 매출채권및기타채권 | E10: 29826.94 | F10: 29826.94 | G10: 26603.7 | H10: 27490.9 | I10: 28660.96 | J10: 25860.04 | K10: 25860.04 | L10: 30722.17 | M10: 29774.47 | N10: 30375.24 | O10: 22078.23 | P10: 22078.23 | Q10: 21329.5 | R10: 21107.77 | S10: 22454.2 | T10: 24495.8 | U10: 24495.8 | V10: 18665.93 | W10: 17971.77 | X10: 19855.61 | Y10: 20803.23 | Z10: 20803.23 | AA10: 16847.48 | AB10: 17790.61
A11: 1 | C11: 재고자산 | E11: 13343.8 | F11: 13343.8 | G11: 16142.92 | H11: 15730.32 | I11: 16121.53 | J11: 10282.62 | K11: 10282.62 | L11: 16326.05 | M11: 15609.36 | N11: 17494.75 | O11: 10964.95 | P11: 10964.95 | Q11: 11529.15 | R11: 15242.38 | S11: 15215.46 | T11: 10952.44 | U11: 10952.44 | V11: 13458.86 | W11: 12491.89 | X11: 14687.48 | Y11: 10608.71 | Z11: 10608.71 | AA11: 13091.05 | AB11: 15406
A12: 1 | C12: 기타유동자산 | E12: 921.02 | F12: 921.02 | G12: 1794.28 | H12: 1680.95 | I12: 2025.31 | J12: 1609.9 | K12: 1609.9 | L12: 2544.26 | M12: 2035.85 | N12: 1805.82 | O12: 2426.66 | P12: 2426.66 | Q12: 2190.48 | R12: 1391.3 | S12: 2466.75 | T12: 1528.43 | U12: 1528.43 | V12: 818.24 | W12: 837.8 | X12: 1069.99 | Y12: 1729.94 | Z12: 1729.94 | AA12: 1865.2 | AB12: 2148.33
A13: 1 | C13: 비유동자산 | E13: 34382.87 | F13: 34382.87 | G13: 34126.5 | H13: 43512.49 | I13: 43414.55 | J13: 47680.59 | K13: 47680.59 | L13: 46138.47 | M13: 45796.91 | N13: 46741.88 | O13: 46996.94 | P13: 46996.94 | Q13: 47596.1 | R13: 48229.75 | S13: 47788.06 | T13: 48888.79 | U13: 48888.79 | V13: 51030.52 | W13: 51782.17 | X13: 57266.16 | Y13: 55992.34 | Z13: 55992.34 | AA13: 56367.92 | AB13: 54825.77
A14: 1 | C14: 장기금융자산 | E14: 16.25 | F14: 16.25 | G14: 15.41 | H14: 16.16 | I14: 17.06 | J14: 17.96 | K14: 17.96 | L14: 19.16 | M14: 7.93 | N14: 8.98 | O14: 5.3 | P14: 5.3 | Q14: 8.83 | R14: 9.55 | S14: 10 | T14: 10.45 | U14: 10.45 | V14: 10.9 | W14: 111.35 | X14: 111.8 | Y14: 112.25 | Z14: 112.25 | AA14: 112.7 | AB14: 3900.08
A15: 1 | C15: 투자자산 | E15: 4770.28 | F15: 4770.28 | G15: 4769.44 | H15: 4770.19 | I15: 4771.09 | J15: 4867.7 | K15: 4867.7 | L15: 4868.9 | M15: 5107.67 | N15: 5108.72 | O15: 4855.04 | P15: 4855.04 | Q15: 4858.57 | R15: 5119.29 | S15: 5119.74 | T15: 1311.36 | U15: 1311.36 | V15: 1311.81 | W15: 1412.26 | X15: 6539.59 | Y15: 6540.04 | Z15: 6540.04 | AA15: 6540.49 | AB15: 10327.87
A16: 1 | C16: 장기매출채권및기타채권 | E16: 532.65 | F16: 532.65 | G16: 594.05 | H16: 613.23 | I16: 625.8 | L16: 1481.28 | M16: 1495.64 | N16: 1465.19 | AB16: 4165.23
A17: 1 | C17: 종속기업및관계기업투자 | E17: 4754.03 | F17: 4754.03 | G17: 4754.03 | H17: 4754.03 | I17: 4754.03 | J17: 4849.74 | K17: 4849.74 | L17: 4849.74 | M17: 5099.74 | N17: 5099.74 | O17: 4849.74 | P17: 4849.74 | Q17: 4849.74 | R17: 5109.74 | S17: 5109.74 | T17: 1300.91 | U17: 1300.91 | V17: 1300.91 | W17: 1300.91 | X17: 6427.79 | Y17: 6427.79 | Z17: 6427.79 | AA17: 6427.79 | AB17: 6427.79
A18: 1 | C18: 투자부동산 | E18: 4093.44 | F18: 4093.44 | G18: 4070.09 | H18: 13742.86 | I18: 13709.75 | J18: 13676.64 | K18: 13676.64 | L18: 13646.79 | M18: 13580.22 | N18: 13585.58 | O18: 13544.21 | P18: 13544.21 | Q18: 13509.81 | R18: 13476.54 | S18: 13442.8 | T18: 13442.8 | U18: 13442.8 | V18: 13409.69 | W18: 13809.16 | X18: 13774.7 | Y18: 13740.23 | Z18: 13740.23 | AA18: 14810.47 | AB18: 14769.14
A19: 1 | C19: 유형자산 | E19: 24105.27 | F19: 24105.27 | G19: 24017.61 | H19: 23926.35 | I19: 23854.93 | J19: 23389.4 | K19: 23389.4 | L19: 23357.63 | M19: 23274.66 | N19: 24387.81 | O19: 24162.89 | P19: 24162.89 | Q19: 24410.27 | R19: 24702.15 | S19: 24614.45 | T19: 24374.69 | U19: 24374.69 | V19: 24282.16 | W19: 24288.55 | X19: 24659.29 | Y19: 25093.06 | Z19: 25093.06 | AA19: 24183.81 | AB19: 24063.65
A20: 1 | C20: 무형자산 | E20: 425.26 | F20: 425.26 | G20: 453.36 | H20: 459.87 | I20: 452.99 | L20: 831.27 | M20: 780.37 | R20: 671.27 | AB20: 520.63
A21: 1 | C21: 자산총계 | E21: 101589.09 | F21: 101589.09 | G21: 99082.18 | H21: 113620.52 | I21: 118270.37 | J21: 113195.86 | K21: 113195.86 | L21: 125550.98 | M21: 118254.88 | N21: 120604.3 | O21: 111825.27 | P21: 111825.27 | Q21: 113128.16 | R21: 116774.15 | S21: 122930.07 | T21: 121146.05 | U21: 121146.05 | V21: 112895.29 | W21: 110548.57 | X21: 115668.62 | Y21: 109940.73 | Z21: 109940.73 | AA21: 105491.92 | AB21: 109072.34
A22: 1 | C22: 유동부채 | E22: 11392.97 | F22: 11392.97 | G22: 10204.6 | H22: 12366.13 | I22: 16031.01 | J22: 20913.27 | K22: 20913.27 | L22: 26879.2 | M22: 21758.13 | N22: 22119.12 | O22: 15007.08 | P22: 15007.08 | Q22: 19800.29 | R22: 19412.01 | S22: 23970.95 | T22: 26742.11 | U22: 26742.11 | V22: 18585.49 | W22: 15698.97 | X22: 18371.65 | Y22: 16310.74 | Z22: 16310.74 | AA22: 13983.3 | AB22: 15079.7
A23: 1 | C23: 매입채무및기타채무 | E23: 8477.91 | F23: 8477.91 | G23: 7408.29 | H23: 6861.55 | I23: 7390 | J23: 8715.63 | K23: 8715.63 | L23: 13507.88 | M23: 7940.77 | N23: 14492.12 | O23: 7189.96 | P23: 7189.96 | Q23: 7124 | R23: 5885.66 | S23: 8986.97 | T23: 8674.68 | U23: 8674.68 | V23: 6016.03 | W23: 6291.4 | X23: 6723.15 | Y23: 8037.99 | Z23: 8037.99 | AA23: 5195.24 | AB23: 6955.43
A24: 1 | C24: 단기차입금 | E24: 230.28 | F24: 230.28 | G24: 280.63 | H24: 384.69 | I24: 3270.05 | J24: 6641.54 | K24: 6641.54 | L24: 6640.13 | M24: 9684.67 | N24: 1040.46 | O24: 6127.72 | P24: 6127.72 | Q24: 8051.85 | R24: 7643.49 | S24: 7758.59 | T24: 11350.08 | U24: 11350.08 | V24: 8967.05 | W24: 7638.32 | X24: 8913.31 | Y24: 6573.36 | Z24: 6573.36 | AA24: 7191.04 | AB24: 6310.07
A25: 1 | C25: 당기법인세부채(미지급법인세) | E25: 891.71 | F25: 891.71 | G25: 500.39 | H25: 2497.93 | I25: 3130.47 | J25: 2361.95 | K25: 2361.95 | L25: 1319.03 | M25: 0 | N25: 0 | O25: 0 | P25: 0 | T25: 2851.01 | U25: 2851.01 | V25: 687.02 | W25: 0 | X25: 0 | Y25: 437.65 | Z25: 437.65 | AA25: 265.87 | AB25: 448.98
A26: 1 | C26: 기타유동부채 | E26: 1793.07 | F26: 1793.07 | G26: 2015.28 | H26: 2621.96 | I26: 2240.49 | J26: 3194.14 | K26: 3194.14 | L26: 5412.16 | M26: 4132.68 | N26: 6586.54 | O26: 1689.4 | P26: 1689.4 | Q26: 4624.44 | R26: 5882.86 | S26: 7225.4 | T26: 474.8 | U26: 474.8 | V26: 502.56 | W26: 505.53 | X26: 739.68 | Y26: 967.29 | Z26: 967.29 | AA26: 553.64 | AB26: 461.92
A27: 1 | C27: 비유동부채 | E27: 1409.68 | F27: 1409.68 | G27: 1394.98 | H27: 2024.77 | I27: 2288.23 | J27: 838.66 | K27: 838.66 | L27: 853.11 | M27: 834.21 | N27: 834.21 | O27: 775.84 | P27: 775.84 | Q27: 590.84 | R27: 1750.7 | S27: 1690.76 | T27: 1687.62 | U27: 1687.62 | V27: 1899.61 | W27: 2073.23 | X27: 2233.63 | Y27: 1430.27 | Z27: 1430.27 | AA27: 1593.34 | AB27: 1723.64
A28: 1 | C28: 장기매입채무및기타채무 | E28: 582.4 | F28: 582.4 | G28: 572.9 | H28: 811.77 | I28: 823.95 | J28: 830.46 | K28: 830.46 | L28: 830.46 | M28: 830.46 | N28: 830.46 | O28: 729.96 | P28: 729.96 | Q28: 544.96 | R28: 1157.08 | S28: 1097.14 | T28: 1089.88 | U28: 1089.88 | V28: 1090.95 | W28: 1092.02 | X28: 976.09 | Y28: 961.72 | Z28: 961.72 | AA28: 953.45 | AB28: 954.69
A29: 1 | C29: 확정급여부채 | E29: 0 | F29: 0 | G29: 0 | H29: 27.67 | I29: 279.07 | J29: 0 | K29: 0 | L29: 14.46 | M29: 0 | N29: 0 | T29: 576.25 | U29: 576.25 | V29: 787.17 | W29: 971.68 | X29: 1117.91 | Y29: 281.07 | Z29: 281.07 | AA29: 471.21 | AB29: 621.13
A30: 1 | C30: 이연법인세부채 | E30: 803.23 | F30: 803.23 | G30: 803.23 | H30: 1171.72 | I30: 1171.72 | J30: 0 | K30: 0 | L30: 0 | M30: 0 | N30: 0 | O30: 0 | P30: 0 | R30: 547.75 | S30: 547.75
A31: 1 | C31: 기타비유동부채 | E31: 24.05 | F31: 24.05 | G31: 18.85 | H31: 13.61 | I31: 13.49 | J31: 8.2 | K31: 8.2 | L31: 8.2 | M31: 3.75 | N31: 3.75 | O31: 45.87 | P31: 45.87 | Q31: 45.87 | R31: 45.87 | S31: 45.87 | T31: 21.49 | U31: 21.49 | V31: 21.49 | W31: 9.53 | X31: 139.62 | Y31: 187.48 | Z31: 187.48 | AA31: 168.68 | AB31: 147.83
A32: 1 | C32: 부채총계 | E32: 12802.65 | F32: 12802.65 | G32: 11599.57 | H32: 14390.9 | I32: 18319.24 | J32: 21751.92 | K32: 21751.92 | L32: 27732.31 | M32: 22592.34 | N32: 22953.33 | O32: 15782.91 | P32: 15782.91 | Q32: 20391.13 | R32: 21162.71 | S32: 25661.71 | T32: 28429.74 | U32: 28429.74 | V32: 20485.1 | W32: 17772.2 | X32: 20605.28 | Y32: 17741.01 | Z32: 17741.01 | AA32: 15576.64 | AB32: 16803.34
A33: 1 | C33: 자본금 | E33: 16223.08 | F33: 16223.08 | G33: 16223.08 | H33: 16223.08 | I33: 16223.08 | J33: 16223.08 | K33: 16223.08 | L33: 16223.08 | M33: 16223.08 | N33: 16223.08 | O33: 16223.08 | P33: 16223.08 | Q33: 16223.08 | R33: 16223.08 | S33: 16223.08 | T33: 16223.08 | U33: 16223.08 | V33: 16223.08 | W33: 16223.08 | X33: 16223.08 | Y33: 16223.08 | Z33: 16223.08 | AA33: 16223.08 | AB33: 16223.08
A34: 1 | C34: 자본잉여금 | E34: 8439.1 | F34: 8439.1 | G34: 8439.1 | H34: 19275.7 | I34: 19275.7 | J34: 19275.7 | K34: 19275.7 | L34: 19275.7 | M34: 19275.7 | N34: 19275.7 | O34: 19275.7 | P34: 19275.7 | Q34: 19275.7 | R34: 19275.7 | S34: 19275.7 | T34: 19275.7 | U34: 19275.7 | V34: 19275.7 | W34: 19275.7 | X34: 19275.7 | Y34: 19275.7 | Z34: 19275.7 | AA34: 19275.7 | AB34: 19275.7
A35: 1 | C35: 기타자본 | E35: -739.12 | F35: -739.12 | G35: -713.36 | H35: 885.23 | I35: 911.56 | J35: 937.9 | K35: 937.9 | L35: 963.66 | M35: 963.09 | N35: 963.09 | O35: 963.09 | P35: 963.09 | Q35: 963.09 | R35: 963.09 | S35: 963.09 | T35: 963.09 | U35: 963.09 | V35: 963.09 | W35: 963.09 | X35: 963.09 | Y35: 963.09 | Z35: 963.09 | AA35: 963.09 | AB35: 963.09
A36: 1 | C36: 이익잉여금 | E36: 64863.38 | F36: 64863.38 | G36: 63533.79 | H36: 62845.61 | I36: 63540.79 | J36: 55007.26 | K36: 55007.26 | L36: 61356.23 | M36: 59200.68 | N36: 61189.1 | O36: 59580.49 | P36: 59580.49 | Q36: 56275.17 | R36: 59149.57 | S36: 60806.49 | T36: 56254.45 | U36: 56254.45 | V36: 55948.33 | W36: 56314.5 | X36: 58601.48 | Y36: 56061.67 | Z36: 56061.67 | AA36: 54090.54 | AB36: 56535.91
A37: 1 | C37: 자본총계 | E37: 88786.44 | F37: 88786.44 | G37: 87482.61 | H37: 99229.62 | I37: 99951.13 | J37: 91443.93 | K37: 91443.93 | L37: 97818.67 | M37: 95662.55 | N37: 97650.97 | O37: 96042.36 | P37: 96042.36 | Q37: 92737.03 | R37: 95611.44 | S37: 97268.35 | T37: 92716.31 | U37: 92716.31 | V37: 92410.19 | W37: 92776.36 | X37: 95063.35 | Y37: 92199.73 | Z37: 92199.73 | AA37: 89915.28 | AB37: 92269
A38: 1 | C38: 부채와자본총계 | E38: 101589.09 | F38: 101589.09 | G38: 99082.18 | H38: 113620.52 | I38: 118270.37 | J38: 113195.86 | K38: 113195.86 | L38: 125550.98 | M38: 118254.88 | N38: 120604.3 | O38: 111825.27 | P38: 111825.27 | Q38: 113128.16 | R38: 116774.15 | S38: 122930.07 | T38: 121146.05 | U38: 121146.05 | V38: 112895.29 | W38: 110548.57 | X38: 115668.62 | Y38: 109940.73 | Z38: 109940.73 | AA38: 105491.92 | AB38: 109072.34
A39: 1 | C39: 지배주주지분 | E39: 88786.44 | F39: 88786.44 | G39: 87482.61 | H39: 99229.62 | I39: 99951.13 | J39: 91443.93 | K39: 91443.93 | L39: 97818.67 | M39: 95662.55 | N39: 97650.97 | O39: 96042.36 | P39: 96042.36 | Q39: 92737.03 | R39: 95611.44 | S39: 97268.35 | T39: 92716.31 | U39: 92716.31 | V39: 92410.19 | W39: 92776.36 | X39: 95063.35 | Y39: 92199.73 | Z39: 92199.73 | AA39: 89915.28 | AB39: 92269
A40: 1 | C40: 총차입금 | E40: 230.28 | F40: 230.28 | G40: 280.63 | H40: 384.69 | I40: 3270.05 | J40: 6641.54 | K40: 6641.54 | L40: 7470.59 | M40: 9684.67 | N40: 1040.46 | O40: 6127.72 | P40: 6127.72 | Q40: 8051.85 | R40: 7643.49 | S40: 7758.59 | T40: 11350.08 | U40: 11350.08 | V40: 8967.05 | W40: 7638.32 | X40: 8913.31 | Y40: 6573.36 | Z40: 6573.36 | AA40: 7191.04 | AB40: 6310.07
A41: 1 | C41: 순차입금 | E41: -12664.25 | F41: -12664.25 | G41: -9262.74 | H41: -15525.35 | I41: -15196.46 | J41: -8372.13 | K41: -8372.13 | L41: -12495.56 | M41: -4733.45 | N41: -6573.82 | O41: -1885.41 | P41: -1885.41 | Q41: 1659.03 | R41: -8854.65 | S41: -11749.21 | T41: -23161.34 | U41: -23161.34 | V41: -14052.74 | W41: -11257.77 | X41: -3278.18 | Y41: -9793.24 | Z41: -9793.24 | AA41: -2420.05 | AB41: -1347.31
A42: 1 | C42: 이자발생자산 | E42: 12910.78 | F42: 12910.78 | G42: 9558.78 | H42: 15926.2 | I42: 18483.57 | J42: 15031.63 | K42: 15031.63 | L42: 19985.31 | M42: 14426.05 | N42: 7623.26 | O42: 8018.43 | P42: 8018.43 | Q42: 6401.65 | R42: 16507.69 | S42: 19517.8 | T42: 34521.87 | U42: 34521.87 | V42: 23030.69 | W42: 19007.44 | X42: 12303.29 | Y42: 16478.85 | Z42: 16478.85 | AA42: 9723.79 | AB42: 11557.46
A43: 1 | C43: 이연법인세자산 | J43: 1494.79 | K43: 1494.79 | L43: 76.44 | M43: 76.08 | N43: 76.08 | O43: 308.43 | P43: 308.43 | Q43: 450.57 | S43: 0 | T43: 2242.04 | U43: 2242.04 | V43: 2242.04 | W43: 1936.1 | X43: 1936.1 | Y43: 729 | Z43: 729 | AA43: 729 | AB43: 607.79
A44: 1 | C44: 기타비유동자산 | J44: 713 | K44: 713 | L44: 713 | M44: 622.31 | N44: 622.31 | O44: 575.98 | P44: 575.98 | Q44: 575.98 | R44: 903.63 | S44: 801.06 | T44: 703.62 | U44: 703.62 | V44: 703.62 | W44: 715.75 | X44: 650.66 | Y44: 557.77 | Z44: 557.77 | AA44: 465.93 | AB44: 371.47
A45: 1 | C45: 당기법인세자산(선급법인세) | L45: 22.26 | N45: 49.04 | O45: 69.25 | P45: 69.25 | Q45: 90.52 | R45: 40.15 | S45: 61.87 | T45: 0 | U45: 0 | V45: 27.34 | W45: 46.25 | X45: 61.73 | Y45: 0 | Z45: 0 | AA45: 15.97
A46: 1 | C46: 장기차입금 | L46: 830.46
A47: 1 | C47: 단기금융부채(face) | N47: 1040.46
A48: 1 | C48: 유동확정계약자산 | T48: 3124.2 | U48: 3124.2 | V48: 2942.4 | W48: 2282.84 | X48: 1153.84 | Y48: 910.49 | Z48: 910.49 | AA48: 349.55
A49: 1 | C49: 단기파생상품부채 | T49: 3391.55 | U49: 3391.55 | V49: 2412.83 | W49: 1263.71 | X49: 1995.51 | Y49: 294.45 | Z49: 294.45 | AA49: 777.52
A50: 1 | C50: 단기금융부채 | T50: 3391.55 | U50: 3391.55 | V50: 2412.83 | W50: 1263.71 | X50: 1995.51 | Y50: 294.45 | Z50: 294.45 | AA50: 777.52
A51: 1 | C51: 기타포괄이익누계액 | Y51: -323.81 | Z51: -323.81 | AA51: -637.12 | AB51: -728.77
A52: 1 | C52: 계약자산 | AB52: 806.58
A53: 1 | C53: 계약부채 | AB53: 903.3
A54: 1 | C54: 매출액(수익) | E54: 17891.7 | G54: 10217.42 | H54: 12856.89 | I54: 12032.91 | J54: 19705.25 | K54: 54812.47 | L54: 10032.52 | M54: 14786.58 | N54: 13309.68 | O54: 22815.43 | P54: 60944.21 | Q54: 9440.07 | R54: 10657.95 | S54: 14891.33 | T54: 25352.32 | U54: 60341.67 | V54: 8004.89 | W54: 12448.93 | X54: 11641.16 | Y54: 18412.25 | Z54: 50507.23 | AA54: 7018.37 | AB54: 13839.24
A55: 1 | C55: 매출원가 | E55: 13869.16 | G55: 8254.5 | H55: 12057.18 | I55: 10628.22 | J55: 20669.86 | K55: 51609.76 | L55: 8644.87 | M55: 13932.42 | N55: 10522.59 | O55: 21432.83 | P55: 54532.71 | Q55: 10454.64 | R55: 6877.1 | S55: 14253.5 | T55: 18127.58 | U55: 49712.82 | V55: 6206.16 | W55: 11479.52 | X55: 8690.62 | Y55: 14965.02 | Z55: 41341.32 | AA55: 6925.3 | AB55: 10489.11
A56: 1 | C56: 매출총이익 | E56: 4022.54 | G56: 1962.92 | H56: 799.72 | I56: 1404.68 | J56: -964.61 | K56: 3202.71 | L56: 1387.65 | M56: 854.16 | N56: 2787.08 | O56: 1382.6 | P56: 6411.49 | Q56: -1014.56 | R56: 3780.85 | S56: 637.83 | T56: 7224.74 | U56: 10628.86 | V56: 1798.73 | W56: 969.41 | X56: 2950.54 | Y56: 3447.23 | Z56: 9165.91 | AA56: 93.07 | AB56: 3350.13
A57: 1 | C57: 판관비 | E57: 981.51 | G57: 1513.56 | H57: 1011.44 | I57: 1705.34 | J57: 9014.89 | K57: 13245.23 | L57: 1362.33 | M57: 2378.75 | N57: 1490.14 | O57: 6.95 | P57: 5238.17 | Q57: 1722.88 | R57: 1468.27 | S57: 1432.32 | T57: 4587.22 | U57: 9210.69 | V57: 2009.48 | W57: 1344.44 | X57: 1398.64 | Y57: 3873.4 | Z57: 8625.96 | AA57: 1697.43 | AB57: 1925.99
A58: 1 | C58: 영업이익 | E58: 3041.03 | G58: 449.36 | H58: -211.72 | I58: -300.65 | J58: -9979.5 | K58: -10042.51 | L58: 25.32 | M58: -1524.6 | N58: 1296.94 | O58: 1375.65 | P58: 1173.31 | Q58: -2737.44 | R58: 2312.58 | S58: -794.48 | T58: 2637.51 | U58: 1418.17 | V58: -210.75 | W58: -375.03 | X58: 1551.9 | Y58: -426.16 | Z58: 539.96 | AA58: -1604.37 | AB58: 1424.14
A59: 1 | C59: 기타영업외수익 | E59: 19.58 | G59: 26.2 | H59: 67.33 | I59: 103.75 | J59: 100.17 | K59: 297.45 | L59: 345.67 | M59: -75.37 | N59: 227.64 | O59: 435.63 | P59: 933.57 | Q59: 107.17 | R59: 159.11 | S59: 875.75 | T59: -778.41 | U59: 363.62 | V59: 272.42 | W59: 110.31 | X59: 70.09 | Y59: 47.22 | Z59: 500.04 | AA59: 70.28 | AB59: 74.81
A60: 1 | C60: 기타영업외비용 | E60: 67.79 | G60: 45.56 | H60: 53.38 | I60: 45.57 | J60: 1249.75 | K60: 1394.26 | L60: 48.07 | M60: 247.68 | N60: -44.68 | O60: -35.01 | P60: 216.06 | Q60: 109.34 | R60: 42.21 | S60: 47.16 | T60: 3844.2 | U60: 4042.91 | V60: 53.65 | W60: 80.38 | X60: 62.2 | Y60: 81.69 | Z60: 277.92 | AA60: 64.64 | AB60: 117.69
A61: 1 | C61: 금융수익 | E61: 276.24 | G61: 464.51 | H61: 549.43 | I61: 1458.6 | J61: -192.71 | K61: 2279.83 | L61: 1015.85 | M61: 2003.49 | N61: 1355.52 | O61: 1459.66 | P61: 5834.52 | Q61: 1519.01 | R61: 1220.83 | S61: 2241.54 | T61: 240.63 | U61: 5222.01 | V61: 1099.85 | W61: 1614.85 | X61: 919.36 | Y61: 1348.6 | Z61: 4982.66 | AA61: 1795.33 | AB61: 2258.35
A62: 1 | C62: 금융비용 | E62: 285.34 | G62: 823.01 | H62: 1210.63 | I62: 514.3 | J62: 96.24 | K62: 2644.18 | L62: 325.47 | M62: 1986.57 | N62: 936.37 | O62: -1428.92 | P62: 1819.49 | Q62: 1060.08 | R62: 482.96 | S62: -155.9 | T62: 2915.01 | U62: 4302.15 | V62: 928.8 | W62: 471.97 | X62: 192.17 | Y62: 571.08 | Z62: 2164.02 | AA62: 1520.8 | AB62: 577.88
A63: 1 | C63: 법인세비용차감전계속사업이익 | E63: 2983.72 | G63: 71.51 | H63: -858.99 | I63: 701.84 | J63: -11418.02 | K63: -11503.66 | L63: 1013.29 | M63: -1830.72 | N63: 1988.42 | O63: 4734.86 | P63: 5905.85 | Q63: -2280.69 | R63: 3167.35 | S63: 2431.54 | T63: -4659.47 | U63: -1341.27 | V63: 179.08 | W63: 797.78 | X63: 2286.98 | Y63: 316.89 | Z63: 3580.73 | AA63: -1324.21 | AB63: 3061.73
A64: 1 | C64: 법인세비용 | E64: 640.7 | G64: 15.73 | H64: -170.81 | I64: 6.66 | J64: -2358.26 | K64: -2506.68 | L64: 0 | M64: 0.36 | N64: 0 | O64: 1143.27 | P64: 1143.63 | R64: 292.94 | S64: 774.63 | T64: -577.31 | W64: 431.61 | X64: 0 | Y64: 2044.37 | AA64: 0 | AB64: 616.36
A65: 1 | C65: 당기순이익 | E65: 2343.02 | G65: 55.78 | H65: -688.18 | I65: 695.18 | J65: -9059.76 | K65: -8996.98 | L65: 1013.29 | M65: -1831.09 | N65: 1988.42 | O65: 3592.32 | P65: 4762.94 | Q65: -2280.69 | R65: 2874.41 | S65: 1656.91 | T65: -4082.15 | U65: -1831.52 | V65: 179.08 | W65: 366.17 | X65: 2286.98 | Y65: -1727.48 | Z65: 1104.75 | AA65: -1324.21 | AB65: 2445.37
A66: 1 | C66: 총포괄손익 | E66: 2629.66 | G66: 55.78 | H66: -688.18 | I66: 695.18 | J66: -8533.54 | K66: -8470.76 | L66: 1013.29 | M66: -1831.09 | N66: 1988.42 | O66: 3727.08 | P66: 4897.7 | Q66: -2280.69 | R66: 2874.41 | S66: 1656.91 | T66: -5089.99 | U66: -2839.36 | V66: 179.08 | W66: 366.17 | X66: 2286.98 | Y66: -2863.62 | Z66: -31.39 | AA66: -1637.52 | AB66: 2353.72
A67: 1 | C67: 금융손익 | E67: -9.1 | G67: -358.5 | H67: -661.2 | I67: 944.3 | J67: -288.95 | K67: -364.35 | L67: 690.38 | M67: 16.92 | N67: 419.15 | O67: 2888.58 | P67: 4015.03 | Q67: 458.93 | R67: 737.87 | S67: 2397.44 | T67: -2674.38 | U67: 919.86 | V67: 171.05 | W67: 1142.88 | X67: 727.18 | Y67: 777.52 | Z67: 2818.63 | AA67: 274.52 | AB67: 1680.47
A68: 1 | C68: 기타영업외손익 | E68: -48.21 | G68: -19.36 | H68: 13.95 | I68: 58.18 | J68: -1149.58 | K68: -1096.81 | L68: 297.6 | M68: -323.05 | N68: 272.32 | O68: 470.64 | P68: 717.51 | Q68: -2.17 | R68: 116.9 | S68: 828.59 | T68: -4622.61 | U68: -3679.29 | V68: 218.77 | W68: 29.93 | X68: 7.89 | Y68: -34.47 | Z68: 222.12 | AA68: 5.64 | AB68: -42.88
A69: 1 | C69: (지배주주지분)당기순이익 | E69: 2343.02 | G69: 55.78 | H69: -688.18 | I69: 695.18 | J69: -9059.76 | K69: -8996.98 | L69: 1013.29 | M69: -1831.09 | N69: 1988.42 | O69: 3592.32 | P69: 4762.94 | Q69: -2280.69 | R69: 2874.41 | S69: 1656.91 | T69: -4082.15 | U69: -1831.52 | V69: 179.08 | W69: 366.17 | X69: 2286.98 | Y69: -1727.48 | Z69: 1104.75 | AA69: -1324.21 | AB69: 2445.37
A70: 1 | C70: 계속사업이익 | E70: 2343.02 | G70: 55.78 | H70: -688.18 | I70: 695.18 | J70: -9059.76 | K70: -8996.98 | L70: 1013.29 | M70: -1831.09 | N70: 1988.42 | O70: 3592.32 | P70: 4762.94 | Q70: -2280.69 | R70: 2874.41 | S70: 1656.91 | T70: -4082.15 | U70: -1831.52 | V70: 179.08 | W70: 366.17 | X70: 2286.98 | Y70: -1727.48 | Z70: 1104.75 | AA70: -1324.21 | AB70: 2445.37
A71: 1 | C71: 영업활동으로인한현금흐름 | E71: 1593.59 | G71: -2530.41 | H71: 1175.14 | I71: 423.94 | J71: -1767.15 | K71: -2698.48 | L71: 1491.58 | M71: -7982.81 | N71: 9049.02 | O71: -9730.65 | P71: -7172.86 | Q71: -2690.79 | R71: 12781.85 | S71: 2420.11 | T71: -9357.79 | U71: 3153.38 | V71: -1347.94 | W71: 679.75 | X71: 179.99 | Y71: -37.41 | Z71: -525.61 | AA71: -2475.97 | AB71: -670.07
A72: 1 | C72: 배당금수취(CF) | E72: 34.61 | G72: 32.07 | H72: 84.82 | I72: 50.16 | J72: 38.75 | K72: 205.8 | L72: 21.4 | M72: 112.97 | N72: 46.65 | O72: 38.65 | P72: 219.67 | Q72: 30.3 | R72: 87.77 | S72: 55.62 | T72: 40.34 | U72: 214.03 | V72: 13.86 | W72: 50.52 | X72: 49.18 | Y72: 56.82 | Z72: 170.38 | AA72: 7.07 | AB72: 64.59
A73: 1 | C73: 법인세납부(CF) | E73: -160.83 | G73: -407.05 | H73: -519.63 | I73: -264.09 | J73: -326.68 | K73: -1517.45 | L73: -1042.92 | M73: -1319.03 | N73: 0 | O73: 7.83 | P73: -2354.12 | Q73: 0 | R73: 734.48 | S73: -803.73 | T73: 762.69 | U73: 693.44 | V73: -2163.99 | W73: -858.95 | X73: -15.48 | Y73: -17.44 | Z73: -3055.86 | AA73: -171.79 | AB73: -171.79
A74: 1 | C74: 투자활동으로인한현금흐름 | E74: -198.21 | G74: 277.68 | H74: -14702.08 | I74: 7118.74 | J74: -5230.45 | K74: -12536.11 | L74: -34.44 | M74: -1133.7 | N74: -2749.69 | O74: 4671.64 | P74: 753.81 | Q74: -591.73 | R74: -1677.85 | S74: -41.11 | T74: 18302.16 | U74: 15991.47 | V74: -7225.6 | W74: -3083.62 | X74: -6707.22 | Y74: 7128.88 | Z74: -9887.56 | AA74: -3447.63 | AB74: -1083.67
A75: 1 | C75: 재무활동으로인한현금흐름 | E75: 89.87 | G75: 48.34 | H75: 14413.22 | I75: 2404.05 | J75: 3896.75 | K75: 20762.36 | L75: -6.9 | M75: 2682.69 | N75: -8727.68 | O75: 5451.67 | P75: -600.22 | Q75: 1696.06 | R75: -971.84 | S75: 502.88 | T75: 2750.31 | U75: 3977.41 | V75: -2870.47 | W75: -819.98 | X75: 929.25 | Y75: -2589.23 | Z75: -5350.43 | AA75: -348.74 | AB75: -889.73
A76: 1 | C76: 단기차입금의증가 | E76: 152.65 | G76: 141.83 | H76: 254.75 | I76: 11217.06 | J76: 3664.29 | K76: 15277.93 | L76: 2142.05 | M76: 5570.93 | N76: 0 | O76: 0 | P76: 7712.98 | Q76: 7712.98 | S76: 1525.62 | T76: 10035.62 | V76: 1899.57 | W76: 2142.91 | X76: 2292.8 | Y76: 2382.86 | Z76: 8718.14 | AA76: 2907.9 | AB76: 1677.08
A77: 1 | C77: 자기주식의취득 | E77: 0 | G77: 0 | H77: 0 | I77: 0 | J77: 0 | K77: 0
A78: 1 | C78: 단기차입금의감소 | E78: 55.84 | G78: 78.5 | H78: 151.78 | I78: 8581.53 | L78: 2143.47 | M78: 2558.29 | N78: 8727.68 | Q78: 5527.85 | S78: 1018.1 | T78: 7285.3 | V78: 4284.84 | W78: 2962.89 | X78: 1356.35 | Y78: 4959.18 | Z78: 13563.26 | AA78: 2592.62 | AB78: 2555.22
A79: 1 | C79: 배당금지급 | E79: 0 | G79: 0 | H79: 1385.37 | I79: 0 | J79: 0 | K79: 1385.37 | L79: 0 | M79: 324.46 | N79: 0 | O79: 0 | P79: 324.46 | Q79: 486.69 | R79: 0 | S79: 0 | T79: 0 | U79: 486.69 | V79: 485.19 | W79: 0 | X79: 0 | Y79: 0 | Z79: 485.19 | AA79: 646.92 | AB79: 0
A80: 1 | C80: 현금및현금성자산의증감 | E80: 2950.77 | G80: -4362.26 | H80: 1756.13 | I80: 20018.87 | J80: -6537.91 | K80: 10874.83 | L80: 1450.23 | M80: -11363.42 | N80: -4905.01 | O80: 787.89 | P80: -14030.31 | Q80: -1617.58 | R80: 10114.99 | S80: 3010.62 | T80: 35001.53 | U80: 46509.56 | V80: -22753.92 | W80: -6688 | X80: -11173.57 | Y80: 24684.28 | Z80: -15931.21 | AA80: -6194.57
A81: 1 | C81: 기말현금및현금성자산 | E81: 1465.53 | G81: 7502.48 | H81: 869.84 | I81: 10072.15 | J81: -3437.07 | K81: 15007.4 | L81: 16457.63 | M81: -6379.82 | N81: -2476.69 | O81: 395.24 | P81: 7996.36 | Q81: 6378.78 | R81: 10114.99 | S81: 3010.63 | T81: 11879.27 | U81: 31383.67 | V81: 20073.74 | W81: -3464.14 | X81: -5575.6 | Y81: 4418.46 | Z81: 15452.46 | AA81: 9257.89 | AB81: -2608.12
A82: 1 | C82: 장기차입금의증가 | G82: 0 | H82: 0 | I82: 0
A83: 1 | C83: 이자수취(CF) | O83: 810.29 | Q83: 135.45 | V83: 178.14 | W83: 132.94 | X83: 101.28 | Y83: 22.12 | Z83: 434.48 | AA83: 103.14 | AB83: 60.91
A84: 1 | C84: 이자지급(CF) | S84: -108.85

Sheet subQ
A1: YQ | C1: subQ 분기 서브모델(억원, U=100) | E1: 4Q21 | F1: 2021 | G1: 1Q22 | H1: 2Q22 | I1: 3Q22 | J1: 4Q22 | K1: 2022 | L1: 1Q23 | M1: 2Q23 | N1: 3Q23 | O1: 4Q23 | P1: 2023 | Q1: 1Q24 | R1: 2Q24 | S1: 3Q24 | T1: 4Q24 | U1: 2024 | V1: 1Q25 | W1: 2Q25 | X1: 3Q25 | Y1: 4Q25 | Z1: 2025 | AA1: 1Q26 | AB1: 2Q26 | AC1: 3Q26 | AD1: 4Q26 | AE1: 2026 | AF1: 1Q27 | AG1: 2Q27 | AH1: 3Q27 | AI1: 4Q27 | AJ1: 2027 | AK1: 1Q28 | AL1: 2Q28 | AM1: 3Q28 | AN1: 4Q28 | AO1: 2028
A2: A=이름(key) B=그룹 C=단위 D=FnGuide 계정명(VLOOKUP 키). 확정=VLOOKUP(BS), 추정=변수 가정 참조
E3: 1 | F3: 2 | G3: 3 | H3: 4 | I3: 5 | J3: 6 | K3: 7 | L3: 8 | M3: 9 | N3: 10 | O3: 11 | P3: 12 | Q3: 13 | R3: 14 | S3: 15 | T3: 16 | U3: 17 | V3: 18 | W3: 19 | X3: 20 | Y3: 21 | Z3: 22 | AA3: 23 | AB3: 24 | AC3: 25 | AD3: 26 | AE3: 27 | AF3: 28 | AG3: 29 | AH3: 30 | AI3: 31 | AJ3: 32 | AK3: 33 | AL3: 34 | AM3: 35 | AN3: 36 | AO3: 37
E4: 2021.12 | F4: 2021.12A | G4: 2022.03 | H4: 2022.06 | I4: 2022.09 | J4: 2022.12 | K4: 2022.12A | L4: 2023.03 | M4: 2023.06 | N4: 2023.09 | O4: 2023.12 | P4: 2023.12A | Q4: 2024.03 | R4: 2024.06 | S4: 2024.09 | T4: 2024.12 | U4: 2024.12A | V4: 2025.03 | W4: 2025.06 | X4: 2025.09 | Y4: 2025.12 | Z4: 2025.12A | AA4: 2026.03 | AB4: 2026.06 | AC4: 2026.09 | AD4: 2026.12 | AE4: 2026.12A | AF4: 2027.03 | AG4: 2027.06 | AH4: 2027.09 | AI4: 2027.12 | AJ4: 2027.12A | AK4: 2028.03 | AL4: 2028.06 | AM4: 2028.09 | AN4: 2028.12 | AO4: 2028.12A
A5: 매출액 | B5: 손익 | C5: 억원 | D5: 매출액(수익) | E5: =IFERROR(VLOOKUP($D5,BS연결,MATCH(E$1,BS연결H,0),0)/100,"") | G5: =IFERROR(VLOOKUP($D5,BS연결,MATCH(G$1,BS연결H,0),0)/100,"") | H5: =IFERROR(VLOOKUP($D5,BS연결,MATCH(H$1,BS연결H,0),0)/100,"") | I5: =IFERROR(VLOOKUP($D5,BS연결,MATCH(I$1,BS연결H,0),0)/100,"") | J5: =IFERROR(VLOOKUP($D5,BS연결,MATCH(J$1,BS연결H,0),0)/100,"") | K5: =IFERROR(VLOOKUP($D5,BS연결,MATCH(K$1,BS연결H,0),0)/100,"") | L5: =IFERROR(VLOOKUP($D5,BS연결,MATCH(L$1,BS연결H,0),0)/100,"") | M5: =IFERROR(VLOOKUP($D5,BS연결,MATCH(M$1,BS연결H,0),0)/100,"") | N5: =IFERROR(VLOOKUP($D5,BS연결,MATCH(N$1,BS연결H,0),0)/100,"") | ... AB5: =IFERROR(VLOOKUP($D5,BS연결,MATCH(AB$1,BS연결H,0),0)/100,"") | AC5: =IFERROR(X5*(1+변수!AC21),"") | AD5: =IFERROR(Y5*(1+변수!AD21),"") | AE5: =SUM(AA5:AD5) | AF5: =IFERROR(AA5*(1+변수!AF21),"") | AG5: =IFERROR(AB5*(1+변수!AG21),"") | AH5: =IFERROR(AC5*(1+변수!AH21),"") | AI5: =IFERROR(AD5*(1+변수!AI21),"") | AJ5: =SUM(AF5:AI5) | AK5: =IFERROR(AF5*(1+변수!AK21),"") | AL5: =IFERROR(AG5*(1+변수!AL21),"") | AM5: =IFERROR(AH5*(1+변수!AM21),"") | AN5: =IFERROR(AI5*(1+변수!AN21),"") | AO5: =SUM(AK5:AN5)
A6: 매출원가 | B6: 손익 | C6: 억원 | D6: 매출원가 | E6: =IFERROR(VLOOKUP($D6,BS연결,MATCH(E$1,BS연결H,0),0)/100,"") | G6: =IFERROR(VLOOKUP($D6,BS연결,MATCH(G$1,BS연결H,0),0)/100,"") | H6: =IFERROR(VLOOKUP($D6,BS연결,MATCH(H$1,BS연결H,0),0)/100,"") | I6: =IFERROR(VLOOKUP($D6,BS연결,MATCH(I$1,BS연결H,0),0)/100,"") | J6: =IFERROR(VLOOKUP($D6,BS연결,MATCH(J$1,BS연결H,0),0)/100,"") | K6: =IFERROR(VLOOKUP($D6,BS연결,MATCH(K$1,BS연결H,0),0)/100,"") | L6: =IFERROR(VLOOKUP($D6,BS연결,MATCH(L$1,BS연결H,0),0)/100,"") | M6: =IFERROR(VLOOKUP($D6,BS연결,MATCH(M$1,BS연결H,0),0)/100,"") | N6: =IFERROR(VLOOKUP($D6,BS연결,MATCH(N$1,BS연결H,0),0)/100,"") | ... AB6: =IFERROR(VLOOKUP($D6,BS연결,MATCH(AB$1,BS연결H,0),0)/100,"") | AC6: =IFERROR(AC5-AC7,"") | AD6: =IFERROR(AD5-AD7,"") | AE6: =SUM(AA6:AD6) | AF6: =IFERROR(AF5-AF7,"") | AG6: =IFERROR(AG5-AG7,"") | AH6: =IFERROR(AH5-AH7,"") | AI6: =IFERROR(AI5-AI7,"") | AJ6: =SUM(AF6:AI6) | AK6: =IFERROR(AK5-AK7,"") | AL6: =IFERROR(AL5-AL7,"") | AM6: =IFERROR(AM5-AM7,"") | AN6: =IFERROR(AN5-AN7,"") | AO6: =SUM(AK6:AN6)
A7: 매출총이익 | B7: 손익 | C7: 억원 | D7: 매출총이익 | E7: =IFERROR(VLOOKUP($D7,BS연결,MATCH(E$1,BS연결H,0),0)/100,"") | G7: =IFERROR(VLOOKUP($D7,BS연결,MATCH(G$1,BS연결H,0),0)/100,"") | H7: =IFERROR(VLOOKUP($D7,BS연결,MATCH(H$1,BS연결H,0),0)/100,"") | I7: =IFERROR(VLOOKUP($D7,BS연결,MATCH(I$1,BS연결H,0),0)/100,"") | J7: =IFERROR(VLOOKUP($D7,BS연결,MATCH(J$1,BS연결H,0),0)/100,"") | K7: =SUM(G7:J7) | L7: =IFERROR(VLOOKUP($D7,BS연결,MATCH(L$1,BS연결H,0),0)/100,"") | M7: =IFERROR(VLOOKUP($D7,BS연결,MATCH(M$1,BS연결H,0),0)/100,"") | N7: =IFERROR(VLOOKUP($D7,BS연결,MATCH(N$1,BS연결H,0),0)/100,"") | O7: =IFERROR(VLOOKUP($D7,BS연결,MATCH(O$1,BS연결H,0),0)/100,"") | P7: =IFERROR(VLOOKUP($D7,BS연결,MATCH(P$1,BS연결H,0),0)/100,"") | Q7: =IFERROR(VLOOKUP($D7,BS연결,MATCH(Q$1,BS연결H,0),0)/100,"") | R7: =IFERROR(VLOOKUP($D7,BS연결,MATCH(R$1,BS연결H,0),0)/100,"") | S7: =IFERROR(VLOOKUP($D7,BS연결,MATCH(S$1,BS연결H,0),0)/100,"") | ... AB7: =IFERROR(VLOOKUP($D7,BS연결,MATCH(AB$1,BS연결H,0),0)/100,"") | AC7: =IFERROR(AC9+AC8,"") | AD7: =IFERROR(AD9+AD8,"") | AE7: =SUM(AA7:AD7) | AF7: =IFERROR(AF9+AF8,"") | AG7: =IFERROR(AG9+AG8,"") | AH7: =IFERROR(AH9+AH8,"") | AI7: =IFERROR(AI9+AI8,"") | AJ7: =SUM(AF7:AI7) | AK7: =IFERROR(AK9+AK8,"") | AL7: =IFERROR(AL9+AL8,"") | AM7: =IFERROR(AM9+AM8,"") | AN7: =IFERROR(AN9+AN8,"") | AO7: =SUM(AK7:AN7)
A8: 판관비 | B8: 손익 | C8: 억원 | D8: 판관비 | E8: =IFERROR(VLOOKUP($D8,BS연결,MATCH(E$1,BS연결H,0),0)/100,"") | G8: =IFERROR(VLOOKUP($D8,BS연결,MATCH(G$1,BS연결H,0),0)/100,"") | H8: =IFERROR(VLOOKUP($D8,BS연결,MATCH(H$1,BS연결H,0),0)/100,"") | I8: =IFERROR(VLOOKUP($D8,BS연결,MATCH(I$1,BS연결H,0),0)/100,"") | J8: =IFERROR(VLOOKUP($D8,BS연결,MATCH(J$1,BS연결H,0),0)/100,"") | K8: =SUM(G8:J8) | L8: =IFERROR(VLOOKUP($D8,BS연결,MATCH(L$1,BS연결H,0),0)/100,"") | M8: =IFERROR(VLOOKUP($D8,BS연결,MATCH(M$1,BS연결H,0),0)/100,"") | N8: =IFERROR(VLOOKUP($D8,BS연결,MATCH(N$1,BS연결H,0),0)/100,"") | O8: =IFERROR(VLOOKUP($D8,BS연결,MATCH(O$1,BS연결H,0),0)/100,"") | P8: =IFERROR(VLOOKUP($D8,BS연결,MATCH(P$1,BS연결H,0),0)/100,"") | Q8: =IFERROR(VLOOKUP($D8,BS연결,MATCH(Q$1,BS연결H,0),0)/100,"") | R8: =IFERROR(VLOOKUP($D8,BS연결,MATCH(R$1,BS연결H,0),0)/100,"") | S8: =IFERROR(VLOOKUP($D8,BS연결,MATCH(S$1,BS연결H,0),0)/100,"") | ... Y8: =IFERROR(VLOOKUP($D8,BS연결,MATCH(Y$1,BS연결H,0),0)/100,"") | Z8: =SUM(V8:Y8) | AA8: =IFERROR(VLOOKUP($D8,BS연결,MATCH(AA$1,BS연결H,0),0)/100,"") | AB8: =IFERROR(VLOOKUP($D8,BS연결,MATCH(AB$1,BS연결H,0),0)/100,"") | AC8: =IFERROR(AC5*변수!AC22,"") | AD8: =IFERROR(AD5*변수!AD22,"") | AE8: =SUM(AA8:AD8) | AF8: =IFERROR(AF5*변수!AF22,"") | AG8: =IFERROR(AG5*변수!AG22,"") | AH8: =IFERROR(AH5*변수!AH22,"") | AI8: =IFERROR(AI5*변수!AI22,"") | AJ8: =SUM(AF8:AI8) | AK8: =IFERROR(AK5*변수!AK22,"") | AL8: =IFERROR(AL5*변수!AL22,"") | AM8: =IFERROR(AM5*변수!AM22,"") | AN8: =IFERROR(AN5*변수!AN22,"") | AO8: =SUM(AK8:AN8)
A9: 영업이익 | B9: 손익 | C9: 억원 | D9: 영업이익 | E9: =IFERROR(VLOOKUP($D9,BS연결,MATCH(E$1,BS연결H,0),0)/100,"") | G9: =IFERROR(VLOOKUP($D9,BS연결,MATCH(G$1,BS연결H,0),0)/100,"") | H9: =IFERROR(VLOOKUP($D9,BS연결,MATCH(H$1,BS연결H,0),0)/100,"") | I9: =IFERROR(VLOOKUP($D9,BS연결,MATCH(I$1,BS연결H,0),0)/100,"") | J9: =IFERROR(VLOOKUP($D9,BS연결,MATCH(J$1,BS연결H,0),0)/100,"") | K9: =IFERROR(VLOOKUP($D9,BS연결,MATCH(K$1,BS연결H,0),0)/100,"") | L9: =IFERROR(VLOOKUP($D9,BS연결,MATCH(L$1,BS연결H,0),0)/100,"") | M9: =IFERROR(VLOOKUP($D9,BS연결,MATCH(M$1,BS연결H,0),0)/100,"") | N9: =IFERROR(VLOOKUP($D9,BS연결,MATCH(N$1,BS연결H,0),0)/100,"") | ... AB9: =IFERROR(VLOOKUP($D9,BS연결,MATCH(AB$1,BS연결H,0),0)/100,"") | AC9: =IFERROR(AC5*변수!AC23,"") | AD9: =IFERROR(AD5*변수!AD23,"") | AE9: =SUM(AA9:AD9) | AF9: =IFERROR(AF5*변수!AF23,"") | AG9: =IFERROR(AG5*변수!AG23,"") | AH9: =IFERROR(AH5*변수!AH23,"") | AI9: =IFERROR(AI5*변수!AI23,"") | AJ9: =SUM(AF9:AI9) | AK9: =IFERROR(AK5*변수!AK23,"") | AL9: =IFERROR(AL5*변수!AL23,"") | AM9: =IFERROR(AM5*변수!AM23,"") | AN9: =IFERROR(AN5*변수!AN23,"") | AO9: =SUM(AK9:AN9)
A10: OPM | B10: 손익 | C10: % | D10: 영업이익률 | E10: =IFERROR(E9/E5,"") | G10: =IFERROR(G9/G5,"") | H10: =IFERROR(H9/H5,"") | I10: =IFERROR(I9/I5,"") | J10: =IFERROR(J9/J5,"") | K10: =IFERROR(K9/K5,"") | L10: =IFERROR(L9/L5,"") | M10: =IFERROR(M9/M5,"") | N10: =IFERROR(N9/N5,"") | ... AO10: =IFERROR(AO9/AO5,"")
A11: 금융손익 | B11: 손익 | C11: 억원 | D11: 금융손익 | E11: =IFERROR(VLOOKUP($D11,BS연결,MATCH(E$1,BS연결H,0),0)/100,"") | G11: =IFERROR(VLOOKUP($D11,BS연결,MATCH(G$1,BS연결H,0),0)/100,"") | H11: =IFERROR(VLOOKUP($D11,BS연결,MATCH(H$1,BS연결H,0),0)/100,"") | I11: =IFERROR(VLOOKUP($D11,BS연결,MATCH(I$1,BS연결H,0),0)/100,"") | J11: =IFERROR(VLOOKUP($D11,BS연결,MATCH(J$1,BS연결H,0),0)/100,"") | K11: =SUM(G11:J11) | L11: =IFERROR(VLOOKUP($D11,BS연결,MATCH(L$1,BS연결H,0),0)/100,"") | M11: =IFERROR(VLOOKUP($D11,BS연결,MATCH(M$1,BS연결H,0),0)/100,"") | N11: =IFERROR(VLOOKUP($D11,BS연결,MATCH(N$1,BS연결H,0),0)/100,"") | O11: =IFERROR(VLOOKUP($D11,BS연결,MATCH(O$1,BS연결H,0),0)/100,"") | P11: =IFERROR(VLOOKUP($D11,BS연결,MATCH(P$1,BS연결H,0),0)/100,"") | Q11: =IFERROR(VLOOKUP($D11,BS연결,MATCH(Q$1,BS연결H,0),0)/100,"") | R11: =IFERROR(VLOOKUP($D11,BS연결,MATCH(R$1,BS연결H,0),0)/100,"") | S11: =IFERROR(VLOOKUP($D11,BS연결,MATCH(S$1,BS연결H,0),0)/100,"") | T11: =IFERROR(VLOOKUP($D11,BS연결,MATCH(T$1,BS연결H,0),0)/100,"") | U11: =SUM(Q11:T11) | V11: =IFERROR(VLOOKUP($D11,BS연결,MATCH(V$1,BS연결H,0),0)/100,"") | W11: =IFERROR(VLOOKUP($D11,BS연결,MATCH(W$1,BS연결H,0),0)/100,"") | X11: =IFERROR(VLOOKUP($D11,BS연결,MATCH(X$1,BS연결H,0),0)/100,"") | Y11: =IFERROR(VLOOKUP($D11,BS연결,MATCH(Y$1,BS연결H,0),0)/100,"") | Z11: =IFERROR(VLOOKUP($D11,BS연결,MATCH(Z$1,BS연결H,0),0)/100,"") | AA11: =IFERROR(VLOOKUP($D11,BS연결,MATCH(AA$1,BS연결H,0),0)/100,"") | AB11: =IFERROR(VLOOKUP($D11,BS연결,MATCH(AB$1,BS연결H,0),0)/100,"") | AC11: =IFERROR(AC12+AC13,"") | AD11: =IFERROR(AD12+AD13,"") | AE11: =SUM(AA11:AD11) | AF11: =IFERROR(AF12+AF13,"") | AG11: =IFERROR(AG12+AG13,"") | AH11: =IFERROR(AH12+AH13,"") | AI11: =IFERROR(AI12+AI13,"") | AJ11: =SUM(AF11:AI11) | AK11: =IFERROR(AK12+AK13,"") | AL11: =IFERROR(AL12+AL13,"") | AM11: =IFERROR(AM12+AM13,"") | AN11: =IFERROR(AN12+AN13,"") | AO11: =SUM(AK11:AN11)
A12: 이자손익 | B12: 손익 | C12: 억원 | D12: 이자손익 | G12: =IFERROR(VLOOKUP($D12,BS연결,MATCH(G$1,BS연결H,0),0)/100,"") | H12: =IFERROR(VLOOKUP($D12,BS연결,MATCH(H$1,BS연결H,0),0)/100,"") | I12: =IFERROR(VLOOKUP($D12,BS연결,MATCH(I$1,BS연결H,0),0)/100,"") | J12: =IFERROR(VLOOKUP($D12,BS연결,MATCH(J$1,BS연결H,0),0)/100,"") | K12: =IFERROR(VLOOKUP($D12,BS연결,MATCH(K$1,BS연결H,0),0)/100,"") | L12: =IFERROR(VLOOKUP($D12,BS연결,MATCH(L$1,BS연결H,0),0)/100,"") | M12: =IFERROR(VLOOKUP($D12,BS연결,MATCH(M$1,BS연결H,0),0)/100,"") | N12: =IFERROR(VLOOKUP($D12,BS연결,MATCH(N$1,BS연결H,0),0)/100,"") | ... AB12: =IFERROR(VLOOKUP($D12,BS연결,MATCH(AB$1,BS연결H,0),0)/100,"") | AC12: =IFERROR((AB25*변수!$D$50-AB23*변수!$D$51)/4,"") | AD12: =IFERROR((AC25*변수!$D$50-AC23*변수!$D$51)/4,"") | AE12: =SUM(AA12:AD12) | AF12: =IFERROR((AD25*변수!$D$50-AD23*변수!$D$51)/4,"") | AG12: =IFERROR((AF25*변수!$D$50-AF23*변수!$D$51)/4,"") | AH12: =IFERROR((AG25*변수!$D$50-AG23*변수!$D$51)/4,"") | AI12: =IFERROR((AH25*변수!$D$50-AH23*변수!$D$51)/4,"") | AJ12: =SUM(AF12:AI12) | AK12: =IFERROR((AI25*변수!$D$50-AI23*변수!$D$51)/4,"") | AL12: =IFERROR((AK25*변수!$D$50-AK23*변수!$D$51)/4,"") | AM12: =IFERROR((AL25*변수!$D$50-AL23*변수!$D$51)/4,"") | AN12: =IFERROR((AM25*변수!$D$50-AM23*변수!$D$51)/4,"") | AO12: =SUM(AK12:AN12)
A13: 외환손익 | B13: 손익 | C13: 억원 | D13: 외환손익(실적만; 추정 환효과는 환관련손익) | G13: =IFERROR((VLOOKUP("외환차익",BS연결,MATCH(G$1,BS연결H,0),0)-VLOOKUP("외환차손",BS연결,MATCH(G$1,BS연결H,0),0)+VLOOKUP("외화환산이익",BS연결,MATCH(G$1,BS연결H,0),0)-VLOOKUP("외화환산손실",BS연결,MATCH(G$1,BS연결H,0),0))/100,"") | H13: =IFERROR((VLOOKUP("외환차익",BS연결,MATCH(H$1,BS연결H,0),0)-VLOOKUP("외환차손",BS연결,MATCH(H$1,BS연결H,0),0)+VLOOKUP("외화환산이익",BS연결,MATCH(H$1,BS연결H,0),0)-VLOOKUP("외화환산손실",BS연결,MATCH(H$1,BS연결H,0),0))/100,"") | K13: =SUM(G13:J13) | M13: =IFERROR((VLOOKUP("외환차익",BS연결,MATCH(M$1,BS연결H,0),0)-VLOOKUP("외환차손",BS연결,MATCH(M$1,BS연결H,0),0)+VLOOKUP("외화환산이익",BS연결,MATCH(M$1,BS연결H,0),0)-VLOOKUP("외화환산손실",BS연결,MATCH(M$1,BS연결H,0),0))/100,"") | N13: =IFERROR((VLOOKUP("외환차익",BS연결,MATCH(N$1,BS연결H,0),0)-VLOOKUP("외환차손",BS연결,MATCH(N$1,BS연결H,0),0)+VLOOKUP("외화환산이익",BS연결,MATCH(N$1,BS연결H,0),0)-VLOOKUP("외화환산손실",BS연결,MATCH(N$1,BS연결H,0),0))/100,"") | O13: =IFERROR((VLOOKUP("외환차익",BS연결,MATCH(O$1,BS연결H,0),0)-VLOOKUP("외환차손",BS연결,MATCH(O$1,BS연결H,0),0)+VLOOKUP("외화환산이익",BS연결,MATCH(O$1,BS연결H,0),0)-VLOOKUP("외화환산손실",BS연결,MATCH(O$1,BS연결H,0),0))/100,"") | P13: =SUM(L13:O13) | Q13: =IFERROR((VLOOKUP("외환차익",BS연결,MATCH(Q$1,BS연결H,0),0)-VLOOKUP("외환차손",BS연결,MATCH(Q$1,BS연결H,0),0)+VLOOKUP("외화환산이익",BS연결,MATCH(Q$1,BS연결H,0),0)-VLOOKUP("외화환산손실",BS연결,MATCH(Q$1,BS연결H,0),0))/100,"") | R13: =IFERROR((VLOOKUP("외환차익",BS연결,MATCH(R$1,BS연결H,0),0)-VLOOKUP("외환차손",BS연결,MATCH(R$1,BS연결H,0),0)+VLOOKUP("외화환산이익",BS연결,MATCH(R$1,BS연결H,0),0)-VLOOKUP("외화환산손실",BS연결,MATCH(R$1,BS연결H,0),0))/100,"") | S13: =IFERROR((VLOOKUP("외환차익",BS연결,MATCH(S$1,BS연결H,0),0)-VLOOKUP("외환차손",BS연결,MATCH(S$1,BS연결H,0),0)+VLOOKUP("외화환산이익",BS연결,MATCH(S$1,BS연결H,0),0)-VLOOKUP("외화환산손실",BS연결,MATCH(S$1,BS연결H,0),0))/100,"") | T13: =IFERROR((VLOOKUP("외환차익",BS연결,MATCH(T$1,BS연결H,0),0)-VLOOKUP("외환차손",BS연결,MATCH(T$1,BS연결H,0),0)+VLOOKUP("외화환산이익",BS연결,MATCH(T$1,BS연결H,0),0)-VLOOKUP("외화환산손실",BS연결,MATCH(T$1,BS연결H,0),0))/100,"") | U13: =SUM(Q13:T13) | V13: =IFERROR((VLOOKUP("외환차익",BS연결,MATCH(V$1,BS연결H,0),0)-VLOOKUP("외환차손",BS연결,MATCH(V$1,BS연결H,0),0)+VLOOKUP("외화환산이익",BS연결,MATCH(V$1,BS연결H,0),0)-VLOOKUP("외화환산손실",BS연결,MATCH(V$1,BS연결H,0),0))/100,"") | W13: =IFERROR((VLOOKUP("외환차익",BS연결,MATCH(W$1,BS연결H,0),0)-VLOOKUP("외환차손",BS연결,MATCH(W$1,BS연결H,0),0)+VLOOKUP("외화환산이익",BS연결,MATCH(W$1,BS연결H,0),0)-VLOOKUP("외화환산손실",BS연결,MATCH(W$1,BS연결H,0),0))/100,"") | X13: =IFERROR((VLOOKUP("외환차익",BS연결,MATCH(X$1,BS연결H,0),0)-VLOOKUP("외환차손",BS연결,MATCH(X$1,BS연결H,0),0)+VLOOKUP("외화환산이익",BS연결,MATCH(X$1,BS연결H,0),0)-VLOOKUP("외화환산손실",BS연결,MATCH(X$1,BS연결H,0),0))/100,"") | Y13: =IFERROR((VLOOKUP("외환차익",BS연결,MATCH(Y$1,BS연결H,0),0)-VLOOKUP("외환차손",BS연결,MATCH(Y$1,BS연결H,0),0)+VLOOKUP("외화환산이익",BS연결,MATCH(Y$1,BS연결H,0),0)-VLOOKUP("외화환산손실",BS연결,MATCH(Y$1,BS연결H,0),0))/100,"") | Z13: =SUM(V13:Y13) | AA13: =IFERROR((VLOOKUP("외환차익",BS연결,MATCH(AA$1,BS연결H,0),0)-VLOOKUP("외환차손",BS연결,MATCH(AA$1,BS연결H,0),0)+VLOOKUP("외화환산이익",BS연결,MATCH(AA$1,BS연결H,0),0)-VLOOKUP("외화환산손실",BS연결,MATCH(AA$1,BS연결H,0),0))/100,"") | AB13: =IFERROR((VLOOKUP("외환차익",BS연결,MATCH(AB$1,BS연결H,0),0)-VLOOKUP("외환차손",BS연결,MATCH(AB$1,BS연결H,0),0)+VLOOKUP("외화환산이익",BS연결,MATCH(AB$1,BS연결H,0),0)-VLOOKUP("외화환산손실",BS연결,MATCH(AB$1,BS연결H,0),0))/100,"") | AC13: =변수!AC24 | AD13: =변수!AD24 | AE13: =SUM(AA13:AD13) | AF13: =변수!AF24 | AG13: =변수!AG24 | AH13: =변수!AH24 | AI13: =변수!AI24 | AJ13: =SUM(AF13:AI13) | AK13: =변수!AK24 | AL13: =변수!AL24 | AM13: =변수!AM24 | AN13: =변수!AN24 | AO13: =SUM(AK13:AN13)
A14: 기타영업외손익 | B14: 손익 | C14: 억원 | D14: 기타영업외손익 | E14: =IFERROR(VLOOKUP($D14,BS연결,MATCH(E$1,BS연결H,0),0)/100,"") | G14: =IFERROR(VLOOKUP($D14,BS연결,MATCH(G$1,BS연결H,0),0)/100,"") | H14: =IFERROR(VLOOKUP($D14,BS연결,MATCH(H$1,BS연결H,0),0)/100,"") | I14: =IFERROR(VLOOKUP($D14,BS연결,MATCH(I$1,BS연결H,0),0)/100,"") | J14: =IFERROR(VLOOKUP($D14,BS연결,MATCH(J$1,BS연결H,0),0)/100,"") | K14: =IFERROR(VLOOKUP($D14,BS연결,MATCH(K$1,BS연결H,0),0)/100,"") | L14: =IFERROR(VLOOKUP($D14,BS연결,MATCH(L$1,BS연결H,0),0)/100,"") | M14: =IFERROR(VLOOKUP($D14,BS연결,MATCH(M$1,BS연결H,0),0)/100,"") | N14: =IFERROR(VLOOKUP($D14,BS연결,MATCH(N$1,BS연결H,0),0)/100,"") | ... AB14: =IFERROR(VLOOKUP($D14,BS연결,MATCH(AB$1,BS연결H,0),0)/100,"") | AC14: =변수!AC25 | AD14: =변수!AD25 | AE14: =SUM(AA14:AD14) | AF14: =변수!AF25 | AG14: =변수!AG25 | AH14: =변수!AH25 | AI14: =변수!AI25 | AJ14: =SUM(AF14:AI14) | AK14: =변수!AK25 | AL14: =변수!AL25 | AM14: =변수!AM25 | AN14: =변수!AN25 | AO14: =SUM(AK14:AN14)
A15: 세전이익 | B15: 손익 | C15: 억원 | D15: 법인세비용차감전계속사업이익 | E15: =IFERROR(VLOOKUP($D15,BS연결,MATCH(E$1,BS연결H,0),0)/100,"") | G15: =IFERROR(VLOOKUP($D15,BS연결,MATCH(G$1,BS연결H,0),0)/100,"") | H15: =IFERROR(VLOOKUP($D15,BS연결,MATCH(H$1,BS연결H,0),0)/100,"") | I15: =IFERROR(VLOOKUP($D15,BS연결,MATCH(I$1,BS연결H,0),0)/100,"") | J15: =IFERROR(VLOOKUP($D15,BS연결,MATCH(J$1,BS연결H,0),0)/100,"") | K15: =IFERROR(VLOOKUP($D15,BS연결,MATCH(K$1,BS연결H,0),0)/100,"") | L15: =IFERROR(VLOOKUP($D15,BS연결,MATCH(L$1,BS연결H,0),0)/100,"") | M15: =IFERROR(VLOOKUP($D15,BS연결,MATCH(M$1,BS연결H,0),0)/100,"") | N15: =IFERROR(VLOOKUP($D15,BS연결,MATCH(N$1,BS연결H,0),0)/100,"") | ... Y15: =IFERROR(VLOOKUP($D15,BS연결,MATCH(Y$1,BS연결H,0),0)/100,"") | Z15: =SUM(V15:Y15) | AA15: =IFERROR(VLOOKUP($D15,BS연결,MATCH(AA$1,BS연결H,0),0)/100,"") | AB15: =IFERROR(VLOOKUP($D15,BS연결,MATCH(AB$1,BS연결H,0),0)/100,"") | AC15: =IFERROR(AC9+AC11+AC14,"") | AD15: =IFERROR(AD9+AD11+AD14,"") | AE15: =SUM(AA15:AD15) | AF15: =IFERROR(AF9+AF11+AF14,"") | AG15: =IFERROR(AG9+AG11+AG14,"") | AH15: =IFERROR(AH9+AH11+AH14,"") | AI15: =IFERROR(AI9+AI11+AI14,"") | AJ15: =SUM(AF15:AI15) | AK15: =IFERROR(AK9+AK11+AK14,"") | AL15: =IFERROR(AL9+AL11+AL14,"") | AM15: =IFERROR(AM9+AM11+AM14,"") | AN15: =IFERROR(AN9+AN11+AN14,"") | AO15: =SUM(AK15:AN15)
A16: 법인세비용 | B16: 손익 | C16: 억원 | D16: 법인세비용 | E16: =IFERROR(VLOOKUP($D16,BS연결,MATCH(E$1,BS연결H,0),0)/100,"") | G16: =IFERROR(VLOOKUP($D16,BS연결,MATCH(G$1,BS연결H,0),0)/100,"") | H16: =IFERROR(VLOOKUP($D16,BS연결,MATCH(H$1,BS연결H,0),0)/100,"") | I16: =IFERROR(VLOOKUP($D16,BS연결,MATCH(I$1,BS연결H,0),0)/100,"") | J16: =IFERROR(VLOOKUP($D16,BS연결,MATCH(J$1,BS연결H,0),0)/100,"") | K16: =IFERROR(VLOOKUP($D16,BS연결,MATCH(K$1,BS연결H,0),0)/100,"") | L16: =IFERROR(VLOOKUP($D16,BS연결,MATCH(L$1,BS연결H,0),0)/100,"") | M16: =IFERROR(VLOOKUP($D16,BS연결,MATCH(M$1,BS연결H,0),0)/100,"") | N16: =IFERROR(VLOOKUP($D16,BS연결,MATCH(N$1,BS연결H,0),0)/100,"") | ... AB16: =IFERROR(VLOOKUP($D16,BS연결,MATCH(AB$1,BS연결H,0),0)/100,"") | AC16: =IFERROR(AC15*변수!AC26,"") | AD16: =IFERROR(AD15*변수!AD26,"") | AE16: =SUM(AA16:AD16) | AF16: =IFERROR(AF15*변수!AF26,"") | AG16: =IFERROR(AG15*변수!AG26,"") | AH16: =IFERROR(AH15*변수!AH26,"") | AI16: =IFERROR(AI15*변수!AI26,"") | AJ16: =SUM(AF16:AI16) | AK16: =IFERROR(AK15*변수!AK26,"") | AL16: =IFERROR(AL15*변수!AL26,"") | AM16: =IFERROR(AM15*변수!AM26,"") | AN16: =IFERROR(AN15*변수!AN26,"") | AO16: =SUM(AK16:AN16)
A17: 당기순이익 | B17: 손익 | C17: 억원 | D17: 당기순이익 | E17: =IFERROR(VLOOKUP($D17,BS연결,MATCH(E$1,BS연결H,0),0)/100,"") | G17: =IFERROR(VLOOKUP($D17,BS연결,MATCH(G$1,BS연결H,0),0)/100,"") | H17: =IFERROR(VLOOKUP($D17,BS연결,MATCH(H$1,BS연결H,0),0)/100,"") | I17: =IFERROR(VLOOKUP($D17,BS연결,MATCH(I$1,BS연결H,0),0)/100,"") | J17: =IFERROR(VLOOKUP($D17,BS연결,MATCH(J$1,BS연결H,0),0)/100,"") | K17: =IFERROR(VLOOKUP($D17,BS연결,MATCH(K$1,BS연결H,0),0)/100,"") | L17: =IFERROR(VLOOKUP($D17,BS연결,MATCH(L$1,BS연결H,0),0)/100,"") | M17: =IFERROR(VLOOKUP($D17,BS연결,MATCH(M$1,BS연결H,0),0)/100,"") | N17: =IFERROR(VLOOKUP($D17,BS연결,MATCH(N$1,BS연결H,0),0)/100,"") | ... AB17: =IFERROR(VLOOKUP($D17,BS연결,MATCH(AB$1,BS연결H,0),0)/100,"") | AC17: =IFERROR(AC15-AC16,"") | AD17: =IFERROR(AD15-AD16,"") | AE17: =SUM(AA17:AD17) | AF17: =IFERROR(AF15-AF16,"") | AG17: =IFERROR(AG15-AG16,"") | AH17: =IFERROR(AH15-AH16,"") | AI17: =IFERROR(AI15-AI16,"") | AJ17: =SUM(AF17:AI17) | AK17: =IFERROR(AK15-AK16,"") | AL17: =IFERROR(AL15-AL16,"") | AM17: =IFERROR(AM15-AM16,"") | AN17: =IFERROR(AN15-AN16,"") | AO17: =SUM(AK17:AN17)
A18: 지배주주순이익 | B18: 손익 | C18: 억원 | D18: (지배주주지분)당기순이익 | E18: =IFERROR(VLOOKUP($D18,BS연결,MATCH(E$1,BS연결H,0),0)/100,"") | G18: =IFERROR(VLOOKUP($D18,BS연결,MATCH(G$1,BS연결H,0),0)/100,"") | H18: =IFERROR(VLOOKUP($D18,BS연결,MATCH(H$1,BS연결H,0),0)/100,"") | I18: =IFERROR(VLOOKUP($D18,BS연결,MATCH(I$1,BS연결H,0),0)/100,"") | J18: =IFERROR(VLOOKUP($D18,BS연결,MATCH(J$1,BS연결H,0),0)/100,"") | K18: =SUM(G18:J18) | L18: =IFERROR(VLOOKUP($D18,BS연결,MATCH(L$1,BS연결H,0),0)/100,"") | M18: =IFERROR(VLOOKUP($D18,BS연결,MATCH(M$1,BS연결H,0),0)/100,"") | N18: =IFERROR(VLOOKUP($D18,BS연결,MATCH(N$1,BS연결H,0),0)/100,"") | O18: =IFERROR(VLOOKUP($D18,BS연결,MATCH(O$1,BS연결H,0),0)/100,"") | P18: =IFERROR(VLOOKUP($D18,BS연결,MATCH(P$1,BS연결H,0),0)/100,"") | Q18: =IFERROR(VLOOKUP($D18,BS연결,MATCH(Q$1,BS연결H,0),0)/100,"") | R18: =IFERROR(VLOOKUP($D18,BS연결,MATCH(R$1,BS연결H,0),0)/100,"") | S18: =IFERROR(VLOOKUP($D18,BS연결,MATCH(S$1,BS연결H,0),0)/100,"") | ... AB18: =IFERROR(VLOOKUP($D18,BS연결,MATCH(AB$1,BS연결H,0),0)/100,"") | AC18: =IFERROR(AC17*변수!AC27,"") | AD18: =IFERROR(AD17*변수!AD27,"") | AE18: =SUM(AA18:AD18) | AF18: =IFERROR(AF17*변수!AF27,"") | AG18: =IFERROR(AG17*변수!AG27,"") | AH18: =IFERROR(AH17*변수!AH27,"") | AI18: =IFERROR(AI17*변수!AI27,"") | AJ18: =SUM(AF18:AI18) | AK18: =IFERROR(AK17*변수!AK27,"") | AL18: =IFERROR(AL17*변수!AL27,"") | AM18: =IFERROR(AM17*변수!AM27,"") | AN18: =IFERROR(AN17*변수!AN27,"") | AO18: =SUM(AK18:AN18)
A19: 자산총계 | B19: 재무상태 | C19: 억원 | D19: 자산총계 | E19: =IFERROR(VLOOKUP($D19,BS연결,MATCH(E$1,BS연결H,0),0)/100,"") | F19: =IFERROR(VLOOKUP($D19,BS연결,MATCH(F$1,BS연결H,0),0)/100,"") | G19: =IFERROR(VLOOKUP($D19,BS연결,MATCH(G$1,BS연결H,0),0)/100,"") | H19: =IFERROR(VLOOKUP($D19,BS연결,MATCH(H$1,BS연결H,0),0)/100,"") | I19: =IFERROR(VLOOKUP($D19,BS연결,MATCH(I$1,BS연결H,0),0)/100,"") | J19: =IFERROR(VLOOKUP($D19,BS연결,MATCH(J$1,BS연결H,0),0)/100,"") | K19: =IFERROR(VLOOKUP($D19,BS연결,MATCH(K$1,BS연결H,0),0)/100,"") | L19: =IFERROR(VLOOKUP($D19,BS연결,MATCH(L$1,BS연결H,0),0)/100,"") | ... AB19: =IFERROR(VLOOKUP($D19,BS연결,MATCH(AB$1,BS연결H,0),0)/100,"") | AC19: =IFERROR(AC20+AC21,"") | AD19: =IFERROR(AD20+AD21,"") | AE19: =AD19 | AF19: =IFERROR(AF20+AF21,"") | AG19: =IFERROR(AG20+AG21,"") | AH19: =IFERROR(AH20+AH21,"") | AI19: =IFERROR(AI20+AI21,"") | AJ19: =AI19 | AK19: =IFERROR(AK20+AK21,"") | AL19: =IFERROR(AL20+AL21,"") | AM19: =IFERROR(AM20+AM21,"") | AN19: =IFERROR(AN20+AN21,"") | AO19: =AN19
A20: 부채총계 | B20: 재무상태 | C20: 억원 | D20: 부채총계 | E20: =IFERROR(VLOOKUP($D20,BS연결,MATCH(E$1,BS연결H,0),0)/100,"") | F20: =IFERROR(VLOOKUP($D20,BS연결,MATCH(F$1,BS연결H,0),0)/100,"") | G20: =IFERROR(VLOOKUP($D20,BS연결,MATCH(G$1,BS연결H,0),0)/100,"") | H20: =IFERROR(VLOOKUP($D20,BS연결,MATCH(H$1,BS연결H,0),0)/100,"") | I20: =IFERROR(VLOOKUP($D20,BS연결,MATCH(I$1,BS연결H,0),0)/100,"") | J20: =IFERROR(VLOOKUP($D20,BS연결,MATCH(J$1,BS연결H,0),0)/100,"") | K20: =IFERROR(VLOOKUP($D20,BS연결,MATCH(K$1,BS연결H,0),0)/100,"") | L20: =IFERROR(VLOOKUP($D20,BS연결,MATCH(L$1,BS연결H,0),0)/100,"") | ... AB20: =IFERROR(VLOOKUP($D20,BS연결,MATCH(AB$1,BS연결H,0),0)/100,"") | AC20: =IFERROR(AB20*(1+변수!AC28),"") | AD20: =IFERROR(AC20*(1+변수!AD28),"") | AE20: =AD20 | AF20: =IFERROR(AD20*(1+변수!AF28),"") | AG20: =IFERROR(AF20*(1+변수!AG28),"") | AH20: =IFERROR(AG20*(1+변수!AH28),"") | AI20: =IFERROR(AH20*(1+변수!AI28),"") | AJ20: =AI20 | AK20: =IFERROR(AI20*(1+변수!AK28),"") | AL20: =IFERROR(AK20*(1+변수!AL28),"") | AM20: =IFERROR(AL20*(1+변수!AM28),"") | AN20: =IFERROR(AM20*(1+변수!AN28),"") | AO20: =AN20
A21: 자본총계 | B21: 재무상태 | C21: 억원 | D21: 자본총계 | E21: =IFERROR(VLOOKUP($D21,BS연결,MATCH(E$1,BS연결H,0),0)/100,"") | F21: =IFERROR(VLOOKUP($D21,BS연결,MATCH(F$1,BS연결H,0),0)/100,"") | G21: =IFERROR(VLOOKUP($D21,BS연결,MATCH(G$1,BS연결H,0),0)/100,"") | H21: =IFERROR(VLOOKUP($D21,BS연결,MATCH(H$1,BS연결H,0),0)/100,"") | I21: =IFERROR(VLOOKUP($D21,BS연결,MATCH(I$1,BS연결H,0),0)/100,"") | J21: =IFERROR(VLOOKUP($D21,BS연결,MATCH(J$1,BS연결H,0),0)/100,"") | K21: =IFERROR(VLOOKUP($D21,BS연결,MATCH(K$1,BS연결H,0),0)/100,"") | L21: =IFERROR(VLOOKUP($D21,BS연결,MATCH(L$1,BS연결H,0),0)/100,"") | ... AB21: =IFERROR(VLOOKUP($D21,BS연결,MATCH(AB$1,BS연결H,0),0)/100,"") | AC21: =IFERROR(AB21+AC17-변수!AC29,"") | AD21: =IFERROR(AC21+AD17-변수!AD29,"") | AE21: =AD21 | AF21: =IFERROR(AD21+AF17-변수!AF29,"") | AG21: =IFERROR(AF21+AG17-변수!AG29,"") | AH21: =IFERROR(AG21+AH17-변수!AH29,"") | AI21: =IFERROR(AH21+AI17-변수!AI29,"") | AJ21: =AI21 | AK21: =IFERROR(AI21+AK17-변수!AK29,"") | AL21: =IFERROR(AK21+AL17-변수!AL29,"") | AM21: =IFERROR(AL21+AM17-변수!AM29,"") | AN21: =IFERROR(AM21+AN17-변수!AN29,"") | AO21: =AN21
A22: 지배주주지분 | B22: 재무상태 | C22: 억원 | D22: 지배주주지분 | E22: =IFERROR(VLOOKUP($D22,BS연결,MATCH(E$1,BS연결H,0),0)/100,"") | F22: =IFERROR(VLOOKUP($D22,BS연결,MATCH(F$1,BS연결H,0),0)/100,"") | G22: =IFERROR(VLOOKUP($D22,BS연결,MATCH(G$1,BS연결H,0),0)/100,"") | H22: =IFERROR(VLOOKUP($D22,BS연결,MATCH(H$1,BS연결H,0),0)/100,"") | I22: =IFERROR(VLOOKUP($D22,BS연결,MATCH(I$1,BS연결H,0),0)/100,"") | J22: =IFERROR(VLOOKUP($D22,BS연결,MATCH(J$1,BS연결H,0),0)/100,"") | K22: =IFERROR(VLOOKUP($D22,BS연결,MATCH(K$1,BS연결H,0),0)/100,"") | L22: =IFERROR(VLOOKUP($D22,BS연결,MATCH(L$1,BS연결H,0),0)/100,"") | ... AB22: =IFERROR(VLOOKUP($D22,BS연결,MATCH(AB$1,BS연결H,0),0)/100,"") | AC22: =IFERROR(AB22+AC18-변수!AC30,"") | AD22: =IFERROR(AC22+AD18-변수!AD30,"") | AE22: =AD22 | AF22: =IFERROR(AD22+AF18-변수!AF30,"") | AG22: =IFERROR(AF22+AG18-변수!AG30,"") | AH22: =IFERROR(AG22+AH18-변수!AH30,"") | AI22: =IFERROR(AH22+AI18-변수!AI30,"") | AJ22: =AI22 | AK22: =IFERROR(AI22+AK18-변수!AK30,"") | AL22: =IFERROR(AK22+AL18-변수!AL30,"") | AM22: =IFERROR(AL22+AM18-변수!AM30,"") | AN22: =IFERROR(AM22+AN18-변수!AN30,"") | AO22: =AN22
A23: 총차입금 | B23: 재무상태 | C23: 억원 | D23: 총차입금 | E23: =IFERROR(VLOOKUP($D23,BS연결,MATCH(E$1,BS연결H,0),0)/100,"") | F23: =IFERROR(VLOOKUP($D23,BS연결,MATCH(F$1,BS연결H,0),0)/100,"") | G23: =IFERROR(VLOOKUP($D23,BS연결,MATCH(G$1,BS연결H,0),0)/100,"") | H23: =IFERROR(VLOOKUP($D23,BS연결,MATCH(H$1,BS연결H,0),0)/100,"") | I23: =IFERROR(VLOOKUP($D23,BS연결,MATCH(I$1,BS연결H,0),0)/100,"") | J23: =IFERROR(VLOOKUP($D23,BS연결,MATCH(J$1,BS연결H,0),0)/100,"") | K23: =IFERROR(VLOOKUP($D23,BS연결,MATCH(K$1,BS연결H,0),0)/100,"") | L23: =IFERROR(VLOOKUP($D23,BS연결,MATCH(L$1,BS연결H,0),0)/100,"") | ... AB23: =IFERROR(VLOOKUP($D23,BS연결,MATCH(AB$1,BS연결H,0),0)/100,"") | AC23: =IFERROR(AB23*(1+변수!AC31),"") | AD23: =IFERROR(AC23*(1+변수!AD31),"") | AE23: =AD23 | AF23: =IFERROR(AD23*(1+변수!AF31),"") | AG23: =IFERROR(AF23*(1+변수!AG31),"") | AH23: =IFERROR(AG23*(1+변수!AH31),"") | AI23: =IFERROR(AH23*(1+변수!AI31),"") | AJ23: =AI23 | AK23: =IFERROR(AI23*(1+변수!AK31),"") | AL23: =IFERROR(AK23*(1+변수!AL31),"") | AM23: =IFERROR(AL23*(1+변수!AM31),"") | AN23: =IFERROR(AM23*(1+변수!AN31),"") | AO23: =AN23
A24: 순차입금 | B24: 재무상태 | C24: 억원 | D24: 순차입금 | E24: =IFERROR(VLOOKUP($D24,BS연결,MATCH(E$1,BS연결H,0),0)/100,"") | F24: =IFERROR(VLOOKUP($D24,BS연결,MATCH(F$1,BS연결H,0),0)/100,"") | G24: =IFERROR(VLOOKUP($D24,BS연결,MATCH(G$1,BS연결H,0),0)/100,"") | H24: =IFERROR(VLOOKUP($D24,BS연결,MATCH(H$1,BS연결H,0),0)/100,"") | I24: =IFERROR(VLOOKUP($D24,BS연결,MATCH(I$1,BS연결H,0),0)/100,"") | J24: =IFERROR(VLOOKUP($D24,BS연결,MATCH(J$1,BS연결H,0),0)/100,"") | K24: =IFERROR(VLOOKUP($D24,BS연결,MATCH(K$1,BS연결H,0),0)/100,"") | L24: =IFERROR(VLOOKUP($D24,BS연결,MATCH(L$1,BS연결H,0),0)/100,"") | ... AB24: =IFERROR(VLOOKUP($D24,BS연결,MATCH(AB$1,BS연결H,0),0)/100,"") | AC24: =IFERROR(AB24*(1+변수!AC32),"") | AD24: =IFERROR(AC24*(1+변수!AD32),"") | AE24: =AD24 | AF24: =IFERROR(AD24*(1+변수!AF32),"") | AG24: =IFERROR(AF24*(1+변수!AG32),"") | AH24: =IFERROR(AG24*(1+변수!AH32),"") | AI24: =IFERROR(AH24*(1+변수!AI32),"") | AJ24: =AI24 | AK24: =IFERROR(AI24*(1+변수!AK32),"") | AL24: =IFERROR(AK24*(1+변수!AL32),"") | AM24: =IFERROR(AL24*(1+변수!AM32),"") | AN24: =IFERROR(AM24*(1+변수!AN32),"") | AO24: =AN24
A25: 이자발생자산 | B25: 재무상태 | C25: 억원 | D25: 이자발생자산 | E25: =IFERROR(VLOOKUP($D25,BS연결,MATCH(E$1,BS연결H,0),0)/100,"") | F25: =IFERROR(VLOOKUP($D25,BS연결,MATCH(F$1,BS연결H,0),0)/100,"") | G25: =IFERROR(VLOOKUP($D25,BS연결,MATCH(G$1,BS연결H,0),0)/100,"") | H25: =IFERROR(VLOOKUP($D25,BS연결,MATCH(H$1,BS연결H,0),0)/100,"") | I25: =IFERROR(VLOOKUP($D25,BS연결,MATCH(I$1,BS연결H,0),0)/100,"") | J25: =IFERROR(VLOOKUP($D25,BS연결,MATCH(J$1,BS연결H,0),0)/100,"") | K25: =IFERROR(VLOOKUP($D25,BS연결,MATCH(K$1,BS연결H,0),0)/100,"") | L25: =IFERROR(VLOOKUP($D25,BS연결,MATCH(L$1,BS연결H,0),0)/100,"") | ... AB25: =IFERROR(VLOOKUP($D25,BS연결,MATCH(AB$1,BS연결H,0),0)/100,"") | AC25: =IFERROR(AB25*(1+변수!AC33),"") | AD25: =IFERROR(AC25*(1+변수!AD33),"") | AE25: =AD25 | AF25: =IFERROR(AD25*(1+변수!AF33),"") | AG25: =IFERROR(AF25*(1+변수!AG33),"") | AH25: =IFERROR(AG25*(1+변수!AH33),"") | AI25: =IFERROR(AH25*(1+변수!AI33),"") | AJ25: =AI25 | AK25: =IFERROR(AI25*(1+변수!AK33),"") | AL25: =IFERROR(AK25*(1+변수!AL33),"") | AM25: =IFERROR(AL25*(1+변수!AM33),"") | AN25: =IFERROR(AM25*(1+변수!AN33),"") | AO25: =AN25
A26: 현금및현금성자산 | B26: 재무상태 | C26: 억원 | D26: 현금및현금성자산 | E26: =IFERROR(VLOOKUP($D26,BS연결,MATCH(E$1,BS연결H,0),0)/100,"") | F26: =IFERROR(VLOOKUP($D26,BS연결,MATCH(F$1,BS연결H,0),0)/100,"") | G26: =IFERROR(VLOOKUP($D26,BS연결,MATCH(G$1,BS연결H,0),0)/100,"") | H26: =IFERROR(VLOOKUP($D26,BS연결,MATCH(H$1,BS연결H,0),0)/100,"") | I26: =IFERROR(VLOOKUP($D26,BS연결,MATCH(I$1,BS연결H,0),0)/100,"") | J26: =IFERROR(VLOOKUP($D26,BS연결,MATCH(J$1,BS연결H,0),0)/100,"") | K26: =IFERROR(VLOOKUP($D26,BS연결,MATCH(K$1,BS연결H,0),0)/100,"") | L26: =IFERROR(VLOOKUP($D26,BS연결,MATCH(L$1,BS연결H,0),0)/100,"") | ... AB26: =IFERROR(VLOOKUP($D26,BS연결,MATCH(AB$1,BS연결H,0),0)/100,"") | AE26: =AD26 | AJ26: =AI26 | AO26: =AN26
A27: 영업활동현금흐름 | B27: 현금흐름 | C27: 억원 | D27: 영업활동으로인한현금흐름 | E27: =IFERROR(VLOOKUP($D27,BS연결,MATCH(E$1,BS연결H,0),0)/100,"") | G27: =IFERROR(VLOOKUP($D27,BS연결,MATCH(G$1,BS연결H,0),0)/100,"") | H27: =IFERROR(VLOOKUP($D27,BS연결,MATCH(H$1,BS연결H,0),0)/100,"") | I27: =IFERROR(VLOOKUP($D27,BS연결,MATCH(I$1,BS연결H,0),0)/100,"") | J27: =IFERROR(VLOOKUP($D27,BS연결,MATCH(J$1,BS연결H,0),0)/100,"") | K27: =IFERROR(VLOOKUP($D27,BS연결,MATCH(K$1,BS연결H,0),0)/100,"") | L27: =IFERROR(VLOOKUP($D27,BS연결,MATCH(L$1,BS연결H,0),0)/100,"") | M27: =IFERROR(VLOOKUP($D27,BS연결,MATCH(M$1,BS연결H,0),0)/100,"") | N27: =IFERROR(VLOOKUP($D27,BS연결,MATCH(N$1,BS연결H,0),0)/100,"") | ... AB27: =IFERROR(VLOOKUP($D27,BS연결,MATCH(AB$1,BS연결H,0),0)/100,"") | AE27: =SUM(AA27:AD27) | AJ27: =SUM(AF27:AI27) | AO27: =SUM(AK27:AN27)
A28: 주식수 | B28: 주당 | C28: 백만주 | D28: 유통주식수 | E28: 30.786 | F28: =E28 | G28: 30.786 | H28: 32.446 | I28: 32.446 | J28: 32.446 | K28: =J28 | L28: 32.446 | M28: 32.446 | N28: 32.446 | O28: 32.446 | P28: =O28 | Q28: 32.446 | R28: 32.346 | S28: 32.346 | T28: 32.346 | U28: =T28 | V28: 32.346 | W28: 32.346 | X28: 32.346 | Y28: 32.346 | Z28: =Y28 | AA28: 32.346 | AB28: 32.346 | AC28: =IFERROR(AB28*(1+변수!AC36),"") | AD28: =IFERROR(AC28*(1+변수!AD36),"") | AE28: =AD28 | AF28: =IFERROR(AD28*(1+변수!AF36),"") | AG28: =IFERROR(AF28*(1+변수!AG36),"") | AH28: =IFERROR(AG28*(1+변수!AH36),"") | AI28: =IFERROR(AH28*(1+변수!AI36),"") | AJ28: =AI28 | AK28: =IFERROR(AI28*(1+변수!AK36),"") | AL28: =IFERROR(AK28*(1+변수!AL36),"") | AM28: =IFERROR(AL28*(1+변수!AM36),"") | AN28: =IFERROR(AM28*(1+변수!AN36),"") | AO28: =AN28
A29: EPS | B29: 주당 | C29: 원 | D29: EPS | E29: =IFERROR(E18*100/E28,"") | G29: =IFERROR(G18*100/G28,"") | H29: =IFERROR(H18*100/H28,"") | I29: =IFERROR(I18*100/I28,"") | J29: =IFERROR(J18*100/J28,"") | K29: =SUM(G29:J29) | L29: =IFERROR(L18*100/L28,"") | M29: =IFERROR(M18*100/M28,"") | N29: =IFERROR(N18*100/N28,"") | O29: =IFERROR(O18*100/O28,"") | P29: =SUM(L29:O29) | Q29: =IFERROR(Q18*100/Q28,"") | R29: =IFERROR(R18*100/R28,"") | S29: =IFERROR(S18*100/S28,"") | T29: =IFERROR(T18*100/T28,"") | U29: =SUM(Q29:T29) | V29: =IFERROR(V18*100/V28,"") | W29: =IFERROR(W18*100/W28,"") | X29: =IFERROR(X18*100/X28,"") | Y29: =IFERROR(Y18*100/Y28,"") | Z29: =SUM(V29:Y29) | AA29: =IFERROR(AA18*100/AA28,"") | AB29: =IFERROR(AB18*100/AB28,"") | AC29: =IFERROR(AC18*100/AC28,"") | AD29: =IFERROR(AD18*100/AD28,"") | AE29: =SUM(AA29:AD29) | AF29: =IFERROR(AF18*100/AF28,"") | AG29: =IFERROR(AG18*100/AG28,"") | AH29: =IFERROR(AH18*100/AH28,"") | AI29: =IFERROR(AI18*100/AI28,"") | AJ29: =SUM(AF29:AI29) | AK29: =IFERROR(AK18*100/AK28,"") | AL29: =IFERROR(AL18*100/AL28,"") | AM29: =IFERROR(AM18*100/AM28,"") | AN29: =IFERROR(AN18*100/AN28,"") | AO29: =SUM(AK29:AN29)
A30: BPS | B30: 주당 | C30: 원 | D30: BPS | E30: =IFERROR(E22*100/E28,"") | F30: =E30 | G30: =IFERROR(G22*100/G28,"") | H30: =IFERROR(H22*100/H28,"") | I30: =IFERROR(I22*100/I28,"") | J30: =IFERROR(J22*100/J28,"") | K30: =J30 | L30: =IFERROR(L22*100/L28,"") | M30: =IFERROR(M22*100/M28,"") | N30: =IFERROR(N22*100/N28,"") | O30: =IFERROR(O22*100/O28,"") | P30: =O30 | Q30: =IFERROR(Q22*100/Q28,"") | R30: =IFERROR(R22*100/R28,"") | S30: =IFERROR(S22*100/S28,"") | T30: =IFERROR(T22*100/T28,"") | U30: =T30 | V30: =IFERROR(V22*100/V28,"") | W30: =IFERROR(W22*100/W28,"") | X30: =IFERROR(X22*100/X28,"") | Y30: =IFERROR(Y22*100/Y28,"") | Z30: =Y30 | AA30: =IFERROR(AA22*100/AA28,"") | AB30: =IFERROR(AB22*100/AB28,"") | AC30: =IFERROR(AC22*100/AC28,"") | AD30: =IFERROR(AD22*100/AD28,"") | AE30: =AD30 | AF30: =IFERROR(AF22*100/AF28,"") | AG30: =IFERROR(AG22*100/AG28,"") | AH30: =IFERROR(AH22*100/AH28,"") | AI30: =IFERROR(AI22*100/AI28,"") | AJ30: =AI30 | AK30: =IFERROR(AK22*100/AK28,"") | AL30: =IFERROR(AL22*100/AL28,"") | AM30: =IFERROR(AM22*100/AM28,"") | AN30: =IFERROR(AN22*100/AN28,"") | AO30: =AN30
A31: DPS | B31: 주당 | C31: 원 | D31: DPS(보통주) | E31: 45 | F31: 45 | J31: 10 | K31: =SUM(G31:J31) | O31: 0 | P31: =SUM(L31:O31) | T31: 15 | U31: =SUM(Q31:T31) | Y31: 20 | Z31: =SUM(V31:Y31) | AD31: =변수!AD37 | AE31: =SUM(AA31:AD31) | AI31: =변수!AI37 | AJ31: =SUM(AF31:AI31) | AN31: =변수!AN37 | AO31: =SUM(AK31:AN31)
A32: PER | B32: 주당 | C32: 배 | D32: PER | F32: =E32 | I32: =IFERROR(변수!I18/(E29+G29+H29+I29),"") | K32: =J32 | O32: =IFERROR(변수!O18/(L29+M29+N29+O29),"") | P32: =O32 | Q32: =IFERROR(변수!Q18/(M29+N29+O29+Q29),"") | R32: =IFERROR(변수!R18/(N29+O29+Q29+R29),"") | S32: =IFERROR(변수!S18/(O29+Q29+R29+S29),"") | U32: =T32 | V32: =IFERROR(변수!V18/(R29+S29+T29+V29),"") | Z32: =Y32 | AE32: =AD32 | AF32: =IFERROR(변수!$D$40/(AB29+AC29+AD29+AF29),"") | AJ32: =AI32 | AO32: =AN32
A33: PBR | B33: 주당 | C33: 배 | D33: PBR | E33: =IFERROR(변수!E18/E30,"") | F33: =E33 | G33: =IFERROR(변수!G18/G30,"") | H33: =IFERROR(변수!H18/H30,"") | I33: =IFERROR(변수!I18/I30,"") | J33: =IFERROR(변수!J18/J30,"") | K33: =J33 | L33: =IFERROR(변수!L18/L30,"") | M33: =IFERROR(변수!M18/M30,"") | N33: =IFERROR(변수!N18/N30,"") | O33: =IFERROR(변수!O18/O30,"") | P33: =O33 | Q33: =IFERROR(변수!Q18/Q30,"") | R33: =IFERROR(변수!R18/R30,"") | S33: =IFERROR(변수!S18/S30,"") | T33: =IFERROR(변수!T18/T30,"") | U33: =T33 | V33: =IFERROR(변수!V18/V30,"") | W33: =IFERROR(변수!W18/W30,"") | X33: =IFERROR(변수!X18/X30,"") | Y33: =IFERROR(변수!Y18/Y30,"") | Z33: =Y33 | AA33: =IFERROR(변수!AA18/AA30,"") | AB33: =IFERROR(변수!AB18/AB30,"") | AC33: =IFERROR(변수!$D$40/AC30,"") | AD33: =IFERROR(변수!$D$40/AD30,"") | AE33: =AD33 | AF33: =IFERROR(변수!$D$40/AF30,"") | AG33: =IFERROR(변수!$D$40/AG30,"") | AH33: =IFERROR(변수!$D$40/AH30,"") | AI33: =IFERROR(변수!$D$40/AI30,"") | AJ33: =AI33 | AK33: =IFERROR(변수!$D$40/AK30,"") | AL33: =IFERROR(변수!$D$40/AL30,"") | AM33: =IFERROR(변수!$D$40/AM30,"") | AN33: =IFERROR(변수!$D$40/AN30,"") | AO33: =AN33
A34: 매출전사 | B34: 사업부 | C34: 억원 | D34: 매출 전사(부문 미분리) | E34: 181.81 | G34: 108.92 | H34: 128.21 | I34: 126.47 | J34: 196.8 | K34: =SUM(G34:J34) | L34: 97.24 | M34: 141.66 | N34: 156.17 | O34: 217.48 | P34: =SUM(L34:O34) | Q34: 93.81 | R34: 112.12 | S34: 154.73 | T34: 270.19 | U34: =SUM(Q34:T34) | V34: 89.82 | W34: 135.26 | X34: 137.05 | Y34: 165.06 | Z34: =SUM(V34:Y34) | AA34: 75.62 | AB34: 143.5 | AC34: =IFERROR(AC5,"") | AD34: =IFERROR(AD5,"") | AE34: =SUM(AA34:AD34) | AF34: =IFERROR(AF5,"") | AG34: =IFERROR(AG5,"") | AH34: =IFERROR(AH5,"") | AI34: =IFERROR(AI5,"") | AJ34: =SUM(AF34:AI34) | AK34: =IFERROR(AK5,"") | AL34: =IFERROR(AL5,"") | AM34: =IFERROR(AM5,"") | AN34: =IFERROR(AN5,"") | AO34: =SUM(AK34:AN34)
A35: OP전사 | B35: 사업부 | C35: 억원 | D35: OP 전사(부문 미분리) | E35: 29.93 | G35: 5.03 | H35: -4.13 | I35: -0.9 | J35: -90.83 | K35: =SUM(G35:J35) | L35: 0.58 | M35: -12.92 | N35: 10.91 | O35: 0.87 | P35: =SUM(L35:O35) | Q35: -27.37 | R35: 20.51 | S35: -13.09 | T35: 14.28 | U35: =SUM(Q35:T35) | V35: -5.3 | W35: -2.38 | X35: 11.6 | Y35: -18.69 | Z35: =SUM(V35:Y35) | AA35: -16.05 | AB35: 11.18 | AC35: =IFERROR(AC9,"") | AD35: =IFERROR(AD9,"") | AE35: =SUM(AA35:AD35) | AF35: =IFERROR(AF9,"") | AG35: =IFERROR(AG9,"") | AH35: =IFERROR(AH9,"") | AI35: =IFERROR(AI9,"") | AJ35: =SUM(AF35:AI35) | AK35: =IFERROR(AK9,"") | AL35: =IFERROR(AL9,"") | AM35: =IFERROR(AM9,"") | AN35: =IFERROR(AN9,"") | AO35: =SUM(AK35:AN35)
B36: 비율(참고)
A37: NPM | C37: % | D37: 지배주주순이익 / 매출액 | E37: =IFERROR(E18/E5,"") | F37: =IFERROR(F18/F5,"") | G37: =IFERROR(G18/G5,"") | H37: =IFERROR(H18/H5,"") | I37: =IFERROR(I18/I5,"") | J37: =IFERROR(J18/J5,"") | K37: =IFERROR(K18/K5,"") | L37: =IFERROR(L18/L5,"") | ... AO37: =IFERROR(AO18/AO5,"")
A38: 매출원가율 | C38: % | D38: 매출원가 / 매출액 | E38: =IFERROR(E6/E5,"") | F38: =IFERROR(F6/F5,"") | G38: =IFERROR(G6/G5,"") | H38: =IFERROR(H6/H5,"") | I38: =IFERROR(I6/I5,"") | J38: =IFERROR(J6/J5,"") | K38: =IFERROR(K6/K5,"") | L38: =IFERROR(L6/L5,"") | ... AO38: =IFERROR(AO6/AO5,"")
A39: 판관비율 | C39: % | D39: 판관비 / 매출액 | E39: =IFERROR(E8/E5,"") | F39: =IFERROR(F8/F5,"") | G39: =IFERROR(G8/G5,"") | H39: =IFERROR(H8/H5,"") | I39: =IFERROR(I8/I5,"") | J39: =IFERROR(J8/J5,"") | K39: =IFERROR(K8/K5,"") | L39: =IFERROR(L8/L5,"") | ... AO39: =IFERROR(AO8/AO5,"")

Sheet 분기
C1: 이름: 분기H — subQ 를 이름으로 VLOOKUP(억원) | E1: 4Q21 | F1: 1Q22 | G1: 2Q22 | H1: 3Q22 | I1: 4Q22 | J1: 1Q23 | K1: 2Q23 | L1: 3Q23 | M1: 4Q23 | N1: 1Q24 | O1: 2Q24 | P1: 3Q24 | Q1: 4Q24 | R1: 1Q25 | S1: 2Q25 | T1: 3Q25 | U1: 4Q25 | V1: 1Q26 | W1: 2Q26 | X1: 3Q26 | Y1: 4Q26 | Z1: 1Q27 | AA1: 2Q27 | AB1: 3Q27 | AC1: 4Q27 | AD1: 1Q28 | AE1: 2Q28 | AF1: 3Q28 | AG1: 4Q28
C2: 종가: | D2: =변수!D40
C3: 기준일: | D3: 20261013 | E3: 1 | F3: 2 | G3: 3 | H3: 4 | I3: 5 | J3: 6 | K3: 7 | L3: 8 | M3: 9 | N3: 10 | O3: 11 | P3: 12 | Q3: 13 | R3: 14 | S3: 15 | T3: 16 | U3: 17 | V3: 18 | W3: 19 | X3: 20 | Y3: 21 | Z3: 22 | AA3: 23 | AB3: 24 | AC3: 25 | AD3: 26 | AE3: 27 | AF3: 28 | AG3: 29
E4: 2021.12 | F4: 2022.03 | G4: 2022.06 | H4: 2022.09 | I4: 2022.12 | J4: 2023.03 | K4: 2023.06 | L4: 2023.09 | M4: 2023.12 | N4: 2024.03 | O4: 2024.06 | P4: 2024.09 | Q4: 2024.12 | R4: 2025.03 | S4: 2025.06 | T4: 2025.09 | U4: 2025.12 | V4: 2026.03 | W4: 2026.06 | X4: 2026.09 | Y4: 2026.12 | Z4: 2027.03 | AA4: 2027.06 | AB4: 2027.09 | AC4: 2027.12 | AD4: 2028.03 | AE4: 2028.06 | AF4: 2028.09 | AG4: 2028.12
A5: 매출액 | D5: 매출액 | E5: =IFERROR(VLOOKUP($A5,subQ,MATCH(E$1,SUBQH,0),0),"") | F5: =IFERROR(VLOOKUP($A5,subQ,MATCH(F$1,SUBQH,0),0),"") | G5: =IFERROR(VLOOKUP($A5,subQ,MATCH(G$1,SUBQH,0),0),"") | H5: =IFERROR(VLOOKUP($A5,subQ,MATCH(H$1,SUBQH,0),0),"") | I5: =IFERROR(VLOOKUP($A5,subQ,MATCH(I$1,SUBQH,0),0),"") | J5: =IFERROR(VLOOKUP($A5,subQ,MATCH(J$1,SUBQH,0),0),"") | K5: =IFERROR(VLOOKUP($A5,subQ,MATCH(K$1,SUBQH,0),0),"") | L5: =IFERROR(VLOOKUP($A5,subQ,MATCH(L$1,SUBQH,0),0),"") | ... AG5: =IFERROR(VLOOKUP($A5,subQ,MATCH(AG$1,SUBQH,0),0),"")
A6: 매출원가 | D6: 매출원가 | E6: =IFERROR(VLOOKUP($A6,subQ,MATCH(E$1,SUBQH,0),0),"") | F6: =IFERROR(VLOOKUP($A6,subQ,MATCH(F$1,SUBQH,0),0),"") | G6: =IFERROR(VLOOKUP($A6,subQ,MATCH(G$1,SUBQH,0),0),"") | H6: =IFERROR(VLOOKUP($A6,subQ,MATCH(H$1,SUBQH,0),0),"") | I6: =IFERROR(VLOOKUP($A6,subQ,MATCH(I$1,SUBQH,0),0),"") | J6: =IFERROR(VLOOKUP($A6,subQ,MATCH(J$1,SUBQH,0),0),"") | K6: =IFERROR(VLOOKUP($A6,subQ,MATCH(K$1,SUBQH,0),0),"") | L6: =IFERROR(VLOOKUP($A6,subQ,MATCH(L$1,SUBQH,0),0),"") | ... AG6: =IFERROR(VLOOKUP($A6,subQ,MATCH(AG$1,SUBQH,0),0),"")
A7: 매출총이익 | D7: 매출총이익 | E7: =IFERROR(VLOOKUP($A7,subQ,MATCH(E$1,SUBQH,0),0),"") | F7: =IFERROR(VLOOKUP($A7,subQ,MATCH(F$1,SUBQH,0),0),"") | G7: =IFERROR(VLOOKUP($A7,subQ,MATCH(G$1,SUBQH,0),0),"") | H7: =IFERROR(VLOOKUP($A7,subQ,MATCH(H$1,SUBQH,0),0),"") | I7: =IFERROR(VLOOKUP($A7,subQ,MATCH(I$1,SUBQH,0),0),"") | J7: =IFERROR(VLOOKUP($A7,subQ,MATCH(J$1,SUBQH,0),0),"") | K7: =IFERROR(VLOOKUP($A7,subQ,MATCH(K$1,SUBQH,0),0),"") | L7: =IFERROR(VLOOKUP($A7,subQ,MATCH(L$1,SUBQH,0),0),"") | ... AG7: =IFERROR(VLOOKUP($A7,subQ,MATCH(AG$1,SUBQH,0),0),"")
A8: 판관비 | D8: 판매비와관리비 | E8: =IFERROR(VLOOKUP($A8,subQ,MATCH(E$1,SUBQH,0),0),"") | F8: =IFERROR(VLOOKUP($A8,subQ,MATCH(F$1,SUBQH,0),0),"") | G8: =IFERROR(VLOOKUP($A8,subQ,MATCH(G$1,SUBQH,0),0),"") | H8: =IFERROR(VLOOKUP($A8,subQ,MATCH(H$1,SUBQH,0),0),"") | I8: =IFERROR(VLOOKUP($A8,subQ,MATCH(I$1,SUBQH,0),0),"") | J8: =IFERROR(VLOOKUP($A8,subQ,MATCH(J$1,SUBQH,0),0),"") | K8: =IFERROR(VLOOKUP($A8,subQ,MATCH(K$1,SUBQH,0),0),"") | L8: =IFERROR(VLOOKUP($A8,subQ,MATCH(L$1,SUBQH,0),0),"") | ... AG8: =IFERROR(VLOOKUP($A8,subQ,MATCH(AG$1,SUBQH,0),0),"")
A9: 영업이익 | D9: 영업이익 | E9: =IFERROR(VLOOKUP($A9,subQ,MATCH(E$1,SUBQH,0),0),"") | F9: =IFERROR(VLOOKUP($A9,subQ,MATCH(F$1,SUBQH,0),0),"") | G9: =IFERROR(VLOOKUP($A9,subQ,MATCH(G$1,SUBQH,0),0),"") | H9: =IFERROR(VLOOKUP($A9,subQ,MATCH(H$1,SUBQH,0),0),"") | I9: =IFERROR(VLOOKUP($A9,subQ,MATCH(I$1,SUBQH,0),0),"") | J9: =IFERROR(VLOOKUP($A9,subQ,MATCH(J$1,SUBQH,0),0),"") | K9: =IFERROR(VLOOKUP($A9,subQ,MATCH(K$1,SUBQH,0),0),"") | L9: =IFERROR(VLOOKUP($A9,subQ,MATCH(L$1,SUBQH,0),0),"") | ... AG9: =IFERROR(VLOOKUP($A9,subQ,MATCH(AG$1,SUBQH,0),0),"")
A10: OPM | D10: 영업이익률 | E10: =IFERROR(VLOOKUP($A10,subQ,MATCH(E$1,SUBQH,0),0),"") | F10: =IFERROR(VLOOKUP($A10,subQ,MATCH(F$1,SUBQH,0),0),"") | G10: =IFERROR(VLOOKUP($A10,subQ,MATCH(G$1,SUBQH,0),0),"") | H10: =IFERROR(VLOOKUP($A10,subQ,MATCH(H$1,SUBQH,0),0),"") | I10: =IFERROR(VLOOKUP($A10,subQ,MATCH(I$1,SUBQH,0),0),"") | J10: =IFERROR(VLOOKUP($A10,subQ,MATCH(J$1,SUBQH,0),0),"") | K10: =IFERROR(VLOOKUP($A10,subQ,MATCH(K$1,SUBQH,0),0),"") | L10: =IFERROR(VLOOKUP($A10,subQ,MATCH(L$1,SUBQH,0),0),"") | ... AG10: =IFERROR(VLOOKUP($A10,subQ,MATCH(AG$1,SUBQH,0),0),"")
A11: 금융손익 | D11: 금융손익(이자·환 포함) | E11: =IFERROR(VLOOKUP($A11,subQ,MATCH(E$1,SUBQH,0),0),"") | F11: =IFERROR(VLOOKUP($A11,subQ,MATCH(F$1,SUBQH,0),0),"") | G11: =IFERROR(VLOOKUP($A11,subQ,MATCH(G$1,SUBQH,0),0),"") | H11: =IFERROR(VLOOKUP($A11,subQ,MATCH(H$1,SUBQH,0),0),"") | I11: =IFERROR(VLOOKUP($A11,subQ,MATCH(I$1,SUBQH,0),0),"") | J11: =IFERROR(VLOOKUP($A11,subQ,MATCH(J$1,SUBQH,0),0),"") | K11: =IFERROR(VLOOKUP($A11,subQ,MATCH(K$1,SUBQH,0),0),"") | L11: =IFERROR(VLOOKUP($A11,subQ,MATCH(L$1,SUBQH,0),0),"") | ... AG11: =IFERROR(VLOOKUP($A11,subQ,MATCH(AG$1,SUBQH,0),0),"")
A12: 이자손익 | D12: 이자손익(이자수익 − 이자비용) | E12: =IFERROR(VLOOKUP($A12,subQ,MATCH(E$1,SUBQH,0),0),"") | F12: =IFERROR(VLOOKUP($A12,subQ,MATCH(F$1,SUBQH,0),0),"") | G12: =IFERROR(VLOOKUP($A12,subQ,MATCH(G$1,SUBQH,0),0),"") | H12: =IFERROR(VLOOKUP($A12,subQ,MATCH(H$1,SUBQH,0),0),"") | I12: =IFERROR(VLOOKUP($A12,subQ,MATCH(I$1,SUBQH,0),0),"") | J12: =IFERROR(VLOOKUP($A12,subQ,MATCH(J$1,SUBQH,0),0),"") | K12: =IFERROR(VLOOKUP($A12,subQ,MATCH(K$1,SUBQH,0),0),"") | L12: =IFERROR(VLOOKUP($A12,subQ,MATCH(L$1,SUBQH,0),0),"") | ... AG12: =IFERROR(VLOOKUP($A12,subQ,MATCH(AG$1,SUBQH,0),0),"")
A13: 외환손익 | D13: 외환손익(실적만; 추정 환효과는 환관련손익) | E13: =IFERROR(VLOOKUP($A13,subQ,MATCH(E$1,SUBQH,0),0),"") | F13: =IFERROR(VLOOKUP($A13,subQ,MATCH(F$1,SUBQH,0),0),"") | G13: =IFERROR(VLOOKUP($A13,subQ,MATCH(G$1,SUBQH,0),0),"") | H13: =IFERROR(VLOOKUP($A13,subQ,MATCH(H$1,SUBQH,0),0),"") | I13: =IFERROR(VLOOKUP($A13,subQ,MATCH(I$1,SUBQH,0),0),"") | J13: =IFERROR(VLOOKUP($A13,subQ,MATCH(J$1,SUBQH,0),0),"") | K13: =IFERROR(VLOOKUP($A13,subQ,MATCH(K$1,SUBQH,0),0),"") | L13: =IFERROR(VLOOKUP($A13,subQ,MATCH(L$1,SUBQH,0),0),"") | ... AG13: =IFERROR(VLOOKUP($A13,subQ,MATCH(AG$1,SUBQH,0),0),"")
A14: 기타영업외손익 | D14: 기타영업외손익 | E14: =IFERROR(VLOOKUP($A14,subQ,MATCH(E$1,SUBQH,0),0),"") | F14: =IFERROR(VLOOKUP($A14,subQ,MATCH(F$1,SUBQH,0),0),"") | G14: =IFERROR(VLOOKUP($A14,subQ,MATCH(G$1,SUBQH,0),0),"") | H14: =IFERROR(VLOOKUP($A14,subQ,MATCH(H$1,SUBQH,0),0),"") | I14: =IFERROR(VLOOKUP($A14,subQ,MATCH(I$1,SUBQH,0),0),"") | J14: =IFERROR(VLOOKUP($A14,subQ,MATCH(J$1,SUBQH,0),0),"") | K14: =IFERROR(VLOOKUP($A14,subQ,MATCH(K$1,SUBQH,0),0),"") | L14: =IFERROR(VLOOKUP($A14,subQ,MATCH(L$1,SUBQH,0),0),"") | ... AG14: =IFERROR(VLOOKUP($A14,subQ,MATCH(AG$1,SUBQH,0),0),"")
A15: 세전이익 | D15: 법인세비용차감전이익 | E15: =IFERROR(VLOOKUP($A15,subQ,MATCH(E$1,SUBQH,0),0),"") | F15: =IFERROR(VLOOKUP($A15,subQ,MATCH(F$1,SUBQH,0),0),"") | G15: =IFERROR(VLOOKUP($A15,subQ,MATCH(G$1,SUBQH,0),0),"") | H15: =IFERROR(VLOOKUP($A15,subQ,MATCH(H$1,SUBQH,0),0),"") | I15: =IFERROR(VLOOKUP($A15,subQ,MATCH(I$1,SUBQH,0),0),"") | J15: =IFERROR(VLOOKUP($A15,subQ,MATCH(J$1,SUBQH,0),0),"") | K15: =IFERROR(VLOOKUP($A15,subQ,MATCH(K$1,SUBQH,0),0),"") | L15: =IFERROR(VLOOKUP($A15,subQ,MATCH(L$1,SUBQH,0),0),"") | ... AG15: =IFERROR(VLOOKUP($A15,subQ,MATCH(AG$1,SUBQH,0),0),"")
A16: 법인세비용 | D16: 법인세비용 | E16: =IFERROR(VLOOKUP($A16,subQ,MATCH(E$1,SUBQH,0),0),"") | F16: =IFERROR(VLOOKUP($A16,subQ,MATCH(F$1,SUBQH,0),0),"") | G16: =IFERROR(VLOOKUP($A16,subQ,MATCH(G$1,SUBQH,0),0),"") | H16: =IFERROR(VLOOKUP($A16,subQ,MATCH(H$1,SUBQH,0),0),"") | I16: =IFERROR(VLOOKUP($A16,subQ,MATCH(I$1,SUBQH,0),0),"") | J16: =IFERROR(VLOOKUP($A16,subQ,MATCH(J$1,SUBQH,0),0),"") | K16: =IFERROR(VLOOKUP($A16,subQ,MATCH(K$1,SUBQH,0),0),"") | L16: =IFERROR(VLOOKUP($A16,subQ,MATCH(L$1,SUBQH,0),0),"") | ... AG16: =IFERROR(VLOOKUP($A16,subQ,MATCH(AG$1,SUBQH,0),0),"")
... A36: NPM | D36: NPM | E36: =IFERROR(VLOOKUP($A36,subQ,MATCH(E$1,SUBQH,0),0),"") | F36: =IFERROR(VLOOKUP($A36,subQ,MATCH(F$1,SUBQH,0),0),"") | G36: =IFERROR(VLOOKUP($A36,subQ,MATCH(G$1,SUBQH,0),0),"") | H36: =IFERROR(VLOOKUP($A36,subQ,MATCH(H$1,SUBQH,0),0),"") | I36: =IFERROR(VLOOKUP($A36,subQ,MATCH(I$1,SUBQH,0),0),"") | J36: =IFERROR(VLOOKUP($A36,subQ,MATCH(J$1,SUBQH,0),0),"") | K36: =IFERROR(VLOOKUP($A36,subQ,MATCH(K$1,SUBQH,0),0),"") | L36: =IFERROR(VLOOKUP($A36,subQ,MATCH(L$1,SUBQH,0),0),"") | ... AG36: =IFERROR(VLOOKUP($A36,subQ,MATCH(AG$1,SUBQH,0),0),"")
A37: 매출액 YoY | D37: 매출액 YoY | I37: =IFERROR(I5/E5-1,"") | J37: =IFERROR(J5/F5-1,"") | K37: =IFERROR(K5/G5-1,"") | L37: =IFERROR(L5/H5-1,"") | M37: =IFERROR(M5/I5-1,"") | N37: =IFERROR(N5/J5-1,"") | O37: =IFERROR(O5/K5-1,"") | P37: =IFERROR(P5/L5-1,"") | ... AG37: =IFERROR(AG5/AC5-1,"")
A38: 영업이익 YoY | D38: 영업이익 YoY | I38: =IFERROR(I9/E9-1,"") | J38: =IFERROR(J9/F9-1,"") | K38: =IFERROR(K9/G9-1,"") | L38: =IFERROR(L9/H9-1,"") | M38: =IFERROR(M9/I9-1,"") | N38: =IFERROR(N9/J9-1,"") | O38: =IFERROR(O9/K9-1,"") | P38: =IFERROR(P9/L9-1,"") | ... AG38: =IFERROR(AG9/AC9-1,"")
A39: 지배주주순이익 YoY | D39: 지배주주순이익 YoY | I39: =IFERROR(I18/E18-1,"") | J39: =IFERROR(J18/F18-1,"") | K39: =IFERROR(K18/G18-1,"") | L39: =IFERROR(L18/H18-1,"") | M39: =IFERROR(M18/I18-1,"") | N39: =IFERROR(N18/J18-1,"") | O39: =IFERROR(O18/K18-1,"") | P39: =IFERROR(P18/L18-1,"") | ... AG39: =IFERROR(AG18/AC18-1,"")

Sheet 연간예상
C1: 이름: 연간예상H — subQ 를 이름으로 VLOOKUP(억원) | E1: 2021 | F1: 2022 | G1: 2023 | H1: 2024 | I1: 2025 | J1: 2026 | K1: 2027 | L1: 2028
C2: 종가: | D2: =변수!D40
C3: 기준일: | D3: 20261013 | E3: 1 | F3: 2 | G3: 3 | H3: 4 | I3: 5 | J3: 6 | K3: 7 | L3: 8
E4: 2021.12A | F4: 2022.12A | G4: 2023.12A | H4: 2024.12A | I4: 2025.12A | J4: 2026.12A | K4: 2027.12A | L4: 2028.12A
A5: 매출액 | D5: 매출액 | E5: =IFERROR(VLOOKUP($A5,subQ,MATCH(E$1,SUBQH,0),0),"") | F5: =IFERROR(VLOOKUP($A5,subQ,MATCH(F$1,SUBQH,0),0),"") | G5: =IFERROR(VLOOKUP($A5,subQ,MATCH(G$1,SUBQH,0),0),"") | H5: =IFERROR(VLOOKUP($A5,subQ,MATCH(H$1,SUBQH,0),0),"") | I5: =IFERROR(VLOOKUP($A5,subQ,MATCH(I$1,SUBQH,0),0),"") | J5: =IFERROR(VLOOKUP($A5,subQ,MATCH(J$1,SUBQH,0),0),"") | K5: =IFERROR(VLOOKUP($A5,subQ,MATCH(K$1,SUBQH,0),0),"") | L5: =IFERROR(VLOOKUP($A5,subQ,MATCH(L$1,SUBQH,0),0),"")
A6: 매출원가 | D6: 매출원가 | E6: =IFERROR(VLOOKUP($A6,subQ,MATCH(E$1,SUBQH,0),0),"") | F6: =IFERROR(VLOOKUP($A6,subQ,MATCH(F$1,SUBQH,0),0),"") | G6: =IFERROR(VLOOKUP($A6,subQ,MATCH(G$1,SUBQH,0),0),"") | H6: =IFERROR(VLOOKUP($A6,subQ,MATCH(H$1,SUBQH,0),0),"") | I6: =IFERROR(VLOOKUP($A6,subQ,MATCH(I$1,SUBQH,0),0),"") | J6: =IFERROR(VLOOKUP($A6,subQ,MATCH(J$1,SUBQH,0),0),"") | K6: =IFERROR(VLOOKUP($A6,subQ,MATCH(K$1,SUBQH,0),0),"") | L6: =IFERROR(VLOOKUP($A6,subQ,MATCH(L$1,SUBQH,0),0),"")
A7: 매출총이익 | D7: 매출총이익 | E7: =IFERROR(VLOOKUP($A7,subQ,MATCH(E$1,SUBQH,0),0),"") | F7: =IFERROR(VLOOKUP($A7,subQ,MATCH(F$1,SUBQH,0),0),"") | G7: =IFERROR(VLOOKUP($A7,subQ,MATCH(G$1,SUBQH,0),0),"") | H7: =IFERROR(VLOOKUP($A7,subQ,MATCH(H$1,SUBQH,0),0),"") | I7: =IFERROR(VLOOKUP($A7,subQ,MATCH(I$1,SUBQH,0),0),"") | J7: =IFERROR(VLOOKUP($A7,subQ,MATCH(J$1,SUBQH,0),0),"") | K7: =IFERROR(VLOOKUP($A7,subQ,MATCH(K$1,SUBQH,0),0),"") | L7: =IFERROR(VLOOKUP($A7,subQ,MATCH(L$1,SUBQH,0),0),"")
A8: 판관비 | D8: 판매비와관리비 | E8: =IFERROR(VLOOKUP($A8,subQ,MATCH(E$1,SUBQH,0),0),"") | F8: =IFERROR(VLOOKUP($A8,subQ,MATCH(F$1,SUBQH,0),0),"") | G8: =IFERROR(VLOOKUP($A8,subQ,MATCH(G$1,SUBQH,0),0),"") | H8: =IFERROR(VLOOKUP($A8,subQ,MATCH(H$1,SUBQH,0),0),"") | I8: =IFERROR(VLOOKUP($A8,subQ,MATCH(I$1,SUBQH,0),0),"") | J8: =IFERROR(VLOOKUP($A8,subQ,MATCH(J$1,SUBQH,0),0),"") | K8: =IFERROR(VLOOKUP($A8,subQ,MATCH(K$1,SUBQH,0),0),"") | L8: =IFERROR(VLOOKUP($A8,subQ,MATCH(L$1,SUBQH,0),0),"")
A9: 영업이익 | D9: 영업이익 | E9: =IFERROR(VLOOKUP($A9,subQ,MATCH(E$1,SUBQH,0),0),"") | F9: =IFERROR(VLOOKUP($A9,subQ,MATCH(F$1,SUBQH,0),0),"") | G9: =IFERROR(VLOOKUP($A9,subQ,MATCH(G$1,SUBQH,0),0),"") | H9: =IFERROR(VLOOKUP($A9,subQ,MATCH(H$1,SUBQH,0),0),"") | I9: =IFERROR(VLOOKUP($A9,subQ,MATCH(I$1,SUBQH,0),0),"") | J9: =IFERROR(VLOOKUP($A9,subQ,MATCH(J$1,SUBQH,0),0),"") | K9: =IFERROR(VLOOKUP($A9,subQ,MATCH(K$1,SUBQH,0),0),"") | L9: =IFERROR(VLOOKUP($A9,subQ,MATCH(L$1,SUBQH,0),0),"")
A10: OPM | D10: 영업이익률 | E10: =IFERROR(VLOOKUP($A10,subQ,MATCH(E$1,SUBQH,0),0),"") | F10: =IFERROR(VLOOKUP($A10,subQ,MATCH(F$1,SUBQH,0),0),"") | G10: =IFERROR(VLOOKUP($A10,subQ,MATCH(G$1,SUBQH,0),0),"") | H10: =IFERROR(VLOOKUP($A10,subQ,MATCH(H$1,SUBQH,0),0),"") | I10: =IFERROR(VLOOKUP($A10,subQ,MATCH(I$1,SUBQH,0),0),"") | J10: =IFERROR(VLOOKUP($A10,subQ,MATCH(J$1,SUBQH,0),0),"") | K10: =IFERROR(VLOOKUP($A10,subQ,MATCH(K$1,SUBQH,0),0),"") | L10: =IFERROR(VLOOKUP($A10,subQ,MATCH(L$1,SUBQH,0),0),"")
A11: 금융손익 | D11: 금융손익(이자·환 포함) | E11: =IFERROR(VLOOKUP($A11,subQ,MATCH(E$1,SUBQH,0),0),"") | F11: =IFERROR(VLOOKUP($A11,subQ,MATCH(F$1,SUBQH,0),0),"") | G11: =IFERROR(VLOOKUP($A11,subQ,MATCH(G$1,SUBQH,0),0),"") | H11: =IFERROR(VLOOKUP($A11,subQ,MATCH(H$1,SUBQH,0),0),"") | I11: =IFERROR(VLOOKUP($A11,subQ,MATCH(I$1,SUBQH,0),0),"") | J11: =IFERROR(VLOOKUP($A11,subQ,MATCH(J$1,SUBQH,0),0),"") | K11: =IFERROR(VLOOKUP($A11,subQ,MATCH(K$1,SUBQH,0),0),"") | L11: =IFERROR(VLOOKUP($A11,subQ,MATCH(L$1,SUBQH,0),0),"")
A12: 이자손익 | D12: 이자손익(이자수익 − 이자비용) | E12: =IFERROR(VLOOKUP($A12,subQ,MATCH(E$1,SUBQH,0),0),"") | F12: =IFERROR(VLOOKUP($A12,subQ,MATCH(F$1,SUBQH,0),0),"") | G12: =IFERROR(VLOOKUP($A12,subQ,MATCH(G$1,SUBQH,0),0),"") | H12: =IFERROR(VLOOKUP($A12,subQ,MATCH(H$1,SUBQH,0),0),"") | I12: =IFERROR(VLOOKUP($A12,subQ,MATCH(I$1,SUBQH,0),0),"") | J12: =IFERROR(VLOOKUP($A12,subQ,MATCH(J$1,SUBQH,0),0),"") | K12: =IFERROR(VLOOKUP($A12,subQ,MATCH(K$1,SUBQH,0),0),"") | L12: =IFERROR(VLOOKUP($A12,subQ,MATCH(L$1,SUBQH,0),0),"")
A13: 외환손익 | D13: 외환손익(실적만; 추정 환효과는 환관련손익) | E13: =IFERROR(VLOOKUP($A13,subQ,MATCH(E$1,SUBQH,0),0),"") | F13: =IFERROR(VLOOKUP($A13,subQ,MATCH(F$1,SUBQH,0),0),"") | G13: =IFERROR(VLOOKUP($A13,subQ,MATCH(G$1,SUBQH,0),0),"") | H13: =IFERROR(VLOOKUP($A13,subQ,MATCH(H$1,SUBQH,0),0),"") | I13: =IFERROR(VLOOKUP($A13,subQ,MATCH(I$1,SUBQH,0),0),"") | J13: =IFERROR(VLOOKUP($A13,subQ,MATCH(J$1,SUBQH,0),0),"") | K13: =IFERROR(VLOOKUP($A13,subQ,MATCH(K$1,SUBQH,0),0),"") | L13: =IFERROR(VLOOKUP($A13,subQ,MATCH(L$1,SUBQH,0),0),"")
A14: 기타영업외손익 | D14: 기타영업외손익 | E14: =IFERROR(VLOOKUP($A14,subQ,MATCH(E$1,SUBQH,0),0),"") | F14: =IFERROR(VLOOKUP($A14,subQ,MATCH(F$1,SUBQH,0),0),"") | G14: =IFERROR(VLOOKUP($A14,subQ,MATCH(G$1,SUBQH,0),0),"") | H14: =IFERROR(VLOOKUP($A14,subQ,MATCH(H$1,SUBQH,0),0),"") | I14: =IFERROR(VLOOKUP($A14,subQ,MATCH(I$1,SUBQH,0),0),"") | J14: =IFERROR(VLOOKUP($A14,subQ,MATCH(J$1,SUBQH,0),0),"") | K14: =IFERROR(VLOOKUP($A14,subQ,MATCH(K$1,SUBQH,0),0),"") | L14: =IFERROR(VLOOKUP($A14,subQ,MATCH(L$1,SUBQH,0),0),"")
A15: 세전이익 | D15: 법인세비용차감전이익 | E15: =IFERROR(VLOOKUP($A15,subQ,MATCH(E$1,SUBQH,0),0),"") | F15: =IFERROR(VLOOKUP($A15,subQ,MATCH(F$1,SUBQH,0),0),"") | G15: =IFERROR(VLOOKUP($A15,subQ,MATCH(G$1,SUBQH,0),0),"") | H15: =IFERROR(VLOOKUP($A15,subQ,MATCH(H$1,SUBQH,0),0),"") | I15: =IFERROR(VLOOKUP($A15,subQ,MATCH(I$1,SUBQH,0),0),"") | J15: =IFERROR(VLOOKUP($A15,subQ,MATCH(J$1,SUBQH,0),0),"") | K15: =IFERROR(VLOOKUP($A15,subQ,MATCH(K$1,SUBQH,0),0),"") | L15: =IFERROR(VLOOKUP($A15,subQ,MATCH(L$1,SUBQH,0),0),"")
A16: 법인세비용 | D16: 법인세비용 | E16: =IFERROR(VLOOKUP($A16,subQ,MATCH(E$1,SUBQH,0),0),"") | F16: =IFERROR(VLOOKUP($A16,subQ,MATCH(F$1,SUBQH,0),0),"") | G16: =IFERROR(VLOOKUP($A16,subQ,MATCH(G$1,SUBQH,0),0),"") | H16: =IFERROR(VLOOKUP($A16,subQ,MATCH(H$1,SUBQH,0),0),"") | I16: =IFERROR(VLOOKUP($A16,subQ,MATCH(I$1,SUBQH,0),0),"") | J16: =IFERROR(VLOOKUP($A16,subQ,MATCH(J$1,SUBQH,0),0),"") | K16: =IFERROR(VLOOKUP($A16,subQ,MATCH(K$1,SUBQH,0),0),"") | L16: =IFERROR(VLOOKUP($A16,subQ,MATCH(L$1,SUBQH,0),0),"")
... A36: NPM | D36: NPM | E36: =IFERROR(VLOOKUP($A36,subQ,MATCH(E$1,SUBQH,0),0),"") | F36: =IFERROR(VLOOKUP($A36,subQ,MATCH(F$1,SUBQH,0),0),"") | G36: =IFERROR(VLOOKUP($A36,subQ,MATCH(G$1,SUBQH,0),0),"") | H36: =IFERROR(VLOOKUP($A36,subQ,MATCH(H$1,SUBQH,0),0),"") | I36: =IFERROR(VLOOKUP($A36,subQ,MATCH(I$1,SUBQH,0),0),"") | J36: =IFERROR(VLOOKUP($A36,subQ,MATCH(J$1,SUBQH,0),0),"") | K36: =IFERROR(VLOOKUP($A36,subQ,MATCH(K$1,SUBQH,0),0),"") | L36: =IFERROR(VLOOKUP($A36,subQ,MATCH(L$1,SUBQH,0),0),"")
A37: 매출액 YoY | D37: 매출액 YoY | F37: =IFERROR(F5/E5-1,"") | G37: =IFERROR(G5/F5-1,"") | H37: =IFERROR(H5/G5-1,"") | I37: =IFERROR(I5/H5-1,"") | J37: =IFERROR(J5/I5-1,"") | K37: =IFERROR(K5/J5-1,"") | L37: =IFERROR(L5/K5-1,"")
A38: 영업이익 YoY | D38: 영업이익 YoY | F38: =IFERROR(F9/E9-1,"") | G38: =IFERROR(G9/F9-1,"") | H38: =IFERROR(H9/G9-1,"") | I38: =IFERROR(I9/H9-1,"") | J38: =IFERROR(J9/I9-1,"") | K38: =IFERROR(K9/J9-1,"") | L38: =IFERROR(L9/K9-1,"")
A39: 지배주주순이익 YoY | D39: 지배주주순이익 YoY | F39: =IFERROR(F18/E18-1,"") | G39: =IFERROR(G18/F18-1,"") | H39: =IFERROR(H18/G18-1,"") | I39: =IFERROR(I18/H18-1,"") | J39: =IFERROR(J18/I18-1,"") | K39: =IFERROR(K18/J18-1,"") | L39: =IFERROR(L18/K18-1,"")

Sheet TP
B1: 종가 | C1: =변수!D40
B2: 기준일 | C2: =변수!D41
B3: 모델 산출값 — 목표주가·추천 아님. 밴드·COE 는 변수 시트 3절의 가정
C5: FY | D5: 2025 | E5: 2026 | F5: 2027 | G5: 2028
D6: A | E6: E | F6: E | G6: E
C7: EPS(원) | D7: =IFERROR(VLOOKUP("EPS",subQ,MATCH(D$5,SUBQH,0),0),"") | E7: =IFERROR(VLOOKUP("EPS",subQ,MATCH(E$5,SUBQH,0),0),"") | F7: =IFERROR(VLOOKUP("EPS",subQ,MATCH(F$5,SUBQH,0),0),"") | G7: =IFERROR(VLOOKUP("EPS",subQ,MATCH(G$5,SUBQH,0),0),"")
C8: BPS(원) | D8: =IFERROR(VLOOKUP("BPS",subQ,MATCH(D$5,SUBQH,0),0),"") | E8: =IFERROR(VLOOKUP("BPS",subQ,MATCH(E$5,SUBQH,0),0),"") | F8: =IFERROR(VLOOKUP("BPS",subQ,MATCH(F$5,SUBQH,0),0),"") | G8: =IFERROR(VLOOKUP("BPS",subQ,MATCH(G$5,SUBQH,0),0),"")
C9: 지배주주순이익(억원) | D9: =IFERROR(VLOOKUP("지배주주순이익",subQ,MATCH(D$5,SUBQH,0),0),"") | E9: =IFERROR(VLOOKUP("지배주주순이익",subQ,MATCH(E$5,SUBQH,0),0),"") | F9: =IFERROR(VLOOKUP("지배주주순이익",subQ,MATCH(F$5,SUBQH,0),0),"") | G9: =IFERROR(VLOOKUP("지배주주순이익",subQ,MATCH(G$5,SUBQH,0),0),"")
C10: 영업이익(억원) | D10: =IFERROR(VLOOKUP("영업이익",subQ,MATCH(D$5,SUBQH,0),0),"") | E10: =IFERROR(VLOOKUP("영업이익",subQ,MATCH(E$5,SUBQH,0),0),"") | F10: =IFERROR(VLOOKUP("영업이익",subQ,MATCH(F$5,SUBQH,0),0),"") | G10: =IFERROR(VLOOKUP("영업이익",subQ,MATCH(G$5,SUBQH,0),0),"")
C11: ROE(EPS/기초BPS) | E11: =IFERROR(E7/D8,"") | F11: =IFERROR(F7/E8,"") | G11: =IFERROR(G7/F8,"")
B13: PER
C14: 12M fwd EPS | D14: =IFERROR(E7*변수!D46+F7*(1-변수!D46),"")
C15: 적정가치 @PER_lo | D15: =변수!D43 | E15: =IFERROR(ROUND($D$14*D15,-2),"") | F15: =IFERROR(E15/$C$1-1,"") | G15: 배 · 원 · 종가 대비
C16: 적정가치 @PER_mid | D16: =변수!D44 | E16: =IFERROR(ROUND($D$14*D16,-2),"") | F16: =IFERROR(E16/$C$1-1,"") | G16: 배 · 원 · 종가 대비
C17: 적정가치 @PER_hi | D17: =변수!D45 | E17: =IFERROR(ROUND($D$14*D17,-2),"") | F17: =IFERROR(E17/$C$1-1,"") | G17: 배 · 원 · 종가 대비
C18: 현재 PER(종가/12M fwd EPS) | D18: =IFERROR($C$1/$D$14,"")
B20: PBR
C21: 최근 BPS(마지막 실적 분기) | D21: =IFERROR(VLOOKUP("BPS",subQ,MATCH("2Q26",SUBQH,0),0),"")
C22: ROE fwd(12M fwd EPS / BPS) | D22: =IFERROR($D$14/$D$21,"")
C23: COE | D23: =변수!D42
C24: 적정 PBR = ROE/COE | D24: =IFERROR(D22/D23,"")
C25: 적정가치(PBR) = BPS × 적정PBR | D25: =IFERROR(ROUND(D21*D24,-2),"") | E25: =IFERROR(D25/$C$1-1,"")
C26: 현재 PBR(종가/BPS) | D26: =IFERROR($C$1/D21,"")
B28: 모델 json valuation(참고)
C29: eps_fwd12m | D29: -52.1
C30: bps_latest | D30: 2700
C31: per_now
C32: pbr_now | D32: 0.85
C33: roe_fwd | D33: -0.0193
C34: fair_pbr
C35: fair_value_pbr
C36: ev_ebitda
C37: note | D37: 모델 산출값 — 목표주가·추천 아님

Sheet 외화
C1: 이름: 외화QH — 환율 QoQ · 외화 순노출 × Δ기말환율 | E1: 4Q21 | F1: 1Q22 | G1: 2Q22 | H1: 3Q22 | I1: 4Q22 | J1: 1Q23 | K1: 2Q23 | L1: 3Q23 | M1: 4Q23 | N1: 1Q24 | O1: 2Q24 | P1: 3Q24 | Q1: 4Q24 | R1: 1Q25 | S1: 2Q25 | T1: 3Q25 | U1: 4Q25 | V1: 1Q26 | W1: 2Q26 | X1: 3Q26 | Y1: 4Q26 | Z1: 1Q27 | AA1: 2Q27 | AB1: 3Q27 | AC1: 4Q27 | AD1: 1Q28 | AE1: 2Q28 | AF1: 3Q28 | AG1: 4Q28
E3: 1 | F3: 2 | G3: 3 | H3: 4 | I3: 5 | J3: 6 | K3: 7 | L3: 8 | M3: 9 | N3: 10 | O3: 11 | P3: 12 | Q3: 13 | R3: 14 | S3: 15 | T3: 16 | U3: 17 | V3: 18 | W3: 19 | X3: 20 | Y3: 21 | Z3: 22 | AA3: 23 | AB3: 24 | AC3: 25 | AD3: 26 | AE3: 27 | AF3: 28 | AG3: 29
E4: 2021.12 | F4: 2022.03 | G4: 2022.06 | H4: 2022.09 | I4: 2022.12 | J4: 2023.03 | K4: 2023.06 | L4: 2023.09 | M4: 2023.12 | N4: 2024.03 | O4: 2024.06 | P4: 2024.09 | Q4: 2024.12 | R4: 2025.03 | S4: 2025.06 | T4: 2025.09 | U4: 2025.12 | V4: 2026.03 | W4: 2026.06 | X4: 2026.09 | Y4: 2026.12 | Z4: 2027.03 | AA4: 2027.06 | AB4: 2027.09 | AC4: 2027.12 | AD4: 2028.03 | AE4: 2028.06 | AF4: 2028.09 | AG4: 2028.12
D5: 원/달러(평균) | E5: =IFERROR(VLOOKUP($D5,환율,MATCH(E$1,변수H,0),0),"") | F5: =IFERROR(VLOOKUP($D5,환율,MATCH(F$1,변수H,0),0),"") | G5: =IFERROR(VLOOKUP($D5,환율,MATCH(G$1,변수H,0),0),"") | H5: =IFERROR(VLOOKUP($D5,환율,MATCH(H$1,변수H,0),0),"") | I5: =IFERROR(VLOOKUP($D5,환율,MATCH(I$1,변수H,0),0),"") | J5: =IFERROR(VLOOKUP($D5,환율,MATCH(J$1,변수H,0),0),"") | K5: =IFERROR(VLOOKUP($D5,환율,MATCH(K$1,변수H,0),0),"") | L5: =IFERROR(VLOOKUP($D5,환율,MATCH(L$1,변수H,0),0),"") | ... AG5: =IFERROR(VLOOKUP($D5,환율,MATCH(AG$1,변수H,0),0),"")
A6: 원/달러(평균) QoQ | F6: =IFERROR(F5/E5-1,"") | G6: =IFERROR(G5/F5-1,"") | H6: =IFERROR(H5/G5-1,"") | I6: =IFERROR(I5/H5-1,"") | J6: =IFERROR(J5/I5-1,"") | K6: =IFERROR(K5/J5-1,"") | L6: =IFERROR(L5/K5-1,"") | M6: =IFERROR(M5/L5-1,"") | ... AG6: =IFERROR(AG5/AF5-1,"")
D7: 원/달러(기말) | E7: =IFERROR(VLOOKUP($D7,환율,MATCH(E$1,변수H,0),0),"") | F7: =IFERROR(VLOOKUP($D7,환율,MATCH(F$1,변수H,0),0),"") | G7: =IFERROR(VLOOKUP($D7,환율,MATCH(G$1,변수H,0),0),"") | H7: =IFERROR(VLOOKUP($D7,환율,MATCH(H$1,변수H,0),0),"") | I7: =IFERROR(VLOOKUP($D7,환율,MATCH(I$1,변수H,0),0),"") | J7: =IFERROR(VLOOKUP($D7,환율,MATCH(J$1,변수H,0),0),"") | K7: =IFERROR(VLOOKUP($D7,환율,MATCH(K$1,변수H,0),0),"") | L7: =IFERROR(VLOOKUP($D7,환율,MATCH(L$1,변수H,0),0),"") | ... AG7: =IFERROR(VLOOKUP($D7,환율,MATCH(AG$1,변수H,0),0),"")
A8: 원/달러(기말) QoQ | F8: =IFERROR(F7/E7-1,"") | G8: =IFERROR(G7/F7-1,"") | H8: =IFERROR(H7/G7-1,"") | I8: =IFERROR(I7/H7-1,"") | J8: =IFERROR(J7/I7-1,"") | K8: =IFERROR(K7/J7-1,"") | L8: =IFERROR(L7/K7-1,"") | M8: =IFERROR(M7/L7-1,"") | ... AG8: =IFERROR(AG7/AF7-1,"")
D9: W/Euro(평균) | E9: =IFERROR(VLOOKUP($D9,환율,MATCH(E$1,변수H,0),0),"") | F9: =IFERROR(VLOOKUP($D9,환율,MATCH(F$1,변수H,0),0),"") | G9: =IFERROR(VLOOKUP($D9,환율,MATCH(G$1,변수H,0),0),"") | H9: =IFERROR(VLOOKUP($D9,환율,MATCH(H$1,변수H,0),0),"") | I9: =IFERROR(VLOOKUP($D9,환율,MATCH(I$1,변수H,0),0),"") | J9: =IFERROR(VLOOKUP($D9,환율,MATCH(J$1,변수H,0),0),"") | K9: =IFERROR(VLOOKUP($D9,환율,MATCH(K$1,변수H,0),0),"") | L9: =IFERROR(VLOOKUP($D9,환율,MATCH(L$1,변수H,0),0),"") | ... AG9: =IFERROR(VLOOKUP($D9,환율,MATCH(AG$1,변수H,0),0),"")
A10: W/Euro(평균) QoQ | F10: =IFERROR(F9/E9-1,"") | G10: =IFERROR(G9/F9-1,"") | H10: =IFERROR(H9/G9-1,"") | I10: =IFERROR(I9/H9-1,"") | J10: =IFERROR(J9/I9-1,"") | K10: =IFERROR(K9/J9-1,"") | L10: =IFERROR(L9/K9-1,"") | M10: =IFERROR(M9/L9-1,"") | ... AG10: =IFERROR(AG9/AF9-1,"")
D11: W/Euro(기말) | E11: =IFERROR(VLOOKUP($D11,환율,MATCH(E$1,변수H,0),0),"") | F11: =IFERROR(VLOOKUP($D11,환율,MATCH(F$1,변수H,0),0),"") | G11: =IFERROR(VLOOKUP($D11,환율,MATCH(G$1,변수H,0),0),"") | H11: =IFERROR(VLOOKUP($D11,환율,MATCH(H$1,변수H,0),0),"") | I11: =IFERROR(VLOOKUP($D11,환율,MATCH(I$1,변수H,0),0),"") | J11: =IFERROR(VLOOKUP($D11,환율,MATCH(J$1,변수H,0),0),"") | K11: =IFERROR(VLOOKUP($D11,환율,MATCH(K$1,변수H,0),0),"") | L11: =IFERROR(VLOOKUP($D11,환율,MATCH(L$1,변수H,0),0),"") | ... AG11: =IFERROR(VLOOKUP($D11,환율,MATCH(AG$1,변수H,0),0),"")
A12: W/Euro(기말) QoQ | F12: =IFERROR(F11/E11-1,"") | G12: =IFERROR(G11/F11-1,"") | H12: =IFERROR(H11/G11-1,"") | I12: =IFERROR(I11/H11-1,"") | J12: =IFERROR(J11/I11-1,"") | K12: =IFERROR(K11/J11-1,"") | L12: =IFERROR(L11/K11-1,"") | M12: =IFERROR(M11/L11-1,"") | ... AG12: =IFERROR(AG11/AF11-1,"")
D13: 원/100Y(기말) | E13: =IFERROR(VLOOKUP($D13,환율,MATCH(E$1,변수H,0),0),"") | F13: =IFERROR(VLOOKUP($D13,환율,MATCH(F$1,변수H,0),0),"") | G13: =IFERROR(VLOOKUP($D13,환율,MATCH(G$1,변수H,0),0),"") | H13: =IFERROR(VLOOKUP($D13,환율,MATCH(H$1,변수H,0),0),"") | I13: =IFERROR(VLOOKUP($D13,환율,MATCH(I$1,변수H,0),0),"") | J13: =IFERROR(VLOOKUP($D13,환율,MATCH(J$1,변수H,0),0),"") | K13: =IFERROR(VLOOKUP($D13,환율,MATCH(K$1,변수H,0),0),"") | L13: =IFERROR(VLOOKUP($D13,환율,MATCH(L$1,변수H,0),0),"") | ... AG13: =IFERROR(VLOOKUP($D13,환율,MATCH(AG$1,변수H,0),0),"")
A14: 원/100Y(기말) QoQ | F14: =IFERROR(F13/E13-1,"") | G14: =IFERROR(G13/F13-1,"") | H14: =IFERROR(H13/G13-1,"") | I14: =IFERROR(I13/H13-1,"") | J14: =IFERROR(J13/I13-1,"") | K14: =IFERROR(K13/J13-1,"") | L14: =IFERROR(L13/K13-1,"") | M14: =IFERROR(M13/L13-1,"") | ... AG14: =IFERROR(AG13/AF13-1,"")
A16: 외화순노출 | C16: 외화 순노출(백만$) | D16: =변수!D53 | E16: 외화 순노출 × Δ기말환율 (외화 시트 방식)
A17: 환관련손익추정 | C17: 환관련손익 추정(억원) = 순노출 × Δ원/달러(기말) / 100 | F17: =IFERROR($D$16*(F7-E7)/100,"") | G17: =IFERROR($D$16*(G7-F7)/100,"") | H17: =IFERROR($D$16*(H7-G7)/100,"") | I17: =IFERROR($D$16*(I7-H7)/100,"") | J17: =IFERROR($D$16*(J7-I7)/100,"") | K17: =IFERROR($D$16*(K7-J7)/100,"") | L17: =IFERROR($D$16*(L7-K7)/100,"") | M17: =IFERROR($D$16*(M7-L7)/100,"") | ... AG17: =IFERROR($D$16*(AG7-AF7)/100,"")
A18: fx_pnl.by_q | C18: 모델 fx_pnl.by_q(억원, 참고)
C19: 외화 순노출 미공시(face) → 0 + 표기
