Workbook
Name 변수H: 변수!$C$1:$AO$1
Name 환율: 변수!$C$6:$AO$13
Name BS연결H: BS연결!$C$1:$AO$1
Name BS연결: BS연결!$C$5:$AO$118
Name BS별도H: BS별도!$C$1:$AO$1
Name BS별도: BS별도!$C$5:$AO$95
Name SUBQH: subQ!$A$1:$AO$1
Name subQ: subQ!$A$5:$AO$45

Sheet README
A1: 영흥(012160) 실적 모델 — ARGUS 한국조선
A2: 기준 분기 2026Q2 · 마지막 실적 2026Q2 · 생성 2026-10-19
A3: 모든 수치는 모델 산출값(DART 공개 재무제표 + 우리 추정)이다 — 목표주가·투자 추천 아님. 참고용 · 투자조언 아님.
A5: 시트
A6: 변수 가정 시계열. 환율 8행(ECB via frankfurter — L2 fx.json; 추정 분기 = 노란 가정), 추정 드라이버(노란 셀 = 모델값에서 역산한 가정, 바꾸면 재계산; 연녹 셀 = 3절 스칼라 참조 수식), 3절 스칼라 가정(세율·판관비율·지배주주비중·이자율·종가·PER 밴드·COE·외화 순노출·헤지비율)
A7: BS연결/BS별도 FnGuide 계정명 × 기간 값 덤프(백만원). 행1 분기라벨, 행4 YYYY.MM / YYYY.12A. 이름정의 BS연결H·BS연결(계정명 C열부터)
A8: subQ 분기 서브모델(억원 = 백만원/100). 확정 행: =IFERROR(VLOOKUP($D행,BS연결,MATCH(E$1,BS연결H,0),0)/100,"") 추정 행: 변수 시트 가정 셀 참조 수식. 외환손익·파생상품손익은 BS 계정 합·차, 기타금융손익은 잔차, OPM·EPS·BPS·PER·PBR 은 파생 수식, 조정EPS 는 EPS 참조(일회성 의심 분기만 산식 셀)
A9: SLS 선표(조선사만, sls json 있을 때): 요약 행(sls 저장값) + 계약별 스케줄(백만$) × (헤지비율 × 헤지환율 + (1−헤지비율) × 건조시점 환율[변수 원/달러(평균)]) → 원화 수식 블록 → 합계 행이 subQ 매출조선에 연결
A10: 시나리오 신규수주 보수/기준/낙관(forecast_panel 패널, 모델에 scenarios 가 있을 때만): 매출액·영업이익 = subQ 기준값 ± (시나리오 신규 − base 신규) × OPM. base 만 subQ 행에 포함, 나머지는 합산 안 함
A11: 분기/연간예상 subQ 를 이름(A열 key)으로 VLOOKUP 한 보고서 표(억원)
A12: TP PER 밴드 × 12M fwd EPS, PBR = ROE/COE × BPS — 모델 산출값 구간, 목표주가·추천 아님
A13: 외화 환율 QoQ, 외화 순노출 × Δ기말환율 → 환관련손익 추정
... A35: 백테스트: {"freeze": "2025Q2", "horizon": 4, "revenue_wape_pct": 2.5, "op_wape_pct": 86.5, "n": 4, "note": "단일 회사 4분기 — 통계 아님", "driver_at_freeze": "trend_seasonal", "selection_oos_at_freeze": null, "frozen_inputs": "fin(연결/별도)·고객 조선사 모델·지주 자회사 모델은 2025Q2 까지의 분기만; 선표는 체결일 ≤ 2025Q2 말일 계약(원장 최신 금액·코호트 등급, 환산 없음); 잔고는 yards_cache 2025Q2; 시세·환율 forward·prices·forecast_panel 신규수주 미사용. 고객 가중치(suppliers.json 언급 비중)와 합병 체인링크는 현재 지식; 고객 연동 채택은 동결 모델 안에서도 자기 la−4분기 OOS 규칙(selection_oos_at_freeze)", "detail": [{"q": "2025Q3", "rev_pred": 1092.86, "rev_act": 1098.95, "op_pred": -9.26, "op_act": -69.66}, {"q": "2025Q4", "rev_pred": 1004.22, "rev_act": 963.22, "op_pred": -8.51, "op_act": -22.38}, {"q": "2026Q1", "rev_pred": 1019.23, "rev_act": 964.25, "op_pred": -8.63, "op_act": -14.39}, {"q": "2026Q2", "rev_pred": 1067.88, "rev_act": 1067.67, "op_pred": -9.05, "op_act": 21.74}]}

Sheet 변수
C1: 이름: 변수H | E1: 4Q21 | F1: 2021 | G1: 1Q22 | H1: 2Q22 | I1: 3Q22 | J1: 4Q22 | K1: 2022 | L1: 1Q23 | M1: 2Q23 | N1: 3Q23 | O1: 4Q23 | P1: 2023 | Q1: 1Q24 | R1: 2Q24 | S1: 3Q24 | T1: 4Q24 | U1: 2024 | V1: 1Q25 | W1: 2Q25 | X1: 3Q25 | Y1: 4Q25 | Z1: 2025 | AA1: 1Q26 | AB1: 2Q26 | AC1: 3Q26 | AD1: 4Q26 | AE1: 2026 | AF1: 1Q27 | AG1: 2Q27 | AH1: 3Q27 | AI1: 4Q27 | AJ1: 2027 | AK1: 1Q28 | AL1: 2Q28 | AM1: 3Q28 | AN1: 4Q28 | AO1: 2028
A2: 가정 시계열 — 노란 셀은 추정 가정(모델값에서 역산), 연녹 셀은 3절 스칼라 참조 수식. 바꾸면 subQ·분기·연간예상·TP·시나리오가 재계산됩니다.
E3: 1 | F3: 2 | G3: 3 | H3: 4 | I3: 5 | J3: 6 | K3: 7 | L3: 8 | M3: 9 | N3: 10 | O3: 11 | P3: 12 | Q3: 13 | R3: 14 | S3: 15 | T3: 16 | U3: 17 | V3: 18 | W3: 19 | X3: 20 | Y3: 21 | Z3: 22 | AA3: 23 | AB3: 24 | AC3: 25 | AD3: 26 | AE3: 27 | AF3: 28 | AG3: 29 | AH3: 30 | AI3: 31 | AJ3: 32 | AK3: 33 | AL3: 34 | AM3: 35 | AN3: 36 | AO3: 37
E4: 2021.12 | F4: 2021.12A | G4: 2022.03 | H4: 2022.06 | I4: 2022.09 | J4: 2022.12 | K4: 2022.12A | L4: 2023.03 | M4: 2023.06 | N4: 2023.09 | O4: 2023.12 | P4: 2023.12A | Q4: 2024.03 | R4: 2024.06 | S4: 2024.09 | T4: 2024.12 | U4: 2024.12A | V4: 2025.03 | W4: 2025.06 | X4: 2025.09 | Y4: 2025.12 | Z4: 2025.12A | AA4: 2026.03 | AB4: 2026.06 | AC4: 2026.09 | AD4: 2026.12 | AE4: 2026.12A | AF4: 2027.03 | AG4: 2027.06 | AH4: 2027.09 | AI4: 2027.12 | AJ4: 2027.12A | AK4: 2028.03 | AL4: 2028.06 | AM4: 2028.09 | AN4: 2028.12 | AO4: 2028.12A
B5: 1. FX | C5: 이름: 환율
A6: USDKRW_avg | C6: 원/달러(평균) | E6: 1183.5 | F6: 1145.51 | G6: 1205.78 | H6: 1262.09 | I6: 1341.93 | J6: 1360.12 | K6: 1292.98 | L6: 1276.95 | M6: 1315.69 | N6: 1313.62 | O6: 1322.01 | P6: 1306.85 | Q6: 1330.14 | R6: 1371.28 | S6: 1356.22 | T6: 1396.3 | U6: 1363.53 | V6: 1452.28 | W6: 1398.52 | X6: 1386.95 | Y6: 1449.19 | Z6: 1421.52 | AA6: 1466.12 | AB6: 1501.75 | AC6: 1418.75 | AD6: 1342.11 | AE6: 1454.27 | AF6: 1332.1 | AG6: 1332.1 | AH6: 1332.1 | AI6: 1332.1 | AK6: 1332.1 | AL6: 1332.1 | AM6: 1332.1 | AN6: 1332.1
A7: USDKRW_end | C7: 원/달러(기말) | E7: 1188.75 | F7: 1188.75 | G7: 1213.74 | H7: 1301.24 | I7: 1436.9 | J7: 1260.16 | K7: 1260.16 | L7: 1305.99 | M7: 1321.44 | N7: 1345.35 | O7: 1297.43 | P7: 1297.43 | Q7: 1349.25 | R7: 1377.73 | S7: 1312.17 | T7: 1474.78 | U7: 1474.78 | V7: 1474.54 | W7: 1355.13 | X7: 1403.67 | Y7: 1444.2 | Z7: 1444.2 | AA7: 1524.8 | AB7: 1550.89 | AC7: 1355.4 | AD7: 1332.1 | AE7: 1332.1 | AF7: 1332.1 | AG7: 1332.1 | AH7: 1332.1 | AI7: 1332.1 | AK7: 1332.1 | AL7: 1332.1 | AM7: 1332.1 | AN7: 1332.1
A8: JPY100KRW_avg | C8: 원/100Y(평균) | E8: 1041.02 | F8: 1042.74 | G8: 1036.79 | H8: 972.23 | I8: 970.61 | J8: 961.03 | K8: 985.1 | L8: 964.89 | M8: 957.36 | N8: 909 | O8: 893.22 | P8: 931.11 | Q8: 896.29 | R8: 880.14 | S8: 909.35 | T8: 917.25 | U8: 900.92 | V8: 952.59 | W8: 967.92 | X8: 940.32 | Y8: 940.77 | Z8: 950.17 | AA8: 934.39 | AB8: 942.16 | AC8: 890.41 | AD8: 848.59 | AE8: 917.39 | AF8: 842.99 | AG8: 842.99 | AH8: 842.99 | AI8: 842.99 | AK8: 842.99 | AL8: 842.99 | AM8: 842.99 | AN8: 842.99
A9: JPY100KRW_end | C9: 원/100Y(기말) | E9: 1032.62 | F9: 1032.62 | G9: 996.83 | H9: 954.9 | I9: 993.29 | J9: 955.54 | K9: 955.54 | L9: 980.62 | M9: 913.67 | N9: 901.47 | O9: 917.04 | P9: 917.04 | Q9: 892.42 | R9: 857.76 | S9: 919.21 | T9: 939.65 | U9: 939.65 | V9: 986.84 | W9: 938.85 | X9: 948.49 | Y9: 921.81 | Z9: 921.81 | AA9: 955.99 | AB9: 954.75 | AC9: 863.31 | AD9: 842.99 | AE9: 842.99 | AF9: 842.99 | AG9: 842.99 | AH9: 842.99 | AI9: 842.99 | AK9: 842.99 | AL9: 842.99 | AM9: 842.99 | AN9: 842.99
A10: EURKRW_avg | C10: W/Euro(평균) | E10: 1353.32 | F10: 1354.06 | G10: 1352.29 | H10: 1343.31 | I10: 1350.63 | J10: 1386.07 | K10: 1358.07 | L10: 1369.93 | M10: 1432.41 | N10: 1429.41 | O10: 1420.91 | P10: 1412.88 | Q10: 1444.21 | R10: 1476.42 | S10: 1489.3 | T10: 1490.78 | U10: 1475.4 | V10: 1528.33 | W10: 1585.13 | X10: 1620.04 | Y10: 1686.02 | Z10: 1605.45 | AA10: 1715.47 | AB10: 1746.09 | AC10: 1631.97 | AD10: 1505.3 | AE10: 1685.25 | AF10: 1499.02 | AG10: 1499.02 | AH10: 1499.02 | AI10: 1499.02 | AK10: 1499.02 | AL10: 1499.02 | AM10: 1499.02 | AN10: 1499.02
A11: EURKRW_end | C11: W/Euro(기말) | E11: 1346.38 | F11: 1346.38 | G11: 1347.37 | H11: 1351.6 | I11: 1400.62 | J11: 1344.08 | K11: 1344.08 | L11: 1420.26 | M11: 1435.88 | N11: 1425.26 | O11: 1433.66 | P11: 1433.66 | Q11: 1458.68 | R11: 1474.86 | S11: 1469.1 | T11: 1532.14 | U11: 1532.14 | V11: 1594.72 | W11: 1588.22 | X11: 1648.04 | Y11: 1696.94 | Z11: 1696.94 | AA11: 1753.21 | AB11: 1767.09 | AC11: 1539.06 | AD11: 1499.02 | AE11: 1499.02 | AF11: 1499.02 | AG11: 1499.02 | AH11: 1499.02 | AI11: 1499.02 | AK11: 1499.02 | AL11: 1499.02 | AM11: 1499.02 | AN11: 1499.02
A12: CNYKRW_avg | C12: 원/중국원(평균) | E12: 185.14 | F12: 177.65 | G12: 189.93 | H12: 190.76 | I12: 195.79 | J12: 191.09 | K12: 191.93 | L12: 186.59 | M12: 187.45 | N12: 181.28 | O12: 182.86 | P12: 184.52 | Q12: 185.04 | R12: 189.35 | S12: 189.24 | T12: 194.24 | U12: 189.49 | V12: 199.63 | W12: 193.41 | X12: 193.79 | Y12: 204.38 | Z12: 197.8 | AA12: 211.75 | AB12: 220.8 | AC12: 210.43 | AD12: 200.38 | AE12: 213.41 | AF12: 199.23 | AG12: 199.23 | AH12: 199.23 | AI12: 199.23 | AK12: 199.23 | AL12: 199.23 | AM12: 199.23 | AN12: 199.23
A13: CNYKRW_end | C13: 원/중국원(기말) | E13: 187.13 | F13: 187.13 | G13: 191.38 | H13: 194.13 | I13: 201.92 | J13: 182.67 | K13: 182.67 | L13: 189.97 | M13: 181.8 | N13: 184.26 | O13: 182.61 | P13: 182.61 | Q13: 186.66 | R13: 189.7 | S13: 187.12 | T13: 202.04 | U13: 202.04 | V13: 203.3 | W13: 189.14 | X13: 197.16 | Y13: 206.28 | Z13: 206.28 | AA13: 220.97 | AB13: 228.56 | AC13: 202.16 | AD13: 199.23 | AE13: 199.23 | AF13: 199.23 | AG13: 199.23 | AH13: 199.23 | AI13: 199.23 | AK13: 199.23 | AL13: 199.23 | AM13: 199.23 | AN13: 199.23
B14: 1b. 종가
A15: price_close_end | C15: 종가(기말) | E15: 5275 | G15: 5050 | H15: 3825 | I15: 3495 | J15: 3545 | L15: 3810 | M15: 3875 | N15: 3065 | O15: 2815 | Q15: 2575 | R15: 2625 | S15: 2430 | T15: 2030 | V15: 1955 | W15: 2715 | X15: 2825 | Y15: 2445 | AA15: 2750 | AB15: 1350 | AC15: 2120 | AD15: 2190
A16: price_high | C16: 종가(최고) | E16: 5900 | G16: 5425 | H16: 5575 | I16: 4470 | J16: 3905 | L16: 4180 | M16: 4065 | N16: 3935 | O16: 3410 | Q16: 2890 | R16: 3050 | S16: 2725 | T16: 2450 | V16: 2175 | W16: 3185 | X16: 3670 | Y16: 3285 | AA16: 4040 | AB16: 2950 | AC16: 3020 | AD16: 2430
A17: price_low | C17: 종가(최저) | E17: 4830 | G17: 4350 | H17: 3330 | I17: 3335 | J17: 3030 | L17: 3370 | M17: 3575 | N17: 3020 | O17: 2590 | Q17: 2550 | R17: 2415 | S17: 2335 | T17: 1795 | V17: 1950 | W17: 1795 | X17: 2435 | Y17: 2410 | AA17: 2235 | AB17: 1281 | AC17: 1284 | AD17: 2020
A18: price_avg | C18: 종가(평균) | E18: 5327.9 | G18: 4851.4 | H18: 4796.3 | I18: 4012.5 | J18: 3587.5 | L18: 3846.2 | M18: 3777.8 | N18: 3423.7 | O18: 2846.2 | Q18: 2714.3 | R18: 2592.8 | S18: 2509.2 | T18: 2191.1 | V18: 2034.6 | W18: 2397 | X18: 2891.5 | Y18: 2732.4 | AA18: 2643.8 | AB18: 2335.4 | AC18: 2271.6 | AD18: 2189.5
B20: 2. 추정 드라이버 | C20: 실적 열 = subQ 실현값(수식), 추정 열 = 가정(노란 = 모델값 역산, 연녹 = 3절 스칼라 참조)
A21: drv:매출액 | B21: yoy | C21: 매출액 YoY | J21: =IFERROR(subQ!J5/subQ!E5-1,"") | L21: =IFERROR(subQ!L5/subQ!G5-1,"") | M21: =IFERROR(subQ!M5/subQ!H5-1,"") | N21: =IFERROR(subQ!N5/subQ!I5-1,"") | O21: =IFERROR(subQ!O5/subQ!J5-1,"") | Q21: =IFERROR(subQ!Q5/subQ!L5-1,"") | R21: =IFERROR(subQ!R5/subQ!M5-1,"") | S21: =IFERROR(subQ!S5/subQ!N5-1,"") | T21: =IFERROR(subQ!T5/subQ!O5-1,"") | V21: =IFERROR(subQ!V5/subQ!Q5-1,"") | W21: =IFERROR(subQ!W5/subQ!R5-1,"") | X21: =IFERROR(subQ!X5/subQ!S5-1,"") | Y21: =IFERROR(subQ!Y5/subQ!T5-1,"") | AA21: =IFERROR(subQ!AA5/subQ!V5-1,"") | AB21: =IFERROR(subQ!AB5/subQ!W5-1,"") | AC21: -0.10141899 | AD21: -0.10141958 | AF21: -0.10142747 | AG21: -0.10142512 | AH21: -0.050713924 | AI21: -0.050720368 | AK21: -0.050701137 | AL21: -0.050709833 | AM21: -0.02535683 | AN21: -0.025352044
A22: drv:판관비 | B22: ratio | C22: 판관비율(/매출) | E22: =IFERROR(subQ!E8/subQ!E5,"") | F22: =IFERROR(subQ!F8/subQ!F5,"") | G22: =IFERROR(subQ!G8/subQ!G5,"") | H22: =IFERROR(subQ!H8/subQ!H5,"") | I22: =IFERROR(subQ!I8/subQ!I5,"") | J22: =IFERROR(subQ!J8/subQ!J5,"") | K22: =IFERROR(subQ!K8/subQ!K5,"") | L22: =IFERROR(subQ!L8/subQ!L5,"") | ... AB22: =IFERROR(subQ!AB8/subQ!AB5,"") | AC22: =$D$53 | AD22: =$D$53 | AE22: =IFERROR(subQ!AE8/subQ!AE5,"") | AF22: =$D$53 | AG22: =$D$53 | AH22: =$D$53 | AI22: =$D$53 | AJ22: =IFERROR(subQ!AJ8/subQ!AJ5,"") | AK22: =$D$53 | AL22: =$D$53 | AM22: =$D$53 | AN22: =$D$53 | AO22: =IFERROR(subQ!AO8/subQ!AO5,"")
A23: drv:영업이익 | B23: ratio | C23: 영업이익률(OPM) | E23: =IFERROR(subQ!E9/subQ!E5,"") | F23: =IFERROR(subQ!F9/subQ!F5,"") | G23: =IFERROR(subQ!G9/subQ!G5,"") | H23: =IFERROR(subQ!H9/subQ!H5,"") | I23: =IFERROR(subQ!I9/subQ!I5,"") | J23: =IFERROR(subQ!J9/subQ!J5,"") | K23: =IFERROR(subQ!K9/subQ!K5,"") | L23: =IFERROR(subQ!L9/subQ!L5,"") | ... AB23: =IFERROR(subQ!AB9/subQ!AB5,"") | AC23: -0.017711392 | AD23: -0.017711691 | AE23: =IFERROR(subQ!AE9/subQ!AE5,"") | AF23: -0.017715967 | AG23: -0.017709354 | AH23: -0.017708178 | AI23: -0.017708701 | AJ23: =IFERROR(subQ!AJ9/subQ!AJ5,"") | AK23: -0.017713855 | AL23: -0.017711067 | AM23: -0.017709188 | AN23: -0.017707293 | AO23: =IFERROR(subQ!AO9/subQ!AO5,"")
A24: drv:외환손익 | B24: abs | C24: 외환손익 (가정, 억원) | E24: =subQ!E13 | F24: =subQ!F13 | G24: =subQ!G13 | H24: =subQ!H13 | I24: =subQ!I13 | J24: =subQ!J13 | K24: =subQ!K13 | L24: =subQ!L13 | ... AB24: =subQ!AB13 | AC24: 0 | AD24: 0 | AE24: =subQ!AE13 | AF24: 0 | AG24: 0 | AH24: 0 | AI24: 0 | AJ24: =subQ!AJ13 | AK24: 0 | AL24: 0 | AM24: 0 | AN24: 0 | AO24: =subQ!AO13
A25: drv:파생상품손익 | B25: abs | C25: 파생상품손익 (가정, 억원) | E25: =subQ!E14 | F25: =subQ!F14 | G25: =subQ!G14 | H25: =subQ!H14 | I25: =subQ!I14 | J25: =subQ!J14 | K25: =subQ!K14 | L25: =subQ!L14 | ... AB25: =subQ!AB14 | AC25: 0 | AD25: 0 | AE25: =subQ!AE14 | AF25: 0 | AG25: 0 | AH25: 0 | AI25: 0 | AJ25: =subQ!AJ14 | AK25: 0 | AL25: 0 | AM25: 0 | AN25: 0 | AO25: =subQ!AO14
A26: drv:기타금융손익 | B26: abs | C26: 기타금융손익 (가정, 억원) | E26: =subQ!E15 | F26: =subQ!F15 | G26: =subQ!G15 | H26: =subQ!H15 | I26: =subQ!I15 | J26: =subQ!J15 | K26: =subQ!K15 | L26: =subQ!L15 | ... AB26: =subQ!AB15 | AC26: 0 | AD26: 0 | AE26: =subQ!AE15 | AF26: 0 | AG26: 0 | AH26: 0 | AI26: 0 | AJ26: =subQ!AJ15 | AK26: 0 | AL26: 0 | AM26: 0 | AN26: 0 | AO26: =subQ!AO15
A27: drv:기타영업외손익 | B27: abs | C27: 기타영업외손익 (가정, 억원) | E27: =subQ!E16 | F27: =subQ!F16 | G27: =subQ!G16 | H27: =subQ!H16 | I27: =subQ!I16 | J27: =subQ!J16 | K27: =subQ!K16 | L27: =subQ!L16 | ... AB27: =subQ!AB16 | AC27: 0 | AD27: 0 | AE27: =subQ!AE16 | AF27: 0 | AG27: 0 | AH27: 0 | AI27: 0 | AJ27: =subQ!AJ16 | AK27: 0 | AL27: 0 | AM27: 0 | AN27: 0 | AO27: =subQ!AO16
A28: drv:지분법손익 | B28: abs | C28: 지분법손익 (가정, 억원) | E28: =subQ!E17 | F28: =subQ!F17 | G28: =subQ!G17 | H28: =subQ!H17 | I28: =subQ!I17 | J28: =subQ!J17 | K28: =subQ!K17 | L28: =subQ!L17 | ... AB28: =subQ!AB17 | AC28: -0.74 | AD28: -0.74 | AE28: =subQ!AE17 | AF28: -0.74 | AG28: -0.74 | AH28: -0.74 | AI28: -0.74 | AJ28: =subQ!AJ17 | AK28: -0.74 | AL28: -0.74 | AM28: -0.74 | AN28: -0.74 | AO28: =subQ!AO17
A29: drv:법인세비용 | B29: ratio | C29: 법인세율(/세전) | E29: =IFERROR(subQ!E19/subQ!E18,"") | F29: =IFERROR(subQ!F19/subQ!F18,"") | G29: =IFERROR(subQ!G19/subQ!G18,"") | H29: =IFERROR(subQ!H19/subQ!H18,"") | I29: =IFERROR(subQ!I19/subQ!I18,"") | J29: =IFERROR(subQ!J19/subQ!J18,"") | K29: =IFERROR(subQ!K19/subQ!K18,"") | L29: =IFERROR(subQ!L19/subQ!L18,"") | ... AB29: =IFERROR(subQ!AB19/subQ!AB18,"") | AC29: 0 | AD29: 0 | AE29: =IFERROR(subQ!AE19/subQ!AE18,"") | AF29: 0 | AG29: 0 | AH29: 0 | AI29: 0 | AJ29: =IFERROR(subQ!AJ19/subQ!AJ18,"") | AK29: 0 | AL29: 0 | AM29: 0 | AN29: 0 | AO29: =IFERROR(subQ!AO19/subQ!AO18,"")
A30: drv:지배주주순이익 | B30: ratio | C30: 지배주주 비중(/당기순이익) | E30: =IFERROR(subQ!E21/subQ!E20,"") | F30: =IFERROR(subQ!F21/subQ!F20,"") | G30: =IFERROR(subQ!G21/subQ!G20,"") | H30: =IFERROR(subQ!H21/subQ!H20,"") | I30: =IFERROR(subQ!I21/subQ!I20,"") | J30: =IFERROR(subQ!J21/subQ!J20,"") | K30: =IFERROR(subQ!K21/subQ!K20,"") | L30: =IFERROR(subQ!L21/subQ!L20,"") | ... AB30: =IFERROR(subQ!AB21/subQ!AB20,"") | AC30: =$D$54 | AD30: =$D$54 | AE30: =IFERROR(subQ!AE21/subQ!AE20,"") | AF30: =$D$54 | AG30: =$D$54 | AH30: =$D$54 | AI30: =$D$54 | AJ30: =IFERROR(subQ!AJ21/subQ!AJ20,"") | AK30: =$D$54 | AL30: =$D$54 | AM30: =$D$54 | AN30: =$D$54 | AO30: =IFERROR(subQ!AO21/subQ!AO20,"")
A31: drv:중단사업이익 | B31: abs | C31: 중단사업이익 (가정, 억원) | E31: =subQ!E22 | F31: =subQ!F22 | G31: =subQ!G22 | H31: =subQ!H22 | I31: =subQ!I22 | J31: =subQ!J22 | K31: =subQ!K22 | L31: =subQ!L22 | ... AB31: =subQ!AB22 | AE31: =subQ!AE22 | AJ31: =subQ!AJ22 | AO31: =subQ!AO22
A32: drv:부채총계 | B32: qoq | C32: 부채총계 QoQ | G32: =IFERROR(subQ!G24/subQ!E24-1,"") | H32: =IFERROR(subQ!H24/subQ!G24-1,"") | I32: =IFERROR(subQ!I24/subQ!H24-1,"") | J32: =IFERROR(subQ!J24/subQ!I24-1,"") | L32: =IFERROR(subQ!L24/subQ!J24-1,"") | M32: =IFERROR(subQ!M24/subQ!L24-1,"") | N32: =IFERROR(subQ!N24/subQ!M24-1,"") | O32: =IFERROR(subQ!O24/subQ!N24-1,"") | Q32: =IFERROR(subQ!Q24/subQ!O24-1,"") | R32: =IFERROR(subQ!R24/subQ!Q24-1,"") | S32: =IFERROR(subQ!S24/subQ!R24-1,"") | T32: =IFERROR(subQ!T24/subQ!S24-1,"") | V32: =IFERROR(subQ!V24/subQ!T24-1,"") | W32: =IFERROR(subQ!W24/subQ!V24-1,"") | X32: =IFERROR(subQ!X24/subQ!W24-1,"") | Y32: =IFERROR(subQ!Y24/subQ!X24-1,"") | AA32: =IFERROR(subQ!AA24/subQ!Y24-1,"") | AB32: =IFERROR(subQ!AB24/subQ!AA24-1,"") | AC32: 9.32e-07 | AD32: 0 | AF32: 0 | AG32: 0 | AH32: 0 | AI32: 0 | AK32: 0 | AL32: 0 | AM32: 0 | AN32: 0
A33: drv:자본총계 | B33: roll | C33: 자본총계 기타변동(배당 등, 억원) | G33: =IFERROR(subQ!E25+subQ!G20-subQ!G25,"") | H33: =IFERROR(subQ!G25+subQ!H20-subQ!H25,"") | I33: =IFERROR(subQ!H25+subQ!I20-subQ!I25,"") | J33: =IFERROR(subQ!I25+subQ!J20-subQ!J25,"") | L33: =IFERROR(subQ!J25+subQ!L20-subQ!L25,"") | M33: =IFERROR(subQ!L25+subQ!M20-subQ!M25,"") | N33: =IFERROR(subQ!M25+subQ!N20-subQ!N25,"") | O33: =IFERROR(subQ!N25+subQ!O20-subQ!O25,"") | Q33: =IFERROR(subQ!O25+subQ!Q20-subQ!Q25,"") | R33: =IFERROR(subQ!Q25+subQ!R20-subQ!R25,"") | S33: =IFERROR(subQ!R25+subQ!S20-subQ!S25,"") | T33: =IFERROR(subQ!S25+subQ!T20-subQ!T25,"") | V33: =IFERROR(subQ!T25+subQ!V20-subQ!V25,"") | W33: =IFERROR(subQ!V25+subQ!W20-subQ!W25,"") | X33: =IFERROR(subQ!W25+subQ!X20-subQ!X25,"") | Y33: =IFERROR(subQ!X25+subQ!Y20-subQ!Y25,"") | AA33: =IFERROR(subQ!Y25+subQ!AA20-subQ!AA25,"") | AB33: =IFERROR(subQ!AA25+subQ!AB20-subQ!AB25,"") | AC33: -0.004607013 | AD33: 0.005532376 | AF33: -0.014077506 | AG33: 0.008403083 | AH33: -0.005168202 | AI33: 0.00102731 | AK33: -0.004402449 | AL33: 0.001096063 | AM33: 0.001008086 | AN33: -0.000711033
A34: drv:지배주주지분 | B34: roll | C34: 지배주주지분 기타변동(배당 등, 억원) | G34: =IFERROR(subQ!E26+subQ!G21-subQ!G26,"") | H34: =IFERROR(subQ!G26+subQ!H21-subQ!H26,"") | I34: =IFERROR(subQ!H26+subQ!I21-subQ!I26,"") | J34: =IFERROR(subQ!I26+subQ!J21-subQ!J26,"") | L34: =IFERROR(subQ!J26+subQ!L21-subQ!L26,"") | M34: =IFERROR(subQ!L26+subQ!M21-subQ!M26,"") | N34: =IFERROR(subQ!M26+subQ!N21-subQ!N26,"") | O34: =IFERROR(subQ!N26+subQ!O21-subQ!O26,"") | Q34: =IFERROR(subQ!O26+subQ!Q21-subQ!Q26,"") | R34: =IFERROR(subQ!Q26+subQ!R21-subQ!R26,"") | S34: =IFERROR(subQ!R26+subQ!S21-subQ!S26,"") | T34: =IFERROR(subQ!S26+subQ!T21-subQ!T26,"") | V34: =IFERROR(subQ!T26+subQ!V21-subQ!V26,"") | W34: =IFERROR(subQ!V26+subQ!W21-subQ!W26,"") | X34: =IFERROR(subQ!W26+subQ!X21-subQ!X26,"") | Y34: =IFERROR(subQ!X26+subQ!Y21-subQ!Y26,"") | AA34: =IFERROR(subQ!Y26+subQ!AA21-subQ!AA26,"") | AB34: =IFERROR(subQ!AA26+subQ!AB21-subQ!AB26,"") | AC34: -0.002307013 | AD34: -0.004467624 | AF34: -0.004077506 | AG34: -0.001596917 | AH34: 0.004831798 | AI34: 0.00102731 | AK34: -0.004402449 | AL34: 0.001096063 | AM34: 0.001008086 | AN34: -0.000711033
A35: drv:총차입금 | B35: qoq | C35: 총차입금 QoQ | G35: =IFERROR(subQ!G27/subQ!E27-1,"") | H35: =IFERROR(subQ!H27/subQ!G27-1,"") | I35: =IFERROR(subQ!I27/subQ!H27-1,"") | J35: =IFERROR(subQ!J27/subQ!I27-1,"") | L35: =IFERROR(subQ!L27/subQ!J27-1,"") | M35: =IFERROR(subQ!M27/subQ!L27-1,"") | N35: =IFERROR(subQ!N27/subQ!M27-1,"") | O35: =IFERROR(subQ!O27/subQ!N27-1,"") | Q35: =IFERROR(subQ!Q27/subQ!O27-1,"") | R35: =IFERROR(subQ!R27/subQ!Q27-1,"") | S35: =IFERROR(subQ!S27/subQ!R27-1,"") | T35: =IFERROR(subQ!T27/subQ!S27-1,"") | V35: =IFERROR(subQ!V27/subQ!T27-1,"") | W35: =IFERROR(subQ!W27/subQ!V27-1,"") | X35: =IFERROR(subQ!X27/subQ!W27-1,"") | Y35: =IFERROR(subQ!Y27/subQ!X27-1,"") | AA35: =IFERROR(subQ!AA27/subQ!Y27-1,"") | AB35: =IFERROR(subQ!AB27/subQ!AA27-1,"") | AC35: 2.27e-06 | AD35: 0 | AF35: 0 | AG35: 0 | AH35: 0 | AI35: 0 | AK35: 0 | AL35: 0 | AM35: 0 | AN35: 0
A36: drv:순차입금 | B36: qoq | C36: 순차입금 QoQ | G36: =IFERROR(subQ!G28/subQ!E28-1,"") | H36: =IFERROR(subQ!H28/subQ!G28-1,"") | I36: =IFERROR(subQ!I28/subQ!H28-1,"") | J36: =IFERROR(subQ!J28/subQ!I28-1,"") | L36: =IFERROR(subQ!L28/subQ!J28-1,"") | M36: =IFERROR(subQ!M28/subQ!L28-1,"") | N36: =IFERROR(subQ!N28/subQ!M28-1,"") | O36: =IFERROR(subQ!O28/subQ!N28-1,"") | Q36: =IFERROR(subQ!Q28/subQ!O28-1,"") | R36: =IFERROR(subQ!R28/subQ!Q28-1,"") | S36: =IFERROR(subQ!S28/subQ!R28-1,"") | T36: =IFERROR(subQ!T28/subQ!S28-1,"") | V36: =IFERROR(subQ!V28/subQ!T28-1,"") | W36: =IFERROR(subQ!W28/subQ!V28-1,"") | X36: =IFERROR(subQ!X28/subQ!W28-1,"") | Y36: =IFERROR(subQ!Y28/subQ!X28-1,"") | AA36: =IFERROR(subQ!AA28/subQ!Y28-1,"") | AB36: =IFERROR(subQ!AB28/subQ!AA28-1,"") | AC36: 0.028858632 | AD36: 0.026897334 | AF36: 0.026818584 | AG36: 0.028025548 | AH36: 0.027600277 | AI36: 0.025944934 | AK36: 0.025887628 | AL36: 0.026935643 | AM36: 0.026873783 | AN36: 0.025427962
A37: drv:이자발생자산 | B37: qoq | C37: 이자발생자산 QoQ | G37: =IFERROR(subQ!G29/subQ!E29-1,"") | H37: =IFERROR(subQ!H29/subQ!G29-1,"") | I37: =IFERROR(subQ!I29/subQ!H29-1,"") | J37: =IFERROR(subQ!J29/subQ!I29-1,"") | L37: =IFERROR(subQ!L29/subQ!J29-1,"") | M37: =IFERROR(subQ!M29/subQ!L29-1,"") | N37: =IFERROR(subQ!N29/subQ!M29-1,"") | O37: =IFERROR(subQ!O29/subQ!N29-1,"") | Q37: =IFERROR(subQ!Q29/subQ!O29-1,"") | R37: =IFERROR(subQ!R29/subQ!Q29-1,"") | S37: =IFERROR(subQ!S29/subQ!R29-1,"") | T37: =IFERROR(subQ!T29/subQ!S29-1,"") | V37: =IFERROR(subQ!V29/subQ!T29-1,"") | W37: =IFERROR(subQ!W29/subQ!V29-1,"") | X37: =IFERROR(subQ!X29/subQ!W29-1,"") | Y37: =IFERROR(subQ!Y29/subQ!X29-1,"") | AA37: =IFERROR(subQ!AA29/subQ!Y29-1,"") | AB37: =IFERROR(subQ!AB29/subQ!AA29-1,"") | AC37: -0.35694972 | AD37: -0.53228737 | AF37: -1.1652542 | AG37: 7.5662393 | AH37: 0.89423796 | AI37: 0.45601791 | AK37: 0.32061138 | AL37: 0.25914258 | AM37: 0.21086696 | AN37: 0.16920451
A38: drv:현금및현금성자산 | B38: qoq | C38: 현금및현금성자산 QoQ | G38: =IFERROR(subQ!G30/subQ!E30-1,"") | H38: =IFERROR(subQ!H30/subQ!G30-1,"") | I38: =IFERROR(subQ!I30/subQ!H30-1,"") | J38: =IFERROR(subQ!J30/subQ!I30-1,"") | L38: =IFERROR(subQ!L30/subQ!J30-1,"") | M38: =IFERROR(subQ!M30/subQ!L30-1,"") | N38: =IFERROR(subQ!N30/subQ!M30-1,"") | O38: =IFERROR(subQ!O30/subQ!N30-1,"") | Q38: =IFERROR(subQ!Q30/subQ!O30-1,"") | R38: =IFERROR(subQ!R30/subQ!Q30-1,"") | S38: =IFERROR(subQ!S30/subQ!R30-1,"") | T38: =IFERROR(subQ!T30/subQ!S30-1,"") | V38: =IFERROR(subQ!V30/subQ!T30-1,"") | W38: =IFERROR(subQ!W30/subQ!V30-1,"") | X38: =IFERROR(subQ!X30/subQ!W30-1,"") | Y38: =IFERROR(subQ!Y30/subQ!X30-1,"") | AA38: =IFERROR(subQ!AA30/subQ!Y30-1,"") | AB38: =IFERROR(subQ!AB30/subQ!AA30-1,"")
A39: drv:CAPEX | B39: yoy | C39: CAPEX YoY | J39: =IFERROR(subQ!J31/subQ!E31-1,"") | L39: =IFERROR(subQ!L31/subQ!G31-1,"") | M39: =IFERROR(subQ!M31/subQ!H31-1,"") | N39: =IFERROR(subQ!N31/subQ!I31-1,"") | O39: =IFERROR(subQ!O31/subQ!J31-1,"") | Q39: =IFERROR(subQ!Q31/subQ!L31-1,"") | R39: =IFERROR(subQ!R31/subQ!M31-1,"") | S39: =IFERROR(subQ!S31/subQ!N31-1,"") | T39: =IFERROR(subQ!T31/subQ!O31-1,"") | V39: =IFERROR(subQ!V31/subQ!Q31-1,"") | W39: =IFERROR(subQ!W31/subQ!R31-1,"") | X39: =IFERROR(subQ!X31/subQ!S31-1,"") | Y39: =IFERROR(subQ!Y31/subQ!T31-1,"") | AA39: =IFERROR(subQ!AA31/subQ!V31-1,"") | AB39: =IFERROR(subQ!AB31/subQ!W31-1,"") | AC39: -0.26462615 | AD39: 0.1634261 | AF39: 3.6239709 | AG39: -0.12307589 | AH39: 0 | AI39: 0 | AK39: 0 | AL39: 0 | AM39: 0 | AN39: 0
A40: drv:영업활동현금흐름 | B40: yoy | C40: 영업활동현금흐름 YoY | J40: =IFERROR(subQ!J32/subQ!E32-1,"") | L40: =IFERROR(subQ!L32/subQ!G32-1,"") | M40: =IFERROR(subQ!M32/subQ!H32-1,"") | N40: =IFERROR(subQ!N32/subQ!I32-1,"") | O40: =IFERROR(subQ!O32/subQ!J32-1,"") | Q40: =IFERROR(subQ!Q32/subQ!L32-1,"") | R40: =IFERROR(subQ!R32/subQ!M32-1,"") | S40: =IFERROR(subQ!S32/subQ!N32-1,"") | T40: =IFERROR(subQ!T32/subQ!O32-1,"") | V40: =IFERROR(subQ!V32/subQ!Q32-1,"") | W40: =IFERROR(subQ!W32/subQ!R32-1,"") | X40: =IFERROR(subQ!X32/subQ!S32-1,"") | Y40: =IFERROR(subQ!Y32/subQ!T32-1,"") | AA40: =IFERROR(subQ!AA32/subQ!V32-1,"") | AB40: =IFERROR(subQ!AB32/subQ!W32-1,"")
A41: drv:주식수 | B41: qoq | C41: 주식수 QoQ | G41: =IFERROR(subQ!G33/subQ!E33-1,"") | H41: =IFERROR(subQ!H33/subQ!G33-1,"") | I41: =IFERROR(subQ!I33/subQ!H33-1,"") | J41: =IFERROR(subQ!J33/subQ!I33-1,"") | L41: =IFERROR(subQ!L33/subQ!J33-1,"") | M41: =IFERROR(subQ!M33/subQ!L33-1,"") | N41: =IFERROR(subQ!N33/subQ!M33-1,"") | O41: =IFERROR(subQ!O33/subQ!N33-1,"") | Q41: =IFERROR(subQ!Q33/subQ!O33-1,"") | R41: =IFERROR(subQ!R33/subQ!Q33-1,"") | S41: =IFERROR(subQ!S33/subQ!R33-1,"") | T41: =IFERROR(subQ!T33/subQ!S33-1,"") | V41: =IFERROR(subQ!V33/subQ!T33-1,"") | W41: =IFERROR(subQ!W33/subQ!V33-1,"") | X41: =IFERROR(subQ!X33/subQ!W33-1,"") | Y41: =IFERROR(subQ!Y33/subQ!X33-1,"") | AA41: =IFERROR(subQ!AA33/subQ!Y33-1,"") | AB41: =IFERROR(subQ!AB33/subQ!AA33-1,"") | AC41: 0 | AD41: 0 | AF41: 0 | AG41: 0 | AH41: 0 | AI41: 0 | AK41: 0 | AL41: 0 | AM41: 0 | AN41: 0
A42: drv:DPS | B42: abs | C42: DPS (가정, 원) | E42: =subQ!E37 | F42: =subQ!F37 | G42: =subQ!G37 | H42: =subQ!H37 | I42: =subQ!I37 | J42: =subQ!J37 | K42: =subQ!K37 | L42: =subQ!L37 | ... AB42: =subQ!AB37 | AD42: 0 | AE42: =subQ!AE37 | AI42: 0 | AJ42: =subQ!AJ37 | AN42: 0 | AO42: =subQ!AO37
B44: 3. 밸류에이션·스칼라 | C44: 노란 셀 = 가정. '연결' 표시는 추정 전 분기 수식이 이 셀을 참조한다는 뜻
A45: sc:종가 | C45: 종가 | D45: 2190 | E45: 원 — 네이버 정규장 종가(aik 확정종가 대조 · aik 2,205원)
A46: sc:기준일 | C46: 기준일 | D46: 20261019 | E46: 종가 기준일
A47: sc:COE | C47: COE | D47: 0.09 | E47: 자기자본비용(가정) — TP 적정 PBR = ROE/COE
A48: sc:PER_lo | C48: PER_lo | D48: 10 | E48: PER 밴드 하단(배) — sector_default(레퍼런스 TP_PE PB 예시 10/15/20배; 과거 양(+)EPS 분기 1개 < 4)
A49: sc:PER_mid | C49: PER_mid | D49: 15 | E49: PER 밴드 중단(배)
A50: sc:PER_hi | C50: PER_hi | D50: 20 | E50: PER 밴드 상단(배)
A51: sc:EPS_Y1가중 | C51: EPS_Y1가중 | D51: 0.5 | E51: 12M fwd EPS = FY(last_actual연도)E × w + FY+1E × (1−w) — 기준 분기 2Q 이면 0.5(가정)
A52: sc:세율 | C52: 세율 | D52: 0.2291 | E52: 참고(연결 안 됨: MAX(세전,0)×단일 세율로 재현 불가(지주 자회사 합산 등) → 분기별 역산) — 모델 assumptions 값 · 최근 12분기 세전 합 ≤ 0 → 클립 대신 최근 8분기 중 세전 > 0 인 2분기(2025Q1~2026Q2)의 법인세/세전 중위 22.9%
A53: sc:판관비율 | C53: 판관비율 | D53: 0.078475198 | E53: 연결 — 판관비 = 매출액 × 판관비율(역산, 재현 오차 ≤ 0.05억 · 모델 assumptions 0.0785)
A54: sc:지배주주비중 | C54: 지배주주비중 | D54: 1 | E54: 연결 — 지배주주순이익 = 당기순이익 × 비중(역산, 재현 오차 ≤ 0.05억)
A55: sc:이자율_자산 | C55: 이자율_자산 | D55: 0.093032603 | E55: 연결 — 이자손익 = (전분기 이자발생자산 × 자산이자율 − 전분기 총차입금 × 부채이자율)/4(역산, 재현 오차 ≤ 0.05억 · 모델 assumptions 0.093)
A56: sc:이자율_부채 | C56: 이자율_부채 | D56: 0.056982688 | E56: 연결 — 같은 수식의 부채 쪽(총차입금 행이 없으면 0)(역산, 재현 오차 ≤ 0.05억 · 모델 assumptions 0.057)
A57: sc:배당성향 | C57: 배당성향 | E57: 배당성향(참고 — 모델은 직전 DPS 유지·Q2 지급 가정)
A58: sc:외화순노출_백만$ | C58: 외화순노출_백만$ | E58: 외화 순노출 × Δ기말환율 (외화 시트 방식) — 외화 순노출 미공시(face) → 0 + 표기
A59: sc:헤지비율 | C59: 헤지비율 | E59: sls 없음
A60: sc:헤지환율_약정 | C60: 헤지환율_약정 | E60: sls 없음

Sheet BS연결
B1: (백만원) | C1: 이름: BS연결H | E1: 4Q21 | F1: 2021 | G1: 1Q22 | H1: 2Q22 | I1: 3Q22 | J1: 4Q22 | K1: 2022 | L1: 1Q23 | M1: 2Q23 | N1: 3Q23 | O1: 4Q23 | P1: 2023 | Q1: 1Q24 | R1: 2Q24 | S1: 3Q24 | T1: 4Q24 | U1: 2024 | V1: 1Q25 | W1: 2Q25 | X1: 3Q25 | Y1: 4Q25 | Z1: 2025 | AA1: 1Q26 | AB1: 2Q26 | AC1: 3Q26 | AD1: 4Q26 | AE1: 2026 | AF1: 1Q27 | AG1: 2Q27 | AH1: 3Q27 | AI1: 4Q27 | AJ1: 2027 | AK1: 1Q28 | AL1: 2Q28 | AM1: 3Q28 | AN1: 4Q28 | AO1: 2028
B2: 연결 | D2: fin json(kship_fin.py)
B3: 영흥(연) | C3: UPDATE: 26-10-19 | E3: 1 | F3: 2 | G3: 3 | H3: 4 | I3: 5 | J3: 6 | K3: 7 | L3: 8 | M3: 9 | N3: 10 | O3: 11 | P3: 12 | Q3: 13 | R3: 14 | S3: 15 | T3: 16 | U3: 17 | V3: 18 | W3: 19 | X3: 20 | Y3: 21 | Z3: 22 | AA3: 23 | AB3: 24 | AC3: 25 | AD3: 26 | AE3: 27 | AF3: 28 | AG3: 29 | AH3: 30 | AI3: 31 | AJ3: 32 | AK3: 33 | AL3: 34 | AM3: 35 | AN3: 36 | AO3: 37
B4: Account Code | C4: AccountNAME | E4: 2021.12 | F4: 2021.12A | G4: 2022.03 | H4: 2022.06 | I4: 2022.09 | J4: 2022.12 | K4: 2022.12A | L4: 2023.03 | M4: 2023.06 | N4: 2023.09 | O4: 2023.12 | P4: 2023.12A | Q4: 2024.03 | R4: 2024.06 | S4: 2024.09 | T4: 2024.12 | U4: 2024.12A | V4: 2025.03 | W4: 2025.06 | X4: 2025.09 | Y4: 2025.12 | Z4: 2025.12A | AA4: 2026.03 | AB4: 2026.06 | AC4: 2026.09 | AD4: 2026.12 | AE4: 2026.12A | AF4: 2027.03 | AG4: 2027.06 | AH4: 2027.09 | AI4: 2027.12 | AJ4: 2027.12A | AK4: 2028.03 | AL4: 2028.06 | AM4: 2028.09 | AN4: 2028.12 | AO4: 2028.12A
A5: 1 | C5: 유동자산 | E5: 242197.5 | F5: 242197.5 | G5: 257229.62 | H5: 283835.52 | I5: 266355.06 | J5: 273435.84 | K5: 273435.84 | L5: 267898.7 | M5: 267020.11 | N5: 258764.33 | O5: 262428.63 | P5: 262428.63 | Q5: 282515.78 | R5: 273846.39 | S5: 264994.74 | T5: 243785.08 | U5: 243785.08 | V5: 222758.63 | W5: 245765.39 | X5: 232796.09 | Y5: 250698.06 | Z5: 250698.06 | AA5: 244058.04 | AB5: 243711.53
A6: 1 | C6: 현금및현금성자산 | E6: 12141.94 | F6: 12141.94 | G6: 14196.15 | H6: 20665.07 | I6: 11166.26 | J6: 17308.1 | K6: 17308.1 | L6: 7896 | M6: 12652.42 | N6: 11742.51 | O6: 10693.65 | P6: 10693.65 | Q6: 10977.25 | R6: 8498.27 | S6: 8719.82 | T6: 9952.2 | U6: 9952.2 | V6: 12303.56 | W6: 14386.45 | X6: 11199.33 | Y6: 10981.3 | Z6: 10981.3 | AA6: 8450.55 | AB6: 6889.74
A7: 1 | C7: 매출채권및기타채권 | E7: 103115.2 | F7: 103115.2 | G7: 114459.5 | H7: 118090.8 | I7: 120367.12 | J7: 120372.16 | K7: 120372.16 | L7: 115048.36 | M7: 115923.64 | N7: 113183.25 | O7: 107004.35 | P7: 107004.35 | Q7: 4652.7 | R7: 2720.48 | S7: 98834.18 | T7: 105472.57 | U7: 105472.57 | V7: 104755.85 | W7: 96159.93 | X7: 92355.54 | Y7: 82699.79 | Z7: 82699.79 | AA7: 82708.05 | AB7: 85802.93
A8: 1 | C8: 재고자산 | E8: 123761.31 | F8: 123761.31 | G8: 123535.65 | H8: 140504.73 | I8: 129123.3 | J8: 129965.2 | K8: 129965.2 | L8: 141182.67 | M8: 132090.21 | N8: 127148.85 | O8: 120658.04 | P8: 120658.04 | Q8: 130520.75 | R8: 132701.91 | S8: 126953.67 | T8: 111144.98 | U8: 111144.98 | V8: 92656.48 | W8: 87833.4 | X8: 80213.52 | Y8: 84349.72 | Z8: 84349.72 | AA8: 84020.84 | AB8: 84189.36
A9: 1 | C9: 당기법인세자산(선급법인세) | E9: 54.69 | F9: 54.69 | G9: 75.29 | H9: 37.79 | I9: 71.44 | J9: 180.72 | K9: 180.72 | L9: 180.82 | M9: 11.39 | N9: 13.04 | O9: 13.05 | P9: 13.05 | Q9: 25.48 | R9: 10.2 | S9: 65.89 | T9: 0 | U9: 0 | V9: 23.54 | W9: 46.86 | X9: 89.73 | Y9: 128.81 | Z9: 128.81 | AA9: 62.71 | AB9: 106.1
A10: 1 | C10: 기타유동자산 | E10: 3124.35 | F10: 3124.35 | G10: 4963.03 | H10: 4537.13 | I10: 3000.04 | J10: 2523.38 | K10: 2523.38 | L10: 3496.34 | M10: 2123.46 | N10: 2460.4 | O10: 1636.69 | P10: 1636.69 | Q10: 2662.46 | R10: 1805.61 | S10: 2165.68 | T10: 2468.44 | U10: 2468.44 | V10: 2263.09 | W10: 2084.75 | X10: 3683.96 | Y10: 4685.06 | Z10: 4685.06 | AA10: 9229.79 | AB10: 9313.92
A11: 1 | C11: 비유동자산 | E11: 276763.56 | F11: 276763.56 | G11: 274207.76 | H11: 274008.22 | I11: 269826.5 | J11: 262248.66 | K11: 262248.66 | L11: 260318.99 | M11: 255499.34 | N11: 255463.62 | O11: 281674.2 | P11: 281674.2 | Q11: 279624.19 | R11: 282181.74 | S11: 271154.45 | T11: 269611.03 | U11: 269611.03 | V11: 266348.32 | W11: 203522.89 | X11: 197868.21 | Y11: 149129.23 | Z11: 149129.23 | AA11: 145564.36 | AB11: 146793.08
A12: 1 | C12: 장기금융자산 | E12: 2500.98 | F12: 2500.98 | G12: 2141.85 | H12: 2719.21 | I12: 2169.34 | J12: 1236.1 | K12: 1236.1 | L12: 1149.53 | M12: 1296.68 | N12: 921.19 | O12: 1634.75 | P12: 1634.75 | Q12: 492.46 | R12: 728.25 | S12: 700.17 | T12: 600.15 | U12: 600.15 | V12: -146.2 | W12: 126.22 | X12: 29.65 | Y12: 39.45 | Z12: 39.45 | AA12: 1791.31 | AB12: 2526.32
A13: 1 | C13: 투자자산 | E13: 2707.66 | F13: 2707.66 | G13: 3730.69 | H13: 4814.13 | I13: 5185.22 | J13: 4191.95 | K13: 4191.95 | L13: 4154.73 | M13: 4156.28 | N13: 3744.84 | O13: 4290.52 | P13: 4290.52 | Q13: 3089.78 | R13: 3094.69 | S13: 3164.65 | T13: 2944.87 | U13: 2944.87 | V13: 2263.43 | W13: 2149.89 | X13: 1961.35 | Y13: 1870.66 | Z13: 1870.66 | AA13: 3706.53 | AB13: 4434.8
A14: 1 | C14: 장기매출채권및기타채권 | E14: 383.55 | F14: 383.55 | G14: 363.6 | H14: 343.65 | I14: 323.7 | J14: 303.75 | K14: 303.75 | L14: 283.8 | M14: 90.86 | N14: 59.85 | O14: 39.9 | P14: 39.9 | Q14: 19.95 | Y14: 1921.1 | Z14: 1921.1 | AB14: 2475.96
A15: 1 | C15: 종속기업및관계기업투자 | E15: 206.68 | F15: 206.68 | G15: 1588.84 | H15: 2094.92 | I15: 3015.88 | J15: 2955.85 | K15: 2955.85 | L15: 3005.2 | M15: 2859.6 | N15: 2823.65 | O15: 2655.77 | P15: 2655.77 | Q15: 2597.32 | R15: 2366.44 | S15: 2464.48 | T15: 2344.72 | U15: 2344.72 | V15: 2409.63 | W15: 2023.67 | X15: 1931.7 | Y15: 1831.21 | Z15: 1831.21 | AA15: 1915.22 | AB15: 1908.48
A16: 1 | C16: 유형자산 | E16: 239919.05 | F16: 239919.05 | G16: 237492.95 | H16: 235698.71 | I16: 234487.91 | J16: 230616.32 | K16: 230616.32 | L16: 229419.69 | M16: 227530.58 | N16: 228349.07 | O16: 258636.99 | P16: 258636.99 | Q16: 257152.14 | R16: 256891.35 | S16: 245788.81 | T16: 240474.8 | U16: 240474.8 | V16: 239800.62 | W16: 177882.57 | X16: 173162.02 | Y16: 125591.32 | Z16: 125591.32 | AA16: 123375.54 | AB16: 123100.04
A17: 1 | C17: 투자부동산 | E17: 2640.39 | F17: 2640.39 | G17: 2634.61 | H17: 2628.82 | M17: 1612.98 | N17: 1652.3
A18: 1 | C18: 사용권자산 | E18: 4897.58 | F18: 4897.58 | G18: 4703.51 | H18: 5220.52 | I18: 5336.87 | J18: 4896.03 | K18: 4896.03 | L18: 4965.52 | M18: 1459.7 | N18: 1585.21 | O18: 1528.34 | P18: 1528.34 | Q18: 2160.77 | R18: 1943.9 | S18: 1830.58 | T18: 1349.11 | U18: 1349.11 | V18: 1336.42 | W18: 2079.97 | X18: 2005.94 | Y18: 2087.38 | Z18: 2087.38 | AA18: 1060.61 | AB18: 1147.31
A19: 1 | C19: 기타비유동자산 | E19: 4945.13 | F19: 4945.13 | G19: 4748.53 | H19: 5277.71 | I19: 5398.36 | J19: 7663.76 | K19: 7663.76 | L19: 7525.57 | M19: 3855.9 | N19: 3967.18 | O19: 1773.81 | P19: 1773.81 | Q19: 2212.57 | R19: 1991.1 | S19: 1875.46 | T19: 1349.11 | U19: 1349.11 | V19: 1336.42 | W19: 2079.97 | X19: 2005.94 | Y19: 2099.36 | Z19: 2099.36 | AA19: 1072.59 | AB19: 1147.31
A20: 1 | C20: 무형자산 | E20: 19680.43 | F20: 19680.43 | G20: 19093.78 | H20: 18525.95 | I20: 17980.26 | J20: 17311.7 | K20: 17311.7 | L20: 16735.01 | M20: 16134.7 | N20: 15533.31 | O20: 14666.31 | P20: 14666.31 | Q20: 14082.01 | R20: 16645.74 | S20: 16551.91 | T20: 12662.67 | U20: 12662.67 | V20: 11722.73 | W20: 11352.87 | X20: 10911.51 | Y20: 10541.89 | Z20: 10541.89 | AA20: 10150.24 | AB20: 10143.76
A21: 1 | C21: 이연법인세자산 | E21: 1550.54 | F21: 1550.54 | G21: 1550.54 | H21: 1930.54 | I21: 1936.88 | J21: 26.46 | K21: 26.46 | L21: 27.22 | M21: 27.41 | N21: 28.07 | O21: 22.18 | P21: 22.18 | Q21: 809.66 | R21: 983.74 | S21: 1143.55 | T21: 6029.07 | U21: 6029.07 | V21: 5454.87 | W21: 5409.69 | X21: 4962.87 | Y21: 5559.29 | Z21: 5559.29 | AA21: 5273.01 | AB21: 5491.2
A22: 1 | C22: 자산총계 | E22: 518961.06 | F22: 518961.06 | G22: 531437.39 | H22: 557843.74 | I22: 536181.56 | J22: 535684.5 | K22: 535684.5 | L22: 528217.69 | M22: 522519.45 | N22: 514227.95 | O22: 544102.83 | P22: 544102.83 | Q22: 562139.97 | R22: 556028.14 | S22: 536149.2 | T22: 513396.1 | U22: 513396.1 | V22: 489106.95 | W22: 449288.28 | X22: 430664.3 | Y22: 399827.28 | Z22: 399827.28 | AA22: 389622.4 | AB22: 390504.61
A23: 1 | C23: 유동부채 | E23: 227367.77 | F23: 227367.77 | G23: 234813.89 | H23: 267634.17 | I23: 247355.69 | J23: 258920.5 | K23: 258920.5 | L23: 258290.3 | M23: 267833.21 | N23: 262558.71 | O23: 250149.72 | P23: 250149.72 | Q23: 272901.88 | R23: 267104.06 | S23: 252114.67 | T23: 239390.59 | U23: 239390.59 | V23: 217873.28 | W23: 218537.12 | X23: 213078.4 | Y23: 199657.31 | Z23: 199657.31 | AA23: 191560.33 | AB23: 184929.31
A24: 1 | C24: 매입채무및기타채무 | E24: 69523.35 | F24: 69523.35 | G24: 75572.47 | H24: 74602.98 | I24: 61280.35 | J24: 63763.3 | K24: 63763.3 | L24: 74497.36 | M24: 71402.85 | N24: 72070.14 | O24: 68812.44 | P24: 68812.44 | Q24: 79723.95 | R24: 79941.61 | S24: 69233.21 | T24: 68145.15 | U24: 68145.15 | V24: 59402.17 | W24: 67871.6 | X24: 64564.06 | Y24: 60123.73 | Z24: 60123.73 | AA24: 60397.11 | AB24: 68704.56
A25: 1 | C25: 단기차입금 | E25: 128047.99 | F25: 128047.99 | G25: 129056.26 | H25: 147198.76 | I25: 149378.34 | J25: 160834.85 | K25: 160834.85 | L25: 152352.87 | M25: 148524.7 | N25: 152031.34 | O25: 139635.63 | P25: 139635.63 | Q25: 146250.37 | R25: 144594.32 | S25: 142311.23 | T25: 143242.68 | U25: 143242.68 | V25: 144739.88 | W25: 118033.41 | X25: 115935.86 | Y25: 96735.11 | Z25: 96735.11 | AA25: 106190 | AB25: 97273.93
A26: 1 | C26: 유동성장기부채 | E26: 24055.28 | F26: 24055.28 | G26: 24609.3 | H26: 38684.7 | I26: 29953.32 | J26: 27062.47 | K26: 27062.47 | L26: 25903.52 | M26: 40868.81 | N26: 32462.14 | O26: 34106.92 | P26: 34106.92 | Q26: 43891.77 | R26: 37711.63 | S26: 35843.8 | T26: 19730.81 | U26: 19730.81 | V26: 10572.6 | W26: 16000 | X26: 16000 | Y26: 26484.18 | Z26: 26484.18 | AA26: 16000
A27: 1 | C27: 단기파생상품부채 | E27: 2188.07 | F27: 2188.07 | G27: 2575.9 | H27: 3155.03 | I27: 3352.05 | J27: 4151.77 | K27: 4151.77 | L27: 3509.91 | M27: 2703.54 | N27: 1638.14 | O27: 1479.47 | P27: 1479.47 | Q27: 1285.4 | R27: 889.57 | S27: 711.8 | T27: 999.33 | U27: 999.33 | V27: 69.71
A28: 1 | C28: 단기금융부채 | E28: 2831.8 | F28: 2831.8 | G28: 3121.86 | H28: 3681.33 | I28: 3821.52 | J28: 4705.52 | K28: 4705.52 | L28: 4095.61 | M28: 3171.72 | N28: 2067.68 | O28: 1934.94 | P28: 1934.94 | Q28: 1886.17 | R28: 1342.1 | S28: 1209.34 | T28: 1566.53 | U28: 1566.53 | V28: 672.03 | W28: 729.55 | X28: 712.37 | Y28: 860.43 | Z28: 860.43 | AA28: 578.22 | AB28: 629.17
A29: 1 | C29: 유동리스부채 | E29: 643.73 | F29: 643.73 | G29: 545.96 | H29: 526.3 | I29: 469.47 | J29: 553.75 | K29: 553.75 | L29: 585.7 | M29: 468.18 | N29: 429.54 | O29: 455.47 | P29: 455.47 | Q29: 600.77 | R29: 452.53 | S29: 497.54 | T29: 567.2 | U29: 567.2 | V29: 602.32 | W29: 729.55 | X29: 712.37 | Y29: 860.43 | Z29: 860.43 | AA29: 578.22 | AB29: 629.17
A30: 1 | C30: 리스부채 | E30: 1183.41 | F30: 1183.41 | G30: 986.04 | H30: 1208.14 | I30: 1078.99 | J30: 1148.65 | K30: 1148.65 | L30: 1161.74 | M30: 844.82 | N30: 994.54 | O30: 982.66 | P30: 982.66 | Q30: 1629.48 | R30: 1266.65 | S30: 1183.79 | T30: 1218.7 | U30: 1218.7 | V30: 1216.17 | W30: 1838.53 | X30: 1821.37 | Y30: 1931.05 | Z30: 1931.05 | AA30: 1024.27 | AB30: 1018.65
A31: 1 | C31: 단기충당부채 | E31: 424.66 | F31: 424.66 | G31: 346.21 | H31: 474.72 | I31: 448.26 | J31: 315.29 | K31: 315.29 | L31: 284.49 | M31: 366.45 | N31: 316.34 | O31: 408.27 | P31: 408.27 | Q31: 415.33 | R31: 428.57 | S31: 426.15 | T31: 383.37 | U31: 383.37 | V31: 377.41 | W31: 401.32 | X31: 409.98 | Y31: 397.68 | Z31: 397.68 | AA31: 409.42 | AB31: 434.33
A32: 1 | C32: 당기법인세부채(미지급법인세) | E32: 1190.17 | F32: 1190.17 | G32: 1084.6 | H32: 1082.67 | I32: 783.07 | J32: 648.12 | K32: 648.12 | L32: 433.92 | M32: 4.74 | N32: 4.85 | O32: 4.67 | P32: 4.67 | R32: 824.05 | S32: 156.2 | T32: 392.84 | U32: 392.84 | V32: 188.53 | W32: 0.9 | X32: 1.13 | Y32: 25.46 | Z32: 25.46 | AA32: 24.48 | AB32: 0.31
A33: 1 | C33: 기타유동부채 | E33: 1294.52 | F33: 1294.52 | G33: 1023.19 | H33: 1909.02 | I33: 1690.84 | J33: 1590.94 | K33: 1590.94 | L33: 722.52 | M33: 2994.8 | N33: 3517.63 | O33: 4220.43 | P33: 4220.43 | Q33: 386.87 | R33: 1780.18 | S33: 1867.79 | T33: 5037.37 | U33: 5037.37 | V33: 1625.44 | W33: 15295.68 | X33: 15397.7 | Y33: 15025.92 | Z33: 15025.92 | AA33: 7814.56 | AB33: 9778.52
A34: 1 | C34: 비유동부채 | E34: 93667.56 | F34: 93667.56 | G34: 99885.5 | H34: 87206.58 | I34: 83941.14 | J34: 78607.7 | K34: 78607.7 | L34: 75569.69 | M34: 64616.2 | N34: 61901.4 | O34: 64081.94 | P34: 64081.94 | Q34: 58739.31 | R34: 56521.96 | S34: 55881 | T34: 57168.43 | U34: 57168.43 | V34: 54885.02 | W34: 39445.14 | X34: 43996.47 | Y34: 35839.12 | Z34: 35839.12 | AA34: 34218.16 | AB34: 40470.48
A35: 1 | C35: 장기매입채무및기타채무 | E35: 1207.4 | F35: 1207.4 | G35: 1207.4 | H35: 1329.12 | I35: 1389.98 | J35: 1505.18 | K35: 1505.18 | L35: 1464.32 | O35: 1334.13 | P35: 1334.13 | Q35: 1327.16 | R35: 1709.54 | S35: 1764.28 | T35: 2114.96 | U35: 2114.96 | V35: 1981.33 | W35: 2190.52 | X35: 2262.04 | Y35: 2817.46 | Z35: 2817.46 | AA35: 2666.29 | AB35: 2583.03
A36: 1 | C36: 장기차입금 | E36: 40847.07 | F36: 40847.07 | G36: 38884.67 | H36: 34813.41 | I36: 31619.57 | J36: 29722.01 | K36: 29722.01 | L36: 26847.65 | M36: 35700.62 | N36: 28203.59 | O36: 25039.89 | P36: 25039.89 | Q36: 17992.86 | R36: 10071.17 | S36: 8200.36 | T36: 7416.94 | U36: 7416.94 | V36: 5268.97 | W36: 3160.82 | X36: 2494.73 | Y36: 2042.92 | Z36: 2042.92 | AA36: 1568.71 | AB36: 1399.23
A37: 1 | C37: 사채 | E37: 29296.23 | F37: 29296.23 | G37: 35716.05 | H37: 30000 | I37: 30000 | J37: 30000 | K37: 30000 | L37: 30000 | M37: 10000 | O37: 10000 | P37: 10000 | Q37: 10000 | R37: 16000 | S37: 16000 | T37: 16000 | U37: 16000 | V37: 16000 | W37: 8000 | X37: 8000 | Y37: 10594.46 | Z37: 10594.46 | AA37: 10184.36 | AB37: 16681.56
A38: 1 | C38: 장기파생상품부채 | E38: 1927.74 | F38: 1927.74 | G38: 3940.54 | Y38: 2091.1 | Z38: 2091.1 | AA38: 1760.05 | AB38: 1985.46
A39: 1 | C39: 장기금융부채 | E39: 2467.42 | F39: 2467.42 | G39: 4380.62 | H39: 681.84 | I39: 609.52 | J39: 594.9 | K39: 594.9 | L39: 576.04 | M39: 376.64 | N39: 565 | O39: 527.19 | P39: 527.19 | Q39: 1028.71 | R39: 814.12 | S39: 686.25 | T39: 651.5 | U39: 651.5 | V39: 613.85 | W39: 1108.98 | X39: 1109 | Y39: 3161.72 | Z39: 3161.72 | AA39: 2206.1 | AB39: 2374.94
A40: 1 | C40: 비유동리스부채 | E40: 539.68 | F40: 539.68 | G40: 440.08 | H40: 681.84 | I40: 609.52 | J40: 594.9 | K40: 594.9 | L40: 576.04 | M40: 376.64 | N40: 565 | O40: 527.19 | P40: 527.19 | Q40: 1028.71 | R40: 814.12 | S40: 686.25 | T40: 651.5 | U40: 651.5 | V40: 613.85 | W40: 1108.98 | X40: 1109 | Y40: 1070.62 | Z40: 1070.62 | AA40: 446.05 | AB40: 389.48
A41: 1 | C41: 확정급여부채 | E41: 6523.25 | F41: 6523.25 | G41: 7047.83 | H41: 7607.14 | I41: 7892.69 | J41: 5165.28 | K41: 5165.28 | L41: 5179.48 | M41: 4948.89 | N41: 5146.41 | O41: 5863.45 | P41: 5863.45 | Q41: 6367.1 | R41: 6962.3 | S41: 7706.65 | T41: 9427.28 | U41: 9427.28 | V41: 9537.12 | W41: 9608.67 | X41: 8794.92 | Y41: 7894.87 | Z41: 7894.87 | AA41: 8259.38 | AB41: 8944.84
A42: 1 | C42: 이연법인세부채 | E42: 13326.19 | F42: 13326.19 | G42: 12648.92 | H42: 12775.08 | I42: 12429.39 | J42: 11620.34 | K42: 11620.34 | L42: 11502.21 | M42: 12054.79 | N42: 11954.55 | O42: 21317.29 | P42: 21317.29 | Q42: 22023.49 | R42: 20964.84 | S42: 21523.47 | T42: 21557.75 | U42: 21557.75 | V42: 21483.76 | W42: 15376.15 | X42: 21335.78 | Y42: 9327.68 | Z42: 9327.68 | AA42: 9333.32 | AB42: 8486.89
A43: 1 | C43: 부채총계 | E43: 321035.33 | F43: 321035.33 | G43: 334699.39 | H43: 354840.75 | I43: 331296.83 | J43: 337528.2 | K43: 337528.2 | L43: 333859.99 | M43: 332449.41 | N43: 324460.11 | O43: 314231.67 | P43: 314231.67 | Q43: 331641.19 | R43: 323626.02 | S43: 307995.67 | T43: 296559.02 | U43: 296559.02 | V43: 272758.3 | W43: 257982.26 | X43: 257074.87 | Y43: 235496.43 | Z43: 235496.43 | AA43: 225778.49 | AB43: 225399.79
A44: 1 | C44: 지배주주지분 | E44: 165883.99 | F44: 165883.99 | G44: 168075.23 | H44: 172630.95 | I44: 174078.82 | J44: 170709.67 | K44: 170709.67 | L44: 169618.83 | M44: 167823.36 | N44: 157866.81 | O44: 194622.28 | P44: 194622.28 | Q44: 196002.83 | R44: 195297.16 | S44: 192131.85 | T44: 186050.32 | U44: 186050.32 | V44: 186022.66 | W44: 161286.6 | X44: 143803.29 | Y44: 135773.77 | Z44: 135773.77 | AA44: 136005.2 | AB44: 137079.04
A45: 1 | C45: 자본금 | E45: 50655.19 | F45: 50655.19 | G45: 50655.19 | H45: 50655.19 | I45: 50655.19 | J45: 50655.19 | K45: 50655.19 | L45: 50655.19 | M45: 50655.19 | N45: 50655.19 | O45: 50655.19 | P45: 50655.19 | Q45: 50655.19 | R45: 50655.19 | S45: 50655.19 | T45: 50655.19 | U45: 50655.19 | V45: 50655.19 | W45: 50655.19 | X45: 50655.19 | Y45: 50655.19 | Z45: 50655.19 | AA45: 50655.19 | AB45: 39051.76
A46: 1 | C46: 자본잉여금 | E46: 94821.45 | F46: 94821.45 | G46: 94821.45 | H46: 94821.45 | I46: 94821.45 | J46: 94821.45 | K46: 94821.45 | L46: 94821.45 | M46: 94821.45 | N46: 94821.45 | O46: 94821.45 | P46: 94821.45 | Q46: 94821.45 | R46: 94821.45 | S46: 94821.45 | T46: 94821.45 | U46: 94821.45 | V46: 94821.45 | W46: 94821.45 | X46: 94821.45 | Y46: 94821.45 | Z46: 94821.45 | AA46: 94821.45 | AB46: 94821.45
A47: 1 | C47: 기타자본 | E47: -77423.44 | F47: -77423.44 | G47: -74723.81 | H47: -74723.81 | I47: -74723.81 | J47: -74729.72 | K47: -74729.72 | L47: -74729.72 | M47: -74501.11 | N47: -83426.32 | O47: -87597 | P47: -87597 | Q47: -87522.51 | R47: -88575.44 | S47: -88575.44 | T47: -84643.55 | U47: -84643.55 | V47: -84643.55 | W47: -84643.55 | X47: -84947.26 | Y47: -83592.16 | Z47: -83592.16 | AA47: -82661.51 | AB47: -70019.77
A48: 1 | C48: 기타포괄이익누계액 | E48: 1454.45 | F48: 1454.45 | G48: 1353.14 | H48: 2063.54 | I48: 2740.85 | J48: 1257.95 | K48: 1257.95 | L48: 1631.35 | M48: 1662.76 | N48: 1391.88 | O48: 45822.47 | P48: 45822.47 | Q48: 44720.79 | R48: 44972.59 | S48: 44959.2 | T48: 41978.19 | U48: 41978.19 | V48: 40897.29 | W48: 40857.34 | X48: 40816.92 | Y48: 42005.92 | Z48: 42005.92 | AA48: 40893.68 | AB48: 41195.83
A49: 1 | C49: 이익잉여금 | E49: 96376.35 | F49: 96376.35 | G49: 95969.26 | H49: 99814.59 | I49: 100585.13 | J49: 98704.81 | K49: 98704.81 | L49: 97240.57 | M49: 95185.07 | N49: 94424.62 | O49: 90920.18 | P49: 90920.18 | Q49: 93327.91 | R49: 93423.37 | S49: 90271.46 | T49: 83239.04 | U49: 83239.04 | V49: 84292.28 | W49: 59596.16 | X49: 42457 | Y49: 31883.37 | Z49: 31883.37 | AA49: 32296.4 | AB49: 32029.77
A50: 1 | C50: 비지배주주지분 | E50: 32041.73 | F50: 32041.73 | G50: 28662.77 | H50: 30372.03 | I50: 30805.91 | J50: 27446.62 | K50: 27446.62 | L50: 24738.86 | M50: 22246.68 | N50: 31901.02 | O50: 35248.88 | P50: 35248.88 | Q50: 34495.95 | R50: 37104.96 | S50: 36021.68 | T50: 30786.76 | U50: 30786.76 | V50: 30325.99 | W50: 30019.42 | X50: 29786.14 | Y50: 28557.09 | Z50: 28557.09 | AA50: 27838.7 | AB50: 28025.78
... A55: 1 | C55: 이자발생자산 | E55: 14642.92 | F55: 14642.92 | G55: 16338 | H55: 23384.28 | I55: 13335.6 | J55: 19003.59 | K55: 19003.59 | L55: 9140.04 | M55: 14011.75 | N55: 12773.77 | O55: 12367.84 | P55: 12367.84 | Q55: 11493.05 | R55: 9227.91 | S55: 9419.99 | T55: 10552.35 | U55: 10552.35 | V55: 12157.36 | W55: 14512.67 | X55: 11228.98 | Y55: 11020.75 | Z55: 11020.75 | AA55: 10241.86 | AB55: 9416.06
A56: 1 | C56: 매각예정비유동자산및처분자산 | I56: 2626.9 | J56: 2626.9 | K56: 2626.9 | M56: 4156.36 | N56: 4106.21 | O56: 22383.41 | P56: 22383.41 | Q56: 17434.8 | R56: 17434.8 | S56: 27878.69 | T56: 14698.12 | U56: 14698.12 | V56: 10756.11 | W56: 45254.01 | X56: 45254.01 | Y56: 67853.37 | Z56: 67853.37 | AA56: 57409.48 | AB56: 57409.48
A57: 1 | C57: 유동파생상품자산 | J57: 459.39 | K57: 459.39 | L57: 94.51 | M57: 62.65 | N57: 110.07 | O57: 39.44 | P57: 39.44 | Q57: 23.34 | R57: 1.39 | S57: 0
A58: 1 | C58: 단기금융자산 | J58: 459.39 | K58: 459.39 | L58: 94.51 | M58: 62.65 | N58: 110.07 | O58: 39.44 | P58: 39.44 | Q58: 23.34 | R58: 1.39 | S58: 0
A59: 1 | C59: 계약부채 | M59: 499.15 | N59: 88.59 | O59: 1023.79 | P59: 1023.79 | Q59: 281.53 | R59: 435.1 | S59: 1043.4 | T59: 880.67 | U59: 880.67 | V59: 204.88 | W59: 147.7 | X59: 25.92 | Y59: 0.81 | Z59: 0.81 | AA59: 35.06 | AB59: 101.36
A60: 1 | C60: 단기금융부채(face) | M60: 148524.7 | N60: 152031.34 | O60: 139635.63 | P60: 139635.63 | T60: 143242.68 | U60: 143242.68 | AB60: 97273.93
A61: 1 | C61: 장기금융부채(face) | M61: 35700.62 | N61: 28203.59 | O61: 25039.89 | P61: 25039.89 | Q61: 17992.86 | R61: 10071.17 | S61: 8200.36 | T61: 7416.94 | U61: 7416.94
A62: 1 | C62: 기타비유동부채 | N62: 14672.2
A63: 1 | C63: 기타유동금융자산 | R63: 417.74 | S63: 376.81 | T63: 48.77 | U63: 48.77
A64: 1 | C64: 단기사채 | AB64: 8000
A65: 1 | C65: 매출액(수익) | E65: 96057.87 | G65: 114580.42 | H65: 120824.3 | I65: 167721.9 | J65: 124242.11 | K65: 527368.73 | L65: 123171.79 | M65: 132706.49 | N65: 133880.09 | O65: 110252.18 | P65: 500010.55 | Q65: 125035.04 | R65: 126960.72 | S65: 119001.99 | T65: 109350.58 | U65: 480348.33 | V65: 110984.99 | W65: 116282.15 | X65: 109895.49 | Y65: 96321.93 | Z65: 433484.56 | AA65: 96425.16 | AB65: 106766.84
A66: 1 | C66: 매출원가 | E66: 81266.72 | G66: 102663.81 | H66: 108864.47 | I66: 156061.28 | J66: 116590.29 | K66: 484179.85 | L66: 117210.77 | M66: 121415.31 | N66: 124451.39 | O66: 101875.19 | P66: 464952.66 | Q66: 112834.99 | R66: 115295.13 | S66: 111376.23 | T66: 103992.88 | U66: 443499.23 | V66: 104669.82 | W66: 110836.26 | X66: 108520.05 | Y66: 84029.44 | Z66: 408055.57 | AA66: 90049.51 | AB66: 97531.59
A67: 1 | C67: 매출총이익 | E67: 14791.15 | G67: 11916.62 | H67: 11959.83 | I67: 11660.62 | J67: 7651.82 | K67: 43188.89 | L67: 5961.02 | M67: 11291.18 | N67: 9428.71 | O67: 8376.99 | P67: 35057.9 | Q67: 12200.06 | R67: 11665.59 | S67: 7625.75 | T67: 5357.7 | U67: 36849.1 | V67: 6315.17 | W67: 5445.88 | X67: 1375.44 | Y67: 12292.49 | Z67: 25428.98 | AA67: 6375.65 | AB67: 9235.25
A68: 1 | C68: 판관비 | E68: 11180.27 | G68: 10176.78 | H68: 9919.78 | I68: 9952.71 | J68: 8912.64 | K68: 38961.91 | L68: 8781.51 | M68: 8933.89 | N68: 6884.13 | O68: 9205.9 | P68: 33805.43 | Q68: 8328.17 | R68: 8921.49 | S68: 8747 | T68: 7779.79 | U68: 33776.45 | V68: 7895.72 | W68: 7829.58 | X68: 8341.64 | Y68: 14530.64 | Z68: 38597.58 | AA68: 7814.78 | AB68: 7061.41
A69: 1 | C69: 영업이익 | E69: 3610.88 | G69: 1739.84 | H69: 2040.05 | I69: 1707.91 | J69: -1260.82 | K69: 4226.98 | L69: -2820.49 | M69: 2357.29 | N69: 2544.58 | O69: -828.91 | P69: 1252.47 | Q69: 3871.89 | R69: 2744.1 | S69: -1121.25 | T69: -2422.09 | U69: 3072.65 | V69: -1580.55 | W69: -2383.7 | X69: -6966.2 | Y69: -2238.15 | Z69: -13168.6 | AA69: -1439.13 | AB69: 2173.84
A70: 1 | C70: 금융수익 | E70: 1308.08 | G70: 933.37 | H70: 5271.66 | I70: 4688.71 | J70: 2284.43 | K70: 13178.17 | L70: 2065.51 | M70: 1600.61 | N70: 2573.19 | O70: 1016.08 | P70: 7255.39 | Q70: 1590.99 | R70: 1450.06 | S70: 412.14 | T70: 1731.52 | U70: 5184.71 | V70: 1160.12 | W70: 421.25 | X70: 622.52 | Y70: 1416.49 | Z70: 3620.38 | AA70: 812.59 | AB70: 314.11
A71: 1 | C71: 금융비용 | E71: 2298 | G71: 4398.4 | H71: 2978.31 | I71: 5354.61 | J71: 8151.35 | K71: 20882.67 | L71: 5069.6 | M71: 5354.28 | N71: 5231.55 | O71: 4261.11 | P71: 19916.54 | Q71: 4180.28 | R71: 4647.34 | S71: 3993.5 | T71: 2987.75 | U71: 15808.87 | V71: 3038.57 | W71: 3666.21 | X71: 1693.13 | Y71: 2452.25 | Z71: 10850.16 | AA71: 2248.64 | AB71: 2221.45
A72: 1 | C72: 기타영업외수익 | E72: -4195.51 | G72: 616.24 | H72: 1456.97 | I72: 373.34 | J72: 256.14 | K72: 2702.69 | L72: 2342.9 | M72: 397.74 | N72: 325.44 | O72: 3399.75 | P72: 6465.83 | Q72: 1720.09 | R72: 517.81 | S72: 135.7 | T72: -296.61 | U72: 2076.99 | V72: 5952.67 | W72: 206.21 | X72: 563.96 | Y72: 173.29 | Z72: 6896.13 | AA72: 1607.88 | AB72: 69.46
A73: 1 | C73: 기타영업외비용 | E73: 88.46 | G73: 94.72 | H73: 125.36 | I73: 193.57 | J73: 1500.56 | K73: 1914.21 | L73: 280.2 | M73: 636.27 | N73: 177.78 | O73: 3224.44 | P73: 4318.69 | Q73: 280.34 | R73: 284.68 | S73: 291.62 | T73: 9563.82 | U73: 10420.46 | V73: 1071.16 | W73: 25512.18 | X73: 3594.59 | Y73: 22732.58 | Z73: 52910.51 | AA73: 117.12 | AB73: 61.67
A74: 1 | C74: 법인세비용차감전계속사업이익 | E74: -1595.5 | G74: -1192.33 | H74: 6135.28 | I74: 1113.6 | J74: -8302.06 | K74: -2245.51 | L74: -3772.02 | M74: -1674.17 | N74: -844.1 | O74: -3213.16 | P74: -9503.45 | Q74: 2710.86 | R74: -554.61 | S74: -4879.89 | T74: -13733.36 | U74: -16457 | V74: 1370.42 | W74: -31030 | X74: -11168.25 | Y74: -25889.73 | Z74: -66717.56 | AA74: -1349.53 | AB74: 258.96
A75: 1 | C75: 법인세비용 | E75: -3843.84 | G75: -130.16 | H75: 498.15 | I75: -70.89 | J75: 314.03 | K75: 611.13 | L75: 373.08 | M75: 495.28 | N75: -4.07 | O75: -1871.04 | P75: -1006.75 | Q75: 175.56 | R75: -172.62 | S75: -179.27 | T75: -1792.8 | U75: -1969.13 | V75: 628.81 | W75: -6067.95 | X75: 6465.23 | Y75: -13444.02 | Z75: -12417.93 | AA75: 258.37 | AB75: -0.16
A76: 1 | C76: 계속사업이익 | E76: 2248.34 | G76: -1062.17 | H76: 5637.13 | I76: 1184.49 | J76: -8616.07 | K76: -2856.62 | L76: -4145.1 | M76: -2169.45 | N76: -840.03 | O76: -1342.12 | P76: -8496.7 | Q76: 2535.3 | R76: -381.99 | S76: -4700.62 | T76: -11940.55 | U76: -14487.86 | V76: 741.61 | W76: -24962.05 | X76: -17633.48 | Y76: -12445.72 | Z76: -54299.64 | AA76: -1607.9 | AB76: 259.12
A77: 1 | C77: 중단사업이익 | E77: 3645.97 | T77: -486.19 | V77: -156.22 | Y77: 0
A78: 1 | C78: 당기순이익 | E78: 5894.31 | G78: -1062.17 | H78: 5637.13 | I78: 1184.49 | J78: -8616.07 | K78: -2856.62 | L78: -4145.1 | M78: -2169.45 | N78: -840.03 | O78: -1342.12 | P78: -8496.7 | Q78: 2535.3 | R78: -381.99 | S78: -4700.62 | T78: -12426.74 | U78: -14974.05 | V78: 585.39 | W78: -24962.05 | X78: -17633.48 | Y78: -12445.72 | Z78: -54455.86 | AA78: -1607.9 | AB78: 259.12
A79: 1 | C79: 총포괄손익 | E79: 6742.08 | G79: -1163.73 | H79: 6264.99 | I79: 1881.74 | J79: -7339.45 | K79: -356.45 | L79: -3798.6 | M79: -2208.39 | N79: -1114.56 | O79: 40963.3 | P79: 33841.75 | Q79: -619.94 | R79: -132.75 | S79: -4723.87 | T79: -11576.91 | U79: -17053.47 | V79: -488.43 | W79: -25192.63 | X79: -17691.01 | Y79: -10461.39 | Z79: -53833.46 | AA79: -1417.6 | AB79: 222.6
A80: 1 | C80: (지배주주지분)당기순이익 | E80: 3371.09 | G80: -407.09 | H80: 3900.96 | I80: 784.36 | J80: -4605.78 | K80: -327.55 | L80: -1446.78 | M80: -2029.21 | N80: -750.46 | O80: -2174.99 | P80: -6401.44 | Q80: 2429.59 | R80: 128.28 | S80: -3135.39 | T80: -7237.51 | U80: -7815.03 | V80: 1064.61 | W80: -24672.18 | X80: -17128.65 | Y80: -11593.19 | Z80: -52329.41 | AA80: -893.03 | AB80: 41.03
A81: 1 | C81: (비지배주주지분)당기순이익 | E81: 2523.22 | G81: -655.08 | H81: 1736.16 | I81: 400.13 | J81: -4010.31 | K81: -2529.1 | L81: -2698.32 | M81: -140.25 | N81: -89.57 | O81: 832.86 | P81: -2095.28 | Q81: 105.71 | R81: -510.27 | S81: -1565.23 | T81: -5189.24 | U81: -7159.03 | V81: -479.22 | W81: -289.87 | X81: -504.82 | Y81: -852.53 | Z81: -2126.44 | AA81: -714.88 | AB81: 218.09
A82: 1 | C82: 금융손익 | E82: -989.92 | G82: -3465.03 | H82: 2293.35 | I82: -665.9 | J82: -5866.92 | K82: -7704.5 | L82: -3004.09 | M82: -3753.67 | N82: -2658.36 | O82: -3245.03 | P82: -12661.15 | Q82: -2589.29 | R82: -3197.28 | S82: -3581.36 | T82: -1256.23 | U82: -10624.16 | V82: -1878.45 | W82: -3244.96 | X82: -1070.61 | Y82: -1035.76 | Z82: -7229.78 | AA82: -1436.05 | AB82: -1907.34
A83: 1 | C83: 기타영업외손익 | E83: -4283.97 | G83: 521.52 | H83: 1331.61 | I83: 179.77 | J83: -1244.42 | K83: 788.48 | L83: 2062.7 | M83: -238.53 | N83: 147.66 | O83: 175.31 | P83: 2147.14 | Q83: 1439.75 | R83: 233.13 | S83: -155.92 | T83: -9860.43 | U83: -8343.47 | V83: 4881.51 | W83: -25305.97 | X83: -3030.63 | Y83: -22559.29 | Z83: -46014.38 | AA83: 1490.76 | AB83: 7.79
A84: 1 | C84: 종속기업,공동지배기업및관계기업관련손익 | G84: 11.34 | H84: 470.27 | I84: -108.19 | J84: 70.11 | K84: 443.53 | L84: -10.13 | M84: -39.26 | N84: -877.96 | O84: 685.47 | P84: -241.88 | Q84: -11.48 | R84: -334.55 | S84: -21.36 | T84: -194.62 | U84: -562.01 | V84: -52.1 | W84: -95.36 | X84: -100.81 | AA84: 34.89
A85: 1 | C85: 지분법관련손익 | G85: 11.34 | H85: 470.27 | I85: -108.19 | J85: 70.11 | K85: 443.53 | L85: -10.13 | M85: -39.26 | N85: -877.96 | O85: 685.47 | P85: -241.88 | Q85: -11.48 | R85: -334.55 | S85: -21.36 | T85: -194.62 | U85: -562.01 | V85: -52.1 | W85: -95.36 | X85: -100.81 | AA85: 34.89
A86: 1 | C86: 배당금수익 | G86: 42.95 | H86: 0 | I86: 0 | J86: 0 | K86: 42.95 | L86: 52.15 | M86: 0 | N86: 0 | O86: 0 | P86: 52.15 | Q86: 61.35 | R86: 0 | S86: 1.26 | T86: 1.18 | U86: 63.79 | V86: 61.99 | W86: 0 | X86: 0 | Y86: 0 | Z86: 61.99 | AB86: 0
A87: 1 | C87: 외환차익 | G87: 432.87 | H87: 1531.56 | I87: 1642.73 | J87: 2140.29 | K87: 5747.45 | L87: 651.3 | M87: 1093.84 | N87: 1026.61 | O87: 464.46 | P87: 3236.21 | Q87: 571.18 | R87: 1087.33 | S87: 354.54 | T87: 800.15 | U87: 2813.2 | V87: 285.76 | W87: 375.18 | X87: 412.26 | Y87: 688.92 | Z87: 1762.12 | AB87: 323.72
A88: 1 | C88: 외환차손 | G88: 187.73 | H88: 1022.46 | I88: 1238.11 | J88: 1732.72 | K88: 4181.02 | L88: 514.14 | M88: 818.75 | N88: 512.27 | O88: 841.73 | P88: 2686.89 | Q88: 221.96 | R88: 882.37 | S88: 518.33 | T88: 132.8 | U88: 1755.46 | V88: 315.26 | W88: 688.63 | X88: 155.78 | Y88: 208.07 | Z88: 1367.74 | AB88: 141.87
A89: 1 | C89: 외화환산이익 | G89: 385.02 | H89: 825.43 | I89: 1841.97 | J89: -1468.02 | K89: 1584.4 | L89: 883.91 | M89: -292.52 | N89: -74.23 | O89: -100.31 | P89: 416.85 | Q89: 650.44 | R89: 31.24 | S89: -112.2 | T89: 918.64 | U89: 1488.12 | V89: 416.38 | W89: -161.69 | X89: -23.39 | Y89: -105.48 | Z89: 125.82 | AB89: -156.46
A90: 1 | C90: 외화환산손실 | G90: 264.91 | H90: 318.48 | I90: 804.5 | J90: 1066.11 | K90: 2454 | L90: 302.43 | M90: 225.01 | N90: 235.04 | O90: -70.99 | P90: 691.49 | Q90: 478.71 | R90: 5.82 | S90: 72.64 | T90: 243.36 | U90: 800.53 | V90: 109.7 | W90: 507.93 | X90: -397.79 | Y90: 21.01 | Z90: 240.85 | AB90: -16.74
A91: 1 | C91: 파생상품이익 | G91: 25.9 | H91: 1902.67 | I91: 1190.73 | J91: 1500.97 | K91: 4620.27 | L91: 437.67 | M91: 463.23 | N91: 1396.89 | O91: 641.49 | P91: 2939.28 | Q91: 201.92 | R91: 246.73 | S91: 100.96 | T91: -76.05 | U91: 473.56 | V91: 121.45 | W91: 12.67 | X91: 0 | Y91: 0 | Z91: 134.12 | AB91: 0
A92: 1 | C92: 파생상품손실 | G92: 1408.68 | H92: -1147.6 | I92: 0 | J92: 250.09 | K92: 511.17 | L92: 364.88 | M92: 31.86 | N92: 210.71 | O92: 70.63 | P92: 678.08 | Q92: 226.36 | R92: 21.95 | S92: 15.46 | T92: 225.47 | U92: 489.24 | AB92: 225.41
A93: 1 | C93: 이자수익 | AB93: 128.09
A94: 1 | C94: 이자비용 | AB94: 1758.92
A95: 1 | C95: 이자손익 | AB95: -1630.83
A96: 1 | C96: 영업활동으로인한현금흐름 | E96: -2675.54 | G96: -1261.68 | H96: -12165.09 | I96: 2442.21 | J96: 8126.82 | K96: -2857.74 | L96: -6154.45 | M96: 20108.73 | N96: 4404.98 | O96: 6219.3 | P96: 24578.56 | Q96: -5958.74 | R96: 12271.57 | S96: -19295.86 | T96: 32937.13 | U96: 19954.1 | V96: 3827.83 | W96: 37329.48 | X96: -34.48 | Y96: 301.28 | Z96: 41424.11 | AA96: -12125.26 | AB96: 12030.08
A97: 1 | C97: 이자수취(CF) | E97: 58.61 | G97: 40.16 | H97: 51.56 | I97: -40.6 | J97: 11.38 | K97: 62.5 | L97: 32.55 | M97: 35.42 | N97: 181.25 | O97: 36.62 | P97: 285.84 | Q97: 56.29 | R97: 59.99 | S97: 33.57 | T97: 52.66 | U97: 202.51 | V97: 177.65 | W97: 173.26 | X97: 207.26 | Y97: 492.63 | Z97: 1050.8 | AA97: 146.78 | AB97: 127.91
A98: 1 | C98: 이자지급(CF) | E98: -1357.25 | G98: -1437.3 | H98: -1718.35 | I98: -2036.47 | J98: -2608.64 | K98: -7800.76 | L98: -2635.89 | M98: -2892.55 | Q98: -2821.94 | R98: -2758.24 | S98: -2723.2 | T98: -2348.38 | U98: -10651.76 | V98: -3330.05 | W98: -1664.51 | X98: -1811.51 | Y98: -1869.28 | Z98: -8675.35 | AA98: -2587.67 | AB98: -1361.54
A99: 1 | C99: 배당금수취(CF) | E99: 0 | I99: 0 | J99: 0 | N99: 0 | O99: 0 | S99: 1.26 | T99: 1.18 | X99: 0 | Y99: 0
A100: 1 | C100: 법인세납부(CF) | E100: 849.81 | G100: -592.47 | H100: -726.37 | I100: -473.36 | J100: -236.31 | K100: -2028.51 | L100: -674.8 | M100: -219.16 | N100: -94.27 | O100: -6.09 | P100: -994.32 | Q100: -19.37 | R100: -18.24 | S100: -22.22 | T100: -101.78 | U100: -161.61 | V100: -190.33 | W100: -232.45 | X100: -67.31 | Y100: -267.92 | Z100: -758.01 | AA100: 65.48 | AB100: -69.28
A101: 1 | C101: 투자활동으로인한현금흐름 | E101: -3107.19 | G101: -2296.12 | H101: -2837.3 | I101: -2003.77 | J101: -11635.24 | K101: -18772.43 | L101: 11073.44 | M101: -11492.17 | N101: 3988.79 | O101: 11972.66 | P101: 15542.72 | Q101: -274.38 | R101: -2792.85 | S101: -470.05 | T101: 8972.59 | U101: 5435.31 | V101: 9339.05 | W101: -3549.15 | X101: -185.3 | Y101: 2339.99 | Z101: 7944.59 | AA101: 11303.16 | AB101: -2667.8
A102: 1 | C102: 유형자산의증가 | E102: 3301.56 | G102: 1052.3 | H102: 2078.92 | I102: 1764.97 | J102: 2093.24 | K102: 6989.43 | L102: 1667.33 | M102: 2271.25 | N102: 4628.97 | O102: 1719.6 | P102: 10287.15 | Q102: 1107.78 | R102: 2258.07 | S102: 2744.78 | T102: 3008.12 | U102: 9118.75 | V102: 2102.66 | W102: 1136.44 | X102: 2489.89 | Y102: 1573.8 | Z102: 7302.79 | AA102: 395.98 | AB102: 2087.98
A103: 1 | C103: CAPEX | E103: 3301.56 | G103: 1052.3 | H103: 2078.92 | I103: 1764.97 | J103: 2093.24 | K103: 6989.43 | L103: 1667.33 | M103: 2271.25 | N103: 4628.97 | O103: 1719.6 | P103: 10287.15 | Q103: 1107.78 | R103: 2260.21 | S103: 2744.78 | T103: 3009 | U103: 9121.77 | V103: 2102.66 | W103: 1136.44 | X103: 2489.89 | Y103: 1573.8 | Z103: 7302.79 | AA103: 395.98 | AB103: 2087.98
A104: 1 | C104: 무형자산의증가 | E104: 0 | S104: 0 | T104: 0.88
...

Sheet BS별도
B1: (백만원) | C1: 이름: BS별도H | E1: 4Q21 | F1: 2021 | G1: 1Q22 | H1: 2Q22 | I1: 3Q22 | J1: 4Q22 | K1: 2022 | L1: 1Q23 | M1: 2Q23 | N1: 3Q23 | O1: 4Q23 | P1: 2023 | Q1: 1Q24 | R1: 2Q24 | S1: 3Q24 | T1: 4Q24 | U1: 2024 | V1: 1Q25 | W1: 2Q25 | X1: 3Q25 | Y1: 4Q25 | Z1: 2025 | AA1: 1Q26 | AB1: 2Q26 | AC1: 3Q26 | AD1: 4Q26 | AE1: 2026 | AF1: 1Q27 | AG1: 2Q27 | AH1: 3Q27 | AI1: 4Q27 | AJ1: 2027 | AK1: 1Q28 | AL1: 2Q28 | AM1: 3Q28 | AN1: 4Q28 | AO1: 2028
B2: 별도 | D2: fin json(kship_fin.py)
B3: 영흥(별) | C3: UPDATE: 26-10-19 | E3: 1 | F3: 2 | G3: 3 | H3: 4 | I3: 5 | J3: 6 | K3: 7 | L3: 8 | M3: 9 | N3: 10 | O3: 11 | P3: 12 | Q3: 13 | R3: 14 | S3: 15 | T3: 16 | U3: 17 | V3: 18 | W3: 19 | X3: 20 | Y3: 21 | Z3: 22 | AA3: 23 | AB3: 24 | AC3: 25 | AD3: 26 | AE3: 27 | AF3: 28 | AG3: 29 | AH3: 30 | AI3: 31 | AJ3: 32 | AK3: 33 | AL3: 34 | AM3: 35 | AN3: 36 | AO3: 37
B4: Account Code | C4: AccountNAME | E4: 2021.12 | F4: 2021.12A | G4: 2022.03 | H4: 2022.06 | I4: 2022.09 | J4: 2022.12 | K4: 2022.12A | L4: 2023.03 | M4: 2023.06 | N4: 2023.09 | O4: 2023.12 | P4: 2023.12A | Q4: 2024.03 | R4: 2024.06 | S4: 2024.09 | T4: 2024.12 | U4: 2024.12A | V4: 2025.03 | W4: 2025.06 | X4: 2025.09 | Y4: 2025.12 | Z4: 2025.12A | AA4: 2026.03 | AB4: 2026.06 | AC4: 2026.09 | AD4: 2026.12 | AE4: 2026.12A | AF4: 2027.03 | AG4: 2027.06 | AH4: 2027.09 | AI4: 2027.12 | AJ4: 2027.12A | AK4: 2028.03 | AL4: 2028.06 | AM4: 2028.09 | AN4: 2028.12 | AO4: 2028.12A
A5: 1 | C5: 유동자산 | E5: 127901.24 | F5: 127901.24 | G5: 164885.18 | H5: 145861.32 | I5: 154932.85 | J5: 141742.41 | K5: 141742.41 | L5: 140617.91 | M5: 142277.94 | N5: 132883.29 | O5: 125139.44 | P5: 125139.44 | Q5: 94166.33 | R5: 88928.81 | S5: 94051.99 | T5: 96273.6 | U5: 96273.6 | V5: 82867.17 | W5: 107130.33 | X5: 95354.6 | Y5: 115943.86 | Z5: 115943.86 | AA5: 107329.74 | AB5: 107038.24
A6: 1 | C6: 현금및현금성자산 | E6: 3360.57 | F6: 3360.57 | G6: 7012.23 | H6: 5687.75 | I6: 3351.63 | J6: 6845.4 | K6: 6845.4 | L6: 4845.63 | M6: 8431.54 | N6: 6766.95 | O6: 6645.99 | P6: 6645.99 | Q6: 6439.27 | R6: 3477.55 | S6: 2431.1 | T6: 5449.63 | U6: 5449.63 | V6: 8557.64 | W6: 6558.62 | X6: 6266.19 | Y6: 6799.46 | Z6: 6799.46 | AA6: 3460.11 | AB6: 2785.19
A7: 1 | C7: 매출채권및기타채권 | E7: 61029.82 | F7: 61029.82 | G7: 87025.47 | H7: 60190.68 | I7: 69955.76 | J7: 57049.32 | K7: 57049.32 | L7: 59458.06 | M7: 53663.29 | N7: 49552.02 | O7: 45480.96 | P7: 45480.96 | Q7: 41939.39 | R7: 39168.92 | S7: 37525.73 | T7: 36993.54 | U7: 36993.54 | V7: 30325.52 | W7: 29243.14 | X7: 27296.55 | Y7: 24742.12 | Z7: 24742.12 | AA7: 16472.27 | AB7: 23359.13
A8: 1 | C8: 재고자산 | E8: 62453.75 | F8: 62453.75 | G8: 69119.13 | H8: 78099.51 | I8: 77480.31 | J8: 74229.77 | K8: 74229.77 | L8: 74947.19 | M8: 72206.44 | N8: 68554.08 | O8: 65897.36 | P8: 65897.36 | Q8: 44203.07 | R8: 44908.39 | S8: 42164.5 | T8: 37654.88 | U8: 37654.88 | V8: 32695.89 | W8: 25064.08 | X8: 14497.97 | Y8: 12947.24 | Z8: 12947.24 | AA8: 14445.84 | AB8: 15118.11
A9: 1 | C9: 기타유동자산 | E9: 1057.1 | F9: 1057.1 | G9: 1728.36 | H9: 1883.38 | I9: 1518.25 | J9: 965.31 | K9: 965.31 | L9: 1351.9 | M9: 1863.84 | N9: 1975.53 | O9: 1287.33 | P9: 1287.33 | Q9: 1572.08 | R9: 1373.94 | S9: 1454.08 | T9: 2025.46 | U9: 2025.46 | V9: 839.28 | W9: 1312.18 | X9: 2321.34 | AA9: 7254.34
A10: 1 | C10: 비유동자산 | E10: 217848.15 | F10: 217848.15 | G10: 219495.62 | H10: 220410.14 | I10: 218293.54 | J10: 212406.83 | K10: 212406.83 | L10: 210319.27 | M10: 203174.07 | N10: 203641.3 | O10: 251420.99 | P10: 251420.99 | Q10: 253032.35 | R10: 251803.19 | S10: 239006.39 | T10: 233754.28 | U10: 233754.28 | V10: 230950.42 | W10: 170468.29 | X10: 166163.42 | Y10: 118525.69 | Z10: 118525.69 | AA10: 116357.85 | AB10: 116464.28
A11: 1 | C11: 장기금융자산 | E11: 1669.98 | F11: 1669.98 | G11: 1307.85 | H11: 1552.21 | I11: 999.34 | J11: 1053.1 | K11: 1053.1 | L11: 963.53 | M11: 1107.68 | N11: 917.19 | O11: 1632.75 | P11: 1632.75 | Q11: 475.13 | R11: 710.36 | S11: 680.97 | T11: 576.45 | U11: 576.45 | V11: -173.48 | W11: 97.05 | X11: -2.96 | Y11: 3.5 | Z11: 3.5 | AA11: 1751.02 | AB11: 3.5
A12: 1 | C12: 투자자산 | E12: 51031.11 | F12: 51031.11 | G12: 54391.27 | H12: 56551.56 | I12: 57762.42 | J12: 54465.77 | K12: 54465.77 | L12: 53116.52 | M12: 47004.12 | N12: 47155.38 | O12: 49607.17 | P12: 49607.17 | Q12: 78921.45 | R12: 78482.68 | S12: 76968.77 | T12: 72148.96 | U12: 72148.96 | V12: 70042.65 | W12: 69767.28 | X12: 69971.61 | Y12: 69360.91 | Z12: 69360.91 | AA12: 69902.03 | AB12: 1186.35
A13: 1 | C13: 장기매출채권및기타채권 | E13: 383.55 | F13: 383.55 | G13: 363.6 | H13: 343.65 | I13: 323.7 | J13: 303.75 | K13: 303.75 | L13: 283.8 | M13: 90.86 | N13: 59.85 | O13: 39.9 | P13: 39.9 | Q13: 19.95 | Y13: 1376.35 | Z13: 1376.35 | AB13: 1334.57
A14: 1 | C14: 종속기업및관계기업투자 | E14: 49361.13 | F14: 49361.13 | G14: 53083.42 | H14: 54999.35 | I14: 56763.08 | J14: 53412.67 | K14: 53412.67 | L14: 52152.99 | M14: 45896.44 | N14: 46238.19 | O14: 47974.42 | P14: 47974.42 | Q14: 78446.32 | R14: 77772.32 | S14: 76287.8 | T14: 71572.51 | U14: 71572.51 | V14: 70216.13 | W14: 69670.23 | X14: 69974.57 | Y14: 69357.41 | Z14: 69357.41 | AA14: 68151.01 | AB14: 1182.85
A15: 1 | C15: 유형자산 | E15: 158538.58 | F15: 158538.58 | G15: 156913 | H15: 155045.38 | I15: 154136.5 | J15: 151895.47 | K15: 151895.47 | L15: 151092.29 | M15: 150350.6 | N15: 150378.8 | O15: 196221.28 | P15: 196221.28 | Q15: 168460.71 | R15: 167716.38 | S15: 156588.62 | T15: 155822.43 | U15: 155822.43 | V15: 155181.74 | W15: 94595.84 | X15: 90062.63 | Y15: 44349.98 | Z15: 44349.98 | AA15: 44125.33 | AB15: 44075.83
A16: 1 | C16: 투자부동산 | E16: 2640.39 | F16: 2640.39 | G16: 2634.61 | H16: 2628.82
A17: 1 | C17: 사용권자산 | E17: 588.19 | F17: 588.19 | G17: 465.1 | H17: 938.1 | I17: 828.68 | J17: 906.3 | K17: 906.3 | L17: 904.16 | M17: 789.05 | N17: 990.23 | O17: 993.18 | P17: 993.18 | Q17: 947.8 | R17: 879.51 | S17: 854.39 | T17: 819.75 | U17: 819.75 | V17: 765.19 | W17: 1430.01 | X17: 1360.87 | Y17: 1446.58 | Z17: 1446.58 | AA17: 494.26 | AB17: 572.45
A18: 1 | C18: 기타비유동자산 | E18: 588.19 | F18: 588.19 | G18: 465.1 | H18: 938.1 | I18: 828.68 | J18: 906.3 | K18: 906.3 | L18: 904.16 | M18: 789.05 | N18: 990.23 | O18: 993.18 | P18: 993.18 | Q18: 947.8 | R18: 879.51 | S18: 854.39 | T18: 819.75 | U18: 819.75 | V18: 765.19 | W18: 1430.01 | X18: 1360.87 | Y18: 1446.58 | Z18: 1446.58 | AA18: 494.26 | AB18: 572.45
A19: 1 | C19: 무형자산 | E19: 865.13 | F19: 865.13 | G19: 859.85 | H19: 854.58 | I19: 849.31 | J19: 844.03 | K19: 844.03 | L19: 838.76 | M19: 829.78 | N19: 824.63 | O19: 569.48 | P19: 569.48 | Q19: 547.71 | R19: 543.43 | S19: 539.15 | T19: 534.88 | U19: 534.88 | V19: 530.6 | W19: 526.32 | X19: 450.55 | Y19: 446.27 | Z19: 446.27 | AA19: 442 | AB19: 437.72
A20: 1 | C20: 자산총계 | E20: 345749.39 | F20: 345749.39 | G20: 384380.8 | H20: 366271.45 | I20: 373226.39 | J20: 354149.24 | K20: 354149.24 | L20: 350937.17 | M20: 345452.01 | N20: 336524.6 | O20: 376560.43 | P20: 376560.43 | Q20: 347198.68 | R20: 340732 | S20: 333058.38 | T20: 330027.88 | U20: 330027.88 | V20: 313817.59 | W20: 277598.62 | X20: 261518.02 | Y20: 234469.55 | Z20: 234469.55 | AA20: 223687.59 | AB20: 223502.53
A21: 1 | C21: 유동부채 | E21: 130296.6 | F21: 130296.6 | G21: 160202.96 | H21: 147182.86 | I21: 150830.49 | J21: 141008.46 | K21: 141008.46 | L21: 141086.61 | M21: 138958.89 | N21: 132392.72 | O21: 126842.33 | P21: 126842.33 | Q21: 106003.09 | R21: 102103.74 | S21: 98521.2 | T21: 99935.53 | U21: 99935.53 | V21: 85385.22 | W21: 79901.85 | X21: 76283.43 | Y21: 66219.35 | Z21: 66219.35 | AA21: 56785.88 | AB21: 55933.12
A22: 1 | C22: 매입채무및기타채무 | E22: 29031.44 | F22: 29031.44 | G22: 53510.93 | H22: 28875.12 | I22: 32416.48 | J22: 21967.6 | K22: 21967.6 | L22: 27230.36 | M22: 23350.21 | N22: 27008.4 | O22: 26884.98 | P22: 26884.98 | Q22: 22199.57 | R22: 22804.77 | S22: 22141.54 | T22: 18933.99 | U22: 18933.99 | V22: 15913.82 | W22: 12780.83 | X22: 12896.18 | Y22: 1628.13 | Z22: 1628.13 | AA22: 10379.15 | AB22: 1724.34
A23: 1 | C23: 단기차입금 | E23: 84636.25 | F23: 84636.25 | G23: 89193.14 | H23: 96257.78 | I23: 96179.3 | J23: 98707.12 | K23: 98707.12 | L23: 94612.33 | M23: 96758.42 | N23: 96768.68 | O23: 90823.85 | P23: 90823.85 | Q23: 79509.35 | R23: 76160.89 | S23: 74341.05 | T23: 74617.37 | U23: 74617.37 | V23: 67182.87 | W23: 51367.21 | X23: 47928.97 | Y23: 41853.93 | Z23: 41853.93 | AA23: 39011.9 | AB23: 36479.76
A24: 1 | C24: 유동성장기부채 | E24: 12891.14 | F24: 12891.14 | G24: 13536.56 | H24: 17716.09 | I24: 18097.83 | J24: 15564.94 | K24: 15564.94 | L24: 15927.26 | M24: 14465.55 | N24: 5839.97 | O24: 3771.31 | P24: 3771.31 | Q24: 2986.46 | R24: 970
A25: 1 | C25: 단기파생상품부채 | E25: 2133.55 | F25: 2133.55 | G25: 2521.39 | H25: 1946.64 | I25: 1909.67 | J25: 2453.74 | K25: 2453.74 | L25: 2220.78 | M25: 1872.54 | N25: 771.33 | O25: 503.38 | P25: 503.38 | Q25: 273.08 | R25: 53.47
A26: 1 | C26: 단기금융부채 | E26: 2432.95 | F26: 2432.95 | G26: 2762.06 | H26: 2238.9 | I26: 2151.86 | J26: 2779.12 | K26: 2779.12 | L26: 2581.58 | M26: 2189.53 | N26: 1108.22 | O26: 906.3 | P26: 906.3 | Q26: 718.27 | R26: 278.6 | S26: 340.22 | T26: 378.21 | U26: 378.21 | V26: 399.18 | W26: 496.57 | X26: 456.7 | Y26: 591.46 | Z26: 591.46 | AA26: 325.87 | AB26: 391.41
A27: 1 | C27: 유동리스부채 | E27: 299.4 | F27: 299.4 | G27: 240.67 | H27: 292.26 | I27: 242.19 | J27: 325.38 | K27: 325.38 | L27: 360.8 | M27: 316.99 | N27: 336.89 | O27: 402.92 | P27: 402.92 | Q27: 445.19 | R27: 225.13 | S27: 340.22 | T27: 378.21 | U27: 378.21 | V27: 399.18 | W27: 496.57 | X27: 456.7 | Y27: 591.46 | Z27: 591.46 | AA27: 325.87 | AB27: 391.41
A28: 1 | C28: 리스부채 | E28: 519.11 | F28: 519.11 | G28: 432.37 | H28: 788.86 | I28: 716.84 | J28: 829.05 | K28: 829.05 | L28: 867.86 | M28: 671.21 | N28: 897.29 | O28: 929.31 | P28: 929.31 | Q28: 928.23 | R28: 708.67 | S28: 700.19 | T28: 699.25 | U28: 699.25 | V28: 691.55 | W28: 1230.13 | X28: 1204.58 | Y28: 1324.16 | Z28: 1324.16 | AA28: 482.71 | AB28: 516.51
A29: 1 | C29: 단기충당부채 | E29: 69.08 | F29: 69.08 | G29: 55.5 | H29: 51.71 | I29: 49.78 | J29: 46.98 | K29: 46.98 | L29: 39.79 | M29: 34.45 | N29: 30.76 | O29: 29.09 | P29: 29.09
A30: 1 | C30: 당기법인세부채(미지급법인세) | E30: 559.53 | F30: 559.53 | G30: 741.19 | H30: 912.1 | I30: 761.01 | J30: 648.12 | K30: 648.12 | L30: 433.92 | R30: 698.06 | T30: 198.01 | U30: 198.01 | V30: 91.12
A31: 1 | C31: 기타유동부채 | E31: 676.19 | F31: 676.19 | G31: 403.58 | H31: 1131.17 | I31: 1174.24 | J31: 1294.58 | K31: 1294.58 | L31: 261.37 | M31: 1058.79 | N31: 1061.46 | O31: 3877.98 | P31: 3877.98 | Q31: -4.84 | R31: 215.48 | S31: 218.12 | T31: 4552.33 | U31: 4552.33 | V31: 1354.07 | W31: 14900.51 | X31: 14821.54 | Y31: 14429.11 | Z31: 14429.11 | AA31: 7012.71 | AB31: 9134.11
A32: 1 | C32: 비유동부채 | E32: 43195.1 | F32: 43195.1 | G32: 49728.91 | H32: 40083.93 | I32: 41943.38 | J32: 36057.4 | K32: 36057.4 | L32: 33858.02 | M32: 32385.53 | N32: 30605.64 | O32: 38705.32 | P32: 38705.32 | Q32: 29630.41 | R32: 27768.75 | S32: 26842.97 | T32: 28479.69 | U32: 28479.69 | V32: 26919.31 | W32: 20919.77 | X32: 25669.92 | Y32: 16986.03 | Z32: 16986.03 | AA32: 15382.86 | AB32: 14976.72
A33: 1 | C33: 장기매입채무및기타채무 | E33: 142.56 | F33: 142.56 | G33: 142.56 | H33: 153.09 | I33: 158.36 | J33: 163.18 | K33: 163.18 | L33: 169.67 | Q33: 129.66 | R33: 134.49 | S33: 139.32 | T33: 146.3 | U33: 146.3 | V33: 151.14 | W33: 155.99 | X33: 160.62 | Y33: 44.54 | Z33: 44.54 | AA33: 46.59 | AB33: 48.63
A34: 1 | C34: 장기차입금 | E34: 25583.84 | F34: 25583.84 | G34: 24757.06 | H34: 21423.14 | I34: 23196.36 | J34: 20586.25 | K34: 20586.25 | L34: 18392.8 | M34: 16199.35 | N34: 14005.91 | O34: 11812.46 | P34: 11812.46 | Q34: 5833.33 | R34: 4166.67 | S34: 2500 | T34: 1250 | U34: 1250
A35: 1 | C35: 비유동리스부채 | E35: 219.71 | F35: 219.71 | G35: 191.7 | H35: 496.6 | I35: 474.65 | J35: 503.67 | K35: 503.67 | L35: 507.06 | M35: 354.22 | N35: 560.4 | O35: 526.39 | P35: 526.39 | Q35: 483.04 | R35: 483.54 | S35: 359.97 | T35: 321.04 | U35: 321.04 | V35: 292.37 | W35: 733.56 | X35: 747.88 | Y35: 732.7 | Z35: 732.7 | AA35: 156.84 | AB35: 125.1
A36: 1 | C36: 장기금융부채 | E36: 219.71 | F36: 219.71 | G36: 1531.81 | H36: 496.6 | I36: 474.65 | J36: 503.67 | K36: 503.67 | L36: 507.06 | M36: 354.22 | N36: 560.4 | O36: 526.39 | P36: 526.39 | Q36: 483.04 | R36: 483.54 | S36: 359.97 | T36: 321.04 | U36: 321.04 | V36: 292.37 | W36: 733.56 | X36: 747.88 | Y36: 2823.8 | Z36: 2823.8 | AA36: 1916.89 | AB36: 2110.56
A37: 1 | C37: 확정급여부채 | E37: 6132.63 | F37: 6132.63 | G37: 6637.91 | H37: 7171.06 | I37: 7482.27 | J37: 4775.05 | K37: 4775.05 | L37: 4739.98 | M37: 4868.53 | N37: 5146.41 | O37: 5863.45 | P37: 5863.45 | Q37: 2135.54 | R37: 2423.84 | S37: 2725.84 | T37: 5638.04 | U37: 5638.04 | V37: 5441.07 | W37: 5080.83 | X37: 3778.42 | Y37: 2474.33 | Z37: 2474.33 | AA37: 2186.12 | AB37: 2339.13
A38: 1 | C38: 이연법인세부채 | E38: 11116.36 | F38: 11116.36 | G38: 10576.49 | H38: 10840.04 | I38: 10631.75 | J38: 10029.25 | K38: 10029.25 | L38: 10048.51 | M38: 10546.53 | N38: 10528.54 | O38: 20117.68 | P38: 20117.68 | Q38: 20904.17 | R38: 20265.25 | S38: 20904.17 | T38: 20983.01 | U38: 20983.01 | V38: 20983.01 | W38: 14949.4 | X38: 20983.01 | Y38: 9048.91 | Z38: 9048.91 | AA38: 9048.91 | AB38: 8196.84
A39: 1 | C39: 부채총계 | E39: 173491.69 | F39: 173491.69 | G39: 209931.87 | H39: 187266.79 | I39: 192773.87 | J39: 177065.86 | K39: 177065.86 | L39: 174944.64 | M39: 171344.41 | N39: 162998.36 | O39: 165547.65 | P39: 165547.65 | Q39: 135633.5 | R39: 129872.49 | S39: 125364.17 | T39: 128415.21 | U39: 128415.21 | V39: 112304.53 | W39: 100821.62 | X39: 101953.35 | Y39: 83205.39 | Z39: 83205.39 | AA39: 72168.74 | AB39: 70909.85
A40: 1 | C40: 자본금 | E40: 50655.19 | F40: 50655.19 | G40: 50655.19 | H40: 50655.19 | I40: 50655.19 | J40: 50655.19 | K40: 50655.19 | L40: 50655.19 | M40: 50655.19 | N40: 50655.19 | O40: 50655.19 | P40: 50655.19 | Q40: 50655.19 | R40: 50655.19 | S40: 50655.19 | T40: 50655.19 | U40: 50655.19 | V40: 50655.19 | W40: 50655.19 | X40: 50655.19 | Y40: 50655.19 | Z40: 50655.19 | AA40: 50655.19 | AB40: 39051.76
A41: 1 | C41: 자본잉여금 | E41: 94821.45 | F41: 94821.45 | G41: 94821.45 | H41: 94821.45 | I41: 94821.45 | J41: 94821.45 | K41: 94821.45 | L41: 94821.45 | M41: 94821.45 | N41: 94821.45 | O41: 94821.45 | P41: 94821.45 | Q41: 94821.45 | R41: 94821.45 | S41: 94821.45 | T41: 94821.45 | U41: 94821.45 | V41: 94821.45 | W41: 94821.45 | X41: 94821.45 | Y41: 94821.45 | Z41: 94821.45 | AA41: 94821.45 | AB41: 94821.45
A42: 1 | C42: 기타자본 | E42: -74141.44 | F42: -74141.44 | G42: -74141.44 | H42: -74141.44 | I42: -74141.44 | J42: -74141.44 | K42: -74141.44 | L42: -74141.44 | M42: -74141.44 | N42: -74141.44 | O42: -74141.44 | P42: -74141.44 | Q42: -74895.09 | R42: -74895.09 | S42: -74895.09 | T42: -74895.09 | U42: -74895.09 | V42: -74895.09 | W42: -74895.09 | X42: -74920.67 | Y42: -73717.85 | Z42: -73717.85 | AA42: -72787.2 | AB42: -60145.46
A43: 1 | C43: 기타포괄이익누계액 | E43: 4546.15 | F43: 4546.15 | G43: 7144.48 | H43: 7854.87 | I43: 8532.19 | J43: 7043.37 | K43: 7043.37 | L43: 7416.77 | M43: 7587.32 | N43: 7779.01 | O43: 48757.41 | P43: 48757.41 | Q43: 47655.73 | R43: 46854.59 | S43: 46841.2 | T43: 48735.4 | U43: 48735.4 | V43: 47554.68 | W43: 47542.6 | X43: 47502.18 | Y43: 48565.32 | Z43: 48565.32 | AA43: 47476.33 | AB43: 47778.48
A44: 1 | C44: 이익잉여금 | E44: 96376.35 | F44: 96376.35 | G44: 95969.26 | H44: 99814.59 | I44: 100585.13 | J44: 98704.81 | K44: 98704.81 | L44: 97240.57 | M44: 95185.07 | N44: 94412.04 | O44: 90920.18 | P44: 90920.18 | Q44: 93327.91 | R44: 93423.37 | S44: 90271.46 | T44: 82295.72 | U44: 82295.72 | V44: 83376.84 | W44: 58652.85 | X44: 41506.53 | Y44: 30940.06 | Z44: 30940.06 | AA44: 31353.08 | AB44: 31086.45
A45: 1 | C45: 자본총계 | E45: 172257.7 | F45: 172257.7 | G45: 174448.94 | H45: 179004.66 | I45: 180452.52 | J45: 177083.38 | K45: 177083.38 | L45: 175992.54 | M45: 174107.59 | N45: 173526.24 | O45: 211012.79 | P45: 211012.79 | Q45: 211565.18 | R45: 210859.51 | S45: 207694.2 | T45: 201612.67 | U45: 201612.67 | V45: 201513.06 | W45: 176777 | X45: 159564.67 | Y45: 151264.16 | Z45: 151264.16 | AA45: 151518.85 | AB45: 152592.68
A46: 1 | C46: 부채와자본총계 | E46: 345749.39 | F46: 345749.39 | G46: 384380.8 | H46: 366271.45 | I46: 373226.39 | J46: 354149.24 | K46: 354149.24 | L46: 350937.17 | M46: 345452.01 | N46: 336524.6 | O46: 376560.43 | P46: 376560.43 | Q46: 347198.68 | R46: 340732 | S46: 333058.38 | T46: 330027.88 | U46: 330027.88 | V46: 313817.59 | W46: 277598.62 | X46: 261518.02 | Y46: 234469.55 | Z46: 234469.55 | AA46: 223687.59 | AB46: 223502.53
... A50: 1 | C50: 이자발생자산 | E50: 5030.55 | F50: 5030.55 | G50: 8320.08 | H50: 7239.96 | I50: 4350.97 | J50: 7924.21 | K50: 7924.21 | L50: 5824.29 | M50: 9546.2 | N50: 7684.14 | O50: 8278.74 | P50: 8278.74 | Q50: 6914.4 | R50: 4187.91 | S50: 3112.07 | T50: 6026.08 | U50: 6026.08 | V50: 8384.16 | W50: 6655.67 | X50: 6263.23 | Y50: 6802.96 | Z50: 6802.96 | AA50: 5211.13 | AB50: 2788.69
A51: 1 | C51: 사채 | G51: 6083.08 | Y51: 2594.46 | Z51: 2594.46 | AA51: 2184.36 | AB51: 2281.56
A52: 1 | C52: 장기파생상품부채 | G52: 1340.11 | Y52: 2091.1 | Z52: 2091.1 | AA52: 1760.05 | AB52: 1985.46
A53: 1 | C53: 매각예정비유동자산및처분자산 | I53: 2626.9 | J53: 2626.9 | K53: 2626.9 | M53: 6105.86 | N53: 6034.71 | O53: 5827.81 | P53: 5827.81 | S53: 10443.89 | T53: 14150.1 | U53: 14150.1 | V53: 10443.89 | W53: 44941.79 | X53: 44941.79 | AA53: 57409.48
A54: 1 | C54: 유동파생상품자산 | J54: 25.71 | K54: 25.71 | L54: 15.13 | M54: 6.98
A55: 1 | C55: 단기금융자산 | J55: 25.71 | K55: 25.71 | L55: 15.13 | M55: 6.98
A56: 1 | C56: 계약부채 | M56: 499.15 | N56: 88.59 | O56: 104.17 | P56: 104.17 | Q56: 237.37 | R56: 419.02 | S56: 1009.91 | T56: 847.89 | U56: 847.89 | V56: 158.87 | W56: 132.5 | X56: 0
A57: 1 | C57: 단기금융부채(face) | M57: 96758.42 | N57: 96768.68 | O57: 90823.85 | P57: 90823.85 | Q57: 79509.35 | R57: 76160.89 | S57: 74341.05 | T57: 74617.37 | U57: 74617.37 | V57: 67182.87 | W57: 51367.21 | X57: 47928.97 | Y57: 41853.93 | Z57: 41853.93 | AA57: 39011.9 | AB57: 36479.76
A58: 1 | C58: 장기금융부채(face) | M58: 16199.35 | N58: 14005.91 | O58: 11812.46 | P58: 11812.46 | Q58: 5833.33 | R58: 4166.67 | S58: 2500 | T58: 1250 | U58: 1250
A59: 1 | C59: 당기법인세자산(선급법인세) | Q59: 12.53 | S59: 32.69 | V59: 4.94 | W59: 10.52 | X59: 30.76
A60: 1 | C60: 기타유동금융자산 | Y60: 3601.67 | Z60: 3601.67 | AB60: 8366.33
A61: 1 | C61: 매출액(수익) | E61: 51883.53 | G61: 55746 | H61: 56371.45 | I61: 56472.23 | J61: 55459.42 | K61: 224049.1 | L61: 50284.93 | M61: 52775.94 | N61: 48444.3 | O61: 49268.07 | P61: 200773.24 | Q61: 45210.88 | R61: 38518.6 | S61: 37240.63 | T61: 35576.7 | U61: 156546.81 | V61: 33853.53 | W61: 32115.92 | X61: 28205.9 | Y61: 19492.22 | Z61: 113667.57 | AA61: 20241.72 | AB61: 21329.93
A62: 1 | C62: 매출원가 | E62: 43731.29 | G62: 47864.32 | H62: 50643.76 | I62: 50333.72 | J62: 50180.28 | K62: 199022.08 | L62: 45954.85 | M62: 48088.05 | N62: 44268.21 | O62: 44828.23 | P62: 183139.34 | Q62: 39625.32 | R62: 34809.83 | S62: 34323.91 | T62: 33642.7 | U62: 142401.76 | V62: 33472.24 | W62: 33460.93 | X62: 33006.13 | Y62: 12164.53 | Z62: 112103.83 | AA62: 17826.89 | AB62: 18719.63
A63: 1 | C63: 매출총이익 | E63: 8152.22 | G63: 7881.69 | H63: 5727.68 | I63: 6138.51 | J63: 5279.14 | K63: 25027.02 | L63: 4330.07 | M63: 4687.89 | N63: 4176.09 | O63: 4439.83 | P63: 17633.88 | Q63: 5585.56 | R63: 3708.77 | S63: 2916.72 | T63: 1934 | U63: 14145.05 | V63: 381.29 | W63: -1345.01 | X63: -4800.24 | Y63: 7327.69 | Z63: 1563.73 | AA63: 2414.82 | AB63: 2610.31
A64: 1 | C64: 판관비 | E64: 5201.47 | G64: 6462.72 | H64: 4524.02 | I64: 5491.64 | J64: 4779.47 | K64: 21257.85 | L64: 4678.15 | M64: 4331.37 | N64: 3743.26 | O64: 4556.76 | P64: 17309.54 | Q64: 3362.2 | R64: 3164.76 | S64: 3510.4 | T64: 3836.76 | U64: 13874.12 | V64: 2977.76 | W64: 2676.3 | X64: 3306.37 | Y64: 9288.95 | Z64: 18249.38 | AA64: 3041.26 | AB64: 1910.54
A65: 1 | C65: 영업이익 | E65: 2950.75 | G65: 1419.24 | H65: 1203.66 | I65: 646.87 | J65: 499.67 | K65: 3769.44 | L65: -348.08 | M65: 356.52 | N65: 432.83 | O65: -116.93 | P65: 324.34 | Q65: 2223.36 | R65: 544.01 | S65: -593.68 | T65: -1902.76 | U65: 270.93 | V65: -2596.47 | W65: -4021.31 | X65: -8106.61 | Y65: -1961.26 | Z65: -16685.65 | AA65: -626.44 | AB65: 699.77
A66: 1 | C66: 금융수익 | E66: 661.25 | G66: 737.49 | H66: 3789.74 | I66: 3039.55 | J66: 438.5 | K66: 8005.28 | L66: 1634.23 | M66: 1207.27 | N66: 1745.71 | O66: 689.81 | P66: 5277.02 | Q66: 1420.85 | R66: 917.27 | S66: 465.99 | T66: 1786.82 | U66: 4590.93 | V66: 807.09 | W66: 367.03 | X66: 454.64 | Y66: 526.98 | Z66: 2155.74 | AA66: 492.13 | AB66: 147.16
A67: 1 | C67: 금융비용 | E67: 1083.27 | G67: 2578.67 | H67: 2098.36 | I67: 3652.34 | J67: 3434.64 | K67: 11764.01 | L67: 2704.21 | M67: 3034.58 | N67: 2948.4 | O67: 2213.44 | P67: 10900.63 | Q67: 2148.99 | R67: 1741.5 | S67: 1703.68 | T67: 1841.65 | U67: 7435.82 | V67: 1338.2 | W67: 1547.25 | X67: 414.76 | Y67: 662.72 | Z67: 3962.93 | AA67: 808.63 | AB67: 841.87
A68: 1 | C68: 기타영업외수익 | E68: 181.44 | G68: 554.57 | H68: 314.39 | I68: 220.51 | J68: 131.7 | K68: 1221.17 | L68: 2238.5 | M68: 225 | N68: 128.93 | O68: 1633.83 | P68: 4226.26 | Q68: 1601.66 | R68: 100.9 | S68: 93.79 | T68: 30.54 | U68: 1826.89 | V68: 5318.3 | W68: 224.54 | X68: 264.47 | Y68: 547.58 | Z68: 6354.89 | AA68: 1386.02 | AB68: 102.82
A69: 1 | C69: 기타영업외비용 | E69: 563.54 | G69: 3.16 | H69: 33.77 | I69: 13.18 | J69: 1206.33 | K69: 1256.44 | L69: 82.28 | M69: 181.46 | N69: 0.94 | O69: 2652.22 | P69: 2916.9 | Q69: 11.39 | R69: 1.08 | S69: 0.39 | T69: 0.69 | U69: 13.55 | V69: 149.82 | W69: 25506.88 | X69: 3555.21 | Y69: 22409.49 | Z69: 51621.4 | AA69: 114.57 | AB69: 27.81
A70: 1 | C70: 법인세비용차감전계속사업이익 | E70: 5181.85 | G70: -399.85 | H70: 4627.43 | I70: 840.69 | J70: -5903.81 | K70: -835.54 | L70: -948.31 | M70: -1608.19 | N70: -703.61 | O70: -2632.28 | P70: -5892.39 | Q70: 2671.11 | R70: 166.79 | S70: -3215.82 | T70: -7276.86 | U70: -7654.78 | V70: 1249.22 | W70: -30751.89 | X70: -10955.44 | Y70: -24564.06 | Z70: -65022.17 | AA70: -937.45 | AB70: 231.02
A71: 1 | C71: 법인세비용 | E71: 305.67 | G71: 7.23 | H71: 726.47 | I71: 56.34 | J71: -1298.04 | K71: -508 | L71: 498.47 | M71: 421.01 | N71: 59.43 | O71: -469.88 | P71: 509.03 | Q71: 241.53 | R71: 38.52 | S71: -80.44 | T71: 903.96 | U71: 1103.57 | V71: 156.73 | W71: -6051.84 | X71: 6054.52 | Y71: -12852.17 | Z71: -12692.76 | AA71: -44.42 | AB71: 189.99
A72: 1 | C72: 당기순이익 | E72: 4876.18 | G72: -407.09 | H72: 3900.96 | I72: 784.36 | J72: -4605.78 | K72: -327.55 | L72: -1446.78 | M72: -2029.21 | N72: -763.04 | O72: -2162.41 | P72: -6401.44 | Q72: 2429.59 | R72: 128.28 | S72: -3135.39 | T72: -8180.82 | U72: -8758.34 | V72: 1092.48 | W72: -24700.05 | X72: -17009.95 | Y72: -11711.9 | Z72: -52329.42 | AA72: -893.03 | AB72: 41.03
... A79: 1 | C79: 이자수취(CF) | E79: 109.39 | G79: 109.15 | H79: 114.35 | I79: 146.85 | J79: 141.81 | K79: 512.16 | L79: 146.61 | M79: 146.73 | N79: 376.91 | O79: 332.29 | P79: 1002.54 | Q79: 314.83 | R79: -34.8 | S79: 98.08 | T79: 87.95 | U79: 466.06 | V79: 107.52 | W79: 107.02 | X79: 158.99 | Y79: 143.42 | Z79: 516.95 | AA79: 192.32 | AB79: 172.25
A80: 1 | C80: 이자지급(CF) | E80: -779.99 | G80: -730.54 | H80: -833.22 | I80: -1057.94 | J80: -1281.96 | K80: -3903.66 | L80: -1390.36 | M80: -1411.54 | Q80: -1465.9 | R80: -1316.44 | S80: -1254.77 | T80: -1145.46 | U80: -5182.57 | V80: -1065.06 | W80: -840.14 | X80: -635.33 | AA80: -502.51
A81: 1 | C81: 배당금수취(CF) | E81: 0 | I81: 0 | J81: 0 | N81: 0 | O81: 0 | S81: 0 | T81: 0 | X81: 0 | Y81: 0
A82: 1 | C82: 법인세납부(CF) | E82: -22.38 | G82: -285.77 | H82: -345.78 | I82: -294.09 | J82: -25.08 | K82: -950.72 | L82: -674.7 | M82: -387.04 | N82: -37.61 | O82: -20.09 | P82: -1119.44 | Q82: -12.53 | R82: -16.33 | S82: -5.25 | T82: -2.34 | U82: -36.45 | V82: -111.83 | W82: -135.02 | X82: -20.24 | Y82: -19.67 | Z82: -286.76 | AA82: 11.91 | AB82: -31.57
A83: 1 | C83: 투자활동으로인한현금흐름 | E83: -923.7 | G83: -1419.38 | H83: 676.73 | I83: -2235.12 | J83: 1257.76 | K83: -1720.01 | L83: 3779.28 | M83: -571.18 | N83: -2267.87 | O83: 10141.98 | P83: 11082.21 | Q83: 3809.92 | R83: -1718.38 | S83: 759.61 | T83: -496.83 | U83: 2354.32 | V83: 9038.97 | W83: -4673.52 | X83: 1709 | Y83: -1942.66 | Z83: 4131.79 | AA83: 11485.82 | AB83: -68.66
A84: 1 | C84: 유형자산의증가 | E84: 978.84 | G84: 209.25 | H84: 528.96 | I84: 659.55 | J84: 730.92 | K84: 2128.68 | L84: 635.15 | M84: 1209.09 | N84: 2217.01 | O84: 783.81 | P84: 4845.06 | Q84: 595.59 | R84: 206.33 | S84: 308.53 | T84: 415.98 | U84: 1526.43 | V84: 11.14 | W84: 663.52 | X84: 528.62 | Y84: 1448.69 | Z84: 2651.97 | AA84: 232.58 | AB84: 106.3
A85: 1 | C85: CAPEX | E85: 978.84 | G85: 209.25 | H85: 528.96 | I85: 659.55 | J85: 730.92 | K85: 2128.68 | L85: 635.15 | M85: 1209.09 | N85: 2217.01 | O85: 783.81 | P85: 4845.06 | Q85: 595.59 | R85: 206.33 | S85: 308.53 | T85: 415.98 | U85: 1526.43 | V85: 11.14 | W85: 663.52 | X85: 528.62 | Y85: 1448.69 | Z85: 2651.97 | AA85: 232.58 | AB85: 106.3
A86: 1 | C86: 유형자산의감소 | E86: 0.7 | G86: 261.82 | H86: 224.2 | I86: 13.63 | J86: 29.63 | K86: 529.28 | L86: 17.01 | M86: 350.82 | N86: 16.64 | O86: 2855.29 | P86: 3239.76 | Q86: 4.55 | R86: 0 | S86: 4.73 | T86: 0 | U86: 9.28 | V86: 143.34 | W86: 0 | X86: 2234.36
A87: 1 | C87: 재무활동으로인한현금흐름 | E87: -7433.52 | G87: 10581.18 | H87: 1275.86 | I87: 1170.91 | J87: -947.83 | K87: 12080.12 | L87: -6963.68 | M87: -2511.58 | N87: -12338.83 | O87: -10182.59 | P87: -31996.68 | Q87: 870.2 | R87: -7508.03 | S87: -4327.04 | T87: -1764.65 | U87: -12729.52 | V87: -8829.4 | W87: -15955.95 | X87: -3717.59 | Y87: 23.73 | Z87: -28479.21 | AA87: -3065.49 | AB87: -2628.08
A88: 1 | C88: 단기차입금의증가 | E88: 19363.18 | G88: 28319.17 | H88: 30135.12 | I88: 40081.76 | J88: 24856.99 | K88: 123393.04 | L88: 35583.45 | M88: 31812.81 | N88: 33491.87 | Q88: 46519.49 | R88: 25903.68 | S88: 25150.09 | T88: 9197.84 | U88: 106771.1 | V88: 31081.56 | W88: 15595.48 | X88: 15708.1 | Y88: 7635.39 | Z88: 70020.53 | AA88: 12999.17 | AB88: 13837.93
A89: 1 | C89: 장기차입금의증가 | E89: 0 | J89: 0
A90: 1 | C90: 단기차입금의감소 | E90: 26745.67 | G90: 24658.3 | H90: 26714.51 | I90: 43832.7 | J90: 22903.23 | K90: 118108.74 | L90: 42030.63 | M90: 31731.94 | N90: 35924.98 | Q90: 43754.12 | R90: 30871.37 | S90: 28290 | T90: 10844.38 | U90: 113759.87 | V90: 39802.82 | W90: 31282 | X90: 19260.24 | Y90: 13655.29 | Z90: 104000.35 | AA90: 15926.44 | AB90: 16340.91
A91: 1 | C91: 리스부채의상환 | E91: 67.53 | G91: 79.68 | H91: 193.26 | I91: 78.13 | J91: 87.63 | K91: 438.7 | L91: 79.19 | M91: 204.07 | N91: 89.26 | O91: 110.96 | P91: 483.48 | Q91: 99.03 | R91: 235.55 | S91: 132.45 | T91: 118.11 | U91: 585.14 | V91: 108.14 | W91: 269.42 | X91: 139.88 | Y91: 152.37 | Z91: 669.81 | AA91: 138.21 | AB91: 125.11
A92: 1 | C92: 배당금지급 | E92: 0
A93: 1 | C93: 현금및현금성자산의증감 | E93: -3456.61 | G93: 3688.93 | H93: -1369.49 | I93: -2331.79 | J93: 3625.88 | K93: 3613.53 | L93: -2003.71 | M93: 3517.91 | N93: -1599.99 | O93: -78.32 | P93: -164.11 | Q93: 1254.63 | R93: -4431.26 | S93: -1027.85 | T93: 2946.2 | U93: -1258.28 | V93: 3045.54 | W93: -1870.92 | X93: -384.24 | Y93: 650.16 | Z93: 1440.54 | AA93: -3419.38 | AB93: -595
A94: 1 | C94: 기말현금및현금성자산 | E94: -3492.36 | G94: 7012.23 | H94: -1324.48 | I94: -2336.12 | J94: 3493.77 | K94: 6845.4 | L94: 4845.63 | M94: 3585.91 | N94: -1664.59 | O94: -120.96 | P94: 6645.99 | Q94: 6439.27 | R94: -2961.72 | S94: -1046.45 | T94: 3018.53 | U94: 5449.63 | V94: 8557.64 | W94: -1999.02 | X94: -292.43 | Y94: 533.27 | Z94: 6799.46 | AA94: 3460.11 | AB94: -674.92
A95: 1 | C95: 자기주식의취득 | Q95: 753.65 | R95: 0 | S95: 0 | T95: 0 | U95: 753.65 | Y95: 0

Sheet subQ
A1: YQ | C1: subQ 분기 서브모델(억원, U=100) | E1: 4Q21 | F1: 2021 | G1: 1Q22 | H1: 2Q22 | I1: 3Q22 | J1: 4Q22 | K1: 2022 | L1: 1Q23 | M1: 2Q23 | N1: 3Q23 | O1: 4Q23 | P1: 2023 | Q1: 1Q24 | R1: 2Q24 | S1: 3Q24 | T1: 4Q24 | U1: 2024 | V1: 1Q25 | W1: 2Q25 | X1: 3Q25 | Y1: 4Q25 | Z1: 2025 | AA1: 1Q26 | AB1: 2Q26 | AC1: 3Q26 | AD1: 4Q26 | AE1: 2026 | AF1: 1Q27 | AG1: 2Q27 | AH1: 3Q27 | AI1: 4Q27 | AJ1: 2027 | AK1: 1Q28 | AL1: 2Q28 | AM1: 3Q28 | AN1: 4Q28 | AO1: 2028
A2: A=이름(key) B=그룹 C=단위 D=FnGuide 계정명(VLOOKUP 키). 확정=VLOOKUP(BS), 추정=변수 가정 참조
E3: 1 | F3: 2 | G3: 3 | H3: 4 | I3: 5 | J3: 6 | K3: 7 | L3: 8 | M3: 9 | N3: 10 | O3: 11 | P3: 12 | Q3: 13 | R3: 14 | S3: 15 | T3: 16 | U3: 17 | V3: 18 | W3: 19 | X3: 20 | Y3: 21 | Z3: 22 | AA3: 23 | AB3: 24 | AC3: 25 | AD3: 26 | AE3: 27 | AF3: 28 | AG3: 29 | AH3: 30 | AI3: 31 | AJ3: 32 | AK3: 33 | AL3: 34 | AM3: 35 | AN3: 36 | AO3: 37
E4: 2021.12 | F4: 2021.12A | G4: 2022.03 | H4: 2022.06 | I4: 2022.09 | J4: 2022.12 | K4: 2022.12A | L4: 2023.03 | M4: 2023.06 | N4: 2023.09 | O4: 2023.12 | P4: 2023.12A | Q4: 2024.03 | R4: 2024.06 | S4: 2024.09 | T4: 2024.12 | U4: 2024.12A | V4: 2025.03 | W4: 2025.06 | X4: 2025.09 | Y4: 2025.12 | Z4: 2025.12A | AA4: 2026.03 | AB4: 2026.06 | AC4: 2026.09 | AD4: 2026.12 | AE4: 2026.12A | AF4: 2027.03 | AG4: 2027.06 | AH4: 2027.09 | AI4: 2027.12 | AJ4: 2027.12A | AK4: 2028.03 | AL4: 2028.06 | AM4: 2028.09 | AN4: 2028.12 | AO4: 2028.12A
A5: 매출액 | B5: 손익 | C5: 억원 | D5: 매출액(수익) | E5: =IFERROR(VLOOKUP($D5,BS연결,MATCH(E$1,BS연결H,0),0)/100,"") | G5: =IFERROR(VLOOKUP($D5,BS연결,MATCH(G$1,BS연결H,0),0)/100,"") | H5: =IFERROR(VLOOKUP($D5,BS연결,MATCH(H$1,BS연결H,0),0)/100,"") | I5: =IFERROR(VLOOKUP($D5,BS연결,MATCH(I$1,BS연결H,0),0)/100,"") | J5: =IFERROR(VLOOKUP($D5,BS연결,MATCH(J$1,BS연결H,0),0)/100,"") | K5: =IFERROR(VLOOKUP($D5,BS연결,MATCH(K$1,BS연결H,0),0)/100,"") | L5: =IFERROR(VLOOKUP($D5,BS연결,MATCH(L$1,BS연결H,0),0)/100,"") | M5: =IFERROR(VLOOKUP($D5,BS연결,MATCH(M$1,BS연결H,0),0)/100,"") | N5: =IFERROR(VLOOKUP($D5,BS연결,MATCH(N$1,BS연결H,0),0)/100,"") | ... AB5: =IFERROR(VLOOKUP($D5,BS연결,MATCH(AB$1,BS연결H,0),0)/100,"") | AC5: =IFERROR(X5*(1+변수!AC21),"") | AD5: =IFERROR(Y5*(1+변수!AD21),"") | AE5: =SUM(AA5:AD5) | AF5: =IFERROR(AA5*(1+변수!AF21),"") | AG5: =IFERROR(AB5*(1+변수!AG21),"") | AH5: =IFERROR(AC5*(1+변수!AH21),"") | AI5: =IFERROR(AD5*(1+변수!AI21),"") | AJ5: =SUM(AF5:AI5) | AK5: =IFERROR(AF5*(1+변수!AK21),"") | AL5: =IFERROR(AG5*(1+변수!AL21),"") | AM5: =IFERROR(AH5*(1+변수!AM21),"") | AN5: =IFERROR(AI5*(1+변수!AN21),"") | AO5: =SUM(AK5:AN5)
A6: 매출원가 | B6: 손익 | C6: 억원 | D6: 매출원가 | E6: =IFERROR(VLOOKUP($D6,BS연결,MATCH(E$1,BS연결H,0),0)/100,"") | G6: =IFERROR(VLOOKUP($D6,BS연결,MATCH(G$1,BS연결H,0),0)/100,"") | H6: =IFERROR(VLOOKUP($D6,BS연결,MATCH(H$1,BS연결H,0),0)/100,"") | I6: =IFERROR(VLOOKUP($D6,BS연결,MATCH(I$1,BS연결H,0),0)/100,"") | J6: =IFERROR(VLOOKUP($D6,BS연결,MATCH(J$1,BS연결H,0),0)/100,"") | K6: =IFERROR(VLOOKUP($D6,BS연결,MATCH(K$1,BS연결H,0),0)/100,"") | L6: =IFERROR(VLOOKUP($D6,BS연결,MATCH(L$1,BS연결H,0),0)/100,"") | M6: =IFERROR(VLOOKUP($D6,BS연결,MATCH(M$1,BS연결H,0),0)/100,"") | N6: =IFERROR(VLOOKUP($D6,BS연결,MATCH(N$1,BS연결H,0),0)/100,"") | ... AB6: =IFERROR(VLOOKUP($D6,BS연결,MATCH(AB$1,BS연결H,0),0)/100,"") | AC6: =IFERROR(AC5-AC7,"") | AD6: =IFERROR(AD5-AD7,"") | AE6: =SUM(AA6:AD6) | AF6: =IFERROR(AF5-AF7,"") | AG6: =IFERROR(AG5-AG7,"") | AH6: =IFERROR(AH5-AH7,"") | AI6: =IFERROR(AI5-AI7,"") | AJ6: =SUM(AF6:AI6) | AK6: =IFERROR(AK5-AK7,"") | AL6: =IFERROR(AL5-AL7,"") | AM6: =IFERROR(AM5-AM7,"") | AN6: =IFERROR(AN5-AN7,"") | AO6: =SUM(AK6:AN6)
A7: 매출총이익 | B7: 손익 | C7: 억원 | D7: 매출총이익 | E7: =IFERROR(VLOOKUP($D7,BS연결,MATCH(E$1,BS연결H,0),0)/100,"") | G7: =IFERROR(VLOOKUP($D7,BS연결,MATCH(G$1,BS연결H,0),0)/100,"") | H7: =IFERROR(VLOOKUP($D7,BS연결,MATCH(H$1,BS연결H,0),0)/100,"") | I7: =IFERROR(VLOOKUP($D7,BS연결,MATCH(I$1,BS연결H,0),0)/100,"") | J7: =IFERROR(VLOOKUP($D7,BS연결,MATCH(J$1,BS연결H,0),0)/100,"") | K7: =IFERROR(VLOOKUP($D7,BS연결,MATCH(K$1,BS연결H,0),0)/100,"") | L7: =IFERROR(VLOOKUP($D7,BS연결,MATCH(L$1,BS연결H,0),0)/100,"") | M7: =IFERROR(VLOOKUP($D7,BS연결,MATCH(M$1,BS연결H,0),0)/100,"") | N7: =IFERROR(VLOOKUP($D7,BS연결,MATCH(N$1,BS연결H,0),0)/100,"") | ... AB7: =IFERROR(VLOOKUP($D7,BS연결,MATCH(AB$1,BS연결H,0),0)/100,"") | AC7: =IFERROR(AC9+AC8,"") | AD7: =IFERROR(AD9+AD8,"") | AE7: =SUM(AA7:AD7) | AF7: =IFERROR(AF9+AF8,"") | AG7: =IFERROR(AG9+AG8,"") | AH7: =IFERROR(AH9+AH8,"") | AI7: =IFERROR(AI9+AI8,"") | AJ7: =SUM(AF7:AI7) | AK7: =IFERROR(AK9+AK8,"") | AL7: =IFERROR(AL9+AL8,"") | AM7: =IFERROR(AM9+AM8,"") | AN7: =IFERROR(AN9+AN8,"") | AO7: =SUM(AK7:AN7)
A8: 판관비 | B8: 손익 | C8: 억원 | D8: 판관비 | E8: =IFERROR(VLOOKUP($D8,BS연결,MATCH(E$1,BS연결H,0),0)/100,"") | G8: =IFERROR(VLOOKUP($D8,BS연결,MATCH(G$1,BS연결H,0),0)/100,"") | H8: =IFERROR(VLOOKUP($D8,BS연결,MATCH(H$1,BS연결H,0),0)/100,"") | I8: =IFERROR(VLOOKUP($D8,BS연결,MATCH(I$1,BS연결H,0),0)/100,"") | J8: =IFERROR(VLOOKUP($D8,BS연결,MATCH(J$1,BS연결H,0),0)/100,"") | K8: =IFERROR(VLOOKUP($D8,BS연결,MATCH(K$1,BS연결H,0),0)/100,"") | L8: =IFERROR(VLOOKUP($D8,BS연결,MATCH(L$1,BS연결H,0),0)/100,"") | M8: =IFERROR(VLOOKUP($D8,BS연결,MATCH(M$1,BS연결H,0),0)/100,"") | N8: =IFERROR(VLOOKUP($D8,BS연결,MATCH(N$1,BS연결H,0),0)/100,"") | ... Y8: =IFERROR(VLOOKUP($D8,BS연결,MATCH(Y$1,BS연결H,0),0)/100,"") | Z8: =SUM(V8:Y8) | AA8: =IFERROR(VLOOKUP($D8,BS연결,MATCH(AA$1,BS연결H,0),0)/100,"") | AB8: =IFERROR(VLOOKUP($D8,BS연결,MATCH(AB$1,BS연결H,0),0)/100,"") | AC8: =IFERROR(AC5*변수!AC22,"") | AD8: =IFERROR(AD5*변수!AD22,"") | AE8: =SUM(AA8:AD8) | AF8: =IFERROR(AF5*변수!AF22,"") | AG8: =IFERROR(AG5*변수!AG22,"") | AH8: =IFERROR(AH5*변수!AH22,"") | AI8: =IFERROR(AI5*변수!AI22,"") | AJ8: =SUM(AF8:AI8) | AK8: =IFERROR(AK5*변수!AK22,"") | AL8: =IFERROR(AL5*변수!AL22,"") | AM8: =IFERROR(AM5*변수!AM22,"") | AN8: =IFERROR(AN5*변수!AN22,"") | AO8: =SUM(AK8:AN8)
A9: 영업이익 | B9: 손익 | C9: 억원 | D9: 영업이익 | E9: =IFERROR(VLOOKUP($D9,BS연결,MATCH(E$1,BS연결H,0),0)/100,"") | G9: =IFERROR(VLOOKUP($D9,BS연결,MATCH(G$1,BS연결H,0),0)/100,"") | H9: =IFERROR(VLOOKUP($D9,BS연결,MATCH(H$1,BS연결H,0),0)/100,"") | I9: =IFERROR(VLOOKUP($D9,BS연결,MATCH(I$1,BS연결H,0),0)/100,"") | J9: =IFERROR(VLOOKUP($D9,BS연결,MATCH(J$1,BS연결H,0),0)/100,"") | K9: =IFERROR(VLOOKUP($D9,BS연결,MATCH(K$1,BS연결H,0),0)/100,"") | L9: =IFERROR(VLOOKUP($D9,BS연결,MATCH(L$1,BS연결H,0),0)/100,"") | M9: =IFERROR(VLOOKUP($D9,BS연결,MATCH(M$1,BS연결H,0),0)/100,"") | N9: =IFERROR(VLOOKUP($D9,BS연결,MATCH(N$1,BS연결H,0),0)/100,"") | ... AB9: =IFERROR(VLOOKUP($D9,BS연결,MATCH(AB$1,BS연결H,0),0)/100,"") | AC9: =IFERROR(AC5*변수!AC23,"") | AD9: =IFERROR(AD5*변수!AD23,"") | AE9: =SUM(AA9:AD9) | AF9: =IFERROR(AF5*변수!AF23,"") | AG9: =IFERROR(AG5*변수!AG23,"") | AH9: =IFERROR(AH5*변수!AH23,"") | AI9: =IFERROR(AI5*변수!AI23,"") | AJ9: =SUM(AF9:AI9) | AK9: =IFERROR(AK5*변수!AK23,"") | AL9: =IFERROR(AL5*변수!AL23,"") | AM9: =IFERROR(AM5*변수!AM23,"") | AN9: =IFERROR(AN5*변수!AN23,"") | AO9: =SUM(AK9:AN9)
A10: OPM | B10: 손익 | C10: % | D10: 영업이익률 | E10: =IFERROR(E9/E5,"") | G10: =IFERROR(G9/G5,"") | H10: =IFERROR(H9/H5,"") | I10: =IFERROR(I9/I5,"") | J10: =IFERROR(J9/J5,"") | K10: =IFERROR(K9/K5,"") | L10: =IFERROR(L9/L5,"") | M10: =IFERROR(M9/M5,"") | N10: =IFERROR(N9/N5,"") | ... AO10: =IFERROR(AO9/AO5,"")
A11: 금융손익 | B11: 손익 | C11: 억원 | D11: 금융손익 | E11: =IFERROR(VLOOKUP($D11,BS연결,MATCH(E$1,BS연결H,0),0)/100,"") | G11: =IFERROR(VLOOKUP($D11,BS연결,MATCH(G$1,BS연결H,0),0)/100,"") | H11: =IFERROR(VLOOKUP($D11,BS연결,MATCH(H$1,BS연결H,0),0)/100,"") | I11: =IFERROR(VLOOKUP($D11,BS연결,MATCH(I$1,BS연결H,0),0)/100,"") | J11: =IFERROR(VLOOKUP($D11,BS연결,MATCH(J$1,BS연결H,0),0)/100,"") | K11: =IFERROR(VLOOKUP($D11,BS연결,MATCH(K$1,BS연결H,0),0)/100,"") | L11: =IFERROR(VLOOKUP($D11,BS연결,MATCH(L$1,BS연결H,0),0)/100,"") | M11: =IFERROR(VLOOKUP($D11,BS연결,MATCH(M$1,BS연결H,0),0)/100,"") | N11: =IFERROR(VLOOKUP($D11,BS연결,MATCH(N$1,BS연결H,0),0)/100,"") | ... T11: =IFERROR(VLOOKUP($D11,BS연결,MATCH(T$1,BS연결H,0),0)/100,"") | U11: =SUM(Q11:T11) | V11: =IFERROR(VLOOKUP($D11,BS연결,MATCH(V$1,BS연결H,0),0)/100,"") | W11: =IFERROR(VLOOKUP($D11,BS연결,MATCH(W$1,BS연결H,0),0)/100,"") | X11: =IFERROR(VLOOKUP($D11,BS연결,MATCH(X$1,BS연결H,0),0)/100,"") | Y11: =IFERROR(VLOOKUP($D11,BS연결,MATCH(Y$1,BS연결H,0),0)/100,"") | Z11: =IFERROR(VLOOKUP($D11,BS연결,MATCH(Z$1,BS연결H,0),0)/100,"") | AA11: =IFERROR(VLOOKUP($D11,BS연결,MATCH(AA$1,BS연결H,0),0)/100,"") | AB11: =IFERROR(VLOOKUP($D11,BS연결,MATCH(AB$1,BS연결H,0),0)/100,"") | AC11: =IFERROR(AC12+AC13+AC14+AC15,"") | AD11: =IFERROR(AD12+AD13+AD14+AD15,"") | AE11: =SUM(AA11:AD11) | AF11: =IFERROR(AF12+AF13+AF14+AF15,"") | AG11: =IFERROR(AG12+AG13+AG14+AG15,"") | AH11: =IFERROR(AH12+AH13+AH14+AH15,"") | AI11: =IFERROR(AI12+AI13+AI14+AI15,"") | AJ11: =SUM(AF11:AI11) | AK11: =IFERROR(AK12+AK13+AK14+AK15,"") | AL11: =IFERROR(AL12+AL13+AL14+AL15,"") | AM11: =IFERROR(AM12+AM13+AM14+AM15,"") | AN11: =IFERROR(AN12+AN13+AN14+AN15,"") | AO11: =SUM(AK11:AN11)
A12: 이자손익 | B12: 손익 | C12: 억원 | D12: 이자손익 | K12: =SUM(G12:J12) | P12: =SUM(L12:O12) | U12: =SUM(Q12:T12) | Z12: =SUM(V12:Y12) | AB12: =IFERROR(VLOOKUP($D12,BS연결,MATCH(AB$1,BS연결H,0),0)/100,"") | AC12: =IFERROR((AB29*변수!$D$55-AB27*변수!$D$56)/4,"") | AD12: =IFERROR((AC29*변수!$D$55-AC27*변수!$D$56)/4,"") | AE12: =SUM(AA12:AD12) | AF12: =IFERROR((AD29*변수!$D$55-AD27*변수!$D$56)/4,"") | AG12: =IFERROR((AF29*변수!$D$55-AF27*변수!$D$56)/4,"") | AH12: =IFERROR((AG29*변수!$D$55-AG27*변수!$D$56)/4,"") | AI12: =IFERROR((AH29*변수!$D$55-AH27*변수!$D$56)/4,"") | AJ12: =SUM(AF12:AI12) | AK12: =IFERROR((AI29*변수!$D$55-AI27*변수!$D$56)/4,"") | AL12: =IFERROR((AK29*변수!$D$55-AK27*변수!$D$56)/4,"") | AM12: =IFERROR((AL29*변수!$D$55-AL27*변수!$D$56)/4,"") | AN12: =IFERROR((AM29*변수!$D$55-AM27*변수!$D$56)/4,"") | AO12: =SUM(AK12:AN12)
A13: 외환손익 | B13: 손익 | C13: 억원 | D13: 외환손익(실적만; 추정 환효과는 환관련손익) | G13: =IFERROR((VLOOKUP("외환차익",BS연결,MATCH(G$1,BS연결H,0),0)-VLOOKUP("외환차손",BS연결,MATCH(G$1,BS연결H,0),0)+VLOOKUP("외화환산이익",BS연결,MATCH(G$1,BS연결H,0),0)-VLOOKUP("외화환산손실",BS연결,MATCH(G$1,BS연결H,0),0))/100,"") | H13: =IFERROR((VLOOKUP("외환차익",BS연결,MATCH(H$1,BS연결H,0),0)-VLOOKUP("외환차손",BS연결,MATCH(H$1,BS연결H,0),0)+VLOOKUP("외화환산이익",BS연결,MATCH(H$1,BS연결H,0),0)-VLOOKUP("외화환산손실",BS연결,MATCH(H$1,BS연결H,0),0))/100,"") | I13: =IFERROR((VLOOKUP("외환차익",BS연결,MATCH(I$1,BS연결H,0),0)-VLOOKUP("외환차손",BS연결,MATCH(I$1,BS연결H,0),0)+VLOOKUP("외화환산이익",BS연결,MATCH(I$1,BS연결H,0),0)-VLOOKUP("외화환산손실",BS연결,MATCH(I$1,BS연결H,0),0))/100,"") | J13: =IFERROR((VLOOKUP("외환차익",BS연결,MATCH(J$1,BS연결H,0),0)-VLOOKUP("외환차손",BS연결,MATCH(J$1,BS연결H,0),0)+VLOOKUP("외화환산이익",BS연결,MATCH(J$1,BS연결H,0),0)-VLOOKUP("외화환산손실",BS연결,MATCH(J$1,BS연결H,0),0))/100,"") | K13: =SUM(G13:J13) | L13: =IFERROR((VLOOKUP("외환차익",BS연결,MATCH(L$1,BS연결H,0),0)-VLOOKUP("외환차손",BS연결,MATCH(L$1,BS연결H,0),0)+VLOOKUP("외화환산이익",BS연결,MATCH(L$1,BS연결H,0),0)-VLOOKUP("외화환산손실",BS연결,MATCH(L$1,BS연결H,0),0))/100,"") | M13: =IFERROR((VLOOKUP("외환차익",BS연결,MATCH(M$1,BS연결H,0),0)-VLOOKUP("외환차손",BS연결,MATCH(M$1,BS연결H,0),0)+VLOOKUP("외화환산이익",BS연결,MATCH(M$1,BS연결H,0),0)-VLOOKUP("외화환산손실",BS연결,MATCH(M$1,BS연결H,0),0))/100,"") | N13: =IFERROR((VLOOKUP("외환차익",BS연결,MATCH(N$1,BS연결H,0),0)-VLOOKUP("외환차손",BS연결,MATCH(N$1,BS연결H,0),0)+VLOOKUP("외화환산이익",BS연결,MATCH(N$1,BS연결H,0),0)-VLOOKUP("외화환산손실",BS연결,MATCH(N$1,BS연결H,0),0))/100,"") | O13: =IFERROR((VLOOKUP("외환차익",BS연결,MATCH(O$1,BS연결H,0),0)-VLOOKUP("외환차손",BS연결,MATCH(O$1,BS연결H,0),0)+VLOOKUP("외화환산이익",BS연결,MATCH(O$1,BS연결H,0),0)-VLOOKUP("외화환산손실",BS연결,MATCH(O$1,BS연결H,0),0))/100,"") | P13: =SUM(L13:O13) | Q13: =IFERROR((VLOOKUP("외환차익",BS연결,MATCH(Q$1,BS연결H,0),0)-VLOOKUP("외환차손",BS연결,MATCH(Q$1,BS연결H,0),0)+VLOOKUP("외화환산이익",BS연결,MATCH(Q$1,BS연결H,0),0)-VLOOKUP("외화환산손실",BS연결,MATCH(Q$1,BS연결H,0),0))/100,"") | R13: =IFERROR((VLOOKUP("외환차익",BS연결,MATCH(R$1,BS연결H,0),0)-VLOOKUP("외환차손",BS연결,MATCH(R$1,BS연결H,0),0)+VLOOKUP("외화환산이익",BS연결,MATCH(R$1,BS연결H,0),0)-VLOOKUP("외화환산손실",BS연결,MATCH(R$1,BS연결H,0),0))/100,"") | S13: =IFERROR((VLOOKUP("외환차익",BS연결,MATCH(S$1,BS연결H,0),0)-VLOOKUP("외환차손",BS연결,MATCH(S$1,BS연결H,0),0)+VLOOKUP("외화환산이익",BS연결,MATCH(S$1,BS연결H,0),0)-VLOOKUP("외화환산손실",BS연결,MATCH(S$1,BS연결H,0),0))/100,"") | T13: =IFERROR((VLOOKUP("외환차익",BS연결,MATCH(T$1,BS연결H,0),0)-VLOOKUP("외환차손",BS연결,MATCH(T$1,BS연결H,0),0)+VLOOKUP("외화환산이익",BS연결,MATCH(T$1,BS연결H,0),0)-VLOOKUP("외화환산손실",BS연결,MATCH(T$1,BS연결H,0),0))/100,"") | U13: =SUM(Q13:T13) | V13: =IFERROR((VLOOKUP("외환차익",BS연결,MATCH(V$1,BS연결H,0),0)-VLOOKUP("외환차손",BS연결,MATCH(V$1,BS연결H,0),0)+VLOOKUP("외화환산이익",BS연결,MATCH(V$1,BS연결H,0),0)-VLOOKUP("외화환산손실",BS연결,MATCH(V$1,BS연결H,0),0))/100,"") | W13: =IFERROR((VLOOKUP("외환차익",BS연결,MATCH(W$1,BS연결H,0),0)-VLOOKUP("외환차손",BS연결,MATCH(W$1,BS연결H,0),0)+VLOOKUP("외화환산이익",BS연결,MATCH(W$1,BS연결H,0),0)-VLOOKUP("외화환산손실",BS연결,MATCH(W$1,BS연결H,0),0))/100,"") | X13: =IFERROR((VLOOKUP("외환차익",BS연결,MATCH(X$1,BS연결H,0),0)-VLOOKUP("외환차손",BS연결,MATCH(X$1,BS연결H,0),0)+VLOOKUP("외화환산이익",BS연결,MATCH(X$1,BS연결H,0),0)-VLOOKUP("외화환산손실",BS연결,MATCH(X$1,BS연결H,0),0))/100,"") | Y13: =IFERROR((VLOOKUP("외환차익",BS연결,MATCH(Y$1,BS연결H,0),0)-VLOOKUP("외환차손",BS연결,MATCH(Y$1,BS연결H,0),0)+VLOOKUP("외화환산이익",BS연결,MATCH(Y$1,BS연결H,0),0)-VLOOKUP("외화환산손실",BS연결,MATCH(Y$1,BS연결H,0),0))/100,"") | Z13: =SUM(V13:Y13) | AB13: =IFERROR((VLOOKUP("외환차익",BS연결,MATCH(AB$1,BS연결H,0),0)-VLOOKUP("외환차손",BS연결,MATCH(AB$1,BS연결H,0),0)+VLOOKUP("외화환산이익",BS연결,MATCH(AB$1,BS연결H,0),0)-VLOOKUP("외화환산손실",BS연결,MATCH(AB$1,BS연결H,0),0))/100,"") | AC13: =변수!AC24 | AD13: =변수!AD24 | AE13: =SUM(AA13:AD13) | AF13: =변수!AF24 | AG13: =변수!AG24 | AH13: =변수!AH24 | AI13: =변수!AI24 | AJ13: =SUM(AF13:AI13) | AK13: =변수!AK24 | AL13: =변수!AL24 | AM13: =변수!AM24 | AN13: =변수!AN24 | AO13: =SUM(AK13:AN13)
A14: 파생상품손익 | B14: 손익 | C14: 억원 | D14: 파생상품손익 | G14: =IFERROR((VLOOKUP("파생상품이익",BS연결,MATCH(G$1,BS연결H,0),0)-VLOOKUP("파생상품손실",BS연결,MATCH(G$1,BS연결H,0),0))/100,"") | H14: =IFERROR((VLOOKUP("파생상품이익",BS연결,MATCH(H$1,BS연결H,0),0)-VLOOKUP("파생상품손실",BS연결,MATCH(H$1,BS연결H,0),0))/100,"") | I14: =IFERROR((VLOOKUP("파생상품이익",BS연결,MATCH(I$1,BS연결H,0),0)-VLOOKUP("파생상품손실",BS연결,MATCH(I$1,BS연결H,0),0))/100,"") | J14: =IFERROR((VLOOKUP("파생상품이익",BS연결,MATCH(J$1,BS연결H,0),0)-VLOOKUP("파생상품손실",BS연결,MATCH(J$1,BS연결H,0),0))/100,"") | K14: =SUM(G14:J14) | L14: =IFERROR((VLOOKUP("파생상품이익",BS연결,MATCH(L$1,BS연결H,0),0)-VLOOKUP("파생상품손실",BS연결,MATCH(L$1,BS연결H,0),0))/100,"") | M14: =IFERROR((VLOOKUP("파생상품이익",BS연결,MATCH(M$1,BS연결H,0),0)-VLOOKUP("파생상품손실",BS연결,MATCH(M$1,BS연결H,0),0))/100,"") | N14: =IFERROR((VLOOKUP("파생상품이익",BS연결,MATCH(N$1,BS연결H,0),0)-VLOOKUP("파생상품손실",BS연결,MATCH(N$1,BS연결H,0),0))/100,"") | O14: =IFERROR((VLOOKUP("파생상품이익",BS연결,MATCH(O$1,BS연결H,0),0)-VLOOKUP("파생상품손실",BS연결,MATCH(O$1,BS연결H,0),0))/100,"") | P14: =SUM(L14:O14) | Q14: =IFERROR((VLOOKUP("파생상품이익",BS연결,MATCH(Q$1,BS연결H,0),0)-VLOOKUP("파생상품손실",BS연결,MATCH(Q$1,BS연결H,0),0))/100,"") | R14: =IFERROR((VLOOKUP("파생상품이익",BS연결,MATCH(R$1,BS연결H,0),0)-VLOOKUP("파생상품손실",BS연결,MATCH(R$1,BS연결H,0),0))/100,"") | S14: =IFERROR((VLOOKUP("파생상품이익",BS연결,MATCH(S$1,BS연결H,0),0)-VLOOKUP("파생상품손실",BS연결,MATCH(S$1,BS연결H,0),0))/100,"") | T14: =IFERROR((VLOOKUP("파생상품이익",BS연결,MATCH(T$1,BS연결H,0),0)-VLOOKUP("파생상품손실",BS연결,MATCH(T$1,BS연결H,0),0))/100,"") | U14: =SUM(Q14:T14) | Z14: =SUM(V14:Y14) | AB14: =IFERROR((VLOOKUP("파생상품이익",BS연결,MATCH(AB$1,BS연결H,0),0)-VLOOKUP("파생상품손실",BS연결,MATCH(AB$1,BS연결H,0),0))/100,"") | AC14: =변수!AC25 | AD14: =변수!AD25 | AE14: =SUM(AA14:AD14) | AF14: =변수!AF25 | AG14: =변수!AG25 | AH14: =변수!AH25 | AI14: =변수!AI25 | AJ14: =SUM(AF14:AI14) | AK14: =변수!AK25 | AL14: =변수!AL25 | AM14: =변수!AM25 | AN14: =변수!AN25 | AO14: =SUM(AK14:AN14)
A15: 기타금융손익 | B15: 손익 | C15: 억원 | D15: 기타금융손익(금융손익 잔차) | K15: =SUM(G15:J15) | P15: =SUM(L15:O15) | U15: =SUM(Q15:T15) | Z15: =SUM(V15:Y15) | AB15: =IFERROR(AB11-AB12-AB13-AB14,"") | AC15: =변수!AC26 | AD15: =변수!AD26 | AE15: =SUM(AA15:AD15) | AF15: =변수!AF26 | AG15: =변수!AG26 | AH15: =변수!AH26 | AI15: =변수!AI26 | AJ15: =SUM(AF15:AI15) | AK15: =변수!AK26 | AL15: =변수!AL26 | AM15: =변수!AM26 | AN15: =변수!AN26 | AO15: =SUM(AK15:AN15)
A16: 기타영업외손익 | B16: 손익 | C16: 억원 | D16: 기타영업외손익 | E16: =IFERROR(VLOOKUP($D16,BS연결,MATCH(E$1,BS연결H,0),0)/100,"") | G16: =IFERROR(VLOOKUP($D16,BS연결,MATCH(G$1,BS연결H,0),0)/100,"") | H16: =IFERROR(VLOOKUP($D16,BS연결,MATCH(H$1,BS연결H,0),0)/100,"") | I16: =IFERROR(VLOOKUP($D16,BS연결,MATCH(I$1,BS연결H,0),0)/100,"") | J16: =IFERROR(VLOOKUP($D16,BS연결,MATCH(J$1,BS연결H,0),0)/100,"") | K16: =SUM(G16:J16) | L16: =IFERROR(VLOOKUP($D16,BS연결,MATCH(L$1,BS연결H,0),0)/100,"") | M16: =IFERROR(VLOOKUP($D16,BS연결,MATCH(M$1,BS연결H,0),0)/100,"") | N16: =IFERROR(VLOOKUP($D16,BS연결,MATCH(N$1,BS연결H,0),0)/100,"") | O16: =IFERROR(VLOOKUP($D16,BS연결,MATCH(O$1,BS연결H,0),0)/100,"") | P16: =IFERROR(VLOOKUP($D16,BS연결,MATCH(P$1,BS연결H,0),0)/100,"") | Q16: =IFERROR(VLOOKUP($D16,BS연결,MATCH(Q$1,BS연결H,0),0)/100,"") | R16: =IFERROR(VLOOKUP($D16,BS연결,MATCH(R$1,BS연결H,0),0)/100,"") | S16: =IFERROR(VLOOKUP($D16,BS연결,MATCH(S$1,BS연결H,0),0)/100,"") | ... AB16: =IFERROR(VLOOKUP($D16,BS연결,MATCH(AB$1,BS연결H,0),0)/100,"") | AC16: =변수!AC27 | AD16: =변수!AD27 | AE16: =SUM(AA16:AD16) | AF16: =변수!AF27 | AG16: =변수!AG27 | AH16: =변수!AH27 | AI16: =변수!AI27 | AJ16: =SUM(AF16:AI16) | AK16: =변수!AK27 | AL16: =변수!AL27 | AM16: =변수!AM27 | AN16: =변수!AN27 | AO16: =SUM(AK16:AN16)
A17: 지분법손익 | B17: 손익 | C17: 억원 | D17: 종속기업,공동지배기업및관계기업관련손익 | G17: =IFERROR(VLOOKUP($D17,BS연결,MATCH(G$1,BS연결H,0),0)/100,"") | H17: =IFERROR(VLOOKUP($D17,BS연결,MATCH(H$1,BS연결H,0),0)/100,"") | I17: =IFERROR(VLOOKUP($D17,BS연결,MATCH(I$1,BS연결H,0),0)/100,"") | J17: =IFERROR(VLOOKUP($D17,BS연결,MATCH(J$1,BS연결H,0),0)/100,"") | K17: =IFERROR(VLOOKUP($D17,BS연결,MATCH(K$1,BS연결H,0),0)/100,"") | L17: =IFERROR(VLOOKUP($D17,BS연결,MATCH(L$1,BS연결H,0),0)/100,"") | M17: =IFERROR(VLOOKUP($D17,BS연결,MATCH(M$1,BS연결H,0),0)/100,"") | N17: =IFERROR(VLOOKUP($D17,BS연결,MATCH(N$1,BS연결H,0),0)/100,"") | ... X17: =IFERROR(VLOOKUP($D17,BS연결,MATCH(X$1,BS연결H,0),0)/100,"") | Z17: =SUM(V17:Y17) | AA17: =IFERROR(VLOOKUP($D17,BS연결,MATCH(AA$1,BS연결H,0),0)/100,"") | AC17: =변수!AC28 | AD17: =변수!AD28 | AE17: =SUM(AA17:AD17) | AF17: =변수!AF28 | AG17: =변수!AG28 | AH17: =변수!AH28 | AI17: =변수!AI28 | AJ17: =SUM(AF17:AI17) | AK17: =변수!AK28 | AL17: =변수!AL28 | AM17: =변수!AM28 | AN17: =변수!AN28 | AO17: =SUM(AK17:AN17)
A18: 세전이익 | B18: 손익 | C18: 억원 | D18: 법인세비용차감전계속사업이익 | E18: =IFERROR(VLOOKUP($D18,BS연결,MATCH(E$1,BS연결H,0),0)/100,"") | G18: =IFERROR(VLOOKUP($D18,BS연결,MATCH(G$1,BS연결H,0),0)/100,"") | H18: =IFERROR(VLOOKUP($D18,BS연결,MATCH(H$1,BS연결H,0),0)/100,"") | I18: =IFERROR(VLOOKUP($D18,BS연결,MATCH(I$1,BS연결H,0),0)/100,"") | J18: =IFERROR(VLOOKUP($D18,BS연결,MATCH(J$1,BS연결H,0),0)/100,"") | K18: =IFERROR(VLOOKUP($D18,BS연결,MATCH(K$1,BS연결H,0),0)/100,"") | L18: =IFERROR(VLOOKUP($D18,BS연결,MATCH(L$1,BS연결H,0),0)/100,"") | M18: =IFERROR(VLOOKUP($D18,BS연결,MATCH(M$1,BS연결H,0),0)/100,"") | N18: =IFERROR(VLOOKUP($D18,BS연결,MATCH(N$1,BS연결H,0),0)/100,"") | ... AB18: =IFERROR(VLOOKUP($D18,BS연결,MATCH(AB$1,BS연결H,0),0)/100,"") | AC18: =IFERROR(AC9+AC11+AC16+AC17,"") | AD18: =IFERROR(AD9+AD11+AD16+AD17,"") | AE18: =SUM(AA18:AD18) | AF18: =IFERROR(AF9+AF11+AF16+AF17,"") | AG18: =IFERROR(AG9+AG11+AG16+AG17,"") | AH18: =IFERROR(AH9+AH11+AH16+AH17,"") | AI18: =IFERROR(AI9+AI11+AI16+AI17,"") | AJ18: =SUM(AF18:AI18) | AK18: =IFERROR(AK9+AK11+AK16+AK17,"") | AL18: =IFERROR(AL9+AL11+AL16+AL17,"") | AM18: =IFERROR(AM9+AM11+AM16+AM17,"") | AN18: =IFERROR(AN9+AN11+AN16+AN17,"") | AO18: =SUM(AK18:AN18)
A19: 법인세비용 | B19: 손익 | C19: 억원 | D19: 법인세비용 | E19: =IFERROR(VLOOKUP($D19,BS연결,MATCH(E$1,BS연결H,0),0)/100,"") | G19: =IFERROR(VLOOKUP($D19,BS연결,MATCH(G$1,BS연결H,0),0)/100,"") | H19: =IFERROR(VLOOKUP($D19,BS연결,MATCH(H$1,BS연결H,0),0)/100,"") | I19: =IFERROR(VLOOKUP($D19,BS연결,MATCH(I$1,BS연결H,0),0)/100,"") | J19: =IFERROR(VLOOKUP($D19,BS연결,MATCH(J$1,BS연결H,0),0)/100,"") | K19: =IFERROR(VLOOKUP($D19,BS연결,MATCH(K$1,BS연결H,0),0)/100,"") | L19: =IFERROR(VLOOKUP($D19,BS연결,MATCH(L$1,BS연결H,0),0)/100,"") | M19: =IFERROR(VLOOKUP($D19,BS연결,MATCH(M$1,BS연결H,0),0)/100,"") | N19: =IFERROR(VLOOKUP($D19,BS연결,MATCH(N$1,BS연결H,0),0)/100,"") | ... AB19: =IFERROR(VLOOKUP($D19,BS연결,MATCH(AB$1,BS연결H,0),0)/100,"") | AC19: =IFERROR(AC18*변수!AC29,"") | AD19: =IFERROR(AD18*변수!AD29,"") | AE19: =SUM(AA19:AD19) | AF19: =IFERROR(AF18*변수!AF29,"") | AG19: =IFERROR(AG18*변수!AG29,"") | AH19: =IFERROR(AH18*변수!AH29,"") | AI19: =IFERROR(AI18*변수!AI29,"") | AJ19: =SUM(AF19:AI19) | AK19: =IFERROR(AK18*변수!AK29,"") | AL19: =IFERROR(AL18*변수!AL29,"") | AM19: =IFERROR(AM18*변수!AM29,"") | AN19: =IFERROR(AN18*변수!AN29,"") | AO19: =SUM(AK19:AN19)
A20: 당기순이익 | B20: 손익 | C20: 억원 | D20: 당기순이익 | E20: =IFERROR(VLOOKUP($D20,BS연결,MATCH(E$1,BS연결H,0),0)/100,"") | G20: =IFERROR(VLOOKUP($D20,BS연결,MATCH(G$1,BS연결H,0),0)/100,"") | H20: =IFERROR(VLOOKUP($D20,BS연결,MATCH(H$1,BS연결H,0),0)/100,"") | I20: =IFERROR(VLOOKUP($D20,BS연결,MATCH(I$1,BS연결H,0),0)/100,"") | J20: =IFERROR(VLOOKUP($D20,BS연결,MATCH(J$1,BS연결H,0),0)/100,"") | K20: =IFERROR(VLOOKUP($D20,BS연결,MATCH(K$1,BS연결H,0),0)/100,"") | L20: =IFERROR(VLOOKUP($D20,BS연결,MATCH(L$1,BS연결H,0),0)/100,"") | M20: =IFERROR(VLOOKUP($D20,BS연결,MATCH(M$1,BS연결H,0),0)/100,"") | N20: =IFERROR(VLOOKUP($D20,BS연결,MATCH(N$1,BS연결H,0),0)/100,"") | ... AB20: =IFERROR(VLOOKUP($D20,BS연결,MATCH(AB$1,BS연결H,0),0)/100,"") | AC20: =IFERROR(AC18-AC19,"") | AD20: =IFERROR(AD18-AD19,"") | AE20: =SUM(AA20:AD20) | AF20: =IFERROR(AF18-AF19,"") | AG20: =IFERROR(AG18-AG19,"") | AH20: =IFERROR(AH18-AH19,"") | AI20: =IFERROR(AI18-AI19,"") | AJ20: =SUM(AF20:AI20) | AK20: =IFERROR(AK18-AK19,"") | AL20: =IFERROR(AL18-AL19,"") | AM20: =IFERROR(AM18-AM19,"") | AN20: =IFERROR(AN18-AN19,"") | AO20: =SUM(AK20:AN20)
A21: 지배주주순이익 | B21: 손익 | C21: 억원 | D21: (지배주주지분)당기순이익 | E21: =IFERROR(VLOOKUP($D21,BS연결,MATCH(E$1,BS연결H,0),0)/100,"") | G21: =IFERROR(VLOOKUP($D21,BS연결,MATCH(G$1,BS연결H,0),0)/100,"") | H21: =IFERROR(VLOOKUP($D21,BS연결,MATCH(H$1,BS연결H,0),0)/100,"") | I21: =IFERROR(VLOOKUP($D21,BS연결,MATCH(I$1,BS연결H,0),0)/100,"") | J21: =IFERROR(VLOOKUP($D21,BS연결,MATCH(J$1,BS연결H,0),0)/100,"") | K21: =IFERROR(VLOOKUP($D21,BS연결,MATCH(K$1,BS연결H,0),0)/100,"") | L21: =IFERROR(VLOOKUP($D21,BS연결,MATCH(L$1,BS연결H,0),0)/100,"") | M21: =IFERROR(VLOOKUP($D21,BS연결,MATCH(M$1,BS연결H,0),0)/100,"") | N21: =IFERROR(VLOOKUP($D21,BS연결,MATCH(N$1,BS연결H,0),0)/100,"") | ... AB21: =IFERROR(VLOOKUP($D21,BS연결,MATCH(AB$1,BS연결H,0),0)/100,"") | AC21: =IFERROR(AC20*변수!AC30,"") | AD21: =IFERROR(AD20*변수!AD30,"") | AE21: =SUM(AA21:AD21) | AF21: =IFERROR(AF20*변수!AF30,"") | AG21: =IFERROR(AG20*변수!AG30,"") | AH21: =IFERROR(AH20*변수!AH30,"") | AI21: =IFERROR(AI20*변수!AI30,"") | AJ21: =SUM(AF21:AI21) | AK21: =IFERROR(AK20*변수!AK30,"") | AL21: =IFERROR(AL20*변수!AL30,"") | AM21: =IFERROR(AM20*변수!AM30,"") | AN21: =IFERROR(AN20*변수!AN30,"") | AO21: =SUM(AK21:AN21)
A22: 중단사업이익 | B22: 손익 | C22: 억원 | D22: 중단사업이익 | E22: =IFERROR(VLOOKUP($D22,BS연결,MATCH(E$1,BS연결H,0),0)/100,"") | K22: =SUM(G22:J22) | P22: =SUM(L22:O22) | T22: =IFERROR(VLOOKUP($D22,BS연결,MATCH(T$1,BS연결H,0),0)/100,"") | U22: =SUM(Q22:T22) | V22: =IFERROR(VLOOKUP($D22,BS연결,MATCH(V$1,BS연결H,0),0)/100,"") | Y22: =IFERROR(VLOOKUP($D22,BS연결,MATCH(Y$1,BS연결H,0),0)/100,"") | Z22: =SUM(V22:Y22) | AE22: =SUM(AA22:AD22) | AJ22: =SUM(AF22:AI22) | AO22: =SUM(AK22:AN22)
A23: 자산총계 | B23: 재무상태 | C23: 억원 | D23: 자산총계 | E23: =IFERROR(VLOOKUP($D23,BS연결,MATCH(E$1,BS연결H,0),0)/100,"") | F23: =IFERROR(VLOOKUP($D23,BS연결,MATCH(F$1,BS연결H,0),0)/100,"") | G23: =IFERROR(VLOOKUP($D23,BS연결,MATCH(G$1,BS연결H,0),0)/100,"") | H23: =IFERROR(VLOOKUP($D23,BS연결,MATCH(H$1,BS연결H,0),0)/100,"") | I23: =IFERROR(VLOOKUP($D23,BS연결,MATCH(I$1,BS연결H,0),0)/100,"") | J23: =IFERROR(VLOOKUP($D23,BS연결,MATCH(J$1,BS연결H,0),0)/100,"") | K23: =IFERROR(VLOOKUP($D23,BS연결,MATCH(K$1,BS연결H,0),0)/100,"") | L23: =IFERROR(VLOOKUP($D23,BS연결,MATCH(L$1,BS연결H,0),0)/100,"") | ... AB23: =IFERROR(VLOOKUP($D23,BS연결,MATCH(AB$1,BS연결H,0),0)/100,"") | AC23: =IFERROR(AC24+AC25,"") | AD23: =IFERROR(AD24+AD25,"") | AE23: =AD23 | AF23: =IFERROR(AF24+AF25,"") | AG23: =IFERROR(AG24+AG25,"") | AH23: =IFERROR(AH24+AH25,"") | AI23: =IFERROR(AI24+AI25,"") | AJ23: =AI23 | AK23: =IFERROR(AK24+AK25,"") | AL23: =IFERROR(AL24+AL25,"") | AM23: =IFERROR(AM24+AM25,"") | AN23: =IFERROR(AN24+AN25,"") | AO23: =AN23
A24: 부채총계 | B24: 재무상태 | C24: 억원 | D24: 부채총계 | E24: =IFERROR(VLOOKUP($D24,BS연결,MATCH(E$1,BS연결H,0),0)/100,"") | F24: =IFERROR(VLOOKUP($D24,BS연결,MATCH(F$1,BS연결H,0),0)/100,"") | G24: =IFERROR(VLOOKUP($D24,BS연결,MATCH(G$1,BS연결H,0),0)/100,"") | H24: =IFERROR(VLOOKUP($D24,BS연결,MATCH(H$1,BS연결H,0),0)/100,"") | I24: =IFERROR(VLOOKUP($D24,BS연결,MATCH(I$1,BS연결H,0),0)/100,"") | J24: =IFERROR(VLOOKUP($D24,BS연결,MATCH(J$1,BS연결H,0),0)/100,"") | K24: =IFERROR(VLOOKUP($D24,BS연결,MATCH(K$1,BS연결H,0),0)/100,"") | L24: =IFERROR(VLOOKUP($D24,BS연결,MATCH(L$1,BS연결H,0),0)/100,"") | ... AB24: =IFERROR(VLOOKUP($D24,BS연결,MATCH(AB$1,BS연결H,0),0)/100,"") | AC24: =IFERROR(AB24*(1+변수!AC32),"") | AD24: =IFERROR(AC24*(1+변수!AD32),"") | AE24: =AD24 | AF24: =IFERROR(AD24*(1+변수!AF32),"") | AG24: =IFERROR(AF24*(1+변수!AG32),"") | AH24: =IFERROR(AG24*(1+변수!AH32),"") | AI24: =IFERROR(AH24*(1+변수!AI32),"") | AJ24: =AI24 | AK24: =IFERROR(AI24*(1+변수!AK32),"") | AL24: =IFERROR(AK24*(1+변수!AL32),"") | AM24: =IFERROR(AL24*(1+변수!AM32),"") | AN24: =IFERROR(AM24*(1+변수!AN32),"") | AO24: =AN24
A25: 자본총계 | B25: 재무상태 | C25: 억원 | D25: 자본총계 | E25: =IFERROR(VLOOKUP($D25,BS연결,MATCH(E$1,BS연결H,0),0)/100,"") | F25: =IFERROR(VLOOKUP($D25,BS연결,MATCH(F$1,BS연결H,0),0)/100,"") | G25: =IFERROR(VLOOKUP($D25,BS연결,MATCH(G$1,BS연결H,0),0)/100,"") | H25: =IFERROR(VLOOKUP($D25,BS연결,MATCH(H$1,BS연결H,0),0)/100,"") | I25: =IFERROR(VLOOKUP($D25,BS연결,MATCH(I$1,BS연결H,0),0)/100,"") | J25: =IFERROR(VLOOKUP($D25,BS연결,MATCH(J$1,BS연결H,0),0)/100,"") | K25: =IFERROR(VLOOKUP($D25,BS연결,MATCH(K$1,BS연결H,0),0)/100,"") | L25: =IFERROR(VLOOKUP($D25,BS연결,MATCH(L$1,BS연결H,0),0)/100,"") | ... AB25: =IFERROR(VLOOKUP($D25,BS연결,MATCH(AB$1,BS연결H,0),0)/100,"") | AC25: =IFERROR(AB25+AC20-변수!AC33,"") | AD25: =IFERROR(AC25+AD20-변수!AD33,"") | AE25: =AD25 | AF25: =IFERROR(AD25+AF20-변수!AF33,"") | AG25: =IFERROR(AF25+AG20-변수!AG33,"") | AH25: =IFERROR(AG25+AH20-변수!AH33,"") | AI25: =IFERROR(AH25+AI20-변수!AI33,"") | AJ25: =AI25 | AK25: =IFERROR(AI25+AK20-변수!AK33,"") | AL25: =IFERROR(AK25+AL20-변수!AL33,"") | AM25: =IFERROR(AL25+AM20-변수!AM33,"") | AN25: =IFERROR(AM25+AN20-변수!AN33,"") | AO25: =AN25
A26: 지배주주지분 | B26: 재무상태 | C26: 억원 | D26: 지배주주지분 | E26: =IFERROR(VLOOKUP($D26,BS연결,MATCH(E$1,BS연결H,0),0)/100,"") | F26: =IFERROR(VLOOKUP($D26,BS연결,MATCH(F$1,BS연결H,0),0)/100,"") | G26: =IFERROR(VLOOKUP($D26,BS연결,MATCH(G$1,BS연결H,0),0)/100,"") | H26: =IFERROR(VLOOKUP($D26,BS연결,MATCH(H$1,BS연결H,0),0)/100,"") | I26: =IFERROR(VLOOKUP($D26,BS연결,MATCH(I$1,BS연결H,0),0)/100,"") | J26: =IFERROR(VLOOKUP($D26,BS연결,MATCH(J$1,BS연결H,0),0)/100,"") | K26: =IFERROR(VLOOKUP($D26,BS연결,MATCH(K$1,BS연결H,0),0)/100,"") | L26: =IFERROR(VLOOKUP($D26,BS연결,MATCH(L$1,BS연결H,0),0)/100,"") | ... AB26: =IFERROR(VLOOKUP($D26,BS연결,MATCH(AB$1,BS연결H,0),0)/100,"") | AC26: =IFERROR(AB26+AC21-변수!AC34,"") | AD26: =IFERROR(AC26+AD21-변수!AD34,"") | AE26: =AD26 | AF26: =IFERROR(AD26+AF21-변수!AF34,"") | AG26: =IFERROR(AF26+AG21-변수!AG34,"") | AH26: =IFERROR(AG26+AH21-변수!AH34,"") | AI26: =IFERROR(AH26+AI21-변수!AI34,"") | AJ26: =AI26 | AK26: =IFERROR(AI26+AK21-변수!AK34,"") | AL26: =IFERROR(AK26+AL21-변수!AL34,"") | AM26: =IFERROR(AL26+AM21-변수!AM34,"") | AN26: =IFERROR(AM26+AN21-변수!AN34,"") | AO26: =AN26
A27: 총차입금 | B27: 재무상태 | C27: 억원 | D27: 총차입금 | E27: =IFERROR(VLOOKUP($D27,BS연결,MATCH(E$1,BS연결H,0),0)/100,"") | F27: =IFERROR(VLOOKUP($D27,BS연결,MATCH(F$1,BS연결H,0),0)/100,"") | G27: =IFERROR(VLOOKUP($D27,BS연결,MATCH(G$1,BS연결H,0),0)/100,"") | H27: =IFERROR(VLOOKUP($D27,BS연결,MATCH(H$1,BS연결H,0),0)/100,"") | I27: =IFERROR(VLOOKUP($D27,BS연결,MATCH(I$1,BS연결H,0),0)/100,"") | J27: =IFERROR(VLOOKUP($D27,BS연결,MATCH(J$1,BS연결H,0),0)/100,"") | K27: =IFERROR(VLOOKUP($D27,BS연결,MATCH(K$1,BS연결H,0),0)/100,"") | L27: =IFERROR(VLOOKUP($D27,BS연결,MATCH(L$1,BS연결H,0),0)/100,"") | ... AB27: =IFERROR(VLOOKUP($D27,BS연결,MATCH(AB$1,BS연결H,0),0)/100,"") | AC27: =IFERROR(AB27*(1+변수!AC35),"") | AD27: =IFERROR(AC27*(1+변수!AD35),"") | AE27: =AD27 | AF27: =IFERROR(AD27*(1+변수!AF35),"") | AG27: =IFERROR(AF27*(1+변수!AG35),"") | AH27: =IFERROR(AG27*(1+변수!AH35),"") | AI27: =IFERROR(AH27*(1+변수!AI35),"") | AJ27: =AI27 | AK27: =IFERROR(AI27*(1+변수!AK35),"") | AL27: =IFERROR(AK27*(1+변수!AL35),"") | AM27: =IFERROR(AL27*(1+변수!AM35),"") | AN27: =IFERROR(AM27*(1+변수!AN35),"") | AO27: =AN27
A28: 순차입금 | B28: 재무상태 | C28: 억원 | D28: 순차입금 | E28: =IFERROR(VLOOKUP($D28,BS연결,MATCH(E$1,BS연결H,0),0)/100,"") | F28: =IFERROR(VLOOKUP($D28,BS연결,MATCH(F$1,BS연결H,0),0)/100,"") | G28: =IFERROR(VLOOKUP($D28,BS연결,MATCH(G$1,BS연결H,0),0)/100,"") | H28: =IFERROR(VLOOKUP($D28,BS연결,MATCH(H$1,BS연결H,0),0)/100,"") | I28: =IFERROR(VLOOKUP($D28,BS연결,MATCH(I$1,BS연결H,0),0)/100,"") | J28: =IFERROR(VLOOKUP($D28,BS연결,MATCH(J$1,BS연결H,0),0)/100,"") | K28: =IFERROR(VLOOKUP($D28,BS연결,MATCH(K$1,BS연결H,0),0)/100,"") | L28: =IFERROR(VLOOKUP($D28,BS연결,MATCH(L$1,BS연결H,0),0)/100,"") | ... AB28: =IFERROR(VLOOKUP($D28,BS연결,MATCH(AB$1,BS연결H,0),0)/100,"") | AC28: =IFERROR(AB28*(1+변수!AC36),"") | AD28: =IFERROR(AC28*(1+변수!AD36),"") | AE28: =AD28 | AF28: =IFERROR(AD28*(1+변수!AF36),"") | AG28: =IFERROR(AF28*(1+변수!AG36),"") | AH28: =IFERROR(AG28*(1+변수!AH36),"") | AI28: =IFERROR(AH28*(1+변수!AI36),"") | AJ28: =AI28 | AK28: =IFERROR(AI28*(1+변수!AK36),"") | AL28: =IFERROR(AK28*(1+변수!AL36),"") | AM28: =IFERROR(AL28*(1+변수!AM36),"") | AN28: =IFERROR(AM28*(1+변수!AN36),"") | AO28: =AN28
A29: 이자발생자산 | B29: 재무상태 | C29: 억원 | D29: 이자발생자산 | E29: =IFERROR(VLOOKUP($D29,BS연결,MATCH(E$1,BS연결H,0),0)/100,"") | F29: =IFERROR(VLOOKUP($D29,BS연결,MATCH(F$1,BS연결H,0),0)/100,"") | G29: =IFERROR(VLOOKUP($D29,BS연결,MATCH(G$1,BS연결H,0),0)/100,"") | H29: =IFERROR(VLOOKUP($D29,BS연결,MATCH(H$1,BS연결H,0),0)/100,"") | I29: =IFERROR(VLOOKUP($D29,BS연결,MATCH(I$1,BS연결H,0),0)/100,"") | J29: =IFERROR(VLOOKUP($D29,BS연결,MATCH(J$1,BS연결H,0),0)/100,"") | K29: =IFERROR(VLOOKUP($D29,BS연결,MATCH(K$1,BS연결H,0),0)/100,"") | L29: =IFERROR(VLOOKUP($D29,BS연결,MATCH(L$1,BS연결H,0),0)/100,"") | ... AB29: =IFERROR(VLOOKUP($D29,BS연결,MATCH(AB$1,BS연결H,0),0)/100,"") | AC29: =IFERROR(AB29*(1+변수!AC37),"") | AD29: =IFERROR(AC29*(1+변수!AD37),"") | AE29: =AD29 | AF29: =IFERROR(AD29*(1+변수!AF37),"") | AG29: =IFERROR(AF29*(1+변수!AG37),"") | AH29: =IFERROR(AG29*(1+변수!AH37),"") | AI29: =IFERROR(AH29*(1+변수!AI37),"") | AJ29: =AI29 | AK29: =IFERROR(AI29*(1+변수!AK37),"") | AL29: =IFERROR(AK29*(1+변수!AL37),"") | AM29: =IFERROR(AL29*(1+변수!AM37),"") | AN29: =IFERROR(AM29*(1+변수!AN37),"") | AO29: =AN29
A30: 현금및현금성자산 | B30: 재무상태 | C30: 억원 | D30: 현금및현금성자산 | E30: =IFERROR(VLOOKUP($D30,BS연결,MATCH(E$1,BS연결H,0),0)/100,"") | F30: =IFERROR(VLOOKUP($D30,BS연결,MATCH(F$1,BS연결H,0),0)/100,"") | G30: =IFERROR(VLOOKUP($D30,BS연결,MATCH(G$1,BS연결H,0),0)/100,"") | H30: =IFERROR(VLOOKUP($D30,BS연결,MATCH(H$1,BS연결H,0),0)/100,"") | I30: =IFERROR(VLOOKUP($D30,BS연결,MATCH(I$1,BS연결H,0),0)/100,"") | J30: =IFERROR(VLOOKUP($D30,BS연결,MATCH(J$1,BS연결H,0),0)/100,"") | K30: =IFERROR(VLOOKUP($D30,BS연결,MATCH(K$1,BS연결H,0),0)/100,"") | L30: =IFERROR(VLOOKUP($D30,BS연결,MATCH(L$1,BS연결H,0),0)/100,"") | ... AB30: =IFERROR(VLOOKUP($D30,BS연결,MATCH(AB$1,BS연결H,0),0)/100,"") | AE30: =AD30 | AJ30: =AI30 | AO30: =AN30
A31: CAPEX | B31: 현금흐름 | C31: 억원 | D31: CAPEX | E31: =IFERROR(VLOOKUP($D31,BS연결,MATCH(E$1,BS연결H,0),0)/100,"") | G31: =IFERROR(VLOOKUP($D31,BS연결,MATCH(G$1,BS연결H,0),0)/100,"") | H31: =IFERROR(VLOOKUP($D31,BS연결,MATCH(H$1,BS연결H,0),0)/100,"") | I31: =IFERROR(VLOOKUP($D31,BS연결,MATCH(I$1,BS연결H,0),0)/100,"") | J31: =IFERROR(VLOOKUP($D31,BS연결,MATCH(J$1,BS연결H,0),0)/100,"") | K31: =IFERROR(VLOOKUP($D31,BS연결,MATCH(K$1,BS연결H,0),0)/100,"") | L31: =IFERROR(VLOOKUP($D31,BS연결,MATCH(L$1,BS연결H,0),0)/100,"") | M31: =IFERROR(VLOOKUP($D31,BS연결,MATCH(M$1,BS연결H,0),0)/100,"") | N31: =IFERROR(VLOOKUP($D31,BS연결,MATCH(N$1,BS연결H,0),0)/100,"") | ... AB31: =IFERROR(VLOOKUP($D31,BS연결,MATCH(AB$1,BS연결H,0),0)/100,"") | AC31: =IFERROR(X31*(1+변수!AC39),"") | AD31: =IFERROR(Y31*(1+변수!AD39),"") | AE31: =SUM(AA31:AD31) | AF31: =IFERROR(AA31*(1+변수!AF39),"") | AG31: =IFERROR(AB31*(1+변수!AG39),"") | AH31: =IFERROR(AC31*(1+변수!AH39),"") | AI31: =IFERROR(AD31*(1+변수!AI39),"") | AJ31: =SUM(AF31:AI31) | AK31: =IFERROR(AF31*(1+변수!AK39),"") | AL31: =IFERROR(AG31*(1+변수!AL39),"") | AM31: =IFERROR(AH31*(1+변수!AM39),"") | AN31: =IFERROR(AI31*(1+변수!AN39),"") | AO31: =SUM(AK31:AN31)
A32: 영업활동현금흐름 | B32: 현금흐름 | C32: 억원 | D32: 영업활동으로인한현금흐름 | E32: =IFERROR(VLOOKUP($D32,BS연결,MATCH(E$1,BS연결H,0),0)/100,"") | G32: =IFERROR(VLOOKUP($D32,BS연결,MATCH(G$1,BS연결H,0),0)/100,"") | H32: =IFERROR(VLOOKUP($D32,BS연결,MATCH(H$1,BS연결H,0),0)/100,"") | I32: =IFERROR(VLOOKUP($D32,BS연결,MATCH(I$1,BS연결H,0),0)/100,"") | J32: =IFERROR(VLOOKUP($D32,BS연결,MATCH(J$1,BS연결H,0),0)/100,"") | K32: =IFERROR(VLOOKUP($D32,BS연결,MATCH(K$1,BS연결H,0),0)/100,"") | L32: =IFERROR(VLOOKUP($D32,BS연결,MATCH(L$1,BS연결H,0),0)/100,"") | M32: =IFERROR(VLOOKUP($D32,BS연결,MATCH(M$1,BS연결H,0),0)/100,"") | N32: =IFERROR(VLOOKUP($D32,BS연결,MATCH(N$1,BS연결H,0),0)/100,"") | ... AB32: =IFERROR(VLOOKUP($D32,BS연결,MATCH(AB$1,BS연결H,0),0)/100,"") | AE32: =SUM(AA32:AD32) | AJ32: =SUM(AF32:AI32) | AO32: =SUM(AK32:AN32)
A33: 주식수 | B33: 주당 | C33: 백만주 | D33: 유통주식수 | E33: 13.900369 | F33: =E33 | G33: 13.900369 | H33: 13.900369 | I33: 13.900369 | J33: 13.900369 | K33: =J33 | L33: 13.900369 | M33: 13.900369 | N33: 13.900369 | O33: 13.900369 | P33: =O33 | Q33: 13.900369 | R33: 13.634061 | S33: 13.634061 | T33: 13.634061 | U33: =T33 | V33: 13.634061 | W33: 13.634061 | X33: 13.634061 | Y33: 13.620703 | Z33: =Y33 | AA33: 13.620703 | AB33: 14.008 | AC33: =IFERROR(AB33*(1+변수!AC41),"") | AD33: =IFERROR(AC33*(1+변수!AD41),"") | AE33: =AD33 | AF33: =IFERROR(AD33*(1+변수!AF41),"") | AG33: =IFERROR(AF33*(1+변수!AG41),"") | AH33: =IFERROR(AG33*(1+변수!AH41),"") | AI33: =IFERROR(AH33*(1+변수!AI41),"") | AJ33: =AI33 | AK33: =IFERROR(AI33*(1+변수!AK41),"") | AL33: =IFERROR(AK33*(1+변수!AL41),"") | AM33: =IFERROR(AL33*(1+변수!AM41),"") | AN33: =IFERROR(AM33*(1+변수!AN41),"") | AO33: =AN33
A34: EPS | B34: 주당 | C34: 원 | D34: EPS | E34: =IFERROR(E21*100/E33,"") | G34: =IFERROR(G21*100/G33,"") | H34: =IFERROR(H21*100/H33,"") | I34: =IFERROR(I21*100/I33,"") | J34: =IFERROR(J21*100/J33,"") | K34: =SUM(G34:J34) | L34: =IFERROR(L21*100/L33,"") | M34: =IFERROR(M21*100/M33,"") | N34: =IFERROR(N21*100/N33,"") | O34: =IFERROR(O21*100/O33,"") | P34: =SUM(L34:O34) | Q34: =IFERROR(Q21*100/Q33,"") | R34: =IFERROR(R21*100/R33,"") | S34: =IFERROR(S21*100/S33,"") | T34: =IFERROR(T21*100/T33,"") | U34: =SUM(Q34:T34) | V34: =IFERROR(V21*100/V33,"") | W34: =IFERROR(W21*100/W33,"") | X34: =IFERROR(X21*100/X33,"") | Y34: =IFERROR(Y21*100/Y33,"") | Z34: =SUM(V34:Y34) | AA34: =IFERROR(AA21*100/AA33,"") | AB34: =IFERROR(AB21*100/AB33,"") | AC34: =IFERROR(AC21*100/AC33,"") | AD34: =IFERROR(AD21*100/AD33,"") | AE34: =SUM(AA34:AD34) | AF34: =IFERROR(AF21*100/AF33,"") | AG34: =IFERROR(AG21*100/AG33,"") | AH34: =IFERROR(AH21*100/AH33,"") | AI34: =IFERROR(AI21*100/AI33,"") | AJ34: =SUM(AF34:AI34) | AK34: =IFERROR(AK21*100/AK33,"") | AL34: =IFERROR(AL21*100/AL33,"") | AM34: =IFERROR(AM21*100/AM33,"") | AN34: =IFERROR(AN21*100/AN33,"") | AO34: =SUM(AK34:AN34)
A35: 조정EPS | B35: 주당 | C35: 원 | D35: 조정 EPS(일회성 의심 분기의 초과 비영업손익 세후 차감 — 모델 추정) | E35: =IFERROR(E34,"") | G35: =IFERROR(G34,"") | H35: =IFERROR(H34,"") | I35: =IFERROR(I34,"") | J35: =IFERROR(J34,"") | K35: =SUM(G35:J35) | L35: =IFERROR(L34,"") | M35: =IFERROR(M34,"") | N35: =IFERROR(N34,"") | O35: =IFERROR(O34,"") | P35: =SUM(L35:O35) | Q35: =IFERROR(Q34,"") | R35: =IFERROR(R34,"") | S35: =IFERROR(S34,"") | T35: =IFERROR(T34,"") | U35: =SUM(Q35:T35) | V35: =IFERROR(V34,"") | W35: =IFERROR(W34,"") | X35: =IFERROR(X34,"") | Y35: =IFERROR((Y21-(-156.9)*(0.9315))*100/Y33,"") | Z35: =SUM(V35:Y35) | AA35: =IFERROR(AA34,"") | AB35: =IFERROR(AB34,"") | AC35: =IFERROR(AC34,"") | AD35: =IFERROR(AD34,"") | AE35: =SUM(AA35:AD35) | AF35: =IFERROR(AF34,"") | AG35: =IFERROR(AG34,"") | AH35: =IFERROR(AH34,"") | AI35: =IFERROR(AI34,"") | AJ35: =SUM(AF35:AI35) | AK35: =IFERROR(AK34,"") | AL35: =IFERROR(AL34,"") | AM35: =IFERROR(AM34,"") | AN35: =IFERROR(AN34,"") | AO35: =SUM(AK35:AN35)
A36: BPS | B36: 주당 | C36: 원 | D36: BPS | E36: =IFERROR(E26*100/E33,"") | F36: =E36 | G36: =IFERROR(G26*100/G33,"") | H36: =IFERROR(H26*100/H33,"") | I36: =IFERROR(I26*100/I33,"") | J36: =IFERROR(J26*100/J33,"") | K36: =J36 | L36: =IFERROR(L26*100/L33,"") | M36: =IFERROR(M26*100/M33,"") | N36: =IFERROR(N26*100/N33,"") | O36: =IFERROR(O26*100/O33,"") | P36: =O36 | Q36: =IFERROR(Q26*100/Q33,"") | R36: =IFERROR(R26*100/R33,"") | S36: =IFERROR(S26*100/S33,"") | T36: =IFERROR(T26*100/T33,"") | U36: =T36 | V36: =IFERROR(V26*100/V33,"") | W36: =IFERROR(W26*100/W33,"") | X36: =IFERROR(X26*100/X33,"") | Y36: =IFERROR(Y26*100/Y33,"") | Z36: =Y36 | AA36: =IFERROR(AA26*100/AA33,"") | AB36: =IFERROR(AB26*100/AB33,"") | AC36: =IFERROR(AC26*100/AC33,"") | AD36: =IFERROR(AD26*100/AD33,"") | AE36: =AD36 | AF36: =IFERROR(AF26*100/AF33,"") | AG36: =IFERROR(AG26*100/AG33,"") | AH36: =IFERROR(AH26*100/AH33,"") | AI36: =IFERROR(AI26*100/AI33,"") | AJ36: =AI36 | AK36: =IFERROR(AK26*100/AK33,"") | AL36: =IFERROR(AL26*100/AL33,"") | AM36: =IFERROR(AM26*100/AM33,"") | AN36: =IFERROR(AN26*100/AN33,"") | AO36: =AN36
A37: DPS | B37: 주당 | C37: 원 | D37: DPS(보통주) | E37: 0 | F37: 0 | J37: 0 | K37: =SUM(G37:J37) | O37: 0 | P37: =SUM(L37:O37) | T37: 0 | U37: =SUM(Q37:T37) | Y37: 0 | Z37: =SUM(V37:Y37) | AD37: =변수!AD42 | AE37: =SUM(AA37:AD37) | AI37: =변수!AI42 | AJ37: =SUM(AF37:AI37) | AN37: =변수!AN42 | AO37: =SUM(AK37:AN37)
A38: PER | B38: 주당 | C38: 배 | D38: PER | F38: =E38 | I38: =IFERROR(변수!I18/(E34+G34+H34+I34),"") | K38: =J38 | P38: =O38 | U38: =T38 | Z38: =Y38 | AE38: =AD38 | AJ38: =AI38 | AO38: =AN38
A39: PBR | B39: 주당 | C39: 배 | D39: PBR | E39: =IFERROR(변수!E18/E36,"") | F39: =E39 | G39: =IFERROR(변수!G18/G36,"") | H39: =IFERROR(변수!H18/H36,"") | I39: =IFERROR(변수!I18/I36,"") | J39: =IFERROR(변수!J18/J36,"") | K39: =J39 | L39: =IFERROR(변수!L18/L36,"") | M39: =IFERROR(변수!M18/M36,"") | N39: =IFERROR(변수!N18/N36,"") | O39: =IFERROR(변수!O18/O36,"") | P39: =O39 | Q39: =IFERROR(변수!Q18/Q36,"") | R39: =IFERROR(변수!R18/R36,"") | S39: =IFERROR(변수!S18/S36,"") | T39: =IFERROR(변수!T18/T36,"") | U39: =T39 | V39: =IFERROR(변수!V18/V36,"") | W39: =IFERROR(변수!W18/W36,"") | X39: =IFERROR(변수!X18/X36,"") | Y39: =IFERROR(변수!Y18/Y36,"") | Z39: =Y39 | AA39: =IFERROR(변수!AA18/AA36,"") | AB39: =IFERROR(변수!AB18/AB36,"") | AC39: =IFERROR(변수!$D$45/AC36,"") | AD39: =IFERROR(변수!$D$45/AD36,"") | AE39: =AD39 | AF39: =IFERROR(변수!$D$45/AF36,"") | AG39: =IFERROR(변수!$D$45/AG36,"") | AH39: =IFERROR(변수!$D$45/AH36,"") | AI39: =IFERROR(변수!$D$45/AI36,"") | AJ39: =AI39 | AK39: =IFERROR(변수!$D$45/AK36,"") | AL39: =IFERROR(변수!$D$45/AL36,"") | AM39: =IFERROR(변수!$D$45/AM36,"") | AN39: =IFERROR(변수!$D$45/AN36,"") | AO39: =AN39
A40: 매출전사 | B40: 사업부 | C40: 억원 | D40: 매출 전사(부문 미분리) | E40: 960.58 | G40: 1145.8 | H40: 1208.24 | I40: 1677.22 | J40: 1242.42 | K40: =SUM(G40:J40) | L40: 1231.72 | M40: 1327.06 | N40: 1338.8 | O40: 1102.52 | P40: =SUM(L40:O40) | Q40: 1250.35 | R40: 1269.61 | S40: 1190.02 | T40: 1093.51 | U40: =SUM(Q40:T40) | V40: 1109.85 | W40: 1162.82 | X40: 1098.95 | Y40: 963.22 | Z40: =SUM(V40:Y40) | AA40: 964.25 | AB40: 1067.67 | AC40: =IFERROR(AC5,"") | AD40: =IFERROR(AD5,"") | AE40: =SUM(AA40:AD40) | AF40: =IFERROR(AF5,"") | AG40: =IFERROR(AG5,"") | AH40: =IFERROR(AH5,"") | AI40: =IFERROR(AI5,"") | AJ40: =SUM(AF40:AI40) | AK40: =IFERROR(AK5,"") | AL40: =IFERROR(AL5,"") | AM40: =IFERROR(AM5,"") | AN40: =IFERROR(AN5,"") | AO40: =SUM(AK40:AN40)
A41: OP전사 | B41: 사업부 | C41: 억원 | D41: OP 전사(부문 미분리) | E41: 36.11 | G41: 17.4 | H41: 20.4 | I41: 17.08 | J41: -12.61 | K41: =SUM(G41:J41) | L41: -28.2 | M41: 23.57 | N41: 25.45 | O41: -8.29 | P41: =SUM(L41:O41) | Q41: 38.72 | R41: 27.44 | S41: -11.21 | T41: -24.22 | U41: =SUM(Q41:T41) | V41: -15.81 | W41: -23.84 | X41: -69.66 | Y41: -22.38 | Z41: =SUM(V41:Y41) | AA41: -14.39 | AB41: 21.74 | AC41: =IFERROR(AC9,"") | AD41: =IFERROR(AD9,"") | AE41: =SUM(AA41:AD41) | AF41: =IFERROR(AF9,"") | AG41: =IFERROR(AG9,"") | AH41: =IFERROR(AH9,"") | AI41: =IFERROR(AI9,"") | AJ41: =SUM(AF41:AI41) | AK41: =IFERROR(AK9,"") | AL41: =IFERROR(AL9,"") | AM41: =IFERROR(AM9,"") | AN41: =IFERROR(AN9,"") | AO41: =SUM(AK41:AN41)
B42: 비율(참고)
A43: NPM | C43: % | D43: 지배주주순이익 / 매출액 | E43: =IFERROR(E21/E5,"") | F43: =IFERROR(F21/F5,"") | G43: =IFERROR(G21/G5,"") | H43: =IFERROR(H21/H5,"") | I43: =IFERROR(I21/I5,"") | J43: =IFERROR(J21/J5,"") | K43: =IFERROR(K21/K5,"") | L43: =IFERROR(L21/L5,"") | ... AO43: =IFERROR(AO21/AO5,"")
A44: 매출원가율 | C44: % | D44: 매출원가 / 매출액 | E44: =IFERROR(E6/E5,"") | F44: =IFERROR(F6/F5,"") | G44: =IFERROR(G6/G5,"") | H44: =IFERROR(H6/H5,"") | I44: =IFERROR(I6/I5,"") | J44: =IFERROR(J6/J5,"") | K44: =IFERROR(K6/K5,"") | L44: =IFERROR(L6/L5,"") | ... AO44: =IFERROR(AO6/AO5,"")
A45: 판관비율 | C45: % | D45: 판관비 / 매출액 | E45: =IFERROR(E8/E5,"") | F45: =IFERROR(F8/F5,"") | G45: =IFERROR(G8/G5,"") | H45: =IFERROR(H8/H5,"") | I45: =IFERROR(I8/I5,"") | J45: =IFERROR(J8/J5,"") | K45: =IFERROR(K8/K5,"") | L45: =IFERROR(L8/L5,"") | ... AO45: =IFERROR(AO8/AO5,"")

Sheet 분기
C1: 이름: 분기H — subQ 를 이름으로 VLOOKUP(억원) | E1: 4Q21 | F1: 1Q22 | G1: 2Q22 | H1: 3Q22 | I1: 4Q22 | J1: 1Q23 | K1: 2Q23 | L1: 3Q23 | M1: 4Q23 | N1: 1Q24 | O1: 2Q24 | P1: 3Q24 | Q1: 4Q24 | R1: 1Q25 | S1: 2Q25 | T1: 3Q25 | U1: 4Q25 | V1: 1Q26 | W1: 2Q26 | X1: 3Q26 | Y1: 4Q26 | Z1: 1Q27 | AA1: 2Q27 | AB1: 3Q27 | AC1: 4Q27 | AD1: 1Q28 | AE1: 2Q28 | AF1: 3Q28 | AG1: 4Q28
C2: 종가: | D2: =변수!D45
C3: 기준일: | D3: 20261019 | E3: 1 | F3: 2 | G3: 3 | H3: 4 | I3: 5 | J3: 6 | K3: 7 | L3: 8 | M3: 9 | N3: 10 | O3: 11 | P3: 12 | Q3: 13 | R3: 14 | S3: 15 | T3: 16 | U3: 17 | V3: 18 | W3: 19 | X3: 20 | Y3: 21 | Z3: 22 | AA3: 23 | AB3: 24 | AC3: 25 | AD3: 26 | AE3: 27 | AF3: 28 | AG3: 29
E4: 2021.12 | F4: 2022.03 | G4: 2022.06 | H4: 2022.09 | I4: 2022.12 | J4: 2023.03 | K4: 2023.06 | L4: 2023.09 | M4: 2023.12 | N4: 2024.03 | O4: 2024.06 | P4: 2024.09 | Q4: 2024.12 | R4: 2025.03 | S4: 2025.06 | T4: 2025.09 | U4: 2025.12 | V4: 2026.03 | W4: 2026.06 | X4: 2026.09 | Y4: 2026.12 | Z4: 2027.03 | AA4: 2027.06 | AB4: 2027.09 | AC4: 2027.12 | AD4: 2028.03 | AE4: 2028.06 | AF4: 2028.09 | AG4: 2028.12
A5: 매출액 | D5: 매출액 | E5: =IFERROR(VLOOKUP($A5,subQ,MATCH(E$1,SUBQH,0),0),"") | F5: =IFERROR(VLOOKUP($A5,subQ,MATCH(F$1,SUBQH,0),0),"") | G5: =IFERROR(VLOOKUP($A5,subQ,MATCH(G$1,SUBQH,0),0),"") | H5: =IFERROR(VLOOKUP($A5,subQ,MATCH(H$1,SUBQH,0),0),"") | I5: =IFERROR(VLOOKUP($A5,subQ,MATCH(I$1,SUBQH,0),0),"") | J5: =IFERROR(VLOOKUP($A5,subQ,MATCH(J$1,SUBQH,0),0),"") | K5: =IFERROR(VLOOKUP($A5,subQ,MATCH(K$1,SUBQH,0),0),"") | L5: =IFERROR(VLOOKUP($A5,subQ,MATCH(L$1,SUBQH,0),0),"") | ... AG5: =IFERROR(VLOOKUP($A5,subQ,MATCH(AG$1,SUBQH,0),0),"")
A6: 매출원가 | D6: 매출원가 | E6: =IFERROR(VLOOKUP($A6,subQ,MATCH(E$1,SUBQH,0),0),"") | F6: =IFERROR(VLOOKUP($A6,subQ,MATCH(F$1,SUBQH,0),0),"") | G6: =IFERROR(VLOOKUP($A6,subQ,MATCH(G$1,SUBQH,0),0),"") | H6: =IFERROR(VLOOKUP($A6,subQ,MATCH(H$1,SUBQH,0),0),"") | I6: =IFERROR(VLOOKUP($A6,subQ,MATCH(I$1,SUBQH,0),0),"") | J6: =IFERROR(VLOOKUP($A6,subQ,MATCH(J$1,SUBQH,0),0),"") | K6: =IFERROR(VLOOKUP($A6,subQ,MATCH(K$1,SUBQH,0),0),"") | L6: =IFERROR(VLOOKUP($A6,subQ,MATCH(L$1,SUBQH,0),0),"") | ... AG6: =IFERROR(VLOOKUP($A6,subQ,MATCH(AG$1,SUBQH,0),0),"")
A7: 매출총이익 | D7: 매출총이익 | E7: =IFERROR(VLOOKUP($A7,subQ,MATCH(E$1,SUBQH,0),0),"") | F7: =IFERROR(VLOOKUP($A7,subQ,MATCH(F$1,SUBQH,0),0),"") | G7: =IFERROR(VLOOKUP($A7,subQ,MATCH(G$1,SUBQH,0),0),"") | H7: =IFERROR(VLOOKUP($A7,subQ,MATCH(H$1,SUBQH,0),0),"") | I7: =IFERROR(VLOOKUP($A7,subQ,MATCH(I$1,SUBQH,0),0),"") | J7: =IFERROR(VLOOKUP($A7,subQ,MATCH(J$1,SUBQH,0),0),"") | K7: =IFERROR(VLOOKUP($A7,subQ,MATCH(K$1,SUBQH,0),0),"") | L7: =IFERROR(VLOOKUP($A7,subQ,MATCH(L$1,SUBQH,0),0),"") | ... AG7: =IFERROR(VLOOKUP($A7,subQ,MATCH(AG$1,SUBQH,0),0),"")
A8: 판관비 | D8: 판매비와관리비 | E8: =IFERROR(VLOOKUP($A8,subQ,MATCH(E$1,SUBQH,0),0),"") | F8: =IFERROR(VLOOKUP($A8,subQ,MATCH(F$1,SUBQH,0),0),"") | G8: =IFERROR(VLOOKUP($A8,subQ,MATCH(G$1,SUBQH,0),0),"") | H8: =IFERROR(VLOOKUP($A8,subQ,MATCH(H$1,SUBQH,0),0),"") | I8: =IFERROR(VLOOKUP($A8,subQ,MATCH(I$1,SUBQH,0),0),"") | J8: =IFERROR(VLOOKUP($A8,subQ,MATCH(J$1,SUBQH,0),0),"") | K8: =IFERROR(VLOOKUP($A8,subQ,MATCH(K$1,SUBQH,0),0),"") | L8: =IFERROR(VLOOKUP($A8,subQ,MATCH(L$1,SUBQH,0),0),"") | ... AG8: =IFERROR(VLOOKUP($A8,subQ,MATCH(AG$1,SUBQH,0),0),"")
A9: 영업이익 | D9: 영업이익 | E9: =IFERROR(VLOOKUP($A9,subQ,MATCH(E$1,SUBQH,0),0),"") | F9: =IFERROR(VLOOKUP($A9,subQ,MATCH(F$1,SUBQH,0),0),"") | G9: =IFERROR(VLOOKUP($A9,subQ,MATCH(G$1,SUBQH,0),0),"") | H9: =IFERROR(VLOOKUP($A9,subQ,MATCH(H$1,SUBQH,0),0),"") | I9: =IFERROR(VLOOKUP($A9,subQ,MATCH(I$1,SUBQH,0),0),"") | J9: =IFERROR(VLOOKUP($A9,subQ,MATCH(J$1,SUBQH,0),0),"") | K9: =IFERROR(VLOOKUP($A9,subQ,MATCH(K$1,SUBQH,0),0),"") | L9: =IFERROR(VLOOKUP($A9,subQ,MATCH(L$1,SUBQH,0),0),"") | ... AG9: =IFERROR(VLOOKUP($A9,subQ,MATCH(AG$1,SUBQH,0),0),"")
A10: OPM | D10: 영업이익률 | E10: =IFERROR(VLOOKUP($A10,subQ,MATCH(E$1,SUBQH,0),0),"") | F10: =IFERROR(VLOOKUP($A10,subQ,MATCH(F$1,SUBQH,0),0),"") | G10: =IFERROR(VLOOKUP($A10,subQ,MATCH(G$1,SUBQH,0),0),"") | H10: =IFERROR(VLOOKUP($A10,subQ,MATCH(H$1,SUBQH,0),0),"") | I10: =IFERROR(VLOOKUP($A10,subQ,MATCH(I$1,SUBQH,0),0),"") | J10: =IFERROR(VLOOKUP($A10,subQ,MATCH(J$1,SUBQH,0),0),"") | K10: =IFERROR(VLOOKUP($A10,subQ,MATCH(K$1,SUBQH,0),0),"") | L10: =IFERROR(VLOOKUP($A10,subQ,MATCH(L$1,SUBQH,0),0),"") | ... AG10: =IFERROR(VLOOKUP($A10,subQ,MATCH(AG$1,SUBQH,0),0),"")
A11: 금융손익 | D11: 금융손익(이자·환 포함) | E11: =IFERROR(VLOOKUP($A11,subQ,MATCH(E$1,SUBQH,0),0),"") | F11: =IFERROR(VLOOKUP($A11,subQ,MATCH(F$1,SUBQH,0),0),"") | G11: =IFERROR(VLOOKUP($A11,subQ,MATCH(G$1,SUBQH,0),0),"") | H11: =IFERROR(VLOOKUP($A11,subQ,MATCH(H$1,SUBQH,0),0),"") | I11: =IFERROR(VLOOKUP($A11,subQ,MATCH(I$1,SUBQH,0),0),"") | J11: =IFERROR(VLOOKUP($A11,subQ,MATCH(J$1,SUBQH,0),0),"") | K11: =IFERROR(VLOOKUP($A11,subQ,MATCH(K$1,SUBQH,0),0),"") | L11: =IFERROR(VLOOKUP($A11,subQ,MATCH(L$1,SUBQH,0),0),"") | ... AG11: =IFERROR(VLOOKUP($A11,subQ,MATCH(AG$1,SUBQH,0),0),"")
A12: 이자손익 | D12: 이자손익(이자수익 − 이자비용) | E12: =IFERROR(VLOOKUP($A12,subQ,MATCH(E$1,SUBQH,0),0),"") | F12: =IFERROR(VLOOKUP($A12,subQ,MATCH(F$1,SUBQH,0),0),"") | G12: =IFERROR(VLOOKUP($A12,subQ,MATCH(G$1,SUBQH,0),0),"") | H12: =IFERROR(VLOOKUP($A12,subQ,MATCH(H$1,SUBQH,0),0),"") | I12: =IFERROR(VLOOKUP($A12,subQ,MATCH(I$1,SUBQH,0),0),"") | J12: =IFERROR(VLOOKUP($A12,subQ,MATCH(J$1,SUBQH,0),0),"") | K12: =IFERROR(VLOOKUP($A12,subQ,MATCH(K$1,SUBQH,0),0),"") | L12: =IFERROR(VLOOKUP($A12,subQ,MATCH(L$1,SUBQH,0),0),"") | ... AG12: =IFERROR(VLOOKUP($A12,subQ,MATCH(AG$1,SUBQH,0),0),"")
A13: 외환손익 | D13: 외환손익(실적만; 추정 환효과는 환관련손익) | E13: =IFERROR(VLOOKUP($A13,subQ,MATCH(E$1,SUBQH,0),0),"") | F13: =IFERROR(VLOOKUP($A13,subQ,MATCH(F$1,SUBQH,0),0),"") | G13: =IFERROR(VLOOKUP($A13,subQ,MATCH(G$1,SUBQH,0),0),"") | H13: =IFERROR(VLOOKUP($A13,subQ,MATCH(H$1,SUBQH,0),0),"") | I13: =IFERROR(VLOOKUP($A13,subQ,MATCH(I$1,SUBQH,0),0),"") | J13: =IFERROR(VLOOKUP($A13,subQ,MATCH(J$1,SUBQH,0),0),"") | K13: =IFERROR(VLOOKUP($A13,subQ,MATCH(K$1,SUBQH,0),0),"") | L13: =IFERROR(VLOOKUP($A13,subQ,MATCH(L$1,SUBQH,0),0),"") | ... AG13: =IFERROR(VLOOKUP($A13,subQ,MATCH(AG$1,SUBQH,0),0),"")
A14: 파생상품손익 | D14: 파생상품손익 | E14: =IFERROR(VLOOKUP($A14,subQ,MATCH(E$1,SUBQH,0),0),"") | F14: =IFERROR(VLOOKUP($A14,subQ,MATCH(F$1,SUBQH,0),0),"") | G14: =IFERROR(VLOOKUP($A14,subQ,MATCH(G$1,SUBQH,0),0),"") | H14: =IFERROR(VLOOKUP($A14,subQ,MATCH(H$1,SUBQH,0),0),"") | I14: =IFERROR(VLOOKUP($A14,subQ,MATCH(I$1,SUBQH,0),0),"") | J14: =IFERROR(VLOOKUP($A14,subQ,MATCH(J$1,SUBQH,0),0),"") | K14: =IFERROR(VLOOKUP($A14,subQ,MATCH(K$1,SUBQH,0),0),"") | L14: =IFERROR(VLOOKUP($A14,subQ,MATCH(L$1,SUBQH,0),0),"") | ... AG14: =IFERROR(VLOOKUP($A14,subQ,MATCH(AG$1,SUBQH,0),0),"")
A15: 기타금융손익 | D15: 기타금융손익(금융손익 잔차) | E15: =IFERROR(VLOOKUP($A15,subQ,MATCH(E$1,SUBQH,0),0),"") | F15: =IFERROR(VLOOKUP($A15,subQ,MATCH(F$1,SUBQH,0),0),"") | G15: =IFERROR(VLOOKUP($A15,subQ,MATCH(G$1,SUBQH,0),0),"") | H15: =IFERROR(VLOOKUP($A15,subQ,MATCH(H$1,SUBQH,0),0),"") | I15: =IFERROR(VLOOKUP($A15,subQ,MATCH(I$1,SUBQH,0),0),"") | J15: =IFERROR(VLOOKUP($A15,subQ,MATCH(J$1,SUBQH,0),0),"") | K15: =IFERROR(VLOOKUP($A15,subQ,MATCH(K$1,SUBQH,0),0),"") | L15: =IFERROR(VLOOKUP($A15,subQ,MATCH(L$1,SUBQH,0),0),"") | ... AG15: =IFERROR(VLOOKUP($A15,subQ,MATCH(AG$1,SUBQH,0),0),"")
A16: 기타영업외손익 | D16: 기타영업외손익 | E16: =IFERROR(VLOOKUP($A16,subQ,MATCH(E$1,SUBQH,0),0),"") | F16: =IFERROR(VLOOKUP($A16,subQ,MATCH(F$1,SUBQH,0),0),"") | G16: =IFERROR(VLOOKUP($A16,subQ,MATCH(G$1,SUBQH,0),0),"") | H16: =IFERROR(VLOOKUP($A16,subQ,MATCH(H$1,SUBQH,0),0),"") | I16: =IFERROR(VLOOKUP($A16,subQ,MATCH(I$1,SUBQH,0),0),"") | J16: =IFERROR(VLOOKUP($A16,subQ,MATCH(J$1,SUBQH,0),0),"") | K16: =IFERROR(VLOOKUP($A16,subQ,MATCH(K$1,SUBQH,0),0),"") | L16: =IFERROR(VLOOKUP($A16,subQ,MATCH(L$1,SUBQH,0),0),"") | ... AG16: =IFERROR(VLOOKUP($A16,subQ,MATCH(AG$1,SUBQH,0),0),"")
... A42: NPM | D42: NPM | E42: =IFERROR(VLOOKUP($A42,subQ,MATCH(E$1,SUBQH,0),0),"") | F42: =IFERROR(VLOOKUP($A42,subQ,MATCH(F$1,SUBQH,0),0),"") | G42: =IFERROR(VLOOKUP($A42,subQ,MATCH(G$1,SUBQH,0),0),"") | H42: =IFERROR(VLOOKUP($A42,subQ,MATCH(H$1,SUBQH,0),0),"") | I42: =IFERROR(VLOOKUP($A42,subQ,MATCH(I$1,SUBQH,0),0),"") | J42: =IFERROR(VLOOKUP($A42,subQ,MATCH(J$1,SUBQH,0),0),"") | K42: =IFERROR(VLOOKUP($A42,subQ,MATCH(K$1,SUBQH,0),0),"") | L42: =IFERROR(VLOOKUP($A42,subQ,MATCH(L$1,SUBQH,0),0),"") | ... AG42: =IFERROR(VLOOKUP($A42,subQ,MATCH(AG$1,SUBQH,0),0),"")
A43: 매출액 YoY | D43: 매출액 YoY | I43: =IFERROR(I5/E5-1,"") | J43: =IFERROR(J5/F5-1,"") | K43: =IFERROR(K5/G5-1,"") | L43: =IFERROR(L5/H5-1,"") | M43: =IFERROR(M5/I5-1,"") | N43: =IFERROR(N5/J5-1,"") | O43: =IFERROR(O5/K5-1,"") | P43: =IFERROR(P5/L5-1,"") | ... AG43: =IFERROR(AG5/AC5-1,"")
A44: 영업이익 YoY | D44: 영업이익 YoY | I44: =IFERROR(I9/E9-1,"") | J44: =IFERROR(J9/F9-1,"") | K44: =IFERROR(K9/G9-1,"") | L44: =IFERROR(L9/H9-1,"") | M44: =IFERROR(M9/I9-1,"") | N44: =IFERROR(N9/J9-1,"") | O44: =IFERROR(O9/K9-1,"") | P44: =IFERROR(P9/L9-1,"") | ... AG44: =IFERROR(AG9/AC9-1,"")
A45: 지배주주순이익 YoY | D45: 지배주주순이익 YoY | I45: =IFERROR(I21/E21-1,"") | J45: =IFERROR(J21/F21-1,"") | K45: =IFERROR(K21/G21-1,"") | L45: =IFERROR(L21/H21-1,"") | M45: =IFERROR(M21/I21-1,"") | N45: =IFERROR(N21/J21-1,"") | O45: =IFERROR(O21/K21-1,"") | P45: =IFERROR(P21/L21-1,"") | ... AG45: =IFERROR(AG21/AC21-1,"")

Sheet 연간예상
C1: 이름: 연간예상H — subQ 를 이름으로 VLOOKUP(억원) | E1: 2021 | F1: 2022 | G1: 2023 | H1: 2024 | I1: 2025 | J1: 2026 | K1: 2027 | L1: 2028
C2: 종가: | D2: =변수!D45
C3: 기준일: | D3: 20261019 | E3: 1 | F3: 2 | G3: 3 | H3: 4 | I3: 5 | J3: 6 | K3: 7 | L3: 8
E4: 2021.12A | F4: 2022.12A | G4: 2023.12A | H4: 2024.12A | I4: 2025.12A | J4: 2026.12A | K4: 2027.12A | L4: 2028.12A
A5: 매출액 | D5: 매출액 | E5: =IFERROR(VLOOKUP($A5,subQ,MATCH(E$1,SUBQH,0),0),"") | F5: =IFERROR(VLOOKUP($A5,subQ,MATCH(F$1,SUBQH,0),0),"") | G5: =IFERROR(VLOOKUP($A5,subQ,MATCH(G$1,SUBQH,0),0),"") | H5: =IFERROR(VLOOKUP($A5,subQ,MATCH(H$1,SUBQH,0),0),"") | I5: =IFERROR(VLOOKUP($A5,subQ,MATCH(I$1,SUBQH,0),0),"") | J5: =IFERROR(VLOOKUP($A5,subQ,MATCH(J$1,SUBQH,0),0),"") | K5: =IFERROR(VLOOKUP($A5,subQ,MATCH(K$1,SUBQH,0),0),"") | L5: =IFERROR(VLOOKUP($A5,subQ,MATCH(L$1,SUBQH,0),0),"")
A6: 매출원가 | D6: 매출원가 | E6: =IFERROR(VLOOKUP($A6,subQ,MATCH(E$1,SUBQH,0),0),"") | F6: =IFERROR(VLOOKUP($A6,subQ,MATCH(F$1,SUBQH,0),0),"") | G6: =IFERROR(VLOOKUP($A6,subQ,MATCH(G$1,SUBQH,0),0),"") | H6: =IFERROR(VLOOKUP($A6,subQ,MATCH(H$1,SUBQH,0),0),"") | I6: =IFERROR(VLOOKUP($A6,subQ,MATCH(I$1,SUBQH,0),0),"") | J6: =IFERROR(VLOOKUP($A6,subQ,MATCH(J$1,SUBQH,0),0),"") | K6: =IFERROR(VLOOKUP($A6,subQ,MATCH(K$1,SUBQH,0),0),"") | L6: =IFERROR(VLOOKUP($A6,subQ,MATCH(L$1,SUBQH,0),0),"")
A7: 매출총이익 | D7: 매출총이익 | E7: =IFERROR(VLOOKUP($A7,subQ,MATCH(E$1,SUBQH,0),0),"") | F7: =IFERROR(VLOOKUP($A7,subQ,MATCH(F$1,SUBQH,0),0),"") | G7: =IFERROR(VLOOKUP($A7,subQ,MATCH(G$1,SUBQH,0),0),"") | H7: =IFERROR(VLOOKUP($A7,subQ,MATCH(H$1,SUBQH,0),0),"") | I7: =IFERROR(VLOOKUP($A7,subQ,MATCH(I$1,SUBQH,0),0),"") | J7: =IFERROR(VLOOKUP($A7,subQ,MATCH(J$1,SUBQH,0),0),"") | K7: =IFERROR(VLOOKUP($A7,subQ,MATCH(K$1,SUBQH,0),0),"") | L7: =IFERROR(VLOOKUP($A7,subQ,MATCH(L$1,SUBQH,0),0),"")
A8: 판관비 | D8: 판매비와관리비 | E8: =IFERROR(VLOOKUP($A8,subQ,MATCH(E$1,SUBQH,0),0),"") | F8: =IFERROR(VLOOKUP($A8,subQ,MATCH(F$1,SUBQH,0),0),"") | G8: =IFERROR(VLOOKUP($A8,subQ,MATCH(G$1,SUBQH,0),0),"") | H8: =IFERROR(VLOOKUP($A8,subQ,MATCH(H$1,SUBQH,0),0),"") | I8: =IFERROR(VLOOKUP($A8,subQ,MATCH(I$1,SUBQH,0),0),"") | J8: =IFERROR(VLOOKUP($A8,subQ,MATCH(J$1,SUBQH,0),0),"") | K8: =IFERROR(VLOOKUP($A8,subQ,MATCH(K$1,SUBQH,0),0),"") | L8: =IFERROR(VLOOKUP($A8,subQ,MATCH(L$1,SUBQH,0),0),"")
A9: 영업이익 | D9: 영업이익 | E9: =IFERROR(VLOOKUP($A9,subQ,MATCH(E$1,SUBQH,0),0),"") | F9: =IFERROR(VLOOKUP($A9,subQ,MATCH(F$1,SUBQH,0),0),"") | G9: =IFERROR(VLOOKUP($A9,subQ,MATCH(G$1,SUBQH,0),0),"") | H9: =IFERROR(VLOOKUP($A9,subQ,MATCH(H$1,SUBQH,0),0),"") | I9: =IFERROR(VLOOKUP($A9,subQ,MATCH(I$1,SUBQH,0),0),"") | J9: =IFERROR(VLOOKUP($A9,subQ,MATCH(J$1,SUBQH,0),0),"") | K9: =IFERROR(VLOOKUP($A9,subQ,MATCH(K$1,SUBQH,0),0),"") | L9: =IFERROR(VLOOKUP($A9,subQ,MATCH(L$1,SUBQH,0),0),"")
A10: OPM | D10: 영업이익률 | E10: =IFERROR(VLOOKUP($A10,subQ,MATCH(E$1,SUBQH,0),0),"") | F10: =IFERROR(VLOOKUP($A10,subQ,MATCH(F$1,SUBQH,0),0),"") | G10: =IFERROR(VLOOKUP($A10,subQ,MATCH(G$1,SUBQH,0),0),"") | H10: =IFERROR(VLOOKUP($A10,subQ,MATCH(H$1,SUBQH,0),0),"") | I10: =IFERROR(VLOOKUP($A10,subQ,MATCH(I$1,SUBQH,0),0),"") | J10: =IFERROR(VLOOKUP($A10,subQ,MATCH(J$1,SUBQH,0),0),"") | K10: =IFERROR(VLOOKUP($A10,subQ,MATCH(K$1,SUBQH,0),0),"") | L10: =IFERROR(VLOOKUP($A10,subQ,MATCH(L$1,SUBQH,0),0),"")
A11: 금융손익 | D11: 금융손익(이자·환 포함) | E11: =IFERROR(VLOOKUP($A11,subQ,MATCH(E$1,SUBQH,0),0),"") | F11: =IFERROR(VLOOKUP($A11,subQ,MATCH(F$1,SUBQH,0),0),"") | G11: =IFERROR(VLOOKUP($A11,subQ,MATCH(G$1,SUBQH,0),0),"") | H11: =IFERROR(VLOOKUP($A11,subQ,MATCH(H$1,SUBQH,0),0),"") | I11: =IFERROR(VLOOKUP($A11,subQ,MATCH(I$1,SUBQH,0),0),"") | J11: =IFERROR(VLOOKUP($A11,subQ,MATCH(J$1,SUBQH,0),0),"") | K11: =IFERROR(VLOOKUP($A11,subQ,MATCH(K$1,SUBQH,0),0),"") | L11: =IFERROR(VLOOKUP($A11,subQ,MATCH(L$1,SUBQH,0),0),"")
A12: 이자손익 | D12: 이자손익(이자수익 − 이자비용) | E12: =IFERROR(VLOOKUP($A12,subQ,MATCH(E$1,SUBQH,0),0),"") | F12: =IFERROR(VLOOKUP($A12,subQ,MATCH(F$1,SUBQH,0),0),"") | G12: =IFERROR(VLOOKUP($A12,subQ,MATCH(G$1,SUBQH,0),0),"") | H12: =IFERROR(VLOOKUP($A12,subQ,MATCH(H$1,SUBQH,0),0),"") | I12: =IFERROR(VLOOKUP($A12,subQ,MATCH(I$1,SUBQH,0),0),"") | J12: =IFERROR(VLOOKUP($A12,subQ,MATCH(J$1,SUBQH,0),0),"") | K12: =IFERROR(VLOOKUP($A12,subQ,MATCH(K$1,SUBQH,0),0),"") | L12: =IFERROR(VLOOKUP($A12,subQ,MATCH(L$1,SUBQH,0),0),"")
A13: 외환손익 | D13: 외환손익(실적만; 추정 환효과는 환관련손익) | E13: =IFERROR(VLOOKUP($A13,subQ,MATCH(E$1,SUBQH,0),0),"") | F13: =IFERROR(VLOOKUP($A13,subQ,MATCH(F$1,SUBQH,0),0),"") | G13: =IFERROR(VLOOKUP($A13,subQ,MATCH(G$1,SUBQH,0),0),"") | H13: =IFERROR(VLOOKUP($A13,subQ,MATCH(H$1,SUBQH,0),0),"") | I13: =IFERROR(VLOOKUP($A13,subQ,MATCH(I$1,SUBQH,0),0),"") | J13: =IFERROR(VLOOKUP($A13,subQ,MATCH(J$1,SUBQH,0),0),"") | K13: =IFERROR(VLOOKUP($A13,subQ,MATCH(K$1,SUBQH,0),0),"") | L13: =IFERROR(VLOOKUP($A13,subQ,MATCH(L$1,SUBQH,0),0),"")
A14: 파생상품손익 | D14: 파생상품손익 | E14: =IFERROR(VLOOKUP($A14,subQ,MATCH(E$1,SUBQH,0),0),"") | F14: =IFERROR(VLOOKUP($A14,subQ,MATCH(F$1,SUBQH,0),0),"") | G14: =IFERROR(VLOOKUP($A14,subQ,MATCH(G$1,SUBQH,0),0),"") | H14: =IFERROR(VLOOKUP($A14,subQ,MATCH(H$1,SUBQH,0),0),"") | I14: =IFERROR(VLOOKUP($A14,subQ,MATCH(I$1,SUBQH,0),0),"") | J14: =IFERROR(VLOOKUP($A14,subQ,MATCH(J$1,SUBQH,0),0),"") | K14: =IFERROR(VLOOKUP($A14,subQ,MATCH(K$1,SUBQH,0),0),"") | L14: =IFERROR(VLOOKUP($A14,subQ,MATCH(L$1,SUBQH,0),0),"")
A15: 기타금융손익 | D15: 기타금융손익(금융손익 잔차) | E15: =IFERROR(VLOOKUP($A15,subQ,MATCH(E$1,SUBQH,0),0),"") | F15: =IFERROR(VLOOKUP($A15,subQ,MATCH(F$1,SUBQH,0),0),"") | G15: =IFERROR(VLOOKUP($A15,subQ,MATCH(G$1,SUBQH,0),0),"") | H15: =IFERROR(VLOOKUP($A15,subQ,MATCH(H$1,SUBQH,0),0),"") | I15: =IFERROR(VLOOKUP($A15,subQ,MATCH(I$1,SUBQH,0),0),"") | J15: =IFERROR(VLOOKUP($A15,subQ,MATCH(J$1,SUBQH,0),0),"") | K15: =IFERROR(VLOOKUP($A15,subQ,MATCH(K$1,SUBQH,0),0),"") | L15: =IFERROR(VLOOKUP($A15,subQ,MATCH(L$1,SUBQH,0),0),"")
A16: 기타영업외손익 | D16: 기타영업외손익 | E16: =IFERROR(VLOOKUP($A16,subQ,MATCH(E$1,SUBQH,0),0),"") | F16: =IFERROR(VLOOKUP($A16,subQ,MATCH(F$1,SUBQH,0),0),"") | G16: =IFERROR(VLOOKUP($A16,subQ,MATCH(G$1,SUBQH,0),0),"") | H16: =IFERROR(VLOOKUP($A16,subQ,MATCH(H$1,SUBQH,0),0),"") | I16: =IFERROR(VLOOKUP($A16,subQ,MATCH(I$1,SUBQH,0),0),"") | J16: =IFERROR(VLOOKUP($A16,subQ,MATCH(J$1,SUBQH,0),0),"") | K16: =IFERROR(VLOOKUP($A16,subQ,MATCH(K$1,SUBQH,0),0),"") | L16: =IFERROR(VLOOKUP($A16,subQ,MATCH(L$1,SUBQH,0),0),"")
... A42: NPM | D42: NPM | E42: =IFERROR(VLOOKUP($A42,subQ,MATCH(E$1,SUBQH,0),0),"") | F42: =IFERROR(VLOOKUP($A42,subQ,MATCH(F$1,SUBQH,0),0),"") | G42: =IFERROR(VLOOKUP($A42,subQ,MATCH(G$1,SUBQH,0),0),"") | H42: =IFERROR(VLOOKUP($A42,subQ,MATCH(H$1,SUBQH,0),0),"") | I42: =IFERROR(VLOOKUP($A42,subQ,MATCH(I$1,SUBQH,0),0),"") | J42: =IFERROR(VLOOKUP($A42,subQ,MATCH(J$1,SUBQH,0),0),"") | K42: =IFERROR(VLOOKUP($A42,subQ,MATCH(K$1,SUBQH,0),0),"") | L42: =IFERROR(VLOOKUP($A42,subQ,MATCH(L$1,SUBQH,0),0),"")
A43: 매출액 YoY | D43: 매출액 YoY | F43: =IFERROR(F5/E5-1,"") | G43: =IFERROR(G5/F5-1,"") | H43: =IFERROR(H5/G5-1,"") | I43: =IFERROR(I5/H5-1,"") | J43: =IFERROR(J5/I5-1,"") | K43: =IFERROR(K5/J5-1,"") | L43: =IFERROR(L5/K5-1,"")
A44: 영업이익 YoY | D44: 영업이익 YoY | F44: =IFERROR(F9/E9-1,"") | G44: =IFERROR(G9/F9-1,"") | H44: =IFERROR(H9/G9-1,"") | I44: =IFERROR(I9/H9-1,"") | J44: =IFERROR(J9/I9-1,"") | K44: =IFERROR(K9/J9-1,"") | L44: =IFERROR(L9/K9-1,"")
A45: 지배주주순이익 YoY | D45: 지배주주순이익 YoY | F45: =IFERROR(F21/E21-1,"") | G45: =IFERROR(G21/F21-1,"") | H45: =IFERROR(H21/G21-1,"") | I45: =IFERROR(I21/H21-1,"") | J45: =IFERROR(J21/I21-1,"") | K45: =IFERROR(K21/J21-1,"") | L45: =IFERROR(L21/K21-1,"")

Sheet TP
B1: 종가 | C1: =변수!D45
B2: 기준일 | C2: =변수!D46
B3: 모델 산출값 — 목표주가·추천 아님. 밴드·COE 는 변수 시트 3절의 가정
C5: FY | D5: 2025 | E5: 2026 | F5: 2027 | G5: 2028
D6: A | E6: E | F6: E | G6: E
C7: EPS(원) | D7: =IFERROR(VLOOKUP("EPS",subQ,MATCH(D$5,SUBQH,0),0),"") | E7: =IFERROR(VLOOKUP("EPS",subQ,MATCH(E$5,SUBQH,0),0),"") | F7: =IFERROR(VLOOKUP("EPS",subQ,MATCH(F$5,SUBQH,0),0),"") | G7: =IFERROR(VLOOKUP("EPS",subQ,MATCH(G$5,SUBQH,0),0),"")
C8: BPS(원) | D8: =IFERROR(VLOOKUP("BPS",subQ,MATCH(D$5,SUBQH,0),0),"") | E8: =IFERROR(VLOOKUP("BPS",subQ,MATCH(E$5,SUBQH,0),0),"") | F8: =IFERROR(VLOOKUP("BPS",subQ,MATCH(F$5,SUBQH,0),0),"") | G8: =IFERROR(VLOOKUP("BPS",subQ,MATCH(G$5,SUBQH,0),0),"")
C9: 지배주주순이익(억원) | D9: =IFERROR(VLOOKUP("지배주주순이익",subQ,MATCH(D$5,SUBQH,0),0),"") | E9: =IFERROR(VLOOKUP("지배주주순이익",subQ,MATCH(E$5,SUBQH,0),0),"") | F9: =IFERROR(VLOOKUP("지배주주순이익",subQ,MATCH(F$5,SUBQH,0),0),"") | G9: =IFERROR(VLOOKUP("지배주주순이익",subQ,MATCH(G$5,SUBQH,0),0),"")
C10: 영업이익(억원) | D10: =IFERROR(VLOOKUP("영업이익",subQ,MATCH(D$5,SUBQH,0),0),"") | E10: =IFERROR(VLOOKUP("영업이익",subQ,MATCH(E$5,SUBQH,0),0),"") | F10: =IFERROR(VLOOKUP("영업이익",subQ,MATCH(F$5,SUBQH,0),0),"") | G10: =IFERROR(VLOOKUP("영업이익",subQ,MATCH(G$5,SUBQH,0),0),"")
C11: ROE(EPS/기초BPS) | E11: =IFERROR(E7/D8,"") | F11: =IFERROR(F7/E8,"") | G11: =IFERROR(G7/F8,"")
B13: PER
C14: 12M fwd EPS | D14: =IFERROR(E7*변수!D51+F7*(1-변수!D51),"")
C15: 적정가치 @PER_lo | D15: =변수!D48 | E15: =IFERROR(ROUND($D$14*D15,-2),"") | F15: =IFERROR(E15/$C$1-1,"") | G15: 배 · 원 · 종가 대비
C16: 적정가치 @PER_mid | D16: =변수!D49 | E16: =IFERROR(ROUND($D$14*D16,-2),"") | F16: =IFERROR(E16/$C$1-1,"") | G16: 배 · 원 · 종가 대비
C17: 적정가치 @PER_hi | D17: =변수!D50 | E17: =IFERROR(ROUND($D$14*D17,-2),"") | F17: =IFERROR(E17/$C$1-1,"") | G17: 배 · 원 · 종가 대비
C18: 현재 PER(종가/12M fwd EPS) | D18: =IFERROR($C$1/$D$14,"")
B20: PBR
C21: 최근 BPS(마지막 실적 분기) | D21: =IFERROR(VLOOKUP("BPS",subQ,MATCH("2Q26",SUBQH,0),0),"")
C22: ROE fwd(12M fwd EPS / BPS) | D22: =IFERROR($D$14/$D$21,"")
C23: COE | D23: =변수!D47
C24: 적정 PBR = ROE/COE | D24: =IFERROR(D22/D23,"")
C25: 적정가치(PBR) = BPS × 적정PBR | D25: =IFERROR(ROUND(D21*D24,-2),"") | E25: =IFERROR(D25/$C$1-1,"")
C26: 현재 PBR(종가/BPS) | D26: =IFERROR($C$1/D21,"")
B28: 모델 json valuation(참고)
C29: eps_fwd12m | D29: -958.4
C30: bps_latest | D30: 9785.9
C31: per_now
C32: pbr_now | D32: 0.22
C33: roe_fwd | D33: -0.0979
C34: fair_pbr
C35: fair_value_pbr
C36: ev_ebitda
C37: note | D37: 모델 산출값 — 목표주가·추천 아님

Sheet 외화
C1: 이름: 외화QH — 환율 QoQ · 외화 순노출 × Δ기말환율 | E1: 4Q21 | F1: 1Q22 | G1: 2Q22 | H1: 3Q22 | I1: 4Q22 | J1: 1Q23 | K1: 2Q23 | L1: 3Q23 | M1: 4Q23 | N1: 1Q24 | O1: 2Q24 | P1: 3Q24 | Q1: 4Q24 | R1: 1Q25 | S1: 2Q25 | T1: 3Q25 | U1: 4Q25 | V1: 1Q26 | W1: 2Q26 | X1: 3Q26 | Y1: 4Q26 | Z1: 1Q27 | AA1: 2Q27 | AB1: 3Q27 | AC1: 4Q27 | AD1: 1Q28 | AE1: 2Q28 | AF1: 3Q28 | AG1: 4Q28
E3: 1 | F3: 2 | G3: 3 | H3: 4 | I3: 5 | J3: 6 | K3: 7 | L3: 8 | M3: 9 | N3: 10 | O3: 11 | P3: 12 | Q3: 13 | R3: 14 | S3: 15 | T3: 16 | U3: 17 | V3: 18 | W3: 19 | X3: 20 | Y3: 21 | Z3: 22 | AA3: 23 | AB3: 24 | AC3: 25 | AD3: 26 | AE3: 27 | AF3: 28 | AG3: 29
E4: 2021.12 | F4: 2022.03 | G4: 2022.06 | H4: 2022.09 | I4: 2022.12 | J4: 2023.03 | K4: 2023.06 | L4: 2023.09 | M4: 2023.12 | N4: 2024.03 | O4: 2024.06 | P4: 2024.09 | Q4: 2024.12 | R4: 2025.03 | S4: 2025.06 | T4: 2025.09 | U4: 2025.12 | V4: 2026.03 | W4: 2026.06 | X4: 2026.09 | Y4: 2026.12 | Z4: 2027.03 | AA4: 2027.06 | AB4: 2027.09 | AC4: 2027.12 | AD4: 2028.03 | AE4: 2028.06 | AF4: 2028.09 | AG4: 2028.12
D5: 원/달러(평균) | E5: =IFERROR(VLOOKUP($D5,환율,MATCH(E$1,변수H,0),0),"") | F5: =IFERROR(VLOOKUP($D5,환율,MATCH(F$1,변수H,0),0),"") | G5: =IFERROR(VLOOKUP($D5,환율,MATCH(G$1,변수H,0),0),"") | H5: =IFERROR(VLOOKUP($D5,환율,MATCH(H$1,변수H,0),0),"") | I5: =IFERROR(VLOOKUP($D5,환율,MATCH(I$1,변수H,0),0),"") | J5: =IFERROR(VLOOKUP($D5,환율,MATCH(J$1,변수H,0),0),"") | K5: =IFERROR(VLOOKUP($D5,환율,MATCH(K$1,변수H,0),0),"") | L5: =IFERROR(VLOOKUP($D5,환율,MATCH(L$1,변수H,0),0),"") | ... AG5: =IFERROR(VLOOKUP($D5,환율,MATCH(AG$1,변수H,0),0),"")
A6: 원/달러(평균) QoQ | F6: =IFERROR(F5/E5-1,"") | G6: =IFERROR(G5/F5-1,"") | H6: =IFERROR(H5/G5-1,"") | I6: =IFERROR(I5/H5-1,"") | J6: =IFERROR(J5/I5-1,"") | K6: =IFERROR(K5/J5-1,"") | L6: =IFERROR(L5/K5-1,"") | M6: =IFERROR(M5/L5-1,"") | ... AG6: =IFERROR(AG5/AF5-1,"")
D7: 원/달러(기말) | E7: =IFERROR(VLOOKUP($D7,환율,MATCH(E$1,변수H,0),0),"") | F7: =IFERROR(VLOOKUP($D7,환율,MATCH(F$1,변수H,0),0),"") | G7: =IFERROR(VLOOKUP($D7,환율,MATCH(G$1,변수H,0),0),"") | H7: =IFERROR(VLOOKUP($D7,환율,MATCH(H$1,변수H,0),0),"") | I7: =IFERROR(VLOOKUP($D7,환율,MATCH(I$1,변수H,0),0),"") | J7: =IFERROR(VLOOKUP($D7,환율,MATCH(J$1,변수H,0),0),"") | K7: =IFERROR(VLOOKUP($D7,환율,MATCH(K$1,변수H,0),0),"") | L7: =IFERROR(VLOOKUP($D7,환율,MATCH(L$1,변수H,0),0),"") | ... AG7: =IFERROR(VLOOKUP($D7,환율,MATCH(AG$1,변수H,0),0),"")
A8: 원/달러(기말) QoQ | F8: =IFERROR(F7/E7-1,"") | G8: =IFERROR(G7/F7-1,"") | H8: =IFERROR(H7/G7-1,"") | I8: =IFERROR(I7/H7-1,"") | J8: =IFERROR(J7/I7-1,"") | K8: =IFERROR(K7/J7-1,"") | L8: =IFERROR(L7/K7-1,"") | M8: =IFERROR(M7/L7-1,"") | ... AG8: =IFERROR(AG7/AF7-1,"")
D9: W/Euro(평균) | E9: =IFERROR(VLOOKUP($D9,환율,MATCH(E$1,변수H,0),0),"") | F9: =IFERROR(VLOOKUP($D9,환율,MATCH(F$1,변수H,0),0),"") | G9: =IFERROR(VLOOKUP($D9,환율,MATCH(G$1,변수H,0),0),"") | H9: =IFERROR(VLOOKUP($D9,환율,MATCH(H$1,변수H,0),0),"") | I9: =IFERROR(VLOOKUP($D9,환율,MATCH(I$1,변수H,0),0),"") | J9: =IFERROR(VLOOKUP($D9,환율,MATCH(J$1,변수H,0),0),"") | K9: =IFERROR(VLOOKUP($D9,환율,MATCH(K$1,변수H,0),0),"") | L9: =IFERROR(VLOOKUP($D9,환율,MATCH(L$1,변수H,0),0),"") | ... AG9: =IFERROR(VLOOKUP($D9,환율,MATCH(AG$1,변수H,0),0),"")
A10: W/Euro(평균) QoQ | F10: =IFERROR(F9/E9-1,"") | G10: =IFERROR(G9/F9-1,"") | H10: =IFERROR(H9/G9-1,"") | I10: =IFERROR(I9/H9-1,"") | J10: =IFERROR(J9/I9-1,"") | K10: =IFERROR(K9/J9-1,"") | L10: =IFERROR(L9/K9-1,"") | M10: =IFERROR(M9/L9-1,"") | ... AG10: =IFERROR(AG9/AF9-1,"")
D11: W/Euro(기말) | E11: =IFERROR(VLOOKUP($D11,환율,MATCH(E$1,변수H,0),0),"") | F11: =IFERROR(VLOOKUP($D11,환율,MATCH(F$1,변수H,0),0),"") | G11: =IFERROR(VLOOKUP($D11,환율,MATCH(G$1,변수H,0),0),"") | H11: =IFERROR(VLOOKUP($D11,환율,MATCH(H$1,변수H,0),0),"") | I11: =IFERROR(VLOOKUP($D11,환율,MATCH(I$1,변수H,0),0),"") | J11: =IFERROR(VLOOKUP($D11,환율,MATCH(J$1,변수H,0),0),"") | K11: =IFERROR(VLOOKUP($D11,환율,MATCH(K$1,변수H,0),0),"") | L11: =IFERROR(VLOOKUP($D11,환율,MATCH(L$1,변수H,0),0),"") | ... AG11: =IFERROR(VLOOKUP($D11,환율,MATCH(AG$1,변수H,0),0),"")
A12: W/Euro(기말) QoQ | F12: =IFERROR(F11/E11-1,"") | G12: =IFERROR(G11/F11-1,"") | H12: =IFERROR(H11/G11-1,"") | I12: =IFERROR(I11/H11-1,"") | J12: =IFERROR(J11/I11-1,"") | K12: =IFERROR(K11/J11-1,"") | L12: =IFERROR(L11/K11-1,"") | M12: =IFERROR(M11/L11-1,"") | ... AG12: =IFERROR(AG11/AF11-1,"")
D13: 원/100Y(기말) | E13: =IFERROR(VLOOKUP($D13,환율,MATCH(E$1,변수H,0),0),"") | F13: =IFERROR(VLOOKUP($D13,환율,MATCH(F$1,변수H,0),0),"") | G13: =IFERROR(VLOOKUP($D13,환율,MATCH(G$1,변수H,0),0),"") | H13: =IFERROR(VLOOKUP($D13,환율,MATCH(H$1,변수H,0),0),"") | I13: =IFERROR(VLOOKUP($D13,환율,MATCH(I$1,변수H,0),0),"") | J13: =IFERROR(VLOOKUP($D13,환율,MATCH(J$1,변수H,0),0),"") | K13: =IFERROR(VLOOKUP($D13,환율,MATCH(K$1,변수H,0),0),"") | L13: =IFERROR(VLOOKUP($D13,환율,MATCH(L$1,변수H,0),0),"") | ... AG13: =IFERROR(VLOOKUP($D13,환율,MATCH(AG$1,변수H,0),0),"")
A14: 원/100Y(기말) QoQ | F14: =IFERROR(F13/E13-1,"") | G14: =IFERROR(G13/F13-1,"") | H14: =IFERROR(H13/G13-1,"") | I14: =IFERROR(I13/H13-1,"") | J14: =IFERROR(J13/I13-1,"") | K14: =IFERROR(K13/J13-1,"") | L14: =IFERROR(L13/K13-1,"") | M14: =IFERROR(M13/L13-1,"") | ... AG14: =IFERROR(AG13/AF13-1,"")
A16: 외화순노출 | C16: 외화 순노출(백만$) | D16: =변수!D58 | E16: 외화 순노출 × Δ기말환율 (외화 시트 방식)
A17: 환관련손익추정 | C17: 환관련손익 추정(억원) = 순노출 × Δ원/달러(기말) / 100 | F17: =IFERROR($D$16*(F7-E7)/100,"") | G17: =IFERROR($D$16*(G7-F7)/100,"") | H17: =IFERROR($D$16*(H7-G7)/100,"") | I17: =IFERROR($D$16*(I7-H7)/100,"") | J17: =IFERROR($D$16*(J7-I7)/100,"") | K17: =IFERROR($D$16*(K7-J7)/100,"") | L17: =IFERROR($D$16*(L7-K7)/100,"") | M17: =IFERROR($D$16*(M7-L7)/100,"") | ... AG17: =IFERROR($D$16*(AG7-AF7)/100,"")
A18: fx_pnl.by_q | C18: 모델 fx_pnl.by_q(억원, 참고)
C19: 외화 순노출 미공시(face) → 0 + 표기
