Workbook
Name 변수H: 변수!$C$1:$AO$1
Name 환율: 변수!$C$6:$AO$13
Name BS연결H: BS연결!$C$1:$AO$1
Name BS연결: BS연결!$C$5:$AO$104
Name BS별도H: BS별도!$C$1:$AO$1
Name BS별도: BS별도!$C$5:$AO$92
Name SUBQH: subQ!$A$1:$AO$1
Name subQ: subQ!$A$5:$AO$44

Sheet README
A1: 금강공업(014280) 실적 모델 — ARGUS 한국조선
A2: 기준 분기 2026Q2 · 마지막 실적 2026Q2 · 생성 2026-10-26
A3: 모든 수치는 모델 산출값(DART 공개 재무제표 + 우리 추정)이다 — 목표주가·투자 추천 아님. 참고용 · 투자조언 아님.
A5: 시트
A6: 변수 가정 시계열. 환율 8행(ECB via frankfurter — L2 fx.json; 추정 분기 = 노란 가정), 추정 드라이버(노란 셀 = 모델값에서 역산한 가정, 바꾸면 재계산; 연녹 셀 = 3절 스칼라 참조 수식), 3절 스칼라 가정(세율·판관비율·지배주주비중·이자율·종가·PER 밴드·COE·외화 순노출·헤지비율)
A7: BS연결/BS별도 FnGuide 계정명 × 기간 값 덤프(백만원). 행1 분기라벨, 행4 YYYY.MM / YYYY.12A. 이름정의 BS연결H·BS연결(계정명 C열부터)
A8: subQ 분기 서브모델(억원 = 백만원/100). 확정 행: =IFERROR(VLOOKUP($D행,BS연결,MATCH(E$1,BS연결H,0),0)/100,"") 추정 행: 변수 시트 가정 셀 참조 수식. 외환손익·파생상품손익은 BS 계정 합·차, 기타금융손익은 잔차, OPM·EPS·BPS·PER·PBR 은 파생 수식, 조정EPS 는 EPS 참조(일회성 의심 분기만 산식 셀)
A9: SLS 선표(조선사만, sls json 있을 때): 요약 행(sls 저장값) + 계약별 스케줄(백만$) × (헤지비율 × 헤지환율 + (1−헤지비율) × 건조시점 환율[변수 원/달러(평균)]) → 원화 수식 블록 → 합계 행이 subQ 매출조선에 연결
A10: 시나리오 신규수주 보수/기준/낙관(forecast_panel 패널, 모델에 scenarios 가 있을 때만): 매출액·영업이익 = subQ 기준값 ± (시나리오 신규 − base 신규) × OPM. base 만 subQ 행에 포함, 나머지는 합산 안 함
A11: 분기/연간예상 subQ 를 이름(A열 key)으로 VLOOKUP 한 보고서 표(억원)
A12: TP PER 밴드 × 12M fwd EPS, PBR = ROE/COE × BPS — 모델 산출값 구간, 목표주가·추천 아님
A13: 외화 환율 QoQ, 외화 순노출 × Δ기말환율 → 환관련손익 추정
... A35: 백테스트: {"freeze": "2025Q2", "horizon": 4, "revenue_wape_pct": 7.1, "op_wape_pct": 99.1, "n": 4, "note": "단일 회사 4분기 — 통계 아님", "driver_at_freeze": "trend_seasonal", "selection_oos_at_freeze": null, "frozen_inputs": "fin(연결/별도)·고객 조선사 모델·지주 자회사 모델은 2025Q2 까지의 분기만; 선표는 체결일 ≤ 2025Q2 말일 계약(원장 최신 금액·코호트 등급, 환산 없음); 잔고는 yards_cache 2025Q2; 시세·환율 forward·prices·forecast_panel 신규수주 미사용. 고객 가중치(suppliers.json 언급 비중)와 합병 체인링크는 현재 지식; 고객 연동 채택은 동결 모델 안에서도 자기 la−4분기 OOS 규칙(selection_oos_at_freeze)", "detail": [{"q": "2025Q3", "rev_pred": 1894.0, "rev_act": 2052.74, "op_pred": 77.15, "op_act": -0.39}, {"q": "2025Q4", "rev_pred": 2042.29, "rev_act": 1871.9, "op_pred": 83.19, "op_act": -5.64}, {"q": "2026Q1", "rev_pred": 1934.7, "rev_act": 1966.68, "op_pred": 78.8, "op_act": 132.39}, {"q": "2026Q2", "rev_pred": 2071.1, "rev_act": 2290.92, "op_pred": 84.36, "op_act": 179.9}]}

Sheet 변수
C1: 이름: 변수H | E1: 4Q21 | F1: 2021 | G1: 1Q22 | H1: 2Q22 | I1: 3Q22 | J1: 4Q22 | K1: 2022 | L1: 1Q23 | M1: 2Q23 | N1: 3Q23 | O1: 4Q23 | P1: 2023 | Q1: 1Q24 | R1: 2Q24 | S1: 3Q24 | T1: 4Q24 | U1: 2024 | V1: 1Q25 | W1: 2Q25 | X1: 3Q25 | Y1: 4Q25 | Z1: 2025 | AA1: 1Q26 | AB1: 2Q26 | AC1: 3Q26 | AD1: 4Q26 | AE1: 2026 | AF1: 1Q27 | AG1: 2Q27 | AH1: 3Q27 | AI1: 4Q27 | AJ1: 2027 | AK1: 1Q28 | AL1: 2Q28 | AM1: 3Q28 | AN1: 4Q28 | AO1: 2028
A2: 가정 시계열 — 노란 셀은 추정 가정(모델값에서 역산), 연녹 셀은 3절 스칼라 참조 수식. 바꾸면 subQ·분기·연간예상·TP·시나리오가 재계산됩니다.
E3: 1 | F3: 2 | G3: 3 | H3: 4 | I3: 5 | J3: 6 | K3: 7 | L3: 8 | M3: 9 | N3: 10 | O3: 11 | P3: 12 | Q3: 13 | R3: 14 | S3: 15 | T3: 16 | U3: 17 | V3: 18 | W3: 19 | X3: 20 | Y3: 21 | Z3: 22 | AA3: 23 | AB3: 24 | AC3: 25 | AD3: 26 | AE3: 27 | AF3: 28 | AG3: 29 | AH3: 30 | AI3: 31 | AJ3: 32 | AK3: 33 | AL3: 34 | AM3: 35 | AN3: 36 | AO3: 37
E4: 2021.12 | F4: 2021.12A | G4: 2022.03 | H4: 2022.06 | I4: 2022.09 | J4: 2022.12 | K4: 2022.12A | L4: 2023.03 | M4: 2023.06 | N4: 2023.09 | O4: 2023.12 | P4: 2023.12A | Q4: 2024.03 | R4: 2024.06 | S4: 2024.09 | T4: 2024.12 | U4: 2024.12A | V4: 2025.03 | W4: 2025.06 | X4: 2025.09 | Y4: 2025.12 | Z4: 2025.12A | AA4: 2026.03 | AB4: 2026.06 | AC4: 2026.09 | AD4: 2026.12 | AE4: 2026.12A | AF4: 2027.03 | AG4: 2027.06 | AH4: 2027.09 | AI4: 2027.12 | AJ4: 2027.12A | AK4: 2028.03 | AL4: 2028.06 | AM4: 2028.09 | AN4: 2028.12 | AO4: 2028.12A
B5: 1. FX | C5: 이름: 환율
A6: USDKRW_avg | C6: 원/달러(평균) | E6: 1183.5 | F6: 1145.51 | G6: 1205.78 | H6: 1262.09 | I6: 1341.93 | J6: 1360.12 | K6: 1292.98 | L6: 1276.95 | M6: 1315.69 | N6: 1313.62 | O6: 1322.01 | P6: 1306.85 | Q6: 1330.14 | R6: 1371.28 | S6: 1356.22 | T6: 1396.3 | U6: 1363.53 | V6: 1452.28 | W6: 1398.52 | X6: 1386.95 | Y6: 1449.19 | Z6: 1421.52 | AA6: 1466.12 | AB6: 1501.75 | AC6: 1418.75 | AD6: 1337.49 | AE6: 1451.19 | AF6: 1324.45 | AG6: 1324.45 | AH6: 1324.45 | AI6: 1324.45 | AK6: 1324.45 | AL6: 1324.45 | AM6: 1324.45 | AN6: 1324.45
A7: USDKRW_end | C7: 원/달러(기말) | E7: 1188.75 | F7: 1188.75 | G7: 1213.74 | H7: 1301.24 | I7: 1436.9 | J7: 1260.16 | K7: 1260.16 | L7: 1305.99 | M7: 1321.44 | N7: 1345.35 | O7: 1297.43 | P7: 1297.43 | Q7: 1349.25 | R7: 1377.73 | S7: 1312.17 | T7: 1474.78 | U7: 1474.78 | V7: 1474.54 | W7: 1355.13 | X7: 1403.67 | Y7: 1444.2 | Z7: 1444.2 | AA7: 1524.8 | AB7: 1550.89 | AC7: 1355.4 | AD7: 1324.45 | AE7: 1324.45 | AF7: 1324.45 | AG7: 1324.45 | AH7: 1324.45 | AI7: 1324.45 | AK7: 1324.45 | AL7: 1324.45 | AM7: 1324.45 | AN7: 1324.45
A8: JPY100KRW_avg | C8: 원/100Y(평균) | E8: 1041.02 | F8: 1042.74 | G8: 1036.79 | H8: 972.23 | I8: 970.61 | J8: 961.03 | K8: 985.1 | L8: 964.89 | M8: 957.36 | N8: 909 | O8: 893.22 | P8: 931.11 | Q8: 896.29 | R8: 880.14 | S8: 909.35 | T8: 917.25 | U8: 900.92 | V8: 952.59 | W8: 967.92 | X8: 940.32 | Y8: 940.77 | Z8: 950.17 | AA8: 934.39 | AB8: 942.16 | AC8: 890.41 | AD8: 846.51 | AE8: 915.57 | AF8: 844.67 | AG8: 844.67 | AH8: 844.67 | AI8: 844.67 | AK8: 844.67 | AL8: 844.67 | AM8: 844.67 | AN8: 844.67
A9: JPY100KRW_end | C9: 원/100Y(기말) | E9: 1032.62 | F9: 1032.62 | G9: 996.83 | H9: 954.9 | I9: 993.29 | J9: 955.54 | K9: 955.54 | L9: 980.62 | M9: 913.67 | N9: 901.47 | O9: 917.04 | P9: 917.04 | Q9: 892.42 | R9: 857.76 | S9: 919.21 | T9: 939.65 | U9: 939.65 | V9: 986.84 | W9: 938.85 | X9: 948.49 | Y9: 921.81 | Z9: 921.81 | AA9: 955.99 | AB9: 954.75 | AC9: 863.31 | AD9: 844.67 | AE9: 844.67 | AF9: 844.67 | AG9: 844.67 | AH9: 844.67 | AI9: 844.67 | AK9: 844.67 | AL9: 844.67 | AM9: 844.67 | AN9: 844.67
A10: EURKRW_avg | C10: W/Euro(평균) | E10: 1353.32 | F10: 1354.06 | G10: 1352.29 | H10: 1343.31 | I10: 1350.63 | J10: 1386.07 | K10: 1358.07 | L10: 1369.93 | M10: 1432.41 | N10: 1429.41 | O10: 1420.91 | P10: 1412.88 | Q10: 1444.21 | R10: 1476.42 | S10: 1489.3 | T10: 1490.78 | U10: 1475.4 | V10: 1528.33 | W10: 1585.13 | X10: 1620.04 | Y10: 1686.02 | Z10: 1605.45 | AA10: 1715.47 | AB10: 1746.09 | AC10: 1631.97 | AD10: 1500.06 | AE10: 1680.5 | AF10: 1482.45 | AG10: 1482.45 | AH10: 1482.45 | AI10: 1482.45 | AK10: 1482.45 | AL10: 1482.45 | AM10: 1482.45 | AN10: 1482.45
A11: EURKRW_end | C11: W/Euro(기말) | E11: 1346.38 | F11: 1346.38 | G11: 1347.37 | H11: 1351.6 | I11: 1400.62 | J11: 1344.08 | K11: 1344.08 | L11: 1420.26 | M11: 1435.88 | N11: 1425.26 | O11: 1433.66 | P11: 1433.66 | Q11: 1458.68 | R11: 1474.86 | S11: 1469.1 | T11: 1532.14 | U11: 1532.14 | V11: 1594.72 | W11: 1588.22 | X11: 1648.04 | Y11: 1696.94 | Z11: 1696.94 | AA11: 1753.21 | AB11: 1767.09 | AC11: 1539.06 | AD11: 1482.45 | AE11: 1482.45 | AF11: 1482.45 | AG11: 1482.45 | AH11: 1482.45 | AI11: 1482.45 | AK11: 1482.45 | AL11: 1482.45 | AM11: 1482.45 | AN11: 1482.45
A12: CNYKRW_avg | C12: 원/중국원(평균) | E12: 185.14 | F12: 177.65 | G12: 189.93 | H12: 190.76 | I12: 195.79 | J12: 191.09 | K12: 191.93 | L12: 186.59 | M12: 187.45 | N12: 181.28 | O12: 182.86 | P12: 184.52 | Q12: 185.04 | R12: 189.35 | S12: 189.24 | T12: 194.24 | U12: 189.49 | V12: 199.63 | W12: 193.41 | X12: 193.79 | Y12: 204.38 | Z12: 197.8 | AA12: 211.75 | AB12: 220.8 | AC12: 210.43 | AD12: 199.88 | AE12: 213.06 | AF12: 198.56 | AG12: 198.56 | AH12: 198.56 | AI12: 198.56 | AK12: 198.56 | AL12: 198.56 | AM12: 198.56 | AN12: 198.56
A13: CNYKRW_end | C13: 원/중국원(기말) | E13: 187.13 | F13: 187.13 | G13: 191.38 | H13: 194.13 | I13: 201.92 | J13: 182.67 | K13: 182.67 | L13: 189.97 | M13: 181.8 | N13: 184.26 | O13: 182.61 | P13: 182.61 | Q13: 186.66 | R13: 189.7 | S13: 187.12 | T13: 202.04 | U13: 202.04 | V13: 203.3 | W13: 189.14 | X13: 197.16 | Y13: 206.28 | Z13: 206.28 | AA13: 220.97 | AB13: 228.56 | AC13: 202.16 | AD13: 198.56 | AE13: 198.56 | AF13: 198.56 | AG13: 198.56 | AH13: 198.56 | AI13: 198.56 | AK13: 198.56 | AL13: 198.56 | AM13: 198.56 | AN13: 198.56
B14: 1b. 종가
A15: price_close_end | C15: 종가(기말) | E15: 7820 | G15: 9730 | H15: 6980 | I15: 5170 | J15: 6190 | L15: 5370 | M15: 7310 | N15: 5590 | O15: 5680 | Q15: 5680 | R15: 4970 | S15: 4330 | T15: 3900 | V15: 4300 | W15: 4590 | X15: 4770 | Y15: 6060 | AA15: 4720 | AB15: 4080 | AC15: 4850 | AD15: 4015
A16: price_high | C16: 종가(최고) | E16: 8360 | G16: 10200 | H16: 10800 | I16: 8000 | J16: 8440 | L16: 6600 | M16: 8230 | N16: 7930 | O16: 6120 | Q16: 6540 | R16: 5730 | S16: 5270 | T16: 5150 | V16: 5640 | W16: 5120 | X16: 6280 | Y16: 8470 | AA16: 6730 | AB16: 6590 | AC16: 5450 | AD16: 5040
A17: price_low | C17: 종가(최저) | E17: 7500 | G17: 7520 | H17: 6480 | I17: 4995 | J17: 4795 | L17: 4990 | M17: 4990 | N17: 5410 | O17: 5220 | Q17: 5560 | R17: 4945 | S17: 3985 | T17: 3800 | V17: 3860 | W17: 3910 | X17: 4080 | Y17: 4640 | AA17: 4630 | AB17: 3700 | AC17: 3420 | AD17: 3940
A18: price_avg | C18: 종가(평균) | E18: 7937.3 | G18: 8495.3 | H18: 8934.7 | I18: 6809.2 | J18: 6044.1 | L18: 5873.9 | M18: 5608.7 | N18: 6340.2 | O18: 5610 | Q18: 6043.4 | R18: 5328.6 | S18: 4714.3 | T18: 4248.3 | V18: 4115.6 | W18: 4586.2 | X18: 4743.5 | Y18: 6017.2 | AA18: 5625.4 | AB18: 4864.8 | AC18: 4234.7 | AD18: 4361.2
B20: 2. 추정 드라이버 | C20: 실적 열 = subQ 실현값(수식), 추정 열 = 가정(노란 = 모델값 역산, 연녹 = 3절 스칼라 참조)
A21: drv:매출액 | B21: yoy | C21: 매출액 YoY | J21: =IFERROR(subQ!J5/subQ!E5-1,"") | L21: =IFERROR(subQ!L5/subQ!G5-1,"") | M21: =IFERROR(subQ!M5/subQ!H5-1,"") | N21: =IFERROR(subQ!N5/subQ!I5-1,"") | O21: =IFERROR(subQ!O5/subQ!J5-1,"") | Q21: =IFERROR(subQ!Q5/subQ!L5-1,"") | R21: =IFERROR(subQ!R5/subQ!M5-1,"") | S21: =IFERROR(subQ!S5/subQ!N5-1,"") | T21: =IFERROR(subQ!T5/subQ!O5-1,"") | V21: =IFERROR(subQ!V5/subQ!Q5-1,"") | W21: =IFERROR(subQ!W5/subQ!R5-1,"") | X21: =IFERROR(subQ!X5/subQ!S5-1,"") | Y21: =IFERROR(subQ!Y5/subQ!T5-1,"") | AA21: =IFERROR(subQ!AA5/subQ!V5-1,"") | AB21: =IFERROR(subQ!AB5/subQ!W5-1,"") | AC21: 0.007322264 | AD21: 0.007324486 | AF21: 0.007323828 | AG21: 0.007323205 | AH21: 0.003660949 | AI21: 0.003659293 | AK21: 0.00365962 | AL21: 0.003661654 | AM21: 0.001831025 | AN21: 0.001833544
A22: drv:판관비 | B22: ratio | C22: 판관비율(/매출) | E22: =IFERROR(subQ!E8/subQ!E5,"") | F22: =IFERROR(subQ!F8/subQ!F5,"") | G22: =IFERROR(subQ!G8/subQ!G5,"") | H22: =IFERROR(subQ!H8/subQ!H5,"") | I22: =IFERROR(subQ!I8/subQ!I5,"") | J22: =IFERROR(subQ!J8/subQ!J5,"") | K22: =IFERROR(subQ!K8/subQ!K5,"") | L22: =IFERROR(subQ!L8/subQ!L5,"") | ... AB22: =IFERROR(subQ!AB8/subQ!AB5,"") | AC22: =$D$51 | AD22: =$D$51 | AE22: =IFERROR(subQ!AE8/subQ!AE5,"") | AF22: =$D$51 | AG22: =$D$51 | AH22: =$D$51 | AI22: =$D$51 | AJ22: =IFERROR(subQ!AJ8/subQ!AJ5,"") | AK22: =$D$51 | AL22: =$D$51 | AM22: =$D$51 | AN22: =$D$51 | AO22: =IFERROR(subQ!AO8/subQ!AO5,"")
A23: drv:영업이익 | B23: ratio | C23: 영업이익률(OPM) | E23: =IFERROR(subQ!E9/subQ!E5,"") | F23: =IFERROR(subQ!F9/subQ!F5,"") | G23: =IFERROR(subQ!G9/subQ!G5,"") | H23: =IFERROR(subQ!H9/subQ!H5,"") | I23: =IFERROR(subQ!I9/subQ!I5,"") | J23: =IFERROR(subQ!J9/subQ!J5,"") | K23: =IFERROR(subQ!K9/subQ!K5,"") | L23: =IFERROR(subQ!L9/subQ!L5,"") | ... AB23: =IFERROR(subQ!AB9/subQ!AB5,"") | AC23: 0.026772804 | AD23: 0.026771177 | AE23: =IFERROR(subQ!AE9/subQ!AE5,"") | AF23: 0.026773275 | AG23: 0.026771244 | AH23: 0.026771517 | AI23: 0.026773967 | AJ23: =IFERROR(subQ!AJ9/subQ!AJ5,"") | AK23: 0.02677121 | AL23: 0.026772877 | AM23: 0.026770684 | AN23: 0.026772434 | AO23: =IFERROR(subQ!AO9/subQ!AO5,"")
A24: drv:기타영업외손익 | B24: abs | C24: 기타영업외손익 (가정, 억원) | E24: =subQ!E13 | F24: =subQ!F13 | G24: =subQ!G13 | H24: =subQ!H13 | I24: =subQ!I13 | J24: =subQ!J13 | K24: =subQ!K13 | L24: =subQ!L13 | ... AB24: =subQ!AB13 | AC24: 0 | AD24: 0 | AE24: =subQ!AE13 | AF24: 0 | AG24: 0 | AH24: 0 | AI24: 0 | AJ24: =subQ!AJ13 | AK24: 0 | AL24: 0 | AM24: 0 | AN24: 0 | AO24: =subQ!AO13
A25: drv:지분법손익 | B25: abs | C25: 지분법손익 (가정, 억원) | E25: =subQ!E14 | F25: =subQ!F14 | G25: =subQ!G14 | H25: =subQ!H14 | I25: =subQ!I14 | J25: =subQ!J14 | K25: =subQ!K14 | L25: =subQ!L14 | ... AB25: =subQ!AB14 | AC25: 10.37 | AD25: 10.37 | AE25: =subQ!AE14 | AF25: 10.37 | AG25: 10.37 | AH25: 10.37 | AI25: 10.37 | AJ25: =subQ!AJ14 | AK25: 10.37 | AL25: 10.37 | AM25: 10.37 | AN25: 10.37 | AO25: =subQ!AO14
A26: drv:법인세비용 | B26: tax | C26: 법인세율(/세전) — 법인세 = MAX(세전,0) × 세율 | E26: =IFERROR(subQ!E16/subQ!E15,"") | F26: =IFERROR(subQ!F16/subQ!F15,"") | G26: =IFERROR(subQ!G16/subQ!G15,"") | H26: =IFERROR(subQ!H16/subQ!H15,"") | I26: =IFERROR(subQ!I16/subQ!I15,"") | J26: =IFERROR(subQ!J16/subQ!J15,"") | K26: =IFERROR(subQ!K16/subQ!K15,"") | L26: =IFERROR(subQ!L16/subQ!L15,"") | ... AB26: =IFERROR(subQ!AB16/subQ!AB15,"") | AC26: =$D$50 | AD26: =$D$50 | AE26: =IFERROR(subQ!AE16/subQ!AE15,"") | AF26: =$D$50 | AG26: =$D$50 | AH26: =$D$50 | AI26: =$D$50 | AJ26: =IFERROR(subQ!AJ16/subQ!AJ15,"") | AK26: =$D$50 | AL26: =$D$50 | AM26: =$D$50 | AN26: =$D$50 | AO26: =IFERROR(subQ!AO16/subQ!AO15,"")
A27: drv:지배주주순이익 | B27: ratio | C27: 지배주주 비중(/당기순이익) | E27: =IFERROR(subQ!E18/subQ!E17,"") | F27: =IFERROR(subQ!F18/subQ!F17,"") | G27: =IFERROR(subQ!G18/subQ!G17,"") | H27: =IFERROR(subQ!H18/subQ!H17,"") | I27: =IFERROR(subQ!I18/subQ!I17,"") | J27: =IFERROR(subQ!J18/subQ!J17,"") | K27: =IFERROR(subQ!K18/subQ!K17,"") | L27: =IFERROR(subQ!L18/subQ!L17,"") | ... AB27: =IFERROR(subQ!AB18/subQ!AB17,"") | AC27: =$D$52 | AD27: =$D$52 | AE27: =IFERROR(subQ!AE18/subQ!AE17,"") | AF27: =$D$52 | AG27: =$D$52 | AH27: =$D$52 | AI27: =$D$52 | AJ27: =IFERROR(subQ!AJ18/subQ!AJ17,"") | AK27: =$D$52 | AL27: =$D$52 | AM27: =$D$52 | AN27: =$D$52 | AO27: =IFERROR(subQ!AO18/subQ!AO17,"")
A28: drv:중단사업이익 | B28: abs | C28: 중단사업이익 (가정, 억원) | E28: =subQ!E19 | F28: =subQ!F19 | G28: =subQ!G19 | H28: =subQ!H19 | I28: =subQ!I19 | J28: =subQ!J19 | K28: =subQ!K19 | L28: =subQ!L19 | ... AB28: =subQ!AB19 | AE28: =subQ!AE19 | AJ28: =subQ!AJ19 | AO28: =subQ!AO19
A29: drv:감가상각비 | B29: abs | C29: 감가상각비 (가정, 억원) | E29: =subQ!E20 | F29: =subQ!F20 | G29: =subQ!G20 | H29: =subQ!H20 | I29: =subQ!I20 | J29: =subQ!J20 | K29: =subQ!K20 | L29: =subQ!L20 | ... AB29: =subQ!AB20 | AC29: 157.74 | AD29: 157.74 | AE29: =subQ!AE20 | AF29: 157.74 | AG29: 157.74 | AH29: 157.74 | AI29: 157.74 | AJ29: =subQ!AJ20 | AK29: 157.74 | AL29: 157.74 | AM29: 157.74 | AN29: 157.74 | AO29: =subQ!AO20
A30: drv:부채총계 | B30: qoq | C30: 부채총계 QoQ | G30: =IFERROR(subQ!G23/subQ!E23-1,"") | H30: =IFERROR(subQ!H23/subQ!G23-1,"") | I30: =IFERROR(subQ!I23/subQ!H23-1,"") | J30: =IFERROR(subQ!J23/subQ!I23-1,"") | L30: =IFERROR(subQ!L23/subQ!J23-1,"") | M30: =IFERROR(subQ!M23/subQ!L23-1,"") | N30: =IFERROR(subQ!N23/subQ!M23-1,"") | O30: =IFERROR(subQ!O23/subQ!N23-1,"") | Q30: =IFERROR(subQ!Q23/subQ!O23-1,"") | R30: =IFERROR(subQ!R23/subQ!Q23-1,"") | S30: =IFERROR(subQ!S23/subQ!R23-1,"") | T30: =IFERROR(subQ!T23/subQ!S23-1,"") | V30: =IFERROR(subQ!V23/subQ!T23-1,"") | W30: =IFERROR(subQ!W23/subQ!V23-1,"") | X30: =IFERROR(subQ!X23/subQ!W23-1,"") | Y30: =IFERROR(subQ!Y23/subQ!X23-1,"") | AA30: =IFERROR(subQ!AA23/subQ!Y23-1,"") | AB30: =IFERROR(subQ!AB23/subQ!AA23-1,"") | AC30: -3.7e-07 | AD30: 0 | AF30: 0 | AG30: 0 | AH30: 0 | AI30: 0 | AK30: 0 | AL30: 0 | AM30: 0 | AN30: 0
A31: drv:자본총계 | B31: roll | C31: 자본총계 기타변동(배당 등, 억원) | G31: =IFERROR(subQ!E24+subQ!G17-subQ!G24,"") | H31: =IFERROR(subQ!G24+subQ!H17-subQ!H24,"") | I31: =IFERROR(subQ!H24+subQ!I17-subQ!I24,"") | J31: =IFERROR(subQ!I24+subQ!J17-subQ!J24,"") | L31: =IFERROR(subQ!J24+subQ!L17-subQ!L24,"") | M31: =IFERROR(subQ!L24+subQ!M17-subQ!M24,"") | N31: =IFERROR(subQ!M24+subQ!N17-subQ!N24,"") | O31: =IFERROR(subQ!N24+subQ!O17-subQ!O24,"") | Q31: =IFERROR(subQ!O24+subQ!Q17-subQ!Q24,"") | R31: =IFERROR(subQ!Q24+subQ!R17-subQ!R24,"") | S31: =IFERROR(subQ!R24+subQ!S17-subQ!S24,"") | T31: =IFERROR(subQ!S24+subQ!T17-subQ!T24,"") | V31: =IFERROR(subQ!T24+subQ!V17-subQ!V24,"") | W31: =IFERROR(subQ!V24+subQ!W17-subQ!W24,"") | X31: =IFERROR(subQ!W24+subQ!X17-subQ!X24,"") | Y31: =IFERROR(subQ!X24+subQ!Y17-subQ!Y24,"") | AA31: =IFERROR(subQ!Y24+subQ!AA17-subQ!AA24,"") | AB31: =IFERROR(subQ!AA24+subQ!AB17-subQ!AB24,"") | AC31: -0.003270729 | AD31: -0.003910465 | AF31: 0.002227486 | AG31: 34.001436 | AH31: -0.002805422 | AI31: -0.001083468 | AK31: 0.002059293 | AL31: 33.998753 | AM31: -0.007099827 | AN31: 0.003702807
A32: drv:지배주주지분 | B32: roll | C32: 지배주주지분 기타변동(배당 등, 억원) | G32: =IFERROR(subQ!E25+subQ!G18-subQ!G25,"") | H32: =IFERROR(subQ!G25+subQ!H18-subQ!H25,"") | I32: =IFERROR(subQ!H25+subQ!I18-subQ!I25,"") | J32: =IFERROR(subQ!I25+subQ!J18-subQ!J25,"") | L32: =IFERROR(subQ!J25+subQ!L18-subQ!L25,"") | M32: =IFERROR(subQ!L25+subQ!M18-subQ!M25,"") | N32: =IFERROR(subQ!M25+subQ!N18-subQ!N25,"") | O32: =IFERROR(subQ!N25+subQ!O18-subQ!O25,"") | Q32: =IFERROR(subQ!O25+subQ!Q18-subQ!Q25,"") | R32: =IFERROR(subQ!Q25+subQ!R18-subQ!R25,"") | S32: =IFERROR(subQ!R25+subQ!S18-subQ!S25,"") | T32: =IFERROR(subQ!S25+subQ!T18-subQ!T25,"") | V32: =IFERROR(subQ!T25+subQ!V18-subQ!V25,"") | W32: =IFERROR(subQ!V25+subQ!W18-subQ!W25,"") | X32: =IFERROR(subQ!W25+subQ!X18-subQ!X25,"") | Y32: =IFERROR(subQ!X25+subQ!Y18-subQ!Y25,"") | AA32: =IFERROR(subQ!Y25+subQ!AA18-subQ!AA25,"") | AB32: =IFERROR(subQ!AA25+subQ!AB18-subQ!AB25,"") | AC32: 0.001629271 | AD32: -0.003910465 | AF32: 0.002227486 | AG32: 33.991436 | AH32: -0.002805422 | AI32: 0.008916532 | AK32: -0.007940707 | AL32: 33.998753 | AM32: 0.002900173 | AN32: -0.006297193
A33: drv:총차입금 | B33: qoq | C33: 총차입금 QoQ | G33: =IFERROR(subQ!G26/subQ!E26-1,"") | H33: =IFERROR(subQ!H26/subQ!G26-1,"") | I33: =IFERROR(subQ!I26/subQ!H26-1,"") | J33: =IFERROR(subQ!J26/subQ!I26-1,"") | L33: =IFERROR(subQ!L26/subQ!J26-1,"") | M33: =IFERROR(subQ!M26/subQ!L26-1,"") | N33: =IFERROR(subQ!N26/subQ!M26-1,"") | O33: =IFERROR(subQ!O26/subQ!N26-1,"") | Q33: =IFERROR(subQ!Q26/subQ!O26-1,"") | R33: =IFERROR(subQ!R26/subQ!Q26-1,"") | S33: =IFERROR(subQ!S26/subQ!R26-1,"") | T33: =IFERROR(subQ!T26/subQ!S26-1,"") | V33: =IFERROR(subQ!V26/subQ!T26-1,"") | W33: =IFERROR(subQ!W26/subQ!V26-1,"") | X33: =IFERROR(subQ!X26/subQ!W26-1,"") | Y33: =IFERROR(subQ!Y26/subQ!X26-1,"") | AA33: =IFERROR(subQ!AA26/subQ!Y26-1,"") | AB33: =IFERROR(subQ!AB26/subQ!AA26-1,"") | AC33: 2.8e-07 | AD33: 0 | AF33: 0 | AG33: 0 | AH33: 0 | AI33: 0 | AK33: 0 | AL33: 0 | AM33: 0 | AN33: 0
A34: drv:순차입금 | B34: qoq | C34: 순차입금 QoQ | G34: =IFERROR(subQ!G27/subQ!E27-1,"") | H34: =IFERROR(subQ!H27/subQ!G27-1,"") | I34: =IFERROR(subQ!I27/subQ!H27-1,"") | J34: =IFERROR(subQ!J27/subQ!I27-1,"") | L34: =IFERROR(subQ!L27/subQ!J27-1,"") | M34: =IFERROR(subQ!M27/subQ!L27-1,"") | N34: =IFERROR(subQ!N27/subQ!M27-1,"") | O34: =IFERROR(subQ!O27/subQ!N27-1,"") | Q34: =IFERROR(subQ!Q27/subQ!O27-1,"") | R34: =IFERROR(subQ!R27/subQ!Q27-1,"") | S34: =IFERROR(subQ!S27/subQ!R27-1,"") | T34: =IFERROR(subQ!T27/subQ!S27-1,"") | V34: =IFERROR(subQ!V27/subQ!T27-1,"") | W34: =IFERROR(subQ!W27/subQ!V27-1,"") | X34: =IFERROR(subQ!X27/subQ!W27-1,"") | Y34: =IFERROR(subQ!Y27/subQ!X27-1,"") | AA34: =IFERROR(subQ!AA27/subQ!Y27-1,"") | AB34: =IFERROR(subQ!AB27/subQ!AA27-1,"") | AC34: 0.007063276 | AD34: 0.007852913 | AF34: 0.007409057 | AG34: 0.013258393 | AH34: 0.006946989 | AI34: 0.00771517 | AK34: 0.007282481 | AL34: 0.012928319 | AM34: 0.006855242 | AN34: 0.007594875
A35: drv:이자발생자산 | B35: qoq | C35: 이자발생자산 QoQ | G35: =IFERROR(subQ!G28/subQ!E28-1,"") | H35: =IFERROR(subQ!H28/subQ!G28-1,"") | I35: =IFERROR(subQ!I28/subQ!H28-1,"") | J35: =IFERROR(subQ!J28/subQ!I28-1,"") | L35: =IFERROR(subQ!L28/subQ!J28-1,"") | M35: =IFERROR(subQ!M28/subQ!L28-1,"") | N35: =IFERROR(subQ!N28/subQ!M28-1,"") | O35: =IFERROR(subQ!O28/subQ!N28-1,"") | Q35: =IFERROR(subQ!Q28/subQ!O28-1,"") | R35: =IFERROR(subQ!R28/subQ!Q28-1,"") | S35: =IFERROR(subQ!S28/subQ!R28-1,"") | T35: =IFERROR(subQ!T28/subQ!S28-1,"") | V35: =IFERROR(subQ!V28/subQ!T28-1,"") | W35: =IFERROR(subQ!W28/subQ!V28-1,"") | X35: =IFERROR(subQ!X28/subQ!W28-1,"") | Y35: =IFERROR(subQ!Y28/subQ!X28-1,"") | AA35: =IFERROR(subQ!AA28/subQ!Y28-1,"") | AB35: =IFERROR(subQ!AB28/subQ!AA28-1,"") | AC35: -0.018469417 | AD35: -0.021067769 | AF35: -0.020464222 | AG35: -0.037662464 | AH35: -0.020778168 | AI35: -0.023729121 | AK35: -0.02311974 | AL35: -0.042320972 | AM35: -0.02373532 | AN35: -0.027120169
A36: drv:현금및현금성자산 | B36: qoq | C36: 현금및현금성자산 QoQ | G36: =IFERROR(subQ!G29/subQ!E29-1,"") | H36: =IFERROR(subQ!H29/subQ!G29-1,"") | I36: =IFERROR(subQ!I29/subQ!H29-1,"") | J36: =IFERROR(subQ!J29/subQ!I29-1,"") | L36: =IFERROR(subQ!L29/subQ!J29-1,"") | M36: =IFERROR(subQ!M29/subQ!L29-1,"") | N36: =IFERROR(subQ!N29/subQ!M29-1,"") | O36: =IFERROR(subQ!O29/subQ!N29-1,"") | Q36: =IFERROR(subQ!Q29/subQ!O29-1,"") | R36: =IFERROR(subQ!R29/subQ!Q29-1,"") | S36: =IFERROR(subQ!S29/subQ!R29-1,"") | T36: =IFERROR(subQ!T29/subQ!S29-1,"") | V36: =IFERROR(subQ!V29/subQ!T29-1,"") | W36: =IFERROR(subQ!W29/subQ!V29-1,"") | X36: =IFERROR(subQ!X29/subQ!W29-1,"") | Y36: =IFERROR(subQ!Y29/subQ!X29-1,"") | AA36: =IFERROR(subQ!AA29/subQ!Y29-1,"") | AB36: =IFERROR(subQ!AB29/subQ!AA29-1,"")
A37: drv:CAPEX | B37: yoy | C37: CAPEX YoY | J37: =IFERROR(subQ!J30/subQ!E30-1,"") | L37: =IFERROR(subQ!L30/subQ!G30-1,"") | M37: =IFERROR(subQ!M30/subQ!H30-1,"") | N37: =IFERROR(subQ!N30/subQ!I30-1,"") | O37: =IFERROR(subQ!O30/subQ!J30-1,"") | Q37: =IFERROR(subQ!Q30/subQ!L30-1,"") | R37: =IFERROR(subQ!R30/subQ!M30-1,"") | S37: =IFERROR(subQ!S30/subQ!N30-1,"") | T37: =IFERROR(subQ!T30/subQ!O30-1,"") | V37: =IFERROR(subQ!V30/subQ!Q30-1,"") | W37: =IFERROR(subQ!W30/subQ!R30-1,"") | X37: =IFERROR(subQ!X30/subQ!S30-1,"") | Y37: =IFERROR(subQ!Y30/subQ!T30-1,"") | AA37: =IFERROR(subQ!AA30/subQ!V30-1,"") | AB37: =IFERROR(subQ!AB30/subQ!W30-1,"") | AC37: 0.18643839 | AD37: -0.1525655 | AF37: 1.2216524 | AG37: -0.13578498 | AH37: 0 | AI37: 0 | AK37: 0 | AL37: 0 | AM37: 0 | AN37: 0
A38: drv:영업활동현금흐름 | B38: yoy | C38: 영업활동현금흐름 YoY | J38: =IFERROR(subQ!J31/subQ!E31-1,"") | L38: =IFERROR(subQ!L31/subQ!G31-1,"") | M38: =IFERROR(subQ!M31/subQ!H31-1,"") | N38: =IFERROR(subQ!N31/subQ!I31-1,"") | O38: =IFERROR(subQ!O31/subQ!J31-1,"") | Q38: =IFERROR(subQ!Q31/subQ!L31-1,"") | R38: =IFERROR(subQ!R31/subQ!M31-1,"") | S38: =IFERROR(subQ!S31/subQ!N31-1,"") | T38: =IFERROR(subQ!T31/subQ!O31-1,"") | V38: =IFERROR(subQ!V31/subQ!Q31-1,"") | W38: =IFERROR(subQ!W31/subQ!R31-1,"") | X38: =IFERROR(subQ!X31/subQ!S31-1,"") | Y38: =IFERROR(subQ!Y31/subQ!T31-1,"") | AA38: =IFERROR(subQ!AA31/subQ!V31-1,"") | AB38: =IFERROR(subQ!AB31/subQ!W31-1,"")
A39: drv:주식수 | B39: qoq | C39: 주식수 QoQ | G39: =IFERROR(subQ!G32/subQ!E32-1,"") | H39: =IFERROR(subQ!H32/subQ!G32-1,"") | I39: =IFERROR(subQ!I32/subQ!H32-1,"") | J39: =IFERROR(subQ!J32/subQ!I32-1,"") | L39: =IFERROR(subQ!L32/subQ!J32-1,"") | M39: =IFERROR(subQ!M32/subQ!L32-1,"") | N39: =IFERROR(subQ!N32/subQ!M32-1,"") | O39: =IFERROR(subQ!O32/subQ!N32-1,"") | Q39: =IFERROR(subQ!Q32/subQ!O32-1,"") | R39: =IFERROR(subQ!R32/subQ!Q32-1,"") | S39: =IFERROR(subQ!S32/subQ!R32-1,"") | T39: =IFERROR(subQ!T32/subQ!S32-1,"") | V39: =IFERROR(subQ!V32/subQ!T32-1,"") | W39: =IFERROR(subQ!W32/subQ!V32-1,"") | X39: =IFERROR(subQ!X32/subQ!W32-1,"") | Y39: =IFERROR(subQ!Y32/subQ!X32-1,"") | AA39: =IFERROR(subQ!AA32/subQ!Y32-1,"") | AB39: =IFERROR(subQ!AB32/subQ!AA32-1,"") | AC39: 0 | AD39: 0 | AF39: 0 | AG39: 0 | AH39: 0 | AI39: 0 | AK39: 0 | AL39: 0 | AM39: 0 | AN39: 0
A40: drv:DPS | B40: abs | C40: DPS (가정, 원) | E40: =subQ!E36 | F40: =subQ!F36 | G40: =subQ!G36 | H40: =subQ!H36 | I40: =subQ!I36 | J40: =subQ!J36 | K40: =subQ!K36 | L40: =subQ!L36 | ... AB40: =subQ!AB36 | AD40: 120 | AE40: =subQ!AE36 | AI40: 120 | AJ40: =subQ!AJ36 | AN40: 120 | AO40: =subQ!AO36
B42: 3. 밸류에이션·스칼라 | C42: 노란 셀 = 가정. '연결' 표시는 추정 전 분기 수식이 이 셀을 참조한다는 뜻
A43: sc:종가 | C43: 종가 | D43: 4015 | E43: 원 — 네이버 정규장 종가(aik 확정종가 대조 · aik 4,220원)
A44: sc:기준일 | C44: 기준일 | D44: 20261026 | E44: 종가 기준일
A45: sc:COE | C45: COE | D45: 0.09 | E45: 자기자본비용(가정) — TP 적정 PBR = ROE/COE
A46: sc:PER_lo | C46: PER_lo | D46: 10 | E46: PER 밴드 하단(배) — sector_default(레퍼런스 TP_PE PB 예시 10/15/20배; 과거 PER 중위 4.2배가 캡 5~30 밖 — 턴어라운드 초기 TTM EPS 왜곡)
A47: sc:PER_mid | C47: PER_mid | D47: 15 | E47: PER 밴드 중단(배)
A48: sc:PER_hi | C48: PER_hi | D48: 20 | E48: PER 밴드 상단(배)
A49: sc:EPS_Y1가중 | C49: EPS_Y1가중 | D49: 0.5 | E49: 12M fwd EPS = FY(last_actual연도)E × w + FY+1E × (1−w) — 기준 분기 2Q 이면 0.5(가정)
A50: sc:세율 | C50: 세율 | D50: 0.24032543 | E50: 연결 — 법인세 = MAX(세전,0) × 세율(역산, 재현 오차 ≤ 0.05억 · 모델 assumptions 0.2404) · 최근 12분기 유효세율 28.1% 가 5~27% 밖 → 클립 대신 최근 8분기 중 세전 > 0 인 5분기(2024Q3~2026Q2)의 법인세/세전 중위 24.0%
A51: sc:판관비율 | C51: 판관비율 | D51: 0.13401817 | E51: 연결 — 판관비 = 매출액 × 판관비율(역산, 재현 오차 ≤ 0.05억 · 모델 assumptions 0.134)
A52: sc:지배주주비중 | C52: 지배주주비중 | D52: 1 | E52: 연결 — 지배주주순이익 = 당기순이익 × 비중(역산, 재현 오차 ≤ 0.05억)
A53: sc:이자율_자산 | C53: 이자율_자산 | D53: 0.024636603 | E53: 연결 — 이자손익 = (전분기 이자발생자산 × 자산이자율 − 전분기 총차입금 × 부채이자율)/4(역산, 재현 오차 ≤ 0.05억 · 모델 assumptions 0.0247)
A54: sc:이자율_부채 | C54: 이자율_부채 | D54: 0.039959163 | E54: 연결 — 같은 수식의 부채 쪽(총차입금 행이 없으면 0)(역산, 재현 오차 ≤ 0.05억 · 모델 assumptions 0.04)
A55: sc:배당성향 | C55: 배당성향 | E55: 배당성향(참고 — 모델은 직전 DPS 유지·Q2 지급 가정)
A56: sc:외화순노출_백만$ | C56: 외화순노출_백만$ | E56: 외화 순노출 × Δ기말환율 (외화 시트 방식) — 외화 순노출 미공시(face) → 0 + 표기
A57: sc:헤지비율 | C57: 헤지비율 | E57: sls 없음
A58: sc:헤지환율_약정 | C58: 헤지환율_약정 | E58: sls 없음

Sheet BS연결
B1: (백만원) | C1: 이름: BS연결H | E1: 4Q21 | F1: 2021 | G1: 1Q22 | H1: 2Q22 | I1: 3Q22 | J1: 4Q22 | K1: 2022 | L1: 1Q23 | M1: 2Q23 | N1: 3Q23 | O1: 4Q23 | P1: 2023 | Q1: 1Q24 | R1: 2Q24 | S1: 3Q24 | T1: 4Q24 | U1: 2024 | V1: 1Q25 | W1: 2Q25 | X1: 3Q25 | Y1: 4Q25 | Z1: 2025 | AA1: 1Q26 | AB1: 2Q26 | AC1: 3Q26 | AD1: 4Q26 | AE1: 2026 | AF1: 1Q27 | AG1: 2Q27 | AH1: 3Q27 | AI1: 4Q27 | AJ1: 2027 | AK1: 1Q28 | AL1: 2Q28 | AM1: 3Q28 | AN1: 4Q28 | AO1: 2028
B2: 연결 | D2: fin json(kship_fin.py)
B3: 금강공업(연) | C3: UPDATE: 26-10-26 | E3: 1 | F3: 2 | G3: 3 | H3: 4 | I3: 5 | J3: 6 | K3: 7 | L3: 8 | M3: 9 | N3: 10 | O3: 11 | P3: 12 | Q3: 13 | R3: 14 | S3: 15 | T3: 16 | U3: 17 | V3: 18 | W3: 19 | X3: 20 | Y3: 21 | Z3: 22 | AA3: 23 | AB3: 24 | AC3: 25 | AD3: 26 | AE3: 27 | AF3: 28 | AG3: 29 | AH3: 30 | AI3: 31 | AJ3: 32 | AK3: 33 | AL3: 34 | AM3: 35 | AN3: 36 | AO3: 37
B4: Account Code | C4: AccountNAME | E4: 2021.12 | F4: 2021.12A | G4: 2022.03 | H4: 2022.06 | I4: 2022.09 | J4: 2022.12 | K4: 2022.12A | L4: 2023.03 | M4: 2023.06 | N4: 2023.09 | O4: 2023.12 | P4: 2023.12A | Q4: 2024.03 | R4: 2024.06 | S4: 2024.09 | T4: 2024.12 | U4: 2024.12A | V4: 2025.03 | W4: 2025.06 | X4: 2025.09 | Y4: 2025.12 | Z4: 2025.12A | AA4: 2026.03 | AB4: 2026.06 | AC4: 2026.09 | AD4: 2026.12 | AE4: 2026.12A | AF4: 2027.03 | AG4: 2027.06 | AH4: 2027.09 | AI4: 2027.12 | AJ4: 2027.12A | AK4: 2028.03 | AL4: 2028.06 | AM4: 2028.09 | AN4: 2028.12 | AO4: 2028.12A
A5: 1 | C5: 유동자산 | E5: 355324.57 | F5: 355324.57 | G5: 364344.68 | H5: 401523.23 | I5: 449359.38 | J5: 443511.16 | K5: 443511.16 | L5: 450494.2 | M5: 473426.88 | N5: 466982.73 | O5: 455179.4 | P5: 455179.4 | Q5: 468915.29 | R5: 469530.85 | S5: 461818.41 | T5: 453123.57 | U5: 453123.57 | V5: 469424.27 | W5: 509681.05 | X5: 507015.82 | Y5: 461072.94 | Z5: 461072.94 | AA5: 491973.77 | AB5: 528803.02
A6: 1 | C6: 현금및현금성자산 | E6: 95812.34 | F6: 95812.34 | G6: 98416.71 | H6: 99546.1 | I6: 100497.59 | J6: 90140.29 | K6: 90140.29 | L6: 97265.77 | M6: 109737.87 | N6: 97769.93 | O6: 102115.48 | P6: 102115.48 | Q6: 107072.44 | R6: 78957.63 | S6: 91068.04 | T6: 87456.76 | U6: 87456.76 | V6: 121129.8 | W6: 114887.68 | X6: 136169.92 | Y6: 107221.32 | Z6: 107221.32 | AA6: 134973.03 | AB6: 152322.7
A7: 1 | C7: 매출채권및기타채권 | E7: 116584.12 | F7: 116584.12 | G7: 128662.14 | H7: 121899.93 | I7: 136679.1 | J7: 132121.79 | K7: 132121.79 | L7: 143238.06 | M7: 146995.96 | N7: 143414.21 | O7: 142179.68 | P7: 142179.68 | Q7: 149710.13 | R7: 154090.61 | S7: 142551.94 | T7: 161581.55 | U7: 161581.55 | V7: 159856.55 | W7: 181839.38 | X7: 154329.02 | Y7: 139018.71 | Z7: 139018.71 | AA7: 143411.89 | AB7: 151946.29
A8: 1 | C8: 재고자산 | E8: 126845.81 | F8: 126845.81 | G8: 119602.29 | H8: 160295.17 | I8: 189091.75 | J8: 189876.69 | K8: 189876.69 | L8: 178476.11 | M8: 196207.83 | N8: 202528.38 | O8: 186757.6 | P8: 186757.6 | Q8: 188271.57 | R8: 191234.32 | S8: 186077.54 | T8: 165316.92 | U8: 165316.92 | V8: 168424.43 | W8: 178822.42 | X8: 180596.85 | Y8: 176610.81 | Z8: 176610.81 | AA8: 193133.4 | AB8: 204973.52
A9: 1 | C9: 기타유동자산 | E9: 4318.65 | F9: 4318.65 | G9: 5047.3 | H9: 4257.5 | I9: 4470.48 | J9: 3655.29 | K9: 3655.29 | L9: 6028.95 | M9: 4689.67 | N9: 6347.48 | O9: 4648.13 | P9: 4648.13 | Q9: 5341.25 | R9: 6868.74 | S9: 7249.52 | T9: 5919.34 | U9: 5919.34 | V9: 6963.42 | W9: 8749.54 | X9: 9994.04 | Y9: 10347.11 | Z9: 10347.11 | AA9: 11284.78 | AB9: 8946.28
A10: 1 | C10: 당기법인세자산(선급법인세) | E10: 2028.59 | F10: 2028.59 | G10: 2279.65 | H10: 2165.94 | I10: 2659.41 | J10: 2170.41 | K10: 2170.41 | L10: 2323.05 | M10: 2300.81 | N10: 2561.42 | O10: 2457.48 | P10: 2457.48 | Q10: 1531.49 | R10: 1488.84 | S10: 2159.25 | T10: 2773.7 | U10: 2773.7 | V10: 1726.53 | W10: 1552.2 | X10: 1679.11 | Y10: 1875.33 | Z10: 1875.33 | AA10: 662.37 | AB10: 328.12
A11: 1 | C11: 비유동자산 | E11: 513334.18 | F11: 513334.18 | G11: 530372.8 | H11: 542969.35 | I11: 666721.39 | J11: 651290.64 | K11: 651290.64 | L11: 662261.62 | M11: 670731.41 | N11: 671464.62 | O11: 675288.31 | P11: 675288.31 | Q11: 679565.66 | R11: 689860.88 | S11: 705225.43 | T11: 708775.68 | U11: 708775.68 | V11: 720090.89 | W11: 697203.21 | X11: 712713.69 | Y11: 726918.64 | Z11: 726918.64 | AA11: 751863.06 | AB11: 786511.55
A12: 1 | C12: 유형자산 | E12: 421857.81 | F12: 421857.81 | G12: 432432.42 | H12: 442043.01 | I12: 568288.15 | J12: 559968.68 | K12: 559968.68 | L12: 568275.74 | M12: 577159.88 | N12: 576276.88 | O12: 557986.09 | P12: 557986.09 | Q12: 569249.12 | R12: 577502.94 | S12: 557638.19 | T12: 560881.99 | U12: 560881.99 | V12: 565978.92 | W12: 561531.97 | X12: 572807.53 | Y12: 580014.8 | Z12: 580014.8 | AA12: 608547.39 | AB12: 639688.31
A13: 1 | C13: 무형자산 | E13: 8904.19 | F13: 8904.19 | G13: 8689.87 | H13: 8662.35 | I13: 8641.14 | J13: 9002.32 | K13: 9002.32 | L13: 9044.54 | M13: 8034.59 | N13: 8098.3 | O13: 8097.81 | P13: 8097.81 | Q13: 7911.34 | R13: 8407.57 | S13: 8513.16 | T13: 8484.65 | U13: 8484.65 | V13: 9186.83 | W13: 9163.15 | X13: 11167.36 | Y13: 11145.66 | Z13: 11145.66 | AA13: 15263.86 | AB13: 14873.04
A14: 1 | C14: 투자부동산 | E14: 15342.8 | F14: 15342.8 | G14: 16524.27 | H14: 16516.17 | I14: 16563.44 | J14: 17639.57 | K14: 17639.57 | L14: 21026.12 | M14: 20926.2 | N14: 20911.45 | O14: 39545.56 | P14: 39545.56 | Q14: 36299.16 | R14: 36661.48 | S14: 71432.72 | T14: 72426.69 | U14: 72426.69 | V14: 72376.43 | W14: 54056.45 | X14: 53946.85 | Y14: 55366.08 | Z14: 55366.08 | AA14: 55272.84 | AB14: 55129
A15: 1 | C15: 종속기업및관계기업투자 | E15: 19283.43 | F15: 19283.43 | G15: 19947.6 | H15: 21008.37 | I15: 21621.51 | J15: 20160.96 | K15: 20160.96 | L15: 19596.58 | M15: 19545.38 | N15: 19539.27 | O15: 19719.57 | P15: 19719.57 | Q15: 18979.21 | R15: 19698.05 | S15: 19617.06 | X15: 26630.6 | AA15: 29386.82 | AB15: 31662.4
A16: 1 | C16: 투자자산 | E16: 29496.17 | F16: 29496.17 | G16: 30808.03 | H16: 30528.69 | I16: 30887.06 | J16: 29660.05 | K16: 29660.05 | L16: 29462.58 | M16: 29416.43 | N16: 30158.33 | O16: 32002.99 | P16: 32002.99 | Q16: 30925.71 | R16: 31533.26 | S16: 29714.77 | T16: 9563.47 | U16: 9563.47 | V16: 9714.85 | W16: 10278.84 | X16: 39320.84 | Y16: 25154.29 | Z16: 25154.29 | AA16: 51715.98 | AB16: 53625.66
A17: 1 | C17: 장기금융자산 | E17: 10212.74 | F17: 10212.74 | G17: 10860.43 | H17: 9520.32 | I17: 9265.55 | J17: 9499.09 | K17: 9499.09 | L17: 9866 | M17: 9871.05 | N17: 10619.06 | O17: 12283.42 | P17: 12283.42 | Q17: 11946.5 | R17: 11835.21 | S17: 10097.71 | T17: 9563.47 | U17: 9563.47 | V17: 9714.85 | W17: 10278.84 | X17: 12690.24 | Y17: 25154.29 | Z17: 25154.29 | AA17: 22329.16 | AB17: 21963.26
A18: 1 | C18: 장기매출채권및기타채권 | E18: 30105.88 | F18: 30105.88 | J18: 26407.08 | K18: 26407.08 | T18: 26725.86 | U18: 26725.86 | V18: 29380.51 | W18: 29821.75 | Y18: 17811.52 | Z18: 17811.52
A19: 1 | C19: 기타비유동자산 | E19: 5539.22 | F19: 5539.22 | G19: 5315.94 | H19: 4535.88 | I19: 4188.09 | J19: 5568.06 | K19: 5568.06 | L19: 3723.05 | M19: 3717.04 | N19: 3619.77 | O19: 6741.64 | P19: 6741.64 | Q19: 3575.48 | R19: 3531.64 | S19: 3402.68 | T19: 3640.13 | U19: 3640.13 | V19: 3550.97 | W19: 3170.39 | X19: 3338.75 | Y19: 3605.94 | Z19: 3605.94 | AA19: 4516.77 | AB19: 7665.34
A20: 1 | C20: 이연법인세자산 | E20: 1992.21 | F20: 1992.21 | G20: 2083.67 | H20: 2001.29 | I20: 2282.61 | J20: 2780.22 | K20: 2780.22 | L20: 2963.13 | M20: 3091.88 | N20: 2825.83 | O20: 2877.72 | P20: 2877.72 | Q20: 3015.76 | R20: 2727.3 | S20: 2829.31 | T20: 3113.73 | U20: 3113.73 | V20: 2690.64 | W20: 2259.12 | X20: 1855.97 | Y20: 686.79 | Z20: 686.79 | AA20: 658.35 | AB20: 655.42
A21: 1 | C21: 자산총계 | E21: 868658.75 | F21: 868658.75 | G21: 894717.47 | H21: 944492.58 | I21: 1116080.8 | J21: 1094801.8 | K21: 1094801.8 | L21: 1112755.8 | M21: 1144158.3 | N21: 1138447.4 | O21: 1130467.7 | P21: 1130467.7 | Q21: 1148481 | R21: 1159391.7 | S21: 1167043.9 | T21: 1161899.2 | U21: 1161899.2 | V21: 1189515.2 | W21: 1206884.3 | X21: 1219729.5 | Y21: 1187991.6 | Z21: 1187991.6 | AA21: 1243836.8 | AB21: 1315314.6
A22: 1 | C22: 유동부채 | E22: 405262.57 | F22: 405262.57 | G22: 413517.96 | H22: 469980.87 | I22: 535220.67 | J22: 523650.51 | K22: 523650.51 | L22: 531881.92 | M22: 551277.57 | N22: 539718.5 | O22: 529800.87 | P22: 529800.87 | Q22: 565836.39 | R22: 524887.4 | S22: 533069.79 | T22: 512506.28 | U22: 512506.28 | V22: 514526.13 | W22: 560079 | X22: 504626.65 | Y22: 481770.63 | Z22: 481770.63 | AA22: 510531.7 | AB22: 526544.64
A23: 1 | C23: 매입채무및기타채무 | E23: 72400.52 | F23: 72400.52 | G23: 80966.17 | H23: 69928.17 | I23: 93629.64 | J23: 92300.42 | K23: 92300.42 | L23: 83547.49 | M23: 95266.64 | N23: 86621 | O23: 97968.59 | P23: 97968.59 | Q23: 98981.67 | R23: 75941.28 | S23: 77568.12 | T23: 82297.53 | U23: 82297.53 | V23: 82750.33 | W23: 79150.88 | X23: 78834.72 | Y23: 75981.81 | Z23: 75981.81 | AA23: 88284.23 | AB23: 78372.94
A24: 1 | C24: 단기차입금 | E24: 286819.44 | F24: 286819.44 | G24: 278438.88 | H24: 325283.63 | I24: 367192.63 | J24: 390288.61 | K24: 390288.61 | L24: 410737.3 | M24: 406193.92 | N24: 394319.97 | O24: 368173.96 | P24: 368173.96 | Q24: 421487.33 | R24: 400806.67 | S24: 416152.66 | T24: 318960.27 | U24: 318960.27 | V24: 331423.72 | W24: 344850.02 | X24: 315836.81 | Y24: 304530.9 | Z24: 304530.9 | AA24: 331099.6 | AB24: 392878.52
A25: 1 | C25: 기타유동부채 | E25: 27910.06 | F25: 27910.06 | G25: 24353.47 | H25: 24648.4 | I25: 28339.34 | J25: 28995.82 | K25: 28995.82 | L25: 28035.25 | M25: 42788.28 | N25: 50414.24 | O25: 41993.2 | P25: 41993.2 | Q25: 38538.89 | R25: 44457.64 | S25: 36102.92 | T25: 35183.47 | U25: 35183.47 | V25: 34717.63 | W25: 50101.16 | X25: 55714.48 | Y25: 54589.97 | Z25: 54589.97 | AA25: 49711.36 | AB25: 50328.79
A26: 1 | C26: 당기법인세부채(미지급법인세) | E26: 3786.62 | F26: 3786.62 | G26: 5537.07 | H26: 5742.62 | I26: 7035.13 | J26: 9037.21 | K26: 9037.21 | L26: 6005.04 | M26: 4117.92 | N26: 5694.06 | O26: 4087.7 | P26: 4087.7 | Q26: 4549.18 | R26: 1379.86 | S26: 1048.77 | T26: 1444.45 | U26: 1444.45 | V26: 1526.37 | W26: 1572.58 | X26: 1548.36 | Y26: 2604.49 | Z26: 2604.49 | AA26: 2162.81 | AB26: 2290.91
A27: 1 | C27: 유동리스부채 | E27: 2131.97 | F27: 2131.97 | G27: 2295.95 | H27: 2262.4 | I27: 2228.94 | J27: 2010.33 | K27: 2010.33 | L27: 2180.86 | M27: 2126.1 | N27: 1939.13 | O27: 2070.85 | P27: 2070.85 | Q27: 2063.58 | R27: 2013.65 | S27: 1959.8 | T27: 2203.98 | U27: 2203.98 | V27: 2318.32 | W27: 2519.21 | X27: 2198.56 | Y27: 1981.23 | Z27: 1981.23 | AA27: 2013.6 | AB27: 2009.39
A28: 1 | C28: 리스부채 | E28: 10569.52 | F28: 10569.52 | G28: 11175.41 | H28: 13485.52 | I28: 13381.93 | J28: 12888.58 | K28: 12888.58 | L28: 12766.09 | M28: 12346.06 | N28: 11743.01 | O28: 11259.76 | P28: 11259.76 | Q28: 10844.55 | R28: 10146.38 | S28: 10294.72 | T28: 10119.11 | U28: 10119.11 | V28: 10005.1 | W28: 9531.7 | X28: 9026.07 | Y28: 8484.4 | Z28: 8484.4 | AA28: 8609.92 | AB28: 8757.82
A29: 1 | C29: 단기금융부채 | E29: 2131.97 | F29: 2131.97 | G29: 2295.95 | H29: 2262.4 | I29: 2228.94 | J29: 2010.33 | K29: 2010.33 | L29: 2180.86 | M29: 2126.1 | N29: 1939.13 | O29: 2070.85 | P29: 2070.85 | Q29: 2063.58 | R29: 2013.65 | S29: 1959.8 | T29: 2203.98 | U29: 2203.98 | V29: 2318.32 | W29: 2519.21 | X29: 2198.56 | Y29: 1981.23 | Z29: 1981.23 | AA29: 2013.6 | AB29: 2009.39
A30: 1 | C30: 비유동부채 | E30: 76725.39 | F30: 76725.39 | G30: 86683.29 | H30: 73796.94 | I30: 128845.13 | J30: 122936.98 | K30: 122936.98 | L30: 128635.34 | M30: 128009.2 | N30: 125814.39 | O30: 123172.89 | P30: 123172.89 | Q30: 102439.6 | R30: 142039.24 | S30: 137422.15 | T30: 150054.62 | U30: 150054.62 | V30: 168756.12 | W30: 147832.18 | X30: 210418.44 | Y30: 208069.42 | Z30: 208069.42 | AA30: 220536.48 | AB30: 256221.65
A31: 1 | C31: 장기차입금 | E31: 46214.49 | F31: 46214.49 | G31: 55079.55 | H31: 40173.32 | I31: 73636.48 | J31: 72314.73 | K31: 72314.73 | L31: 76116.6 | M31: 78591.6 | N31: 80566.61 | O31: 82131.08 | P31: 82131.08 | Q31: 61557.44 | R31: 101492.78 | S31: 97705.83 | T31: 91283.42 | U31: 91283.42 | V31: 127659.57 | W31: 106939 | X31: 171166.66 | Y31: 172591.76 | Z31: 172591.76 | AA31: 182655.89 | AB31: 215163.31
A32: 1 | C32: 장기매입채무및기타채무 | E32: 1475.59 | F32: 1475.59 | H32: 1716.84 | I32: 1716.91 | J32: 1870.28 | K32: 1870.28 | L32: 2017.65 | M32: 1942.82 | N32: 1974.54 | O32: 1743.85 | P32: 1743.85 | Q32: 1617.13 | T32: 1003.03 | U32: 1003.03 | V32: 1071.82 | W32: 1184.44
A33: 1 | C33: 이연법인세부채 | E33: 18730.14 | F33: 18730.14 | G33: 19315.92 | H33: 19107.62 | I33: 38750.86 | J33: 36177.81 | K33: 36177.81 | L33: 36618.6 | M33: 34566.21 | N33: 31806.04 | O33: 28450.91 | P33: 28450.91 | Q33: 28663.09 | R33: 27897.25 | S33: 26863.34 | T33: 28048.24 | U33: 28048.24 | V33: 28681.25 | W33: 27721.24 | X33: 28159.86 | Y33: 26252.87 | Z33: 26252.87 | AA33: 28691.21 | AB33: 31720.8
A34: 1 | C34: 장기충당부채 | E34: 1194.7 | F34: 1194.7 | G34: 1140.91 | H34: 1093.04 | I34: 1066.47 | J34: 1280.86 | K34: 1280.86 | L34: 1365.25 | M34: 1457.78 | N34: 1445.29 | O34: 1658.13 | P34: 1658.13 | Q34: 1752.04 | R34: 1821.61 | S34: 1846.1 | T34: 1837.54 | U34: 1837.54 | V34: 1776.03 | W34: 1789.66 | X34: 1753.93 | Y34: 1538.96 | Z34: 1538.96 | AA34: 1421.22 | AB34: 1409.59
A35: 1 | C35: 비유동리스부채 | E35: 8437.55 | F35: 8437.55 | G35: 8879.46 | H35: 11223.12 | I35: 11152.99 | J35: 10878.25 | K35: 10878.25 | L35: 10585.23 | M35: 10219.96 | N35: 9803.88 | O35: 9188.91 | P35: 9188.91 | Q35: 8780.97 | R35: 8132.73 | S35: 8334.92 | T35: 7915.13 | U35: 7915.13 | V35: 7686.78 | W35: 7012.49 | X35: 6827.51 | Y35: 6503.17 | Z35: 6503.17 | AA35: 6596.32 | AB35: 6748.43
A36: 1 | C36: 장기금융부채 | E36: 8437.55 | F36: 8437.55 | G36: 10548.94 | H36: 11223.12 | I36: 11152.99 | J36: 10878.25 | K36: 10878.25 | L36: 10585.23 | M36: 10219.96 | N36: 9803.88 | O36: 9188.91 | P36: 9188.91 | Q36: 8780.97 | R36: 8132.73 | S36: 8334.92 | T36: 7915.13 | U36: 7915.13 | V36: 7686.78 | W36: 7012.49 | X36: 6827.51 | Y36: 6503.17 | Z36: 6503.17 | AA36: 6596.32 | AB36: 6748.43
A37: 1 | C37: 부채총계 | E37: 481987.96 | F37: 481987.96 | G37: 500201.25 | H37: 543777.8 | I37: 664065.8 | J37: 646587.48 | K37: 646587.48 | L37: 660517.26 | M37: 679286.76 | N37: 665532.89 | O37: 652973.75 | P37: 652973.75 | Q37: 668275.99 | R37: 666926.64 | S37: 670491.94 | T37: 662560.9 | U37: 662560.9 | V37: 683282.25 | W37: 707911.17 | X37: 715045.1 | Y37: 689840.04 | Z37: 689840.04 | AA37: 731068.19 | AB37: 782766.29
A38: 1 | C38: 지배주주지분 | E38: 310567.99 | F38: 310567.99 | G38: 318287.19 | H38: 324686.41 | I38: 372143.2 | J38: 367103.96 | K38: 367103.96 | L38: 371032.61 | M38: 382410.85 | N38: 392089.67 | O38: 393555.16 | P38: 393555.16 | Q38: 388983.67 | R38: 396499.27 | S38: 397339.04 | T38: 396522.12 | U38: 396522.12 | V38: 389534.89 | W38: 379639.62 | X38: 374876.44 | Y38: 359968.05 | Z38: 359968.05 | AA38: 371954 | AB38: 376768.77
A39: 1 | C39: 자본금 | E39: 63101.14 | F39: 63101.14 | G39: 63101.14 | H39: 63101.14 | I39: 63101.14 | J39: 63101.14 | K39: 63101.14 | L39: 63101.14 | M39: 63101.14 | N39: 63101.14 | O39: 63101.14 | P39: 63101.14 | Q39: 63101.14 | R39: 63101.14 | S39: 63101.14 | T39: 93020.37 | U39: 93020.37 | V39: 93020.37 | W39: 93020.37 | X39: 93020.37 | Y39: 93020.37 | Z39: 93020.37 | AA39: 93020.37 | AB39: 93020.37
A40: 1 | C40: 자본잉여금 | E40: 1069.8 | F40: 1069.8 | G40: 1069.8 | H40: 1173.36 | I40: 7132.85 | J40: 7971.36 | K40: 7971.36 | L40: 7971.36 | M40: 7971.36 | N40: 1772.95 | O40: 1772.95 | P40: 1772.95 | Q40: -3518.65 | R40: 2158.03 | S40: 2158.03 | T40: 35339.94 | U40: 35339.94 | V40: 31031.25 | W40: 31030.83 | X40: 31024.43 | Y40: 43348.05 | Z40: 43348.05 | AA40: 42248.59 | AB40: 40978.84
A41: 1 | C41: 기타자본 | E41: -1474.69 | F41: -1474.69 | G41: -448.57 | H41: -680.36 | I41: 2499.44 | J41: -910.39 | K41: -910.39 | L41: 337.04 | M41: -381.81 | N41: 353.88 | O41: -719.03 | P41: -719.03 | Q41: -493.3 | R41: -146.84 | S41: 1705.47 | T41: 3610.64 | U41: 3610.64 | V41: 3834.48 | W41: 1136.68 | X41: 2677.52 | Y41: 5716.35 | Z41: 5716.35 | AA41: 8384.53 | AB41: 7019.59
A42: 1 | C42: 이익잉여금 | E42: 247871.74 | F42: 247871.74 | G42: 254564.82 | H42: 261092.27 | I42: 299409.77 | J42: 296941.85 | K42: 296941.85 | L42: 299623.07 | M42: 311720.16 | N42: 326861.69 | O42: 329400.1 | P42: 329400.1 | Q42: 329894.47 | R42: 331386.94 | S42: 330374.4 | T42: 327652.3 | U42: 327652.3 | V42: 324749.92 | W42: 317552.88 | X42: 311255.26 | Y42: 280984.42 | Z42: 280984.42 | AA42: 291401.64 | AB42: 298851.11
A43: 1 | C43: 비지배주주지분 | E43: 76102.8 | F43: 76102.8 | G43: 76229.03 | H43: 76028.36 | I43: 79871.77 | J43: 81110.35 | K43: 81110.35 | L43: 81205.94 | M43: 82460.68 | N43: 80824.8 | O43: 83938.79 | P43: 83938.79 | Q43: 91221.3 | R43: 95965.81 | S43: 99212.86 | T43: 102816.23 | U43: 102816.23 | V43: 116698.02 | W43: 119333.47 | X43: 129807.97 | Y43: 138183.49 | Z43: 138183.49 | AA43: 140814.65 | AB43: 155779.52
A44: 1 | C44: 자본총계 | E44: 386670.79 | F44: 386670.79 | G44: 394516.22 | H44: 400714.77 | I44: 452014.97 | J44: 448214.31 | K44: 448214.31 | L44: 452238.55 | M44: 464871.52 | N44: 472914.47 | O44: 477493.96 | P44: 477493.96 | Q44: 480204.96 | R44: 492465.09 | S44: 496551.91 | T44: 499338.34 | U44: 499338.34 | V44: 506232.91 | W44: 498973.09 | X44: 504684.41 | Y44: 498151.54 | Z44: 498151.54 | AA44: 512768.65 | AB44: 532548.28
... A48: 1 | C48: 이자발생자산 | E48: 106025.08 | F48: 106025.08 | G48: 109277.14 | H48: 109066.42 | I48: 109763.14 | J48: 99639.38 | K48: 99639.38 | L48: 107131.77 | M48: 119608.92 | N48: 108388.99 | O48: 114398.9 | P48: 114398.9 | Q48: 119018.94 | R48: 90792.84 | S48: 101165.75 | T48: 97020.23 | U48: 97020.23 | V48: 130844.65 | W48: 125166.52 | X48: 148860.16 | Y48: 132375.61 | Z48: 132375.61 | AA48: 157302.19 | AB48: 174285.96
A49: 1 | C49: 유동성장기부채 | E49: 11833.32 | F49: 11833.32 | G49: 21926.43 | H49: 41219.68 | I49: 35922.74 | O49: 15016.29 | P49: 15016.29 | T49: 72117.5 | U49: 72117.5 | V49: 61392.72 | W49: 81371.09 | X49: 50099.02 | Y49: 41668.61 | Z49: 41668.61 | AA49: 36665.76
A50: 1 | C50: 사채 | E50: 30000 | F50: 30000 | G50: 50000 | O50: 60000 | P50: 60000 | T50: 19967.26 | U50: 19967.26 | V50: 39930.32 | W50: 39936.69
A51: 1 | C51: 기타비유동금융부채 | G51: 1669.48
A52: 1 | C52: 확정급여부채 | I52: 2077.68 | L52: 1769.4 | M52: 1230.82 | N52: 218.03 | Q52: 68.93 | R52: 1092.02 | S52: 1549.62 | X52: 1358.11
A53: 1 | C53: 단기금융부채(face) | J53: 390288.61 | K53: 390288.61 | L53: 410737.3 | M53: 406193.92 | N53: 394319.97 | Q53: 421487.33 | R53: 400806.67 | S53: 416152.66 | AB53: 392878.52
A54: 1 | C54: 단기충당부채 | J54: 42.12 | K54: 42.12 | L54: 44.53 | M54: 46.44 | N54: 46.91
A55: 1 | C55: 매각예정비유동자산및처분자산 | O55: 2254.93 | P55: 2254.93 | Q55: 93.59 | W55: 17729.08 | X55: 17729.08 | Y55: 17729.08 | Z55: 17729.08
A56: 1 | C56: 기타비유동부채 | R56: 1602.86 | S56: 1122.35 | X56: 1152.38 | Y56: 1182.65 | Z56: 1182.65 | AA56: 1171.84 | AB56: 1179.52
A57: 1 | C57: 장기금융부채(face) | X57: 4641.34 | Y57: 172591.76 | Z57: 172591.76 | AA57: 5349.24 | AB57: 11170.58
A58: 1 | C58: 매출액(수익) | E58: 145112.78 | G58: 173504.74 | H58: 169743.96 | I58: 177648.71 | J58: 208034.6 | K58: 728932.01 | L58: 210598.27 | M58: 214308.71 | N58: 211036.44 | O58: 220949.28 | P58: 856892.7 | Q58: 209293.48 | R58: 189474.93 | S58: 193709.01 | T58: 208874.59 | U58: 801352.01 | V58: 197870.76 | W58: 211821.39 | X58: 205273.93 | Y58: 187189.93 | Z58: 802156.01 | AA58: 196667.64 | AB58: 229092.31
A59: 1 | C59: 매출원가 | E59: 121131.79 | G59: 146525.21 | H59: 141725.6 | I59: 150135.15 | J59: 180200.25 | K59: 618586.21 | L59: 174858.2 | M59: 173686.92 | N59: 169138.32 | O59: 181141.91 | P59: 698825.35 | Q59: 173763.71 | R59: 158776.44 | S59: 162033.55 | T59: 180023.28 | U59: 674596.98 | V59: 165223.43 | W59: 179705.97 | X59: 173319.08 | Y59: 161691.22 | Z59: 679939.7 | AA59: 158096.34 | AB59: 182845.31
A60: 1 | C60: 매출총이익 | E60: 23980.99 | G60: 26979.53 | H60: 28018.36 | I60: 27513.56 | J60: 27834.34 | K60: 110345.79 | L60: 35740.07 | M60: 40621.79 | N60: 41898.12 | O60: 39807.37 | P60: 158067.35 | Q60: 35529.77 | R60: 30698.49 | S60: 31675.47 | T60: 28851.31 | U60: 126755.04 | V60: 32647.33 | W60: 32115.42 | X60: 31954.86 | Y60: 25498.71 | Z60: 122216.32 | AA60: 38571.3 | AB60: 46247.01
A61: 1 | C61: 판관비 | E61: 20353.34 | G61: 14958.49 | H61: 18160.71 | I61: 21062.07 | J61: 22225.06 | K61: 76406.33 | L61: 19988.67 | M61: 22359.31 | N61: 22962.35 | O61: 26174.94 | P61: 91485.27 | Q61: 21887.39 | R61: 22025.67 | S61: 25910.01 | T61: 23883.76 | U61: 93706.83 | V61: 25585.14 | W61: 28076.88 | X61: 31994.23 | Y61: 26062.67 | Z61: 111718.92 | AA61: 25332.05 | AB61: 28256.8
A62: 1 | C62: 영업이익 | E62: 3627.65 | G62: 12021.04 | H62: 9857.65 | I62: 6451.49 | J62: 5609.28 | K62: 33939.46 | L62: 15751.4 | M62: 18262.48 | N62: 18935.77 | O62: 13632.43 | P62: 66582.08 | Q62: 13642.38 | R62: 8672.82 | S62: 5765.46 | T62: 4967.55 | U62: 33048.21 | V62: 7062.19 | W62: 4038.54 | X62: -39.37 | Y62: -563.96 | Z62: 10497.4 | AA62: 13239.25 | AB62: 17990.21
A63: 1 | C63: 금융수익 | E63: 583.74 | G63: 593.94 | H63: 478.79 | I63: 620.94 | J63: 963.04 | K63: 2656.71 | L63: 852.84 | M63: 828.47 | N63: 811.14 | O63: 644.24 | P63: 3136.69 | Q63: 967.14 | R63: 860.02 | S63: 960.74 | T63: 1218.14 | U63: 4006.04 | V63: 846.06 | W63: 821.52 | X63: 895.45 | Y63: 724.97 | Z63: 3288 | AA63: 644.12 | AB63: 655.04
A64: 1 | C64: 금융비용 | E64: 2234.36 | G64: 2491.96 | H64: 3085.01 | I64: 3734.54 | J64: 5407.79 | K64: 14719.3 | L64: 6001.9 | M64: 5991.99 | N64: 6040.18 | O64: 6209.19 | P64: 24243.26 | Q64: 6493.93 | R64: 6189.24 | S64: 6274.54 | T64: 6593.13 | U64: 25550.84 | V64: 5857.41 | W64: 5605.04 | X64: 6009.09 | Y64: 5003.02 | Z64: 22474.56 | AA64: 5693.75 | AB64: 6151.99
A65: 1 | C65: 종속기업,공동지배기업및관계기업관련손익 | E65: -658.85 | G65: 664.17 | H65: 1060.77 | I65: -220.18 | J65: -1019.43 | K65: 485.33 | L65: -564.39 | M65: -191.99 | N65: -989.23 | O65: 617.24 | P65: -1128.37 | Q65: 187.59 | R65: 627.13 | S65: 173.46 | T65: 749.88 | U65: 1738.06 | V65: -76.47 | W65: 182.32 | X65: -130.94 | Y65: 1039.84 | Z65: 1014.75 | AA65: 1034.14 | AB65: 2204.96
A66: 1 | C66: 지분법관련손익 | E66: -658.85 | G66: 664.17 | H66: 1060.77 | I66: -220.18 | J66: -1019.43 | K66: 485.33 | L66: -564.39 | M66: -191.99 | N66: -989.23 | O66: 617.24 | P66: -1128.37 | Q66: 187.59 | R66: 627.13 | S66: 173.46 | T66: 749.88 | U66: 1738.06 | V66: -76.47 | W66: 182.32 | X66: -130.94 | Y66: 1039.84 | Z66: 1014.75 | AA66: 1034.14 | AB66: 2204.96
A67: 1 | C67: 기타영업외수익 | E67: 2847.17 | G67: 4021.64 | H67: 4351.69 | I67: 43474.57 | J67: -868.59 | K67: 50979.31 | L67: 4108.38 | M67: 3558.89 | N67: 6242.47 | O67: 2279.38 | P67: 16189.12 | Q67: 3679.77 | R67: 5128.54 | S67: 4565.72 | T67: 5410.03 | U67: 18784.06 | V67: 2899.22 | W67: 4778.35 | X67: 3874.19 | Y67: 2460.32 | Z67: 14012.08 | AA67: 15505.54 | AB67: 3377.59
A68: 1 | C68: 기타영업외비용 | E68: 351.52 | G68: 1409.1 | H68: 4483.01 | I68: 5008.1 | J68: 2104.4 | K68: 13004.61 | L68: 3754.11 | M68: 2659.65 | N68: 2778.08 | O68: 5037.27 | P68: 14229.11 | Q68: 2312.02 | R68: 2982.9 | S68: 1808.59 | T68: 3870.59 | U68: 10974.1 | V68: 1475.36 | W68: 6434.43 | X68: 2860.15 | Y68: 30970.3 | Z68: 41740.24 | AA68: 3648.36 | AB68: 3635.51
A69: 1 | C69: 법인세비용 | E69: -701.76 | G69: 3501.11 | H69: 2466.36 | I69: 3451.28 | J69: -2461.66 | K69: 6957.09 | L69: 1851.41 | M69: 1126.39 | N69: 1195.67 | O69: -2587.03 | P69: 1586.44 | Q69: 1368.94 | R69: 878.89 | S69: 714.43 | T69: 1244.92 | U69: 4207.18 | V69: 1048.55 | W69: 1047.06 | X69: 1335.56 | Y69: -1480.2 | Z69: 1950.97 | AA69: 3929.29 | AB69: 3472.04
... A76: 1 | C76: 계속사업이익 | E76: 4515.59 | G76: 9898.62 | H76: 5714.52 | I76: 38132.9 | J76: -366.24 | K76: 53379.8 | L76: 8540.82 | M76: 12679.81 | N76: 14986.22 | O76: 8513.87 | P76: 44720.72 | Q76: 8302 | R76: 5237.46 | S76: 2667.82 | T76: 636.96 | U76: 16844.24 | V76: 2349.68 | W76: -3265.8 | X76: -5605.46 | Y76: -30831.96 | Z76: -37353.54 | AA76: 17151.64 | AB76: 10968.27
A77: 1 | C77: 법인세비용차감전계속사업이익 | G77: 13399.73 | H77: 8180.87 | I77: 41584.18 | L77: 10392.22 | M77: 13806.2 | N77: 16181.89 | O77: 5926.84 | P77: 46307.15 | Q77: 9670.93 | R77: 6116.35 | S77: 3382.25 | T77: 1881.88 | U77: 21051.41 | V77: 3398.23 | W77: -2218.74 | X77: -4269.9 | Y77: -32312.16 | Z77: -35402.57 | AA77: 21080.93 | AB77: 14440.3
A78: 1 | C78: 중단사업이익 | O78: 67.36 | Y78: 0
A79: 1 | C79: 영업활동으로인한현금흐름 | E79: -20624.88 | G79: -7379.67 | H79: -33035.8 | I79: 2049.71 | J79: 11497.41 | K79: -26868.35 | L79: 1383.86 | M79: 13002.49 | N79: 13278.22 | O79: 21717.6 | P79: 49382.17 | Q79: 3484.62 | R79: -15481.3 | S79: 6934.24 | T79: 18073.4 | U79: 13010.96 | V79: 9210.51 | W79: -15227.96 | X79: 30312.97 | Y79: -2420.88 | Z79: 21874.64 | AA79: -10118.94 | AB79: -17484.33
A80: 1 | C80: 감가상각비 | E80: 14495.29 | G80: 15479.15 | H80: 16425.79 | I80: 16372.54 | J80: 16722.01 | K80: 64999.49 | L80: 15424.78 | M80: 15827.99 | N80: 16210.36 | O80: 13396.35 | P80: 60859.48 | Q80: 14827.91 | R80: 15431.94 | S80: 15858.73 | T80: 15563.15 | U80: 61681.73 | V80: 16407.89 | W80: 16427.79 | X80: 16277.86 | Y80: 17010.4 | Z80: 66123.94 | AA80: 13364.28 | AB80: 15269.63
A81: 1 | C81: 무형자산상각비 | E81: 28.4 | G81: 28.27 | H81: 28.54 | I81: 28.41 | J81: 15.41 | K81: 100.63 | L81: 12.49 | M81: 12.54 | N81: 12.5 | O81: 13.02 | P81: 50.55 | Q81: 14.09 | R81: 14.81 | S81: 20.19 | T81: 20.95 | U81: 70.04 | V81: 20.95 | W81: 20.94 | X81: 20.95 | Y81: 35.11 | Z81: 97.95 | AA81: 42.29 | AB81: 43.05
A82: 1 | C82: 배당금수취(CF) | E82: 21.5 | G82: 0.18 | H82: 112.38 | I82: 129.21 | J82: 2175.58 | K82: 2417.35 | L82: 0.16 | M82: 540.3 | N82: -283.43 | O82: 53.16 | P82: 310.19 | Q82: 0.19 | R82: 846.92 | S82: -477.12 | T82: -370.01 | U82: -0.02 | V82: -397.5 | W82: 1545.81 | X82: 16.61 | Y82: 16.6 | Z82: 1181.52 | AA82: 20.51 | AB82: 1632.47
A83: 1 | C83: 이자수취(CF) | E83: -170.52 | G83: 1180.26 | H83: 591.88 | I83: 908.28 | J83: -1187.94 | K83: 1492.48 | L83: 988.63 | M83: 1167.17 | N83: 1151.29 | O83: 878 | P83: 4185.09 | Q83: 1135.39 | R83: 1110.14 | S83: 983.41 | T83: 1681.41 | U83: 4910.35 | V83: 1596.3 | W83: 889.49 | X83: 934.15 | Y83: 811.88 | Z83: 4231.82 | AA83: 1241.53 | AB83: 790.57
A84: 1 | C84: 이자지급(CF) | E84: -2706.52 | G84: -2456.93 | H84: -3125.35 | I84: -4331.48 | J84: -5331.08 | K84: -15244.84 | L84: -6294.85 | M84: -5774.76 | N84: -6636.97 | O84: -7087.19 | P84: -25793.77 | Q84: -6331.7 | R84: -5839.16 | S84: -7109.59 | T84: -7244.36 | U84: -26524.81 | V84: -5955.43 | W84: -5846.5 | X84: -5439.81 | Y84: -5679.15 | Z84: -22920.89 | AA84: -5267.61 | AB84: -5737.47
A85: 1 | C85: 법인세납부(CF) | E85: -5.08 | G85: -1774 | H85: -2083.06 | I85: -2484.41 | J85: 19.62 | K85: -6321.85 | L85: -4170.89 | M85: -5216.84 | N85: -2572.92 | O85: -2063.45 | P85: -14024.1 | Q85: 617.73 | R85: -4097.32 | S85: -2359.15 | T85: -597.52 | U85: -6436.26 | V85: -1055.65 | W85: 43.01 | X85: -1222.23 | Y85: -160.42 | Z85: -2395.29 | AA85: 213.98 | AB85: -451.13
A86: 1 | C86: 투자활동으로인한현금흐름 | E86: 4701.92 | G86: 482.05 | H86: -12669.27 | I86: -15206.98 | J86: -9643.94 | K86: -37038.14 | L86: -17981.98 | M86: 7722.79 | N86: -6577 | O86: -7936.75 | P86: -24772.94 | Q86: -11713.94 | R86: -28109.91 | S86: -5774.27 | T86: -16618.16 | U86: -62216.28 | V86: 6737.52 | W86: 836.91 | X86: -17927.76 | Y86: -3644.66 | Z86: -13997.99 | AA86: 7788.16 | AB86: -22416.2
A87: 1 | C87: 유형자산의감소 | E87: 12248.7 | G87: 8071.61 | H87: 140.98 | I87: 661.69 | J87: 545.78 | K87: 9420.06 | L87: 486.86 | M87: 2879.49 | N87: 7986.41 | O87: 4169.68 | P87: 15522.44 | Q87: 6253.88 | R87: 6080.11 | S87: 1275.13 | T87: 2709.72 | U87: 16318.84 | V87: 1780.21 | W87: 1309.44 | X87: 427.2 | Y87: 922.06 | Z87: 4438.91 | AA87: 1090.43 | AB87: 2019.29
A88: 1 | C88: 무형자산의감소 | E88: 0 | G88: 273.64 | H88: 0 | I88: 0 | J88: 0 | K88: 273.64 | L88: 0 | M88: 1004.18 | N88: 22.23 | O88: 43.1 | P88: 1069.51 | Q88: 170 | R88: 0 | S88: 0 | T88: 0 | U88: 170 | V88: 0 | Y88: 116.64
A89: 1 | C89: 유형자산의증가 | E89: 4983.76 | G89: 3149.21 | H89: 9066.98 | I89: 3844.09 | J89: 6721.06 | K89: 22781.34 | L89: 16976.63 | M89: 6908.99 | N89: 12597.33 | O89: 10726.14 | P89: 47209.09 | Q89: 21851.08 | R89: 19693.08 | S89: 3350.66 | T89: 10459.73 | U89: 55354.55 | V89: 3917.71 | W89: 2885.65 | X89: 14972.97 | Y89: 23681.47 | Z89: 45457.8 | AA89: 9083.35 | AB89: 23346.77
A90: 1 | C90: CAPEX | E90: 4983.76 | G90: 3149.21 | H90: 9066.98 | I90: 3844.09 | J90: 7102.18 | K90: 23162.46 | L90: 16979.82 | M90: 6918.5 | N90: 12694.92 | O90: 10738.45 | P90: 47331.69 | Q90: 21851.08 | R90: 20148 | S90: 3469.03 | T90: 10459.73 | U90: 55927.84 | V90: 4126.38 | W90: 2886.26 | X90: 17014.79 | Y90: 23821.31 | Z90: 47848.74 | AA90: 9086.48 | AB90: 23358.77
A91: 1 | C91: 무형자산의증가 | E91: 0 | L91: 3.19 | M91: 9.51 | N91: 97.59 | O91: 12.31 | P91: 122.6 | S91: 118.37 | T91: 0 | V91: 208.67 | W91: 0.61 | X91: 2041.82 | Y91: 139.84 | Z91: 2390.94 | AA91: 3.13 | AB91: 12
A92: 1 | C92: 재무활동으로인한현금흐름 | E92: 4381 | G92: 9352.77 | H92: 46655.07 | I92: 12779.84 | J92: -10136.73 | K92: 58650.95 | L92: 23407.2 | M92: -7900.73 | N92: -18759.99 | O92: -9383.82 | P92: -12637.34 | Q92: 13153.77 | R92: 14907.28 | S92: 12428.21 | T92: -5890.72 | U92: 34598.54 | V92: 17655.32 | W92: 9232.77 | X92: 8317.83 | Y92: -22223.67 | Z92: 12982.25 | AA92: 28131.23 | AB92: 57908.53
A93: 1 | C93: 단기차입금의증가 | E93: 124596.77 | G93: 138614.8 | H93: 227822.67 | I93: 136905.35 | J93: 140795.39 | K93: 644138.21 | L93: 170139.75 | M93: 240067.1 | N93: 167713.67 | O93: 124789.76 | P93: 702710.28 | Q93: 151771.12 | R93: 213536.21 | S93: 200639.42 | V93: 67623.7 | W93: 110643.17 | X93: 99302.93 | Y93: 109206.44 | Z93: 386776.24 | AA93: 81669.59 | AB93: 100539.7
A94: 1 | C94: 장기차입금의증가 | E94: 2999.58 | I94: 4540 | J94: 585 | L94: 4300 | M94: 4164.68 | N94: 5597.32 | O94: 2000 | P94: 16062 | Q94: 5000 | R94: 23572.71 | S94: 40000 | T94: 15239.29 | U94: 83812 | X94: 24000 | AA94: 10000 | AB94: 14885.52
A95: 1 | C95: 단기차입금의감소 | E95: 120848.17 | G95: 147210.54 | H95: 181976.92 | I95: 155953.53 | J95: 151366.37 | K95: 636507.36 | L95: 149300.18 | M95: 223279.24 | N95: 181959.62 | O95: 124399.67 | P95: 678938.71 | Q95: 136080.81 | R95: 226390.66 | S95: 216283.86 | V95: 71737.79 | W95: 105808.59 | X95: 117050.51 | Y95: 86848.09 | Z95: 381444.98 | AA95: 74095.72 | AB95: 101218.34
A96: 1 | C96: 유동성장기부채의감소 | E96: 1799.99 | G96: 1383.33 | H96: 1383.33 | I96: 1383.33 | J96: 7083.33 | K96: 11233.32 | L96: 1083.33 | M96: 23202.48 | N96: 500 | O96: 11083.33 | P96: 35869.14 | Q96: 500 | R96: 11837 | S96: 1640 | T96: 481.03 | U96: 14458.03 | V96: 1597.72 | W96: 23687.01 | X96: 31647.72
A97: 1 | C97: 리스부채의상환 | E97: 694.28 | G97: 627.93 | H97: 678.22 | I97: 655.11 | J97: 628.4 | K97: 2589.66 | L97: 649.04 | M97: 632.77 | N97: 744.84 | O97: 690.57 | P97: 2717.22 | Q97: 762.1 | R97: 764.84 | S97: 781.38 | T97: 815.3 | U97: 3123.62 | V97: 868.63 | W97: 805.65 | X97: 924.59 | Y97: 884.26 | Z97: 3483.13 | AA97: 864.97 | AB97: 638.41
A98: 1 | C98: 배당금지급 | E98: 0 | I98: 0 | J98: 0 | O98: 0 | T98: 0 | X98: 0 | Y98: 0
A99: 1 | C99: 사채의증가 | G99: 19959.78 | H99: 0 | I99: 30000 | J99: 9979.88 | K99: 59939.66 | L99: 0 | M99: 0 | N99: 0 | S99: 0 | T99: 0 | V99: 19959.78 | W99: 0 | X99: 30000 | Y99: 0 | Z99: 49959.78
A100: 1 | C100: 현금및현금성자산의증감 | I100: -377.44 | N100: -12058.78 | O100: 6240.14 | Q100: 4924.45 | R100: -28683.93 | S100: 13588.18 | T100: -4435.49 | U100: -14606.79 | V100: 33603.35 | W100: -5158.28 | X100: 20703.04 | Y100: -28289.21 | Z100: 20858.9 | AA100: 25800.45 | AB100: 18007.99
A101: 1 | C101: 장기차입금의감소 | N101: 147 | O101: 0 | Q101: 3000 | R101: 0 | S101: 0 | T101: 200 | U101: 3200 | V101: 0
A102: 1 | C102: 기말현금및현금성자산 | N102: -11967.94 | O102: 4345.55 | Q102: 107072.44 | R102: -28114.81 | S102: 12110.41 | T102: -3611.28 | U102: 87456.76 | V102: 121129.8 | W102: -6242.12 | X102: 21282.24 | Y102: -28948.6 | Z102: 107221.32 | AA102: 134973.03 | AB102: 17349.67
A103: 1 | C103: 사채의감소 | T103: 0 | V103: 20000
A104: 1 | C104: 차입금의감소 | AA104: 5738.37

Sheet BS별도
B1: (백만원) | C1: 이름: BS별도H | E1: 4Q21 | F1: 2021 | G1: 1Q22 | H1: 2Q22 | I1: 3Q22 | J1: 4Q22 | K1: 2022 | L1: 1Q23 | M1: 2Q23 | N1: 3Q23 | O1: 4Q23 | P1: 2023 | Q1: 1Q24 | R1: 2Q24 | S1: 3Q24 | T1: 4Q24 | U1: 2024 | V1: 1Q25 | W1: 2Q25 | X1: 3Q25 | Y1: 4Q25 | Z1: 2025 | AA1: 1Q26 | AB1: 2Q26 | AC1: 3Q26 | AD1: 4Q26 | AE1: 2026 | AF1: 1Q27 | AG1: 2Q27 | AH1: 3Q27 | AI1: 4Q27 | AJ1: 2027 | AK1: 1Q28 | AL1: 2Q28 | AM1: 3Q28 | AN1: 4Q28 | AO1: 2028
B2: 별도 | D2: fin json(kship_fin.py)
B3: 금강공업(별) | C3: UPDATE: 26-10-26 | E3: 1 | F3: 2 | G3: 3 | H3: 4 | I3: 5 | J3: 6 | K3: 7 | L3: 8 | M3: 9 | N3: 10 | O3: 11 | P3: 12 | Q3: 13 | R3: 14 | S3: 15 | T3: 16 | U3: 17 | V3: 18 | W3: 19 | X3: 20 | Y3: 21 | Z3: 22 | AA3: 23 | AB3: 24 | AC3: 25 | AD3: 26 | AE3: 27 | AF3: 28 | AG3: 29 | AH3: 30 | AI3: 31 | AJ3: 32 | AK3: 33 | AL3: 34 | AM3: 35 | AN3: 36 | AO3: 37
B4: Account Code | C4: AccountNAME | E4: 2021.12 | F4: 2021.12A | G4: 2022.03 | H4: 2022.06 | I4: 2022.09 | J4: 2022.12 | K4: 2022.12A | L4: 2023.03 | M4: 2023.06 | N4: 2023.09 | O4: 2023.12 | P4: 2023.12A | Q4: 2024.03 | R4: 2024.06 | S4: 2024.09 | T4: 2024.12 | U4: 2024.12A | V4: 2025.03 | W4: 2025.06 | X4: 2025.09 | Y4: 2025.12 | Z4: 2025.12A | AA4: 2026.03 | AB4: 2026.06 | AC4: 2026.09 | AD4: 2026.12 | AE4: 2026.12A | AF4: 2027.03 | AG4: 2027.06 | AH4: 2027.09 | AI4: 2027.12 | AJ4: 2027.12A | AK4: 2028.03 | AL4: 2028.06 | AM4: 2028.09 | AN4: 2028.12 | AO4: 2028.12A
A5: 1 | C5: 유동자산 | E5: 209804.88 | F5: 209804.88 | G5: 215678.53 | H5: 224761.49 | I5: 241616.91 | J5: 245761.04 | K5: 245761.04 | L5: 258121.09 | M5: 249644.28 | N5: 255305.18 | O5: 240073.91 | P5: 240073.91 | Q5: 235792.78 | R5: 234155.8 | S5: 219303.76 | T5: 212980.97 | U5: 212980.97 | V5: 227391.71 | W5: 257422.85 | X5: 242310.98 | Y5: 221265.79 | Z5: 221265.79 | AA5: 229562.6 | AB5: 229613.23
A6: 1 | C6: 현금및현금성자산 | E6: 56211.33 | F6: 56211.33 | G6: 63068.22 | H6: 62557.03 | I6: 56924.15 | J6: 55482.4 | K6: 55482.4 | L6: 64060.89 | M6: 65878.19 | N6: 67317.26 | O6: 65114.07 | P6: 65114.07 | Q6: 60951.95 | R6: 35699.06 | S6: 42500.15 | T6: 33620.07 | U6: 33620.07 | V6: 62478.35 | W6: 59097.04 | X6: 58387.56 | Y6: 40936.31 | Z6: 40936.31 | AA6: 50895.72 | AB6: 45502.92
A7: 1 | C7: 매출채권및기타채권 | E7: 71051.36 | F7: 71051.36 | G7: 79382.2 | H7: 69682.08 | I7: 84677.8 | J7: 74994.59 | K7: 74994.59 | L7: 82500.21 | M7: 84019.33 | N7: 82443.28 | O7: 73396.25 | P7: 73396.25 | Q7: 76068.99 | R7: 78023.41 | S7: 72561.45 | T7: 84044.5 | U7: 84044.5 | V7: 88622.19 | W7: 105606.95 | X7: 91253.55 | Y7: 85068.99 | Z7: 85068.99 | AA7: 95848.02 | AB7: 97010.21
A8: 1 | C8: 재고자산 | E8: 80588.22 | F8: 80588.22 | G8: 70907.32 | H8: 89762.15 | I8: 97390.51 | J8: 102324.65 | K8: 102324.65 | L8: 96626.5 | M8: 96980.85 | N8: 102160.01 | O8: 98639.76 | P8: 98639.76 | Q8: 91494.71 | R8: 92500.4 | S8: 80782.31 | T8: 72328.67 | U8: 72328.67 | V8: 74642.29 | W8: 72485.39 | X8: 71923.61 | Y8: 72945.22 | Z8: 72945.22 | AA8: 74058.06 | AB8: 79671.95
A9: 1 | C9: 기타유동자산 | E9: 1859.83 | F9: 1859.83 | G9: 2184.43 | H9: 2674.5 | I9: 2581.61 | J9: 2690.45 | K9: 2690.45 | L9: 4804.86 | M9: 2675.12 | N9: 3302.72 | O9: 2680.36 | P9: 2680.36 | Q9: 2168.45 | R9: 2845.12 | S9: 2728.3 | T9: 1780.97 | U9: 1780.97 | V9: 1479.11 | W9: 1728.94 | X9: 2668.58 | Y9: 4203.56 | Z9: 4203.56 | AA9: 8252.03 | AB9: 7239.77
A10: 1 | C10: 비유동자산 | E10: 375938.79 | F10: 375938.79 | G10: 389084.43 | H10: 391450.92 | I10: 400681.81 | J10: 405052.28 | K10: 405052.28 | L10: 415104.05 | M10: 423923.12 | N10: 425979.99 | O10: 427836.99 | P10: 427836.99 | Q10: 426795.35 | R10: 425554.37 | S10: 435035.78 | T10: 421179.7 | U10: 421179.7 | V10: 417168.43 | W10: 393786.91 | X10: 401727.3 | Y10: 403158.61 | Z10: 403158.61 | AA10: 407470.17 | AB10: 427437.85
A11: 1 | C11: 유형자산 | E11: 287539.8 | F11: 287539.8 | G11: 298478.59 | H11: 301386.04 | I11: 293651.66 | J11: 291985.25 | K11: 291985.25 | L11: 296473.66 | M11: 305655.06 | N11: 302494.24 | O11: 302714 | P11: 302714 | Q11: 301399.87 | R11: 301639.11 | S11: 274533.63 | T11: 270613.11 | U11: 270613.11 | V11: 262070.53 | W11: 257806.17 | X11: 263163.56 | Y11: 237870.35 | Z11: 237870.35 | AA11: 246856.51 | AB11: 266179.05
A12: 1 | C12: 무형자산 | E12: 6286.68 | F12: 6286.68 | G12: 6278.78 | H12: 6270.88 | I12: 6262.99 | J12: 6255.09 | K12: 6255.09 | L12: 6294.89 | M12: 5291.22 | N12: 5356.35 | O12: 5392.37 | P12: 5392.37 | Q12: 5207.31 | R12: 5259.44 | S12: 5252.74 | T12: 5238.88 | U12: 5238.88 | V12: 5225.02 | W12: 5211.16 | X12: 5176.94 | Y12: 5125.47 | Z12: 5125.47 | AA12: 5124.12 | AB12: 5109.8
A13: 1 | C13: 투자부동산 | E13: 4457.39 | F13: 4457.39 | G13: 5196.9 | H13: 5189.5 | I13: 5182.1 | J13: 5040.37 | K13: 5040.37 | L13: 8261.9 | M13: 8251.85 | N13: 8241.81 | O13: 8231.77 | P13: 8231.77 | Q13: 5005.86 | R13: 4998.96 | S13: 38883.16 | T13: 39841.93 | U13: 39841.93 | V13: 39821.77 | W13: 21995.46 | X13: 21877.13 | Y13: 22452.16 | Z13: 22452.16 | AA13: 22333.83 | AB13: 22215.49
A14: 1 | C14: 종속기업및관계기업투자 | E14: 49728.36 | F14: 49728.36 | G14: 49728.36 | H14: 49728.36 | I14: 59955.64 | J14: 64958.85 | K14: 64958.85 | L14: 64958.85 | M14: 64958.85 | N14: 79987.37 | O14: 79991.03 | P14: 79991.03 | Q14: 85694.32 | R14: 84699.47 | S14: 84699.47 | T14: 84699.47 | U14: 84699.47 | V14: 87978.14 | W14: 87978.14 | X14: 87978.14 | Y14: 97976.33 | Z14: 97976.33 | AA14: 98476.33 | AB14: 98476.33
A15: 1 | C15: 투자자산 | E15: 57841.34 | F15: 57841.34 | G15: 58566.77 | H15: 57365.29 | I15: 81950.28 | J15: 87327.19 | K15: 87327.19 | L15: 87607.65 | M15: 87747.11 | N15: 97531.61 | O15: 98980.51 | P15: 98980.51 | Q15: 104199.5 | R15: 103019.28 | S15: 103214.28 | T15: 92633.31 | U15: 92633.31 | V15: 96046.91 | W15: 96587.83 | X15: 98967.01 | Y15: 97976.33 | Z15: 97976.33 | AA15: 118213.02 | AB15: 117733.89
A16: 1 | C16: 장기금융자산 | E16: 8112.98 | F16: 8112.98 | G16: 8838.41 | H16: 7636.93 | I16: 21994.64 | J16: 22368.34 | K16: 22368.34 | L16: 22648.8 | M16: 22788.26 | N16: 17544.24 | O16: 18989.48 | P16: 18989.48 | Q16: 18505.18 | R16: 18319.81 | S16: 18514.81 | T16: 7933.84 | U16: 7933.84 | V16: 8068.77 | W16: 8609.69 | X16: 10988.87 | AA16: 19736.69 | AB16: 19257.56
A17: 1 | C17: 장기매출채권및기타채권 | E17: 18420.87 | F17: 18420.87 | J17: 12590.51 | K17: 12590.51 | N17: 11023.46 | O17: 9061.46 | P17: 9061.46 | Q17: 8896.46 | R17: 9111.46 | S17: 11571.68 | T17: 7930.14 | U17: 7930.14 | V17: 10933.92 | W17: 11160.92 | Y17: 12557.58 | Z17: 12557.58
A18: 1 | C18: 자산총계 | E18: 585743.67 | F18: 585743.67 | G18: 604762.97 | H18: 616212.41 | I18: 642298.72 | J18: 650813.32 | K18: 650813.32 | L18: 673225.14 | M18: 673567.4 | N18: 681285.17 | O18: 667910.9 | P18: 667910.9 | Q18: 662588.12 | R18: 659710.17 | S18: 654339.55 | T18: 634160.67 | U18: 634160.67 | V18: 644560.14 | W18: 651209.76 | X18: 644038.27 | Y18: 624424.39 | Z18: 624424.39 | AA18: 637032.77 | AB18: 657051.08
A19: 1 | C19: 유동부채 | E19: 251120.2 | F19: 251120.2 | G19: 250479.75 | H19: 273211.41 | I19: 256792.41 | J19: 272536.84 | K19: 272536.84 | L19: 288907.37 | M19: 280743.04 | N19: 278123.45 | O19: 270344.62 | P19: 270344.62 | Q19: 289148.2 | R19: 255963.78 | S19: 259920 | T19: 241410.79 | U19: 241410.79 | V19: 237169.31 | W19: 265352.67 | X19: 231448.49 | Y19: 225633.33 | Z19: 225633.33 | AA19: 228237.1 | AB19: 238542.16
A20: 1 | C20: 매입채무및기타채무 | E20: 45755.8 | F20: 45755.8 | G20: 46994.27 | H20: 43989.62 | I20: 42192.48 | J20: 48879.89 | K20: 48879.89 | L20: 48014.59 | M20: 51967.66 | N20: 43883.99 | O20: 49255.25 | P20: 49255.25 | Q20: 43473.81 | R20: 37727.75 | S20: 34473.1 | T20: 36936.36 | U20: 36936.36 | V20: 40598.54 | W20: 38631.93 | X20: 36595.06 | Y20: 35328.19 | Z20: 35328.19 | AA20: 40135.9 | AB20: 39054.88
A21: 1 | C21: 단기차입금 | E21: 186541.72 | F21: 186541.72 | G21: 183406.9 | H21: 209688.93 | I21: 195582.02 | J21: 201942.54 | K21: 201942.54 | L21: 219652.69 | M21: 202627.24 | N21: 201585.73 | O21: 197800.36 | P21: 197800.36 | Q21: 224297.37 | R21: 196802.4 | S21: 210373.39 | T21: 193318.2 | U21: 193318.2 | V21: 183555.52 | W21: 201257.65 | X21: 164524.23 | Y21: 166598.57 | Z21: 166598.57 | AA21: 166093.77 | AB21: 178567.68
A22: 1 | C22: 단기금융부채(face) | E22: 186541.72 | F22: 186541.72 | G22: 183406.9 | H22: 209688.93 | I22: 195582.02 | J22: 201942.54 | K22: 201942.54 | L22: 219652.69 | M22: 202627.24 | N22: 201585.73 | O22: 197800.36 | P22: 197800.36 | Q22: 224297.37 | R22: 196802.4 | S22: 210373.39 | T22: 193318.2 | U22: 193318.2 | V22: 183555.52 | W22: 201257.65 | X22: 164524.23 | Y22: 166598.57 | Z22: 166598.57 | AA22: 166093.77 | AB22: 178567.68
A23: 1 | C23: 기타유동부채 | E23: 14228.54 | F23: 14228.54 | G23: 13490.4 | H23: 13096.15 | I23: 11333.51 | J23: 12340.31 | K23: 12340.31 | L23: 14492.16 | M23: 21400.4 | N23: 26297.08 | O23: 19350.99 | P23: 19350.99 | Q23: 17136.23 | R23: 19508.88 | S23: 14056.02 | T23: 10250.68 | U23: 10250.68 | V23: 12080.39 | W23: 24246.83 | X23: 29308.22 | Y23: 22908.39 | Z23: 22908.39 | AA23: 21120.19 | AB23: 19826.69
A24: 1 | C24: 당기법인세부채(미지급법인세) | E24: 3605.79 | F24: 3605.79 | G24: 5456.55 | H24: 5295.69 | I24: 6509.69 | J24: 8317.87 | K24: 8317.87 | L24: 5565.28 | M24: 3630.1 | N24: 5240.05 | O24: 2866.99 | P24: 2866.99 | Q24: 3029.23 | R24: 775.16 | T24: 0 | U24: 0 | Y24: 0 | Z24: 0
A25: 1 | C25: 유동리스부채 | E25: 988.35 | F25: 988.35 | G25: 1131.63 | H25: 1141.03 | I25: 1174.71 | J25: 1056.23 | K25: 1056.23 | L25: 1182.66 | M25: 1117.63 | N25: 1116.6 | O25: 1071.03 | P25: 1071.03 | Q25: 1211.56 | R25: 1149.59 | S25: 1017.49 | T25: 905.54 | U25: 905.54 | V25: 934.85 | W25: 1216.26 | X25: 1020.99 | Y25: 798.17 | Z25: 798.17 | AA25: 887.24 | AB25: 1092.91
A26: 1 | C26: 리스부채 | E26: 6639.93 | F26: 6639.93 | G26: 7421.46 | H26: 8726.64 | I26: 8835.65 | J26: 8560.65 | K26: 8560.65 | L26: 8548.42 | M26: 8241.09 | N26: 8252.53 | O26: 7959 | P26: 7959 | Q26: 7810.63 | R26: 6762.82 | S26: 6483.86 | T26: 6244.93 | U26: 6244.93 | V26: 6098.61 | W26: 6077.98 | X26: 5739.46 | Y26: 5389.7 | Z26: 5389.7 | AA26: 5353.17 | AB26: 5441.83
A27: 1 | C27: 단기금융부채 | E27: 988.35 | F27: 988.35 | G27: 1131.63 | H27: 1141.03 | I27: 1174.71 | J27: 1056.23 | K27: 1056.23 | L27: 1182.66 | M27: 1117.63 | N27: 1116.6 | O27: 1071.03 | P27: 1071.03 | Q27: 1211.56 | R27: 1149.59 | S27: 1017.49 | T27: 905.54 | U27: 905.54 | V27: 934.85 | W27: 1216.26 | X27: 1020.99 | Y27: 798.17 | Z27: 798.17 | AA27: 887.24 | AB27: 1092.91
A28: 1 | C28: 비유동부채 | E28: 52668.28 | F28: 52668.28 | G28: 63079.03 | H28: 44536.3 | I28: 75143.5 | J28: 71627.11 | K28: 71627.11 | L28: 75112.85 | M28: 74744.61 | N28: 74470.47 | O28: 73357.35 | P28: 73357.35 | Q28: 50693.98 | R28: 79440.13 | S28: 78921.66 | T28: 80086.42 | U28: 80086.42 | V28: 99313.64 | W28: 88416.49 | X28: 122692.89 | Y28: 120262.57 | Z28: 120262.57 | AA28: 122082.92 | AB28: 131905.04
A29: 1 | C29: 장기차입금 | E29: 42842.13 | F29: 42842.13 | G29: 52879.93 | H29: 32854.42 | I29: 62827.74 | J29: 59952.73 | K29: 59952.73 | L29: 63902.86 | M29: 62960.6 | N29: 63915.87 | O29: 62970.37 | P29: 62970.37 | Q29: 39988.45 | R29: 69951.06 | S29: 69964.09 | T29: 69967.26 | U29: 69967.26 | V29: 89930.32 | W29: 79936.69 | X29: 113943.2 | Y29: 113949.77 | Z29: 113949.77 | AA29: 113956.26 | AB29: 122975.88
A30: 1 | C30: 장기금융부채(face) | E30: 877.63 | F30: 877.63 | G30: 953.64 | H30: 901.43 | I30: 868.26 | L30: 948.26 | N30: 949.26
A31: 1 | C31: 이연법인세부채 | E31: 3037.01 | F31: 3037.01 | G31: 2828.8 | H31: 3065.13 | I31: 3654.28 | J31: 2126.99 | K31: 2126.99 | L31: 2595.5 | M31: 2340.99 | N31: 2110.44 | O31: 1046.56 | P31: 1046.56 | Q31: 1544.24 | R31: 1278.97 | S31: 1352.07 | T31: 2692.49 | U31: 2692.49 | V31: 2100.8 | W31: 1520.69 | X31: 1996.33 | AA31: 1995.07 | AB31: 2976.09
A32: 1 | C32: 장기충당부채 | E32: 1137.56 | F32: 1137.56 | G32: 1080.48 | H32: 1031.15 | I32: 1000.55 | J32: 1174.71 | K32: 1174.71 | L32: 1248.72 | M32: 1330.03 | N32: 1308.23 | O32: 1494.19 | P32: 1494.19 | Q32: 1578.3 | R32: 1635.6 | S32: 1655.25 | T32: 1562.97 | U32: 1562.97 | V32: 1570.39 | W32: 1585.33 | X32: 1547.83 | Y32: 1278.33 | Z32: 1278.33 | AA32: 1222.71 | AB32: 1203.41
A33: 1 | C33: 비유동리스부채 | E33: 5651.58 | F33: 5651.58 | G33: 6289.83 | H33: 7585.61 | I33: 7660.94 | J33: 7504.42 | K33: 7504.42 | L33: 7365.76 | M33: 7123.46 | N33: 7135.93 | O33: 6887.97 | P33: 6887.97 | Q33: 6599.07 | R33: 5613.23 | S33: 5466.37 | T33: 5339.39 | U33: 5339.39 | V33: 5163.76 | W33: 4861.72 | X33: 4718.47 | Y33: 4591.53 | Z33: 4591.53 | AA33: 4465.93 | AB33: 4348.92
A34: 1 | C34: 장기금융부채 | E34: 5651.58 | F34: 5651.58 | G34: 6289.83 | H34: 7585.61 | I34: 7660.94 | J34: 7504.42 | K34: 7504.42 | L34: 7365.76 | M34: 7123.46 | N34: 7135.93 | O34: 6887.97 | P34: 6887.97 | Q34: 6599.07 | R34: 5613.23 | S34: 5466.37 | T34: 5339.39 | U34: 5339.39 | V34: 5163.76 | W34: 4861.72 | X34: 4718.47 | Y34: 4591.53 | Z34: 4591.53 | AA34: 4465.93 | AB34: 4348.92
A35: 1 | C35: 부채총계 | E35: 303788.48 | F35: 303788.48 | G35: 313558.78 | H35: 317747.71 | I35: 331935.91 | J35: 344163.96 | K35: 344163.96 | L35: 364020.22 | M35: 355487.65 | N35: 352593.92 | O35: 343701.96 | P35: 343701.96 | Q35: 339842.18 | R35: 335403.91 | S35: 338841.66 | T35: 321497.21 | U35: 321497.21 | V35: 336482.95 | W35: 353769.17 | X35: 354141.37 | Y35: 345895.89 | Z35: 345895.89 | AA35: 350320.01 | AB35: 370447.2
A36: 1 | C36: 자본금 | E36: 93020.37 | F36: 93020.37 | G36: 93020.37 | H36: 93020.37 | I36: 93020.37 | J36: 93020.37 | K36: 93020.37 | L36: 93020.37 | M36: 93020.37 | N36: 93020.37 | O36: 93020.37 | P36: 93020.37 | Q36: 93020.37 | R36: 93020.37 | S36: 93020.37 | T36: 93020.37 | U36: 93020.37 | V36: 93020.37 | W36: 93020.37 | X36: 93020.37 | Y36: 93020.37 | Z36: 93020.37 | AA36: 93020.37 | AB36: 93020.37
A37: 1 | C37: 자본잉여금 | E37: 49143.43 | F37: 49143.43 | G37: 49143.43 | H37: 49143.43 | I37: 49143.43 | J37: 49143.43 | K37: 49143.43 | L37: 49143.43 | M37: 49143.43 | N37: 49143.43 | O37: 49143.43 | P37: 49143.43 | Q37: 49143.43 | R37: 49143.43 | S37: 49143.43 | T37: 49143.43 | U37: 49143.43 | V37: 49143.43 | W37: 49143.43 | X37: 49143.43 | Y37: 59499.36 | Z37: 59499.36 | AA37: 59499.36 | AB37: 59499.36
A38: 1 | C38: 기타자본 | E38: 246.37 | F38: 246.37 | G38: 795.37 | H38: 57.9 | I38: -94.38 | J38: 163.38 | K38: 163.38 | L38: 332.33 | M38: 390.46 | N38: 767.29 | O38: 846.62 | P38: 846.62 | Q38: 344.84 | R38: 132.31 | S38: -31.92 | T38: -526.34 | U38: -526.34 | V38: -471.5 | W38: -164.58 | X38: -180.87 | Y38: 243.01 | Z38: 243.01 | AA38: -1050.22 | AB38: -3166.14
A39: 1 | C39: 이익잉여금 | E39: 202646.16 | F39: 202646.16 | G39: 211346.15 | H39: 219344.14 | I39: 231394.54 | J39: 227423.32 | K39: 227423.32 | L39: 229809.92 | M39: 238626.62 | N39: 248861.3 | O39: 244299.66 | P39: 244299.66 | Q39: 243338.44 | R39: 245111.29 | S39: 236467.14 | T39: 234127.14 | U39: 234127.14 | V39: 229486.02 | W39: 218542.51 | X39: 211015.11 | Y39: 188866.9 | Z39: 188866.9 | AA39: 198344.38 | AB39: 200351.43
A40: 1 | C40: 자본총계 | E40: 281955.19 | F40: 281955.19 | G40: 291204.18 | H40: 298464.7 | I40: 310362.82 | J40: 306649.36 | K40: 306649.36 | L40: 309204.92 | M40: 318079.75 | N40: 328691.25 | O40: 324208.94 | P40: 324208.94 | Q40: 322745.94 | R40: 324306.26 | S40: 315497.89 | T40: 312663.46 | U40: 312663.46 | V40: 308077.19 | W40: 297440.59 | X40: 289896.9 | Y40: 278528.5 | Z40: 278528.5 | AA40: 286712.75 | AB40: 286603.88
A41: 1 | C41: 부채와자본총계 | E41: 585743.67 | F41: 585743.67 | G41: 604762.97 | H41: 616212.41 | I41: 642298.72 | J41: 650813.32 | K41: 650813.32 | L41: 673225.14 | M41: 673567.4 | N41: 681285.17 | O41: 667910.9 | P41: 667910.9 | Q41: 662588.12 | R41: 659710.17 | S41: 654339.55 | T41: 634160.67 | U41: 634160.67 | V41: 644560.14 | W41: 651209.76 | X41: 644038.27 | Y41: 624424.39 | Z41: 624424.39 | AA41: 637032.77 | AB41: 657051.08
A42: 1 | C42: 지배주주지분 | E42: 281955.19 | F42: 281955.19 | G42: 291204.18 | H42: 298464.7 | I42: 310362.82 | J42: 306649.36 | K42: 306649.36 | L42: 309204.92 | M42: 318079.75 | N42: 328691.25 | O42: 324208.94 | P42: 324208.94 | Q42: 322745.94 | R42: 324306.26 | S42: 315497.89 | T42: 312663.46 | U42: 312663.46 | V42: 308077.19 | W42: 297440.59 | X42: 289896.9 | Y42: 278528.5 | Z42: 278528.5 | AA42: 286712.75 | AB42: 286603.88
A43: 1 | C43: 총차입금 | E43: 229383.85 | F43: 229383.85 | G43: 236286.83 | H43: 242543.35 | I43: 258409.76 | J43: 261895.27 | K43: 261895.27 | L43: 283555.55 | M43: 265587.84 | N43: 265501.6 | O43: 260770.73 | P43: 260770.73 | Q43: 264285.82 | R43: 266753.46 | S43: 280337.48 | T43: 263285.46 | U43: 263285.46 | V43: 273485.84 | W43: 281194.34 | X43: 278467.43 | Y43: 280548.34 | Z43: 280548.34 | AA43: 280050.03 | AB43: 301543.56
... A45: 1 | C45: 이자발생자산 | E45: 64324.31 | F45: 64324.31 | G45: 71906.63 | H45: 70193.96 | I45: 78918.79 | J45: 77850.74 | K45: 77850.74 | L45: 86709.69 | M45: 88666.45 | N45: 84861.5 | O45: 84103.55 | P45: 84103.55 | Q45: 79457.13 | R45: 54018.87 | S45: 61014.96 | T45: 41553.91 | U45: 41553.91 | V45: 70547.12 | W45: 67706.73 | X45: 69376.43 | Y45: 40936.31 | Z45: 40936.31 | AA45: 70632.41 | AB45: 64760.48
A46: 1 | C46: 기타비유동부채 | J46: 868.26 | K46: 868.26 | O46: 958.26 | P46: 958.26 | Q46: 983.92 | R46: 961.28 | S46: 483.89 | T46: 524.31 | U46: 524.31 | V46: 548.37 | W46: 512.07 | X46: 487.07 | Y46: 442.95 | Z46: 442.95 | AA46: 442.95 | AB46: 400.73
A47: 1 | C47: 기타비유동자산 | M47: 736.61 | N47: 1332.53 | O47: 3456.88 | P47: 3456.88 | Q47: 2086.35 | R47: 1526.11 | S47: 1580.29 | T47: 4922.33 | U47: 4922.33 | V47: 3070.29 | W47: 1025.38 | X47: 1386.52 | Y47: 4569.26 | Z47: 4569.26 | AA47: 2872.35 | AB47: 4179.54
A48: 1 | C48: 장기매입채무및기타채무 | M48: 989.54
A49: 1 | C49: 매각예정비유동자산및처분자산 | O49: 184.52 | P49: 184.52 | T49: 0 | U49: 0 | W49: 17729.08 | X49: 17729.08 | Y49: 17729.08 | Z49: 17729.08
A50: 1 | C50: 당기법인세자산(선급법인세) | S50: 593.73 | T50: 1124.42 | U50: 1124.42 | V50: 147.58 | W50: 222.46 | X50: 299.35 | Y50: 355.57 | Z50: 355.57 | AA50: 481.7 | AB50: 188.39
A51: 1 | C51: 매출액(수익) | E51: 71375.54 | G51: 94478.51 | H51: 85677.78 | I51: 87208.91 | J51: 89482.4 | K51: 356847.6 | L51: 93272.54 | M51: 90851.52 | N51: 85283.41 | O51: 91926.01 | P51: 361333.48 | Q51: 84154.61 | R51: 69208.47 | S51: 68390.24 | T51: 72177.94 | U51: 293931.26 | V51: 76105.43 | W51: 78756.57 | X51: 72964.88 | Y51: 62285.75 | Z51: 290112.63 | AA51: 74561.94 | AB51: 80495.62
A52: 1 | C52: 매출원가 | E52: 58589.02 | G52: 76061.05 | H52: 68602.09 | I52: 70090.73 | J52: 74524.65 | K52: 289278.52 | L52: 74003.7 | M52: 67185.45 | N52: 63791.71 | O52: 74739.73 | P52: 279720.59 | Q52: 71051.96 | R52: 62004.67 | S52: 61176.67 | T52: 67216.7 | U52: 261450 | V52: 66025.74 | W52: 69334.57 | X52: 65593.1 | Y52: 60649.1 | Z52: 261602.51 | AA52: 59425.33 | AB52: 63454.21
A53: 1 | C53: 매출총이익 | E53: 12786.52 | G53: 18417.46 | H53: 17075.69 | I53: 17118.18 | J53: 14957.76 | K53: 67569.09 | L53: 19268.84 | M53: 23666.08 | N53: 21491.7 | O53: 17186.27 | P53: 81612.89 | Q53: 13102.65 | R53: 7203.8 | S53: 7213.56 | T53: 4961.25 | U53: 32481.26 | V53: 10079.69 | W53: 9422.01 | X53: 7371.78 | Y53: 1636.65 | Z53: 28510.13 | AA53: 15136.61 | AB53: 17041.41
A54: 1 | C54: 판관비 | E54: 6491.68 | G54: 5787.62 | H54: 8110.38 | I54: 11231.68 | J54: 12671.39 | K54: 37801.07 | L54: 10065.13 | M54: 9619.88 | N54: 10541.62 | O54: 16534.21 | P54: 46760.84 | Q54: 9374.12 | R54: 8958.78 | S54: 11277.81 | T54: 7225.27 | U54: 36835.98 | V54: 11879.22 | W54: 13906.23 | X54: 15164.35 | Y54: 10465.79 | Z54: 51415.59 | AA54: 10363.15 | AB54: 12106
A55: 1 | C55: 영업이익 | E55: 6294.84 | G55: 12629.84 | H55: 8965.31 | I55: 5886.5 | J55: 2286.37 | K55: 29768.02 | L55: 9203.71 | M55: 14046.2 | N55: 10950.08 | O55: 652.06 | P55: 34852.05 | Q55: 3728.53 | R55: -1754.98 | S55: -4064.25 | T55: -2264.02 | U55: -4354.72 | V55: -1799.53 | W55: -4484.22 | X55: -7792.57 | Y55: -8829.14 | Z55: -22905.46 | AA55: 4773.46 | AB55: 4935.41
A56: 1 | C56: 금융수익 | E56: 1157.06 | G56: 498.87 | H56: 534.35 | I56: 661.91 | J56: 895.99 | K56: 2591.12 | L56: 900.23 | M56: 828.49 | N56: 832.86 | O56: 694.73 | P56: 3256.31 | Q56: 743.57 | R56: 570.75 | S56: 656.99 | T56: 801.2 | U56: 2772.51 | V56: 448.97 | W56: 383.11 | X56: 417.54 | Y56: 757.6 | Z56: 2007.22 | AA56: 371.71 | AB56: 270.81
A57: 1 | C57: 금융비용 | E57: 1361.76 | G57: 1724.38 | H57: 2064.26 | I57: 2401.51 | J57: 2887.92 | K57: 9078.07 | L57: 3212.4 | M57: 3380.75 | N57: 3083.4 | O57: 3435.41 | P57: 13111.96 | Q57: 3471.44 | R57: 3107.62 | S57: 3324.38 | T57: 3365.41 | U57: 13268.85 | V57: 3004.64 | W57: 2933.74 | X57: 2888.14 | Y57: 2776.69 | Z57: 11603.21 | AA57: 2873.49 | AB57: 2981.97
A58: 1 | C58: 기타영업외수익 | E58: 1537.35 | G58: 3322.99 | H58: 3067.6 | I58: 13133.17 | J58: -4222.13 | K58: 15301.63 | L58: 2362.4 | M58: 943.66 | N58: 3896.88 | O58: -667.89 | P58: 6535.05 | Q58: 2691.5 | R58: 7821.93 | S58: 750.96 | T58: 3731.44 | U58: 14995.83 | V58: 2307.4 | W58: 1494.99 | X58: 3449.28 | Y58: 10003.85 | Z58: 17255.52 | AA58: 13607.05 | AB58: 1783.42
A59: 1 | C59: 기타영업외비용 | E59: 5684.96 | G59: 574.21 | H59: 954.92 | I59: 1544.94 | J59: 6.11 | K59: 3080.18 | L59: 923.29 | M59: 1171.61 | N59: 624.84 | O59: 1559.06 | P59: 4278.8 | Q59: 340.31 | R59: 843.52 | S59: 1905.79 | T59: 159.85 | U59: 3249.47 | V59: 624.86 | W59: 4806.26 | X59: 1338.52 | Y59: 24396.95 | Z59: 31166.59 | AA59: 582.13 | AB59: 849.98
A60: 1 | C60: 법인세비용 | E60: 1301.64 | G60: 2893.43 | H60: 2333.45 | I60: 3714.67 | J60: 19.05 | K60: 8960.6 | L60: 1588.48 | M60: 2673.26 | N60: 2739.6 | O60: -1421.33 | P60: 5580.01 | Q60: 846.89 | R60: 596.63 | S60: 527.1 | T60: 1313.14 | U60: 3283.76 | V60: -756.66 | W60: -399.54 | X60: 249.01 | Y60: -2401.86 | Z60: -3309.05 | AA60: 2415.73 | AB60: 1332.75
A61: 1 | C61: 당기순이익 | E61: 640.9 | G61: 11259.68 | H61: 7214.62 | I61: 12020.45 | J61: -3952.85 | K61: 26541.9 | L61: 6742.18 | M61: 8592.75 | N61: 9231.99 | O61: -2894.22 | P61: 21672.7 | Q61: 2504.96 | R61: 2089.93 | S61: -8413.56 | T61: -2569.8 | U61: -6388.47 | V61: -1916 | W61: -9946.58 | X61: -8401.41 | Y61: -22839.46 | Z61: -43103.45 | AA61: 12880.87 | AB61: 1824.95
A62: 1 | C62: 총포괄손익 | E62: 143.39 | G62: 12001.01 | H62: 7260.52 | I62: 11898.12 | J62: -3713.45 | K62: 27446.2 | L62: 5856.8 | M62: 8874.83 | N62: 10611.49 | O62: -4482.31 | P62: 20860.81 | Q62: 1838.25 | R62: 1560.32 | S62: -8808.37 | T62: -2834.43 | U62: -8244.23 | V62: -1285.03 | W62: -10636.6 | X62: -7543.7 | Y62: -21724.32 | Z62: -41189.65 | AA62: 11660.37 | AB62: -108.87
... A66: 1 | C66: 계속사업이익 | E66: 640.9 | G66: 11259.68 | H66: 7214.62 | I66: 12020.45 | J66: -3952.85 | K66: 26541.9 | L66: 6742.18 | M66: 8592.75 | N66: 9231.99 | O66: -2894.22 | P66: 21672.7 | Q66: 2504.96 | R66: 2089.93 | S66: -8413.56 | T66: -2569.8 | U66: -6388.47 | V66: -1916 | W66: -9946.58 | X66: -8401.41 | Y66: -22839.46 | Z66: -43103.45 | AA66: 12880.87 | AB66: 1824.95
A67: 1 | C67: 법인세비용차감전계속사업이익 | G67: 14153.11 | H67: 9548.07 | I67: 15735.13 | L67: 8330.66 | M67: 11266 | N67: 11971.59 | O67: -4315.55 | P67: 27252.7 | Q67: 3351.85 | R67: 2686.56 | S67: -7886.46 | T67: -1256.65 | U67: -3104.7 | V67: -2672.66 | W67: -10346.11 | X67: -8152.4 | Y67: -25241.34 | Z67: -46412.51 | AA67: 15296.6 | AB67: 3157.69
A68: 1 | C68: 영업활동으로인한현금흐름 | E68: -19143 | G68: -4795.2 | H68: -970.17 | I68: -6465.36 | J68: 17418.98 | K68: 5188.25 | L68: 2459.28 | M68: 15224.35 | N68: 14668.16 | O68: 9076.19 | P68: 41427.98 | Q68: 4510.45 | R68: -342.06 | S68: -1319.76 | T68: 3718.33 | U68: 6566.96 | V68: 1371.72 | W68: -4916.63 | X68: 11777.95 | Y68: -16165.59 | Z68: -7932.55 | AA68: -8481.17 | AB68: -5345.57
A69: 1 | C69: 감가상각비 | E69: 10375.87 | G69: 11828.28 | H69: 12741.97 | I69: 12590.42 | J69: 12106.39 | K69: 49267.06 | L69: 11576.32 | M69: 12147.78 | N69: 12252.53 | O69: 11796.06 | P69: 47772.69 | Q69: 11084.59 | R69: 10748.19 | S69: 10889.33 | T69: 10293.71 | U69: 43015.82 | V69: 10238.88 | W69: 9769.64 | X69: 9425.95 | Y69: 9132.2 | Z69: 38566.67 | AA69: 4938.64 | AB69: 5770.15
A70: 1 | C70: 배당금수취(CF) | E70: 21.5 | I70: 17.2 | J70: 8.6 | N70: 12.03 | O70: 10.75 | S70: 16.91 | T70: -713.23 | V70: -768.26 | W70: 1629.17 | X70: 16.6 | Y70: 16.61 | Z70: 894.12
A71: 1 | C71: 이자수취(CF) | E71: 195.94 | G71: 574.72 | H71: 82.01 | I71: 288.42 | J71: 354.95 | K71: 1300.1 | L71: 456.52 | M71: 564.08 | N71: 584.08 | O71: 382.89 | P71: 1987.57 | Q71: 732.39 | R71: 419.86 | S71: 454.17 | T71: 1108.44 | U71: 2714.86 | V71: 1111.06 | W71: 385.57 | X71: 412.04 | Y71: 293.07 | Z71: 2201.74 | AA71: 856.43 | AB71: 278.28
A72: 1 | C72: 이자지급(CF) | E72: -1245.31 | G72: -1607.17 | H72: -2071.37 | I72: -2703.54 | J72: -2775.93 | K72: -9158.01 | L72: -3328.18 | M72: -2940.29 | N72: -3478.54 | O72: -3889.34 | P72: -13636.35 | Q72: -3275.92 | R72: -2721.18 | S72: -3827.31 | T72: -3180.58 | U72: -13004.99 | V72: -3025.46 | W72: -3052.16 | X72: -2752.48 | Y72: -2807.88 | Z72: -11637.98 | AA72: -2804.18 | AB72: -2961.27
A73: 1 | C73: 법인세납부(CF) | E73: -13.73 | G73: -1459.96 | H73: -2115.58 | I73: -1877.02 | J73: 194.33 | K73: -5258.23 | L73: -3724.71 | M73: -4741.04 | N73: -1774.59 | O73: -1742.54 | P73: -11982.88 | Q73: -10.81 | R73: -2976.05 | S73: -1718.55 | T73: -433.5 | U73: -5138.91 | V73: -149.32 | W73: 1051.28 | X73: -76.89 | Y73: 154.2 | Z73: 979.27 | AA73: -139.02 | AB73: 487.03
A74: 1 | C74: 투자활동으로인한현금흐름 | E74: -3115.89 | G74: 5032.14 | H74: -2830.97 | I74: -15301.12 | J74: -21806.02 | K74: -34905.97 | L74: -14445.88 | M74: 7527.66 | N74: -11907 | O74: -7049.81 | P74: -25875.03 | Q74: -11848.24 | R74: -23664.19 | S74: -5048.3 | T74: 4798.47 | U74: -35762.26 | V74: 17688.44 | W74: -2283.61 | X74: -9546.92 | Y74: -2939.49 | Z74: 2918.42 | AA74: 19402.28 | AB74: -17496.38
A75: 1 | C75: 유형자산의감소 | E75: 7.53 | G75: 6199.04 | H75: 7.45 | I75: 253.14 | J75: 73.76 | K75: 6533.39 | L75: 66.3 | M75: 58.49 | N75: 4283.59 | O75: 151.91 | P75: 4560.29 | Q75: 5487.71 | R75: 2478.16 | S75: 443.49 | T75: 314.8 | U75: 8724.16 | V75: 163.35 | W75: 29.64 | X75: 3.5 | Y75: 86.19 | Z75: 282.68 | AA75: 32.89 | AB75: 0
A76: 1 | C76: 무형자산의감소 | E76: 0 | G76: 30 | H76: 0 | I76: 0 | J76: 0 | K76: 30 | L76: 0 | M76: 1004.18 | N76: 25.74 | Q76: 170 | R76: 0 | S76: 0 | T76: 0 | U76: 170 | V76: 0 | Y76: 26.73
A77: 1 | C77: 유형자산의증가 | E77: 3394.5 | G77: 712.46 | H77: 3653.07 | I77: 1238.27 | J77: 4047.16 | K77: 9650.96 | L77: 11567.3 | M77: 3427.69 | N77: 3904.04 | O77: 7914.21 | P77: 26813.24 | Q77: 10391.44 | R77: 13214.34 | T77: 3960.55 | V77: 1587.7 | W77: 859.44 | X77: 9526.14 | Y77: 873.98 | Z77: 12847.26 | AA77: 3228.9 | AB77: 15086.39
A78: 1 | C78: CAPEX | E78: 3394.5 | G78: 712.46 | H78: 3653.07 | I78: 1238.27 | J78: 4047.16 | K78: 9650.96 | L78: 11567.3 | M78: 3437.2 | N78: 4005.14 | O78: 7910.7 | P78: 26920.34 | Q78: 10391.44 | R78: 13225.26 | S78: 6.99 | T78: 3960.55 | U78: 27584.24 | V78: 1587.7 | W78: 859.44 | X78: 9526.53 | Y78: 873.98 | Z78: 12847.65 | AA78: 3228.9 | AB78: 15086.39
A79: 1 | C79: 재무활동으로인한현금흐름 | E79: 9730.26 | G79: 6545.75 | H79: 3246.74 | I79: 15580.6 | J79: 4022.59 | K79: 29395.68 | L79: 20391.76 | M79: -20761.37 | N79: -1354.17 | O79: -4092.27 | P79: -5816.05 | Q79: 3144.55 | R79: -1216.16 | S79: 13188.97 | T79: -17450.68 | U79: -2333.32 | V79: 9802.15 | W79: 3986.99 | X79: -3133.96 | Y79: 1675.47 | Z79: 12330.65 | AA79: -962.32 | AB79: 17441.31
A80: 1 | C80: 단기차입금의증가 | E80: 75303.9 | G80: 93687.55 | H80: 122384.16 | I80: 68547.65 | J80: 75004.81 | K80: 359624.17 | L80: 97443.4 | M80: 173329.26 | N80: 99594.14 | O80: 71492.09 | P80: 441858.89 | Q80: 88995.01 | R80: 126323.93 | S80: 136395.91 | T80: 83564.08 | U80: 435278.93 | V80: 67623.7 | W80: 97476.34 | X80: 91479.69 | Y80: 106812 | Z80: 363391.73 | AA80: 73099.75 | AB80: 93441.24
A81: 1 | C81: 단기차입금의감소 | E81: 68243.71 | G81: 106822.37 | H81: 116088.48 | I81: 82657.63 | J81: 74639.65 | K81: 380208.13 | L81: 79735.26 | M81: 168362.93 | N81: 100637.28 | O81: 65280.82 | P81: 414016.29 | Q81: 82483.78 | R81: 153824.06 | S81: 152830.1 | T81: 86542.63 | U81: 475680.57 | V81: 65499.41 | W81: 95166.97 | X81: 98430.51 | Y81: 95609.41 | Z81: 354706.3 | AA81: 73745.72 | AB81: 97523.22
A82: 1 | C82: 유동성장기부채의감소 | E82: 0 | N82: 0 | O82: 10000 | S82: 0 | T82: 0 | X82: 31000 | Y82: 10000
A83: 1 | C83: 배당금지급 | E83: 0 | I83: 0 | J83: 0 | N83: 0 | O83: 0 | S83: 0 | T83: 0 | X83: 0 | Y83: 0
A84: 1 | C84: 리스부채의상환 | E84: 329.94 | G84: 279.21 | H84: 296.94 | I84: 309.42 | J84: 322.45 | K84: 1208.02 | L84: 316.37 | M84: 307.34 | N84: 311.02 | O84: 303.54 | P84: 1238.27 | Q84: 366.68 | R84: 374.67 | S84: 376.84 | T84: 392.65 | U84: 1510.84 | V84: 393.91 | W84: 413.91 | X84: 400.54 | Y84: 398.89 | Z84: 1607.25 | AA84: 397.65 | AB84: 397.65
A85: 1 | C85: 무형자산상각비 | G85: 7.9 | H85: 7.9 | I85: 7.9 | J85: 7.9 | K85: 31.6 | L85: 9.67 | M85: 9.66 | N85: 9.67 | O85: 10.21 | P85: 39.21 | Q85: 11.32 | R85: 12.08 | S85: 13.69 | T85: 13.86 | U85: 50.95 | V85: 13.86 | W85: 13.86 | X85: 13.86 | Y85: 13.88 | Z85: 55.46 | AA85: 14.02 | AB85: 14.33
A86: 1 | C86: 사채의증가 | G86: 19959.78 | H86: 0 | I86: 30000 | J86: 9979.88 | K86: 59939.66 | L86: 0 | M86: 0 | N86: 0 | S86: 0 | T86: 0 | V86: 19959.78 | W86: 0 | X86: 30000 | Y86: 0 | Z86: 49959.78
A87: 1 | C87: 현금및현금성자산의증감 | I87: -6185.89 | N87: 1407 | O87: -2065.88 | Q87: -4193.23 | R87: -25222.42 | S87: 6820.92 | T87: -8933.9 | U87: -31528.63 | V87: 28862.32 | W87: -3213.26 | X87: -902.93 | Y87: -17429.61 | Z87: 7316.52 | AA87: 9958.79 | AB87: -5400.64
A88: 1 | C88: 장기차입금의증가 | L88: 3000 | M88: 0 | N88: 0 | O88: 0 | P88: 3000 | S88: 40000 | T88: 0 | Y88: 0
A89: 1 | C89: 무형자산의증가 | N89: 101.1 | S89: 6.99 | T89: 0 | Y89: 0
A90: 1 | C90: 기말현금및현금성자산 | N90: 1439.07 | O90: -2203.19 | Q90: 60951.95 | R90: -25252.89 | S90: 6801.09 | T90: -8880.08 | U90: 33620.07 | V90: 62478.35 | W90: -3381.31 | X90: -709.48 | Y90: -17451.25 | Z90: 40936.31 | AA90: 50895.72 | AB90: -5392.8
A91: 1 | C91: 장기차입금의감소 | Q91: 3000 | R91: 0 | S91: 0 | T91: 0 | U91: 3000 | V91: 0
A92: 1 | C92: 사채의감소 | T92: 0 | V92: 20000

Sheet subQ
A1: YQ | C1: subQ 분기 서브모델(억원, U=100) | E1: 4Q21 | F1: 2021 | G1: 1Q22 | H1: 2Q22 | I1: 3Q22 | J1: 4Q22 | K1: 2022 | L1: 1Q23 | M1: 2Q23 | N1: 3Q23 | O1: 4Q23 | P1: 2023 | Q1: 1Q24 | R1: 2Q24 | S1: 3Q24 | T1: 4Q24 | U1: 2024 | V1: 1Q25 | W1: 2Q25 | X1: 3Q25 | Y1: 4Q25 | Z1: 2025 | AA1: 1Q26 | AB1: 2Q26 | AC1: 3Q26 | AD1: 4Q26 | AE1: 2026 | AF1: 1Q27 | AG1: 2Q27 | AH1: 3Q27 | AI1: 4Q27 | AJ1: 2027 | AK1: 1Q28 | AL1: 2Q28 | AM1: 3Q28 | AN1: 4Q28 | AO1: 2028
A2: A=이름(key) B=그룹 C=단위 D=FnGuide 계정명(VLOOKUP 키). 확정=VLOOKUP(BS), 추정=변수 가정 참조
E3: 1 | F3: 2 | G3: 3 | H3: 4 | I3: 5 | J3: 6 | K3: 7 | L3: 8 | M3: 9 | N3: 10 | O3: 11 | P3: 12 | Q3: 13 | R3: 14 | S3: 15 | T3: 16 | U3: 17 | V3: 18 | W3: 19 | X3: 20 | Y3: 21 | Z3: 22 | AA3: 23 | AB3: 24 | AC3: 25 | AD3: 26 | AE3: 27 | AF3: 28 | AG3: 29 | AH3: 30 | AI3: 31 | AJ3: 32 | AK3: 33 | AL3: 34 | AM3: 35 | AN3: 36 | AO3: 37
E4: 2021.12 | F4: 2021.12A | G4: 2022.03 | H4: 2022.06 | I4: 2022.09 | J4: 2022.12 | K4: 2022.12A | L4: 2023.03 | M4: 2023.06 | N4: 2023.09 | O4: 2023.12 | P4: 2023.12A | Q4: 2024.03 | R4: 2024.06 | S4: 2024.09 | T4: 2024.12 | U4: 2024.12A | V4: 2025.03 | W4: 2025.06 | X4: 2025.09 | Y4: 2025.12 | Z4: 2025.12A | AA4: 2026.03 | AB4: 2026.06 | AC4: 2026.09 | AD4: 2026.12 | AE4: 2026.12A | AF4: 2027.03 | AG4: 2027.06 | AH4: 2027.09 | AI4: 2027.12 | AJ4: 2027.12A | AK4: 2028.03 | AL4: 2028.06 | AM4: 2028.09 | AN4: 2028.12 | AO4: 2028.12A
A5: 매출액 | B5: 손익 | C5: 억원 | D5: 매출액(수익) | E5: =IFERROR(VLOOKUP($D5,BS연결,MATCH(E$1,BS연결H,0),0)/100,"") | G5: =IFERROR(VLOOKUP($D5,BS연결,MATCH(G$1,BS연결H,0),0)/100,"") | H5: =IFERROR(VLOOKUP($D5,BS연결,MATCH(H$1,BS연결H,0),0)/100,"") | I5: =IFERROR(VLOOKUP($D5,BS연결,MATCH(I$1,BS연결H,0),0)/100,"") | J5: =IFERROR(VLOOKUP($D5,BS연결,MATCH(J$1,BS연결H,0),0)/100,"") | K5: =IFERROR(VLOOKUP($D5,BS연결,MATCH(K$1,BS연결H,0),0)/100,"") | L5: =IFERROR(VLOOKUP($D5,BS연결,MATCH(L$1,BS연결H,0),0)/100,"") | M5: =IFERROR(VLOOKUP($D5,BS연결,MATCH(M$1,BS연결H,0),0)/100,"") | N5: =IFERROR(VLOOKUP($D5,BS연결,MATCH(N$1,BS연결H,0),0)/100,"") | ... AB5: =IFERROR(VLOOKUP($D5,BS연결,MATCH(AB$1,BS연결H,0),0)/100,"") | AC5: =IFERROR(X5*(1+변수!AC21),"") | AD5: =IFERROR(Y5*(1+변수!AD21),"") | AE5: =SUM(AA5:AD5) | AF5: =IFERROR(AA5*(1+변수!AF21),"") | AG5: =IFERROR(AB5*(1+변수!AG21),"") | AH5: =IFERROR(AC5*(1+변수!AH21),"") | AI5: =IFERROR(AD5*(1+변수!AI21),"") | AJ5: =SUM(AF5:AI5) | AK5: =IFERROR(AF5*(1+변수!AK21),"") | AL5: =IFERROR(AG5*(1+변수!AL21),"") | AM5: =IFERROR(AH5*(1+변수!AM21),"") | AN5: =IFERROR(AI5*(1+변수!AN21),"") | AO5: =SUM(AK5:AN5)
A6: 매출원가 | B6: 손익 | C6: 억원 | D6: 매출원가 | E6: =IFERROR(VLOOKUP($D6,BS연결,MATCH(E$1,BS연결H,0),0)/100,"") | G6: =IFERROR(VLOOKUP($D6,BS연결,MATCH(G$1,BS연결H,0),0)/100,"") | H6: =IFERROR(VLOOKUP($D6,BS연결,MATCH(H$1,BS연결H,0),0)/100,"") | I6: =IFERROR(VLOOKUP($D6,BS연결,MATCH(I$1,BS연결H,0),0)/100,"") | J6: =IFERROR(VLOOKUP($D6,BS연결,MATCH(J$1,BS연결H,0),0)/100,"") | K6: =IFERROR(VLOOKUP($D6,BS연결,MATCH(K$1,BS연결H,0),0)/100,"") | L6: =IFERROR(VLOOKUP($D6,BS연결,MATCH(L$1,BS연결H,0),0)/100,"") | M6: =IFERROR(VLOOKUP($D6,BS연결,MATCH(M$1,BS연결H,0),0)/100,"") | N6: =IFERROR(VLOOKUP($D6,BS연결,MATCH(N$1,BS연결H,0),0)/100,"") | ... AB6: =IFERROR(VLOOKUP($D6,BS연결,MATCH(AB$1,BS연결H,0),0)/100,"") | AC6: =IFERROR(AC5-AC7,"") | AD6: =IFERROR(AD5-AD7,"") | AE6: =SUM(AA6:AD6) | AF6: =IFERROR(AF5-AF7,"") | AG6: =IFERROR(AG5-AG7,"") | AH6: =IFERROR(AH5-AH7,"") | AI6: =IFERROR(AI5-AI7,"") | AJ6: =SUM(AF6:AI6) | AK6: =IFERROR(AK5-AK7,"") | AL6: =IFERROR(AL5-AL7,"") | AM6: =IFERROR(AM5-AM7,"") | AN6: =IFERROR(AN5-AN7,"") | AO6: =SUM(AK6:AN6)
A7: 매출총이익 | B7: 손익 | C7: 억원 | D7: 매출총이익 | E7: =IFERROR(VLOOKUP($D7,BS연결,MATCH(E$1,BS연결H,0),0)/100,"") | G7: =IFERROR(VLOOKUP($D7,BS연결,MATCH(G$1,BS연결H,0),0)/100,"") | H7: =IFERROR(VLOOKUP($D7,BS연결,MATCH(H$1,BS연결H,0),0)/100,"") | I7: =IFERROR(VLOOKUP($D7,BS연결,MATCH(I$1,BS연결H,0),0)/100,"") | J7: =IFERROR(VLOOKUP($D7,BS연결,MATCH(J$1,BS연결H,0),0)/100,"") | K7: =IFERROR(VLOOKUP($D7,BS연결,MATCH(K$1,BS연결H,0),0)/100,"") | L7: =IFERROR(VLOOKUP($D7,BS연결,MATCH(L$1,BS연결H,0),0)/100,"") | M7: =IFERROR(VLOOKUP($D7,BS연결,MATCH(M$1,BS연결H,0),0)/100,"") | N7: =IFERROR(VLOOKUP($D7,BS연결,MATCH(N$1,BS연결H,0),0)/100,"") | ... AB7: =IFERROR(VLOOKUP($D7,BS연결,MATCH(AB$1,BS연결H,0),0)/100,"") | AC7: =IFERROR(AC9+AC8,"") | AD7: =IFERROR(AD9+AD8,"") | AE7: =SUM(AA7:AD7) | AF7: =IFERROR(AF9+AF8,"") | AG7: =IFERROR(AG9+AG8,"") | AH7: =IFERROR(AH9+AH8,"") | AI7: =IFERROR(AI9+AI8,"") | AJ7: =SUM(AF7:AI7) | AK7: =IFERROR(AK9+AK8,"") | AL7: =IFERROR(AL9+AL8,"") | AM7: =IFERROR(AM9+AM8,"") | AN7: =IFERROR(AN9+AN8,"") | AO7: =SUM(AK7:AN7)
A8: 판관비 | B8: 손익 | C8: 억원 | D8: 판관비 | E8: =IFERROR(VLOOKUP($D8,BS연결,MATCH(E$1,BS연결H,0),0)/100,"") | G8: =IFERROR(VLOOKUP($D8,BS연결,MATCH(G$1,BS연결H,0),0)/100,"") | H8: =IFERROR(VLOOKUP($D8,BS연결,MATCH(H$1,BS연결H,0),0)/100,"") | I8: =IFERROR(VLOOKUP($D8,BS연결,MATCH(I$1,BS연결H,0),0)/100,"") | J8: =IFERROR(VLOOKUP($D8,BS연결,MATCH(J$1,BS연결H,0),0)/100,"") | K8: =IFERROR(VLOOKUP($D8,BS연결,MATCH(K$1,BS연결H,0),0)/100,"") | L8: =IFERROR(VLOOKUP($D8,BS연결,MATCH(L$1,BS연결H,0),0)/100,"") | M8: =IFERROR(VLOOKUP($D8,BS연결,MATCH(M$1,BS연결H,0),0)/100,"") | N8: =IFERROR(VLOOKUP($D8,BS연결,MATCH(N$1,BS연결H,0),0)/100,"") | ... AB8: =IFERROR(VLOOKUP($D8,BS연결,MATCH(AB$1,BS연결H,0),0)/100,"") | AC8: =IFERROR(AC5*변수!AC22,"") | AD8: =IFERROR(AD5*변수!AD22,"") | AE8: =SUM(AA8:AD8) | AF8: =IFERROR(AF5*변수!AF22,"") | AG8: =IFERROR(AG5*변수!AG22,"") | AH8: =IFERROR(AH5*변수!AH22,"") | AI8: =IFERROR(AI5*변수!AI22,"") | AJ8: =SUM(AF8:AI8) | AK8: =IFERROR(AK5*변수!AK22,"") | AL8: =IFERROR(AL5*변수!AL22,"") | AM8: =IFERROR(AM5*변수!AM22,"") | AN8: =IFERROR(AN5*변수!AN22,"") | AO8: =SUM(AK8:AN8)
A9: 영업이익 | B9: 손익 | C9: 억원 | D9: 영업이익 | E9: =IFERROR(VLOOKUP($D9,BS연결,MATCH(E$1,BS연결H,0),0)/100,"") | G9: =IFERROR(VLOOKUP($D9,BS연결,MATCH(G$1,BS연결H,0),0)/100,"") | H9: =IFERROR(VLOOKUP($D9,BS연결,MATCH(H$1,BS연결H,0),0)/100,"") | I9: =IFERROR(VLOOKUP($D9,BS연결,MATCH(I$1,BS연결H,0),0)/100,"") | J9: =IFERROR(VLOOKUP($D9,BS연결,MATCH(J$1,BS연결H,0),0)/100,"") | K9: =IFERROR(VLOOKUP($D9,BS연결,MATCH(K$1,BS연결H,0),0)/100,"") | L9: =IFERROR(VLOOKUP($D9,BS연결,MATCH(L$1,BS연결H,0),0)/100,"") | M9: =IFERROR(VLOOKUP($D9,BS연결,MATCH(M$1,BS연결H,0),0)/100,"") | N9: =IFERROR(VLOOKUP($D9,BS연결,MATCH(N$1,BS연결H,0),0)/100,"") | ... AB9: =IFERROR(VLOOKUP($D9,BS연결,MATCH(AB$1,BS연결H,0),0)/100,"") | AC9: =IFERROR(AC5*변수!AC23,"") | AD9: =IFERROR(AD5*변수!AD23,"") | AE9: =SUM(AA9:AD9) | AF9: =IFERROR(AF5*변수!AF23,"") | AG9: =IFERROR(AG5*변수!AG23,"") | AH9: =IFERROR(AH5*변수!AH23,"") | AI9: =IFERROR(AI5*변수!AI23,"") | AJ9: =SUM(AF9:AI9) | AK9: =IFERROR(AK5*변수!AK23,"") | AL9: =IFERROR(AL5*변수!AL23,"") | AM9: =IFERROR(AM5*변수!AM23,"") | AN9: =IFERROR(AN5*변수!AN23,"") | AO9: =SUM(AK9:AN9)
A10: OPM | B10: 손익 | C10: % | D10: 영업이익률 | E10: =IFERROR(E9/E5,"") | G10: =IFERROR(G9/G5,"") | H10: =IFERROR(H9/H5,"") | I10: =IFERROR(I9/I5,"") | J10: =IFERROR(J9/J5,"") | K10: =IFERROR(K9/K5,"") | L10: =IFERROR(L9/L5,"") | M10: =IFERROR(M9/M5,"") | N10: =IFERROR(N9/N5,"") | ... AO10: =IFERROR(AO9/AO5,"")
A11: 금융손익 | B11: 손익 | C11: 억원 | D11: 금융손익 | E11: =IFERROR(VLOOKUP($D11,BS연결,MATCH(E$1,BS연결H,0),0)/100,"") | G11: =IFERROR(VLOOKUP($D11,BS연결,MATCH(G$1,BS연결H,0),0)/100,"") | H11: =IFERROR(VLOOKUP($D11,BS연결,MATCH(H$1,BS연결H,0),0)/100,"") | I11: =IFERROR(VLOOKUP($D11,BS연결,MATCH(I$1,BS연결H,0),0)/100,"") | J11: =IFERROR(VLOOKUP($D11,BS연결,MATCH(J$1,BS연결H,0),0)/100,"") | K11: =IFERROR(VLOOKUP($D11,BS연결,MATCH(K$1,BS연결H,0),0)/100,"") | L11: =IFERROR(VLOOKUP($D11,BS연결,MATCH(L$1,BS연결H,0),0)/100,"") | M11: =IFERROR(VLOOKUP($D11,BS연결,MATCH(M$1,BS연결H,0),0)/100,"") | N11: =IFERROR(VLOOKUP($D11,BS연결,MATCH(N$1,BS연결H,0),0)/100,"") | ... AB11: =IFERROR(VLOOKUP($D11,BS연결,MATCH(AB$1,BS연결H,0),0)/100,"") | AC11: =IFERROR(AC12,"") | AD11: =IFERROR(AD12,"") | AE11: =SUM(AA11:AD11) | AF11: =IFERROR(AF12,"") | AG11: =IFERROR(AG12,"") | AH11: =IFERROR(AH12,"") | AI11: =IFERROR(AI12,"") | AJ11: =SUM(AF11:AI11) | AK11: =IFERROR(AK12,"") | AL11: =IFERROR(AL12,"") | AM11: =IFERROR(AM12,"") | AN11: =IFERROR(AN12,"") | AO11: =SUM(AK11:AN11)
A12: 이자손익 | B12: 손익 | C12: 억원 | D12: 이자손익 | K12: =SUM(G12:J12) | P12: =SUM(L12:O12) | U12: =SUM(Q12:T12) | Z12: =SUM(V12:Y12) | AC12: =IFERROR((AB28*변수!$D$53-AB26*변수!$D$54)/4,"") | AD12: =IFERROR((AC28*변수!$D$53-AC26*변수!$D$54)/4,"") | AE12: =SUM(AA12:AD12) | AF12: =IFERROR((AD28*변수!$D$53-AD26*변수!$D$54)/4,"") | AG12: =IFERROR((AF28*변수!$D$53-AF26*변수!$D$54)/4,"") | AH12: =IFERROR((AG28*변수!$D$53-AG26*변수!$D$54)/4,"") | AI12: =IFERROR((AH28*변수!$D$53-AH26*변수!$D$54)/4,"") | AJ12: =SUM(AF12:AI12) | AK12: =IFERROR((AI28*변수!$D$53-AI26*변수!$D$54)/4,"") | AL12: =IFERROR((AK28*변수!$D$53-AK26*변수!$D$54)/4,"") | AM12: =IFERROR((AL28*변수!$D$53-AL26*변수!$D$54)/4,"") | AN12: =IFERROR((AM28*변수!$D$53-AM26*변수!$D$54)/4,"") | AO12: =SUM(AK12:AN12)
A13: 기타영업외손익 | B13: 손익 | C13: 억원 | D13: 기타영업외손익 | E13: =IFERROR(VLOOKUP($D13,BS연결,MATCH(E$1,BS연결H,0),0)/100,"") | G13: =IFERROR(VLOOKUP($D13,BS연결,MATCH(G$1,BS연결H,0),0)/100,"") | H13: =IFERROR(VLOOKUP($D13,BS연결,MATCH(H$1,BS연결H,0),0)/100,"") | I13: =IFERROR(VLOOKUP($D13,BS연결,MATCH(I$1,BS연결H,0),0)/100,"") | J13: =IFERROR(VLOOKUP($D13,BS연결,MATCH(J$1,BS연결H,0),0)/100,"") | K13: =IFERROR(VLOOKUP($D13,BS연결,MATCH(K$1,BS연결H,0),0)/100,"") | L13: =IFERROR(VLOOKUP($D13,BS연결,MATCH(L$1,BS연결H,0),0)/100,"") | M13: =IFERROR(VLOOKUP($D13,BS연결,MATCH(M$1,BS연결H,0),0)/100,"") | N13: =IFERROR(VLOOKUP($D13,BS연결,MATCH(N$1,BS연결H,0),0)/100,"") | ... AB13: =IFERROR(VLOOKUP($D13,BS연결,MATCH(AB$1,BS연결H,0),0)/100,"") | AC13: =변수!AC24 | AD13: =변수!AD24 | AE13: =SUM(AA13:AD13) | AF13: =변수!AF24 | AG13: =변수!AG24 | AH13: =변수!AH24 | AI13: =변수!AI24 | AJ13: =SUM(AF13:AI13) | AK13: =변수!AK24 | AL13: =변수!AL24 | AM13: =변수!AM24 | AN13: =변수!AN24 | AO13: =SUM(AK13:AN13)
A14: 지분법손익 | B14: 손익 | C14: 억원 | D14: 종속기업,공동지배기업및관계기업관련손익 | E14: =IFERROR(VLOOKUP($D14,BS연결,MATCH(E$1,BS연결H,0),0)/100,"") | G14: =IFERROR(VLOOKUP($D14,BS연결,MATCH(G$1,BS연결H,0),0)/100,"") | H14: =IFERROR(VLOOKUP($D14,BS연결,MATCH(H$1,BS연결H,0),0)/100,"") | I14: =IFERROR(VLOOKUP($D14,BS연결,MATCH(I$1,BS연결H,0),0)/100,"") | J14: =IFERROR(VLOOKUP($D14,BS연결,MATCH(J$1,BS연결H,0),0)/100,"") | K14: =IFERROR(VLOOKUP($D14,BS연결,MATCH(K$1,BS연결H,0),0)/100,"") | L14: =IFERROR(VLOOKUP($D14,BS연결,MATCH(L$1,BS연결H,0),0)/100,"") | M14: =IFERROR(VLOOKUP($D14,BS연결,MATCH(M$1,BS연결H,0),0)/100,"") | N14: =IFERROR(VLOOKUP($D14,BS연결,MATCH(N$1,BS연결H,0),0)/100,"") | ... AB14: =IFERROR(VLOOKUP($D14,BS연결,MATCH(AB$1,BS연결H,0),0)/100,"") | AC14: =변수!AC25 | AD14: =변수!AD25 | AE14: =SUM(AA14:AD14) | AF14: =변수!AF25 | AG14: =변수!AG25 | AH14: =변수!AH25 | AI14: =변수!AI25 | AJ14: =SUM(AF14:AI14) | AK14: =변수!AK25 | AL14: =변수!AL25 | AM14: =변수!AM25 | AN14: =변수!AN25 | AO14: =SUM(AK14:AN14)
A15: 세전이익 | B15: 손익 | C15: 억원 | D15: 법인세비용차감전계속사업이익 | G15: =IFERROR(VLOOKUP($D15,BS연결,MATCH(G$1,BS연결H,0),0)/100,"") | H15: =IFERROR(VLOOKUP($D15,BS연결,MATCH(H$1,BS연결H,0),0)/100,"") | I15: =IFERROR(VLOOKUP($D15,BS연결,MATCH(I$1,BS연결H,0),0)/100,"") | K15: =SUM(G15:J15) | L15: =IFERROR(VLOOKUP($D15,BS연결,MATCH(L$1,BS연결H,0),0)/100,"") | M15: =IFERROR(VLOOKUP($D15,BS연결,MATCH(M$1,BS연결H,0),0)/100,"") | N15: =IFERROR(VLOOKUP($D15,BS연결,MATCH(N$1,BS연결H,0),0)/100,"") | O15: =IFERROR(VLOOKUP($D15,BS연결,MATCH(O$1,BS연결H,0),0)/100,"") | P15: =IFERROR(VLOOKUP($D15,BS연결,MATCH(P$1,BS연결H,0),0)/100,"") | Q15: =IFERROR(VLOOKUP($D15,BS연결,MATCH(Q$1,BS연결H,0),0)/100,"") | R15: =IFERROR(VLOOKUP($D15,BS연결,MATCH(R$1,BS연결H,0),0)/100,"") | S15: =IFERROR(VLOOKUP($D15,BS연결,MATCH(S$1,BS연결H,0),0)/100,"") | ... AB15: =IFERROR(VLOOKUP($D15,BS연결,MATCH(AB$1,BS연결H,0),0)/100,"") | AC15: =IFERROR(AC9+AC11+AC13+AC14,"") | AD15: =IFERROR(AD9+AD11+AD13+AD14,"") | AE15: =SUM(AA15:AD15) | AF15: =IFERROR(AF9+AF11+AF13+AF14,"") | AG15: =IFERROR(AG9+AG11+AG13+AG14,"") | AH15: =IFERROR(AH9+AH11+AH13+AH14,"") | AI15: =IFERROR(AI9+AI11+AI13+AI14,"") | AJ15: =SUM(AF15:AI15) | AK15: =IFERROR(AK9+AK11+AK13+AK14,"") | AL15: =IFERROR(AL9+AL11+AL13+AL14,"") | AM15: =IFERROR(AM9+AM11+AM13+AM14,"") | AN15: =IFERROR(AN9+AN11+AN13+AN14,"") | AO15: =SUM(AK15:AN15)
A16: 법인세비용 | B16: 손익 | C16: 억원 | D16: 법인세비용 | E16: =IFERROR(VLOOKUP($D16,BS연결,MATCH(E$1,BS연결H,0),0)/100,"") | G16: =IFERROR(VLOOKUP($D16,BS연결,MATCH(G$1,BS연결H,0),0)/100,"") | H16: =IFERROR(VLOOKUP($D16,BS연결,MATCH(H$1,BS연결H,0),0)/100,"") | I16: =IFERROR(VLOOKUP($D16,BS연결,MATCH(I$1,BS연결H,0),0)/100,"") | J16: =IFERROR(VLOOKUP($D16,BS연결,MATCH(J$1,BS연결H,0),0)/100,"") | K16: =IFERROR(VLOOKUP($D16,BS연결,MATCH(K$1,BS연결H,0),0)/100,"") | L16: =IFERROR(VLOOKUP($D16,BS연결,MATCH(L$1,BS연결H,0),0)/100,"") | M16: =IFERROR(VLOOKUP($D16,BS연결,MATCH(M$1,BS연결H,0),0)/100,"") | N16: =IFERROR(VLOOKUP($D16,BS연결,MATCH(N$1,BS연결H,0),0)/100,"") | ... AB16: =IFERROR(VLOOKUP($D16,BS연결,MATCH(AB$1,BS연결H,0),0)/100,"") | AC16: =IFERROR(MAX(AC15,0)*변수!AC26,"") | AD16: =IFERROR(MAX(AD15,0)*변수!AD26,"") | AE16: =SUM(AA16:AD16) | AF16: =IFERROR(MAX(AF15,0)*변수!AF26,"") | AG16: =IFERROR(MAX(AG15,0)*변수!AG26,"") | AH16: =IFERROR(MAX(AH15,0)*변수!AH26,"") | AI16: =IFERROR(MAX(AI15,0)*변수!AI26,"") | AJ16: =SUM(AF16:AI16) | AK16: =IFERROR(MAX(AK15,0)*변수!AK26,"") | AL16: =IFERROR(MAX(AL15,0)*변수!AL26,"") | AM16: =IFERROR(MAX(AM15,0)*변수!AM26,"") | AN16: =IFERROR(MAX(AN15,0)*변수!AN26,"") | AO16: =SUM(AK16:AN16)
A17: 당기순이익 | B17: 손익 | C17: 억원 | D17: 당기순이익 | E17: =IFERROR(VLOOKUP($D17,BS연결,MATCH(E$1,BS연결H,0),0)/100,"") | G17: =IFERROR(VLOOKUP($D17,BS연결,MATCH(G$1,BS연결H,0),0)/100,"") | H17: =IFERROR(VLOOKUP($D17,BS연결,MATCH(H$1,BS연결H,0),0)/100,"") | I17: =IFERROR(VLOOKUP($D17,BS연결,MATCH(I$1,BS연결H,0),0)/100,"") | J17: =IFERROR(VLOOKUP($D17,BS연결,MATCH(J$1,BS연결H,0),0)/100,"") | K17: =SUM(G17:J17) | L17: =IFERROR(VLOOKUP($D17,BS연결,MATCH(L$1,BS연결H,0),0)/100,"") | M17: =IFERROR(VLOOKUP($D17,BS연결,MATCH(M$1,BS연결H,0),0)/100,"") | N17: =IFERROR(VLOOKUP($D17,BS연결,MATCH(N$1,BS연결H,0),0)/100,"") | O17: =IFERROR(VLOOKUP($D17,BS연결,MATCH(O$1,BS연결H,0),0)/100,"") | P17: =IFERROR(VLOOKUP($D17,BS연결,MATCH(P$1,BS연결H,0),0)/100,"") | Q17: =IFERROR(VLOOKUP($D17,BS연결,MATCH(Q$1,BS연결H,0),0)/100,"") | R17: =IFERROR(VLOOKUP($D17,BS연결,MATCH(R$1,BS연결H,0),0)/100,"") | S17: =IFERROR(VLOOKUP($D17,BS연결,MATCH(S$1,BS연결H,0),0)/100,"") | ... AB17: =IFERROR(VLOOKUP($D17,BS연결,MATCH(AB$1,BS연결H,0),0)/100,"") | AC17: =IFERROR(AC15-AC16,"") | AD17: =IFERROR(AD15-AD16,"") | AE17: =SUM(AA17:AD17) | AF17: =IFERROR(AF15-AF16,"") | AG17: =IFERROR(AG15-AG16,"") | AH17: =IFERROR(AH15-AH16,"") | AI17: =IFERROR(AI15-AI16,"") | AJ17: =SUM(AF17:AI17) | AK17: =IFERROR(AK15-AK16,"") | AL17: =IFERROR(AL15-AL16,"") | AM17: =IFERROR(AM15-AM16,"") | AN17: =IFERROR(AN15-AN16,"") | AO17: =SUM(AK17:AN17)
A18: 지배주주순이익 | B18: 손익 | C18: 억원 | D18: (지배주주지분)당기순이익 | E18: =IFERROR(VLOOKUP($D18,BS연결,MATCH(E$1,BS연결H,0),0)/100,"") | G18: =IFERROR(VLOOKUP($D18,BS연결,MATCH(G$1,BS연결H,0),0)/100,"") | H18: =IFERROR(VLOOKUP($D18,BS연결,MATCH(H$1,BS연결H,0),0)/100,"") | I18: =IFERROR(VLOOKUP($D18,BS연결,MATCH(I$1,BS연결H,0),0)/100,"") | J18: =IFERROR(VLOOKUP($D18,BS연결,MATCH(J$1,BS연결H,0),0)/100,"") | K18: =IFERROR(VLOOKUP($D18,BS연결,MATCH(K$1,BS연결H,0),0)/100,"") | L18: =IFERROR(VLOOKUP($D18,BS연결,MATCH(L$1,BS연결H,0),0)/100,"") | M18: =IFERROR(VLOOKUP($D18,BS연결,MATCH(M$1,BS연결H,0),0)/100,"") | N18: =IFERROR(VLOOKUP($D18,BS연결,MATCH(N$1,BS연결H,0),0)/100,"") | ... AB18: =IFERROR(VLOOKUP($D18,BS연결,MATCH(AB$1,BS연결H,0),0)/100,"") | AC18: =IFERROR(AC17*변수!AC27,"") | AD18: =IFERROR(AD17*변수!AD27,"") | AE18: =SUM(AA18:AD18) | AF18: =IFERROR(AF17*변수!AF27,"") | AG18: =IFERROR(AG17*변수!AG27,"") | AH18: =IFERROR(AH17*변수!AH27,"") | AI18: =IFERROR(AI17*변수!AI27,"") | AJ18: =SUM(AF18:AI18) | AK18: =IFERROR(AK17*변수!AK27,"") | AL18: =IFERROR(AL17*변수!AL27,"") | AM18: =IFERROR(AM17*변수!AM27,"") | AN18: =IFERROR(AN17*변수!AN27,"") | AO18: =SUM(AK18:AN18)
A19: 중단사업이익 | B19: 손익 | C19: 억원 | D19: 중단사업이익 | K19: =SUM(G19:J19) | O19: =IFERROR(VLOOKUP($D19,BS연결,MATCH(O$1,BS연결H,0),0)/100,"") | P19: =SUM(L19:O19) | U19: =SUM(Q19:T19) | Y19: =IFERROR(VLOOKUP($D19,BS연결,MATCH(Y$1,BS연결H,0),0)/100,"") | Z19: =SUM(V19:Y19) | AE19: =SUM(AA19:AD19) | AJ19: =SUM(AF19:AI19) | AO19: =SUM(AK19:AN19)
A20: 감가상각비 | B20: 손익 | C20: 억원 | D20: 감가상각비 | E20: =IFERROR(VLOOKUP($D20,BS연결,MATCH(E$1,BS연결H,0),0)/100,"") | G20: =IFERROR(VLOOKUP($D20,BS연결,MATCH(G$1,BS연결H,0),0)/100,"") | H20: =IFERROR(VLOOKUP($D20,BS연결,MATCH(H$1,BS연결H,0),0)/100,"") | I20: =IFERROR(VLOOKUP($D20,BS연결,MATCH(I$1,BS연결H,0),0)/100,"") | J20: =IFERROR(VLOOKUP($D20,BS연결,MATCH(J$1,BS연결H,0),0)/100,"") | K20: =IFERROR(VLOOKUP($D20,BS연결,MATCH(K$1,BS연결H,0),0)/100,"") | L20: =IFERROR(VLOOKUP($D20,BS연결,MATCH(L$1,BS연결H,0),0)/100,"") | M20: =IFERROR(VLOOKUP($D20,BS연결,MATCH(M$1,BS연결H,0),0)/100,"") | N20: =IFERROR(VLOOKUP($D20,BS연결,MATCH(N$1,BS연결H,0),0)/100,"") | ... AB20: =IFERROR(VLOOKUP($D20,BS연결,MATCH(AB$1,BS연결H,0),0)/100,"") | AC20: =변수!AC29 | AD20: =변수!AD29 | AE20: =SUM(AA20:AD20) | AF20: =변수!AF29 | AG20: =변수!AG29 | AH20: =변수!AH29 | AI20: =변수!AI29 | AJ20: =SUM(AF20:AI20) | AK20: =변수!AK29 | AL20: =변수!AL29 | AM20: =변수!AM29 | AN20: =변수!AN29 | AO20: =SUM(AK20:AN20)
A21: EBITDA | B21: 손익 | C21: 억원 | D21: EBITDA | E21: 181.23 | G21: 275 | H21: 262.83 | I21: 228.24 | J21: 223.31 | K21: =SUM(G21:J21) | L21: 311.76 | M21: 340.9 | N21: 351.46 | O21: 270.29 | P21: =SUM(L21:O21) | Q21: 284.7 | R21: 241.05 | S21: 216.24 | T21: 205.31 | U21: =SUM(Q21:T21) | V21: 234.7 | W21: 204.66 | X21: 162.38 | Y21: 164.46 | Z21: =SUM(V21:Y21) | AA21: 266.04 | AB21: 332.6 | AC21: =IFERROR(AC9+AC20,"") | AD21: =IFERROR(AD9+AD20,"") | AE21: =SUM(AA21:AD21) | AF21: =IFERROR(AF9+AF20,"") | AG21: =IFERROR(AG9+AG20,"") | AH21: =IFERROR(AH9+AH20,"") | AI21: =IFERROR(AI9+AI20,"") | AJ21: =SUM(AF21:AI21) | AK21: =IFERROR(AK9+AK20,"") | AL21: =IFERROR(AL9+AL20,"") | AM21: =IFERROR(AM9+AM20,"") | AN21: =IFERROR(AN9+AN20,"") | AO21: =SUM(AK21:AN21)
A22: 자산총계 | B22: 재무상태 | C22: 억원 | D22: 자산총계 | E22: =IFERROR(VLOOKUP($D22,BS연결,MATCH(E$1,BS연결H,0),0)/100,"") | F22: =IFERROR(VLOOKUP($D22,BS연결,MATCH(F$1,BS연결H,0),0)/100,"") | G22: =IFERROR(VLOOKUP($D22,BS연결,MATCH(G$1,BS연결H,0),0)/100,"") | H22: =IFERROR(VLOOKUP($D22,BS연결,MATCH(H$1,BS연결H,0),0)/100,"") | I22: =IFERROR(VLOOKUP($D22,BS연결,MATCH(I$1,BS연결H,0),0)/100,"") | J22: =IFERROR(VLOOKUP($D22,BS연결,MATCH(J$1,BS연결H,0),0)/100,"") | K22: =IFERROR(VLOOKUP($D22,BS연결,MATCH(K$1,BS연결H,0),0)/100,"") | L22: =IFERROR(VLOOKUP($D22,BS연결,MATCH(L$1,BS연결H,0),0)/100,"") | ... AB22: =IFERROR(VLOOKUP($D22,BS연결,MATCH(AB$1,BS연결H,0),0)/100,"") | AC22: =IFERROR(AC23+AC24,"") | AD22: =IFERROR(AD23+AD24,"") | AE22: =AD22 | AF22: =IFERROR(AF23+AF24,"") | AG22: =IFERROR(AG23+AG24,"") | AH22: =IFERROR(AH23+AH24,"") | AI22: =IFERROR(AI23+AI24,"") | AJ22: =AI22 | AK22: =IFERROR(AK23+AK24,"") | AL22: =IFERROR(AL23+AL24,"") | AM22: =IFERROR(AM23+AM24,"") | AN22: =IFERROR(AN23+AN24,"") | AO22: =AN22
A23: 부채총계 | B23: 재무상태 | C23: 억원 | D23: 부채총계 | E23: =IFERROR(VLOOKUP($D23,BS연결,MATCH(E$1,BS연결H,0),0)/100,"") | F23: =IFERROR(VLOOKUP($D23,BS연결,MATCH(F$1,BS연결H,0),0)/100,"") | G23: =IFERROR(VLOOKUP($D23,BS연결,MATCH(G$1,BS연결H,0),0)/100,"") | H23: =IFERROR(VLOOKUP($D23,BS연결,MATCH(H$1,BS연결H,0),0)/100,"") | I23: =IFERROR(VLOOKUP($D23,BS연결,MATCH(I$1,BS연결H,0),0)/100,"") | J23: =IFERROR(VLOOKUP($D23,BS연결,MATCH(J$1,BS연결H,0),0)/100,"") | K23: =IFERROR(VLOOKUP($D23,BS연결,MATCH(K$1,BS연결H,0),0)/100,"") | L23: =IFERROR(VLOOKUP($D23,BS연결,MATCH(L$1,BS연결H,0),0)/100,"") | ... AB23: =IFERROR(VLOOKUP($D23,BS연결,MATCH(AB$1,BS연결H,0),0)/100,"") | AC23: =IFERROR(AB23*(1+변수!AC30),"") | AD23: =IFERROR(AC23*(1+변수!AD30),"") | AE23: =AD23 | AF23: =IFERROR(AD23*(1+변수!AF30),"") | AG23: =IFERROR(AF23*(1+변수!AG30),"") | AH23: =IFERROR(AG23*(1+변수!AH30),"") | AI23: =IFERROR(AH23*(1+변수!AI30),"") | AJ23: =AI23 | AK23: =IFERROR(AI23*(1+변수!AK30),"") | AL23: =IFERROR(AK23*(1+변수!AL30),"") | AM23: =IFERROR(AL23*(1+변수!AM30),"") | AN23: =IFERROR(AM23*(1+변수!AN30),"") | AO23: =AN23
A24: 자본총계 | B24: 재무상태 | C24: 억원 | D24: 자본총계 | E24: =IFERROR(VLOOKUP($D24,BS연결,MATCH(E$1,BS연결H,0),0)/100,"") | F24: =IFERROR(VLOOKUP($D24,BS연결,MATCH(F$1,BS연결H,0),0)/100,"") | G24: =IFERROR(VLOOKUP($D24,BS연결,MATCH(G$1,BS연결H,0),0)/100,"") | H24: =IFERROR(VLOOKUP($D24,BS연결,MATCH(H$1,BS연결H,0),0)/100,"") | I24: =IFERROR(VLOOKUP($D24,BS연결,MATCH(I$1,BS연결H,0),0)/100,"") | J24: =IFERROR(VLOOKUP($D24,BS연결,MATCH(J$1,BS연결H,0),0)/100,"") | K24: =IFERROR(VLOOKUP($D24,BS연결,MATCH(K$1,BS연결H,0),0)/100,"") | L24: =IFERROR(VLOOKUP($D24,BS연결,MATCH(L$1,BS연결H,0),0)/100,"") | ... AB24: =IFERROR(VLOOKUP($D24,BS연결,MATCH(AB$1,BS연결H,0),0)/100,"") | AC24: =IFERROR(AB24+AC17-변수!AC31,"") | AD24: =IFERROR(AC24+AD17-변수!AD31,"") | AE24: =AD24 | AF24: =IFERROR(AD24+AF17-변수!AF31,"") | AG24: =IFERROR(AF24+AG17-변수!AG31,"") | AH24: =IFERROR(AG24+AH17-변수!AH31,"") | AI24: =IFERROR(AH24+AI17-변수!AI31,"") | AJ24: =AI24 | AK24: =IFERROR(AI24+AK17-변수!AK31,"") | AL24: =IFERROR(AK24+AL17-변수!AL31,"") | AM24: =IFERROR(AL24+AM17-변수!AM31,"") | AN24: =IFERROR(AM24+AN17-변수!AN31,"") | AO24: =AN24
A25: 지배주주지분 | B25: 재무상태 | C25: 억원 | D25: 지배주주지분 | E25: =IFERROR(VLOOKUP($D25,BS연결,MATCH(E$1,BS연결H,0),0)/100,"") | F25: =IFERROR(VLOOKUP($D25,BS연결,MATCH(F$1,BS연결H,0),0)/100,"") | G25: =IFERROR(VLOOKUP($D25,BS연결,MATCH(G$1,BS연결H,0),0)/100,"") | H25: =IFERROR(VLOOKUP($D25,BS연결,MATCH(H$1,BS연결H,0),0)/100,"") | I25: =IFERROR(VLOOKUP($D25,BS연결,MATCH(I$1,BS연결H,0),0)/100,"") | J25: =IFERROR(VLOOKUP($D25,BS연결,MATCH(J$1,BS연결H,0),0)/100,"") | K25: =IFERROR(VLOOKUP($D25,BS연결,MATCH(K$1,BS연결H,0),0)/100,"") | L25: =IFERROR(VLOOKUP($D25,BS연결,MATCH(L$1,BS연결H,0),0)/100,"") | ... AB25: =IFERROR(VLOOKUP($D25,BS연결,MATCH(AB$1,BS연결H,0),0)/100,"") | AC25: =IFERROR(AB25+AC18-변수!AC32,"") | AD25: =IFERROR(AC25+AD18-변수!AD32,"") | AE25: =AD25 | AF25: =IFERROR(AD25+AF18-변수!AF32,"") | AG25: =IFERROR(AF25+AG18-변수!AG32,"") | AH25: =IFERROR(AG25+AH18-변수!AH32,"") | AI25: =IFERROR(AH25+AI18-변수!AI32,"") | AJ25: =AI25 | AK25: =IFERROR(AI25+AK18-변수!AK32,"") | AL25: =IFERROR(AK25+AL18-변수!AL32,"") | AM25: =IFERROR(AL25+AM18-변수!AM32,"") | AN25: =IFERROR(AM25+AN18-변수!AN32,"") | AO25: =AN25
A26: 총차입금 | B26: 재무상태 | C26: 억원 | D26: 총차입금 | E26: =IFERROR(VLOOKUP($D26,BS연결,MATCH(E$1,BS연결H,0),0)/100,"") | F26: =IFERROR(VLOOKUP($D26,BS연결,MATCH(F$1,BS연결H,0),0)/100,"") | G26: =IFERROR(VLOOKUP($D26,BS연결,MATCH(G$1,BS연결H,0),0)/100,"") | H26: =IFERROR(VLOOKUP($D26,BS연결,MATCH(H$1,BS연결H,0),0)/100,"") | I26: =IFERROR(VLOOKUP($D26,BS연결,MATCH(I$1,BS연결H,0),0)/100,"") | J26: =IFERROR(VLOOKUP($D26,BS연결,MATCH(J$1,BS연결H,0),0)/100,"") | K26: =IFERROR(VLOOKUP($D26,BS연결,MATCH(K$1,BS연결H,0),0)/100,"") | L26: =IFERROR(VLOOKUP($D26,BS연결,MATCH(L$1,BS연결H,0),0)/100,"") | ... AB26: =IFERROR(VLOOKUP($D26,BS연결,MATCH(AB$1,BS연결H,0),0)/100,"") | AC26: =IFERROR(AB26*(1+변수!AC33),"") | AD26: =IFERROR(AC26*(1+변수!AD33),"") | AE26: =AD26 | AF26: =IFERROR(AD26*(1+변수!AF33),"") | AG26: =IFERROR(AF26*(1+변수!AG33),"") | AH26: =IFERROR(AG26*(1+변수!AH33),"") | AI26: =IFERROR(AH26*(1+변수!AI33),"") | AJ26: =AI26 | AK26: =IFERROR(AI26*(1+변수!AK33),"") | AL26: =IFERROR(AK26*(1+변수!AL33),"") | AM26: =IFERROR(AL26*(1+변수!AM33),"") | AN26: =IFERROR(AM26*(1+변수!AN33),"") | AO26: =AN26
A27: 순차입금 | B27: 재무상태 | C27: 억원 | D27: 순차입금 | E27: =IFERROR(VLOOKUP($D27,BS연결,MATCH(E$1,BS연결H,0),0)/100,"") | F27: =IFERROR(VLOOKUP($D27,BS연결,MATCH(F$1,BS연결H,0),0)/100,"") | G27: =IFERROR(VLOOKUP($D27,BS연결,MATCH(G$1,BS연결H,0),0)/100,"") | H27: =IFERROR(VLOOKUP($D27,BS연결,MATCH(H$1,BS연결H,0),0)/100,"") | I27: =IFERROR(VLOOKUP($D27,BS연결,MATCH(I$1,BS연결H,0),0)/100,"") | J27: =IFERROR(VLOOKUP($D27,BS연결,MATCH(J$1,BS연결H,0),0)/100,"") | K27: =IFERROR(VLOOKUP($D27,BS연결,MATCH(K$1,BS연결H,0),0)/100,"") | L27: =IFERROR(VLOOKUP($D27,BS연결,MATCH(L$1,BS연결H,0),0)/100,"") | ... AB27: =IFERROR(VLOOKUP($D27,BS연결,MATCH(AB$1,BS연결H,0),0)/100,"") | AC27: =IFERROR(AB27*(1+변수!AC34),"") | AD27: =IFERROR(AC27*(1+변수!AD34),"") | AE27: =AD27 | AF27: =IFERROR(AD27*(1+변수!AF34),"") | AG27: =IFERROR(AF27*(1+변수!AG34),"") | AH27: =IFERROR(AG27*(1+변수!AH34),"") | AI27: =IFERROR(AH27*(1+변수!AI34),"") | AJ27: =AI27 | AK27: =IFERROR(AI27*(1+변수!AK34),"") | AL27: =IFERROR(AK27*(1+변수!AL34),"") | AM27: =IFERROR(AL27*(1+변수!AM34),"") | AN27: =IFERROR(AM27*(1+변수!AN34),"") | AO27: =AN27
A28: 이자발생자산 | B28: 재무상태 | C28: 억원 | D28: 이자발생자산 | E28: =IFERROR(VLOOKUP($D28,BS연결,MATCH(E$1,BS연결H,0),0)/100,"") | F28: =IFERROR(VLOOKUP($D28,BS연결,MATCH(F$1,BS연결H,0),0)/100,"") | G28: =IFERROR(VLOOKUP($D28,BS연결,MATCH(G$1,BS연결H,0),0)/100,"") | H28: =IFERROR(VLOOKUP($D28,BS연결,MATCH(H$1,BS연결H,0),0)/100,"") | I28: =IFERROR(VLOOKUP($D28,BS연결,MATCH(I$1,BS연결H,0),0)/100,"") | J28: =IFERROR(VLOOKUP($D28,BS연결,MATCH(J$1,BS연결H,0),0)/100,"") | K28: =IFERROR(VLOOKUP($D28,BS연결,MATCH(K$1,BS연결H,0),0)/100,"") | L28: =IFERROR(VLOOKUP($D28,BS연결,MATCH(L$1,BS연결H,0),0)/100,"") | ... AB28: =IFERROR(VLOOKUP($D28,BS연결,MATCH(AB$1,BS연결H,0),0)/100,"") | AC28: =IFERROR(AB28*(1+변수!AC35),"") | AD28: =IFERROR(AC28*(1+변수!AD35),"") | AE28: =AD28 | AF28: =IFERROR(AD28*(1+변수!AF35),"") | AG28: =IFERROR(AF28*(1+변수!AG35),"") | AH28: =IFERROR(AG28*(1+변수!AH35),"") | AI28: =IFERROR(AH28*(1+변수!AI35),"") | AJ28: =AI28 | AK28: =IFERROR(AI28*(1+변수!AK35),"") | AL28: =IFERROR(AK28*(1+변수!AL35),"") | AM28: =IFERROR(AL28*(1+변수!AM35),"") | AN28: =IFERROR(AM28*(1+변수!AN35),"") | AO28: =AN28
A29: 현금및현금성자산 | B29: 재무상태 | C29: 억원 | D29: 현금및현금성자산 | E29: =IFERROR(VLOOKUP($D29,BS연결,MATCH(E$1,BS연결H,0),0)/100,"") | F29: =IFERROR(VLOOKUP($D29,BS연결,MATCH(F$1,BS연결H,0),0)/100,"") | G29: =IFERROR(VLOOKUP($D29,BS연결,MATCH(G$1,BS연결H,0),0)/100,"") | H29: =IFERROR(VLOOKUP($D29,BS연결,MATCH(H$1,BS연결H,0),0)/100,"") | I29: =IFERROR(VLOOKUP($D29,BS연결,MATCH(I$1,BS연결H,0),0)/100,"") | J29: =IFERROR(VLOOKUP($D29,BS연결,MATCH(J$1,BS연결H,0),0)/100,"") | K29: =IFERROR(VLOOKUP($D29,BS연결,MATCH(K$1,BS연결H,0),0)/100,"") | L29: =IFERROR(VLOOKUP($D29,BS연결,MATCH(L$1,BS연결H,0),0)/100,"") | ... AB29: =IFERROR(VLOOKUP($D29,BS연결,MATCH(AB$1,BS연결H,0),0)/100,"") | AE29: =AD29 | AJ29: =AI29 | AO29: =AN29
A30: CAPEX | B30: 현금흐름 | C30: 억원 | D30: CAPEX | E30: =IFERROR(VLOOKUP($D30,BS연결,MATCH(E$1,BS연결H,0),0)/100,"") | G30: =IFERROR(VLOOKUP($D30,BS연결,MATCH(G$1,BS연결H,0),0)/100,"") | H30: =IFERROR(VLOOKUP($D30,BS연결,MATCH(H$1,BS연결H,0),0)/100,"") | I30: =IFERROR(VLOOKUP($D30,BS연결,MATCH(I$1,BS연결H,0),0)/100,"") | J30: =IFERROR(VLOOKUP($D30,BS연결,MATCH(J$1,BS연결H,0),0)/100,"") | K30: =IFERROR(VLOOKUP($D30,BS연결,MATCH(K$1,BS연결H,0),0)/100,"") | L30: =IFERROR(VLOOKUP($D30,BS연결,MATCH(L$1,BS연결H,0),0)/100,"") | M30: =IFERROR(VLOOKUP($D30,BS연결,MATCH(M$1,BS연결H,0),0)/100,"") | N30: =IFERROR(VLOOKUP($D30,BS연결,MATCH(N$1,BS연결H,0),0)/100,"") | ... AB30: =IFERROR(VLOOKUP($D30,BS연결,MATCH(AB$1,BS연결H,0),0)/100,"") | AC30: =IFERROR(X30*(1+변수!AC37),"") | AD30: =IFERROR(Y30*(1+변수!AD37),"") | AE30: =SUM(AA30:AD30) | AF30: =IFERROR(AA30*(1+변수!AF37),"") | AG30: =IFERROR(AB30*(1+변수!AG37),"") | AH30: =IFERROR(AC30*(1+변수!AH37),"") | AI30: =IFERROR(AD30*(1+변수!AI37),"") | AJ30: =SUM(AF30:AI30) | AK30: =IFERROR(AF30*(1+변수!AK37),"") | AL30: =IFERROR(AG30*(1+변수!AL37),"") | AM30: =IFERROR(AH30*(1+변수!AM37),"") | AN30: =IFERROR(AI30*(1+변수!AN37),"") | AO30: =SUM(AK30:AN30)
A31: 영업활동현금흐름 | B31: 현금흐름 | C31: 억원 | D31: 영업활동으로인한현금흐름 | E31: =IFERROR(VLOOKUP($D31,BS연결,MATCH(E$1,BS연결H,0),0)/100,"") | G31: =IFERROR(VLOOKUP($D31,BS연결,MATCH(G$1,BS연결H,0),0)/100,"") | H31: =IFERROR(VLOOKUP($D31,BS연결,MATCH(H$1,BS연결H,0),0)/100,"") | I31: =IFERROR(VLOOKUP($D31,BS연결,MATCH(I$1,BS연결H,0),0)/100,"") | J31: =IFERROR(VLOOKUP($D31,BS연결,MATCH(J$1,BS연결H,0),0)/100,"") | K31: =IFERROR(VLOOKUP($D31,BS연결,MATCH(K$1,BS연결H,0),0)/100,"") | L31: =IFERROR(VLOOKUP($D31,BS연결,MATCH(L$1,BS연결H,0),0)/100,"") | M31: =IFERROR(VLOOKUP($D31,BS연결,MATCH(M$1,BS연결H,0),0)/100,"") | N31: =IFERROR(VLOOKUP($D31,BS연결,MATCH(N$1,BS연결H,0),0)/100,"") | ... AB31: =IFERROR(VLOOKUP($D31,BS연결,MATCH(AB$1,BS연결H,0),0)/100,"") | AE31: =SUM(AA31:AD31) | AJ31: =SUM(AF31:AI31) | AO31: =SUM(AK31:AN31)
A32: 주식수 | B32: 주당 | C32: 백만주 | D32: 유통주식수 | E32: 26.872 | F32: =E32 | G32: 26.872 | H32: 26.872 | I32: 26.872 | J32: 26.872 | K32: =J32 | L32: 26.872 | M32: 26.872 | N32: 26.872 | O32: 26.872 | P32: =O32 | Q32: 26.872 | R32: 26.872 | S32: 26.872 | T32: 26.872 | U32: =T32 | V32: 26.872 | W32: 26.872 | X32: 26.872 | Y32: 28.329 | Z32: =Y32 | AA32: 28.329 | AB32: 28.329 | AC32: =IFERROR(AB32*(1+변수!AC39),"") | AD32: =IFERROR(AC32*(1+변수!AD39),"") | AE32: =AD32 | AF32: =IFERROR(AD32*(1+변수!AF39),"") | AG32: =IFERROR(AF32*(1+변수!AG39),"") | AH32: =IFERROR(AG32*(1+변수!AH39),"") | AI32: =IFERROR(AH32*(1+변수!AI39),"") | AJ32: =AI32 | AK32: =IFERROR(AI32*(1+변수!AK39),"") | AL32: =IFERROR(AK32*(1+변수!AL39),"") | AM32: =IFERROR(AL32*(1+변수!AM39),"") | AN32: =IFERROR(AM32*(1+변수!AN39),"") | AO32: =AN32
A33: EPS | B33: 주당 | C33: 원 | D33: EPS | E33: =IFERROR(E18*100/E32,"") | G33: =IFERROR(G18*100/G32,"") | H33: =IFERROR(H18*100/H32,"") | I33: =IFERROR(I18*100/I32,"") | J33: =IFERROR(J18*100/J32,"") | K33: =SUM(G33:J33) | L33: =IFERROR(L18*100/L32,"") | M33: =IFERROR(M18*100/M32,"") | N33: =IFERROR(N18*100/N32,"") | O33: =IFERROR(O18*100/O32,"") | P33: =SUM(L33:O33) | Q33: =IFERROR(Q18*100/Q32,"") | R33: =IFERROR(R18*100/R32,"") | S33: =IFERROR(S18*100/S32,"") | T33: =IFERROR(T18*100/T32,"") | U33: =SUM(Q33:T33) | V33: =IFERROR(V18*100/V32,"") | W33: =IFERROR(W18*100/W32,"") | X33: =IFERROR(X18*100/X32,"") | Y33: =IFERROR(Y18*100/Y32,"") | Z33: =SUM(V33:Y33) | AA33: =IFERROR(AA18*100/AA32,"") | AB33: =IFERROR(AB18*100/AB32,"") | AC33: =IFERROR(AC18*100/AC32,"") | AD33: =IFERROR(AD18*100/AD32,"") | AE33: =SUM(AA33:AD33) | AF33: =IFERROR(AF18*100/AF32,"") | AG33: =IFERROR(AG18*100/AG32,"") | AH33: =IFERROR(AH18*100/AH32,"") | AI33: =IFERROR(AI18*100/AI32,"") | AJ33: =SUM(AF33:AI33) | AK33: =IFERROR(AK18*100/AK32,"") | AL33: =IFERROR(AL18*100/AL32,"") | AM33: =IFERROR(AM18*100/AM32,"") | AN33: =IFERROR(AN18*100/AN32,"") | AO33: =SUM(AK33:AN33)
A34: 조정EPS | B34: 주당 | C34: 원 | D34: 조정 EPS(일회성 의심 분기의 초과 비영업손익 세후 차감 — 모델 추정) | E34: =IFERROR(E33,"") | G34: =IFERROR(G33,"") | H34: =IFERROR(H33,"") | I34: =IFERROR(I33,"") | J34: =IFERROR(J33,"") | K34: =SUM(G34:J34) | L34: =IFERROR(L33,"") | M34: =IFERROR(M33,"") | N34: =IFERROR(N33,"") | O34: =IFERROR(O33,"") | P34: =SUM(L34:O34) | Q34: =IFERROR(Q33,"") | R34: =IFERROR(R33,"") | S34: =IFERROR(S33,"") | T34: =IFERROR(T33,"") | U34: =SUM(Q34:T34) | V34: =IFERROR(V33,"") | W34: =IFERROR(W33,"") | X34: =IFERROR(X33,"") | Y34: =IFERROR((Y18-(-214.18)*(1.0))*100/Y32,"") | Z34: =SUM(V34:Y34) | AA34: =IFERROR(AA33,"") | AB34: =IFERROR(AB33,"") | AC34: =IFERROR(AC33,"") | AD34: =IFERROR(AD33,"") | AE34: =SUM(AA34:AD34) | AF34: =IFERROR(AF33,"") | AG34: =IFERROR(AG33,"") | AH34: =IFERROR(AH33,"") | AI34: =IFERROR(AI33,"") | AJ34: =SUM(AF34:AI34) | AK34: =IFERROR(AK33,"") | AL34: =IFERROR(AL33,"") | AM34: =IFERROR(AM33,"") | AN34: =IFERROR(AN33,"") | AO34: =SUM(AK34:AN34)
A35: BPS | B35: 주당 | C35: 원 | D35: BPS | E35: =IFERROR(E25*100/E32,"") | F35: =E35 | G35: =IFERROR(G25*100/G32,"") | H35: =IFERROR(H25*100/H32,"") | I35: =IFERROR(I25*100/I32,"") | J35: =IFERROR(J25*100/J32,"") | K35: =J35 | L35: =IFERROR(L25*100/L32,"") | M35: =IFERROR(M25*100/M32,"") | N35: =IFERROR(N25*100/N32,"") | O35: =IFERROR(O25*100/O32,"") | P35: =O35 | Q35: =IFERROR(Q25*100/Q32,"") | R35: =IFERROR(R25*100/R32,"") | S35: =IFERROR(S25*100/S32,"") | T35: =IFERROR(T25*100/T32,"") | U35: =T35 | V35: =IFERROR(V25*100/V32,"") | W35: =IFERROR(W25*100/W32,"") | X35: =IFERROR(X25*100/X32,"") | Y35: =IFERROR(Y25*100/Y32,"") | Z35: =Y35 | AA35: =IFERROR(AA25*100/AA32,"") | AB35: =IFERROR(AB25*100/AB32,"") | AC35: =IFERROR(AC25*100/AC32,"") | AD35: =IFERROR(AD25*100/AD32,"") | AE35: =AD35 | AF35: =IFERROR(AF25*100/AF32,"") | AG35: =IFERROR(AG25*100/AG32,"") | AH35: =IFERROR(AH25*100/AH32,"") | AI35: =IFERROR(AI25*100/AI32,"") | AJ35: =AI35 | AK35: =IFERROR(AK25*100/AK32,"") | AL35: =IFERROR(AL25*100/AL32,"") | AM35: =IFERROR(AM25*100/AM32,"") | AN35: =IFERROR(AN25*100/AN32,"") | AO35: =AN35
A36: DPS | B36: 주당 | C36: 원 | D36: DPS(보통주) | E36: 100 | F36: 100 | J36: 120 | K36: =SUM(G36:J36) | O36: 120 | P36: =SUM(L36:O36) | T36: 120 | U36: =SUM(Q36:T36) | Y36: 120 | Z36: =SUM(V36:Y36) | AD36: =변수!AD40 | AE36: =SUM(AA36:AD36) | AI36: =변수!AI40 | AJ36: =SUM(AF36:AI36) | AN36: =변수!AN40 | AO36: =SUM(AK36:AN36)
A37: PER | B37: 주당 | C37: 배 | D37: PER | F37: =E37 | I37: =IFERROR(변수!I18/(E33+G33+H33+I33),"") | J37: =IFERROR(변수!J18/(G33+H33+I33+J33),"") | K37: =J37 | L37: =IFERROR(변수!L18/(H33+I33+J33+L33),"") | M37: =IFERROR(변수!M18/(I33+J33+L33+M33),"") | N37: =IFERROR(변수!N18/(J33+L33+M33+N33),"") | O37: =IFERROR(변수!O18/(L33+M33+N33+O33),"") | P37: =O37 | Q37: =IFERROR(변수!Q18/(M33+N33+O33+Q33),"") | R37: =IFERROR(변수!R18/(N33+O33+Q33+R33),"") | S37: =IFERROR(변수!S18/(O33+Q33+R33+S33),"") | T37: =IFERROR(변수!T18/(Q33+R33+S33+T33),"") | U37: =T37 | Z37: =Y37 | AD37: =IFERROR(변수!$D$43/(AA33+AB33+AC33+AD33),"") | AE37: =AD37 | AF37: =IFERROR(변수!$D$43/(AB33+AC33+AD33+AF33),"") | AG37: =IFERROR(변수!$D$43/(AC33+AD33+AF33+AG33),"") | AH37: =IFERROR(변수!$D$43/(AD33+AF33+AG33+AH33),"") | AI37: =IFERROR(변수!$D$43/(AF33+AG33+AH33+AI33),"") | AJ37: =AI37 | AK37: =IFERROR(변수!$D$43/(AG33+AH33+AI33+AK33),"") | AL37: =IFERROR(변수!$D$43/(AH33+AI33+AK33+AL33),"") | AM37: =IFERROR(변수!$D$43/(AI33+AK33+AL33+AM33),"") | AN37: =IFERROR(변수!$D$43/(AK33+AL33+AM33+AN33),"") | AO37: =AN37
A38: PBR | B38: 주당 | C38: 배 | D38: PBR | E38: =IFERROR(변수!E18/E35,"") | F38: =E38 | G38: =IFERROR(변수!G18/G35,"") | H38: =IFERROR(변수!H18/H35,"") | I38: =IFERROR(변수!I18/I35,"") | J38: =IFERROR(변수!J18/J35,"") | K38: =J38 | L38: =IFERROR(변수!L18/L35,"") | M38: =IFERROR(변수!M18/M35,"") | N38: =IFERROR(변수!N18/N35,"") | O38: =IFERROR(변수!O18/O35,"") | P38: =O38 | Q38: =IFERROR(변수!Q18/Q35,"") | R38: =IFERROR(변수!R18/R35,"") | S38: =IFERROR(변수!S18/S35,"") | T38: =IFERROR(변수!T18/T35,"") | U38: =T38 | V38: =IFERROR(변수!V18/V35,"") | W38: =IFERROR(변수!W18/W35,"") | X38: =IFERROR(변수!X18/X35,"") | Y38: =IFERROR(변수!Y18/Y35,"") | Z38: =Y38 | AA38: =IFERROR(변수!AA18/AA35,"") | AB38: =IFERROR(변수!AB18/AB35,"") | AC38: =IFERROR(변수!$D$43/AC35,"") | AD38: =IFERROR(변수!$D$43/AD35,"") | AE38: =AD38 | AF38: =IFERROR(변수!$D$43/AF35,"") | AG38: =IFERROR(변수!$D$43/AG35,"") | AH38: =IFERROR(변수!$D$43/AH35,"") | AI38: =IFERROR(변수!$D$43/AI35,"") | AJ38: =AI38 | AK38: =IFERROR(변수!$D$43/AK35,"") | AL38: =IFERROR(변수!$D$43/AL35,"") | AM38: =IFERROR(변수!$D$43/AM35,"") | AN38: =IFERROR(변수!$D$43/AN35,"") | AO38: =AN38
A39: 매출전사 | B39: 사업부 | C39: 억원 | D39: 매출 전사(부문 미분리) | E39: 1451.13 | G39: 1735.05 | H39: 1697.44 | I39: 1776.49 | J39: 2080.35 | K39: =SUM(G39:J39) | L39: 2105.98 | M39: 2143.09 | N39: 2110.36 | O39: 2209.49 | P39: =SUM(L39:O39) | Q39: 2092.93 | R39: 1894.75 | S39: 1937.09 | T39: 2088.75 | U39: =SUM(Q39:T39) | V39: 1978.71 | W39: 2118.21 | X39: 2052.74 | Y39: 1871.9 | Z39: =SUM(V39:Y39) | AA39: 1966.68 | AB39: 2290.92 | AC39: =IFERROR(AC5,"") | AD39: =IFERROR(AD5,"") | AE39: =SUM(AA39:AD39) | AF39: =IFERROR(AF5,"") | AG39: =IFERROR(AG5,"") | AH39: =IFERROR(AH5,"") | AI39: =IFERROR(AI5,"") | AJ39: =SUM(AF39:AI39) | AK39: =IFERROR(AK5,"") | AL39: =IFERROR(AL5,"") | AM39: =IFERROR(AM5,"") | AN39: =IFERROR(AN5,"") | AO39: =SUM(AK39:AN39)
A40: OP전사 | B40: 사업부 | C40: 억원 | D40: OP 전사(부문 미분리) | E40: 36.28 | G40: 120.21 | H40: 98.58 | I40: 64.51 | J40: 56.09 | K40: =SUM(G40:J40) | L40: 157.51 | M40: 182.62 | N40: 189.36 | O40: 136.32 | P40: =SUM(L40:O40) | Q40: 136.42 | R40: 86.73 | S40: 57.65 | T40: 49.68 | U40: =SUM(Q40:T40) | V40: 70.62 | W40: 40.39 | X40: -0.39 | Y40: -5.64 | Z40: =SUM(V40:Y40) | AA40: 132.39 | AB40: 179.9 | AC40: =IFERROR(AC9,"") | AD40: =IFERROR(AD9,"") | AE40: =SUM(AA40:AD40) | AF40: =IFERROR(AF9,"") | AG40: =IFERROR(AG9,"") | AH40: =IFERROR(AH9,"") | AI40: =IFERROR(AI9,"") | AJ40: =SUM(AF40:AI40) | AK40: =IFERROR(AK9,"") | AL40: =IFERROR(AL9,"") | AM40: =IFERROR(AM9,"") | AN40: =IFERROR(AN9,"") | AO40: =SUM(AK40:AN40)
B41: 비율(참고)
A42: NPM | C42: % | D42: 지배주주순이익 / 매출액 | E42: =IFERROR(E18/E5,"") | F42: =IFERROR(F18/F5,"") | G42: =IFERROR(G18/G5,"") | H42: =IFERROR(H18/H5,"") | I42: =IFERROR(I18/I5,"") | J42: =IFERROR(J18/J5,"") | K42: =IFERROR(K18/K5,"") | L42: =IFERROR(L18/L5,"") | ... AO42: =IFERROR(AO18/AO5,"")
A43: 매출원가율 | C43: % | D43: 매출원가 / 매출액 | E43: =IFERROR(E6/E5,"") | F43: =IFERROR(F6/F5,"") | G43: =IFERROR(G6/G5,"") | H43: =IFERROR(H6/H5,"") | I43: =IFERROR(I6/I5,"") | J43: =IFERROR(J6/J5,"") | K43: =IFERROR(K6/K5,"") | L43: =IFERROR(L6/L5,"") | ... AO43: =IFERROR(AO6/AO5,"")
A44: 판관비율 | C44: % | D44: 판관비 / 매출액 | E44: =IFERROR(E8/E5,"") | F44: =IFERROR(F8/F5,"") | G44: =IFERROR(G8/G5,"") | H44: =IFERROR(H8/H5,"") | I44: =IFERROR(I8/I5,"") | J44: =IFERROR(J8/J5,"") | K44: =IFERROR(K8/K5,"") | L44: =IFERROR(L8/L5,"") | ... AO44: =IFERROR(AO8/AO5,"")

Sheet 분기
C1: 이름: 분기H — subQ 를 이름으로 VLOOKUP(억원) | E1: 4Q21 | F1: 1Q22 | G1: 2Q22 | H1: 3Q22 | I1: 4Q22 | J1: 1Q23 | K1: 2Q23 | L1: 3Q23 | M1: 4Q23 | N1: 1Q24 | O1: 2Q24 | P1: 3Q24 | Q1: 4Q24 | R1: 1Q25 | S1: 2Q25 | T1: 3Q25 | U1: 4Q25 | V1: 1Q26 | W1: 2Q26 | X1: 3Q26 | Y1: 4Q26 | Z1: 1Q27 | AA1: 2Q27 | AB1: 3Q27 | AC1: 4Q27 | AD1: 1Q28 | AE1: 2Q28 | AF1: 3Q28 | AG1: 4Q28
C2: 종가: | D2: =변수!D43
C3: 기준일: | D3: 20261026 | E3: 1 | F3: 2 | G3: 3 | H3: 4 | I3: 5 | J3: 6 | K3: 7 | L3: 8 | M3: 9 | N3: 10 | O3: 11 | P3: 12 | Q3: 13 | R3: 14 | S3: 15 | T3: 16 | U3: 17 | V3: 18 | W3: 19 | X3: 20 | Y3: 21 | Z3: 22 | AA3: 23 | AB3: 24 | AC3: 25 | AD3: 26 | AE3: 27 | AF3: 28 | AG3: 29
E4: 2021.12 | F4: 2022.03 | G4: 2022.06 | H4: 2022.09 | I4: 2022.12 | J4: 2023.03 | K4: 2023.06 | L4: 2023.09 | M4: 2023.12 | N4: 2024.03 | O4: 2024.06 | P4: 2024.09 | Q4: 2024.12 | R4: 2025.03 | S4: 2025.06 | T4: 2025.09 | U4: 2025.12 | V4: 2026.03 | W4: 2026.06 | X4: 2026.09 | Y4: 2026.12 | Z4: 2027.03 | AA4: 2027.06 | AB4: 2027.09 | AC4: 2027.12 | AD4: 2028.03 | AE4: 2028.06 | AF4: 2028.09 | AG4: 2028.12
A5: 매출액 | D5: 매출액 | E5: =IFERROR(VLOOKUP($A5,subQ,MATCH(E$1,SUBQH,0),0),"") | F5: =IFERROR(VLOOKUP($A5,subQ,MATCH(F$1,SUBQH,0),0),"") | G5: =IFERROR(VLOOKUP($A5,subQ,MATCH(G$1,SUBQH,0),0),"") | H5: =IFERROR(VLOOKUP($A5,subQ,MATCH(H$1,SUBQH,0),0),"") | I5: =IFERROR(VLOOKUP($A5,subQ,MATCH(I$1,SUBQH,0),0),"") | J5: =IFERROR(VLOOKUP($A5,subQ,MATCH(J$1,SUBQH,0),0),"") | K5: =IFERROR(VLOOKUP($A5,subQ,MATCH(K$1,SUBQH,0),0),"") | L5: =IFERROR(VLOOKUP($A5,subQ,MATCH(L$1,SUBQH,0),0),"") | ... AG5: =IFERROR(VLOOKUP($A5,subQ,MATCH(AG$1,SUBQH,0),0),"")
A6: 매출원가 | D6: 매출원가 | E6: =IFERROR(VLOOKUP($A6,subQ,MATCH(E$1,SUBQH,0),0),"") | F6: =IFERROR(VLOOKUP($A6,subQ,MATCH(F$1,SUBQH,0),0),"") | G6: =IFERROR(VLOOKUP($A6,subQ,MATCH(G$1,SUBQH,0),0),"") | H6: =IFERROR(VLOOKUP($A6,subQ,MATCH(H$1,SUBQH,0),0),"") | I6: =IFERROR(VLOOKUP($A6,subQ,MATCH(I$1,SUBQH,0),0),"") | J6: =IFERROR(VLOOKUP($A6,subQ,MATCH(J$1,SUBQH,0),0),"") | K6: =IFERROR(VLOOKUP($A6,subQ,MATCH(K$1,SUBQH,0),0),"") | L6: =IFERROR(VLOOKUP($A6,subQ,MATCH(L$1,SUBQH,0),0),"") | ... AG6: =IFERROR(VLOOKUP($A6,subQ,MATCH(AG$1,SUBQH,0),0),"")
A7: 매출총이익 | D7: 매출총이익 | E7: =IFERROR(VLOOKUP($A7,subQ,MATCH(E$1,SUBQH,0),0),"") | F7: =IFERROR(VLOOKUP($A7,subQ,MATCH(F$1,SUBQH,0),0),"") | G7: =IFERROR(VLOOKUP($A7,subQ,MATCH(G$1,SUBQH,0),0),"") | H7: =IFERROR(VLOOKUP($A7,subQ,MATCH(H$1,SUBQH,0),0),"") | I7: =IFERROR(VLOOKUP($A7,subQ,MATCH(I$1,SUBQH,0),0),"") | J7: =IFERROR(VLOOKUP($A7,subQ,MATCH(J$1,SUBQH,0),0),"") | K7: =IFERROR(VLOOKUP($A7,subQ,MATCH(K$1,SUBQH,0),0),"") | L7: =IFERROR(VLOOKUP($A7,subQ,MATCH(L$1,SUBQH,0),0),"") | ... AG7: =IFERROR(VLOOKUP($A7,subQ,MATCH(AG$1,SUBQH,0),0),"")
A8: 판관비 | D8: 판매비와관리비 | E8: =IFERROR(VLOOKUP($A8,subQ,MATCH(E$1,SUBQH,0),0),"") | F8: =IFERROR(VLOOKUP($A8,subQ,MATCH(F$1,SUBQH,0),0),"") | G8: =IFERROR(VLOOKUP($A8,subQ,MATCH(G$1,SUBQH,0),0),"") | H8: =IFERROR(VLOOKUP($A8,subQ,MATCH(H$1,SUBQH,0),0),"") | I8: =IFERROR(VLOOKUP($A8,subQ,MATCH(I$1,SUBQH,0),0),"") | J8: =IFERROR(VLOOKUP($A8,subQ,MATCH(J$1,SUBQH,0),0),"") | K8: =IFERROR(VLOOKUP($A8,subQ,MATCH(K$1,SUBQH,0),0),"") | L8: =IFERROR(VLOOKUP($A8,subQ,MATCH(L$1,SUBQH,0),0),"") | ... AG8: =IFERROR(VLOOKUP($A8,subQ,MATCH(AG$1,SUBQH,0),0),"")
A9: 영업이익 | D9: 영업이익 | E9: =IFERROR(VLOOKUP($A9,subQ,MATCH(E$1,SUBQH,0),0),"") | F9: =IFERROR(VLOOKUP($A9,subQ,MATCH(F$1,SUBQH,0),0),"") | G9: =IFERROR(VLOOKUP($A9,subQ,MATCH(G$1,SUBQH,0),0),"") | H9: =IFERROR(VLOOKUP($A9,subQ,MATCH(H$1,SUBQH,0),0),"") | I9: =IFERROR(VLOOKUP($A9,subQ,MATCH(I$1,SUBQH,0),0),"") | J9: =IFERROR(VLOOKUP($A9,subQ,MATCH(J$1,SUBQH,0),0),"") | K9: =IFERROR(VLOOKUP($A9,subQ,MATCH(K$1,SUBQH,0),0),"") | L9: =IFERROR(VLOOKUP($A9,subQ,MATCH(L$1,SUBQH,0),0),"") | ... AG9: =IFERROR(VLOOKUP($A9,subQ,MATCH(AG$1,SUBQH,0),0),"")
A10: OPM | D10: 영업이익률 | E10: =IFERROR(VLOOKUP($A10,subQ,MATCH(E$1,SUBQH,0),0),"") | F10: =IFERROR(VLOOKUP($A10,subQ,MATCH(F$1,SUBQH,0),0),"") | G10: =IFERROR(VLOOKUP($A10,subQ,MATCH(G$1,SUBQH,0),0),"") | H10: =IFERROR(VLOOKUP($A10,subQ,MATCH(H$1,SUBQH,0),0),"") | I10: =IFERROR(VLOOKUP($A10,subQ,MATCH(I$1,SUBQH,0),0),"") | J10: =IFERROR(VLOOKUP($A10,subQ,MATCH(J$1,SUBQH,0),0),"") | K10: =IFERROR(VLOOKUP($A10,subQ,MATCH(K$1,SUBQH,0),0),"") | L10: =IFERROR(VLOOKUP($A10,subQ,MATCH(L$1,SUBQH,0),0),"") | ... AG10: =IFERROR(VLOOKUP($A10,subQ,MATCH(AG$1,SUBQH,0),0),"")
A11: 금융손익 | D11: 금융손익(이자·환 포함) | E11: =IFERROR(VLOOKUP($A11,subQ,MATCH(E$1,SUBQH,0),0),"") | F11: =IFERROR(VLOOKUP($A11,subQ,MATCH(F$1,SUBQH,0),0),"") | G11: =IFERROR(VLOOKUP($A11,subQ,MATCH(G$1,SUBQH,0),0),"") | H11: =IFERROR(VLOOKUP($A11,subQ,MATCH(H$1,SUBQH,0),0),"") | I11: =IFERROR(VLOOKUP($A11,subQ,MATCH(I$1,SUBQH,0),0),"") | J11: =IFERROR(VLOOKUP($A11,subQ,MATCH(J$1,SUBQH,0),0),"") | K11: =IFERROR(VLOOKUP($A11,subQ,MATCH(K$1,SUBQH,0),0),"") | L11: =IFERROR(VLOOKUP($A11,subQ,MATCH(L$1,SUBQH,0),0),"") | ... AG11: =IFERROR(VLOOKUP($A11,subQ,MATCH(AG$1,SUBQH,0),0),"")
A12: 이자손익 | D12: 이자손익(이자수익 − 이자비용) | E12: =IFERROR(VLOOKUP($A12,subQ,MATCH(E$1,SUBQH,0),0),"") | F12: =IFERROR(VLOOKUP($A12,subQ,MATCH(F$1,SUBQH,0),0),"") | G12: =IFERROR(VLOOKUP($A12,subQ,MATCH(G$1,SUBQH,0),0),"") | H12: =IFERROR(VLOOKUP($A12,subQ,MATCH(H$1,SUBQH,0),0),"") | I12: =IFERROR(VLOOKUP($A12,subQ,MATCH(I$1,SUBQH,0),0),"") | J12: =IFERROR(VLOOKUP($A12,subQ,MATCH(J$1,SUBQH,0),0),"") | K12: =IFERROR(VLOOKUP($A12,subQ,MATCH(K$1,SUBQH,0),0),"") | L12: =IFERROR(VLOOKUP($A12,subQ,MATCH(L$1,SUBQH,0),0),"") | ... AG12: =IFERROR(VLOOKUP($A12,subQ,MATCH(AG$1,SUBQH,0),0),"")
A13: 기타영업외손익 | D13: 기타영업외손익 | E13: =IFERROR(VLOOKUP($A13,subQ,MATCH(E$1,SUBQH,0),0),"") | F13: =IFERROR(VLOOKUP($A13,subQ,MATCH(F$1,SUBQH,0),0),"") | G13: =IFERROR(VLOOKUP($A13,subQ,MATCH(G$1,SUBQH,0),0),"") | H13: =IFERROR(VLOOKUP($A13,subQ,MATCH(H$1,SUBQH,0),0),"") | I13: =IFERROR(VLOOKUP($A13,subQ,MATCH(I$1,SUBQH,0),0),"") | J13: =IFERROR(VLOOKUP($A13,subQ,MATCH(J$1,SUBQH,0),0),"") | K13: =IFERROR(VLOOKUP($A13,subQ,MATCH(K$1,SUBQH,0),0),"") | L13: =IFERROR(VLOOKUP($A13,subQ,MATCH(L$1,SUBQH,0),0),"") | ... AG13: =IFERROR(VLOOKUP($A13,subQ,MATCH(AG$1,SUBQH,0),0),"")
A14: 지분법손익 | D14: 지분법손익 | E14: =IFERROR(VLOOKUP($A14,subQ,MATCH(E$1,SUBQH,0),0),"") | F14: =IFERROR(VLOOKUP($A14,subQ,MATCH(F$1,SUBQH,0),0),"") | G14: =IFERROR(VLOOKUP($A14,subQ,MATCH(G$1,SUBQH,0),0),"") | H14: =IFERROR(VLOOKUP($A14,subQ,MATCH(H$1,SUBQH,0),0),"") | I14: =IFERROR(VLOOKUP($A14,subQ,MATCH(I$1,SUBQH,0),0),"") | J14: =IFERROR(VLOOKUP($A14,subQ,MATCH(J$1,SUBQH,0),0),"") | K14: =IFERROR(VLOOKUP($A14,subQ,MATCH(K$1,SUBQH,0),0),"") | L14: =IFERROR(VLOOKUP($A14,subQ,MATCH(L$1,SUBQH,0),0),"") | ... AG14: =IFERROR(VLOOKUP($A14,subQ,MATCH(AG$1,SUBQH,0),0),"")
A15: 세전이익 | D15: 법인세비용차감전이익 | E15: =IFERROR(VLOOKUP($A15,subQ,MATCH(E$1,SUBQH,0),0),"") | F15: =IFERROR(VLOOKUP($A15,subQ,MATCH(F$1,SUBQH,0),0),"") | G15: =IFERROR(VLOOKUP($A15,subQ,MATCH(G$1,SUBQH,0),0),"") | H15: =IFERROR(VLOOKUP($A15,subQ,MATCH(H$1,SUBQH,0),0),"") | I15: =IFERROR(VLOOKUP($A15,subQ,MATCH(I$1,SUBQH,0),0),"") | J15: =IFERROR(VLOOKUP($A15,subQ,MATCH(J$1,SUBQH,0),0),"") | K15: =IFERROR(VLOOKUP($A15,subQ,MATCH(K$1,SUBQH,0),0),"") | L15: =IFERROR(VLOOKUP($A15,subQ,MATCH(L$1,SUBQH,0),0),"") | ... AG15: =IFERROR(VLOOKUP($A15,subQ,MATCH(AG$1,SUBQH,0),0),"")
A16: 법인세비용 | D16: 법인세비용 | E16: =IFERROR(VLOOKUP($A16,subQ,MATCH(E$1,SUBQH,0),0),"") | F16: =IFERROR(VLOOKUP($A16,subQ,MATCH(F$1,SUBQH,0),0),"") | G16: =IFERROR(VLOOKUP($A16,subQ,MATCH(G$1,SUBQH,0),0),"") | H16: =IFERROR(VLOOKUP($A16,subQ,MATCH(H$1,SUBQH,0),0),"") | I16: =IFERROR(VLOOKUP($A16,subQ,MATCH(I$1,SUBQH,0),0),"") | J16: =IFERROR(VLOOKUP($A16,subQ,MATCH(J$1,SUBQH,0),0),"") | K16: =IFERROR(VLOOKUP($A16,subQ,MATCH(K$1,SUBQH,0),0),"") | L16: =IFERROR(VLOOKUP($A16,subQ,MATCH(L$1,SUBQH,0),0),"") | ... AG16: =IFERROR(VLOOKUP($A16,subQ,MATCH(AG$1,SUBQH,0),0),"")
... A41: NPM | D41: NPM | E41: =IFERROR(VLOOKUP($A41,subQ,MATCH(E$1,SUBQH,0),0),"") | F41: =IFERROR(VLOOKUP($A41,subQ,MATCH(F$1,SUBQH,0),0),"") | G41: =IFERROR(VLOOKUP($A41,subQ,MATCH(G$1,SUBQH,0),0),"") | H41: =IFERROR(VLOOKUP($A41,subQ,MATCH(H$1,SUBQH,0),0),"") | I41: =IFERROR(VLOOKUP($A41,subQ,MATCH(I$1,SUBQH,0),0),"") | J41: =IFERROR(VLOOKUP($A41,subQ,MATCH(J$1,SUBQH,0),0),"") | K41: =IFERROR(VLOOKUP($A41,subQ,MATCH(K$1,SUBQH,0),0),"") | L41: =IFERROR(VLOOKUP($A41,subQ,MATCH(L$1,SUBQH,0),0),"") | ... AG41: =IFERROR(VLOOKUP($A41,subQ,MATCH(AG$1,SUBQH,0),0),"")
A42: 매출액 YoY | D42: 매출액 YoY | I42: =IFERROR(I5/E5-1,"") | J42: =IFERROR(J5/F5-1,"") | K42: =IFERROR(K5/G5-1,"") | L42: =IFERROR(L5/H5-1,"") | M42: =IFERROR(M5/I5-1,"") | N42: =IFERROR(N5/J5-1,"") | O42: =IFERROR(O5/K5-1,"") | P42: =IFERROR(P5/L5-1,"") | ... AG42: =IFERROR(AG5/AC5-1,"")
A43: 영업이익 YoY | D43: 영업이익 YoY | I43: =IFERROR(I9/E9-1,"") | J43: =IFERROR(J9/F9-1,"") | K43: =IFERROR(K9/G9-1,"") | L43: =IFERROR(L9/H9-1,"") | M43: =IFERROR(M9/I9-1,"") | N43: =IFERROR(N9/J9-1,"") | O43: =IFERROR(O9/K9-1,"") | P43: =IFERROR(P9/L9-1,"") | ... AG43: =IFERROR(AG9/AC9-1,"")
A44: 지배주주순이익 YoY | D44: 지배주주순이익 YoY | I44: =IFERROR(I18/E18-1,"") | J44: =IFERROR(J18/F18-1,"") | K44: =IFERROR(K18/G18-1,"") | L44: =IFERROR(L18/H18-1,"") | M44: =IFERROR(M18/I18-1,"") | N44: =IFERROR(N18/J18-1,"") | O44: =IFERROR(O18/K18-1,"") | P44: =IFERROR(P18/L18-1,"") | ... AG44: =IFERROR(AG18/AC18-1,"")

Sheet 연간예상
C1: 이름: 연간예상H — subQ 를 이름으로 VLOOKUP(억원) | E1: 2021 | F1: 2022 | G1: 2023 | H1: 2024 | I1: 2025 | J1: 2026 | K1: 2027 | L1: 2028
C2: 종가: | D2: =변수!D43
C3: 기준일: | D3: 20261026 | E3: 1 | F3: 2 | G3: 3 | H3: 4 | I3: 5 | J3: 6 | K3: 7 | L3: 8
E4: 2021.12A | F4: 2022.12A | G4: 2023.12A | H4: 2024.12A | I4: 2025.12A | J4: 2026.12A | K4: 2027.12A | L4: 2028.12A
A5: 매출액 | D5: 매출액 | E5: =IFERROR(VLOOKUP($A5,subQ,MATCH(E$1,SUBQH,0),0),"") | F5: =IFERROR(VLOOKUP($A5,subQ,MATCH(F$1,SUBQH,0),0),"") | G5: =IFERROR(VLOOKUP($A5,subQ,MATCH(G$1,SUBQH,0),0),"") | H5: =IFERROR(VLOOKUP($A5,subQ,MATCH(H$1,SUBQH,0),0),"") | I5: =IFERROR(VLOOKUP($A5,subQ,MATCH(I$1,SUBQH,0),0),"") | J5: =IFERROR(VLOOKUP($A5,subQ,MATCH(J$1,SUBQH,0),0),"") | K5: =IFERROR(VLOOKUP($A5,subQ,MATCH(K$1,SUBQH,0),0),"") | L5: =IFERROR(VLOOKUP($A5,subQ,MATCH(L$1,SUBQH,0),0),"")
A6: 매출원가 | D6: 매출원가 | E6: =IFERROR(VLOOKUP($A6,subQ,MATCH(E$1,SUBQH,0),0),"") | F6: =IFERROR(VLOOKUP($A6,subQ,MATCH(F$1,SUBQH,0),0),"") | G6: =IFERROR(VLOOKUP($A6,subQ,MATCH(G$1,SUBQH,0),0),"") | H6: =IFERROR(VLOOKUP($A6,subQ,MATCH(H$1,SUBQH,0),0),"") | I6: =IFERROR(VLOOKUP($A6,subQ,MATCH(I$1,SUBQH,0),0),"") | J6: =IFERROR(VLOOKUP($A6,subQ,MATCH(J$1,SUBQH,0),0),"") | K6: =IFERROR(VLOOKUP($A6,subQ,MATCH(K$1,SUBQH,0),0),"") | L6: =IFERROR(VLOOKUP($A6,subQ,MATCH(L$1,SUBQH,0),0),"")
A7: 매출총이익 | D7: 매출총이익 | E7: =IFERROR(VLOOKUP($A7,subQ,MATCH(E$1,SUBQH,0),0),"") | F7: =IFERROR(VLOOKUP($A7,subQ,MATCH(F$1,SUBQH,0),0),"") | G7: =IFERROR(VLOOKUP($A7,subQ,MATCH(G$1,SUBQH,0),0),"") | H7: =IFERROR(VLOOKUP($A7,subQ,MATCH(H$1,SUBQH,0),0),"") | I7: =IFERROR(VLOOKUP($A7,subQ,MATCH(I$1,SUBQH,0),0),"") | J7: =IFERROR(VLOOKUP($A7,subQ,MATCH(J$1,SUBQH,0),0),"") | K7: =IFERROR(VLOOKUP($A7,subQ,MATCH(K$1,SUBQH,0),0),"") | L7: =IFERROR(VLOOKUP($A7,subQ,MATCH(L$1,SUBQH,0),0),"")
A8: 판관비 | D8: 판매비와관리비 | E8: =IFERROR(VLOOKUP($A8,subQ,MATCH(E$1,SUBQH,0),0),"") | F8: =IFERROR(VLOOKUP($A8,subQ,MATCH(F$1,SUBQH,0),0),"") | G8: =IFERROR(VLOOKUP($A8,subQ,MATCH(G$1,SUBQH,0),0),"") | H8: =IFERROR(VLOOKUP($A8,subQ,MATCH(H$1,SUBQH,0),0),"") | I8: =IFERROR(VLOOKUP($A8,subQ,MATCH(I$1,SUBQH,0),0),"") | J8: =IFERROR(VLOOKUP($A8,subQ,MATCH(J$1,SUBQH,0),0),"") | K8: =IFERROR(VLOOKUP($A8,subQ,MATCH(K$1,SUBQH,0),0),"") | L8: =IFERROR(VLOOKUP($A8,subQ,MATCH(L$1,SUBQH,0),0),"")
A9: 영업이익 | D9: 영업이익 | E9: =IFERROR(VLOOKUP($A9,subQ,MATCH(E$1,SUBQH,0),0),"") | F9: =IFERROR(VLOOKUP($A9,subQ,MATCH(F$1,SUBQH,0),0),"") | G9: =IFERROR(VLOOKUP($A9,subQ,MATCH(G$1,SUBQH,0),0),"") | H9: =IFERROR(VLOOKUP($A9,subQ,MATCH(H$1,SUBQH,0),0),"") | I9: =IFERROR(VLOOKUP($A9,subQ,MATCH(I$1,SUBQH,0),0),"") | J9: =IFERROR(VLOOKUP($A9,subQ,MATCH(J$1,SUBQH,0),0),"") | K9: =IFERROR(VLOOKUP($A9,subQ,MATCH(K$1,SUBQH,0),0),"") | L9: =IFERROR(VLOOKUP($A9,subQ,MATCH(L$1,SUBQH,0),0),"")
A10: OPM | D10: 영업이익률 | E10: =IFERROR(VLOOKUP($A10,subQ,MATCH(E$1,SUBQH,0),0),"") | F10: =IFERROR(VLOOKUP($A10,subQ,MATCH(F$1,SUBQH,0),0),"") | G10: =IFERROR(VLOOKUP($A10,subQ,MATCH(G$1,SUBQH,0),0),"") | H10: =IFERROR(VLOOKUP($A10,subQ,MATCH(H$1,SUBQH,0),0),"") | I10: =IFERROR(VLOOKUP($A10,subQ,MATCH(I$1,SUBQH,0),0),"") | J10: =IFERROR(VLOOKUP($A10,subQ,MATCH(J$1,SUBQH,0),0),"") | K10: =IFERROR(VLOOKUP($A10,subQ,MATCH(K$1,SUBQH,0),0),"") | L10: =IFERROR(VLOOKUP($A10,subQ,MATCH(L$1,SUBQH,0),0),"")
A11: 금융손익 | D11: 금융손익(이자·환 포함) | E11: =IFERROR(VLOOKUP($A11,subQ,MATCH(E$1,SUBQH,0),0),"") | F11: =IFERROR(VLOOKUP($A11,subQ,MATCH(F$1,SUBQH,0),0),"") | G11: =IFERROR(VLOOKUP($A11,subQ,MATCH(G$1,SUBQH,0),0),"") | H11: =IFERROR(VLOOKUP($A11,subQ,MATCH(H$1,SUBQH,0),0),"") | I11: =IFERROR(VLOOKUP($A11,subQ,MATCH(I$1,SUBQH,0),0),"") | J11: =IFERROR(VLOOKUP($A11,subQ,MATCH(J$1,SUBQH,0),0),"") | K11: =IFERROR(VLOOKUP($A11,subQ,MATCH(K$1,SUBQH,0),0),"") | L11: =IFERROR(VLOOKUP($A11,subQ,MATCH(L$1,SUBQH,0),0),"")
A12: 이자손익 | D12: 이자손익(이자수익 − 이자비용) | E12: =IFERROR(VLOOKUP($A12,subQ,MATCH(E$1,SUBQH,0),0),"") | F12: =IFERROR(VLOOKUP($A12,subQ,MATCH(F$1,SUBQH,0),0),"") | G12: =IFERROR(VLOOKUP($A12,subQ,MATCH(G$1,SUBQH,0),0),"") | H12: =IFERROR(VLOOKUP($A12,subQ,MATCH(H$1,SUBQH,0),0),"") | I12: =IFERROR(VLOOKUP($A12,subQ,MATCH(I$1,SUBQH,0),0),"") | J12: =IFERROR(VLOOKUP($A12,subQ,MATCH(J$1,SUBQH,0),0),"") | K12: =IFERROR(VLOOKUP($A12,subQ,MATCH(K$1,SUBQH,0),0),"") | L12: =IFERROR(VLOOKUP($A12,subQ,MATCH(L$1,SUBQH,0),0),"")
A13: 기타영업외손익 | D13: 기타영업외손익 | E13: =IFERROR(VLOOKUP($A13,subQ,MATCH(E$1,SUBQH,0),0),"") | F13: =IFERROR(VLOOKUP($A13,subQ,MATCH(F$1,SUBQH,0),0),"") | G13: =IFERROR(VLOOKUP($A13,subQ,MATCH(G$1,SUBQH,0),0),"") | H13: =IFERROR(VLOOKUP($A13,subQ,MATCH(H$1,SUBQH,0),0),"") | I13: =IFERROR(VLOOKUP($A13,subQ,MATCH(I$1,SUBQH,0),0),"") | J13: =IFERROR(VLOOKUP($A13,subQ,MATCH(J$1,SUBQH,0),0),"") | K13: =IFERROR(VLOOKUP($A13,subQ,MATCH(K$1,SUBQH,0),0),"") | L13: =IFERROR(VLOOKUP($A13,subQ,MATCH(L$1,SUBQH,0),0),"")
A14: 지분법손익 | D14: 지분법손익 | E14: =IFERROR(VLOOKUP($A14,subQ,MATCH(E$1,SUBQH,0),0),"") | F14: =IFERROR(VLOOKUP($A14,subQ,MATCH(F$1,SUBQH,0),0),"") | G14: =IFERROR(VLOOKUP($A14,subQ,MATCH(G$1,SUBQH,0),0),"") | H14: =IFERROR(VLOOKUP($A14,subQ,MATCH(H$1,SUBQH,0),0),"") | I14: =IFERROR(VLOOKUP($A14,subQ,MATCH(I$1,SUBQH,0),0),"") | J14: =IFERROR(VLOOKUP($A14,subQ,MATCH(J$1,SUBQH,0),0),"") | K14: =IFERROR(VLOOKUP($A14,subQ,MATCH(K$1,SUBQH,0),0),"") | L14: =IFERROR(VLOOKUP($A14,subQ,MATCH(L$1,SUBQH,0),0),"")
A15: 세전이익 | D15: 법인세비용차감전이익 | E15: =IFERROR(VLOOKUP($A15,subQ,MATCH(E$1,SUBQH,0),0),"") | F15: =IFERROR(VLOOKUP($A15,subQ,MATCH(F$1,SUBQH,0),0),"") | G15: =IFERROR(VLOOKUP($A15,subQ,MATCH(G$1,SUBQH,0),0),"") | H15: =IFERROR(VLOOKUP($A15,subQ,MATCH(H$1,SUBQH,0),0),"") | I15: =IFERROR(VLOOKUP($A15,subQ,MATCH(I$1,SUBQH,0),0),"") | J15: =IFERROR(VLOOKUP($A15,subQ,MATCH(J$1,SUBQH,0),0),"") | K15: =IFERROR(VLOOKUP($A15,subQ,MATCH(K$1,SUBQH,0),0),"") | L15: =IFERROR(VLOOKUP($A15,subQ,MATCH(L$1,SUBQH,0),0),"")
A16: 법인세비용 | D16: 법인세비용 | E16: =IFERROR(VLOOKUP($A16,subQ,MATCH(E$1,SUBQH,0),0),"") | F16: =IFERROR(VLOOKUP($A16,subQ,MATCH(F$1,SUBQH,0),0),"") | G16: =IFERROR(VLOOKUP($A16,subQ,MATCH(G$1,SUBQH,0),0),"") | H16: =IFERROR(VLOOKUP($A16,subQ,MATCH(H$1,SUBQH,0),0),"") | I16: =IFERROR(VLOOKUP($A16,subQ,MATCH(I$1,SUBQH,0),0),"") | J16: =IFERROR(VLOOKUP($A16,subQ,MATCH(J$1,SUBQH,0),0),"") | K16: =IFERROR(VLOOKUP($A16,subQ,MATCH(K$1,SUBQH,0),0),"") | L16: =IFERROR(VLOOKUP($A16,subQ,MATCH(L$1,SUBQH,0),0),"")
... A41: NPM | D41: NPM | E41: =IFERROR(VLOOKUP($A41,subQ,MATCH(E$1,SUBQH,0),0),"") | F41: =IFERROR(VLOOKUP($A41,subQ,MATCH(F$1,SUBQH,0),0),"") | G41: =IFERROR(VLOOKUP($A41,subQ,MATCH(G$1,SUBQH,0),0),"") | H41: =IFERROR(VLOOKUP($A41,subQ,MATCH(H$1,SUBQH,0),0),"") | I41: =IFERROR(VLOOKUP($A41,subQ,MATCH(I$1,SUBQH,0),0),"") | J41: =IFERROR(VLOOKUP($A41,subQ,MATCH(J$1,SUBQH,0),0),"") | K41: =IFERROR(VLOOKUP($A41,subQ,MATCH(K$1,SUBQH,0),0),"") | L41: =IFERROR(VLOOKUP($A41,subQ,MATCH(L$1,SUBQH,0),0),"")
A42: 매출액 YoY | D42: 매출액 YoY | F42: =IFERROR(F5/E5-1,"") | G42: =IFERROR(G5/F5-1,"") | H42: =IFERROR(H5/G5-1,"") | I42: =IFERROR(I5/H5-1,"") | J42: =IFERROR(J5/I5-1,"") | K42: =IFERROR(K5/J5-1,"") | L42: =IFERROR(L5/K5-1,"")
A43: 영업이익 YoY | D43: 영업이익 YoY | F43: =IFERROR(F9/E9-1,"") | G43: =IFERROR(G9/F9-1,"") | H43: =IFERROR(H9/G9-1,"") | I43: =IFERROR(I9/H9-1,"") | J43: =IFERROR(J9/I9-1,"") | K43: =IFERROR(K9/J9-1,"") | L43: =IFERROR(L9/K9-1,"")
A44: 지배주주순이익 YoY | D44: 지배주주순이익 YoY | F44: =IFERROR(F18/E18-1,"") | G44: =IFERROR(G18/F18-1,"") | H44: =IFERROR(H18/G18-1,"") | I44: =IFERROR(I18/H18-1,"") | J44: =IFERROR(J18/I18-1,"") | K44: =IFERROR(K18/J18-1,"") | L44: =IFERROR(L18/K18-1,"")

Sheet TP
B1: 종가 | C1: =변수!D43
B2: 기준일 | C2: =변수!D44
B3: 모델 산출값 — 목표주가·추천 아님. 밴드·COE 는 변수 시트 3절의 가정
C5: FY | D5: 2025 | E5: 2026 | F5: 2027 | G5: 2028
D6: A | E6: E | F6: E | G6: E
C7: EPS(원) | D7: =IFERROR(VLOOKUP("EPS",subQ,MATCH(D$5,SUBQH,0),0),"") | E7: =IFERROR(VLOOKUP("EPS",subQ,MATCH(E$5,SUBQH,0),0),"") | F7: =IFERROR(VLOOKUP("EPS",subQ,MATCH(F$5,SUBQH,0),0),"") | G7: =IFERROR(VLOOKUP("EPS",subQ,MATCH(G$5,SUBQH,0),0),"")
C8: BPS(원) | D8: =IFERROR(VLOOKUP("BPS",subQ,MATCH(D$5,SUBQH,0),0),"") | E8: =IFERROR(VLOOKUP("BPS",subQ,MATCH(E$5,SUBQH,0),0),"") | F8: =IFERROR(VLOOKUP("BPS",subQ,MATCH(F$5,SUBQH,0),0),"") | G8: =IFERROR(VLOOKUP("BPS",subQ,MATCH(G$5,SUBQH,0),0),"")
C9: 지배주주순이익(억원) | D9: =IFERROR(VLOOKUP("지배주주순이익",subQ,MATCH(D$5,SUBQH,0),0),"") | E9: =IFERROR(VLOOKUP("지배주주순이익",subQ,MATCH(E$5,SUBQH,0),0),"") | F9: =IFERROR(VLOOKUP("지배주주순이익",subQ,MATCH(F$5,SUBQH,0),0),"") | G9: =IFERROR(VLOOKUP("지배주주순이익",subQ,MATCH(G$5,SUBQH,0),0),"")
C10: 영업이익(억원) | D10: =IFERROR(VLOOKUP("영업이익",subQ,MATCH(D$5,SUBQH,0),0),"") | E10: =IFERROR(VLOOKUP("영업이익",subQ,MATCH(E$5,SUBQH,0),0),"") | F10: =IFERROR(VLOOKUP("영업이익",subQ,MATCH(F$5,SUBQH,0),0),"") | G10: =IFERROR(VLOOKUP("영업이익",subQ,MATCH(G$5,SUBQH,0),0),"")
C11: ROE(EPS/기초BPS) | E11: =IFERROR(E7/D8,"") | F11: =IFERROR(F7/E8,"") | G11: =IFERROR(G7/F8,"")
B13: PER
C14: 12M fwd EPS | D14: =IFERROR(E7*변수!D49+F7*(1-변수!D49),"")
C15: 적정가치 @PER_lo | D15: =변수!D46 | E15: =IFERROR(ROUND($D$14*D15,-2),"") | F15: =IFERROR(E15/$C$1-1,"") | G15: 배 · 원 · 종가 대비
C16: 적정가치 @PER_mid | D16: =변수!D47 | E16: =IFERROR(ROUND($D$14*D16,-2),"") | F16: =IFERROR(E16/$C$1-1,"") | G16: 배 · 원 · 종가 대비
C17: 적정가치 @PER_hi | D17: =변수!D48 | E17: =IFERROR(ROUND($D$14*D17,-2),"") | F17: =IFERROR(E17/$C$1-1,"") | G17: 배 · 원 · 종가 대비
C18: 현재 PER(종가/12M fwd EPS) | D18: =IFERROR($C$1/$D$14,"")
B20: PBR
C21: 최근 BPS(마지막 실적 분기) | D21: =IFERROR(VLOOKUP("BPS",subQ,MATCH("2Q26",SUBQH,0),0),"")
C22: ROE fwd(12M fwd EPS / BPS) | D22: =IFERROR($D$14/$D$21,"")
C23: COE | D23: =변수!D45
C24: 적정 PBR = ROE/COE | D24: =IFERROR(D22/D23,"")
C25: 적정가치(PBR) = BPS × 적정PBR | D25: =IFERROR(ROUND(D21*D24,-2),"") | E25: =IFERROR(D25/$C$1-1,"")
C26: 현재 PBR(종가/BPS) | D26: =IFERROR($C$1/D21,"")
B28: 모델 json valuation(참고)
C29: eps_fwd12m | D29: 163.3
C30: bps_latest | D30: 13299.6
C31: per_now | D31: 24.59
C32: pbr_now | D32: 0.3
C33: roe_fwd | D33: 0.0123
C34: fair_pbr | D34: 0.14
C35: fair_value_pbr | D35: 1900
C36: ev_ebitda | D36: 6.69
C37: note | D37: 모델 산출값 — 목표주가·추천 아님

Sheet 외화
C1: 이름: 외화QH — 환율 QoQ · 외화 순노출 × Δ기말환율 | E1: 4Q21 | F1: 1Q22 | G1: 2Q22 | H1: 3Q22 | I1: 4Q22 | J1: 1Q23 | K1: 2Q23 | L1: 3Q23 | M1: 4Q23 | N1: 1Q24 | O1: 2Q24 | P1: 3Q24 | Q1: 4Q24 | R1: 1Q25 | S1: 2Q25 | T1: 3Q25 | U1: 4Q25 | V1: 1Q26 | W1: 2Q26 | X1: 3Q26 | Y1: 4Q26 | Z1: 1Q27 | AA1: 2Q27 | AB1: 3Q27 | AC1: 4Q27 | AD1: 1Q28 | AE1: 2Q28 | AF1: 3Q28 | AG1: 4Q28
E3: 1 | F3: 2 | G3: 3 | H3: 4 | I3: 5 | J3: 6 | K3: 7 | L3: 8 | M3: 9 | N3: 10 | O3: 11 | P3: 12 | Q3: 13 | R3: 14 | S3: 15 | T3: 16 | U3: 17 | V3: 18 | W3: 19 | X3: 20 | Y3: 21 | Z3: 22 | AA3: 23 | AB3: 24 | AC3: 25 | AD3: 26 | AE3: 27 | AF3: 28 | AG3: 29
E4: 2021.12 | F4: 2022.03 | G4: 2022.06 | H4: 2022.09 | I4: 2022.12 | J4: 2023.03 | K4: 2023.06 | L4: 2023.09 | M4: 2023.12 | N4: 2024.03 | O4: 2024.06 | P4: 2024.09 | Q4: 2024.12 | R4: 2025.03 | S4: 2025.06 | T4: 2025.09 | U4: 2025.12 | V4: 2026.03 | W4: 2026.06 | X4: 2026.09 | Y4: 2026.12 | Z4: 2027.03 | AA4: 2027.06 | AB4: 2027.09 | AC4: 2027.12 | AD4: 2028.03 | AE4: 2028.06 | AF4: 2028.09 | AG4: 2028.12
D5: 원/달러(평균) | E5: =IFERROR(VLOOKUP($D5,환율,MATCH(E$1,변수H,0),0),"") | F5: =IFERROR(VLOOKUP($D5,환율,MATCH(F$1,변수H,0),0),"") | G5: =IFERROR(VLOOKUP($D5,환율,MATCH(G$1,변수H,0),0),"") | H5: =IFERROR(VLOOKUP($D5,환율,MATCH(H$1,변수H,0),0),"") | I5: =IFERROR(VLOOKUP($D5,환율,MATCH(I$1,변수H,0),0),"") | J5: =IFERROR(VLOOKUP($D5,환율,MATCH(J$1,변수H,0),0),"") | K5: =IFERROR(VLOOKUP($D5,환율,MATCH(K$1,변수H,0),0),"") | L5: =IFERROR(VLOOKUP($D5,환율,MATCH(L$1,변수H,0),0),"") | ... AG5: =IFERROR(VLOOKUP($D5,환율,MATCH(AG$1,변수H,0),0),"")
A6: 원/달러(평균) QoQ | F6: =IFERROR(F5/E5-1,"") | G6: =IFERROR(G5/F5-1,"") | H6: =IFERROR(H5/G5-1,"") | I6: =IFERROR(I5/H5-1,"") | J6: =IFERROR(J5/I5-1,"") | K6: =IFERROR(K5/J5-1,"") | L6: =IFERROR(L5/K5-1,"") | M6: =IFERROR(M5/L5-1,"") | ... AG6: =IFERROR(AG5/AF5-1,"")
D7: 원/달러(기말) | E7: =IFERROR(VLOOKUP($D7,환율,MATCH(E$1,변수H,0),0),"") | F7: =IFERROR(VLOOKUP($D7,환율,MATCH(F$1,변수H,0),0),"") | G7: =IFERROR(VLOOKUP($D7,환율,MATCH(G$1,변수H,0),0),"") | H7: =IFERROR(VLOOKUP($D7,환율,MATCH(H$1,변수H,0),0),"") | I7: =IFERROR(VLOOKUP($D7,환율,MATCH(I$1,변수H,0),0),"") | J7: =IFERROR(VLOOKUP($D7,환율,MATCH(J$1,변수H,0),0),"") | K7: =IFERROR(VLOOKUP($D7,환율,MATCH(K$1,변수H,0),0),"") | L7: =IFERROR(VLOOKUP($D7,환율,MATCH(L$1,변수H,0),0),"") | ... AG7: =IFERROR(VLOOKUP($D7,환율,MATCH(AG$1,변수H,0),0),"")
A8: 원/달러(기말) QoQ | F8: =IFERROR(F7/E7-1,"") | G8: =IFERROR(G7/F7-1,"") | H8: =IFERROR(H7/G7-1,"") | I8: =IFERROR(I7/H7-1,"") | J8: =IFERROR(J7/I7-1,"") | K8: =IFERROR(K7/J7-1,"") | L8: =IFERROR(L7/K7-1,"") | M8: =IFERROR(M7/L7-1,"") | ... AG8: =IFERROR(AG7/AF7-1,"")
D9: W/Euro(평균) | E9: =IFERROR(VLOOKUP($D9,환율,MATCH(E$1,변수H,0),0),"") | F9: =IFERROR(VLOOKUP($D9,환율,MATCH(F$1,변수H,0),0),"") | G9: =IFERROR(VLOOKUP($D9,환율,MATCH(G$1,변수H,0),0),"") | H9: =IFERROR(VLOOKUP($D9,환율,MATCH(H$1,변수H,0),0),"") | I9: =IFERROR(VLOOKUP($D9,환율,MATCH(I$1,변수H,0),0),"") | J9: =IFERROR(VLOOKUP($D9,환율,MATCH(J$1,변수H,0),0),"") | K9: =IFERROR(VLOOKUP($D9,환율,MATCH(K$1,변수H,0),0),"") | L9: =IFERROR(VLOOKUP($D9,환율,MATCH(L$1,변수H,0),0),"") | ... AG9: =IFERROR(VLOOKUP($D9,환율,MATCH(AG$1,변수H,0),0),"")
A10: W/Euro(평균) QoQ | F10: =IFERROR(F9/E9-1,"") | G10: =IFERROR(G9/F9-1,"") | H10: =IFERROR(H9/G9-1,"") | I10: =IFERROR(I9/H9-1,"") | J10: =IFERROR(J9/I9-1,"") | K10: =IFERROR(K9/J9-1,"") | L10: =IFERROR(L9/K9-1,"") | M10: =IFERROR(M9/L9-1,"") | ... AG10: =IFERROR(AG9/AF9-1,"")
D11: W/Euro(기말) | E11: =IFERROR(VLOOKUP($D11,환율,MATCH(E$1,변수H,0),0),"") | F11: =IFERROR(VLOOKUP($D11,환율,MATCH(F$1,변수H,0),0),"") | G11: =IFERROR(VLOOKUP($D11,환율,MATCH(G$1,변수H,0),0),"") | H11: =IFERROR(VLOOKUP($D11,환율,MATCH(H$1,변수H,0),0),"") | I11: =IFERROR(VLOOKUP($D11,환율,MATCH(I$1,변수H,0),0),"") | J11: =IFERROR(VLOOKUP($D11,환율,MATCH(J$1,변수H,0),0),"") | K11: =IFERROR(VLOOKUP($D11,환율,MATCH(K$1,변수H,0),0),"") | L11: =IFERROR(VLOOKUP($D11,환율,MATCH(L$1,변수H,0),0),"") | ... AG11: =IFERROR(VLOOKUP($D11,환율,MATCH(AG$1,변수H,0),0),"")
A12: W/Euro(기말) QoQ | F12: =IFERROR(F11/E11-1,"") | G12: =IFERROR(G11/F11-1,"") | H12: =IFERROR(H11/G11-1,"") | I12: =IFERROR(I11/H11-1,"") | J12: =IFERROR(J11/I11-1,"") | K12: =IFERROR(K11/J11-1,"") | L12: =IFERROR(L11/K11-1,"") | M12: =IFERROR(M11/L11-1,"") | ... AG12: =IFERROR(AG11/AF11-1,"")
D13: 원/100Y(기말) | E13: =IFERROR(VLOOKUP($D13,환율,MATCH(E$1,변수H,0),0),"") | F13: =IFERROR(VLOOKUP($D13,환율,MATCH(F$1,변수H,0),0),"") | G13: =IFERROR(VLOOKUP($D13,환율,MATCH(G$1,변수H,0),0),"") | H13: =IFERROR(VLOOKUP($D13,환율,MATCH(H$1,변수H,0),0),"") | I13: =IFERROR(VLOOKUP($D13,환율,MATCH(I$1,변수H,0),0),"") | J13: =IFERROR(VLOOKUP($D13,환율,MATCH(J$1,변수H,0),0),"") | K13: =IFERROR(VLOOKUP($D13,환율,MATCH(K$1,변수H,0),0),"") | L13: =IFERROR(VLOOKUP($D13,환율,MATCH(L$1,변수H,0),0),"") | ... AG13: =IFERROR(VLOOKUP($D13,환율,MATCH(AG$1,변수H,0),0),"")
A14: 원/100Y(기말) QoQ | F14: =IFERROR(F13/E13-1,"") | G14: =IFERROR(G13/F13-1,"") | H14: =IFERROR(H13/G13-1,"") | I14: =IFERROR(I13/H13-1,"") | J14: =IFERROR(J13/I13-1,"") | K14: =IFERROR(K13/J13-1,"") | L14: =IFERROR(L13/K13-1,"") | M14: =IFERROR(M13/L13-1,"") | ... AG14: =IFERROR(AG13/AF13-1,"")
A16: 외화순노출 | C16: 외화 순노출(백만$) | D16: =변수!D56 | E16: 외화 순노출 × Δ기말환율 (외화 시트 방식)
A17: 환관련손익추정 | C17: 환관련손익 추정(억원) = 순노출 × Δ원/달러(기말) / 100 | F17: =IFERROR($D$16*(F7-E7)/100,"") | G17: =IFERROR($D$16*(G7-F7)/100,"") | H17: =IFERROR($D$16*(H7-G7)/100,"") | I17: =IFERROR($D$16*(I7-H7)/100,"") | J17: =IFERROR($D$16*(J7-I7)/100,"") | K17: =IFERROR($D$16*(K7-J7)/100,"") | L17: =IFERROR($D$16*(L7-K7)/100,"") | M17: =IFERROR($D$16*(M7-L7)/100,"") | ... AG17: =IFERROR($D$16*(AG7-AF7)/100,"")
A18: fx_pnl.by_q | C18: 모델 fx_pnl.by_q(억원, 참고)
C19: 외화 순노출 미공시(face) → 0 + 표기
