Workbook
Name 변수H: 변수!$C$1:$AO$1
Name 환율: 변수!$C$6:$AO$13
Name BS연결H: BS연결!$C$1:$AO$1
Name BS연결: BS연결!$C$5:$AO$113
Name BS별도H: BS별도!$C$1:$AO$1
Name BS별도: BS별도!$C$5:$AO$99
Name SUBQH: subQ!$A$1:$AO$1
Name subQ: subQ!$A$5:$AO$44

Sheet README
A1: 한국카본(017960) 실적 모델 — ARGUS 한국조선
A2: 기준 분기 2026Q2 · 마지막 실적 2026Q2 · 생성 2026-10-11
A3: 모든 수치는 모델 산출값(DART 공개 재무제표 + 우리 추정)이다 — 목표주가·투자 추천 아님. 참고용 · 투자조언 아님.
A5: 시트
A6: 변수 가정 시계열. 환율 8행(ECB via frankfurter — L2 fx.json; 추정 분기 = 노란 가정), 추정 드라이버(노란 셀 = 모델값에서 역산한 가정, 바꾸면 재계산; 연녹 셀 = 3절 스칼라 참조 수식), 3절 스칼라 가정(세율·판관비율·지배주주비중·이자율·종가·PER 밴드·COE·외화 순노출·헤지비율)
A7: BS연결/BS별도 FnGuide 계정명 × 기간 값 덤프(백만원). 행1 분기라벨, 행4 YYYY.MM / YYYY.12A. 이름정의 BS연결H·BS연결(계정명 C열부터)
A8: subQ 분기 서브모델(억원 = 백만원/100). 확정 행: =IFERROR(VLOOKUP($D행,BS연결,MATCH(E$1,BS연결H,0),0)/100,"") 추정 행: 변수 시트 가정 셀 참조 수식. 외환손익·파생상품손익은 BS 계정 합·차, 기타금융손익은 잔차, OPM·EPS·BPS·PER·PBR 은 파생 수식
A9: SLS 선표(조선사만, sls json 있을 때): 요약 행(sls 저장값) + 계약별 스케줄(백만$) × (헤지비율 × 헤지환율 + (1−헤지비율) × 건조시점 환율[변수 원/달러(평균)]) → 원화 수식 블록 → 합계 행이 subQ 매출조선에 연결
A10: 시나리오 신규수주 보수/기준/낙관(forecast_panel 패널, 모델에 scenarios 가 있을 때만): 매출액·영업이익 = subQ 기준값 ± (시나리오 신규 − base 신규) × OPM. base 만 subQ 행에 포함, 나머지는 합산 안 함
A11: 분기/연간예상 subQ 를 이름(A열 key)으로 VLOOKUP 한 보고서 표(억원)
A12: TP PER 밴드 × 12M fwd EPS, PBR = ROE/COE × BPS — 모델 산출값 구간, 목표주가·추천 아님
A13: 외화 환율 QoQ, 외화 순노출 × Δ기말환율 → 환관련손익 추정
... A34: 백테스트: {"freeze": "2025Q2", "horizon": 4, "revenue_wape_pct": 11.1, "op_wape_pct": 63.7, "n": 4, "note": "단일 회사 4분기 — 통계 아님", "driver_at_freeze": "customer_yard_revenue_weighted", "selection_oos_at_freeze": {"freeze": "2024Q2", "n": 4, "wape_link": 27.5, "wape_trend": 34.3, "adopted": true, "decision": "adopted"}, "frozen_inputs": "fin(연결/별도)·고객 조선사 모델·지주 자회사 모델은 2025Q2 까지의 분기만; 선표는 체결일 ≤ 2025Q2 말일 계약(원장 최신 금액·코호트 등급, 환산 없음); 잔고는 yards_cache 2025Q2; 시세·환율 forward·prices·forecast_panel 신규수주 미사용. 고객 가중치(suppliers.json 언급 비중)와 합병 체인링크는 현재 지식; 고객 연동 채택은 동결 모델 안에서도 자기 la−4분기 OOS 규칙(selection_oos_at_freeze)", "detail": [{"q": "2025Q3", "rev_pred": 2265.3, "rev_act": 2211.32, "op_pred": 152.37, "op_act": 298.63}, {"q": "2025Q4", "rev_pred": 2533.53, "rev_act": 2318.43, "op_pred": 170.41, "op_act": 383.37}, {"q": "2026Q1", "rev_pred": 1831.63, "rev_act": 2118.22, "op_pred": 123.2, "op_act": 410.66}, {"q": "2026Q2", "rev_pred": 1982.74, "rev_act": 2433.78, "op_pred": 133.36, "op_act": 504.0}]}

Sheet 변수
C1: 이름: 변수H | E1: 4Q21 | F1: 2021 | G1: 1Q22 | H1: 2Q22 | I1: 3Q22 | J1: 4Q22 | K1: 2022 | L1: 1Q23 | M1: 2Q23 | N1: 3Q23 | O1: 4Q23 | P1: 2023 | Q1: 1Q24 | R1: 2Q24 | S1: 3Q24 | T1: 4Q24 | U1: 2024 | V1: 1Q25 | W1: 2Q25 | X1: 3Q25 | Y1: 4Q25 | Z1: 2025 | AA1: 1Q26 | AB1: 2Q26 | AC1: 3Q26 | AD1: 4Q26 | AE1: 2026 | AF1: 1Q27 | AG1: 2Q27 | AH1: 3Q27 | AI1: 4Q27 | AJ1: 2027 | AK1: 1Q28 | AL1: 2Q28 | AM1: 3Q28 | AN1: 4Q28 | AO1: 2028
A2: 가정 시계열 — 노란 셀은 추정 가정(모델값에서 역산), 연녹 셀은 3절 스칼라 참조 수식. 바꾸면 subQ·분기·연간예상·TP·시나리오가 재계산됩니다.
E3: 1 | F3: 2 | G3: 3 | H3: 4 | I3: 5 | J3: 6 | K3: 7 | L3: 8 | M3: 9 | N3: 10 | O3: 11 | P3: 12 | Q3: 13 | R3: 14 | S3: 15 | T3: 16 | U3: 17 | V3: 18 | W3: 19 | X3: 20 | Y3: 21 | Z3: 22 | AA3: 23 | AB3: 24 | AC3: 25 | AD3: 26 | AE3: 27 | AF3: 28 | AG3: 29 | AH3: 30 | AI3: 31 | AJ3: 32 | AK3: 33 | AL3: 34 | AM3: 35 | AN3: 36 | AO3: 37
E4: 2021.12 | F4: 2021.12A | G4: 2022.03 | H4: 2022.06 | I4: 2022.09 | J4: 2022.12 | K4: 2022.12A | L4: 2023.03 | M4: 2023.06 | N4: 2023.09 | O4: 2023.12 | P4: 2023.12A | Q4: 2024.03 | R4: 2024.06 | S4: 2024.09 | T4: 2024.12 | U4: 2024.12A | V4: 2025.03 | W4: 2025.06 | X4: 2025.09 | Y4: 2025.12 | Z4: 2025.12A | AA4: 2026.03 | AB4: 2026.06 | AC4: 2026.09 | AD4: 2026.12 | AE4: 2026.12A | AF4: 2027.03 | AG4: 2027.06 | AH4: 2027.09 | AI4: 2027.12 | AJ4: 2027.12A | AK4: 2028.03 | AL4: 2028.06 | AM4: 2028.09 | AN4: 2028.12 | AO4: 2028.12A
B5: 1. FX | C5: 이름: 환율
A6: USDKRW_avg | C6: 원/달러(평균) | E6: 1183.5 | F6: 1145.51 | G6: 1205.78 | H6: 1262.09 | I6: 1341.93 | J6: 1360.12 | K6: 1292.98 | L6: 1276.95 | M6: 1315.69 | N6: 1313.62 | O6: 1322.01 | P6: 1306.85 | Q6: 1330.14 | R6: 1371.28 | S6: 1356.22 | T6: 1396.3 | U6: 1363.53 | V6: 1452.28 | W6: 1398.52 | X6: 1386.95 | Y6: 1449.19 | Z6: 1421.52 | AA6: 1466.12 | AB6: 1501.75 | AC6: 1418.75 | AD6: 1345.14 | AE6: 1457.21 | AF6: 1341.49 | AG6: 1341.49 | AH6: 1341.49 | AI6: 1341.49 | AK6: 1341.49 | AL6: 1341.49 | AM6: 1341.49 | AN6: 1341.49
A7: USDKRW_end | C7: 원/달러(기말) | E7: 1188.75 | F7: 1188.75 | G7: 1213.74 | H7: 1301.24 | I7: 1436.9 | J7: 1260.16 | K7: 1260.16 | L7: 1305.99 | M7: 1321.44 | N7: 1345.35 | O7: 1297.43 | P7: 1297.43 | Q7: 1349.25 | R7: 1377.73 | S7: 1312.17 | T7: 1474.78 | U7: 1474.78 | V7: 1474.54 | W7: 1355.13 | X7: 1403.67 | Y7: 1444.2 | Z7: 1444.2 | AA7: 1524.8 | AB7: 1550.89 | AC7: 1355.4 | AD7: 1341.49 | AE7: 1341.49 | AF7: 1341.49 | AG7: 1341.49 | AH7: 1341.49 | AI7: 1341.49 | AK7: 1341.49 | AL7: 1341.49 | AM7: 1341.49 | AN7: 1341.49
A8: JPY100KRW_avg | C8: 원/100Y(평균) | E8: 1041.02 | F8: 1042.74 | G8: 1036.79 | H8: 972.23 | I8: 970.61 | J8: 961.03 | K8: 985.1 | L8: 964.89 | M8: 957.36 | N8: 909 | O8: 893.22 | P8: 931.11 | Q8: 896.29 | R8: 880.14 | S8: 909.35 | T8: 917.25 | U8: 900.92 | V8: 952.59 | W8: 967.92 | X8: 940.32 | Y8: 940.77 | Z8: 950.17 | AA8: 934.39 | AB8: 942.16 | AC8: 890.41 | AD8: 850.79 | AE8: 919.21 | AF8: 847.7 | AG8: 847.7 | AH8: 847.7 | AI8: 847.7 | AK8: 847.7 | AL8: 847.7 | AM8: 847.7 | AN8: 847.7
A9: JPY100KRW_end | C9: 원/100Y(기말) | E9: 1032.62 | F9: 1032.62 | G9: 996.83 | H9: 954.9 | I9: 993.29 | J9: 955.54 | K9: 955.54 | L9: 980.62 | M9: 913.67 | N9: 901.47 | O9: 917.04 | P9: 917.04 | Q9: 892.42 | R9: 857.76 | S9: 919.21 | T9: 939.65 | U9: 939.65 | V9: 986.84 | W9: 938.85 | X9: 948.49 | Y9: 921.81 | Z9: 921.81 | AA9: 955.99 | AB9: 954.75 | AC9: 863.31 | AD9: 847.7 | AE9: 847.7 | AF9: 847.7 | AG9: 847.7 | AH9: 847.7 | AI9: 847.7 | AK9: 847.7 | AL9: 847.7 | AM9: 847.7 | AN9: 847.7
A10: EURKRW_avg | C10: W/Euro(평균) | E10: 1353.32 | F10: 1354.06 | G10: 1352.29 | H10: 1343.31 | I10: 1350.63 | J10: 1386.07 | K10: 1358.07 | L10: 1369.93 | M10: 1432.41 | N10: 1429.41 | O10: 1420.91 | P10: 1412.88 | Q10: 1444.21 | R10: 1476.42 | S10: 1489.3 | T10: 1490.78 | U10: 1475.4 | V10: 1528.33 | W10: 1585.13 | X10: 1620.04 | Y10: 1686.02 | Z10: 1605.45 | AA10: 1715.47 | AB10: 1746.09 | AC10: 1631.97 | AD10: 1509.74 | AE10: 1689.95 | AF10: 1503.27 | AG10: 1503.27 | AH10: 1503.27 | AI10: 1503.27 | AK10: 1503.27 | AL10: 1503.27 | AM10: 1503.27 | AN10: 1503.27
A11: EURKRW_end | C11: W/Euro(기말) | E11: 1346.38 | F11: 1346.38 | G11: 1347.37 | H11: 1351.6 | I11: 1400.62 | J11: 1344.08 | K11: 1344.08 | L11: 1420.26 | M11: 1435.88 | N11: 1425.26 | O11: 1433.66 | P11: 1433.66 | Q11: 1458.68 | R11: 1474.86 | S11: 1469.1 | T11: 1532.14 | U11: 1532.14 | V11: 1594.72 | W11: 1588.22 | X11: 1648.04 | Y11: 1696.94 | Z11: 1696.94 | AA11: 1753.21 | AB11: 1767.09 | AC11: 1539.06 | AD11: 1503.27 | AE11: 1503.27 | AF11: 1503.27 | AG11: 1503.27 | AH11: 1503.27 | AI11: 1503.27 | AK11: 1503.27 | AL11: 1503.27 | AM11: 1503.27 | AN11: 1503.27
A12: CNYKRW_avg | C12: 원/중국원(평균) | E12: 185.14 | F12: 177.65 | G12: 189.93 | H12: 190.76 | I12: 195.79 | J12: 191.09 | K12: 191.93 | L12: 186.59 | M12: 187.45 | N12: 181.28 | O12: 182.86 | P12: 184.52 | Q12: 185.04 | R12: 189.35 | S12: 189.24 | T12: 194.24 | U12: 189.49 | V12: 199.63 | W12: 193.41 | X12: 193.79 | Y12: 204.38 | Z12: 197.8 | AA12: 211.75 | AB12: 220.8 | AC12: 210.43 | AD12: 200.69 | AE12: 213.75 | AF12: 200.46 | AG12: 200.46 | AH12: 200.46 | AI12: 200.46 | AK12: 200.46 | AL12: 200.46 | AM12: 200.46 | AN12: 200.46
A13: CNYKRW_end | C13: 원/중국원(기말) | E13: 187.13 | F13: 187.13 | G13: 191.38 | H13: 194.13 | I13: 201.92 | J13: 182.67 | K13: 182.67 | L13: 189.97 | M13: 181.8 | N13: 184.26 | O13: 182.61 | P13: 182.61 | Q13: 186.66 | R13: 189.7 | S13: 187.12 | T13: 202.04 | U13: 202.04 | V13: 203.3 | W13: 189.14 | X13: 197.16 | Y13: 206.28 | Z13: 206.28 | AA13: 220.97 | AB13: 228.56 | AC13: 202.16 | AD13: 200.46 | AE13: 200.46 | AF13: 200.46 | AG13: 200.46 | AH13: 200.46 | AI13: 200.46 | AK13: 200.46 | AL13: 200.46 | AM13: 200.46 | AN13: 200.46
B14: 1b. 종가
A15: price_close_end | C15: 종가(기말) | E15: 10750 | G15: 11750 | H15: 14600 | I15: 11900 | J15: 11050 | L15: 12280 | M15: 11650 | N15: 12550 | O15: 11640 | Q15: 10730 | R15: 10730 | S15: 10810 | T15: 11750 | V15: 13540 | W15: 26000 | X15: 32700 | Y15: 29850 | AA15: 38850 | AB15: 26700 | AC15: 20100 | AD15: 19260
A16: price_high | C16: 종가(최고) | E16: 13500 | G16: 12900 | H16: 15350 | I16: 16200 | J16: 12800 | L16: 12380 | M16: 12980 | N16: 15240 | O16: 12840 | Q16: 11760 | R16: 11940 | S16: 13350 | T16: 11930 | V16: 16930 | W16: 26850 | X16: 35850 | Y16: 39300 | AA16: 50800 | AB16: 54100 | AC16: 27950 | AD16: 21100
A17: price_low | C17: 종가(최저) | E17: 9100 | G17: 9950 | H17: 10750 | I17: 11450 | J17: 10450 | L17: 10300 | M17: 10820 | N17: 11540 | O17: 11000 | Q17: 9870 | R17: 10050 | S17: 10230 | T17: 9400 | V17: 11600 | W17: 13870 | X17: 22200 | Y17: 25800 | AA17: 27450 | AB17: 25050 | AC17: 18530 | AD17: 19150
A18: price_avg | C18: 종가(평균) | E18: 11223.7 | G18: 11368.1 | H18: 13100.8 | I18: 13811.9 | J18: 11543.5 | L18: 11282.3 | M18: 11674.8 | N18: 13436.3 | O18: 11875.5 | Q18: 10720 | R18: 10857 | S18: 11507.3 | T18: 10811.5 | V18: 14238.3 | W18: 20896.3 | X18: 29762.3 | Y18: 32022 | AA18: 38489 | AB18: 39775.4 | AC18: 22833.4 | AD18: 20212
B20: 2. 추정 드라이버 | C20: 실적 열 = subQ 실현값(수식), 추정 열 = 가정(노란 = 모델값 역산, 연녹 = 3절 스칼라 참조)
A21: drv:매출액 | B21: yoy | C21: 매출액 YoY | J21: =IFERROR(subQ!J5/subQ!E5-1,"") | L21: =IFERROR(subQ!L5/subQ!G5-1,"") | M21: =IFERROR(subQ!M5/subQ!H5-1,"") | N21: =IFERROR(subQ!N5/subQ!I5-1,"") | O21: =IFERROR(subQ!O5/subQ!J5-1,"") | Q21: =IFERROR(subQ!Q5/subQ!L5-1,"") | R21: =IFERROR(subQ!R5/subQ!M5-1,"") | S21: =IFERROR(subQ!S5/subQ!N5-1,"") | T21: =IFERROR(subQ!T5/subQ!O5-1,"") | V21: =IFERROR(subQ!V5/subQ!Q5-1,"") | W21: =IFERROR(subQ!W5/subQ!R5-1,"") | X21: =IFERROR(subQ!X5/subQ!S5-1,"") | Y21: =IFERROR(subQ!Y5/subQ!T5-1,"") | AA21: =IFERROR(subQ!AA5/subQ!V5-1,"") | AB21: =IFERROR(subQ!AB5/subQ!W5-1,"") | AC21: 0.20311785 | AD21: 0.44822143 | AF21: 0.30638744 | AG21: 0.32217969 | AH21: 0.20329038 | AI21: 0.14746247 | AK21: 0.13146454 | AL21: 0.14057659 | AM21: 0.17888503 | AN21: 0.16527804
A22: drv:판관비 | B22: ratio | C22: 판관비율(/매출) | E22: =IFERROR(subQ!E8/subQ!E5,"") | F22: =IFERROR(subQ!F8/subQ!F5,"") | G22: =IFERROR(subQ!G8/subQ!G5,"") | H22: =IFERROR(subQ!H8/subQ!H5,"") | I22: =IFERROR(subQ!I8/subQ!I5,"") | J22: =IFERROR(subQ!J8/subQ!J5,"") | K22: =IFERROR(subQ!K8/subQ!K5,"") | L22: =IFERROR(subQ!L8/subQ!L5,"") | ... AB22: =IFERROR(subQ!AB8/subQ!AB5,"") | AC22: =$D$53 | AD22: =$D$53 | AE22: =IFERROR(subQ!AE8/subQ!AE5,"") | AF22: =$D$53 | AG22: =$D$53 | AH22: =$D$53 | AI22: =$D$53 | AJ22: =IFERROR(subQ!AJ8/subQ!AJ5,"") | AK22: =$D$53 | AL22: =$D$53 | AM22: =$D$53 | AN22: =$D$53 | AO22: =IFERROR(subQ!AO8/subQ!AO5,"")
A23: drv:영업이익 | B23: ratio | C23: 영업이익률(OPM) | E23: =IFERROR(subQ!E9/subQ!E5,"") | F23: =IFERROR(subQ!F9/subQ!F5,"") | G23: =IFERROR(subQ!G9/subQ!G5,"") | H23: =IFERROR(subQ!H9/subQ!H5,"") | I23: =IFERROR(subQ!I9/subQ!I5,"") | J23: =IFERROR(subQ!J9/subQ!J5,"") | K23: =IFERROR(subQ!K9/subQ!K5,"") | L23: =IFERROR(subQ!L9/subQ!L5,"") | ... AB23: =IFERROR(subQ!AB9/subQ!AB5,"") | AC23: 0.1376744 | AD23: 0.13767274 | AE23: =IFERROR(subQ!AE9/subQ!AE5,"") | AF23: 0.13767296 | AG23: 0.13767407 | AH23: 0.13767403 | AI23: 0.13767416 | AJ23: =IFERROR(subQ!AJ9/subQ!AJ5,"") | AK23: 0.13767486 | AL23: 0.13767455 | AM23: 0.13767356 | AN23: 0.13767488 | AO23: =IFERROR(subQ!AO9/subQ!AO5,"")
A24: drv:외환손익 | B24: abs | C24: 외환손익 (가정, 억원) | E24: =subQ!E13 | F24: =subQ!F13 | G24: =subQ!G13 | H24: =subQ!H13 | I24: =subQ!I13 | J24: =subQ!J13 | K24: =subQ!K13 | L24: =subQ!L13 | ... AB24: =subQ!AB13 | AC24: 0 | AD24: 0 | AE24: =subQ!AE13 | AF24: 0 | AG24: 0 | AH24: 0 | AI24: 0 | AJ24: =subQ!AJ13 | AK24: 0 | AL24: 0 | AM24: 0 | AN24: 0 | AO24: =subQ!AO13
A25: drv:파생상품손익 | B25: abs | C25: 파생상품손익 (가정, 억원) | E25: =subQ!E14 | F25: =subQ!F14 | G25: =subQ!G14 | H25: =subQ!H14 | I25: =subQ!I14 | J25: =subQ!J14 | K25: =subQ!K14 | L25: =subQ!L14 | ... AB25: =subQ!AB14 | AC25: 0 | AD25: 0 | AE25: =subQ!AE14 | AF25: 0 | AG25: 0 | AH25: 0 | AI25: 0 | AJ25: =subQ!AJ14 | AK25: 0 | AL25: 0 | AM25: 0 | AN25: 0 | AO25: =subQ!AO14
A26: drv:기타금융손익 | B26: abs | C26: 기타금융손익 (가정, 억원) | E26: =subQ!E15 | F26: =subQ!F15 | G26: =subQ!G15 | H26: =subQ!H15 | I26: =subQ!I15 | J26: =subQ!J15 | K26: =subQ!K15 | L26: =subQ!L15 | ... AB26: =subQ!AB15 | AC26: 0 | AD26: 0 | AE26: =subQ!AE15 | AF26: 0 | AG26: 0 | AH26: 0 | AI26: 0 | AJ26: =subQ!AJ15 | AK26: 0 | AL26: 0 | AM26: 0 | AN26: 0 | AO26: =subQ!AO15
A27: drv:기타영업외손익 | B27: abs | C27: 기타영업외손익 (가정, 억원) | E27: =subQ!E16 | F27: =subQ!F16 | G27: =subQ!G16 | H27: =subQ!H16 | I27: =subQ!I16 | J27: =subQ!J16 | K27: =subQ!K16 | L27: =subQ!L16 | ... AB27: =subQ!AB16 | AC27: 0 | AD27: 0 | AE27: =subQ!AE16 | AF27: 0 | AG27: 0 | AH27: 0 | AI27: 0 | AJ27: =subQ!AJ16 | AK27: 0 | AL27: 0 | AM27: 0 | AN27: 0 | AO27: =subQ!AO16
A28: drv:지분법손익 | B28: abs | C28: 지분법손익 (가정, 억원) | E28: =subQ!E17 | F28: =subQ!F17 | G28: =subQ!G17 | H28: =subQ!H17 | I28: =subQ!I17 | J28: =subQ!J17 | K28: =subQ!K17 | L28: =subQ!L17 | ... AB28: =subQ!AB17 | AC28: 0.13 | AD28: 0.13 | AE28: =subQ!AE17 | AF28: 0.13 | AG28: 0.13 | AH28: 0.13 | AI28: 0.13 | AJ28: =subQ!AJ17 | AK28: 0.13 | AL28: 0.13 | AM28: 0.13 | AN28: 0.13 | AO28: =subQ!AO17
A29: drv:법인세비용 | B29: tax | C29: 법인세율(/세전) — 법인세 = MAX(세전,0) × 세율 | E29: =IFERROR(subQ!E19/subQ!E18,"") | F29: =IFERROR(subQ!F19/subQ!F18,"") | G29: =IFERROR(subQ!G19/subQ!G18,"") | H29: =IFERROR(subQ!H19/subQ!H18,"") | I29: =IFERROR(subQ!I19/subQ!I18,"") | J29: =IFERROR(subQ!J19/subQ!J18,"") | K29: =IFERROR(subQ!K19/subQ!K18,"") | L29: =IFERROR(subQ!L19/subQ!L18,"") | ... AB29: =IFERROR(subQ!AB19/subQ!AB18,"") | AC29: =$D$52 | AD29: =$D$52 | AE29: =IFERROR(subQ!AE19/subQ!AE18,"") | AF29: =$D$52 | AG29: =$D$52 | AH29: =$D$52 | AI29: =$D$52 | AJ29: =IFERROR(subQ!AJ19/subQ!AJ18,"") | AK29: =$D$52 | AL29: =$D$52 | AM29: =$D$52 | AN29: =$D$52 | AO29: =IFERROR(subQ!AO19/subQ!AO18,"")
A30: drv:지배주주순이익 | B30: ratio | C30: 지배주주 비중(/당기순이익) | E30: =IFERROR(subQ!E21/subQ!E20,"") | F30: =IFERROR(subQ!F21/subQ!F20,"") | G30: =IFERROR(subQ!G21/subQ!G20,"") | H30: =IFERROR(subQ!H21/subQ!H20,"") | I30: =IFERROR(subQ!I21/subQ!I20,"") | J30: =IFERROR(subQ!J21/subQ!J20,"") | K30: =IFERROR(subQ!K21/subQ!K20,"") | L30: =IFERROR(subQ!L21/subQ!L20,"") | ... AB30: =IFERROR(subQ!AB21/subQ!AB20,"") | AC30: =$D$54 | AD30: =$D$54 | AE30: =IFERROR(subQ!AE21/subQ!AE20,"") | AF30: =$D$54 | AG30: =$D$54 | AH30: =$D$54 | AI30: =$D$54 | AJ30: =IFERROR(subQ!AJ21/subQ!AJ20,"") | AK30: =$D$54 | AL30: =$D$54 | AM30: =$D$54 | AN30: =$D$54 | AO30: =IFERROR(subQ!AO21/subQ!AO20,"")
A31: drv:중단사업이익 | B31: abs | C31: 중단사업이익 (가정, 억원) | E31: =subQ!E22 | F31: =subQ!F22 | G31: =subQ!G22 | H31: =subQ!H22 | I31: =subQ!I22 | J31: =subQ!J22 | K31: =subQ!K22 | L31: =subQ!L22 | ... AB31: =subQ!AB22 | AE31: =subQ!AE22 | AJ31: =subQ!AJ22 | AO31: =subQ!AO22
A32: drv:부채총계 | B32: qoq | C32: 부채총계 QoQ | G32: =IFERROR(subQ!G24/subQ!E24-1,"") | H32: =IFERROR(subQ!H24/subQ!G24-1,"") | I32: =IFERROR(subQ!I24/subQ!H24-1,"") | J32: =IFERROR(subQ!J24/subQ!I24-1,"") | L32: =IFERROR(subQ!L24/subQ!J24-1,"") | M32: =IFERROR(subQ!M24/subQ!L24-1,"") | N32: =IFERROR(subQ!N24/subQ!M24-1,"") | O32: =IFERROR(subQ!O24/subQ!N24-1,"") | Q32: =IFERROR(subQ!Q24/subQ!O24-1,"") | R32: =IFERROR(subQ!R24/subQ!Q24-1,"") | S32: =IFERROR(subQ!S24/subQ!R24-1,"") | T32: =IFERROR(subQ!T24/subQ!S24-1,"") | V32: =IFERROR(subQ!V24/subQ!T24-1,"") | W32: =IFERROR(subQ!W24/subQ!V24-1,"") | X32: =IFERROR(subQ!X24/subQ!W24-1,"") | Y32: =IFERROR(subQ!Y24/subQ!X24-1,"") | AA32: =IFERROR(subQ!AA24/subQ!Y24-1,"") | AB32: =IFERROR(subQ!AB24/subQ!AA24-1,"") | AC32: -1.29e-07 | AD32: 0 | AF32: 0 | AG32: 0 | AH32: 0 | AI32: 0 | AK32: 0 | AL32: 0 | AM32: 0 | AN32: 0
A33: drv:자본총계 | B33: roll | C33: 자본총계 기타변동(배당 등, 억원) | G33: =IFERROR(subQ!E25+subQ!G20-subQ!G25,"") | H33: =IFERROR(subQ!G25+subQ!H20-subQ!H25,"") | I33: =IFERROR(subQ!H25+subQ!I20-subQ!I25,"") | J33: =IFERROR(subQ!I25+subQ!J20-subQ!J25,"") | L33: =IFERROR(subQ!J25+subQ!L20-subQ!L25,"") | M33: =IFERROR(subQ!L25+subQ!M20-subQ!M25,"") | N33: =IFERROR(subQ!M25+subQ!N20-subQ!N25,"") | O33: =IFERROR(subQ!N25+subQ!O20-subQ!O25,"") | Q33: =IFERROR(subQ!O25+subQ!Q20-subQ!Q25,"") | R33: =IFERROR(subQ!Q25+subQ!R20-subQ!R25,"") | S33: =IFERROR(subQ!R25+subQ!S20-subQ!S25,"") | T33: =IFERROR(subQ!S25+subQ!T20-subQ!T25,"") | V33: =IFERROR(subQ!T25+subQ!V20-subQ!V25,"") | W33: =IFERROR(subQ!V25+subQ!W20-subQ!W25,"") | X33: =IFERROR(subQ!W25+subQ!X20-subQ!X25,"") | Y33: =IFERROR(subQ!X25+subQ!Y20-subQ!Y25,"") | AA33: =IFERROR(subQ!Y25+subQ!AA20-subQ!AA25,"") | AB33: =IFERROR(subQ!AA25+subQ!AB20-subQ!AB25,"") | AC33: -0.004330132 | AD33: 0.001043259 | AF33: -0.001711291 | AG33: 165.36151 | AH33: 0.004605395 | AI33: -0.006652731 | AK33: 0.002243721 | AL33: 165.36435 | AM33: 0.007007229 | AN33: -0.004456199
A34: drv:지배주주지분 | B34: roll | C34: 지배주주지분 기타변동(배당 등, 억원) | G34: =IFERROR(subQ!E26+subQ!G21-subQ!G26,"") | H34: =IFERROR(subQ!G26+subQ!H21-subQ!H26,"") | I34: =IFERROR(subQ!H26+subQ!I21-subQ!I26,"") | J34: =IFERROR(subQ!I26+subQ!J21-subQ!J26,"") | L34: =IFERROR(subQ!J26+subQ!L21-subQ!L26,"") | M34: =IFERROR(subQ!L26+subQ!M21-subQ!M26,"") | N34: =IFERROR(subQ!M26+subQ!N21-subQ!N26,"") | O34: =IFERROR(subQ!N26+subQ!O21-subQ!O26,"") | Q34: =IFERROR(subQ!O26+subQ!Q21-subQ!Q26,"") | R34: =IFERROR(subQ!Q26+subQ!R21-subQ!R26,"") | S34: =IFERROR(subQ!R26+subQ!S21-subQ!S26,"") | T34: =IFERROR(subQ!S26+subQ!T21-subQ!T26,"") | V34: =IFERROR(subQ!T26+subQ!V21-subQ!V26,"") | W34: =IFERROR(subQ!V26+subQ!W21-subQ!W26,"") | X34: =IFERROR(subQ!W26+subQ!X21-subQ!X26,"") | Y34: =IFERROR(subQ!X26+subQ!Y21-subQ!Y26,"") | AA34: =IFERROR(subQ!Y26+subQ!AA21-subQ!AA26,"") | AB34: =IFERROR(subQ!AA26+subQ!AB21-subQ!AB26,"") | AC34: -0.004330132 | AD34: 0.001043259 | AF34: -0.001711291 | AG34: 165.36151 | AH34: 0.004605395 | AI34: -0.006652731 | AK34: 0.002243721 | AL34: 165.36435 | AM34: 0.007007229 | AN34: -0.004456199
A35: drv:총차입금 | B35: qoq | C35: 총차입금 QoQ | G35: =IFERROR(subQ!G27/subQ!E27-1,"") | H35: =IFERROR(subQ!H27/subQ!G27-1,"") | I35: =IFERROR(subQ!I27/subQ!H27-1,"") | J35: =IFERROR(subQ!J27/subQ!I27-1,"") | L35: =IFERROR(subQ!L27/subQ!J27-1,"") | M35: =IFERROR(subQ!M27/subQ!L27-1,"") | N35: =IFERROR(subQ!N27/subQ!M27-1,"") | O35: =IFERROR(subQ!O27/subQ!N27-1,"") | Q35: =IFERROR(subQ!Q27/subQ!O27-1,"") | R35: =IFERROR(subQ!R27/subQ!Q27-1,"") | S35: =IFERROR(subQ!S27/subQ!R27-1,"") | T35: =IFERROR(subQ!T27/subQ!S27-1,"") | V35: =IFERROR(subQ!V27/subQ!T27-1,"") | W35: =IFERROR(subQ!W27/subQ!V27-1,"") | X35: =IFERROR(subQ!X27/subQ!W27-1,"") | Y35: =IFERROR(subQ!Y27/subQ!X27-1,"") | AA35: =IFERROR(subQ!AA27/subQ!Y27-1,"") | AB35: =IFERROR(subQ!AB27/subQ!AA27-1,"") | AC35: 7.1e-08 | AD35: 0 | AF35: 0 | AG35: 0 | AH35: 0 | AI35: 0 | AK35: 0 | AL35: 0 | AM35: 0 | AN35: 0
A36: drv:순차입금 | B36: qoq | C36: 순차입금 QoQ | G36: =IFERROR(subQ!G28/subQ!E28-1,"") | H36: =IFERROR(subQ!H28/subQ!G28-1,"") | I36: =IFERROR(subQ!I28/subQ!H28-1,"") | J36: =IFERROR(subQ!J28/subQ!I28-1,"") | L36: =IFERROR(subQ!L28/subQ!J28-1,"") | M36: =IFERROR(subQ!M28/subQ!L28-1,"") | N36: =IFERROR(subQ!N28/subQ!M28-1,"") | O36: =IFERROR(subQ!O28/subQ!N28-1,"") | Q36: =IFERROR(subQ!Q28/subQ!O28-1,"") | R36: =IFERROR(subQ!R28/subQ!Q28-1,"") | S36: =IFERROR(subQ!S28/subQ!R28-1,"") | T36: =IFERROR(subQ!T28/subQ!S28-1,"") | V36: =IFERROR(subQ!V28/subQ!T28-1,"") | W36: =IFERROR(subQ!W28/subQ!V28-1,"") | X36: =IFERROR(subQ!X28/subQ!W28-1,"") | Y36: =IFERROR(subQ!Y28/subQ!X28-1,"") | AA36: =IFERROR(subQ!AA28/subQ!Y28-1,"") | AB36: =IFERROR(subQ!AB28/subQ!AA28-1,"") | AC36: -17.576424 | AD36: 1.3500197 | AF36: 0.47364102 | AG36: 0.18801777 | AH36: 0.31539477 | AI36: 0.28999229 | AK36: 0.18327208 | AL36: 0.10343826 | AM36: 0.17015306 | AN36: 0.17344525
A37: drv:이자발생자산 | B37: qoq | C37: 이자발생자산 QoQ | G37: =IFERROR(subQ!G29/subQ!E29-1,"") | H37: =IFERROR(subQ!H29/subQ!G29-1,"") | I37: =IFERROR(subQ!I29/subQ!H29-1,"") | J37: =IFERROR(subQ!J29/subQ!I29-1,"") | L37: =IFERROR(subQ!L29/subQ!J29-1,"") | M37: =IFERROR(subQ!M29/subQ!L29-1,"") | N37: =IFERROR(subQ!N29/subQ!M29-1,"") | O37: =IFERROR(subQ!O29/subQ!N29-1,"") | Q37: =IFERROR(subQ!Q29/subQ!O29-1,"") | R37: =IFERROR(subQ!R29/subQ!Q29-1,"") | S37: =IFERROR(subQ!S29/subQ!R29-1,"") | T37: =IFERROR(subQ!T29/subQ!S29-1,"") | V37: =IFERROR(subQ!V29/subQ!T29-1,"") | W37: =IFERROR(subQ!W29/subQ!V29-1,"") | X37: =IFERROR(subQ!X29/subQ!W29-1,"") | Y37: =IFERROR(subQ!Y29/subQ!X29-1,"") | AA37: =IFERROR(subQ!AA29/subQ!Y29-1,"") | AB37: =IFERROR(subQ!AB29/subQ!AA29-1,"") | AC37: 0.16424919 | AD37: 0.17962278 | AF37: 0.12554487 | AG37: 0.065253485 | AH37: 0.12206463 | AI37: 0.13157495 | AK37: 0.094795311 | AL37: 0.057826037 | AM37: 0.099223783 | AN37: 0.10767007
A38: drv:현금및현금성자산 | B38: qoq | C38: 현금및현금성자산 QoQ | G38: =IFERROR(subQ!G30/subQ!E30-1,"") | H38: =IFERROR(subQ!H30/subQ!G30-1,"") | I38: =IFERROR(subQ!I30/subQ!H30-1,"") | J38: =IFERROR(subQ!J30/subQ!I30-1,"") | L38: =IFERROR(subQ!L30/subQ!J30-1,"") | M38: =IFERROR(subQ!M30/subQ!L30-1,"") | N38: =IFERROR(subQ!N30/subQ!M30-1,"") | O38: =IFERROR(subQ!O30/subQ!N30-1,"") | Q38: =IFERROR(subQ!Q30/subQ!O30-1,"") | R38: =IFERROR(subQ!R30/subQ!Q30-1,"") | S38: =IFERROR(subQ!S30/subQ!R30-1,"") | T38: =IFERROR(subQ!T30/subQ!S30-1,"") | V38: =IFERROR(subQ!V30/subQ!T30-1,"") | W38: =IFERROR(subQ!W30/subQ!V30-1,"") | X38: =IFERROR(subQ!X30/subQ!W30-1,"") | Y38: =IFERROR(subQ!Y30/subQ!X30-1,"") | AA38: =IFERROR(subQ!AA30/subQ!Y30-1,"") | AB38: =IFERROR(subQ!AB30/subQ!AA30-1,"")
A39: drv:CAPEX | B39: yoy | C39: CAPEX YoY | J39: =IFERROR(subQ!J31/subQ!E31-1,"") | L39: =IFERROR(subQ!L31/subQ!G31-1,"") | M39: =IFERROR(subQ!M31/subQ!H31-1,"") | N39: =IFERROR(subQ!N31/subQ!I31-1,"") | O39: =IFERROR(subQ!O31/subQ!J31-1,"") | Q39: =IFERROR(subQ!Q31/subQ!L31-1,"") | R39: =IFERROR(subQ!R31/subQ!M31-1,"") | S39: =IFERROR(subQ!S31/subQ!N31-1,"") | T39: =IFERROR(subQ!T31/subQ!O31-1,"") | V39: =IFERROR(subQ!V31/subQ!Q31-1,"") | W39: =IFERROR(subQ!W31/subQ!R31-1,"") | X39: =IFERROR(subQ!X31/subQ!S31-1,"") | Y39: =IFERROR(subQ!Y31/subQ!T31-1,"") | AA39: =IFERROR(subQ!AA31/subQ!V31-1,"") | AB39: =IFERROR(subQ!AB31/subQ!W31-1,"") | AC39: 0.67084079 | AD39: 0 | AF39: 92.587174 | AG39: -0.28594364 | AH39: 0 | AI39: 0 | AK39: 0 | AL39: 0 | AM39: 0 | AN39: 0
A40: drv:영업활동현금흐름 | B40: yoy | C40: 영업활동현금흐름 YoY | J40: =IFERROR(subQ!J32/subQ!E32-1,"") | L40: =IFERROR(subQ!L32/subQ!G32-1,"") | M40: =IFERROR(subQ!M32/subQ!H32-1,"") | N40: =IFERROR(subQ!N32/subQ!I32-1,"") | O40: =IFERROR(subQ!O32/subQ!J32-1,"") | Q40: =IFERROR(subQ!Q32/subQ!L32-1,"") | R40: =IFERROR(subQ!R32/subQ!M32-1,"") | S40: =IFERROR(subQ!S32/subQ!N32-1,"") | T40: =IFERROR(subQ!T32/subQ!O32-1,"") | V40: =IFERROR(subQ!V32/subQ!Q32-1,"") | W40: =IFERROR(subQ!W32/subQ!R32-1,"") | X40: =IFERROR(subQ!X32/subQ!S32-1,"") | Y40: =IFERROR(subQ!Y32/subQ!T32-1,"") | AA40: =IFERROR(subQ!AA32/subQ!V32-1,"") | AB40: =IFERROR(subQ!AB32/subQ!W32-1,"")
A41: drv:주식수 | B41: qoq | C41: 주식수 QoQ | G41: =IFERROR(subQ!G33/subQ!E33-1,"") | H41: =IFERROR(subQ!H33/subQ!G33-1,"") | I41: =IFERROR(subQ!I33/subQ!H33-1,"") | J41: =IFERROR(subQ!J33/subQ!I33-1,"") | L41: =IFERROR(subQ!L33/subQ!J33-1,"") | M41: =IFERROR(subQ!M33/subQ!L33-1,"") | N41: =IFERROR(subQ!N33/subQ!M33-1,"") | O41: =IFERROR(subQ!O33/subQ!N33-1,"") | Q41: =IFERROR(subQ!Q33/subQ!O33-1,"") | R41: =IFERROR(subQ!R33/subQ!Q33-1,"") | S41: =IFERROR(subQ!S33/subQ!R33-1,"") | T41: =IFERROR(subQ!T33/subQ!S33-1,"") | V41: =IFERROR(subQ!V33/subQ!T33-1,"") | W41: =IFERROR(subQ!W33/subQ!V33-1,"") | X41: =IFERROR(subQ!X33/subQ!W33-1,"") | Y41: =IFERROR(subQ!Y33/subQ!X33-1,"") | AA41: =IFERROR(subQ!AA33/subQ!Y33-1,"") | AB41: =IFERROR(subQ!AB33/subQ!AA33-1,"") | AC41: 0 | AD41: 0 | AF41: 0 | AG41: 0 | AH41: 0 | AI41: 0 | AK41: 0 | AL41: 0 | AM41: 0 | AN41: 0
A42: drv:DPS | B42: abs | C42: DPS (가정, 원) | E42: =subQ!E36 | F42: =subQ!F36 | G42: =subQ!G36 | H42: =subQ!H36 | I42: =subQ!I36 | J42: =subQ!J36 | K42: =subQ!K36 | L42: =subQ!L36 | ... AB42: =subQ!AB36 | AD42: 320 | AE42: =subQ!AE36 | AI42: 320 | AJ42: =subQ!AJ36 | AN42: 320 | AO42: =subQ!AO36
B44: 3. 밸류에이션·스칼라 | C44: 노란 셀 = 가정. '연결' 표시는 추정 전 분기 수식이 이 셀을 참조한다는 뜻
A45: sc:종가 | C45: 종가 | D45: 19260 | E45: 원 — 네이버 정규장 종가(aik 확정종가 대조 · aik 20,250원)
A46: sc:기준일 | C46: 기준일 | D46: 20261008 | E46: 종가 기준일
A47: sc:COE | C47: COE | D47: 0.09 | E47: 자기자본비용(가정) — TP 적정 PBR = ROE/COE
A48: sc:PER_lo | C48: PER_lo | D48: 19.7 | E48: PER 밴드 하단(배) — hist_quarterly(분기 평균가 ÷ TTM EPS, 13분기, 25/50/75 백분위) · 캡 5~30배 적용(원값 19.7/24.5/38.1)
A49: sc:PER_mid | C49: PER_mid | D49: 24.5 | E49: PER 밴드 중단(배)
A50: sc:PER_hi | C50: PER_hi | D50: 30 | E50: PER 밴드 상단(배)
A51: sc:EPS_Y1가중 | C51: EPS_Y1가중 | D51: 0.5 | E51: 12M fwd EPS = FY(last_actual연도)E × w + FY+1E × (1−w) — 기준 분기 2Q 이면 0.5(가정)
A52: sc:세율 | C52: 세율 | D52: 0.24355834 | E52: 연결 — 법인세 = MAX(세전,0) × 세율(역산, 재현 오차 ≤ 0.05억 · 모델 assumptions 0.2436) · 최근 12분기 유효세율 28.5% 가 5~27% 밖 → 클립 대신 최근 8분기 중 세전 > 0 인 7분기(2024Q3~2026Q2)의 법인세/세전 중위 24.4%
A53: sc:판관비율 | C53: 판관비율 | D53: 0.095074815 | E53: 연결 — 판관비 = 매출액 × 판관비율(역산, 재현 오차 ≤ 0.05억 · 모델 assumptions 0.0951)
A54: sc:지배주주비중 | C54: 지배주주비중 | D54: 1 | E54: 연결 — 지배주주순이익 = 당기순이익 × 비중(역산, 재현 오차 ≤ 0.05억)
A55: sc:이자율_자산 | C55: 이자율_자산 | D55: 0.019743713 | E55: 연결 — 이자손익 = (전분기 이자발생자산 × 자산이자율 − 전분기 총차입금 × 부채이자율)/4(역산, 재현 오차 ≤ 0.05억 · 모델 assumptions 0.0197)
A56: sc:이자율_부채 | C56: 이자율_부채 | D56: 0.051866664 | E56: 연결 — 같은 수식의 부채 쪽(총차입금 행이 없으면 0)(역산, 재현 오차 ≤ 0.05억 · 모델 assumptions 0.0519)
A57: sc:배당성향 | C57: 배당성향 | D57: 0.1625 | E57: 배당성향(참고 — 모델은 직전 DPS 유지·Q2 지급 가정)
A58: sc:외화순노출_백만$ | C58: 외화순노출_백만$ | E58: 외화 순노출 × Δ기말환율 (외화 시트 방식) — 외화 순노출 미공시(face) → 0 + 표기
A59: sc:헤지비율 | C59: 헤지비율 | E59: sls 없음
A60: sc:헤지환율_약정 | C60: 헤지환율_약정 | E60: sls 없음

Sheet BS연결
B1: (백만원) | C1: 이름: BS연결H | E1: 4Q21 | F1: 2021 | G1: 1Q22 | H1: 2Q22 | I1: 3Q22 | J1: 4Q22 | K1: 2022 | L1: 1Q23 | M1: 2Q23 | N1: 3Q23 | O1: 4Q23 | P1: 2023 | Q1: 1Q24 | R1: 2Q24 | S1: 3Q24 | T1: 4Q24 | U1: 2024 | V1: 1Q25 | W1: 2Q25 | X1: 3Q25 | Y1: 4Q25 | Z1: 2025 | AA1: 1Q26 | AB1: 2Q26 | AC1: 3Q26 | AD1: 4Q26 | AE1: 2026 | AF1: 1Q27 | AG1: 2Q27 | AH1: 3Q27 | AI1: 4Q27 | AJ1: 2027 | AK1: 1Q28 | AL1: 2Q28 | AM1: 3Q28 | AN1: 4Q28 | AO1: 2028
B2: 연결 | D2: fin json(kship_fin.py)
B3: 한국카본(연) | C3: UPDATE: 26-10-11 | E3: 1 | F3: 2 | G3: 3 | H3: 4 | I3: 5 | J3: 6 | K3: 7 | L3: 8 | M3: 9 | N3: 10 | O3: 11 | P3: 12 | Q3: 13 | R3: 14 | S3: 15 | T3: 16 | U3: 17 | V3: 18 | W3: 19 | X3: 20 | Y3: 21 | Z3: 22 | AA3: 23 | AB3: 24 | AC3: 25 | AD3: 26 | AE3: 27 | AF3: 28 | AG3: 29 | AH3: 30 | AI3: 31 | AJ3: 32 | AK3: 33 | AL3: 34 | AM3: 35 | AN3: 36 | AO3: 37
B4: Account Code | C4: AccountNAME | E4: 2021.12 | F4: 2021.12A | G4: 2022.03 | H4: 2022.06 | I4: 2022.09 | J4: 2022.12 | K4: 2022.12A | L4: 2023.03 | M4: 2023.06 | N4: 2023.09 | O4: 2023.12 | P4: 2023.12A | Q4: 2024.03 | R4: 2024.06 | S4: 2024.09 | T4: 2024.12 | U4: 2024.12A | V4: 2025.03 | W4: 2025.06 | X4: 2025.09 | Y4: 2025.12 | Z4: 2025.12A | AA4: 2026.03 | AB4: 2026.06 | AC4: 2026.09 | AD4: 2026.12 | AE4: 2026.12A | AF4: 2027.03 | AG4: 2027.06 | AH4: 2027.09 | AI4: 2027.12 | AJ4: 2027.12A | AK4: 2028.03 | AL4: 2028.06 | AM4: 2028.09 | AN4: 2028.12 | AO4: 2028.12A
A5: 1 | C5: 유동자산 | E5: 247791.87 | F5: 247791.87 | G5: 255393.39 | H5: 230238.29 | I5: 264928.44 | J5: 289163.54 | K5: 289163.54 | L5: 315524.09 | M5: 355804.32 | N5: 400684.73 | O5: 398231.47 | P5: 398231.47 | Q5: 381207.48 | R5: 403917.09 | S5: 430381.52 | T5: 460860.28 | U5: 460860.28 | V5: 500085.88 | W5: 502890.88 | X5: 514786.25 | Y5: 607406.72 | Z5: 607406.72 | AA5: 639843.94 | AB5: 681631.77
A6: 1 | C6: 현금및현금성자산 | E6: 49048.03 | F6: 49048.03 | G6: 55331.27 | H6: 13926.27 | I6: 33955.6 | J6: 53576.76 | K6: 53576.76 | L6: 26157.63 | M6: 20147.7 | N6: 46967.12 | O6: 66697.91 | P6: 66697.91 | Q6: 37198.61 | R6: 81861.13 | S6: 79766.91 | T6: 57565.06 | U6: 57565.06 | V6: 111782.73 | W6: 93232.67 | X6: 102472.41 | Y6: 57866.93 | Z6: 57866.93 | AA6: 81410.23 | AB6: 110991.2
A7: 1 | C7: 단기금융상품 | E7: 15572.82 | F7: 15572.82 | G7: 15064.68 | H7: 13889.3 | I7: 13035.65 | J7: 13165.04 | K7: 13165.04 | L7: 12386.95 | M7: 10759.94 | N7: 17128.44 | O7: 13022.45 | P7: 13022.45 | Q7: 17707.35 | R7: 8729.77 | S7: 9567.13 | T7: 8598.21 | U7: 8598.21 | V7: 8340.84 | W7: 8240.64 | X7: 8149.11 | Y7: 27093.22 | Z7: 27093.22 | AA7: 27408.82 | AB7: 27562.68
A8: 1 | C8: 단기금융자산 | E8: 26206.73 | F8: 26206.73 | G8: 22838.73 | H8: 16474.68 | I8: 13035.65 | J8: 13169.65 | K8: 13169.65 | L8: 14399.7 | M8: 10759.94 | N8: 17128.44 | O8: 13022.45 | P8: 13022.45 | Q8: 17707.35 | R8: 8729.77 | S8: 9567.13 | T8: 8598.21 | U8: 8598.21 | V8: 8340.84 | W8: 16435.73 | X8: 19642.88 | Y8: 36967.87 | Z8: 36967.87 | AA8: 29491.88 | AB8: 28812.89
A9: 1 | C9: 매출채권및기타채권 | E9: 34456.94 | F9: 34456.94 | G9: 36331.24 | H9: 43570.72 | I9: 53976.75 | J9: 39272.3 | K9: 39272.3 | L9: 58037.62 | M9: 74541.64 | N9: 83221.65 | O9: 101111.57 | P9: 101111.57 | Q9: 110410.89 | R9: 85661.03 | S9: 75401.15
A10: 1 | C10: 재고자산 | E10: 90813.55 | F10: 90813.55 | G10: 102484.78 | H10: 134818.99 | I10: 139265.44 | J10: 156268.22 | K10: 156268.22 | L10: 186248.38 | M10: 193333.2 | N10: 220871.23 | O10: 180213.74 | P10: 180213.74 | Q10: 183181.59 | R10: 183391.46 | S10: 195244.82 | T10: 197476.02 | U10: 197476.02 | V10: 190637.47 | W10: 187215.75 | X10: 190217.71 | Y10: 197614.58 | Z10: 197614.58 | AA10: 204378.89 | AB10: 211457.85
A11: 1 | C11: 당기법인세자산(선급법인세) | E11: 1.5 | F11: 1.5 | G11: 2.02 | H11: 0.87 | I11: 1.03 | J11: 1.49 | K11: 1.49 | L11: 1.65 | M11: 0.73 | N11: 1.37 | O11: 2.91 | P11: 2.91 | Q11: 3.35 | R11: 3.5 | S11: 4.6 | T11: 6 | U11: 6 | V11: 7.29 | W11: 2.32 | X11: 4.79 | Y11: 15.32 | Z11: 15.32 | AA11: 15.02 | AB11: 2.17
A12: 1 | C12: 기타유동자산 | E12: 4638.21 | F12: 4638.21 | G12: 3281.96 | H12: 5579.23 | I12: 6464.49 | J12: 7442.53 | K12: 7442.53 | L12: 8361.44 | M12: 12632.03 | N12: 16787.66 | O12: 12638.85 | P12: 12638.85 | Q12: 15366.64 | R12: 18008.01 | S12: 15415.61 | T12: 15033.64 | U12: 15033.64 | V12: 18208.04 | W12: 21927.4 | X12: 22418.53 | Y12: 18096.17 | Z12: 18096.17 | AA12: 32566.7 | AB12: 29001.05
A13: 1 | C13: 매각예정비유동자산및처분자산 | E13: 17.52 | F13: 17.52 | G13: 17.64 | H13: 18.1 | I13: 18.93 | J13: 17.98 | K13: 17.98 | L13: 7.08 | M13: 7.14 | N13: 7.33 | O13: 4.47 | P13: 4.47 | Q13: 4.66 | R13: 4.81 | S13: 4.59
A14: 1 | C14: 비유동자산 | E14: 250546.52 | F14: 250546.52 | G14: 249980.14 | H14: 288907.99 | I14: 292458.61 | J14: 296152.11 | K14: 296152.11 | L14: 296653.95 | M14: 299876.49 | N14: 394313.91 | O14: 394192.2 | P14: 394192.2 | Q14: 407449.62 | R14: 417050.3 | S14: 405736 | T14: 418106.15 | U14: 418106.15 | V14: 421740.83 | W14: 428551.6 | X14: 433794.09 | Y14: 435813.92 | Z14: 435813.92 | AA14: 450490.95 | AB14: 455571.8
A15: 1 | C15: 장기금융자산 | E15: 8603.48 | F15: 8603.48 | G15: 8619.14 | H15: 8633.3 | I15: 6786.97 | J15: 7011.4 | K15: 7011.4 | L15: 4999.55 | M15: 4555.42 | N15: 484 | O15: 352 | P15: 352 | Q15: 352 | R15: 352 | S15: 352 | T15: 28160.62 | U15: 28160.62 | V15: 25462.51 | W15: 27550.69 | X15: 25693.83 | Y15: 24350.66 | Z15: 24350.66 | AA15: 25244.97 | AB15: 24231.24
A16: 1 | C16: 투자자산 | E16: 8603.48 | F16: 8603.48 | G16: 8619.14 | H16: 8633.3 | I16: 6786.97 | J16: 7011.4 | K16: 7011.4 | L16: 4999.55 | M16: 4555.42 | N16: 484 | O16: 352 | P16: 352 | Q16: 352 | R16: 2459.17 | S16: 2201.34 | T16: 30034.34 | U16: 30034.34 | V16: 27223.22 | W16: 29120.98 | X16: 27105.07 | Y16: 26378.47 | Z16: 26378.47 | AA16: 27284.42 | AB16: 24448.87
A17: 1 | C17: 유형자산 | E17: 184644.78 | F17: 184644.78 | G17: 188799.2 | H17: 203871.73 | I17: 210828.11 | J17: 212463.84 | K17: 212463.84 | L17: 216939.52 | M17: 220144.48 | N17: 272351.99 | O17: 271300.75 | P17: 271300.75 | Q17: 282316.44 | R17: 293636.26 | S17: 304656.7 | T17: 312075.75 | U17: 312075.75 | V17: 319612.24 | W17: 330343.11 | X17: 333503.58 | Y17: 335053.95 | Z17: 335053.95 | AA17: 344413.76 | AB17: 352503.89
A18: 1 | C18: 사용권자산 | E18: 4645.89 | F18: 4645.89 | G18: 5065.46 | H18: 5000.07 | I18: 5450.99 | J18: 5837.24 | K18: 5837.24 | L18: 5723.6 | M18: 5853.86 | N18: 5875.01 | O18: 6090.91 | P18: 6090.91 | Q18: 9756.11 | R18: 15708.52 | S18: 8986.02 | T18: 9518.71 | U18: 9518.71 | V18: 9170.11 | W18: 8680.7 | X18: 12931.26 | Y18: 9752.51 | Z18: 9752.51 | AA18: 10981.77 | AB18: 11831.01
A19: 1 | C19: 기타비유동자산 | E19: 5525.31 | F19: 5525.31 | G19: 5927.03 | H19: 5860.87 | I19: 6378.43 | J19: 9312.02 | K19: 9312.02 | L19: 9305.07 | M19: 9392.12 | N19: 9509.02 | O19: 8941.31 | P19: 8941.31 | Q19: 11742.4 | R19: 18659.96 | S19: 11660.56 | T19: 10447.46 | U19: 10447.46 | V19: 10078.95 | W19: 9602.07 | X19: 13910.28 | Y19: 10834.44 | Z19: 10834.44 | AA19: 11388.72 | AB19: 12331.47
A20: 1 | C20: 무형자산 | E20: 2288.39 | F20: 2288.39 | G20: 2267.03 | H20: 2296.01 | I20: 2268.27 | J20: 2254.49 | K20: 2254.49 | L20: 2227.83 | M20: 2203.03 | N20: 37272.64 | O20: 39710.47 | P20: 39710.47 | Q20: 39007.07 | R20: 38318.23 | S20: 38121.11 | T20: 42412.51 | U20: 42412.51 | V20: 41821.46 | W20: 40877.61 | X20: 40040.88 | Y20: 39341.74 | Z20: 39341.74 | AA20: 39145.24 | AB20: 42032.88
A21: 1 | C21: 이연법인세자산 | E21: 1569.61 | F21: 1569.61 | G21: 1430.64 | H21: 1595.32 | I21: 1879.55 | J21: 2866.8 | K21: 2866.8 | L21: 3569.43 | M21: 2562.05 | N21: 1781.31 | O21: 1768.48 | P21: 1768.48 | Q21: 1938.86 | R21: 1840.37 | S21: 565.82
A22: 1 | C22: 자산총계 | E22: 498355.91 | F22: 498355.91 | G22: 505391.17 | H22: 519164.39 | I22: 557405.98 | J22: 585333.64 | K22: 585333.64 | L22: 612185.13 | M22: 655687.95 | N22: 795005.97 | O22: 792428.14 | P22: 792428.14 | Q22: 788661.75 | R22: 820972.2 | S22: 836122.12 | T22: 878968.66 | U22: 878968.66 | V22: 921828.93 | W22: 931444.35 | X22: 948582.27 | Y22: 1043222.6 | Z22: 1043222.6 | AA22: 1090337 | AB22: 1137205.7
A23: 1 | C23: 유동부채 | E23: 93991.13 | F23: 93991.13 | G23: 98508.84 | H23: 100289.98 | I23: 124167.55 | J23: 156336.84 | K23: 156336.84 | L23: 190631.59 | M23: 229480.38 | N23: 267544.14 | O23: 297365.08 | P23: 297365.08 | Q23: 294892.91 | R23: 318477.21 | S23: 326698.75 | T23: 369168.31 | U23: 369168.31 | V23: 400337.98 | W23: 360072.68 | X23: 357565.87 | Y23: 424075.43 | Z23: 424075.43 | AA23: 476206.81 | AB23: 418873.44
A24: 1 | C24: 단기차입금 | E24: 7098 | F24: 7098 | G24: 6933 | H24: 11426 | I24: 34463 | J24: 44318 | K24: 44318 | L24: 56129.22 | M24: 73859.41 | N24: 89467.44 | O24: 89232.02 | P24: 89232.02 | Q24: 68025.21 | R24: 64811.33 | S24: 64507.15 | T24: 47232.3 | U24: 47232.3 | V24: 42758 | W24: 25210.4 | X24: 15969.34 | Y24: 81871.44 | Z24: 81871.44 | AA24: 99511.75 | AB24: 117889.05
A25: 1 | C25: 유동성장기부채 | E25: 15948.57 | F25: 15948.57 | G25: 12166.91 | H25: 939.1 | I25: 4619.33 | J25: 853.42 | K25: 853.42 | L25: 1398.73 | M25: 2046.89 | N25: 4376.03 | O25: 15250.36 | P25: 15250.36 | Q25: 17018.06 | R25: 16697.2 | S25: 6367.2 | T25: 5930.95 | U25: 5930.95 | V25: 4724.7 | W25: 5518.45 | X25: 16312.2 | Y25: 3912.2 | Z25: 3912.2 | AA25: 18462.28 | AB25: 2826.27
A26: 1 | C26: 기타유동금융부채 | E26: 391.38 | F26: 391.38 | G26: 489.57 | H26: 2557.35 | I26: 8009.58 | J26: 1801.08 | K26: 1801.08 | L26: 2916.01 | M26: 2856.94 | N26: 3516.42 | O26: 1059.06 | P26: 1059.06 | Q26: 2527.98 | R26: 3985.62 | S26: 815.26 | T26: 8836.29 | U26: 8836.29 | V26: 8348.9 | W26: 1965.76 | X26: 3812.27 | Y26: 5320.45 | Z26: 5320.45 | AA26: 10209.77 | AB26: 12596.44
A27: 1 | C27: 단기금융부채 | E27: 1067.03 | F27: 1067.03 | G27: 1418.08 | H27: 10499.6 | I27: 9034.81 | J27: 3325.52 | K27: 3325.52 | L27: 4438.28 | M27: 4480.29 | N27: 5228.28 | O27: 2619.86 | P27: 2619.86 | Q27: 4404.86 | R27: 5641.69 | S27: 2014.88 | T27: 10483.33 | U27: 10483.33 | V27: 9889.72 | W27: 28628.7 | X27: 39215.6 | Y27: 35816.73 | Z27: 35816.73 | AA27: 53605.11 | AB27: 18289.54
A28: 1 | C28: 당기법인세부채(미지급법인세) | E28: 6891.83 | F28: 6891.83 | G28: 5705.33 | H28: 3596.05 | I28: 5480.23 | J28: 5749.73 | K28: 5749.73 | L28: 4736.86 | M28: 2115.17 | N28: 5702.61 | O28: 3077.95 | P28: 3077.95 | Q28: 4661.3 | R28: 14146.44 | S28: 10233.25 | T28: 11687.15 | U28: 11687.15 | V28: 11689.01 | W28: 9771.83 | X28: 13253.1 | Y28: 31494.08 | Z28: 31494.08 | AA28: 28404.72 | AB28: 16973.66
A29: 1 | C29: 유동리스부채 | E29: 675.65 | F29: 675.65 | G29: 928.51 | H29: 7942.25 | I29: 1025.23 | J29: 1524.44 | K29: 1524.44 | L29: 1522.27 | M29: 1623.35 | N29: 1711.86 | O29: 1560.8 | P29: 1560.8 | Q29: 1876.88 | R29: 1656.07 | S29: 1199.62 | T29: 1647.04 | U29: 1647.04 | V29: 1540.82 | W29: 1468.82 | X29: 3630.41 | Y29: 2361.39 | Z29: 2361.39 | AA29: 3309.38 | AB29: 4237.91
A30: 1 | C30: 리스부채 | E30: 1583.48 | F30: 1583.48 | G30: 1879.25 | H30: 8737.03 | I30: 1980.98 | J30: 2768.12 | K30: 2768.12 | L30: 2616.72 | M30: 2730.01 | N30: 2843.57 | O30: 2552.46 | P30: 2552.46 | Q30: 5490.17 | R30: 5030.76 | S30: 4899.76 | T30: 5174.05 | U30: 5174.05 | V30: 4934.68 | W30: 4825.87 | X30: 9049.57 | Y30: 5851.97 | Z30: 5851.97 | AA30: 7165.51 | AB30: 7975.5
A31: 1 | C31: 기타유동부채 | E31: 10935.17 | F31: 10935.17 | G31: 10639.42 | H31: 13223.41 | I31: 13219.04 | J31: 30617.17 | K31: 30617.17 | L31: 42970.94 | M31: 55786.23 | N31: 72129.8 | O31: 84883.34 | P31: 84883.34 | Q31: 79767.12 | R31: 105771.63 | S31: 122438.8 | T31: 173791.2 | U31: 173791.2 | V31: 186654.78 | W31: 164353.86 | X31: 150325.64 | Y31: 140999.44 | Z31: 140999.44 | AA31: 140563.77 | AB31: 136649.23
A32: 1 | C32: 비유동부채 | E32: 15359.35 | F32: 15359.35 | G32: 21323.69 | H32: 21749.84 | I32: 33045.29 | J32: 24822.46 | K32: 24822.46 | L32: 23782.36 | M32: 21483.22 | N32: 51148.94 | O32: 40402.35 | P32: 40402.35 | Q32: 44481.94 | R32: 43256.4 | S32: 39192.19 | T32: 35506.43 | U32: 35506.43 | V32: 32798.44 | W32: 45717.67 | X32: 50672.82 | Y32: 38969.49 | Z32: 38969.49 | AA32: 33529.84 | AB32: 44865.76
A33: 1 | C33: 장기차입금 | E33: 2281.09 | F33: 2281.09 | G33: 8372.85 | H33: 8358.7 | I33: 16091.73 | J33: 15953.5 | K33: 15953.5 | L33: 15499.95 | M33: 16725 | N33: 33348.7 | O33: 21104.8 | P33: 21104.8 | Q33: 22895.5 | R33: 21311.2 | S33: 19348.9 | T33: 18062.85 | U33: 18062.85 | V33: 13984.8 | W33: 17406.75 | X33: 15793.34 | Y33: 11400.65 | Z33: 11400.65 | AA33: 10422.6 | AB33: 20621.67
... A36: 1 | C36: 확정급여부채 | E36: 2737.01 | F36: 2737.01 | G36: 3110.59 | H36: 480.06 | I36: 979.05 | J36: 404.81 | K36: 404.81 | L36: 568.32 | M36: 585.99 | N36: 707.52 | O36: 737.4 | P36: 737.4 | Q36: 712.26 | R36: 903.85 | S36: 525.21 | T36: 349.23 | U36: 349.23 | V36: 363.25 | W36: 3026.23 | X36: 7734.72 | Y36: 590.61 | Z36: 590.61 | AA36: 1435.39 | AB36: 677.97
A37: 1 | C37: 이연법인세부채 | E37: 4153.83 | F37: 4153.83 | G37: 3393.59 | H37: 3179.71 | I37: 1288.92 | N37: 1103.74 | O37: 4981.12 | P37: 4981.12 | Q37: 4404.5 | R37: 3666.58 | S37: 4796.24 | T37: 2618.95 | U37: 2618.95 | V37: 4550.25 | W37: 8841.01 | X37: 4484.65 | Y37: 0 | Z37: 0 | AA37: 0
A38: 1 | C38: 기타비유동부채 | E38: 1510.58 | F38: 1510.58 | G38: 1510.58 | H38: 2213.47 | I38: 2213.47 | J38: 6784.07 | K38: 6784.07 | L38: 5972.26 | M38: 2764.98 | N38: 3473.65 | O38: 2113.34 | P38: 2113.34 | Q38: 1309.25 | R38: 1309.25 | S38: 181.82 | T38: 696.44 | U38: 696.44 | V38: 696.44 | W38: 696.44 | X38: 696.44 | Y38: 4137 | Z38: 4137 | AA38: 8701.89 | AB38: 11693.41
A39: 1 | C39: 부채총계 | E39: 109356.56 | F39: 109356.56 | G39: 119832.53 | H39: 122039.82 | I39: 157212.84 | J39: 181165.8 | K39: 181165.8 | L39: 214413.95 | M39: 250963.59 | N39: 318693.07 | O39: 337774.04 | P39: 337774.04 | Q39: 339381.73 | R39: 361740.73 | S39: 365897.73 | T39: 404682.31 | U39: 404682.31 | V39: 433143.96 | W39: 405797.27 | X39: 408245.89 | Y39: 463052.31 | Z39: 463052.31 | AA39: 509744.37 | AB39: 463747.06
A40: 1 | C40: 지배주주지분 | E40: 388999.34 | F40: 388999.34 | G40: 385558.64 | H40: 397124.57 | I40: 400193.14 | J40: 404167.83 | K40: 404167.83 | L40: 397771.18 | M40: 404724.35 | N40: 476312.89 | O40: 454654.11 | P40: 454654.11 | Q40: 449280.03 | R40: 459231.48 | S40: 470224.38 | T40: 474286.35 | U40: 474286.35 | V40: 488684.96 | W40: 525647.07 | X40: 540336.38 | Y40: 580170.31 | Z40: 580170.31 | AA40: 580592.59 | AB40: 673458.63
A41: 1 | C41: 자본금 | E41: 21980.38 | F41: 21980.38 | G41: 21980.38 | H41: 21980.38 | I41: 21980.38 | J41: 21980.38 | K41: 21980.38 | L41: 21980.38 | M41: 21980.38 | N41: 21980.38 | O41: 25954.23 | P41: 25954.23 | Q41: 25954.23 | R41: 25954.23 | S41: 25954.23 | T41: 192789.69 | U41: 192789.69 | V41: 192789.69 | W41: 192789.69 | X41: 192789.69 | Y41: 122789.69 | Z41: 122789.69 | AA41: 122789.69 | AB41: 177321.71
A42: 1 | C42: 자본잉여금 | E42: 74960.11 | F42: 74960.11 | G42: 74960.11 | H42: 74960.11 | I42: 74960.11 | J42: 74960.11 | K42: 74960.11 | L42: 74960.11 | M42: 74960.11 | N42: 74960.11 | O42: 166835.46 | P42: 166835.46 | Q42: 166835.46 | R42: 166835.46 | S42: 166835.46 | T42: 166835.46 | U42: 166835.46 | V42: 166835.46 | W42: 166835.46 | X42: 166835.46 | Y42: 96835.46 | Z42: 96835.46 | AA42: 96835.46 | AB42: 151014.17
A43: 1 | C43: 이익잉여금 | E43: 284714.2 | F43: 284714.2 | G43: 281255.43 | H43: 291374.79 | I43: 290275.57 | J43: 299947.16 | K43: 299947.16 | L43: 292454.73 | M43: 299507.23 | N43: 298574.07 | O43: 278294.99 | P43: 278294.99 | Q43: 272364.55 | R43: 281552.57 | S43: 293777.41 | T43: 294860.83 | U43: 294860.83 | V43: 310714.61 | W43: 332788.74 | X43: 345007.55 | Y43: 454119.35 | Z43: 454119.35 | AA43: 440836.81 | AB43: 476369.66
A44: 1 | C44: 기타포괄이익누계액 | E44: -1193.47 | F44: -1193.47 | G44: -1175.4 | H44: 271.16 | I44: 4438.95 | J44: -1257.94 | K44: -1257.94 | L44: -162.17 | M44: -261.49 | N44: -586.49 | O44: -719.91 | P44: -719.91 | Q44: -163.55 | R44: 599.88 | S44: -632.05 | T44: 2351.2 | U44: 2351.2 | V44: 896.03 | W44: -1584.05 | X44: 886.45 | Y44: 3018.25 | Z44: 3018.25 | AA44: 5535.05 | AB44: 8035.16
A45: 1 | C45: 기타자본 | E45: 8538.13 | F45: 8538.13 | G45: 8538.13 | H45: 8538.13 | I45: 8538.13 | J45: 8538.13 | K45: 8538.13 | L45: 8538.13 | M45: 8538.13 | N45: 81384.83 | O45: -15710.66 | P45: -15710.66 | Q45: -15710.66 | R45: -15710.66 | S45: -15710.66 | T45: -15715.36 | U45: -15715.36 | V45: -15715.36 | W45: 1652.7 | X45: 1652.7 | Y45: 243.02 | Z45: 243.02 | AA45: 11431.04 | AB45: 11732.1
A46: 1 | C46: 자본총계 | E46: 388999.34 | F46: 388999.34 | G46: 385558.64 | H46: 397124.57 | I46: 400193.14 | J46: 404167.83 | K46: 404167.83 | L46: 397771.18 | M46: 404724.35 | N46: 476312.89 | O46: 454654.11 | P46: 454654.11 | Q46: 449280.03 | R46: 459231.48 | S46: 470224.38 | T46: 474286.35 | U46: 474286.35 | V46: 488684.96 | W46: 525647.07 | X46: 540336.38 | Y46: 580170.31 | Z46: 580170.31 | AA46: 580592.59 | AB46: 673458.63
A47: 1 | C47: 부채와자본총계 | E47: 498355.91 | F47: 498355.91 | G47: 505391.17 | H47: 519164.39 | I47: 557405.98 | J47: 585333.64 | K47: 585333.64 | L47: 612185.13 | M47: 655687.95 | N47: 795005.97 | O47: 792428.14 | P47: 792428.14 | Q47: 788661.75 | R47: 820972.2 | S47: 836122.12 | T47: 878968.66 | U47: 878968.66 | V47: 921828.93 | W47: 931444.35 | X47: 948582.27 | Y47: 1043222.6 | Z47: 1043222.6 | AA47: 1090337 | AB47: 1137205.7
A48: 1 | C48: 총차입금 | E48: 25327.66 | F48: 25327.66 | G48: 27472.76 | H48: 20723.8 | I48: 55174.06 | J48: 61124.92 | K48: 61124.92 | L48: 73027.9 | M48: 92631.3 | N48: 137392.17 | O48: 135787.18 | P48: 135787.18 | Q48: 118138.77 | R48: 113019.73 | S48: 100223.25 | T48: 71226.1 | U48: 71226.1 | V48: 61467.5 | W48: 59712.06 | X48: 60642.55 | Y48: 110743.17 | Z48: 110743.17 | AA48: 128396.63 | AB48: 141336.99
A49: 1 | C49: 순차입금 | E49: -49927.1 | F49: -49927.1 | G49: -50697.24 | H49: -9677.15 | I49: 8182.81 | J49: -5621.49 | K49: -5621.49 | L49: 32470.57 | M49: 61723.66 | N49: 73296.61 | O49: 56066.82 | P49: 56066.82 | Q49: 63232.81 | R49: 22428.83 | S49: 10889.21 | T49: 5062.83 | U49: 5062.83 | V49: -58656.07 | W49: -49956.34 | X49: -61472.74 | Y49: 15908.37 | Z49: 15908.37 | AA49: 17494.52 | AB49: 1532.9
A50: 1 | C50: 이자발생자산 | E50: 83858.24 | F50: 83858.24 | G50: 86789.14 | H50: 39034.25 | I50: 53778.22 | J50: 73757.81 | K50: 73757.81 | L50: 45556.88 | M50: 35463.06 | N50: 64579.56 | O50: 80072.36 | P50: 80072.36 | Q50: 55257.96 | R50: 90942.9 | S50: 89686.04 | T50: 94323.89 | U50: 94323.89 | V50: 145586.08 | W50: 137219.09 | X50: 147809.12 | Y50: 119185.46 | Z50: 119185.46 | AA50: 136147.08 | AB50: 164035.33
A51: 1 | C51: 매입채무및기타채무 | G51: 6453.32 | L51: 5592.88 | Q51: 5413.95
A52: 1 | C52: 기타비유동금융부채 | G52: 122.41 | H52: 2787.9 | I52: 11360.4 | J52: 271.05 | K52: 271.05 | L52: 477.47 | M52: 97.23 | N52: 929.57 | Q52: 1052.65 | R52: 2170.4 | S52: 372.36 | T52: 9973.6 | U52: 9973.6 | V52: 9520.95 | W52: 511.22 | X52: 3659.61 | Y52: 5449.43 | Z52: 5449.43 | AA52: 8400.79 | AB52: 6678.26
A53: 1 | C53: 비지배주주지분 | G53: 0 | V53: 0 | W53: 0 | X53: 0 | Y53: 0 | Z53: 0 | AA53: 0 | AB53: 0
A54: 1 | C54: 단기금융부채(face) | N54: 89467.44 | O54: 89232.02 | P54: 89232.02 | Q54: 68025.21 | R54: 64811.33 | S54: 64507.15 | T54: 47232.3 | U54: 47232.3 | V54: 42758 | W54: 25210.4 | X54: 15969.34 | Y54: 81871.44 | Z54: 81871.44 | AA54: 99511.75 | AB54: 117889.05
A55: 1 | C55: 사채 | N55: 10200 | O55: 10200 | P55: 10200 | Q55: 10200 | R55: 10200 | S55: 10000 | T55: 0 | U55: 0 | W55: 11576.46 | X55: 12567.67 | Y55: 13558.88 | Z55: 13558.88 | AA55: 0 | AB55: 0
A56: 1 | C56: 투자부동산 | O56: 15730.94 | P56: 15730.94 | Q56: 15719.73 | R56: 9294.34 | S56: 15697.31 | T56: 15686.1 | U56: 15686.1 | V56: 15674.89 | W56: 15663.68 | X56: 15652.47 | Y56: 15641.26 | Z56: 15641.26 | AA56: 15630.05 | AB56: 15789.67
A57: 1 | C57: 종속기업및관계기업투자 | R57: 2107.17 | S57: 1849.34 | T57: 1873.72 | U57: 1873.72 | V57: 1760.71 | W57: 1570.29 | X57: 1411.24 | Y57: 2027.81 | Z57: 2027.81 | AA57: 2039.45 | AB57: 217.63
A58: 1 | C58: 단기투자자산(공정가치) | T58: 19695.35 | U58: 19695.35 | V58: 11693.26 | W58: 52142.18 | X58: 57482.09 | Y58: 164649.52 | Z58: 164649.52 | AA58: 164064.74 | AB58: 174297.13
A59: 1 | C59: 보통주자본금 | T59: 25954.23 | U59: 25954.23 | V59: 25954.23 | W59: 25954.23 | X59: 25954.23 | Y59: 25954.23 | Z59: 25954.23 | AA59: 25954.23 | AB59: 26307.54
A60: 1 | C60: 유동파생상품자산 | W60: 8195.09 | X60: 11493.77 | Y60: 9874.65 | Z60: 9874.65 | AA60: 2083.06 | AB60: 1250.21
A61: 1 | C61: 단기파생상품부채 | W61: 25194.12 | X61: 31772.92 | Y61: 28134.89 | Z61: 28134.89 | AA61: 40085.96 | AB61: 1455.19
A62: 1 | C62: 매출액(수익) | E62: 81273.74 | G62: 77743.11 | H62: 71565.75 | I62: 114027.69 | J62: 105934.32 | K62: 369270.87 | L62: 102992.29 | M62: 133812.83 | N62: 155652.76 | O62: 201959.49 | P62: 594417.37 | Q62: 182749.95 | R62: 194212.27 | S62: 170620.84 | T62: 194157.79 | U62: 741740.85 | V62: 224561.93 | W62: 231273.16 | X62: 221132.12 | Y62: 231843 | Z62: 908810.21 | AA62: 211821.54 | AB62: 243377.66
A63: 1 | C63: 매출원가 | E63: 70740.96 | G63: 66986.07 | H63: 61834.85 | I63: 93667.89 | J63: 90708.75 | K63: 313197.56 | L63: 89138.15 | M63: 116028.76 | N63: 139255.84 | O63: 186840.58 | P63: 531263.33 | Q63: 161818.12 | R63: 160110.6 | S63: 144443.56 | T63: 157786.06 | U63: 624158.34 | V63: 174552.63 | W63: 179708.49 | X63: 171776.57 | Y63: 169858.28 | Z63: 695895.97 | AA63: 148676.27 | AB63: 171921.09
A64: 1 | C64: 매출총이익 | E64: 10532.78 | G64: 10757.04 | H64: 9730.9 | I64: 20359.8 | J64: 15225.57 | K64: 56073.31 | L64: 13854.14 | M64: 17784.07 | N64: 16396.93 | O64: 15118.92 | P64: 63154.06 | Q64: 20931.83 | R64: 34101.67 | S64: 26177.28 | T64: 36371.73 | U64: 117582.51 | V64: 50009.3 | W64: 51564.68 | X64: 49355.55 | Y64: 61984.72 | Z64: 212914.25 | AA64: 63145.27 | AB64: 71456.57
A65: 1 | C65: 판관비 | E65: 7255.59 | G65: 6473.67 | H65: 7239.26 | I65: 8375.03 | J65: 9187.29 | K65: 31275.25 | L65: 10116.23 | M65: 9889.5 | N65: 11782.62 | O65: 14899.97 | P65: 46688.32 | Q65: 18323.81 | R65: 16322.21 | S65: 18493.15 | T65: 18997.04 | U65: 72136.21 | V65: 18901.91 | W65: 19921.13 | X65: 19493.05 | Y65: 23647.64 | Z65: 81963.73 | AA65: 22079.16 | AB65: 21056.74
A66: 1 | C66: 영업이익 | E66: 3277.2 | G66: 4283.38 | H66: 2491.64 | I66: 11984.76 | J66: 6038.28 | K66: 24798.06 | L66: 3737.91 | M66: 7894.56 | N66: 4614.3 | O66: 218.94 | P66: 16465.71 | Q66: 2608.02 | R66: 17779.47 | S66: 7684.12 | T66: 17374.69 | U66: 45446.3 | V66: 31107.39 | W66: 31643.55 | X66: 29862.51 | Y66: 38337.08 | Z66: 130950.53 | AA66: 41066.11 | AB66: 50399.83
A67: 1 | C67: 기타영업외수익 | E67: 9480.98 | G67: 102 | H67: 9016.94 | I67: 766.15 | J67: -1780.77 | K67: 8104.32 | L67: 109.18 | M67: 10327.58 | N67: 10606.52 | O67: 681.84 | P67: 21725.12 | Q67: 1600.37 | R67: -70.99 | S67: 769.98 | T67: 542.7 | U67: 2842.06 | V67: 297.34 | W67: 512.27 | X67: 445.4 | Y67: 5078.61 | Z67: 6333.62 | AA67: 401.44 | AB67: 2046.96
A68: 1 | C68: 기타영업외비용 | E68: 16885.62 | G68: 26.59 | H68: 32.62 | I68: 37.23 | J68: 54.55 | K68: 150.99 | L68: 33.29 | M68: 16853.91 | N68: 9399.76 | O68: 17926.06 | P68: 44213.02 | Q68: 131.42 | R68: 157.32 | S68: 417.03 | T68: 1012.82 | U68: 1718.59 | V68: 1563.26 | W68: 214.06 | X68: 249.7 | Y68: 447.35 | Z68: 2474.37 | AA68: 373.31 | AB68: 758.78
A69: 1 | C69: 종속기업,공동지배기업및관계기업관련손익 | E69: -1379.92 | G69: -147.01 | H69: 118.79 | I69: 168.73 | J69: -159.87 | K69: -19.36 | L69: -592.85 | M69: -4.99 | O69: 0 | Q69: 26.38 | R69: 84.69 | S69: -96.51
A70: 1 | C70: 지분법관련손익 | E70: -1379.92 | G70: -147.01 | H70: 118.79 | I70: 168.73 | J70: -159.87 | K70: -19.36 | L70: -592.85 | M70: -4.99 | O70: 0 | Q70: 26.38 | R70: 84.69 | S70: -96.51
A71: 1 | C71: 금융수익 | E71: 2773.94 | G71: 2302.86 | H71: 5733.97 | I71: 6341.59 | J71: 2126.71 | K71: 16505.13 | L71: 3299.16 | M71: 6460.19 | N71: 4055.81 | O71: 3381.27 | P71: 17196.43 | Q71: 6095.31 | R71: 4463.38 | S71: 5333.8 | T71: 7707.81 | U71: 23600.3 | V71: 7210.55 | W71: 25333.78 | X71: 1015.75 | Y71: 8144.09 | Z71: 41704.17 | AA71: 33312.07 | AB71: 10724.98
A72: 1 | C72: 금융비용 | E72: 1253.52 | G72: 2180.22 | H72: 6901.31 | I72: 17240.09 | J72: -5984.56 | K72: 20337.06 | L72: 7210.52 | M72: 1282.13 | N72: 7440.69 | O72: 1706.49 | P72: 17639.83 | Q72: 8369.49 | R72: 7068.48 | S72: 1419.27 | T72: 24770.87 | U72: 41628.11 | V72: 8121.01 | W72: 21257.65 | X72: 9284.22 | Y72: 6593.01 | Z72: 45255.89 | AA72: 52603.48 | AB72: 13778.26
A73: 1 | C73: 법인세비용차감전계속사업이익 | E73: -3986.95 | G73: 4334.42 | H73: 10427.41 | I73: 1983.91 | J73: 12154.35 | K73: 28900.09 | L73: -690.41 | M73: 6541.31 | N73: 2436.18 | O73: -15350.51 | P73: -7063.43 | Q73: 1829.18 | R73: 15030.75 | S73: 11855.1 | T73: -275.82 | U73: 28439.21 | V73: 28893.14 | W73: 35964.98 | X73: 21614.26 | Y73: 45391.23 | Z73: 131863.61 | AA73: 21732.84 | AB73: 48544.14
A74: 1 | C74: 법인세비용 | E74: 4695.85 | G74: 1231.35 | H74: 1490.01 | I74: 2831.9 | J74: 3085.95 | K74: 8639.21 | L74: 1254.02 | M74: -379.45 | N74: 3496.45 | O74: 2011.86 | P74: 6382.88 | Q74: 1809.05 | R74: 6364.56 | S74: -413.91 | T74: 355.55 | U74: 8115.25 | V74: 7037.28 | W74: 6607.14 | X74: 5951.8 | Y74: 10523.67 | Z74: 30119.89 | AA74: 6209.77 | AB74: 11982.47
A75: 1 | C75: 계속사업이익 | E75: -8682.8 | G75: 3103.07 | H75: 8937.4 | I75: -847.99 | J75: 9068.4 | K75: 20260.88 | L75: -1944.42 | M75: 6920.76 | N75: -1060.27 | O75: -17362.37 | P75: -13446.3 | Q75: 20.14 | R75: 8666.19 | S75: 12269.01 | T75: -631.38 | U75: 20323.96 | V75: 21855.86 | W75: 29357.84 | X75: 15662.46 | Y75: 34867.56 | Z75: 101743.72 | AA75: 15523.07 | AB75: 36561.67
A76: 1 | C76: 중단사업이익 | E76: -8.03 | G76: 6.18 | H76: 0.13 | I76: 0.18 | J76: -6.5 | K76: -0.01 | L76: 5.99 | M76: 0.09 | N76: 0.03 | O76: -9.24 | P76: -3.13 | R76: 0 | T76: -2.61 | V76: 0 | W76: -0.18 | X76: 0 | Y76: 0 | Z76: -0.18 | AA76: 0 | AB76: 0
A77: 1 | C77: 당기순이익 | E77: -8690.83 | G77: 3109.25 | H77: 8937.53 | I77: -847.81 | J77: 9061.9 | K77: 20260.87 | L77: -1938.44 | M77: 6920.85 | N77: -1060.24 | O77: -17371.61 | P77: -13449.44 | Q77: 20.14 | R77: 8666.19 | S77: 12269.01 | T77: -633.99 | U77: 20321.35 | V77: 21855.86 | W77: 29357.66 | X77: 15662.46 | Y77: 34867.56 | Z77: 101743.54 | AA77: 15523.07 | AB77: 36561.67
A78: 1 | C78: 총포괄손익 | E78: -7959.11 | G78: 3012.63 | H78: 11565.93 | I78: 3068.57 | J78: 3974.7 | K78: 21621.83 | L78: -803.78 | M78: 6953.18 | N78: -1258.17 | O78: -20412.49 | P78: -15521.26 | Q78: 39.87 | R78: 9951.45 | S78: 10992.91 | T78: 4066.67 | U78: 25050.9 | V78: 20796.92 | W78: 19594.05 | X78: 14689.3 | Y78: 41243.6 | Z78: 96323.87 | AA78: 16539.96 | AB78: 38032.95
A79: 1 | C79: 금융손익 | E79: 1520.42 | G79: 122.64 | H79: -1167.34 | I79: -10898.5 | J79: 8111.27 | K79: -3831.93 | L79: -3911.36 | M79: 5178.06 | N79: -3384.88 | O79: 1674.78 | P79: -443.4 | Q79: -2274.18 | R79: -2605.1 | S79: 3914.53 | T79: -17063.06 | U79: -18027.81 | V79: -910.46 | W79: 4076.13 | X79: -8268.47 | Y79: 1551.08 | Z79: -3551.72 | AA79: -19291.41 | AB79: -3053.28
A80: 1 | C80: 기타영업외손익 | E80: -7404.64 | G80: 75.41 | H80: 8984.32 | I80: 728.92 | J80: -1835.32 | K80: 7953.33 | L80: 75.89 | M80: -6526.33 | N80: 1206.76 | O80: -17244.22 | P80: -22487.9 | Q80: 1468.95 | R80: -228.31 | S80: 352.95 | T80: -470.12 | U80: 1123.47 | V80: -1265.92 | W80: 298.21 | X80: 195.7 | Y80: 4631.26 | Z80: 3859.25 | AA80: 28.13 | AB80: 1288.18
A81: 1 | C81: (지배주주지분)당기순이익 | E81: -8690.83 | G81: 3109.25 | H81: 8937.53 | I81: -847.81 | J81: 9061.9 | K81: 20260.87 | L81: -1938.44 | M81: 6920.85 | N81: -1060.24 | O81: -17371.61 | P81: -13449.44 | Q81: 20.14 | R81: 8666.19 | S81: 12269.01 | T81: -633.99 | U81: 20321.35 | V81: 21855.86 | W81: 29357.66 | X81: 15662.46 | Y81: 34867.56 | Z81: 101743.54 | AA81: 15523.07 | AB81: 36561.67
A82: 1 | C82: 이자수익 | G82: 369.45 | H82: 386.72 | I82: 486.91 | J82: 702.31 | K82: 1945.39 | L82: 797.34 | M82: 795.96 | N82: 1338.48 | O82: 1372.57 | P82: 4304.35 | Q82: 1273.5 | R82: 1137.14 | S82: 1473.11 | T82: 1198.9 | U82: 5082.65 | V82: 1270.42 | W82: 1282.52 | X82: 1014.47 | Y82: 787.12 | Z82: 4354.53 | AA82: 541.73 | AB82: 456.22
A83: 1 | C83: 이자비용 | G83: 209.11 | H83: 190.68 | I83: 628.13 | J83: -114.39 | K83: 913.53 | L83: 562.38 | M83: 751.46 | N83: 1461.77 | O83: 1750.71 | P83: 4526.32 | Q83: 1516.6 | R83: 1317.15 | S83: 1437.56 | T83: 786.44 | U83: 5057.75 | V83: 893.55 | W83: 2089.03 | X83: 1596.08 | Y83: 1513.43 | Z83: 6092.09 | AA83: 1859.84 | AB83: 750.21
A84: 1 | C84: 외환차익 | G84: 597.34 | H84: 2275.53 | I84: 2703.01 | J84: 1780.26 | K84: 7356.14 | L84: 1528.26 | M84: 1250.52 | N84: 2553.91 | O84: 1169.56 | P84: 6502.25 | Q84: 2302.92 | R84: 3024.79 | S84: 1326.81 | T84: 5114.12 | U84: 11768.64 | V84: 3427.68 | W84: 3023.88 | X84: 2493.72 | Y84: 7209.12 | Z84: 16154.4 | AA84: 7662.48 | AB84: 7573.53
A85: 1 | C85: 외환차손 | G85: 140.59 | H85: 856.79 | I85: 838.38 | J85: 4123.68 | K85: 5959.44 | L85: 1307.42 | M85: 474.57 | N85: 1264.85 | O85: 2476.11 | P85: 5522.95 | Q85: 653.64 | R85: 986.31 | S85: 2163.78 | T85: 1728.18 | U85: 5531.91 | V85: 3698.64 | W85: 6173.31 | X85: 1845 | Y85: 5523.74 | Z85: 17240.69 | AA85: 3579.48 | AB85: 6319.09
A86: 1 | C86: 외화환산이익 | G86: 307.2 | H86: 102.65 | I86: 1295.17 | J86: -1310.99 | K86: 394.03 | L86: 173.54 | M86: 748.29 | N86: -31.19 | O86: -697.26 | P86: 193.38 | Q86: 1097.53 | R86: -384.29 | S86: -440.06 | T86: 648.27 | U86: 921.45 | V86: 845.34 | W86: -804.9 | X86: 370.97 | Y86: 19.58 | Z86: 430.99 | AA86: 2644.71 | AB86: -1258.81
A87: 1 | C87: 이자손익 | G87: 160.34 | H87: 196.04 | I87: -141.22 | J87: 816.7 | K87: 1031.86 | L87: 234.96 | M87: 44.5 | N87: -123.29 | O87: -378.14 | P87: -221.97 | Q87: -243.1 | R87: -180.01 | S87: 35.55 | T87: 412.46 | U87: 24.9 | V87: 376.87 | W87: -806.51 | X87: -581.61 | Y87: -726.31 | Z87: -1737.56 | AA87: -1318.11 | AB87: -293.99
A88: 1 | C88: 외화환산손실 | H88: 139.03 | L88: 42.15 | M88: -7.7 | N88: 260.2 | O88: 392.34 | P88: 686.99 | Q88: 240.67 | R88: 84.62 | S88: 217.37 | T88: 236.82 | U88: 779.48 | V88: 550.86 | W88: 343.49 | X88: 10.95 | Y88: 930.51 | Z88: 1835.81 | AA88: 2223.97 | AB88: -711.33
A89: 1 | C89: (비지배주주지분)당기순이익 | V89: 0 | X89: 0 | Y89: 0 | AA89: 0 | AB89: 0
A90: 1 | C90: 배당금수익 | V90: 28.03 | W90: 118.37 | X90: 242.96 | Y90: 176.95 | Z90: 566.31 | AA90: 925.54 | AB90: 105.44
A91: 1 | C91: 파생상품이익 | W91: 4985.2 | X91: 3298.69 | Y91: -1619.12 | AA91: 8887.47 | AB91: -832.85
A92: 1 | C92: 파생상품손실 | W92: 12569.47 | X92: 6578.81 | Y92: -19146.35 | AA92: 28630.13 | AB92: 2484.26
A93: 1 | C93: 영업활동으로인한현금흐름 | E93: -530.36 | G93: -5034.76 | H93: -32214.02 | I93: -2962.09 | J93: 32412.02 | K93: -7798.85 | L93: -27449.22 | M93: -1996.2 | N93: 42214.56 | O93: 43750.73 | P93: 56519.87 | Q93: 13586.72 | R93: 72049.03 | S93: 38931.98 | T93: 25966.46 | U93: 150534.19 | V93: 68777.55 | W93: 24604.77 | X93: 1794.97 | Y93: 36365.7 | Z93: 131542.99 | AA93: 25882.55 | AB93: 42768.85
A94: 1 | C94: 배당금수취(CF) | E94: 260.85 | G94: 80.49 | H94: 644.68 | I94: 90.19 | J94: 146.97 | K94: 962.33 | L94: 304.32 | M94: 140.14 | N94: 720.71 | O94: 12.9 | P94: 1178.07 | Q94: 55.84 | R94: 1479.64 | S94: -1083.53 | T94: -176.43 | U94: 275.52 | V94: 55.98 | W94: 134.39 | X94: 259.83 | Y94: 176.95 | Z94: 627.15 | AA94: 940.99 | AB94: 105.44
A95: 1 | C95: 법인세납부(CF) | E95: -301.46 | G95: -2960.82 | H95: -4211.69 | I95: -3071.46 | J95: -5251.16 | K95: -15495.13 | L95: -3022.94 | M95: -1257.03 | N95: -1969.93 | O95: -4375.76 | P95: -10625.66 | Q95: -786.66 | R95: 854.31 | S95: 172.86 | T95: -1448.94 | U95: -1208.43 | V95: -5260.97 | W95: -4895.9 | X95: -5833.57 | Y95: -330.6 | Z95: -16321.04 | AA95: -14198.13 | AB95: -17637.08
A96: 1 | C96: 투자활동으로인한현금흐름 | E96: -326.98 | G96: 9328.36 | H96: -2663.32 | I96: -4977.9 | J96: -13212.11 | K96: -11524.97 | L96: -11398.89 | M96: -17625.6 | N96: 4821.83 | O96: -20225.96 | P96: -44428.62 | Q96: -18871.9 | R96: -14377.61 | S96: -27945 | T96: -20412.25 | U96: -81606.76 | V96: -7348.66 | W96: -60375.22 | X96: 5902.09 | Y96: -126078.18 | Z96: -187899.97 | AA96: -28805.59 | AB96: -10662.14
A97: 1 | C97: 무형자산의증가 | E97: 0.04 | G97: 1.64 | H97: 11.22 | I97: 0.02 | J97: 92.4 | K97: 105.28 | L97: 25.62 | M97: 0.15 | N97: 82.6 | O97: 122.2 | P97: 230.57 | S97: 0 | T97: 6228.67 | X97: 279.5 | AA97: 4.99 | AB97: 654.01
A98: 1 | C98: CAPEX | E98: 0.04 | G98: 1.64 | H98: 11.22 | I98: 0.02 | J98: 92.4 | K98: 105.28 | L98: 25.62 | M98: 0.15 | N98: 82.6 | O98: 122.2 | P98: 230.57 | S98: 0 | T98: 6228.67 | X98: 279.5 | AA98: 4.99 | AB98: 654.01
A99: 1 | C99: 재무활동으로인한현금흐름 | E99: -781.56 | G99: 1904.43 | H99: -6445.66 | I99: 27239.18 | J99: 2375.67 | K99: 25073.62 | L99: 11463.74 | M99: 13499.35 | N99: -27169.08 | O99: -3057.9 | P99: -5263.89 | Q99: -24574.07 | R99: -13619.22 | S99: -13939.73 | T99: -29532.14 | U99: -81665.16 | V99: -9148.45 | W99: 18791.52 | X99: -1132.35 | Y99: 47972.09 | Z99: 56482.81 | AA99: 26592.09 | AB99: -2354.78
A100: 1 | C100: 단기차입금의증가 | E100: 335 | G100: 296 | H100: 5212 | I100: 23543 | J100: 14494 | K100: 43545 | L100: 49488.22 | M100: 23388.64 | N100: 27481.68 | Q100: 5043.5 | R100: 1856.5 | S100: 34414.13 | T100: 18561.29 | U100: 59875.42 | V100: 905 | W100: 2040.82 | Y100: 66109.72 | AA100: 38870.23 | AB100: 46660.48
A101: 1 | C101: 장기차입금의증가 | E101: 0 | G101: 6105.91 | H101: 0 | I101: 8205.91 | J101: 214 | K101: 14525.82 | L101: 105.91 | M101: 2700 | N101: 4800 | O101: 0 | P101: 7605.91 | Q101: 4500 | S101: 86.63 | T101: 5446.17 | V101: 1235.05 | W101: 3764.95 | X101: 0 | Y101: 780 | Z101: 5780 | AA101: 1170 | AB101: 11330
A102: 1 | C102: 단기차입금의감소 | E102: 424 | G102: 461 | H102: 719 | I102: 506 | J102: 4639 | K102: 6325 | L102: 37677 | M102: 5718 | N102: 42967.43 | Q102: 32446.29 | R102: 7204.16 | S102: 36576.89 | T102: 48034.16 | U102: 124261.5 | V102: 5456.16 | W102: 19180.57 | Y102: 428.11 | AA102: 11585 | AB102: 38599.44
...

Sheet BS별도
B1: (백만원) | C1: 이름: BS별도H | E1: 4Q21 | F1: 2021 | G1: 1Q22 | H1: 2Q22 | I1: 3Q22 | J1: 4Q22 | K1: 2022 | L1: 1Q23 | M1: 2Q23 | N1: 3Q23 | O1: 4Q23 | P1: 2023 | Q1: 1Q24 | R1: 2Q24 | S1: 3Q24 | T1: 4Q24 | U1: 2024 | V1: 1Q25 | W1: 2Q25 | X1: 3Q25 | Y1: 4Q25 | Z1: 2025 | AA1: 1Q26 | AB1: 2Q26 | AC1: 3Q26 | AD1: 4Q26 | AE1: 2026 | AF1: 1Q27 | AG1: 2Q27 | AH1: 3Q27 | AI1: 4Q27 | AJ1: 2027 | AK1: 1Q28 | AL1: 2Q28 | AM1: 3Q28 | AN1: 4Q28 | AO1: 2028
B2: 별도 | D2: fin json(kship_fin.py)
B3: 한국카본(별) | C3: UPDATE: 26-10-11 | E3: 1 | F3: 2 | G3: 3 | H3: 4 | I3: 5 | J3: 6 | K3: 7 | L3: 8 | M3: 9 | N3: 10 | O3: 11 | P3: 12 | Q3: 13 | R3: 14 | S3: 15 | T3: 16 | U3: 17 | V3: 18 | W3: 19 | X3: 20 | Y3: 21 | Z3: 22 | AA3: 23 | AB3: 24 | AC3: 25 | AD3: 26 | AE3: 27 | AF3: 28 | AG3: 29 | AH3: 30 | AI3: 31 | AJ3: 32 | AK3: 33 | AL3: 34 | AM3: 35 | AN3: 36 | AO3: 37
B4: Account Code | C4: AccountNAME | E4: 2021.12 | F4: 2021.12A | G4: 2022.03 | H4: 2022.06 | I4: 2022.09 | J4: 2022.12 | K4: 2022.12A | L4: 2023.03 | M4: 2023.06 | N4: 2023.09 | O4: 2023.12 | P4: 2023.12A | Q4: 2024.03 | R4: 2024.06 | S4: 2024.09 | T4: 2024.12 | U4: 2024.12A | V4: 2025.03 | W4: 2025.06 | X4: 2025.09 | Y4: 2025.12 | Z4: 2025.12A | AA4: 2026.03 | AB4: 2026.06 | AC4: 2026.09 | AD4: 2026.12 | AE4: 2026.12A | AF4: 2027.03 | AG4: 2027.06 | AH4: 2027.09 | AI4: 2027.12 | AJ4: 2027.12A | AK4: 2028.03 | AL4: 2028.06 | AM4: 2028.09 | AN4: 2028.12 | AO4: 2028.12A
A5: 1 | C5: 유동자산 | E5: 248746.45 | F5: 248746.45 | G5: 257896.46 | H5: 218944.53 | I5: 253621.5 | J5: 280713.61 | K5: 280713.61 | L5: 306166.07 | M5: 339276.94 | N5: 373051.38 | O5: 367149.03 | P5: 367149.03 | Q5: 353683.87 | R5: 376731.18 | S5: 403039.96 | T5: 432718.6 | U5: 432718.6 | V5: 471861.71 | W5: 477678.27 | X5: 480158.59 | Y5: 555940.26 | Z5: 555940.26 | AA5: 581644.71 | AB5: 597758.17
A6: 1 | C6: 현금및현금성자산 | E6: 46080.64 | F6: 46080.64 | G6: 54670.01 | H6: 9739.52 | I6: 29000.13 | J6: 48142.19 | K6: 48142.19 | L6: 24372.65 | M6: 13701.82 | N6: 44846.31 | O6: 62936.33 | P6: 62936.33 | Q6: 35649.73 | R6: 77744.43 | S6: 75571.99 | T6: 53016.07 | U6: 53016.07 | V6: 103891.63 | W6: 87948.27 | X6: 87587.06 | Y6: 49811.98 | Z6: 49811.98 | AA6: 70042.16 | AB6: 74739.82
A7: 1 | C7: 단기금융상품 | E7: 14719.76 | F7: 14719.76 | G7: 14219.76 | H7: 13727.47 | I7: 12727.47 | J7: 13150.11 | K7: 13150.11 | L7: 11502.62 | M7: 10344.85 | N7: 10044.85 | O7: 10520 | P7: 10520 | Q7: 13520 | R7: 8234 | S7: 7834 | T7: 7600 | U7: 7600 | V7: 7100 | W7: 7100 | X7: 7100 | Y7: 5500 | Z7: 5500 | AA7: 5000 | AB7: 5150
A8: 1 | C8: 단기금융자산 | E8: 25353.67 | F8: 25353.67 | G8: 21993.81 | H8: 16312.85 | I8: 12727.47 | J8: 13154.72 | K8: 13154.72 | L8: 13515.37 | M8: 10344.85 | N8: 10044.85 | O8: 10520 | P8: 10520 | Q8: 13520 | R8: 8234 | S8: 7834 | T8: 7600 | U8: 7600 | V8: 7100 | W8: 15295.09 | X8: 18593.77 | Y8: 15374.65 | Z8: 15374.65 | AA8: 7083.06 | AB8: 6400.21
A9: 1 | C9: 매출채권및기타채권 | E9: 32524.46 | F9: 32524.46 | G9: 34702.48 | H9: 37535.83 | I9: 46786.29 | J9: 35262.81 | K9: 35262.81 | L9: 54868.91 | M9: 70167.13 | N9: 76449.1 | O9: 94009.52 | P9: 94009.52 | Q9: 105242.86 | R9: 78377.46 | S9: 68769.26
A10: 1 | C10: 재고자산 | E10: 85499.77 | F10: 85499.77 | G10: 92992.14 | H10: 123394.54 | I10: 128635.18 | J10: 147190.92 | K10: 147190.92 | L10: 172634.95 | M10: 180981.37 | N10: 201213.14 | O10: 163568.6 | P10: 163568.6 | Q10: 167932.89 | R10: 169678.73 | S10: 180748.87 | T10: 182171.9 | U10: 182171.9 | V10: 176804.66 | W10: 174801.55 | X10: 176997.82 | Y10: 182288.52 | Z10: 182288.52 | AA10: 186964.1 | AB10: 189634.93
A11: 1 | C11: 기타유동자산 | E11: 2215.81 | F11: 2215.81 | G11: 2390.22 | H11: 4887.9 | I11: 4875.78 | J11: 5826.38 | K11: 5826.38 | L11: 7190.99 | M11: 8892.45 | N11: 13114.42 | O11: 9022.23 | P11: 9022.23 | Q11: 11395.21 | R11: 13116.5 | S11: 11168.74 | T11: 11697.65 | U11: 11697.65 | V11: 15563.66 | W11: 18886.01 | X11: 19227.14 | Y11: 14684.72 | Z11: 14684.72 | AA11: 22663.69 | AB11: 23608.04
A12: 1 | C12: 매각예정비유동자산및처분자산 | E12: 10.54 | F12: 10.54 | J12: 10.54 | K12: 10.54 | T12: 0 | U12: 0
A13: 1 | C13: 비유동자산 | E13: 243781.11 | F13: 243781.11 | G13: 242478.9 | H13: 290951.43 | I13: 301983.51 | J13: 293067.35 | K13: 293067.35 | L13: 294236.72 | M13: 301788.82 | N13: 410245.08 | O13: 417173.4 | P13: 417173.4 | Q13: 432534 | R13: 443492.06 | S13: 439172.51 | T13: 437275.81 | U13: 437275.81 | V13: 446343.88 | W13: 456644.18 | X13: 470798.85 | Y13: 477082.48 | Z13: 477082.48 | AA13: 493642.7 | AB13: 524513.85
A14: 1 | C14: 장기금융자산 | E14: 8584.58 | F14: 8584.58 | G14: 73978.96 | H14: 107417.31 | I14: 107465.07 | J14: 6999.42 | K14: 6999.42 | L14: 4987.57 | M14: 4543.44 | N14: 484 | O14: 350 | P14: 350 | Q14: 350 | R14: 350 | S14: 350 | T14: 27523.57 | U14: 27523.57 | V14: 24682.26 | W14: 26827.15 | X14: 24945.72 | Y14: 23586.7 | Z14: 23586.7 | AA14: 24440.57 | AB14: 23412.37
A15: 1 | C15: 투자자산 | E15: 12532.01 | F15: 12532.01 | G15: 99581.24 | H15: 188034.21 | I15: 200650.36 | J15: 21792.81 | K15: 21792.81 | L15: 19780.96 | M15: 40622.01 | N15: 56816.71 | O15: 45799.16 | P15: 45799.16 | Q15: 47353.47 | R15: 1401.38 | S15: 1401.38 | T15: 64241.24 | U15: 64241.24 | V15: 68225.39 | W15: 70370.28 | X15: 78469.32 | Y15: 81011.58 | Z15: 81011.58 | AA15: 89516.62 | AB15: 23412.37
A16: 1 | C16: 종속기업및관계기업투자 | E16: 3947.43 | F16: 3947.43 | G16: 7894.86 | H16: 32988.78 | I16: 39323.88 | J16: 14793.39 | K16: 14793.39 | L16: 14793.39 | M16: 36078.57 | N16: 56332.71 | O16: 45449.16 | P16: 45449.16 | Q16: 47003.47 | R16: 1051.38 | S16: 1051.38 | T16: 36717.67 | U16: 36717.67 | V16: 43543.13 | W16: 43543.13 | X16: 53523.6 | Y16: 57424.88 | Z16: 57424.88 | AA16: 65076.05
A17: 1 | C17: 유형자산 | E17: 165615.79 | F17: 165615.79 | G17: 168139.11 | H17: 170828.77 | I17: 176590.04 | J17: 183353.36 | K17: 183353.36 | L17: 186215.93 | M17: 189963.46 | N17: 228162.59 | O17: 243360.55 | P17: 243360.55 | Q17: 255029.94 | R17: 267278.82 | S17: 280062.19 | T17: 287326.5 | U17: 287326.5 | V17: 294531.33 | W17: 308117.49 | X17: 310938.03 | Y17: 313132.91 | Z17: 313132.91 | AA17: 313735.48 | AB17: 322609.85
A18: 1 | C18: 사용권자산 | E18: 1732.77 | F18: 1732.77 | G18: 2122.97 | H18: 1935.21 | I18: 2155.97 | J18: 2915.76 | K18: 2915.76 | L18: 2714.91 | M18: 2855.7 | N18: 2761.39 | O18: 2428.69 | P18: 2428.69 | Q18: 6066.96 | R18: 5631.85 | S18: 5458.32 | T18: 5708.11 | U18: 5708.11 | V18: 5281.24 | W18: 5187.47 | X18: 9404.63 | Y18: 6102.41 | Z18: 6102.41 | AA18: 7156.09 | AB18: 7886.45
A19: 1 | C19: 기타비유동자산 | E19: 2449.14 | F19: 2449.14 | G19: 2839.34 | H19: 2651.58 | I19: 2872.34 | J19: 6249.36 | K19: 6249.36 | L19: 6161.08 | M19: 6283.8 | N19: 6241.68 | O19: 5106.94 | P19: 5106.94 | Q19: 7783.44 | R19: 8320.79 | S19: 7902.6 | T19: 6424.48 | U19: 6424.48 | V19: 5997.61 | W19: 5903.84 | X19: 10121 | Y19: 6818.78 | Z19: 6818.78 | AA19: 7156.09 | AB19: 7886.45
A20: 1 | C20: 무형자산 | E20: 2184.22 | F20: 2184.22 | G20: 2174.31 | H20: 2173.79 | I20: 2162.19 | J20: 2156.19 | K20: 2156.19 | L20: 2146.74 | M20: 2135.36 | N20: 37987.56 | O20: 41796.7 | P20: 41796.7 | Q20: 41100.43 | R20: 40417.4 | S20: 40230.45 | T20: 44496.83 | U20: 44496.83 | V20: 43914.07 | W20: 42974.18 | X20: 42142.16 | Y20: 41415.16 | Z20: 41415.16 | AA20: 41216.51 | AB20: 40374.84
A21: 1 | C21: 자산총계 | E21: 492538.1 | F21: 492538.1 | G21: 500385.9 | H21: 509906.49 | I21: 555615.55 | J21: 573791.49 | K21: 573791.49 | L21: 600402.79 | M21: 641065.76 | N21: 783296.46 | O21: 784322.42 | P21: 784322.42 | Q21: 786217.86 | R21: 820223.24 | S21: 842212.47 | T21: 869994.41 | U21: 869994.41 | V21: 918205.59 | W21: 934322.44 | X21: 950957.45 | Y21: 1033022.7 | Z21: 1033022.7 | AA21: 1075287.4 | AB21: 1122272
A22: 1 | C22: 유동부채 | E22: 78851.69 | F22: 78851.69 | G22: 83967.9 | H22: 88690.98 | I22: 113909.44 | J22: 149013.55 | K22: 149013.55 | L22: 181495.52 | M22: 214975.25 | N22: 249700.03 | O22: 280286.67 | P22: 280286.67 | Q22: 279433.35 | R22: 302629.05 | S22: 312526.45 | T22: 354900.49 | U22: 354900.49 | V22: 387482.26 | W22: 348751.57 | X22: 344603.09 | Y22: 409857.46 | Z22: 409857.46 | AA22: 457223.22 | AB22: 400651.83
A23: 1 | C23: 기타유동금융부채 | E23: 391.38 | F23: 391.38 | G23: 514.31 | H23: 2591.2 | I23: 8041.3 | J23: 1801.08 | K23: 1801.08 | L23: 2916.01 | M23: 2856.94 | N23: 3516.42 | O23: 1059.06 | P23: 1059.06 | Q23: 2527.98 | R23: 3985.62 | S23: 815.26 | T23: 8836.29 | U23: 8836.29 | V23: 8348.9 | W23: 1965.76 | X23: 3812.27 | Y23: 5320.45 | Z23: 5320.45 | AA23: 10209.77 | AB23: 12596.44
A24: 1 | C24: 단기금융부채 | E24: 1055.2 | F24: 1055.2 | G24: 1434.95 | H24: 3525.58 | I24: 9065.83 | J24: 3325.52 | K24: 3325.52 | L24: 4431.17 | M24: 4476.72 | N24: 5132.7 | O24: 2509.84 | P24: 2509.84 | Q24: 4293.27 | R24: 5527.96 | S24: 1969.97 | T24: 10433.1 | U24: 10433.1 | V24: 9781.18 | W24: 28514.07 | X24: 39100.14 | Y24: 35702.37 | Z24: 35702.37 | AA24: 53488.96 | AB24: 18180.41
A25: 1 | C25: 당기법인세부채(미지급법인세) | E25: 6264.54 | F25: 6264.54 | G25: 5263.87 | H25: 2853.42 | I25: 4146.91 | J25: 5247.03 | K25: 5247.03 | L25: 4126.83 | M25: 1598.55 | N25: 5135.61 | O25: 2841.17 | P25: 2841.17 | Q25: 3941.08 | R25: 13396.71 | S25: 9700.45 | T25: 10435.32 | U25: 10435.32 | V25: 10812.47 | W25: 9771.88 | X25: 12877.18 | Y25: 30700.86 | Z25: 30700.86 | AA25: 27257.11 | AB25: 16261.52
A26: 1 | C26: 유동리스부채 | E26: 663.82 | F26: 663.82 | G26: 920.64 | H26: 934.38 | I26: 1024.53 | J26: 1524.44 | K26: 1524.44 | L26: 1515.16 | M26: 1619.78 | N26: 1616.28 | O26: 1450.78 | P26: 1450.78 | Q26: 1765.29 | R26: 1542.34 | S26: 1154.71 | T26: 1596.81 | U26: 1596.81 | V26: 1432.28 | W26: 1354.19 | X26: 3514.95 | Y26: 2247.03 | Z26: 2247.03 | AA26: 3193.23 | AB26: 4128.78
A27: 1 | C27: 리스부채 | E27: 1570.81 | F27: 1570.81 | G27: 1870.55 | H27: 1729.16 | I27: 1980.28 | J27: 2768.12 | K27: 2768.12 | L27: 2609.61 | M27: 2726.44 | N27: 2679.6 | O27: 2387.63 | P27: 2387.63 | Q27: 5350.15 | R27: 4914.51 | S27: 4828.08 | T27: 5076.4 | U27: 5076.4 | V27: 4706.69 | W27: 4618.57 | X27: 8857.69 | Y27: 5611.94 | Z27: 5611.94 | AA27: 6901.19 | AB27: 7627.75
A28: 1 | C28: 유동성장기부채 | E28: 15056.6 | F28: 15056.6 | G28: 11306.6 | H28: 7556.6 | I28: 3822.35 | J28: 88.1 | K28: 88.1 | L28: 633.41 | M28: 1467.56 | N28: 3755.06 | O28: 14623.96 | P28: 14623.96 | Q28: 16433.3 | R28: 16397.2 | S28: 6067.2 | T28: 5930.95 | U28: 5930.95 | V28: 4724.7 | W28: 5518.45 | X28: 16312.2 | Y28: 3912.2 | Z28: 3912.2 | AA28: 18462.28 | AB28: 2826.27
... A33: 1 | C33: 장기금융부채 | E33: 906.99 | F33: 906.99 | G33: 1072.32 | H33: 3582.68 | I33: 12316.15 | J33: 1514.73 | K33: 1514.73 | L33: 1571.92 | M33: 1203.89 | N33: 1992.89 | O33: 936.85 | P33: 936.85 | Q33: 4637.51 | R33: 5542.57 | S33: 4045.73 | T33: 13453.19 | U33: 13453.19 | V33: 12795.36 | W33: 3775.6 | X33: 9002.35 | Y33: 8814.34 | Z33: 8814.34 | AA33: 12108.75 | AB33: 10177.23
A34: 1 | C34: 확정급여부채 | E34: 1664.66 | F34: 1664.66 | G34: 1954.98 | H34: 172 | I34: 549.94 | O34: 45.16 | P34: 45.16 | Q34: 45.16 | R34: 348.22 | S34: 525.21 | T34: 349.23 | U34: 349.23 | V34: 363.25 | W34: 625.03 | X34: 705.76 | Y34: 590.61 | Z34: 590.61 | AA34: 677.44 | AB34: 761.36
A35: 1 | C35: 이연법인세부채 | E35: 4153.83 | F35: 4153.83 | G35: 3393.59 | H35: 3179.71 | I35: 1288.92 | N35: 1103.74 | O35: 4981.12 | P35: 4981.12 | Q35: 4404.5 | R35: 3666.58 | S35: 4796.24
A36: 1 | C36: 기타비유동부채 | E36: 1510.58 | F36: 1510.58 | G36: 1510.58 | H36: 2213.47 | I36: 2213.47 | J36: 6784.07 | K36: 6784.07 | L36: 5972.26 | M36: 2764.98 | N36: 3473.65 | O36: 2113.34 | P36: 2113.34 | Q36: 1309.25 | R36: 1309.25 | S36: 181.82 | T36: 696.44 | U36: 696.44 | V36: 696.44 | W36: 696.44 | X36: 696.44 | Y36: 4137 | Z36: 4137 | AA36: 8701.89 | AB36: 11693.41
A37: 1 | C37: 부채총계 | E37: 88046.53 | F37: 88046.53 | G37: 98949.91 | H37: 104875.22 | I37: 145490.31 | J37: 172708.85 | K37: 172708.85 | L37: 203982.65 | M37: 235369.12 | N37: 298249.62 | O37: 318467.94 | P37: 318467.94 | Q37: 321725.27 | R37: 343806.87 | S37: 351324.34 | T37: 390081.16 | U37: 390081.16 | V37: 419872.35 | W37: 394074.04 | X37: 394917.62 | Y37: 448358.94 | Z37: 448358.94 | AA37: 490241.86 | AB37: 444883.47
A38: 1 | C38: 자본금 | E38: 21980.38 | F38: 21980.38 | G38: 21980.38 | H38: 21980.38 | I38: 21980.38 | J38: 21980.38 | K38: 21980.38 | L38: 21980.38 | M38: 21980.38 | N38: 21980.38 | O38: 25954.23 | P38: 25954.23 | Q38: 25954.23 | R38: 25954.23 | S38: 25954.23 | T38: 192789.69 | U38: 192789.69 | V38: 192789.69 | W38: 192789.69 | X38: 192789.69 | Y38: 122789.69 | Z38: 122789.69 | AA38: 122789.69 | AB38: 177321.71
A39: 1 | C39: 자본잉여금 | E39: 74960.11 | F39: 74960.11 | G39: 74960.11 | H39: 74960.11 | I39: 74960.11 | J39: 74960.11 | K39: 74960.11 | L39: 74960.11 | M39: 74960.11 | N39: 74960.11 | O39: 166835.46 | P39: 166835.46 | Q39: 166835.46 | R39: 166835.46 | S39: 166835.46 | T39: 166835.46 | U39: 166835.46 | V39: 166835.46 | W39: 166835.46 | X39: 166835.46 | Y39: 96835.46 | Z39: 96835.46 | AA39: 96835.46 | AB39: 151014.17
A40: 1 | C40: 이익잉여금 | E40: 302311.08 | F40: 302311.08 | G40: 299390.5 | H40: 302985.78 | I40: 308079.74 | J40: 299038.94 | K40: 299038.94 | L40: 294376.44 | M40: 303652.93 | N40: 308292.13 | O40: 289114.7 | P40: 289114.7 | Q40: 287756.44 | R40: 299680.2 | S40: 314151.81 | T40: 303177 | U40: 303177 | V40: 321596.98 | W40: 346144.09 | X40: 361935.51 | Y40: 460409.17 | Z40: 460409.17 | AA40: 449602.89 | AB40: 487112.81
A41: 1 | C41: 기타포괄이익누계액 | E41: -3298.12 | F41: -3298.12 | G41: -3433.13 | H41: -3433.13 | I41: -3433.13 | J41: -3434.91 | K41: -3434.91 | L41: -3434.91 | M41: -3434.91 | N41: -3434.91 | O41: -2266.08 | P41: -2266.08 | Q41: -2269.71 | R41: -2269.69 | S41: -2269.55 | T41: -2264.91 | U41: -2264.91 | V41: -2264.91 | W41: -2264.91 | X41: -2264.91 | Y41: -704.91 | Z41: -704.91 | AA41: -704.91 | AB41: -704.91
A42: 1 | C42: 기타자본 | E42: 8538.13 | F42: 8538.13 | G42: 13643.13 | H42: 13643.13 | I42: 13643.13 | J42: 8538.13 | K42: 8538.13 | L42: 8538.13 | M42: 8538.13 | N42: 83249.12 | O42: -13783.82 | P42: -13783.82 | Q42: -13783.82 | R42: -13783.82 | S42: -13783.82 | T42: -13788.53 | U42: -13788.53 | V42: -13788.53 | W42: 3579.53 | X42: 3579.53 | Y42: 2169.86 | Z42: 2169.86 | AA42: 13357.88 | AB42: 13658.93
A43: 1 | C43: 자본총계 | E43: 404491.57 | F43: 404491.57 | G43: 401435.99 | H43: 405031.27 | I43: 410125.23 | J43: 401082.64 | K43: 401082.64 | L43: 396420.15 | M43: 405696.64 | N43: 485046.84 | O43: 465854.48 | P43: 465854.48 | Q43: 464492.6 | R43: 476416.37 | S43: 490888.13 | T43: 479913.25 | U43: 479913.25 | V43: 498333.24 | W43: 540248.4 | X43: 556039.82 | Y43: 584663.8 | Z43: 584663.8 | AA43: 585045.55 | AB43: 677388.55
A44: 1 | C44: 부채와자본총계 | E44: 492538.1 | F44: 492538.1 | G44: 500385.9 | H44: 509906.49 | I44: 555615.55 | J44: 573791.49 | K44: 573791.49 | L44: 600402.79 | M44: 641065.76 | N44: 783296.46 | O44: 784322.42 | P44: 784322.42 | Q44: 786217.86 | R44: 820223.24 | S44: 842212.47 | T44: 869994.41 | U44: 869994.41 | V44: 918205.59 | W44: 934322.44 | X44: 950957.45 | Y44: 1033022.7 | Z44: 1033022.7 | AA44: 1075287.4 | AB44: 1122272
A45: 1 | C45: 지배주주지분 | E45: 404491.57 | F45: 404491.57 | G45: 401435.99 | H45: 405031.27 | I45: 410125.23 | J45: 401082.64 | K45: 401082.64 | L45: 396420.15 | M45: 405696.64 | N45: 485046.84 | O45: 465854.48 | P45: 465854.48 | Q45: 464492.6 | R45: 476416.37 | S45: 490888.13 | T45: 479913.25 | U45: 479913.25 | V45: 498333.24 | W45: 540248.4 | X45: 556039.82 | Y45: 584663.8 | Z45: 584663.8 | AA45: 585045.55 | AB45: 677388.55
A46: 1 | C46: 총차입금 | E46: 16015.37 | F46: 16015.37 | G46: 18357.13 | H46: 18592.98 | I46: 46034.75 | J46: 52484.6 | K46: 52484.6 | L46: 63576.36 | M46: 82998.47 | N46: 126142.3 | O46: 125380.06 | P46: 125380.06 | Q46: 108514.01 | R46: 103751.73 | S46: 92697.43 | T46: 63834.75 | U46: 63834.75 | V46: 56209.5 | W46: 54501.66 | X46: 54708.57 | Y46: 103871.73 | Z46: 103871.73 | AA46: 117884.88 | AB46: 135447.94
A47: 1 | C47: 순차입금 | E47: -55418.94 | F47: -55418.94 | G47: -58306.69 | H47: -7459.39 | I47: 4307.15 | J47: -8812.31 | K47: -8812.31 | L47: 25688.34 | M47: 58951.8 | N47: 71251.14 | O47: 51923.73 | P47: 51923.73 | Q47: 59344.28 | R47: 17773.3 | S47: 9291.44 | T47: 3218.68 | U47: 3218.68 | V47: -54782.13 | W47: -48741.7 | X47: -51472.26 | Y47: 38685.1 | Z47: 38685.1 | AA47: 40759.66 | AB47: 54307.91
A48: 1 | C48: 이자발생자산 | E48: 80018.89 | F48: 80018.89 | G48: 150642.78 | H48: 133469.68 | I48: 149192.67 | J48: 68296.33 | K48: 68296.33 | L48: 42875.59 | M48: 28590.11 | N48: 55375.16 | O48: 73806.33 | P48: 73806.33 | Q48: 49519.73 | R48: 86328.43 | S48: 83755.99 | T48: 88139.64 | U48: 88139.64 | V48: 135673.89 | W48: 130070.51 | X48: 131126.55 | Y48: 88773.33 | Z48: 88773.33 | AA48: 101565.79 | AB48: 104552.4
A49: 1 | C49: 기타유동금융자산 | G49: 73141.62 | H49: 43386.74 | I49: 44324.13
A50: 1 | C50: 장기대여금 | G50: 17707.42 | H50: 47628.12 | I50: 53861.41
A51: 1 | C51: 매입채무및기타채무 | G51: 58146.85 | H51: 59995.15 | I51: 58243.78 | L51: 5592.88 | Q51: 5413.95
A52: 1 | C52: 기타비유동금융부채 | G52: 122.41 | H52: 2787.9 | I52: 11360.4 | J52: 271.05 | K52: 271.05 | L52: 477.47 | M52: 97.23 | N52: 929.57 | Q52: 1052.65 | R52: 2170.4 | S52: 372.36 | T52: 9973.6 | U52: 9973.6 | V52: 9520.95 | W52: 511.22 | X52: 3659.61 | Y52: 5449.43 | Z52: 5449.43 | AA52: 8400.79 | AB52: 6678.26
A53: 1 | C53: 단기차입금 | H53: 4000 | I53: 27000 | J53: 37000 | K53: 37000 | L53: 48000 | M53: 65105.91 | N53: 80407.94 | O53: 80651.3 | P53: 80651.3 | Q53: 60185.21 | R53: 57043.33 | S53: 57381.33 | T53: 39840.95 | U53: 39840.95 | V53: 37500 | W53: 20000 | X53: 10000 | Y53: 75000 | Z53: 75000 | AA53: 89000 | AB53: 112000
A54: 1 | C54: 이연법인세자산 | J54: 1232.07 | K54: 1232.07 | L54: 1903.38 | M54: 865.45 | N54: 47.64 | W54: 0 | Y54: 2321.84 | Z54: 2321.84 | AA54: 0 | AB54: 2195.56
A55: 1 | C55: 단기금융부채(face) | N55: 80407.94 | O55: 80651.3 | P55: 80651.3 | Q55: 60185.21 | R55: 57043.33 | S55: 57381.33 | T55: 39840.95 | U55: 39840.95 | V55: 37500 | W55: 20000 | X55: 10000 | Y55: 75000 | Z55: 75000 | AA55: 89000 | AB55: 112000
A56: 1 | C56: 사채 | N56: 10000 | O56: 10000 | P56: 10000 | Q56: 10000 | R56: 10000 | S56: 10000 | W56: 11576.46 | X56: 12567.67 | Y56: 13558.88 | Z56: 13558.88 | AA56: 0 | AB56: 0
A57: 1 | C57: 투자부동산 | O57: 15730.94 | P57: 15730.94 | Q57: 15719.73 | R57: 15708.52 | S57: 15697.31 | T57: 15686.1 | U57: 15686.1 | V57: 15674.89 | W57: 15663.68 | X57: 15652.47 | Y57: 15641.26 | Z57: 15641.26 | AA57: 15630.05 | AB57: 15789.67
A58: 1 | C58: 장기금융부채(face) | S58: 19248.9
A59: 1 | C59: 단기투자자산(공정가치) | T59: 19695.35 | U59: 19695.35 | V59: 11693.26 | W59: 52142.18 | X59: 57482.09 | Y59: 164649.52 | Z59: 164649.52 | AA59: 164064.74 | AB59: 172797.13
A60: 1 | C60: 보통주자본금 | T60: 25954.23 | U60: 25954.23 | V60: 25954.23 | W60: 25954.23 | X60: 25954.23 | Y60: 25954.23 | Z60: 25954.23 | AA60: 25954.23 | AB60: 26307.54
A61: 1 | C61: 유동파생상품자산 | W61: 8195.09 | X61: 11493.77 | Y61: 9874.65 | Z61: 9874.65 | AA61: 2083.06 | AB61: 1250.21
A62: 1 | C62: 단기파생상품부채 | W62: 25194.12 | X62: 31772.92 | Y62: 28134.89 | Z62: 28134.89 | AA62: 40085.96 | AB62: 1455.19
A63: 1 | C63: 매출액(수익) | E63: 79131.27 | G63: 75323.69 | H63: 64875.39 | I63: 102564.24 | J63: 97444.86 | K63: 340208.18 | L63: 97127.85 | M63: 125767.72 | N63: 152032.53 | O63: 198084.36 | P63: 573012.46 | Q63: 176235.66 | R63: 185261.08 | S63: 162510.94 | T63: 184932.6 | U63: 708940.28 | V63: 214893.09 | W63: 219617.35 | X63: 210154.67 | Y63: 221709.37 | Z63: 866374.48 | AA63: 200112.82 | AB63: 229321.95
A64: 1 | C64: 매출원가 | E64: 68615.11 | G64: 66051.42 | H64: 55528.96 | I64: 81505.8 | J64: 81624.52 | K64: 284710.7 | L64: 84847.72 | M64: 107544.7 | N64: 135598.4 | O64: 181335.13 | P64: 509325.95 | Q64: 153658.39 | R64: 152105.26 | S64: 137402.04 | T64: 149015.41 | U64: 592181.1 | V64: 165172.88 | W64: 168358.56 | X64: 160132.06 | Y64: 162219.72 | Z64: 655883.22 | AA64: 139002.4 | AB64: 159850.76
A65: 1 | C65: 매출총이익 | E65: 10516.15 | G65: 9272.26 | H65: 9346.43 | I65: 21058.44 | J65: 15820.34 | K65: 55497.47 | L65: 12280.14 | M65: 18223.02 | N65: 16434.13 | O65: 16749.23 | P65: 63686.52 | Q65: 22577.27 | R65: 33155.82 | S65: 25108.89 | T65: 35917.18 | U65: 116759.16 | V65: 49720.2 | W65: 51258.79 | X65: 50022.61 | Y65: 59489.65 | Z65: 210491.25 | AA65: 61110.42 | AB65: 69471.19
A66: 1 | C66: 판관비 | E66: 6994.43 | G66: 5793.77 | H66: 6476.92 | I66: 6973.26 | J66: 7534.46 | K66: 26778.41 | L66: 8323.72 | M66: 8192.93 | N66: 9976.82 | O66: 12070.91 | P66: 38564.38 | Q66: 15057.37 | R66: 13951.64 | S66: 16276.27 | T66: 16623.56 | U66: 61908.84 | V66: 16470.92 | W66: 17834.81 | X66: 17216.27 | Y66: 20757.14 | Z66: 72279.14 | AA66: 19537.55 | AB66: 17960.34
A67: 1 | C67: 영업이익 | E67: 3521.71 | G67: 3478.5 | H67: 2869.51 | I67: 14085.18 | J67: 8285.87 | K67: 28719.06 | L67: 3956.41 | M67: 10030.09 | N67: 6457.31 | O67: 4678.32 | P67: 25122.13 | Q67: 7519.89 | R67: 19204.18 | S67: 8832.63 | T67: 19293.62 | U67: 54850.32 | V67: 33249.29 | W67: 33423.98 | X67: 32806.34 | Y67: 38732.5 | Z67: 138212.11 | AA67: 41572.86 | AB67: 51510.85
A68: 1 | C68: 기타영업외수익 | E68: 8792.84 | G68: 78.53 | H68: 87.92 | I68: 129 | J68: 124.86 | K68: 420.31 | L68: 85.15 | M68: 10300.19 | N68: 10534.04 | O68: 322.67 | P68: 21242.05 | Q68: 483.83 | R68: 748.16 | S68: 586.4 | T68: 519.57 | U68: 2337.96 | V68: 262.66 | W68: 986.49 | X68: 423.6 | Y68: 5009.89 | Z68: 6682.64 | AA68: 385.87 | AB68: 2022
A69: 1 | C69: 기타영업외비용 | E69: 19131.47 | G69: 25.3 | H69: 31.75 | I69: 36.55 | J69: 8194.86 | K69: 8288.46 | L69: 30.54 | M69: 16852.38 | N69: 1830.56 | O69: 12220.55 | P69: 30934.03 | Q69: 47.75 | R69: 56.09 | S69: 370.95 | T69: 13519.95 | U69: 13994.74 | V69: 1529.14 | W69: 192.63 | X69: 179.94 | Y69: 9796.83 | Z69: 11698.54 | AA69: 125.05 | AB69: 193.57
A70: 1 | C70: 금융수익 | E70: 3275.81 | G70: 3403.27 | H70: 8515.7 | I70: 11283.18 | J70: -2033.75 | K70: 21168.4 | L70: 5052.52 | M70: 7012.56 | N70: 4820.31 | O70: 2658.84 | P70: 19544.23 | Q70: 7123.84 | R70: 5299.85 | S70: 4137.4 | T70: 10254.46 | U70: 26815.55 | V70: 7666.95 | W70: 27279.16 | X70: 766.02 | Y70: 7989.56 | Z70: 43701.69 | AA70: 33748.23 | AB70: 12747.05
A71: 1 | C71: 금융비용 | E71: 4388.48 | G71: 2275.24 | H71: 7592.83 | I71: 18185.49 | J71: 4174.99 | K71: 32228.55 | L71: 7346.16 | M71: 1843.44 | N71: 12215.9 | O71: 9652 | P71: 31057.5 | Q71: 8926.3 | R71: 7337.82 | S71: 299.57 | T71: 29654.27 | U71: 46217.96 | V71: 8333.2 | W71: 22847.91 | X71: 8966.52 | Y71: 7493.25 | Z71: 47640.88 | AA71: 52067.97 | AB71: 15496.97
A72: 1 | C72: 법인세비용차감전계속사업이익 | E72: -7929.59 | G72: 4659.75 | H72: 3848.54 | I72: 7275.32 | J72: -5992.87 | K72: 9790.74 | L72: 1717.39 | M72: 8647.02 | N72: 7765.21 | O72: -14212.73 | P72: 3916.89 | Q72: 6153.52 | R72: 17858.29 | S72: 12885.9 | T72: -13106.58 | U72: 23791.13 | V72: 31316.56 | W72: 38649.09 | X72: 24849.49 | Y72: 34441.87 | Z72: 129257.01 | AA72: 23513.94 | AB72: 50589.35
A73: 1 | C73: 법인세비용 | E73: 4607.41 | G73: 1015.08 | H73: 989.35 | I73: 2020.25 | J73: 3591.67 | K73: 7616.35 | L73: 964.31 | M73: -552.64 | N73: 3253.08 | O73: 2144.01 | P73: 5808.76 | Q73: 1487.95 | R73: 6456.08 | S73: -1629.87 | T73: -414.36 | U73: 5899.8 | V73: 6894.5 | W73: 6818.45 | X73: 5614.42 | Y73: 10212.47 | Z73: 29539.84 | AA73: 5514.61 | AB73: 12050.61
A74: 1 | C74: 당기순이익 | E74: -12537 | G74: 3644.67 | H74: 2859.19 | I74: 5255.07 | J74: -9584.54 | K74: 2174.39 | L74: 753.08 | M74: 9199.65 | N74: 4512.13 | O74: -16356.74 | P74: -1891.88 | Q74: 4665.56 | R74: 11402.21 | S74: 14515.77 | T74: -12692.22 | U74: 17891.32 | V74: 24422.06 | W74: 31830.64 | X74: 19235.07 | Y74: 24229.41 | Z74: 99717.18 | AA74: 17999.33 | AB74: 38538.74
... A83: 1 | C83: 투자활동으로인한현금흐름 | E83: -2645.38 | G83: 9141.13 | H83: -11629.29 | I83: -5379.92 | J83: -19645.68 | K83: -27513.76 | L83: -9377.64 | M83: -25641.57 | N83: -1519.39 | O83: -23322.07 | P83: -59860.67 | Q83: -18279.05 | R83: -19022.39 | S83: -27876.48 | T83: -18090.55 | U83: -83268.47 | V83: -12199.42 | W83: -63264.34 | X83: -2784.3 | Y83: -117355.25 | Z83: -195603.31 | AA83: -21598.17 | AB83: -48839.39
A84: 1 | C84: 무형자산의증가 | E84: 0.04 | G84: 1.64 | H84: 11.22 | I84: 0.02 | J84: 5.57 | K84: 18.45 | L84: 1.98 | M84: 0 | N84: 82.6 | O84: 105.98 | P84: 190.56 | S84: 509.66 | T84: 5702.17 | V84: 253.83 | W84: 22.77 | X84: 4.96 | Y84: 110.13 | Z84: 391.69 | AA84: 644.02 | AB84: 12.46
A85: 1 | C85: CAPEX | E85: 0.04 | G85: 1.64 | H85: 11.22 | I85: 0.02 | J85: 5.57 | K85: 18.45 | L85: 1.98 | M85: 0 | N85: 82.6 | O85: 105.98 | P85: 190.56 | S85: 509.66 | T85: 5702.17 | V85: 253.83 | W85: 22.77 | X85: 4.96 | Y85: 110.13 | Z85: 391.69 | AA85: 644.02 | AB85: 12.46
A86: 1 | C86: 재무활동으로인한현금흐름 | E86: -742.56 | G86: 2105.14 | H86: -6459.96 | I86: 23694.5 | J86: 9586.31 | K86: 28925.99 | L86: 10659.7 | M86: 13377.61 | N86: -9611.01 | O86: -2632.42 | P86: 11793.88 | Q86: -23559.69 | R86: -13061.94 | S86: -13393.9 | T86: -31405.47 | U86: -81421 | V86: -8165.84 | W86: 19673.77 | X86: -1446.24 | Y86: 47116.11 | Z86: 57177.8 | AA86: 12151.61 | AB86: 13765.2
A87: 1 | C87: 장기차입금의증가 | E87: 0 | G87: 6105.91 | H87: 0 | I87: 8205.91 | J87: 214 | K87: 14525.82 | L87: 105.91 | M87: 2700 | N87: 4800 | O87: 0 | P87: 7605.91 | Q87: 4500 | R87: 0 | S87: 222 | T87: 892 | U87: 5614 | V87: 0 | W87: 5000 | X87: 0 | Y87: 0 | Z87: 5000 | AA87: 0 | AB87: 12500
A88: 1 | C88: 리스부채의상환 | E88: 130.58 | G88: 236.63 | H88: 242.15 | I88: 243.67 | J88: 366.81 | K88: 1089.26 | L88: 431.86 | M88: 451.62 | N88: 466.88 | O88: 502.86 | P88: 1853.22 | Q88: 496.57 | R88: 512.92 | S88: 482.52 | T88: 523.87 | U88: 2015.88 | V88: 540.58 | W88: 522.13 | X88: 661.44 | Y88: 1053.34 | Z88: 2777.49 | AA88: 669.64 | AB88: 1220.32
A89: 1 | C89: 배당금지급 | E89: 0 | I89: 0 | J89: 0 | N89: 0 | O89: 0 | S89: 0 | T89: 0 | X89: 0 | Y89: 0 | AA89: 0 | AB89: 16117.68
A90: 1 | C90: 현금및현금성자산의증감 | E90: -22131.37 | G90: 17093.59 | H90: -89781.16 | I90: 37781.73 | J90: 40223.67 | K90: 5317.83 | L90: -23769.54 | M90: -10670.83 | N90: 31144.49 | O90: 18090.02 | P90: 14794.14 | Q90: -27286.6 | R90: 42094.7 | S90: -2172.44 | T90: -22555.92 | U90: -9920.26 | V90: 50875.56 | W90: -15943.37 | X90: -361.2 | Y90: -37775.08 | Z90: -3204.09 | AA90: 20230.18
A91: 1 | C91: 기말현금및현금성자산 | E91: -3916.18 | G91: 54670.01 | H91: -41427.23 | I91: 15757.35 | J91: 19142.06 | K91: 48142.19 | L91: 24372.65 | M91: -10670.83 | N91: 31144.49 | O91: 18090.02 | P91: 62936.33 | Q91: 35649.73 | R91: 42094.7 | S91: -2172.44 | T91: -22555.92 | U91: 53016.07 | V91: 103891.63 | W91: -15943.36 | X91: -361.21 | Y91: -37775.08 | Z91: 49811.98 | AA91: 70042.16 | AB91: 4697.66
A92: 1 | C92: 단기차입금의감소 | G92: 3764.15 | H92: 3764.15 | I92: 3764.15 | L92: 37000 | M92: 5000 | N92: 25000 | O92: 8305.49 | P92: 75305.49 | Q92: 26463.17 | R92: 5634.17 | S92: 31519.58 | T92: 47413.8 | U92: 111030.72 | V92: 2340.95 | W92: 17500 | X92: 0 | Y92: 0 | Z92: 19840.95 | AA92: 11000 | AB92: 35000
A93: 1 | C93: 단기차입금의증가 | I93: 23000 | J93: 14000 | L93: 48000 | M93: 22105.91 | N93: 27000 | O93: 7000 | P93: 104105.91 | T93: 17500 | V93: 0 | Y93: 65000 | AA93: 25000 | AB93: 58000
A94: 1 | C94: 유동성장기부채의감소 | L94: 14.15 | M94: 42.45 | N94: 15.75 | O94: 370.4 | P94: 442.75 | Q94: 899.96 | R94: 1245.4 | S94: 11239.3 | T94: 2214.3 | U94: 15598.96 | V94: 3284.3 | W94: 784.3 | X94: 784.3 | Y94: 3753.05 | Z94: 8605.95 | AA94: 978.05 | AB94: 2609.3
A95: 1 | C95: 장기차입금의감소 | N95: 0 | O95: 635.2 | S95: 375 | T95: 0 | V95: 2000 | W95: 0 | X95: 0 | Y95: 3075 | Z95: 5075 | AA95: 0 | AB95: 1687.5
A96: 1 | C96: 이자수취(CF) | O96: 1038.35 | Q96: 882.57 | R96: 1044.73 | S96: 1035.22 | T96: 986 | U96: 3948.52 | V96: 946.98 | W96: 1140.38 | X96: 873.63 | Y96: 1012.35 | Z96: 3973.34 | AA96: 560.31 | AB96: 854.41
A97: 1 | C97: 무형자산의감소 | X97: 0 | Y97: 0 | AA97: 0 | AB97: 0
A98: 1 | C98: 사채의감소 | AA98: 0
A99: 1 | C99: 자기주식의취득 | AA99: 0

Sheet subQ
A1: YQ | C1: subQ 분기 서브모델(억원, U=100) | E1: 4Q21 | F1: 2021 | G1: 1Q22 | H1: 2Q22 | I1: 3Q22 | J1: 4Q22 | K1: 2022 | L1: 1Q23 | M1: 2Q23 | N1: 3Q23 | O1: 4Q23 | P1: 2023 | Q1: 1Q24 | R1: 2Q24 | S1: 3Q24 | T1: 4Q24 | U1: 2024 | V1: 1Q25 | W1: 2Q25 | X1: 3Q25 | Y1: 4Q25 | Z1: 2025 | AA1: 1Q26 | AB1: 2Q26 | AC1: 3Q26 | AD1: 4Q26 | AE1: 2026 | AF1: 1Q27 | AG1: 2Q27 | AH1: 3Q27 | AI1: 4Q27 | AJ1: 2027 | AK1: 1Q28 | AL1: 2Q28 | AM1: 3Q28 | AN1: 4Q28 | AO1: 2028
A2: A=이름(key) B=그룹 C=단위 D=FnGuide 계정명(VLOOKUP 키). 확정=VLOOKUP(BS), 추정=변수 가정 참조
E3: 1 | F3: 2 | G3: 3 | H3: 4 | I3: 5 | J3: 6 | K3: 7 | L3: 8 | M3: 9 | N3: 10 | O3: 11 | P3: 12 | Q3: 13 | R3: 14 | S3: 15 | T3: 16 | U3: 17 | V3: 18 | W3: 19 | X3: 20 | Y3: 21 | Z3: 22 | AA3: 23 | AB3: 24 | AC3: 25 | AD3: 26 | AE3: 27 | AF3: 28 | AG3: 29 | AH3: 30 | AI3: 31 | AJ3: 32 | AK3: 33 | AL3: 34 | AM3: 35 | AN3: 36 | AO3: 37
E4: 2021.12 | F4: 2021.12A | G4: 2022.03 | H4: 2022.06 | I4: 2022.09 | J4: 2022.12 | K4: 2022.12A | L4: 2023.03 | M4: 2023.06 | N4: 2023.09 | O4: 2023.12 | P4: 2023.12A | Q4: 2024.03 | R4: 2024.06 | S4: 2024.09 | T4: 2024.12 | U4: 2024.12A | V4: 2025.03 | W4: 2025.06 | X4: 2025.09 | Y4: 2025.12 | Z4: 2025.12A | AA4: 2026.03 | AB4: 2026.06 | AC4: 2026.09 | AD4: 2026.12 | AE4: 2026.12A | AF4: 2027.03 | AG4: 2027.06 | AH4: 2027.09 | AI4: 2027.12 | AJ4: 2027.12A | AK4: 2028.03 | AL4: 2028.06 | AM4: 2028.09 | AN4: 2028.12 | AO4: 2028.12A
A5: 매출액 | B5: 손익 | C5: 억원 | D5: 매출액(수익) | E5: =IFERROR(VLOOKUP($D5,BS연결,MATCH(E$1,BS연결H,0),0)/100,"") | G5: =IFERROR(VLOOKUP($D5,BS연결,MATCH(G$1,BS연결H,0),0)/100,"") | H5: =IFERROR(VLOOKUP($D5,BS연결,MATCH(H$1,BS연결H,0),0)/100,"") | I5: =IFERROR(VLOOKUP($D5,BS연결,MATCH(I$1,BS연결H,0),0)/100,"") | J5: =IFERROR(VLOOKUP($D5,BS연결,MATCH(J$1,BS연결H,0),0)/100,"") | K5: =IFERROR(VLOOKUP($D5,BS연결,MATCH(K$1,BS연결H,0),0)/100,"") | L5: =IFERROR(VLOOKUP($D5,BS연결,MATCH(L$1,BS연결H,0),0)/100,"") | M5: =IFERROR(VLOOKUP($D5,BS연결,MATCH(M$1,BS연결H,0),0)/100,"") | N5: =IFERROR(VLOOKUP($D5,BS연결,MATCH(N$1,BS연결H,0),0)/100,"") | ... AB5: =IFERROR(VLOOKUP($D5,BS연결,MATCH(AB$1,BS연결H,0),0)/100,"") | AC5: =IFERROR(X5*(1+변수!AC21),"") | AD5: =IFERROR(Y5*(1+변수!AD21),"") | AE5: =SUM(AA5:AD5) | AF5: =IFERROR(AA5*(1+변수!AF21),"") | AG5: =IFERROR(AB5*(1+변수!AG21),"") | AH5: =IFERROR(AC5*(1+변수!AH21),"") | AI5: =IFERROR(AD5*(1+변수!AI21),"") | AJ5: =SUM(AF5:AI5) | AK5: =IFERROR(AF5*(1+변수!AK21),"") | AL5: =IFERROR(AG5*(1+변수!AL21),"") | AM5: =IFERROR(AH5*(1+변수!AM21),"") | AN5: =IFERROR(AI5*(1+변수!AN21),"") | AO5: =SUM(AK5:AN5)
A6: 매출원가 | B6: 손익 | C6: 억원 | D6: 매출원가 | E6: =IFERROR(VLOOKUP($D6,BS연결,MATCH(E$1,BS연결H,0),0)/100,"") | G6: =IFERROR(VLOOKUP($D6,BS연결,MATCH(G$1,BS연결H,0),0)/100,"") | H6: =IFERROR(VLOOKUP($D6,BS연결,MATCH(H$1,BS연결H,0),0)/100,"") | I6: =IFERROR(VLOOKUP($D6,BS연결,MATCH(I$1,BS연결H,0),0)/100,"") | J6: =IFERROR(VLOOKUP($D6,BS연결,MATCH(J$1,BS연결H,0),0)/100,"") | K6: =IFERROR(VLOOKUP($D6,BS연결,MATCH(K$1,BS연결H,0),0)/100,"") | L6: =IFERROR(VLOOKUP($D6,BS연결,MATCH(L$1,BS연결H,0),0)/100,"") | M6: =IFERROR(VLOOKUP($D6,BS연결,MATCH(M$1,BS연결H,0),0)/100,"") | N6: =IFERROR(VLOOKUP($D6,BS연결,MATCH(N$1,BS연결H,0),0)/100,"") | ... AB6: =IFERROR(VLOOKUP($D6,BS연결,MATCH(AB$1,BS연결H,0),0)/100,"") | AC6: =IFERROR(AC5-AC7,"") | AD6: =IFERROR(AD5-AD7,"") | AE6: =SUM(AA6:AD6) | AF6: =IFERROR(AF5-AF7,"") | AG6: =IFERROR(AG5-AG7,"") | AH6: =IFERROR(AH5-AH7,"") | AI6: =IFERROR(AI5-AI7,"") | AJ6: =SUM(AF6:AI6) | AK6: =IFERROR(AK5-AK7,"") | AL6: =IFERROR(AL5-AL7,"") | AM6: =IFERROR(AM5-AM7,"") | AN6: =IFERROR(AN5-AN7,"") | AO6: =SUM(AK6:AN6)
A7: 매출총이익 | B7: 손익 | C7: 억원 | D7: 매출총이익 | E7: =IFERROR(VLOOKUP($D7,BS연결,MATCH(E$1,BS연결H,0),0)/100,"") | G7: =IFERROR(VLOOKUP($D7,BS연결,MATCH(G$1,BS연결H,0),0)/100,"") | H7: =IFERROR(VLOOKUP($D7,BS연결,MATCH(H$1,BS연결H,0),0)/100,"") | I7: =IFERROR(VLOOKUP($D7,BS연결,MATCH(I$1,BS연결H,0),0)/100,"") | J7: =IFERROR(VLOOKUP($D7,BS연결,MATCH(J$1,BS연결H,0),0)/100,"") | K7: =IFERROR(VLOOKUP($D7,BS연결,MATCH(K$1,BS연결H,0),0)/100,"") | L7: =IFERROR(VLOOKUP($D7,BS연결,MATCH(L$1,BS연결H,0),0)/100,"") | M7: =IFERROR(VLOOKUP($D7,BS연결,MATCH(M$1,BS연결H,0),0)/100,"") | N7: =IFERROR(VLOOKUP($D7,BS연결,MATCH(N$1,BS연결H,0),0)/100,"") | ... AB7: =IFERROR(VLOOKUP($D7,BS연결,MATCH(AB$1,BS연결H,0),0)/100,"") | AC7: =IFERROR(AC9+AC8,"") | AD7: =IFERROR(AD9+AD8,"") | AE7: =SUM(AA7:AD7) | AF7: =IFERROR(AF9+AF8,"") | AG7: =IFERROR(AG9+AG8,"") | AH7: =IFERROR(AH9+AH8,"") | AI7: =IFERROR(AI9+AI8,"") | AJ7: =SUM(AF7:AI7) | AK7: =IFERROR(AK9+AK8,"") | AL7: =IFERROR(AL9+AL8,"") | AM7: =IFERROR(AM9+AM8,"") | AN7: =IFERROR(AN9+AN8,"") | AO7: =SUM(AK7:AN7)
A8: 판관비 | B8: 손익 | C8: 억원 | D8: 판관비 | E8: =IFERROR(VLOOKUP($D8,BS연결,MATCH(E$1,BS연결H,0),0)/100,"") | G8: =IFERROR(VLOOKUP($D8,BS연결,MATCH(G$1,BS연결H,0),0)/100,"") | H8: =IFERROR(VLOOKUP($D8,BS연결,MATCH(H$1,BS연결H,0),0)/100,"") | I8: =IFERROR(VLOOKUP($D8,BS연결,MATCH(I$1,BS연결H,0),0)/100,"") | J8: =IFERROR(VLOOKUP($D8,BS연결,MATCH(J$1,BS연결H,0),0)/100,"") | K8: =IFERROR(VLOOKUP($D8,BS연결,MATCH(K$1,BS연결H,0),0)/100,"") | L8: =IFERROR(VLOOKUP($D8,BS연결,MATCH(L$1,BS연결H,0),0)/100,"") | M8: =IFERROR(VLOOKUP($D8,BS연결,MATCH(M$1,BS연결H,0),0)/100,"") | N8: =IFERROR(VLOOKUP($D8,BS연결,MATCH(N$1,BS연결H,0),0)/100,"") | ... AB8: =IFERROR(VLOOKUP($D8,BS연결,MATCH(AB$1,BS연결H,0),0)/100,"") | AC8: =IFERROR(AC5*변수!AC22,"") | AD8: =IFERROR(AD5*변수!AD22,"") | AE8: =SUM(AA8:AD8) | AF8: =IFERROR(AF5*변수!AF22,"") | AG8: =IFERROR(AG5*변수!AG22,"") | AH8: =IFERROR(AH5*변수!AH22,"") | AI8: =IFERROR(AI5*변수!AI22,"") | AJ8: =SUM(AF8:AI8) | AK8: =IFERROR(AK5*변수!AK22,"") | AL8: =IFERROR(AL5*변수!AL22,"") | AM8: =IFERROR(AM5*변수!AM22,"") | AN8: =IFERROR(AN5*변수!AN22,"") | AO8: =SUM(AK8:AN8)
A9: 영업이익 | B9: 손익 | C9: 억원 | D9: 영업이익 | E9: =IFERROR(VLOOKUP($D9,BS연결,MATCH(E$1,BS연결H,0),0)/100,"") | G9: =IFERROR(VLOOKUP($D9,BS연결,MATCH(G$1,BS연결H,0),0)/100,"") | H9: =IFERROR(VLOOKUP($D9,BS연결,MATCH(H$1,BS연결H,0),0)/100,"") | I9: =IFERROR(VLOOKUP($D9,BS연결,MATCH(I$1,BS연결H,0),0)/100,"") | J9: =IFERROR(VLOOKUP($D9,BS연결,MATCH(J$1,BS연결H,0),0)/100,"") | K9: =IFERROR(VLOOKUP($D9,BS연결,MATCH(K$1,BS연결H,0),0)/100,"") | L9: =IFERROR(VLOOKUP($D9,BS연결,MATCH(L$1,BS연결H,0),0)/100,"") | M9: =IFERROR(VLOOKUP($D9,BS연결,MATCH(M$1,BS연결H,0),0)/100,"") | N9: =IFERROR(VLOOKUP($D9,BS연결,MATCH(N$1,BS연결H,0),0)/100,"") | ... AB9: =IFERROR(VLOOKUP($D9,BS연결,MATCH(AB$1,BS연결H,0),0)/100,"") | AC9: =IFERROR(AC5*변수!AC23,"") | AD9: =IFERROR(AD5*변수!AD23,"") | AE9: =SUM(AA9:AD9) | AF9: =IFERROR(AF5*변수!AF23,"") | AG9: =IFERROR(AG5*변수!AG23,"") | AH9: =IFERROR(AH5*변수!AH23,"") | AI9: =IFERROR(AI5*변수!AI23,"") | AJ9: =SUM(AF9:AI9) | AK9: =IFERROR(AK5*변수!AK23,"") | AL9: =IFERROR(AL5*변수!AL23,"") | AM9: =IFERROR(AM5*변수!AM23,"") | AN9: =IFERROR(AN5*변수!AN23,"") | AO9: =SUM(AK9:AN9)
A10: OPM | B10: 손익 | C10: % | D10: 영업이익률 | E10: =IFERROR(E9/E5,"") | G10: =IFERROR(G9/G5,"") | H10: =IFERROR(H9/H5,"") | I10: =IFERROR(I9/I5,"") | J10: =IFERROR(J9/J5,"") | K10: =IFERROR(K9/K5,"") | L10: =IFERROR(L9/L5,"") | M10: =IFERROR(M9/M5,"") | N10: =IFERROR(N9/N5,"") | ... AO10: =IFERROR(AO9/AO5,"")
A11: 금융손익 | B11: 손익 | C11: 억원 | D11: 금융손익 | E11: =IFERROR(VLOOKUP($D11,BS연결,MATCH(E$1,BS연결H,0),0)/100,"") | G11: =IFERROR(VLOOKUP($D11,BS연결,MATCH(G$1,BS연결H,0),0)/100,"") | H11: =IFERROR(VLOOKUP($D11,BS연결,MATCH(H$1,BS연결H,0),0)/100,"") | I11: =IFERROR(VLOOKUP($D11,BS연결,MATCH(I$1,BS연결H,0),0)/100,"") | J11: =IFERROR(VLOOKUP($D11,BS연결,MATCH(J$1,BS연결H,0),0)/100,"") | K11: =IFERROR(VLOOKUP($D11,BS연결,MATCH(K$1,BS연결H,0),0)/100,"") | L11: =IFERROR(VLOOKUP($D11,BS연결,MATCH(L$1,BS연결H,0),0)/100,"") | M11: =IFERROR(VLOOKUP($D11,BS연결,MATCH(M$1,BS연결H,0),0)/100,"") | N11: =IFERROR(VLOOKUP($D11,BS연결,MATCH(N$1,BS연결H,0),0)/100,"") | ... AB11: =IFERROR(VLOOKUP($D11,BS연결,MATCH(AB$1,BS연결H,0),0)/100,"") | AC11: =IFERROR(AC12+AC13+AC14+AC15,"") | AD11: =IFERROR(AD12+AD13+AD14+AD15,"") | AE11: =SUM(AA11:AD11) | AF11: =IFERROR(AF12+AF13+AF14+AF15,"") | AG11: =IFERROR(AG12+AG13+AG14+AG15,"") | AH11: =IFERROR(AH12+AH13+AH14+AH15,"") | AI11: =IFERROR(AI12+AI13+AI14+AI15,"") | AJ11: =SUM(AF11:AI11) | AK11: =IFERROR(AK12+AK13+AK14+AK15,"") | AL11: =IFERROR(AL12+AL13+AL14+AL15,"") | AM11: =IFERROR(AM12+AM13+AM14+AM15,"") | AN11: =IFERROR(AN12+AN13+AN14+AN15,"") | AO11: =SUM(AK11:AN11)
A12: 이자손익 | B12: 손익 | C12: 억원 | D12: 이자손익 | G12: =IFERROR(VLOOKUP($D12,BS연결,MATCH(G$1,BS연결H,0),0)/100,"") | H12: =IFERROR(VLOOKUP($D12,BS연결,MATCH(H$1,BS연결H,0),0)/100,"") | I12: =IFERROR(VLOOKUP($D12,BS연결,MATCH(I$1,BS연결H,0),0)/100,"") | J12: =IFERROR(VLOOKUP($D12,BS연결,MATCH(J$1,BS연결H,0),0)/100,"") | K12: =IFERROR(VLOOKUP($D12,BS연결,MATCH(K$1,BS연결H,0),0)/100,"") | L12: =IFERROR(VLOOKUP($D12,BS연결,MATCH(L$1,BS연결H,0),0)/100,"") | M12: =IFERROR(VLOOKUP($D12,BS연결,MATCH(M$1,BS연결H,0),0)/100,"") | N12: =IFERROR(VLOOKUP($D12,BS연결,MATCH(N$1,BS연결H,0),0)/100,"") | ... AB12: =IFERROR(VLOOKUP($D12,BS연결,MATCH(AB$1,BS연결H,0),0)/100,"") | AC12: =IFERROR((AB29*변수!$D$55-AB27*변수!$D$56)/4,"") | AD12: =IFERROR((AC29*변수!$D$55-AC27*변수!$D$56)/4,"") | AE12: =SUM(AA12:AD12) | AF12: =IFERROR((AD29*변수!$D$55-AD27*변수!$D$56)/4,"") | AG12: =IFERROR((AF29*변수!$D$55-AF27*변수!$D$56)/4,"") | AH12: =IFERROR((AG29*변수!$D$55-AG27*변수!$D$56)/4,"") | AI12: =IFERROR((AH29*변수!$D$55-AH27*변수!$D$56)/4,"") | AJ12: =SUM(AF12:AI12) | AK12: =IFERROR((AI29*변수!$D$55-AI27*변수!$D$56)/4,"") | AL12: =IFERROR((AK29*변수!$D$55-AK27*변수!$D$56)/4,"") | AM12: =IFERROR((AL29*변수!$D$55-AL27*변수!$D$56)/4,"") | AN12: =IFERROR((AM29*변수!$D$55-AM27*변수!$D$56)/4,"") | AO12: =SUM(AK12:AN12)
A13: 외환손익 | B13: 손익 | C13: 억원 | D13: 외환손익(실적만; 추정 환효과는 환관련손익) | H13: =IFERROR((VLOOKUP("외환차익",BS연결,MATCH(H$1,BS연결H,0),0)-VLOOKUP("외환차손",BS연결,MATCH(H$1,BS연결H,0),0)+VLOOKUP("외화환산이익",BS연결,MATCH(H$1,BS연결H,0),0)-VLOOKUP("외화환산손실",BS연결,MATCH(H$1,BS연결H,0),0))/100,"") | K13: =SUM(G13:J13) | L13: =IFERROR((VLOOKUP("외환차익",BS연결,MATCH(L$1,BS연결H,0),0)-VLOOKUP("외환차손",BS연결,MATCH(L$1,BS연결H,0),0)+VLOOKUP("외화환산이익",BS연결,MATCH(L$1,BS연결H,0),0)-VLOOKUP("외화환산손실",BS연결,MATCH(L$1,BS연결H,0),0))/100,"") | M13: =IFERROR((VLOOKUP("외환차익",BS연결,MATCH(M$1,BS연결H,0),0)-VLOOKUP("외환차손",BS연결,MATCH(M$1,BS연결H,0),0)+VLOOKUP("외화환산이익",BS연결,MATCH(M$1,BS연결H,0),0)-VLOOKUP("외화환산손실",BS연결,MATCH(M$1,BS연결H,0),0))/100,"") | N13: =IFERROR((VLOOKUP("외환차익",BS연결,MATCH(N$1,BS연결H,0),0)-VLOOKUP("외환차손",BS연결,MATCH(N$1,BS연결H,0),0)+VLOOKUP("외화환산이익",BS연결,MATCH(N$1,BS연결H,0),0)-VLOOKUP("외화환산손실",BS연결,MATCH(N$1,BS연결H,0),0))/100,"") | O13: =IFERROR((VLOOKUP("외환차익",BS연결,MATCH(O$1,BS연결H,0),0)-VLOOKUP("외환차손",BS연결,MATCH(O$1,BS연결H,0),0)+VLOOKUP("외화환산이익",BS연결,MATCH(O$1,BS연결H,0),0)-VLOOKUP("외화환산손실",BS연결,MATCH(O$1,BS연결H,0),0))/100,"") | P13: =SUM(L13:O13) | Q13: =IFERROR((VLOOKUP("외환차익",BS연결,MATCH(Q$1,BS연결H,0),0)-VLOOKUP("외환차손",BS연결,MATCH(Q$1,BS연결H,0),0)+VLOOKUP("외화환산이익",BS연결,MATCH(Q$1,BS연결H,0),0)-VLOOKUP("외화환산손실",BS연결,MATCH(Q$1,BS연결H,0),0))/100,"") | R13: =IFERROR((VLOOKUP("외환차익",BS연결,MATCH(R$1,BS연결H,0),0)-VLOOKUP("외환차손",BS연결,MATCH(R$1,BS연결H,0),0)+VLOOKUP("외화환산이익",BS연결,MATCH(R$1,BS연결H,0),0)-VLOOKUP("외화환산손실",BS연결,MATCH(R$1,BS연결H,0),0))/100,"") | S13: =IFERROR((VLOOKUP("외환차익",BS연결,MATCH(S$1,BS연결H,0),0)-VLOOKUP("외환차손",BS연결,MATCH(S$1,BS연결H,0),0)+VLOOKUP("외화환산이익",BS연결,MATCH(S$1,BS연결H,0),0)-VLOOKUP("외화환산손실",BS연결,MATCH(S$1,BS연결H,0),0))/100,"") | T13: =IFERROR((VLOOKUP("외환차익",BS연결,MATCH(T$1,BS연결H,0),0)-VLOOKUP("외환차손",BS연결,MATCH(T$1,BS연결H,0),0)+VLOOKUP("외화환산이익",BS연결,MATCH(T$1,BS연결H,0),0)-VLOOKUP("외화환산손실",BS연결,MATCH(T$1,BS연결H,0),0))/100,"") | U13: =SUM(Q13:T13) | V13: =IFERROR((VLOOKUP("외환차익",BS연결,MATCH(V$1,BS연결H,0),0)-VLOOKUP("외환차손",BS연결,MATCH(V$1,BS연결H,0),0)+VLOOKUP("외화환산이익",BS연결,MATCH(V$1,BS연결H,0),0)-VLOOKUP("외화환산손실",BS연결,MATCH(V$1,BS연결H,0),0))/100,"") | W13: =IFERROR((VLOOKUP("외환차익",BS연결,MATCH(W$1,BS연결H,0),0)-VLOOKUP("외환차손",BS연결,MATCH(W$1,BS연결H,0),0)+VLOOKUP("외화환산이익",BS연결,MATCH(W$1,BS연결H,0),0)-VLOOKUP("외화환산손실",BS연결,MATCH(W$1,BS연결H,0),0))/100,"") | X13: =IFERROR((VLOOKUP("외환차익",BS연결,MATCH(X$1,BS연결H,0),0)-VLOOKUP("외환차손",BS연결,MATCH(X$1,BS연결H,0),0)+VLOOKUP("외화환산이익",BS연결,MATCH(X$1,BS연결H,0),0)-VLOOKUP("외화환산손실",BS연결,MATCH(X$1,BS연결H,0),0))/100,"") | Y13: =IFERROR((VLOOKUP("외환차익",BS연결,MATCH(Y$1,BS연결H,0),0)-VLOOKUP("외환차손",BS연결,MATCH(Y$1,BS연결H,0),0)+VLOOKUP("외화환산이익",BS연결,MATCH(Y$1,BS연결H,0),0)-VLOOKUP("외화환산손실",BS연결,MATCH(Y$1,BS연결H,0),0))/100,"") | Z13: =SUM(V13:Y13) | AA13: =IFERROR((VLOOKUP("외환차익",BS연결,MATCH(AA$1,BS연결H,0),0)-VLOOKUP("외환차손",BS연결,MATCH(AA$1,BS연결H,0),0)+VLOOKUP("외화환산이익",BS연결,MATCH(AA$1,BS연결H,0),0)-VLOOKUP("외화환산손실",BS연결,MATCH(AA$1,BS연결H,0),0))/100,"") | AB13: =IFERROR((VLOOKUP("외환차익",BS연결,MATCH(AB$1,BS연결H,0),0)-VLOOKUP("외환차손",BS연결,MATCH(AB$1,BS연결H,0),0)+VLOOKUP("외화환산이익",BS연결,MATCH(AB$1,BS연결H,0),0)-VLOOKUP("외화환산손실",BS연결,MATCH(AB$1,BS연결H,0),0))/100,"") | AC13: =변수!AC24 | AD13: =변수!AD24 | AE13: =SUM(AA13:AD13) | AF13: =변수!AF24 | AG13: =변수!AG24 | AH13: =변수!AH24 | AI13: =변수!AI24 | AJ13: =SUM(AF13:AI13) | AK13: =변수!AK24 | AL13: =변수!AL24 | AM13: =변수!AM24 | AN13: =변수!AN24 | AO13: =SUM(AK13:AN13)
A14: 파생상품손익 | B14: 손익 | C14: 억원 | D14: 파생상품손익 | K14: =SUM(G14:J14) | P14: =SUM(L14:O14) | U14: =SUM(Q14:T14) | W14: =IFERROR((VLOOKUP("파생상품이익",BS연결,MATCH(W$1,BS연결H,0),0)-VLOOKUP("파생상품손실",BS연결,MATCH(W$1,BS연결H,0),0))/100,"") | X14: =IFERROR((VLOOKUP("파생상품이익",BS연결,MATCH(X$1,BS연결H,0),0)-VLOOKUP("파생상품손실",BS연결,MATCH(X$1,BS연결H,0),0))/100,"") | Y14: =IFERROR((VLOOKUP("파생상품이익",BS연결,MATCH(Y$1,BS연결H,0),0)-VLOOKUP("파생상품손실",BS연결,MATCH(Y$1,BS연결H,0),0))/100,"") | Z14: =SUM(V14:Y14) | AA14: =IFERROR((VLOOKUP("파생상품이익",BS연결,MATCH(AA$1,BS연결H,0),0)-VLOOKUP("파생상품손실",BS연결,MATCH(AA$1,BS연결H,0),0))/100,"") | AB14: =IFERROR((VLOOKUP("파생상품이익",BS연결,MATCH(AB$1,BS연결H,0),0)-VLOOKUP("파생상품손실",BS연결,MATCH(AB$1,BS연결H,0),0))/100,"") | AC14: =변수!AC25 | AD14: =변수!AD25 | AE14: =SUM(AA14:AD14) | AF14: =변수!AF25 | AG14: =변수!AG25 | AH14: =변수!AH25 | AI14: =변수!AI25 | AJ14: =SUM(AF14:AI14) | AK14: =변수!AK25 | AL14: =변수!AL25 | AM14: =변수!AM25 | AN14: =변수!AN25 | AO14: =SUM(AK14:AN14)
A15: 기타금융손익 | B15: 손익 | C15: 억원 | D15: 기타금융손익(금융손익 잔차) | K15: =SUM(G15:J15) | P15: =SUM(L15:O15) | U15: =SUM(Q15:T15) | W15: =IFERROR(W11-W12-W13-W14,"") | X15: =IFERROR(X11-X12-X13-X14,"") | Y15: =IFERROR(Y11-Y12-Y13-Y14,"") | Z15: =SUM(V15:Y15) | AA15: =IFERROR(AA11-AA12-AA13-AA14,"") | AB15: =IFERROR(AB11-AB12-AB13-AB14,"") | AC15: =변수!AC26 | AD15: =변수!AD26 | AE15: =SUM(AA15:AD15) | AF15: =변수!AF26 | AG15: =변수!AG26 | AH15: =변수!AH26 | AI15: =변수!AI26 | AJ15: =SUM(AF15:AI15) | AK15: =변수!AK26 | AL15: =변수!AL26 | AM15: =변수!AM26 | AN15: =변수!AN26 | AO15: =SUM(AK15:AN15)
A16: 기타영업외손익 | B16: 손익 | C16: 억원 | D16: 기타영업외손익 | E16: =IFERROR(VLOOKUP($D16,BS연결,MATCH(E$1,BS연결H,0),0)/100,"") | G16: =IFERROR(VLOOKUP($D16,BS연결,MATCH(G$1,BS연결H,0),0)/100,"") | H16: =IFERROR(VLOOKUP($D16,BS연결,MATCH(H$1,BS연결H,0),0)/100,"") | I16: =IFERROR(VLOOKUP($D16,BS연결,MATCH(I$1,BS연결H,0),0)/100,"") | J16: =IFERROR(VLOOKUP($D16,BS연결,MATCH(J$1,BS연결H,0),0)/100,"") | K16: =IFERROR(VLOOKUP($D16,BS연결,MATCH(K$1,BS연결H,0),0)/100,"") | L16: =IFERROR(VLOOKUP($D16,BS연결,MATCH(L$1,BS연결H,0),0)/100,"") | M16: =IFERROR(VLOOKUP($D16,BS연결,MATCH(M$1,BS연결H,0),0)/100,"") | N16: =IFERROR(VLOOKUP($D16,BS연결,MATCH(N$1,BS연결H,0),0)/100,"") | ... AB16: =IFERROR(VLOOKUP($D16,BS연결,MATCH(AB$1,BS연결H,0),0)/100,"") | AC16: =변수!AC27 | AD16: =변수!AD27 | AE16: =SUM(AA16:AD16) | AF16: =변수!AF27 | AG16: =변수!AG27 | AH16: =변수!AH27 | AI16: =변수!AI27 | AJ16: =SUM(AF16:AI16) | AK16: =변수!AK27 | AL16: =변수!AL27 | AM16: =변수!AM27 | AN16: =변수!AN27 | AO16: =SUM(AK16:AN16)
A17: 지분법손익 | B17: 손익 | C17: 억원 | D17: 종속기업,공동지배기업및관계기업관련손익 | E17: =IFERROR(VLOOKUP($D17,BS연결,MATCH(E$1,BS연결H,0),0)/100,"") | G17: =IFERROR(VLOOKUP($D17,BS연결,MATCH(G$1,BS연결H,0),0)/100,"") | H17: =IFERROR(VLOOKUP($D17,BS연결,MATCH(H$1,BS연결H,0),0)/100,"") | I17: =IFERROR(VLOOKUP($D17,BS연결,MATCH(I$1,BS연결H,0),0)/100,"") | J17: =IFERROR(VLOOKUP($D17,BS연결,MATCH(J$1,BS연결H,0),0)/100,"") | K17: =IFERROR(VLOOKUP($D17,BS연결,MATCH(K$1,BS연결H,0),0)/100,"") | L17: =IFERROR(VLOOKUP($D17,BS연결,MATCH(L$1,BS연결H,0),0)/100,"") | M17: =IFERROR(VLOOKUP($D17,BS연결,MATCH(M$1,BS연결H,0),0)/100,"") | O17: =IFERROR(VLOOKUP($D17,BS연결,MATCH(O$1,BS연결H,0),0)/100,"") | P17: =SUM(L17:O17) | Q17: =IFERROR(VLOOKUP($D17,BS연결,MATCH(Q$1,BS연결H,0),0)/100,"") | R17: =IFERROR(VLOOKUP($D17,BS연결,MATCH(R$1,BS연결H,0),0)/100,"") | S17: =IFERROR(VLOOKUP($D17,BS연결,MATCH(S$1,BS연결H,0),0)/100,"") | U17: =SUM(Q17:T17) | Z17: =SUM(V17:Y17) | AC17: =변수!AC28 | AD17: =변수!AD28 | AE17: =SUM(AA17:AD17) | AF17: =변수!AF28 | AG17: =변수!AG28 | AH17: =변수!AH28 | AI17: =변수!AI28 | AJ17: =SUM(AF17:AI17) | AK17: =변수!AK28 | AL17: =변수!AL28 | AM17: =변수!AM28 | AN17: =변수!AN28 | AO17: =SUM(AK17:AN17)
A18: 세전이익 | B18: 손익 | C18: 억원 | D18: 법인세비용차감전계속사업이익 | E18: =IFERROR(VLOOKUP($D18,BS연결,MATCH(E$1,BS연결H,0),0)/100,"") | G18: =IFERROR(VLOOKUP($D18,BS연결,MATCH(G$1,BS연결H,0),0)/100,"") | H18: =IFERROR(VLOOKUP($D18,BS연결,MATCH(H$1,BS연결H,0),0)/100,"") | I18: =IFERROR(VLOOKUP($D18,BS연결,MATCH(I$1,BS연결H,0),0)/100,"") | J18: =IFERROR(VLOOKUP($D18,BS연결,MATCH(J$1,BS연결H,0),0)/100,"") | K18: =IFERROR(VLOOKUP($D18,BS연결,MATCH(K$1,BS연결H,0),0)/100,"") | L18: =IFERROR(VLOOKUP($D18,BS연결,MATCH(L$1,BS연결H,0),0)/100,"") | M18: =IFERROR(VLOOKUP($D18,BS연결,MATCH(M$1,BS연결H,0),0)/100,"") | N18: =IFERROR(VLOOKUP($D18,BS연결,MATCH(N$1,BS연결H,0),0)/100,"") | ... AB18: =IFERROR(VLOOKUP($D18,BS연결,MATCH(AB$1,BS연결H,0),0)/100,"") | AC18: =IFERROR(AC9+AC11+AC16+AC17,"") | AD18: =IFERROR(AD9+AD11+AD16+AD17,"") | AE18: =SUM(AA18:AD18) | AF18: =IFERROR(AF9+AF11+AF16+AF17,"") | AG18: =IFERROR(AG9+AG11+AG16+AG17,"") | AH18: =IFERROR(AH9+AH11+AH16+AH17,"") | AI18: =IFERROR(AI9+AI11+AI16+AI17,"") | AJ18: =SUM(AF18:AI18) | AK18: =IFERROR(AK9+AK11+AK16+AK17,"") | AL18: =IFERROR(AL9+AL11+AL16+AL17,"") | AM18: =IFERROR(AM9+AM11+AM16+AM17,"") | AN18: =IFERROR(AN9+AN11+AN16+AN17,"") | AO18: =SUM(AK18:AN18)
A19: 법인세비용 | B19: 손익 | C19: 억원 | D19: 법인세비용 | E19: =IFERROR(VLOOKUP($D19,BS연결,MATCH(E$1,BS연결H,0),0)/100,"") | G19: =IFERROR(VLOOKUP($D19,BS연결,MATCH(G$1,BS연결H,0),0)/100,"") | H19: =IFERROR(VLOOKUP($D19,BS연결,MATCH(H$1,BS연결H,0),0)/100,"") | I19: =IFERROR(VLOOKUP($D19,BS연결,MATCH(I$1,BS연결H,0),0)/100,"") | J19: =IFERROR(VLOOKUP($D19,BS연결,MATCH(J$1,BS연결H,0),0)/100,"") | K19: =IFERROR(VLOOKUP($D19,BS연결,MATCH(K$1,BS연결H,0),0)/100,"") | L19: =IFERROR(VLOOKUP($D19,BS연결,MATCH(L$1,BS연결H,0),0)/100,"") | M19: =IFERROR(VLOOKUP($D19,BS연결,MATCH(M$1,BS연결H,0),0)/100,"") | N19: =IFERROR(VLOOKUP($D19,BS연결,MATCH(N$1,BS연결H,0),0)/100,"") | ... AB19: =IFERROR(VLOOKUP($D19,BS연결,MATCH(AB$1,BS연결H,0),0)/100,"") | AC19: =IFERROR(MAX(AC18,0)*변수!AC29,"") | AD19: =IFERROR(MAX(AD18,0)*변수!AD29,"") | AE19: =SUM(AA19:AD19) | AF19: =IFERROR(MAX(AF18,0)*변수!AF29,"") | AG19: =IFERROR(MAX(AG18,0)*변수!AG29,"") | AH19: =IFERROR(MAX(AH18,0)*변수!AH29,"") | AI19: =IFERROR(MAX(AI18,0)*변수!AI29,"") | AJ19: =SUM(AF19:AI19) | AK19: =IFERROR(MAX(AK18,0)*변수!AK29,"") | AL19: =IFERROR(MAX(AL18,0)*변수!AL29,"") | AM19: =IFERROR(MAX(AM18,0)*변수!AM29,"") | AN19: =IFERROR(MAX(AN18,0)*변수!AN29,"") | AO19: =SUM(AK19:AN19)
A20: 당기순이익 | B20: 손익 | C20: 억원 | D20: 당기순이익 | E20: =IFERROR(VLOOKUP($D20,BS연결,MATCH(E$1,BS연결H,0),0)/100,"") | G20: =IFERROR(VLOOKUP($D20,BS연결,MATCH(G$1,BS연결H,0),0)/100,"") | H20: =IFERROR(VLOOKUP($D20,BS연결,MATCH(H$1,BS연결H,0),0)/100,"") | I20: =IFERROR(VLOOKUP($D20,BS연결,MATCH(I$1,BS연결H,0),0)/100,"") | J20: =IFERROR(VLOOKUP($D20,BS연결,MATCH(J$1,BS연결H,0),0)/100,"") | K20: =IFERROR(VLOOKUP($D20,BS연결,MATCH(K$1,BS연결H,0),0)/100,"") | L20: =IFERROR(VLOOKUP($D20,BS연결,MATCH(L$1,BS연결H,0),0)/100,"") | M20: =IFERROR(VLOOKUP($D20,BS연결,MATCH(M$1,BS연결H,0),0)/100,"") | N20: =IFERROR(VLOOKUP($D20,BS연결,MATCH(N$1,BS연결H,0),0)/100,"") | ... AB20: =IFERROR(VLOOKUP($D20,BS연결,MATCH(AB$1,BS연결H,0),0)/100,"") | AC20: =IFERROR(AC18-AC19,"") | AD20: =IFERROR(AD18-AD19,"") | AE20: =SUM(AA20:AD20) | AF20: =IFERROR(AF18-AF19,"") | AG20: =IFERROR(AG18-AG19,"") | AH20: =IFERROR(AH18-AH19,"") | AI20: =IFERROR(AI18-AI19,"") | AJ20: =SUM(AF20:AI20) | AK20: =IFERROR(AK18-AK19,"") | AL20: =IFERROR(AL18-AL19,"") | AM20: =IFERROR(AM18-AM19,"") | AN20: =IFERROR(AN18-AN19,"") | AO20: =SUM(AK20:AN20)
A21: 지배주주순이익 | B21: 손익 | C21: 억원 | D21: (지배주주지분)당기순이익 | E21: =IFERROR(VLOOKUP($D21,BS연결,MATCH(E$1,BS연결H,0),0)/100,"") | G21: =IFERROR(VLOOKUP($D21,BS연결,MATCH(G$1,BS연결H,0),0)/100,"") | H21: =IFERROR(VLOOKUP($D21,BS연결,MATCH(H$1,BS연결H,0),0)/100,"") | I21: =IFERROR(VLOOKUP($D21,BS연결,MATCH(I$1,BS연결H,0),0)/100,"") | J21: =IFERROR(VLOOKUP($D21,BS연결,MATCH(J$1,BS연결H,0),0)/100,"") | K21: =IFERROR(VLOOKUP($D21,BS연결,MATCH(K$1,BS연결H,0),0)/100,"") | L21: =IFERROR(VLOOKUP($D21,BS연결,MATCH(L$1,BS연결H,0),0)/100,"") | M21: =IFERROR(VLOOKUP($D21,BS연결,MATCH(M$1,BS연결H,0),0)/100,"") | N21: =IFERROR(VLOOKUP($D21,BS연결,MATCH(N$1,BS연결H,0),0)/100,"") | ... AB21: =IFERROR(VLOOKUP($D21,BS연결,MATCH(AB$1,BS연결H,0),0)/100,"") | AC21: =IFERROR(AC20*변수!AC30,"") | AD21: =IFERROR(AD20*변수!AD30,"") | AE21: =SUM(AA21:AD21) | AF21: =IFERROR(AF20*변수!AF30,"") | AG21: =IFERROR(AG20*변수!AG30,"") | AH21: =IFERROR(AH20*변수!AH30,"") | AI21: =IFERROR(AI20*변수!AI30,"") | AJ21: =SUM(AF21:AI21) | AK21: =IFERROR(AK20*변수!AK30,"") | AL21: =IFERROR(AL20*변수!AL30,"") | AM21: =IFERROR(AM20*변수!AM30,"") | AN21: =IFERROR(AN20*변수!AN30,"") | AO21: =SUM(AK21:AN21)
A22: 중단사업이익 | B22: 손익 | C22: 억원 | D22: 중단사업이익 | E22: =IFERROR(VLOOKUP($D22,BS연결,MATCH(E$1,BS연결H,0),0)/100,"") | G22: =IFERROR(VLOOKUP($D22,BS연결,MATCH(G$1,BS연결H,0),0)/100,"") | H22: =IFERROR(VLOOKUP($D22,BS연결,MATCH(H$1,BS연결H,0),0)/100,"") | I22: =IFERROR(VLOOKUP($D22,BS연결,MATCH(I$1,BS연결H,0),0)/100,"") | J22: =IFERROR(VLOOKUP($D22,BS연결,MATCH(J$1,BS연결H,0),0)/100,"") | K22: =IFERROR(VLOOKUP($D22,BS연결,MATCH(K$1,BS연결H,0),0)/100,"") | L22: =IFERROR(VLOOKUP($D22,BS연결,MATCH(L$1,BS연결H,0),0)/100,"") | M22: =IFERROR(VLOOKUP($D22,BS연결,MATCH(M$1,BS연결H,0),0)/100,"") | N22: =IFERROR(VLOOKUP($D22,BS연결,MATCH(N$1,BS연결H,0),0)/100,"") | ... P22: =IFERROR(VLOOKUP($D22,BS연결,MATCH(P$1,BS연결H,0),0)/100,"") | R22: =IFERROR(VLOOKUP($D22,BS연결,MATCH(R$1,BS연결H,0),0)/100,"") | T22: =IFERROR(VLOOKUP($D22,BS연결,MATCH(T$1,BS연결H,0),0)/100,"") | U22: =SUM(Q22:T22) | V22: =IFERROR(VLOOKUP($D22,BS연결,MATCH(V$1,BS연결H,0),0)/100,"") | W22: =IFERROR(VLOOKUP($D22,BS연결,MATCH(W$1,BS연결H,0),0)/100,"") | X22: =IFERROR(VLOOKUP($D22,BS연결,MATCH(X$1,BS연결H,0),0)/100,"") | Y22: =IFERROR(VLOOKUP($D22,BS연결,MATCH(Y$1,BS연결H,0),0)/100,"") | Z22: =IFERROR(VLOOKUP($D22,BS연결,MATCH(Z$1,BS연결H,0),0)/100,"") | AA22: =IFERROR(VLOOKUP($D22,BS연결,MATCH(AA$1,BS연결H,0),0)/100,"") | AB22: =IFERROR(VLOOKUP($D22,BS연결,MATCH(AB$1,BS연결H,0),0)/100,"") | AE22: =SUM(AA22:AD22) | AJ22: =SUM(AF22:AI22) | AO22: =SUM(AK22:AN22)
A23: 자산총계 | B23: 재무상태 | C23: 억원 | D23: 자산총계 | E23: =IFERROR(VLOOKUP($D23,BS연결,MATCH(E$1,BS연결H,0),0)/100,"") | F23: =IFERROR(VLOOKUP($D23,BS연결,MATCH(F$1,BS연결H,0),0)/100,"") | G23: =IFERROR(VLOOKUP($D23,BS연결,MATCH(G$1,BS연결H,0),0)/100,"") | H23: =IFERROR(VLOOKUP($D23,BS연결,MATCH(H$1,BS연결H,0),0)/100,"") | I23: =IFERROR(VLOOKUP($D23,BS연결,MATCH(I$1,BS연결H,0),0)/100,"") | J23: =IFERROR(VLOOKUP($D23,BS연결,MATCH(J$1,BS연결H,0),0)/100,"") | K23: =IFERROR(VLOOKUP($D23,BS연결,MATCH(K$1,BS연결H,0),0)/100,"") | L23: =IFERROR(VLOOKUP($D23,BS연결,MATCH(L$1,BS연결H,0),0)/100,"") | ... AB23: =IFERROR(VLOOKUP($D23,BS연결,MATCH(AB$1,BS연결H,0),0)/100,"") | AC23: =IFERROR(AC24+AC25,"") | AD23: =IFERROR(AD24+AD25,"") | AE23: =AD23 | AF23: =IFERROR(AF24+AF25,"") | AG23: =IFERROR(AG24+AG25,"") | AH23: =IFERROR(AH24+AH25,"") | AI23: =IFERROR(AI24+AI25,"") | AJ23: =AI23 | AK23: =IFERROR(AK24+AK25,"") | AL23: =IFERROR(AL24+AL25,"") | AM23: =IFERROR(AM24+AM25,"") | AN23: =IFERROR(AN24+AN25,"") | AO23: =AN23
A24: 부채총계 | B24: 재무상태 | C24: 억원 | D24: 부채총계 | E24: =IFERROR(VLOOKUP($D24,BS연결,MATCH(E$1,BS연결H,0),0)/100,"") | F24: =IFERROR(VLOOKUP($D24,BS연결,MATCH(F$1,BS연결H,0),0)/100,"") | G24: =IFERROR(VLOOKUP($D24,BS연결,MATCH(G$1,BS연결H,0),0)/100,"") | H24: =IFERROR(VLOOKUP($D24,BS연결,MATCH(H$1,BS연결H,0),0)/100,"") | I24: =IFERROR(VLOOKUP($D24,BS연결,MATCH(I$1,BS연결H,0),0)/100,"") | J24: =IFERROR(VLOOKUP($D24,BS연결,MATCH(J$1,BS연결H,0),0)/100,"") | K24: =IFERROR(VLOOKUP($D24,BS연결,MATCH(K$1,BS연결H,0),0)/100,"") | L24: =IFERROR(VLOOKUP($D24,BS연결,MATCH(L$1,BS연결H,0),0)/100,"") | ... AB24: =IFERROR(VLOOKUP($D24,BS연결,MATCH(AB$1,BS연결H,0),0)/100,"") | AC24: =IFERROR(AB24*(1+변수!AC32),"") | AD24: =IFERROR(AC24*(1+변수!AD32),"") | AE24: =AD24 | AF24: =IFERROR(AD24*(1+변수!AF32),"") | AG24: =IFERROR(AF24*(1+변수!AG32),"") | AH24: =IFERROR(AG24*(1+변수!AH32),"") | AI24: =IFERROR(AH24*(1+변수!AI32),"") | AJ24: =AI24 | AK24: =IFERROR(AI24*(1+변수!AK32),"") | AL24: =IFERROR(AK24*(1+변수!AL32),"") | AM24: =IFERROR(AL24*(1+변수!AM32),"") | AN24: =IFERROR(AM24*(1+변수!AN32),"") | AO24: =AN24
A25: 자본총계 | B25: 재무상태 | C25: 억원 | D25: 자본총계 | E25: =IFERROR(VLOOKUP($D25,BS연결,MATCH(E$1,BS연결H,0),0)/100,"") | F25: =IFERROR(VLOOKUP($D25,BS연결,MATCH(F$1,BS연결H,0),0)/100,"") | G25: =IFERROR(VLOOKUP($D25,BS연결,MATCH(G$1,BS연결H,0),0)/100,"") | H25: =IFERROR(VLOOKUP($D25,BS연결,MATCH(H$1,BS연결H,0),0)/100,"") | I25: =IFERROR(VLOOKUP($D25,BS연결,MATCH(I$1,BS연결H,0),0)/100,"") | J25: =IFERROR(VLOOKUP($D25,BS연결,MATCH(J$1,BS연결H,0),0)/100,"") | K25: =IFERROR(VLOOKUP($D25,BS연결,MATCH(K$1,BS연결H,0),0)/100,"") | L25: =IFERROR(VLOOKUP($D25,BS연결,MATCH(L$1,BS연결H,0),0)/100,"") | ... AB25: =IFERROR(VLOOKUP($D25,BS연결,MATCH(AB$1,BS연결H,0),0)/100,"") | AC25: =IFERROR(AB25+AC20-변수!AC33,"") | AD25: =IFERROR(AC25+AD20-변수!AD33,"") | AE25: =AD25 | AF25: =IFERROR(AD25+AF20-변수!AF33,"") | AG25: =IFERROR(AF25+AG20-변수!AG33,"") | AH25: =IFERROR(AG25+AH20-변수!AH33,"") | AI25: =IFERROR(AH25+AI20-변수!AI33,"") | AJ25: =AI25 | AK25: =IFERROR(AI25+AK20-변수!AK33,"") | AL25: =IFERROR(AK25+AL20-변수!AL33,"") | AM25: =IFERROR(AL25+AM20-변수!AM33,"") | AN25: =IFERROR(AM25+AN20-변수!AN33,"") | AO25: =AN25
A26: 지배주주지분 | B26: 재무상태 | C26: 억원 | D26: 지배주주지분 | E26: =IFERROR(VLOOKUP($D26,BS연결,MATCH(E$1,BS연결H,0),0)/100,"") | F26: =IFERROR(VLOOKUP($D26,BS연결,MATCH(F$1,BS연결H,0),0)/100,"") | G26: =IFERROR(VLOOKUP($D26,BS연결,MATCH(G$1,BS연결H,0),0)/100,"") | H26: =IFERROR(VLOOKUP($D26,BS연결,MATCH(H$1,BS연결H,0),0)/100,"") | I26: =IFERROR(VLOOKUP($D26,BS연결,MATCH(I$1,BS연결H,0),0)/100,"") | J26: =IFERROR(VLOOKUP($D26,BS연결,MATCH(J$1,BS연결H,0),0)/100,"") | K26: =IFERROR(VLOOKUP($D26,BS연결,MATCH(K$1,BS연결H,0),0)/100,"") | L26: =IFERROR(VLOOKUP($D26,BS연결,MATCH(L$1,BS연결H,0),0)/100,"") | ... AB26: =IFERROR(VLOOKUP($D26,BS연결,MATCH(AB$1,BS연결H,0),0)/100,"") | AC26: =IFERROR(AB26+AC21-변수!AC34,"") | AD26: =IFERROR(AC26+AD21-변수!AD34,"") | AE26: =AD26 | AF26: =IFERROR(AD26+AF21-변수!AF34,"") | AG26: =IFERROR(AF26+AG21-변수!AG34,"") | AH26: =IFERROR(AG26+AH21-변수!AH34,"") | AI26: =IFERROR(AH26+AI21-변수!AI34,"") | AJ26: =AI26 | AK26: =IFERROR(AI26+AK21-변수!AK34,"") | AL26: =IFERROR(AK26+AL21-변수!AL34,"") | AM26: =IFERROR(AL26+AM21-변수!AM34,"") | AN26: =IFERROR(AM26+AN21-변수!AN34,"") | AO26: =AN26
A27: 총차입금 | B27: 재무상태 | C27: 억원 | D27: 총차입금 | E27: =IFERROR(VLOOKUP($D27,BS연결,MATCH(E$1,BS연결H,0),0)/100,"") | F27: =IFERROR(VLOOKUP($D27,BS연결,MATCH(F$1,BS연결H,0),0)/100,"") | G27: =IFERROR(VLOOKUP($D27,BS연결,MATCH(G$1,BS연결H,0),0)/100,"") | H27: =IFERROR(VLOOKUP($D27,BS연결,MATCH(H$1,BS연결H,0),0)/100,"") | I27: =IFERROR(VLOOKUP($D27,BS연결,MATCH(I$1,BS연결H,0),0)/100,"") | J27: =IFERROR(VLOOKUP($D27,BS연결,MATCH(J$1,BS연결H,0),0)/100,"") | K27: =IFERROR(VLOOKUP($D27,BS연결,MATCH(K$1,BS연결H,0),0)/100,"") | L27: =IFERROR(VLOOKUP($D27,BS연결,MATCH(L$1,BS연결H,0),0)/100,"") | ... AB27: =IFERROR(VLOOKUP($D27,BS연결,MATCH(AB$1,BS연결H,0),0)/100,"") | AC27: =IFERROR(AB27*(1+변수!AC35),"") | AD27: =IFERROR(AC27*(1+변수!AD35),"") | AE27: =AD27 | AF27: =IFERROR(AD27*(1+변수!AF35),"") | AG27: =IFERROR(AF27*(1+변수!AG35),"") | AH27: =IFERROR(AG27*(1+변수!AH35),"") | AI27: =IFERROR(AH27*(1+변수!AI35),"") | AJ27: =AI27 | AK27: =IFERROR(AI27*(1+변수!AK35),"") | AL27: =IFERROR(AK27*(1+변수!AL35),"") | AM27: =IFERROR(AL27*(1+변수!AM35),"") | AN27: =IFERROR(AM27*(1+변수!AN35),"") | AO27: =AN27
A28: 순차입금 | B28: 재무상태 | C28: 억원 | D28: 순차입금 | E28: =IFERROR(VLOOKUP($D28,BS연결,MATCH(E$1,BS연결H,0),0)/100,"") | F28: =IFERROR(VLOOKUP($D28,BS연결,MATCH(F$1,BS연결H,0),0)/100,"") | G28: =IFERROR(VLOOKUP($D28,BS연결,MATCH(G$1,BS연결H,0),0)/100,"") | H28: =IFERROR(VLOOKUP($D28,BS연결,MATCH(H$1,BS연결H,0),0)/100,"") | I28: =IFERROR(VLOOKUP($D28,BS연결,MATCH(I$1,BS연결H,0),0)/100,"") | J28: =IFERROR(VLOOKUP($D28,BS연결,MATCH(J$1,BS연결H,0),0)/100,"") | K28: =IFERROR(VLOOKUP($D28,BS연결,MATCH(K$1,BS연결H,0),0)/100,"") | L28: =IFERROR(VLOOKUP($D28,BS연결,MATCH(L$1,BS연결H,0),0)/100,"") | ... AB28: =IFERROR(VLOOKUP($D28,BS연결,MATCH(AB$1,BS연결H,0),0)/100,"") | AC28: =IFERROR(AB28*(1+변수!AC36),"") | AD28: =IFERROR(AC28*(1+변수!AD36),"") | AE28: =AD28 | AF28: =IFERROR(AD28*(1+변수!AF36),"") | AG28: =IFERROR(AF28*(1+변수!AG36),"") | AH28: =IFERROR(AG28*(1+변수!AH36),"") | AI28: =IFERROR(AH28*(1+변수!AI36),"") | AJ28: =AI28 | AK28: =IFERROR(AI28*(1+변수!AK36),"") | AL28: =IFERROR(AK28*(1+변수!AL36),"") | AM28: =IFERROR(AL28*(1+변수!AM36),"") | AN28: =IFERROR(AM28*(1+변수!AN36),"") | AO28: =AN28
A29: 이자발생자산 | B29: 재무상태 | C29: 억원 | D29: 이자발생자산 | E29: =IFERROR(VLOOKUP($D29,BS연결,MATCH(E$1,BS연결H,0),0)/100,"") | F29: =IFERROR(VLOOKUP($D29,BS연결,MATCH(F$1,BS연결H,0),0)/100,"") | G29: =IFERROR(VLOOKUP($D29,BS연결,MATCH(G$1,BS연결H,0),0)/100,"") | H29: =IFERROR(VLOOKUP($D29,BS연결,MATCH(H$1,BS연결H,0),0)/100,"") | I29: =IFERROR(VLOOKUP($D29,BS연결,MATCH(I$1,BS연결H,0),0)/100,"") | J29: =IFERROR(VLOOKUP($D29,BS연결,MATCH(J$1,BS연결H,0),0)/100,"") | K29: =IFERROR(VLOOKUP($D29,BS연결,MATCH(K$1,BS연결H,0),0)/100,"") | L29: =IFERROR(VLOOKUP($D29,BS연결,MATCH(L$1,BS연결H,0),0)/100,"") | ... AB29: =IFERROR(VLOOKUP($D29,BS연결,MATCH(AB$1,BS연결H,0),0)/100,"") | AC29: =IFERROR(AB29*(1+변수!AC37),"") | AD29: =IFERROR(AC29*(1+변수!AD37),"") | AE29: =AD29 | AF29: =IFERROR(AD29*(1+변수!AF37),"") | AG29: =IFERROR(AF29*(1+변수!AG37),"") | AH29: =IFERROR(AG29*(1+변수!AH37),"") | AI29: =IFERROR(AH29*(1+변수!AI37),"") | AJ29: =AI29 | AK29: =IFERROR(AI29*(1+변수!AK37),"") | AL29: =IFERROR(AK29*(1+변수!AL37),"") | AM29: =IFERROR(AL29*(1+변수!AM37),"") | AN29: =IFERROR(AM29*(1+변수!AN37),"") | AO29: =AN29
A30: 현금및현금성자산 | B30: 재무상태 | C30: 억원 | D30: 현금및현금성자산 | E30: =IFERROR(VLOOKUP($D30,BS연결,MATCH(E$1,BS연결H,0),0)/100,"") | F30: =IFERROR(VLOOKUP($D30,BS연결,MATCH(F$1,BS연결H,0),0)/100,"") | G30: =IFERROR(VLOOKUP($D30,BS연결,MATCH(G$1,BS연결H,0),0)/100,"") | H30: =IFERROR(VLOOKUP($D30,BS연결,MATCH(H$1,BS연결H,0),0)/100,"") | I30: =IFERROR(VLOOKUP($D30,BS연결,MATCH(I$1,BS연결H,0),0)/100,"") | J30: =IFERROR(VLOOKUP($D30,BS연결,MATCH(J$1,BS연결H,0),0)/100,"") | K30: =IFERROR(VLOOKUP($D30,BS연결,MATCH(K$1,BS연결H,0),0)/100,"") | L30: =IFERROR(VLOOKUP($D30,BS연결,MATCH(L$1,BS연결H,0),0)/100,"") | ... AB30: =IFERROR(VLOOKUP($D30,BS연결,MATCH(AB$1,BS연결H,0),0)/100,"") | AE30: =AD30 | AJ30: =AI30 | AO30: =AN30
A31: CAPEX | B31: 현금흐름 | C31: 억원 | D31: CAPEX | E31: =IFERROR(VLOOKUP($D31,BS연결,MATCH(E$1,BS연결H,0),0)/100,"") | G31: =IFERROR(VLOOKUP($D31,BS연결,MATCH(G$1,BS연결H,0),0)/100,"") | H31: =IFERROR(VLOOKUP($D31,BS연결,MATCH(H$1,BS연결H,0),0)/100,"") | I31: =IFERROR(VLOOKUP($D31,BS연결,MATCH(I$1,BS연결H,0),0)/100,"") | J31: =IFERROR(VLOOKUP($D31,BS연결,MATCH(J$1,BS연결H,0),0)/100,"") | K31: =IFERROR(VLOOKUP($D31,BS연결,MATCH(K$1,BS연결H,0),0)/100,"") | L31: =IFERROR(VLOOKUP($D31,BS연결,MATCH(L$1,BS연결H,0),0)/100,"") | M31: =IFERROR(VLOOKUP($D31,BS연결,MATCH(M$1,BS연결H,0),0)/100,"") | N31: =IFERROR(VLOOKUP($D31,BS연결,MATCH(N$1,BS연결H,0),0)/100,"") | ... P31: =IFERROR(VLOOKUP($D31,BS연결,MATCH(P$1,BS연결H,0),0)/100,"") | S31: =IFERROR(VLOOKUP($D31,BS연결,MATCH(S$1,BS연결H,0),0)/100,"") | T31: =IFERROR(VLOOKUP($D31,BS연결,MATCH(T$1,BS연결H,0),0)/100,"") | U31: =SUM(Q31:T31) | X31: =IFERROR(VLOOKUP($D31,BS연결,MATCH(X$1,BS연결H,0),0)/100,"") | Z31: =SUM(V31:Y31) | AA31: =IFERROR(VLOOKUP($D31,BS연결,MATCH(AA$1,BS연결H,0),0)/100,"") | AB31: =IFERROR(VLOOKUP($D31,BS연결,MATCH(AB$1,BS연결H,0),0)/100,"") | AC31: =IFERROR(X31*(1+변수!AC39),"") | AD31: =IFERROR(AC31*(1+변수!AD39),"") | AE31: =SUM(AA31:AD31) | AF31: =IFERROR(AA31*(1+변수!AF39),"") | AG31: =IFERROR(AB31*(1+변수!AG39),"") | AH31: =IFERROR(AC31*(1+변수!AH39),"") | AI31: =IFERROR(AD31*(1+변수!AI39),"") | AJ31: =SUM(AF31:AI31) | AK31: =IFERROR(AF31*(1+변수!AK39),"") | AL31: =IFERROR(AG31*(1+변수!AL39),"") | AM31: =IFERROR(AH31*(1+변수!AM39),"") | AN31: =IFERROR(AI31*(1+변수!AN39),"") | AO31: =SUM(AK31:AN31)
A32: 영업활동현금흐름 | B32: 현금흐름 | C32: 억원 | D32: 영업활동으로인한현금흐름 | E32: =IFERROR(VLOOKUP($D32,BS연결,MATCH(E$1,BS연결H,0),0)/100,"") | G32: =IFERROR(VLOOKUP($D32,BS연결,MATCH(G$1,BS연결H,0),0)/100,"") | H32: =IFERROR(VLOOKUP($D32,BS연결,MATCH(H$1,BS연결H,0),0)/100,"") | I32: =IFERROR(VLOOKUP($D32,BS연결,MATCH(I$1,BS연결H,0),0)/100,"") | J32: =IFERROR(VLOOKUP($D32,BS연결,MATCH(J$1,BS연결H,0),0)/100,"") | K32: =IFERROR(VLOOKUP($D32,BS연결,MATCH(K$1,BS연결H,0),0)/100,"") | L32: =IFERROR(VLOOKUP($D32,BS연결,MATCH(L$1,BS연결H,0),0)/100,"") | M32: =IFERROR(VLOOKUP($D32,BS연결,MATCH(M$1,BS연결H,0),0)/100,"") | N32: =IFERROR(VLOOKUP($D32,BS연결,MATCH(N$1,BS연결H,0),0)/100,"") | ... AB32: =IFERROR(VLOOKUP($D32,BS연결,MATCH(AB$1,BS연결H,0),0)/100,"") | AE32: =SUM(AA32:AD32) | AJ32: =SUM(AF32:AI32) | AO32: =SUM(AK32:AN32)
A33: 주식수 | B33: 주당 | C33: 백만주 | D33: 유통주식수 | E33: 43.022 | F33: =E33 | G33: 43.022 | H33: 43.022 | I33: 43.022 | J33: 43.022 | K33: =J33 | L33: 43.022 | M33: 43.022 | N33: 41.686 | O33: 49.218 | P33: =O33 | Q33: 49.218 | R33: 49.218 | S33: 49.218 | T33: 49.218 | U33: =T33 | V33: 49.218 | W33: 50.368 | X33: 50.368 | Y33: 50.368 | Z33: =Y33 | AA33: 50.368 | AB33: 51.676 | AC33: =IFERROR(AB33*(1+변수!AC41),"") | AD33: =IFERROR(AC33*(1+변수!AD41),"") | AE33: =AD33 | AF33: =IFERROR(AD33*(1+변수!AF41),"") | AG33: =IFERROR(AF33*(1+변수!AG41),"") | AH33: =IFERROR(AG33*(1+변수!AH41),"") | AI33: =IFERROR(AH33*(1+변수!AI41),"") | AJ33: =AI33 | AK33: =IFERROR(AI33*(1+변수!AK41),"") | AL33: =IFERROR(AK33*(1+변수!AL41),"") | AM33: =IFERROR(AL33*(1+변수!AM41),"") | AN33: =IFERROR(AM33*(1+변수!AN41),"") | AO33: =AN33
A34: EPS | B34: 주당 | C34: 원 | D34: EPS | E34: =IFERROR(E21*100/E33,"") | G34: =IFERROR(G21*100/G33,"") | H34: =IFERROR(H21*100/H33,"") | I34: =IFERROR(I21*100/I33,"") | J34: =IFERROR(J21*100/J33,"") | K34: =SUM(G34:J34) | L34: =IFERROR(L21*100/L33,"") | M34: =IFERROR(M21*100/M33,"") | N34: =IFERROR(N21*100/N33,"") | O34: =IFERROR(O21*100/O33,"") | P34: =SUM(L34:O34) | Q34: =IFERROR(Q21*100/Q33,"") | R34: =IFERROR(R21*100/R33,"") | S34: =IFERROR(S21*100/S33,"") | T34: =IFERROR(T21*100/T33,"") | U34: =SUM(Q34:T34) | V34: =IFERROR(V21*100/V33,"") | W34: =IFERROR(W21*100/W33,"") | X34: =IFERROR(X21*100/X33,"") | Y34: =IFERROR(Y21*100/Y33,"") | Z34: =SUM(V34:Y34) | AA34: =IFERROR(AA21*100/AA33,"") | AB34: =IFERROR(AB21*100/AB33,"") | AC34: =IFERROR(AC21*100/AC33,"") | AD34: =IFERROR(AD21*100/AD33,"") | AE34: =SUM(AA34:AD34) | AF34: =IFERROR(AF21*100/AF33,"") | AG34: =IFERROR(AG21*100/AG33,"") | AH34: =IFERROR(AH21*100/AH33,"") | AI34: =IFERROR(AI21*100/AI33,"") | AJ34: =SUM(AF34:AI34) | AK34: =IFERROR(AK21*100/AK33,"") | AL34: =IFERROR(AL21*100/AL33,"") | AM34: =IFERROR(AM21*100/AM33,"") | AN34: =IFERROR(AN21*100/AN33,"") | AO34: =SUM(AK34:AN34)
A35: BPS | B35: 주당 | C35: 원 | D35: BPS | E35: =IFERROR(E26*100/E33,"") | F35: =E35 | G35: =IFERROR(G26*100/G33,"") | H35: =IFERROR(H26*100/H33,"") | I35: =IFERROR(I26*100/I33,"") | J35: =IFERROR(J26*100/J33,"") | K35: =J35 | L35: =IFERROR(L26*100/L33,"") | M35: =IFERROR(M26*100/M33,"") | N35: =IFERROR(N26*100/N33,"") | O35: =IFERROR(O26*100/O33,"") | P35: =O35 | Q35: =IFERROR(Q26*100/Q33,"") | R35: =IFERROR(R26*100/R33,"") | S35: =IFERROR(S26*100/S33,"") | T35: =IFERROR(T26*100/T33,"") | U35: =T35 | V35: =IFERROR(V26*100/V33,"") | W35: =IFERROR(W26*100/W33,"") | X35: =IFERROR(X26*100/X33,"") | Y35: =IFERROR(Y26*100/Y33,"") | Z35: =Y35 | AA35: =IFERROR(AA26*100/AA33,"") | AB35: =IFERROR(AB26*100/AB33,"") | AC35: =IFERROR(AC26*100/AC33,"") | AD35: =IFERROR(AD26*100/AD33,"") | AE35: =AD35 | AF35: =IFERROR(AF26*100/AF33,"") | AG35: =IFERROR(AG26*100/AG33,"") | AH35: =IFERROR(AH26*100/AH33,"") | AI35: =IFERROR(AI26*100/AI33,"") | AJ35: =AI35 | AK35: =IFERROR(AK26*100/AK33,"") | AL35: =IFERROR(AL26*100/AL33,"") | AM35: =IFERROR(AM26*100/AM33,"") | AN35: =IFERROR(AN26*100/AN33,"") | AO35: =AN35
A36: DPS | B36: 주당 | C36: 원 | D36: DPS(보통주) | E36: 150 | F36: 150 | J36: 130 | K36: =SUM(G36:J36) | O36: 110 | P36: =SUM(L36:O36) | T36: 130 | U36: =SUM(Q36:T36) | Y36: 320 | Z36: =SUM(V36:Y36) | AD36: =변수!AD42 | AE36: =SUM(AA36:AD36) | AI36: =변수!AI42 | AJ36: =SUM(AF36:AI36) | AN36: =변수!AN42 | AO36: =SUM(AK36:AN36)
A37: PER | B37: 주당 | C37: 배 | D37: PER | F37: =E37 | I37: =IFERROR(변수!I18/(E34+G34+H34+I34),"") | J37: =IFERROR(변수!J18/(G34+H34+I34+J34),"") | K37: =J37 | L37: =IFERROR(변수!L18/(H34+I34+J34+L34),"") | M37: =IFERROR(변수!M18/(I34+J34+L34+M34),"") | N37: =IFERROR(변수!N18/(J34+L34+M34+N34),"") | P37: =O37 | S37: =IFERROR(변수!S18/(O34+Q34+R34+S34),"") | T37: =IFERROR(변수!T18/(Q34+R34+S34+T34),"") | U37: =T37 | V37: =IFERROR(변수!V18/(R34+S34+T34+V34),"") | W37: =IFERROR(변수!W18/(S34+T34+V34+W34),"") | X37: =IFERROR(변수!X18/(T34+V34+W34+X34),"") | Y37: =IFERROR(변수!Y18/(V34+W34+X34+Y34),"") | Z37: =Y37 | AA37: =IFERROR(변수!AA18/(W34+X34+Y34+AA34),"") | AB37: =IFERROR(변수!AB18/(X34+Y34+AA34+AB34),"") | AC37: =IFERROR(변수!$D$45/(Y34+AA34+AB34+AC34),"") | AD37: =IFERROR(변수!$D$45/(AA34+AB34+AC34+AD34),"") | AE37: =AD37 | AF37: =IFERROR(변수!$D$45/(AB34+AC34+AD34+AF34),"") | AG37: =IFERROR(변수!$D$45/(AC34+AD34+AF34+AG34),"") | AH37: =IFERROR(변수!$D$45/(AD34+AF34+AG34+AH34),"") | AI37: =IFERROR(변수!$D$45/(AF34+AG34+AH34+AI34),"") | AJ37: =AI37 | AK37: =IFERROR(변수!$D$45/(AG34+AH34+AI34+AK34),"") | AL37: =IFERROR(변수!$D$45/(AH34+AI34+AK34+AL34),"") | AM37: =IFERROR(변수!$D$45/(AI34+AK34+AL34+AM34),"") | AN37: =IFERROR(변수!$D$45/(AK34+AL34+AM34+AN34),"") | AO37: =AN37
A38: PBR | B38: 주당 | C38: 배 | D38: PBR | E38: =IFERROR(변수!E18/E35,"") | F38: =E38 | G38: =IFERROR(변수!G18/G35,"") | H38: =IFERROR(변수!H18/H35,"") | I38: =IFERROR(변수!I18/I35,"") | J38: =IFERROR(변수!J18/J35,"") | K38: =J38 | L38: =IFERROR(변수!L18/L35,"") | M38: =IFERROR(변수!M18/M35,"") | N38: =IFERROR(변수!N18/N35,"") | O38: =IFERROR(변수!O18/O35,"") | P38: =O38 | Q38: =IFERROR(변수!Q18/Q35,"") | R38: =IFERROR(변수!R18/R35,"") | S38: =IFERROR(변수!S18/S35,"") | T38: =IFERROR(변수!T18/T35,"") | U38: =T38 | V38: =IFERROR(변수!V18/V35,"") | W38: =IFERROR(변수!W18/W35,"") | X38: =IFERROR(변수!X18/X35,"") | Y38: =IFERROR(변수!Y18/Y35,"") | Z38: =Y38 | AA38: =IFERROR(변수!AA18/AA35,"") | AB38: =IFERROR(변수!AB18/AB35,"") | AC38: =IFERROR(변수!$D$45/AC35,"") | AD38: =IFERROR(변수!$D$45/AD35,"") | AE38: =AD38 | AF38: =IFERROR(변수!$D$45/AF35,"") | AG38: =IFERROR(변수!$D$45/AG35,"") | AH38: =IFERROR(변수!$D$45/AH35,"") | AI38: =IFERROR(변수!$D$45/AI35,"") | AJ38: =AI38 | AK38: =IFERROR(변수!$D$45/AK35,"") | AL38: =IFERROR(변수!$D$45/AL35,"") | AM38: =IFERROR(변수!$D$45/AM35,"") | AN38: =IFERROR(변수!$D$45/AN35,"") | AO38: =AN38
A39: 매출전사 | B39: 사업부 | C39: 억원 | D39: 매출 전사(부문 미분리) | E39: 812.74 | G39: 777.43 | H39: 715.66 | I39: 1140.28 | J39: 1059.34 | K39: =SUM(G39:J39) | L39: 1029.92 | M39: 1338.13 | N39: 1556.53 | O39: 2019.59 | P39: =SUM(L39:O39) | Q39: 1827.5 | R39: 1942.12 | S39: 1706.21 | T39: 1941.58 | U39: =SUM(Q39:T39) | V39: 2245.62 | W39: 2312.73 | X39: 2211.32 | Y39: 2318.43 | Z39: =SUM(V39:Y39) | AA39: 2118.22 | AB39: 2433.78 | AC39: =IFERROR(AC5,"") | AD39: =IFERROR(AD5,"") | AE39: =SUM(AA39:AD39) | AF39: =IFERROR(AF5,"") | AG39: =IFERROR(AG5,"") | AH39: =IFERROR(AH5,"") | AI39: =IFERROR(AI5,"") | AJ39: =SUM(AF39:AI39) | AK39: =IFERROR(AK5,"") | AL39: =IFERROR(AL5,"") | AM39: =IFERROR(AM5,"") | AN39: =IFERROR(AN5,"") | AO39: =SUM(AK39:AN39)
A40: OP전사 | B40: 사업부 | C40: 억원 | D40: OP 전사(부문 미분리) | E40: 32.77 | G40: 42.83 | H40: 24.92 | I40: 119.85 | J40: 60.38 | K40: =SUM(G40:J40) | L40: 37.38 | M40: 78.95 | N40: 46.14 | O40: 2.19 | P40: =SUM(L40:O40) | Q40: 26.08 | R40: 177.79 | S40: 76.84 | T40: 173.75 | U40: =SUM(Q40:T40) | V40: 311.07 | W40: 316.44 | X40: 298.63 | Y40: 383.37 | Z40: =SUM(V40:Y40) | AA40: 410.66 | AB40: 504 | AC40: =IFERROR(AC9,"") | AD40: =IFERROR(AD9,"") | AE40: =SUM(AA40:AD40) | AF40: =IFERROR(AF9,"") | AG40: =IFERROR(AG9,"") | AH40: =IFERROR(AH9,"") | AI40: =IFERROR(AI9,"") | AJ40: =SUM(AF40:AI40) | AK40: =IFERROR(AK9,"") | AL40: =IFERROR(AL9,"") | AM40: =IFERROR(AM9,"") | AN40: =IFERROR(AN9,"") | AO40: =SUM(AK40:AN40)
B41: 비율(참고)
A42: NPM | C42: % | D42: 지배주주순이익 / 매출액 | E42: =IFERROR(E21/E5,"") | F42: =IFERROR(F21/F5,"") | G42: =IFERROR(G21/G5,"") | H42: =IFERROR(H21/H5,"") | I42: =IFERROR(I21/I5,"") | J42: =IFERROR(J21/J5,"") | K42: =IFERROR(K21/K5,"") | L42: =IFERROR(L21/L5,"") | ... AO42: =IFERROR(AO21/AO5,"")
A43: 매출원가율 | C43: % | D43: 매출원가 / 매출액 | E43: =IFERROR(E6/E5,"") | F43: =IFERROR(F6/F5,"") | G43: =IFERROR(G6/G5,"") | H43: =IFERROR(H6/H5,"") | I43: =IFERROR(I6/I5,"") | J43: =IFERROR(J6/J5,"") | K43: =IFERROR(K6/K5,"") | L43: =IFERROR(L6/L5,"") | ... AO43: =IFERROR(AO6/AO5,"")
A44: 판관비율 | C44: % | D44: 판관비 / 매출액 | E44: =IFERROR(E8/E5,"") | F44: =IFERROR(F8/F5,"") | G44: =IFERROR(G8/G5,"") | H44: =IFERROR(H8/H5,"") | I44: =IFERROR(I8/I5,"") | J44: =IFERROR(J8/J5,"") | K44: =IFERROR(K8/K5,"") | L44: =IFERROR(L8/L5,"") | ... AO44: =IFERROR(AO8/AO5,"")

Sheet 분기
C1: 이름: 분기H — subQ 를 이름으로 VLOOKUP(억원) | E1: 4Q21 | F1: 1Q22 | G1: 2Q22 | H1: 3Q22 | I1: 4Q22 | J1: 1Q23 | K1: 2Q23 | L1: 3Q23 | M1: 4Q23 | N1: 1Q24 | O1: 2Q24 | P1: 3Q24 | Q1: 4Q24 | R1: 1Q25 | S1: 2Q25 | T1: 3Q25 | U1: 4Q25 | V1: 1Q26 | W1: 2Q26 | X1: 3Q26 | Y1: 4Q26 | Z1: 1Q27 | AA1: 2Q27 | AB1: 3Q27 | AC1: 4Q27 | AD1: 1Q28 | AE1: 2Q28 | AF1: 3Q28 | AG1: 4Q28
C2: 종가: | D2: =변수!D45
C3: 기준일: | D3: 20261008 | E3: 1 | F3: 2 | G3: 3 | H3: 4 | I3: 5 | J3: 6 | K3: 7 | L3: 8 | M3: 9 | N3: 10 | O3: 11 | P3: 12 | Q3: 13 | R3: 14 | S3: 15 | T3: 16 | U3: 17 | V3: 18 | W3: 19 | X3: 20 | Y3: 21 | Z3: 22 | AA3: 23 | AB3: 24 | AC3: 25 | AD3: 26 | AE3: 27 | AF3: 28 | AG3: 29
E4: 2021.12 | F4: 2022.03 | G4: 2022.06 | H4: 2022.09 | I4: 2022.12 | J4: 2023.03 | K4: 2023.06 | L4: 2023.09 | M4: 2023.12 | N4: 2024.03 | O4: 2024.06 | P4: 2024.09 | Q4: 2024.12 | R4: 2025.03 | S4: 2025.06 | T4: 2025.09 | U4: 2025.12 | V4: 2026.03 | W4: 2026.06 | X4: 2026.09 | Y4: 2026.12 | Z4: 2027.03 | AA4: 2027.06 | AB4: 2027.09 | AC4: 2027.12 | AD4: 2028.03 | AE4: 2028.06 | AF4: 2028.09 | AG4: 2028.12
A5: 매출액 | D5: 매출액 | E5: =IFERROR(VLOOKUP($A5,subQ,MATCH(E$1,SUBQH,0),0),"") | F5: =IFERROR(VLOOKUP($A5,subQ,MATCH(F$1,SUBQH,0),0),"") | G5: =IFERROR(VLOOKUP($A5,subQ,MATCH(G$1,SUBQH,0),0),"") | H5: =IFERROR(VLOOKUP($A5,subQ,MATCH(H$1,SUBQH,0),0),"") | I5: =IFERROR(VLOOKUP($A5,subQ,MATCH(I$1,SUBQH,0),0),"") | J5: =IFERROR(VLOOKUP($A5,subQ,MATCH(J$1,SUBQH,0),0),"") | K5: =IFERROR(VLOOKUP($A5,subQ,MATCH(K$1,SUBQH,0),0),"") | L5: =IFERROR(VLOOKUP($A5,subQ,MATCH(L$1,SUBQH,0),0),"") | ... AG5: =IFERROR(VLOOKUP($A5,subQ,MATCH(AG$1,SUBQH,0),0),"")
A6: 매출원가 | D6: 매출원가 | E6: =IFERROR(VLOOKUP($A6,subQ,MATCH(E$1,SUBQH,0),0),"") | F6: =IFERROR(VLOOKUP($A6,subQ,MATCH(F$1,SUBQH,0),0),"") | G6: =IFERROR(VLOOKUP($A6,subQ,MATCH(G$1,SUBQH,0),0),"") | H6: =IFERROR(VLOOKUP($A6,subQ,MATCH(H$1,SUBQH,0),0),"") | I6: =IFERROR(VLOOKUP($A6,subQ,MATCH(I$1,SUBQH,0),0),"") | J6: =IFERROR(VLOOKUP($A6,subQ,MATCH(J$1,SUBQH,0),0),"") | K6: =IFERROR(VLOOKUP($A6,subQ,MATCH(K$1,SUBQH,0),0),"") | L6: =IFERROR(VLOOKUP($A6,subQ,MATCH(L$1,SUBQH,0),0),"") | ... AG6: =IFERROR(VLOOKUP($A6,subQ,MATCH(AG$1,SUBQH,0),0),"")
A7: 매출총이익 | D7: 매출총이익 | E7: =IFERROR(VLOOKUP($A7,subQ,MATCH(E$1,SUBQH,0),0),"") | F7: =IFERROR(VLOOKUP($A7,subQ,MATCH(F$1,SUBQH,0),0),"") | G7: =IFERROR(VLOOKUP($A7,subQ,MATCH(G$1,SUBQH,0),0),"") | H7: =IFERROR(VLOOKUP($A7,subQ,MATCH(H$1,SUBQH,0),0),"") | I7: =IFERROR(VLOOKUP($A7,subQ,MATCH(I$1,SUBQH,0),0),"") | J7: =IFERROR(VLOOKUP($A7,subQ,MATCH(J$1,SUBQH,0),0),"") | K7: =IFERROR(VLOOKUP($A7,subQ,MATCH(K$1,SUBQH,0),0),"") | L7: =IFERROR(VLOOKUP($A7,subQ,MATCH(L$1,SUBQH,0),0),"") | ... AG7: =IFERROR(VLOOKUP($A7,subQ,MATCH(AG$1,SUBQH,0),0),"")
A8: 판관비 | D8: 판매비와관리비 | E8: =IFERROR(VLOOKUP($A8,subQ,MATCH(E$1,SUBQH,0),0),"") | F8: =IFERROR(VLOOKUP($A8,subQ,MATCH(F$1,SUBQH,0),0),"") | G8: =IFERROR(VLOOKUP($A8,subQ,MATCH(G$1,SUBQH,0),0),"") | H8: =IFERROR(VLOOKUP($A8,subQ,MATCH(H$1,SUBQH,0),0),"") | I8: =IFERROR(VLOOKUP($A8,subQ,MATCH(I$1,SUBQH,0),0),"") | J8: =IFERROR(VLOOKUP($A8,subQ,MATCH(J$1,SUBQH,0),0),"") | K8: =IFERROR(VLOOKUP($A8,subQ,MATCH(K$1,SUBQH,0),0),"") | L8: =IFERROR(VLOOKUP($A8,subQ,MATCH(L$1,SUBQH,0),0),"") | ... AG8: =IFERROR(VLOOKUP($A8,subQ,MATCH(AG$1,SUBQH,0),0),"")
A9: 영업이익 | D9: 영업이익 | E9: =IFERROR(VLOOKUP($A9,subQ,MATCH(E$1,SUBQH,0),0),"") | F9: =IFERROR(VLOOKUP($A9,subQ,MATCH(F$1,SUBQH,0),0),"") | G9: =IFERROR(VLOOKUP($A9,subQ,MATCH(G$1,SUBQH,0),0),"") | H9: =IFERROR(VLOOKUP($A9,subQ,MATCH(H$1,SUBQH,0),0),"") | I9: =IFERROR(VLOOKUP($A9,subQ,MATCH(I$1,SUBQH,0),0),"") | J9: =IFERROR(VLOOKUP($A9,subQ,MATCH(J$1,SUBQH,0),0),"") | K9: =IFERROR(VLOOKUP($A9,subQ,MATCH(K$1,SUBQH,0),0),"") | L9: =IFERROR(VLOOKUP($A9,subQ,MATCH(L$1,SUBQH,0),0),"") | ... AG9: =IFERROR(VLOOKUP($A9,subQ,MATCH(AG$1,SUBQH,0),0),"")
A10: OPM | D10: 영업이익률 | E10: =IFERROR(VLOOKUP($A10,subQ,MATCH(E$1,SUBQH,0),0),"") | F10: =IFERROR(VLOOKUP($A10,subQ,MATCH(F$1,SUBQH,0),0),"") | G10: =IFERROR(VLOOKUP($A10,subQ,MATCH(G$1,SUBQH,0),0),"") | H10: =IFERROR(VLOOKUP($A10,subQ,MATCH(H$1,SUBQH,0),0),"") | I10: =IFERROR(VLOOKUP($A10,subQ,MATCH(I$1,SUBQH,0),0),"") | J10: =IFERROR(VLOOKUP($A10,subQ,MATCH(J$1,SUBQH,0),0),"") | K10: =IFERROR(VLOOKUP($A10,subQ,MATCH(K$1,SUBQH,0),0),"") | L10: =IFERROR(VLOOKUP($A10,subQ,MATCH(L$1,SUBQH,0),0),"") | ... AG10: =IFERROR(VLOOKUP($A10,subQ,MATCH(AG$1,SUBQH,0),0),"")
A11: 금융손익 | D11: 금융손익(이자·환 포함) | E11: =IFERROR(VLOOKUP($A11,subQ,MATCH(E$1,SUBQH,0),0),"") | F11: =IFERROR(VLOOKUP($A11,subQ,MATCH(F$1,SUBQH,0),0),"") | G11: =IFERROR(VLOOKUP($A11,subQ,MATCH(G$1,SUBQH,0),0),"") | H11: =IFERROR(VLOOKUP($A11,subQ,MATCH(H$1,SUBQH,0),0),"") | I11: =IFERROR(VLOOKUP($A11,subQ,MATCH(I$1,SUBQH,0),0),"") | J11: =IFERROR(VLOOKUP($A11,subQ,MATCH(J$1,SUBQH,0),0),"") | K11: =IFERROR(VLOOKUP($A11,subQ,MATCH(K$1,SUBQH,0),0),"") | L11: =IFERROR(VLOOKUP($A11,subQ,MATCH(L$1,SUBQH,0),0),"") | ... AG11: =IFERROR(VLOOKUP($A11,subQ,MATCH(AG$1,SUBQH,0),0),"")
A12: 이자손익 | D12: 이자손익(이자수익 − 이자비용) | E12: =IFERROR(VLOOKUP($A12,subQ,MATCH(E$1,SUBQH,0),0),"") | F12: =IFERROR(VLOOKUP($A12,subQ,MATCH(F$1,SUBQH,0),0),"") | G12: =IFERROR(VLOOKUP($A12,subQ,MATCH(G$1,SUBQH,0),0),"") | H12: =IFERROR(VLOOKUP($A12,subQ,MATCH(H$1,SUBQH,0),0),"") | I12: =IFERROR(VLOOKUP($A12,subQ,MATCH(I$1,SUBQH,0),0),"") | J12: =IFERROR(VLOOKUP($A12,subQ,MATCH(J$1,SUBQH,0),0),"") | K12: =IFERROR(VLOOKUP($A12,subQ,MATCH(K$1,SUBQH,0),0),"") | L12: =IFERROR(VLOOKUP($A12,subQ,MATCH(L$1,SUBQH,0),0),"") | ... AG12: =IFERROR(VLOOKUP($A12,subQ,MATCH(AG$1,SUBQH,0),0),"")
A13: 외환손익 | D13: 외환손익(실적만; 추정 환효과는 환관련손익) | E13: =IFERROR(VLOOKUP($A13,subQ,MATCH(E$1,SUBQH,0),0),"") | F13: =IFERROR(VLOOKUP($A13,subQ,MATCH(F$1,SUBQH,0),0),"") | G13: =IFERROR(VLOOKUP($A13,subQ,MATCH(G$1,SUBQH,0),0),"") | H13: =IFERROR(VLOOKUP($A13,subQ,MATCH(H$1,SUBQH,0),0),"") | I13: =IFERROR(VLOOKUP($A13,subQ,MATCH(I$1,SUBQH,0),0),"") | J13: =IFERROR(VLOOKUP($A13,subQ,MATCH(J$1,SUBQH,0),0),"") | K13: =IFERROR(VLOOKUP($A13,subQ,MATCH(K$1,SUBQH,0),0),"") | L13: =IFERROR(VLOOKUP($A13,subQ,MATCH(L$1,SUBQH,0),0),"") | ... AG13: =IFERROR(VLOOKUP($A13,subQ,MATCH(AG$1,SUBQH,0),0),"")
A14: 파생상품손익 | D14: 파생상품손익 | E14: =IFERROR(VLOOKUP($A14,subQ,MATCH(E$1,SUBQH,0),0),"") | F14: =IFERROR(VLOOKUP($A14,subQ,MATCH(F$1,SUBQH,0),0),"") | G14: =IFERROR(VLOOKUP($A14,subQ,MATCH(G$1,SUBQH,0),0),"") | H14: =IFERROR(VLOOKUP($A14,subQ,MATCH(H$1,SUBQH,0),0),"") | I14: =IFERROR(VLOOKUP($A14,subQ,MATCH(I$1,SUBQH,0),0),"") | J14: =IFERROR(VLOOKUP($A14,subQ,MATCH(J$1,SUBQH,0),0),"") | K14: =IFERROR(VLOOKUP($A14,subQ,MATCH(K$1,SUBQH,0),0),"") | L14: =IFERROR(VLOOKUP($A14,subQ,MATCH(L$1,SUBQH,0),0),"") | ... AG14: =IFERROR(VLOOKUP($A14,subQ,MATCH(AG$1,SUBQH,0),0),"")
A15: 기타금융손익 | D15: 기타금융손익(금융손익 잔차) | E15: =IFERROR(VLOOKUP($A15,subQ,MATCH(E$1,SUBQH,0),0),"") | F15: =IFERROR(VLOOKUP($A15,subQ,MATCH(F$1,SUBQH,0),0),"") | G15: =IFERROR(VLOOKUP($A15,subQ,MATCH(G$1,SUBQH,0),0),"") | H15: =IFERROR(VLOOKUP($A15,subQ,MATCH(H$1,SUBQH,0),0),"") | I15: =IFERROR(VLOOKUP($A15,subQ,MATCH(I$1,SUBQH,0),0),"") | J15: =IFERROR(VLOOKUP($A15,subQ,MATCH(J$1,SUBQH,0),0),"") | K15: =IFERROR(VLOOKUP($A15,subQ,MATCH(K$1,SUBQH,0),0),"") | L15: =IFERROR(VLOOKUP($A15,subQ,MATCH(L$1,SUBQH,0),0),"") | ... AG15: =IFERROR(VLOOKUP($A15,subQ,MATCH(AG$1,SUBQH,0),0),"")
A16: 기타영업외손익 | D16: 기타영업외손익 | E16: =IFERROR(VLOOKUP($A16,subQ,MATCH(E$1,SUBQH,0),0),"") | F16: =IFERROR(VLOOKUP($A16,subQ,MATCH(F$1,SUBQH,0),0),"") | G16: =IFERROR(VLOOKUP($A16,subQ,MATCH(G$1,SUBQH,0),0),"") | H16: =IFERROR(VLOOKUP($A16,subQ,MATCH(H$1,SUBQH,0),0),"") | I16: =IFERROR(VLOOKUP($A16,subQ,MATCH(I$1,SUBQH,0),0),"") | J16: =IFERROR(VLOOKUP($A16,subQ,MATCH(J$1,SUBQH,0),0),"") | K16: =IFERROR(VLOOKUP($A16,subQ,MATCH(K$1,SUBQH,0),0),"") | L16: =IFERROR(VLOOKUP($A16,subQ,MATCH(L$1,SUBQH,0),0),"") | ... AG16: =IFERROR(VLOOKUP($A16,subQ,MATCH(AG$1,SUBQH,0),0),"")
... A41: NPM | D41: NPM | E41: =IFERROR(VLOOKUP($A41,subQ,MATCH(E$1,SUBQH,0),0),"") | F41: =IFERROR(VLOOKUP($A41,subQ,MATCH(F$1,SUBQH,0),0),"") | G41: =IFERROR(VLOOKUP($A41,subQ,MATCH(G$1,SUBQH,0),0),"") | H41: =IFERROR(VLOOKUP($A41,subQ,MATCH(H$1,SUBQH,0),0),"") | I41: =IFERROR(VLOOKUP($A41,subQ,MATCH(I$1,SUBQH,0),0),"") | J41: =IFERROR(VLOOKUP($A41,subQ,MATCH(J$1,SUBQH,0),0),"") | K41: =IFERROR(VLOOKUP($A41,subQ,MATCH(K$1,SUBQH,0),0),"") | L41: =IFERROR(VLOOKUP($A41,subQ,MATCH(L$1,SUBQH,0),0),"") | ... AG41: =IFERROR(VLOOKUP($A41,subQ,MATCH(AG$1,SUBQH,0),0),"")
A42: 매출액 YoY | D42: 매출액 YoY | I42: =IFERROR(I5/E5-1,"") | J42: =IFERROR(J5/F5-1,"") | K42: =IFERROR(K5/G5-1,"") | L42: =IFERROR(L5/H5-1,"") | M42: =IFERROR(M5/I5-1,"") | N42: =IFERROR(N5/J5-1,"") | O42: =IFERROR(O5/K5-1,"") | P42: =IFERROR(P5/L5-1,"") | ... AG42: =IFERROR(AG5/AC5-1,"")
A43: 영업이익 YoY | D43: 영업이익 YoY | I43: =IFERROR(I9/E9-1,"") | J43: =IFERROR(J9/F9-1,"") | K43: =IFERROR(K9/G9-1,"") | L43: =IFERROR(L9/H9-1,"") | M43: =IFERROR(M9/I9-1,"") | N43: =IFERROR(N9/J9-1,"") | O43: =IFERROR(O9/K9-1,"") | P43: =IFERROR(P9/L9-1,"") | ... AG43: =IFERROR(AG9/AC9-1,"")
A44: 지배주주순이익 YoY | D44: 지배주주순이익 YoY | I44: =IFERROR(I21/E21-1,"") | J44: =IFERROR(J21/F21-1,"") | K44: =IFERROR(K21/G21-1,"") | L44: =IFERROR(L21/H21-1,"") | M44: =IFERROR(M21/I21-1,"") | N44: =IFERROR(N21/J21-1,"") | O44: =IFERROR(O21/K21-1,"") | P44: =IFERROR(P21/L21-1,"") | ... AG44: =IFERROR(AG21/AC21-1,"")

Sheet 연간예상
C1: 이름: 연간예상H — subQ 를 이름으로 VLOOKUP(억원) | E1: 2021 | F1: 2022 | G1: 2023 | H1: 2024 | I1: 2025 | J1: 2026 | K1: 2027 | L1: 2028
C2: 종가: | D2: =변수!D45
C3: 기준일: | D3: 20261008 | E3: 1 | F3: 2 | G3: 3 | H3: 4 | I3: 5 | J3: 6 | K3: 7 | L3: 8
E4: 2021.12A | F4: 2022.12A | G4: 2023.12A | H4: 2024.12A | I4: 2025.12A | J4: 2026.12A | K4: 2027.12A | L4: 2028.12A
A5: 매출액 | D5: 매출액 | E5: =IFERROR(VLOOKUP($A5,subQ,MATCH(E$1,SUBQH,0),0),"") | F5: =IFERROR(VLOOKUP($A5,subQ,MATCH(F$1,SUBQH,0),0),"") | G5: =IFERROR(VLOOKUP($A5,subQ,MATCH(G$1,SUBQH,0),0),"") | H5: =IFERROR(VLOOKUP($A5,subQ,MATCH(H$1,SUBQH,0),0),"") | I5: =IFERROR(VLOOKUP($A5,subQ,MATCH(I$1,SUBQH,0),0),"") | J5: =IFERROR(VLOOKUP($A5,subQ,MATCH(J$1,SUBQH,0),0),"") | K5: =IFERROR(VLOOKUP($A5,subQ,MATCH(K$1,SUBQH,0),0),"") | L5: =IFERROR(VLOOKUP($A5,subQ,MATCH(L$1,SUBQH,0),0),"")
A6: 매출원가 | D6: 매출원가 | E6: =IFERROR(VLOOKUP($A6,subQ,MATCH(E$1,SUBQH,0),0),"") | F6: =IFERROR(VLOOKUP($A6,subQ,MATCH(F$1,SUBQH,0),0),"") | G6: =IFERROR(VLOOKUP($A6,subQ,MATCH(G$1,SUBQH,0),0),"") | H6: =IFERROR(VLOOKUP($A6,subQ,MATCH(H$1,SUBQH,0),0),"") | I6: =IFERROR(VLOOKUP($A6,subQ,MATCH(I$1,SUBQH,0),0),"") | J6: =IFERROR(VLOOKUP($A6,subQ,MATCH(J$1,SUBQH,0),0),"") | K6: =IFERROR(VLOOKUP($A6,subQ,MATCH(K$1,SUBQH,0),0),"") | L6: =IFERROR(VLOOKUP($A6,subQ,MATCH(L$1,SUBQH,0),0),"")
A7: 매출총이익 | D7: 매출총이익 | E7: =IFERROR(VLOOKUP($A7,subQ,MATCH(E$1,SUBQH,0),0),"") | F7: =IFERROR(VLOOKUP($A7,subQ,MATCH(F$1,SUBQH,0),0),"") | G7: =IFERROR(VLOOKUP($A7,subQ,MATCH(G$1,SUBQH,0),0),"") | H7: =IFERROR(VLOOKUP($A7,subQ,MATCH(H$1,SUBQH,0),0),"") | I7: =IFERROR(VLOOKUP($A7,subQ,MATCH(I$1,SUBQH,0),0),"") | J7: =IFERROR(VLOOKUP($A7,subQ,MATCH(J$1,SUBQH,0),0),"") | K7: =IFERROR(VLOOKUP($A7,subQ,MATCH(K$1,SUBQH,0),0),"") | L7: =IFERROR(VLOOKUP($A7,subQ,MATCH(L$1,SUBQH,0),0),"")
A8: 판관비 | D8: 판매비와관리비 | E8: =IFERROR(VLOOKUP($A8,subQ,MATCH(E$1,SUBQH,0),0),"") | F8: =IFERROR(VLOOKUP($A8,subQ,MATCH(F$1,SUBQH,0),0),"") | G8: =IFERROR(VLOOKUP($A8,subQ,MATCH(G$1,SUBQH,0),0),"") | H8: =IFERROR(VLOOKUP($A8,subQ,MATCH(H$1,SUBQH,0),0),"") | I8: =IFERROR(VLOOKUP($A8,subQ,MATCH(I$1,SUBQH,0),0),"") | J8: =IFERROR(VLOOKUP($A8,subQ,MATCH(J$1,SUBQH,0),0),"") | K8: =IFERROR(VLOOKUP($A8,subQ,MATCH(K$1,SUBQH,0),0),"") | L8: =IFERROR(VLOOKUP($A8,subQ,MATCH(L$1,SUBQH,0),0),"")
A9: 영업이익 | D9: 영업이익 | E9: =IFERROR(VLOOKUP($A9,subQ,MATCH(E$1,SUBQH,0),0),"") | F9: =IFERROR(VLOOKUP($A9,subQ,MATCH(F$1,SUBQH,0),0),"") | G9: =IFERROR(VLOOKUP($A9,subQ,MATCH(G$1,SUBQH,0),0),"") | H9: =IFERROR(VLOOKUP($A9,subQ,MATCH(H$1,SUBQH,0),0),"") | I9: =IFERROR(VLOOKUP($A9,subQ,MATCH(I$1,SUBQH,0),0),"") | J9: =IFERROR(VLOOKUP($A9,subQ,MATCH(J$1,SUBQH,0),0),"") | K9: =IFERROR(VLOOKUP($A9,subQ,MATCH(K$1,SUBQH,0),0),"") | L9: =IFERROR(VLOOKUP($A9,subQ,MATCH(L$1,SUBQH,0),0),"")
A10: OPM | D10: 영업이익률 | E10: =IFERROR(VLOOKUP($A10,subQ,MATCH(E$1,SUBQH,0),0),"") | F10: =IFERROR(VLOOKUP($A10,subQ,MATCH(F$1,SUBQH,0),0),"") | G10: =IFERROR(VLOOKUP($A10,subQ,MATCH(G$1,SUBQH,0),0),"") | H10: =IFERROR(VLOOKUP($A10,subQ,MATCH(H$1,SUBQH,0),0),"") | I10: =IFERROR(VLOOKUP($A10,subQ,MATCH(I$1,SUBQH,0),0),"") | J10: =IFERROR(VLOOKUP($A10,subQ,MATCH(J$1,SUBQH,0),0),"") | K10: =IFERROR(VLOOKUP($A10,subQ,MATCH(K$1,SUBQH,0),0),"") | L10: =IFERROR(VLOOKUP($A10,subQ,MATCH(L$1,SUBQH,0),0),"")
A11: 금융손익 | D11: 금융손익(이자·환 포함) | E11: =IFERROR(VLOOKUP($A11,subQ,MATCH(E$1,SUBQH,0),0),"") | F11: =IFERROR(VLOOKUP($A11,subQ,MATCH(F$1,SUBQH,0),0),"") | G11: =IFERROR(VLOOKUP($A11,subQ,MATCH(G$1,SUBQH,0),0),"") | H11: =IFERROR(VLOOKUP($A11,subQ,MATCH(H$1,SUBQH,0),0),"") | I11: =IFERROR(VLOOKUP($A11,subQ,MATCH(I$1,SUBQH,0),0),"") | J11: =IFERROR(VLOOKUP($A11,subQ,MATCH(J$1,SUBQH,0),0),"") | K11: =IFERROR(VLOOKUP($A11,subQ,MATCH(K$1,SUBQH,0),0),"") | L11: =IFERROR(VLOOKUP($A11,subQ,MATCH(L$1,SUBQH,0),0),"")
A12: 이자손익 | D12: 이자손익(이자수익 − 이자비용) | E12: =IFERROR(VLOOKUP($A12,subQ,MATCH(E$1,SUBQH,0),0),"") | F12: =IFERROR(VLOOKUP($A12,subQ,MATCH(F$1,SUBQH,0),0),"") | G12: =IFERROR(VLOOKUP($A12,subQ,MATCH(G$1,SUBQH,0),0),"") | H12: =IFERROR(VLOOKUP($A12,subQ,MATCH(H$1,SUBQH,0),0),"") | I12: =IFERROR(VLOOKUP($A12,subQ,MATCH(I$1,SUBQH,0),0),"") | J12: =IFERROR(VLOOKUP($A12,subQ,MATCH(J$1,SUBQH,0),0),"") | K12: =IFERROR(VLOOKUP($A12,subQ,MATCH(K$1,SUBQH,0),0),"") | L12: =IFERROR(VLOOKUP($A12,subQ,MATCH(L$1,SUBQH,0),0),"")
A13: 외환손익 | D13: 외환손익(실적만; 추정 환효과는 환관련손익) | E13: =IFERROR(VLOOKUP($A13,subQ,MATCH(E$1,SUBQH,0),0),"") | F13: =IFERROR(VLOOKUP($A13,subQ,MATCH(F$1,SUBQH,0),0),"") | G13: =IFERROR(VLOOKUP($A13,subQ,MATCH(G$1,SUBQH,0),0),"") | H13: =IFERROR(VLOOKUP($A13,subQ,MATCH(H$1,SUBQH,0),0),"") | I13: =IFERROR(VLOOKUP($A13,subQ,MATCH(I$1,SUBQH,0),0),"") | J13: =IFERROR(VLOOKUP($A13,subQ,MATCH(J$1,SUBQH,0),0),"") | K13: =IFERROR(VLOOKUP($A13,subQ,MATCH(K$1,SUBQH,0),0),"") | L13: =IFERROR(VLOOKUP($A13,subQ,MATCH(L$1,SUBQH,0),0),"")
A14: 파생상품손익 | D14: 파생상품손익 | E14: =IFERROR(VLOOKUP($A14,subQ,MATCH(E$1,SUBQH,0),0),"") | F14: =IFERROR(VLOOKUP($A14,subQ,MATCH(F$1,SUBQH,0),0),"") | G14: =IFERROR(VLOOKUP($A14,subQ,MATCH(G$1,SUBQH,0),0),"") | H14: =IFERROR(VLOOKUP($A14,subQ,MATCH(H$1,SUBQH,0),0),"") | I14: =IFERROR(VLOOKUP($A14,subQ,MATCH(I$1,SUBQH,0),0),"") | J14: =IFERROR(VLOOKUP($A14,subQ,MATCH(J$1,SUBQH,0),0),"") | K14: =IFERROR(VLOOKUP($A14,subQ,MATCH(K$1,SUBQH,0),0),"") | L14: =IFERROR(VLOOKUP($A14,subQ,MATCH(L$1,SUBQH,0),0),"")
A15: 기타금융손익 | D15: 기타금융손익(금융손익 잔차) | E15: =IFERROR(VLOOKUP($A15,subQ,MATCH(E$1,SUBQH,0),0),"") | F15: =IFERROR(VLOOKUP($A15,subQ,MATCH(F$1,SUBQH,0),0),"") | G15: =IFERROR(VLOOKUP($A15,subQ,MATCH(G$1,SUBQH,0),0),"") | H15: =IFERROR(VLOOKUP($A15,subQ,MATCH(H$1,SUBQH,0),0),"") | I15: =IFERROR(VLOOKUP($A15,subQ,MATCH(I$1,SUBQH,0),0),"") | J15: =IFERROR(VLOOKUP($A15,subQ,MATCH(J$1,SUBQH,0),0),"") | K15: =IFERROR(VLOOKUP($A15,subQ,MATCH(K$1,SUBQH,0),0),"") | L15: =IFERROR(VLOOKUP($A15,subQ,MATCH(L$1,SUBQH,0),0),"")
A16: 기타영업외손익 | D16: 기타영업외손익 | E16: =IFERROR(VLOOKUP($A16,subQ,MATCH(E$1,SUBQH,0),0),"") | F16: =IFERROR(VLOOKUP($A16,subQ,MATCH(F$1,SUBQH,0),0),"") | G16: =IFERROR(VLOOKUP($A16,subQ,MATCH(G$1,SUBQH,0),0),"") | H16: =IFERROR(VLOOKUP($A16,subQ,MATCH(H$1,SUBQH,0),0),"") | I16: =IFERROR(VLOOKUP($A16,subQ,MATCH(I$1,SUBQH,0),0),"") | J16: =IFERROR(VLOOKUP($A16,subQ,MATCH(J$1,SUBQH,0),0),"") | K16: =IFERROR(VLOOKUP($A16,subQ,MATCH(K$1,SUBQH,0),0),"") | L16: =IFERROR(VLOOKUP($A16,subQ,MATCH(L$1,SUBQH,0),0),"")
... A41: NPM | D41: NPM | E41: =IFERROR(VLOOKUP($A41,subQ,MATCH(E$1,SUBQH,0),0),"") | F41: =IFERROR(VLOOKUP($A41,subQ,MATCH(F$1,SUBQH,0),0),"") | G41: =IFERROR(VLOOKUP($A41,subQ,MATCH(G$1,SUBQH,0),0),"") | H41: =IFERROR(VLOOKUP($A41,subQ,MATCH(H$1,SUBQH,0),0),"") | I41: =IFERROR(VLOOKUP($A41,subQ,MATCH(I$1,SUBQH,0),0),"") | J41: =IFERROR(VLOOKUP($A41,subQ,MATCH(J$1,SUBQH,0),0),"") | K41: =IFERROR(VLOOKUP($A41,subQ,MATCH(K$1,SUBQH,0),0),"") | L41: =IFERROR(VLOOKUP($A41,subQ,MATCH(L$1,SUBQH,0),0),"")
A42: 매출액 YoY | D42: 매출액 YoY | F42: =IFERROR(F5/E5-1,"") | G42: =IFERROR(G5/F5-1,"") | H42: =IFERROR(H5/G5-1,"") | I42: =IFERROR(I5/H5-1,"") | J42: =IFERROR(J5/I5-1,"") | K42: =IFERROR(K5/J5-1,"") | L42: =IFERROR(L5/K5-1,"")
A43: 영업이익 YoY | D43: 영업이익 YoY | F43: =IFERROR(F9/E9-1,"") | G43: =IFERROR(G9/F9-1,"") | H43: =IFERROR(H9/G9-1,"") | I43: =IFERROR(I9/H9-1,"") | J43: =IFERROR(J9/I9-1,"") | K43: =IFERROR(K9/J9-1,"") | L43: =IFERROR(L9/K9-1,"")
A44: 지배주주순이익 YoY | D44: 지배주주순이익 YoY | F44: =IFERROR(F21/E21-1,"") | G44: =IFERROR(G21/F21-1,"") | H44: =IFERROR(H21/G21-1,"") | I44: =IFERROR(I21/H21-1,"") | J44: =IFERROR(J21/I21-1,"") | K44: =IFERROR(K21/J21-1,"") | L44: =IFERROR(L21/K21-1,"")

Sheet TP
B1: 종가 | C1: =변수!D45
B2: 기준일 | C2: =변수!D46
B3: 모델 산출값 — 목표주가·추천 아님. 밴드·COE 는 변수 시트 3절의 가정
C5: FY | D5: 2025 | E5: 2026 | F5: 2027 | G5: 2028
D6: A | E6: E | F6: E | G6: E
C7: EPS(원) | D7: =IFERROR(VLOOKUP("EPS",subQ,MATCH(D$5,SUBQH,0),0),"") | E7: =IFERROR(VLOOKUP("EPS",subQ,MATCH(E$5,SUBQH,0),0),"") | F7: =IFERROR(VLOOKUP("EPS",subQ,MATCH(F$5,SUBQH,0),0),"") | G7: =IFERROR(VLOOKUP("EPS",subQ,MATCH(G$5,SUBQH,0),0),"")
C8: BPS(원) | D8: =IFERROR(VLOOKUP("BPS",subQ,MATCH(D$5,SUBQH,0),0),"") | E8: =IFERROR(VLOOKUP("BPS",subQ,MATCH(E$5,SUBQH,0),0),"") | F8: =IFERROR(VLOOKUP("BPS",subQ,MATCH(F$5,SUBQH,0),0),"") | G8: =IFERROR(VLOOKUP("BPS",subQ,MATCH(G$5,SUBQH,0),0),"")
C9: 지배주주순이익(억원) | D9: =IFERROR(VLOOKUP("지배주주순이익",subQ,MATCH(D$5,SUBQH,0),0),"") | E9: =IFERROR(VLOOKUP("지배주주순이익",subQ,MATCH(E$5,SUBQH,0),0),"") | F9: =IFERROR(VLOOKUP("지배주주순이익",subQ,MATCH(F$5,SUBQH,0),0),"") | G9: =IFERROR(VLOOKUP("지배주주순이익",subQ,MATCH(G$5,SUBQH,0),0),"")
C10: 영업이익(억원) | D10: =IFERROR(VLOOKUP("영업이익",subQ,MATCH(D$5,SUBQH,0),0),"") | E10: =IFERROR(VLOOKUP("영업이익",subQ,MATCH(E$5,SUBQH,0),0),"") | F10: =IFERROR(VLOOKUP("영업이익",subQ,MATCH(F$5,SUBQH,0),0),"") | G10: =IFERROR(VLOOKUP("영업이익",subQ,MATCH(G$5,SUBQH,0),0),"")
C11: ROE(EPS/기초BPS) | E11: =IFERROR(E7/D8,"") | F11: =IFERROR(F7/E8,"") | G11: =IFERROR(G7/F8,"")
B13: PER
C14: 12M fwd EPS | D14: =IFERROR(E7*변수!D51+F7*(1-변수!D51),"")
C15: 적정가치 @PER_lo | D15: =변수!D48 | E15: =IFERROR(ROUND($D$14*D15,-2),"") | F15: =IFERROR(E15/$C$1-1,"") | G15: 배 · 원 · 종가 대비
C16: 적정가치 @PER_mid | D16: =변수!D49 | E16: =IFERROR(ROUND($D$14*D16,-2),"") | F16: =IFERROR(E16/$C$1-1,"") | G16: 배 · 원 · 종가 대비
C17: 적정가치 @PER_hi | D17: =변수!D50 | E17: =IFERROR(ROUND($D$14*D17,-2),"") | F17: =IFERROR(E17/$C$1-1,"") | G17: 배 · 원 · 종가 대비
C18: 현재 PER(종가/12M fwd EPS) | D18: =IFERROR($C$1/$D$14,"")
B20: PBR
C21: 최근 BPS(마지막 실적 분기) | D21: =IFERROR(VLOOKUP("BPS",subQ,MATCH("2Q26",SUBQH,0),0),"")
C22: ROE fwd(12M fwd EPS / BPS) | D22: =IFERROR($D$14/$D$21,"")
C23: COE | D23: =변수!D47
C24: 적정 PBR = ROE/COE | D24: =IFERROR(D22/D23,"")
C25: 적정가치(PBR) = BPS × 적정PBR | D25: =IFERROR(ROUND(D21*D24,-2),"") | E25: =IFERROR(D25/$C$1-1,"")
C26: 현재 PBR(종가/BPS) | D26: =IFERROR($C$1/D21,"")
B28: 모델 json valuation(참고)
C29: eps_fwd12m | D29: 2372.7
C30: bps_latest | D30: 13032.2
C31: per_now | D31: 8.12
C32: pbr_now | D32: 1.48
C33: roe_fwd | D33: 0.1821
C34: fair_pbr | D34: 2.02
C35: fair_value_pbr | D35: 26300
C36: ev_ebitda
C37: note | D37: 모델 산출값 — 목표주가·추천 아님

Sheet 외화
C1: 이름: 외화QH — 환율 QoQ · 외화 순노출 × Δ기말환율 | E1: 4Q21 | F1: 1Q22 | G1: 2Q22 | H1: 3Q22 | I1: 4Q22 | J1: 1Q23 | K1: 2Q23 | L1: 3Q23 | M1: 4Q23 | N1: 1Q24 | O1: 2Q24 | P1: 3Q24 | Q1: 4Q24 | R1: 1Q25 | S1: 2Q25 | T1: 3Q25 | U1: 4Q25 | V1: 1Q26 | W1: 2Q26 | X1: 3Q26 | Y1: 4Q26 | Z1: 1Q27 | AA1: 2Q27 | AB1: 3Q27 | AC1: 4Q27 | AD1: 1Q28 | AE1: 2Q28 | AF1: 3Q28 | AG1: 4Q28
E3: 1 | F3: 2 | G3: 3 | H3: 4 | I3: 5 | J3: 6 | K3: 7 | L3: 8 | M3: 9 | N3: 10 | O3: 11 | P3: 12 | Q3: 13 | R3: 14 | S3: 15 | T3: 16 | U3: 17 | V3: 18 | W3: 19 | X3: 20 | Y3: 21 | Z3: 22 | AA3: 23 | AB3: 24 | AC3: 25 | AD3: 26 | AE3: 27 | AF3: 28 | AG3: 29
E4: 2021.12 | F4: 2022.03 | G4: 2022.06 | H4: 2022.09 | I4: 2022.12 | J4: 2023.03 | K4: 2023.06 | L4: 2023.09 | M4: 2023.12 | N4: 2024.03 | O4: 2024.06 | P4: 2024.09 | Q4: 2024.12 | R4: 2025.03 | S4: 2025.06 | T4: 2025.09 | U4: 2025.12 | V4: 2026.03 | W4: 2026.06 | X4: 2026.09 | Y4: 2026.12 | Z4: 2027.03 | AA4: 2027.06 | AB4: 2027.09 | AC4: 2027.12 | AD4: 2028.03 | AE4: 2028.06 | AF4: 2028.09 | AG4: 2028.12
D5: 원/달러(평균) | E5: =IFERROR(VLOOKUP($D5,환율,MATCH(E$1,변수H,0),0),"") | F5: =IFERROR(VLOOKUP($D5,환율,MATCH(F$1,변수H,0),0),"") | G5: =IFERROR(VLOOKUP($D5,환율,MATCH(G$1,변수H,0),0),"") | H5: =IFERROR(VLOOKUP($D5,환율,MATCH(H$1,변수H,0),0),"") | I5: =IFERROR(VLOOKUP($D5,환율,MATCH(I$1,변수H,0),0),"") | J5: =IFERROR(VLOOKUP($D5,환율,MATCH(J$1,변수H,0),0),"") | K5: =IFERROR(VLOOKUP($D5,환율,MATCH(K$1,변수H,0),0),"") | L5: =IFERROR(VLOOKUP($D5,환율,MATCH(L$1,변수H,0),0),"") | ... AG5: =IFERROR(VLOOKUP($D5,환율,MATCH(AG$1,변수H,0),0),"")
A6: 원/달러(평균) QoQ | F6: =IFERROR(F5/E5-1,"") | G6: =IFERROR(G5/F5-1,"") | H6: =IFERROR(H5/G5-1,"") | I6: =IFERROR(I5/H5-1,"") | J6: =IFERROR(J5/I5-1,"") | K6: =IFERROR(K5/J5-1,"") | L6: =IFERROR(L5/K5-1,"") | M6: =IFERROR(M5/L5-1,"") | ... AG6: =IFERROR(AG5/AF5-1,"")
D7: 원/달러(기말) | E7: =IFERROR(VLOOKUP($D7,환율,MATCH(E$1,변수H,0),0),"") | F7: =IFERROR(VLOOKUP($D7,환율,MATCH(F$1,변수H,0),0),"") | G7: =IFERROR(VLOOKUP($D7,환율,MATCH(G$1,변수H,0),0),"") | H7: =IFERROR(VLOOKUP($D7,환율,MATCH(H$1,변수H,0),0),"") | I7: =IFERROR(VLOOKUP($D7,환율,MATCH(I$1,변수H,0),0),"") | J7: =IFERROR(VLOOKUP($D7,환율,MATCH(J$1,변수H,0),0),"") | K7: =IFERROR(VLOOKUP($D7,환율,MATCH(K$1,변수H,0),0),"") | L7: =IFERROR(VLOOKUP($D7,환율,MATCH(L$1,변수H,0),0),"") | ... AG7: =IFERROR(VLOOKUP($D7,환율,MATCH(AG$1,변수H,0),0),"")
A8: 원/달러(기말) QoQ | F8: =IFERROR(F7/E7-1,"") | G8: =IFERROR(G7/F7-1,"") | H8: =IFERROR(H7/G7-1,"") | I8: =IFERROR(I7/H7-1,"") | J8: =IFERROR(J7/I7-1,"") | K8: =IFERROR(K7/J7-1,"") | L8: =IFERROR(L7/K7-1,"") | M8: =IFERROR(M7/L7-1,"") | ... AG8: =IFERROR(AG7/AF7-1,"")
D9: W/Euro(평균) | E9: =IFERROR(VLOOKUP($D9,환율,MATCH(E$1,변수H,0),0),"") | F9: =IFERROR(VLOOKUP($D9,환율,MATCH(F$1,변수H,0),0),"") | G9: =IFERROR(VLOOKUP($D9,환율,MATCH(G$1,변수H,0),0),"") | H9: =IFERROR(VLOOKUP($D9,환율,MATCH(H$1,변수H,0),0),"") | I9: =IFERROR(VLOOKUP($D9,환율,MATCH(I$1,변수H,0),0),"") | J9: =IFERROR(VLOOKUP($D9,환율,MATCH(J$1,변수H,0),0),"") | K9: =IFERROR(VLOOKUP($D9,환율,MATCH(K$1,변수H,0),0),"") | L9: =IFERROR(VLOOKUP($D9,환율,MATCH(L$1,변수H,0),0),"") | ... AG9: =IFERROR(VLOOKUP($D9,환율,MATCH(AG$1,변수H,0),0),"")
A10: W/Euro(평균) QoQ | F10: =IFERROR(F9/E9-1,"") | G10: =IFERROR(G9/F9-1,"") | H10: =IFERROR(H9/G9-1,"") | I10: =IFERROR(I9/H9-1,"") | J10: =IFERROR(J9/I9-1,"") | K10: =IFERROR(K9/J9-1,"") | L10: =IFERROR(L9/K9-1,"") | M10: =IFERROR(M9/L9-1,"") | ... AG10: =IFERROR(AG9/AF9-1,"")
D11: W/Euro(기말) | E11: =IFERROR(VLOOKUP($D11,환율,MATCH(E$1,변수H,0),0),"") | F11: =IFERROR(VLOOKUP($D11,환율,MATCH(F$1,변수H,0),0),"") | G11: =IFERROR(VLOOKUP($D11,환율,MATCH(G$1,변수H,0),0),"") | H11: =IFERROR(VLOOKUP($D11,환율,MATCH(H$1,변수H,0),0),"") | I11: =IFERROR(VLOOKUP($D11,환율,MATCH(I$1,변수H,0),0),"") | J11: =IFERROR(VLOOKUP($D11,환율,MATCH(J$1,변수H,0),0),"") | K11: =IFERROR(VLOOKUP($D11,환율,MATCH(K$1,변수H,0),0),"") | L11: =IFERROR(VLOOKUP($D11,환율,MATCH(L$1,변수H,0),0),"") | ... AG11: =IFERROR(VLOOKUP($D11,환율,MATCH(AG$1,변수H,0),0),"")
A12: W/Euro(기말) QoQ | F12: =IFERROR(F11/E11-1,"") | G12: =IFERROR(G11/F11-1,"") | H12: =IFERROR(H11/G11-1,"") | I12: =IFERROR(I11/H11-1,"") | J12: =IFERROR(J11/I11-1,"") | K12: =IFERROR(K11/J11-1,"") | L12: =IFERROR(L11/K11-1,"") | M12: =IFERROR(M11/L11-1,"") | ... AG12: =IFERROR(AG11/AF11-1,"")
D13: 원/100Y(기말) | E13: =IFERROR(VLOOKUP($D13,환율,MATCH(E$1,변수H,0),0),"") | F13: =IFERROR(VLOOKUP($D13,환율,MATCH(F$1,변수H,0),0),"") | G13: =IFERROR(VLOOKUP($D13,환율,MATCH(G$1,변수H,0),0),"") | H13: =IFERROR(VLOOKUP($D13,환율,MATCH(H$1,변수H,0),0),"") | I13: =IFERROR(VLOOKUP($D13,환율,MATCH(I$1,변수H,0),0),"") | J13: =IFERROR(VLOOKUP($D13,환율,MATCH(J$1,변수H,0),0),"") | K13: =IFERROR(VLOOKUP($D13,환율,MATCH(K$1,변수H,0),0),"") | L13: =IFERROR(VLOOKUP($D13,환율,MATCH(L$1,변수H,0),0),"") | ... AG13: =IFERROR(VLOOKUP($D13,환율,MATCH(AG$1,변수H,0),0),"")
A14: 원/100Y(기말) QoQ | F14: =IFERROR(F13/E13-1,"") | G14: =IFERROR(G13/F13-1,"") | H14: =IFERROR(H13/G13-1,"") | I14: =IFERROR(I13/H13-1,"") | J14: =IFERROR(J13/I13-1,"") | K14: =IFERROR(K13/J13-1,"") | L14: =IFERROR(L13/K13-1,"") | M14: =IFERROR(M13/L13-1,"") | ... AG14: =IFERROR(AG13/AF13-1,"")
A16: 외화순노출 | C16: 외화 순노출(백만$) | D16: =변수!D58 | E16: 외화 순노출 × Δ기말환율 (외화 시트 방식)
A17: 환관련손익추정 | C17: 환관련손익 추정(억원) = 순노출 × Δ원/달러(기말) / 100 | F17: =IFERROR($D$16*(F7-E7)/100,"") | G17: =IFERROR($D$16*(G7-F7)/100,"") | H17: =IFERROR($D$16*(H7-G7)/100,"") | I17: =IFERROR($D$16*(I7-H7)/100,"") | J17: =IFERROR($D$16*(J7-I7)/100,"") | K17: =IFERROR($D$16*(K7-J7)/100,"") | L17: =IFERROR($D$16*(L7-K7)/100,"") | M17: =IFERROR($D$16*(M7-L7)/100,"") | ... AG17: =IFERROR($D$16*(AG7-AF7)/100,"")
A18: fx_pnl.by_q | C18: 모델 fx_pnl.by_q(억원, 참고)
C19: 외화 순노출 미공시(face) → 0 + 표기
