Workbook
Name 변수H: 변수!$C$1:$AO$1
Name 환율: 변수!$C$6:$AO$13
Name BS연결H: BS연결!$C$1:$AO$1
Name BS연결: BS연결!$C$5:$AO$103
Name BS별도H: BS별도!$C$1:$AO$1
Name BS별도: BS별도!$C$5:$AO$82
Name SUBQH: subQ!$A$1:$AO$1
Name subQ: subQ!$A$5:$AO$43

Sheet README
A1: 태광(023160) 실적 모델 — ARGUS 한국조선
A2: 기준 분기 2026Q2 · 마지막 실적 2026Q2 · 생성 2026-10-11
A3: 모든 수치는 모델 산출값(DART 공개 재무제표 + 우리 추정)이다 — 목표주가·투자 추천 아님. 참고용 · 투자조언 아님.
A5: 시트
A6: 변수 가정 시계열. 환율 8행(ECB via frankfurter — L2 fx.json; 추정 분기 = 노란 가정), 추정 드라이버(노란 셀 = 모델값에서 역산한 가정, 바꾸면 재계산; 연녹 셀 = 3절 스칼라 참조 수식), 3절 스칼라 가정(세율·판관비율·지배주주비중·이자율·종가·PER 밴드·COE·외화 순노출·헤지비율)
A7: BS연결/BS별도 FnGuide 계정명 × 기간 값 덤프(백만원). 행1 분기라벨, 행4 YYYY.MM / YYYY.12A. 이름정의 BS연결H·BS연결(계정명 C열부터)
A8: subQ 분기 서브모델(억원 = 백만원/100). 확정 행: =IFERROR(VLOOKUP($D행,BS연결,MATCH(E$1,BS연결H,0),0)/100,"") 추정 행: 변수 시트 가정 셀 참조 수식. 외환손익·파생상품손익은 BS 계정 합·차, 기타금융손익은 잔차, OPM·EPS·BPS·PER·PBR 은 파생 수식, 조정EPS 는 EPS 참조(일회성 의심 분기만 산식 셀)
A9: SLS 선표(조선사만, sls json 있을 때): 요약 행(sls 저장값) + 계약별 스케줄(백만$) × (헤지비율 × 헤지환율 + (1−헤지비율) × 건조시점 환율[변수 원/달러(평균)]) → 원화 수식 블록 → 합계 행이 subQ 매출조선에 연결
A10: 시나리오 신규수주 보수/기준/낙관(forecast_panel 패널, 모델에 scenarios 가 있을 때만): 매출액·영업이익 = subQ 기준값 ± (시나리오 신규 − base 신규) × OPM. base 만 subQ 행에 포함, 나머지는 합산 안 함
A11: 분기/연간예상 subQ 를 이름(A열 key)으로 VLOOKUP 한 보고서 표(억원)
A12: TP PER 밴드 × 12M fwd EPS, PBR = ROE/COE × BPS — 모델 산출값 구간, 목표주가·추천 아님
A13: 외화 환율 QoQ, 외화 순노출 × Δ기말환율 → 환관련손익 추정
... A35: 백테스트: {"freeze": "2025Q2", "horizon": 4, "revenue_wape_pct": 26.1, "op_wape_pct": 27.8, "n": 4, "note": "단일 회사 4분기 — 통계 아님", "driver_at_freeze": "trend_seasonal", "selection_oos_at_freeze": null, "frozen_inputs": "fin(연결/별도)·고객 조선사 모델·지주 자회사 모델은 2025Q2 까지의 분기만; 선표는 체결일 ≤ 2025Q2 말일 계약(원장 최신 금액·코호트 등급, 환산 없음); 잔고는 yards_cache 2025Q2; 시세·환율 forward·prices·forecast_panel 신규수주 미사용. 고객 가중치(suppliers.json 언급 비중)와 합병 체인링크는 현재 지식; 고객 연동 채택은 동결 모델 안에서도 자기 la−4분기 OOS 규칙(selection_oos_at_freeze)", "detail": [{"q": "2025Q3", "rev_pred": 569.88, "rev_act": 814.15, "op_pred": 76.42, "op_act": 115.69}, {"q": "2025Q4", "rev_pred": 610.49, "rev_act": 806.0, "op_pred": 81.87, "op_act": 121.05}, {"q": "2026Q1", "rev_pred": 578.02, "rev_act": 822.75, "op_pred": 77.51, "op_act": 93.5}, {"q": "2026Q2", "rev_pred": 667.36, "rev_act": 837.46, "op_pred": 89.49, "op_act": 72.12}]}

Sheet 변수
C1: 이름: 변수H | E1: 4Q21 | F1: 2021 | G1: 1Q22 | H1: 2Q22 | I1: 3Q22 | J1: 4Q22 | K1: 2022 | L1: 1Q23 | M1: 2Q23 | N1: 3Q23 | O1: 4Q23 | P1: 2023 | Q1: 1Q24 | R1: 2Q24 | S1: 3Q24 | T1: 4Q24 | U1: 2024 | V1: 1Q25 | W1: 2Q25 | X1: 3Q25 | Y1: 4Q25 | Z1: 2025 | AA1: 1Q26 | AB1: 2Q26 | AC1: 3Q26 | AD1: 4Q26 | AE1: 2026 | AF1: 1Q27 | AG1: 2Q27 | AH1: 3Q27 | AI1: 4Q27 | AJ1: 2027 | AK1: 1Q28 | AL1: 2Q28 | AM1: 3Q28 | AN1: 4Q28 | AO1: 2028
A2: 가정 시계열 — 노란 셀은 추정 가정(모델값에서 역산), 연녹 셀은 3절 스칼라 참조 수식. 바꾸면 subQ·분기·연간예상·TP·시나리오가 재계산됩니다.
E3: 1 | F3: 2 | G3: 3 | H3: 4 | I3: 5 | J3: 6 | K3: 7 | L3: 8 | M3: 9 | N3: 10 | O3: 11 | P3: 12 | Q3: 13 | R3: 14 | S3: 15 | T3: 16 | U3: 17 | V3: 18 | W3: 19 | X3: 20 | Y3: 21 | Z3: 22 | AA3: 23 | AB3: 24 | AC3: 25 | AD3: 26 | AE3: 27 | AF3: 28 | AG3: 29 | AH3: 30 | AI3: 31 | AJ3: 32 | AK3: 33 | AL3: 34 | AM3: 35 | AN3: 36 | AO3: 37
E4: 2021.12 | F4: 2021.12A | G4: 2022.03 | H4: 2022.06 | I4: 2022.09 | J4: 2022.12 | K4: 2022.12A | L4: 2023.03 | M4: 2023.06 | N4: 2023.09 | O4: 2023.12 | P4: 2023.12A | Q4: 2024.03 | R4: 2024.06 | S4: 2024.09 | T4: 2024.12 | U4: 2024.12A | V4: 2025.03 | W4: 2025.06 | X4: 2025.09 | Y4: 2025.12 | Z4: 2025.12A | AA4: 2026.03 | AB4: 2026.06 | AC4: 2026.09 | AD4: 2026.12 | AE4: 2026.12A | AF4: 2027.03 | AG4: 2027.06 | AH4: 2027.09 | AI4: 2027.12 | AJ4: 2027.12A | AK4: 2028.03 | AL4: 2028.06 | AM4: 2028.09 | AN4: 2028.12 | AO4: 2028.12A
B5: 1. FX | C5: 이름: 환율
A6: USDKRW_avg | C6: 원/달러(평균) | E6: 1183.5 | F6: 1145.51 | G6: 1205.78 | H6: 1262.09 | I6: 1341.93 | J6: 1360.12 | K6: 1292.98 | L6: 1276.95 | M6: 1315.69 | N6: 1313.62 | O6: 1322.01 | P6: 1306.85 | Q6: 1330.14 | R6: 1371.28 | S6: 1356.22 | T6: 1396.3 | U6: 1363.53 | V6: 1452.28 | W6: 1398.52 | X6: 1386.95 | Y6: 1449.19 | Z6: 1421.52 | AA6: 1466.12 | AB6: 1501.75 | AC6: 1418.75 | AD6: 1345.14 | AE6: 1457.21 | AF6: 1341.49 | AG6: 1341.49 | AH6: 1341.49 | AI6: 1341.49 | AK6: 1341.49 | AL6: 1341.49 | AM6: 1341.49 | AN6: 1341.49
A7: USDKRW_end | C7: 원/달러(기말) | E7: 1188.75 | F7: 1188.75 | G7: 1213.74 | H7: 1301.24 | I7: 1436.9 | J7: 1260.16 | K7: 1260.16 | L7: 1305.99 | M7: 1321.44 | N7: 1345.35 | O7: 1297.43 | P7: 1297.43 | Q7: 1349.25 | R7: 1377.73 | S7: 1312.17 | T7: 1474.78 | U7: 1474.78 | V7: 1474.54 | W7: 1355.13 | X7: 1403.67 | Y7: 1444.2 | Z7: 1444.2 | AA7: 1524.8 | AB7: 1550.89 | AC7: 1355.4 | AD7: 1341.49 | AE7: 1341.49 | AF7: 1341.49 | AG7: 1341.49 | AH7: 1341.49 | AI7: 1341.49 | AK7: 1341.49 | AL7: 1341.49 | AM7: 1341.49 | AN7: 1341.49
A8: JPY100KRW_avg | C8: 원/100Y(평균) | E8: 1041.02 | F8: 1042.74 | G8: 1036.79 | H8: 972.23 | I8: 970.61 | J8: 961.03 | K8: 985.1 | L8: 964.89 | M8: 957.36 | N8: 909 | O8: 893.22 | P8: 931.11 | Q8: 896.29 | R8: 880.14 | S8: 909.35 | T8: 917.25 | U8: 900.92 | V8: 952.59 | W8: 967.92 | X8: 940.32 | Y8: 940.77 | Z8: 950.17 | AA8: 934.39 | AB8: 942.16 | AC8: 890.41 | AD8: 850.79 | AE8: 919.21 | AF8: 847.7 | AG8: 847.7 | AH8: 847.7 | AI8: 847.7 | AK8: 847.7 | AL8: 847.7 | AM8: 847.7 | AN8: 847.7
A9: JPY100KRW_end | C9: 원/100Y(기말) | E9: 1032.62 | F9: 1032.62 | G9: 996.83 | H9: 954.9 | I9: 993.29 | J9: 955.54 | K9: 955.54 | L9: 980.62 | M9: 913.67 | N9: 901.47 | O9: 917.04 | P9: 917.04 | Q9: 892.42 | R9: 857.76 | S9: 919.21 | T9: 939.65 | U9: 939.65 | V9: 986.84 | W9: 938.85 | X9: 948.49 | Y9: 921.81 | Z9: 921.81 | AA9: 955.99 | AB9: 954.75 | AC9: 863.31 | AD9: 847.7 | AE9: 847.7 | AF9: 847.7 | AG9: 847.7 | AH9: 847.7 | AI9: 847.7 | AK9: 847.7 | AL9: 847.7 | AM9: 847.7 | AN9: 847.7
A10: EURKRW_avg | C10: W/Euro(평균) | E10: 1353.32 | F10: 1354.06 | G10: 1352.29 | H10: 1343.31 | I10: 1350.63 | J10: 1386.07 | K10: 1358.07 | L10: 1369.93 | M10: 1432.41 | N10: 1429.41 | O10: 1420.91 | P10: 1412.88 | Q10: 1444.21 | R10: 1476.42 | S10: 1489.3 | T10: 1490.78 | U10: 1475.4 | V10: 1528.33 | W10: 1585.13 | X10: 1620.04 | Y10: 1686.02 | Z10: 1605.45 | AA10: 1715.47 | AB10: 1746.09 | AC10: 1631.97 | AD10: 1509.74 | AE10: 1689.95 | AF10: 1503.27 | AG10: 1503.27 | AH10: 1503.27 | AI10: 1503.27 | AK10: 1503.27 | AL10: 1503.27 | AM10: 1503.27 | AN10: 1503.27
A11: EURKRW_end | C11: W/Euro(기말) | E11: 1346.38 | F11: 1346.38 | G11: 1347.37 | H11: 1351.6 | I11: 1400.62 | J11: 1344.08 | K11: 1344.08 | L11: 1420.26 | M11: 1435.88 | N11: 1425.26 | O11: 1433.66 | P11: 1433.66 | Q11: 1458.68 | R11: 1474.86 | S11: 1469.1 | T11: 1532.14 | U11: 1532.14 | V11: 1594.72 | W11: 1588.22 | X11: 1648.04 | Y11: 1696.94 | Z11: 1696.94 | AA11: 1753.21 | AB11: 1767.09 | AC11: 1539.06 | AD11: 1503.27 | AE11: 1503.27 | AF11: 1503.27 | AG11: 1503.27 | AH11: 1503.27 | AI11: 1503.27 | AK11: 1503.27 | AL11: 1503.27 | AM11: 1503.27 | AN11: 1503.27
A12: CNYKRW_avg | C12: 원/중국원(평균) | E12: 185.14 | F12: 177.65 | G12: 189.93 | H12: 190.76 | I12: 195.79 | J12: 191.09 | K12: 191.93 | L12: 186.59 | M12: 187.45 | N12: 181.28 | O12: 182.86 | P12: 184.52 | Q12: 185.04 | R12: 189.35 | S12: 189.24 | T12: 194.24 | U12: 189.49 | V12: 199.63 | W12: 193.41 | X12: 193.79 | Y12: 204.38 | Z12: 197.8 | AA12: 211.75 | AB12: 220.8 | AC12: 210.43 | AD12: 200.69 | AE12: 213.75 | AF12: 200.46 | AG12: 200.46 | AH12: 200.46 | AI12: 200.46 | AK12: 200.46 | AL12: 200.46 | AM12: 200.46 | AN12: 200.46
A13: CNYKRW_end | C13: 원/중국원(기말) | E13: 187.13 | F13: 187.13 | G13: 191.38 | H13: 194.13 | I13: 201.92 | J13: 182.67 | K13: 182.67 | L13: 189.97 | M13: 181.8 | N13: 184.26 | O13: 182.61 | P13: 182.61 | Q13: 186.66 | R13: 189.7 | S13: 187.12 | T13: 202.04 | U13: 202.04 | V13: 203.3 | W13: 189.14 | X13: 197.16 | Y13: 206.28 | Z13: 206.28 | AA13: 220.97 | AB13: 228.56 | AC13: 202.16 | AD13: 200.46 | AE13: 200.46 | AF13: 200.46 | AG13: 200.46 | AH13: 200.46 | AI13: 200.46 | AK13: 200.46 | AL13: 200.46 | AM13: 200.46 | AN13: 200.46
B14: 1b. 종가
A15: price_close_end | C15: 종가(기말) | E15: 10850 | G15: 10450 | H15: 13700 | I15: 16400 | J15: 16100 | L15: 16920 | M15: 18430 | N15: 17990 | O15: 14730 | Q15: 12280 | R15: 12980 | S15: 13660 | T15: 17660 | V15: 20650 | W15: 21100 | X15: 25800 | Y15: 21700 | AA15: 35000 | AB15: 24650 | AC15: 28150 | AD15: 26200
A16: price_high | C16: 종가(최고) | E16: 13000 | G16: 12000 | H16: 14200 | I16: 20200 | J16: 19200 | L16: 17950 | M16: 19920 | N16: 22650 | O16: 18100 | Q16: 14750 | R16: 16050 | S16: 17920 | T16: 18650 | V16: 27000 | W16: 23700 | X16: 32300 | Y16: 30200 | AA16: 38650 | AB16: 51300 | AC16: 29650 | AD16: 29250
A17: price_low | C17: 종가(최저) | E17: 9960 | G17: 9330 | H17: 9810 | I17: 11350 | J17: 14250 | L17: 14500 | M17: 15870 | N17: 17580 | O17: 13810 | Q17: 11440 | R17: 11130 | S17: 12270 | T17: 11880 | V17: 17100 | W17: 17700 | X17: 18660 | Y17: 21500 | AA17: 20750 | AB17: 22900 | AC17: 19420 | AD17: 26100
A18: price_avg | C18: 종가(평균) | E18: 10849.2 | G18: 10539.5 | H18: 11707.9 | I18: 15465.9 | J18: 16645.2 | L18: 15899.7 | M18: 17783.6 | N18: 19757.7 | O18: 15427.2 | Q18: 12963.8 | R18: 12421.7 | S18: 14479.7 | T18: 14842 | V18: 21949.8 | W18: 20637 | X18: 23374 | Y18: 24900 | AA18: 28277.1 | AB18: 36761.5 | AC18: 24219.4 | AD18: 27320
B20: 2. 추정 드라이버 | C20: 실적 열 = subQ 실현값(수식), 추정 열 = 가정(노란 = 모델값 역산, 연녹 = 3절 스칼라 참조)
A21: drv:매출액 | B21: yoy | C21: 매출액 YoY | J21: =IFERROR(subQ!J5/subQ!E5-1,"") | L21: =IFERROR(subQ!L5/subQ!G5-1,"") | M21: =IFERROR(subQ!M5/subQ!H5-1,"") | N21: =IFERROR(subQ!N5/subQ!I5-1,"") | O21: =IFERROR(subQ!O5/subQ!J5-1,"") | Q21: =IFERROR(subQ!Q5/subQ!L5-1,"") | R21: =IFERROR(subQ!R5/subQ!M5-1,"") | S21: =IFERROR(subQ!S5/subQ!N5-1,"") | T21: =IFERROR(subQ!T5/subQ!O5-1,"") | V21: =IFERROR(subQ!V5/subQ!Q5-1,"") | W21: =IFERROR(subQ!W5/subQ!R5-1,"") | X21: =IFERROR(subQ!X5/subQ!S5-1,"") | Y21: =IFERROR(subQ!Y5/subQ!T5-1,"") | AA21: =IFERROR(subQ!AA5/subQ!V5-1,"") | AB21: =IFERROR(subQ!AB5/subQ!W5-1,"") | AC21: 0.24797059 | AD21: 0.24796402 | AF21: 0.24796916 | AG21: 0.24797049 | AH21: 0.12398134 | AI21: 0.12398346 | AK21: 0.12398103 | AL21: 0.12397619 | AM21: 0.061987198 | AN21: 0.061995277
A22: drv:판관비 | B22: ratio | C22: 판관비율(/매출) | E22: =IFERROR(subQ!E8/subQ!E5,"") | F22: =IFERROR(subQ!F8/subQ!F5,"") | G22: =IFERROR(subQ!G8/subQ!G5,"") | H22: =IFERROR(subQ!H8/subQ!H5,"") | I22: =IFERROR(subQ!I8/subQ!I5,"") | J22: =IFERROR(subQ!J8/subQ!J5,"") | K22: =IFERROR(subQ!K8/subQ!K5,"") | L22: =IFERROR(subQ!L8/subQ!L5,"") | ... AB22: =IFERROR(subQ!AB8/subQ!AB5,"") | AC22: =$D$51 | AD22: =$D$51 | AE22: =IFERROR(subQ!AE8/subQ!AE5,"") | AF22: =$D$51 | AG22: =$D$51 | AH22: =$D$51 | AI22: =$D$51 | AJ22: =IFERROR(subQ!AJ8/subQ!AJ5,"") | AK22: =$D$51 | AL22: =$D$51 | AM22: =$D$51 | AN22: =$D$51 | AO22: =IFERROR(subQ!AO8/subQ!AO5,"")
A23: drv:영업이익 | B23: ratio | C23: 영업이익률(OPM) | E23: =IFERROR(subQ!E9/subQ!E5,"") | F23: =IFERROR(subQ!F9/subQ!F5,"") | G23: =IFERROR(subQ!G9/subQ!G5,"") | H23: =IFERROR(subQ!H9/subQ!H5,"") | I23: =IFERROR(subQ!I9/subQ!I5,"") | J23: =IFERROR(subQ!J9/subQ!J5,"") | K23: =IFERROR(subQ!K9/subQ!K5,"") | L23: =IFERROR(subQ!L9/subQ!L5,"") | ... AB23: =IFERROR(subQ!AB9/subQ!AB5,"") | AC23: 0.12045786 | AD23: 0.12046408 | AE23: =IFERROR(subQ!AE9/subQ!AE5,"") | AF23: 0.12046515 | AG23: 0.12046464 | AH23: 0.12046304 | AI23: 0.12046136 | AJ23: =IFERROR(subQ!AJ9/subQ!AJ5,"") | AK23: 0.12046063 | AL23: 0.12045731 | AM23: 0.12046504 | AN23: 0.12045875 | AO23: =IFERROR(subQ!AO9/subQ!AO5,"")
A24: drv:외환손익 | B24: abs | C24: 외환손익 (가정, 억원) | E24: =subQ!E13 | F24: =subQ!F13 | G24: =subQ!G13 | H24: =subQ!H13 | I24: =subQ!I13 | J24: =subQ!J13 | K24: =subQ!K13 | L24: =subQ!L13 | ... AB24: =subQ!AB13 | AC24: 0 | AD24: 0 | AE24: =subQ!AE13 | AF24: 0 | AG24: 0 | AH24: 0 | AI24: 0 | AJ24: =subQ!AJ13 | AK24: 0 | AL24: 0 | AM24: 0 | AN24: 0 | AO24: =subQ!AO13
A25: drv:파생상품손익 | B25: abs | C25: 파생상품손익 (가정, 억원) | E25: =subQ!E14 | F25: =subQ!F14 | G25: =subQ!G14 | H25: =subQ!H14 | I25: =subQ!I14 | J25: =subQ!J14 | K25: =subQ!K14 | L25: =subQ!L14 | ... AB25: =subQ!AB14 | AC25: 0 | AD25: 0 | AE25: =subQ!AE14 | AF25: 0 | AG25: 0 | AH25: 0 | AI25: 0 | AJ25: =subQ!AJ14 | AK25: 0 | AL25: 0 | AM25: 0 | AN25: 0 | AO25: =subQ!AO14
A26: drv:기타금융손익 | B26: abs | C26: 기타금융손익 (가정, 억원) | E26: =subQ!E15 | F26: =subQ!F15 | G26: =subQ!G15 | H26: =subQ!H15 | I26: =subQ!I15 | J26: =subQ!J15 | K26: =subQ!K15 | L26: =subQ!L15 | ... AB26: =subQ!AB15 | AC26: 0 | AD26: 0 | AE26: =subQ!AE15 | AF26: 0 | AG26: 0 | AH26: 0 | AI26: 0 | AJ26: =subQ!AJ15 | AK26: 0 | AL26: 0 | AM26: 0 | AN26: 0 | AO26: =subQ!AO15
A27: drv:기타영업외손익 | B27: abs | C27: 기타영업외손익 (가정, 억원) | E27: =subQ!E16 | F27: =subQ!F16 | G27: =subQ!G16 | H27: =subQ!H16 | I27: =subQ!I16 | J27: =subQ!J16 | K27: =subQ!K16 | L27: =subQ!L16 | ... AB27: =subQ!AB16 | AC27: 0 | AD27: 0 | AE27: =subQ!AE16 | AF27: 0 | AG27: 0 | AH27: 0 | AI27: 0 | AJ27: =subQ!AJ16 | AK27: 0 | AL27: 0 | AM27: 0 | AN27: 0 | AO27: =subQ!AO16
A28: drv:법인세비용 | B28: tax | C28: 법인세율(/세전) — 법인세 = MAX(세전,0) × 세율 | E28: =IFERROR(subQ!E18/subQ!E17,"") | F28: =IFERROR(subQ!F18/subQ!F17,"") | G28: =IFERROR(subQ!G18/subQ!G17,"") | H28: =IFERROR(subQ!H18/subQ!H17,"") | I28: =IFERROR(subQ!I18/subQ!I17,"") | J28: =IFERROR(subQ!J18/subQ!J17,"") | K28: =IFERROR(subQ!K18/subQ!K17,"") | L28: =IFERROR(subQ!L18/subQ!L17,"") | ... AB28: =IFERROR(subQ!AB18/subQ!AB17,"") | AC28: =$D$50 | AD28: =$D$50 | AE28: =IFERROR(subQ!AE18/subQ!AE17,"") | AF28: =$D$50 | AG28: =$D$50 | AH28: =$D$50 | AI28: =$D$50 | AJ28: =IFERROR(subQ!AJ18/subQ!AJ17,"") | AK28: =$D$50 | AL28: =$D$50 | AM28: =$D$50 | AN28: =$D$50 | AO28: =IFERROR(subQ!AO18/subQ!AO17,"")
A29: drv:지배주주순이익 | B29: ratio | C29: 지배주주 비중(/당기순이익) | E29: =IFERROR(subQ!E20/subQ!E19,"") | F29: =IFERROR(subQ!F20/subQ!F19,"") | G29: =IFERROR(subQ!G20/subQ!G19,"") | H29: =IFERROR(subQ!H20/subQ!H19,"") | I29: =IFERROR(subQ!I20/subQ!I19,"") | J29: =IFERROR(subQ!J20/subQ!J19,"") | K29: =IFERROR(subQ!K20/subQ!K19,"") | L29: =IFERROR(subQ!L20/subQ!L19,"") | ... AB29: =IFERROR(subQ!AB20/subQ!AB19,"") | AC29: =$D$52 | AD29: =$D$52 | AE29: =IFERROR(subQ!AE20/subQ!AE19,"") | AF29: =$D$52 | AG29: =$D$52 | AH29: =$D$52 | AI29: =$D$52 | AJ29: =IFERROR(subQ!AJ20/subQ!AJ19,"") | AK29: =$D$52 | AL29: =$D$52 | AM29: =$D$52 | AN29: =$D$52 | AO29: =IFERROR(subQ!AO20/subQ!AO19,"")
A30: drv:부채총계 | B30: qoq | C30: 부채총계 QoQ | G30: =IFERROR(subQ!G22/subQ!E22-1,"") | H30: =IFERROR(subQ!H22/subQ!G22-1,"") | I30: =IFERROR(subQ!I22/subQ!H22-1,"") | J30: =IFERROR(subQ!J22/subQ!I22-1,"") | L30: =IFERROR(subQ!L22/subQ!J22-1,"") | M30: =IFERROR(subQ!M22/subQ!L22-1,"") | N30: =IFERROR(subQ!N22/subQ!M22-1,"") | O30: =IFERROR(subQ!O22/subQ!N22-1,"") | Q30: =IFERROR(subQ!Q22/subQ!O22-1,"") | R30: =IFERROR(subQ!R22/subQ!Q22-1,"") | S30: =IFERROR(subQ!S22/subQ!R22-1,"") | T30: =IFERROR(subQ!T22/subQ!S22-1,"") | V30: =IFERROR(subQ!V22/subQ!T22-1,"") | W30: =IFERROR(subQ!W22/subQ!V22-1,"") | X30: =IFERROR(subQ!X22/subQ!W22-1,"") | Y30: =IFERROR(subQ!Y22/subQ!X22-1,"") | AA30: =IFERROR(subQ!AA22/subQ!Y22-1,"") | AB30: =IFERROR(subQ!AB22/subQ!AA22-1,"") | AC30: -2.697e-06 | AD30: 0 | AF30: 0 | AG30: 0 | AH30: 0 | AI30: 0 | AK30: 0 | AL30: 0 | AM30: 0 | AN30: 0
A31: drv:자본총계 | B31: roll | C31: 자본총계 기타변동(배당 등, 억원) | G31: =IFERROR(subQ!E23+subQ!G19-subQ!G23,"") | H31: =IFERROR(subQ!G23+subQ!H19-subQ!H23,"") | I31: =IFERROR(subQ!H23+subQ!I19-subQ!I23,"") | J31: =IFERROR(subQ!I23+subQ!J19-subQ!J23,"") | L31: =IFERROR(subQ!J23+subQ!L19-subQ!L23,"") | M31: =IFERROR(subQ!L23+subQ!M19-subQ!M23,"") | N31: =IFERROR(subQ!M23+subQ!N19-subQ!N23,"") | O31: =IFERROR(subQ!N23+subQ!O19-subQ!O23,"") | Q31: =IFERROR(subQ!O23+subQ!Q19-subQ!Q23,"") | R31: =IFERROR(subQ!Q23+subQ!R19-subQ!R23,"") | S31: =IFERROR(subQ!R23+subQ!S19-subQ!S23,"") | T31: =IFERROR(subQ!S23+subQ!T19-subQ!T23,"") | V31: =IFERROR(subQ!T23+subQ!V19-subQ!V23,"") | W31: =IFERROR(subQ!V23+subQ!W19-subQ!W23,"") | X31: =IFERROR(subQ!W23+subQ!X19-subQ!X23,"") | Y31: =IFERROR(subQ!X23+subQ!Y19-subQ!Y23,"") | AA31: =IFERROR(subQ!Y23+subQ!AA19-subQ!AA23,"") | AB31: =IFERROR(subQ!AA23+subQ!AB19-subQ!AB23,"") | AC31: 0.001426637 | AD31: -0.006432463 | AF31: 0.005158254 | AG31: 137.41641 | AH31: 0.001358742 | AI31: -0.002688399 | AK31: -0.003877286 | AL31: 137.41489 | AM31: -0.001249449 | AN31: 0.000347983
A32: drv:지배주주지분 | B32: roll | C32: 지배주주지분 기타변동(배당 등, 억원) | G32: =IFERROR(subQ!E24+subQ!G20-subQ!G24,"") | H32: =IFERROR(subQ!G24+subQ!H20-subQ!H24,"") | I32: =IFERROR(subQ!H24+subQ!I20-subQ!I24,"") | J32: =IFERROR(subQ!I24+subQ!J20-subQ!J24,"") | L32: =IFERROR(subQ!J24+subQ!L20-subQ!L24,"") | M32: =IFERROR(subQ!L24+subQ!M20-subQ!M24,"") | N32: =IFERROR(subQ!M24+subQ!N20-subQ!N24,"") | O32: =IFERROR(subQ!N24+subQ!O20-subQ!O24,"") | Q32: =IFERROR(subQ!O24+subQ!Q20-subQ!Q24,"") | R32: =IFERROR(subQ!Q24+subQ!R20-subQ!R24,"") | S32: =IFERROR(subQ!R24+subQ!S20-subQ!S24,"") | T32: =IFERROR(subQ!S24+subQ!T20-subQ!T24,"") | V32: =IFERROR(subQ!T24+subQ!V20-subQ!V24,"") | W32: =IFERROR(subQ!V24+subQ!W20-subQ!W24,"") | X32: =IFERROR(subQ!W24+subQ!X20-subQ!X24,"") | Y32: =IFERROR(subQ!X24+subQ!Y20-subQ!Y24,"") | AA32: =IFERROR(subQ!Y24+subQ!AA20-subQ!AA24,"") | AB32: =IFERROR(subQ!AA24+subQ!AB20-subQ!AB24,"") | AC32: -0.002710044 | AD32: -0.002047167 | AF32: 0.006312485 | AG32: 137.41185 | AH32: 0.000648768 | AI32: 0.001121743 | AK32: -0.007415714 | AL32: 137.41378 | AM32: -0.001036902 | AN32: -0.003067668
A33: drv:총차입금 | B33: qoq | C33: 총차입금 QoQ | G33: =IFERROR(subQ!G25/subQ!E25-1,"") | H33: =IFERROR(subQ!H25/subQ!G25-1,"") | I33: =IFERROR(subQ!I25/subQ!H25-1,"") | J33: =IFERROR(subQ!J25/subQ!I25-1,"") | L33: =IFERROR(subQ!L25/subQ!J25-1,"") | M33: =IFERROR(subQ!M25/subQ!L25-1,"") | N33: =IFERROR(subQ!N25/subQ!M25-1,"") | O33: =IFERROR(subQ!O25/subQ!N25-1,"") | Q33: =IFERROR(subQ!Q25/subQ!O25-1,"") | R33: =IFERROR(subQ!R25/subQ!Q25-1,"") | S33: =IFERROR(subQ!S25/subQ!R25-1,"") | T33: =IFERROR(subQ!T25/subQ!S25-1,"") | V33: =IFERROR(subQ!V25/subQ!T25-1,"") | W33: =IFERROR(subQ!W25/subQ!V25-1,"") | X33: =IFERROR(subQ!X25/subQ!W25-1,"") | Y33: =IFERROR(subQ!Y25/subQ!X25-1,"") | AA33: =IFERROR(subQ!AA25/subQ!Y25-1,"") | AB33: =IFERROR(subQ!AB25/subQ!AA25-1,"")
A34: drv:순차입금 | B34: qoq | C34: 순차입금 QoQ | G34: =IFERROR(subQ!G26/subQ!E26-1,"") | H34: =IFERROR(subQ!H26/subQ!G26-1,"") | I34: =IFERROR(subQ!I26/subQ!H26-1,"") | J34: =IFERROR(subQ!J26/subQ!I26-1,"") | L34: =IFERROR(subQ!L26/subQ!J26-1,"") | M34: =IFERROR(subQ!M26/subQ!L26-1,"") | N34: =IFERROR(subQ!N26/subQ!M26-1,"") | O34: =IFERROR(subQ!O26/subQ!N26-1,"") | Q34: =IFERROR(subQ!Q26/subQ!O26-1,"") | R34: =IFERROR(subQ!R26/subQ!Q26-1,"") | S34: =IFERROR(subQ!S26/subQ!R26-1,"") | T34: =IFERROR(subQ!T26/subQ!S26-1,"") | V34: =IFERROR(subQ!V26/subQ!T26-1,"") | W34: =IFERROR(subQ!W26/subQ!V26-1,"") | X34: =IFERROR(subQ!X26/subQ!W26-1,"") | Y34: =IFERROR(subQ!Y26/subQ!X26-1,"") | AA34: =IFERROR(subQ!AA26/subQ!Y26-1,"") | AB34: =IFERROR(subQ!AB26/subQ!AA26-1,"")
A35: drv:이자발생자산 | B35: qoq | C35: 이자발생자산 QoQ | G35: =IFERROR(subQ!G27/subQ!E27-1,"") | H35: =IFERROR(subQ!H27/subQ!G27-1,"") | I35: =IFERROR(subQ!I27/subQ!H27-1,"") | J35: =IFERROR(subQ!J27/subQ!I27-1,"") | L35: =IFERROR(subQ!L27/subQ!J27-1,"") | M35: =IFERROR(subQ!M27/subQ!L27-1,"") | N35: =IFERROR(subQ!N27/subQ!M27-1,"") | O35: =IFERROR(subQ!O27/subQ!N27-1,"") | Q35: =IFERROR(subQ!Q27/subQ!O27-1,"") | R35: =IFERROR(subQ!R27/subQ!Q27-1,"") | S35: =IFERROR(subQ!S27/subQ!R27-1,"") | T35: =IFERROR(subQ!T27/subQ!S27-1,"") | V35: =IFERROR(subQ!V27/subQ!T27-1,"") | W35: =IFERROR(subQ!W27/subQ!V27-1,"") | X35: =IFERROR(subQ!X27/subQ!W27-1,"") | Y35: =IFERROR(subQ!Y27/subQ!X27-1,"") | AA35: =IFERROR(subQ!AA27/subQ!Y27-1,"") | AB35: =IFERROR(subQ!AB27/subQ!AA27-1,"") | AC35: 0.088846424 | AD35: 0.081284272 | AF35: 0.077033324 | AG35: -0.020670265 | AH35: 0.080935126 | AI35: 0.074585012 | AK35: 0.071123909 | AL35: -0.009106642 | AM35: 0.07047619 | AN35: 0.065582859
A36: drv:현금및현금성자산 | B36: qoq | C36: 현금및현금성자산 QoQ | G36: =IFERROR(subQ!G28/subQ!E28-1,"") | H36: =IFERROR(subQ!H28/subQ!G28-1,"") | I36: =IFERROR(subQ!I28/subQ!H28-1,"") | J36: =IFERROR(subQ!J28/subQ!I28-1,"") | L36: =IFERROR(subQ!L28/subQ!J28-1,"") | M36: =IFERROR(subQ!M28/subQ!L28-1,"") | N36: =IFERROR(subQ!N28/subQ!M28-1,"") | O36: =IFERROR(subQ!O28/subQ!N28-1,"") | Q36: =IFERROR(subQ!Q28/subQ!O28-1,"") | R36: =IFERROR(subQ!R28/subQ!Q28-1,"") | S36: =IFERROR(subQ!S28/subQ!R28-1,"") | T36: =IFERROR(subQ!T28/subQ!S28-1,"") | V36: =IFERROR(subQ!V28/subQ!T28-1,"") | W36: =IFERROR(subQ!W28/subQ!V28-1,"") | X36: =IFERROR(subQ!X28/subQ!W28-1,"") | Y36: =IFERROR(subQ!Y28/subQ!X28-1,"") | AA36: =IFERROR(subQ!AA28/subQ!Y28-1,"") | AB36: =IFERROR(subQ!AB28/subQ!AA28-1,"")
A37: drv:CAPEX | B37: yoy | C37: CAPEX YoY | J37: =IFERROR(subQ!J29/subQ!E29-1,"") | L37: =IFERROR(subQ!L29/subQ!G29-1,"") | M37: =IFERROR(subQ!M29/subQ!H29-1,"") | N37: =IFERROR(subQ!N29/subQ!I29-1,"") | O37: =IFERROR(subQ!O29/subQ!J29-1,"") | Q37: =IFERROR(subQ!Q29/subQ!L29-1,"") | R37: =IFERROR(subQ!R29/subQ!M29-1,"") | S37: =IFERROR(subQ!S29/subQ!N29-1,"") | T37: =IFERROR(subQ!T29/subQ!O29-1,"") | V37: =IFERROR(subQ!V29/subQ!Q29-1,"") | W37: =IFERROR(subQ!W29/subQ!R29-1,"") | X37: =IFERROR(subQ!X29/subQ!S29-1,"") | Y37: =IFERROR(subQ!Y29/subQ!T29-1,"") | AA37: =IFERROR(subQ!AA29/subQ!V29-1,"") | AB37: =IFERROR(subQ!AB29/subQ!W29-1,"") | AC37: -0.51739673 | AD37: -0.17378461 | AF37: 0.26701409 | AG37: 1.2566078 | AH37: 0 | AI37: 0 | AK37: 0 | AL37: 0 | AM37: 0 | AN37: 0
A38: drv:영업활동현금흐름 | B38: yoy | C38: 영업활동현금흐름 YoY | J38: =IFERROR(subQ!J30/subQ!E30-1,"") | L38: =IFERROR(subQ!L30/subQ!G30-1,"") | M38: =IFERROR(subQ!M30/subQ!H30-1,"") | N38: =IFERROR(subQ!N30/subQ!I30-1,"") | O38: =IFERROR(subQ!O30/subQ!J30-1,"") | Q38: =IFERROR(subQ!Q30/subQ!L30-1,"") | R38: =IFERROR(subQ!R30/subQ!M30-1,"") | S38: =IFERROR(subQ!S30/subQ!N30-1,"") | T38: =IFERROR(subQ!T30/subQ!O30-1,"") | V38: =IFERROR(subQ!V30/subQ!Q30-1,"") | W38: =IFERROR(subQ!W30/subQ!R30-1,"") | X38: =IFERROR(subQ!X30/subQ!S30-1,"") | Y38: =IFERROR(subQ!Y30/subQ!T30-1,"") | AA38: =IFERROR(subQ!AA30/subQ!V30-1,"") | AB38: =IFERROR(subQ!AB30/subQ!W30-1,"")
A39: drv:주식수 | B39: qoq | C39: 주식수 QoQ | G39: =IFERROR(subQ!G31/subQ!E31-1,"") | H39: =IFERROR(subQ!H31/subQ!G31-1,"") | I39: =IFERROR(subQ!I31/subQ!H31-1,"") | J39: =IFERROR(subQ!J31/subQ!I31-1,"") | L39: =IFERROR(subQ!L31/subQ!J31-1,"") | M39: =IFERROR(subQ!M31/subQ!L31-1,"") | N39: =IFERROR(subQ!N31/subQ!M31-1,"") | O39: =IFERROR(subQ!O31/subQ!N31-1,"") | Q39: =IFERROR(subQ!Q31/subQ!O31-1,"") | R39: =IFERROR(subQ!R31/subQ!Q31-1,"") | S39: =IFERROR(subQ!S31/subQ!R31-1,"") | T39: =IFERROR(subQ!T31/subQ!S31-1,"") | V39: =IFERROR(subQ!V31/subQ!T31-1,"") | W39: =IFERROR(subQ!W31/subQ!V31-1,"") | X39: =IFERROR(subQ!X31/subQ!W31-1,"") | Y39: =IFERROR(subQ!Y31/subQ!X31-1,"") | AA39: =IFERROR(subQ!AA31/subQ!Y31-1,"") | AB39: =IFERROR(subQ!AB31/subQ!AA31-1,"") | AC39: 0 | AD39: 0 | AF39: 0 | AG39: 0 | AH39: 0 | AI39: 0 | AK39: 0 | AL39: 0 | AM39: 0 | AN39: 0
A40: drv:DPS | B40: abs | C40: DPS (가정, 원) | E40: =subQ!E35 | F40: =subQ!F35 | G40: =subQ!G35 | H40: =subQ!H35 | I40: =subQ!I35 | J40: =subQ!J35 | K40: =subQ!K35 | L40: =subQ!L35 | ... AB40: =subQ!AB35 | AD40: 535 | AE40: =subQ!AE35 | AI40: 535 | AJ40: =subQ!AJ35 | AN40: 535 | AO40: =subQ!AO35
B42: 3. 밸류에이션·스칼라 | C42: 노란 셀 = 가정. '연결' 표시는 추정 전 분기 수식이 이 셀을 참조한다는 뜻
A43: sc:종가 | C43: 종가 | D43: 26200 | E43: 원 — 네이버 정규장 종가(aik 확정종가 대조 · aik 26,700원)
A44: sc:기준일 | C44: 기준일 | D44: 20261008 | E44: 종가 기준일
A45: sc:COE | C45: COE | D45: 0.09 | E45: 자기자본비용(가정) — TP 적정 PBR = ROE/COE
A46: sc:PER_lo | C46: PER_lo | D46: 8.5 | E46: PER 밴드 하단(배) — hist_quarterly(분기 평균가 ÷ TTM EPS, 16분기, 25/50/75 백분위)
A47: sc:PER_mid | C47: PER_mid | D47: 9.1 | E47: PER 밴드 중단(배)
A48: sc:PER_hi | C48: PER_hi | D48: 12 | E48: PER 밴드 상단(배)
A49: sc:EPS_Y1가중 | C49: EPS_Y1가중 | D49: 0.5 | E49: 12M fwd EPS = FY(last_actual연도)E × w + FY+1E × (1−w) — 기준 분기 2Q 이면 0.5(가정)
A50: sc:세율 | C50: 세율 | D50: 0.21251567 | E50: 연결 — 법인세 = MAX(세전,0) × 세율(역산, 재현 오차 ≤ 0.05억 · 모델 assumptions 0.2125) · 최근 12분기 유효세율 21.3%(5~27% 안 — 그대로)
A51: sc:판관비율 | C51: 판관비율 | D51: 0.18433573 | E51: 연결 — 판관비 = 매출액 × 판관비율(역산, 재현 오차 ≤ 0.05억 · 모델 assumptions 0.1843)
A52: sc:지배주주비중 | C52: 지배주주비중 | D52: 0.92397239 | E52: 연결 — 지배주주순이익 = 당기순이익 × 비중(역산, 재현 오차 ≤ 0.05억)
A53: sc:이자율_자산 | C53: 이자율_자산 | D53: 0.027668381 | E53: 연결 — 이자손익 = (전분기 이자발생자산 × 자산이자율 − 전분기 총차입금 × 부채이자율)/4(역산, 재현 오차 ≤ 0.05억 · 모델 assumptions 0.0277)
A54: sc:이자율_부채 | C54: 이자율_부채 | D54: 0 | E54: 연결 — 같은 수식의 부채 쪽(총차입금 행이 없으면 0)(역산, 재현 오차 ≤ 0.05억)
A55: sc:배당성향 | C55: 배당성향 | D55: 0.2151 | E55: 배당성향(참고 — 모델은 직전 DPS 유지·Q2 지급 가정)
A56: sc:외화순노출_백만$ | C56: 외화순노출_백만$ | E56: 외화 순노출 × Δ기말환율 (외화 시트 방식) — 외화 순노출 미공시(face) → 0 + 표기
A57: sc:헤지비율 | C57: 헤지비율 | E57: sls 없음
A58: sc:헤지환율_약정 | C58: 헤지환율_약정 | E58: sls 없음

Sheet BS연결
B1: (백만원) | C1: 이름: BS연결H | E1: 4Q21 | F1: 2021 | G1: 1Q22 | H1: 2Q22 | I1: 3Q22 | J1: 4Q22 | K1: 2022 | L1: 1Q23 | M1: 2Q23 | N1: 3Q23 | O1: 4Q23 | P1: 2023 | Q1: 1Q24 | R1: 2Q24 | S1: 3Q24 | T1: 4Q24 | U1: 2024 | V1: 1Q25 | W1: 2Q25 | X1: 3Q25 | Y1: 4Q25 | Z1: 2025 | AA1: 1Q26 | AB1: 2Q26 | AC1: 3Q26 | AD1: 4Q26 | AE1: 2026 | AF1: 1Q27 | AG1: 2Q27 | AH1: 3Q27 | AI1: 4Q27 | AJ1: 2027 | AK1: 1Q28 | AL1: 2Q28 | AM1: 3Q28 | AN1: 4Q28 | AO1: 2028
B2: 연결 | D2: fin json(kship_fin.py)
B3: 태광(연) | C3: UPDATE: 26-10-11 | E3: 1 | F3: 2 | G3: 3 | H3: 4 | I3: 5 | J3: 6 | K3: 7 | L3: 8 | M3: 9 | N3: 10 | O3: 11 | P3: 12 | Q3: 13 | R3: 14 | S3: 15 | T3: 16 | U3: 17 | V3: 18 | W3: 19 | X3: 20 | Y3: 21 | Z3: 22 | AA3: 23 | AB3: 24 | AC3: 25 | AD3: 26 | AE3: 27 | AF3: 28 | AG3: 29 | AH3: 30 | AI3: 31 | AJ3: 32 | AK3: 33 | AL3: 34 | AM3: 35 | AN3: 36 | AO3: 37
B4: Account Code | C4: AccountNAME | E4: 2021.12 | F4: 2021.12A | G4: 2022.03 | H4: 2022.06 | I4: 2022.09 | J4: 2022.12 | K4: 2022.12A | L4: 2023.03 | M4: 2023.06 | N4: 2023.09 | O4: 2023.12 | P4: 2023.12A | Q4: 2024.03 | R4: 2024.06 | S4: 2024.09 | T4: 2024.12 | U4: 2024.12A | V4: 2025.03 | W4: 2025.06 | X4: 2025.09 | Y4: 2025.12 | Z4: 2025.12A | AA4: 2026.03 | AB4: 2026.06 | AC4: 2026.09 | AD4: 2026.12 | AE4: 2026.12A | AF4: 2027.03 | AG4: 2027.06 | AH4: 2027.09 | AI4: 2027.12 | AJ4: 2027.12A | AK4: 2028.03 | AL4: 2028.06 | AM4: 2028.09 | AN4: 2028.12 | AO4: 2028.12A
A5: 1 | C5: 유동자산 | E5: 234559.23 | F5: 234559.23 | G5: 234461.35 | H5: 248409.7 | I5: 296899.58 | J5: 312707.86 | K5: 312707.86 | L5: 317108.74 | M5: 305897.59 | N5: 314132.32 | O5: 303514.7 | P5: 303514.7 | Q5: 311867.18 | R5: 297125.07 | S5: 295044.38 | T5: 308837.75 | U5: 308837.75 | V5: 315184.15 | W5: 324760.5 | X5: 380332.7 | Y5: 415239.28 | Z5: 415239.28 | AA5: 443932.37 | AB5: 514576.86
A6: 1 | C6: 현금및현금성자산 | E6: 42139.37 | F6: 42139.37 | G6: 33900.03 | H6: 32641.44 | I6: 57472.58 | J6: 47228.3 | K6: 47228.3 | L6: 37151.72 | M6: 39634.42 | N6: 26507.16 | O6: 30872.63 | P6: 30872.63 | Q6: 52296.02 | R6: 28421.61 | S6: 39473.29 | T6: 32062.22 | U6: 32062.22 | V6: 34806.43 | W6: 29598.46 | X6: 31977.01 | Y6: 35596.04 | Z6: 35596.04 | AA6: 42988.67 | AB6: 50147.66
A7: 1 | C7: 단기금융상품 | E7: 6736.71 | F7: 6736.71 | G7: 7094.19 | H7: 7032.87 | I7: 17356.18 | J7: 28793.26 | K7: 28793.26 | L7: 36508.73 | M7: 32853.19 | N7: 33011.18 | O7: 35738.28 | P7: 35738.28 | Q7: 32047.84 | R7: 28494.54 | S7: 28311.97
A8: 1 | C8: 단기금융자산 | E8: 6736.71 | F8: 6736.71 | G8: 7094.19 | H8: 7032.87 | I8: 17356.18 | J8: 28793.26 | K8: 28793.26 | L8: 36508.73 | M8: 32853.19 | N8: 33011.18 | O8: 35738.28 | P8: 35738.28 | Q8: 32047.84 | R8: 28494.54 | S8: 28311.97
A9: 1 | C9: 매출채권및기타채권 | E9: 57041.18 | F9: 57041.18 | G9: 64324.36 | H9: 75387.68 | I9: 78509.07 | J9: 73647.2 | K9: 73647.2 | L9: 77759.23 | M9: 77482.26 | N9: 68301.3 | O9: 65341.43 | P9: 65341.43 | Q9: 63864.4 | R9: 60247.78 | S9: 60615.72 | T9: 64451.52 | U9: 64451.52 | V9: 58913.1 | W9: 66205.99 | X9: 74405.79 | Y9: 74455.91 | Z9: 74455.91 | AA9: 80960.6 | AB9: 85500.51
A10: 1 | C10: 기타유동금융자산 | E10: 5737.56 | F10: 5737.56 | G10: 9786.47 | H10: 11722.97 | I10: 18801.63 | J10: 30546.47 | K10: 30546.47 | L10: 37066.72 | M10: 25616.97 | N10: 58087.69 | O10: 45942.23 | P10: 45942.23 | Q10: 47987.12 | R10: 61403.64 | S10: 46312.56 | T10: 33518.65 | U10: 33518.65 | V10: 34723.19 | W10: 31218 | X10: 21483.62 | Y10: 20314.31 | Z10: 20314.31 | AA10: 10429.69 | AB10: 14781.62
A11: 1 | C11: 재고자산 | E11: 122174.85 | F11: 122174.85 | G11: 117897.08 | H11: 121314.95 | I11: 124299.44 | J11: 130243.16 | K11: 130243.16 | L11: 126389.4 | M11: 127834.67 | N11: 126588.77 | O11: 124326.72 | P11: 124326.72 | Q11: 114121.3 | R11: 117077.86 | S11: 117995.25 | T11: 123155.71 | U11: 123155.71 | V11: 130072.66 | W11: 136654.07 | X11: 141510.26 | Y11: 151819.31 | Z11: 151819.31 | AA11: 147274.39 | AB11: 143956.53
A12: 1 | C12: 당기법인세자산(선급법인세) | E12: 10.19 | F12: 10.19 | G12: 11.34 | H12: 2.14 | I12: 25.11 | J12: 55.66 | K12: 55.66 | L12: 155 | M12: 59.45 | N12: 118.85 | O12: 218.11 | P12: 218.11 | Q12: 71.13 | R12: 109.7 | S12: 317.5 | T12: 238.3 | U12: 238.3 | V12: 132.56 | W12: 121.87 | X12: 212.83 | Y12: 168.88 | Z12: 168.88 | AA12: 184.81 | AB12: 13.88
A13: 1 | C13: 기타유동자산 | E13: 719.37 | F13: 719.37 | G13: 1447.88 | H13: 307.67 | I13: 435.56 | J13: 2193.82 | K13: 2193.82 | L13: 2077.94 | M13: 2416.64 | N13: 1517.37 | O13: 1075.3 | P13: 1075.3 | Q13: 1479.37 | R13: 1369.95 | S13: 2018.09 | T13: 1797.78 | U13: 1797.78 | V13: 2038.1 | W13: 1917.27 | X13: 1119.27 | Y13: 2511.37 | Z13: 2511.37 | AA13: 3220.61 | AB13: 2608.11
A14: 1 | C14: 비유동자산 | E14: 270627.22 | F14: 270627.22 | G14: 276409.66 | H14: 277859.66 | I14: 284433.96 | J14: 281287.28 | K14: 281287.28 | L14: 287071.83 | M14: 314264.96 | N14: 312130.68 | O14: 322780.54 | P14: 322780.54 | Q14: 333320.8 | R14: 347620.24 | S14: 357396.91 | T14: 351501.26 | U14: 351501.26 | V14: 359518.24 | W14: 358904.68 | X14: 344413.25 | Y14: 325576.34 | Z14: 325576.34 | AA14: 329624.68 | AB14: 336171.02
A15: 1 | C15: 장기금융자산 | E15: 34968.87 | F15: 34968.87 | G15: 38753.09 | H15: 38717.62 | I15: 43840.98 | J15: 39393.47 | K15: 39393.47 | L15: 43361.21 | M15: 64872.87 | N15: 53124.15 | O15: 61385.61 | P15: 61385.61 | Q15: 69983.71 | R15: 78473.29 | S15: 88736.93 | T15: 85142.68 | U15: 85142.68 | V15: 90382.97 | W15: 87844.72 | X15: 69426.81 | Y15: 61379.9 | Z15: 61379.9 | AA15: 62413.27 | AB15: 65415.01
A16: 1 | C16: 투자자산 | E16: 34968.87 | F16: 34968.87 | G16: 38753.09 | H16: 38717.62 | I16: 43840.98 | J16: 39393.47 | K16: 39393.47 | L16: 43361.21 | M16: 64872.87 | N16: 53124.15 | O16: 61385.61 | P16: 61385.61 | Q16: 69983.71 | R16: 78473.29 | S16: 88736.93 | T16: 85142.68 | U16: 85142.68 | V16: 90382.97 | W16: 87844.72 | X16: 69426.81 | Y16: 61379.9 | Z16: 61379.9 | AA16: 62413.27 | AB16: 65415.01
A17: 1 | C17: 장기매출채권및기타채권 | E17: 6156.67 | F17: 6156.67 | G17: 8439.22 | H17: 9500.55 | I17: 11343.51 | J17: 11196.11 | K17: 11196.11 | L17: 12100.51 | M17: 12410.27 | N17: 14298.23 | O17: 14756.87 | P17: 14756.87 | Q17: 15578.71 | R17: 15657.48 | T17: 12049.29 | U17: 12049.29 | V17: 11402.09 | W17: 11874.94 | X17: 2413.68 | Y17: 2363.25 | Z17: 2363.25 | AA17: 4190.46 | AB17: 4486.77
A18: 1 | C18: 기타비유동자산 | E18: 1822.24 | F18: 1822.24 | G18: 1812.25 | H18: 1644.93 | I18: 1922.29 | J18: 2336.88 | K18: 2336.88 | L18: 2412.8 | M18: 2233.42 | N18: 2706.12 | O18: 2721.28 | P18: 2721.28 | Q18: 2555.58 | R18: 2996.53 | S18: 2740.72 | T18: 2638.79 | U18: 2638.79 | V18: 3439.48 | W18: 3126.72 | X18: 6875.37 | Y18: 6903.09 | Z18: 6903.09 | AA18: 4604.31 | AB18: 4734.63
A19: 1 | C19: 투자부동산 | E19: 26782.55 | F19: 26782.55 | G19: 26724.92 | H19: 26667.3 | I19: 26609.67 | J19: 26552.04 | K19: 26552.04 | L19: 26494.42 | M19: 24778.67 | N19: 24726.7 | O19: 24674.74 | P19: 24674.74 | Q19: 24622.78 | R19: 24570.81 | S19: 24518.85 | T19: 24466.88 | U19: 24466.88 | V19: 24414.92 | W19: 24362.96 | X19: 24310.99 | Y19: 24259.03 | Z19: 24259.03 | AA19: 24207.06 | AB19: 24155.1
A20: 1 | C20: 유형자산 | E20: 163478.05 | F20: 163478.05 | G20: 163482 | H20: 164376.76 | I20: 163978.77 | J20: 163675.49 | K20: 163675.49 | L20: 164925.56 | M20: 170587.84 | N20: 174684.98 | O20: 177399.55 | P20: 177399.55 | Q20: 178775.5 | R20: 181371.68 | S20: 182149.92 | T20: 183237.06 | U20: 183237.06 | V20: 186121.92 | W20: 188118.35 | X20: 189383.65 | Y20: 188572.56 | Z20: 188572.56 | AA20: 187801.61 | AB20: 185998.35
A21: 1 | C21: 무형자산 | E21: 42730.96 | F21: 42730.96 | G21: 42510.3 | H21: 42264.64 | I21: 42050.87 | J21: 41838.63 | K21: 41838.63 | L21: 41573.76 | M21: 41379.7 | N21: 41138.17 | O21: 40907.54 | P21: 40907.54 | Q21: 40671.7 | R21: 40622.55 | S21: 40392.66 | T21: 40155.42 | U21: 40155.42 | V21: 39945.73 | W21: 39765.88 | X21: 39584.04 | Y21: 31927.35 | Z21: 31927.35 | AA21: 31711.17 | AB21: 31503.12
A22: 1 | C22: 자산총계 | E22: 505186.45 | F22: 505186.45 | G22: 510871.01 | H22: 526269.36 | I22: 581333.54 | J22: 593995.15 | K22: 593995.15 | L22: 604180.57 | M22: 620162.54 | N22: 626263 | O22: 626295.25 | P22: 626295.25 | Q22: 645187.97 | R22: 644745.31 | S22: 652441.28 | T22: 660339.01 | U22: 660339.01 | V22: 674702.39 | W22: 683665.18 | X22: 724745.95 | Y22: 740815.62 | Z22: 740815.62 | AA22: 773557.05 | AB22: 850747.88
A23: 1 | C23: 유동부채 | E23: 28727.05 | F23: 28727.05 | G23: 28559.27 | H23: 30571.49 | I23: 45894.25 | J23: 52478.26 | K23: 52478.26 | L23: 45856.33 | M23: 43508.34 | N23: 37939.96 | O23: 34017.82 | P23: 34017.82 | Q23: 40906.49 | R23: 32954.27 | S23: 34086.74 | T23: 34503.12 | U23: 34503.12 | V23: 44281.74 | W23: 38558.26 | X23: 45159.42 | Y23: 52715.81 | Z23: 52715.81 | AA23: 57364.13 | AB23: 54116.73
A24: 1 | C24: 매입채무및기타채무 | E24: 21968 | F24: 21968 | G24: 18247.04 | H24: 21711.69 | I24: 22470.82 | J24: 33860.15 | K24: 33860.15 | L24: 26398.45 | M24: 29852.57 | N24: 23885.79 | O24: 21914.11 | P24: 21914.11 | Q24: 21403.45 | R24: 23884.22 | S24: 25314.71 | T24: 24807.98 | U24: 24807.98 | V24: 28613.05 | W24: 30089.72 | X24: 30841 | Y24: 34255.56 | Z24: 34255.56 | AA24: 29119.31 | AB24: 28973.14
A25: 1 | C25: 기타유동부채 | E25: 1883.29 | F25: 1883.29 | G25: 2673.48 | H25: 1978.62 | I25: 6509.83 | J25: 7796.78 | K25: 7796.78 | L25: 3061.06 | M25: 2734.96 | N25: 1500.98 | O25: 2076.72 | P25: 2076.72 | Q25: 1673.58 | R25: 1372.41 | S25: 2236.45 | T25: 2927.15 | U25: 2927.15 | V25: 1663.87 | W25: 1455.05 | X25: 537.53 | Y25: 1688.85 | Z25: 1688.85 | AA25: 1146.16 | AB25: 1225.62
A26: 1 | C26: 기타유동금융부채 | E26: 1776.87 | F26: 1776.87 | G26: 4323.71 | H26: 1679.95 | I26: 3033.46 | J26: 1886.38 | K26: 1886.38 | L26: 6362.99 | M26: 1859.09 | N26: 1986.89 | O26: 1960.99 | P26: 1960.99 | Q26: 6385.69 | R26: 2173.13 | S26: 2112.34 | T26: 992.96 | U26: 992.96 | V26: 7471.13 | W26: 1015.93 | X26: 1027.81 | Y26: 5678.54 | Z26: 5678.54 | AA26: 12298.8 | AB26: 5809.91
A27: 1 | C27: 단기금융부채 | E27: 1776.87 | F27: 1776.87 | G27: 4323.71 | H27: 1679.95 | I27: 3033.46 | J27: 1886.38 | K27: 1886.38 | L27: 6362.99 | M27: 1859.09 | N27: 1986.89 | O27: 1960.99 | P27: 1960.99 | Q27: 6385.69 | R27: 2173.13 | S27: 2112.34 | T27: 2144.4 | U27: 2144.4 | V27: 8885.42 | W27: 2343.38 | X27: 2388.46 | Y27: 7031.24 | Z27: 7031.24 | AA27: 13942.91 | AB27: 7515.57
A28: 1 | C28: 당기법인세부채(미지급법인세) | E28: 2991.41 | F28: 2991.41 | G28: 3201.2 | H28: 5089.41 | I28: 13776.68 | J28: 8868.96 | K28: 8868.96 | L28: 9949.18 | M28: 8973.91 | N28: 10479.06 | O28: 8007.92 | P28: 8007.92 | Q28: 11390.68 | R28: 5473.88 | S28: 4376.71 | T28: 4533.84 | U28: 4533.84 | V28: 5036.41 | W28: 4597.18 | X28: 9991.77 | Y28: 8810.54 | Z28: 8810.54 | AA28: 11117.3 | AB28: 14729.48
A29: 1 | C29: 단기충당부채 | E29: 107.48 | F29: 107.48 | G29: 113.85 | H29: 111.83 | I29: 103.47 | J29: 65.98 | K29: 65.98 | L29: 84.66 | M29: 87.81 | N29: 87.23 | O29: 58.08 | P29: 58.08 | Q29: 53.1 | R29: 50.63 | S29: 46.53 | T29: 89.74 | U29: 89.74 | V29: 82.99 | W29: 72.92 | X29: 80.53 | Y29: 127.87 | Z29: 127.87 | AA29: 142.83 | AB29: 168.74
A30: 1 | C30: 비유동부채 | E30: 23378.56 | F30: 23378.56 | G30: 23427.62 | H30: 23188.85 | I30: 19605.29 | J30: 17284.15 | K30: 17284.15 | L30: 17428.54 | M30: 18086.74 | N30: 18102.98 | O30: 16885.99 | P30: 16885.99 | Q30: 17381.88 | R30: 18858.68 | S30: 18457.42 | T30: 16348.53 | U30: 16348.53 | V30: 16951.65 | W30: 18272.56 | X30: 23065.38 | Y30: 18483.09 | Z30: 18483.09 | AA30: 22672.67 | AB30: 34882.51
A31: 1 | C31: 기타비유동부채 | E31: 45.73 | F31: 45.73 | G31: 48.47 | H31: 51.21 | I31: 53.94 | J31: 51.52 | K31: 51.52 | L31: 55.27 | M31: 58.5 | N31: 62 | O31: 58.93 | P31: 58.93 | Q31: 62.61 | R31: 66.29 | S31: 69.98
A32: 1 | C32: 장기매입채무및기타채무 | E32: 5000 | F32: 5000 | G32: 4750 | H32: 4500 | T32: 60.91 | U32: 60.91 | V32: 64.62 | W32: 68.32 | X32: 72.03 | Y32: 64.95 | Z32: 64.95 | AA32: 68.78 | AB32: 72.61
A33: 1 | C33: 확정급여부채 | E33: 2363.97 | F33: 2363.97 | G33: 2734.89 | H33: 2424.78 | I33: 3032.34 | L33: 31.52
A34: 1 | C34: 이연법인세부채 | E34: 5218.06 | F34: 5218.06 | G34: 4959.19 | H34: 5040.6 | I34: 4636.07 | J34: 5590.98 | K34: 5590.98 | L34: 5866.77 | M34: 6306.13 | N34: 5755.8 | O34: 5394.84 | P34: 5394.84 | Q34: 6262.42 | R34: 6682.58 | S34: 6534.5 | T34: 5398.7 | U34: 5398.7 | V34: 5697.33 | W34: 7038.16 | X34: 11748.2 | Y34: 12654.86 | Z34: 12654.86 | AA34: 15975.27 | AB34: 27930.19
A35: 1 | C35: 장기충당부채 | E35: 2272.36 | F35: 2272.36 | G35: 2322.13 | H35: 2569.93 | I35: 2985.97 | J35: 3334.05 | K35: 3334.05 | L35: 3038.86 | M35: 3336.33 | N35: 3455.91 | O35: 3455.41 | P35: 3455.41 | Q35: 3184.91 | R35: 3901.36 | S35: 3747.9 | T35: 3642.15 | U35: 3642.15 | V35: 3146.15 | W35: 3346.25 | X35: 3513.43 | Y35: 3797.78 | Z35: 3797.78 | AA35: 3405.83 | AB35: 3609.07
A36: 1 | C36: 기타비유동금융부채 | E36: 8478.44 | F36: 8478.44 | G36: 8612.94 | H36: 8602.32 | I36: 8896.97 | J36: 8307.6 | K36: 8307.6 | L36: 8436.11 | M36: 8385.77 | N36: 8829.27 | O36: 7976.81 | P36: 7976.81 | Q36: 7871.94 | R36: 8208.44 | S36: 8105.05 | T36: 5484.4 | U36: 5484.4 | V36: 5546.41 | W36: 5609.84 | X36: 5674.71 | Y36: 61.8 | Z36: 61.8 | AA36: 61.8 | AB36: 61.8
A37: 1 | C37: 장기금융부채 | E37: 8478.44 | F37: 8478.44 | G37: 8612.94 | H37: 8602.32 | I37: 8896.97 | J37: 8307.6 | K37: 8307.6 | L37: 8436.11 | M37: 8385.77 | N37: 8829.27 | O37: 7976.81 | P37: 7976.81 | Q37: 7871.94 | R37: 8208.44 | S37: 8105.05 | T37: 7099.41 | U37: 7099.41 | V37: 7716.46 | W37: 7565.77 | X37: 7731.71 | Y37: 1965.49 | Z37: 1965.49 | AA37: 3222.79 | AB37: 3270.64
A38: 1 | C38: 부채총계 | E38: 52105.61 | F38: 52105.61 | G38: 51986.89 | H38: 53760.34 | I38: 65499.54 | J38: 69762.41 | K38: 69762.41 | L38: 63284.87 | M38: 61595.08 | N38: 56042.94 | O38: 50903.81 | P38: 50903.81 | Q38: 58288.38 | R38: 51812.95 | S38: 52544.16 | T38: 50851.65 | U38: 50851.65 | V38: 61233.39 | W38: 56830.82 | X38: 68224.79 | Y38: 71198.89 | Z38: 71198.89 | AA38: 80036.8 | AB38: 88999.24
A39: 1 | C39: 지배주주지분 | E39: 436133.57 | F39: 436133.57 | G39: 441042.44 | H39: 453310.34 | I39: 472915.85 | J39: 480089.17 | K39: 480089.17 | L39: 495190.25 | M39: 512255.34 | N39: 523726.08 | O39: 528792.38 | P39: 528792.38 | Q39: 540739.24 | R39: 550003.28 | S39: 557094.14 | T39: 566047.08 | U39: 566047.08 | V39: 570009.76 | W39: 584929.49 | X39: 613745.74 | Y39: 624576.99 | Z39: 624576.99 | AA39: 646534.42 | AB39: 706581.84
A40: 1 | C40: 자본금 | E40: 13250 | F40: 13250 | G40: 13250 | H40: 13250 | I40: 13250 | J40: 13250 | K40: 13250 | L40: 13250 | M40: 13250 | N40: 13250 | O40: 13250 | P40: 13250 | Q40: 13250 | R40: 13250 | S40: 13250 | T40: 13250 | U40: 13250 | V40: 13250 | W40: 13250 | X40: 13250 | Y40: 13250 | Z40: 13250 | AA40: 13250 | AB40: 13250
A41: 1 | C41: 자본잉여금 | E41: 34375.54 | F41: 34375.54 | G41: 34375.54 | H41: 34784.92 | I41: 45779.77 | J41: 44320.38 | K41: 44320.38 | L41: 44320.38 | M41: 44308.98 | N41: 44308.88 | O41: 44277.12 | P41: 44277.12 | Q41: 44302.68 | R41: 44302.68 | S41: 44302.68 | T41: 44302.68 | U41: 44302.68 | V41: 44302.68 | W41: 27302.68 | X41: 27302.68 | Y41: 27302.68 | Z41: 27302.68 | AA41: 27302.68 | AB41: 27302.68
A42: 1 | C42: 기타자본 | E42: -11255.45 | F42: -11255.45 | G42: -11257.16 | H42: -11255.45 | I42: -11255.45 | J42: -11255.45 | K42: -11255.45 | L42: -11255.45 | M42: -11255.45 | N42: -11255.45 | O42: -11278.62 | P42: -11278.62 | Q42: -11328.2 | R42: -12134.06 | S42: -12134.63 | T42: -12122.1 | U42: -12122.1 | V42: -12122.1 | W42: -12122.1 | X42: -12122.1 | Y42: -12122.1 | Z42: -12122.1 | AA42: -899.48 | AB42: -5070.18
A43: 1 | C43: 기타포괄이익누계액 | E43: -1522.12 | F43: -1522.12 | G43: -1519.52 | H43: -1475.46 | I43: -1428.98 | J43: -1519.39 | K43: -1519.39 | L43: -1495.33 | M43: -1503.6 | N43: -1493.84 | O43: -1832.13 | P43: -1832.13 | Q43: -1791.93 | R43: -1757.16 | S43: -1801.34 | T43: -1415.75 | U43: -1415.75 | V43: -1419.23 | W43: -1586.87 | X43: -1517.88 | Y43: -1236.66 | Z43: -1236.66 | AA43: -1104.03 | AB43: -1101.56
A44: 1 | C44: 이익잉여금 | E44: 401285.6 | F44: 401285.6 | G44: 406193.58 | H44: 418006.33 | I44: 426570.51 | J44: 435293.62 | K44: 435293.62 | L44: 450370.64 | M44: 467455.41 | N44: 478916.47 | O44: 484376.01 | P44: 484376.01 | Q44: 496306.69 | R44: 506341.83 | S44: 513477.42 | T44: 522032.24 | U44: 522032.24 | V44: 525998.41 | W44: 558085.77 | X44: 586833.04 | Y44: 597383.07 | Z44: 597383.07 | AA44: 607985.25 | AB44: 672200.9
A45: 1 | C45: 비지배주주지분 | E45: 16947.27 | F45: 16947.27 | G45: 17841.68 | H45: 19198.69 | I45: 42918.15 | J45: 44143.56 | K45: 44143.56 | L45: 45705.45 | M45: 46312.12 | N45: 46493.98 | O45: 46599.05 | P45: 46599.05 | Q45: 46160.35 | R45: 42929.07 | S45: 42802.99 | T45: 43440.29 | U45: 43440.29 | V45: 43459.24 | W45: 41904.88 | X45: 42775.41 | Y45: 45039.74 | Z45: 45039.74 | AA45: 46985.82 | AB45: 55166.8
... A48: 1 | C48: 이자발생자산 | E48: 83844.95 | F48: 83844.95 | G48: 79747.31 | H48: 78391.93 | I48: 118669.74 | J48: 115415.03 | K48: 115415.03 | L48: 117021.66 | M48: 137360.48 | N48: 112642.49 | O48: 127996.52 | P48: 127996.52 | Q48: 154327.57 | R48: 135389.44 | S48: 156522.19 | T48: 117204.9 | U48: 117204.9 | V48: 125189.4 | W48: 117443.18 | X48: 101403.82 | Y48: 96975.94 | Z48: 96975.94 | AA48: 105401.94 | AB48: 115562.67
A49: 1 | C49: 장기차입금 | E49: 4000 | F49: 4000 | G49: 3750 | H49: 3500
A50: 1 | C50: 총차입금 | E50: 4000 | F50: 4000 | G50: 3750 | H50: 3500
A51: 1 | C51: 순차입금 | E51: -44876.08 | F51: -44876.08 | G51: -37244.22 | H51: -36174.31
A52: 1 | C52: 단기투자자산(공정가치) | T52: 53613.58 | U52: 53613.58 | V52: 54498.12 | W52: 59044.85 | X52: 109623.91 | Y52: 130373.46 | Z52: 130373.46 | AA52: 158873.61 | AB52: 217568.54
A53: 1 | C53: 사용권자산 | T53: 2638.79 | U53: 2638.79 | V53: 3439.48 | W53: 3126.72 | X53: 3252.51 | Y53: 3090.54 | Z53: 3090.54 | AA53: 4604.31 | AB53: 4734.63
A54: 1 | C54: 유동리스부채 | T54: 1151.44 | U54: 1151.44 | V54: 1414.29 | W54: 1327.45 | X54: 1360.65 | Y54: 1352.7 | Z54: 1352.7 | AA54: 1644.11 | AB54: 1705.66
A55: 1 | C55: 리스부채 | T55: 2766.45 | U55: 2766.45 | V55: 3584.34 | W55: 3283.38 | X55: 3417.65 | Y55: 3256.39 | Z55: 3256.39 | AA55: 4805.1 | AB55: 4914.5
A56: 1 | C56: 비유동리스부채 | T56: 1615.01 | U56: 1615.01 | V56: 2170.05 | W56: 1955.93 | X56: 2057 | Y56: 1903.69 | Z56: 1903.69 | AA56: 3160.99 | AB56: 3208.84
A57: 1 | C57: 계약부채 | X57: 1320.13 | Y57: 801.74 | Z57: 801.74 | AA57: 1895.62 | AB57: 1504.19
A58: 1 | C58: 매출액(수익) | E58: 45882.65 | G58: 49064.7 | H58: 56489.03 | I58: 67935.29 | J58: 76253.64 | K58: 249742.66 | L58: 83913.27 | M58: 82223.61 | N58: 74590.26 | O58: 71340.33 | P58: 312067.47 | Q58: 73365.32 | R58: 65538.32 | S58: 61753.24 | T58: 66153.12 | U58: 266810 | V58: 62634.58 | W58: 72315.65 | X58: 81415.38 | Y58: 80600.08 | Z58: 296965.69 | AA58: 82275.27 | AB58: 83745.57
A59: 1 | C59: 매출원가 | E59: 37012.44 | G59: 36564.72 | H59: 38230.42 | I59: 47429.38 | J59: 53222.48 | K59: 175447 | L59: 56254.84 | M59: 56080.44 | N59: 54689.85 | O59: 55531.31 | P59: 222556.44 | Q59: 53405.49 | R59: 46487.78 | S59: 46526.64 | T59: 48189.7 | U59: 194609.61 | V59: 47288.56 | W59: 54547.78 | X59: 56421 | Y59: 52772.88 | Z59: 211030.22 | AA59: 58641.44 | AB59: 59864.13
A60: 1 | C60: 매출총이익 | E60: 8870.21 | G60: 12499.98 | H60: 18258.61 | I60: 20505.91 | J60: 23031.17 | K60: 74295.67 | L60: 27658.43 | M60: 26143.17 | N60: 19900.41 | O60: 15809.02 | P60: 89511.03 | Q60: 19959.83 | R60: 19050.54 | S60: 15226.6 | T60: 17963.42 | U60: 72200.39 | V60: 15346.02 | W60: 17767.87 | X60: 24994.38 | Y60: 27827.21 | Z60: 85935.48 | AA60: 23633.82 | AB60: 23881.45
A61: 1 | C61: 판관비 | E61: 5948.72 | G61: 5931.15 | H61: 6353.48 | I61: 10123.24 | J61: 6537.75 | K61: 28945.62 | L61: 7733.11 | M61: 8076.09 | N61: 7662.17 | O61: 8315.57 | P61: 31786.94 | Q61: 7106.06 | R61: 9233.62 | S61: 7648.5 | T61: 8339.25 | U61: 32327.43 | V61: 7942.22 | W61: 10111.09 | X61: 13425.57 | Y61: 15721.75 | Z61: 47200.63 | AA61: 14284.12 | AB61: 16669.62
A62: 1 | C62: 영업이익 | E62: 2921.49 | G62: 6568.84 | H62: 11905.14 | I62: 10382.66 | J62: 16493.41 | K62: 45350.05 | L62: 19925.32 | M62: 18067.08 | N62: 12238.24 | O62: 7493.46 | P62: 57724.1 | Q62: 12853.77 | R62: 9816.92 | S62: 7578.1 | T62: 9624.16 | U62: 39872.95 | V62: 7403.81 | W62: 7656.78 | X62: 11568.8 | Y62: 12105.46 | Z62: 38734.85 | AA62: 9349.7 | AB62: 7211.82
A63: 1 | C63: 기타영업외수익 | E63: 478.77 | G63: 482.47 | H63: 1305.08 | I63: 339.84 | J63: 259.28 | K63: 2386.67 | L63: 335.84 | M63: 460.18 | N63: 968.06 | O63: -152.64 | P63: 1611.44 | Q63: 112.72 | R63: 178.67 | S63: 179.06 | T63: 240.15 | U63: 710.6 | V63: 566.63 | W63: 558.59 | X63: 928 | Y63: 666.39 | Z63: 2719.61 | AA63: 1066.97 | AB63: 641.84
A64: 1 | C64: 기타영업외비용 | E64: 25.43 | G64: 244.51 | H64: -106.32 | I64: 88.86 | J64: 1889.29 | K64: 2116.34 | L64: 171.77 | M64: 537.68 | N64: 195.44 | O64: 4.59 | P64: 909.48 | Q64: 410.44 | R64: -47.08 | S64: 81.19 | T64: 147.42 | U64: 591.97 | V64: 116.74 | W64: 184.95 | X64: 677.87 | Y64: 10322.95 | Z64: 11302.51 | AA64: 960.45 | AB64: 282.84
A65: 1 | C65: 금융수익 | E65: 770.33 | G65: 3512.23 | H65: 4195.95 | I65: 10259.75 | J65: -4003.6 | K65: 13964.33 | L65: 7817.51 | M65: 4464.17 | N65: 2517.25 | O65: 2899.46 | P65: 17698.39 | Q65: 10812 | R65: 4485.77 | S65: 2333.37 | T65: 7696.02 | U65: 25327.16 | V65: 7084.71 | W65: 13490.28 | X65: 26858.27 | Y65: 15673.01 | Z65: 63106.27 | AA65: 35321.92 | AB65: 82809.4
A66: 1 | C66: 금융비용 | E66: 538.9 | G66: 636.57 | H66: 1591.73 | I66: 2561.97 | J66: 8006.81 | K66: 12797.08 | L66: 1731.28 | M66: 746.6 | N66: 558.53 | O66: 2442.93 | P66: 5479.34 | Q66: 2306.16 | R66: 1397.9 | S66: 1522.56 | T66: 2261.07 | U66: 7487.69 | V66: 2061.08 | W66: 4368.27 | X66: -983.17 | Y66: 1619.17 | Z66: 7065.35 | AA66: 7309.55 | AB66: 3747.48
A67: 1 | C67: 법인세비용차감전계속사업이익 | E67: 3606.26 | G67: 9682.46 | H67: 15920.75 | I67: 18331.43 | J67: 2852.99 | K67: 46787.63 | L67: 26175.63 | M67: 21707.16 | N67: 14969.58 | O67: 7792.76 | P67: 70645.13 | Q67: 21061.89 | R67: 13130.54 | S67: 8486.78 | T67: 15151.85 | U67: 57831.06 | V67: 12877.33 | W67: 17152.43 | X67: 39660.37 | Y67: 16502.73 | Z67: 86192.86 | AA67: 37468.59 | AB67: 86632.74
A68: 1 | C68: 법인세비용 | E68: 1125.74 | G68: 1146.91 | H68: 3506.48 | I68: 9648.94 | J68: -4298.14 | K68: 10004.19 | L68: 5311.76 | M68: 4111.79 | N68: 3360.53 | O68: -267.39 | P68: 12516.69 | Q68: 4395.65 | R68: 2682.23 | S68: 1605.3 | T68: 3026.99 | U68: 11710.17 | V68: 2639.24 | W68: 3769.95 | X68: 9931.77 | Y68: 4337.47 | Z68: 20678.43 | AA68: 8649.04 | AB68: 17687.2
A69: 1 | C69: 당기순이익 | E69: 2480.52 | G69: 8535.55 | H69: 12414.27 | I69: 8682.49 | J69: 7151.13 | K69: 36783.44 | L69: 20863.87 | M69: 17595.37 | N69: 11609.05 | O69: 8060.14 | P69: 58128.43 | Q69: 16666.25 | R69: 10448.31 | S69: 6881.48 | T69: 12124.87 | U69: 46120.91 | V69: 10238.09 | W69: 13382.48 | X69: 29728.6 | Y69: 12165.26 | Z69: 65514.43 | AA69: 28819.55 | AB69: 68945.54
... A75: 1 | C75: 계속사업이익 | E75: 2480.52 | G75: 8535.55 | H75: 12414.27 | I75: 8682.49 | J75: 7151.13 | K75: 36783.44 | L75: 20863.87 | M75: 17595.37 | N75: 11609.05 | O75: 8060.14 | P75: 58128.43 | Q75: 16666.25 | R75: 10448.31 | S75: 6881.48 | T75: 12124.87 | U75: 46120.91 | V75: 10238.09 | W75: 13382.48 | X75: 29728.6 | Y75: 12165.26 | Z75: 65514.43 | AA75: 28819.55 | AB75: 68945.54
A76: 1 | C76: 이자수익 | G76: 165.75 | H76: 25.55 | I76: 103.69 | J76: 904.07 | K76: 1199.06 | L76: 1282.93 | M76: 1141.47 | N76: 1017.33 | O76: 1229.47 | P76: 4671.2 | Q76: 1224.13 | R76: 1177.4 | S76: 1598.08 | T76: 1055.31 | U76: 5054.92 | V76: 1109.68 | W76: 1068.14 | X76: 896.13 | Y76: 622.78 | Z76: 3696.73 | AA76: 528.01 | AB76: 853.82
A77: 1 | C77: 이자비용 | G77: 177.14 | H77: -9.04 | I77: -4.18 | J77: 479.37 | K77: 643.29 | L77: 140.93 | M77: 332.32 | N77: -20.45 | O77: 310.13 | P77: 762.93 | Q77: 151.88 | R77: 149.55 | S77: 136.27 | T77: 163.6 | U77: 601.3 | V77: 156.64 | W77: 144.95 | X77: 148.26 | Y77: 148.88 | Z77: 598.73 | AA77: 151.66 | AB77: 153.64
A78: 1 | C78: 외환차익 | G78: 924.31 | H78: 1182.64 | I78: 2840.75 | J78: 6333.05 | K78: 11280.75 | L78: 1819.42 | M78: 1733.56 | N78: 1240.01 | O78: 1043.99 | P78: 5836.98 | Q78: 1781.18 | R78: 1633.34 | S78: 519.07 | T78: 2549.83 | U78: 6483.42 | V78: 371.65 | W78: 483.76 | X78: 660.52 | Y78: 2118.01 | Z78: 3633.94 | AA78: 1706.57 | AB78: 1905.71
A79: 1 | C79: 외환차손 | G79: 19.6 | H79: 190.38 | I79: -14.66 | J79: 2864.67 | K79: 3059.99 | L79: 791.93 | M79: 528.62 | N79: 695.13 | O79: 748.81 | P79: 2764.49 | Q79: 111.51 | R79: 275 | S79: 573.43 | T79: 552.41 | U79: 1512.35 | V79: 702.18 | W79: 1284.27 | X79: 920.1 | Y79: 516.37 | Z79: 3422.92 | AA79: 436.52 | AB79: 478.36
A80: 1 | C80: 외화환산이익 | G80: 983.49 | H80: 2011.79 | I80: 1877.92 | J80: -4108.45 | K80: 764.75 | L80: 1887.06 | M80: -238.72 | N80: 822.4 | O80: -1620.7 | P80: 850.04 | Q80: 1842.94 | R80: 897.55 | S80: -1904.5 | T80: 3387.41 | U80: 4223.4 | V80: 699.77 | W80: -68.48 | X80: 440.43 | Y80: 100.27 | Z80: 1171.99 | AA80: 2804.1 | AB80: 293.97
A81: 1 | C81: 외화환산손실 | G81: 198.77 | H81: -88.63 | I81: -197.18 | J81: 4710.8 | K81: 4623.76 | L81: 76.23 | M81: 216.15 | N81: -173.54 | O81: 1092.8 | P81: 1211.64 | Q81: 84.18 | R81: 134.63 | S81: 868.14 | T81: -641.15 | U81: 445.8 | V81: 108.74 | W81: 3043.05 | X81: -2108.69 | Y81: -129.72 | Z81: 913.38 | AA81: 301.88 | AB81: -33.85
A82: 1 | C82: 이자손익 | G82: -11.39 | H82: 34.59 | I82: 107.87 | J82: 424.7 | K82: 555.77 | L82: 1142 | M82: 809.15 | N82: 1037.78 | O82: 919.34 | P82: 3908.27 | Q82: 1072.25 | R82: 1027.85 | S82: 1461.81 | T82: 891.71 | U82: 4453.62 | V82: 953.04 | W82: 923.19 | X82: 747.87 | Y82: 473.9 | Z82: 3098 | AA82: 376.35 | AB82: 700.18
A83: 1 | C83: 배당금수익 | I83: -230.49 | J83: 250.3 | L83: 247.41 | M83: 0 | N83: 230.36 | O83: 419.19 | P83: 896.96 | Q83: 2171.45 | R83: 1030.02 | S83: 390.64 | T83: 578.59 | U83: 4170.7 | V83: 1143 | W83: 1996.34 | X83: 1572.58 | Y83: 1539.32 | Z83: 6251.24 | AA83: 8560.67 | AB83: 13138.22
A84: 1 | C84: 파생상품손실 | J84: -917.24 | L84: 91.55 | M84: 19.3 | N84: 0 | O84: 0 | P84: 110.85
A85: 1 | C85: 파생상품이익 | L85: 27.5 | M85: 0 | N85: 0 | O85: 0 | P85: 27.5
A86: 1 | C86: 영업활동으로인한현금흐름 | E86: 5631.88 | G86: 1308.85 | H86: 7559.13 | I86: 19713.69 | J86: 17724.36 | K86: 46306.03 | L86: 8744.18 | M86: 17711.67 | N86: 18769.41 | O86: 9110.22 | P86: 54335.48 | Q86: 30487.9 | R86: 7843.26 | S86: 8998.17 | T86: 11905.71 | U86: 59235.04 | V86: 12123.88 | W86: -4130.61 | X86: 3252.87 | Y86: 8119.54 | Z86: 19365.68 | AA86: 15166.52 | AB86: 23690.2
A87: 1 | C87: 법인세납부(CF) | E87: -14.38 | G87: -1143.05 | H87: -1450.86 | I87: -1331.31 | J87: -50.52 | K87: -3975.74 | L87: -4298.49 | M87: -4579.57 | N87: -2458.53 | O87: -2257.13 | P87: -13593.72 | Q87: -33.48 | R87: -8200.08 | S87: -3112.13 | T87: -3147.12 | U87: -14492.81 | V87: -1958.87 | W87: -2800.01 | X87: -1806.14 | Y87: -4762.65 | Z87: -11327.67 | AA87: -3404.59 | AB87: -3446.91
A88: 1 | C88: 투자활동으로인한현금흐름 | E88: -4821.21 | G88: -9050.98 | H88: -7501.76 | I88: -23861.58 | J88: -22154.8 | K88: -62569.12 | L88: -18693.6 | M88: -10389.25 | N88: -31607.3 | O88: -2384.59 | P88: -63074.74 | Q88: -7862.3 | R88: -22384.81 | S88: 2712.94 | T88: -18234.75 | U88: -45768.92 | V88: -8948.63 | W88: 6042.23 | X88: 6871.48 | Y88: -2917.41 | Z88: 1047.67 | AA88: -7548.33 | AB88: -3526.6
A89: 1 | C89: 유형자산의감소 | E89: 218.08 | G89: 3 | H89: 48.41 | J89: 183.33 | L89: 30 | M89: 2 | N89: 22.19 | O89: 4.8 | P89: 58.99 | Q89: 31.38 | R89: 15.47 | S89: 12.38 | T89: 3.7 | U89: 62.93 | V89: 34.55 | W89: 65.51 | X89: 3.4 | Y89: 0 | Z89: 103.46 | AA89: 17.19 | AB89: 49.23
A90: 1 | C90: CAPEX | E90: 21.76 | G90: 1478.05 | H90: 3027 | I90: 867.86 | J90: 1824.02 | K90: 7196.93 | L90: 2952.28 | M90: 5562.44 | N90: 6195.16 | O90: 5569.21 | P90: 20279.09 | Q90: 3225.73 | R90: 2368.39 | S90: 3537 | T90: 4178.41 | U90: 13309.53 | V90: 4577.35 | W90: 4107.83 | X90: 3738.06 | Y90: 2183.45 | Z90: 14606.69 | AA90: 1423.82 | AB90: 799.43
A91: 1 | C91: 무형자산의증가 | E91: 36 | G91: 24 | H91: 0 | I91: 40.5 | L91: 18.9 | M91: 51.4 | N91: 0 | O91: 0 | P91: 70.3 | S91: 1.65 | T91: 1.85
A92: 1 | C92: 재무활동으로인한현금흐름 | E92: -1351.47 | G92: -424.8 | H92: -1645.65 | I92: 28642.64 | J92: -3846.38 | K92: 22725.81 | L92: -291 | M92: -4749.92 | N92: -333.15 | O92: -2157.11 | P92: -7531.18 | Q92: -1353.79 | R92: -9374.72 | S92: -416.38 | T92: -1384.92 | U92: -12529.81 | V92: -455.2 | W92: -6925.51 | X92: -7838.35 | Y92: -1504.48 | Z92: -16723.54 | AA92: -495.43 | AB92: -13109.61
A93: 1 | C93: 단기차입금의증가 | E93: 0 | G93: 10.57 | H93: 181.42 | N93: 0 | O93: 0
A94: 1 | C94: 배당금지급 | E94: 0 | I94: 0 | J94: 0 | N94: 0 | O94: 0 | S94: 0 | T94: 0 | X94: 7372.16 | Y94: 0
A95: 1 | C95: 현금및현금성자산의증감 | E95: -1636.57 | G95: -16406.27 | H95: -2846.87 | I95: 49325.89 | J95: -18521.09 | K95: 11551.66 | L95: -20317.01 | M95: 5055.22 | N95: -26298.31 | O95: 8933.99 | P95: -32626.11 | Q95: 42695.19 | R95: -47790.68 | S95: 13696.15 | T95: -7411.07 | U95: 1189.59 | V95: 2744.21 | W95: -5207.97 | X95: 2378.55 | Y95: 3619.03 | Z95: 3533.82 | AA95: 7392.62 | AB95: 7159
A96: 1 | C96: 기말현금및현금성자산 | E96: -9182.83 | G96: 33900.03 | H96: -1258.59 | I96: 24831.14 | J96: -10244.28 | K96: 47228.3 | L96: 37151.72 | M96: 2482.7 | N96: -13127.26 | O96: 4365.47 | P96: 30872.63 | Q96: 52296.02 | R96: -23874.41 | S96: 11051.68 | T96: -7411.07 | U96: 32062.22 | V96: 34806.43 | W96: -5207.97 | X96: 2378.55 | Y96: 3619.03 | Z96: 35596.04 | AA96: 42988.67 | AB96: 7158.99
A97: 1 | C97: 유형자산의증가 | G97: 1454.05 | H97: 3027 | I97: 827.36 | J97: 1837.62 | K97: 7146.03 | L97: 2933.38 | M97: 5511.04 | N97: 6195.16 | O97: 5569.21 | P97: 20208.79 | Q97: 3225.73 | R97: 2354.09 | S97: 3535.35 | T97: 4176.56 | U97: 13291.73 | V97: 4577.35 | W97: 4107.83 | X97: 3738.06 | Y97: 1926.92 | Z97: 14350.16 | AA97: 1423.82 | AB97: 795.68
A98: 1 | C98: 장기차입금의증가 | G98: 12.59
A99: 1 | C99: 배당금수취(CF) | I99: 19.81 | J99: 0 | L99: 247.41 | M99: 0 | N99: 230.36 | O99: 419.19 | P99: 896.96 | Q99: 2171.45 | R99: 1030.02 | S99: 390.64 | T99: 578.59 | U99: 4170.7 | V99: 1143 | W99: 1996.34 | X99: 1572.58 | Y99: 1539.32 | Z99: 6251.24 | AA99: 8560.67 | AB99: 13138.22
A100: 1 | C100: 단기차입금의감소 | I100: 500 | J100: 47.64 | N100: 0 | O100: 0
A101: 1 | C101: 장기차입금의감소 | J101: 0 | S101: 0.65 | T101: 1.15 | X101: 0 | Y101: 0
A102: 1 | C102: 이자수취(CF) | O102: 1356.08 | Q102: 1441.54 | R102: 975 | S102: 1706.58 | T102: 933.82 | U102: 5056.94 | V102: 1328.75 | W102: 776.81 | X102: 1028.13 | Y102: 717.54 | Z102: 3851.23 | AA102: 855.06 | AB102: 773.92
A103: 1 | C103: 리스부채의상환 | V103: 455.2 | W103: 458.7 | X103: 466.18 | Y103: 464.65 | Z103: 1844.73 | AA103: 495.43 | AB103: 537.2

Sheet BS별도
B1: (백만원) | C1: 이름: BS별도H | E1: 4Q21 | F1: 2021 | G1: 1Q22 | H1: 2Q22 | I1: 3Q22 | J1: 4Q22 | K1: 2022 | L1: 1Q23 | M1: 2Q23 | N1: 3Q23 | O1: 4Q23 | P1: 2023 | Q1: 1Q24 | R1: 2Q24 | S1: 3Q24 | T1: 4Q24 | U1: 2024 | V1: 1Q25 | W1: 2Q25 | X1: 3Q25 | Y1: 4Q25 | Z1: 2025 | AA1: 1Q26 | AB1: 2Q26 | AC1: 3Q26 | AD1: 4Q26 | AE1: 2026 | AF1: 1Q27 | AG1: 2Q27 | AH1: 3Q27 | AI1: 4Q27 | AJ1: 2027 | AK1: 1Q28 | AL1: 2Q28 | AM1: 3Q28 | AN1: 4Q28 | AO1: 2028
B2: 별도 | D2: fin json(kship_fin.py)
B3: 태광(별) | C3: UPDATE: 26-10-11 | E3: 1 | F3: 2 | G3: 3 | H3: 4 | I3: 5 | J3: 6 | K3: 7 | L3: 8 | M3: 9 | N3: 10 | O3: 11 | P3: 12 | Q3: 13 | R3: 14 | S3: 15 | T3: 16 | U3: 17 | V3: 18 | W3: 19 | X3: 20 | Y3: 21 | Z3: 22 | AA3: 23 | AB3: 24 | AC3: 25 | AD3: 26 | AE3: 27 | AF3: 28 | AG3: 29 | AH3: 30 | AI3: 31 | AJ3: 32 | AK3: 33 | AL3: 34 | AM3: 35 | AN3: 36 | AO3: 37
B4: Account Code | C4: AccountNAME | E4: 2021.12 | F4: 2021.12A | G4: 2022.03 | H4: 2022.06 | I4: 2022.09 | J4: 2022.12 | K4: 2022.12A | L4: 2023.03 | M4: 2023.06 | N4: 2023.09 | O4: 2023.12 | P4: 2023.12A | Q4: 2024.03 | R4: 2024.06 | S4: 2024.09 | T4: 2024.12 | U4: 2024.12A | V4: 2025.03 | W4: 2025.06 | X4: 2025.09 | Y4: 2025.12 | Z4: 2025.12A | AA4: 2026.03 | AB4: 2026.06 | AC4: 2026.09 | AD4: 2026.12 | AE4: 2026.12A | AF4: 2027.03 | AG4: 2027.06 | AH4: 2027.09 | AI4: 2027.12 | AJ4: 2027.12A | AK4: 2028.03 | AL4: 2028.06 | AM4: 2028.09 | AN4: 2028.12 | AO4: 2028.12A
A5: 1 | C5: 유동자산 | E5: 216266.88 | F5: 216266.88 | G5: 214975.2 | H5: 228355.5 | I5: 253029.84 | J5: 269367.92 | K5: 269367.92 | L5: 266800.19 | M5: 254925.99 | N5: 263511.68 | O5: 252239.34 | P5: 252239.34 | Q5: 260332.03 | R5: 246927.63 | S5: 244137.34 | T5: 261536.48 | U5: 261536.48 | V5: 268912.84 | W5: 280361.68 | X5: 335292.26 | Y5: 368106.62 | Z5: 368106.62 | AA5: 393664.84 | AB5: 440749.32
A6: 1 | C6: 현금및현금성자산 | E6: 37489.7 | F6: 37489.7 | G6: 29916.02 | H6: 25450.98 | I6: 36545.66 | J6: 39788.18 | K6: 39788.18 | L6: 29508.58 | M6: 31670.32 | N6: 19613.33 | O6: 20700.49 | P6: 20700.49 | Q6: 35597.96 | R6: 15490.5 | S6: 22021.93 | T6: 21625.67 | U6: 21625.67 | V6: 23963.95 | W6: 19334.72 | X6: 24067.15 | Y6: 28880.08 | Z6: 28880.08 | AA6: 37649.52 | AB6: 39460.64
A7: 1 | C7: 단기금융상품 | E7: 6585.65 | F7: 6585.65 | G7: 6529.55 | H7: 6457.87 | I7: 6956.18 | J7: 6375.6 | K7: 6375.6 | L7: 16504.43 | M7: 16536.09 | N7: 16648.66 | O7: 16634.68 | P7: 16634.68 | Q7: 16862.13 | R7: 17017.16 | S7: 16762.67
A8: 1 | C8: 단기금융자산 | E8: 6585.65 | F8: 6585.65 | G8: 6529.55 | H8: 6457.87 | I8: 6956.18 | J8: 6375.6 | K8: 6375.6 | L8: 16504.43 | M8: 16536.09 | N8: 16648.66 | O8: 16634.68 | P8: 16634.68 | Q8: 16862.13 | R8: 17017.16 | S8: 16762.67
A9: 1 | C9: 매출채권및기타채권 | E9: 45948.44 | F9: 45948.44 | G9: 52738.11 | H9: 65252.23 | I9: 68804.29 | J9: 62842.59 | K9: 62842.59 | L9: 65893.48 | M9: 64984.57 | N9: 57663.87 | O9: 51334.22 | P9: 51334.22 | Q9: 54386.89 | R9: 48870.27 | S9: 52314.45 | T9: 52927.05 | U9: 52927.05 | V9: 49379.11 | W9: 57833.43 | X9: 65071.86 | Y9: 64161.59 | Z9: 64161.59 | AA9: 68792.58 | AB9: 71044.57
A10: 1 | C10: 기타유동금융자산 | E10: 5737.56 | F10: 5737.56 | G10: 9786.47 | H10: 11722.97 | I10: 18801.63 | J10: 30546.47 | K10: 30546.47 | L10: 29866.72 | M10: 15575.32 | N10: 45056.97 | O10: 41655.73 | P10: 41655.73 | Q10: 42016.51 | R10: 51298.44 | S10: 37568.32 | T10: 16933.52 | U10: 16933.52 | V10: 18494.5 | W10: 18120.16 | X10: 18275.88 | Y10: 17008.4 | Z10: 17008.4 | AA10: 9008.4 | AB10: 9008.4
A11: 1 | C11: 재고자산 | E11: 120039.24 | F11: 120039.24 | G11: 115498.07 | H11: 119253.71 | I11: 121721.79 | J11: 127844.22 | K11: 127844.22 | L11: 123341.21 | M11: 124651.95 | N11: 123665.12 | O11: 121315.29 | P11: 121315.29 | Q11: 110644.13 | R11: 113427.13 | S11: 113797.91 | T11: 119159.76 | U11: 119159.76 | V11: 125225.5 | W11: 132493.72 | X11: 137226.58 | Y11: 147949.81 | Z11: 147949.81 | AA11: 142619.85 | AB11: 137098.48
A12: 1 | C12: 기타유동자산 | E12: 466.3 | F12: 466.3 | G12: 506.98 | H12: 217.75 | I12: 200.29 | J12: 1970.86 | K12: 1970.86 | L12: 1685.76 | M12: 1507.74 | N12: 863.74 | O12: 598.93 | P12: 598.93 | Q12: 824.42 | R12: 824.14 | S12: 1672.06 | T12: 1653.28 | U12: 1653.28 | V12: 1874.39 | W12: 1607.05 | X12: 899.23 | Y12: 2080.87 | Z12: 2080.87 | AA12: 2740.17 | AB12: 2132.1
A13: 1 | C13: 비유동자산 | E13: 246467.93 | F13: 246467.93 | G13: 252380.03 | H13: 252842.58 | I13: 254228.23 | J13: 251200.6 | K13: 251200.6 | L13: 262434.85 | M13: 288830.9 | N13: 286843.69 | O13: 298038.31 | P13: 298038.31 | Q13: 308984.17 | R13: 326067.52 | S13: 336956.34 | T13: 326436.28 | U13: 326436.28 | V13: 332729.75 | W13: 332718.52 | X13: 316392.82 | Y13: 305286.45 | Z13: 305286.45 | AA13: 307690.72 | AB13: 316830.95
A14: 1 | C14: 장기금융자산 | E14: 33277.24 | F14: 33277.24 | G14: 37556.45 | H14: 37415.98 | I14: 37424.34 | J14: 32837.94 | K14: 32837.94 | L14: 41708.87 | M14: 63100.53 | N14: 51231.81 | O14: 59953.28 | P14: 59953.28 | Q14: 68501.38 | R14: 77323.76 | S14: 87997.4 | T14: 79403.15 | U14: 79403.15 | V14: 83343.44 | W14: 80805.19 | X14: 60404.52 | Y14: 52357.61 | Z14: 52357.61 | AA14: 53390.98 | AB14: 58335.37
A15: 1 | C15: 투자자산 | E15: 103316.89 | F15: 103316.89 | G15: 107596.1 | H15: 107455.63 | I15: 107463.99 | J15: 102877.59 | K15: 102877.59 | L15: 111748.52 | M15: 133140.18 | N15: 121271.46 | O15: 129992.93 | P15: 129992.93 | Q15: 138541.03 | R15: 151063.41 | S15: 161737.05 | T15: 153142.8 | U15: 153142.8 | V15: 157083.09 | W15: 154544.84 | X15: 134144.17 | Y15: 126097.26 | Z15: 126097.26 | AA15: 127130.63 | AB15: 58335.37
A16: 1 | C16: 장기매출채권및기타채권 | E16: 5889.27 | F16: 5889.27 | G16: 8043.78 | H16: 8941.51 | I16: 10721.97 | J16: 10504.61 | K16: 10504.61 | L16: 11348.22 | M16: 11599.63 | N16: 13513.58 | O16: 13952.92 | P16: 13952.92 | Q16: 14738.07 | R16: 14754.24 | T16: 11255.92 | U16: 11255.92 | V16: 10655.96 | W16: 11252 | X16: 1761.31 | Y16: 1720.51 | Z16: 1720.51 | AA16: 3454.27 | AB16: 3709.83
A17: 1 | C17: 기타비유동자산 | E17: 1164.57 | F17: 1164.57 | G17: 1196.62 | H17: 1066.56 | I17: 995.42 | J17: 1255.51 | K17: 1255.51 | L17: 1524.25 | M17: 1479.78 | N17: 1979 | O17: 1944.23 | P17: 1944.23 | Q17: 1860.68 | R17: 2011.91 | S17: 1911.07 | T17: 1829.93 | U17: 1829.93 | V17: 1907.94 | W17: 1848.08 | X17: 5739.76 | Y17: 5759.79 | Z17: 5759.79 | AA17: 1911.23 | AB17: 1981.67
A18: 1 | C18: 유형자산 | E18: 139708.68 | F18: 139708.68 | G18: 139166.76 | H18: 139038.85 | I18: 138743.56 | J18: 138613.55 | K18: 138613.55 | L18: 140027.41 | M18: 143002.93 | N18: 147055.07 | O18: 149674.51 | P18: 149674.51 | Q18: 151213.23 | R18: 152845.27 | S18: 153867.02 | T18: 155040.96 | U18: 155040.96 | V18: 157950.18 | W18: 159916.59 | X18: 160993.62 | Y18: 160098.52 | Z18: 160098.52 | AA18: 158984.2 | AB18: 157675.49
A19: 1 | C19: 무형자산 | E19: 1700.65 | F19: 1700.65 | G19: 1688.9 | H19: 1652.16 | I19: 1615.41 | J19: 1610.98 | K19: 1610.98 | L19: 1572.18 | M19: 1568.85 | N19: 1530.55 | O19: 1493.51 | P19: 1493.51 | Q19: 1456.48 | R19: 1420.14 | S19: 1387.81 | T19: 1355.55 | U19: 1355.55 | V19: 1321.45 | W19: 1345.9 | X19: 1335.27 | Y19: 1439.21 | Z19: 1439.21 | AA19: 1430.15 | AB19: 1422.09
A20: 1 | C20: 종속기업및관계기업투자 | E20: 70039.65 | F20: 70039.65 | G20: 70039.65 | H20: 70039.65 | I20: 70039.65 | J20: 70039.65 | K20: 70039.65 | L20: 70039.65 | M20: 70039.65 | N20: 70039.65 | O20: 70039.65 | P20: 70039.65 | Q20: 70039.65 | R20: 73739.65 | S20: 73739.65 | T20: 73739.65 | U20: 73739.65 | V20: 73739.65 | W20: 73739.65 | X20: 73739.65 | Y20: 73739.65 | Z20: 73739.65 | AA20: 73739.65
A21: 1 | C21: 자산총계 | E21: 462734.81 | F21: 462734.81 | G21: 467355.24 | H21: 481198.08 | I21: 507258.07 | J21: 520568.52 | K21: 520568.52 | L21: 529235.03 | M21: 543756.89 | N21: 550355.37 | O21: 550277.65 | P21: 550277.65 | Q21: 569316.2 | R21: 572995.16 | S21: 581093.68 | T21: 587972.75 | U21: 587972.75 | V21: 601642.59 | W21: 613080.2 | X21: 651685.08 | Y21: 673393.07 | Z21: 673393.07 | AA21: 701355.56 | AB21: 757580.27
A22: 1 | C22: 유동부채 | E22: 21820.91 | F22: 21820.91 | G22: 22046.69 | H22: 24592.52 | I22: 40546.26 | J22: 46500.55 | K22: 46500.55 | L22: 40621.84 | M22: 37465.71 | N22: 32707.27 | O22: 28354.97 | P22: 28354.97 | Q22: 35050.96 | R22: 27670.93 | S22: 28846.86 | T22: 28308.13 | U22: 28308.13 | V22: 37927.34 | W22: 32084.26 | X22: 37364.16 | Y22: 41007.91 | Z22: 41007.91 | AA22: 45146.79 | AB22: 40554.04
A23: 1 | C23: 매입채무및기타채무 | E23: 17163.12 | F23: 17163.12 | G23: 14271.6 | H23: 17556.15 | I23: 19129.69 | J23: 29964.03 | K23: 29964.03 | L23: 23355.93 | M23: 25733.33 | N23: 20576.96 | O23: 17996.19 | P23: 17996.19 | Q23: 17134.08 | R23: 20388.99 | S23: 21861.23 | T23: 20573 | U23: 20573 | V23: 24350.96 | W23: 25541.23 | X23: 25467.13 | Y23: 29743.51 | Z23: 29743.51 | AA23: 24389.23 | AB23: 23188.75
A24: 1 | C24: 기타유동부채 | E24: 1210.53 | F24: 1210.53 | G24: 1564.26 | H24: 1558.96 | I24: 5978.7 | J24: 7177.35 | K24: 7177.35 | L24: 2625.22 | M24: 2370.4 | N24: 1155.36 | O24: 1732 | P24: 1732 | Q24: 1494.8 | R24: 1175.51 | S24: 1996.9 | T24: 2603.54 | U24: 2603.54 | V24: 1367 | W24: 1233.83 | X24: 401.76 | Y24: 919.69 | Z24: 919.69 | AA24: 510.79 | AB24: 413.62
A25: 1 | C25: 기타유동금융부채 | E25: 455.86 | F25: 455.86 | G25: 3009.64 | H25: 388 | I25: 1661.19 | J25: 494.33 | K25: 494.33 | L25: 4988.85 | M25: 524.07 | N25: 614.18 | O25: 620.55 | P25: 620.55 | Q25: 5052.12 | R25: 665.35 | S25: 631.84 | V25: 6466.81 | X25: 0 | Y25: 0 | Z25: 0 | AA25: 6466.81 | AB25: 0
A26: 1 | C26: 단기금융부채 | E26: 455.86 | F26: 455.86 | G26: 3009.64 | H26: 388 | I26: 1661.19 | J26: 494.33 | K26: 494.33 | L26: 4988.85 | M26: 524.07 | N26: 614.18 | O26: 620.55 | P26: 620.55 | Q26: 5052.12 | R26: 665.35 | S26: 631.84 | T26: 622.36 | U26: 622.36 | V26: 7201.84 | W26: 736.9 | X26: 796.45 | Y26: 757.32 | Z26: 757.32 | AA26: 7253.06 | AB26: 815.84
A27: 1 | C27: 당기법인세부채(미지급법인세) | E27: 2991.41 | F27: 2991.41 | G27: 3201.2 | H27: 5089.41 | I27: 13776.68 | J27: 8864.84 | K27: 8864.84 | L27: 9651.84 | M27: 8837.91 | N27: 10360.76 | O27: 8006.24 | P27: 8006.24 | Q27: 11369.96 | R27: 5441.08 | S27: 4356.89 | T27: 4509.24 | U27: 4509.24 | V27: 5007.54 | W27: 4572.31 | X27: 9973.39 | Y27: 8798.62 | Z27: 8798.62 | AA27: 11116.2 | AB27: 14632.3
A28: 1 | C28: 비유동부채 | E28: 7414.36 | F28: 7414.36 | G28: 7855.92 | H28: 7788.83 | I28: 8454.73 | J28: 7133.64 | K28: 7133.64 | L28: 7388.12 | M28: 8172.4 | N28: 8185.14 | O28: 7833.07 | P28: 7833.07 | Q28: 8396.91 | R28: 9706.86 | S28: 9396.1 | T28: 8232.3 | U28: 8232.3 | V28: 8238.82 | W28: 9663.77 | X28: 14580.9 | Y28: 15606.95 | Z28: 15606.95 | AA28: 18629.5 | AB28: 26699.32
A29: 1 | C29: 확정급여부채 | E29: 2327.44 | F29: 2327.44 | G29: 2695.59 | H29: 2380.25 | I29: 2982.58 | V29: 259.86 | W29: 181.27 | X29: 0 | Y29: 0 | Z29: 0
A30: 1 | C30: 이연법인세부채 | E30: 2045.55 | F30: 2045.55 | G30: 1997.64 | H30: 2089 | I30: 1816.58 | J30: 2919.57 | K30: 2919.57 | L30: 3255.76 | M30: 3791.65 | N30: 3267.46 | O30: 2947.94 | P30: 2947.94 | Q30: 3899.14 | R30: 4347.81 | S30: 4254.8 | T30: 3174.24 | U30: 3174.24 | V30: 3537.16 | W30: 4899.83 | X30: 9690.28 | Y30: 10569.41 | Z30: 10569.41 | AA30: 13977.54 | AB30: 21831.48
A31: 1 | C31: 장기충당부채 | E31: 2272.36 | F31: 2272.36 | G31: 2322.13 | H31: 2569.93 | I31: 2985.97 | J31: 3334.05 | K31: 3334.05 | L31: 3038.86 | M31: 3336.33 | N31: 3455.91 | O31: 3455.41 | P31: 3455.41 | Q31: 3184.91 | R31: 3901.36 | S31: 3747.9 | T31: 3642.15 | U31: 3642.15 | V31: 3146.15 | W31: 3346.25 | X31: 3513.43 | Y31: 3797.78 | Z31: 3797.78 | AA31: 3405.83 | AB31: 3609.07
A32: 1 | C32: 기타비유동금융부채 | E32: 769 | F32: 769 | G32: 840.57 | H32: 749.65 | I32: 669.6 | J32: 880.01 | K32: 880.01 | L32: 1093.5 | M32: 1044.41 | N32: 1461.77 | O32: 1429.72 | P32: 1429.72 | Q32: 1312.86 | R32: 1457.68 | S32: 1393.41
A33: 1 | C33: 장기금융부채 | E33: 769 | F33: 769 | G33: 840.57 | H33: 749.65 | I33: 669.6 | J33: 880.01 | K33: 880.01 | L33: 1093.5 | M33: 1044.41 | N33: 1461.77 | O33: 1429.72 | P33: 1429.72 | Q33: 1312.86 | R33: 1457.68 | S33: 1393.41 | T33: 1326.13 | U33: 1326.13 | V33: 1295.66 | W33: 1236.42 | X33: 1377.19 | Y33: 1239.75 | Z33: 1239.75 | AA33: 1246.13 | AB33: 1258.77
A34: 1 | C34: 부채총계 | E34: 29235.27 | F34: 29235.27 | G34: 29902.62 | H34: 32381.35 | I34: 49000.98 | J34: 53634.18 | K34: 53634.18 | L34: 48009.96 | M34: 45638.1 | N34: 40892.41 | O34: 36188.05 | P34: 36188.05 | Q34: 43447.87 | R34: 37377.78 | S34: 38242.96 | T34: 36540.43 | U34: 36540.43 | V34: 46166.16 | W34: 41748.03 | X34: 51945.06 | Y34: 56614.86 | Z34: 56614.86 | AA34: 63776.29 | AB34: 67253.36
A35: 1 | C35: 자본금 | E35: 13250 | F35: 13250 | G35: 13250 | H35: 13250 | I35: 13250 | J35: 13250 | K35: 13250 | L35: 13250 | M35: 13250 | N35: 13250 | O35: 13250 | P35: 13250 | Q35: 13250 | R35: 13250 | S35: 13250 | T35: 13250 | U35: 13250 | V35: 13250 | W35: 13250 | X35: 13250 | Y35: 13250 | Z35: 13250 | AA35: 13250 | AB35: 13250
A36: 1 | C36: 자본잉여금 | E36: 34425.4 | F36: 34425.4 | G36: 34425.4 | H36: 34425.4 | I36: 34425.4 | J36: 34425.4 | K36: 34425.4 | L36: 34425.4 | M36: 34425.4 | N36: 34425.4 | O36: 34425.4 | P36: 34425.4 | Q36: 34425.4 | R36: 34425.4 | S36: 34425.4 | T36: 34425.4 | U36: 34425.4 | V36: 34425.4 | W36: 17425.4 | X36: 17425.4 | Y36: 17425.4 | Z36: 17425.4 | AA36: 17425.4 | AB36: 17425.4
A37: 1 | C37: 기타자본 | E37: -11222.62 | F37: -11222.62 | G37: -11222.62 | H37: -11222.62 | I37: -11222.62 | J37: -11222.62 | K37: -11222.62 | L37: -11222.62 | M37: -11222.62 | N37: -11222.62 | O37: -11222.62 | P37: -11222.62 | Q37: -11222.62 | R37: -11222.62 | S37: -11222.62 | T37: -11222.62 | U37: -11222.62 | V37: -11222.62 | W37: -11222.62 | X37: -11222.62 | Y37: -11222.62 | Z37: -11222.62 | AA37: 0 | AB37: -4658.56
A38: 1 | C38: 기타포괄이익누계액 | E38: -1541.77 | F38: -1541.77 | G38: -1541.77 | H38: -1541.77 | I38: -1541.77 | J38: -1554.05 | K38: -1554.05 | L38: -1554.05 | M38: -1554.05 | N38: -1554.05 | O38: -1874.26 | P38: -1874.26 | Q38: -1874.26 | R38: -1874.26 | S38: -1874.26 | T38: -1644.6 | U38: -1644.6 | V38: -1644.6 | W38: -1644.6 | X38: -1644.6 | Y38: -1437.67 | Z38: -1437.67 | AA38: -1437.67 | AB38: -1437.67
A39: 1 | C39: 이익잉여금 | E39: 398588.53 | F39: 398588.53 | G39: 402541.61 | H39: 413905.71 | I39: 423346.08 | J39: 432035.61 | K39: 432035.61 | L39: 446326.35 | M39: 463220.06 | N39: 474564.24 | O39: 479511.08 | P39: 479511.08 | Q39: 491289.81 | R39: 501038.85 | S39: 508272.2 | T39: 516624.14 | U39: 516624.14 | V39: 520668.25 | W39: 553523.99 | X39: 581931.85 | Y39: 598763.1 | Z39: 598763.1 | AA39: 608341.53 | AB39: 665747.73
A40: 1 | C40: 자본총계 | E40: 433499.54 | F40: 433499.54 | G40: 437452.62 | H40: 448816.73 | I40: 458257.09 | J40: 466934.34 | K40: 466934.34 | L40: 481225.08 | M40: 498118.79 | N40: 509462.96 | O40: 514089.6 | P40: 514089.6 | Q40: 525868.33 | R40: 535617.37 | S40: 542850.72 | T40: 551432.32 | U40: 551432.32 | V40: 555476.42 | W40: 571332.17 | X40: 599740.02 | Y40: 616778.21 | Z40: 616778.21 | AA40: 637579.26 | AB40: 690326.91
A41: 1 | C41: 부채와자본총계 | E41: 462734.81 | F41: 462734.81 | G41: 467355.24 | H41: 481198.08 | I41: 507258.07 | J41: 520568.52 | K41: 520568.52 | L41: 529235.03 | M41: 543756.89 | N41: 550355.37 | O41: 550277.65 | P41: 550277.65 | Q41: 569316.2 | R41: 572995.16 | S41: 581093.68 | T41: 587972.75 | U41: 587972.75 | V41: 601642.59 | W41: 613080.2 | X41: 651685.08 | Y41: 673393.07 | Z41: 673393.07 | AA41: 701355.56 | AB41: 757580.27
A42: 1 | C42: 지배주주지분 | E42: 433499.54 | F42: 433499.54 | G42: 437452.62 | H42: 448816.73 | I42: 458257.09 | J42: 466934.34 | K42: 466934.34 | L42: 481225.08 | M42: 498118.79 | N42: 509462.96 | O42: 514089.6 | P42: 514089.6 | Q42: 525868.33 | R42: 535617.37 | S42: 542850.72 | T42: 551432.32 | U42: 551432.32 | V42: 555476.42 | W42: 571332.17 | X42: 599740.02 | Y42: 616778.21 | Z42: 616778.21 | AA42: 637579.26 | AB42: 690326.91
A43: 1 | C43: 이자발생자산 | E43: 77352.59 | F43: 77352.59 | G43: 74002.02 | H43: 69324.83 | I43: 80926.18 | J43: 79001.72 | K43: 79001.72 | L43: 87721.88 | M43: 111306.94 | N43: 87493.8 | O43: 97288.45 | P43: 97288.45 | Q43: 120961.47 | R43: 109831.42 | S43: 126782 | T43: 101028.82 | U43: 101028.82 | V43: 107307.39 | W43: 100139.91 | X43: 84471.67 | Y43: 81237.69 | Z43: 81237.69 | AA43: 91040.5 | AB43: 97796.01
A44: 1 | C44: 단기투자자산(공정가치) | T44: 49237.2 | U44: 49237.2 | V44: 49975.4 | W44: 50972.6 | X44: 89751.57 | Y44: 108025.87 | Z44: 108025.87 | AA44: 132854.33 | AB44: 182005.13
A45: 1 | C45: 사용권자산 | T45: 1829.93 | U45: 1829.93 | V45: 1907.94 | W45: 1848.08 | X45: 2046.1 | Y45: 1872.4 | Z45: 1872.4 | AA45: 1911.23 | AB45: 1981.67
A46: 1 | C46: 유동리스부채 | T46: 622.36 | U46: 622.36 | V46: 735.03 | W46: 736.9 | X46: 796.45 | Y46: 757.32 | Z46: 757.32 | AA46: 786.25 | AB46: 815.84
A47: 1 | C47: 리스부채 | T47: 1948.49 | U47: 1948.49 | V47: 2030.69 | W47: 1973.32 | X47: 2173.64 | Y47: 1997.07 | Z47: 1997.07 | AA47: 2032.38 | AB47: 2074.61
A48: 1 | C48: 비유동리스부채 | T48: 1326.13 | U48: 1326.13 | V48: 1295.66 | W48: 1236.42 | X48: 1377.19 | Y48: 1239.75 | Z48: 1239.75 | AA48: 1246.13 | AB48: 1258.77
A49: 1 | C49: 계약부채 | X49: 725.43 | Y49: 788.77 | Z49: 788.77 | AA49: 1877.51 | AB49: 1503.53
A50: 1 | C50: 매출액(수익) | E50: 36274.62 | G50: 39170.41 | H50: 48030.91 | I50: 60280.41 | J50: 66076.73 | K50: 213558.46 | L50: 73148.69 | M50: 71719.92 | N50: 65351.9 | O50: 59697.68 | P50: 269918.19 | Q50: 65354.32 | R50: 56250.03 | S50: 55148.93 | T50: 56313.1 | U50: 233066.38 | V50: 55689.99 | W50: 65648.41 | X50: 72943.47 | Y50: 71335.36 | Z50: 265617.23 | AA50: 73835.1 | AB50: 73223.77
A51: 1 | C51: 매출원가 | E51: 28867.41 | G51: 30372.89 | H51: 31986.19 | I51: 41374.29 | J51: 45674.48 | K51: 149407.85 | L51: 49373.97 | M51: 47823.52 | N51: 46926.98 | O51: 47011.43 | P51: 191135.9 | Q51: 47213.64 | R51: 39434.43 | S51: 41208.15 | T51: 40226.89 | U51: 168083.11 | V51: 41623.65 | W51: 47461.72 | X51: 49319.52 | Y51: 45462.98 | Z51: 183867.87 | AA51: 50981.11 | AB51: 51720.2
A52: 1 | C52: 매출총이익 | E52: 7407.21 | G52: 8797.52 | H52: 16044.72 | I52: 18906.12 | J52: 20402.26 | K52: 64150.62 | L52: 23774.72 | M52: 23896.4 | N52: 18424.92 | O52: 12686.25 | P52: 78782.29 | Q52: 18140.68 | R52: 16815.6 | S52: 13940.79 | T52: 16086.22 | U52: 64983.29 | V52: 14066.35 | W52: 18186.69 | X52: 23623.95 | Y52: 25872.37 | Z52: 81749.36 | AA52: 22853.99 | AB52: 21503.57
A53: 1 | C53: 판관비 | E53: 3446.79 | G53: 3823.57 | H53: 4644.41 | I53: 6787.2 | J53: 4585.33 | K53: 19840.51 | L53: 5491.88 | M53: 6026.11 | N53: 6004.39 | O53: 6005.25 | P53: 23527.63 | Q53: 5163.38 | R53: 7176.61 | S53: 5716.84 | T53: 6435.09 | U53: 24491.92 | V53: 5947.93 | W53: 8194.44 | X53: 11078.09 | Y53: 13368.03 | Z53: 38588.49 | AA53: 11814.33 | AB53: 13713.2
A54: 1 | C54: 영업이익 | E54: 3960.41 | G54: 4973.94 | H54: 11400.3 | I54: 12118.92 | J54: 15816.92 | K54: 44310.08 | L54: 18282.84 | M54: 17870.29 | N54: 12420.53 | O54: 6681 | P54: 55254.66 | Q54: 12977.3 | R54: 9638.99 | S54: 8223.95 | T54: 9651.12 | U54: 40491.36 | V54: 8118.42 | W54: 9992.25 | X54: 12545.87 | Y54: 12504.35 | Z54: 43160.89 | AA54: 11039.66 | AB54: 7790.37
A55: 1 | C55: 기타영업외수익 | E55: 311.68 | G55: 426.27 | H55: 1164.65 | I55: 281.86 | J55: 222.04 | K55: 2094.82 | L55: 209.15 | M55: 381.1 | N55: 891.05 | O55: -334.32 | P55: 1146.98 | Q55: 56.81 | R55: 142.06 | S55: 143.22 | T55: 204.49 | U55: 546.58 | V55: 506.75 | W55: 518.75 | X55: 890.08 | Y55: 583.07 | Z55: 2498.65 | AA55: 826.04 | AB55: 586.98
A56: 1 | C56: 기타영업외비용 | E56: 17.71 | G56: 118.36 | H56: 0.42 | I56: 67.42 | J56: 1669.58 | K56: 1855.78 | L56: 55.44 | M56: 486.51 | N56: 21.44 | O56: 63.83 | P56: 627.22 | Q56: 303.6 | R56: -64.76 | S56: 77.37 | T56: 94.19 | U56: 410.4 | V56: 108.7 | W56: 186.15 | X56: 675.13 | Y56: 2732.12 | Z56: 3702.1 | AA56: 428.92 | AB56: 249.79
A57: 1 | C57: 금융수익 | E57: 734.64 | G57: 3282.37 | H57: 3818.37 | I57: 9673.46 | J57: -3904.21 | K57: 12869.99 | L57: 6999.32 | M57: 3764.45 | N57: 1923.36 | O57: 2478.16 | P57: 15165.29 | Q57: 9957.26 | R57: 3781.56 | S57: 1715.39 | T57: 6518.41 | U57: 21972.62 | V57: 6238.74 | W57: 12508.16 | X57: 24995.23 | Y57: 11740.42 | Z57: 55482.55 | AA57: 30241.84 | AB57: 60846
A58: 1 | C58: 금융비용 | E58: 379.48 | G58: 478.69 | H58: 1224.48 | I58: 2668.99 | J58: 7334.71 | K58: 11706.87 | L58: 1610.4 | M58: 402.49 | N58: 592.34 | O58: 2054.61 | P58: 4659.84 | Q58: 2144.54 | R58: 1149.43 | S58: 1309.21 | T58: 2046.35 | U58: 6649.53 | V58: 1760.99 | W58: 3717.63 | X58: -858.76 | Y58: 1597.23 | Z58: 6217.09 | AA58: 6975.99 | AB58: 3407.52
A59: 1 | C59: 법인세비용차감전계속사업이익 | E59: 4609.55 | G59: 8085.54 | H59: 15158.42 | I59: 19337.83 | J59: 3130.47 | K59: 45712.26 | L59: 23825.46 | M59: 21126.84 | N59: 14621.16 | O59: 6706.4 | P59: 66279.86 | Q59: 20543.23 | R59: 12477.94 | S59: 8695.99 | T59: 14233.5 | U59: 55950.66 | V59: 12994.21 | W59: 19115.37 | X59: 38614.8 | Y59: 20498.5 | Z59: 91222.88 | AA59: 34702.63 | AB59: 65566.04
A60: 1 | C60: 법인세비용 | E60: 1131.76 | G60: 1353.96 | H60: 3522.04 | I60: 9766.8 | J60: -4149.26 | K60: 10493.54 | L60: 5224.26 | M60: 4280.96 | N60: 3247.94 | O60: 57.59 | P60: 12810.75 | Q60: 4503.31 | R60: 2700 | S60: 1658.3 | T60: 2720.6 | U60: 11582.21 | V60: 2702.52 | W60: 3668.94 | X60: 9989.65 | Y60: 4200.48 | Z60: 20561.59 | AA60: 8736.66 | AB60: 13465.9
A61: 1 | C61: 당기순이익 | E61: 3477.77 | G61: 6731.57 | H61: 11636.38 | I61: 9571.04 | J61: 7279.73 | K61: 35218.72 | L61: 18601.2 | M61: 16845.88 | N61: 11373.22 | O61: 6648.8 | P61: 53469.1 | Q61: 16039.91 | R61: 9777.93 | S61: 7037.69 | T61: 11512.89 | U61: 44368.42 | V61: 10291.7 | W61: 15446.44 | X61: 28625.15 | Y61: 16298.02 | Z61: 70661.31 | AA61: 25965.97 | AB61: 52100.14
... A69: 1 | C69: 투자활동으로인한현금흐름 | E69: -10050.75 | G69: -8209.09 | H69: -5230.23 | I69: -9193.92 | J69: -12135.05 | K69: -34768.29 | L69: -18705.36 | M69: -10020.41 | N69: -27678.66 | O69: -8524.02 | P69: -64928.45 | Q69: -10022.45 | R69: -24731.51 | S69: 913.11 | T69: -12622.23 | U69: -46463.08 | V69: -8085.98 | W69: 6572.59 | X69: 9558.33 | Y69: -3510.72 | Z69: 4534.22 | AA69: -9377.54 | AB69: -12637.04
A70: 1 | C70: 유형자산의감소 | E70: 32.88 | G70: 3 | H70: 4 | I70: 6 | J70: 5 | K70: 18 | L70: 30 | M70: 2 | O70: 4.8 | Q70: 31.38 | R70: 15.47 | S70: 12.38 | T70: 3.7 | U70: 62.93 | V70: 34.55 | W70: 65.51 | X70: 3 | Y70: 0 | Z70: 103.06 | AA70: 2.73 | AB70: 49.23
A71: 1 | C71: 유형자산의증가 | E71: 192.28 | G71: 708.39 | H71: 1140.39 | I71: 983.21 | J71: 1190.03 | K71: 4022.02 | L71: 2776.83 | M71: 4342.25 | N71: 5416.5 | O71: 5318.79 | P71: 17854.37 | Q71: 3208.47 | R71: 1775.49 | S71: 3229.06 | T71: 4098.44 | U71: 12311.46 | V71: 4438.64 | W71: 3520.53 | X71: 3304.28 | Y71: 1628.5 | Z71: 12891.95 | AA71: 848.06 | AB71: 953.45
A72: 1 | C72: CAPEX | E72: 212.28 | G72: 732.39 | H72: 1140.39 | I72: 983.21 | J72: 1206.53 | K72: 4062.52 | L72: 2776.83 | M72: 4378.25 | N72: 5416.5 | O72: 5318.79 | P72: 17890.37 | Q72: 3208.47 | R72: 1775.49 | S72: 3230.71 | T72: 4100.29 | U72: 12314.96 | V72: 4438.64 | W72: 3572.6 | X72: 3278.21 | Y72: 1790.83 | Z72: 13080.28 | AA72: 848.06 | AB72: 953.45
A73: 1 | C73: 무형자산의증가 | E73: 20 | G73: 24 | H73: 0 | I73: 0 | J73: 16.5 | K73: 40.5 | N73: 0 | O73: 0 | T73: 1.85 | Y73: 162.33
A74: 1 | C74: 재무활동으로인한현금흐름 | E74: -136.67 | G74: -148.2 | H74: -2737 | I74: -151.45 | J74: -152.61 | K74: -3189.26 | L74: -161.29 | M74: -4573.85 | N74: -196.66 | O74: -209.47 | P74: -5141.27 | Q74: -218.11 | R74: -4630.38 | S74: -233.64 | T74: -231.91 | U74: -5314.04 | V74: -233.22 | W74: -6703.83 | X74: -7623.73 | Y74: -255.59 | Z74: -14816.37 | AA74: -254.67 | AB74: -11382.78
A75: 1 | C75: 단기차입금의감소 | E75: 0 | L75: 1797.3 | M75: 0 | N75: 0 | O75: 0 | P75: 1797.3
A76: 1 | C76: 배당금지급 | E76: 0 | I76: 0 | J76: 0 | N76: 0 | O76: 0 | S76: 0 | T76: 0 | X76: 7372.16 | Y76: 0
A77: 1 | C77: 현금및현금성자산의증감 | E77: -12738.65 | G77: -15146.86 | H77: -9136.61 | I77: 21820.43 | J77: 8110.14 | K77: 5647.1 | L77: -20630.02 | M77: 4362.15 | N77: -24086.58 | O77: 2310.57 | P77: -38043.88 | Q77: 29769.86 | R77: -40213.19 | S77: 13125.52 | T77: -1757.01 | U77: 925.18 | V77: 2338.28 | W77: -4629.23 | X77: 4732.43 | Y77: 4812.93 | Z77: 7254.41 | AA77: 8769.44 | AB77: 1811.13
A78: 1 | C78: 기말현금및현금성자산 | E78: -6647.86 | G78: 29916.02 | H78: -4465.04 | I78: -61996.64 | J78: 76333.84 | K78: 39788.18 | L78: 29508.58 | M78: 2161.74 | N78: -12056.99 | O78: 1087.16 | P78: 20700.49 | Q78: 35597.96 | R78: -20107.46 | S78: 6531.43 | T78: -396.26 | U78: 21625.67 | V78: 23963.95 | W78: -4629.23 | X78: 4732.43 | Y78: 4812.93 | Z78: 28880.08 | AA78: 37649.52 | AB78: 1811.12
A79: 1 | C79: 배당금수취(CF) | I79: 19.81 | J79: 0 | L79: 247.41 | M79: 0 | N79: 230.36 | O79: 419.19 | P79: 896.96 | Q79: 2171.45 | R79: 1030.02 | S79: 390.64 | T79: 578.59 | U79: 4170.7 | V79: 1143 | W79: 1996.34 | X79: 1566.78 | Y79: 1530.94 | Z79: 6237.06 | AA79: 8560.59 | AB79: 12763.63
A80: 1 | C80: 단기차입금의증가 | L80: 1797.3 | M80: 0 | N80: 0 | O80: 0 | P80: 1797.3
A81: 1 | C81: 이자수취(CF) | O81: 904.46 | Q81: 1303.2 | R81: 708.24 | S81: 1100.94 | T81: 832.32 | U81: 3944.7 | V81: 1155.43 | W81: 609.12 | X81: 604.16 | Y81: 551.61 | Z81: 2920.32 | AA81: 790.21 | AB81: 647.53
A82: 1 | C82: 리스부채의상환 | V82: 233.22 | W82: 237.02 | X82: 251.56 | Y82: 255.6 | Z82: 977.4 | AA82: 254.67 | AB82: 257.41

Sheet subQ
A1: YQ | C1: subQ 분기 서브모델(억원, U=100) | E1: 4Q21 | F1: 2021 | G1: 1Q22 | H1: 2Q22 | I1: 3Q22 | J1: 4Q22 | K1: 2022 | L1: 1Q23 | M1: 2Q23 | N1: 3Q23 | O1: 4Q23 | P1: 2023 | Q1: 1Q24 | R1: 2Q24 | S1: 3Q24 | T1: 4Q24 | U1: 2024 | V1: 1Q25 | W1: 2Q25 | X1: 3Q25 | Y1: 4Q25 | Z1: 2025 | AA1: 1Q26 | AB1: 2Q26 | AC1: 3Q26 | AD1: 4Q26 | AE1: 2026 | AF1: 1Q27 | AG1: 2Q27 | AH1: 3Q27 | AI1: 4Q27 | AJ1: 2027 | AK1: 1Q28 | AL1: 2Q28 | AM1: 3Q28 | AN1: 4Q28 | AO1: 2028
A2: A=이름(key) B=그룹 C=단위 D=FnGuide 계정명(VLOOKUP 키). 확정=VLOOKUP(BS), 추정=변수 가정 참조
E3: 1 | F3: 2 | G3: 3 | H3: 4 | I3: 5 | J3: 6 | K3: 7 | L3: 8 | M3: 9 | N3: 10 | O3: 11 | P3: 12 | Q3: 13 | R3: 14 | S3: 15 | T3: 16 | U3: 17 | V3: 18 | W3: 19 | X3: 20 | Y3: 21 | Z3: 22 | AA3: 23 | AB3: 24 | AC3: 25 | AD3: 26 | AE3: 27 | AF3: 28 | AG3: 29 | AH3: 30 | AI3: 31 | AJ3: 32 | AK3: 33 | AL3: 34 | AM3: 35 | AN3: 36 | AO3: 37
E4: 2021.12 | F4: 2021.12A | G4: 2022.03 | H4: 2022.06 | I4: 2022.09 | J4: 2022.12 | K4: 2022.12A | L4: 2023.03 | M4: 2023.06 | N4: 2023.09 | O4: 2023.12 | P4: 2023.12A | Q4: 2024.03 | R4: 2024.06 | S4: 2024.09 | T4: 2024.12 | U4: 2024.12A | V4: 2025.03 | W4: 2025.06 | X4: 2025.09 | Y4: 2025.12 | Z4: 2025.12A | AA4: 2026.03 | AB4: 2026.06 | AC4: 2026.09 | AD4: 2026.12 | AE4: 2026.12A | AF4: 2027.03 | AG4: 2027.06 | AH4: 2027.09 | AI4: 2027.12 | AJ4: 2027.12A | AK4: 2028.03 | AL4: 2028.06 | AM4: 2028.09 | AN4: 2028.12 | AO4: 2028.12A
A5: 매출액 | B5: 손익 | C5: 억원 | D5: 매출액(수익) | E5: =IFERROR(VLOOKUP($D5,BS연결,MATCH(E$1,BS연결H,0),0)/100,"") | G5: =IFERROR(VLOOKUP($D5,BS연결,MATCH(G$1,BS연결H,0),0)/100,"") | H5: =IFERROR(VLOOKUP($D5,BS연결,MATCH(H$1,BS연결H,0),0)/100,"") | I5: =IFERROR(VLOOKUP($D5,BS연결,MATCH(I$1,BS연결H,0),0)/100,"") | J5: =IFERROR(VLOOKUP($D5,BS연결,MATCH(J$1,BS연결H,0),0)/100,"") | K5: =IFERROR(VLOOKUP($D5,BS연결,MATCH(K$1,BS연결H,0),0)/100,"") | L5: =IFERROR(VLOOKUP($D5,BS연결,MATCH(L$1,BS연결H,0),0)/100,"") | M5: =IFERROR(VLOOKUP($D5,BS연결,MATCH(M$1,BS연결H,0),0)/100,"") | N5: =IFERROR(VLOOKUP($D5,BS연결,MATCH(N$1,BS연결H,0),0)/100,"") | ... AB5: =IFERROR(VLOOKUP($D5,BS연결,MATCH(AB$1,BS연결H,0),0)/100,"") | AC5: =IFERROR(X5*(1+변수!AC21),"") | AD5: =IFERROR(Y5*(1+변수!AD21),"") | AE5: =SUM(AA5:AD5) | AF5: =IFERROR(AA5*(1+변수!AF21),"") | AG5: =IFERROR(AB5*(1+변수!AG21),"") | AH5: =IFERROR(AC5*(1+변수!AH21),"") | AI5: =IFERROR(AD5*(1+변수!AI21),"") | AJ5: =SUM(AF5:AI5) | AK5: =IFERROR(AF5*(1+변수!AK21),"") | AL5: =IFERROR(AG5*(1+변수!AL21),"") | AM5: =IFERROR(AH5*(1+변수!AM21),"") | AN5: =IFERROR(AI5*(1+변수!AN21),"") | AO5: =SUM(AK5:AN5)
A6: 매출원가 | B6: 손익 | C6: 억원 | D6: 매출원가 | E6: =IFERROR(VLOOKUP($D6,BS연결,MATCH(E$1,BS연결H,0),0)/100,"") | G6: =IFERROR(VLOOKUP($D6,BS연결,MATCH(G$1,BS연결H,0),0)/100,"") | H6: =IFERROR(VLOOKUP($D6,BS연결,MATCH(H$1,BS연결H,0),0)/100,"") | I6: =IFERROR(VLOOKUP($D6,BS연결,MATCH(I$1,BS연결H,0),0)/100,"") | J6: =IFERROR(VLOOKUP($D6,BS연결,MATCH(J$1,BS연결H,0),0)/100,"") | K6: =IFERROR(VLOOKUP($D6,BS연결,MATCH(K$1,BS연결H,0),0)/100,"") | L6: =IFERROR(VLOOKUP($D6,BS연결,MATCH(L$1,BS연결H,0),0)/100,"") | M6: =IFERROR(VLOOKUP($D6,BS연결,MATCH(M$1,BS연결H,0),0)/100,"") | N6: =IFERROR(VLOOKUP($D6,BS연결,MATCH(N$1,BS연결H,0),0)/100,"") | ... AB6: =IFERROR(VLOOKUP($D6,BS연결,MATCH(AB$1,BS연결H,0),0)/100,"") | AC6: =IFERROR(AC5-AC7,"") | AD6: =IFERROR(AD5-AD7,"") | AE6: =SUM(AA6:AD6) | AF6: =IFERROR(AF5-AF7,"") | AG6: =IFERROR(AG5-AG7,"") | AH6: =IFERROR(AH5-AH7,"") | AI6: =IFERROR(AI5-AI7,"") | AJ6: =SUM(AF6:AI6) | AK6: =IFERROR(AK5-AK7,"") | AL6: =IFERROR(AL5-AL7,"") | AM6: =IFERROR(AM5-AM7,"") | AN6: =IFERROR(AN5-AN7,"") | AO6: =SUM(AK6:AN6)
A7: 매출총이익 | B7: 손익 | C7: 억원 | D7: 매출총이익 | E7: =IFERROR(VLOOKUP($D7,BS연결,MATCH(E$1,BS연결H,0),0)/100,"") | G7: =IFERROR(VLOOKUP($D7,BS연결,MATCH(G$1,BS연결H,0),0)/100,"") | H7: =IFERROR(VLOOKUP($D7,BS연결,MATCH(H$1,BS연결H,0),0)/100,"") | I7: =IFERROR(VLOOKUP($D7,BS연결,MATCH(I$1,BS연결H,0),0)/100,"") | J7: =IFERROR(VLOOKUP($D7,BS연결,MATCH(J$1,BS연결H,0),0)/100,"") | K7: =IFERROR(VLOOKUP($D7,BS연결,MATCH(K$1,BS연결H,0),0)/100,"") | L7: =IFERROR(VLOOKUP($D7,BS연결,MATCH(L$1,BS연결H,0),0)/100,"") | M7: =IFERROR(VLOOKUP($D7,BS연결,MATCH(M$1,BS연결H,0),0)/100,"") | N7: =IFERROR(VLOOKUP($D7,BS연결,MATCH(N$1,BS연결H,0),0)/100,"") | ... AB7: =IFERROR(VLOOKUP($D7,BS연결,MATCH(AB$1,BS연결H,0),0)/100,"") | AC7: =IFERROR(AC9+AC8,"") | AD7: =IFERROR(AD9+AD8,"") | AE7: =SUM(AA7:AD7) | AF7: =IFERROR(AF9+AF8,"") | AG7: =IFERROR(AG9+AG8,"") | AH7: =IFERROR(AH9+AH8,"") | AI7: =IFERROR(AI9+AI8,"") | AJ7: =SUM(AF7:AI7) | AK7: =IFERROR(AK9+AK8,"") | AL7: =IFERROR(AL9+AL8,"") | AM7: =IFERROR(AM9+AM8,"") | AN7: =IFERROR(AN9+AN8,"") | AO7: =SUM(AK7:AN7)
A8: 판관비 | B8: 손익 | C8: 억원 | D8: 판관비 | E8: =IFERROR(VLOOKUP($D8,BS연결,MATCH(E$1,BS연결H,0),0)/100,"") | G8: =IFERROR(VLOOKUP($D8,BS연결,MATCH(G$1,BS연결H,0),0)/100,"") | H8: =IFERROR(VLOOKUP($D8,BS연결,MATCH(H$1,BS연결H,0),0)/100,"") | I8: =IFERROR(VLOOKUP($D8,BS연결,MATCH(I$1,BS연결H,0),0)/100,"") | J8: =IFERROR(VLOOKUP($D8,BS연결,MATCH(J$1,BS연결H,0),0)/100,"") | K8: =IFERROR(VLOOKUP($D8,BS연결,MATCH(K$1,BS연결H,0),0)/100,"") | L8: =IFERROR(VLOOKUP($D8,BS연결,MATCH(L$1,BS연결H,0),0)/100,"") | M8: =IFERROR(VLOOKUP($D8,BS연결,MATCH(M$1,BS연결H,0),0)/100,"") | N8: =IFERROR(VLOOKUP($D8,BS연결,MATCH(N$1,BS연결H,0),0)/100,"") | ... AB8: =IFERROR(VLOOKUP($D8,BS연결,MATCH(AB$1,BS연결H,0),0)/100,"") | AC8: =IFERROR(AC5*변수!AC22,"") | AD8: =IFERROR(AD5*변수!AD22,"") | AE8: =SUM(AA8:AD8) | AF8: =IFERROR(AF5*변수!AF22,"") | AG8: =IFERROR(AG5*변수!AG22,"") | AH8: =IFERROR(AH5*변수!AH22,"") | AI8: =IFERROR(AI5*변수!AI22,"") | AJ8: =SUM(AF8:AI8) | AK8: =IFERROR(AK5*변수!AK22,"") | AL8: =IFERROR(AL5*변수!AL22,"") | AM8: =IFERROR(AM5*변수!AM22,"") | AN8: =IFERROR(AN5*변수!AN22,"") | AO8: =SUM(AK8:AN8)
A9: 영업이익 | B9: 손익 | C9: 억원 | D9: 영업이익 | E9: =IFERROR(VLOOKUP($D9,BS연결,MATCH(E$1,BS연결H,0),0)/100,"") | G9: =IFERROR(VLOOKUP($D9,BS연결,MATCH(G$1,BS연결H,0),0)/100,"") | H9: =IFERROR(VLOOKUP($D9,BS연결,MATCH(H$1,BS연결H,0),0)/100,"") | I9: =IFERROR(VLOOKUP($D9,BS연결,MATCH(I$1,BS연결H,0),0)/100,"") | J9: =IFERROR(VLOOKUP($D9,BS연결,MATCH(J$1,BS연결H,0),0)/100,"") | K9: =IFERROR(VLOOKUP($D9,BS연결,MATCH(K$1,BS연결H,0),0)/100,"") | L9: =IFERROR(VLOOKUP($D9,BS연결,MATCH(L$1,BS연결H,0),0)/100,"") | M9: =IFERROR(VLOOKUP($D9,BS연결,MATCH(M$1,BS연결H,0),0)/100,"") | N9: =IFERROR(VLOOKUP($D9,BS연결,MATCH(N$1,BS연결H,0),0)/100,"") | ... AB9: =IFERROR(VLOOKUP($D9,BS연결,MATCH(AB$1,BS연결H,0),0)/100,"") | AC9: =IFERROR(AC5*변수!AC23,"") | AD9: =IFERROR(AD5*변수!AD23,"") | AE9: =SUM(AA9:AD9) | AF9: =IFERROR(AF5*변수!AF23,"") | AG9: =IFERROR(AG5*변수!AG23,"") | AH9: =IFERROR(AH5*변수!AH23,"") | AI9: =IFERROR(AI5*변수!AI23,"") | AJ9: =SUM(AF9:AI9) | AK9: =IFERROR(AK5*변수!AK23,"") | AL9: =IFERROR(AL5*변수!AL23,"") | AM9: =IFERROR(AM5*변수!AM23,"") | AN9: =IFERROR(AN5*변수!AN23,"") | AO9: =SUM(AK9:AN9)
A10: OPM | B10: 손익 | C10: % | D10: 영업이익률 | E10: =IFERROR(E9/E5,"") | G10: =IFERROR(G9/G5,"") | H10: =IFERROR(H9/H5,"") | I10: =IFERROR(I9/I5,"") | J10: =IFERROR(J9/J5,"") | K10: =IFERROR(K9/K5,"") | L10: =IFERROR(L9/L5,"") | M10: =IFERROR(M9/M5,"") | N10: =IFERROR(N9/N5,"") | ... AO10: =IFERROR(AO9/AO5,"")
A11: 금융손익 | B11: 손익 | C11: 억원 | D11: 금융손익 | E11: =IFERROR(VLOOKUP($D11,BS연결,MATCH(E$1,BS연결H,0),0)/100,"") | G11: =IFERROR(VLOOKUP($D11,BS연결,MATCH(G$1,BS연결H,0),0)/100,"") | H11: =IFERROR(VLOOKUP($D11,BS연결,MATCH(H$1,BS연결H,0),0)/100,"") | I11: =IFERROR(VLOOKUP($D11,BS연결,MATCH(I$1,BS연결H,0),0)/100,"") | J11: =IFERROR(VLOOKUP($D11,BS연결,MATCH(J$1,BS연결H,0),0)/100,"") | K11: =IFERROR(VLOOKUP($D11,BS연결,MATCH(K$1,BS연결H,0),0)/100,"") | L11: =IFERROR(VLOOKUP($D11,BS연결,MATCH(L$1,BS연결H,0),0)/100,"") | M11: =IFERROR(VLOOKUP($D11,BS연결,MATCH(M$1,BS연결H,0),0)/100,"") | N11: =IFERROR(VLOOKUP($D11,BS연결,MATCH(N$1,BS연결H,0),0)/100,"") | ... AB11: =IFERROR(VLOOKUP($D11,BS연결,MATCH(AB$1,BS연결H,0),0)/100,"") | AC11: =IFERROR(AC12+AC13+AC14+AC15,"") | AD11: =IFERROR(AD12+AD13+AD14+AD15,"") | AE11: =SUM(AA11:AD11) | AF11: =IFERROR(AF12+AF13+AF14+AF15,"") | AG11: =IFERROR(AG12+AG13+AG14+AG15,"") | AH11: =IFERROR(AH12+AH13+AH14+AH15,"") | AI11: =IFERROR(AI12+AI13+AI14+AI15,"") | AJ11: =SUM(AF11:AI11) | AK11: =IFERROR(AK12+AK13+AK14+AK15,"") | AL11: =IFERROR(AL12+AL13+AL14+AL15,"") | AM11: =IFERROR(AM12+AM13+AM14+AM15,"") | AN11: =IFERROR(AN12+AN13+AN14+AN15,"") | AO11: =SUM(AK11:AN11)
A12: 이자손익 | B12: 손익 | C12: 억원 | D12: 이자손익 | G12: =IFERROR(VLOOKUP($D12,BS연결,MATCH(G$1,BS연결H,0),0)/100,"") | H12: =IFERROR(VLOOKUP($D12,BS연결,MATCH(H$1,BS연결H,0),0)/100,"") | I12: =IFERROR(VLOOKUP($D12,BS연결,MATCH(I$1,BS연결H,0),0)/100,"") | J12: =IFERROR(VLOOKUP($D12,BS연결,MATCH(J$1,BS연결H,0),0)/100,"") | K12: =SUM(G12:J12) | L12: =IFERROR(VLOOKUP($D12,BS연결,MATCH(L$1,BS연결H,0),0)/100,"") | M12: =IFERROR(VLOOKUP($D12,BS연결,MATCH(M$1,BS연결H,0),0)/100,"") | N12: =IFERROR(VLOOKUP($D12,BS연결,MATCH(N$1,BS연결H,0),0)/100,"") | O12: =IFERROR(VLOOKUP($D12,BS연결,MATCH(O$1,BS연결H,0),0)/100,"") | P12: =IFERROR(VLOOKUP($D12,BS연결,MATCH(P$1,BS연결H,0),0)/100,"") | Q12: =IFERROR(VLOOKUP($D12,BS연결,MATCH(Q$1,BS연결H,0),0)/100,"") | R12: =IFERROR(VLOOKUP($D12,BS연결,MATCH(R$1,BS연결H,0),0)/100,"") | S12: =IFERROR(VLOOKUP($D12,BS연결,MATCH(S$1,BS연결H,0),0)/100,"") | ... AB12: =IFERROR(VLOOKUP($D12,BS연결,MATCH(AB$1,BS연결H,0),0)/100,"") | AC12: =IFERROR((AB27*변수!$D$53-AB25*변수!$D$54)/4,"") | AD12: =IFERROR((AC27*변수!$D$53-AC25*변수!$D$54)/4,"") | AE12: =SUM(AA12:AD12) | AF12: =IFERROR((AD27*변수!$D$53-AD25*변수!$D$54)/4,"") | AG12: =IFERROR((AF27*변수!$D$53-AF25*변수!$D$54)/4,"") | AH12: =IFERROR((AG27*변수!$D$53-AG25*변수!$D$54)/4,"") | AI12: =IFERROR((AH27*변수!$D$53-AH25*변수!$D$54)/4,"") | AJ12: =SUM(AF12:AI12) | AK12: =IFERROR((AI27*변수!$D$53-AI25*변수!$D$54)/4,"") | AL12: =IFERROR((AK27*변수!$D$53-AK25*변수!$D$54)/4,"") | AM12: =IFERROR((AL27*변수!$D$53-AL25*변수!$D$54)/4,"") | AN12: =IFERROR((AM27*변수!$D$53-AM25*변수!$D$54)/4,"") | AO12: =SUM(AK12:AN12)
A13: 외환손익 | B13: 손익 | C13: 억원 | D13: 외환손익(실적만; 추정 환효과는 환관련손익) | G13: =IFERROR((VLOOKUP("외환차익",BS연결,MATCH(G$1,BS연결H,0),0)-VLOOKUP("외환차손",BS연결,MATCH(G$1,BS연결H,0),0)+VLOOKUP("외화환산이익",BS연결,MATCH(G$1,BS연결H,0),0)-VLOOKUP("외화환산손실",BS연결,MATCH(G$1,BS연결H,0),0))/100,"") | H13: =IFERROR((VLOOKUP("외환차익",BS연결,MATCH(H$1,BS연결H,0),0)-VLOOKUP("외환차손",BS연결,MATCH(H$1,BS연결H,0),0)+VLOOKUP("외화환산이익",BS연결,MATCH(H$1,BS연결H,0),0)-VLOOKUP("외화환산손실",BS연결,MATCH(H$1,BS연결H,0),0))/100,"") | I13: =IFERROR((VLOOKUP("외환차익",BS연결,MATCH(I$1,BS연결H,0),0)-VLOOKUP("외환차손",BS연결,MATCH(I$1,BS연결H,0),0)+VLOOKUP("외화환산이익",BS연결,MATCH(I$1,BS연결H,0),0)-VLOOKUP("외화환산손실",BS연결,MATCH(I$1,BS연결H,0),0))/100,"") | J13: =IFERROR((VLOOKUP("외환차익",BS연결,MATCH(J$1,BS연결H,0),0)-VLOOKUP("외환차손",BS연결,MATCH(J$1,BS연결H,0),0)+VLOOKUP("외화환산이익",BS연결,MATCH(J$1,BS연결H,0),0)-VLOOKUP("외화환산손실",BS연결,MATCH(J$1,BS연결H,0),0))/100,"") | K13: =SUM(G13:J13) | L13: =IFERROR((VLOOKUP("외환차익",BS연결,MATCH(L$1,BS연결H,0),0)-VLOOKUP("외환차손",BS연결,MATCH(L$1,BS연결H,0),0)+VLOOKUP("외화환산이익",BS연결,MATCH(L$1,BS연결H,0),0)-VLOOKUP("외화환산손실",BS연결,MATCH(L$1,BS연결H,0),0))/100,"") | M13: =IFERROR((VLOOKUP("외환차익",BS연결,MATCH(M$1,BS연결H,0),0)-VLOOKUP("외환차손",BS연결,MATCH(M$1,BS연결H,0),0)+VLOOKUP("외화환산이익",BS연결,MATCH(M$1,BS연결H,0),0)-VLOOKUP("외화환산손실",BS연결,MATCH(M$1,BS연결H,0),0))/100,"") | N13: =IFERROR((VLOOKUP("외환차익",BS연결,MATCH(N$1,BS연결H,0),0)-VLOOKUP("외환차손",BS연결,MATCH(N$1,BS연결H,0),0)+VLOOKUP("외화환산이익",BS연결,MATCH(N$1,BS연결H,0),0)-VLOOKUP("외화환산손실",BS연결,MATCH(N$1,BS연결H,0),0))/100,"") | O13: =IFERROR((VLOOKUP("외환차익",BS연결,MATCH(O$1,BS연결H,0),0)-VLOOKUP("외환차손",BS연결,MATCH(O$1,BS연결H,0),0)+VLOOKUP("외화환산이익",BS연결,MATCH(O$1,BS연결H,0),0)-VLOOKUP("외화환산손실",BS연결,MATCH(O$1,BS연결H,0),0))/100,"") | P13: =SUM(L13:O13) | Q13: =IFERROR((VLOOKUP("외환차익",BS연결,MATCH(Q$1,BS연결H,0),0)-VLOOKUP("외환차손",BS연결,MATCH(Q$1,BS연결H,0),0)+VLOOKUP("외화환산이익",BS연결,MATCH(Q$1,BS연결H,0),0)-VLOOKUP("외화환산손실",BS연결,MATCH(Q$1,BS연결H,0),0))/100,"") | R13: =IFERROR((VLOOKUP("외환차익",BS연결,MATCH(R$1,BS연결H,0),0)-VLOOKUP("외환차손",BS연결,MATCH(R$1,BS연결H,0),0)+VLOOKUP("외화환산이익",BS연결,MATCH(R$1,BS연결H,0),0)-VLOOKUP("외화환산손실",BS연결,MATCH(R$1,BS연결H,0),0))/100,"") | S13: =IFERROR((VLOOKUP("외환차익",BS연결,MATCH(S$1,BS연결H,0),0)-VLOOKUP("외환차손",BS연결,MATCH(S$1,BS연결H,0),0)+VLOOKUP("외화환산이익",BS연결,MATCH(S$1,BS연결H,0),0)-VLOOKUP("외화환산손실",BS연결,MATCH(S$1,BS연결H,0),0))/100,"") | T13: =IFERROR((VLOOKUP("외환차익",BS연결,MATCH(T$1,BS연결H,0),0)-VLOOKUP("외환차손",BS연결,MATCH(T$1,BS연결H,0),0)+VLOOKUP("외화환산이익",BS연결,MATCH(T$1,BS연결H,0),0)-VLOOKUP("외화환산손실",BS연결,MATCH(T$1,BS연결H,0),0))/100,"") | U13: =SUM(Q13:T13) | V13: =IFERROR((VLOOKUP("외환차익",BS연결,MATCH(V$1,BS연결H,0),0)-VLOOKUP("외환차손",BS연결,MATCH(V$1,BS연결H,0),0)+VLOOKUP("외화환산이익",BS연결,MATCH(V$1,BS연결H,0),0)-VLOOKUP("외화환산손실",BS연결,MATCH(V$1,BS연결H,0),0))/100,"") | W13: =IFERROR((VLOOKUP("외환차익",BS연결,MATCH(W$1,BS연결H,0),0)-VLOOKUP("외환차손",BS연결,MATCH(W$1,BS연결H,0),0)+VLOOKUP("외화환산이익",BS연결,MATCH(W$1,BS연결H,0),0)-VLOOKUP("외화환산손실",BS연결,MATCH(W$1,BS연결H,0),0))/100,"") | X13: =IFERROR((VLOOKUP("외환차익",BS연결,MATCH(X$1,BS연결H,0),0)-VLOOKUP("외환차손",BS연결,MATCH(X$1,BS연결H,0),0)+VLOOKUP("외화환산이익",BS연결,MATCH(X$1,BS연결H,0),0)-VLOOKUP("외화환산손실",BS연결,MATCH(X$1,BS연결H,0),0))/100,"") | Y13: =IFERROR((VLOOKUP("외환차익",BS연결,MATCH(Y$1,BS연결H,0),0)-VLOOKUP("외환차손",BS연결,MATCH(Y$1,BS연결H,0),0)+VLOOKUP("외화환산이익",BS연결,MATCH(Y$1,BS연결H,0),0)-VLOOKUP("외화환산손실",BS연결,MATCH(Y$1,BS연결H,0),0))/100,"") | Z13: =SUM(V13:Y13) | AA13: =IFERROR((VLOOKUP("외환차익",BS연결,MATCH(AA$1,BS연결H,0),0)-VLOOKUP("외환차손",BS연결,MATCH(AA$1,BS연결H,0),0)+VLOOKUP("외화환산이익",BS연결,MATCH(AA$1,BS연결H,0),0)-VLOOKUP("외화환산손실",BS연결,MATCH(AA$1,BS연결H,0),0))/100,"") | AB13: =IFERROR((VLOOKUP("외환차익",BS연결,MATCH(AB$1,BS연결H,0),0)-VLOOKUP("외환차손",BS연결,MATCH(AB$1,BS연결H,0),0)+VLOOKUP("외화환산이익",BS연결,MATCH(AB$1,BS연결H,0),0)-VLOOKUP("외화환산손실",BS연결,MATCH(AB$1,BS연결H,0),0))/100,"") | AC13: =변수!AC24 | AD13: =변수!AD24 | AE13: =SUM(AA13:AD13) | AF13: =변수!AF24 | AG13: =변수!AG24 | AH13: =변수!AH24 | AI13: =변수!AI24 | AJ13: =SUM(AF13:AI13) | AK13: =변수!AK24 | AL13: =변수!AL24 | AM13: =변수!AM24 | AN13: =변수!AN24 | AO13: =SUM(AK13:AN13)
A14: 파생상품손익 | B14: 손익 | C14: 억원 | D14: 파생상품손익 | K14: =SUM(G14:J14) | L14: =IFERROR((VLOOKUP("파생상품이익",BS연결,MATCH(L$1,BS연결H,0),0)-VLOOKUP("파생상품손실",BS연결,MATCH(L$1,BS연결H,0),0))/100,"") | M14: =IFERROR((VLOOKUP("파생상품이익",BS연결,MATCH(M$1,BS연결H,0),0)-VLOOKUP("파생상품손실",BS연결,MATCH(M$1,BS연결H,0),0))/100,"") | N14: =IFERROR((VLOOKUP("파생상품이익",BS연결,MATCH(N$1,BS연결H,0),0)-VLOOKUP("파생상품손실",BS연결,MATCH(N$1,BS연결H,0),0))/100,"") | O14: =IFERROR((VLOOKUP("파생상품이익",BS연결,MATCH(O$1,BS연결H,0),0)-VLOOKUP("파생상품손실",BS연결,MATCH(O$1,BS연결H,0),0))/100,"") | P14: =SUM(L14:O14) | U14: =SUM(Q14:T14) | Z14: =SUM(V14:Y14) | AC14: =변수!AC25 | AD14: =변수!AD25 | AE14: =SUM(AA14:AD14) | AF14: =변수!AF25 | AG14: =변수!AG25 | AH14: =변수!AH25 | AI14: =변수!AI25 | AJ14: =SUM(AF14:AI14) | AK14: =변수!AK25 | AL14: =변수!AL25 | AM14: =변수!AM25 | AN14: =변수!AN25 | AO14: =SUM(AK14:AN14)
A15: 기타금융손익 | B15: 손익 | C15: 억원 | D15: 기타금융손익(금융손익 잔차) | K15: =SUM(G15:J15) | L15: =IFERROR(L11-L12-L13-L14,"") | M15: =IFERROR(M11-M12-M13-M14,"") | N15: =IFERROR(N11-N12-N13-N14,"") | O15: =IFERROR(O11-O12-O13-O14,"") | P15: =SUM(L15:O15) | U15: =SUM(Q15:T15) | Z15: =SUM(V15:Y15) | AC15: =변수!AC26 | AD15: =변수!AD26 | AE15: =SUM(AA15:AD15) | AF15: =변수!AF26 | AG15: =변수!AG26 | AH15: =변수!AH26 | AI15: =변수!AI26 | AJ15: =SUM(AF15:AI15) | AK15: =변수!AK26 | AL15: =변수!AL26 | AM15: =변수!AM26 | AN15: =변수!AN26 | AO15: =SUM(AK15:AN15)
A16: 기타영업외손익 | B16: 손익 | C16: 억원 | D16: 기타영업외손익 | E16: =IFERROR(VLOOKUP($D16,BS연결,MATCH(E$1,BS연결H,0),0)/100,"") | G16: =IFERROR(VLOOKUP($D16,BS연결,MATCH(G$1,BS연결H,0),0)/100,"") | H16: =IFERROR(VLOOKUP($D16,BS연결,MATCH(H$1,BS연결H,0),0)/100,"") | I16: =IFERROR(VLOOKUP($D16,BS연결,MATCH(I$1,BS연결H,0),0)/100,"") | J16: =IFERROR(VLOOKUP($D16,BS연결,MATCH(J$1,BS연결H,0),0)/100,"") | K16: =IFERROR(VLOOKUP($D16,BS연결,MATCH(K$1,BS연결H,0),0)/100,"") | L16: =IFERROR(VLOOKUP($D16,BS연결,MATCH(L$1,BS연결H,0),0)/100,"") | M16: =IFERROR(VLOOKUP($D16,BS연결,MATCH(M$1,BS연결H,0),0)/100,"") | N16: =IFERROR(VLOOKUP($D16,BS연결,MATCH(N$1,BS연결H,0),0)/100,"") | ... AB16: =IFERROR(VLOOKUP($D16,BS연결,MATCH(AB$1,BS연결H,0),0)/100,"") | AC16: =변수!AC27 | AD16: =변수!AD27 | AE16: =SUM(AA16:AD16) | AF16: =변수!AF27 | AG16: =변수!AG27 | AH16: =변수!AH27 | AI16: =변수!AI27 | AJ16: =SUM(AF16:AI16) | AK16: =변수!AK27 | AL16: =변수!AL27 | AM16: =변수!AM27 | AN16: =변수!AN27 | AO16: =SUM(AK16:AN16)
A17: 세전이익 | B17: 손익 | C17: 억원 | D17: 법인세비용차감전계속사업이익 | E17: =IFERROR(VLOOKUP($D17,BS연결,MATCH(E$1,BS연결H,0),0)/100,"") | G17: =IFERROR(VLOOKUP($D17,BS연결,MATCH(G$1,BS연결H,0),0)/100,"") | H17: =IFERROR(VLOOKUP($D17,BS연결,MATCH(H$1,BS연결H,0),0)/100,"") | I17: =IFERROR(VLOOKUP($D17,BS연결,MATCH(I$1,BS연결H,0),0)/100,"") | J17: =IFERROR(VLOOKUP($D17,BS연결,MATCH(J$1,BS연결H,0),0)/100,"") | K17: =IFERROR(VLOOKUP($D17,BS연결,MATCH(K$1,BS연결H,0),0)/100,"") | L17: =IFERROR(VLOOKUP($D17,BS연결,MATCH(L$1,BS연결H,0),0)/100,"") | M17: =IFERROR(VLOOKUP($D17,BS연결,MATCH(M$1,BS연결H,0),0)/100,"") | N17: =IFERROR(VLOOKUP($D17,BS연결,MATCH(N$1,BS연결H,0),0)/100,"") | ... AB17: =IFERROR(VLOOKUP($D17,BS연결,MATCH(AB$1,BS연결H,0),0)/100,"") | AC17: =IFERROR(AC9+AC11+AC16,"") | AD17: =IFERROR(AD9+AD11+AD16,"") | AE17: =SUM(AA17:AD17) | AF17: =IFERROR(AF9+AF11+AF16,"") | AG17: =IFERROR(AG9+AG11+AG16,"") | AH17: =IFERROR(AH9+AH11+AH16,"") | AI17: =IFERROR(AI9+AI11+AI16,"") | AJ17: =SUM(AF17:AI17) | AK17: =IFERROR(AK9+AK11+AK16,"") | AL17: =IFERROR(AL9+AL11+AL16,"") | AM17: =IFERROR(AM9+AM11+AM16,"") | AN17: =IFERROR(AN9+AN11+AN16,"") | AO17: =SUM(AK17:AN17)
A18: 법인세비용 | B18: 손익 | C18: 억원 | D18: 법인세비용 | E18: =IFERROR(VLOOKUP($D18,BS연결,MATCH(E$1,BS연결H,0),0)/100,"") | G18: =IFERROR(VLOOKUP($D18,BS연결,MATCH(G$1,BS연결H,0),0)/100,"") | H18: =IFERROR(VLOOKUP($D18,BS연결,MATCH(H$1,BS연결H,0),0)/100,"") | I18: =IFERROR(VLOOKUP($D18,BS연결,MATCH(I$1,BS연결H,0),0)/100,"") | J18: =IFERROR(VLOOKUP($D18,BS연결,MATCH(J$1,BS연결H,0),0)/100,"") | K18: =IFERROR(VLOOKUP($D18,BS연결,MATCH(K$1,BS연결H,0),0)/100,"") | L18: =IFERROR(VLOOKUP($D18,BS연결,MATCH(L$1,BS연결H,0),0)/100,"") | M18: =IFERROR(VLOOKUP($D18,BS연결,MATCH(M$1,BS연결H,0),0)/100,"") | N18: =IFERROR(VLOOKUP($D18,BS연결,MATCH(N$1,BS연결H,0),0)/100,"") | O18: =IFERROR(VLOOKUP($D18,BS연결,MATCH(O$1,BS연결H,0),0)/100,"") | P18: =SUM(L18:O18) | Q18: =IFERROR(VLOOKUP($D18,BS연결,MATCH(Q$1,BS연결H,0),0)/100,"") | R18: =IFERROR(VLOOKUP($D18,BS연결,MATCH(R$1,BS연결H,0),0)/100,"") | S18: =IFERROR(VLOOKUP($D18,BS연결,MATCH(S$1,BS연결H,0),0)/100,"") | T18: =IFERROR(VLOOKUP($D18,BS연결,MATCH(T$1,BS연결H,0),0)/100,"") | U18: =IFERROR(VLOOKUP($D18,BS연결,MATCH(U$1,BS연결H,0),0)/100,"") | V18: =IFERROR(VLOOKUP($D18,BS연결,MATCH(V$1,BS연결H,0),0)/100,"") | W18: =IFERROR(VLOOKUP($D18,BS연결,MATCH(W$1,BS연결H,0),0)/100,"") | X18: =IFERROR(VLOOKUP($D18,BS연결,MATCH(X$1,BS연결H,0),0)/100,"") | ... AB18: =IFERROR(VLOOKUP($D18,BS연결,MATCH(AB$1,BS연결H,0),0)/100,"") | AC18: =IFERROR(MAX(AC17,0)*변수!AC28,"") | AD18: =IFERROR(MAX(AD17,0)*변수!AD28,"") | AE18: =SUM(AA18:AD18) | AF18: =IFERROR(MAX(AF17,0)*변수!AF28,"") | AG18: =IFERROR(MAX(AG17,0)*변수!AG28,"") | AH18: =IFERROR(MAX(AH17,0)*변수!AH28,"") | AI18: =IFERROR(MAX(AI17,0)*변수!AI28,"") | AJ18: =SUM(AF18:AI18) | AK18: =IFERROR(MAX(AK17,0)*변수!AK28,"") | AL18: =IFERROR(MAX(AL17,0)*변수!AL28,"") | AM18: =IFERROR(MAX(AM17,0)*변수!AM28,"") | AN18: =IFERROR(MAX(AN17,0)*변수!AN28,"") | AO18: =SUM(AK18:AN18)
A19: 당기순이익 | B19: 손익 | C19: 억원 | D19: 당기순이익 | E19: =IFERROR(VLOOKUP($D19,BS연결,MATCH(E$1,BS연결H,0),0)/100,"") | G19: =IFERROR(VLOOKUP($D19,BS연결,MATCH(G$1,BS연결H,0),0)/100,"") | H19: =IFERROR(VLOOKUP($D19,BS연결,MATCH(H$1,BS연결H,0),0)/100,"") | I19: =IFERROR(VLOOKUP($D19,BS연결,MATCH(I$1,BS연결H,0),0)/100,"") | J19: =IFERROR(VLOOKUP($D19,BS연결,MATCH(J$1,BS연결H,0),0)/100,"") | K19: =IFERROR(VLOOKUP($D19,BS연결,MATCH(K$1,BS연결H,0),0)/100,"") | L19: =IFERROR(VLOOKUP($D19,BS연결,MATCH(L$1,BS연결H,0),0)/100,"") | M19: =IFERROR(VLOOKUP($D19,BS연결,MATCH(M$1,BS연결H,0),0)/100,"") | N19: =IFERROR(VLOOKUP($D19,BS연결,MATCH(N$1,BS연결H,0),0)/100,"") | ... AB19: =IFERROR(VLOOKUP($D19,BS연결,MATCH(AB$1,BS연결H,0),0)/100,"") | AC19: =IFERROR(AC17-AC18,"") | AD19: =IFERROR(AD17-AD18,"") | AE19: =SUM(AA19:AD19) | AF19: =IFERROR(AF17-AF18,"") | AG19: =IFERROR(AG17-AG18,"") | AH19: =IFERROR(AH17-AH18,"") | AI19: =IFERROR(AI17-AI18,"") | AJ19: =SUM(AF19:AI19) | AK19: =IFERROR(AK17-AK18,"") | AL19: =IFERROR(AL17-AL18,"") | AM19: =IFERROR(AM17-AM18,"") | AN19: =IFERROR(AN17-AN18,"") | AO19: =SUM(AK19:AN19)
A20: 지배주주순이익 | B20: 손익 | C20: 억원 | D20: (지배주주지분)당기순이익 | E20: =IFERROR(VLOOKUP($D20,BS연결,MATCH(E$1,BS연결H,0),0)/100,"") | G20: =IFERROR(VLOOKUP($D20,BS연결,MATCH(G$1,BS연결H,0),0)/100,"") | H20: =IFERROR(VLOOKUP($D20,BS연결,MATCH(H$1,BS연결H,0),0)/100,"") | I20: =IFERROR(VLOOKUP($D20,BS연결,MATCH(I$1,BS연결H,0),0)/100,"") | J20: =IFERROR(VLOOKUP($D20,BS연결,MATCH(J$1,BS연결H,0),0)/100,"") | K20: =IFERROR(VLOOKUP($D20,BS연결,MATCH(K$1,BS연결H,0),0)/100,"") | L20: =IFERROR(VLOOKUP($D20,BS연결,MATCH(L$1,BS연결H,0),0)/100,"") | M20: =IFERROR(VLOOKUP($D20,BS연결,MATCH(M$1,BS연결H,0),0)/100,"") | N20: =IFERROR(VLOOKUP($D20,BS연결,MATCH(N$1,BS연결H,0),0)/100,"") | ... AB20: =IFERROR(VLOOKUP($D20,BS연결,MATCH(AB$1,BS연결H,0),0)/100,"") | AC20: =IFERROR(AC19*변수!AC29,"") | AD20: =IFERROR(AD19*변수!AD29,"") | AE20: =SUM(AA20:AD20) | AF20: =IFERROR(AF19*변수!AF29,"") | AG20: =IFERROR(AG19*변수!AG29,"") | AH20: =IFERROR(AH19*변수!AH29,"") | AI20: =IFERROR(AI19*변수!AI29,"") | AJ20: =SUM(AF20:AI20) | AK20: =IFERROR(AK19*변수!AK29,"") | AL20: =IFERROR(AL19*변수!AL29,"") | AM20: =IFERROR(AM19*변수!AM29,"") | AN20: =IFERROR(AN19*변수!AN29,"") | AO20: =SUM(AK20:AN20)
A21: 자산총계 | B21: 재무상태 | C21: 억원 | D21: 자산총계 | E21: =IFERROR(VLOOKUP($D21,BS연결,MATCH(E$1,BS연결H,0),0)/100,"") | F21: =IFERROR(VLOOKUP($D21,BS연결,MATCH(F$1,BS연결H,0),0)/100,"") | G21: =IFERROR(VLOOKUP($D21,BS연결,MATCH(G$1,BS연결H,0),0)/100,"") | H21: =IFERROR(VLOOKUP($D21,BS연결,MATCH(H$1,BS연결H,0),0)/100,"") | I21: =IFERROR(VLOOKUP($D21,BS연결,MATCH(I$1,BS연결H,0),0)/100,"") | J21: =IFERROR(VLOOKUP($D21,BS연결,MATCH(J$1,BS연결H,0),0)/100,"") | K21: =IFERROR(VLOOKUP($D21,BS연결,MATCH(K$1,BS연결H,0),0)/100,"") | L21: =IFERROR(VLOOKUP($D21,BS연결,MATCH(L$1,BS연결H,0),0)/100,"") | ... AB21: =IFERROR(VLOOKUP($D21,BS연결,MATCH(AB$1,BS연결H,0),0)/100,"") | AC21: =IFERROR(AC22+AC23,"") | AD21: =IFERROR(AD22+AD23,"") | AE21: =AD21 | AF21: =IFERROR(AF22+AF23,"") | AG21: =IFERROR(AG22+AG23,"") | AH21: =IFERROR(AH22+AH23,"") | AI21: =IFERROR(AI22+AI23,"") | AJ21: =AI21 | AK21: =IFERROR(AK22+AK23,"") | AL21: =IFERROR(AL22+AL23,"") | AM21: =IFERROR(AM22+AM23,"") | AN21: =IFERROR(AN22+AN23,"") | AO21: =AN21
A22: 부채총계 | B22: 재무상태 | C22: 억원 | D22: 부채총계 | E22: =IFERROR(VLOOKUP($D22,BS연결,MATCH(E$1,BS연결H,0),0)/100,"") | F22: =IFERROR(VLOOKUP($D22,BS연결,MATCH(F$1,BS연결H,0),0)/100,"") | G22: =IFERROR(VLOOKUP($D22,BS연결,MATCH(G$1,BS연결H,0),0)/100,"") | H22: =IFERROR(VLOOKUP($D22,BS연결,MATCH(H$1,BS연결H,0),0)/100,"") | I22: =IFERROR(VLOOKUP($D22,BS연결,MATCH(I$1,BS연결H,0),0)/100,"") | J22: =IFERROR(VLOOKUP($D22,BS연결,MATCH(J$1,BS연결H,0),0)/100,"") | K22: =IFERROR(VLOOKUP($D22,BS연결,MATCH(K$1,BS연결H,0),0)/100,"") | L22: =IFERROR(VLOOKUP($D22,BS연결,MATCH(L$1,BS연결H,0),0)/100,"") | ... AB22: =IFERROR(VLOOKUP($D22,BS연결,MATCH(AB$1,BS연결H,0),0)/100,"") | AC22: =IFERROR(AB22*(1+변수!AC30),"") | AD22: =IFERROR(AC22*(1+변수!AD30),"") | AE22: =AD22 | AF22: =IFERROR(AD22*(1+변수!AF30),"") | AG22: =IFERROR(AF22*(1+변수!AG30),"") | AH22: =IFERROR(AG22*(1+변수!AH30),"") | AI22: =IFERROR(AH22*(1+변수!AI30),"") | AJ22: =AI22 | AK22: =IFERROR(AI22*(1+변수!AK30),"") | AL22: =IFERROR(AK22*(1+변수!AL30),"") | AM22: =IFERROR(AL22*(1+변수!AM30),"") | AN22: =IFERROR(AM22*(1+변수!AN30),"") | AO22: =AN22
A23: 자본총계 | B23: 재무상태 | C23: 억원 | D23: 자본총계 | E23: =IFERROR(VLOOKUP($D23,BS연결,MATCH(E$1,BS연결H,0),0)/100,"") | F23: =IFERROR(VLOOKUP($D23,BS연결,MATCH(F$1,BS연결H,0),0)/100,"") | G23: =IFERROR(VLOOKUP($D23,BS연결,MATCH(G$1,BS연결H,0),0)/100,"") | H23: =IFERROR(VLOOKUP($D23,BS연결,MATCH(H$1,BS연결H,0),0)/100,"") | I23: =IFERROR(VLOOKUP($D23,BS연결,MATCH(I$1,BS연결H,0),0)/100,"") | J23: =IFERROR(VLOOKUP($D23,BS연결,MATCH(J$1,BS연결H,0),0)/100,"") | K23: =IFERROR(VLOOKUP($D23,BS연결,MATCH(K$1,BS연결H,0),0)/100,"") | L23: =IFERROR(VLOOKUP($D23,BS연결,MATCH(L$1,BS연결H,0),0)/100,"") | ... AB23: =IFERROR(VLOOKUP($D23,BS연결,MATCH(AB$1,BS연결H,0),0)/100,"") | AC23: =IFERROR(AB23+AC19-변수!AC31,"") | AD23: =IFERROR(AC23+AD19-변수!AD31,"") | AE23: =AD23 | AF23: =IFERROR(AD23+AF19-변수!AF31,"") | AG23: =IFERROR(AF23+AG19-변수!AG31,"") | AH23: =IFERROR(AG23+AH19-변수!AH31,"") | AI23: =IFERROR(AH23+AI19-변수!AI31,"") | AJ23: =AI23 | AK23: =IFERROR(AI23+AK19-변수!AK31,"") | AL23: =IFERROR(AK23+AL19-변수!AL31,"") | AM23: =IFERROR(AL23+AM19-변수!AM31,"") | AN23: =IFERROR(AM23+AN19-변수!AN31,"") | AO23: =AN23
A24: 지배주주지분 | B24: 재무상태 | C24: 억원 | D24: 지배주주지분 | E24: =IFERROR(VLOOKUP($D24,BS연결,MATCH(E$1,BS연결H,0),0)/100,"") | F24: =IFERROR(VLOOKUP($D24,BS연결,MATCH(F$1,BS연결H,0),0)/100,"") | G24: =IFERROR(VLOOKUP($D24,BS연결,MATCH(G$1,BS연결H,0),0)/100,"") | H24: =IFERROR(VLOOKUP($D24,BS연결,MATCH(H$1,BS연결H,0),0)/100,"") | I24: =IFERROR(VLOOKUP($D24,BS연결,MATCH(I$1,BS연결H,0),0)/100,"") | J24: =IFERROR(VLOOKUP($D24,BS연결,MATCH(J$1,BS연결H,0),0)/100,"") | K24: =IFERROR(VLOOKUP($D24,BS연결,MATCH(K$1,BS연결H,0),0)/100,"") | L24: =IFERROR(VLOOKUP($D24,BS연결,MATCH(L$1,BS연결H,0),0)/100,"") | ... AB24: =IFERROR(VLOOKUP($D24,BS연결,MATCH(AB$1,BS연결H,0),0)/100,"") | AC24: =IFERROR(AB24+AC20-변수!AC32,"") | AD24: =IFERROR(AC24+AD20-변수!AD32,"") | AE24: =AD24 | AF24: =IFERROR(AD24+AF20-변수!AF32,"") | AG24: =IFERROR(AF24+AG20-변수!AG32,"") | AH24: =IFERROR(AG24+AH20-변수!AH32,"") | AI24: =IFERROR(AH24+AI20-변수!AI32,"") | AJ24: =AI24 | AK24: =IFERROR(AI24+AK20-변수!AK32,"") | AL24: =IFERROR(AK24+AL20-변수!AL32,"") | AM24: =IFERROR(AL24+AM20-변수!AM32,"") | AN24: =IFERROR(AM24+AN20-변수!AN32,"") | AO24: =AN24
A25: 총차입금 | B25: 재무상태 | C25: 억원 | D25: 총차입금 | E25: =IFERROR(VLOOKUP($D25,BS연결,MATCH(E$1,BS연결H,0),0)/100,"") | F25: =IFERROR(VLOOKUP($D25,BS연결,MATCH(F$1,BS연결H,0),0)/100,"") | G25: =IFERROR(VLOOKUP($D25,BS연결,MATCH(G$1,BS연결H,0),0)/100,"") | H25: =IFERROR(VLOOKUP($D25,BS연결,MATCH(H$1,BS연결H,0),0)/100,"") | K25: =J25 | P25: =O25 | U25: =T25 | Z25: =Y25 | AE25: =AD25 | AJ25: =AI25 | AO25: =AN25
A26: 순차입금 | B26: 재무상태 | C26: 억원 | D26: 순차입금 | E26: =IFERROR(VLOOKUP($D26,BS연결,MATCH(E$1,BS연결H,0),0)/100,"") | F26: =IFERROR(VLOOKUP($D26,BS연결,MATCH(F$1,BS연결H,0),0)/100,"") | G26: =IFERROR(VLOOKUP($D26,BS연결,MATCH(G$1,BS연결H,0),0)/100,"") | H26: =IFERROR(VLOOKUP($D26,BS연결,MATCH(H$1,BS연결H,0),0)/100,"") | K26: =J26 | P26: =O26 | U26: =T26 | Z26: =Y26 | AE26: =AD26 | AJ26: =AI26 | AO26: =AN26
A27: 이자발생자산 | B27: 재무상태 | C27: 억원 | D27: 이자발생자산 | E27: =IFERROR(VLOOKUP($D27,BS연결,MATCH(E$1,BS연결H,0),0)/100,"") | F27: =IFERROR(VLOOKUP($D27,BS연결,MATCH(F$1,BS연결H,0),0)/100,"") | G27: =IFERROR(VLOOKUP($D27,BS연결,MATCH(G$1,BS연결H,0),0)/100,"") | H27: =IFERROR(VLOOKUP($D27,BS연결,MATCH(H$1,BS연결H,0),0)/100,"") | I27: =IFERROR(VLOOKUP($D27,BS연결,MATCH(I$1,BS연결H,0),0)/100,"") | J27: =IFERROR(VLOOKUP($D27,BS연결,MATCH(J$1,BS연결H,0),0)/100,"") | K27: =IFERROR(VLOOKUP($D27,BS연결,MATCH(K$1,BS연결H,0),0)/100,"") | L27: =IFERROR(VLOOKUP($D27,BS연결,MATCH(L$1,BS연결H,0),0)/100,"") | ... AB27: =IFERROR(VLOOKUP($D27,BS연결,MATCH(AB$1,BS연결H,0),0)/100,"") | AC27: =IFERROR(AB27*(1+변수!AC35),"") | AD27: =IFERROR(AC27*(1+변수!AD35),"") | AE27: =AD27 | AF27: =IFERROR(AD27*(1+변수!AF35),"") | AG27: =IFERROR(AF27*(1+변수!AG35),"") | AH27: =IFERROR(AG27*(1+변수!AH35),"") | AI27: =IFERROR(AH27*(1+변수!AI35),"") | AJ27: =AI27 | AK27: =IFERROR(AI27*(1+변수!AK35),"") | AL27: =IFERROR(AK27*(1+변수!AL35),"") | AM27: =IFERROR(AL27*(1+변수!AM35),"") | AN27: =IFERROR(AM27*(1+변수!AN35),"") | AO27: =AN27
A28: 현금및현금성자산 | B28: 재무상태 | C28: 억원 | D28: 현금및현금성자산 | E28: =IFERROR(VLOOKUP($D28,BS연결,MATCH(E$1,BS연결H,0),0)/100,"") | F28: =IFERROR(VLOOKUP($D28,BS연결,MATCH(F$1,BS연결H,0),0)/100,"") | G28: =IFERROR(VLOOKUP($D28,BS연결,MATCH(G$1,BS연결H,0),0)/100,"") | H28: =IFERROR(VLOOKUP($D28,BS연결,MATCH(H$1,BS연결H,0),0)/100,"") | I28: =IFERROR(VLOOKUP($D28,BS연결,MATCH(I$1,BS연결H,0),0)/100,"") | J28: =IFERROR(VLOOKUP($D28,BS연결,MATCH(J$1,BS연결H,0),0)/100,"") | K28: =IFERROR(VLOOKUP($D28,BS연결,MATCH(K$1,BS연결H,0),0)/100,"") | L28: =IFERROR(VLOOKUP($D28,BS연결,MATCH(L$1,BS연결H,0),0)/100,"") | ... AB28: =IFERROR(VLOOKUP($D28,BS연결,MATCH(AB$1,BS연결H,0),0)/100,"") | AE28: =AD28 | AJ28: =AI28 | AO28: =AN28
A29: CAPEX | B29: 현금흐름 | C29: 억원 | D29: CAPEX | E29: =IFERROR(VLOOKUP($D29,BS연결,MATCH(E$1,BS연결H,0),0)/100,"") | G29: =IFERROR(VLOOKUP($D29,BS연결,MATCH(G$1,BS연결H,0),0)/100,"") | H29: =IFERROR(VLOOKUP($D29,BS연결,MATCH(H$1,BS연결H,0),0)/100,"") | I29: =IFERROR(VLOOKUP($D29,BS연결,MATCH(I$1,BS연결H,0),0)/100,"") | J29: =IFERROR(VLOOKUP($D29,BS연결,MATCH(J$1,BS연결H,0),0)/100,"") | K29: =IFERROR(VLOOKUP($D29,BS연결,MATCH(K$1,BS연결H,0),0)/100,"") | L29: =IFERROR(VLOOKUP($D29,BS연결,MATCH(L$1,BS연결H,0),0)/100,"") | M29: =IFERROR(VLOOKUP($D29,BS연결,MATCH(M$1,BS연결H,0),0)/100,"") | N29: =IFERROR(VLOOKUP($D29,BS연결,MATCH(N$1,BS연결H,0),0)/100,"") | ... AB29: =IFERROR(VLOOKUP($D29,BS연결,MATCH(AB$1,BS연결H,0),0)/100,"") | AC29: =IFERROR(X29*(1+변수!AC37),"") | AD29: =IFERROR(Y29*(1+변수!AD37),"") | AE29: =SUM(AA29:AD29) | AF29: =IFERROR(AA29*(1+변수!AF37),"") | AG29: =IFERROR(AB29*(1+변수!AG37),"") | AH29: =IFERROR(AC29*(1+변수!AH37),"") | AI29: =IFERROR(AD29*(1+변수!AI37),"") | AJ29: =SUM(AF29:AI29) | AK29: =IFERROR(AF29*(1+변수!AK37),"") | AL29: =IFERROR(AG29*(1+변수!AL37),"") | AM29: =IFERROR(AH29*(1+변수!AM37),"") | AN29: =IFERROR(AI29*(1+변수!AN37),"") | AO29: =SUM(AK29:AN29)
A30: 영업활동현금흐름 | B30: 현금흐름 | C30: 억원 | D30: 영업활동으로인한현금흐름 | E30: =IFERROR(VLOOKUP($D30,BS연결,MATCH(E$1,BS연결H,0),0)/100,"") | G30: =IFERROR(VLOOKUP($D30,BS연결,MATCH(G$1,BS연결H,0),0)/100,"") | H30: =IFERROR(VLOOKUP($D30,BS연결,MATCH(H$1,BS연결H,0),0)/100,"") | I30: =IFERROR(VLOOKUP($D30,BS연결,MATCH(I$1,BS연결H,0),0)/100,"") | J30: =IFERROR(VLOOKUP($D30,BS연결,MATCH(J$1,BS연결H,0),0)/100,"") | K30: =IFERROR(VLOOKUP($D30,BS연결,MATCH(K$1,BS연결H,0),0)/100,"") | L30: =IFERROR(VLOOKUP($D30,BS연결,MATCH(L$1,BS연결H,0),0)/100,"") | M30: =IFERROR(VLOOKUP($D30,BS연결,MATCH(M$1,BS연결H,0),0)/100,"") | N30: =IFERROR(VLOOKUP($D30,BS연결,MATCH(N$1,BS연결H,0),0)/100,"") | ... AB30: =IFERROR(VLOOKUP($D30,BS연결,MATCH(AB$1,BS연결H,0),0)/100,"") | AE30: =SUM(AA30:AD30) | AJ30: =SUM(AF30:AI30) | AO30: =SUM(AK30:AN30)
A31: 주식수 | B31: 주당 | C31: 백만주 | D31: 유통주식수 | E31: 25.867 | F31: =E31 | G31: 25.867 | H31: 25.867 | I31: 25.867 | J31: 25.867 | K31: =J31 | L31: 25.867 | M31: 25.867 | N31: 25.867 | O31: 25.867 | P31: =O31 | Q31: 25.867 | R31: 25.867 | S31: 25.867 | T31: 25.867 | U31: =T31 | V31: 25.867 | W31: 25.867 | X31: 25.867 | Y31: 25.867 | Z31: =Y31 | AA31: 25.867 | AB31: 25.684 | AC31: =IFERROR(AB31*(1+변수!AC39),"") | AD31: =IFERROR(AC31*(1+변수!AD39),"") | AE31: =AD31 | AF31: =IFERROR(AD31*(1+변수!AF39),"") | AG31: =IFERROR(AF31*(1+변수!AG39),"") | AH31: =IFERROR(AG31*(1+변수!AH39),"") | AI31: =IFERROR(AH31*(1+변수!AI39),"") | AJ31: =AI31 | AK31: =IFERROR(AI31*(1+변수!AK39),"") | AL31: =IFERROR(AK31*(1+변수!AL39),"") | AM31: =IFERROR(AL31*(1+변수!AM39),"") | AN31: =IFERROR(AM31*(1+변수!AN39),"") | AO31: =AN31
A32: EPS | B32: 주당 | C32: 원 | D32: EPS | E32: =IFERROR(E20*100/E31,"") | G32: =IFERROR(G20*100/G31,"") | H32: =IFERROR(H20*100/H31,"") | I32: =IFERROR(I20*100/I31,"") | J32: =IFERROR(J20*100/J31,"") | K32: =SUM(G32:J32) | L32: =IFERROR(L20*100/L31,"") | M32: =IFERROR(M20*100/M31,"") | N32: =IFERROR(N20*100/N31,"") | O32: =IFERROR(O20*100/O31,"") | P32: =SUM(L32:O32) | Q32: =IFERROR(Q20*100/Q31,"") | R32: =IFERROR(R20*100/R31,"") | S32: =IFERROR(S20*100/S31,"") | T32: =IFERROR(T20*100/T31,"") | U32: =SUM(Q32:T32) | V32: =IFERROR(V20*100/V31,"") | W32: =IFERROR(W20*100/W31,"") | X32: =IFERROR(X20*100/X31,"") | Y32: =IFERROR(Y20*100/Y31,"") | Z32: =SUM(V32:Y32) | AA32: =IFERROR(AA20*100/AA31,"") | AB32: =IFERROR(AB20*100/AB31,"") | AC32: =IFERROR(AC20*100/AC31,"") | AD32: =IFERROR(AD20*100/AD31,"") | AE32: =SUM(AA32:AD32) | AF32: =IFERROR(AF20*100/AF31,"") | AG32: =IFERROR(AG20*100/AG31,"") | AH32: =IFERROR(AH20*100/AH31,"") | AI32: =IFERROR(AI20*100/AI31,"") | AJ32: =SUM(AF32:AI32) | AK32: =IFERROR(AK20*100/AK31,"") | AL32: =IFERROR(AL20*100/AL31,"") | AM32: =IFERROR(AM20*100/AM31,"") | AN32: =IFERROR(AN20*100/AN31,"") | AO32: =SUM(AK32:AN32)
A33: 조정EPS | B33: 주당 | C33: 원 | D33: 조정 EPS(일회성 의심 분기의 초과 비영업손익 세후 차감 — 모델 추정) | E33: =IFERROR(E32,"") | G33: =IFERROR(G32,"") | H33: =IFERROR(H32,"") | I33: =IFERROR(I32,"") | J33: =IFERROR(J32,"") | K33: =SUM(G33:J33) | L33: =IFERROR(L32,"") | M33: =IFERROR(M32,"") | N33: =IFERROR(N32,"") | O33: =IFERROR(O32,"") | P33: =SUM(L33:O33) | Q33: =IFERROR(Q32,"") | R33: =IFERROR(R32,"") | S33: =IFERROR(S32,"") | T33: =IFERROR(T32,"") | U33: =SUM(Q33:T33) | V33: =IFERROR(V32,"") | W33: =IFERROR(W32,"") | X33: =IFERROR(X32,"") | Y33: =IFERROR(Y32,"") | Z33: =SUM(V33:Y33) | AA33: =IFERROR(AA32,"") | AB33: =IFERROR((AB20-(588.5)*(0.8544))*100/AB31,"") | AC33: =IFERROR(AC32,"") | AD33: =IFERROR(AD32,"") | AE33: =SUM(AA33:AD33) | AF33: =IFERROR(AF32,"") | AG33: =IFERROR(AG32,"") | AH33: =IFERROR(AH32,"") | AI33: =IFERROR(AI32,"") | AJ33: =SUM(AF33:AI33) | AK33: =IFERROR(AK32,"") | AL33: =IFERROR(AL32,"") | AM33: =IFERROR(AM32,"") | AN33: =IFERROR(AN32,"") | AO33: =SUM(AK33:AN33)
A34: BPS | B34: 주당 | C34: 원 | D34: BPS | E34: =IFERROR(E24*100/E31,"") | F34: =E34 | G34: =IFERROR(G24*100/G31,"") | H34: =IFERROR(H24*100/H31,"") | I34: =IFERROR(I24*100/I31,"") | J34: =IFERROR(J24*100/J31,"") | K34: =J34 | L34: =IFERROR(L24*100/L31,"") | M34: =IFERROR(M24*100/M31,"") | N34: =IFERROR(N24*100/N31,"") | O34: =IFERROR(O24*100/O31,"") | P34: =O34 | Q34: =IFERROR(Q24*100/Q31,"") | R34: =IFERROR(R24*100/R31,"") | S34: =IFERROR(S24*100/S31,"") | T34: =IFERROR(T24*100/T31,"") | U34: =T34 | V34: =IFERROR(V24*100/V31,"") | W34: =IFERROR(W24*100/W31,"") | X34: =IFERROR(X24*100/X31,"") | Y34: =IFERROR(Y24*100/Y31,"") | Z34: =Y34 | AA34: =IFERROR(AA24*100/AA31,"") | AB34: =IFERROR(AB24*100/AB31,"") | AC34: =IFERROR(AC24*100/AC31,"") | AD34: =IFERROR(AD24*100/AD31,"") | AE34: =AD34 | AF34: =IFERROR(AF24*100/AF31,"") | AG34: =IFERROR(AG24*100/AG31,"") | AH34: =IFERROR(AH24*100/AH31,"") | AI34: =IFERROR(AI24*100/AI31,"") | AJ34: =AI34 | AK34: =IFERROR(AK24*100/AK31,"") | AL34: =IFERROR(AL24*100/AL31,"") | AM34: =IFERROR(AM24*100/AM31,"") | AN34: =IFERROR(AN24*100/AN31,"") | AO34: =AN34
A35: DPS | B35: 주당 | C35: 원 | D35: DPS(보통주) | E35: 100 | F35: 100 | J35: 170 | K35: =SUM(G35:J35) | O35: 170 | P35: =SUM(L35:O35) | T35: 250 | U35: =SUM(Q35:T35) | Y35: 535 | Z35: =SUM(V35:Y35) | AD35: =변수!AD40 | AE35: =SUM(AA35:AD35) | AI35: =변수!AI40 | AJ35: =SUM(AF35:AI35) | AN35: =변수!AN40 | AO35: =SUM(AK35:AN35)
A36: PER | B36: 주당 | C36: 배 | D36: PER | F36: =E36 | I36: =IFERROR(변수!I18/(E32+G32+H32+I32),"") | J36: =IFERROR(변수!J18/(G32+H32+I32+J32),"") | K36: =J36 | L36: =IFERROR(변수!L18/(H32+I32+J32+L32),"") | M36: =IFERROR(변수!M18/(I32+J32+L32+M32),"") | N36: =IFERROR(변수!N18/(J32+L32+M32+N32),"") | O36: =IFERROR(변수!O18/(L32+M32+N32+O32),"") | P36: =O36 | Q36: =IFERROR(변수!Q18/(M32+N32+O32+Q32),"") | R36: =IFERROR(변수!R18/(N32+O32+Q32+R32),"") | S36: =IFERROR(변수!S18/(O32+Q32+R32+S32),"") | T36: =IFERROR(변수!T18/(Q32+R32+S32+T32),"") | U36: =T36 | V36: =IFERROR(변수!V18/(R32+S32+T32+V32),"") | W36: =IFERROR(변수!W18/(S32+T32+V32+W32),"") | X36: =IFERROR(변수!X18/(T32+V32+W32+X32),"") | Y36: =IFERROR(변수!Y18/(V32+W32+X32+Y32),"") | Z36: =Y36 | AA36: =IFERROR(변수!AA18/(W32+X32+Y32+AA32),"") | AB36: =IFERROR(변수!AB18/(X32+Y32+AA32+AB32),"") | AC36: =IFERROR(변수!$D$43/(Y32+AA32+AB32+AC32),"") | AD36: =IFERROR(변수!$D$43/(AA32+AB32+AC32+AD32),"") | AE36: =AD36 | AF36: =IFERROR(변수!$D$43/(AB32+AC32+AD32+AF32),"") | AG36: =IFERROR(변수!$D$43/(AC32+AD32+AF32+AG32),"") | AH36: =IFERROR(변수!$D$43/(AD32+AF32+AG32+AH32),"") | AI36: =IFERROR(변수!$D$43/(AF32+AG32+AH32+AI32),"") | AJ36: =AI36 | AK36: =IFERROR(변수!$D$43/(AG32+AH32+AI32+AK32),"") | AL36: =IFERROR(변수!$D$43/(AH32+AI32+AK32+AL32),"") | AM36: =IFERROR(변수!$D$43/(AI32+AK32+AL32+AM32),"") | AN36: =IFERROR(변수!$D$43/(AK32+AL32+AM32+AN32),"") | AO36: =AN36
A37: PBR | B37: 주당 | C37: 배 | D37: PBR | E37: =IFERROR(변수!E18/E34,"") | F37: =E37 | G37: =IFERROR(변수!G18/G34,"") | H37: =IFERROR(변수!H18/H34,"") | I37: =IFERROR(변수!I18/I34,"") | J37: =IFERROR(변수!J18/J34,"") | K37: =J37 | L37: =IFERROR(변수!L18/L34,"") | M37: =IFERROR(변수!M18/M34,"") | N37: =IFERROR(변수!N18/N34,"") | O37: =IFERROR(변수!O18/O34,"") | P37: =O37 | Q37: =IFERROR(변수!Q18/Q34,"") | R37: =IFERROR(변수!R18/R34,"") | S37: =IFERROR(변수!S18/S34,"") | T37: =IFERROR(변수!T18/T34,"") | U37: =T37 | V37: =IFERROR(변수!V18/V34,"") | W37: =IFERROR(변수!W18/W34,"") | X37: =IFERROR(변수!X18/X34,"") | Y37: =IFERROR(변수!Y18/Y34,"") | Z37: =Y37 | AA37: =IFERROR(변수!AA18/AA34,"") | AB37: =IFERROR(변수!AB18/AB34,"") | AC37: =IFERROR(변수!$D$43/AC34,"") | AD37: =IFERROR(변수!$D$43/AD34,"") | AE37: =AD37 | AF37: =IFERROR(변수!$D$43/AF34,"") | AG37: =IFERROR(변수!$D$43/AG34,"") | AH37: =IFERROR(변수!$D$43/AH34,"") | AI37: =IFERROR(변수!$D$43/AI34,"") | AJ37: =AI37 | AK37: =IFERROR(변수!$D$43/AK34,"") | AL37: =IFERROR(변수!$D$43/AL34,"") | AM37: =IFERROR(변수!$D$43/AM34,"") | AN37: =IFERROR(변수!$D$43/AN34,"") | AO37: =AN37
A38: 매출전사 | B38: 사업부 | C38: 억원 | D38: 매출 전사(부문 미분리) | E38: 458.83 | G38: 490.65 | H38: 564.89 | I38: 679.35 | J38: 762.54 | K38: =SUM(G38:J38) | L38: 839.13 | M38: 822.24 | N38: 745.9 | O38: 713.4 | P38: =SUM(L38:O38) | Q38: 733.65 | R38: 655.38 | S38: 617.53 | T38: 661.53 | U38: =SUM(Q38:T38) | V38: 626.35 | W38: 723.16 | X38: 814.15 | Y38: 806 | Z38: =SUM(V38:Y38) | AA38: 822.75 | AB38: 837.46 | AC38: =IFERROR(AC5,"") | AD38: =IFERROR(AD5,"") | AE38: =SUM(AA38:AD38) | AF38: =IFERROR(AF5,"") | AG38: =IFERROR(AG5,"") | AH38: =IFERROR(AH5,"") | AI38: =IFERROR(AI5,"") | AJ38: =SUM(AF38:AI38) | AK38: =IFERROR(AK5,"") | AL38: =IFERROR(AL5,"") | AM38: =IFERROR(AM5,"") | AN38: =IFERROR(AN5,"") | AO38: =SUM(AK38:AN38)
A39: OP전사 | B39: 사업부 | C39: 억원 | D39: OP 전사(부문 미분리) | E39: 29.21 | G39: 65.69 | H39: 119.05 | I39: 103.83 | J39: 164.93 | K39: =SUM(G39:J39) | L39: 199.25 | M39: 180.67 | N39: 122.38 | O39: 74.93 | P39: =SUM(L39:O39) | Q39: 128.54 | R39: 98.17 | S39: 75.78 | T39: 96.24 | U39: =SUM(Q39:T39) | V39: 74.04 | W39: 76.57 | X39: 115.69 | Y39: 121.05 | Z39: =SUM(V39:Y39) | AA39: 93.5 | AB39: 72.12 | AC39: =IFERROR(AC9,"") | AD39: =IFERROR(AD9,"") | AE39: =SUM(AA39:AD39) | AF39: =IFERROR(AF9,"") | AG39: =IFERROR(AG9,"") | AH39: =IFERROR(AH9,"") | AI39: =IFERROR(AI9,"") | AJ39: =SUM(AF39:AI39) | AK39: =IFERROR(AK9,"") | AL39: =IFERROR(AL9,"") | AM39: =IFERROR(AM9,"") | AN39: =IFERROR(AN9,"") | AO39: =SUM(AK39:AN39)
B40: 비율(참고)
A41: NPM | C41: % | D41: 지배주주순이익 / 매출액 | E41: =IFERROR(E20/E5,"") | F41: =IFERROR(F20/F5,"") | G41: =IFERROR(G20/G5,"") | H41: =IFERROR(H20/H5,"") | I41: =IFERROR(I20/I5,"") | J41: =IFERROR(J20/J5,"") | K41: =IFERROR(K20/K5,"") | L41: =IFERROR(L20/L5,"") | ... AO41: =IFERROR(AO20/AO5,"")
A42: 매출원가율 | C42: % | D42: 매출원가 / 매출액 | E42: =IFERROR(E6/E5,"") | F42: =IFERROR(F6/F5,"") | G42: =IFERROR(G6/G5,"") | H42: =IFERROR(H6/H5,"") | I42: =IFERROR(I6/I5,"") | J42: =IFERROR(J6/J5,"") | K42: =IFERROR(K6/K5,"") | L42: =IFERROR(L6/L5,"") | ... AO42: =IFERROR(AO6/AO5,"")
A43: 판관비율 | C43: % | D43: 판관비 / 매출액 | E43: =IFERROR(E8/E5,"") | F43: =IFERROR(F8/F5,"") | G43: =IFERROR(G8/G5,"") | H43: =IFERROR(H8/H5,"") | I43: =IFERROR(I8/I5,"") | J43: =IFERROR(J8/J5,"") | K43: =IFERROR(K8/K5,"") | L43: =IFERROR(L8/L5,"") | ... AO43: =IFERROR(AO8/AO5,"")

Sheet 분기
C1: 이름: 분기H — subQ 를 이름으로 VLOOKUP(억원) | E1: 4Q21 | F1: 1Q22 | G1: 2Q22 | H1: 3Q22 | I1: 4Q22 | J1: 1Q23 | K1: 2Q23 | L1: 3Q23 | M1: 4Q23 | N1: 1Q24 | O1: 2Q24 | P1: 3Q24 | Q1: 4Q24 | R1: 1Q25 | S1: 2Q25 | T1: 3Q25 | U1: 4Q25 | V1: 1Q26 | W1: 2Q26 | X1: 3Q26 | Y1: 4Q26 | Z1: 1Q27 | AA1: 2Q27 | AB1: 3Q27 | AC1: 4Q27 | AD1: 1Q28 | AE1: 2Q28 | AF1: 3Q28 | AG1: 4Q28
C2: 종가: | D2: =변수!D43
C3: 기준일: | D3: 20261008 | E3: 1 | F3: 2 | G3: 3 | H3: 4 | I3: 5 | J3: 6 | K3: 7 | L3: 8 | M3: 9 | N3: 10 | O3: 11 | P3: 12 | Q3: 13 | R3: 14 | S3: 15 | T3: 16 | U3: 17 | V3: 18 | W3: 19 | X3: 20 | Y3: 21 | Z3: 22 | AA3: 23 | AB3: 24 | AC3: 25 | AD3: 26 | AE3: 27 | AF3: 28 | AG3: 29
E4: 2021.12 | F4: 2022.03 | G4: 2022.06 | H4: 2022.09 | I4: 2022.12 | J4: 2023.03 | K4: 2023.06 | L4: 2023.09 | M4: 2023.12 | N4: 2024.03 | O4: 2024.06 | P4: 2024.09 | Q4: 2024.12 | R4: 2025.03 | S4: 2025.06 | T4: 2025.09 | U4: 2025.12 | V4: 2026.03 | W4: 2026.06 | X4: 2026.09 | Y4: 2026.12 | Z4: 2027.03 | AA4: 2027.06 | AB4: 2027.09 | AC4: 2027.12 | AD4: 2028.03 | AE4: 2028.06 | AF4: 2028.09 | AG4: 2028.12
A5: 매출액 | D5: 매출액 | E5: =IFERROR(VLOOKUP($A5,subQ,MATCH(E$1,SUBQH,0),0),"") | F5: =IFERROR(VLOOKUP($A5,subQ,MATCH(F$1,SUBQH,0),0),"") | G5: =IFERROR(VLOOKUP($A5,subQ,MATCH(G$1,SUBQH,0),0),"") | H5: =IFERROR(VLOOKUP($A5,subQ,MATCH(H$1,SUBQH,0),0),"") | I5: =IFERROR(VLOOKUP($A5,subQ,MATCH(I$1,SUBQH,0),0),"") | J5: =IFERROR(VLOOKUP($A5,subQ,MATCH(J$1,SUBQH,0),0),"") | K5: =IFERROR(VLOOKUP($A5,subQ,MATCH(K$1,SUBQH,0),0),"") | L5: =IFERROR(VLOOKUP($A5,subQ,MATCH(L$1,SUBQH,0),0),"") | ... AG5: =IFERROR(VLOOKUP($A5,subQ,MATCH(AG$1,SUBQH,0),0),"")
A6: 매출원가 | D6: 매출원가 | E6: =IFERROR(VLOOKUP($A6,subQ,MATCH(E$1,SUBQH,0),0),"") | F6: =IFERROR(VLOOKUP($A6,subQ,MATCH(F$1,SUBQH,0),0),"") | G6: =IFERROR(VLOOKUP($A6,subQ,MATCH(G$1,SUBQH,0),0),"") | H6: =IFERROR(VLOOKUP($A6,subQ,MATCH(H$1,SUBQH,0),0),"") | I6: =IFERROR(VLOOKUP($A6,subQ,MATCH(I$1,SUBQH,0),0),"") | J6: =IFERROR(VLOOKUP($A6,subQ,MATCH(J$1,SUBQH,0),0),"") | K6: =IFERROR(VLOOKUP($A6,subQ,MATCH(K$1,SUBQH,0),0),"") | L6: =IFERROR(VLOOKUP($A6,subQ,MATCH(L$1,SUBQH,0),0),"") | ... AG6: =IFERROR(VLOOKUP($A6,subQ,MATCH(AG$1,SUBQH,0),0),"")
A7: 매출총이익 | D7: 매출총이익 | E7: =IFERROR(VLOOKUP($A7,subQ,MATCH(E$1,SUBQH,0),0),"") | F7: =IFERROR(VLOOKUP($A7,subQ,MATCH(F$1,SUBQH,0),0),"") | G7: =IFERROR(VLOOKUP($A7,subQ,MATCH(G$1,SUBQH,0),0),"") | H7: =IFERROR(VLOOKUP($A7,subQ,MATCH(H$1,SUBQH,0),0),"") | I7: =IFERROR(VLOOKUP($A7,subQ,MATCH(I$1,SUBQH,0),0),"") | J7: =IFERROR(VLOOKUP($A7,subQ,MATCH(J$1,SUBQH,0),0),"") | K7: =IFERROR(VLOOKUP($A7,subQ,MATCH(K$1,SUBQH,0),0),"") | L7: =IFERROR(VLOOKUP($A7,subQ,MATCH(L$1,SUBQH,0),0),"") | ... AG7: =IFERROR(VLOOKUP($A7,subQ,MATCH(AG$1,SUBQH,0),0),"")
A8: 판관비 | D8: 판매비와관리비 | E8: =IFERROR(VLOOKUP($A8,subQ,MATCH(E$1,SUBQH,0),0),"") | F8: =IFERROR(VLOOKUP($A8,subQ,MATCH(F$1,SUBQH,0),0),"") | G8: =IFERROR(VLOOKUP($A8,subQ,MATCH(G$1,SUBQH,0),0),"") | H8: =IFERROR(VLOOKUP($A8,subQ,MATCH(H$1,SUBQH,0),0),"") | I8: =IFERROR(VLOOKUP($A8,subQ,MATCH(I$1,SUBQH,0),0),"") | J8: =IFERROR(VLOOKUP($A8,subQ,MATCH(J$1,SUBQH,0),0),"") | K8: =IFERROR(VLOOKUP($A8,subQ,MATCH(K$1,SUBQH,0),0),"") | L8: =IFERROR(VLOOKUP($A8,subQ,MATCH(L$1,SUBQH,0),0),"") | ... AG8: =IFERROR(VLOOKUP($A8,subQ,MATCH(AG$1,SUBQH,0),0),"")
A9: 영업이익 | D9: 영업이익 | E9: =IFERROR(VLOOKUP($A9,subQ,MATCH(E$1,SUBQH,0),0),"") | F9: =IFERROR(VLOOKUP($A9,subQ,MATCH(F$1,SUBQH,0),0),"") | G9: =IFERROR(VLOOKUP($A9,subQ,MATCH(G$1,SUBQH,0),0),"") | H9: =IFERROR(VLOOKUP($A9,subQ,MATCH(H$1,SUBQH,0),0),"") | I9: =IFERROR(VLOOKUP($A9,subQ,MATCH(I$1,SUBQH,0),0),"") | J9: =IFERROR(VLOOKUP($A9,subQ,MATCH(J$1,SUBQH,0),0),"") | K9: =IFERROR(VLOOKUP($A9,subQ,MATCH(K$1,SUBQH,0),0),"") | L9: =IFERROR(VLOOKUP($A9,subQ,MATCH(L$1,SUBQH,0),0),"") | ... AG9: =IFERROR(VLOOKUP($A9,subQ,MATCH(AG$1,SUBQH,0),0),"")
A10: OPM | D10: 영업이익률 | E10: =IFERROR(VLOOKUP($A10,subQ,MATCH(E$1,SUBQH,0),0),"") | F10: =IFERROR(VLOOKUP($A10,subQ,MATCH(F$1,SUBQH,0),0),"") | G10: =IFERROR(VLOOKUP($A10,subQ,MATCH(G$1,SUBQH,0),0),"") | H10: =IFERROR(VLOOKUP($A10,subQ,MATCH(H$1,SUBQH,0),0),"") | I10: =IFERROR(VLOOKUP($A10,subQ,MATCH(I$1,SUBQH,0),0),"") | J10: =IFERROR(VLOOKUP($A10,subQ,MATCH(J$1,SUBQH,0),0),"") | K10: =IFERROR(VLOOKUP($A10,subQ,MATCH(K$1,SUBQH,0),0),"") | L10: =IFERROR(VLOOKUP($A10,subQ,MATCH(L$1,SUBQH,0),0),"") | ... AG10: =IFERROR(VLOOKUP($A10,subQ,MATCH(AG$1,SUBQH,0),0),"")
A11: 금융손익 | D11: 금융손익(이자·환 포함) | E11: =IFERROR(VLOOKUP($A11,subQ,MATCH(E$1,SUBQH,0),0),"") | F11: =IFERROR(VLOOKUP($A11,subQ,MATCH(F$1,SUBQH,0),0),"") | G11: =IFERROR(VLOOKUP($A11,subQ,MATCH(G$1,SUBQH,0),0),"") | H11: =IFERROR(VLOOKUP($A11,subQ,MATCH(H$1,SUBQH,0),0),"") | I11: =IFERROR(VLOOKUP($A11,subQ,MATCH(I$1,SUBQH,0),0),"") | J11: =IFERROR(VLOOKUP($A11,subQ,MATCH(J$1,SUBQH,0),0),"") | K11: =IFERROR(VLOOKUP($A11,subQ,MATCH(K$1,SUBQH,0),0),"") | L11: =IFERROR(VLOOKUP($A11,subQ,MATCH(L$1,SUBQH,0),0),"") | ... AG11: =IFERROR(VLOOKUP($A11,subQ,MATCH(AG$1,SUBQH,0),0),"")
A12: 이자손익 | D12: 이자손익(이자수익 − 이자비용) | E12: =IFERROR(VLOOKUP($A12,subQ,MATCH(E$1,SUBQH,0),0),"") | F12: =IFERROR(VLOOKUP($A12,subQ,MATCH(F$1,SUBQH,0),0),"") | G12: =IFERROR(VLOOKUP($A12,subQ,MATCH(G$1,SUBQH,0),0),"") | H12: =IFERROR(VLOOKUP($A12,subQ,MATCH(H$1,SUBQH,0),0),"") | I12: =IFERROR(VLOOKUP($A12,subQ,MATCH(I$1,SUBQH,0),0),"") | J12: =IFERROR(VLOOKUP($A12,subQ,MATCH(J$1,SUBQH,0),0),"") | K12: =IFERROR(VLOOKUP($A12,subQ,MATCH(K$1,SUBQH,0),0),"") | L12: =IFERROR(VLOOKUP($A12,subQ,MATCH(L$1,SUBQH,0),0),"") | ... AG12: =IFERROR(VLOOKUP($A12,subQ,MATCH(AG$1,SUBQH,0),0),"")
A13: 외환손익 | D13: 외환손익(실적만; 추정 환효과는 환관련손익) | E13: =IFERROR(VLOOKUP($A13,subQ,MATCH(E$1,SUBQH,0),0),"") | F13: =IFERROR(VLOOKUP($A13,subQ,MATCH(F$1,SUBQH,0),0),"") | G13: =IFERROR(VLOOKUP($A13,subQ,MATCH(G$1,SUBQH,0),0),"") | H13: =IFERROR(VLOOKUP($A13,subQ,MATCH(H$1,SUBQH,0),0),"") | I13: =IFERROR(VLOOKUP($A13,subQ,MATCH(I$1,SUBQH,0),0),"") | J13: =IFERROR(VLOOKUP($A13,subQ,MATCH(J$1,SUBQH,0),0),"") | K13: =IFERROR(VLOOKUP($A13,subQ,MATCH(K$1,SUBQH,0),0),"") | L13: =IFERROR(VLOOKUP($A13,subQ,MATCH(L$1,SUBQH,0),0),"") | ... AG13: =IFERROR(VLOOKUP($A13,subQ,MATCH(AG$1,SUBQH,0),0),"")
A14: 파생상품손익 | D14: 파생상품손익 | E14: =IFERROR(VLOOKUP($A14,subQ,MATCH(E$1,SUBQH,0),0),"") | F14: =IFERROR(VLOOKUP($A14,subQ,MATCH(F$1,SUBQH,0),0),"") | G14: =IFERROR(VLOOKUP($A14,subQ,MATCH(G$1,SUBQH,0),0),"") | H14: =IFERROR(VLOOKUP($A14,subQ,MATCH(H$1,SUBQH,0),0),"") | I14: =IFERROR(VLOOKUP($A14,subQ,MATCH(I$1,SUBQH,0),0),"") | J14: =IFERROR(VLOOKUP($A14,subQ,MATCH(J$1,SUBQH,0),0),"") | K14: =IFERROR(VLOOKUP($A14,subQ,MATCH(K$1,SUBQH,0),0),"") | L14: =IFERROR(VLOOKUP($A14,subQ,MATCH(L$1,SUBQH,0),0),"") | ... AG14: =IFERROR(VLOOKUP($A14,subQ,MATCH(AG$1,SUBQH,0),0),"")
A15: 기타금융손익 | D15: 기타금융손익(금융손익 잔차) | E15: =IFERROR(VLOOKUP($A15,subQ,MATCH(E$1,SUBQH,0),0),"") | F15: =IFERROR(VLOOKUP($A15,subQ,MATCH(F$1,SUBQH,0),0),"") | G15: =IFERROR(VLOOKUP($A15,subQ,MATCH(G$1,SUBQH,0),0),"") | H15: =IFERROR(VLOOKUP($A15,subQ,MATCH(H$1,SUBQH,0),0),"") | I15: =IFERROR(VLOOKUP($A15,subQ,MATCH(I$1,SUBQH,0),0),"") | J15: =IFERROR(VLOOKUP($A15,subQ,MATCH(J$1,SUBQH,0),0),"") | K15: =IFERROR(VLOOKUP($A15,subQ,MATCH(K$1,SUBQH,0),0),"") | L15: =IFERROR(VLOOKUP($A15,subQ,MATCH(L$1,SUBQH,0),0),"") | ... AG15: =IFERROR(VLOOKUP($A15,subQ,MATCH(AG$1,SUBQH,0),0),"")
A16: 기타영업외손익 | D16: 기타영업외손익 | E16: =IFERROR(VLOOKUP($A16,subQ,MATCH(E$1,SUBQH,0),0),"") | F16: =IFERROR(VLOOKUP($A16,subQ,MATCH(F$1,SUBQH,0),0),"") | G16: =IFERROR(VLOOKUP($A16,subQ,MATCH(G$1,SUBQH,0),0),"") | H16: =IFERROR(VLOOKUP($A16,subQ,MATCH(H$1,SUBQH,0),0),"") | I16: =IFERROR(VLOOKUP($A16,subQ,MATCH(I$1,SUBQH,0),0),"") | J16: =IFERROR(VLOOKUP($A16,subQ,MATCH(J$1,SUBQH,0),0),"") | K16: =IFERROR(VLOOKUP($A16,subQ,MATCH(K$1,SUBQH,0),0),"") | L16: =IFERROR(VLOOKUP($A16,subQ,MATCH(L$1,SUBQH,0),0),"") | ... AG16: =IFERROR(VLOOKUP($A16,subQ,MATCH(AG$1,SUBQH,0),0),"")
... A40: NPM | D40: NPM | E40: =IFERROR(VLOOKUP($A40,subQ,MATCH(E$1,SUBQH,0),0),"") | F40: =IFERROR(VLOOKUP($A40,subQ,MATCH(F$1,SUBQH,0),0),"") | G40: =IFERROR(VLOOKUP($A40,subQ,MATCH(G$1,SUBQH,0),0),"") | H40: =IFERROR(VLOOKUP($A40,subQ,MATCH(H$1,SUBQH,0),0),"") | I40: =IFERROR(VLOOKUP($A40,subQ,MATCH(I$1,SUBQH,0),0),"") | J40: =IFERROR(VLOOKUP($A40,subQ,MATCH(J$1,SUBQH,0),0),"") | K40: =IFERROR(VLOOKUP($A40,subQ,MATCH(K$1,SUBQH,0),0),"") | L40: =IFERROR(VLOOKUP($A40,subQ,MATCH(L$1,SUBQH,0),0),"") | ... AG40: =IFERROR(VLOOKUP($A40,subQ,MATCH(AG$1,SUBQH,0),0),"")
A41: 매출액 YoY | D41: 매출액 YoY | I41: =IFERROR(I5/E5-1,"") | J41: =IFERROR(J5/F5-1,"") | K41: =IFERROR(K5/G5-1,"") | L41: =IFERROR(L5/H5-1,"") | M41: =IFERROR(M5/I5-1,"") | N41: =IFERROR(N5/J5-1,"") | O41: =IFERROR(O5/K5-1,"") | P41: =IFERROR(P5/L5-1,"") | ... AG41: =IFERROR(AG5/AC5-1,"")
A42: 영업이익 YoY | D42: 영업이익 YoY | I42: =IFERROR(I9/E9-1,"") | J42: =IFERROR(J9/F9-1,"") | K42: =IFERROR(K9/G9-1,"") | L42: =IFERROR(L9/H9-1,"") | M42: =IFERROR(M9/I9-1,"") | N42: =IFERROR(N9/J9-1,"") | O42: =IFERROR(O9/K9-1,"") | P42: =IFERROR(P9/L9-1,"") | ... AG42: =IFERROR(AG9/AC9-1,"")
A43: 지배주주순이익 YoY | D43: 지배주주순이익 YoY | I43: =IFERROR(I20/E20-1,"") | J43: =IFERROR(J20/F20-1,"") | K43: =IFERROR(K20/G20-1,"") | L43: =IFERROR(L20/H20-1,"") | M43: =IFERROR(M20/I20-1,"") | N43: =IFERROR(N20/J20-1,"") | O43: =IFERROR(O20/K20-1,"") | P43: =IFERROR(P20/L20-1,"") | ... AG43: =IFERROR(AG20/AC20-1,"")

Sheet 연간예상
C1: 이름: 연간예상H — subQ 를 이름으로 VLOOKUP(억원) | E1: 2021 | F1: 2022 | G1: 2023 | H1: 2024 | I1: 2025 | J1: 2026 | K1: 2027 | L1: 2028
C2: 종가: | D2: =변수!D43
C3: 기준일: | D3: 20261008 | E3: 1 | F3: 2 | G3: 3 | H3: 4 | I3: 5 | J3: 6 | K3: 7 | L3: 8
E4: 2021.12A | F4: 2022.12A | G4: 2023.12A | H4: 2024.12A | I4: 2025.12A | J4: 2026.12A | K4: 2027.12A | L4: 2028.12A
A5: 매출액 | D5: 매출액 | E5: =IFERROR(VLOOKUP($A5,subQ,MATCH(E$1,SUBQH,0),0),"") | F5: =IFERROR(VLOOKUP($A5,subQ,MATCH(F$1,SUBQH,0),0),"") | G5: =IFERROR(VLOOKUP($A5,subQ,MATCH(G$1,SUBQH,0),0),"") | H5: =IFERROR(VLOOKUP($A5,subQ,MATCH(H$1,SUBQH,0),0),"") | I5: =IFERROR(VLOOKUP($A5,subQ,MATCH(I$1,SUBQH,0),0),"") | J5: =IFERROR(VLOOKUP($A5,subQ,MATCH(J$1,SUBQH,0),0),"") | K5: =IFERROR(VLOOKUP($A5,subQ,MATCH(K$1,SUBQH,0),0),"") | L5: =IFERROR(VLOOKUP($A5,subQ,MATCH(L$1,SUBQH,0),0),"")
A6: 매출원가 | D6: 매출원가 | E6: =IFERROR(VLOOKUP($A6,subQ,MATCH(E$1,SUBQH,0),0),"") | F6: =IFERROR(VLOOKUP($A6,subQ,MATCH(F$1,SUBQH,0),0),"") | G6: =IFERROR(VLOOKUP($A6,subQ,MATCH(G$1,SUBQH,0),0),"") | H6: =IFERROR(VLOOKUP($A6,subQ,MATCH(H$1,SUBQH,0),0),"") | I6: =IFERROR(VLOOKUP($A6,subQ,MATCH(I$1,SUBQH,0),0),"") | J6: =IFERROR(VLOOKUP($A6,subQ,MATCH(J$1,SUBQH,0),0),"") | K6: =IFERROR(VLOOKUP($A6,subQ,MATCH(K$1,SUBQH,0),0),"") | L6: =IFERROR(VLOOKUP($A6,subQ,MATCH(L$1,SUBQH,0),0),"")
A7: 매출총이익 | D7: 매출총이익 | E7: =IFERROR(VLOOKUP($A7,subQ,MATCH(E$1,SUBQH,0),0),"") | F7: =IFERROR(VLOOKUP($A7,subQ,MATCH(F$1,SUBQH,0),0),"") | G7: =IFERROR(VLOOKUP($A7,subQ,MATCH(G$1,SUBQH,0),0),"") | H7: =IFERROR(VLOOKUP($A7,subQ,MATCH(H$1,SUBQH,0),0),"") | I7: =IFERROR(VLOOKUP($A7,subQ,MATCH(I$1,SUBQH,0),0),"") | J7: =IFERROR(VLOOKUP($A7,subQ,MATCH(J$1,SUBQH,0),0),"") | K7: =IFERROR(VLOOKUP($A7,subQ,MATCH(K$1,SUBQH,0),0),"") | L7: =IFERROR(VLOOKUP($A7,subQ,MATCH(L$1,SUBQH,0),0),"")
A8: 판관비 | D8: 판매비와관리비 | E8: =IFERROR(VLOOKUP($A8,subQ,MATCH(E$1,SUBQH,0),0),"") | F8: =IFERROR(VLOOKUP($A8,subQ,MATCH(F$1,SUBQH,0),0),"") | G8: =IFERROR(VLOOKUP($A8,subQ,MATCH(G$1,SUBQH,0),0),"") | H8: =IFERROR(VLOOKUP($A8,subQ,MATCH(H$1,SUBQH,0),0),"") | I8: =IFERROR(VLOOKUP($A8,subQ,MATCH(I$1,SUBQH,0),0),"") | J8: =IFERROR(VLOOKUP($A8,subQ,MATCH(J$1,SUBQH,0),0),"") | K8: =IFERROR(VLOOKUP($A8,subQ,MATCH(K$1,SUBQH,0),0),"") | L8: =IFERROR(VLOOKUP($A8,subQ,MATCH(L$1,SUBQH,0),0),"")
A9: 영업이익 | D9: 영업이익 | E9: =IFERROR(VLOOKUP($A9,subQ,MATCH(E$1,SUBQH,0),0),"") | F9: =IFERROR(VLOOKUP($A9,subQ,MATCH(F$1,SUBQH,0),0),"") | G9: =IFERROR(VLOOKUP($A9,subQ,MATCH(G$1,SUBQH,0),0),"") | H9: =IFERROR(VLOOKUP($A9,subQ,MATCH(H$1,SUBQH,0),0),"") | I9: =IFERROR(VLOOKUP($A9,subQ,MATCH(I$1,SUBQH,0),0),"") | J9: =IFERROR(VLOOKUP($A9,subQ,MATCH(J$1,SUBQH,0),0),"") | K9: =IFERROR(VLOOKUP($A9,subQ,MATCH(K$1,SUBQH,0),0),"") | L9: =IFERROR(VLOOKUP($A9,subQ,MATCH(L$1,SUBQH,0),0),"")
A10: OPM | D10: 영업이익률 | E10: =IFERROR(VLOOKUP($A10,subQ,MATCH(E$1,SUBQH,0),0),"") | F10: =IFERROR(VLOOKUP($A10,subQ,MATCH(F$1,SUBQH,0),0),"") | G10: =IFERROR(VLOOKUP($A10,subQ,MATCH(G$1,SUBQH,0),0),"") | H10: =IFERROR(VLOOKUP($A10,subQ,MATCH(H$1,SUBQH,0),0),"") | I10: =IFERROR(VLOOKUP($A10,subQ,MATCH(I$1,SUBQH,0),0),"") | J10: =IFERROR(VLOOKUP($A10,subQ,MATCH(J$1,SUBQH,0),0),"") | K10: =IFERROR(VLOOKUP($A10,subQ,MATCH(K$1,SUBQH,0),0),"") | L10: =IFERROR(VLOOKUP($A10,subQ,MATCH(L$1,SUBQH,0),0),"")
A11: 금융손익 | D11: 금융손익(이자·환 포함) | E11: =IFERROR(VLOOKUP($A11,subQ,MATCH(E$1,SUBQH,0),0),"") | F11: =IFERROR(VLOOKUP($A11,subQ,MATCH(F$1,SUBQH,0),0),"") | G11: =IFERROR(VLOOKUP($A11,subQ,MATCH(G$1,SUBQH,0),0),"") | H11: =IFERROR(VLOOKUP($A11,subQ,MATCH(H$1,SUBQH,0),0),"") | I11: =IFERROR(VLOOKUP($A11,subQ,MATCH(I$1,SUBQH,0),0),"") | J11: =IFERROR(VLOOKUP($A11,subQ,MATCH(J$1,SUBQH,0),0),"") | K11: =IFERROR(VLOOKUP($A11,subQ,MATCH(K$1,SUBQH,0),0),"") | L11: =IFERROR(VLOOKUP($A11,subQ,MATCH(L$1,SUBQH,0),0),"")
A12: 이자손익 | D12: 이자손익(이자수익 − 이자비용) | E12: =IFERROR(VLOOKUP($A12,subQ,MATCH(E$1,SUBQH,0),0),"") | F12: =IFERROR(VLOOKUP($A12,subQ,MATCH(F$1,SUBQH,0),0),"") | G12: =IFERROR(VLOOKUP($A12,subQ,MATCH(G$1,SUBQH,0),0),"") | H12: =IFERROR(VLOOKUP($A12,subQ,MATCH(H$1,SUBQH,0),0),"") | I12: =IFERROR(VLOOKUP($A12,subQ,MATCH(I$1,SUBQH,0),0),"") | J12: =IFERROR(VLOOKUP($A12,subQ,MATCH(J$1,SUBQH,0),0),"") | K12: =IFERROR(VLOOKUP($A12,subQ,MATCH(K$1,SUBQH,0),0),"") | L12: =IFERROR(VLOOKUP($A12,subQ,MATCH(L$1,SUBQH,0),0),"")
A13: 외환손익 | D13: 외환손익(실적만; 추정 환효과는 환관련손익) | E13: =IFERROR(VLOOKUP($A13,subQ,MATCH(E$1,SUBQH,0),0),"") | F13: =IFERROR(VLOOKUP($A13,subQ,MATCH(F$1,SUBQH,0),0),"") | G13: =IFERROR(VLOOKUP($A13,subQ,MATCH(G$1,SUBQH,0),0),"") | H13: =IFERROR(VLOOKUP($A13,subQ,MATCH(H$1,SUBQH,0),0),"") | I13: =IFERROR(VLOOKUP($A13,subQ,MATCH(I$1,SUBQH,0),0),"") | J13: =IFERROR(VLOOKUP($A13,subQ,MATCH(J$1,SUBQH,0),0),"") | K13: =IFERROR(VLOOKUP($A13,subQ,MATCH(K$1,SUBQH,0),0),"") | L13: =IFERROR(VLOOKUP($A13,subQ,MATCH(L$1,SUBQH,0),0),"")
A14: 파생상품손익 | D14: 파생상품손익 | E14: =IFERROR(VLOOKUP($A14,subQ,MATCH(E$1,SUBQH,0),0),"") | F14: =IFERROR(VLOOKUP($A14,subQ,MATCH(F$1,SUBQH,0),0),"") | G14: =IFERROR(VLOOKUP($A14,subQ,MATCH(G$1,SUBQH,0),0),"") | H14: =IFERROR(VLOOKUP($A14,subQ,MATCH(H$1,SUBQH,0),0),"") | I14: =IFERROR(VLOOKUP($A14,subQ,MATCH(I$1,SUBQH,0),0),"") | J14: =IFERROR(VLOOKUP($A14,subQ,MATCH(J$1,SUBQH,0),0),"") | K14: =IFERROR(VLOOKUP($A14,subQ,MATCH(K$1,SUBQH,0),0),"") | L14: =IFERROR(VLOOKUP($A14,subQ,MATCH(L$1,SUBQH,0),0),"")
A15: 기타금융손익 | D15: 기타금융손익(금융손익 잔차) | E15: =IFERROR(VLOOKUP($A15,subQ,MATCH(E$1,SUBQH,0),0),"") | F15: =IFERROR(VLOOKUP($A15,subQ,MATCH(F$1,SUBQH,0),0),"") | G15: =IFERROR(VLOOKUP($A15,subQ,MATCH(G$1,SUBQH,0),0),"") | H15: =IFERROR(VLOOKUP($A15,subQ,MATCH(H$1,SUBQH,0),0),"") | I15: =IFERROR(VLOOKUP($A15,subQ,MATCH(I$1,SUBQH,0),0),"") | J15: =IFERROR(VLOOKUP($A15,subQ,MATCH(J$1,SUBQH,0),0),"") | K15: =IFERROR(VLOOKUP($A15,subQ,MATCH(K$1,SUBQH,0),0),"") | L15: =IFERROR(VLOOKUP($A15,subQ,MATCH(L$1,SUBQH,0),0),"")
A16: 기타영업외손익 | D16: 기타영업외손익 | E16: =IFERROR(VLOOKUP($A16,subQ,MATCH(E$1,SUBQH,0),0),"") | F16: =IFERROR(VLOOKUP($A16,subQ,MATCH(F$1,SUBQH,0),0),"") | G16: =IFERROR(VLOOKUP($A16,subQ,MATCH(G$1,SUBQH,0),0),"") | H16: =IFERROR(VLOOKUP($A16,subQ,MATCH(H$1,SUBQH,0),0),"") | I16: =IFERROR(VLOOKUP($A16,subQ,MATCH(I$1,SUBQH,0),0),"") | J16: =IFERROR(VLOOKUP($A16,subQ,MATCH(J$1,SUBQH,0),0),"") | K16: =IFERROR(VLOOKUP($A16,subQ,MATCH(K$1,SUBQH,0),0),"") | L16: =IFERROR(VLOOKUP($A16,subQ,MATCH(L$1,SUBQH,0),0),"")
... A40: NPM | D40: NPM | E40: =IFERROR(VLOOKUP($A40,subQ,MATCH(E$1,SUBQH,0),0),"") | F40: =IFERROR(VLOOKUP($A40,subQ,MATCH(F$1,SUBQH,0),0),"") | G40: =IFERROR(VLOOKUP($A40,subQ,MATCH(G$1,SUBQH,0),0),"") | H40: =IFERROR(VLOOKUP($A40,subQ,MATCH(H$1,SUBQH,0),0),"") | I40: =IFERROR(VLOOKUP($A40,subQ,MATCH(I$1,SUBQH,0),0),"") | J40: =IFERROR(VLOOKUP($A40,subQ,MATCH(J$1,SUBQH,0),0),"") | K40: =IFERROR(VLOOKUP($A40,subQ,MATCH(K$1,SUBQH,0),0),"") | L40: =IFERROR(VLOOKUP($A40,subQ,MATCH(L$1,SUBQH,0),0),"")
A41: 매출액 YoY | D41: 매출액 YoY | F41: =IFERROR(F5/E5-1,"") | G41: =IFERROR(G5/F5-1,"") | H41: =IFERROR(H5/G5-1,"") | I41: =IFERROR(I5/H5-1,"") | J41: =IFERROR(J5/I5-1,"") | K41: =IFERROR(K5/J5-1,"") | L41: =IFERROR(L5/K5-1,"")
A42: 영업이익 YoY | D42: 영업이익 YoY | F42: =IFERROR(F9/E9-1,"") | G42: =IFERROR(G9/F9-1,"") | H42: =IFERROR(H9/G9-1,"") | I42: =IFERROR(I9/H9-1,"") | J42: =IFERROR(J9/I9-1,"") | K42: =IFERROR(K9/J9-1,"") | L42: =IFERROR(L9/K9-1,"")
A43: 지배주주순이익 YoY | D43: 지배주주순이익 YoY | F43: =IFERROR(F20/E20-1,"") | G43: =IFERROR(G20/F20-1,"") | H43: =IFERROR(H20/G20-1,"") | I43: =IFERROR(I20/H20-1,"") | J43: =IFERROR(J20/I20-1,"") | K43: =IFERROR(K20/J20-1,"") | L43: =IFERROR(L20/K20-1,"")

Sheet TP
B1: 종가 | C1: =변수!D43
B2: 기준일 | C2: =변수!D44
B3: 모델 산출값 — 목표주가·추천 아님. 밴드·COE 는 변수 시트 3절의 가정
C5: FY | D5: 2025 | E5: 2026 | F5: 2027 | G5: 2028
D6: A | E6: E | F6: E | G6: E
C7: EPS(원) | D7: =IFERROR(VLOOKUP("EPS",subQ,MATCH(D$5,SUBQH,0),0),"") | E7: =IFERROR(VLOOKUP("EPS",subQ,MATCH(E$5,SUBQH,0),0),"") | F7: =IFERROR(VLOOKUP("EPS",subQ,MATCH(F$5,SUBQH,0),0),"") | G7: =IFERROR(VLOOKUP("EPS",subQ,MATCH(G$5,SUBQH,0),0),"")
C8: BPS(원) | D8: =IFERROR(VLOOKUP("BPS",subQ,MATCH(D$5,SUBQH,0),0),"") | E8: =IFERROR(VLOOKUP("BPS",subQ,MATCH(E$5,SUBQH,0),0),"") | F8: =IFERROR(VLOOKUP("BPS",subQ,MATCH(F$5,SUBQH,0),0),"") | G8: =IFERROR(VLOOKUP("BPS",subQ,MATCH(G$5,SUBQH,0),0),"")
C9: 지배주주순이익(억원) | D9: =IFERROR(VLOOKUP("지배주주순이익",subQ,MATCH(D$5,SUBQH,0),0),"") | E9: =IFERROR(VLOOKUP("지배주주순이익",subQ,MATCH(E$5,SUBQH,0),0),"") | F9: =IFERROR(VLOOKUP("지배주주순이익",subQ,MATCH(F$5,SUBQH,0),0),"") | G9: =IFERROR(VLOOKUP("지배주주순이익",subQ,MATCH(G$5,SUBQH,0),0),"")
C10: 영업이익(억원) | D10: =IFERROR(VLOOKUP("영업이익",subQ,MATCH(D$5,SUBQH,0),0),"") | E10: =IFERROR(VLOOKUP("영업이익",subQ,MATCH(E$5,SUBQH,0),0),"") | F10: =IFERROR(VLOOKUP("영업이익",subQ,MATCH(F$5,SUBQH,0),0),"") | G10: =IFERROR(VLOOKUP("영업이익",subQ,MATCH(G$5,SUBQH,0),0),"")
C11: ROE(EPS/기초BPS) | E11: =IFERROR(E7/D8,"") | F11: =IFERROR(F7/E8,"") | G11: =IFERROR(G7/F8,"")
B13: PER
C14: 12M fwd EPS | D14: =IFERROR(E7*변수!D49+F7*(1-변수!D49),"")
C15: 적정가치 @PER_lo | D15: =변수!D46 | E15: =IFERROR(ROUND($D$14*D15,-2),"") | F15: =IFERROR(E15/$C$1-1,"") | G15: 배 · 원 · 종가 대비
C16: 적정가치 @PER_mid | D16: =변수!D47 | E16: =IFERROR(ROUND($D$14*D16,-2),"") | F16: =IFERROR(E16/$C$1-1,"") | G16: 배 · 원 · 종가 대비
C17: 적정가치 @PER_hi | D17: =변수!D48 | E17: =IFERROR(ROUND($D$14*D17,-2),"") | F17: =IFERROR(E17/$C$1-1,"") | G17: 배 · 원 · 종가 대비
C18: 현재 PER(종가/12M fwd EPS) | D18: =IFERROR($C$1/$D$14,"")
B20: PBR
C21: 최근 BPS(마지막 실적 분기) | D21: =IFERROR(VLOOKUP("BPS",subQ,MATCH("2Q26",SUBQH,0),0),"")
C22: ROE fwd(12M fwd EPS / BPS) | D22: =IFERROR($D$14/$D$21,"")
C23: COE | D23: =변수!D45
C24: 적정 PBR = ROE/COE | D24: =IFERROR(D22/D23,"")
C25: 적정가치(PBR) = BPS × 적정PBR | D25: =IFERROR(ROUND(D21*D24,-2),"") | E25: =IFERROR(D25/$C$1-1,"")
C26: 현재 PBR(종가/BPS) | D26: =IFERROR($C$1/D21,"")
B28: 모델 json valuation(참고)
C29: eps_fwd12m | D29: 1499.8
C30: bps_latest | D30: 27510.3
C31: per_now | D31: 17.47
C32: pbr_now | D32: 0.95
C33: roe_fwd | D33: 0.0545
C34: fair_pbr | D34: 0.61
C35: fair_value_pbr | D35: 16800
C36: ev_ebitda
C37: note | D37: 모델 산출값 — 목표주가·추천 아님

Sheet 외화
C1: 이름: 외화QH — 환율 QoQ · 외화 순노출 × Δ기말환율 | E1: 4Q21 | F1: 1Q22 | G1: 2Q22 | H1: 3Q22 | I1: 4Q22 | J1: 1Q23 | K1: 2Q23 | L1: 3Q23 | M1: 4Q23 | N1: 1Q24 | O1: 2Q24 | P1: 3Q24 | Q1: 4Q24 | R1: 1Q25 | S1: 2Q25 | T1: 3Q25 | U1: 4Q25 | V1: 1Q26 | W1: 2Q26 | X1: 3Q26 | Y1: 4Q26 | Z1: 1Q27 | AA1: 2Q27 | AB1: 3Q27 | AC1: 4Q27 | AD1: 1Q28 | AE1: 2Q28 | AF1: 3Q28 | AG1: 4Q28
E3: 1 | F3: 2 | G3: 3 | H3: 4 | I3: 5 | J3: 6 | K3: 7 | L3: 8 | M3: 9 | N3: 10 | O3: 11 | P3: 12 | Q3: 13 | R3: 14 | S3: 15 | T3: 16 | U3: 17 | V3: 18 | W3: 19 | X3: 20 | Y3: 21 | Z3: 22 | AA3: 23 | AB3: 24 | AC3: 25 | AD3: 26 | AE3: 27 | AF3: 28 | AG3: 29
E4: 2021.12 | F4: 2022.03 | G4: 2022.06 | H4: 2022.09 | I4: 2022.12 | J4: 2023.03 | K4: 2023.06 | L4: 2023.09 | M4: 2023.12 | N4: 2024.03 | O4: 2024.06 | P4: 2024.09 | Q4: 2024.12 | R4: 2025.03 | S4: 2025.06 | T4: 2025.09 | U4: 2025.12 | V4: 2026.03 | W4: 2026.06 | X4: 2026.09 | Y4: 2026.12 | Z4: 2027.03 | AA4: 2027.06 | AB4: 2027.09 | AC4: 2027.12 | AD4: 2028.03 | AE4: 2028.06 | AF4: 2028.09 | AG4: 2028.12
D5: 원/달러(평균) | E5: =IFERROR(VLOOKUP($D5,환율,MATCH(E$1,변수H,0),0),"") | F5: =IFERROR(VLOOKUP($D5,환율,MATCH(F$1,변수H,0),0),"") | G5: =IFERROR(VLOOKUP($D5,환율,MATCH(G$1,변수H,0),0),"") | H5: =IFERROR(VLOOKUP($D5,환율,MATCH(H$1,변수H,0),0),"") | I5: =IFERROR(VLOOKUP($D5,환율,MATCH(I$1,변수H,0),0),"") | J5: =IFERROR(VLOOKUP($D5,환율,MATCH(J$1,변수H,0),0),"") | K5: =IFERROR(VLOOKUP($D5,환율,MATCH(K$1,변수H,0),0),"") | L5: =IFERROR(VLOOKUP($D5,환율,MATCH(L$1,변수H,0),0),"") | ... AG5: =IFERROR(VLOOKUP($D5,환율,MATCH(AG$1,변수H,0),0),"")
A6: 원/달러(평균) QoQ | F6: =IFERROR(F5/E5-1,"") | G6: =IFERROR(G5/F5-1,"") | H6: =IFERROR(H5/G5-1,"") | I6: =IFERROR(I5/H5-1,"") | J6: =IFERROR(J5/I5-1,"") | K6: =IFERROR(K5/J5-1,"") | L6: =IFERROR(L5/K5-1,"") | M6: =IFERROR(M5/L5-1,"") | ... AG6: =IFERROR(AG5/AF5-1,"")
D7: 원/달러(기말) | E7: =IFERROR(VLOOKUP($D7,환율,MATCH(E$1,변수H,0),0),"") | F7: =IFERROR(VLOOKUP($D7,환율,MATCH(F$1,변수H,0),0),"") | G7: =IFERROR(VLOOKUP($D7,환율,MATCH(G$1,변수H,0),0),"") | H7: =IFERROR(VLOOKUP($D7,환율,MATCH(H$1,변수H,0),0),"") | I7: =IFERROR(VLOOKUP($D7,환율,MATCH(I$1,변수H,0),0),"") | J7: =IFERROR(VLOOKUP($D7,환율,MATCH(J$1,변수H,0),0),"") | K7: =IFERROR(VLOOKUP($D7,환율,MATCH(K$1,변수H,0),0),"") | L7: =IFERROR(VLOOKUP($D7,환율,MATCH(L$1,변수H,0),0),"") | ... AG7: =IFERROR(VLOOKUP($D7,환율,MATCH(AG$1,변수H,0),0),"")
A8: 원/달러(기말) QoQ | F8: =IFERROR(F7/E7-1,"") | G8: =IFERROR(G7/F7-1,"") | H8: =IFERROR(H7/G7-1,"") | I8: =IFERROR(I7/H7-1,"") | J8: =IFERROR(J7/I7-1,"") | K8: =IFERROR(K7/J7-1,"") | L8: =IFERROR(L7/K7-1,"") | M8: =IFERROR(M7/L7-1,"") | ... AG8: =IFERROR(AG7/AF7-1,"")
D9: W/Euro(평균) | E9: =IFERROR(VLOOKUP($D9,환율,MATCH(E$1,변수H,0),0),"") | F9: =IFERROR(VLOOKUP($D9,환율,MATCH(F$1,변수H,0),0),"") | G9: =IFERROR(VLOOKUP($D9,환율,MATCH(G$1,변수H,0),0),"") | H9: =IFERROR(VLOOKUP($D9,환율,MATCH(H$1,변수H,0),0),"") | I9: =IFERROR(VLOOKUP($D9,환율,MATCH(I$1,변수H,0),0),"") | J9: =IFERROR(VLOOKUP($D9,환율,MATCH(J$1,변수H,0),0),"") | K9: =IFERROR(VLOOKUP($D9,환율,MATCH(K$1,변수H,0),0),"") | L9: =IFERROR(VLOOKUP($D9,환율,MATCH(L$1,변수H,0),0),"") | ... AG9: =IFERROR(VLOOKUP($D9,환율,MATCH(AG$1,변수H,0),0),"")
A10: W/Euro(평균) QoQ | F10: =IFERROR(F9/E9-1,"") | G10: =IFERROR(G9/F9-1,"") | H10: =IFERROR(H9/G9-1,"") | I10: =IFERROR(I9/H9-1,"") | J10: =IFERROR(J9/I9-1,"") | K10: =IFERROR(K9/J9-1,"") | L10: =IFERROR(L9/K9-1,"") | M10: =IFERROR(M9/L9-1,"") | ... AG10: =IFERROR(AG9/AF9-1,"")
D11: W/Euro(기말) | E11: =IFERROR(VLOOKUP($D11,환율,MATCH(E$1,변수H,0),0),"") | F11: =IFERROR(VLOOKUP($D11,환율,MATCH(F$1,변수H,0),0),"") | G11: =IFERROR(VLOOKUP($D11,환율,MATCH(G$1,변수H,0),0),"") | H11: =IFERROR(VLOOKUP($D11,환율,MATCH(H$1,변수H,0),0),"") | I11: =IFERROR(VLOOKUP($D11,환율,MATCH(I$1,변수H,0),0),"") | J11: =IFERROR(VLOOKUP($D11,환율,MATCH(J$1,변수H,0),0),"") | K11: =IFERROR(VLOOKUP($D11,환율,MATCH(K$1,변수H,0),0),"") | L11: =IFERROR(VLOOKUP($D11,환율,MATCH(L$1,변수H,0),0),"") | ... AG11: =IFERROR(VLOOKUP($D11,환율,MATCH(AG$1,변수H,0),0),"")
A12: W/Euro(기말) QoQ | F12: =IFERROR(F11/E11-1,"") | G12: =IFERROR(G11/F11-1,"") | H12: =IFERROR(H11/G11-1,"") | I12: =IFERROR(I11/H11-1,"") | J12: =IFERROR(J11/I11-1,"") | K12: =IFERROR(K11/J11-1,"") | L12: =IFERROR(L11/K11-1,"") | M12: =IFERROR(M11/L11-1,"") | ... AG12: =IFERROR(AG11/AF11-1,"")
D13: 원/100Y(기말) | E13: =IFERROR(VLOOKUP($D13,환율,MATCH(E$1,변수H,0),0),"") | F13: =IFERROR(VLOOKUP($D13,환율,MATCH(F$1,변수H,0),0),"") | G13: =IFERROR(VLOOKUP($D13,환율,MATCH(G$1,변수H,0),0),"") | H13: =IFERROR(VLOOKUP($D13,환율,MATCH(H$1,변수H,0),0),"") | I13: =IFERROR(VLOOKUP($D13,환율,MATCH(I$1,변수H,0),0),"") | J13: =IFERROR(VLOOKUP($D13,환율,MATCH(J$1,변수H,0),0),"") | K13: =IFERROR(VLOOKUP($D13,환율,MATCH(K$1,변수H,0),0),"") | L13: =IFERROR(VLOOKUP($D13,환율,MATCH(L$1,변수H,0),0),"") | ... AG13: =IFERROR(VLOOKUP($D13,환율,MATCH(AG$1,변수H,0),0),"")
A14: 원/100Y(기말) QoQ | F14: =IFERROR(F13/E13-1,"") | G14: =IFERROR(G13/F13-1,"") | H14: =IFERROR(H13/G13-1,"") | I14: =IFERROR(I13/H13-1,"") | J14: =IFERROR(J13/I13-1,"") | K14: =IFERROR(K13/J13-1,"") | L14: =IFERROR(L13/K13-1,"") | M14: =IFERROR(M13/L13-1,"") | ... AG14: =IFERROR(AG13/AF13-1,"")
A16: 외화순노출 | C16: 외화 순노출(백만$) | D16: =변수!D56 | E16: 외화 순노출 × Δ기말환율 (외화 시트 방식)
A17: 환관련손익추정 | C17: 환관련손익 추정(억원) = 순노출 × Δ원/달러(기말) / 100 | F17: =IFERROR($D$16*(F7-E7)/100,"") | G17: =IFERROR($D$16*(G7-F7)/100,"") | H17: =IFERROR($D$16*(H7-G7)/100,"") | I17: =IFERROR($D$16*(I7-H7)/100,"") | J17: =IFERROR($D$16*(J7-I7)/100,"") | K17: =IFERROR($D$16*(K7-J7)/100,"") | L17: =IFERROR($D$16*(L7-K7)/100,"") | M17: =IFERROR($D$16*(M7-L7)/100,"") | ... AG17: =IFERROR($D$16*(AG7-AF7)/100,"")
A18: fx_pnl.by_q | C18: 모델 fx_pnl.by_q(억원, 참고)
C19: 외화 순노출 미공시(face) → 0 + 표기
