Workbook
Name 변수H: 변수!$C$1:$AO$1
Name 환율: 변수!$C$6:$AO$13
Name BS연결H: BS연결!$C$1:$AO$1
Name BS연결: BS연결!$C$5:$AO$104
Name BS별도H: BS별도!$C$1:$AO$1
Name BS별도: BS별도!$C$5:$AO$89
Name SUBQH: subQ!$A$1:$AO$1
Name subQ: subQ!$A$5:$AO$44

Sheet README
A1: 한국선재(025550) 실적 모델 — ARGUS 한국조선
A2: 기준 분기 2026Q2 · 마지막 실적 2026Q2 · 생성 2026-10-13
A3: 모든 수치는 모델 산출값(DART 공개 재무제표 + 우리 추정)이다 — 목표주가·투자 추천 아님. 참고용 · 투자조언 아님.
A5: 시트
A6: 변수 가정 시계열. 환율 8행(ECB via frankfurter — L2 fx.json; 추정 분기 = 노란 가정), 추정 드라이버(노란 셀 = 모델값에서 역산한 가정, 바꾸면 재계산; 연녹 셀 = 3절 스칼라 참조 수식), 3절 스칼라 가정(세율·판관비율·지배주주비중·이자율·종가·PER 밴드·COE·외화 순노출·헤지비율)
A7: BS연결/BS별도 FnGuide 계정명 × 기간 값 덤프(백만원). 행1 분기라벨, 행4 YYYY.MM / YYYY.12A. 이름정의 BS연결H·BS연결(계정명 C열부터)
A8: subQ 분기 서브모델(억원 = 백만원/100). 확정 행: =IFERROR(VLOOKUP($D행,BS연결,MATCH(E$1,BS연결H,0),0)/100,"") 추정 행: 변수 시트 가정 셀 참조 수식. 외환손익·파생상품손익은 BS 계정 합·차, 기타금융손익은 잔차, OPM·EPS·BPS·PER·PBR 은 파생 수식
A9: SLS 선표(조선사만, sls json 있을 때): 요약 행(sls 저장값) + 계약별 스케줄(백만$) × (헤지비율 × 헤지환율 + (1−헤지비율) × 건조시점 환율[변수 원/달러(평균)]) → 원화 수식 블록 → 합계 행이 subQ 매출조선에 연결
A10: 시나리오 신규수주 보수/기준/낙관(forecast_panel 패널, 모델에 scenarios 가 있을 때만): 매출액·영업이익 = subQ 기준값 ± (시나리오 신규 − base 신규) × OPM. base 만 subQ 행에 포함, 나머지는 합산 안 함
A11: 분기/연간예상 subQ 를 이름(A열 key)으로 VLOOKUP 한 보고서 표(억원)
A12: TP PER 밴드 × 12M fwd EPS, PBR = ROE/COE × BPS — 모델 산출값 구간, 목표주가·추천 아님
A13: 외화 환율 QoQ, 외화 순노출 × Δ기말환율 → 환관련손익 추정
... A34: 백테스트: {"freeze": "2025Q2", "horizon": 4, "revenue_wape_pct": 16.4, "op_wape_pct": 90.2, "n": 4, "note": "단일 회사 4분기 — 통계 아님", "driver_at_freeze": "trend_seasonal", "selection_oos_at_freeze": {"wape_link": null, "wape_trend": null, "adopted": false, "decision": "rejected", "note": "유의성 조건 미달 → OOS 비교 전 기각"}, "frozen_inputs": "fin(연결/별도)·고객 조선사 모델·지주 자회사 모델은 2025Q2 까지의 분기만; 선표는 체결일 ≤ 2025Q2 말일 계약(원장 최신 금액·코호트 등급, 환산 없음); 잔고는 yards_cache 2025Q2; 시세·환율 forward·prices·forecast_panel 신규수주 미사용. 고객 가중치(suppliers.json 언급 비중)와 합병 체인링크는 현재 지식; 고객 연동 채택은 동결 모델 안에서도 자기 la−4분기 OOS 규칙(selection_oos_at_freeze)", "detail": [{"q": "2025Q3", "rev_pred": 501.41, "rev_act": 560.09, "op_pred": 10.02, "op_act": 27.88}, {"q": "2025Q4", "rev_pred": 542.95, "rev_act": 539.23, "op_pred": 10.85, "op_act": -0.36}, {"q": "2026Q1", "rev_pred": 503.83, "rev_act": 661.2, "op_pred": 10.07, "op_act": 81.6}, {"q": "2026Q2", "rev_pred": 529.64, "rev_act": 717.21, "op_pred": 10.59, "op_act": 92.26}]}

Sheet 변수
C1: 이름: 변수H | E1: 4Q21 | F1: 2021 | G1: 1Q22 | H1: 2Q22 | I1: 3Q22 | J1: 4Q22 | K1: 2022 | L1: 1Q23 | M1: 2Q23 | N1: 3Q23 | O1: 4Q23 | P1: 2023 | Q1: 1Q24 | R1: 2Q24 | S1: 3Q24 | T1: 4Q24 | U1: 2024 | V1: 1Q25 | W1: 2Q25 | X1: 3Q25 | Y1: 4Q25 | Z1: 2025 | AA1: 1Q26 | AB1: 2Q26 | AC1: 3Q26 | AD1: 4Q26 | AE1: 2026 | AF1: 1Q27 | AG1: 2Q27 | AH1: 3Q27 | AI1: 4Q27 | AJ1: 2027 | AK1: 1Q28 | AL1: 2Q28 | AM1: 3Q28 | AN1: 4Q28 | AO1: 2028
A2: 가정 시계열 — 노란 셀은 추정 가정(모델값에서 역산), 연녹 셀은 3절 스칼라 참조 수식. 바꾸면 subQ·분기·연간예상·TP·시나리오가 재계산됩니다.
E3: 1 | F3: 2 | G3: 3 | H3: 4 | I3: 5 | J3: 6 | K3: 7 | L3: 8 | M3: 9 | N3: 10 | O3: 11 | P3: 12 | Q3: 13 | R3: 14 | S3: 15 | T3: 16 | U3: 17 | V3: 18 | W3: 19 | X3: 20 | Y3: 21 | Z3: 22 | AA3: 23 | AB3: 24 | AC3: 25 | AD3: 26 | AE3: 27 | AF3: 28 | AG3: 29 | AH3: 30 | AI3: 31 | AJ3: 32 | AK3: 33 | AL3: 34 | AM3: 35 | AN3: 36 | AO3: 37
E4: 2021.12 | F4: 2021.12A | G4: 2022.03 | H4: 2022.06 | I4: 2022.09 | J4: 2022.12 | K4: 2022.12A | L4: 2023.03 | M4: 2023.06 | N4: 2023.09 | O4: 2023.12 | P4: 2023.12A | Q4: 2024.03 | R4: 2024.06 | S4: 2024.09 | T4: 2024.12 | U4: 2024.12A | V4: 2025.03 | W4: 2025.06 | X4: 2025.09 | Y4: 2025.12 | Z4: 2025.12A | AA4: 2026.03 | AB4: 2026.06 | AC4: 2026.09 | AD4: 2026.12 | AE4: 2026.12A | AF4: 2027.03 | AG4: 2027.06 | AH4: 2027.09 | AI4: 2027.12 | AJ4: 2027.12A | AK4: 2028.03 | AL4: 2028.06 | AM4: 2028.09 | AN4: 2028.12 | AO4: 2028.12A
B5: 1. FX | C5: 이름: 환율
A6: USDKRW_avg | C6: 원/달러(평균) | E6: 1183.5 | F6: 1145.51 | G6: 1205.78 | H6: 1262.09 | I6: 1341.93 | J6: 1360.12 | K6: 1292.98 | L6: 1276.95 | M6: 1315.69 | N6: 1313.62 | O6: 1322.01 | P6: 1306.85 | Q6: 1330.14 | R6: 1371.28 | S6: 1356.22 | T6: 1396.3 | U6: 1363.53 | V6: 1452.28 | W6: 1398.52 | X6: 1386.95 | Y6: 1449.19 | Z6: 1421.52 | AA6: 1466.12 | AB6: 1501.75 | AC6: 1418.75 | AD6: 1343.63 | AE6: 1456.58 | AF6: 1333.09 | AG6: 1333.09 | AH6: 1333.09 | AI6: 1333.09 | AK6: 1333.09 | AL6: 1333.09 | AM6: 1333.09 | AN6: 1333.09
A7: USDKRW_end | C7: 원/달러(기말) | E7: 1188.75 | F7: 1188.75 | G7: 1213.74 | H7: 1301.24 | I7: 1436.9 | J7: 1260.16 | K7: 1260.16 | L7: 1305.99 | M7: 1321.44 | N7: 1345.35 | O7: 1297.43 | P7: 1297.43 | Q7: 1349.25 | R7: 1377.73 | S7: 1312.17 | T7: 1474.78 | U7: 1474.78 | V7: 1474.54 | W7: 1355.13 | X7: 1403.67 | Y7: 1444.2 | Z7: 1444.2 | AA7: 1524.8 | AB7: 1550.89 | AC7: 1355.4 | AD7: 1333.09 | AE7: 1333.09 | AF7: 1333.09 | AG7: 1333.09 | AH7: 1333.09 | AI7: 1333.09 | AK7: 1333.09 | AL7: 1333.09 | AM7: 1333.09 | AN7: 1333.09
A8: JPY100KRW_avg | C8: 원/100Y(평균) | E8: 1041.02 | F8: 1042.74 | G8: 1036.79 | H8: 972.23 | I8: 970.61 | J8: 961.03 | K8: 985.1 | L8: 964.89 | M8: 957.36 | N8: 909 | O8: 893.22 | P8: 931.11 | Q8: 896.29 | R8: 880.14 | S8: 909.35 | T8: 917.25 | U8: 900.92 | V8: 952.59 | W8: 967.92 | X8: 940.32 | Y8: 940.77 | Z8: 950.17 | AA8: 934.39 | AB8: 942.16 | AC8: 890.41 | AD8: 849.51 | AE8: 918.81 | AF8: 840.54 | AG8: 840.54 | AH8: 840.54 | AI8: 840.54 | AK8: 840.54 | AL8: 840.54 | AM8: 840.54 | AN8: 840.54
A9: JPY100KRW_end | C9: 원/100Y(기말) | E9: 1032.62 | F9: 1032.62 | G9: 996.83 | H9: 954.9 | I9: 993.29 | J9: 955.54 | K9: 955.54 | L9: 980.62 | M9: 913.67 | N9: 901.47 | O9: 917.04 | P9: 917.04 | Q9: 892.42 | R9: 857.76 | S9: 919.21 | T9: 939.65 | U9: 939.65 | V9: 986.84 | W9: 938.85 | X9: 948.49 | Y9: 921.81 | Z9: 921.81 | AA9: 955.99 | AB9: 954.75 | AC9: 863.31 | AD9: 840.54 | AE9: 840.54 | AF9: 840.54 | AG9: 840.54 | AH9: 840.54 | AI9: 840.54 | AK9: 840.54 | AL9: 840.54 | AM9: 840.54 | AN9: 840.54
A10: EURKRW_avg | C10: W/Euro(평균) | E10: 1353.32 | F10: 1354.06 | G10: 1352.29 | H10: 1343.31 | I10: 1350.63 | J10: 1386.07 | K10: 1358.07 | L10: 1369.93 | M10: 1432.41 | N10: 1429.41 | O10: 1420.91 | P10: 1412.88 | Q10: 1444.21 | R10: 1476.42 | S10: 1489.3 | T10: 1490.78 | U10: 1475.4 | V10: 1528.33 | W10: 1585.13 | X10: 1620.04 | Y10: 1686.02 | Z10: 1605.45 | AA10: 1715.47 | AB10: 1746.09 | AC10: 1631.97 | AD10: 1507.34 | AE10: 1688.95 | AF10: 1490.54 | AG10: 1490.54 | AH10: 1490.54 | AI10: 1490.54 | AK10: 1490.54 | AL10: 1490.54 | AM10: 1490.54 | AN10: 1490.54
A11: EURKRW_end | C11: W/Euro(기말) | E11: 1346.38 | F11: 1346.38 | G11: 1347.37 | H11: 1351.6 | I11: 1400.62 | J11: 1344.08 | K11: 1344.08 | L11: 1420.26 | M11: 1435.88 | N11: 1425.26 | O11: 1433.66 | P11: 1433.66 | Q11: 1458.68 | R11: 1474.86 | S11: 1469.1 | T11: 1532.14 | U11: 1532.14 | V11: 1594.72 | W11: 1588.22 | X11: 1648.04 | Y11: 1696.94 | Z11: 1696.94 | AA11: 1753.21 | AB11: 1767.09 | AC11: 1539.06 | AD11: 1490.54 | AE11: 1490.54 | AF11: 1490.54 | AG11: 1490.54 | AH11: 1490.54 | AI11: 1490.54 | AK11: 1490.54 | AL11: 1490.54 | AM11: 1490.54 | AN11: 1490.54
A12: CNYKRW_avg | C12: 원/중국원(평균) | E12: 185.14 | F12: 177.65 | G12: 189.93 | H12: 190.76 | I12: 195.79 | J12: 191.09 | K12: 191.93 | L12: 186.59 | M12: 187.45 | N12: 181.28 | O12: 182.86 | P12: 184.52 | Q12: 185.04 | R12: 189.35 | S12: 189.24 | T12: 194.24 | U12: 189.49 | V12: 199.63 | W12: 193.41 | X12: 193.79 | Y12: 204.38 | Z12: 197.8 | AA12: 211.75 | AB12: 220.8 | AC12: 210.43 | AD12: 200.5 | AE12: 213.68 | AF12: 199.18 | AG12: 199.18 | AH12: 199.18 | AI12: 199.18 | AK12: 199.18 | AL12: 199.18 | AM12: 199.18 | AN12: 199.18
A13: CNYKRW_end | C13: 원/중국원(기말) | E13: 187.13 | F13: 187.13 | G13: 191.38 | H13: 194.13 | I13: 201.92 | J13: 182.67 | K13: 182.67 | L13: 189.97 | M13: 181.8 | N13: 184.26 | O13: 182.61 | P13: 182.61 | Q13: 186.66 | R13: 189.7 | S13: 187.12 | T13: 202.04 | U13: 202.04 | V13: 203.3 | W13: 189.14 | X13: 197.16 | Y13: 206.28 | Z13: 206.28 | AA13: 220.97 | AB13: 228.56 | AC13: 202.16 | AD13: 199.18 | AE13: 199.18 | AF13: 199.18 | AG13: 199.18 | AH13: 199.18 | AI13: 199.18 | AK13: 199.18 | AL13: 199.18 | AM13: 199.18 | AN13: 199.18
B14: 1b. 종가
A15: price_close_end | C15: 종가(기말) | E15: 5250 | G15: 7080 | H15: 4255 | I15: 3700 | J15: 4010 | L15: 4050 | M15: 4340 | N15: 4010 | O15: 3820 | Q15: 3590 | R15: 3495 | S15: 2980 | T15: 4010 | V15: 3130 | W15: 3540 | X15: 4015 | Y15: 3380 | AA15: 3120 | AB15: 2225 | AC15: 2320 | AD15: 2200
A16: price_high | C16: 종가(최고) | E16: 11150 | G16: 8400 | H16: 7270 | I16: 5260 | J16: 5700 | L16: 4690 | M16: 4945 | N16: 4420 | O16: 4300 | Q16: 3835 | R16: 4115 | S16: 3520 | T16: 5220 | V16: 5020 | W16: 6150 | X16: 5050 | Y16: 4380 | AA16: 3645 | AB16: 4855 | AC16: 2870 | AD16: 2410
A17: price_low | C17: 종가(최저) | E17: 3990 | G17: 3680 | H17: 3760 | I17: 3550 | J17: 3470 | L17: 3755 | M17: 3995 | N17: 3545 | O17: 3750 | Q17: 3345 | R17: 3420 | S17: 2720 | T17: 2740 | V17: 3130 | W17: 3140 | X17: 3110 | Y17: 3220 | AA17: 2865 | AB17: 2015 | AC17: 1801 | AD17: 2150
A18: price_avg | C18: 종가(평균) | E18: 6188.4 | G18: 5326.4 | H18: 5585.7 | I18: 4452.3 | J18: 4333.3 | L18: 4184.4 | M18: 4282.6 | N18: 4059.5 | O18: 3940.5 | Q18: 3647.5 | R18: 3581 | S18: 3135.2 | T18: 3178 | V18: 3817.8 | W18: 3917.4 | X18: 3593 | Y18: 3669.1 | AA18: 3322.5 | AB18: 3268.5 | AC18: 2177.3 | AD18: 2314.3
B20: 2. 추정 드라이버 | C20: 실적 열 = subQ 실현값(수식), 추정 열 = 가정(노란 = 모델값 역산, 연녹 = 3절 스칼라 참조)
A21: drv:매출액 | B21: yoy | C21: 매출액 YoY | J21: =IFERROR(subQ!J5/subQ!E5-1,"") | L21: =IFERROR(subQ!L5/subQ!G5-1,"") | M21: =IFERROR(subQ!M5/subQ!H5-1,"") | N21: =IFERROR(subQ!N5/subQ!I5-1,"") | O21: =IFERROR(subQ!O5/subQ!J5-1,"") | Q21: =IFERROR(subQ!Q5/subQ!L5-1,"") | R21: =IFERROR(subQ!R5/subQ!M5-1,"") | S21: =IFERROR(subQ!S5/subQ!N5-1,"") | T21: =IFERROR(subQ!T5/subQ!O5-1,"") | V21: =IFERROR(subQ!V5/subQ!Q5-1,"") | W21: =IFERROR(subQ!W5/subQ!R5-1,"") | X21: =IFERROR(subQ!X5/subQ!S5-1,"") | Y21: =IFERROR(subQ!Y5/subQ!T5-1,"") | AA21: =IFERROR(subQ!AA5/subQ!V5-1,"") | AB21: =IFERROR(subQ!AB5/subQ!W5-1,"") | AC21: 0.49232759 | AD21: 0.61441075 | AF21: 0.33321557 | AG21: 0.26068862 | AH21: 0.13775364 | AI21: 0.15273279 | AK21: 0.210103 | AL21: 0.25280365 | AM21: 0.26413805 | AN21: 0.25319382
A22: drv:판관비 | B22: ratio | C22: 판관비율(/매출) | E22: =IFERROR(subQ!E8/subQ!E5,"") | F22: =IFERROR(subQ!F8/subQ!F5,"") | G22: =IFERROR(subQ!G8/subQ!G5,"") | H22: =IFERROR(subQ!H8/subQ!H5,"") | I22: =IFERROR(subQ!I8/subQ!I5,"") | J22: =IFERROR(subQ!J8/subQ!J5,"") | K22: =IFERROR(subQ!K8/subQ!K5,"") | L22: =IFERROR(subQ!L8/subQ!L5,"") | ... AB22: =IFERROR(subQ!AB8/subQ!AB5,"") | AC22: =$D$52 | AD22: =$D$52 | AE22: =IFERROR(subQ!AE8/subQ!AE5,"") | AF22: =$D$52 | AG22: =$D$52 | AH22: =$D$52 | AI22: =$D$52 | AJ22: =IFERROR(subQ!AJ8/subQ!AJ5,"") | AK22: =$D$52 | AL22: =$D$52 | AM22: =$D$52 | AN22: =$D$52 | AO22: =IFERROR(subQ!AO8/subQ!AO5,"")
A23: drv:영업이익 | B23: ratio | C23: 영업이익률(OPM) | E23: =IFERROR(subQ!E9/subQ!E5,"") | F23: =IFERROR(subQ!F9/subQ!F5,"") | G23: =IFERROR(subQ!G9/subQ!G5,"") | H23: =IFERROR(subQ!H9/subQ!H5,"") | I23: =IFERROR(subQ!I9/subQ!I5,"") | J23: =IFERROR(subQ!J9/subQ!J5,"") | K23: =IFERROR(subQ!K9/subQ!K5,"") | L23: =IFERROR(subQ!L9/subQ!L5,"") | ... AB23: =IFERROR(subQ!AB9/subQ!AB5,"") | AC23: 0.03688505 | AD23: 0.036885152 | AE23: =IFERROR(subQ!AE9/subQ!AE5,"") | AF23: 0.036879481 | AG23: 0.036884249 | AH23: 0.036888263 | AI23: 0.036880917 | AJ23: =IFERROR(subQ!AJ9/subQ!AJ5,"") | AK23: 0.036888435 | AL23: 0.036883365 | AM23: 0.036883303 | AN23: 0.036888309 | AO23: =IFERROR(subQ!AO9/subQ!AO5,"")
A24: drv:외환손익 | B24: abs | C24: 외환손익 (가정, 억원) | E24: =subQ!E13 | F24: =subQ!F13 | G24: =subQ!G13 | H24: =subQ!H13 | I24: =subQ!I13 | J24: =subQ!J13 | K24: =subQ!K13 | L24: =subQ!L13 | ... AB24: =subQ!AB13 | AC24: 0 | AD24: 0 | AE24: =subQ!AE13 | AF24: 0 | AG24: 0 | AH24: 0 | AI24: 0 | AJ24: =subQ!AJ13 | AK24: 0 | AL24: 0 | AM24: 0 | AN24: 0 | AO24: =subQ!AO13
A25: drv:파생상품손익 | B25: abs | C25: 파생상품손익 (가정, 억원) | E25: =subQ!E14 | F25: =subQ!F14 | G25: =subQ!G14 | H25: =subQ!H14 | I25: =subQ!I14 | J25: =subQ!J14 | K25: =subQ!K14 | L25: =subQ!L14 | ... AB25: =subQ!AB14 | AC25: 0 | AD25: 0 | AE25: =subQ!AE14 | AF25: 0 | AG25: 0 | AH25: 0 | AI25: 0 | AJ25: =subQ!AJ14 | AK25: 0 | AL25: 0 | AM25: 0 | AN25: 0 | AO25: =subQ!AO14
A26: drv:기타금융손익 | B26: abs | C26: 기타금융손익 (가정, 억원) | E26: =subQ!E15 | F26: =subQ!F15 | G26: =subQ!G15 | H26: =subQ!H15 | I26: =subQ!I15 | J26: =subQ!J15 | K26: =subQ!K15 | L26: =subQ!L15 | ... AB26: =subQ!AB15 | AC26: -0.87 | AD26: -0.87 | AE26: =subQ!AE15 | AF26: -0.87 | AG26: -0.87 | AH26: -0.87 | AI26: -0.87 | AJ26: =subQ!AJ15 | AK26: -0.87 | AL26: -0.87 | AM26: -0.87 | AN26: -0.87 | AO26: =subQ!AO15
A27: drv:기타영업외손익 | B27: abs | C27: 기타영업외손익 (가정, 억원) | E27: =subQ!E16 | F27: =subQ!F16 | G27: =subQ!G16 | H27: =subQ!H16 | I27: =subQ!I16 | J27: =subQ!J16 | K27: =subQ!K16 | L27: =subQ!L16 | ... AB27: =subQ!AB16 | AC27: 0 | AD27: 0 | AE27: =subQ!AE16 | AF27: 0 | AG27: 0 | AH27: 0 | AI27: 0 | AJ27: =subQ!AJ16 | AK27: 0 | AL27: 0 | AM27: 0 | AN27: 0 | AO27: =subQ!AO16
A28: drv:법인세비용 | B28: tax | C28: 법인세율(/세전) — 법인세 = MAX(세전,0) × 세율 | E28: =IFERROR(subQ!E18/subQ!E17,"") | F28: =IFERROR(subQ!F18/subQ!F17,"") | G28: =IFERROR(subQ!G18/subQ!G17,"") | H28: =IFERROR(subQ!H18/subQ!H17,"") | I28: =IFERROR(subQ!I18/subQ!I17,"") | J28: =IFERROR(subQ!J18/subQ!J17,"") | K28: =IFERROR(subQ!K18/subQ!K17,"") | L28: =IFERROR(subQ!L18/subQ!L17,"") | ... AB28: =IFERROR(subQ!AB18/subQ!AB17,"") | AC28: =$D$51 | AD28: =$D$51 | AE28: =IFERROR(subQ!AE18/subQ!AE17,"") | AF28: =$D$51 | AG28: =$D$51 | AH28: =$D$51 | AI28: =$D$51 | AJ28: =IFERROR(subQ!AJ18/subQ!AJ17,"") | AK28: =$D$51 | AL28: =$D$51 | AM28: =$D$51 | AN28: =$D$51 | AO28: =IFERROR(subQ!AO18/subQ!AO17,"")
A29: drv:지배주주순이익 | B29: ratio | C29: 지배주주 비중(/당기순이익) | E29: =IFERROR(subQ!E20/subQ!E19,"") | F29: =IFERROR(subQ!F20/subQ!F19,"") | G29: =IFERROR(subQ!G20/subQ!G19,"") | H29: =IFERROR(subQ!H20/subQ!H19,"") | I29: =IFERROR(subQ!I20/subQ!I19,"") | J29: =IFERROR(subQ!J20/subQ!J19,"") | K29: =IFERROR(subQ!K20/subQ!K19,"") | L29: =IFERROR(subQ!L20/subQ!L19,"") | ... AB29: =IFERROR(subQ!AB20/subQ!AB19,"") | AC29: =$D$53 | AD29: =$D$53 | AE29: =IFERROR(subQ!AE20/subQ!AE19,"") | AF29: =$D$53 | AG29: =$D$53 | AH29: =$D$53 | AI29: =$D$53 | AJ29: =IFERROR(subQ!AJ20/subQ!AJ19,"") | AK29: =$D$53 | AL29: =$D$53 | AM29: =$D$53 | AN29: =$D$53 | AO29: =IFERROR(subQ!AO20/subQ!AO19,"")
A30: drv:감가상각비 | B30: abs | C30: 감가상각비 (가정, 억원) | E30: =subQ!E21 | F30: =subQ!F21 | G30: =subQ!G21 | H30: =subQ!H21 | I30: =subQ!I21 | J30: =subQ!J21 | K30: =subQ!K21 | L30: =subQ!L21 | ... AB30: =subQ!AB21 | AC30: 8.59 | AD30: 8.59 | AE30: =subQ!AE21 | AF30: 8.59 | AG30: 8.59 | AH30: 8.59 | AI30: 8.59 | AJ30: =subQ!AJ21 | AK30: 8.59 | AL30: 8.59 | AM30: 8.59 | AN30: 8.59 | AO30: =subQ!AO21
A31: drv:부채총계 | B31: qoq | C31: 부채총계 QoQ | G31: =IFERROR(subQ!G24/subQ!E24-1,"") | H31: =IFERROR(subQ!H24/subQ!G24-1,"") | I31: =IFERROR(subQ!I24/subQ!H24-1,"") | J31: =IFERROR(subQ!J24/subQ!I24-1,"") | L31: =IFERROR(subQ!L24/subQ!J24-1,"") | M31: =IFERROR(subQ!M24/subQ!L24-1,"") | N31: =IFERROR(subQ!N24/subQ!M24-1,"") | O31: =IFERROR(subQ!O24/subQ!N24-1,"") | Q31: =IFERROR(subQ!Q24/subQ!O24-1,"") | R31: =IFERROR(subQ!R24/subQ!Q24-1,"") | S31: =IFERROR(subQ!S24/subQ!R24-1,"") | T31: =IFERROR(subQ!T24/subQ!S24-1,"") | V31: =IFERROR(subQ!V24/subQ!T24-1,"") | W31: =IFERROR(subQ!W24/subQ!V24-1,"") | X31: =IFERROR(subQ!X24/subQ!W24-1,"") | Y31: =IFERROR(subQ!Y24/subQ!X24-1,"") | AA31: =IFERROR(subQ!AA24/subQ!Y24-1,"") | AB31: =IFERROR(subQ!AB24/subQ!AA24-1,"") | AC31: -1.982e-06 | AD31: 0 | AF31: 0 | AG31: 0 | AH31: 0 | AI31: 0 | AK31: 0 | AL31: 0 | AM31: 0 | AN31: 0
A32: drv:자본총계 | B32: roll | C32: 자본총계 기타변동(배당 등, 억원) | G32: =IFERROR(subQ!E25+subQ!G19-subQ!G25,"") | H32: =IFERROR(subQ!G25+subQ!H19-subQ!H25,"") | I32: =IFERROR(subQ!H25+subQ!I19-subQ!I25,"") | J32: =IFERROR(subQ!I25+subQ!J19-subQ!J25,"") | L32: =IFERROR(subQ!J25+subQ!L19-subQ!L25,"") | M32: =IFERROR(subQ!L25+subQ!M19-subQ!M25,"") | N32: =IFERROR(subQ!M25+subQ!N19-subQ!N25,"") | O32: =IFERROR(subQ!N25+subQ!O19-subQ!O25,"") | Q32: =IFERROR(subQ!O25+subQ!Q19-subQ!Q25,"") | R32: =IFERROR(subQ!Q25+subQ!R19-subQ!R25,"") | S32: =IFERROR(subQ!R25+subQ!S19-subQ!S25,"") | T32: =IFERROR(subQ!S25+subQ!T19-subQ!T25,"") | V32: =IFERROR(subQ!T25+subQ!V19-subQ!V25,"") | W32: =IFERROR(subQ!V25+subQ!W19-subQ!W25,"") | X32: =IFERROR(subQ!W25+subQ!X19-subQ!X25,"") | Y32: =IFERROR(subQ!X25+subQ!Y19-subQ!Y25,"") | AA32: =IFERROR(subQ!Y25+subQ!AA19-subQ!AA25,"") | AB32: =IFERROR(subQ!AA25+subQ!AB19-subQ!AB25,"") | AC32: -0.005551127 | AD32: 0.005336598 | AF32: -0.009519283 | AG32: 0.003707072 | AH32: 0.001647216 | AI32: -0.009140911 | AK32: 0.007801071 | AL32: -0.009596813 | AM32: 0.000538047 | AN32: 0.002579829
A33: drv:지배주주지분 | B33: roll | C33: 지배주주지분 기타변동(배당 등, 억원) | G33: =IFERROR(subQ!E26+subQ!G20-subQ!G26,"") | H33: =IFERROR(subQ!G26+subQ!H20-subQ!H26,"") | I33: =IFERROR(subQ!H26+subQ!I20-subQ!I26,"") | J33: =IFERROR(subQ!I26+subQ!J20-subQ!J26,"") | L33: =IFERROR(subQ!J26+subQ!L20-subQ!L26,"") | M33: =IFERROR(subQ!L26+subQ!M20-subQ!M26,"") | N33: =IFERROR(subQ!M26+subQ!N20-subQ!N26,"") | O33: =IFERROR(subQ!N26+subQ!O20-subQ!O26,"") | Q33: =IFERROR(subQ!O26+subQ!Q20-subQ!Q26,"") | R33: =IFERROR(subQ!Q26+subQ!R20-subQ!R26,"") | S33: =IFERROR(subQ!R26+subQ!S20-subQ!S26,"") | T33: =IFERROR(subQ!S26+subQ!T20-subQ!T26,"") | V33: =IFERROR(subQ!T26+subQ!V20-subQ!V26,"") | W33: =IFERROR(subQ!V26+subQ!W20-subQ!W26,"") | X33: =IFERROR(subQ!W26+subQ!X20-subQ!X26,"") | Y33: =IFERROR(subQ!X26+subQ!Y20-subQ!Y26,"") | AA33: =IFERROR(subQ!Y26+subQ!AA20-subQ!AA26,"") | AB33: =IFERROR(subQ!AA26+subQ!AB20-subQ!AB26,"") | AC33: 0.003500113 | AD33: -0.001194358 | AF33: -0.001133734 | AG33: -0.001826434 | AH33: -0.000605712 | AI33: 0.005130087 | AK33: 0.001970908 | AL33: -0.000921222 | AM33: -0.000795995 | AN33: 7.6235e-05
A34: drv:총차입금 | B34: qoq | C34: 총차입금 QoQ | G34: =IFERROR(subQ!G27/subQ!E27-1,"") | H34: =IFERROR(subQ!H27/subQ!G27-1,"") | I34: =IFERROR(subQ!I27/subQ!H27-1,"") | J34: =IFERROR(subQ!J27/subQ!I27-1,"") | L34: =IFERROR(subQ!L27/subQ!J27-1,"") | M34: =IFERROR(subQ!M27/subQ!L27-1,"") | N34: =IFERROR(subQ!N27/subQ!M27-1,"") | O34: =IFERROR(subQ!O27/subQ!N27-1,"") | Q34: =IFERROR(subQ!Q27/subQ!O27-1,"") | R34: =IFERROR(subQ!R27/subQ!Q27-1,"") | S34: =IFERROR(subQ!S27/subQ!R27-1,"") | T34: =IFERROR(subQ!T27/subQ!S27-1,"") | V34: =IFERROR(subQ!V27/subQ!T27-1,"") | W34: =IFERROR(subQ!W27/subQ!V27-1,"") | X34: =IFERROR(subQ!X27/subQ!W27-1,"") | Y34: =IFERROR(subQ!Y27/subQ!X27-1,"") | AA34: =IFERROR(subQ!AA27/subQ!Y27-1,"") | AB34: =IFERROR(subQ!AB27/subQ!AA27-1,"") | AC34: -2.135e-06 | AD34: 0 | AF34: 0 | AG34: 0 | AH34: 0 | AI34: 0 | AK34: 0 | AL34: 0 | AM34: 0 | AN34: 0
A35: drv:순차입금 | B35: qoq | C35: 순차입금 QoQ | G35: =IFERROR(subQ!G28/subQ!E28-1,"") | H35: =IFERROR(subQ!H28/subQ!G28-1,"") | I35: =IFERROR(subQ!I28/subQ!H28-1,"") | J35: =IFERROR(subQ!J28/subQ!I28-1,"") | L35: =IFERROR(subQ!L28/subQ!J28-1,"") | M35: =IFERROR(subQ!M28/subQ!L28-1,"") | N35: =IFERROR(subQ!N28/subQ!M28-1,"") | O35: =IFERROR(subQ!O28/subQ!N28-1,"") | Q35: =IFERROR(subQ!Q28/subQ!O28-1,"") | R35: =IFERROR(subQ!R28/subQ!Q28-1,"") | S35: =IFERROR(subQ!S28/subQ!R28-1,"") | T35: =IFERROR(subQ!T28/subQ!S28-1,"") | V35: =IFERROR(subQ!V28/subQ!T28-1,"") | W35: =IFERROR(subQ!W28/subQ!V28-1,"") | X35: =IFERROR(subQ!X28/subQ!W28-1,"") | Y35: =IFERROR(subQ!Y28/subQ!X28-1,"") | AA35: =IFERROR(subQ!AA28/subQ!Y28-1,"") | AB35: =IFERROR(subQ!AB28/subQ!AA28-1,"") | AC35: 0.065743088 | AD35: 0.061136272 | AF35: 0.057567068 | AG35: 0.054167406 | AH35: 0.050704953 | AI35: 0.047514457 | AK35: 0.044485579 | AL35: 0.041702172 | AM35: 0.039129387 | AN35: 0.036979798
A36: drv:이자발생자산 | B36: qoq | C36: 이자발생자산 QoQ | G36: =IFERROR(subQ!G29/subQ!E29-1,"") | H36: =IFERROR(subQ!H29/subQ!G29-1,"") | I36: =IFERROR(subQ!I29/subQ!H29-1,"") | J36: =IFERROR(subQ!J29/subQ!I29-1,"") | L36: =IFERROR(subQ!L29/subQ!J29-1,"") | M36: =IFERROR(subQ!M29/subQ!L29-1,"") | N36: =IFERROR(subQ!N29/subQ!M29-1,"") | O36: =IFERROR(subQ!O29/subQ!N29-1,"") | Q36: =IFERROR(subQ!Q29/subQ!O29-1,"") | R36: =IFERROR(subQ!R29/subQ!Q29-1,"") | S36: =IFERROR(subQ!S29/subQ!R29-1,"") | T36: =IFERROR(subQ!T29/subQ!S29-1,"") | V36: =IFERROR(subQ!V29/subQ!T29-1,"") | W36: =IFERROR(subQ!W29/subQ!V29-1,"") | X36: =IFERROR(subQ!X29/subQ!W29-1,"") | Y36: =IFERROR(subQ!Y29/subQ!X29-1,"") | AA36: =IFERROR(subQ!AA29/subQ!Y29-1,"") | AB36: =IFERROR(subQ!AB29/subQ!AA29-1,"") | AC36: -0.35512549 | AD36: -0.54585846 | AF36: -1.2006988 | AG36: 5.954039 | AH36: 0.84488284 | AI36: 0.45095804 | AK36: 0.30477722 | AL36: 0.22871151 | AM36: 0.18191576 | AN36: 0.15119149
A37: drv:현금및현금성자산 | B37: qoq | C37: 현금및현금성자산 QoQ | G37: =IFERROR(subQ!G30/subQ!E30-1,"") | H37: =IFERROR(subQ!H30/subQ!G30-1,"") | I37: =IFERROR(subQ!I30/subQ!H30-1,"") | J37: =IFERROR(subQ!J30/subQ!I30-1,"") | L37: =IFERROR(subQ!L30/subQ!J30-1,"") | M37: =IFERROR(subQ!M30/subQ!L30-1,"") | N37: =IFERROR(subQ!N30/subQ!M30-1,"") | O37: =IFERROR(subQ!O30/subQ!N30-1,"") | Q37: =IFERROR(subQ!Q30/subQ!O30-1,"") | R37: =IFERROR(subQ!R30/subQ!Q30-1,"") | S37: =IFERROR(subQ!S30/subQ!R30-1,"") | T37: =IFERROR(subQ!T30/subQ!S30-1,"") | V37: =IFERROR(subQ!V30/subQ!T30-1,"") | W37: =IFERROR(subQ!W30/subQ!V30-1,"") | X37: =IFERROR(subQ!X30/subQ!W30-1,"") | Y37: =IFERROR(subQ!Y30/subQ!X30-1,"") | AA37: =IFERROR(subQ!AA30/subQ!Y30-1,"") | AB37: =IFERROR(subQ!AB30/subQ!AA30-1,"")
A38: drv:CAPEX | B38: yoy | C38: CAPEX YoY | J38: =IFERROR(subQ!J31/subQ!E31-1,"") | L38: =IFERROR(subQ!L31/subQ!G31-1,"") | M38: =IFERROR(subQ!M31/subQ!H31-1,"") | N38: =IFERROR(subQ!N31/subQ!I31-1,"") | O38: =IFERROR(subQ!O31/subQ!J31-1,"") | Q38: =IFERROR(subQ!Q31/subQ!L31-1,"") | R38: =IFERROR(subQ!R31/subQ!M31-1,"") | S38: =IFERROR(subQ!S31/subQ!N31-1,"") | T38: =IFERROR(subQ!T31/subQ!O31-1,"") | V38: =IFERROR(subQ!V31/subQ!Q31-1,"") | W38: =IFERROR(subQ!W31/subQ!R31-1,"") | X38: =IFERROR(subQ!X31/subQ!S31-1,"") | Y38: =IFERROR(subQ!Y31/subQ!T31-1,"") | AA38: =IFERROR(subQ!AA31/subQ!V31-1,"") | AB38: =IFERROR(subQ!AB31/subQ!W31-1,"") | AC38: 0.025046689 | AD38: 0.047030472 | AF38: -0.46821319 | AG38: -0.023896293 | AH38: 0 | AI38: 0 | AK38: 0 | AL38: 0 | AM38: 0 | AN38: 0
A39: drv:영업활동현금흐름 | B39: yoy | C39: 영업활동현금흐름 YoY | J39: =IFERROR(subQ!J32/subQ!E32-1,"") | L39: =IFERROR(subQ!L32/subQ!G32-1,"") | M39: =IFERROR(subQ!M32/subQ!H32-1,"") | N39: =IFERROR(subQ!N32/subQ!I32-1,"") | O39: =IFERROR(subQ!O32/subQ!J32-1,"") | Q39: =IFERROR(subQ!Q32/subQ!L32-1,"") | R39: =IFERROR(subQ!R32/subQ!M32-1,"") | S39: =IFERROR(subQ!S32/subQ!N32-1,"") | T39: =IFERROR(subQ!T32/subQ!O32-1,"") | V39: =IFERROR(subQ!V32/subQ!Q32-1,"") | W39: =IFERROR(subQ!W32/subQ!R32-1,"") | X39: =IFERROR(subQ!X32/subQ!S32-1,"") | Y39: =IFERROR(subQ!Y32/subQ!T32-1,"") | AA39: =IFERROR(subQ!AA32/subQ!V32-1,"") | AB39: =IFERROR(subQ!AB32/subQ!W32-1,"")
A40: drv:주식수 | B40: qoq | C40: 주식수 QoQ | G40: =IFERROR(subQ!G33/subQ!E33-1,"") | H40: =IFERROR(subQ!H33/subQ!G33-1,"") | I40: =IFERROR(subQ!I33/subQ!H33-1,"") | J40: =IFERROR(subQ!J33/subQ!I33-1,"") | L40: =IFERROR(subQ!L33/subQ!J33-1,"") | M40: =IFERROR(subQ!M33/subQ!L33-1,"") | N40: =IFERROR(subQ!N33/subQ!M33-1,"") | O40: =IFERROR(subQ!O33/subQ!N33-1,"") | Q40: =IFERROR(subQ!Q33/subQ!O33-1,"") | R40: =IFERROR(subQ!R33/subQ!Q33-1,"") | S40: =IFERROR(subQ!S33/subQ!R33-1,"") | T40: =IFERROR(subQ!T33/subQ!S33-1,"") | V40: =IFERROR(subQ!V33/subQ!T33-1,"") | W40: =IFERROR(subQ!W33/subQ!V33-1,"") | X40: =IFERROR(subQ!X33/subQ!W33-1,"") | Y40: =IFERROR(subQ!Y33/subQ!X33-1,"") | AA40: =IFERROR(subQ!AA33/subQ!Y33-1,"") | AB40: =IFERROR(subQ!AB33/subQ!AA33-1,"") | AC40: 0 | AD40: 0 | AF40: 0 | AG40: 0 | AH40: 0 | AI40: 0 | AK40: 0 | AL40: 0 | AM40: 0 | AN40: 0
A41: drv:DPS | B41: abs | C41: DPS (가정, 원) | E41: =subQ!E36 | F41: =subQ!F36 | G41: =subQ!G36 | H41: =subQ!H36 | I41: =subQ!I36 | J41: =subQ!J36 | K41: =subQ!K36 | L41: =subQ!L36 | ... AB41: =subQ!AB36 | AD41: 0 | AE41: =subQ!AE36 | AI41: 0 | AJ41: =subQ!AJ36 | AN41: 0 | AO41: =subQ!AO36
B43: 3. 밸류에이션·스칼라 | C43: 노란 셀 = 가정. '연결' 표시는 추정 전 분기 수식이 이 셀을 참조한다는 뜻
A44: sc:종가 | C44: 종가 | D44: 2200 | E44: 원 — 네이버 정규장 종가(aik 확정종가 대조 · aik 2,300원)
A45: sc:기준일 | C45: 기준일 | D45: 20261013 | E45: 종가 기준일
A46: sc:COE | C46: COE | D46: 0.09 | E46: 자기자본비용(가정) — TP 적정 PBR = ROE/COE
A47: sc:PER_lo | C47: PER_lo | D47: 16.5 | E47: PER 밴드 하단(배) — hist_quarterly(분기 평균가 ÷ TTM EPS, 8분기, 25/50/75 백분위) · 캡 5~30배 적용(원값 16.5/18.9/269.8)
A48: sc:PER_mid | C48: PER_mid | D48: 18.9 | E48: PER 밴드 중단(배)
A49: sc:PER_hi | C49: PER_hi | D49: 30 | E49: PER 밴드 상단(배)
A50: sc:EPS_Y1가중 | C50: EPS_Y1가중 | D50: 0.5 | E50: 12M fwd EPS = FY(last_actual연도)E × w + FY+1E × (1−w) — 기준 분기 2Q 이면 0.5(가정)
A51: sc:세율 | C51: 세율 | D51: 0.20947797 | E51: 연결 — 법인세 = MAX(세전,0) × 세율(역산, 재현 오차 ≤ 0.05억 · 모델 assumptions 0.2094) · 최근 12분기 유효세율 214.5% 가 5~27% 밖 → 클립 대신 최근 8분기 중 세전 > 0 인 3분기(2025Q2~2026Q2)의 법인세/세전 중위 20.9%
A52: sc:판관비율 | C52: 판관비율 | D52: 0.079494943 | E52: 연결 — 판관비 = 매출액 × 판관비율(역산, 재현 오차 ≤ 0.05억 · 모델 assumptions 0.0795)
A53: sc:지배주주비중 | C53: 지배주주비중 | D53: 0.4000396 | E53: 연결 — 지배주주순이익 = 당기순이익 × 비중(역산, 재현 오차 ≤ 0.05억)
A54: sc:이자율_자산 | C54: 이자율_자산 | D54: 0.01418342 | E54: 연결 — 이자손익 = (전분기 이자발생자산 × 자산이자율 − 전분기 총차입금 × 부채이자율)/4(역산, 재현 오차 ≤ 0.05억 · 모델 assumptions 0.0142)
A55: sc:이자율_부채 | C55: 이자율_부채 | D55: 0.026824099 | E55: 연결 — 같은 수식의 부채 쪽(총차입금 행이 없으면 0)(역산, 재현 오차 ≤ 0.05억 · 모델 assumptions 0.0268)
A56: sc:배당성향 | C56: 배당성향 | D56: 0 | E56: 배당성향(참고 — 모델은 직전 DPS 유지·Q2 지급 가정)
A57: sc:외화순노출_백만$ | C57: 외화순노출_백만$ | E57: 외화 순노출 × Δ기말환율 (외화 시트 방식) — 외화 순노출 미공시(face) → 0 + 표기
A58: sc:헤지비율 | C58: 헤지비율 | E58: sls 없음
A59: sc:헤지환율_약정 | C59: 헤지환율_약정 | E59: sls 없음

Sheet BS연결
B1: (백만원) | C1: 이름: BS연결H | E1: 4Q21 | F1: 2021 | G1: 1Q22 | H1: 2Q22 | I1: 3Q22 | J1: 4Q22 | K1: 2022 | L1: 1Q23 | M1: 2Q23 | N1: 3Q23 | O1: 4Q23 | P1: 2023 | Q1: 1Q24 | R1: 2Q24 | S1: 3Q24 | T1: 4Q24 | U1: 2024 | V1: 1Q25 | W1: 2Q25 | X1: 3Q25 | Y1: 4Q25 | Z1: 2025 | AA1: 1Q26 | AB1: 2Q26 | AC1: 3Q26 | AD1: 4Q26 | AE1: 2026 | AF1: 1Q27 | AG1: 2Q27 | AH1: 3Q27 | AI1: 4Q27 | AJ1: 2027 | AK1: 1Q28 | AL1: 2Q28 | AM1: 3Q28 | AN1: 4Q28 | AO1: 2028
B2: 연결 | D2: fin json(kship_fin.py)
B3: 한국선재(연) | C3: UPDATE: 26-10-13 | E3: 1 | F3: 2 | G3: 3 | H3: 4 | I3: 5 | J3: 6 | K3: 7 | L3: 8 | M3: 9 | N3: 10 | O3: 11 | P3: 12 | Q3: 13 | R3: 14 | S3: 15 | T3: 16 | U3: 17 | V3: 18 | W3: 19 | X3: 20 | Y3: 21 | Z3: 22 | AA3: 23 | AB3: 24 | AC3: 25 | AD3: 26 | AE3: 27 | AF3: 28 | AG3: 29 | AH3: 30 | AI3: 31 | AJ3: 32 | AK3: 33 | AL3: 34 | AM3: 35 | AN3: 36 | AO3: 37
B4: Account Code | C4: AccountNAME | E4: 2021.12 | F4: 2021.12A | G4: 2022.03 | H4: 2022.06 | I4: 2022.09 | J4: 2022.12 | K4: 2022.12A | L4: 2023.03 | M4: 2023.06 | N4: 2023.09 | O4: 2023.12 | P4: 2023.12A | Q4: 2024.03 | R4: 2024.06 | S4: 2024.09 | T4: 2024.12 | U4: 2024.12A | V4: 2025.03 | W4: 2025.06 | X4: 2025.09 | Y4: 2025.12 | Z4: 2025.12A | AA4: 2026.03 | AB4: 2026.06 | AC4: 2026.09 | AD4: 2026.12 | AE4: 2026.12A | AF4: 2027.03 | AG4: 2027.06 | AH4: 2027.09 | AI4: 2027.12 | AJ4: 2027.12A | AK4: 2028.03 | AL4: 2028.06 | AM4: 2028.09 | AN4: 2028.12 | AO4: 2028.12A
A5: 1 | C5: 유동자산 | E5: 128783.58 | F5: 128783.58 | G5: 120306.92 | H5: 131396.07 | I5: 134033.31 | J5: 133702.02 | K5: 133702.02 | L5: 141614.08 | M5: 145407.39 | N5: 142787.04 | O5: 136603.81 | P5: 136603.81 | Q5: 142221.05 | R5: 140110.2 | S5: 126204.84 | T5: 135071.57 | U5: 135071.57 | V5: 139396.69 | W5: 136584.72 | X5: 136085.34 | Y5: 159679.18 | Z5: 159679.18 | AA5: 168118.69 | AB5: 158387.87
A6: 1 | C6: 현금및현금성자산 | E6: 13747.89 | F6: 13747.89 | G6: 15481.2 | H6: 6807.06 | I6: 8409.03 | J6: 10624.64 | K6: 10624.64 | L6: 5378.3 | M6: 6760.54 | N6: 8304.65 | O6: 17625.28 | P6: 17625.28 | Q6: 14072.42 | R6: 12155.05 | S6: 12829.42 | T6: 11545.19 | U6: 11545.19 | V6: 13828.71 | W6: 7134.25 | X6: 6909.09 | Y6: 30670.84 | Z6: 30670.84 | AA6: 19668.35 | AB6: 22556.87
A7: 1 | C7: 매출채권및기타채권 | E7: 30020.98 | F7: 30020.98 | G7: 34467.9 | H7: 33354.23 | I7: 37882.07 | J7: 37004.14 | K7: 37004.14 | L7: 40241.39 | M7: 38813.57 | N7: 42333.99 | O7: 37036.62 | P7: 37036.62 | Q7: 34665.73 | R7: 39956.6 | S7: 34878.15 | T7: 38211.65 | U7: 38211.65 | V7: 35341.44 | W7: 35732.61 | X7: 36441.44 | Y7: 37383.56 | Z7: 37383.56 | AA7: 42704.15 | AB7: 46207
A8: 1 | C8: 재고자산 | E8: 67720.78 | F8: 67720.78 | G8: 68763.07 | H8: 87510.11 | I8: 84232.85 | J8: 83764.55 | K8: 83764.55 | L8: 93458.61 | M8: 97535.85 | N8: 90942.65 | O8: 80846.32 | P8: 80846.32 | Q8: 90196.25 | R8: 87004.8 | S8: 77560.77 | T8: 84041.37 | U8: 84041.37 | V8: 72455.68 | W8: 80046.91 | X8: 86785.69 | Y8: 86092.85 | Z8: 86092.85 | AA8: 86684.45 | AB8: 87679.63
A9: 1 | C9: 기타유동금융자산 | E9: 297.98 | F9: 297.98 | G9: 298.73 | H9: 299.72 | I9: 2069.66 | J9: 409.71 | K9: 409.71 | L9: 389.79 | M9: 392.66 | Y9: 2441.98 | Z9: 2441.98 | AA9: 8331.42
A10: 1 | C10: 기타유동자산 | E10: 1046.73 | F10: 1046.73 | G10: 1296.03 | H10: 3424.94 | I10: 1439.7 | J10: 1898.97 | K10: 1898.97 | L10: 2146 | M10: 1904.77 | N10: 1205.75 | O10: 1005.78 | P10: 1005.78 | Q10: 1835.77 | R10: 993.76 | S10: 936.5 | T10: 1273.36 | U10: 1273.36 | V10: 651.12 | W10: 1371.05 | X10: 2649.64 | Y10: 2804.92 | Z10: 2804.92 | AA10: 2561.4 | AB10: 1819.38
A11: 1 | C11: 매각예정비유동자산및처분자산 | E11: 15949.22 | F11: 15949.22 | I11: 0
A12: 1 | C12: 비유동자산 | E12: 120984.81 | F12: 120984.81 | G12: 122279 | H12: 123202.95 | I12: 123038.23 | J12: 121157.68 | K12: 121157.68 | L12: 120394.59 | M12: 124522.46 | N12: 130532.16 | O12: 134117.46 | P12: 134117.46 | Q12: 132563.48 | R12: 133097.98 | S12: 132563.46 | T12: 146356.79 | U12: 146356.79 | V12: 154123.63 | W12: 158729.62 | X12: 178527.47 | Y12: 175661.2 | Z12: 175661.2 | AA12: 201330.87 | AB12: 207817.27
A13: 1 | C13: 장기금융자산 | E13: 1431.33 | F13: 1431.33 | G13: 1100.32 | H13: 1100.32 | I13: 1100.32 | J13: 1100.32 | K13: 1100.32 | L13: 1100.32 | M13: 1100.32 | N13: 1100.32 | O13: 824.43 | P13: 824.43 | Q13: 824.43 | R13: 232.43 | S13: 328.01 | T13: 13244.31 | U13: 13244.31 | V13: 13343.48 | W13: 11797.35 | X13: 19306.18 | Y13: 847.86 | Z13: 847.86 | AA13: 1753.08 | AB13: 1874.24
A14: 1 | C14: 투자자산 | E14: 3232.7 | F14: 3232.7 | G14: 3627.75 | H14: 2451.16 | I14: 2200.37 | J14: 2300.91 | K14: 2300.91 | L14: 2300.65 | M14: 2460.67 | N14: 2328.31 | O14: 4078.78 | P14: 4078.78 | Q14: 3334.56 | R14: 3832.53 | S14: 3648.66 | T14: 15356.23 | U14: 15356.23 | V14: 13343.48 | W14: 11797.35 | X14: 19306.18 | Y14: 847.86 | Z14: 847.86 | AA14: 1753.08 | AB14: 1874.24
A15: 1 | C15: 장기매출채권및기타채권 | E15: 2289.28 | F15: 2289.28 | G15: 2326.96 | H15: 2676.74 | I15: 3235.92 | J15: 2234.53 | K15: 2234.53 | L15: 2264.74 | M15: 2326.5 | N15: 2478.5 | O15: 1839.79 | P15: 1839.79 | Q15: 1893.07 | R15: 1827.05 | S15: 1744.11 | T15: 1501.59 | U15: 1501.59 | V15: 1420.68 | W15: 1175.67 | X15: 726.91 | Y15: 723.1 | Z15: 723.1 | AA15: 735.62 | AB15: 554.44
A16: 1 | C16: 종속기업및관계기업투자 | E16: 1801.37 | F16: 1801.37 | G16: 2527.43 | H16: 1350.84 | I16: 1100.05 | J16: 1200.59 | K16: 1200.59 | L16: 1200.33 | M16: 1360.35 | N16: 1227.99 | O16: 3254.35 | P16: 3254.35 | Q16: 2510.13 | R16: 3600.1 | S16: 3320.65 | T16: 2111.92 | U16: 2111.92 | V16: 0 | W16: 0 | X16: 0
A17: 1 | C17: 유형자산 | E17: 102120.29 | F17: 102120.29 | G17: 102657.56 | H17: 104484.87 | I17: 104156.19 | J17: 103055.01 | K17: 103055.01 | L17: 102290.88 | M17: 101453.37 | N17: 107463.27 | O17: 110158.06 | P17: 110158.06 | Q17: 109447.74 | R17: 109158.98 | S17: 106962.36 | T17: 109022.01 | U17: 109022.01 | V17: 116055.02 | W17: 121928.53 | X17: 133061.24 | Y17: 143859.13 | Z17: 143859.13 | AA17: 167857.02 | AB17: 178990.5
A18: 1 | C18: 사용권자산 | E18: 1148.29 | F18: 1148.29 | G18: 1151.83 | H18: 1120.97 | I18: 1015.99 | J18: 1078.31 | K18: 1078.31 | L18: 1058.42 | M18: 1074.2 | N18: 1065.28 | O18: 886.72 | P18: 886.72 | Q18: 763.3 | R18: 1074.51 | S18: 1093.72 | T18: 858.9 | U18: 858.9 | V18: 850.91 | W18: 810.54 | X18: 690.55 | Y18: 658.08 | Z18: 658.08 | AA18: 1097.31 | AB18: 1031.44
A19: 1 | C19: 기타비유동자산 | E19: 1148.29 | F19: 1148.29 | G19: 1151.83 | H19: 1120.97 | I19: 1015.99 | J19: 1078.31 | K19: 1078.31 | L19: 1058.42 | M19: 1074.2 | N19: 1065.28 | O19: 886.72 | P19: 886.72 | Q19: 763.3 | R19: 1074.51 | S19: 1093.72 | T19: 858.9 | U19: 858.9 | V19: 850.91 | W19: 810.54 | X19: 690.55 | Y19: 658.08 | Z19: 658.08 | AA19: 1097.31 | AB19: 1031.44
A20: 1 | C20: 투자부동산 | E20: 11754.61 | F20: 11754.61 | G20: 11734.68 | H20: 11707 | I20: 11679.31 | J20: 11651.62 | K20: 11651.62 | L20: 11623.94 | M20: 16362.66 | N20: 16317.16 | O20: 16290.49 | P20: 16290.49 | Q20: 16254.41 | R20: 16218.32 | S20: 18088.71 | T20: 18512.27 | U20: 18512.27 | V20: 18443.07 | W20: 19358.9 | X20: 21145.94 | Y20: 22230.49 | Z20: 22230.49 | AA20: 24162.53 | AB20: 18964.52
A21: 1 | C21: 무형자산 | E21: 439.65 | F21: 439.65 | G21: 422.31 | H21: 404.54 | I21: 390.46 | J21: 472.6 | K21: 472.6 | L21: 491.27 | M21: 480.36 | N21: 467.97 | O21: 457.76 | P21: 457.76 | Q21: 449.13 | R21: 441.54 | S21: 453.35 | T21: 483.46 | U21: 483.46 | V21: 501.32 | W21: 1209.68 | X21: 1241.76 | Y21: 1233.54 | Z21: 1233.54 | AA21: 1809.38
A22: 1 | C22: 자산총계 | E22: 249768.39 | F22: 249768.39 | G22: 242585.92 | H22: 254599.01 | I22: 257071.54 | J22: 254859.7 | K22: 254859.7 | L22: 262008.67 | M22: 269929.85 | N22: 273319.2 | O22: 270721.26 | P22: 270721.26 | Q22: 274784.53 | R22: 273208.18 | S22: 258768.3 | T22: 281428.37 | U22: 281428.37 | V22: 293520.32 | W22: 295314.34 | X22: 314612.81 | Y22: 335340.38 | Z22: 335340.38 | AA22: 369449.56 | AB22: 366205.15
A23: 1 | C23: 유동부채 | E23: 124211.41 | F23: 124211.41 | G23: 106730.32 | H23: 118229.07 | I23: 120270.61 | J23: 118720.1 | K23: 118720.1 | L23: 131576.39 | M23: 120991.69 | N23: 117267.56 | O23: 93290.64 | P23: 93290.64 | Q23: 96323.7 | R23: 93227.88 | S23: 79210.86 | T23: 104619.01 | U23: 104619.01 | V23: 116134.8 | W23: 120900.32 | X23: 147396.47 | Y23: 145819.15 | Z23: 145819.15 | AA23: 143724.43 | AB23: 135250.28
A24: 1 | C24: 매입채무및기타채무 | E24: 15074.21 | F24: 15074.21 | G24: 13642.42 | H24: 16353.03 | I24: 15553.65 | J24: 19019.15 | K24: 19019.15 | L24: 15745 | M24: 17635.75 | N24: 12073.89 | O24: 17346.73 | P24: 17346.73 | Q24: 17382.61 | R24: 15785.18 | S24: 7584.09 | T24: 13610.57 | U24: 13610.57 | V24: 8917.89 | W24: 9528.06 | X24: 12880.57 | Y24: 8559.39 | Z24: 8559.39 | AA24: 17953.61 | AB24: 13383.58
A25: 1 | C25: 단기차입금 | E25: 97761.46 | F25: 97761.46 | G25: 69200 | H25: 76300 | I25: 81300 | J25: 73070 | K25: 73070 | L25: 82753 | M25: 86214 | N25: 92360 | O25: 62062.14 | P25: 62062.14 | Q25: 73100 | R25: 70400 | S25: 64850 | T25: 84150 | U25: 84150 | V25: 81450 | W25: 83140 | X25: 89100 | Y25: 105814.67 | Z25: 105814.67 | AA25: 104670.17 | AB25: 111400
A26: 1 | C26: 당기법인세부채(미지급법인세) | E26: 3118.85 | F26: 3118.85 | G26: 1714.12 | H26: 4276.54 | I26: 2775.19 | J26: 3198.36 | K26: 3198.36 | L26: 1805.35 | M26: 1529.14 | N26: 766.29 | R26: 909.62 | S26: 554.96 | T26: 870 | U26: 870 | V26: 563.29 | W26: 832.14 | X26: 407.83 | Y26: 891.68 | Z26: 891.68 | AA26: 516.16 | AB26: 3886.64
A27: 1 | C27: 유동리스부채 | E27: 359.83 | F27: 359.83 | G27: 370.78 | H27: 384.94 | I27: 366.59 | J27: 383.35 | K27: 383.35 | L27: 391.6 | M27: 440.86 | N27: 517.5 | O27: 477.32 | P27: 477.32 | Q27: 428.91 | R27: 594.49 | S27: 666.15 | T27: 641.51 | U27: 641.51 | V27: 1020.1 | W27: 586.89 | X27: 481.46 | Y27: 379.18 | Z27: 379.18 | AA27: 522.92 | AB27: 565.89
A28: 1 | C28: 리스부채 | E28: 1220.25 | F28: 1220.25 | G28: 1225.99 | H28: 1195.39 | I28: 1091.02 | J28: 1155.82 | K28: 1155.82 | L28: 1135.56 | M28: 1150.76 | N28: 1138.43 | O28: 1000.41 | P28: 1000.41 | Q28: 861.17 | R28: 1153.8 | S28: 1167.26 | T28: 1126.03 | U28: 1126.03 | V28: 1060.81 | W28: 972.14 | X28: 800.16 | Y28: 729.78 | Z28: 729.78 | AA28: 1110.21 | AB28: 1044.55
A29: 1 | C29: 단기금융부채 | E29: 3608.91 | F29: 3608.91 | G29: 3599.05 | H29: 3764.4 | I29: 3545.22 | J29: 4211.84 | K29: 4211.84 | L29: 4171.71 | M29: 4180.49 | N29: 4304.32 | O29: 4552.81 | P29: 4552.81 | Q29: 3891.94 | R29: 4692.11 | S29: 4113.58 | T29: 4873.31 | U29: 4873.31 | V29: 14693.01 | W29: 11196.87 | X29: 11248.74 | Y29: 17906.2 | Z29: 17906.2 | AA29: 15371.27 | AB29: 5544.4
A30: 1 | C30: 기타유동금융부채 | E30: 3249.08 | F30: 3249.08 | G30: 3228.27 | H30: 3379.46 | I30: 3178.63 | J30: 3828.49 | K30: 3828.49 | L30: 3780.11 | M30: 3739.63 | N30: 3786.82 | O30: 4075.49 | P30: 4075.49 | Q30: 3463.03 | R30: 4097.62 | S30: 3447.43 | T30: 4231.8 | U30: 4231.8 | V30: 13672.91 | W30: 10609.98 | X30: 10767.28 | Y30: 17527.02 | Z30: 17527.02 | AA30: 14848.35 | AB30: 4978.51
A31: 1 | C31: 기타유동부채 | E31: 4647.99 | F31: 4647.99 | G31: 1097.86 | H31: 856.54 | I31: 596.55 | J31: 2120.74 | K31: 2120.74 | L31: 4001.33 | M31: 1932.31 | N31: 1763.05 | O31: 3328.95 | P31: 3328.95 | Q31: 1949.16 | R31: 1440.98 | S31: 2108.22 | T31: 1115.12 | U31: 1115.12 | V31: 850.67 | W31: 344.57 | X31: 485.47 | Y31: 1742.26 | Z31: 1742.26 | AA31: 1807.83 | AB31: 1035.66
A32: 1 | C32: 비유동부채 | E32: 21639.56 | F32: 21639.56 | G32: 19682.05 | H32: 19430.75 | I32: 19588.83 | J32: 18862.77 | K32: 18862.77 | L32: 13023.26 | M32: 29377.71 | N32: 37094.7 | O32: 33402.75 | P32: 33402.75 | Q32: 33856.67 | R32: 33735.03 | S32: 33570.18 | T32: 31119.03 | U32: 31119.03 | V32: 36590.66 | W32: 29750.8 | X32: 12888.96 | Y32: 40031.84 | Z32: 40031.84 | AA32: 50437.97 | AB32: 51461.09
A33: 1 | C33: 장기차입금 | E33: 8321.4 | F33: 8321.4 | G33: 6000 | H33: 6000 | I33: 6000 | J33: 7000 | K33: 7000 | L33: 1000 | M33: 18600 | N33: 26100 | O33: 23600 | P33: 23600 | Q33: 23600 | R33: 23600 | S33: 23200 | T33: 23200 | U33: 23200 | V33: 23200 | W33: 17000 | Y33: 31760.11 | Z33: 31760.11 | AA33: 41604.61 | AB33: 43133.33
A34: 1 | C34: 확정급여부채 | E34: 3210.15 | F34: 3210.15 | G34: 3576.07 | H34: 3283.56 | I34: 3580.49 | J34: 2990.2 | K34: 2990.2 | L34: 3136.35 | M34: 4623.58 | N34: 4849.93 | O34: 3273.5 | P34: 3273.5 | Q34: 3778.67 | R34: 4533.27 | S34: 4767.03 | T34: 3623.76 | U34: 3623.76 | V34: 4164.49 | W34: 4063.93 | X34: 4275.38
A35: 1 | C35: 이연법인세부채 | E35: 8697.59 | F35: 8697.59 | G35: 8694.76 | H35: 8780.74 | I35: 8777.91 | J35: 7594.1 | K35: 7594.1 | L35: 7586.94 | M35: 4868.24 | N35: 4867.83 | O35: 5270.16 | P35: 5270.16 | Q35: 5269.75 | R35: 4226.45 | S35: 4226.04 | T35: 3594.74 | U35: 3594.74 | V35: 4173.79 | W35: 4303.17 | X35: 4302.43 | Y35: 5519.38 | Z35: 5519.38 | AA35: 5518.99 | AB35: 4699.41
A36: 1 | C36: 비유동리스부채 | E36: 860.42 | F36: 860.42 | G36: 855.21 | H36: 810.45 | I36: 724.43 | J36: 772.47 | K36: 772.47 | L36: 743.96 | M36: 709.9 | N36: 620.93 | O36: 523.09 | P36: 523.09 | Q36: 432.26 | R36: 559.31 | S36: 501.11 | T36: 484.52 | U36: 484.52 | V36: 40.71 | W36: 385.25 | X36: 318.7 | Y36: 350.6 | Z36: 350.6 | AA36: 587.29 | AB36: 478.66
A37: 1 | C37: 장기금융부채 | E37: 1410.42 | F37: 1410.42 | G37: 1411.21 | H37: 1366.45 | I37: 1230.43 | J37: 1278.47 | K37: 1278.47 | L37: 1299.96 | M37: 1285.9 | N37: 1276.93 | O37: 1259.09 | P37: 1259.09 | Q37: 1208.26 | R37: 1375.31 | S37: 1377.11 | T37: 700.52 | U37: 700.52 | V37: 5052.37 | W37: 4383.7 | X37: 4311.15 | Y37: 570.6 | Z37: 570.6 | AA37: 757.29 | AB37: 698.66
A38: 1 | C38: 기타비유동금융부채 | E38: 550 | F38: 550 | G38: 556 | H38: 556 | I38: 506 | J38: 506 | K38: 506 | L38: 556 | M38: 576 | N38: 656 | O38: 736 | P38: 736 | Q38: 776 | R38: 816 | S38: 876 | T38: 216 | U38: 216 | V38: 5011.66 | W38: 3998.45 | X38: 3992.45 | Y38: 220 | Z38: 220 | AA38: 170 | AB38: 220
A39: 1 | C39: 부채총계 | E39: 145850.97 | F39: 145850.97 | G39: 126412.36 | H39: 137659.82 | I39: 139859.45 | J39: 137582.87 | K39: 137582.87 | L39: 144599.65 | M39: 150369.4 | N39: 154362.25 | O39: 126693.39 | P39: 126693.39 | Q39: 130180.38 | R39: 126962.91 | S39: 112781.04 | T39: 135738.03 | U39: 135738.03 | V39: 152725.46 | W39: 150651.12 | X39: 160285.43 | Y39: 185850.99 | Z39: 185850.99 | AA39: 194162.39 | AB39: 186711.37
A40: 1 | C40: 지배주주지분 | E40: 100842.48 | F40: 100842.48 | G40: 112807.35 | H40: 113283.86 | I40: 113018 | J40: 113006.48 | K40: 113006.48 | L40: 112744.65 | M40: 114401.32 | N40: 113558.67 | O40: 121170.84 | P40: 121170.84 | Q40: 121035.37 | R40: 122242.98 | S40: 121814.37 | T40: 120932.72 | U40: 120932.72 | V40: 117914.45 | W40: 120198.15 | X40: 128801.65 | Y40: 123786.51 | Z40: 123786.51 | AA40: 134708.38 | AB40: 137784.22
A41: 1 | C41: 자본금 | E41: 12261.13 | F41: 12261.13 | G41: 12261.13 | H41: 12261.13 | I41: 12261.13 | J41: 12261.13 | K41: 12261.13 | L41: 12261.13 | M41: 12261.13 | N41: 12261.13 | O41: 12261.13 | P41: 12261.13 | Q41: 12261.13 | R41: 12261.13 | S41: 12261.13 | T41: 12261.13 | U41: 12261.13 | V41: 13368.13 | W41: 13368.13 | X41: 13368.13 | Y41: 13368.13 | Z41: 13368.13 | AA41: 13368.13 | AB41: 13368.13
A42: 1 | C42: 자본잉여금 | E42: 19928.82 | F42: 19928.82 | G42: 19928.82 | H42: 19928.82 | I42: 19692.75 | J42: 18226.23 | K42: 18226.23 | L42: 18203.39 | M42: 18203.39 | N42: 17851.98 | O42: 31679.9 | P42: 31679.9 | Q42: 31679.9 | R42: 31679.9 | S42: 31679.9 | T42: 35295.98 | U42: 35295.98 | V42: 32010.34 | W42: 35507.93 | X42: 35513.41 | Y42: 35460.41 | Z42: 35460.41 | AA42: 47378.65 | AB42: 47986.08
A43: 1 | C43: 기타자본 | E43: 744.12 | F43: 744.12 | G43: 1496.28 | H43: 398.14 | I43: 170.03 | J43: 510.25 | K43: 510.25 | L43: 526.69 | M43: 558.77 | N43: 423.13 | O43: 1991.49 | P43: 1991.49 | Q43: 1251.36 | R43: 2322.69 | S43: 2241.84 | T43: -220.78 | U43: -220.78 | V43: -1506.73 | W43: -5948.76 | X43: 1549.25
A44: 1 | C44: 이익잉여금 | E44: 67908.4 | F44: 67908.4 | G44: 79121.12 | H44: 80695.77 | I44: 80894.1 | J44: 82008.88 | K44: 82008.88 | L44: 81753.44 | M44: 83378.03 | N44: 83022.43 | O44: 75238.32 | P44: 75238.32 | Q44: 75842.98 | R44: 75979.26 | S44: 75631.5 | T44: 73596.39 | U44: 73596.39 | V44: 74042.71 | W44: 77270.85 | X44: 78370.85 | Y44: 77377.91 | Z44: 77377.91 | AA44: 76489.74 | AB44: 79155.02
A45: 1 | C45: 비지배주주지분 | E45: 3074.95 | F45: 3074.95 | G45: 3366.2 | H45: 3655.33 | I45: 4194.09 | J45: 4270.35 | K45: 4270.35 | L45: 4664.37 | M45: 5159.13 | N45: 5398.29 | O45: 22857.04 | P45: 22857.04 | Q45: 23568.78 | R45: 24002.29 | S45: 24172.9 | T45: 24757.62 | U45: 24757.62 | V45: 22880.41 | W45: 24465.07 | X45: 25525.74 | Y45: 25702.88 | Z45: 25702.88 | AA45: 40578.79 | AB45: 41709.56
A46: 1 | C46: 자본총계 | E46: 103917.42 | F46: 103917.42 | G46: 116173.55 | H46: 116939.19 | I46: 117212.1 | J46: 117276.83 | K46: 117276.83 | L46: 117409.02 | M46: 119560.46 | N46: 118956.95 | O46: 144027.88 | P46: 144027.88 | Q46: 144604.15 | R46: 146245.27 | S46: 145987.27 | T46: 145690.33 | U46: 145690.33 | V46: 140794.86 | W46: 144663.22 | X46: 154327.38 | Y46: 149489.39 | Z46: 149489.39 | AA46: 175287.17 | AB46: 179493.78
A47: 1 | C47: 부채와자본총계 | E47: 249768.39 | F47: 249768.39 | G47: 242585.92 | H47: 254599.01 | I47: 257071.54 | J47: 254859.7 | K47: 254859.7 | L47: 262008.67 | M47: 269929.85 | N47: 273319.2 | O47: 270721.26 | P47: 270721.26 | Q47: 274784.53 | R47: 273208.18 | S47: 258768.3 | T47: 281428.37 | U47: 281428.37 | V47: 293520.32 | W47: 295314.34 | X47: 314612.81 | Y47: 335340.38 | Z47: 335340.38 | AA47: 369449.56 | AB47: 366205.15
A48: 1 | C48: 총차입금 | E48: 125615.16 | F48: 125615.16 | G48: 92676.87 | H48: 98978.56 | I48: 103800 | J48: 97170 | K48: 97170 | L48: 106853 | M48: 114314 | N48: 124460 | O48: 91662.14 | P48: 91662.14 | Q48: 96700 | R48: 94000 | S48: 88050 | T48: 107350 | U48: 107350 | V48: 114309.95 | W48: 115998.68 | X48: 122373.85 | Y48: 148479.74 | Z48: 148479.74 | AA48: 149680.17 | AB48: 154533.33
A49: 1 | C49: 순차입금 | E49: 111867.27 | F49: 111867.27 | G49: 77195.67 | H49: 92171.5 | I49: 95390.97 | J49: 86545.36 | K49: 86545.36 | L49: 101474.7 | M49: 107553.46 | N49: 116155.35 | O49: 74036.86 | P49: 74036.86 | Q49: 81284.55 | R49: 81844.95 | S49: 75220.58 | T49: 95804.81 | U49: 95804.81 | V49: 83361.5 | W49: 96564.53 | X49: 112165.27 | Y49: 117808.9 | Z49: 117808.9 | AA49: 130011.82 | AB49: 131976.46
A50: 1 | C50: 이자발생자산 | E50: 15179.22 | F50: 15179.22 | G50: 16581.52 | H50: 7907.38 | I50: 9509.35 | J50: 11724.96 | K50: 11724.96 | L50: 6478.62 | M50: 7860.86 | N50: 9404.97 | O50: 18449.71 | P50: 18449.71 | Q50: 16239.88 | R50: 12387.48 | S50: 13157.43 | T50: 24789.5 | U50: 24789.5 | V50: 44291.93 | W50: 31231.5 | X50: 29514.76 | Y50: 31518.7 | Z50: 31518.7 | AA50: 21421.43 | AB50: 24431.11
A51: 1 | C51: 유동성장기부채 | E51: 19532.3 | F51: 19532.3 | G51: 17476.87 | H51: 16678.56 | I51: 16500 | J51: 17100 | K51: 17100 | L51: 23100 | M51: 9500 | N51: 6000 | O51: 6000 | P51: 6000 | V51: 9659.95 | W51: 15858.68 | X51: 33273.85 | Y51: 10904.96 | Z51: 10904.96 | AA51: 3405.39 | AB51: 0
A52: 1 | C52: 당기법인세자산(선급법인세) | O52: 89.81 | P52: 89.81 | Q52: 107.85
A53: 1 | C53: 단기금융상품 | Q53: 1343.03 | V53: 17119.74 | W53: 12299.9 | X53: 3299.49
A54: 1 | C54: 단기금융자산 | Q54: 1343.03 | V54: 17119.74 | W54: 12299.9 | X54: 3299.49
A55: 1 | C55: 단기금융부채(face) | Y55: 105814.67 | Z55: 105814.67 | AA55: 104670.17 | AB55: 111400
A56: 1 | C56: 기타포괄이익누계액 | Y56: -2419.94 | Z56: -2419.94 | AA56: -2528.14 | AB56: -2725.01
A57: 1 | C57: 매출액(수익) | E57: 58902.71 | G57: 61406.78 | H57: 64773.02 | I57: 57703.37 | J57: 61602.39 | K57: 245485.56 | L57: 61668.68 | M57: 66477.86 | N57: 58971.11 | O57: 61330.2 | P57: 248447.85 | Q57: 52985.62 | R57: 59840.34 | S57: 53110.99 | T57: 57511.33 | U57: 223448.28 | V57: 53367.27 | W57: 56100.88 | X57: 56009.15 | Y57: 53923.08 | Z57: 219400.38 | AA57: 66119.84 | AB57: 71721.12
A58: 1 | C58: 매출원가 | E58: 53502.84 | G58: 53759.67 | H58: 54115.03 | I58: 52667.07 | J58: 55099.8 | K58: 215641.57 | L58: 53646.3 | M58: 58263.47 | N58: 53509.25 | O58: 56589.92 | P58: 222008.94 | Q58: 46715.52 | R58: 53533.17 | S58: 47207.51 | T58: 52613.66 | U58: 200069.86 | V58: 48720.45 | W58: 47083.91 | X58: 48593.34 | Y58: 47530.01 | Z58: 191927.71 | AA58: 53140.94 | AB58: 57018.25
A59: 1 | C59: 매출총이익 | E59: 5399.86 | G59: 7647.11 | H59: 10657.98 | I59: 5036.3 | J59: 6502.6 | K59: 29843.99 | L59: 8022.38 | M59: 8214.39 | N59: 5461.86 | O59: 4740.28 | P59: 26438.91 | Q59: 6270.1 | R59: 6307.16 | S59: 5903.47 | T59: 4897.67 | U59: 23378.4 | V59: 4646.83 | W59: 9016.96 | X59: 7415.81 | Y59: 6393.07 | Z59: 27472.67 | AA59: 12978.9 | AB59: 14702.87
A60: 1 | C60: 판관비 | E60: 3114.29 | G60: 4143.02 | H60: 4370.3 | I60: 4400.23 | J60: 5645.22 | K60: 18558.77 | L60: 4549.21 | M60: 4858.2 | N60: 4518.83 | O60: 7390.44 | P60: 21316.68 | Q60: 4416.81 | R60: 4176.07 | S60: 4629.26 | T60: 4125.79 | U60: 17347.93 | V60: 4392.6 | W60: 3848.44 | X60: 4627.74 | Y60: 6429.21 | Z60: 19297.99 | AA60: 4818.98 | AB60: 5476.91
A61: 1 | C61: 영업이익 | E61: 2285.57 | G61: 3504.09 | H61: 6287.68 | I61: 636.08 | J61: 857.38 | K61: 11285.23 | L61: 3473.17 | M61: 3356.19 | N61: 943.03 | O61: -2650.17 | P61: 5122.22 | Q61: 1853.28 | R61: 2131.09 | S61: 1274.21 | T61: 771.87 | U61: 6030.45 | V61: 254.23 | W61: 5168.52 | X61: 2788.07 | Y61: -36.15 | Z61: 8174.67 | AA61: 8159.92 | AB61: 9225.96
A62: 1 | C62: 금융수익 | E62: 139.53 | G62: 288.08 | H62: 655.8 | I62: 1094.05 | J62: -128.25 | K62: 1909.68 | L62: 666.81 | M62: 299.59 | N62: 456.46 | O62: 265.08 | P62: 1687.94 | Q62: 558.67 | R62: 372.34 | S62: 58 | T62: 1006.06 | U62: 1995.07 | V62: 388.26 | W62: 4979.8 | X62: 7.12 | Y62: -2612.72 | Z62: 2762.46 | AA62: 6882.92 | AB62: 13660.59
A63: 1 | C63: 금융비용 | E63: 824.19 | G63: 1211.56 | H63: 1157.98 | I63: 1070.87 | J63: 1949.48 | K63: 5389.89 | L63: 1837.02 | M63: 1721.34 | N63: 1717.07 | O63: 1729.87 | P63: 7005.3 | Q63: 1298.12 | R63: 1266.93 | S63: 1271.32 | T63: 896.57 | U63: 4732.94 | V63: 1160.4 | W63: 2654.33 | X63: 685.32 | Y63: 577.52 | Z63: 5077.57 | AA63: 19143.94 | AB63: 15289.12
A64: 1 | C64: 기타영업외수익 | E64: 370.5 | G64: 9181.55 | H64: 22.39 | I64: 108.46 | J64: 2346.04 | K64: 11658.44 | L64: 166.8 | M64: 113.4 | N64: 203.61 | O64: 171.49 | P64: 655.3 | Q64: 222.98 | R64: 97.73 | S64: 121.47 | T64: 68.3 | U64: 510.48 | V64: 45.81 | W64: 147.46 | X64: 211.99 | Y64: 86.91 | Z64: 492.17 | AA64: 161.21 | AB64: 80.14
A65: 1 | C65: 기타영업외비용 | E65: 48.02 | G65: 234.91 | H65: 6.07 | I65: 10.77 | J65: 456.76 | K65: 708.51 | L65: 99.75 | M65: 297.51 | N65: 86.22 | O65: 2787.3 | P65: 3270.78 | Q65: 92.15 | R65: 19 | S65: 298.16 | T65: 2754.4 | U65: 3163.71 | V65: 8.23 | W65: 790.64 | X65: 208.99 | Y65: 335.94 | Z65: 1343.8 | AA65: 255.63 | AB65: 72.6
A66: 1 | C66: 법인세비용차감전계속사업이익 | E66: 1902.96 | G66: 11501.15 | H66: 5786.34 | I66: 734.27 | J66: 642.06 | K66: 18663.82 | L66: 2353.29 | M66: 1791.16 | N66: -196.92 | O66: -6733.52 | P66: -2785.99 | Q66: 1240.57 | R66: 1306.65 | S66: -120.63 | T66: -1816.59 | U66: 610 | V66: -518.84 | W66: 6850.82 | X66: 2112.87 | Y66: -3475.41 | Z66: 4969.44 | AA66: -4195.52 | AB66: 7604.98
A67: 1 | C67: 법인세비용 | E67: 2873.35 | G67: -2.82 | H67: 4315.52 | I67: -2.82 | J67: -610.78 | K67: 3699.1 | L67: -7.15 | M67: -913.29 | N67: -0.41 | O67: -416.23 | P67: -1337.08 | Q67: -0.41 | R67: 288.97 | S67: 117.95 | T67: -279.54 | U67: 126.97 | V67: -0.41 | W67: 1434.79 | X67: 2.24 | Y67: -192.26 | Z67: 1244.36 | AA67: -175.94 | AB67: 3637.52
A68: 1 | C68: 당기순이익 | E68: -970.39 | G68: 11503.97 | H68: 1470.82 | I68: 737.1 | J68: 1252.84 | K68: 14964.73 | L68: 2360.44 | M68: 2704.45 | N68: -196.51 | O68: -6317.29 | P68: -1448.91 | Q68: 1240.97 | R68: 1017.68 | S68: -238.58 | T68: -1537.05 | U68: 483.02 | V68: -518.43 | W68: 5416.03 | X68: 2110.64 | Y68: -3283.15 | Z68: 3725.09 | AA68: -4019.58 | AB68: 3967.47
... A74: 1 | C74: 계속사업이익 | E74: -970.39 | G74: 11503.97 | H74: 1470.82 | I74: 737.1 | J74: 1252.84 | K74: 14964.73 | L74: 2360.44 | M74: 2704.45 | N74: -196.51 | O74: -6317.29 | P74: -1448.91 | Q74: 1240.97 | R74: 1017.68 | S74: -238.58 | T74: -1537.05 | U74: 483.02 | V74: -518.43 | W74: 5416.03 | X74: 2110.64 | Y74: -3283.15 | Z74: 3725.09 | AA74: -4019.58 | AB74: 3967.47
A75: 1 | C75: 이자수익 | G75: 20.98 | H75: 17.36 | I75: 33.58 | J75: 63.39 | K75: 135.31 | L75: 50.91 | M75: 47.37 | N75: 56.83 | O75: 130.86 | P75: 285.97 | Q75: 94.35 | R75: 87.65 | S75: 90.69 | T75: 108.92 | U75: 381.61 | V75: 70.33 | W75: 92.94 | X75: -43.52 | Y75: 128.37 | Z75: 248.12 | AB75: 149.41
A76: 1 | C76: 이자비용 | G76: 619.85 | H76: 712.25 | I76: 928.51 | J76: 1198.4 | K76: 3459.01 | L76: 1301.27 | M76: 1403.15 | N76: 1495.49 | O76: 1390.47 | P76: 5590.38 | Q76: 1032.8 | R76: 1091.39 | S76: 949.03 | T76: 761.7 | U76: 3834.92 | V76: 823.68 | W76: 926.95 | X76: 724.71 | Y76: 834.18 | Z76: 3309.52 | AB76: 1144.75
A77: 1 | C77: 외환차익 | G77: 117.34 | H77: 355.62 | I77: 437.89 | J77: 634.27 | K77: 1545.12 | L77: 420.89 | M77: 295.15 | N77: 264.19 | O77: 300.48 | P77: 1280.71 | Q77: 293.18 | R77: 254.23 | S77: 121.92 | T77: 322.47 | U77: 991.8 | V77: 58.49 | W77: 309.75 | X77: 112.18 | Y77: 307.29 | Z77: 787.71 | AB77: 435.57
A78: 1 | C78: 외환차손 | G78: 408.6 | H78: 578.83 | I78: 141.79 | J78: 332.03 | K78: 1461.25 | L78: 419.77 | M78: 327.54 | N78: 273.46 | O78: 245.88 | P78: 1266.65 | Q78: 202.25 | R78: 190.23 | S78: 131.65 | T78: 246.37 | U78: 770.5 | V78: 323.28 | W78: 358.43 | X78: 231.84 | Y78: 102.63 | Z78: 1016.18 | AB78: 197.03
A79: 1 | C79: 외화환산이익 | G79: 149.76 | H79: 282.82 | I79: 622.58 | J79: -825.91 | K79: 229.25 | L79: 195.01 | M79: -42.93 | N79: 135.44 | O79: -166.27 | P79: 121.25 | Q79: 171.14 | R79: 30.47 | S79: -154.6 | T79: 574.66 | U79: 621.67 | V79: 189.71 | W79: -154.92 | X79: 55.33 | Y79: -9.02 | Z79: 81.1 | AB79: -106.27
A80: 1 | C80: 외화환산손실 | G80: 183.12 | H80: -133.1 | I80: 0.57 | J80: 419.06 | K80: 469.65 | L80: 115.98 | M80: -9.35 | N80: -51.88 | O80: 93.52 | P80: 148.27 | Q80: 63.06 | R80: -40.13 | S80: 190.63 | T80: -111.49 | U80: 102.07 | V80: 13.44 | W80: 305.11 | X80: -271.23 | Y80: 139.31 | Z80: 186.63 | AB80: -22.96
A81: 1 | C81: 이자손익 | G81: -598.87 | H81: -694.89 | I81: -894.93 | J81: -1135.01 | K81: -3323.7 | L81: -1250.36 | M81: -1355.78 | N81: -1438.66 | O81: -1259.61 | P81: -5304.41 | Q81: -938.45 | R81: -1003.74 | S81: -858.34 | T81: -652.78 | U81: -3453.31 | V81: -753.35 | W81: -834.01 | X81: -768.23 | Y81: -705.81 | Z81: -3061.4 | AB81: -995.34
A82: 1 | C82: 파생상품이익 | W82: 4557.25 | X82: 0 | Y82: -2981.47 | AB82: 13231.27
A83: 1 | C83: 파생상품손실 | W83: 1063.84 | X83: 0 | Y83: -498.62 | AB83: 12408.05
A84: 1 | C84: 영업활동으로인한현금흐름 | E84: 23553.35 | G84: -6348.39 | H84: -10704.54 | I84: 219.35 | J84: 7160.8 | K84: -9672.78 | L84: -12823.7 | M84: 1188.99 | N84: -1097.21 | O84: 17935.62 | P84: 5203.7 | Q84: -6817.31 | R84: -141.65 | S84: 7484.89 | T84: -4376.7 | U84: -3850.77 | V84: 8809.92 | W84: -4361.97 | X84: -1827.95 | Y84: -5555.15 | Z84: -2935.15 | AA84: 9937.16 | AB84: 3266.37
A85: 1 | C85: 감가상각비 | E85: 1278.99 | G85: 1295.36 | H85: 1319.42 | I85: 1299.61 | J85: 1311.88 | K85: 5226.27 | L85: 1306.27 | M85: 1315.98 | N85: 1248.51 | O85: 1256.47 | P85: 5127.23 | Q85: 1098.99 | R85: 1073.65 | S85: 1092.27 | T85: 1114.48 | U85: 4379.39 | V85: 851.96 | W85: 866.21 | X85: 843.39
A86: 1 | C86: 무형자산상각비 | E86: 20.36 | G86: 19.59 | H86: 17.77 | I86: 17.86 | J86: 17.86 | K86: 73.08 | L86: 12.13 | M86: 12.41 | N86: 12.39 | O86: 10.21 | P86: 47.14 | Q86: 8.63 | R86: 7.59 | S86: 8.02 | T86: 8.71 | U86: 32.95 | V86: 7.49 | W86: 6.68 | X86: 7.57
A87: 1 | C87: 법인세납부(CF) | E87: -11.17 | G87: -1404.33 | H87: -1727.34 | I87: -1500.5 | J87: -17.19 | K87: -4649.36 | L87: -1391.98 | M87: -1852.12 | N87: -762.86 | O87: -238.98 | P87: -4245.94 | Q87: -11.53 | R87: -210.94 | S87: -391.63 | T87: -31.95 | U87: -646.05 | V87: -422.59 | W87: -648.27 | X87: -389.91 | Y87: 192.09 | Z87: -1268.68 | AA87: -189.75 | AB87: -526.88
A88: 1 | C88: 투자활동으로인한현금흐름 | E88: -4511.4 | G88: 21693.73 | H88: -4321.42 | I88: -3187.64 | J88: 3453.97 | K88: 17638.64 | L88: -2001.56 | M88: -4935.14 | N88: -8376.21 | O88: -4173.14 | P88: -19486.05 | Q88: -1645.65 | R88: 1090.63 | S88: -661.97 | T88: -16134.44 | U88: -17351.43 | V88: -24517 | W88: -3436.67 | X88: -4204.69 | Y88: 2914.7 | Z88: -29243.66 | AA88: -29771.08 | AB88: -1704.77
A89: 1 | C89: 유형자산의증가 | E89: 1461.21 | G89: 872.5 | H89: 4046.33 | I89: 1166.19 | J89: 829.17 | K89: 6914.19 | L89: 615.67 | M89: 4180.02 | N89: 7424.12 | O89: 5329.47 | P89: 17549.28 | Q89: 361.59 | R89: 725.09 | S89: 768.98 | T89: 5507.34 | U89: 7363 | V89: 7279.15 | W89: 7614.47 | X89: 11619.69 | Y89: 10652.03 | Z89: 37165.34 | AA89: 20972.69 | AB89: 11426.04
A90: 1 | C90: CAPEX | E90: 1461.21 | G90: 874.75 | H90: 4046.33 | I90: 1169.97 | J90: 829.17 | K90: 6920.22 | L90: 637.27 | M90: 4190.72 | N90: 7424.12 | O90: 5329.47 | P90: 17581.58 | Q90: 361.59 | R90: 725.09 | S90: 788.81 | T90: 5546.16 | U90: 7421.65 | V90: 7303.32 | W90: 8329.51 | X90: 10880.48 | Y90: 10652.03 | Z90: 37165.34 | AA90: 20972.69 | AB90: 11426.04
A91: 1 | C91: 무형자산의증가 | E91: 0 | G91: 2.25 | H91: 0 | I91: 3.78 | J91: 0 | K91: 6.03 | L91: 21.6 | M91: 10.7 | N91: 0 | O91: 0 | P91: 32.3 | T91: 38.82 | V91: 24.17 | W91: 715.04
A92: 1 | C92: 재무활동으로인한현금흐름 | E92: -7210.76 | G92: -13505.41 | H92: 6196.49 | I92: 4480.16 | J92: -8195.42 | K92: -11024.18 | L92: 9567.15 | M92: 5133.36 | N92: 11018.27 | O92: -4436 | P92: 21282.78 | Q92: 4898.6 | R92: -2853.68 | S92: -6130.98 | T92: 19194.24 | U92: 15108.18 | V92: 17897.1 | W92: 1109.67 | X92: 5805.41 | Y92: 26479.46 | Z92: 51291.64 | AA92: 8785.69 | AB92: 1349.6
A93: 1 | C93: 단기차입금의증가 | E93: 26394.16 | G93: 20607.81 | H93: 51739.57 | I93: 40208.48 | J93: 43501.19 | K93: 156057.05 | L93: 48530.94 | M93: 71058.95 | N93: 67856.27 | O93: 19120.18 | P93: 206566.34 | Q93: 59203.05 | R93: 40073.7 | S93: 44038.24 | T93: 53570.48 | U93: 196885.47 | V93: 54408.19 | W93: 44444.9 | X93: 54854.28 | Y93: 38109.87 | Z93: 191817.24 | AA93: 31000.03 | AB93: 23769.97
A94: 1 | C94: 장기차입금의증가 | E94: 0 | N94: 7100 | O94: 2000 | T94: 0 | AA94: 10000 | AB94: 2125.22
A95: 1 | C95: 단기차입금의감소 | E95: 32215.18 | G95: 29636.97 | H95: 45239.56 | I95: 35208.48 | J95: 51131.19 | K95: 161216.2 | L95: 38847.94 | M95: 67597.95 | N95: 60310.27 | O95: 50418.3 | P95: 217174.46 | Q95: 48165.2 | R95: 42773.69 | S95: 49588.25 | T95: 34270.47 | U95: 174797.61 | V95: 57608.19 | W95: 42754.9 | X95: 48894.28 | Y95: 37809.87 | Z95: 187067.24 | AA95: 32300.03 | AB95: 17469.97
A96: 1 | C96: 유동성장기부채의감소 | E96: 1267.59 | G96: 2055.43 | H96: 198.31 | I96: 178.56 | J96: 0 | K96: 2432.3 | N96: 3500 | O96: 0 | Q96: 6000 | R96: 0 | S96: 0 | T96: 0 | U96: 6000 | X96: 0
A97: 1 | C97: 현금및현금성자산의증감 | E97: 23662.07 | G97: 1839.93 | H97: -8829.47 | I97: 1511.88 | J97: 2419.34 | K97: -3058.32 | L97: -5258.1 | M97: 1387.19 | N97: 1544.87 | O97: 9326.47 | P97: 7000.43 | Q97: -3564.36 | R97: -1904.71 | S97: 691.95 | T97: -1316.89 | U97: -6094.01 | V97: 2190.02 | W97: -6688.97 | X97: -227.24 | Y97: 23839.03 | Z97: 19112.84 | AA97: -11048.23 | AB97: 2911.2
A98: 1 | C98: 기말현금및현금성자산 | E98: 11830.87 | G98: 15481.2 | H98: -8674.14 | I98: 1601.97 | J98: 2215.61 | K98: 10624.64 | L98: 5378.3 | M98: 1382.24 | N98: 1544.11 | O98: 9320.63 | P98: 17625.28 | Q98: 14072.42 | R98: -1917.37 | S98: 674.37 | T98: -1284.23 | U98: 11545.19 | V98: 13828.71 | W98: -6694.46 | X98: -225.16 | Y98: 23761.75 | Z98: 30670.84 | AA98: 19668.35 | AB98: 2888.52
A99: 1 | C99: 유형자산의감소 | G99: 25.36 | H99: 2.5 | I99: 23 | J99: 2629.27 | K99: 2680.13 | L99: 75.2 | M99: 165 | N99: 3.2 | O99: 0 | P99: 243.4 | Q99: 1.2 | R99: 51.82 | S99: 21.53 | T99: 103.6 | U99: 178.15 | V99: 18.29 | W99: 40 | X99: 173.74 | Y99: 9.65 | Z99: 241.68 | AA99: 114.1 | AB99: 26.2
A100: 1 | C100: 장기차입금의감소 | G100: 2321.4 | H100: 0 | I100: 0 | J100: 0 | K100: 2321.4 | T100: 0
A101: 1 | C101: 자기주식의취득 | J101: 1466.52
A102: 1 | C102: 배당금지급 | N102: 0 | O102: 0
A103: 1 | C103: 이자수취(CF) | O103: 137.58 | Q103: 114.59 | R103: 53.8 | S103: 83.2 | T103: 100.2 | U103: 351.79 | V103: 54.19 | W103: 89.61 | X103: 231.57 | Y103: 85.71 | Z103: 461.08 | AA103: 70.14 | AB103: 147.15
A104: 1 | C104: 리스부채의상환 | O104: 138.01 | Q104: 139.25 | R104: 153.69 | S104: 180.98 | T104: 180.9 | U104: 654.82 | V104: 191.56 | W104: 197.24 | X104: 187.01

Sheet BS별도
B1: (백만원) | C1: 이름: BS별도H | E1: 4Q21 | F1: 2021 | G1: 1Q22 | H1: 2Q22 | I1: 3Q22 | J1: 4Q22 | K1: 2022 | L1: 1Q23 | M1: 2Q23 | N1: 3Q23 | O1: 4Q23 | P1: 2023 | Q1: 1Q24 | R1: 2Q24 | S1: 3Q24 | T1: 4Q24 | U1: 2024 | V1: 1Q25 | W1: 2Q25 | X1: 3Q25 | Y1: 4Q25 | Z1: 2025 | AA1: 1Q26 | AB1: 2Q26 | AC1: 3Q26 | AD1: 4Q26 | AE1: 2026 | AF1: 1Q27 | AG1: 2Q27 | AH1: 3Q27 | AI1: 4Q27 | AJ1: 2027 | AK1: 1Q28 | AL1: 2Q28 | AM1: 3Q28 | AN1: 4Q28 | AO1: 2028
B2: 별도 | D2: fin json(kship_fin.py)
B3: 한국선재(별) | C3: UPDATE: 26-10-13 | E3: 1 | F3: 2 | G3: 3 | H3: 4 | I3: 5 | J3: 6 | K3: 7 | L3: 8 | M3: 9 | N3: 10 | O3: 11 | P3: 12 | Q3: 13 | R3: 14 | S3: 15 | T3: 16 | U3: 17 | V3: 18 | W3: 19 | X3: 20 | Y3: 21 | Z3: 22 | AA3: 23 | AB3: 24 | AC3: 25 | AD3: 26 | AE3: 27 | AF3: 28 | AG3: 29 | AH3: 30 | AI3: 31 | AJ3: 32 | AK3: 33 | AL3: 34 | AM3: 35 | AN3: 36 | AO3: 37
B4: Account Code | C4: AccountNAME | E4: 2021.12 | F4: 2021.12A | G4: 2022.03 | H4: 2022.06 | I4: 2022.09 | J4: 2022.12 | K4: 2022.12A | L4: 2023.03 | M4: 2023.06 | N4: 2023.09 | O4: 2023.12 | P4: 2023.12A | Q4: 2024.03 | R4: 2024.06 | S4: 2024.09 | T4: 2024.12 | U4: 2024.12A | V4: 2025.03 | W4: 2025.06 | X4: 2025.09 | Y4: 2025.12 | Z4: 2025.12A | AA4: 2026.03 | AB4: 2026.06 | AC4: 2026.09 | AD4: 2026.12 | AE4: 2026.12A | AF4: 2027.03 | AG4: 2027.06 | AH4: 2027.09 | AI4: 2027.12 | AJ4: 2027.12A | AK4: 2028.03 | AL4: 2028.06 | AM4: 2028.09 | AN4: 2028.12 | AO4: 2028.12A
A5: 1 | C5: 유동자산 | E5: 97719.53 | F5: 97719.53 | G5: 88231.89 | H5: 95391.35 | I5: 94799.4 | J5: 87637.58 | K5: 87637.58 | L5: 96808.09 | M5: 91197.88 | N5: 87701.19 | O5: 85208.2 | P5: 85208.2 | Q5: 88559.27 | R5: 84293.41 | S5: 76381.12 | T5: 84323.96 | U5: 84323.96 | V5: 74398.52 | W5: 75022.79 | X5: 80277.02 | Y5: 81554.69 | Z5: 81554.69 | AA5: 87292.76 | AB5: 81965.92
A6: 1 | C6: 현금및현금성자산 | E6: 10427.2 | F6: 10427.2 | G6: 13271.53 | H6: 5347.44 | I6: 7330.43 | J6: 7472.62 | K6: 7472.62 | L6: 5155.65 | M6: 6274.97 | N6: 3847.51 | O6: 9787.74 | P6: 9787.74 | Q6: 5041.55 | R6: 2907.23 | S6: 5625.18 | T6: 2079.07 | U6: 2079.07 | V6: 3761.92 | W6: 1391.17 | X6: 2893.17 | Y6: 7462.46 | Z6: 7462.46 | AA6: 11996.52 | AB6: 6209.11
A7: 1 | C7: 매출채권및기타채권 | E7: 25052.42 | F7: 25052.42 | G7: 28932.23 | H7: 26720.63 | I7: 30797.85 | J7: 28469.57 | K7: 28469.57 | L7: 34784.14 | M7: 26029.65 | N7: 30064.29 | O7: 26184.68 | P7: 26184.68 | Q7: 25105.07 | R7: 28181.72 | S7: 26126.19 | T7: 28460.31 | U7: 28460.31 | V7: 27441.1 | W7: 25662.96 | X7: 24458.93 | Y7: 21538.61 | Z7: 21538.61 | AA7: 23922.37 | AB7: 26729.94
A8: 1 | C8: 재고자산 | E8: 45458.24 | F8: 45458.24 | G8: 45200.41 | H8: 61121.07 | I8: 54037.53 | J8: 50697.87 | K8: 50697.87 | L8: 55911.08 | M8: 57205.28 | N8: 53234.33 | O8: 48371.88 | P8: 48371.88 | Q8: 57155.34 | R8: 52699.56 | S8: 44080.18 | T8: 53338.73 | U8: 53338.73 | V8: 43144.01 | W8: 47883.59 | X8: 52070.32 | Y8: 52017.25 | Z8: 52017.25 | AA8: 51308.39 | AB8: 48997.23
A9: 1 | C9: 기타유동금융자산 | E9: 297.98 | F9: 297.98 | G9: 298.73 | H9: 299.72 | I9: 2069.66 | J9: 409.71 | K9: 409.71 | L9: 389.79 | M9: 392.66
A10: 1 | C10: 기타유동자산 | E10: 534.47 | F10: 534.47 | G10: 529 | H10: 1902.5 | I10: 563.94 | J10: 587.81 | K10: 587.81 | L10: 567.43 | M10: 1295.32 | N10: 555.05 | O10: 576.72 | P10: 576.72 | Q10: 958.64 | R10: 504.9 | S10: 549.57 | T10: 445.84 | U10: 445.84 | V10: 51.49 | W10: 85.08 | X10: 827.04 | Y10: 501.31 | Z10: 501.31 | AA10: 65.48 | AB10: 29.64
A11: 1 | C11: 매각예정비유동자산및처분자산 | E11: 15949.22 | F11: 15949.22 | I11: 0
A12: 1 | C12: 비유동자산 | E12: 95091.21 | F12: 95091.21 | G12: 95722.74 | H12: 96657.31 | I12: 97908.56 | J12: 95475.76 | K12: 95475.76 | L12: 95151.24 | M12: 120279.94 | N12: 119734.06 | O12: 128314.85 | P12: 128314.85 | Q12: 127326.53 | R12: 128401.52 | S12: 127175.27 | T12: 137566.02 | U12: 137566.02 | V12: 137905.17 | W12: 139397.88 | X12: 151472.56 | Y12: 140727.52 | Z12: 140727.52 | AA12: 162673.48 | AB12: 168214.53
A13: 1 | C13: 장기금융자산 | E13: 1377.01 | F13: 1377.01 | G13: 1006.5 | H13: 1006.5 | I13: 1006.5 | J13: 1006.5 | K13: 1006.5 | L13: 1006.5 | M13: 1006.5 | N13: 1006.5 | O13: 730.61 | P13: 730.61 | Q13: 730.61 | R13: 138.61 | S13: 257.46 | T13: 12826.84 | U13: 12826.84 | V13: 12926.84 | W13: 11406.69 | X13: 18904.71 | Y13: 300.62 | Z13: 300.62 | AA13: 300.62 | AB13: 300.62
A14: 1 | C14: 투자자산 | E14: 28729.26 | F14: 28729.26 | G14: 29615.21 | H14: 29312.9 | I14: 30839.95 | J14: 29567.85 | K14: 29567.85 | L14: 30346.95 | M14: 32431.12 | N14: 32491.67 | O14: 41639.6 | P14: 41639.6 | Q14: 41230.39 | R14: 42650.64 | S14: 41614.07 | T14: 52658.62 | U14: 52658.62 | V14: 52878.7 | W14: 55109.33 | X14: 64014.38 | Y14: 46609.35 | Z14: 46609.35 | AA14: 57210.77 | AB14: 300.62
A15: 1 | C15: 종속기업및관계기업투자 | E15: 27352.25 | F15: 27352.25 | G15: 28608.71 | H15: 28306.4 | I15: 29833.45 | J15: 28561.35 | K15: 28561.35 | L15: 29340.45 | M15: 31424.62 | N15: 31485.17 | O15: 40908.99 | P15: 40908.99 | Q15: 40499.78 | R15: 42512.03 | S15: 41356.61 | T15: 39831.78 | U15: 39831.78 | V15: 39951.86 | W15: 43702.64 | X15: 45109.67 | Y15: 46308.73 | Z15: 46308.73 | AA15: 56910.15
A16: 1 | C16: 유형자산 | E16: 50780.77 | F16: 50780.77 | G16: 50293.77 | H16: 51643.36 | I16: 51505.09 | J16: 50383.36 | K16: 50383.36 | L16: 49828.77 | M16: 50965.9 | N16: 50520.77 | O16: 50107.9 | P16: 50107.9 | Q16: 49681.82 | R16: 49401.37 | S16: 49263.82 | T16: 48249.93 | U16: 48249.93 | V16: 48524.98 | W16: 48535.4 | X16: 49942.98 | Y16: 49825.87 | Z16: 49825.87 | AA16: 61390.1 | AB16: 61242.27
A17: 1 | C17: 사용권자산 | E17: 1541.63 | F17: 1541.63 | G17: 1440.85 | H17: 1366.37 | I17: 1265.04 | J17: 1164.09 | K17: 1164.09 | L17: 703.06 | M17: 653.31 | N17: 580.07 | O17: 506.83 | P17: 506.83 | Q17: 433.59 | R17: 447.6 | S17: 471.95 | T17: 347.58 | U17: 347.58 | V17: 314.89 | W17: 352.3 | X17: 351.69 | Y17: 353.89 | Z17: 353.89 | AA17: 653.48 | AB17: 577.42
A18: 1 | C18: 기타비유동자산 | E18: 1541.63 | F18: 1541.63 | G18: 1440.85 | H18: 1366.37 | I18: 1265.04 | J18: 1164.09 | K18: 1164.09 | L18: 703.06 | M18: 653.31 | N18: 580.07 | O18: 506.83 | P18: 506.83 | Q18: 433.59 | R18: 447.6 | S18: 471.95 | T18: 347.58 | U18: 347.58 | V18: 314.89 | W18: 352.3 | X18: 351.69 | Y18: 353.89 | Z18: 353.89 | AA18: 653.48 | AB18: 577.42
A19: 1 | C19: 투자부동산 | E19: 13704.73 | F19: 13704.73 | G19: 13673.78 | H19: 13642.83 | I19: 13611.89 | J19: 13580.94 | K19: 13580.94 | L19: 13549.99 | M19: 35514.02 | N19: 35437.82 | O19: 35361.62 | P19: 35361.62 | Q19: 35285.43 | R19: 35209.23 | S19: 35133.04 | T19: 35547.19 | U19: 35547.19 | V19: 35468.58 | W19: 34683.63 | X19: 36462.88 | Y19: 37493.46 | Z19: 37493.46 | AA19: 39417.7 | AB19: 40588
A20: 1 | C20: 무형자산 | E20: 334.81 | F20: 334.81 | G20: 328.62 | H20: 321.56 | I20: 314.5 | J20: 407.44 | K20: 407.44 | L20: 400.38 | M20: 393.49 | N20: 386.63 | O20: 381.94 | P20: 381.94 | Q20: 378.34 | R20: 375.74 | S20: 375.44 | T20: 373.35 | U20: 373.35 | V20: 371.3 | W20: 370.63 | X20: 406.52 | Y20: 404.48 | Z20: 404.48 | AA20: 154.04 | AB20: 131.58
A21: 1 | C21: 자산총계 | E21: 192810.75 | F21: 192810.75 | G21: 183954.63 | H21: 192048.66 | I21: 192707.97 | J21: 183113.34 | K21: 183113.34 | L21: 191959.33 | M21: 211477.81 | N21: 207435.24 | O21: 213523.05 | P21: 213523.05 | Q21: 215885.8 | R21: 212694.93 | S21: 203556.39 | T21: 221889.97 | U21: 221889.97 | V21: 212303.69 | W21: 214420.68 | X21: 231749.58 | Y21: 222282.21 | Z21: 222282.21 | AA21: 249966.24 | AB21: 250180.45
A22: 1 | C22: 유동부채 | E22: 75727.66 | F22: 75727.66 | G22: 57093.91 | H22: 64734.03 | I22: 65611.24 | J22: 57832.64 | K22: 57832.64 | L22: 73241.08 | M22: 73242.14 | N22: 70092.89 | O22: 68593.18 | P22: 68593.18 | Q22: 70893.5 | R22: 65914.65 | S22: 57013.57 | T22: 77859.88 | U22: 77859.88 | V22: 70451.67 | W22: 71389.48 | X22: 96875.04 | Y22: 92044.98 | Z22: 92044.98 | AA22: 98486.4 | AB22: 96179.2
A23: 1 | C23: 매입채무및기타채무 | E23: 8893.52 | F23: 8893.52 | G23: 8497.53 | H23: 12001.68 | I23: 11729.8 | J23: 10068.92 | K23: 10068.92 | L23: 10991.58 | M23: 10213.83 | N23: 6551.38 | O23: 11608.2 | P23: 11608.2 | Q23: 10392.24 | R23: 7836.15 | S23: 4128.56 | T23: 10477.3 | U23: 10477.3 | V23: 5219.2 | W23: 4916.5 | X23: 7754.14 | Y23: 3475.43 | Z23: 3475.43 | AA23: 10234.27 | AB23: 7103.53
A24: 1 | C24: 단기차입금 | E24: 57421.96 | F24: 57421.96 | G24: 43357.12 | H24: 46278.56 | I24: 49100 | J24: 42770 | K24: 42770 | L24: 56250 | M24: 60200 | N24: 60960 | O24: 53162.14 | P24: 53162.14 | Q24: 58200 | R24: 55500 | S24: 50000 | T24: 64700 | U24: 64700 | V24: 62000 | W24: 63690 | X24: 86700 | Y24: 86000 | Z24: 86000 | AA24: 85000 | AB24: 85000
A25: 1 | C25: 당기법인세부채(미지급법인세) | E25: 2806.15 | F25: 2806.15 | G25: 1529.45 | H25: 3438.1 | I25: 2091.36 | J25: 2047.28 | K25: 2047.28 | L25: 1156.78 | M25: 296.86 | N25: 144.55 | R25: 72.85 | S25: 54.43 | T25: 296.41 | U25: 296.41 | V25: 251.24 | W25: 0 | X25: 0 | AA25: -39.56 | AB25: 1011.5
A26: 1 | C26: 유동리스부채 | E26: 396.21 | F26: 396.21 | G26: 400.13 | H26: 404.33 | I26: 408.25 | J26: 412.28 | K26: 412.28 | L26: 300.01 | M26: 308.07 | N26: 303.22 | O26: 294.76 | P26: 294.76 | Q26: 277.97 | R26: 281.67 | S26: 290.57 | T26: 301.61 | U26: 301.61 | V26: 278.21 | W26: 235.33 | X26: 187.49 | Y26: 145.6 | Z26: 145.6 | AA26: 288.92 | AB26: 284.12
A27: 1 | C27: 리스부채 | E27: 1615.94 | F27: 1615.94 | G27: 1518.44 | H27: 1445.06 | I27: 1345.09 | J27: 1244.72 | K27: 1244.72 | L27: 773.71 | M27: 721.89 | N27: 645.93 | O27: 569.37 | P27: 569.37 | Q27: 491.88 | R27: 500.98 | S27: 520.68 | T27: 581.75 | U27: 581.75 | V27: 503.37 | W27: 494.45 | X27: 445.76 | Y27: 401.57 | Z27: 401.57 | AA27: 669.36 | AB27: 592.46
A28: 1 | C28: 단기금융부채 | E28: 2285.61 | F28: 2285.61 | G28: 2266.28 | H28: 2452.76 | I28: 2227.76 | J28: 2472.95 | K28: 2472.95 | L28: 2442.39 | M28: 2392.93 | N28: 2261.9 | O28: 2289.06 | P28: 2289.06 | Q28: 2182.55 | R28: 2262.82 | S28: 1883.44 | T28: 2200.53 | U28: 2200.53 | V28: 1978.52 | W28: 2185.84 | X28: 2071.44 | Y28: 2024.04 | Z28: 2024.04 | AA28: 1999.69 | AB28: 2290.45
A29: 1 | C29: 기타유동금융부채 | E29: 1889.4 | F29: 1889.4 | G29: 1866.15 | H29: 2048.43 | I29: 1819.51 | J29: 2060.67 | K29: 2060.67 | L29: 2142.38 | M29: 2084.86 | N29: 1958.68 | O29: 1994.3 | P29: 1994.3 | Q29: 1904.58 | R29: 1981.15 | S29: 1592.87 | T29: 1898.92 | U29: 1898.92 | V29: 1700.31 | W29: 1950.51 | X29: 1883.95 | Y29: 1878.44 | Z29: 1878.44 | AA29: 1710.77 | AB29: 2006.33
A30: 1 | C30: 기타유동부채 | E30: 4320.44 | F30: 4320.44 | G30: 1443.53 | H30: 562.93 | I30: 462.32 | J30: 473.49 | K30: 473.49 | L30: 2400.34 | M30: 138.52 | N30: 175.06 | O30: 1533.78 | P30: 1533.78 | Q30: 118.71 | R30: 242.83 | S30: 947.14 | T30: 185.64 | U30: 185.64 | V30: 1002.71 | W30: 597.15 | X30: 349.46 | Y30: 545.51 | Z30: 545.51 | AA30: 1291.99 | AB30: 773.71
A31: 1 | C31: 비유동부채 | E31: 16240.61 | F31: 16240.61 | G31: 14053.37 | H31: 14030.77 | I31: 14078.72 | J31: 12415.25 | K31: 12415.25 | L31: 6114.63 | M31: 24070.24 | N31: 24019.58 | O31: 23864.4 | P31: 23864.4 | Q31: 24062.31 | R31: 24564.24 | S31: 24755.39 | T31: 23137.72 | U31: 23137.72 | V31: 23977.91 | W31: 22862.71 | X31: 6102.54 | Y31: 6455.86 | Z31: 6455.86 | AA31: 16776.61 | AB31: 16244.05
A32: 1 | C32: 장기차입금 | E32: 8321.4 | F32: 8321.4 | G32: 6000 | H32: 6000 | I32: 6000 | J32: 6000 | K32: 6000 | M32: 17000 | N32: 17000 | O32: 17000 | P32: 17000 | Q32: 17000 | R32: 17000 | S32: 17000 | T32: 17000 | U32: 17000 | V32: 17000 | W32: 17000 | X32: 0 | AA32: 10000 | AB32: 10000
A33: 1 | C33: 확정급여부채 | E33: 777.71 | F33: 777.71 | G33: 1007.29 | H33: 906.48 | I33: 1108.33 | J33: 407.94 | K33: 407.94 | L33: 436.06 | M33: 1396.25 | N33: 1416.7 | O33: 656.32 | P33: 656.32 | Q33: 914.92 | R33: 1494.88 | S33: 1689.23 | T33: 1059.96 | U33: 1059.96 | V33: 1390.68 | W33: 841.25 | X33: 1087.93
A34: 1 | C34: 이연법인세부채 | E34: 5717.77 | F34: 5717.77 | G34: 5717.77 | H34: 5873.56 | I34: 5873.56 | J34: 5014.87 | K34: 5014.87 | L34: 5014.87 | M34: 4855.17 | N34: 4855.17 | O34: 5508.48 | P34: 5508.48 | Q34: 5508.48 | R34: 5425.05 | S34: 5425.05 | T34: 4386.61 | U34: 4386.61 | V34: 4966.07 | W34: 4366.33 | X34: 4366.33 | Y34: 5687.72 | Z34: 5687.72 | AA34: 5687.72 | AB34: 5035.45
A35: 1 | C35: 비유동리스부채 | E35: 1219.73 | F35: 1219.73 | G35: 1118.31 | H35: 1040.73 | I35: 936.84 | J35: 832.44 | K35: 832.44 | L35: 473.7 | M35: 413.82 | N35: 342.71 | O35: 274.61 | P35: 274.61 | Q35: 213.91 | R35: 219.31 | S35: 230.11 | T35: 280.14 | U35: 280.14 | V35: 225.16 | W35: 259.12 | X35: 258.27 | Y35: 255.97 | Z35: 255.97 | AA35: 380.44 | AB35: 308.34
A36: 1 | C36: 장기금융부채 | E36: 1423.73 | F36: 1423.73 | G36: 1328.31 | H36: 1250.73 | I36: 1096.84 | J36: 992.44 | K36: 992.44 | L36: 663.7 | M36: 818.82 | N36: 747.71 | O36: 699.61 | P36: 699.61 | Q36: 638.91 | R36: 644.31 | S36: 641.11 | T36: 691.14 | U36: 691.14 | V36: 621.16 | W36: 655.12 | X36: 648.27 | Y36: 655.97 | Z36: 655.97 | AA36: 730.44 | AB36: 708.34
A37: 1 | C37: 기타비유동금융부채 | E37: 204 | F37: 204 | G37: 210 | H37: 210 | I37: 160 | J37: 160 | K37: 160 | L37: 190 | M37: 405 | N37: 405 | O37: 425 | P37: 425 | Q37: 425 | R37: 425 | S37: 411 | T37: 411 | U37: 411 | V37: 396 | W37: 396 | X37: 390 | Y37: 400 | Z37: 400 | AA37: 350 | AB37: 400
A38: 1 | C38: 부채총계 | E38: 91968.27 | F38: 91968.27 | G38: 71147.28 | H38: 78764.8 | I38: 79689.96 | J38: 70247.89 | K38: 70247.89 | L38: 79355.7 | M38: 97312.39 | N38: 94112.47 | O38: 92457.59 | P38: 92457.59 | Q38: 94955.81 | R38: 90478.89 | S38: 81768.96 | T38: 100997.6 | U38: 100997.6 | V38: 94429.58 | W38: 94252.18 | X38: 102977.59 | Y38: 98500.84 | Z38: 98500.84 | AA38: 115263 | AB38: 112423.24
A39: 1 | C39: 자본금 | E39: 12261.13 | F39: 12261.13 | G39: 12261.13 | H39: 12261.13 | I39: 12261.13 | J39: 12261.13 | K39: 12261.13 | L39: 12261.13 | M39: 12261.13 | N39: 12261.13 | O39: 12261.13 | P39: 12261.13 | Q39: 12261.13 | R39: 12261.13 | S39: 12261.13 | T39: 12261.13 | U39: 12261.13 | V39: 13368.13 | W39: 13368.13 | X39: 13368.13 | Y39: 13368.13 | Z39: 13368.13 | AA39: 13368.13 | AB39: 13368.13
A40: 1 | C40: 자본잉여금 | E40: 19928.82 | F40: 19928.82 | G40: 19928.82 | H40: 19928.82 | I40: 19692.75 | J40: 18226.23 | K40: 18226.23 | L40: 18203.39 | M40: 18203.39 | N40: 17851.98 | O40: 19432.24 | P40: 19432.24 | Q40: 19432.24 | R40: 19432.24 | S40: 19432.24 | T40: 23055.03 | U40: 23055.03 | V40: 19657.17 | W40: 23145.32 | X40: 23145.32 | Y40: 23092.83 | Z40: 23092.83 | AA40: 23092.83 | AB40: 23700.94
A41: 1 | C41: 기타자본 | E41: 744.12 | F41: 744.12 | G41: 1496.28 | H41: 398.14 | I41: 170.03 | J41: 510.25 | K41: 510.25 | L41: 526.69 | M41: 558.77 | N41: 423.13 | O41: 1991.49 | P41: 1991.49 | Q41: 1251.36 | R41: 2322.69 | S41: 2241.84 | T41: -220.78 | U41: -220.78 | V41: -1506.73 | W41: -5948.76 | X41: 1549.25 | Y41: -2419.94 | Z41: -2419.94 | AA41: -2528.14 | AB41: -2725.01
A42: 1 | C42: 이익잉여금 | E42: 67908.4 | F42: 67908.4 | G42: 79121.12 | H42: 80695.77 | I42: 80894.1 | J42: 81867.85 | K42: 81867.85 | L42: 81612.42 | M42: 83142.14 | N42: 82786.53 | O42: 87380.59 | P42: 87380.59 | Q42: 87985.26 | R42: 88199.98 | S42: 87852.22 | T42: 85797 | U42: 85797 | V42: 86355.55 | W42: 89603.8 | X42: 90709.29 | Y42: 89740.36 | Z42: 89740.36 | AA42: 100770.42 | AB42: 103413.15
A43: 1 | C43: 자본총계 | E43: 100842.48 | F43: 100842.48 | G43: 112807.35 | H43: 113283.86 | I43: 113018 | J43: 112865.46 | K43: 112865.46 | L43: 112603.62 | M43: 114165.43 | N43: 113322.77 | O43: 121065.46 | P43: 121065.46 | Q43: 120929.99 | R43: 122216.04 | S43: 121787.43 | T43: 120892.38 | U43: 120892.38 | V43: 117874.11 | W43: 120168.49 | X43: 128771.99 | Y43: 123781.37 | Z43: 123781.37 | AA43: 134703.24 | AB43: 137757.21
A44: 1 | C44: 부채와자본총계 | E44: 192810.75 | F44: 192810.75 | G44: 183954.63 | H44: 192048.66 | I44: 192707.97 | J44: 183113.34 | K44: 183113.34 | L44: 191959.33 | M44: 211477.81 | N44: 207435.24 | O44: 213523.05 | P44: 213523.05 | Q44: 215885.8 | R44: 212694.93 | S44: 203556.39 | T44: 221889.97 | U44: 221889.97 | V44: 212303.69 | W44: 214420.68 | X44: 231749.58 | Y44: 222282.21 | Z44: 222282.21 | AA44: 249966.24 | AB44: 250180.45
A45: 1 | C45: 지배주주지분 | E45: 100842.48 | F45: 100842.48 | G45: 112807.35 | H45: 113283.86 | I45: 113018 | J45: 112865.46 | K45: 112865.46 | L45: 112603.62 | M45: 114165.43 | N45: 113322.77 | O45: 121065.46 | P45: 121065.46 | Q45: 120929.99 | R45: 122216.04 | S45: 121787.43 | T45: 120892.38 | U45: 120892.38 | V45: 117874.11 | W45: 120168.49 | X45: 128771.99 | Y45: 123781.37 | Z45: 123781.37 | AA45: 134703.24 | AB45: 137757.21
... A48: 1 | C48: 이자발생자산 | E48: 11804.21 | F48: 11804.21 | G48: 14278.03 | H48: 6353.94 | I48: 8336.93 | J48: 8479.12 | K48: 8479.12 | L48: 6162.15 | M48: 7281.47 | N48: 4854.01 | O48: 10518.35 | P48: 10518.35 | Q48: 5772.16 | R48: 3045.84 | S48: 5882.64 | T48: 14905.91 | U48: 14905.91 | V48: 16688.76 | W48: 12797.86 | X48: 21797.88 | Y48: 7763.08 | Z48: 7763.08 | AA48: 12297.14 | AB48: 6509.73
A49: 1 | C49: 단기금융부채(face) | G49: 43357.12 | H49: 46278.56 | I49: 49100 | J49: 42770 | K49: 42770 | L49: 56250 | M49: 60200 | N49: 60960 | O49: 53162.14 | P49: 53162.14 | Q49: 58200 | R49: 55500 | S49: 50000 | T49: 64700 | U49: 64700 | V49: 62000 | W49: 63690 | X49: 86700 | Y49: 86000 | Z49: 86000 | AA49: 85000 | AB49: 85000
A50: 1 | C50: 장기매출채권및기타채권 | I50: 0
A51: 1 | C51: 당기법인세자산(선급법인세) | O51: 287.18 | P51: 287.18 | Q51: 298.66 | X51: 27.56 | Y51: 35.05 | Z51: 35.05 | AA51: 0 | AB51: 0
A52: 1 | C52: 매출액(수익) | E52: 46215.57 | G52: 47671.74 | H52: 50774.88 | I52: 44356.08 | J52: 46423.34 | K52: 189226.04 | L52: 46984.17 | M52: 47481.61 | N52: 41891.87 | O52: 44113.51 | P52: 180471.16 | Q52: 38306.15 | R52: 43050.49 | S52: 39399.08 | T52: 41197.84 | U52: 161953.56 | V52: 38831.35 | W52: 39023.03 | X52: 37145.27 | Y52: 32230.74 | Z52: 147230.39 | AA52: 40729.29 | AB52: 45885.44
A53: 1 | C53: 매출원가 | E53: 40067.95 | G53: 41932.38 | H53: 42835.6 | I53: 42325.43 | J53: 42433.6 | K53: 169527.01 | L53: 42049.79 | M53: 43271.45 | N53: 38636.7 | O53: 40281.09 | P53: 164239.03 | Q53: 34320.24 | R53: 39451.45 | S53: 35039.7 | T53: 37016.75 | U53: 145828.14 | V53: 35702.46 | W53: 34885.46 | X53: 33700.8 | Y53: 28854.96 | Z53: 133143.68 | AA53: 35866.98 | AB53: 39410.34
A54: 1 | C54: 매출총이익 | E54: 6147.62 | G54: 5739.36 | H54: 7939.29 | I54: 2030.65 | J54: 3989.75 | K54: 19699.05 | L54: 4934.38 | M54: 4210.17 | N54: 3255.17 | O54: 3832.42 | P54: 16232.14 | Q54: 3985.91 | R54: 3599.04 | S54: 4359.38 | T54: 4181.09 | U54: 16125.42 | V54: 3128.89 | W54: 4137.57 | X54: 3444.47 | Y54: 3375.78 | Z54: 14086.71 | AA54: 4862.3 | AB54: 6475.1
A55: 1 | C55: 판관비 | E55: 2475.64 | G55: 3184.67 | H55: 3274.36 | I55: 3356.45 | J55: 3350.83 | K55: 13166.31 | L55: 3126.97 | M55: 2986.05 | N55: 2909.62 | O55: 3406.21 | P55: 12428.85 | Q55: 2935.27 | R55: 3066.13 | S55: 3089.47 | T55: 3295.48 | U55: 12386.35 | V55: 2963.75 | W55: 2942.49 | X55: 2970.03 | Y55: 3672.07 | Z55: 12548.34 | AA55: 2994.81 | AB55: 2867.54
A56: 1 | C56: 영업이익 | E56: 3671.99 | G56: 2554.69 | H56: 4664.92 | I56: -1325.8 | J56: 638.93 | K56: 6532.74 | L56: 1807.41 | M56: 1224.12 | N56: 345.55 | O56: 426.22 | P56: 3803.3 | Q56: 1050.64 | R56: 532.91 | S56: 1269.9 | T56: 885.6 | U56: 3739.05 | V56: 165.14 | W56: 1195.08 | X56: 474.44 | Y56: -296.29 | Z56: 1538.37 | AA56: 1867.49 | AB56: 3607.56
A57: 1 | C57: 금융수익 | E57: 86.54 | G57: 143.82 | H57: 275.17 | I57: 360.77 | J57: 344.78 | K57: 1124.54 | L57: 387.03 | M57: 224.26 | N57: 219.62 | O57: 305.15 | P57: 1136.06 | Q57: 228.12 | R57: 138.8 | S57: 137.19 | T57: 291.13 | U57: 795.24 | V57: 187.84 | W57: 226.39 | X57: 82.72 | Y57: 137.89 | Z57: 634.84 | AA57: 360.3 | AB57: 106.16
A58: 1 | C58: 금융비용 | E58: 558.83 | G58: 894.73 | H58: 797.53 | I58: 601.16 | J58: 935.16 | K58: 3228.58 | L58: 1038.1 | M58: 1017.41 | N58: 1098.95 | O58: 948.45 | P58: 4102.91 | Q58: 1012.51 | R58: 966.13 | S58: 815.31 | T58: 828.5 | U58: 3622.45 | V58: 847.61 | W58: 926.54 | X58: 704.29 | Y58: 799.78 | Z58: 3278.22 | AA58: 961.56 | AB58: 819.3
A59: 1 | C59: 기타영업외수익 | E59: 219.09 | G59: 9131.93 | H59: 9.6 | I59: 15.35 | J59: 2018.19 | K59: 11175.07 | L59: 111.1 | M59: 89.55 | N59: 46.32 | O59: 212.77 | P59: 459.74 | Q59: 19.51 | R59: 150.3 | S59: 69.45 | T59: 27.09 | U59: 266.35 | V59: 19.52 | W59: 160.96 | X59: 57.23 | Y59: 77.23 | Z59: 314.94 | AA59: 19.16 | AB59: 33.48
A60: 1 | C60: 기타영업외비용 | E60: 6.91 | G60: 227.3 | H60: 6.07 | I60: 5.98 | J60: 316.63 | K60: 555.98 | L60: 63.68 | M60: 256.77 | N60: 64.34 | O60: 1263.14 | P60: 1647.93 | Q60: 12.02 | R60: 18.72 | S60: 9.83 | T60: 2596.61 | U60: 2637.18 | V60: 4.97 | W60: 971.05 | X60: 208.67 | Y60: 33.12 | Z60: 1217.81 | AA60: 268.85 | AB60: 33.22
A61: 1 | C61: 법인세비용차감전계속사업이익 | E61: 815.4 | G61: 11212.72 | H61: 4809.31 | I61: 198.34 | J61: 225.11 | K61: 16445.48 | L61: 1966.42 | M61: 2597.25 | N61: -355.6 | O61: 5951.39 | P61: 10159.46 | Q61: 604.67 | R61: 889.75 | S61: -229.4 | T61: -2474.9 | U61: -1209.88 | V61: -1095.37 | W61: 3588.78 | X61: 1108.37 | Y61: -3852.33 | Z61: -250.55 | AA61: 9814.96 | AB61: 3832.87
A62: 1 | C62: 법인세비용 | E62: 1944.87 | H62: 3605.35 | I62: 0 | J62: -840.38 | M62: 301.07 | O62: -99.06 | R62: 205.91 | S62: 118.36 | T62: -363.99 | AA62: -1.27 | AB62: 849.51
A63: 1 | C63: 당기순이익 | E63: -1129.46 | G63: 11212.72 | H63: 1203.96 | I63: 198.34 | J63: 1065.49 | K63: 13680.51 | L63: 1966.42 | M63: 2296.18 | N63: -355.6 | O63: 6050.45 | P63: 9957.45 | Q63: 604.67 | R63: 683.83 | S63: -347.75 | T63: -2110.91 | U63: -1170.16 | V63: -1095.37 | W63: 3785.01 | X63: 1105.4 | Y63: -3306.32 | Z63: 488.72 | AA63: 9816.23 | AB63: 2983.36
A64: 1 | C64: 총포괄손익 | E64: -3280.51 | G64: 11964.88 | H64: 476.51 | I64: -29.78 | J64: 1158.11 | K64: 13569.72 | L64: 1982.86 | M64: 1643.32 | N64: -491.24 | O64: 7579.29 | P64: 10714.23 | Q64: -135.47 | R64: 1286.05 | S64: -428.61 | T64: -4517.83 | U64: -3795.86 | V64: -727.41 | W64: 886.7 | X64: 8646.24 | Y64: -4945.76 | Z64: 3859.77 | AA64: 10921.87 | AB64: 2372.94
A65: 1 | C65: 금융손익 | E65: -472.29 | G65: -750.91 | H65: -522.36 | I65: -240.39 | J65: -590.38 | K65: -2104.04 | L65: -651.07 | M65: -793.15 | N65: -879.33 | O65: -643.3 | P65: -2966.85 | Q65: -784.39 | R65: -827.33 | S65: -678.12 | T65: -537.37 | U65: -2827.21 | V65: -659.77 | W65: -700.15 | X65: -621.57 | Y65: -661.89 | Z65: -2643.38 | AA65: -601.26 | AB65: -713.14
A66: 1 | C66: 기타영업외손익 | E66: 212.18 | G66: 8904.63 | H66: 3.53 | I66: 9.37 | J66: 1701.56 | K66: 10619.09 | L66: 47.42 | M66: -167.22 | N66: -18.02 | O66: -1050.37 | P66: -1188.19 | Q66: 7.49 | R66: 131.58 | S66: 59.62 | T66: -2569.52 | U66: -2370.83 | V66: 14.55 | W66: -810.09 | X66: -151.44 | Y66: 44.11 | Z66: -902.87 | AA66: -249.69 | AB66: 0.26
A67: 1 | C67: (지배주주지분)당기순이익 | E67: -1129.46 | G67: 11212.72 | H67: 1203.96 | I67: 198.34 | J67: 1065.49 | K67: 13680.51 | L67: 1966.42 | M67: 2296.18 | N67: -355.6 | O67: 6050.45 | P67: 9957.45 | Q67: 604.67 | R67: 683.83 | S67: -347.75 | T67: -2110.91 | U67: -1170.16 | V67: -1095.37 | W67: 3785.01 | X67: 1105.4 | Y67: -3306.32 | Z67: 488.72 | AA67: 9816.23 | AB67: 2983.36
A68: 1 | C68: 계속사업이익 | E68: -1129.46 | G68: 11212.72 | H68: 1203.96 | I68: 198.34 | J68: 1065.49 | K68: 13680.51 | L68: 1966.42 | M68: 2296.18 | N68: -355.6 | O68: 6050.45 | P68: 9957.45 | Q68: 604.67 | R68: 683.83 | S68: -347.75 | T68: -2110.91 | U68: -1170.16 | V68: -1095.37 | W68: 3785.01 | X68: 1105.4 | Y68: -3306.32 | Z68: 488.72 | AA68: 9816.23 | AB68: 2983.36
A69: 1 | C69: 영업활동으로인한현금흐름 | E69: 19516.81 | G69: -2675.43 | H69: -8904.48 | I69: 1604.69 | J69: 4200.71 | K69: -5774.51 | L69: -3753.25 | M69: 168.12 | N69: -2123.75 | O69: 11730.76 | P69: 6021.88 | Q69: -8682.44 | R69: 1136.05 | S69: 9544.78 | T69: -5947.38 | U69: -3948.99 | V69: 5311.47 | W69: -3604.4 | X69: -932.25 | Y69: -5255.26 | Z69: -4480.44 | AA69: 7711.48 | AB69: -649.99
A70: 1 | C70: 감가상각비 | E70: 756.76 | G70: 738.35 | H70: 721.99 | I70: 673.82 | J70: 675.16 | K70: 2809.32 | L70: 661.21 | M70: 622.76 | N70: 552.17 | O70: 527.16 | P70: 2363.3 | Q70: 499.32 | R70: 458.29 | S70: 454.11 | T70: 445.81 | U70: 1857.53 | V70: 230.14 | W70: 235.07 | X70: 226.16
A71: 1 | C71: 무형자산상각비 | E71: 9.13 | G71: 8.44 | H71: 7.06 | I71: 7.06 | J71: 7.06 | K71: 29.62 | L71: 7.06 | M71: 6.88 | N71: 6.87 | O71: 4.69 | P71: 25.5 | Q71: 3.6 | R71: 2.6 | S71: 2.13 | T71: 2.1 | U71: 10.43 | V71: 2.05 | W71: 0.67 | X71: 1.41
A72: 1 | C72: 법인세납부(CF) | E72: -10.7 | G72: -1276.7 | H72: -1539.29 | I72: -1346.74 | J72: -13.95 | K72: -4176.68 | L72: -890.5 | M72: -1200.8 | N72: -152.3 | O72: -151.05 | P72: -2394.65 | Q72: -11.48 | R72: 81.91 | S72: -61.87 | T72: -17.28 | U72: -8.72 | V72: -168.61 | W72: -301.31 | X72: -2.97 | Y72: 238.02 | Z72: -234.87 | AA72: 1.27 | AB72: 28.89
A73: 1 | C73: 투자활동으로인한현금흐름 | E73: -3550.16 | G73: 22110.1 | H73: -1996.48 | I73: -2197.59 | J73: 4042.09 | K73: 21958.12 | L73: -5963.55 | M73: -17696.71 | N73: -986.7 | O73: 2088.58 | P73: -22558.38 | Q73: -1035.47 | R73: -479.41 | S73: -1232.79 | T73: -12204.25 | U73: -14951.92 | V73: -428.74 | W73: -373.47 | X73: -3491.55 | Y73: 10689.34 | Z73: 6395.58 | AA73: -12053.88 | AB73: -5093.34
A74: 1 | C74: 유형자산의감소 | E74: 9 | G74: 13 | H74: 0 | I74: 0 | J74: 2642.53 | K74: 2655.53 | L74: 58.25 | M74: 0 | N74: 0 | O74: 0 | P74: 58.25 | T74: 0 | V74: 10.91 | W74: 40 | X74: 58.64 | Y74: 6.54 | Z74: 116.09
A75: 1 | C75: 유형자산의증가 | E75: 634.86 | G75: 153.38 | H75: 1996.71 | I75: 431.85 | J75: 266.81 | K75: 2848.75 | L75: 71.81 | M75: 1686.65 | N75: 33.81 | O75: 5.57 | P75: 1797.84 | Q75: 35.48 | R75: 71.4 | S75: 272.14 | T75: 1843.87 | U75: 2222.89 | V75: 349.54 | W75: 194.02 | X75: 1715.35 | AA75: 10976.64 | AB75: 781.15
A76: 1 | C76: CAPEX | E76: 634.86 | G76: 155.63 | H76: 1996.71 | I76: 431.85 | J76: 266.81 | K76: 2851 | L76: 71.81 | M76: 1686.65 | N76: 33.81 | O76: 5.57 | P76: 1797.84 | Q76: 35.48 | R76: 71.4 | S76: 273.97 | T76: 1843.87 | U76: 2224.72 | V76: 349.54 | W76: 194.02 | X76: 1715.35 | AA76: 10976.64 | AB76: 781.15
A77: 1 | C77: 재무활동으로인한현금흐름 | E77: -7210.75 | G77: -16483.72 | H77: 2821.57 | I77: 2485.77 | J77: -7896.89 | K77: -19073.27 | L77: 7388.11 | M77: 18652.83 | N77: 684.05 | O77: -7874.69 | P77: 18850.3 | Q77: 4960.37 | R77: -2778.45 | S77: -5578.74 | T77: 14575.14 | U77: 11178.32 | V77: -3293.39 | W77: 1610.92 | X77: 5924.73 | Y77: -740.83 | Z77: 3501.43 | AA77: 8873.43 | AB77: -41.05
A78: 1 | C78: 단기차입금의증가 | E78: 18747.54 | G78: 17607.81 | H78: 47739.57 | I78: 38208.48 | J78: 40791.19 | K78: 144347.05 | L78: 46327.94 | M78: 52788.81 | N78: 48243.73 | O78: 29520.18 | P78: 176880.66 | Q78: 59203.05 | R78: 40073.7 | S78: 44038.24 | T78: 47570.48 | U78: 190885.47 | V78: 54408.19 | W78: 45411.84 | X78: 53887.34 | Y78: 37109.87 | Z78: 190817.24 | AA78: 31000.03 | AB78: 17469.97
A79: 1 | C79: 장기차입금의증가 | E79: 0 | N79: 0 | O79: 0 | T79: 0 | AA79: 10000 | AB79: 0
A80: 1 | C80: 단기차입금의감소 | E80: 24718.56 | G80: 29636.97 | H80: 44639.56 | I80: 35208.48 | J80: 47121.19 | K80: 156606.2 | L80: 38847.94 | M80: 48838.81 | N80: 47483.73 | O80: 37318.3 | P80: 172488.78 | Q80: 48165.2 | R80: 42773.69 | S80: 49538.25 | T80: 32870.47 | U80: 173347.61 | V80: 57608.19 | W80: 43721.84 | X80: 47877.34 | Y80: 37809.87 | Z80: 187017.24 | AA80: 32000.03 | AB80: 17469.97
A81: 1 | C81: 유동성장기부채의감소 | E81: 1142.84 | G81: 2035.68 | H81: 178.56 | I81: 178.56 | J81: 0 | K81: 2392.8 | Q81: 6000 | R81: 0 | S81: 0 | T81: 0 | U81: 6000
A82: 1 | C82: 현금및현금성자산의증감 | E82: 17511.49 | G82: 2950.95 | H82: -8079.39 | I82: 1892.87 | J82: 345.91 | K82: -2889.66 | L82: -2328.69 | M82: 1124.23 | N82: -2426.39 | O82: 5944.65 | P82: 2313.8 | Q82: -4757.55 | R82: -2121.8 | S82: 2733.25 | T82: -3576.49 | U82: -7722.59 | V82: 1589.35 | W82: -2366.96 | X82: 1500.94 | Y82: 4693.24 | Z82: 5416.57 | AA82: 4531.03 | AB82: -5784.38
A83: 1 | C83: 기말현금및현금성자산 | E83: 8755.58 | G83: 13271.53 | H83: -7924.09 | I83: 1982.99 | J83: 142.19 | K83: 7472.62 | L83: 5155.65 | M83: 1119.32 | N83: -2427.46 | O83: 5940.23 | P83: 9787.74 | Q83: 5041.55 | R83: -2134.32 | S83: 2717.95 | T83: -3546.11 | U83: 2079.07 | V83: 3761.92 | W83: -2370.75 | X83: 1502 | Y83: 4569.29 | Z83: 7462.46 | AA83: 11996.52 | AB83: -5787.41
A84: 1 | C84: 무형자산의증가 | G84: 2.25 | H84: 0 | I84: 0 | J84: 0 | K84: 2.25 | T84: 0
A85: 1 | C85: 장기차입금의감소 | G85: 2321.4 | H85: 0 | I85: 0 | J85: 0 | K85: 2321.4 | T85: 0
A86: 1 | C86: 자기주식의취득 | J86: 1466.52
A87: 1 | C87: 배당금지급 | N87: 0 | O87: 0
A88: 1 | C88: 이자수취(CF) | O88: 75.43 | Q88: 43.5 | R88: 53.94 | S88: 62.23 | T88: 73.29 | U88: 232.96 | V88: 32.68 | W88: 46.21 | X88: 33.41 | Y88: 33.2 | Z88: 145.5 | AA88: 29.26 | AB88: 10.79
A89: 1 | C89: 리스부채의상환 | O89: 76.56 | Q89: 77.49 | R89: 78.44 | S89: 78.75 | T89: 78.6 | U89: 313.28 | V89: 78.39 | W89: 79.08 | X89: 79.27

Sheet subQ
A1: YQ | C1: subQ 분기 서브모델(억원, U=100) | E1: 4Q21 | F1: 2021 | G1: 1Q22 | H1: 2Q22 | I1: 3Q22 | J1: 4Q22 | K1: 2022 | L1: 1Q23 | M1: 2Q23 | N1: 3Q23 | O1: 4Q23 | P1: 2023 | Q1: 1Q24 | R1: 2Q24 | S1: 3Q24 | T1: 4Q24 | U1: 2024 | V1: 1Q25 | W1: 2Q25 | X1: 3Q25 | Y1: 4Q25 | Z1: 2025 | AA1: 1Q26 | AB1: 2Q26 | AC1: 3Q26 | AD1: 4Q26 | AE1: 2026 | AF1: 1Q27 | AG1: 2Q27 | AH1: 3Q27 | AI1: 4Q27 | AJ1: 2027 | AK1: 1Q28 | AL1: 2Q28 | AM1: 3Q28 | AN1: 4Q28 | AO1: 2028
A2: A=이름(key) B=그룹 C=단위 D=FnGuide 계정명(VLOOKUP 키). 확정=VLOOKUP(BS), 추정=변수 가정 참조
E3: 1 | F3: 2 | G3: 3 | H3: 4 | I3: 5 | J3: 6 | K3: 7 | L3: 8 | M3: 9 | N3: 10 | O3: 11 | P3: 12 | Q3: 13 | R3: 14 | S3: 15 | T3: 16 | U3: 17 | V3: 18 | W3: 19 | X3: 20 | Y3: 21 | Z3: 22 | AA3: 23 | AB3: 24 | AC3: 25 | AD3: 26 | AE3: 27 | AF3: 28 | AG3: 29 | AH3: 30 | AI3: 31 | AJ3: 32 | AK3: 33 | AL3: 34 | AM3: 35 | AN3: 36 | AO3: 37
E4: 2021.12 | F4: 2021.12A | G4: 2022.03 | H4: 2022.06 | I4: 2022.09 | J4: 2022.12 | K4: 2022.12A | L4: 2023.03 | M4: 2023.06 | N4: 2023.09 | O4: 2023.12 | P4: 2023.12A | Q4: 2024.03 | R4: 2024.06 | S4: 2024.09 | T4: 2024.12 | U4: 2024.12A | V4: 2025.03 | W4: 2025.06 | X4: 2025.09 | Y4: 2025.12 | Z4: 2025.12A | AA4: 2026.03 | AB4: 2026.06 | AC4: 2026.09 | AD4: 2026.12 | AE4: 2026.12A | AF4: 2027.03 | AG4: 2027.06 | AH4: 2027.09 | AI4: 2027.12 | AJ4: 2027.12A | AK4: 2028.03 | AL4: 2028.06 | AM4: 2028.09 | AN4: 2028.12 | AO4: 2028.12A
A5: 매출액 | B5: 손익 | C5: 억원 | D5: 매출액(수익) | E5: =IFERROR(VLOOKUP($D5,BS연결,MATCH(E$1,BS연결H,0),0)/100,"") | G5: =IFERROR(VLOOKUP($D5,BS연결,MATCH(G$1,BS연결H,0),0)/100,"") | H5: =IFERROR(VLOOKUP($D5,BS연결,MATCH(H$1,BS연결H,0),0)/100,"") | I5: =IFERROR(VLOOKUP($D5,BS연결,MATCH(I$1,BS연결H,0),0)/100,"") | J5: =IFERROR(VLOOKUP($D5,BS연결,MATCH(J$1,BS연결H,0),0)/100,"") | K5: =IFERROR(VLOOKUP($D5,BS연결,MATCH(K$1,BS연결H,0),0)/100,"") | L5: =IFERROR(VLOOKUP($D5,BS연결,MATCH(L$1,BS연결H,0),0)/100,"") | M5: =IFERROR(VLOOKUP($D5,BS연결,MATCH(M$1,BS연결H,0),0)/100,"") | N5: =IFERROR(VLOOKUP($D5,BS연결,MATCH(N$1,BS연결H,0),0)/100,"") | ... AB5: =IFERROR(VLOOKUP($D5,BS연결,MATCH(AB$1,BS연결H,0),0)/100,"") | AC5: =IFERROR(X5*(1+변수!AC21),"") | AD5: =IFERROR(Y5*(1+변수!AD21),"") | AE5: =SUM(AA5:AD5) | AF5: =IFERROR(AA5*(1+변수!AF21),"") | AG5: =IFERROR(AB5*(1+변수!AG21),"") | AH5: =IFERROR(AC5*(1+변수!AH21),"") | AI5: =IFERROR(AD5*(1+변수!AI21),"") | AJ5: =SUM(AF5:AI5) | AK5: =IFERROR(AF5*(1+변수!AK21),"") | AL5: =IFERROR(AG5*(1+변수!AL21),"") | AM5: =IFERROR(AH5*(1+변수!AM21),"") | AN5: =IFERROR(AI5*(1+변수!AN21),"") | AO5: =SUM(AK5:AN5)
A6: 매출원가 | B6: 손익 | C6: 억원 | D6: 매출원가 | E6: =IFERROR(VLOOKUP($D6,BS연결,MATCH(E$1,BS연결H,0),0)/100,"") | G6: =IFERROR(VLOOKUP($D6,BS연결,MATCH(G$1,BS연결H,0),0)/100,"") | H6: =IFERROR(VLOOKUP($D6,BS연결,MATCH(H$1,BS연결H,0),0)/100,"") | I6: =IFERROR(VLOOKUP($D6,BS연결,MATCH(I$1,BS연결H,0),0)/100,"") | J6: =IFERROR(VLOOKUP($D6,BS연결,MATCH(J$1,BS연결H,0),0)/100,"") | K6: =IFERROR(VLOOKUP($D6,BS연결,MATCH(K$1,BS연결H,0),0)/100,"") | L6: =IFERROR(VLOOKUP($D6,BS연결,MATCH(L$1,BS연결H,0),0)/100,"") | M6: =IFERROR(VLOOKUP($D6,BS연결,MATCH(M$1,BS연결H,0),0)/100,"") | N6: =IFERROR(VLOOKUP($D6,BS연결,MATCH(N$1,BS연결H,0),0)/100,"") | ... AB6: =IFERROR(VLOOKUP($D6,BS연결,MATCH(AB$1,BS연결H,0),0)/100,"") | AC6: =IFERROR(AC5-AC7,"") | AD6: =IFERROR(AD5-AD7,"") | AE6: =SUM(AA6:AD6) | AF6: =IFERROR(AF5-AF7,"") | AG6: =IFERROR(AG5-AG7,"") | AH6: =IFERROR(AH5-AH7,"") | AI6: =IFERROR(AI5-AI7,"") | AJ6: =SUM(AF6:AI6) | AK6: =IFERROR(AK5-AK7,"") | AL6: =IFERROR(AL5-AL7,"") | AM6: =IFERROR(AM5-AM7,"") | AN6: =IFERROR(AN5-AN7,"") | AO6: =SUM(AK6:AN6)
A7: 매출총이익 | B7: 손익 | C7: 억원 | D7: 매출총이익 | E7: =IFERROR(VLOOKUP($D7,BS연결,MATCH(E$1,BS연결H,0),0)/100,"") | G7: =IFERROR(VLOOKUP($D7,BS연결,MATCH(G$1,BS연결H,0),0)/100,"") | H7: =IFERROR(VLOOKUP($D7,BS연결,MATCH(H$1,BS연결H,0),0)/100,"") | I7: =IFERROR(VLOOKUP($D7,BS연결,MATCH(I$1,BS연결H,0),0)/100,"") | J7: =IFERROR(VLOOKUP($D7,BS연결,MATCH(J$1,BS연결H,0),0)/100,"") | K7: =IFERROR(VLOOKUP($D7,BS연결,MATCH(K$1,BS연결H,0),0)/100,"") | L7: =IFERROR(VLOOKUP($D7,BS연결,MATCH(L$1,BS연결H,0),0)/100,"") | M7: =IFERROR(VLOOKUP($D7,BS연결,MATCH(M$1,BS연결H,0),0)/100,"") | N7: =IFERROR(VLOOKUP($D7,BS연결,MATCH(N$1,BS연결H,0),0)/100,"") | ... AB7: =IFERROR(VLOOKUP($D7,BS연결,MATCH(AB$1,BS연결H,0),0)/100,"") | AC7: =IFERROR(AC9+AC8,"") | AD7: =IFERROR(AD9+AD8,"") | AE7: =SUM(AA7:AD7) | AF7: =IFERROR(AF9+AF8,"") | AG7: =IFERROR(AG9+AG8,"") | AH7: =IFERROR(AH9+AH8,"") | AI7: =IFERROR(AI9+AI8,"") | AJ7: =SUM(AF7:AI7) | AK7: =IFERROR(AK9+AK8,"") | AL7: =IFERROR(AL9+AL8,"") | AM7: =IFERROR(AM9+AM8,"") | AN7: =IFERROR(AN9+AN8,"") | AO7: =SUM(AK7:AN7)
A8: 판관비 | B8: 손익 | C8: 억원 | D8: 판관비 | E8: =IFERROR(VLOOKUP($D8,BS연결,MATCH(E$1,BS연결H,0),0)/100,"") | G8: =IFERROR(VLOOKUP($D8,BS연결,MATCH(G$1,BS연결H,0),0)/100,"") | H8: =IFERROR(VLOOKUP($D8,BS연결,MATCH(H$1,BS연결H,0),0)/100,"") | I8: =IFERROR(VLOOKUP($D8,BS연결,MATCH(I$1,BS연결H,0),0)/100,"") | J8: =IFERROR(VLOOKUP($D8,BS연결,MATCH(J$1,BS연결H,0),0)/100,"") | K8: =IFERROR(VLOOKUP($D8,BS연결,MATCH(K$1,BS연결H,0),0)/100,"") | L8: =IFERROR(VLOOKUP($D8,BS연결,MATCH(L$1,BS연결H,0),0)/100,"") | M8: =IFERROR(VLOOKUP($D8,BS연결,MATCH(M$1,BS연결H,0),0)/100,"") | N8: =IFERROR(VLOOKUP($D8,BS연결,MATCH(N$1,BS연결H,0),0)/100,"") | ... AB8: =IFERROR(VLOOKUP($D8,BS연결,MATCH(AB$1,BS연결H,0),0)/100,"") | AC8: =IFERROR(AC5*변수!AC22,"") | AD8: =IFERROR(AD5*변수!AD22,"") | AE8: =SUM(AA8:AD8) | AF8: =IFERROR(AF5*변수!AF22,"") | AG8: =IFERROR(AG5*변수!AG22,"") | AH8: =IFERROR(AH5*변수!AH22,"") | AI8: =IFERROR(AI5*변수!AI22,"") | AJ8: =SUM(AF8:AI8) | AK8: =IFERROR(AK5*변수!AK22,"") | AL8: =IFERROR(AL5*변수!AL22,"") | AM8: =IFERROR(AM5*변수!AM22,"") | AN8: =IFERROR(AN5*변수!AN22,"") | AO8: =SUM(AK8:AN8)
A9: 영업이익 | B9: 손익 | C9: 억원 | D9: 영업이익 | E9: =IFERROR(VLOOKUP($D9,BS연결,MATCH(E$1,BS연결H,0),0)/100,"") | G9: =IFERROR(VLOOKUP($D9,BS연결,MATCH(G$1,BS연결H,0),0)/100,"") | H9: =IFERROR(VLOOKUP($D9,BS연결,MATCH(H$1,BS연결H,0),0)/100,"") | I9: =IFERROR(VLOOKUP($D9,BS연결,MATCH(I$1,BS연결H,0),0)/100,"") | J9: =IFERROR(VLOOKUP($D9,BS연결,MATCH(J$1,BS연결H,0),0)/100,"") | K9: =IFERROR(VLOOKUP($D9,BS연결,MATCH(K$1,BS연결H,0),0)/100,"") | L9: =IFERROR(VLOOKUP($D9,BS연결,MATCH(L$1,BS연결H,0),0)/100,"") | M9: =IFERROR(VLOOKUP($D9,BS연결,MATCH(M$1,BS연결H,0),0)/100,"") | N9: =IFERROR(VLOOKUP($D9,BS연결,MATCH(N$1,BS연결H,0),0)/100,"") | ... AB9: =IFERROR(VLOOKUP($D9,BS연결,MATCH(AB$1,BS연결H,0),0)/100,"") | AC9: =IFERROR(AC5*변수!AC23,"") | AD9: =IFERROR(AD5*변수!AD23,"") | AE9: =SUM(AA9:AD9) | AF9: =IFERROR(AF5*변수!AF23,"") | AG9: =IFERROR(AG5*변수!AG23,"") | AH9: =IFERROR(AH5*변수!AH23,"") | AI9: =IFERROR(AI5*변수!AI23,"") | AJ9: =SUM(AF9:AI9) | AK9: =IFERROR(AK5*변수!AK23,"") | AL9: =IFERROR(AL5*변수!AL23,"") | AM9: =IFERROR(AM5*변수!AM23,"") | AN9: =IFERROR(AN5*변수!AN23,"") | AO9: =SUM(AK9:AN9)
A10: OPM | B10: 손익 | C10: % | D10: 영업이익률 | E10: =IFERROR(E9/E5,"") | G10: =IFERROR(G9/G5,"") | H10: =IFERROR(H9/H5,"") | I10: =IFERROR(I9/I5,"") | J10: =IFERROR(J9/J5,"") | K10: =IFERROR(K9/K5,"") | L10: =IFERROR(L9/L5,"") | M10: =IFERROR(M9/M5,"") | N10: =IFERROR(N9/N5,"") | ... AO10: =IFERROR(AO9/AO5,"")
A11: 금융손익 | B11: 손익 | C11: 억원 | D11: 금융손익 | E11: =IFERROR(VLOOKUP($D11,BS연결,MATCH(E$1,BS연결H,0),0)/100,"") | G11: =IFERROR(VLOOKUP($D11,BS연결,MATCH(G$1,BS연결H,0),0)/100,"") | H11: =IFERROR(VLOOKUP($D11,BS연결,MATCH(H$1,BS연결H,0),0)/100,"") | I11: =IFERROR(VLOOKUP($D11,BS연결,MATCH(I$1,BS연결H,0),0)/100,"") | J11: =IFERROR(VLOOKUP($D11,BS연결,MATCH(J$1,BS연결H,0),0)/100,"") | K11: =IFERROR(VLOOKUP($D11,BS연결,MATCH(K$1,BS연결H,0),0)/100,"") | L11: =IFERROR(VLOOKUP($D11,BS연결,MATCH(L$1,BS연결H,0),0)/100,"") | M11: =IFERROR(VLOOKUP($D11,BS연결,MATCH(M$1,BS연결H,0),0)/100,"") | N11: =IFERROR(VLOOKUP($D11,BS연결,MATCH(N$1,BS연결H,0),0)/100,"") | ... AB11: =IFERROR(VLOOKUP($D11,BS연결,MATCH(AB$1,BS연결H,0),0)/100,"") | AC11: =IFERROR(AC12+AC13+AC14+AC15,"") | AD11: =IFERROR(AD12+AD13+AD14+AD15,"") | AE11: =SUM(AA11:AD11) | AF11: =IFERROR(AF12+AF13+AF14+AF15,"") | AG11: =IFERROR(AG12+AG13+AG14+AG15,"") | AH11: =IFERROR(AH12+AH13+AH14+AH15,"") | AI11: =IFERROR(AI12+AI13+AI14+AI15,"") | AJ11: =SUM(AF11:AI11) | AK11: =IFERROR(AK12+AK13+AK14+AK15,"") | AL11: =IFERROR(AL12+AL13+AL14+AL15,"") | AM11: =IFERROR(AM12+AM13+AM14+AM15,"") | AN11: =IFERROR(AN12+AN13+AN14+AN15,"") | AO11: =SUM(AK11:AN11)
A12: 이자손익 | B12: 손익 | C12: 억원 | D12: 이자손익 | G12: =IFERROR(VLOOKUP($D12,BS연결,MATCH(G$1,BS연결H,0),0)/100,"") | H12: =IFERROR(VLOOKUP($D12,BS연결,MATCH(H$1,BS연결H,0),0)/100,"") | I12: =IFERROR(VLOOKUP($D12,BS연결,MATCH(I$1,BS연결H,0),0)/100,"") | J12: =IFERROR(VLOOKUP($D12,BS연결,MATCH(J$1,BS연결H,0),0)/100,"") | K12: =IFERROR(VLOOKUP($D12,BS연결,MATCH(K$1,BS연결H,0),0)/100,"") | L12: =IFERROR(VLOOKUP($D12,BS연결,MATCH(L$1,BS연결H,0),0)/100,"") | M12: =IFERROR(VLOOKUP($D12,BS연결,MATCH(M$1,BS연결H,0),0)/100,"") | N12: =IFERROR(VLOOKUP($D12,BS연결,MATCH(N$1,BS연결H,0),0)/100,"") | ... Z12: =IFERROR(VLOOKUP($D12,BS연결,MATCH(Z$1,BS연결H,0),0)/100,"") | AB12: =IFERROR(VLOOKUP($D12,BS연결,MATCH(AB$1,BS연결H,0),0)/100,"") | AC12: =IFERROR((AB29*변수!$D$54-AB27*변수!$D$55)/4,"") | AD12: =IFERROR((AC29*변수!$D$54-AC27*변수!$D$55)/4,"") | AE12: =SUM(AA12:AD12) | AF12: =IFERROR((AD29*변수!$D$54-AD27*변수!$D$55)/4,"") | AG12: =IFERROR((AF29*변수!$D$54-AF27*변수!$D$55)/4,"") | AH12: =IFERROR((AG29*변수!$D$54-AG27*변수!$D$55)/4,"") | AI12: =IFERROR((AH29*변수!$D$54-AH27*변수!$D$55)/4,"") | AJ12: =SUM(AF12:AI12) | AK12: =IFERROR((AI29*변수!$D$54-AI27*변수!$D$55)/4,"") | AL12: =IFERROR((AK29*변수!$D$54-AK27*변수!$D$55)/4,"") | AM12: =IFERROR((AL29*변수!$D$54-AL27*변수!$D$55)/4,"") | AN12: =IFERROR((AM29*변수!$D$54-AM27*변수!$D$55)/4,"") | AO12: =SUM(AK12:AN12)
A13: 외환손익 | B13: 손익 | C13: 억원 | D13: 외환손익(실적만; 추정 환효과는 환관련손익) | G13: =IFERROR((VLOOKUP("외환차익",BS연결,MATCH(G$1,BS연결H,0),0)-VLOOKUP("외환차손",BS연결,MATCH(G$1,BS연결H,0),0)+VLOOKUP("외화환산이익",BS연결,MATCH(G$1,BS연결H,0),0)-VLOOKUP("외화환산손실",BS연결,MATCH(G$1,BS연결H,0),0))/100,"") | H13: =IFERROR((VLOOKUP("외환차익",BS연결,MATCH(H$1,BS연결H,0),0)-VLOOKUP("외환차손",BS연결,MATCH(H$1,BS연결H,0),0)+VLOOKUP("외화환산이익",BS연결,MATCH(H$1,BS연결H,0),0)-VLOOKUP("외화환산손실",BS연결,MATCH(H$1,BS연결H,0),0))/100,"") | I13: =IFERROR((VLOOKUP("외환차익",BS연결,MATCH(I$1,BS연결H,0),0)-VLOOKUP("외환차손",BS연결,MATCH(I$1,BS연결H,0),0)+VLOOKUP("외화환산이익",BS연결,MATCH(I$1,BS연결H,0),0)-VLOOKUP("외화환산손실",BS연결,MATCH(I$1,BS연결H,0),0))/100,"") | J13: =IFERROR((VLOOKUP("외환차익",BS연결,MATCH(J$1,BS연결H,0),0)-VLOOKUP("외환차손",BS연결,MATCH(J$1,BS연결H,0),0)+VLOOKUP("외화환산이익",BS연결,MATCH(J$1,BS연결H,0),0)-VLOOKUP("외화환산손실",BS연결,MATCH(J$1,BS연결H,0),0))/100,"") | K13: =SUM(G13:J13) | L13: =IFERROR((VLOOKUP("외환차익",BS연결,MATCH(L$1,BS연결H,0),0)-VLOOKUP("외환차손",BS연결,MATCH(L$1,BS연결H,0),0)+VLOOKUP("외화환산이익",BS연결,MATCH(L$1,BS연결H,0),0)-VLOOKUP("외화환산손실",BS연결,MATCH(L$1,BS연결H,0),0))/100,"") | M13: =IFERROR((VLOOKUP("외환차익",BS연결,MATCH(M$1,BS연결H,0),0)-VLOOKUP("외환차손",BS연결,MATCH(M$1,BS연결H,0),0)+VLOOKUP("외화환산이익",BS연결,MATCH(M$1,BS연결H,0),0)-VLOOKUP("외화환산손실",BS연결,MATCH(M$1,BS연결H,0),0))/100,"") | N13: =IFERROR((VLOOKUP("외환차익",BS연결,MATCH(N$1,BS연결H,0),0)-VLOOKUP("외환차손",BS연결,MATCH(N$1,BS연결H,0),0)+VLOOKUP("외화환산이익",BS연결,MATCH(N$1,BS연결H,0),0)-VLOOKUP("외화환산손실",BS연결,MATCH(N$1,BS연결H,0),0))/100,"") | O13: =IFERROR((VLOOKUP("외환차익",BS연결,MATCH(O$1,BS연결H,0),0)-VLOOKUP("외환차손",BS연결,MATCH(O$1,BS연결H,0),0)+VLOOKUP("외화환산이익",BS연결,MATCH(O$1,BS연결H,0),0)-VLOOKUP("외화환산손실",BS연결,MATCH(O$1,BS연결H,0),0))/100,"") | P13: =SUM(L13:O13) | Q13: =IFERROR((VLOOKUP("외환차익",BS연결,MATCH(Q$1,BS연결H,0),0)-VLOOKUP("외환차손",BS연결,MATCH(Q$1,BS연결H,0),0)+VLOOKUP("외화환산이익",BS연결,MATCH(Q$1,BS연결H,0),0)-VLOOKUP("외화환산손실",BS연결,MATCH(Q$1,BS연결H,0),0))/100,"") | R13: =IFERROR((VLOOKUP("외환차익",BS연결,MATCH(R$1,BS연결H,0),0)-VLOOKUP("외환차손",BS연결,MATCH(R$1,BS연결H,0),0)+VLOOKUP("외화환산이익",BS연결,MATCH(R$1,BS연결H,0),0)-VLOOKUP("외화환산손실",BS연결,MATCH(R$1,BS연결H,0),0))/100,"") | S13: =IFERROR((VLOOKUP("외환차익",BS연결,MATCH(S$1,BS연결H,0),0)-VLOOKUP("외환차손",BS연결,MATCH(S$1,BS연결H,0),0)+VLOOKUP("외화환산이익",BS연결,MATCH(S$1,BS연결H,0),0)-VLOOKUP("외화환산손실",BS연결,MATCH(S$1,BS연결H,0),0))/100,"") | T13: =IFERROR((VLOOKUP("외환차익",BS연결,MATCH(T$1,BS연결H,0),0)-VLOOKUP("외환차손",BS연결,MATCH(T$1,BS연결H,0),0)+VLOOKUP("외화환산이익",BS연결,MATCH(T$1,BS연결H,0),0)-VLOOKUP("외화환산손실",BS연결,MATCH(T$1,BS연결H,0),0))/100,"") | U13: =SUM(Q13:T13) | V13: =IFERROR((VLOOKUP("외환차익",BS연결,MATCH(V$1,BS연결H,0),0)-VLOOKUP("외환차손",BS연결,MATCH(V$1,BS연결H,0),0)+VLOOKUP("외화환산이익",BS연결,MATCH(V$1,BS연결H,0),0)-VLOOKUP("외화환산손실",BS연결,MATCH(V$1,BS연결H,0),0))/100,"") | W13: =IFERROR((VLOOKUP("외환차익",BS연결,MATCH(W$1,BS연결H,0),0)-VLOOKUP("외환차손",BS연결,MATCH(W$1,BS연결H,0),0)+VLOOKUP("외화환산이익",BS연결,MATCH(W$1,BS연결H,0),0)-VLOOKUP("외화환산손실",BS연결,MATCH(W$1,BS연결H,0),0))/100,"") | X13: =IFERROR((VLOOKUP("외환차익",BS연결,MATCH(X$1,BS연결H,0),0)-VLOOKUP("외환차손",BS연결,MATCH(X$1,BS연결H,0),0)+VLOOKUP("외화환산이익",BS연결,MATCH(X$1,BS연결H,0),0)-VLOOKUP("외화환산손실",BS연결,MATCH(X$1,BS연결H,0),0))/100,"") | Y13: =IFERROR((VLOOKUP("외환차익",BS연결,MATCH(Y$1,BS연결H,0),0)-VLOOKUP("외환차손",BS연결,MATCH(Y$1,BS연결H,0),0)+VLOOKUP("외화환산이익",BS연결,MATCH(Y$1,BS연결H,0),0)-VLOOKUP("외화환산손실",BS연결,MATCH(Y$1,BS연결H,0),0))/100,"") | Z13: =SUM(V13:Y13) | AB13: =IFERROR((VLOOKUP("외환차익",BS연결,MATCH(AB$1,BS연결H,0),0)-VLOOKUP("외환차손",BS연결,MATCH(AB$1,BS연결H,0),0)+VLOOKUP("외화환산이익",BS연결,MATCH(AB$1,BS연결H,0),0)-VLOOKUP("외화환산손실",BS연결,MATCH(AB$1,BS연결H,0),0))/100,"") | AC13: =변수!AC24 | AD13: =변수!AD24 | AE13: =SUM(AA13:AD13) | AF13: =변수!AF24 | AG13: =변수!AG24 | AH13: =변수!AH24 | AI13: =변수!AI24 | AJ13: =SUM(AF13:AI13) | AK13: =변수!AK24 | AL13: =변수!AL24 | AM13: =변수!AM24 | AN13: =변수!AN24 | AO13: =SUM(AK13:AN13)
A14: 파생상품손익 | B14: 손익 | C14: 억원 | D14: 파생상품손익 | K14: =SUM(G14:J14) | P14: =SUM(L14:O14) | U14: =SUM(Q14:T14) | W14: =IFERROR((VLOOKUP("파생상품이익",BS연결,MATCH(W$1,BS연결H,0),0)-VLOOKUP("파생상품손실",BS연결,MATCH(W$1,BS연결H,0),0))/100,"") | X14: =IFERROR((VLOOKUP("파생상품이익",BS연결,MATCH(X$1,BS연결H,0),0)-VLOOKUP("파생상품손실",BS연결,MATCH(X$1,BS연결H,0),0))/100,"") | Y14: =IFERROR((VLOOKUP("파생상품이익",BS연결,MATCH(Y$1,BS연결H,0),0)-VLOOKUP("파생상품손실",BS연결,MATCH(Y$1,BS연결H,0),0))/100,"") | Z14: =SUM(V14:Y14) | AB14: =IFERROR((VLOOKUP("파생상품이익",BS연결,MATCH(AB$1,BS연결H,0),0)-VLOOKUP("파생상품손실",BS연결,MATCH(AB$1,BS연결H,0),0))/100,"") | AC14: =변수!AC25 | AD14: =변수!AD25 | AE14: =SUM(AA14:AD14) | AF14: =변수!AF25 | AG14: =변수!AG25 | AH14: =변수!AH25 | AI14: =변수!AI25 | AJ14: =SUM(AF14:AI14) | AK14: =변수!AK25 | AL14: =변수!AL25 | AM14: =변수!AM25 | AN14: =변수!AN25 | AO14: =SUM(AK14:AN14)
A15: 기타금융손익 | B15: 손익 | C15: 억원 | D15: 기타금융손익(금융손익 잔차) | K15: =SUM(G15:J15) | P15: =SUM(L15:O15) | U15: =SUM(Q15:T15) | W15: =IFERROR(W11-W12-W13-W14,"") | X15: =IFERROR(X11-X12-X13-X14,"") | Y15: =IFERROR(Y11-Y12-Y13-Y14,"") | Z15: =SUM(V15:Y15) | AB15: =IFERROR(AB11-AB12-AB13-AB14,"") | AC15: =변수!AC26 | AD15: =변수!AD26 | AE15: =SUM(AA15:AD15) | AF15: =변수!AF26 | AG15: =변수!AG26 | AH15: =변수!AH26 | AI15: =변수!AI26 | AJ15: =SUM(AF15:AI15) | AK15: =변수!AK26 | AL15: =변수!AL26 | AM15: =변수!AM26 | AN15: =변수!AN26 | AO15: =SUM(AK15:AN15)
A16: 기타영업외손익 | B16: 손익 | C16: 억원 | D16: 기타영업외손익 | E16: =IFERROR(VLOOKUP($D16,BS연결,MATCH(E$1,BS연결H,0),0)/100,"") | G16: =IFERROR(VLOOKUP($D16,BS연결,MATCH(G$1,BS연결H,0),0)/100,"") | H16: =IFERROR(VLOOKUP($D16,BS연결,MATCH(H$1,BS연결H,0),0)/100,"") | I16: =IFERROR(VLOOKUP($D16,BS연결,MATCH(I$1,BS연결H,0),0)/100,"") | J16: =IFERROR(VLOOKUP($D16,BS연결,MATCH(J$1,BS연결H,0),0)/100,"") | K16: =IFERROR(VLOOKUP($D16,BS연결,MATCH(K$1,BS연결H,0),0)/100,"") | L16: =IFERROR(VLOOKUP($D16,BS연결,MATCH(L$1,BS연결H,0),0)/100,"") | M16: =IFERROR(VLOOKUP($D16,BS연결,MATCH(M$1,BS연결H,0),0)/100,"") | N16: =IFERROR(VLOOKUP($D16,BS연결,MATCH(N$1,BS연결H,0),0)/100,"") | ... AB16: =IFERROR(VLOOKUP($D16,BS연결,MATCH(AB$1,BS연결H,0),0)/100,"") | AC16: =변수!AC27 | AD16: =변수!AD27 | AE16: =SUM(AA16:AD16) | AF16: =변수!AF27 | AG16: =변수!AG27 | AH16: =변수!AH27 | AI16: =변수!AI27 | AJ16: =SUM(AF16:AI16) | AK16: =변수!AK27 | AL16: =변수!AL27 | AM16: =변수!AM27 | AN16: =변수!AN27 | AO16: =SUM(AK16:AN16)
A17: 세전이익 | B17: 손익 | C17: 억원 | D17: 법인세비용차감전계속사업이익 | E17: =IFERROR(VLOOKUP($D17,BS연결,MATCH(E$1,BS연결H,0),0)/100,"") | G17: =IFERROR(VLOOKUP($D17,BS연결,MATCH(G$1,BS연결H,0),0)/100,"") | H17: =IFERROR(VLOOKUP($D17,BS연결,MATCH(H$1,BS연결H,0),0)/100,"") | I17: =IFERROR(VLOOKUP($D17,BS연결,MATCH(I$1,BS연결H,0),0)/100,"") | J17: =IFERROR(VLOOKUP($D17,BS연결,MATCH(J$1,BS연결H,0),0)/100,"") | K17: =IFERROR(VLOOKUP($D17,BS연결,MATCH(K$1,BS연결H,0),0)/100,"") | L17: =IFERROR(VLOOKUP($D17,BS연결,MATCH(L$1,BS연결H,0),0)/100,"") | M17: =IFERROR(VLOOKUP($D17,BS연결,MATCH(M$1,BS연결H,0),0)/100,"") | N17: =IFERROR(VLOOKUP($D17,BS연결,MATCH(N$1,BS연결H,0),0)/100,"") | ... AB17: =IFERROR(VLOOKUP($D17,BS연결,MATCH(AB$1,BS연결H,0),0)/100,"") | AC17: =IFERROR(AC9+AC11+AC16,"") | AD17: =IFERROR(AD9+AD11+AD16,"") | AE17: =SUM(AA17:AD17) | AF17: =IFERROR(AF9+AF11+AF16,"") | AG17: =IFERROR(AG9+AG11+AG16,"") | AH17: =IFERROR(AH9+AH11+AH16,"") | AI17: =IFERROR(AI9+AI11+AI16,"") | AJ17: =SUM(AF17:AI17) | AK17: =IFERROR(AK9+AK11+AK16,"") | AL17: =IFERROR(AL9+AL11+AL16,"") | AM17: =IFERROR(AM9+AM11+AM16,"") | AN17: =IFERROR(AN9+AN11+AN16,"") | AO17: =SUM(AK17:AN17)
A18: 법인세비용 | B18: 손익 | C18: 억원 | D18: 법인세비용 | E18: =IFERROR(VLOOKUP($D18,BS연결,MATCH(E$1,BS연결H,0),0)/100,"") | G18: =IFERROR(VLOOKUP($D18,BS연결,MATCH(G$1,BS연결H,0),0)/100,"") | H18: =IFERROR(VLOOKUP($D18,BS연결,MATCH(H$1,BS연결H,0),0)/100,"") | I18: =IFERROR(VLOOKUP($D18,BS연결,MATCH(I$1,BS연결H,0),0)/100,"") | J18: =IFERROR(VLOOKUP($D18,BS연결,MATCH(J$1,BS연결H,0),0)/100,"") | K18: =IFERROR(VLOOKUP($D18,BS연결,MATCH(K$1,BS연결H,0),0)/100,"") | L18: =IFERROR(VLOOKUP($D18,BS연결,MATCH(L$1,BS연결H,0),0)/100,"") | M18: =IFERROR(VLOOKUP($D18,BS연결,MATCH(M$1,BS연결H,0),0)/100,"") | N18: =IFERROR(VLOOKUP($D18,BS연결,MATCH(N$1,BS연결H,0),0)/100,"") | ... AB18: =IFERROR(VLOOKUP($D18,BS연결,MATCH(AB$1,BS연결H,0),0)/100,"") | AC18: =IFERROR(MAX(AC17,0)*변수!AC28,"") | AD18: =IFERROR(MAX(AD17,0)*변수!AD28,"") | AE18: =SUM(AA18:AD18) | AF18: =IFERROR(MAX(AF17,0)*변수!AF28,"") | AG18: =IFERROR(MAX(AG17,0)*변수!AG28,"") | AH18: =IFERROR(MAX(AH17,0)*변수!AH28,"") | AI18: =IFERROR(MAX(AI17,0)*변수!AI28,"") | AJ18: =SUM(AF18:AI18) | AK18: =IFERROR(MAX(AK17,0)*변수!AK28,"") | AL18: =IFERROR(MAX(AL17,0)*변수!AL28,"") | AM18: =IFERROR(MAX(AM17,0)*변수!AM28,"") | AN18: =IFERROR(MAX(AN17,0)*변수!AN28,"") | AO18: =SUM(AK18:AN18)
A19: 당기순이익 | B19: 손익 | C19: 억원 | D19: 당기순이익 | E19: =IFERROR(VLOOKUP($D19,BS연결,MATCH(E$1,BS연결H,0),0)/100,"") | G19: =IFERROR(VLOOKUP($D19,BS연결,MATCH(G$1,BS연결H,0),0)/100,"") | H19: =IFERROR(VLOOKUP($D19,BS연결,MATCH(H$1,BS연결H,0),0)/100,"") | I19: =IFERROR(VLOOKUP($D19,BS연결,MATCH(I$1,BS연결H,0),0)/100,"") | J19: =IFERROR(VLOOKUP($D19,BS연결,MATCH(J$1,BS연결H,0),0)/100,"") | K19: =IFERROR(VLOOKUP($D19,BS연결,MATCH(K$1,BS연결H,0),0)/100,"") | L19: =IFERROR(VLOOKUP($D19,BS연결,MATCH(L$1,BS연결H,0),0)/100,"") | M19: =IFERROR(VLOOKUP($D19,BS연결,MATCH(M$1,BS연결H,0),0)/100,"") | N19: =IFERROR(VLOOKUP($D19,BS연결,MATCH(N$1,BS연결H,0),0)/100,"") | ... AB19: =IFERROR(VLOOKUP($D19,BS연결,MATCH(AB$1,BS연결H,0),0)/100,"") | AC19: =IFERROR(AC17-AC18,"") | AD19: =IFERROR(AD17-AD18,"") | AE19: =SUM(AA19:AD19) | AF19: =IFERROR(AF17-AF18,"") | AG19: =IFERROR(AG17-AG18,"") | AH19: =IFERROR(AH17-AH18,"") | AI19: =IFERROR(AI17-AI18,"") | AJ19: =SUM(AF19:AI19) | AK19: =IFERROR(AK17-AK18,"") | AL19: =IFERROR(AL17-AL18,"") | AM19: =IFERROR(AM17-AM18,"") | AN19: =IFERROR(AN17-AN18,"") | AO19: =SUM(AK19:AN19)
A20: 지배주주순이익 | B20: 손익 | C20: 억원 | D20: (지배주주지분)당기순이익 | E20: =IFERROR(VLOOKUP($D20,BS연결,MATCH(E$1,BS연결H,0),0)/100,"") | G20: =IFERROR(VLOOKUP($D20,BS연결,MATCH(G$1,BS연결H,0),0)/100,"") | H20: =IFERROR(VLOOKUP($D20,BS연결,MATCH(H$1,BS연결H,0),0)/100,"") | I20: =IFERROR(VLOOKUP($D20,BS연결,MATCH(I$1,BS연결H,0),0)/100,"") | J20: =IFERROR(VLOOKUP($D20,BS연결,MATCH(J$1,BS연결H,0),0)/100,"") | K20: =IFERROR(VLOOKUP($D20,BS연결,MATCH(K$1,BS연결H,0),0)/100,"") | L20: =IFERROR(VLOOKUP($D20,BS연결,MATCH(L$1,BS연결H,0),0)/100,"") | M20: =IFERROR(VLOOKUP($D20,BS연결,MATCH(M$1,BS연결H,0),0)/100,"") | N20: =IFERROR(VLOOKUP($D20,BS연결,MATCH(N$1,BS연결H,0),0)/100,"") | O20: =IFERROR(VLOOKUP($D20,BS연결,MATCH(O$1,BS연결H,0),0)/100,"") | P20: =SUM(L20:O20) | Q20: =IFERROR(VLOOKUP($D20,BS연결,MATCH(Q$1,BS연결H,0),0)/100,"") | R20: =IFERROR(VLOOKUP($D20,BS연결,MATCH(R$1,BS연결H,0),0)/100,"") | S20: =IFERROR(VLOOKUP($D20,BS연결,MATCH(S$1,BS연결H,0),0)/100,"") | T20: =IFERROR(VLOOKUP($D20,BS연결,MATCH(T$1,BS연결H,0),0)/100,"") | U20: =IFERROR(VLOOKUP($D20,BS연결,MATCH(U$1,BS연결H,0),0)/100,"") | V20: =IFERROR(VLOOKUP($D20,BS연결,MATCH(V$1,BS연결H,0),0)/100,"") | W20: =IFERROR(VLOOKUP($D20,BS연결,MATCH(W$1,BS연결H,0),0)/100,"") | X20: =IFERROR(VLOOKUP($D20,BS연결,MATCH(X$1,BS연결H,0),0)/100,"") | ... AB20: =IFERROR(VLOOKUP($D20,BS연결,MATCH(AB$1,BS연결H,0),0)/100,"") | AC20: =IFERROR(AC19*변수!AC29,"") | AD20: =IFERROR(AD19*변수!AD29,"") | AE20: =SUM(AA20:AD20) | AF20: =IFERROR(AF19*변수!AF29,"") | AG20: =IFERROR(AG19*변수!AG29,"") | AH20: =IFERROR(AH19*변수!AH29,"") | AI20: =IFERROR(AI19*변수!AI29,"") | AJ20: =SUM(AF20:AI20) | AK20: =IFERROR(AK19*변수!AK29,"") | AL20: =IFERROR(AL19*변수!AL29,"") | AM20: =IFERROR(AM19*변수!AM29,"") | AN20: =IFERROR(AN19*변수!AN29,"") | AO20: =SUM(AK20:AN20)
A21: 감가상각비 | B21: 손익 | C21: 억원 | D21: 감가상각비 | E21: =IFERROR(VLOOKUP($D21,BS연결,MATCH(E$1,BS연결H,0),0)/100,"") | G21: =IFERROR(VLOOKUP($D21,BS연결,MATCH(G$1,BS연결H,0),0)/100,"") | H21: =IFERROR(VLOOKUP($D21,BS연결,MATCH(H$1,BS연결H,0),0)/100,"") | I21: =IFERROR(VLOOKUP($D21,BS연결,MATCH(I$1,BS연결H,0),0)/100,"") | J21: =IFERROR(VLOOKUP($D21,BS연결,MATCH(J$1,BS연결H,0),0)/100,"") | K21: =IFERROR(VLOOKUP($D21,BS연결,MATCH(K$1,BS연결H,0),0)/100,"") | L21: =IFERROR(VLOOKUP($D21,BS연결,MATCH(L$1,BS연결H,0),0)/100,"") | M21: =IFERROR(VLOOKUP($D21,BS연결,MATCH(M$1,BS연결H,0),0)/100,"") | N21: =IFERROR(VLOOKUP($D21,BS연결,MATCH(N$1,BS연결H,0),0)/100,"") | ... X21: =IFERROR(VLOOKUP($D21,BS연결,MATCH(X$1,BS연결H,0),0)/100,"") | Z21: =SUM(V21:Y21) | AC21: =변수!AC30 | AD21: =변수!AD30 | AE21: =SUM(AA21:AD21) | AF21: =변수!AF30 | AG21: =변수!AG30 | AH21: =변수!AH30 | AI21: =변수!AI30 | AJ21: =SUM(AF21:AI21) | AK21: =변수!AK30 | AL21: =변수!AL30 | AM21: =변수!AM30 | AN21: =변수!AN30 | AO21: =SUM(AK21:AN21)
A22: EBITDA | B22: 손익 | C22: 억원 | D22: EBITDA | E22: 35.65 | G22: 47.99 | H22: 76.07 | I22: 19.36 | J22: 21.69 | K22: =SUM(G22:J22) | L22: 47.79 | M22: 46.72 | N22: 21.92 | O22: -13.94 | P22: =SUM(L22:O22) | Q22: 29.52 | R22: 32.05 | S22: 23.66 | T22: 18.86 | U22: =SUM(Q22:T22) | V22: 11.06 | W22: 60.35 | X22: 36.31 | Z22: =SUM(V22:Y22) | AC22: =IFERROR(AC9+AC21,"") | AD22: =IFERROR(AD9+AD21,"") | AE22: =SUM(AA22:AD22) | AF22: =IFERROR(AF9+AF21,"") | AG22: =IFERROR(AG9+AG21,"") | AH22: =IFERROR(AH9+AH21,"") | AI22: =IFERROR(AI9+AI21,"") | AJ22: =SUM(AF22:AI22) | AK22: =IFERROR(AK9+AK21,"") | AL22: =IFERROR(AL9+AL21,"") | AM22: =IFERROR(AM9+AM21,"") | AN22: =IFERROR(AN9+AN21,"") | AO22: =SUM(AK22:AN22)
A23: 자산총계 | B23: 재무상태 | C23: 억원 | D23: 자산총계 | E23: =IFERROR(VLOOKUP($D23,BS연결,MATCH(E$1,BS연결H,0),0)/100,"") | F23: =IFERROR(VLOOKUP($D23,BS연결,MATCH(F$1,BS연결H,0),0)/100,"") | G23: =IFERROR(VLOOKUP($D23,BS연결,MATCH(G$1,BS연결H,0),0)/100,"") | H23: =IFERROR(VLOOKUP($D23,BS연결,MATCH(H$1,BS연결H,0),0)/100,"") | I23: =IFERROR(VLOOKUP($D23,BS연결,MATCH(I$1,BS연결H,0),0)/100,"") | J23: =IFERROR(VLOOKUP($D23,BS연결,MATCH(J$1,BS연결H,0),0)/100,"") | K23: =IFERROR(VLOOKUP($D23,BS연결,MATCH(K$1,BS연결H,0),0)/100,"") | L23: =IFERROR(VLOOKUP($D23,BS연결,MATCH(L$1,BS연결H,0),0)/100,"") | ... AB23: =IFERROR(VLOOKUP($D23,BS연결,MATCH(AB$1,BS연결H,0),0)/100,"") | AC23: =IFERROR(AC24+AC25,"") | AD23: =IFERROR(AD24+AD25,"") | AE23: =AD23 | AF23: =IFERROR(AF24+AF25,"") | AG23: =IFERROR(AG24+AG25,"") | AH23: =IFERROR(AH24+AH25,"") | AI23: =IFERROR(AI24+AI25,"") | AJ23: =AI23 | AK23: =IFERROR(AK24+AK25,"") | AL23: =IFERROR(AL24+AL25,"") | AM23: =IFERROR(AM24+AM25,"") | AN23: =IFERROR(AN24+AN25,"") | AO23: =AN23
A24: 부채총계 | B24: 재무상태 | C24: 억원 | D24: 부채총계 | E24: =IFERROR(VLOOKUP($D24,BS연결,MATCH(E$1,BS연결H,0),0)/100,"") | F24: =IFERROR(VLOOKUP($D24,BS연결,MATCH(F$1,BS연결H,0),0)/100,"") | G24: =IFERROR(VLOOKUP($D24,BS연결,MATCH(G$1,BS연결H,0),0)/100,"") | H24: =IFERROR(VLOOKUP($D24,BS연결,MATCH(H$1,BS연결H,0),0)/100,"") | I24: =IFERROR(VLOOKUP($D24,BS연결,MATCH(I$1,BS연결H,0),0)/100,"") | J24: =IFERROR(VLOOKUP($D24,BS연결,MATCH(J$1,BS연결H,0),0)/100,"") | K24: =IFERROR(VLOOKUP($D24,BS연결,MATCH(K$1,BS연결H,0),0)/100,"") | L24: =IFERROR(VLOOKUP($D24,BS연결,MATCH(L$1,BS연결H,0),0)/100,"") | ... AB24: =IFERROR(VLOOKUP($D24,BS연결,MATCH(AB$1,BS연결H,0),0)/100,"") | AC24: =IFERROR(AB24*(1+변수!AC31),"") | AD24: =IFERROR(AC24*(1+변수!AD31),"") | AE24: =AD24 | AF24: =IFERROR(AD24*(1+변수!AF31),"") | AG24: =IFERROR(AF24*(1+변수!AG31),"") | AH24: =IFERROR(AG24*(1+변수!AH31),"") | AI24: =IFERROR(AH24*(1+변수!AI31),"") | AJ24: =AI24 | AK24: =IFERROR(AI24*(1+변수!AK31),"") | AL24: =IFERROR(AK24*(1+변수!AL31),"") | AM24: =IFERROR(AL24*(1+변수!AM31),"") | AN24: =IFERROR(AM24*(1+변수!AN31),"") | AO24: =AN24
A25: 자본총계 | B25: 재무상태 | C25: 억원 | D25: 자본총계 | E25: =IFERROR(VLOOKUP($D25,BS연결,MATCH(E$1,BS연결H,0),0)/100,"") | F25: =IFERROR(VLOOKUP($D25,BS연결,MATCH(F$1,BS연결H,0),0)/100,"") | G25: =IFERROR(VLOOKUP($D25,BS연결,MATCH(G$1,BS연결H,0),0)/100,"") | H25: =IFERROR(VLOOKUP($D25,BS연결,MATCH(H$1,BS연결H,0),0)/100,"") | I25: =IFERROR(VLOOKUP($D25,BS연결,MATCH(I$1,BS연결H,0),0)/100,"") | J25: =IFERROR(VLOOKUP($D25,BS연결,MATCH(J$1,BS연결H,0),0)/100,"") | K25: =IFERROR(VLOOKUP($D25,BS연결,MATCH(K$1,BS연결H,0),0)/100,"") | L25: =IFERROR(VLOOKUP($D25,BS연결,MATCH(L$1,BS연결H,0),0)/100,"") | ... AB25: =IFERROR(VLOOKUP($D25,BS연결,MATCH(AB$1,BS연결H,0),0)/100,"") | AC25: =IFERROR(AB25+AC19-변수!AC32,"") | AD25: =IFERROR(AC25+AD19-변수!AD32,"") | AE25: =AD25 | AF25: =IFERROR(AD25+AF19-변수!AF32,"") | AG25: =IFERROR(AF25+AG19-변수!AG32,"") | AH25: =IFERROR(AG25+AH19-변수!AH32,"") | AI25: =IFERROR(AH25+AI19-변수!AI32,"") | AJ25: =AI25 | AK25: =IFERROR(AI25+AK19-변수!AK32,"") | AL25: =IFERROR(AK25+AL19-변수!AL32,"") | AM25: =IFERROR(AL25+AM19-변수!AM32,"") | AN25: =IFERROR(AM25+AN19-변수!AN32,"") | AO25: =AN25
A26: 지배주주지분 | B26: 재무상태 | C26: 억원 | D26: 지배주주지분 | E26: =IFERROR(VLOOKUP($D26,BS연결,MATCH(E$1,BS연결H,0),0)/100,"") | F26: =IFERROR(VLOOKUP($D26,BS연결,MATCH(F$1,BS연결H,0),0)/100,"") | G26: =IFERROR(VLOOKUP($D26,BS연결,MATCH(G$1,BS연결H,0),0)/100,"") | H26: =IFERROR(VLOOKUP($D26,BS연결,MATCH(H$1,BS연결H,0),0)/100,"") | I26: =IFERROR(VLOOKUP($D26,BS연결,MATCH(I$1,BS연결H,0),0)/100,"") | J26: =IFERROR(VLOOKUP($D26,BS연결,MATCH(J$1,BS연결H,0),0)/100,"") | K26: =IFERROR(VLOOKUP($D26,BS연결,MATCH(K$1,BS연결H,0),0)/100,"") | L26: =IFERROR(VLOOKUP($D26,BS연결,MATCH(L$1,BS연결H,0),0)/100,"") | ... AB26: =IFERROR(VLOOKUP($D26,BS연결,MATCH(AB$1,BS연결H,0),0)/100,"") | AC26: =IFERROR(AB26+AC20-변수!AC33,"") | AD26: =IFERROR(AC26+AD20-변수!AD33,"") | AE26: =AD26 | AF26: =IFERROR(AD26+AF20-변수!AF33,"") | AG26: =IFERROR(AF26+AG20-변수!AG33,"") | AH26: =IFERROR(AG26+AH20-변수!AH33,"") | AI26: =IFERROR(AH26+AI20-변수!AI33,"") | AJ26: =AI26 | AK26: =IFERROR(AI26+AK20-변수!AK33,"") | AL26: =IFERROR(AK26+AL20-변수!AL33,"") | AM26: =IFERROR(AL26+AM20-변수!AM33,"") | AN26: =IFERROR(AM26+AN20-변수!AN33,"") | AO26: =AN26
A27: 총차입금 | B27: 재무상태 | C27: 억원 | D27: 총차입금 | E27: =IFERROR(VLOOKUP($D27,BS연결,MATCH(E$1,BS연결H,0),0)/100,"") | F27: =IFERROR(VLOOKUP($D27,BS연결,MATCH(F$1,BS연결H,0),0)/100,"") | G27: =IFERROR(VLOOKUP($D27,BS연결,MATCH(G$1,BS연결H,0),0)/100,"") | H27: =IFERROR(VLOOKUP($D27,BS연결,MATCH(H$1,BS연결H,0),0)/100,"") | I27: =IFERROR(VLOOKUP($D27,BS연결,MATCH(I$1,BS연결H,0),0)/100,"") | J27: =IFERROR(VLOOKUP($D27,BS연결,MATCH(J$1,BS연결H,0),0)/100,"") | K27: =IFERROR(VLOOKUP($D27,BS연결,MATCH(K$1,BS연결H,0),0)/100,"") | L27: =IFERROR(VLOOKUP($D27,BS연결,MATCH(L$1,BS연결H,0),0)/100,"") | ... AB27: =IFERROR(VLOOKUP($D27,BS연결,MATCH(AB$1,BS연결H,0),0)/100,"") | AC27: =IFERROR(AB27*(1+변수!AC34),"") | AD27: =IFERROR(AC27*(1+변수!AD34),"") | AE27: =AD27 | AF27: =IFERROR(AD27*(1+변수!AF34),"") | AG27: =IFERROR(AF27*(1+변수!AG34),"") | AH27: =IFERROR(AG27*(1+변수!AH34),"") | AI27: =IFERROR(AH27*(1+변수!AI34),"") | AJ27: =AI27 | AK27: =IFERROR(AI27*(1+변수!AK34),"") | AL27: =IFERROR(AK27*(1+변수!AL34),"") | AM27: =IFERROR(AL27*(1+변수!AM34),"") | AN27: =IFERROR(AM27*(1+변수!AN34),"") | AO27: =AN27
A28: 순차입금 | B28: 재무상태 | C28: 억원 | D28: 순차입금 | E28: =IFERROR(VLOOKUP($D28,BS연결,MATCH(E$1,BS연결H,0),0)/100,"") | F28: =IFERROR(VLOOKUP($D28,BS연결,MATCH(F$1,BS연결H,0),0)/100,"") | G28: =IFERROR(VLOOKUP($D28,BS연결,MATCH(G$1,BS연결H,0),0)/100,"") | H28: =IFERROR(VLOOKUP($D28,BS연결,MATCH(H$1,BS연결H,0),0)/100,"") | I28: =IFERROR(VLOOKUP($D28,BS연결,MATCH(I$1,BS연결H,0),0)/100,"") | J28: =IFERROR(VLOOKUP($D28,BS연결,MATCH(J$1,BS연결H,0),0)/100,"") | K28: =IFERROR(VLOOKUP($D28,BS연결,MATCH(K$1,BS연결H,0),0)/100,"") | L28: =IFERROR(VLOOKUP($D28,BS연결,MATCH(L$1,BS연결H,0),0)/100,"") | ... AB28: =IFERROR(VLOOKUP($D28,BS연결,MATCH(AB$1,BS연결H,0),0)/100,"") | AC28: =IFERROR(AB28*(1+변수!AC35),"") | AD28: =IFERROR(AC28*(1+변수!AD35),"") | AE28: =AD28 | AF28: =IFERROR(AD28*(1+변수!AF35),"") | AG28: =IFERROR(AF28*(1+변수!AG35),"") | AH28: =IFERROR(AG28*(1+변수!AH35),"") | AI28: =IFERROR(AH28*(1+변수!AI35),"") | AJ28: =AI28 | AK28: =IFERROR(AI28*(1+변수!AK35),"") | AL28: =IFERROR(AK28*(1+변수!AL35),"") | AM28: =IFERROR(AL28*(1+변수!AM35),"") | AN28: =IFERROR(AM28*(1+변수!AN35),"") | AO28: =AN28
A29: 이자발생자산 | B29: 재무상태 | C29: 억원 | D29: 이자발생자산 | E29: =IFERROR(VLOOKUP($D29,BS연결,MATCH(E$1,BS연결H,0),0)/100,"") | F29: =IFERROR(VLOOKUP($D29,BS연결,MATCH(F$1,BS연결H,0),0)/100,"") | G29: =IFERROR(VLOOKUP($D29,BS연결,MATCH(G$1,BS연결H,0),0)/100,"") | H29: =IFERROR(VLOOKUP($D29,BS연결,MATCH(H$1,BS연결H,0),0)/100,"") | I29: =IFERROR(VLOOKUP($D29,BS연결,MATCH(I$1,BS연결H,0),0)/100,"") | J29: =IFERROR(VLOOKUP($D29,BS연결,MATCH(J$1,BS연결H,0),0)/100,"") | K29: =IFERROR(VLOOKUP($D29,BS연결,MATCH(K$1,BS연결H,0),0)/100,"") | L29: =IFERROR(VLOOKUP($D29,BS연결,MATCH(L$1,BS연결H,0),0)/100,"") | ... AB29: =IFERROR(VLOOKUP($D29,BS연결,MATCH(AB$1,BS연결H,0),0)/100,"") | AC29: =IFERROR(AB29*(1+변수!AC36),"") | AD29: =IFERROR(AC29*(1+변수!AD36),"") | AE29: =AD29 | AF29: =IFERROR(AD29*(1+변수!AF36),"") | AG29: =IFERROR(AF29*(1+변수!AG36),"") | AH29: =IFERROR(AG29*(1+변수!AH36),"") | AI29: =IFERROR(AH29*(1+변수!AI36),"") | AJ29: =AI29 | AK29: =IFERROR(AI29*(1+변수!AK36),"") | AL29: =IFERROR(AK29*(1+변수!AL36),"") | AM29: =IFERROR(AL29*(1+변수!AM36),"") | AN29: =IFERROR(AM29*(1+변수!AN36),"") | AO29: =AN29
A30: 현금및현금성자산 | B30: 재무상태 | C30: 억원 | D30: 현금및현금성자산 | E30: =IFERROR(VLOOKUP($D30,BS연결,MATCH(E$1,BS연결H,0),0)/100,"") | F30: =IFERROR(VLOOKUP($D30,BS연결,MATCH(F$1,BS연결H,0),0)/100,"") | G30: =IFERROR(VLOOKUP($D30,BS연결,MATCH(G$1,BS연결H,0),0)/100,"") | H30: =IFERROR(VLOOKUP($D30,BS연결,MATCH(H$1,BS연결H,0),0)/100,"") | I30: =IFERROR(VLOOKUP($D30,BS연결,MATCH(I$1,BS연결H,0),0)/100,"") | J30: =IFERROR(VLOOKUP($D30,BS연결,MATCH(J$1,BS연결H,0),0)/100,"") | K30: =IFERROR(VLOOKUP($D30,BS연결,MATCH(K$1,BS연결H,0),0)/100,"") | L30: =IFERROR(VLOOKUP($D30,BS연결,MATCH(L$1,BS연결H,0),0)/100,"") | ... AB30: =IFERROR(VLOOKUP($D30,BS연결,MATCH(AB$1,BS연결H,0),0)/100,"") | AE30: =AD30 | AJ30: =AI30 | AO30: =AN30
A31: CAPEX | B31: 현금흐름 | C31: 억원 | D31: CAPEX | E31: =IFERROR(VLOOKUP($D31,BS연결,MATCH(E$1,BS연결H,0),0)/100,"") | G31: =IFERROR(VLOOKUP($D31,BS연결,MATCH(G$1,BS연결H,0),0)/100,"") | H31: =IFERROR(VLOOKUP($D31,BS연결,MATCH(H$1,BS연결H,0),0)/100,"") | I31: =IFERROR(VLOOKUP($D31,BS연결,MATCH(I$1,BS연결H,0),0)/100,"") | J31: =IFERROR(VLOOKUP($D31,BS연결,MATCH(J$1,BS연결H,0),0)/100,"") | K31: =IFERROR(VLOOKUP($D31,BS연결,MATCH(K$1,BS연결H,0),0)/100,"") | L31: =IFERROR(VLOOKUP($D31,BS연결,MATCH(L$1,BS연결H,0),0)/100,"") | M31: =IFERROR(VLOOKUP($D31,BS연결,MATCH(M$1,BS연결H,0),0)/100,"") | N31: =IFERROR(VLOOKUP($D31,BS연결,MATCH(N$1,BS연결H,0),0)/100,"") | ... AB31: =IFERROR(VLOOKUP($D31,BS연결,MATCH(AB$1,BS연결H,0),0)/100,"") | AC31: =IFERROR(X31*(1+변수!AC38),"") | AD31: =IFERROR(Y31*(1+변수!AD38),"") | AE31: =SUM(AA31:AD31) | AF31: =IFERROR(AA31*(1+변수!AF38),"") | AG31: =IFERROR(AB31*(1+변수!AG38),"") | AH31: =IFERROR(AC31*(1+변수!AH38),"") | AI31: =IFERROR(AD31*(1+변수!AI38),"") | AJ31: =SUM(AF31:AI31) | AK31: =IFERROR(AF31*(1+변수!AK38),"") | AL31: =IFERROR(AG31*(1+변수!AL38),"") | AM31: =IFERROR(AH31*(1+변수!AM38),"") | AN31: =IFERROR(AI31*(1+변수!AN38),"") | AO31: =SUM(AK31:AN31)
A32: 영업활동현금흐름 | B32: 현금흐름 | C32: 억원 | D32: 영업활동으로인한현금흐름 | E32: =IFERROR(VLOOKUP($D32,BS연결,MATCH(E$1,BS연결H,0),0)/100,"") | G32: =IFERROR(VLOOKUP($D32,BS연결,MATCH(G$1,BS연결H,0),0)/100,"") | H32: =IFERROR(VLOOKUP($D32,BS연결,MATCH(H$1,BS연결H,0),0)/100,"") | I32: =IFERROR(VLOOKUP($D32,BS연결,MATCH(I$1,BS연결H,0),0)/100,"") | J32: =IFERROR(VLOOKUP($D32,BS연결,MATCH(J$1,BS연결H,0),0)/100,"") | K32: =IFERROR(VLOOKUP($D32,BS연결,MATCH(K$1,BS연결H,0),0)/100,"") | L32: =IFERROR(VLOOKUP($D32,BS연결,MATCH(L$1,BS연결H,0),0)/100,"") | M32: =IFERROR(VLOOKUP($D32,BS연결,MATCH(M$1,BS연결H,0),0)/100,"") | N32: =IFERROR(VLOOKUP($D32,BS연결,MATCH(N$1,BS연결H,0),0)/100,"") | ... AB32: =IFERROR(VLOOKUP($D32,BS연결,MATCH(AB$1,BS연결H,0),0)/100,"") | AE32: =SUM(AA32:AD32) | AJ32: =SUM(AF32:AI32) | AO32: =SUM(AK32:AN32)
A33: 주식수 | B33: 주당 | C33: 백만주 | D33: 유통주식수 | E33: 22.651 | F33: =E33 | G33: 22.651 | H33: 22.651 | I33: 22.597 | J33: 22.219 | K33: =J33 | L33: 22.213 | M33: 22.213 | N33: 22.123 | O33: 22.123 | P33: =O33 | Q33: 22.123 | R33: 22.123 | S33: 22.123 | T33: 23.3 | U33: =T33 | V33: 24.144 | W33: 24.144 | X33: 24.144 | Y33: 24.144 | Z33: =Y33 | AA33: 24.144 | AB33: 24.144 | AC33: =IFERROR(AB33*(1+변수!AC40),"") | AD33: =IFERROR(AC33*(1+변수!AD40),"") | AE33: =AD33 | AF33: =IFERROR(AD33*(1+변수!AF40),"") | AG33: =IFERROR(AF33*(1+변수!AG40),"") | AH33: =IFERROR(AG33*(1+변수!AH40),"") | AI33: =IFERROR(AH33*(1+변수!AI40),"") | AJ33: =AI33 | AK33: =IFERROR(AI33*(1+변수!AK40),"") | AL33: =IFERROR(AK33*(1+변수!AL40),"") | AM33: =IFERROR(AL33*(1+변수!AM40),"") | AN33: =IFERROR(AM33*(1+변수!AN40),"") | AO33: =AN33
A34: EPS | B34: 주당 | C34: 원 | D34: EPS | E34: =IFERROR(E20*100/E33,"") | G34: =IFERROR(G20*100/G33,"") | H34: =IFERROR(H20*100/H33,"") | I34: =IFERROR(I20*100/I33,"") | J34: =IFERROR(J20*100/J33,"") | K34: =SUM(G34:J34) | L34: =IFERROR(L20*100/L33,"") | M34: =IFERROR(M20*100/M33,"") | N34: =IFERROR(N20*100/N33,"") | O34: =IFERROR(O20*100/O33,"") | P34: =SUM(L34:O34) | Q34: =IFERROR(Q20*100/Q33,"") | R34: =IFERROR(R20*100/R33,"") | S34: =IFERROR(S20*100/S33,"") | T34: =IFERROR(T20*100/T33,"") | U34: =SUM(Q34:T34) | V34: =IFERROR(V20*100/V33,"") | W34: =IFERROR(W20*100/W33,"") | X34: =IFERROR(X20*100/X33,"") | Y34: =IFERROR(Y20*100/Y33,"") | Z34: =SUM(V34:Y34) | AA34: =IFERROR(AA20*100/AA33,"") | AB34: =IFERROR(AB20*100/AB33,"") | AC34: =IFERROR(AC20*100/AC33,"") | AD34: =IFERROR(AD20*100/AD33,"") | AE34: =SUM(AA34:AD34) | AF34: =IFERROR(AF20*100/AF33,"") | AG34: =IFERROR(AG20*100/AG33,"") | AH34: =IFERROR(AH20*100/AH33,"") | AI34: =IFERROR(AI20*100/AI33,"") | AJ34: =SUM(AF34:AI34) | AK34: =IFERROR(AK20*100/AK33,"") | AL34: =IFERROR(AL20*100/AL33,"") | AM34: =IFERROR(AM20*100/AM33,"") | AN34: =IFERROR(AN20*100/AN33,"") | AO34: =SUM(AK34:AN34)
A35: BPS | B35: 주당 | C35: 원 | D35: BPS | E35: =IFERROR(E26*100/E33,"") | F35: =E35 | G35: =IFERROR(G26*100/G33,"") | H35: =IFERROR(H26*100/H33,"") | I35: =IFERROR(I26*100/I33,"") | J35: =IFERROR(J26*100/J33,"") | K35: =J35 | L35: =IFERROR(L26*100/L33,"") | M35: =IFERROR(M26*100/M33,"") | N35: =IFERROR(N26*100/N33,"") | O35: =IFERROR(O26*100/O33,"") | P35: =O35 | Q35: =IFERROR(Q26*100/Q33,"") | R35: =IFERROR(R26*100/R33,"") | S35: =IFERROR(S26*100/S33,"") | T35: =IFERROR(T26*100/T33,"") | U35: =T35 | V35: =IFERROR(V26*100/V33,"") | W35: =IFERROR(W26*100/W33,"") | X35: =IFERROR(X26*100/X33,"") | Y35: =IFERROR(Y26*100/Y33,"") | Z35: =Y35 | AA35: =IFERROR(AA26*100/AA33,"") | AB35: =IFERROR(AB26*100/AB33,"") | AC35: =IFERROR(AC26*100/AC33,"") | AD35: =IFERROR(AD26*100/AD33,"") | AE35: =AD35 | AF35: =IFERROR(AF26*100/AF33,"") | AG35: =IFERROR(AG26*100/AG33,"") | AH35: =IFERROR(AH26*100/AH33,"") | AI35: =IFERROR(AI26*100/AI33,"") | AJ35: =AI35 | AK35: =IFERROR(AK26*100/AK33,"") | AL35: =IFERROR(AL26*100/AL33,"") | AM35: =IFERROR(AM26*100/AM33,"") | AN35: =IFERROR(AN26*100/AN33,"") | AO35: =AN35
A36: DPS | B36: 주당 | C36: 원 | D36: DPS(보통주) | E36: 0 | F36: 0 | J36: 100 | K36: =SUM(G36:J36) | O36: 0 | P36: =SUM(L36:O36) | T36: 0 | U36: =SUM(Q36:T36) | Y36: 0 | Z36: =SUM(V36:Y36) | AD36: =변수!AD41 | AE36: =SUM(AA36:AD36) | AI36: =변수!AI41 | AJ36: =SUM(AF36:AI36) | AN36: =변수!AN41 | AO36: =SUM(AK36:AN36)
A37: PER | B37: 주당 | C37: 배 | D37: PER | F37: =E37 | I37: =IFERROR(변수!I18/(E34+G34+H34+I34),"") | J37: =IFERROR(변수!J18/(G34+H34+I34+J34),"") | K37: =J37 | L37: =IFERROR(변수!L18/(H34+I34+J34+L34),"") | M37: =IFERROR(변수!M18/(I34+J34+L34+M34),"") | N37: =IFERROR(변수!N18/(J34+L34+M34+N34),"") | P37: =O37 | U37: =T37 | W37: =IFERROR(변수!W18/(S34+T34+V34+W34),"") | X37: =IFERROR(변수!X18/(T34+V34+W34+X34),"") | Y37: =IFERROR(변수!Y18/(V34+W34+X34+Y34),"") | Z37: =Y37 | AD37: =IFERROR(변수!$D$44/(AA34+AB34+AC34+AD34),"") | AE37: =AD37 | AF37: =IFERROR(변수!$D$44/(AB34+AC34+AD34+AF34),"") | AG37: =IFERROR(변수!$D$44/(AC34+AD34+AF34+AG34),"") | AH37: =IFERROR(변수!$D$44/(AD34+AF34+AG34+AH34),"") | AI37: =IFERROR(변수!$D$44/(AF34+AG34+AH34+AI34),"") | AJ37: =AI37 | AK37: =IFERROR(변수!$D$44/(AG34+AH34+AI34+AK34),"") | AL37: =IFERROR(변수!$D$44/(AH34+AI34+AK34+AL34),"") | AM37: =IFERROR(변수!$D$44/(AI34+AK34+AL34+AM34),"") | AN37: =IFERROR(변수!$D$44/(AK34+AL34+AM34+AN34),"") | AO37: =AN37
A38: PBR | B38: 주당 | C38: 배 | D38: PBR | E38: =IFERROR(변수!E18/E35,"") | F38: =E38 | G38: =IFERROR(변수!G18/G35,"") | H38: =IFERROR(변수!H18/H35,"") | I38: =IFERROR(변수!I18/I35,"") | J38: =IFERROR(변수!J18/J35,"") | K38: =J38 | L38: =IFERROR(변수!L18/L35,"") | M38: =IFERROR(변수!M18/M35,"") | N38: =IFERROR(변수!N18/N35,"") | O38: =IFERROR(변수!O18/O35,"") | P38: =O38 | Q38: =IFERROR(변수!Q18/Q35,"") | R38: =IFERROR(변수!R18/R35,"") | S38: =IFERROR(변수!S18/S35,"") | T38: =IFERROR(변수!T18/T35,"") | U38: =T38 | V38: =IFERROR(변수!V18/V35,"") | W38: =IFERROR(변수!W18/W35,"") | X38: =IFERROR(변수!X18/X35,"") | Y38: =IFERROR(변수!Y18/Y35,"") | Z38: =Y38 | AA38: =IFERROR(변수!AA18/AA35,"") | AB38: =IFERROR(변수!AB18/AB35,"") | AC38: =IFERROR(변수!$D$44/AC35,"") | AD38: =IFERROR(변수!$D$44/AD35,"") | AE38: =AD38 | AF38: =IFERROR(변수!$D$44/AF35,"") | AG38: =IFERROR(변수!$D$44/AG35,"") | AH38: =IFERROR(변수!$D$44/AH35,"") | AI38: =IFERROR(변수!$D$44/AI35,"") | AJ38: =AI38 | AK38: =IFERROR(변수!$D$44/AK35,"") | AL38: =IFERROR(변수!$D$44/AL35,"") | AM38: =IFERROR(변수!$D$44/AM35,"") | AN38: =IFERROR(변수!$D$44/AN35,"") | AO38: =AN38
A39: 매출전사 | B39: 사업부 | C39: 억원 | D39: 매출 전사(부문 미분리) | E39: 589.03 | G39: 614.07 | H39: 647.73 | I39: 577.03 | J39: 616.02 | K39: =SUM(G39:J39) | L39: 616.69 | M39: 664.78 | N39: 589.71 | O39: 613.3 | P39: =SUM(L39:O39) | Q39: 529.86 | R39: 598.4 | S39: 531.11 | T39: 575.11 | U39: =SUM(Q39:T39) | V39: 533.67 | W39: 561.01 | X39: 560.09 | Y39: 539.23 | Z39: =SUM(V39:Y39) | AA39: 661.2 | AB39: 717.21 | AC39: =IFERROR(AC5,"") | AD39: =IFERROR(AD5,"") | AE39: =SUM(AA39:AD39) | AF39: =IFERROR(AF5,"") | AG39: =IFERROR(AG5,"") | AH39: =IFERROR(AH5,"") | AI39: =IFERROR(AI5,"") | AJ39: =SUM(AF39:AI39) | AK39: =IFERROR(AK5,"") | AL39: =IFERROR(AL5,"") | AM39: =IFERROR(AM5,"") | AN39: =IFERROR(AN5,"") | AO39: =SUM(AK39:AN39)
A40: OP전사 | B40: 사업부 | C40: 억원 | D40: OP 전사(부문 미분리) | E40: 22.86 | G40: 35.04 | H40: 62.88 | I40: 6.36 | J40: 8.57 | K40: =SUM(G40:J40) | L40: 34.73 | M40: 33.56 | N40: 9.43 | O40: -26.5 | P40: =SUM(L40:O40) | Q40: 18.53 | R40: 21.31 | S40: 12.74 | T40: 7.72 | U40: =SUM(Q40:T40) | V40: 2.54 | W40: 51.69 | X40: 27.88 | Y40: -0.36 | Z40: =SUM(V40:Y40) | AA40: 81.6 | AB40: 92.26 | AC40: =IFERROR(AC9,"") | AD40: =IFERROR(AD9,"") | AE40: =SUM(AA40:AD40) | AF40: =IFERROR(AF9,"") | AG40: =IFERROR(AG9,"") | AH40: =IFERROR(AH9,"") | AI40: =IFERROR(AI9,"") | AJ40: =SUM(AF40:AI40) | AK40: =IFERROR(AK9,"") | AL40: =IFERROR(AL9,"") | AM40: =IFERROR(AM9,"") | AN40: =IFERROR(AN9,"") | AO40: =SUM(AK40:AN40)
B41: 비율(참고)
A42: NPM | C42: % | D42: 지배주주순이익 / 매출액 | E42: =IFERROR(E20/E5,"") | F42: =IFERROR(F20/F5,"") | G42: =IFERROR(G20/G5,"") | H42: =IFERROR(H20/H5,"") | I42: =IFERROR(I20/I5,"") | J42: =IFERROR(J20/J5,"") | K42: =IFERROR(K20/K5,"") | L42: =IFERROR(L20/L5,"") | ... AO42: =IFERROR(AO20/AO5,"")
A43: 매출원가율 | C43: % | D43: 매출원가 / 매출액 | E43: =IFERROR(E6/E5,"") | F43: =IFERROR(F6/F5,"") | G43: =IFERROR(G6/G5,"") | H43: =IFERROR(H6/H5,"") | I43: =IFERROR(I6/I5,"") | J43: =IFERROR(J6/J5,"") | K43: =IFERROR(K6/K5,"") | L43: =IFERROR(L6/L5,"") | ... AO43: =IFERROR(AO6/AO5,"")
A44: 판관비율 | C44: % | D44: 판관비 / 매출액 | E44: =IFERROR(E8/E5,"") | F44: =IFERROR(F8/F5,"") | G44: =IFERROR(G8/G5,"") | H44: =IFERROR(H8/H5,"") | I44: =IFERROR(I8/I5,"") | J44: =IFERROR(J8/J5,"") | K44: =IFERROR(K8/K5,"") | L44: =IFERROR(L8/L5,"") | ... AO44: =IFERROR(AO8/AO5,"")

Sheet 분기
C1: 이름: 분기H — subQ 를 이름으로 VLOOKUP(억원) | E1: 4Q21 | F1: 1Q22 | G1: 2Q22 | H1: 3Q22 | I1: 4Q22 | J1: 1Q23 | K1: 2Q23 | L1: 3Q23 | M1: 4Q23 | N1: 1Q24 | O1: 2Q24 | P1: 3Q24 | Q1: 4Q24 | R1: 1Q25 | S1: 2Q25 | T1: 3Q25 | U1: 4Q25 | V1: 1Q26 | W1: 2Q26 | X1: 3Q26 | Y1: 4Q26 | Z1: 1Q27 | AA1: 2Q27 | AB1: 3Q27 | AC1: 4Q27 | AD1: 1Q28 | AE1: 2Q28 | AF1: 3Q28 | AG1: 4Q28
C2: 종가: | D2: =변수!D44
C3: 기준일: | D3: 20261013 | E3: 1 | F3: 2 | G3: 3 | H3: 4 | I3: 5 | J3: 6 | K3: 7 | L3: 8 | M3: 9 | N3: 10 | O3: 11 | P3: 12 | Q3: 13 | R3: 14 | S3: 15 | T3: 16 | U3: 17 | V3: 18 | W3: 19 | X3: 20 | Y3: 21 | Z3: 22 | AA3: 23 | AB3: 24 | AC3: 25 | AD3: 26 | AE3: 27 | AF3: 28 | AG3: 29
E4: 2021.12 | F4: 2022.03 | G4: 2022.06 | H4: 2022.09 | I4: 2022.12 | J4: 2023.03 | K4: 2023.06 | L4: 2023.09 | M4: 2023.12 | N4: 2024.03 | O4: 2024.06 | P4: 2024.09 | Q4: 2024.12 | R4: 2025.03 | S4: 2025.06 | T4: 2025.09 | U4: 2025.12 | V4: 2026.03 | W4: 2026.06 | X4: 2026.09 | Y4: 2026.12 | Z4: 2027.03 | AA4: 2027.06 | AB4: 2027.09 | AC4: 2027.12 | AD4: 2028.03 | AE4: 2028.06 | AF4: 2028.09 | AG4: 2028.12
A5: 매출액 | D5: 매출액 | E5: =IFERROR(VLOOKUP($A5,subQ,MATCH(E$1,SUBQH,0),0),"") | F5: =IFERROR(VLOOKUP($A5,subQ,MATCH(F$1,SUBQH,0),0),"") | G5: =IFERROR(VLOOKUP($A5,subQ,MATCH(G$1,SUBQH,0),0),"") | H5: =IFERROR(VLOOKUP($A5,subQ,MATCH(H$1,SUBQH,0),0),"") | I5: =IFERROR(VLOOKUP($A5,subQ,MATCH(I$1,SUBQH,0),0),"") | J5: =IFERROR(VLOOKUP($A5,subQ,MATCH(J$1,SUBQH,0),0),"") | K5: =IFERROR(VLOOKUP($A5,subQ,MATCH(K$1,SUBQH,0),0),"") | L5: =IFERROR(VLOOKUP($A5,subQ,MATCH(L$1,SUBQH,0),0),"") | ... AG5: =IFERROR(VLOOKUP($A5,subQ,MATCH(AG$1,SUBQH,0),0),"")
A6: 매출원가 | D6: 매출원가 | E6: =IFERROR(VLOOKUP($A6,subQ,MATCH(E$1,SUBQH,0),0),"") | F6: =IFERROR(VLOOKUP($A6,subQ,MATCH(F$1,SUBQH,0),0),"") | G6: =IFERROR(VLOOKUP($A6,subQ,MATCH(G$1,SUBQH,0),0),"") | H6: =IFERROR(VLOOKUP($A6,subQ,MATCH(H$1,SUBQH,0),0),"") | I6: =IFERROR(VLOOKUP($A6,subQ,MATCH(I$1,SUBQH,0),0),"") | J6: =IFERROR(VLOOKUP($A6,subQ,MATCH(J$1,SUBQH,0),0),"") | K6: =IFERROR(VLOOKUP($A6,subQ,MATCH(K$1,SUBQH,0),0),"") | L6: =IFERROR(VLOOKUP($A6,subQ,MATCH(L$1,SUBQH,0),0),"") | ... AG6: =IFERROR(VLOOKUP($A6,subQ,MATCH(AG$1,SUBQH,0),0),"")
A7: 매출총이익 | D7: 매출총이익 | E7: =IFERROR(VLOOKUP($A7,subQ,MATCH(E$1,SUBQH,0),0),"") | F7: =IFERROR(VLOOKUP($A7,subQ,MATCH(F$1,SUBQH,0),0),"") | G7: =IFERROR(VLOOKUP($A7,subQ,MATCH(G$1,SUBQH,0),0),"") | H7: =IFERROR(VLOOKUP($A7,subQ,MATCH(H$1,SUBQH,0),0),"") | I7: =IFERROR(VLOOKUP($A7,subQ,MATCH(I$1,SUBQH,0),0),"") | J7: =IFERROR(VLOOKUP($A7,subQ,MATCH(J$1,SUBQH,0),0),"") | K7: =IFERROR(VLOOKUP($A7,subQ,MATCH(K$1,SUBQH,0),0),"") | L7: =IFERROR(VLOOKUP($A7,subQ,MATCH(L$1,SUBQH,0),0),"") | ... AG7: =IFERROR(VLOOKUP($A7,subQ,MATCH(AG$1,SUBQH,0),0),"")
A8: 판관비 | D8: 판매비와관리비 | E8: =IFERROR(VLOOKUP($A8,subQ,MATCH(E$1,SUBQH,0),0),"") | F8: =IFERROR(VLOOKUP($A8,subQ,MATCH(F$1,SUBQH,0),0),"") | G8: =IFERROR(VLOOKUP($A8,subQ,MATCH(G$1,SUBQH,0),0),"") | H8: =IFERROR(VLOOKUP($A8,subQ,MATCH(H$1,SUBQH,0),0),"") | I8: =IFERROR(VLOOKUP($A8,subQ,MATCH(I$1,SUBQH,0),0),"") | J8: =IFERROR(VLOOKUP($A8,subQ,MATCH(J$1,SUBQH,0),0),"") | K8: =IFERROR(VLOOKUP($A8,subQ,MATCH(K$1,SUBQH,0),0),"") | L8: =IFERROR(VLOOKUP($A8,subQ,MATCH(L$1,SUBQH,0),0),"") | ... AG8: =IFERROR(VLOOKUP($A8,subQ,MATCH(AG$1,SUBQH,0),0),"")
A9: 영업이익 | D9: 영업이익 | E9: =IFERROR(VLOOKUP($A9,subQ,MATCH(E$1,SUBQH,0),0),"") | F9: =IFERROR(VLOOKUP($A9,subQ,MATCH(F$1,SUBQH,0),0),"") | G9: =IFERROR(VLOOKUP($A9,subQ,MATCH(G$1,SUBQH,0),0),"") | H9: =IFERROR(VLOOKUP($A9,subQ,MATCH(H$1,SUBQH,0),0),"") | I9: =IFERROR(VLOOKUP($A9,subQ,MATCH(I$1,SUBQH,0),0),"") | J9: =IFERROR(VLOOKUP($A9,subQ,MATCH(J$1,SUBQH,0),0),"") | K9: =IFERROR(VLOOKUP($A9,subQ,MATCH(K$1,SUBQH,0),0),"") | L9: =IFERROR(VLOOKUP($A9,subQ,MATCH(L$1,SUBQH,0),0),"") | ... AG9: =IFERROR(VLOOKUP($A9,subQ,MATCH(AG$1,SUBQH,0),0),"")
A10: OPM | D10: 영업이익률 | E10: =IFERROR(VLOOKUP($A10,subQ,MATCH(E$1,SUBQH,0),0),"") | F10: =IFERROR(VLOOKUP($A10,subQ,MATCH(F$1,SUBQH,0),0),"") | G10: =IFERROR(VLOOKUP($A10,subQ,MATCH(G$1,SUBQH,0),0),"") | H10: =IFERROR(VLOOKUP($A10,subQ,MATCH(H$1,SUBQH,0),0),"") | I10: =IFERROR(VLOOKUP($A10,subQ,MATCH(I$1,SUBQH,0),0),"") | J10: =IFERROR(VLOOKUP($A10,subQ,MATCH(J$1,SUBQH,0),0),"") | K10: =IFERROR(VLOOKUP($A10,subQ,MATCH(K$1,SUBQH,0),0),"") | L10: =IFERROR(VLOOKUP($A10,subQ,MATCH(L$1,SUBQH,0),0),"") | ... AG10: =IFERROR(VLOOKUP($A10,subQ,MATCH(AG$1,SUBQH,0),0),"")
A11: 금융손익 | D11: 금융손익(이자·환 포함) | E11: =IFERROR(VLOOKUP($A11,subQ,MATCH(E$1,SUBQH,0),0),"") | F11: =IFERROR(VLOOKUP($A11,subQ,MATCH(F$1,SUBQH,0),0),"") | G11: =IFERROR(VLOOKUP($A11,subQ,MATCH(G$1,SUBQH,0),0),"") | H11: =IFERROR(VLOOKUP($A11,subQ,MATCH(H$1,SUBQH,0),0),"") | I11: =IFERROR(VLOOKUP($A11,subQ,MATCH(I$1,SUBQH,0),0),"") | J11: =IFERROR(VLOOKUP($A11,subQ,MATCH(J$1,SUBQH,0),0),"") | K11: =IFERROR(VLOOKUP($A11,subQ,MATCH(K$1,SUBQH,0),0),"") | L11: =IFERROR(VLOOKUP($A11,subQ,MATCH(L$1,SUBQH,0),0),"") | ... AG11: =IFERROR(VLOOKUP($A11,subQ,MATCH(AG$1,SUBQH,0),0),"")
A12: 이자손익 | D12: 이자손익(이자수익 − 이자비용) | E12: =IFERROR(VLOOKUP($A12,subQ,MATCH(E$1,SUBQH,0),0),"") | F12: =IFERROR(VLOOKUP($A12,subQ,MATCH(F$1,SUBQH,0),0),"") | G12: =IFERROR(VLOOKUP($A12,subQ,MATCH(G$1,SUBQH,0),0),"") | H12: =IFERROR(VLOOKUP($A12,subQ,MATCH(H$1,SUBQH,0),0),"") | I12: =IFERROR(VLOOKUP($A12,subQ,MATCH(I$1,SUBQH,0),0),"") | J12: =IFERROR(VLOOKUP($A12,subQ,MATCH(J$1,SUBQH,0),0),"") | K12: =IFERROR(VLOOKUP($A12,subQ,MATCH(K$1,SUBQH,0),0),"") | L12: =IFERROR(VLOOKUP($A12,subQ,MATCH(L$1,SUBQH,0),0),"") | ... AG12: =IFERROR(VLOOKUP($A12,subQ,MATCH(AG$1,SUBQH,0),0),"")
A13: 외환손익 | D13: 외환손익(실적만; 추정 환효과는 환관련손익) | E13: =IFERROR(VLOOKUP($A13,subQ,MATCH(E$1,SUBQH,0),0),"") | F13: =IFERROR(VLOOKUP($A13,subQ,MATCH(F$1,SUBQH,0),0),"") | G13: =IFERROR(VLOOKUP($A13,subQ,MATCH(G$1,SUBQH,0),0),"") | H13: =IFERROR(VLOOKUP($A13,subQ,MATCH(H$1,SUBQH,0),0),"") | I13: =IFERROR(VLOOKUP($A13,subQ,MATCH(I$1,SUBQH,0),0),"") | J13: =IFERROR(VLOOKUP($A13,subQ,MATCH(J$1,SUBQH,0),0),"") | K13: =IFERROR(VLOOKUP($A13,subQ,MATCH(K$1,SUBQH,0),0),"") | L13: =IFERROR(VLOOKUP($A13,subQ,MATCH(L$1,SUBQH,0),0),"") | ... AG13: =IFERROR(VLOOKUP($A13,subQ,MATCH(AG$1,SUBQH,0),0),"")
A14: 파생상품손익 | D14: 파생상품손익 | E14: =IFERROR(VLOOKUP($A14,subQ,MATCH(E$1,SUBQH,0),0),"") | F14: =IFERROR(VLOOKUP($A14,subQ,MATCH(F$1,SUBQH,0),0),"") | G14: =IFERROR(VLOOKUP($A14,subQ,MATCH(G$1,SUBQH,0),0),"") | H14: =IFERROR(VLOOKUP($A14,subQ,MATCH(H$1,SUBQH,0),0),"") | I14: =IFERROR(VLOOKUP($A14,subQ,MATCH(I$1,SUBQH,0),0),"") | J14: =IFERROR(VLOOKUP($A14,subQ,MATCH(J$1,SUBQH,0),0),"") | K14: =IFERROR(VLOOKUP($A14,subQ,MATCH(K$1,SUBQH,0),0),"") | L14: =IFERROR(VLOOKUP($A14,subQ,MATCH(L$1,SUBQH,0),0),"") | ... AG14: =IFERROR(VLOOKUP($A14,subQ,MATCH(AG$1,SUBQH,0),0),"")
A15: 기타금융손익 | D15: 기타금융손익(금융손익 잔차) | E15: =IFERROR(VLOOKUP($A15,subQ,MATCH(E$1,SUBQH,0),0),"") | F15: =IFERROR(VLOOKUP($A15,subQ,MATCH(F$1,SUBQH,0),0),"") | G15: =IFERROR(VLOOKUP($A15,subQ,MATCH(G$1,SUBQH,0),0),"") | H15: =IFERROR(VLOOKUP($A15,subQ,MATCH(H$1,SUBQH,0),0),"") | I15: =IFERROR(VLOOKUP($A15,subQ,MATCH(I$1,SUBQH,0),0),"") | J15: =IFERROR(VLOOKUP($A15,subQ,MATCH(J$1,SUBQH,0),0),"") | K15: =IFERROR(VLOOKUP($A15,subQ,MATCH(K$1,SUBQH,0),0),"") | L15: =IFERROR(VLOOKUP($A15,subQ,MATCH(L$1,SUBQH,0),0),"") | ... AG15: =IFERROR(VLOOKUP($A15,subQ,MATCH(AG$1,SUBQH,0),0),"")
A16: 기타영업외손익 | D16: 기타영업외손익 | E16: =IFERROR(VLOOKUP($A16,subQ,MATCH(E$1,SUBQH,0),0),"") | F16: =IFERROR(VLOOKUP($A16,subQ,MATCH(F$1,SUBQH,0),0),"") | G16: =IFERROR(VLOOKUP($A16,subQ,MATCH(G$1,SUBQH,0),0),"") | H16: =IFERROR(VLOOKUP($A16,subQ,MATCH(H$1,SUBQH,0),0),"") | I16: =IFERROR(VLOOKUP($A16,subQ,MATCH(I$1,SUBQH,0),0),"") | J16: =IFERROR(VLOOKUP($A16,subQ,MATCH(J$1,SUBQH,0),0),"") | K16: =IFERROR(VLOOKUP($A16,subQ,MATCH(K$1,SUBQH,0),0),"") | L16: =IFERROR(VLOOKUP($A16,subQ,MATCH(L$1,SUBQH,0),0),"") | ... AG16: =IFERROR(VLOOKUP($A16,subQ,MATCH(AG$1,SUBQH,0),0),"")
... A41: NPM | D41: NPM | E41: =IFERROR(VLOOKUP($A41,subQ,MATCH(E$1,SUBQH,0),0),"") | F41: =IFERROR(VLOOKUP($A41,subQ,MATCH(F$1,SUBQH,0),0),"") | G41: =IFERROR(VLOOKUP($A41,subQ,MATCH(G$1,SUBQH,0),0),"") | H41: =IFERROR(VLOOKUP($A41,subQ,MATCH(H$1,SUBQH,0),0),"") | I41: =IFERROR(VLOOKUP($A41,subQ,MATCH(I$1,SUBQH,0),0),"") | J41: =IFERROR(VLOOKUP($A41,subQ,MATCH(J$1,SUBQH,0),0),"") | K41: =IFERROR(VLOOKUP($A41,subQ,MATCH(K$1,SUBQH,0),0),"") | L41: =IFERROR(VLOOKUP($A41,subQ,MATCH(L$1,SUBQH,0),0),"") | ... AG41: =IFERROR(VLOOKUP($A41,subQ,MATCH(AG$1,SUBQH,0),0),"")
A42: 매출액 YoY | D42: 매출액 YoY | I42: =IFERROR(I5/E5-1,"") | J42: =IFERROR(J5/F5-1,"") | K42: =IFERROR(K5/G5-1,"") | L42: =IFERROR(L5/H5-1,"") | M42: =IFERROR(M5/I5-1,"") | N42: =IFERROR(N5/J5-1,"") | O42: =IFERROR(O5/K5-1,"") | P42: =IFERROR(P5/L5-1,"") | ... AG42: =IFERROR(AG5/AC5-1,"")
A43: 영업이익 YoY | D43: 영업이익 YoY | I43: =IFERROR(I9/E9-1,"") | J43: =IFERROR(J9/F9-1,"") | K43: =IFERROR(K9/G9-1,"") | L43: =IFERROR(L9/H9-1,"") | M43: =IFERROR(M9/I9-1,"") | N43: =IFERROR(N9/J9-1,"") | O43: =IFERROR(O9/K9-1,"") | P43: =IFERROR(P9/L9-1,"") | ... AG43: =IFERROR(AG9/AC9-1,"")
A44: 지배주주순이익 YoY | D44: 지배주주순이익 YoY | I44: =IFERROR(I20/E20-1,"") | J44: =IFERROR(J20/F20-1,"") | K44: =IFERROR(K20/G20-1,"") | L44: =IFERROR(L20/H20-1,"") | M44: =IFERROR(M20/I20-1,"") | N44: =IFERROR(N20/J20-1,"") | O44: =IFERROR(O20/K20-1,"") | P44: =IFERROR(P20/L20-1,"") | ... AG44: =IFERROR(AG20/AC20-1,"")

Sheet 연간예상
C1: 이름: 연간예상H — subQ 를 이름으로 VLOOKUP(억원) | E1: 2021 | F1: 2022 | G1: 2023 | H1: 2024 | I1: 2025 | J1: 2026 | K1: 2027 | L1: 2028
C2: 종가: | D2: =변수!D44
C3: 기준일: | D3: 20261013 | E3: 1 | F3: 2 | G3: 3 | H3: 4 | I3: 5 | J3: 6 | K3: 7 | L3: 8
E4: 2021.12A | F4: 2022.12A | G4: 2023.12A | H4: 2024.12A | I4: 2025.12A | J4: 2026.12A | K4: 2027.12A | L4: 2028.12A
A5: 매출액 | D5: 매출액 | E5: =IFERROR(VLOOKUP($A5,subQ,MATCH(E$1,SUBQH,0),0),"") | F5: =IFERROR(VLOOKUP($A5,subQ,MATCH(F$1,SUBQH,0),0),"") | G5: =IFERROR(VLOOKUP($A5,subQ,MATCH(G$1,SUBQH,0),0),"") | H5: =IFERROR(VLOOKUP($A5,subQ,MATCH(H$1,SUBQH,0),0),"") | I5: =IFERROR(VLOOKUP($A5,subQ,MATCH(I$1,SUBQH,0),0),"") | J5: =IFERROR(VLOOKUP($A5,subQ,MATCH(J$1,SUBQH,0),0),"") | K5: =IFERROR(VLOOKUP($A5,subQ,MATCH(K$1,SUBQH,0),0),"") | L5: =IFERROR(VLOOKUP($A5,subQ,MATCH(L$1,SUBQH,0),0),"")
A6: 매출원가 | D6: 매출원가 | E6: =IFERROR(VLOOKUP($A6,subQ,MATCH(E$1,SUBQH,0),0),"") | F6: =IFERROR(VLOOKUP($A6,subQ,MATCH(F$1,SUBQH,0),0),"") | G6: =IFERROR(VLOOKUP($A6,subQ,MATCH(G$1,SUBQH,0),0),"") | H6: =IFERROR(VLOOKUP($A6,subQ,MATCH(H$1,SUBQH,0),0),"") | I6: =IFERROR(VLOOKUP($A6,subQ,MATCH(I$1,SUBQH,0),0),"") | J6: =IFERROR(VLOOKUP($A6,subQ,MATCH(J$1,SUBQH,0),0),"") | K6: =IFERROR(VLOOKUP($A6,subQ,MATCH(K$1,SUBQH,0),0),"") | L6: =IFERROR(VLOOKUP($A6,subQ,MATCH(L$1,SUBQH,0),0),"")
A7: 매출총이익 | D7: 매출총이익 | E7: =IFERROR(VLOOKUP($A7,subQ,MATCH(E$1,SUBQH,0),0),"") | F7: =IFERROR(VLOOKUP($A7,subQ,MATCH(F$1,SUBQH,0),0),"") | G7: =IFERROR(VLOOKUP($A7,subQ,MATCH(G$1,SUBQH,0),0),"") | H7: =IFERROR(VLOOKUP($A7,subQ,MATCH(H$1,SUBQH,0),0),"") | I7: =IFERROR(VLOOKUP($A7,subQ,MATCH(I$1,SUBQH,0),0),"") | J7: =IFERROR(VLOOKUP($A7,subQ,MATCH(J$1,SUBQH,0),0),"") | K7: =IFERROR(VLOOKUP($A7,subQ,MATCH(K$1,SUBQH,0),0),"") | L7: =IFERROR(VLOOKUP($A7,subQ,MATCH(L$1,SUBQH,0),0),"")
A8: 판관비 | D8: 판매비와관리비 | E8: =IFERROR(VLOOKUP($A8,subQ,MATCH(E$1,SUBQH,0),0),"") | F8: =IFERROR(VLOOKUP($A8,subQ,MATCH(F$1,SUBQH,0),0),"") | G8: =IFERROR(VLOOKUP($A8,subQ,MATCH(G$1,SUBQH,0),0),"") | H8: =IFERROR(VLOOKUP($A8,subQ,MATCH(H$1,SUBQH,0),0),"") | I8: =IFERROR(VLOOKUP($A8,subQ,MATCH(I$1,SUBQH,0),0),"") | J8: =IFERROR(VLOOKUP($A8,subQ,MATCH(J$1,SUBQH,0),0),"") | K8: =IFERROR(VLOOKUP($A8,subQ,MATCH(K$1,SUBQH,0),0),"") | L8: =IFERROR(VLOOKUP($A8,subQ,MATCH(L$1,SUBQH,0),0),"")
A9: 영업이익 | D9: 영업이익 | E9: =IFERROR(VLOOKUP($A9,subQ,MATCH(E$1,SUBQH,0),0),"") | F9: =IFERROR(VLOOKUP($A9,subQ,MATCH(F$1,SUBQH,0),0),"") | G9: =IFERROR(VLOOKUP($A9,subQ,MATCH(G$1,SUBQH,0),0),"") | H9: =IFERROR(VLOOKUP($A9,subQ,MATCH(H$1,SUBQH,0),0),"") | I9: =IFERROR(VLOOKUP($A9,subQ,MATCH(I$1,SUBQH,0),0),"") | J9: =IFERROR(VLOOKUP($A9,subQ,MATCH(J$1,SUBQH,0),0),"") | K9: =IFERROR(VLOOKUP($A9,subQ,MATCH(K$1,SUBQH,0),0),"") | L9: =IFERROR(VLOOKUP($A9,subQ,MATCH(L$1,SUBQH,0),0),"")
A10: OPM | D10: 영업이익률 | E10: =IFERROR(VLOOKUP($A10,subQ,MATCH(E$1,SUBQH,0),0),"") | F10: =IFERROR(VLOOKUP($A10,subQ,MATCH(F$1,SUBQH,0),0),"") | G10: =IFERROR(VLOOKUP($A10,subQ,MATCH(G$1,SUBQH,0),0),"") | H10: =IFERROR(VLOOKUP($A10,subQ,MATCH(H$1,SUBQH,0),0),"") | I10: =IFERROR(VLOOKUP($A10,subQ,MATCH(I$1,SUBQH,0),0),"") | J10: =IFERROR(VLOOKUP($A10,subQ,MATCH(J$1,SUBQH,0),0),"") | K10: =IFERROR(VLOOKUP($A10,subQ,MATCH(K$1,SUBQH,0),0),"") | L10: =IFERROR(VLOOKUP($A10,subQ,MATCH(L$1,SUBQH,0),0),"")
A11: 금융손익 | D11: 금융손익(이자·환 포함) | E11: =IFERROR(VLOOKUP($A11,subQ,MATCH(E$1,SUBQH,0),0),"") | F11: =IFERROR(VLOOKUP($A11,subQ,MATCH(F$1,SUBQH,0),0),"") | G11: =IFERROR(VLOOKUP($A11,subQ,MATCH(G$1,SUBQH,0),0),"") | H11: =IFERROR(VLOOKUP($A11,subQ,MATCH(H$1,SUBQH,0),0),"") | I11: =IFERROR(VLOOKUP($A11,subQ,MATCH(I$1,SUBQH,0),0),"") | J11: =IFERROR(VLOOKUP($A11,subQ,MATCH(J$1,SUBQH,0),0),"") | K11: =IFERROR(VLOOKUP($A11,subQ,MATCH(K$1,SUBQH,0),0),"") | L11: =IFERROR(VLOOKUP($A11,subQ,MATCH(L$1,SUBQH,0),0),"")
A12: 이자손익 | D12: 이자손익(이자수익 − 이자비용) | E12: =IFERROR(VLOOKUP($A12,subQ,MATCH(E$1,SUBQH,0),0),"") | F12: =IFERROR(VLOOKUP($A12,subQ,MATCH(F$1,SUBQH,0),0),"") | G12: =IFERROR(VLOOKUP($A12,subQ,MATCH(G$1,SUBQH,0),0),"") | H12: =IFERROR(VLOOKUP($A12,subQ,MATCH(H$1,SUBQH,0),0),"") | I12: =IFERROR(VLOOKUP($A12,subQ,MATCH(I$1,SUBQH,0),0),"") | J12: =IFERROR(VLOOKUP($A12,subQ,MATCH(J$1,SUBQH,0),0),"") | K12: =IFERROR(VLOOKUP($A12,subQ,MATCH(K$1,SUBQH,0),0),"") | L12: =IFERROR(VLOOKUP($A12,subQ,MATCH(L$1,SUBQH,0),0),"")
A13: 외환손익 | D13: 외환손익(실적만; 추정 환효과는 환관련손익) | E13: =IFERROR(VLOOKUP($A13,subQ,MATCH(E$1,SUBQH,0),0),"") | F13: =IFERROR(VLOOKUP($A13,subQ,MATCH(F$1,SUBQH,0),0),"") | G13: =IFERROR(VLOOKUP($A13,subQ,MATCH(G$1,SUBQH,0),0),"") | H13: =IFERROR(VLOOKUP($A13,subQ,MATCH(H$1,SUBQH,0),0),"") | I13: =IFERROR(VLOOKUP($A13,subQ,MATCH(I$1,SUBQH,0),0),"") | J13: =IFERROR(VLOOKUP($A13,subQ,MATCH(J$1,SUBQH,0),0),"") | K13: =IFERROR(VLOOKUP($A13,subQ,MATCH(K$1,SUBQH,0),0),"") | L13: =IFERROR(VLOOKUP($A13,subQ,MATCH(L$1,SUBQH,0),0),"")
A14: 파생상품손익 | D14: 파생상품손익 | E14: =IFERROR(VLOOKUP($A14,subQ,MATCH(E$1,SUBQH,0),0),"") | F14: =IFERROR(VLOOKUP($A14,subQ,MATCH(F$1,SUBQH,0),0),"") | G14: =IFERROR(VLOOKUP($A14,subQ,MATCH(G$1,SUBQH,0),0),"") | H14: =IFERROR(VLOOKUP($A14,subQ,MATCH(H$1,SUBQH,0),0),"") | I14: =IFERROR(VLOOKUP($A14,subQ,MATCH(I$1,SUBQH,0),0),"") | J14: =IFERROR(VLOOKUP($A14,subQ,MATCH(J$1,SUBQH,0),0),"") | K14: =IFERROR(VLOOKUP($A14,subQ,MATCH(K$1,SUBQH,0),0),"") | L14: =IFERROR(VLOOKUP($A14,subQ,MATCH(L$1,SUBQH,0),0),"")
A15: 기타금융손익 | D15: 기타금융손익(금융손익 잔차) | E15: =IFERROR(VLOOKUP($A15,subQ,MATCH(E$1,SUBQH,0),0),"") | F15: =IFERROR(VLOOKUP($A15,subQ,MATCH(F$1,SUBQH,0),0),"") | G15: =IFERROR(VLOOKUP($A15,subQ,MATCH(G$1,SUBQH,0),0),"") | H15: =IFERROR(VLOOKUP($A15,subQ,MATCH(H$1,SUBQH,0),0),"") | I15: =IFERROR(VLOOKUP($A15,subQ,MATCH(I$1,SUBQH,0),0),"") | J15: =IFERROR(VLOOKUP($A15,subQ,MATCH(J$1,SUBQH,0),0),"") | K15: =IFERROR(VLOOKUP($A15,subQ,MATCH(K$1,SUBQH,0),0),"") | L15: =IFERROR(VLOOKUP($A15,subQ,MATCH(L$1,SUBQH,0),0),"")
A16: 기타영업외손익 | D16: 기타영업외손익 | E16: =IFERROR(VLOOKUP($A16,subQ,MATCH(E$1,SUBQH,0),0),"") | F16: =IFERROR(VLOOKUP($A16,subQ,MATCH(F$1,SUBQH,0),0),"") | G16: =IFERROR(VLOOKUP($A16,subQ,MATCH(G$1,SUBQH,0),0),"") | H16: =IFERROR(VLOOKUP($A16,subQ,MATCH(H$1,SUBQH,0),0),"") | I16: =IFERROR(VLOOKUP($A16,subQ,MATCH(I$1,SUBQH,0),0),"") | J16: =IFERROR(VLOOKUP($A16,subQ,MATCH(J$1,SUBQH,0),0),"") | K16: =IFERROR(VLOOKUP($A16,subQ,MATCH(K$1,SUBQH,0),0),"") | L16: =IFERROR(VLOOKUP($A16,subQ,MATCH(L$1,SUBQH,0),0),"")
... A41: NPM | D41: NPM | E41: =IFERROR(VLOOKUP($A41,subQ,MATCH(E$1,SUBQH,0),0),"") | F41: =IFERROR(VLOOKUP($A41,subQ,MATCH(F$1,SUBQH,0),0),"") | G41: =IFERROR(VLOOKUP($A41,subQ,MATCH(G$1,SUBQH,0),0),"") | H41: =IFERROR(VLOOKUP($A41,subQ,MATCH(H$1,SUBQH,0),0),"") | I41: =IFERROR(VLOOKUP($A41,subQ,MATCH(I$1,SUBQH,0),0),"") | J41: =IFERROR(VLOOKUP($A41,subQ,MATCH(J$1,SUBQH,0),0),"") | K41: =IFERROR(VLOOKUP($A41,subQ,MATCH(K$1,SUBQH,0),0),"") | L41: =IFERROR(VLOOKUP($A41,subQ,MATCH(L$1,SUBQH,0),0),"")
A42: 매출액 YoY | D42: 매출액 YoY | F42: =IFERROR(F5/E5-1,"") | G42: =IFERROR(G5/F5-1,"") | H42: =IFERROR(H5/G5-1,"") | I42: =IFERROR(I5/H5-1,"") | J42: =IFERROR(J5/I5-1,"") | K42: =IFERROR(K5/J5-1,"") | L42: =IFERROR(L5/K5-1,"")
A43: 영업이익 YoY | D43: 영업이익 YoY | F43: =IFERROR(F9/E9-1,"") | G43: =IFERROR(G9/F9-1,"") | H43: =IFERROR(H9/G9-1,"") | I43: =IFERROR(I9/H9-1,"") | J43: =IFERROR(J9/I9-1,"") | K43: =IFERROR(K9/J9-1,"") | L43: =IFERROR(L9/K9-1,"")
A44: 지배주주순이익 YoY | D44: 지배주주순이익 YoY | F44: =IFERROR(F20/E20-1,"") | G44: =IFERROR(G20/F20-1,"") | H44: =IFERROR(H20/G20-1,"") | I44: =IFERROR(I20/H20-1,"") | J44: =IFERROR(J20/I20-1,"") | K44: =IFERROR(K20/J20-1,"") | L44: =IFERROR(L20/K20-1,"")

Sheet TP
B1: 종가 | C1: =변수!D44
B2: 기준일 | C2: =변수!D45
B3: 모델 산출값 — 목표주가·추천 아님. 밴드·COE 는 변수 시트 3절의 가정
C5: FY | D5: 2025 | E5: 2026 | F5: 2027 | G5: 2028
D6: A | E6: E | F6: E | G6: E
C7: EPS(원) | D7: =IFERROR(VLOOKUP("EPS",subQ,MATCH(D$5,SUBQH,0),0),"") | E7: =IFERROR(VLOOKUP("EPS",subQ,MATCH(E$5,SUBQH,0),0),"") | F7: =IFERROR(VLOOKUP("EPS",subQ,MATCH(F$5,SUBQH,0),0),"") | G7: =IFERROR(VLOOKUP("EPS",subQ,MATCH(G$5,SUBQH,0),0),"")
C8: BPS(원) | D8: =IFERROR(VLOOKUP("BPS",subQ,MATCH(D$5,SUBQH,0),0),"") | E8: =IFERROR(VLOOKUP("BPS",subQ,MATCH(E$5,SUBQH,0),0),"") | F8: =IFERROR(VLOOKUP("BPS",subQ,MATCH(F$5,SUBQH,0),0),"") | G8: =IFERROR(VLOOKUP("BPS",subQ,MATCH(G$5,SUBQH,0),0),"")
C9: 지배주주순이익(억원) | D9: =IFERROR(VLOOKUP("지배주주순이익",subQ,MATCH(D$5,SUBQH,0),0),"") | E9: =IFERROR(VLOOKUP("지배주주순이익",subQ,MATCH(E$5,SUBQH,0),0),"") | F9: =IFERROR(VLOOKUP("지배주주순이익",subQ,MATCH(F$5,SUBQH,0),0),"") | G9: =IFERROR(VLOOKUP("지배주주순이익",subQ,MATCH(G$5,SUBQH,0),0),"")
C10: 영업이익(억원) | D10: =IFERROR(VLOOKUP("영업이익",subQ,MATCH(D$5,SUBQH,0),0),"") | E10: =IFERROR(VLOOKUP("영업이익",subQ,MATCH(E$5,SUBQH,0),0),"") | F10: =IFERROR(VLOOKUP("영업이익",subQ,MATCH(F$5,SUBQH,0),0),"") | G10: =IFERROR(VLOOKUP("영업이익",subQ,MATCH(G$5,SUBQH,0),0),"")
C11: ROE(EPS/기초BPS) | E11: =IFERROR(E7/D8,"") | F11: =IFERROR(F7/E8,"") | G11: =IFERROR(G7/F8,"")
B13: PER
C14: 12M fwd EPS | D14: =IFERROR(E7*변수!D50+F7*(1-변수!D50),"")
C15: 적정가치 @PER_lo | D15: =변수!D47 | E15: =IFERROR(ROUND($D$14*D15,-2),"") | F15: =IFERROR(E15/$C$1-1,"") | G15: 배 · 원 · 종가 대비
C16: 적정가치 @PER_mid | D16: =변수!D48 | E16: =IFERROR(ROUND($D$14*D16,-2),"") | F16: =IFERROR(E16/$C$1-1,"") | G16: 배 · 원 · 종가 대비
C17: 적정가치 @PER_hi | D17: =변수!D49 | E17: =IFERROR(ROUND($D$14*D17,-2),"") | F17: =IFERROR(E17/$C$1-1,"") | G17: 배 · 원 · 종가 대비
C18: 현재 PER(종가/12M fwd EPS) | D18: =IFERROR($C$1/$D$14,"")
B20: PBR
C21: 최근 BPS(마지막 실적 분기) | D21: =IFERROR(VLOOKUP("BPS",subQ,MATCH("2Q26",SUBQH,0),0),"")
C22: ROE fwd(12M fwd EPS / BPS) | D22: =IFERROR($D$14/$D$21,"")
C23: COE | D23: =변수!D46
C24: 적정 PBR = ROE/COE | D24: =IFERROR(D22/D23,"")
C25: 적정가치(PBR) = BPS × 적정PBR | D25: =IFERROR(ROUND(D21*D24,-2),"") | E25: =IFERROR(D25/$C$1-1,"")
C26: 현재 PBR(종가/BPS) | D26: =IFERROR($C$1/D21,"")
B28: 모델 json valuation(참고)
C29: eps_fwd12m | D29: 112
C30: bps_latest | D30: 5706.8
C31: per_now | D31: 19.64
C32: pbr_now | D32: 0.39
C33: roe_fwd | D33: 0.0196
C34: fair_pbr | D34: 0.22
C35: fair_value_pbr | D35: 1300
C36: ev_ebitda | D36: 11.34
C37: note | D37: 모델 산출값 — 목표주가·추천 아님

Sheet 외화
C1: 이름: 외화QH — 환율 QoQ · 외화 순노출 × Δ기말환율 | E1: 4Q21 | F1: 1Q22 | G1: 2Q22 | H1: 3Q22 | I1: 4Q22 | J1: 1Q23 | K1: 2Q23 | L1: 3Q23 | M1: 4Q23 | N1: 1Q24 | O1: 2Q24 | P1: 3Q24 | Q1: 4Q24 | R1: 1Q25 | S1: 2Q25 | T1: 3Q25 | U1: 4Q25 | V1: 1Q26 | W1: 2Q26 | X1: 3Q26 | Y1: 4Q26 | Z1: 1Q27 | AA1: 2Q27 | AB1: 3Q27 | AC1: 4Q27 | AD1: 1Q28 | AE1: 2Q28 | AF1: 3Q28 | AG1: 4Q28
E3: 1 | F3: 2 | G3: 3 | H3: 4 | I3: 5 | J3: 6 | K3: 7 | L3: 8 | M3: 9 | N3: 10 | O3: 11 | P3: 12 | Q3: 13 | R3: 14 | S3: 15 | T3: 16 | U3: 17 | V3: 18 | W3: 19 | X3: 20 | Y3: 21 | Z3: 22 | AA3: 23 | AB3: 24 | AC3: 25 | AD3: 26 | AE3: 27 | AF3: 28 | AG3: 29
E4: 2021.12 | F4: 2022.03 | G4: 2022.06 | H4: 2022.09 | I4: 2022.12 | J4: 2023.03 | K4: 2023.06 | L4: 2023.09 | M4: 2023.12 | N4: 2024.03 | O4: 2024.06 | P4: 2024.09 | Q4: 2024.12 | R4: 2025.03 | S4: 2025.06 | T4: 2025.09 | U4: 2025.12 | V4: 2026.03 | W4: 2026.06 | X4: 2026.09 | Y4: 2026.12 | Z4: 2027.03 | AA4: 2027.06 | AB4: 2027.09 | AC4: 2027.12 | AD4: 2028.03 | AE4: 2028.06 | AF4: 2028.09 | AG4: 2028.12
D5: 원/달러(평균) | E5: =IFERROR(VLOOKUP($D5,환율,MATCH(E$1,변수H,0),0),"") | F5: =IFERROR(VLOOKUP($D5,환율,MATCH(F$1,변수H,0),0),"") | G5: =IFERROR(VLOOKUP($D5,환율,MATCH(G$1,변수H,0),0),"") | H5: =IFERROR(VLOOKUP($D5,환율,MATCH(H$1,변수H,0),0),"") | I5: =IFERROR(VLOOKUP($D5,환율,MATCH(I$1,변수H,0),0),"") | J5: =IFERROR(VLOOKUP($D5,환율,MATCH(J$1,변수H,0),0),"") | K5: =IFERROR(VLOOKUP($D5,환율,MATCH(K$1,변수H,0),0),"") | L5: =IFERROR(VLOOKUP($D5,환율,MATCH(L$1,변수H,0),0),"") | ... AG5: =IFERROR(VLOOKUP($D5,환율,MATCH(AG$1,변수H,0),0),"")
A6: 원/달러(평균) QoQ | F6: =IFERROR(F5/E5-1,"") | G6: =IFERROR(G5/F5-1,"") | H6: =IFERROR(H5/G5-1,"") | I6: =IFERROR(I5/H5-1,"") | J6: =IFERROR(J5/I5-1,"") | K6: =IFERROR(K5/J5-1,"") | L6: =IFERROR(L5/K5-1,"") | M6: =IFERROR(M5/L5-1,"") | ... AG6: =IFERROR(AG5/AF5-1,"")
D7: 원/달러(기말) | E7: =IFERROR(VLOOKUP($D7,환율,MATCH(E$1,변수H,0),0),"") | F7: =IFERROR(VLOOKUP($D7,환율,MATCH(F$1,변수H,0),0),"") | G7: =IFERROR(VLOOKUP($D7,환율,MATCH(G$1,변수H,0),0),"") | H7: =IFERROR(VLOOKUP($D7,환율,MATCH(H$1,변수H,0),0),"") | I7: =IFERROR(VLOOKUP($D7,환율,MATCH(I$1,변수H,0),0),"") | J7: =IFERROR(VLOOKUP($D7,환율,MATCH(J$1,변수H,0),0),"") | K7: =IFERROR(VLOOKUP($D7,환율,MATCH(K$1,변수H,0),0),"") | L7: =IFERROR(VLOOKUP($D7,환율,MATCH(L$1,변수H,0),0),"") | ... AG7: =IFERROR(VLOOKUP($D7,환율,MATCH(AG$1,변수H,0),0),"")
A8: 원/달러(기말) QoQ | F8: =IFERROR(F7/E7-1,"") | G8: =IFERROR(G7/F7-1,"") | H8: =IFERROR(H7/G7-1,"") | I8: =IFERROR(I7/H7-1,"") | J8: =IFERROR(J7/I7-1,"") | K8: =IFERROR(K7/J7-1,"") | L8: =IFERROR(L7/K7-1,"") | M8: =IFERROR(M7/L7-1,"") | ... AG8: =IFERROR(AG7/AF7-1,"")
D9: W/Euro(평균) | E9: =IFERROR(VLOOKUP($D9,환율,MATCH(E$1,변수H,0),0),"") | F9: =IFERROR(VLOOKUP($D9,환율,MATCH(F$1,변수H,0),0),"") | G9: =IFERROR(VLOOKUP($D9,환율,MATCH(G$1,변수H,0),0),"") | H9: =IFERROR(VLOOKUP($D9,환율,MATCH(H$1,변수H,0),0),"") | I9: =IFERROR(VLOOKUP($D9,환율,MATCH(I$1,변수H,0),0),"") | J9: =IFERROR(VLOOKUP($D9,환율,MATCH(J$1,변수H,0),0),"") | K9: =IFERROR(VLOOKUP($D9,환율,MATCH(K$1,변수H,0),0),"") | L9: =IFERROR(VLOOKUP($D9,환율,MATCH(L$1,변수H,0),0),"") | ... AG9: =IFERROR(VLOOKUP($D9,환율,MATCH(AG$1,변수H,0),0),"")
A10: W/Euro(평균) QoQ | F10: =IFERROR(F9/E9-1,"") | G10: =IFERROR(G9/F9-1,"") | H10: =IFERROR(H9/G9-1,"") | I10: =IFERROR(I9/H9-1,"") | J10: =IFERROR(J9/I9-1,"") | K10: =IFERROR(K9/J9-1,"") | L10: =IFERROR(L9/K9-1,"") | M10: =IFERROR(M9/L9-1,"") | ... AG10: =IFERROR(AG9/AF9-1,"")
D11: W/Euro(기말) | E11: =IFERROR(VLOOKUP($D11,환율,MATCH(E$1,변수H,0),0),"") | F11: =IFERROR(VLOOKUP($D11,환율,MATCH(F$1,변수H,0),0),"") | G11: =IFERROR(VLOOKUP($D11,환율,MATCH(G$1,변수H,0),0),"") | H11: =IFERROR(VLOOKUP($D11,환율,MATCH(H$1,변수H,0),0),"") | I11: =IFERROR(VLOOKUP($D11,환율,MATCH(I$1,변수H,0),0),"") | J11: =IFERROR(VLOOKUP($D11,환율,MATCH(J$1,변수H,0),0),"") | K11: =IFERROR(VLOOKUP($D11,환율,MATCH(K$1,변수H,0),0),"") | L11: =IFERROR(VLOOKUP($D11,환율,MATCH(L$1,변수H,0),0),"") | ... AG11: =IFERROR(VLOOKUP($D11,환율,MATCH(AG$1,변수H,0),0),"")
A12: W/Euro(기말) QoQ | F12: =IFERROR(F11/E11-1,"") | G12: =IFERROR(G11/F11-1,"") | H12: =IFERROR(H11/G11-1,"") | I12: =IFERROR(I11/H11-1,"") | J12: =IFERROR(J11/I11-1,"") | K12: =IFERROR(K11/J11-1,"") | L12: =IFERROR(L11/K11-1,"") | M12: =IFERROR(M11/L11-1,"") | ... AG12: =IFERROR(AG11/AF11-1,"")
D13: 원/100Y(기말) | E13: =IFERROR(VLOOKUP($D13,환율,MATCH(E$1,변수H,0),0),"") | F13: =IFERROR(VLOOKUP($D13,환율,MATCH(F$1,변수H,0),0),"") | G13: =IFERROR(VLOOKUP($D13,환율,MATCH(G$1,변수H,0),0),"") | H13: =IFERROR(VLOOKUP($D13,환율,MATCH(H$1,변수H,0),0),"") | I13: =IFERROR(VLOOKUP($D13,환율,MATCH(I$1,변수H,0),0),"") | J13: =IFERROR(VLOOKUP($D13,환율,MATCH(J$1,변수H,0),0),"") | K13: =IFERROR(VLOOKUP($D13,환율,MATCH(K$1,변수H,0),0),"") | L13: =IFERROR(VLOOKUP($D13,환율,MATCH(L$1,변수H,0),0),"") | ... AG13: =IFERROR(VLOOKUP($D13,환율,MATCH(AG$1,변수H,0),0),"")
A14: 원/100Y(기말) QoQ | F14: =IFERROR(F13/E13-1,"") | G14: =IFERROR(G13/F13-1,"") | H14: =IFERROR(H13/G13-1,"") | I14: =IFERROR(I13/H13-1,"") | J14: =IFERROR(J13/I13-1,"") | K14: =IFERROR(K13/J13-1,"") | L14: =IFERROR(L13/K13-1,"") | M14: =IFERROR(M13/L13-1,"") | ... AG14: =IFERROR(AG13/AF13-1,"")
A16: 외화순노출 | C16: 외화 순노출(백만$) | D16: =변수!D57 | E16: 외화 순노출 × Δ기말환율 (외화 시트 방식)
A17: 환관련손익추정 | C17: 환관련손익 추정(억원) = 순노출 × Δ원/달러(기말) / 100 | F17: =IFERROR($D$16*(F7-E7)/100,"") | G17: =IFERROR($D$16*(G7-F7)/100,"") | H17: =IFERROR($D$16*(H7-G7)/100,"") | I17: =IFERROR($D$16*(I7-H7)/100,"") | J17: =IFERROR($D$16*(J7-I7)/100,"") | K17: =IFERROR($D$16*(K7-J7)/100,"") | L17: =IFERROR($D$16*(L7-K7)/100,"") | M17: =IFERROR($D$16*(M7-L7)/100,"") | ... AG17: =IFERROR($D$16*(AG7-AF7)/100,"")
A18: fx_pnl.by_q | C18: 모델 fx_pnl.by_q(억원, 참고)
C19: 외화 순노출 미공시(face) → 0 + 표기
