Workbook
Name 변수H: 변수!$C$1:$AO$1
Name 환율: 변수!$C$6:$AO$13
Name BS연결H: BS연결!$C$1:$AO$1
Name BS연결: BS연결!$C$5:$AO$5
Name BS별도H: BS별도!$C$1:$AO$1
Name BS별도: BS별도!$C$5:$AO$90
Name SUBQH: subQ!$A$1:$AO$1
Name subQ: subQ!$A$5:$AO$41

Sheet README
A1: 한국주강(025890) 실적 모델 — ARGUS 한국조선
A2: 기준 분기 2026Q2 · 마지막 실적 2026Q2 · 생성 2026-10-14
A3: 모든 수치는 모델 산출값(DART 공개 재무제표 + 우리 추정)이다 — 목표주가·투자 추천 아님. 참고용 · 투자조언 아님.
A5: 시트
A6: 변수 가정 시계열. 환율 8행(ECB via frankfurter — L2 fx.json; 추정 분기 = 노란 가정), 추정 드라이버(노란 셀 = 모델값에서 역산한 가정, 바꾸면 재계산; 연녹 셀 = 3절 스칼라 참조 수식), 3절 스칼라 가정(세율·판관비율·지배주주비중·이자율·종가·PER 밴드·COE·외화 순노출·헤지비율)
A7: BS연결/BS별도 FnGuide 계정명 × 기간 값 덤프(백만원). 행1 분기라벨, 행4 YYYY.MM / YYYY.12A. 이름정의 BS연결H·BS연결(계정명 C열부터)
A8: subQ 분기 서브모델(억원 = 백만원/100). 확정 행: =IFERROR(VLOOKUP($D행,BS연결,MATCH(E$1,BS연결H,0),0)/100,"") 추정 행: 변수 시트 가정 셀 참조 수식. 외환손익·파생상품손익은 BS 계정 합·차, 기타금융손익은 잔차, OPM·EPS·BPS·PER·PBR 은 파생 수식
A9: SLS 선표(조선사만, sls json 있을 때): 요약 행(sls 저장값) + 계약별 스케줄(백만$) × (헤지비율 × 헤지환율 + (1−헤지비율) × 건조시점 환율[변수 원/달러(평균)]) → 원화 수식 블록 → 합계 행이 subQ 매출조선에 연결
A10: 시나리오 신규수주 보수/기준/낙관(forecast_panel 패널, 모델에 scenarios 가 있을 때만): 매출액·영업이익 = subQ 기준값 ± (시나리오 신규 − base 신규) × OPM. base 만 subQ 행에 포함, 나머지는 합산 안 함
A11: 분기/연간예상 subQ 를 이름(A열 key)으로 VLOOKUP 한 보고서 표(억원)
A12: TP PER 밴드 × 12M fwd EPS, PBR = ROE/COE × BPS — 모델 산출값 구간, 목표주가·추천 아님
A13: 외화 환율 QoQ, 외화 순노출 × Δ기말환율 → 환관련손익 추정
... A34: 백테스트: {"freeze": "2025Q2", "horizon": 4, "revenue_wape_pct": 16.0, "op_wape_pct": 180.2, "n": 4, "note": "단일 회사 4분기 — 통계 아님", "driver_at_freeze": "trend_seasonal", "selection_oos_at_freeze": null, "frozen_inputs": "fin(연결/별도)·고객 조선사 모델·지주 자회사 모델은 2025Q2 까지의 분기만; 선표는 체결일 ≤ 2025Q2 말일 계약(원장 최신 금액·코호트 등급, 환산 없음); 잔고는 yards_cache 2025Q2; 시세·환율 forward·prices·forecast_panel 신규수주 미사용. 고객 가중치(suppliers.json 언급 비중)와 합병 체인링크는 현재 지식; 고객 연동 채택은 동결 모델 안에서도 자기 la−4분기 OOS 규칙(selection_oos_at_freeze)", "detail": [{"q": "2025Q3", "rev_pred": 83.53, "rev_act": 97.77, "op_pred": 2.39, "op_act": -3.27}, {"q": "2025Q4", "rev_pred": 115.84, "rev_act": 89.99, "op_pred": 3.32, "op_act": -2.78}, {"q": "2026Q1", "rev_pred": 79.11, "rev_act": 88.26, "op_pred": 2.27, "op_act": 0.59}, {"q": "2026Q2", "rev_pred": 97.99, "rev_act": 110.76, "op_pred": 2.81, "op_act": 1.53}]}

Sheet 변수
C1: 이름: 변수H | E1: 4Q21 | F1: 2021 | G1: 1Q22 | H1: 2Q22 | I1: 3Q22 | J1: 4Q22 | K1: 2022 | L1: 1Q23 | M1: 2Q23 | N1: 3Q23 | O1: 4Q23 | P1: 2023 | Q1: 1Q24 | R1: 2Q24 | S1: 3Q24 | T1: 4Q24 | U1: 2024 | V1: 1Q25 | W1: 2Q25 | X1: 3Q25 | Y1: 4Q25 | Z1: 2025 | AA1: 1Q26 | AB1: 2Q26 | AC1: 3Q26 | AD1: 4Q26 | AE1: 2026 | AF1: 1Q27 | AG1: 2Q27 | AH1: 3Q27 | AI1: 4Q27 | AJ1: 2027 | AK1: 1Q28 | AL1: 2Q28 | AM1: 3Q28 | AN1: 4Q28 | AO1: 2028
A2: 가정 시계열 — 노란 셀은 추정 가정(모델값에서 역산), 연녹 셀은 3절 스칼라 참조 수식. 바꾸면 subQ·분기·연간예상·TP·시나리오가 재계산됩니다.
E3: 1 | F3: 2 | G3: 3 | H3: 4 | I3: 5 | J3: 6 | K3: 7 | L3: 8 | M3: 9 | N3: 10 | O3: 11 | P3: 12 | Q3: 13 | R3: 14 | S3: 15 | T3: 16 | U3: 17 | V3: 18 | W3: 19 | X3: 20 | Y3: 21 | Z3: 22 | AA3: 23 | AB3: 24 | AC3: 25 | AD3: 26 | AE3: 27 | AF3: 28 | AG3: 29 | AH3: 30 | AI3: 31 | AJ3: 32 | AK3: 33 | AL3: 34 | AM3: 35 | AN3: 36 | AO3: 37
E4: 2021.12 | F4: 2021.12A | G4: 2022.03 | H4: 2022.06 | I4: 2022.09 | J4: 2022.12 | K4: 2022.12A | L4: 2023.03 | M4: 2023.06 | N4: 2023.09 | O4: 2023.12 | P4: 2023.12A | Q4: 2024.03 | R4: 2024.06 | S4: 2024.09 | T4: 2024.12 | U4: 2024.12A | V4: 2025.03 | W4: 2025.06 | X4: 2025.09 | Y4: 2025.12 | Z4: 2025.12A | AA4: 2026.03 | AB4: 2026.06 | AC4: 2026.09 | AD4: 2026.12 | AE4: 2026.12A | AF4: 2027.03 | AG4: 2027.06 | AH4: 2027.09 | AI4: 2027.12 | AJ4: 2027.12A | AK4: 2028.03 | AL4: 2028.06 | AM4: 2028.09 | AN4: 2028.12 | AO4: 2028.12A
B5: 1. FX | C5: 이름: 환율
A6: USDKRW_avg | C6: 원/달러(평균) | E6: 1183.5 | F6: 1145.51 | G6: 1205.78 | H6: 1262.09 | I6: 1341.93 | J6: 1360.12 | K6: 1292.98 | L6: 1276.95 | M6: 1315.69 | N6: 1313.62 | O6: 1322.01 | P6: 1306.85 | Q6: 1330.14 | R6: 1371.28 | S6: 1356.22 | T6: 1396.3 | U6: 1363.53 | V6: 1452.28 | W6: 1398.52 | X6: 1386.95 | Y6: 1449.19 | Z6: 1421.52 | AA6: 1466.12 | AB6: 1501.75 | AC6: 1418.75 | AD6: 1343.39 | AE6: 1456.01 | AF6: 1341.45 | AG6: 1341.45 | AH6: 1341.45 | AI6: 1341.45 | AK6: 1341.45 | AL6: 1341.45 | AM6: 1341.45 | AN6: 1341.45
A7: USDKRW_end | C7: 원/달러(기말) | E7: 1188.75 | F7: 1188.75 | G7: 1213.74 | H7: 1301.24 | I7: 1436.9 | J7: 1260.16 | K7: 1260.16 | L7: 1305.99 | M7: 1321.44 | N7: 1345.35 | O7: 1297.43 | P7: 1297.43 | Q7: 1349.25 | R7: 1377.73 | S7: 1312.17 | T7: 1474.78 | U7: 1474.78 | V7: 1474.54 | W7: 1355.13 | X7: 1403.67 | Y7: 1444.2 | Z7: 1444.2 | AA7: 1524.8 | AB7: 1550.89 | AC7: 1355.4 | AD7: 1341.45 | AE7: 1341.45 | AF7: 1341.45 | AG7: 1341.45 | AH7: 1341.45 | AI7: 1341.45 | AK7: 1341.45 | AL7: 1341.45 | AM7: 1341.45 | AN7: 1341.45
A8: JPY100KRW_avg | C8: 원/100Y(평균) | E8: 1041.02 | F8: 1042.74 | G8: 1036.79 | H8: 972.23 | I8: 970.61 | J8: 961.03 | K8: 985.1 | L8: 964.89 | M8: 957.36 | N8: 909 | O8: 893.22 | P8: 931.11 | Q8: 896.29 | R8: 880.14 | S8: 909.35 | T8: 917.25 | U8: 900.92 | V8: 952.59 | W8: 967.92 | X8: 940.32 | Y8: 940.77 | Z8: 950.17 | AA8: 934.39 | AB8: 942.16 | AC8: 890.41 | AD8: 849.39 | AE8: 918.46 | AF8: 848.37 | AG8: 848.37 | AH8: 848.37 | AI8: 848.37 | AK8: 848.37 | AL8: 848.37 | AM8: 848.37 | AN8: 848.37
A9: JPY100KRW_end | C9: 원/100Y(기말) | E9: 1032.62 | F9: 1032.62 | G9: 996.83 | H9: 954.9 | I9: 993.29 | J9: 955.54 | K9: 955.54 | L9: 980.62 | M9: 913.67 | N9: 901.47 | O9: 917.04 | P9: 917.04 | Q9: 892.42 | R9: 857.76 | S9: 919.21 | T9: 939.65 | U9: 939.65 | V9: 986.84 | W9: 938.85 | X9: 948.49 | Y9: 921.81 | Z9: 921.81 | AA9: 955.99 | AB9: 954.75 | AC9: 863.31 | AD9: 848.37 | AE9: 848.37 | AF9: 848.37 | AG9: 848.37 | AH9: 848.37 | AI9: 848.37 | AK9: 848.37 | AL9: 848.37 | AM9: 848.37 | AN9: 848.37
A10: EURKRW_avg | C10: W/Euro(평균) | E10: 1353.32 | F10: 1354.06 | G10: 1352.29 | H10: 1343.31 | I10: 1350.63 | J10: 1386.07 | K10: 1358.07 | L10: 1369.93 | M10: 1432.41 | N10: 1429.41 | O10: 1420.91 | P10: 1412.88 | Q10: 1444.21 | R10: 1476.42 | S10: 1489.3 | T10: 1490.78 | U10: 1475.4 | V10: 1528.33 | W10: 1585.13 | X10: 1620.04 | Y10: 1686.02 | Z10: 1605.45 | AA10: 1715.47 | AB10: 1746.09 | AC10: 1631.97 | AD10: 1506.62 | AE10: 1688.01 | AF10: 1500.82 | AG10: 1500.82 | AH10: 1500.82 | AI10: 1500.82 | AK10: 1500.82 | AL10: 1500.82 | AM10: 1500.82 | AN10: 1500.82
A11: EURKRW_end | C11: W/Euro(기말) | E11: 1346.38 | F11: 1346.38 | G11: 1347.37 | H11: 1351.6 | I11: 1400.62 | J11: 1344.08 | K11: 1344.08 | L11: 1420.26 | M11: 1435.88 | N11: 1425.26 | O11: 1433.66 | P11: 1433.66 | Q11: 1458.68 | R11: 1474.86 | S11: 1469.1 | T11: 1532.14 | U11: 1532.14 | V11: 1594.72 | W11: 1588.22 | X11: 1648.04 | Y11: 1696.94 | Z11: 1696.94 | AA11: 1753.21 | AB11: 1767.09 | AC11: 1539.06 | AD11: 1500.82 | AE11: 1500.82 | AF11: 1500.82 | AG11: 1500.82 | AH11: 1500.82 | AI11: 1500.82 | AK11: 1500.82 | AL11: 1500.82 | AM11: 1500.82 | AN11: 1500.82
A12: CNYKRW_avg | C12: 원/중국원(평균) | E12: 185.14 | F12: 177.65 | G12: 189.93 | H12: 190.76 | I12: 195.79 | J12: 191.09 | K12: 191.93 | L12: 186.59 | M12: 187.45 | N12: 181.28 | O12: 182.86 | P12: 184.52 | Q12: 185.04 | R12: 189.35 | S12: 189.24 | T12: 194.24 | U12: 189.49 | V12: 199.63 | W12: 193.41 | X12: 193.79 | Y12: 204.38 | Z12: 197.8 | AA12: 211.75 | AB12: 220.8 | AC12: 210.43 | AD12: 200.49 | AE12: 213.61 | AF12: 200.4 | AG12: 200.4 | AH12: 200.4 | AI12: 200.4 | AK12: 200.4 | AL12: 200.4 | AM12: 200.4 | AN12: 200.4
A13: CNYKRW_end | C13: 원/중국원(기말) | E13: 187.13 | F13: 187.13 | G13: 191.38 | H13: 194.13 | I13: 201.92 | J13: 182.67 | K13: 182.67 | L13: 189.97 | M13: 181.8 | N13: 184.26 | O13: 182.61 | P13: 182.61 | Q13: 186.66 | R13: 189.7 | S13: 187.12 | T13: 202.04 | U13: 202.04 | V13: 203.3 | W13: 189.14 | X13: 197.16 | Y13: 206.28 | Z13: 206.28 | AA13: 220.97 | AB13: 228.56 | AC13: 202.16 | AD13: 200.4 | AE13: 200.4 | AF13: 200.4 | AG13: 200.4 | AH13: 200.4 | AI13: 200.4 | AK13: 200.4 | AL13: 200.4 | AM13: 200.4 | AN13: 200.4
B14: 1b. 종가
A15: price_close_end | C15: 종가(기말) | E15: 5320 | G15: 4260 | H15: 2710 | I15: 2410 | J15: 2560 | L15: 3390 | M15: 3355 | N15: 2775 | O15: 3035 | Q15: 2550 | R15: 2085 | S15: 1981 | T15: 1879 | V15: 1727 | W15: 1856 | X15: 1882 | Y15: 1805 | AA15: 1956 | AB15: 2180 | AC15: 2680 | AD15: 2500
A16: price_high | C16: 종가(최고) | E16: 8580 | G16: 5640 | H16: 4465 | I16: 4170 | J16: 3260 | L16: 4170 | M16: 4705 | N16: 3375 | O16: 3185 | Q16: 3205 | R16: 2565 | S16: 2865 | T16: 2525 | V16: 1969 | W16: 1952 | X16: 2300 | Y16: 2235 | AA16: 2155 | AB16: 2340 | AC16: 2790 | AD16: 2780
A17: price_low | C17: 종가(최저) | E17: 3150 | G17: 3990 | H17: 2420 | I17: 2355 | J17: 2295 | L17: 2490 | M17: 2970 | N17: 2540 | O17: 2300 | Q17: 2450 | R17: 2060 | S17: 1850 | T17: 1747 | V17: 1715 | W17: 1715 | X17: 1780 | Y17: 1638 | AA17: 1494 | AB17: 1772 | AC17: 2130 | AD17: 2450
A18: price_avg | C18: 종가(평균) | E18: 6118.8 | G18: 4601.7 | H18: 3655.8 | I18: 2809.9 | J18: 2565.4 | L18: 3426.5 | M18: 3367.5 | N18: 2833.7 | O18: 2793.8 | Q18: 2734.1 | R18: 2292.9 | S18: 2079.9 | T18: 1971.1 | V18: 1809.4 | W18: 1836.2 | X18: 1905 | Y18: 1790.6 | AA18: 1732.8 | AB18: 2055.9 | AC18: 2432.7 | AD18: 2609.4
B20: 2. 추정 드라이버 | C20: 실적 열 = subQ 실현값(수식), 추정 열 = 가정(노란 = 모델값 역산, 연녹 = 3절 스칼라 참조)
A21: drv:매출액 | B21: yoy | C21: 매출액 YoY | J21: =IFERROR(subQ!J5/subQ!E5-1,"") | L21: =IFERROR(subQ!L5/subQ!G5-1,"") | M21: =IFERROR(subQ!M5/subQ!H5-1,"") | N21: =IFERROR(subQ!N5/subQ!I5-1,"") | O21: =IFERROR(subQ!O5/subQ!J5-1,"") | Q21: =IFERROR(subQ!Q5/subQ!L5-1,"") | R21: =IFERROR(subQ!R5/subQ!M5-1,"") | S21: =IFERROR(subQ!S5/subQ!N5-1,"") | T21: =IFERROR(subQ!T5/subQ!O5-1,"") | V21: =IFERROR(subQ!V5/subQ!Q5-1,"") | W21: =IFERROR(subQ!W5/subQ!R5-1,"") | X21: =IFERROR(subQ!X5/subQ!S5-1,"") | Y21: =IFERROR(subQ!Y5/subQ!T5-1,"") | AA21: =IFERROR(subQ!AA5/subQ!V5-1,"") | AB21: =IFERROR(subQ!AB5/subQ!W5-1,"") | AC21: -0.13754306 | AD21: -0.1375373 | AF21: -0.13758822 | AG21: -0.13758001 | AH21: -0.068785579 | AI21: -0.068805566 | AK21: -0.068707304 | AL21: -0.068781407 | AM21: -0.034386144 | AN21: -0.03445413
A22: drv:판관비 | B22: ratio | C22: 판관비율(/매출) | E22: =IFERROR(subQ!E8/subQ!E5,"") | F22: =IFERROR(subQ!F8/subQ!F5,"") | G22: =IFERROR(subQ!G8/subQ!G5,"") | H22: =IFERROR(subQ!H8/subQ!H5,"") | I22: =IFERROR(subQ!I8/subQ!I5,"") | J22: =IFERROR(subQ!J8/subQ!J5,"") | K22: =IFERROR(subQ!K8/subQ!K5,"") | L22: =IFERROR(subQ!L8/subQ!L5,"") | ... AB22: =IFERROR(subQ!AB8/subQ!AB5,"") | AC22: =$D$50 | AD22: =$D$50 | AE22: =IFERROR(subQ!AE8/subQ!AE5,"") | AF22: =$D$50 | AG22: =$D$50 | AH22: =$D$50 | AI22: =$D$50 | AJ22: =IFERROR(subQ!AJ8/subQ!AJ5,"") | AK22: =$D$50 | AL22: =$D$50 | AM22: =$D$50 | AN22: =$D$50 | AO22: =IFERROR(subQ!AO8/subQ!AO5,"")
A23: drv:영업이익 | B23: ratio | C23: 영업이익률(OPM) | E23: =IFERROR(subQ!E9/subQ!E5,"") | F23: =IFERROR(subQ!F9/subQ!F5,"") | G23: =IFERROR(subQ!G9/subQ!G5,"") | H23: =IFERROR(subQ!H9/subQ!H5,"") | I23: =IFERROR(subQ!I9/subQ!I5,"") | J23: =IFERROR(subQ!J9/subQ!J5,"") | K23: =IFERROR(subQ!K9/subQ!K5,"") | L23: =IFERROR(subQ!L9/subQ!L5,"") | ... AB23: =IFERROR(subQ!AB9/subQ!AB5,"") | AC23: 0.007234345 | AD23: 0.007344414 | AE23: =IFERROR(subQ!AE9/subQ!AE5,"") | AF23: 0.007225434 | AG23: 0.007328308 | AH23: 0.007259297 | AI23: 0.00733361 | AJ23: =IFERROR(subQ!AJ9/subQ!AJ5,"") | AK23: 0.007335308 | AL23: 0.007307476 | AM23: 0.007254023 | AN23: 0.007308684 | AO23: =IFERROR(subQ!AO9/subQ!AO5,"")
A24: drv:외환손익 | B24: abs | C24: 외환손익 (가정, 억원) | E24: =subQ!E13 | F24: =subQ!F13 | G24: =subQ!G13 | H24: =subQ!H13 | I24: =subQ!I13 | J24: =subQ!J13 | K24: =subQ!K13 | L24: =subQ!L13 | ... AB24: =subQ!AB13 | AC24: 0 | AD24: 0 | AE24: =subQ!AE13 | AF24: 0 | AG24: 0 | AH24: 0 | AI24: 0 | AJ24: =subQ!AJ13 | AK24: 0 | AL24: 0 | AM24: 0 | AN24: 0 | AO24: =subQ!AO13
A25: drv:기타영업외손익 | B25: abs | C25: 기타영업외손익 (가정, 억원) | E25: =subQ!E14 | F25: =subQ!F14 | G25: =subQ!G14 | H25: =subQ!H14 | I25: =subQ!I14 | J25: =subQ!J14 | K25: =subQ!K14 | L25: =subQ!L14 | ... AB25: =subQ!AB14 | AC25: 0 | AD25: 0 | AE25: =subQ!AE14 | AF25: 0 | AG25: 0 | AH25: 0 | AI25: 0 | AJ25: =subQ!AJ14 | AK25: 0 | AL25: 0 | AM25: 0 | AN25: 0 | AO25: =subQ!AO14
A26: drv:지분법손익 | B26: abs | C26: 지분법손익 (가정, 억원) | E26: =subQ!E15 | F26: =subQ!F15 | G26: =subQ!G15 | H26: =subQ!H15 | I26: =subQ!I15 | J26: =subQ!J15 | K26: =subQ!K15 | L26: =subQ!L15 | ... AB26: =subQ!AB15 | AC26: 0 | AD26: 0 | AE26: =subQ!AE15 | AF26: 0 | AG26: 0 | AH26: 0 | AI26: 0 | AJ26: =subQ!AJ15 | AK26: 0 | AL26: 0 | AM26: 0 | AN26: 0 | AO26: =subQ!AO15
A27: drv:법인세비용 | B27: tax | C27: 법인세율(/세전) — 법인세 = MAX(세전,0) × 세율 | E27: =IFERROR(subQ!E17/subQ!E16,"") | F27: =IFERROR(subQ!F17/subQ!F16,"") | G27: =IFERROR(subQ!G17/subQ!G16,"") | H27: =IFERROR(subQ!H17/subQ!H16,"") | I27: =IFERROR(subQ!I17/subQ!I16,"") | J27: =IFERROR(subQ!J17/subQ!J16,"") | K27: =IFERROR(subQ!K17/subQ!K16,"") | L27: =IFERROR(subQ!L17/subQ!L16,"") | ... AB27: =IFERROR(subQ!AB17/subQ!AB16,"") | AC27: =$D$49 | AD27: =$D$49 | AE27: =IFERROR(subQ!AE17/subQ!AE16,"") | AF27: =$D$49 | AG27: =$D$49 | AH27: =$D$49 | AI27: =$D$49 | AJ27: =IFERROR(subQ!AJ17/subQ!AJ16,"") | AK27: =$D$49 | AL27: =$D$49 | AM27: =$D$49 | AN27: =$D$49 | AO27: =IFERROR(subQ!AO17/subQ!AO16,"")
A28: drv:지배주주순이익 | B28: ratio | C28: 지배주주 비중(/당기순이익) | E28: =IFERROR(subQ!E19/subQ!E18,"") | F28: =IFERROR(subQ!F19/subQ!F18,"") | G28: =IFERROR(subQ!G19/subQ!G18,"") | H28: =IFERROR(subQ!H19/subQ!H18,"") | I28: =IFERROR(subQ!I19/subQ!I18,"") | J28: =IFERROR(subQ!J19/subQ!J18,"") | K28: =IFERROR(subQ!K19/subQ!K18,"") | L28: =IFERROR(subQ!L19/subQ!L18,"") | ... AB28: =IFERROR(subQ!AB19/subQ!AB18,"") | AC28: =$D$51 | AD28: =$D$51 | AE28: =IFERROR(subQ!AE19/subQ!AE18,"") | AF28: =$D$51 | AG28: =$D$51 | AH28: =$D$51 | AI28: =$D$51 | AJ28: =IFERROR(subQ!AJ19/subQ!AJ18,"") | AK28: =$D$51 | AL28: =$D$51 | AM28: =$D$51 | AN28: =$D$51 | AO28: =IFERROR(subQ!AO19/subQ!AO18,"")
A29: drv:부채총계 | B29: qoq | C29: 부채총계 QoQ | G29: =IFERROR(subQ!G21/subQ!E21-1,"") | H29: =IFERROR(subQ!H21/subQ!G21-1,"") | I29: =IFERROR(subQ!I21/subQ!H21-1,"") | J29: =IFERROR(subQ!J21/subQ!I21-1,"") | L29: =IFERROR(subQ!L21/subQ!J21-1,"") | M29: =IFERROR(subQ!M21/subQ!L21-1,"") | N29: =IFERROR(subQ!N21/subQ!M21-1,"") | O29: =IFERROR(subQ!O21/subQ!N21-1,"") | Q29: =IFERROR(subQ!Q21/subQ!O21-1,"") | R29: =IFERROR(subQ!R21/subQ!Q21-1,"") | S29: =IFERROR(subQ!S21/subQ!R21-1,"") | T29: =IFERROR(subQ!T21/subQ!S21-1,"") | V29: =IFERROR(subQ!V21/subQ!T21-1,"") | W29: =IFERROR(subQ!W21/subQ!V21-1,"") | X29: =IFERROR(subQ!X21/subQ!W21-1,"") | Y29: =IFERROR(subQ!Y21/subQ!X21-1,"") | AA29: =IFERROR(subQ!AA21/subQ!Y21-1,"") | AB29: =IFERROR(subQ!AB21/subQ!AA21-1,"") | AC29: -1.5125e-05 | AD29: 0 | AF29: 0 | AG29: 0 | AH29: 0 | AI29: 0 | AK29: 0 | AL29: 0 | AM29: 0 | AN29: 0
A30: drv:자본총계 | B30: roll | C30: 자본총계 기타변동(배당 등, 억원) | G30: =IFERROR(subQ!E22+subQ!G18-subQ!G22,"") | H30: =IFERROR(subQ!G22+subQ!H18-subQ!H22,"") | I30: =IFERROR(subQ!H22+subQ!I18-subQ!I22,"") | J30: =IFERROR(subQ!I22+subQ!J18-subQ!J22,"") | L30: =IFERROR(subQ!J22+subQ!L18-subQ!L22,"") | M30: =IFERROR(subQ!L22+subQ!M18-subQ!M22,"") | N30: =IFERROR(subQ!M22+subQ!N18-subQ!N22,"") | O30: =IFERROR(subQ!N22+subQ!O18-subQ!O22,"") | Q30: =IFERROR(subQ!O22+subQ!Q18-subQ!Q22,"") | R30: =IFERROR(subQ!Q22+subQ!R18-subQ!R22,"") | S30: =IFERROR(subQ!R22+subQ!S18-subQ!S22,"") | T30: =IFERROR(subQ!S22+subQ!T18-subQ!T22,"") | V30: =IFERROR(subQ!T22+subQ!V18-subQ!V22,"") | W30: =IFERROR(subQ!V22+subQ!W18-subQ!W22,"") | X30: =IFERROR(subQ!W22+subQ!X18-subQ!X22,"") | Y30: =IFERROR(subQ!X22+subQ!Y18-subQ!Y22,"") | AA30: =IFERROR(subQ!Y22+subQ!AA18-subQ!AA22,"") | AB30: =IFERROR(subQ!AA22+subQ!AB18-subQ!AB22,"") | AC30: 0.000649977 | AD30: 0.003249978 | AF30: -0.002249972 | AG30: 0.003999985 | AH30: -0.00675 | AI30: 0.009999995 | AK30: 0.009999985 | AL30: -0.004750008 | AM30: -0.002249981 | AN30: 0.00999997
A31: drv:지배주주지분 | B31: roll | C31: 지배주주지분 기타변동(배당 등, 억원) | G31: =IFERROR(subQ!E23+subQ!G19-subQ!G23,"") | H31: =IFERROR(subQ!G23+subQ!H19-subQ!H23,"") | I31: =IFERROR(subQ!H23+subQ!I19-subQ!I23,"") | J31: =IFERROR(subQ!I23+subQ!J19-subQ!J23,"") | L31: =IFERROR(subQ!J23+subQ!L19-subQ!L23,"") | M31: =IFERROR(subQ!L23+subQ!M19-subQ!M23,"") | N31: =IFERROR(subQ!M23+subQ!N19-subQ!N23,"") | O31: =IFERROR(subQ!N23+subQ!O19-subQ!O23,"") | Q31: =IFERROR(subQ!O23+subQ!Q19-subQ!Q23,"") | R31: =IFERROR(subQ!Q23+subQ!R19-subQ!R23,"") | S31: =IFERROR(subQ!R23+subQ!S19-subQ!S23,"") | T31: =IFERROR(subQ!S23+subQ!T19-subQ!T23,"") | V31: =IFERROR(subQ!T23+subQ!V19-subQ!V23,"") | W31: =IFERROR(subQ!V23+subQ!W19-subQ!W23,"") | X31: =IFERROR(subQ!W23+subQ!X19-subQ!X23,"") | Y31: =IFERROR(subQ!X23+subQ!Y19-subQ!Y23,"") | AA31: =IFERROR(subQ!Y23+subQ!AA19-subQ!AA23,"") | AB31: =IFERROR(subQ!AA23+subQ!AB19-subQ!AB23,"") | AC31: 0.000649977 | AD31: 0.003249978 | AF31: -0.002249972 | AG31: 0.003999985 | AH31: -0.00675 | AI31: 0.009999995 | AK31: 0.009999985 | AL31: -0.004750008 | AM31: -0.002249981 | AN31: 0.00999997
A32: drv:총차입금 | B32: qoq | C32: 총차입금 QoQ | G32: =IFERROR(subQ!G24/subQ!E24-1,"") | H32: =IFERROR(subQ!H24/subQ!G24-1,"") | I32: =IFERROR(subQ!I24/subQ!H24-1,"") | J32: =IFERROR(subQ!J24/subQ!I24-1,"") | L32: =IFERROR(subQ!L24/subQ!J24-1,"") | M32: =IFERROR(subQ!M24/subQ!L24-1,"") | N32: =IFERROR(subQ!N24/subQ!M24-1,"") | O32: =IFERROR(subQ!O24/subQ!N24-1,"") | Q32: =IFERROR(subQ!Q24/subQ!O24-1,"") | R32: =IFERROR(subQ!R24/subQ!Q24-1,"") | S32: =IFERROR(subQ!S24/subQ!R24-1,"") | T32: =IFERROR(subQ!T24/subQ!S24-1,"") | V32: =IFERROR(subQ!V24/subQ!T24-1,"") | W32: =IFERROR(subQ!W24/subQ!V24-1,"") | X32: =IFERROR(subQ!X24/subQ!W24-1,"") | Y32: =IFERROR(subQ!Y24/subQ!X24-1,"") | AA32: =IFERROR(subQ!AA24/subQ!Y24-1,"") | AB32: =IFERROR(subQ!AB24/subQ!AA24-1,"") | AC32: 0 | AD32: 0 | AF32: 0 | AG32: 0 | AH32: 0 | AI32: 0 | AK32: 0 | AL32: 0 | AM32: 0 | AN32: 0
A33: drv:순차입금 | B33: qoq | C33: 순차입금 QoQ | G33: =IFERROR(subQ!G25/subQ!E25-1,"") | H33: =IFERROR(subQ!H25/subQ!G25-1,"") | I33: =IFERROR(subQ!I25/subQ!H25-1,"") | J33: =IFERROR(subQ!J25/subQ!I25-1,"") | L33: =IFERROR(subQ!L25/subQ!J25-1,"") | M33: =IFERROR(subQ!M25/subQ!L25-1,"") | N33: =IFERROR(subQ!N25/subQ!M25-1,"") | O33: =IFERROR(subQ!O25/subQ!N25-1,"") | Q33: =IFERROR(subQ!Q25/subQ!O25-1,"") | R33: =IFERROR(subQ!R25/subQ!Q25-1,"") | S33: =IFERROR(subQ!S25/subQ!R25-1,"") | T33: =IFERROR(subQ!T25/subQ!S25-1,"") | V33: =IFERROR(subQ!V25/subQ!T25-1,"") | W33: =IFERROR(subQ!W25/subQ!V25-1,"") | X33: =IFERROR(subQ!X25/subQ!W25-1,"") | Y33: =IFERROR(subQ!Y25/subQ!X25-1,"") | AA33: =IFERROR(subQ!AA25/subQ!Y25-1,"") | AB33: =IFERROR(subQ!AB25/subQ!AA25-1,"") | AC33: -0.001020109 | AD33: -0.000346741 | AF33: -0.00017343 | AG33: -0.002081526 | AH33: -0.000347645 | AI33: 0.000347766 | AK33: 0.000347645 | AL33: -0.001390096 | AM33: -0.000174004 | AN33: 0.000522102
A34: drv:이자발생자산 | B34: qoq | C34: 이자발생자산 QoQ | G34: =IFERROR(subQ!G26/subQ!E26-1,"") | H34: =IFERROR(subQ!H26/subQ!G26-1,"") | I34: =IFERROR(subQ!I26/subQ!H26-1,"") | J34: =IFERROR(subQ!J26/subQ!I26-1,"") | L34: =IFERROR(subQ!L26/subQ!J26-1,"") | M34: =IFERROR(subQ!M26/subQ!L26-1,"") | N34: =IFERROR(subQ!N26/subQ!M26-1,"") | O34: =IFERROR(subQ!O26/subQ!N26-1,"") | Q34: =IFERROR(subQ!Q26/subQ!O26-1,"") | R34: =IFERROR(subQ!R26/subQ!Q26-1,"") | S34: =IFERROR(subQ!S26/subQ!R26-1,"") | T34: =IFERROR(subQ!T26/subQ!S26-1,"") | V34: =IFERROR(subQ!V26/subQ!T26-1,"") | W34: =IFERROR(subQ!W26/subQ!V26-1,"") | X34: =IFERROR(subQ!X26/subQ!W26-1,"") | Y34: =IFERROR(subQ!Y26/subQ!X26-1,"") | AA34: =IFERROR(subQ!AA26/subQ!Y26-1,"") | AB34: =IFERROR(subQ!AB26/subQ!AA26-1,"") | AC34: 0.015604337 | AD34: 0.005208333 | AF34: 0.002590674 | AG34: 0.031007752 | AH34: 0.005012531 | AI34: -0.004987531 | AK34: -0.005012531 | AL34: 0.020151134 | AM34: 0.002469136 | AN34: -0.007389163
A35: drv:현금및현금성자산 | B35: qoq | C35: 현금및현금성자산 QoQ | G35: =IFERROR(subQ!G27/subQ!E27-1,"") | H35: =IFERROR(subQ!H27/subQ!G27-1,"") | I35: =IFERROR(subQ!I27/subQ!H27-1,"") | J35: =IFERROR(subQ!J27/subQ!I27-1,"") | L35: =IFERROR(subQ!L27/subQ!J27-1,"") | M35: =IFERROR(subQ!M27/subQ!L27-1,"") | N35: =IFERROR(subQ!N27/subQ!M27-1,"") | O35: =IFERROR(subQ!O27/subQ!N27-1,"") | Q35: =IFERROR(subQ!Q27/subQ!O27-1,"") | R35: =IFERROR(subQ!R27/subQ!Q27-1,"") | S35: =IFERROR(subQ!S27/subQ!R27-1,"") | T35: =IFERROR(subQ!T27/subQ!S27-1,"") | V35: =IFERROR(subQ!V27/subQ!T27-1,"") | W35: =IFERROR(subQ!W27/subQ!V27-1,"") | X35: =IFERROR(subQ!X27/subQ!W27-1,"") | Y35: =IFERROR(subQ!Y27/subQ!X27-1,"") | AA35: =IFERROR(subQ!AA27/subQ!Y27-1,"") | AB35: =IFERROR(subQ!AB27/subQ!AA27-1,"")
A36: drv:CAPEX | B36: yoy | C36: CAPEX YoY | J36: =IFERROR(subQ!J28/subQ!E28-1,"") | L36: =IFERROR(subQ!L28/subQ!G28-1,"") | M36: =IFERROR(subQ!M28/subQ!H28-1,"") | N36: =IFERROR(subQ!N28/subQ!I28-1,"") | O36: =IFERROR(subQ!O28/subQ!J28-1,"") | Q36: =IFERROR(subQ!Q28/subQ!L28-1,"") | R36: =IFERROR(subQ!R28/subQ!M28-1,"") | S36: =IFERROR(subQ!S28/subQ!N28-1,"") | T36: =IFERROR(subQ!T28/subQ!O28-1,"") | V36: =IFERROR(subQ!V28/subQ!Q28-1,"") | W36: =IFERROR(subQ!W28/subQ!R28-1,"") | X36: =IFERROR(subQ!X28/subQ!S28-1,"") | Y36: =IFERROR(subQ!Y28/subQ!T28-1,"") | AA36: =IFERROR(subQ!AA28/subQ!V28-1,"") | AB36: =IFERROR(subQ!AB28/subQ!W28-1,"") | AC36: -0.3777764 | AD36: 1.5613253 | AF36: 3.4513343 | AG36: -0.70565623 | AH36: 0 | AI36: 0 | AK36: 0 | AL36: 0 | AM36: 0 | AN36: 0
A37: drv:영업활동현금흐름 | B37: yoy | C37: 영업활동현금흐름 YoY | J37: =IFERROR(subQ!J29/subQ!E29-1,"") | L37: =IFERROR(subQ!L29/subQ!G29-1,"") | M37: =IFERROR(subQ!M29/subQ!H29-1,"") | N37: =IFERROR(subQ!N29/subQ!I29-1,"") | O37: =IFERROR(subQ!O29/subQ!J29-1,"") | Q37: =IFERROR(subQ!Q29/subQ!L29-1,"") | R37: =IFERROR(subQ!R29/subQ!M29-1,"") | S37: =IFERROR(subQ!S29/subQ!N29-1,"") | T37: =IFERROR(subQ!T29/subQ!O29-1,"") | V37: =IFERROR(subQ!V29/subQ!Q29-1,"") | W37: =IFERROR(subQ!W29/subQ!R29-1,"") | X37: =IFERROR(subQ!X29/subQ!S29-1,"") | Y37: =IFERROR(subQ!Y29/subQ!T29-1,"") | AA37: =IFERROR(subQ!AA29/subQ!V29-1,"") | AB37: =IFERROR(subQ!AB29/subQ!W29-1,"")
A38: drv:주식수 | B38: qoq | C38: 주식수 QoQ | G38: =IFERROR(subQ!G30/subQ!E30-1,"") | H38: =IFERROR(subQ!H30/subQ!G30-1,"") | I38: =IFERROR(subQ!I30/subQ!H30-1,"") | J38: =IFERROR(subQ!J30/subQ!I30-1,"") | L38: =IFERROR(subQ!L30/subQ!J30-1,"") | M38: =IFERROR(subQ!M30/subQ!L30-1,"") | N38: =IFERROR(subQ!N30/subQ!M30-1,"") | O38: =IFERROR(subQ!O30/subQ!N30-1,"") | Q38: =IFERROR(subQ!Q30/subQ!O30-1,"") | R38: =IFERROR(subQ!R30/subQ!Q30-1,"") | S38: =IFERROR(subQ!S30/subQ!R30-1,"") | T38: =IFERROR(subQ!T30/subQ!S30-1,"") | V38: =IFERROR(subQ!V30/subQ!T30-1,"") | W38: =IFERROR(subQ!W30/subQ!V30-1,"") | X38: =IFERROR(subQ!X30/subQ!W30-1,"") | Y38: =IFERROR(subQ!Y30/subQ!X30-1,"") | AA38: =IFERROR(subQ!AA30/subQ!Y30-1,"") | AB38: =IFERROR(subQ!AB30/subQ!AA30-1,"") | AC38: 0 | AD38: 0 | AF38: 0 | AG38: 0 | AH38: 0 | AI38: 0 | AK38: 0 | AL38: 0 | AM38: 0 | AN38: 0
A39: drv:DPS | B39: abs | C39: DPS (가정, 원) | E39: =subQ!E33 | F39: =subQ!F33 | G39: =subQ!G33 | H39: =subQ!H33 | I39: =subQ!I33 | J39: =subQ!J33 | K39: =subQ!K33 | L39: =subQ!L33 | ... AB39: =subQ!AB33 | AD39: 0 | AE39: =subQ!AE33 | AI39: 0 | AJ39: =subQ!AJ33 | AN39: 0 | AO39: =subQ!AO33
B41: 3. 밸류에이션·스칼라 | C41: 노란 셀 = 가정. '연결' 표시는 추정 전 분기 수식이 이 셀을 참조한다는 뜻
A42: sc:종가 | C42: 종가 | D42: 2500 | E42: 원 — 네이버 정규장 종가(aik 확정종가 대조 · aik 2,560원)
A43: sc:기준일 | C43: 기준일 | D43: 20261014 | E43: 종가 기준일
A44: sc:COE | C44: COE | D44: 0.09 | E44: 자기자본비용(가정) — TP 적정 PBR = ROE/COE
A45: sc:PER_lo | C45: PER_lo | D45: 16.6 | E45: PER 밴드 하단(배) — hist_quarterly(분기 평균가 ÷ TTM EPS, 12분기, 25/50/75 백분위)
A46: sc:PER_mid | C46: PER_mid | D46: 21 | E46: PER 밴드 중단(배)
A47: sc:PER_hi | C47: PER_hi | D47: 28.8 | E47: PER 밴드 상단(배)
A48: sc:EPS_Y1가중 | C48: EPS_Y1가중 | D48: 0.5 | E48: 12M fwd EPS = FY(last_actual연도)E × w + FY+1E × (1−w) — 기준 분기 2Q 이면 0.5(가정)
A49: sc:세율 | C49: 세율 | D49: 0.225 | E49: 연결 — 법인세 = MAX(세전,0) × 세율(역산, 재현 오차 ≤ 0.05억 · 모델 assumptions 0.22) · 최근 12분기 유효세율 -2.4% 가 5~27% 밖; 세전 > 0 분기 중위 1.0% 도 5~27% 밖 → 법정세율 근사 22% 가정
A50: sc:판관비율 | C50: 판관비율 | D50: 0.048619904 | E50: 연결 — 판관비 = 매출액 × 판관비율(역산, 재현 오차 ≤ 0.05억 · 모델 assumptions 0.0486)
A51: sc:지배주주비중 | C51: 지배주주비중 | D51: 1 | E51: 연결 — 지배주주순이익 = 당기순이익 × 비중(역산, 재현 오차 ≤ 0.05억)
A52: sc:이자율_자산 | C52: 이자율_자산 | D52: 3.0470438e-13 | E52: 연결 — 이자손익 = (전분기 이자발생자산 × 자산이자율 − 전분기 총차입금 × 부채이자율)/4(역산, 재현 오차 ≤ 0.05억 · 모델 assumptions 0.003)
A53: sc:이자율_부채 | C53: 이자율_부채 | D53: 0.035773435 | E53: 연결 — 같은 수식의 부채 쪽(총차입금 행이 없으면 0)(역산, 재현 오차 ≤ 0.05억 · 모델 assumptions 0.0361)
A54: sc:배당성향 | C54: 배당성향 | E54: 배당성향(참고 — 모델은 직전 DPS 유지·Q2 지급 가정)
A55: sc:외화순노출_백만$ | C55: 외화순노출_백만$ | E55: 외화 순노출 × Δ기말환율 (외화 시트 방식) — 외화 순노출 미공시(face) → 0 + 표기
A56: sc:헤지비율 | C56: 헤지비율 | E56: sls 없음
A57: sc:헤지환율_약정 | C57: 헤지환율_약정 | E57: sls 없음

Sheet BS연결
B1: (백만원) | C1: 이름: BS연결H | E1: 4Q21 | F1: 2021 | G1: 1Q22 | H1: 2Q22 | I1: 3Q22 | J1: 4Q22 | K1: 2022 | L1: 1Q23 | M1: 2Q23 | N1: 3Q23 | O1: 4Q23 | P1: 2023 | Q1: 1Q24 | R1: 2Q24 | S1: 3Q24 | T1: 4Q24 | U1: 2024 | V1: 1Q25 | W1: 2Q25 | X1: 3Q25 | Y1: 4Q25 | Z1: 2025 | AA1: 1Q26 | AB1: 2Q26 | AC1: 3Q26 | AD1: 4Q26 | AE1: 2026 | AF1: 1Q27 | AG1: 2Q27 | AH1: 3Q27 | AI1: 4Q27 | AJ1: 2027 | AK1: 1Q28 | AL1: 2Q28 | AM1: 3Q28 | AN1: 4Q28 | AO1: 2028
B2: 연결 | D2: fin json(kship_fin.py)
B3: 한국주강(연) | C3: UPDATE: 26-10-14 | E3: 1 | F3: 2 | G3: 3 | H3: 4 | I3: 5 | J3: 6 | K3: 7 | L3: 8 | M3: 9 | N3: 10 | O3: 11 | P3: 12 | Q3: 13 | R3: 14 | S3: 15 | T3: 16 | U3: 17 | V3: 18 | W3: 19 | X3: 20 | Y3: 21 | Z3: 22 | AA3: 23 | AB3: 24 | AC3: 25 | AD3: 26 | AE3: 27 | AF3: 28 | AG3: 29 | AH3: 30 | AI3: 31 | AJ3: 32 | AK3: 33 | AL3: 34 | AM3: 35 | AN3: 36 | AO3: 37
B4: Account Code | C4: AccountNAME | E4: 2021.12 | F4: 2021.12A | G4: 2022.03 | H4: 2022.06 | I4: 2022.09 | J4: 2022.12 | K4: 2022.12A | L4: 2023.03 | M4: 2023.06 | N4: 2023.09 | O4: 2023.12 | P4: 2023.12A | Q4: 2024.03 | R4: 2024.06 | S4: 2024.09 | T4: 2024.12 | U4: 2024.12A | V4: 2025.03 | W4: 2025.06 | X4: 2025.09 | Y4: 2025.12 | Z4: 2025.12A | AA4: 2026.03 | AB4: 2026.06 | AC4: 2026.09 | AD4: 2026.12 | AE4: 2026.12A | AF4: 2027.03 | AG4: 2027.06 | AH4: 2027.09 | AI4: 2027.12 | AJ4: 2027.12A | AK4: 2028.03 | AL4: 2028.06 | AM4: 2028.09 | AN4: 2028.12 | AO4: 2028.12A

Sheet BS별도
B1: (백만원) | C1: 이름: BS별도H | E1: 4Q21 | F1: 2021 | G1: 1Q22 | H1: 2Q22 | I1: 3Q22 | J1: 4Q22 | K1: 2022 | L1: 1Q23 | M1: 2Q23 | N1: 3Q23 | O1: 4Q23 | P1: 2023 | Q1: 1Q24 | R1: 2Q24 | S1: 3Q24 | T1: 4Q24 | U1: 2024 | V1: 1Q25 | W1: 2Q25 | X1: 3Q25 | Y1: 4Q25 | Z1: 2025 | AA1: 1Q26 | AB1: 2Q26 | AC1: 3Q26 | AD1: 4Q26 | AE1: 2026 | AF1: 1Q27 | AG1: 2Q27 | AH1: 3Q27 | AI1: 4Q27 | AJ1: 2027 | AK1: 1Q28 | AL1: 2Q28 | AM1: 3Q28 | AN1: 4Q28 | AO1: 2028
B2: 별도 | D2: fin json(kship_fin.py)
B3: 한국주강(별) | C3: UPDATE: 26-10-14 | E3: 1 | F3: 2 | G3: 3 | H3: 4 | I3: 5 | J3: 6 | K3: 7 | L3: 8 | M3: 9 | N3: 10 | O3: 11 | P3: 12 | Q3: 13 | R3: 14 | S3: 15 | T3: 16 | U3: 17 | V3: 18 | W3: 19 | X3: 20 | Y3: 21 | Z3: 22 | AA3: 23 | AB3: 24 | AC3: 25 | AD3: 26 | AE3: 27 | AF3: 28 | AG3: 29 | AH3: 30 | AI3: 31 | AJ3: 32 | AK3: 33 | AL3: 34 | AM3: 35 | AN3: 36 | AO3: 37
B4: Account Code | C4: AccountNAME | E4: 2021.12 | F4: 2021.12A | G4: 2022.03 | H4: 2022.06 | I4: 2022.09 | J4: 2022.12 | K4: 2022.12A | L4: 2023.03 | M4: 2023.06 | N4: 2023.09 | O4: 2023.12 | P4: 2023.12A | Q4: 2024.03 | R4: 2024.06 | S4: 2024.09 | T4: 2024.12 | U4: 2024.12A | V4: 2025.03 | W4: 2025.06 | X4: 2025.09 | Y4: 2025.12 | Z4: 2025.12A | AA4: 2026.03 | AB4: 2026.06 | AC4: 2026.09 | AD4: 2026.12 | AE4: 2026.12A | AF4: 2027.03 | AG4: 2027.06 | AH4: 2027.09 | AI4: 2027.12 | AJ4: 2027.12A | AK4: 2028.03 | AL4: 2028.06 | AM4: 2028.09 | AN4: 2028.12 | AO4: 2028.12A
A5: 1 | C5: 유동자산 | E5: 19645.63 | F5: 19645.63 | G5: 22931.95 | H5: 22828.71 | I5: 19870.34 | J5: 19844.24 | K5: 19844.24 | L5: 18645.58 | M5: 17736.31 | N5: 17885.42 | O5: 15572.79 | P5: 15572.79 | Q5: 14976.06 | R5: 15130.63 | S5: 13951.38 | T5: 12638.31 | U5: 12638.31 | V5: 12547.46 | W5: 11618.59 | X5: 11929.24 | Y5: 10043.6 | Z5: 10043.6 | AA5: 13996.42 | AB5: 14320.99
A6: 1 | C6: 현금및현금성자산 | E6: 65.03 | F6: 65.03 | G6: 737.38 | H6: 154.42 | I6: 377.37 | J6: 280.39 | K6: 280.39 | L6: 439.97 | M6: 384.23 | N6: 79.82 | O6: 1372.91 | P6: 1372.91 | Q6: 1625.64 | R6: 98.54 | S6: 1057.16 | T6: 1046.79 | U6: 1046.79 | V6: 155.94 | W6: 11.57 | X6: 101.11 | Y6: 420.12 | Z6: 420.12 | AA6: 14.36 | AB6: 264.11
A7: 1 | C7: 단기금융상품 | E7: 3000 | F7: 3000 | G7: 3000 | H7: 3000 | I7: 3000 | J7: 3456.01 | K7: 3456.01 | L7: 459.47 | M7: 0 | N7: 0 | O7: 0 | P7: 0 | Q7: 500 | R7: 2000 | S7: 1500 | T7: 500 | U7: 500 | V7: 500 | W7: 0 | X7: 0 | Y7: 0 | Z7: 0 | AA7: 0 | AB7: 0
A8: 1 | C8: 단기금융자산 | E8: 3000 | F8: 3000 | G8: 3000 | H8: 3000 | I8: 3000 | J8: 3456.01 | K8: 3456.01 | L8: 459.47 | M8: 0 | N8: 0 | O8: 0 | P8: 0 | Q8: 500 | R8: 2000 | S8: 1500 | T8: 500 | U8: 500 | V8: 500 | W8: 0 | X8: 0 | Y8: 0 | Z8: 0 | AA8: 0 | AB8: 0
A9: 1 | C9: 매출채권및기타채권 | E9: 9529.65 | F9: 9529.65 | G9: 9760.39 | H9: 9554.88 | I9: 6619.81 | J9: 7587.65 | K9: 7587.65 | L9: 7381.91 | M9: 5265.44 | N9: 7121.86 | O9: 7349.03 | P9: 7349.03 | Q9: 6242.03 | R9: 6195.95 | S9: 3831.77 | T9: 5125.8 | U9: 5125.8 | V9: 4532.29 | W9: 4220.87 | X9: 4063.69 | Y9: 1611.99 | Z9: 1611.99 | AA9: 3597.46 | AB9: 3463.49
A10: 1 | C10: 재고자산 | E10: 6832.02 | F10: 6832.02 | G10: 8271.7 | H10: 10027.89 | I10: 9810.5 | J10: 8385.32 | K10: 8385.32 | L10: 9919.93 | M10: 11741.47 | N10: 10387.04 | O10: 6588.36 | P10: 6588.36 | Q10: 6467.87 | R10: 6668.86 | S10: 7130.5 | T10: 5925.59 | U10: 5925.59 | V10: 7287.1 | W10: 7313.98 | X10: 7636.83 | Y10: 7871.67 | Z10: 7871.67 | AA10: 10230.91 | AB10: 10488.31
A11: 1 | C11: 기타유동자산 | E11: 156.74 | F11: 156.74 | G11: 113.34 | H11: 60.81 | I11: 26.74 | J11: 43.39 | K11: 43.39 | L11: 365.64 | M11: 344.17 | N11: 294.38 | O11: 200.52 | P11: 200.52 | Q11: 77.12 | R11: 105.02 | S11: 135.78 | T11: 9.39 | U11: 9.39 | V11: 38.01 | W11: 59.41 | X11: 116.22 | Y11: 130.51 | Z11: 130.51 | AA11: 147.58 | AB11: 104.99
A12: 1 | C12: 비유동자산 | E12: 30549.15 | F12: 30549.15 | G12: 30171.65 | H12: 29449.18 | I12: 29088.47 | J12: 28200.98 | K12: 28200.98 | L12: 31115.79 | M12: 30620.5 | N12: 28724.33 | O12: 28614.14 | P12: 28614.14 | Q12: 28774.93 | R12: 28462.44 | S12: 28733.04 | T12: 28860.06 | U12: 28860.06 | V12: 28332.37 | W12: 27935.44 | X12: 28400.01 | Y12: 28263.21 | Z12: 28263.21 | AA12: 28723.52 | AB12: 29039.8
A13: 1 | C13: 장기금융자산 | E13: 1100.26 | F13: 1100.26 | G13: 1123.69 | H13: 802.42 | I13: 810.37 | J13: 362.62 | K13: 362.62 | L13: 367.63 | M13: 1.33 | N13: 0.44 | O13: 6.46 | P13: 6.46 | Q13: 13.43 | R13: 20.44 | S13: 28.37 | T13: 39.97 | U13: 39.97 | V13: 51.83 | W13: 63.85 | X13: 76.3 | Y13: 88.81 | Z13: 88.81 | AA13: 101.38 | AB13: 113.99
A14: 1 | C14: 투자자산 | E14: 1100.26 | F14: 1100.26 | G14: 1123.69 | H14: 802.42 | I14: 810.37 | J14: 362.62 | K14: 362.62 | L14: 367.63 | M14: 1.33 | N14: 0.44 | O14: 6.46 | P14: 6.46 | Q14: 13.43 | R14: 20.44 | S14: 28.37 | T14: 39.97 | U14: 39.97 | V14: 51.83 | W14: 63.85 | X14: 76.3 | Y14: 88.81 | Z14: 88.81 | AA14: 101.38 | AB14: 113.99
A15: 1 | C15: 투자부동산 | E15: 1927.84 | F15: 1927.84 | G15: 1910.87 | H15: 1893.89 | I15: 1876.92 | J15: 5034.69 | K15: 5034.69 | L15: 5017.71 | M15: 5000.74 | N15: 4983.76 | O15: 4966.79 | P15: 4966.79 | Q15: 4949.81 | R15: 4932.84 | S15: 4915.86 | T15: 4898.89 | U15: 4898.89 | V15: 4881.91 | W15: 4864.94 | X15: 4895.16 | Y15: 4877.77 | Z15: 4877.77 | AA15: 4860.39 | AB15: 4843
A16: 1 | C16: 유형자산 | E16: 25428.81 | F16: 25428.81 | G16: 25062.96 | H16: 24696.83 | I16: 24309.93 | J16: 20824.75 | K16: 20824.75 | L16: 20791.57 | M16: 20673.97 | N16: 20458.68 | O16: 20450.46 | P16: 20450.46 | Q16: 20453.75 | R16: 20508.36 | S16: 20348.88 | T16: 20324.77 | U16: 20324.77 | V16: 20305.71 | W16: 20175.24 | X16: 20512.36 | Y16: 20452.36 | Z16: 20452.36 | AA16: 20351.92 | AB16: 21522.69
... A27: 1 | C27: 비유동부채 | E27: 1944.33 | F27: 1944.33 | G27: 6295.67 | H27: 6317.23 | I27: 5788.29 | J27: 5486.13 | K27: 5486.13 | L27: 5534.82 | M27: 6146.57 | N27: 5787.93 | O27: 5107.64 | P27: 5107.64 | Q27: 734.42 | R27: 773.54 | S27: 866.72 | T27: 642.29 | U27: 642.29 | V27: 721.96 | W27: 683.16 | X27: 704.6 | Y27: 518.33 | Z27: 518.33 | AA27: 487.49 | AB27: 323.02
A28: 1 | C28: 장기차입금 | E28: 800 | F28: 800 | G28: 5200 | H28: 5200 | I28: 4700 | J28: 4400 | K28: 4400 | L28: 4400 | M28: 4400 | N28: 4400 | O28: 4400 | P28: 4400 | Q28: 0 | R28: 0 | S28: 0 | T28: 0 | U28: 0 | Y28: 0 | Z28: 0
A29: 1 | C29: 비유동리스부채 | E29: 324.52 | F29: 324.52 | G29: 312.62 | H29: 312.34 | I29: 323.47 | J29: 310.05 | K29: 310.05 | L29: 296.33 | M29: 399.44 | N29: 399.79 | O29: 375.52 | P29: 375.52 | Q29: 357.41 | R29: 325.28 | S29: 302.68 | T29: 281.29 | U29: 281.29 | V29: 259.39 | W29: 236.98 | X29: 247 | Y29: 279.95 | Z29: 279.95 | AA29: 257.12 | AB29: 102.71
A30: 1 | C30: 장기금융부채 | E30: 324.52 | F30: 324.52 | G30: 312.62 | H30: 312.34 | I30: 323.47 | J30: 310.05 | K30: 310.05 | L30: 296.33 | M30: 399.44 | N30: 399.79 | O30: 375.52 | P30: 375.52 | Q30: 357.41 | R30: 325.28 | S30: 302.68 | T30: 281.29 | U30: 281.29 | V30: 259.39 | W30: 236.98 | X30: 247 | Y30: 279.95 | Z30: 279.95 | AA30: 257.12 | AB30: 102.71
A31: 1 | C31: 확정급여부채 | E31: 819.81 | F31: 819.81 | G31: 783.05 | H31: 804.89 | I31: 764.82 | J31: 776.08 | K31: 776.08 | L31: 838.49 | M31: 767.17 | N31: 758.78 | O31: 324.73 | P31: 324.73 | Q31: 369.62 | R31: 440.88 | S31: 519.82 | T31: 288.17 | U31: 288.17 | V31: 389.74 | W31: 446.18 | X31: 457.6 | Y31: 238.38 | Z31: 238.38 | AA31: 230.37 | AB31: 220.31
A32: 1 | C32: 부채총계 | E32: 22132.88 | F32: 22132.88 | G32: 23014.3 | H32: 22202.98 | I32: 19112.3 | J32: 18273.22 | K32: 18273.22 | L32: 16941.12 | M32: 15801.91 | N32: 14141.48 | O32: 11207.43 | P32: 11207.43 | Q32: 10590.17 | R32: 10582.19 | S32: 9670.09 | T32: 7363.07 | U32: 7363.07 | V32: 7165.98 | W32: 5667.47 | X32: 6689.54 | Y32: 5025.88 | Z32: 5025.88 | AA32: 8763.54 | AB32: 9917.15
A33: 1 | C33: 자본금 | E33: 5654.63 | F33: 5654.63 | G33: 5654.63 | H33: 5654.63 | I33: 5654.63 | J33: 5654.63 | K33: 5654.63 | L33: 5654.63 | M33: 5654.63 | N33: 5654.63 | O33: 5654.63 | P33: 5654.63 | Q33: 5654.63 | R33: 5654.63 | S33: 5654.63 | T33: 5654.63 | U33: 5654.63 | V33: 5654.63 | W33: 5654.63 | X33: 5654.63 | Y33: 5654.63 | Z33: 5654.63 | AA33: 5654.63 | AB33: 5654.63
A34: 1 | C34: 자본잉여금 | E34: 4409.7 | F34: 4409.7 | G34: 4409.7 | H34: 4409.7 | I34: 4409.7 | J34: 4409.7 | K34: 4409.7 | L34: 4409.7 | M34: 4409.7 | N34: 4409.7 | O34: 4409.7 | P34: 4409.7 | Q34: 4409.7 | R34: 4409.7 | S34: 4409.7 | T34: 4409.7 | U34: 4409.7 | V34: 4409.7 | W34: 4409.7 | X34: 4409.7 | Y34: 4409.7 | Z34: 4409.7 | AA34: 4409.7 | AB34: 4409.7
A35: 1 | C35: 기타자본 | E35: -922.91 | F35: -922.91 | G35: -922.91 | H35: -922.91 | I35: -922.91 | J35: -922.91 | K35: -922.91 | L35: -922.91 | M35: -922.91 | N35: -922.91 | O35: -922.91 | P35: -922.91 | Q35: -922.91 | R35: -922.91 | S35: -922.91 | T35: -922.91 | U35: -922.91 | V35: -922.91 | W35: -922.91 | X35: -922.91 | Y35: -922.91 | Z35: -922.91 | AA35: -922.91 | AB35: 0
A36: 1 | C36: 기타포괄이익누계액 | E36: -914.76 | F36: -914.76 | G36: -914.76 | H36: -914.76 | I36: -914.76 | J36: -1009.36 | K36: -1009.36 | L36: 1968.34 | M36: 1278.38 | N36: -48.53 | O36: -125.4 | P36: -125.4 | Q36: 67.1 | R36: -213.84 | S36: 155.95 | T36: 299.51 | U36: 299.51 | V36: -178.99 | W36: -266.05 | X36: -222.55 | Y36: -305.25 | Z36: -305.25 | AA36: 288.75 | AB36: -393.25
A37: 1 | C37: 이익잉여금 | E37: 19835.24 | F37: 19835.24 | G37: 21862.64 | H37: 21848.25 | I37: 21619.85 | J37: 21639.94 | K37: 21639.94 | L37: 21710.5 | M37: 22135.1 | N37: 23375.37 | O37: 23963.49 | P37: 23963.49 | Q37: 23952.31 | R37: 24083.3 | S37: 23716.96 | T37: 24694.36 | U37: 24694.36 | V37: 24751.41 | W37: 25011.19 | X37: 24720.84 | Y37: 24444.77 | Z37: 24444.77 | AA37: 24526.23 | AB37: 23772.56
A38: 1 | C38: 자본총계 | E38: 28061.9 | F38: 28061.9 | G38: 30089.3 | H38: 30074.91 | I38: 29846.51 | J38: 29772.01 | K38: 29772.01 | L38: 32820.26 | M38: 32554.9 | N38: 32468.26 | O38: 32979.51 | P38: 32979.51 | Q38: 33160.83 | R38: 33010.88 | S38: 33014.33 | T38: 34135.29 | U38: 34135.29 | V38: 33713.85 | W38: 33886.56 | X38: 33639.72 | Y38: 33280.94 | Z38: 33280.94 | AA38: 33956.4 | AB38: 33443.64
A39: 1 | C39: 부채와자본총계 | E39: 50194.78 | F39: 50194.78 | G39: 53103.6 | H39: 52277.89 | I39: 48958.81 | J39: 48045.22 | K39: 48045.22 | L39: 49761.38 | M39: 48356.81 | N39: 46609.75 | O39: 44186.93 | P39: 44186.93 | Q39: 43751 | R39: 43593.07 | S39: 42684.42 | T39: 41498.37 | U39: 41498.37 | V39: 40879.83 | W39: 39554.03 | X39: 40329.26 | Y39: 38306.81 | Z39: 38306.81 | AA39: 42719.94 | AB39: 43360.79
A40: 1 | C40: 지배주주지분 | E40: 28061.9 | F40: 28061.9 | G40: 30089.3 | H40: 30074.91 | I40: 29846.51 | J40: 29772.01 | K40: 29772.01 | L40: 32820.26 | M40: 32554.9 | N40: 32468.26 | O40: 32979.51 | P40: 32979.51 | Q40: 33160.83 | R40: 33010.88 | S40: 33014.33 | T40: 34135.29 | U40: 34135.29 | V40: 33713.85 | W40: 33886.56 | X40: 33639.72 | Y40: 33280.94 | Z40: 33280.94 | AA40: 33956.4 | AB40: 33443.64
... A43: 1 | C43: 이자발생자산 | E43: 4165.29 | F43: 4165.29 | G43: 4861.07 | H43: 3956.84 | I43: 4187.74 | J43: 4099.02 | K43: 4099.02 | L43: 1267.07 | M43: 385.56 | N43: 80.26 | O43: 1379.37 | P43: 1379.37 | Q43: 2139.07 | R43: 2118.98 | S43: 2585.53 | T43: 1586.76 | U43: 1586.76 | V43: 707.77 | W43: 75.42 | X43: 177.41 | Y43: 508.93 | Z43: 508.93 | AA43: 115.74 | AB43: 378.1
A44: 1 | C44: 유동성장기부채 | I44: 500 | J44: 800 | K44: 800 | L44: 800 | M44: 300 | N44: 300 | O44: 0 | P44: 0 | Q44: 4400 | R44: 4000 | S44: 2500 | T44: 1000 | U44: 1000 | V44: 0 | W44: 0 | X44: 0 | Y44: 0 | Z44: 0 | AA44: 0 | AB44: 0
A45: 1 | C45: 당기법인세자산(선급법인세) | L45: 0
A46: 1 | C46: 이연법인세부채 | M46: 579.96 | N46: 229.36 | O46: 7.38 | P46: 7.38 | Q46: 7.38 | R46: 7.38 | S46: 44.22 | T46: 72.83 | U46: 72.83 | V46: 72.83 | W46: 0 | X46: 0 | Y46: 0 | Z46: 0 | AA46: 0 | AB46: 0
A47: 1 | C47: 당기법인세부채(미지급법인세) | Q47: 0.62 | R47: 0 | S47: -3.26 | T47: 8.69 | U47: 8.69 | V47: 1.09 | W47: 5.45 | X47: 0 | Y47: 0 | Z47: 0 | AA47: 0 | AB47: 0
A48: 1 | C48: 단기파생상품부채 | T48: 18.74 | U48: 18.74 | V48: 0 | W48: 0 | X48: 0 | Y48: 0 | Z48: 0 | AA48: 0 | AB48: 0
A49: 1 | C49: 매출액(수익) | E49: 13539.08 | G49: 13295.39 | H49: 13675.13 | I49: 11800.98 | J49: 15599.61 | K49: 54371.11 | L49: 12447.67 | M49: 11473.4 | N49: 13682.34 | O49: 16207.82 | P49: 53811.23 | Q49: 11670.52 | R49: 11863.49 | S49: 9950.07 | T49: 13799.66 | U49: 47283.74 | V49: 9423.76 | W49: 11673.15 | X49: 9776.72 | Y49: 8998.65 | Z49: 39872.28 | AA49: 8826.41 | AB49: 11075.81
A50: 1 | C50: 매출원가 | E50: 13479.8 | G50: 13324.39 | H50: 13030.46 | I50: 11361.06 | J50: 14756.26 | K50: 52472.17 | L50: 11622.53 | M50: 10398.59 | N50: 12182.33 | O50: 15007.37 | P50: 49210.82 | Q50: 11083.31 | R50: 10962.74 | S50: 9743.61 | T50: 12176.45 | U50: 43966.11 | V50: 8797.89 | W50: 10816.16 | X50: 9646.74 | Y50: 8822.51 | Z50: 38083.3 | AA50: 8311.54 | AB50: 10445.85
A51: 1 | C51: 매출총이익 | E51: 59.29 | G51: -29.01 | H51: 644.67 | I51: 439.92 | J51: 843.34 | K51: 1898.92 | L51: 825.14 | M51: 1074.82 | N51: 1500 | O51: 1200.45 | P51: 4600.41 | Q51: 587.21 | R51: 900.75 | S51: 206.46 | T51: 1623.22 | U51: 3317.64 | V51: 625.88 | W51: 856.99 | X51: 129.97 | Y51: 176.14 | Z51: 1788.98 | AA51: 514.88 | AB51: 629.95
A52: 1 | C52: 판관비 | E52: 478.32 | G52: 654.77 | H52: 578.68 | I52: 560.02 | J52: 623.11 | K52: 2416.58 | L52: 566.99 | M52: 504.33 | N52: 580.31 | O52: 530.3 | P52: 2181.93 | Q52: 525.21 | R52: 581.22 | S52: 521.2 | T52: 615.04 | U52: 2242.67 | V52: 551.52 | W52: 502.65 | X52: 457.07 | Y52: 454.41 | Z52: 1965.65 | AA52: 455.94 | AB52: 477.17
A53: 1 | C53: 영업이익 | E53: -419.03 | G53: -683.78 | H53: 65.99 | I53: -120.1 | J53: 220.23 | K53: -517.66 | L53: 258.15 | M53: 570.49 | N53: 919.69 | O53: 670.15 | P53: 2418.48 | Q53: 61.99 | R53: 319.53 | S53: -314.74 | T53: 1008.18 | U53: 1074.96 | V53: 74.36 | W53: 354.34 | X53: -327.1 | Y53: -278.28 | Z53: -176.68 | AA53: 58.93 | AB53: 152.78
A54: 1 | C54: 금융수익 | E54: 14.96 | G54: 15.5 | H54: 22.17 | I54: 23.76 | J54: 22.31 | K54: 83.74 | L54: 18.8 | M54: 11.43 | N54: 0.37 | O54: 35.5 | P54: 66.1 | Q54: 3.71 | R54: 21.17 | S54: 17.19 | T54: 43.63 | U54: 85.7 | V54: 7.98 | W54: 1.32 | X54: 0.53 | Y54: 0.09 | Z54: 9.92 | AA54: 0.32 | AB54: 0.27
A55: 1 | C55: 금융비용 | E55: 94.26 | G55: 89.11 | H55: 144.95 | I55: 103.57 | J55: 139.24 | K55: 476.87 | L55: 143.13 | M55: 117.71 | N55: 110.79 | O55: 106.19 | P55: 477.82 | Q55: 93.67 | R55: 86.11 | S55: 69.32 | T55: 64.6 | U55: 313.7 | V55: 26.1 | W55: 24.45 | X55: 18.05 | Y55: 23.64 | Z55: 92.24 | AA55: 31.02 | AB55: 56.17
A56: 1 | C56: 종속기업,공동지배기업및관계기업관련손익 | E56: 0 | I56: 0 | J56: 0
A57: 1 | C57: 기타영업외손익 | E57: -56.25 | G57: 2754.89 | H57: 14.14 | I57: -49.07 | J57: -87.71 | K57: 2632.25 | L57: -21.17 | M57: -40.87 | N57: 444.58 | O57: -100.9 | P57: 281.64 | Q57: -8.75 | R57: -29.59 | S57: -44.04 | T57: 7.07 | U57: -75.31 | V57: 41.98 | W57: 9.03 | X57: -2.7 | Y57: 0.7 | Z57: 49.01 | AA57: -13.52 | AB57: 33.43
A58: 1 | C58: 법인세비용차감전계속사업이익 | E58: -554.59 | G58: 1997.49 | H58: -42.66 | I58: -248.98 | J58: 15.59 | K58: 1721.44 | L58: 112.64 | M58: 423.34 | N58: 1253.85 | O58: 498.57 | P58: 2288.4 | Q58: -36.72 | R58: 225 | S58: -410.91 | T58: 994.28 | U58: 771.65 | V58: 98.22 | W58: 340.24 | X58: -347.32 | Y58: -301.12 | Z58: -209.98 | AA58: 14.72 | AB58: 130.31
A59: 1 | C59: 법인세비용 | E59: 0 | G59: 0 | H59: 0 | I59: 0 | J59: 0 | K59: 0 | L59: 0 | M59: 0 | S59: -57.46 | T59: 9.52 | X59: -26.44 | Y59: 14.92
A60: 1 | C60: 당기순이익 | E60: -554.59 | G60: 1997.49 | H60: -42.66 | I60: -248.98 | J60: 15.59 | K60: 1721.44 | L60: 112.64 | M60: 425.39 | N60: 1253.85 | O60: 705.25 | P60: 2497.13 | Q60: -36.72 | R60: 167.54 | S60: -353.45 | T60: 984.76 | U60: 762.13 | V60: 98.22 | W60: 247.35 | X60: -320.88 | Y60: -316.04 | Z60: -291.35 | AA60: 14.72 | AB60: 130.31
A61: 1 | C61: 총포괄손익 | E61: 1146.33 | G61: 2027.4 | H61: -14.39 | I61: -228.4 | J61: -74.5 | K61: 1710.11 | L61: 3048.26 | M61: 316.65 | N61: -86.63 | O61: 511.24 | P61: 3789.52 | Q61: 181.32 | R61: -149.95 | S61: 3.45 | T61: 1120.97 | U61: 1155.79 | V61: -421.44 | W61: 172.71 | X61: -246.84 | Y61: -358.78 | Z61: -854.35 | AA61: 675.47 | AB61: -512.76
A62: 1 | C62: 금융손익 | E62: -79.3 | G62: -73.61 | H62: -122.78 | I62: -79.81 | J62: -116.93 | K62: -393.13 | L62: -124.33 | M62: -106.28 | N62: -110.42 | O62: -70.69 | P62: -411.72 | Q62: -89.96 | R62: -64.94 | S62: -52.13 | T62: -20.97 | U62: -228 | V62: -18.12 | W62: -23.13 | X62: -17.52 | Y62: -23.55 | Z62: -82.32 | AA62: -30.7 | AB62: -55.9
A63: 1 | C63: (지배주주지분)당기순이익 | E63: -554.59 | G63: 1997.49 | H63: -42.66 | I63: -248.98 | J63: 15.59 | K63: 1721.44 | L63: 112.64 | M63: 425.39 | N63: 1253.85 | O63: 705.25 | P63: 2497.13 | Q63: -36.72 | R63: 167.54 | S63: -353.45 | T63: 984.76 | U63: 762.13 | V63: 98.22 | W63: 247.35 | X63: -320.88 | Y63: -316.04 | Z63: -291.35 | AA63: 14.72 | AB63: 130.31
A64: 1 | C64: 계속사업이익 | E64: -554.59 | G64: 1997.49 | H64: -42.66 | I64: -248.98 | J64: 15.59 | K64: 1721.44 | L64: 112.64 | M64: 425.39 | N64: 1253.85 | O64: 705.25 | P64: 2497.13 | Q64: -36.72 | R64: 167.54 | S64: -353.45 | T64: 984.76 | U64: 762.13 | V64: 98.22 | W64: 247.35 | X64: -320.88 | Y64: -316.04 | Z64: -291.35 | AA64: 14.72 | AB64: 130.31
A65: 1 | C65: 이자수익 | G65: 9.15 | H65: 15.89 | I65: 16.12 | J65: 16.05 | K65: 57.21 | L65: 12.73 | M65: 0.04 | N65: 0.37 | O65: 0.14 | P65: 13.28 | Q65: 1.61 | R65: 16.54 | S65: 17.19 | T65: 10.04 | U65: 45.38 | V65: 6.44 | W65: 1.33 | X65: 0.53 | Y65: 0.09 | Z65: 8.39 | AA65: 0.21 | AB65: 0.06
A66: 1 | C66: 이자비용 | G66: 89.11 | H66: 132.13 | I66: 105.51 | J66: 135.06 | K66: 461.81 | L66: 143.13 | M66: 116.34 | N66: 90.8 | O66: 85.15 | P66: 435.42 | Q66: 80.1 | R66: 72.25 | S66: 54.63 | T66: 34.74 | U66: 241.72 | V66: 21.04 | W66: 15.31 | X66: 10.44 | Y66: 16.28 | Z66: 63.07 | AA66: 23.71 | AB66: 47.59
A67: 1 | C67: 이자손익 | G67: -79.96 | H67: -116.24 | I67: -89.39 | J67: -119.01 | K67: -404.6 | L67: -130.4 | M67: -116.3 | N67: -90.43 | O67: -85.01 | P67: -422.14 | Q67: -78.49 | R67: -55.71 | S67: -37.44 | T67: -24.7 | U67: -196.34 | V67: -14.6 | W67: -13.98 | X67: -9.91 | Y67: -16.19 | Z67: -54.68 | AA67: -23.5 | AB67: -47.53
A68: 1 | C68: 외환차익 | M68: 5.52 | N68: 0 | O68: 34.95 | Q68: 1.42 | R68: 5.31 | S68: 0 | T68: 8.71 | U68: 15.44 | V68: 1.49 | W68: 0.04 | X68: 0 | Y68: 0 | Z68: 1.53 | AA68: 0.11 | AB68: 0.21
A69: 1 | C69: 외환차손 | M69: 0.83 | N69: 0.29 | O69: 0.16 | R69: 1.91 | S69: 1.55 | T69: 0 | V69: 0.09 | W69: 1.27 | X69: 0.2 | Y69: 0 | Z69: 1.56 | AB69: 1.32
A70: 1 | C70: 외화환산손실 | M70: 0.54 | N70: -0.54 | Q70: 0.93 | R70: -0.93 | S70: 1.24
A71: 1 | C71: 외화환산이익 | Q71: 0.67 | R71: -0.67 | V71: 0.05 | W71: -0.05
A72: 1 | C72: 파생상품손실 | V72: 0.9 | W72: 0 | X72: 0 | Y72: 0 | Z72: 0.9
A73: 1 | C73: 영업활동으로인한현금흐름 | E73: -2062.42 | G73: -2890.82 | H73: -346.11 | I73: 4045.72 | J73: 802.99 | K73: 1611.78 | L73: -1134.31 | M73: 1851.1 | N73: 558.24 | O73: 2354.57 | P73: 3629.6 | Q73: 964.97 | R73: 1181.27 | S73: 2067.25 | T73: 1263.52 | U73: 5477.01 | V73: -420.3 | W73: 918.64 | X73: -78.62 | Y73: 1605.29 | Z73: 2025.01 | AA73: -3963.94 | AB73: -684.57
A74: 1 | C74: 배당금수취(CF) | E74: 0
A75: 1 | C75: 법인세납부(CF) | E75: 0 | G75: -5.11 | H75: 7.06 | I75: -0.01 | J75: 0 | K75: 1.94 | L75: -9.8 | M75: -2.79 | N75: -0.05 | O75: -0.02 | P75: -12.66 | Q75: -0.15 | R75: -0.7 | S75: -0.69 | T75: -6.66 | U75: -8.2 | V75: -7.9 | W75: -4.03 | X75: -5.51 | Y75: 34.9 | Z75: 17.46 | AA75: -0.03 | AB75: -0.01
A76: 1 | C76: 투자활동으로인한현금흐름 | E76: -275.48 | G76: 2744.14 | H76: 372.68 | I76: -9.46 | J76: -128.19 | K76: 2979.17 | L76: 2827.09 | M76: 644.93 | N76: 413.77 | O76: -284.86 | P76: 3600.93 | Q76: -688.92 | R76: -1785.88 | S76: 416.31 | T76: 746.59 | U76: -1311.9 | V76: -170.79 | W76: 457.47 | X76: -714.38 | Y76: -101.46 | Z76: -529.16 | AA76: -105.19 | AB76: -1385.61
A77: 1 | C77: 유형자산의감소 | E77: 0 | G77: 2773.66 | H77: 66.13 | I77: -0.13 | L77: 0 | M77: 0 | N77: 480 | O77: 0 | P77: 480 | Q77: 11 | R77: 0 | S77: 0 | T77: 38.77 | U77: 49.77 | V77: 26 | W77: 29.8 | X77: 0 | Y77: 7.29 | Z77: 63.09 | AA77: 5 | AB77: 0
A78: 1 | C78: 유형자산의증가 | E78: 264.1 | G78: 12.12 | H78: 21.01 | I78: 6.92 | J78: 120.42 | K78: 160.47 | L78: 170.5 | M78: 186.71 | N78: 46.88 | O78: 265.46 | P78: 669.55 | Q78: 180.3 | R78: 266 | S78: 63.86 | T78: 268.22 | U78: 778.38 | V78: 176.78 | W78: 36.9 | X78: 646.07 | Y78: 156.95 | Z78: 1016.7 | AA78: 90.31 | AB78: 1365.75
A79: 1 | C79: CAPEX | E79: 264.1 | G79: 12.12 | H79: 21.01 | I79: 6.92 | J79: 120.42 | K79: 160.47 | L79: 170.5 | M79: 186.71 | N79: 46.88 | O79: 265.46 | P79: 669.55 | Q79: 180.3 | R79: 266 | S79: 63.86 | T79: 268.22 | U79: 778.38 | V79: 176.78 | W79: 36.9 | X79: 646.07 | Y79: 156.95 | Z79: 1016.7 | AA79: 90.31 | AB79: 1365.75
A80: 1 | C80: 재무활동으로인한현금흐름 | E80: 2187.95 | G80: 819.03 | H80: -609.52 | I80: -3813.32 | J80: -771.78 | K80: -4375.59 | L80: -1533.21 | M80: -2551.43 | N80: -1276.75 | O80: -769.13 | P80: -6130.52 | Q80: -22.39 | R80: -923.41 | S80: -1523.71 | T80: -2024.26 | U80: -4493.77 | V80: -299.83 | W80: -1520.41 | X80: 882.54 | Y80: -1184.83 | Z80: -2122.53 | AA80: 3663.38 | AB80: 2319.93
A81: 1 | C81: 단기차입금의증가 | E81: 2187.95 | G81: 3580.97 | I81: 333.32 | J81: 771.78 | L81: 1533.21 | N81: 4802.08 | V81: 725 | W81: 45 | X81: 3687.24 | Y81: 6227.33 | Z81: 10684.57 | AA81: 9661.55
A82: 1 | C82: 장기차입금의증가 | E82: 0 | G82: 4400 | H82: 0 | I82: 0 | L82: 0 | M82: 0 | N82: 0
A83: 1 | C83: 유동성장기부채의감소 | E83: 0 | G83: 0 | H83: 0 | L83: 0 | M83: 500 | N83: 0 | O83: 300 | P83: 800 | S83: 1500 | T83: 1500 | V83: 1000 | W83: 0 | X83: 0 | Y83: 0 | Z83: 1000 | AA83: 0 | AB83: 0
A84: 1 | C84: 단기차입금의감소 | E84: 0 | I84: 3480 | O84: 5249.09 | Q84: 0 | R84: 500 | S84: 0 | T84: 500 | U84: 1000 | Y84: 7365.21 | AA84: 5969.27
A85: 1 | C85: 장기차입금의감소 | E85: 0
A86: 1 | C86: 현금및현금성자산의증감 | E86: -149.96 | G86: 672.35 | H86: -582.96 | I86: 222.95 | J86: -96.98 | K86: 215.36 | L86: 159.58 | M86: -55.41 | N86: -304.74 | O86: 1300.58 | P86: 1100.01 | Q86: 253.66 | R86: -1528.03 | S86: 959.86 | T86: -14.16 | U86: -328.67 | V86: -890.91 | W86: -144.32 | X86: 89.55 | Y86: 319 | Z86: -626.68 | AA86: -405.75 | AB86: 249.74
A87: 1 | C87: 기말현금및현금성자산 | E87: -149.96 | G87: 737.38 | H87: -582.96 | I87: 222.95 | J87: -96.98 | K87: 280.39 | L87: 439.97 | M87: -55.74 | N87: -304.41 | O87: 1293.09 | P87: 1372.91 | Q87: 1625.64 | R87: -1527.1 | S87: 958.62 | T87: -10.37 | U87: 1046.79 | V87: 155.94 | W87: -144.37 | X87: 89.54 | Y87: 319.01 | Z87: 420.12 | AA87: 14.36 | AB87: 249.75
A88: 1 | C88: 무형자산의증가 | G88: 0
A89: 1 | C89: 리스부채의상환 | N89: 21.68 | O89: 22.12 | Q89: 22.39 | R89: 23.41 | S89: 23.71 | T89: 24.26 | U89: 93.77 | V89: 24.83 | W89: 25.41 | X89: 25.35 | Y89: 27.3 | Z89: 102.89 | AA89: 28.9 | AB89: 25.79
A90: 1 | C90: 이자수취(CF) | O90: 0.14 | Q90: 0.98 | T90: 22.09 | V90: -4.5 | W90: 25.52 | X90: 0.53 | Y90: 0.09 | Z90: 21.64 | AA90: 0.21 | AB90: 0.05

Sheet subQ
A1: YQ | C1: subQ 분기 서브모델(억원, U=100) | E1: 4Q21 | F1: 2021 | G1: 1Q22 | H1: 2Q22 | I1: 3Q22 | J1: 4Q22 | K1: 2022 | L1: 1Q23 | M1: 2Q23 | N1: 3Q23 | O1: 4Q23 | P1: 2023 | Q1: 1Q24 | R1: 2Q24 | S1: 3Q24 | T1: 4Q24 | U1: 2024 | V1: 1Q25 | W1: 2Q25 | X1: 3Q25 | Y1: 4Q25 | Z1: 2025 | AA1: 1Q26 | AB1: 2Q26 | AC1: 3Q26 | AD1: 4Q26 | AE1: 2026 | AF1: 1Q27 | AG1: 2Q27 | AH1: 3Q27 | AI1: 4Q27 | AJ1: 2027 | AK1: 1Q28 | AL1: 2Q28 | AM1: 3Q28 | AN1: 4Q28 | AO1: 2028
A2: A=이름(key) B=그룹 C=단위 D=FnGuide 계정명(VLOOKUP 키). 확정=VLOOKUP(BS), 추정=변수 가정 참조
E3: 1 | F3: 2 | G3: 3 | H3: 4 | I3: 5 | J3: 6 | K3: 7 | L3: 8 | M3: 9 | N3: 10 | O3: 11 | P3: 12 | Q3: 13 | R3: 14 | S3: 15 | T3: 16 | U3: 17 | V3: 18 | W3: 19 | X3: 20 | Y3: 21 | Z3: 22 | AA3: 23 | AB3: 24 | AC3: 25 | AD3: 26 | AE3: 27 | AF3: 28 | AG3: 29 | AH3: 30 | AI3: 31 | AJ3: 32 | AK3: 33 | AL3: 34 | AM3: 35 | AN3: 36 | AO3: 37
E4: 2021.12 | F4: 2021.12A | G4: 2022.03 | H4: 2022.06 | I4: 2022.09 | J4: 2022.12 | K4: 2022.12A | L4: 2023.03 | M4: 2023.06 | N4: 2023.09 | O4: 2023.12 | P4: 2023.12A | Q4: 2024.03 | R4: 2024.06 | S4: 2024.09 | T4: 2024.12 | U4: 2024.12A | V4: 2025.03 | W4: 2025.06 | X4: 2025.09 | Y4: 2025.12 | Z4: 2025.12A | AA4: 2026.03 | AB4: 2026.06 | AC4: 2026.09 | AD4: 2026.12 | AE4: 2026.12A | AF4: 2027.03 | AG4: 2027.06 | AH4: 2027.09 | AI4: 2027.12 | AJ4: 2027.12A | AK4: 2028.03 | AL4: 2028.06 | AM4: 2028.09 | AN4: 2028.12 | AO4: 2028.12A
A5: 매출액 | B5: 손익 | C5: 억원 | D5: 매출액(수익) | E5: =IFERROR(VLOOKUP($D5,BS별도,MATCH(E$1,BS별도H,0),0)/100,"") | G5: =IFERROR(VLOOKUP($D5,BS별도,MATCH(G$1,BS별도H,0),0)/100,"") | H5: =IFERROR(VLOOKUP($D5,BS별도,MATCH(H$1,BS별도H,0),0)/100,"") | I5: =IFERROR(VLOOKUP($D5,BS별도,MATCH(I$1,BS별도H,0),0)/100,"") | J5: =IFERROR(VLOOKUP($D5,BS별도,MATCH(J$1,BS별도H,0),0)/100,"") | K5: =SUM(G5:J5) | L5: =IFERROR(VLOOKUP($D5,BS별도,MATCH(L$1,BS별도H,0),0)/100,"") | M5: =IFERROR(VLOOKUP($D5,BS별도,MATCH(M$1,BS별도H,0),0)/100,"") | N5: =IFERROR(VLOOKUP($D5,BS별도,MATCH(N$1,BS별도H,0),0)/100,"") | O5: =IFERROR(VLOOKUP($D5,BS별도,MATCH(O$1,BS별도H,0),0)/100,"") | P5: =SUM(L5:O5) | Q5: =IFERROR(VLOOKUP($D5,BS별도,MATCH(Q$1,BS별도H,0),0)/100,"") | R5: =IFERROR(VLOOKUP($D5,BS별도,MATCH(R$1,BS별도H,0),0)/100,"") | S5: =IFERROR(VLOOKUP($D5,BS별도,MATCH(S$1,BS별도H,0),0)/100,"") | T5: =IFERROR(VLOOKUP($D5,BS별도,MATCH(T$1,BS별도H,0),0)/100,"") | U5: =SUM(Q5:T5) | V5: =IFERROR(VLOOKUP($D5,BS별도,MATCH(V$1,BS별도H,0),0)/100,"") | W5: =IFERROR(VLOOKUP($D5,BS별도,MATCH(W$1,BS별도H,0),0)/100,"") | X5: =IFERROR(VLOOKUP($D5,BS별도,MATCH(X$1,BS별도H,0),0)/100,"") | Y5: =IFERROR(VLOOKUP($D5,BS별도,MATCH(Y$1,BS별도H,0),0)/100,"") | Z5: =SUM(V5:Y5) | AA5: =IFERROR(VLOOKUP($D5,BS별도,MATCH(AA$1,BS별도H,0),0)/100,"") | AB5: =IFERROR(VLOOKUP($D5,BS별도,MATCH(AB$1,BS별도H,0),0)/100,"") | AC5: =IFERROR(X5*(1+변수!AC21),"") | AD5: =IFERROR(Y5*(1+변수!AD21),"") | AE5: =SUM(AA5:AD5) | AF5: =IFERROR(AA5*(1+변수!AF21),"") | AG5: =IFERROR(AB5*(1+변수!AG21),"") | AH5: =IFERROR(AC5*(1+변수!AH21),"") | AI5: =IFERROR(AD5*(1+변수!AI21),"") | AJ5: =SUM(AF5:AI5) | AK5: =IFERROR(AF5*(1+변수!AK21),"") | AL5: =IFERROR(AG5*(1+변수!AL21),"") | AM5: =IFERROR(AH5*(1+변수!AM21),"") | AN5: =IFERROR(AI5*(1+변수!AN21),"") | AO5: =SUM(AK5:AN5)
A6: 매출원가 | B6: 손익 | C6: 억원 | D6: 매출원가 | E6: =IFERROR(VLOOKUP($D6,BS별도,MATCH(E$1,BS별도H,0),0)/100,"") | G6: =IFERROR(VLOOKUP($D6,BS별도,MATCH(G$1,BS별도H,0),0)/100,"") | H6: =IFERROR(VLOOKUP($D6,BS별도,MATCH(H$1,BS별도H,0),0)/100,"") | I6: =IFERROR(VLOOKUP($D6,BS별도,MATCH(I$1,BS별도H,0),0)/100,"") | J6: =IFERROR(VLOOKUP($D6,BS별도,MATCH(J$1,BS별도H,0),0)/100,"") | K6: =SUM(G6:J6) | L6: =IFERROR(VLOOKUP($D6,BS별도,MATCH(L$1,BS별도H,0),0)/100,"") | M6: =IFERROR(VLOOKUP($D6,BS별도,MATCH(M$1,BS별도H,0),0)/100,"") | N6: =IFERROR(VLOOKUP($D6,BS별도,MATCH(N$1,BS별도H,0),0)/100,"") | O6: =IFERROR(VLOOKUP($D6,BS별도,MATCH(O$1,BS별도H,0),0)/100,"") | P6: =SUM(L6:O6) | Q6: =IFERROR(VLOOKUP($D6,BS별도,MATCH(Q$1,BS별도H,0),0)/100,"") | R6: =IFERROR(VLOOKUP($D6,BS별도,MATCH(R$1,BS별도H,0),0)/100,"") | S6: =IFERROR(VLOOKUP($D6,BS별도,MATCH(S$1,BS별도H,0),0)/100,"") | T6: =IFERROR(VLOOKUP($D6,BS별도,MATCH(T$1,BS별도H,0),0)/100,"") | U6: =SUM(Q6:T6) | V6: =IFERROR(VLOOKUP($D6,BS별도,MATCH(V$1,BS별도H,0),0)/100,"") | W6: =IFERROR(VLOOKUP($D6,BS별도,MATCH(W$1,BS별도H,0),0)/100,"") | X6: =IFERROR(VLOOKUP($D6,BS별도,MATCH(X$1,BS별도H,0),0)/100,"") | Y6: =IFERROR(VLOOKUP($D6,BS별도,MATCH(Y$1,BS별도H,0),0)/100,"") | Z6: =SUM(V6:Y6) | AA6: =IFERROR(VLOOKUP($D6,BS별도,MATCH(AA$1,BS별도H,0),0)/100,"") | AB6: =IFERROR(VLOOKUP($D6,BS별도,MATCH(AB$1,BS별도H,0),0)/100,"") | AC6: =IFERROR(AC5-AC7,"") | AD6: =IFERROR(AD5-AD7,"") | AE6: =SUM(AA6:AD6) | AF6: =IFERROR(AF5-AF7,"") | AG6: =IFERROR(AG5-AG7,"") | AH6: =IFERROR(AH5-AH7,"") | AI6: =IFERROR(AI5-AI7,"") | AJ6: =SUM(AF6:AI6) | AK6: =IFERROR(AK5-AK7,"") | AL6: =IFERROR(AL5-AL7,"") | AM6: =IFERROR(AM5-AM7,"") | AN6: =IFERROR(AN5-AN7,"") | AO6: =SUM(AK6:AN6)
A7: 매출총이익 | B7: 손익 | C7: 억원 | D7: 매출총이익 | E7: =IFERROR(VLOOKUP($D7,BS별도,MATCH(E$1,BS별도H,0),0)/100,"") | G7: =IFERROR(VLOOKUP($D7,BS별도,MATCH(G$1,BS별도H,0),0)/100,"") | H7: =IFERROR(VLOOKUP($D7,BS별도,MATCH(H$1,BS별도H,0),0)/100,"") | I7: =IFERROR(VLOOKUP($D7,BS별도,MATCH(I$1,BS별도H,0),0)/100,"") | J7: =IFERROR(VLOOKUP($D7,BS별도,MATCH(J$1,BS별도H,0),0)/100,"") | K7: =SUM(G7:J7) | L7: =IFERROR(VLOOKUP($D7,BS별도,MATCH(L$1,BS별도H,0),0)/100,"") | M7: =IFERROR(VLOOKUP($D7,BS별도,MATCH(M$1,BS별도H,0),0)/100,"") | N7: =IFERROR(VLOOKUP($D7,BS별도,MATCH(N$1,BS별도H,0),0)/100,"") | O7: =IFERROR(VLOOKUP($D7,BS별도,MATCH(O$1,BS별도H,0),0)/100,"") | P7: =SUM(L7:O7) | Q7: =IFERROR(VLOOKUP($D7,BS별도,MATCH(Q$1,BS별도H,0),0)/100,"") | R7: =IFERROR(VLOOKUP($D7,BS별도,MATCH(R$1,BS별도H,0),0)/100,"") | S7: =IFERROR(VLOOKUP($D7,BS별도,MATCH(S$1,BS별도H,0),0)/100,"") | T7: =IFERROR(VLOOKUP($D7,BS별도,MATCH(T$1,BS별도H,0),0)/100,"") | U7: =SUM(Q7:T7) | V7: =IFERROR(VLOOKUP($D7,BS별도,MATCH(V$1,BS별도H,0),0)/100,"") | W7: =IFERROR(VLOOKUP($D7,BS별도,MATCH(W$1,BS별도H,0),0)/100,"") | X7: =IFERROR(VLOOKUP($D7,BS별도,MATCH(X$1,BS별도H,0),0)/100,"") | Y7: =IFERROR(VLOOKUP($D7,BS별도,MATCH(Y$1,BS별도H,0),0)/100,"") | Z7: =SUM(V7:Y7) | AA7: =IFERROR(VLOOKUP($D7,BS별도,MATCH(AA$1,BS별도H,0),0)/100,"") | AB7: =IFERROR(VLOOKUP($D7,BS별도,MATCH(AB$1,BS별도H,0),0)/100,"") | AC7: =IFERROR(AC9+AC8,"") | AD7: =IFERROR(AD9+AD8,"") | AE7: =SUM(AA7:AD7) | AF7: =IFERROR(AF9+AF8,"") | AG7: =IFERROR(AG9+AG8,"") | AH7: =IFERROR(AH9+AH8,"") | AI7: =IFERROR(AI9+AI8,"") | AJ7: =SUM(AF7:AI7) | AK7: =IFERROR(AK9+AK8,"") | AL7: =IFERROR(AL9+AL8,"") | AM7: =IFERROR(AM9+AM8,"") | AN7: =IFERROR(AN9+AN8,"") | AO7: =SUM(AK7:AN7)
A8: 판관비 | B8: 손익 | C8: 억원 | D8: 판관비 | E8: =IFERROR(VLOOKUP($D8,BS별도,MATCH(E$1,BS별도H,0),0)/100,"") | G8: =IFERROR(VLOOKUP($D8,BS별도,MATCH(G$1,BS별도H,0),0)/100,"") | H8: =IFERROR(VLOOKUP($D8,BS별도,MATCH(H$1,BS별도H,0),0)/100,"") | I8: =IFERROR(VLOOKUP($D8,BS별도,MATCH(I$1,BS별도H,0),0)/100,"") | J8: =IFERROR(VLOOKUP($D8,BS별도,MATCH(J$1,BS별도H,0),0)/100,"") | K8: =SUM(G8:J8) | L8: =IFERROR(VLOOKUP($D8,BS별도,MATCH(L$1,BS별도H,0),0)/100,"") | M8: =IFERROR(VLOOKUP($D8,BS별도,MATCH(M$1,BS별도H,0),0)/100,"") | N8: =IFERROR(VLOOKUP($D8,BS별도,MATCH(N$1,BS별도H,0),0)/100,"") | O8: =IFERROR(VLOOKUP($D8,BS별도,MATCH(O$1,BS별도H,0),0)/100,"") | P8: =SUM(L8:O8) | Q8: =IFERROR(VLOOKUP($D8,BS별도,MATCH(Q$1,BS별도H,0),0)/100,"") | R8: =IFERROR(VLOOKUP($D8,BS별도,MATCH(R$1,BS별도H,0),0)/100,"") | S8: =IFERROR(VLOOKUP($D8,BS별도,MATCH(S$1,BS별도H,0),0)/100,"") | T8: =IFERROR(VLOOKUP($D8,BS별도,MATCH(T$1,BS별도H,0),0)/100,"") | U8: =SUM(Q8:T8) | V8: =IFERROR(VLOOKUP($D8,BS별도,MATCH(V$1,BS별도H,0),0)/100,"") | W8: =IFERROR(VLOOKUP($D8,BS별도,MATCH(W$1,BS별도H,0),0)/100,"") | X8: =IFERROR(VLOOKUP($D8,BS별도,MATCH(X$1,BS별도H,0),0)/100,"") | Y8: =IFERROR(VLOOKUP($D8,BS별도,MATCH(Y$1,BS별도H,0),0)/100,"") | Z8: =SUM(V8:Y8) | AA8: =IFERROR(VLOOKUP($D8,BS별도,MATCH(AA$1,BS별도H,0),0)/100,"") | AB8: =IFERROR(VLOOKUP($D8,BS별도,MATCH(AB$1,BS별도H,0),0)/100,"") | AC8: =IFERROR(AC5*변수!AC22,"") | AD8: =IFERROR(AD5*변수!AD22,"") | AE8: =SUM(AA8:AD8) | AF8: =IFERROR(AF5*변수!AF22,"") | AG8: =IFERROR(AG5*변수!AG22,"") | AH8: =IFERROR(AH5*변수!AH22,"") | AI8: =IFERROR(AI5*변수!AI22,"") | AJ8: =SUM(AF8:AI8) | AK8: =IFERROR(AK5*변수!AK22,"") | AL8: =IFERROR(AL5*변수!AL22,"") | AM8: =IFERROR(AM5*변수!AM22,"") | AN8: =IFERROR(AN5*변수!AN22,"") | AO8: =SUM(AK8:AN8)
A9: 영업이익 | B9: 손익 | C9: 억원 | D9: 영업이익 | E9: =IFERROR(VLOOKUP($D9,BS별도,MATCH(E$1,BS별도H,0),0)/100,"") | G9: =IFERROR(VLOOKUP($D9,BS별도,MATCH(G$1,BS별도H,0),0)/100,"") | H9: =IFERROR(VLOOKUP($D9,BS별도,MATCH(H$1,BS별도H,0),0)/100,"") | I9: =IFERROR(VLOOKUP($D9,BS별도,MATCH(I$1,BS별도H,0),0)/100,"") | J9: =IFERROR(VLOOKUP($D9,BS별도,MATCH(J$1,BS별도H,0),0)/100,"") | K9: =SUM(G9:J9) | L9: =IFERROR(VLOOKUP($D9,BS별도,MATCH(L$1,BS별도H,0),0)/100,"") | M9: =IFERROR(VLOOKUP($D9,BS별도,MATCH(M$1,BS별도H,0),0)/100,"") | N9: =IFERROR(VLOOKUP($D9,BS별도,MATCH(N$1,BS별도H,0),0)/100,"") | O9: =IFERROR(VLOOKUP($D9,BS별도,MATCH(O$1,BS별도H,0),0)/100,"") | P9: =SUM(L9:O9) | Q9: =IFERROR(VLOOKUP($D9,BS별도,MATCH(Q$1,BS별도H,0),0)/100,"") | R9: =IFERROR(VLOOKUP($D9,BS별도,MATCH(R$1,BS별도H,0),0)/100,"") | S9: =IFERROR(VLOOKUP($D9,BS별도,MATCH(S$1,BS별도H,0),0)/100,"") | T9: =IFERROR(VLOOKUP($D9,BS별도,MATCH(T$1,BS별도H,0),0)/100,"") | U9: =SUM(Q9:T9) | V9: =IFERROR(VLOOKUP($D9,BS별도,MATCH(V$1,BS별도H,0),0)/100,"") | W9: =IFERROR(VLOOKUP($D9,BS별도,MATCH(W$1,BS별도H,0),0)/100,"") | X9: =IFERROR(VLOOKUP($D9,BS별도,MATCH(X$1,BS별도H,0),0)/100,"") | Y9: =IFERROR(VLOOKUP($D9,BS별도,MATCH(Y$1,BS별도H,0),0)/100,"") | Z9: =SUM(V9:Y9) | AA9: =IFERROR(VLOOKUP($D9,BS별도,MATCH(AA$1,BS별도H,0),0)/100,"") | AB9: =IFERROR(VLOOKUP($D9,BS별도,MATCH(AB$1,BS별도H,0),0)/100,"") | AC9: =IFERROR(AC5*변수!AC23,"") | AD9: =IFERROR(AD5*변수!AD23,"") | AE9: =SUM(AA9:AD9) | AF9: =IFERROR(AF5*변수!AF23,"") | AG9: =IFERROR(AG5*변수!AG23,"") | AH9: =IFERROR(AH5*변수!AH23,"") | AI9: =IFERROR(AI5*변수!AI23,"") | AJ9: =SUM(AF9:AI9) | AK9: =IFERROR(AK5*변수!AK23,"") | AL9: =IFERROR(AL5*변수!AL23,"") | AM9: =IFERROR(AM5*변수!AM23,"") | AN9: =IFERROR(AN5*변수!AN23,"") | AO9: =SUM(AK9:AN9)
A10: OPM | B10: 손익 | C10: % | D10: 영업이익률 | E10: =IFERROR(E9/E5,"") | G10: =IFERROR(G9/G5,"") | H10: =IFERROR(H9/H5,"") | I10: =IFERROR(I9/I5,"") | J10: =IFERROR(J9/J5,"") | K10: =IFERROR(K9/K5,"") | L10: =IFERROR(L9/L5,"") | M10: =IFERROR(M9/M5,"") | N10: =IFERROR(N9/N5,"") | ... AO10: =IFERROR(AO9/AO5,"")
A11: 금융손익 | B11: 손익 | C11: 억원 | D11: 금융손익 | E11: =IFERROR(VLOOKUP($D11,BS별도,MATCH(E$1,BS별도H,0),0)/100,"") | G11: =IFERROR(VLOOKUP($D11,BS별도,MATCH(G$1,BS별도H,0),0)/100,"") | H11: =IFERROR(VLOOKUP($D11,BS별도,MATCH(H$1,BS별도H,0),0)/100,"") | I11: =IFERROR(VLOOKUP($D11,BS별도,MATCH(I$1,BS별도H,0),0)/100,"") | J11: =IFERROR(VLOOKUP($D11,BS별도,MATCH(J$1,BS별도H,0),0)/100,"") | K11: =SUM(G11:J11) | L11: =IFERROR(VLOOKUP($D11,BS별도,MATCH(L$1,BS별도H,0),0)/100,"") | M11: =IFERROR(VLOOKUP($D11,BS별도,MATCH(M$1,BS별도H,0),0)/100,"") | N11: =IFERROR(VLOOKUP($D11,BS별도,MATCH(N$1,BS별도H,0),0)/100,"") | O11: =IFERROR(VLOOKUP($D11,BS별도,MATCH(O$1,BS별도H,0),0)/100,"") | P11: =SUM(L11:O11) | Q11: =IFERROR(VLOOKUP($D11,BS별도,MATCH(Q$1,BS별도H,0),0)/100,"") | R11: =IFERROR(VLOOKUP($D11,BS별도,MATCH(R$1,BS별도H,0),0)/100,"") | S11: =IFERROR(VLOOKUP($D11,BS별도,MATCH(S$1,BS별도H,0),0)/100,"") | T11: =IFERROR(VLOOKUP($D11,BS별도,MATCH(T$1,BS별도H,0),0)/100,"") | U11: =SUM(Q11:T11) | V11: =IFERROR(VLOOKUP($D11,BS별도,MATCH(V$1,BS별도H,0),0)/100,"") | W11: =IFERROR(VLOOKUP($D11,BS별도,MATCH(W$1,BS별도H,0),0)/100,"") | X11: =IFERROR(VLOOKUP($D11,BS별도,MATCH(X$1,BS별도H,0),0)/100,"") | Y11: =IFERROR(VLOOKUP($D11,BS별도,MATCH(Y$1,BS별도H,0),0)/100,"") | Z11: =SUM(V11:Y11) | AA11: =IFERROR(VLOOKUP($D11,BS별도,MATCH(AA$1,BS별도H,0),0)/100,"") | AB11: =IFERROR(VLOOKUP($D11,BS별도,MATCH(AB$1,BS별도H,0),0)/100,"") | AC11: =IFERROR(AC12+AC13,"") | AD11: =IFERROR(AD12+AD13,"") | AE11: =SUM(AA11:AD11) | AF11: =IFERROR(AF12+AF13,"") | AG11: =IFERROR(AG12+AG13,"") | AH11: =IFERROR(AH12+AH13,"") | AI11: =IFERROR(AI12+AI13,"") | AJ11: =SUM(AF11:AI11) | AK11: =IFERROR(AK12+AK13,"") | AL11: =IFERROR(AL12+AL13,"") | AM11: =IFERROR(AM12+AM13,"") | AN11: =IFERROR(AN12+AN13,"") | AO11: =SUM(AK11:AN11)
A12: 이자손익 | B12: 손익 | C12: 억원 | D12: 이자손익 | G12: =IFERROR(VLOOKUP($D12,BS별도,MATCH(G$1,BS별도H,0),0)/100,"") | H12: =IFERROR(VLOOKUP($D12,BS별도,MATCH(H$1,BS별도H,0),0)/100,"") | I12: =IFERROR(VLOOKUP($D12,BS별도,MATCH(I$1,BS별도H,0),0)/100,"") | J12: =IFERROR(VLOOKUP($D12,BS별도,MATCH(J$1,BS별도H,0),0)/100,"") | K12: =SUM(G12:J12) | L12: =IFERROR(VLOOKUP($D12,BS별도,MATCH(L$1,BS별도H,0),0)/100,"") | M12: =IFERROR(VLOOKUP($D12,BS별도,MATCH(M$1,BS별도H,0),0)/100,"") | N12: =IFERROR(VLOOKUP($D12,BS별도,MATCH(N$1,BS별도H,0),0)/100,"") | O12: =IFERROR(VLOOKUP($D12,BS별도,MATCH(O$1,BS별도H,0),0)/100,"") | P12: =SUM(L12:O12) | Q12: =IFERROR(VLOOKUP($D12,BS별도,MATCH(Q$1,BS별도H,0),0)/100,"") | R12: =IFERROR(VLOOKUP($D12,BS별도,MATCH(R$1,BS별도H,0),0)/100,"") | S12: =IFERROR(VLOOKUP($D12,BS별도,MATCH(S$1,BS별도H,0),0)/100,"") | T12: =IFERROR(VLOOKUP($D12,BS별도,MATCH(T$1,BS별도H,0),0)/100,"") | U12: =SUM(Q12:T12) | V12: =IFERROR(VLOOKUP($D12,BS별도,MATCH(V$1,BS별도H,0),0)/100,"") | W12: =IFERROR(VLOOKUP($D12,BS별도,MATCH(W$1,BS별도H,0),0)/100,"") | X12: =IFERROR(VLOOKUP($D12,BS별도,MATCH(X$1,BS별도H,0),0)/100,"") | Y12: =IFERROR(VLOOKUP($D12,BS별도,MATCH(Y$1,BS별도H,0),0)/100,"") | Z12: =SUM(V12:Y12) | AA12: =IFERROR(VLOOKUP($D12,BS별도,MATCH(AA$1,BS별도H,0),0)/100,"") | AB12: =IFERROR(VLOOKUP($D12,BS별도,MATCH(AB$1,BS별도H,0),0)/100,"") | AC12: =IFERROR((AB26*변수!$D$52-AB24*변수!$D$53)/4,"") | AD12: =IFERROR((AC26*변수!$D$52-AC24*변수!$D$53)/4,"") | AE12: =SUM(AA12:AD12) | AF12: =IFERROR((AD26*변수!$D$52-AD24*변수!$D$53)/4,"") | AG12: =IFERROR((AF26*변수!$D$52-AF24*변수!$D$53)/4,"") | AH12: =IFERROR((AG26*변수!$D$52-AG24*변수!$D$53)/4,"") | AI12: =IFERROR((AH26*변수!$D$52-AH24*변수!$D$53)/4,"") | AJ12: =SUM(AF12:AI12) | AK12: =IFERROR((AI26*변수!$D$52-AI24*변수!$D$53)/4,"") | AL12: =IFERROR((AK26*변수!$D$52-AK24*변수!$D$53)/4,"") | AM12: =IFERROR((AL26*변수!$D$52-AL24*변수!$D$53)/4,"") | AN12: =IFERROR((AM26*변수!$D$52-AM24*변수!$D$53)/4,"") | AO12: =SUM(AK12:AN12)
A13: 외환손익 | B13: 손익 | C13: 억원 | D13: 외환손익(실적만; 추정 환효과는 환관련손익) | K13: =SUM(G13:J13) | P13: =SUM(L13:O13) | R13: =IFERROR((VLOOKUP("외환차익",BS별도,MATCH(R$1,BS별도H,0),0)-VLOOKUP("외환차손",BS별도,MATCH(R$1,BS별도H,0),0)+VLOOKUP("외화환산이익",BS별도,MATCH(R$1,BS별도H,0),0)-VLOOKUP("외화환산손실",BS별도,MATCH(R$1,BS별도H,0),0))/100,"") | U13: =SUM(Q13:T13) | Z13: =SUM(V13:Y13) | AC13: =변수!AC24 | AD13: =변수!AD24 | AE13: =SUM(AA13:AD13) | AF13: =변수!AF24 | AG13: =변수!AG24 | AH13: =변수!AH24 | AI13: =변수!AI24 | AJ13: =SUM(AF13:AI13) | AK13: =변수!AK24 | AL13: =변수!AL24 | AM13: =변수!AM24 | AN13: =변수!AN24 | AO13: =SUM(AK13:AN13)
A14: 기타영업외손익 | B14: 손익 | C14: 억원 | D14: 기타영업외손익 | E14: =IFERROR(VLOOKUP($D14,BS별도,MATCH(E$1,BS별도H,0),0)/100,"") | G14: =IFERROR(VLOOKUP($D14,BS별도,MATCH(G$1,BS별도H,0),0)/100,"") | H14: =IFERROR(VLOOKUP($D14,BS별도,MATCH(H$1,BS별도H,0),0)/100,"") | I14: =IFERROR(VLOOKUP($D14,BS별도,MATCH(I$1,BS별도H,0),0)/100,"") | J14: =IFERROR(VLOOKUP($D14,BS별도,MATCH(J$1,BS별도H,0),0)/100,"") | K14: =SUM(G14:J14) | L14: =IFERROR(VLOOKUP($D14,BS별도,MATCH(L$1,BS별도H,0),0)/100,"") | M14: =IFERROR(VLOOKUP($D14,BS별도,MATCH(M$1,BS별도H,0),0)/100,"") | N14: =IFERROR(VLOOKUP($D14,BS별도,MATCH(N$1,BS별도H,0),0)/100,"") | O14: =IFERROR(VLOOKUP($D14,BS별도,MATCH(O$1,BS별도H,0),0)/100,"") | P14: =SUM(L14:O14) | Q14: =IFERROR(VLOOKUP($D14,BS별도,MATCH(Q$1,BS별도H,0),0)/100,"") | R14: =IFERROR(VLOOKUP($D14,BS별도,MATCH(R$1,BS별도H,0),0)/100,"") | S14: =IFERROR(VLOOKUP($D14,BS별도,MATCH(S$1,BS별도H,0),0)/100,"") | T14: =IFERROR(VLOOKUP($D14,BS별도,MATCH(T$1,BS별도H,0),0)/100,"") | U14: =SUM(Q14:T14) | V14: =IFERROR(VLOOKUP($D14,BS별도,MATCH(V$1,BS별도H,0),0)/100,"") | W14: =IFERROR(VLOOKUP($D14,BS별도,MATCH(W$1,BS별도H,0),0)/100,"") | X14: =IFERROR(VLOOKUP($D14,BS별도,MATCH(X$1,BS별도H,0),0)/100,"") | Y14: =IFERROR(VLOOKUP($D14,BS별도,MATCH(Y$1,BS별도H,0),0)/100,"") | Z14: =SUM(V14:Y14) | AA14: =IFERROR(VLOOKUP($D14,BS별도,MATCH(AA$1,BS별도H,0),0)/100,"") | AB14: =IFERROR(VLOOKUP($D14,BS별도,MATCH(AB$1,BS별도H,0),0)/100,"") | AC14: =변수!AC25 | AD14: =변수!AD25 | AE14: =SUM(AA14:AD14) | AF14: =변수!AF25 | AG14: =변수!AG25 | AH14: =변수!AH25 | AI14: =변수!AI25 | AJ14: =SUM(AF14:AI14) | AK14: =변수!AK25 | AL14: =변수!AL25 | AM14: =변수!AM25 | AN14: =변수!AN25 | AO14: =SUM(AK14:AN14)
A15: 지분법손익 | B15: 손익 | C15: 억원 | D15: 종속기업,공동지배기업및관계기업관련손익 | E15: =IFERROR(VLOOKUP($D15,BS별도,MATCH(E$1,BS별도H,0),0)/100,"") | I15: =IFERROR(VLOOKUP($D15,BS별도,MATCH(I$1,BS별도H,0),0)/100,"") | J15: =IFERROR(VLOOKUP($D15,BS별도,MATCH(J$1,BS별도H,0),0)/100,"") | K15: =SUM(G15:J15) | P15: =SUM(L15:O15) | U15: =SUM(Q15:T15) | Z15: =SUM(V15:Y15) | AC15: =변수!AC26 | AD15: =변수!AD26 | AE15: =SUM(AA15:AD15) | AF15: =변수!AF26 | AG15: =변수!AG26 | AH15: =변수!AH26 | AI15: =변수!AI26 | AJ15: =SUM(AF15:AI15) | AK15: =변수!AK26 | AL15: =변수!AL26 | AM15: =변수!AM26 | AN15: =변수!AN26 | AO15: =SUM(AK15:AN15)
A16: 세전이익 | B16: 손익 | C16: 억원 | D16: 법인세비용차감전계속사업이익 | E16: =IFERROR(VLOOKUP($D16,BS별도,MATCH(E$1,BS별도H,0),0)/100,"") | G16: =IFERROR(VLOOKUP($D16,BS별도,MATCH(G$1,BS별도H,0),0)/100,"") | H16: =IFERROR(VLOOKUP($D16,BS별도,MATCH(H$1,BS별도H,0),0)/100,"") | I16: =IFERROR(VLOOKUP($D16,BS별도,MATCH(I$1,BS별도H,0),0)/100,"") | J16: =IFERROR(VLOOKUP($D16,BS별도,MATCH(J$1,BS별도H,0),0)/100,"") | K16: =SUM(G16:J16) | L16: =IFERROR(VLOOKUP($D16,BS별도,MATCH(L$1,BS별도H,0),0)/100,"") | M16: =IFERROR(VLOOKUP($D16,BS별도,MATCH(M$1,BS별도H,0),0)/100,"") | N16: =IFERROR(VLOOKUP($D16,BS별도,MATCH(N$1,BS별도H,0),0)/100,"") | O16: =IFERROR(VLOOKUP($D16,BS별도,MATCH(O$1,BS별도H,0),0)/100,"") | P16: =SUM(L16:O16) | Q16: =IFERROR(VLOOKUP($D16,BS별도,MATCH(Q$1,BS별도H,0),0)/100,"") | R16: =IFERROR(VLOOKUP($D16,BS별도,MATCH(R$1,BS별도H,0),0)/100,"") | S16: =IFERROR(VLOOKUP($D16,BS별도,MATCH(S$1,BS별도H,0),0)/100,"") | T16: =IFERROR(VLOOKUP($D16,BS별도,MATCH(T$1,BS별도H,0),0)/100,"") | U16: =SUM(Q16:T16) | V16: =IFERROR(VLOOKUP($D16,BS별도,MATCH(V$1,BS별도H,0),0)/100,"") | W16: =IFERROR(VLOOKUP($D16,BS별도,MATCH(W$1,BS별도H,0),0)/100,"") | X16: =IFERROR(VLOOKUP($D16,BS별도,MATCH(X$1,BS별도H,0),0)/100,"") | Y16: =IFERROR(VLOOKUP($D16,BS별도,MATCH(Y$1,BS별도H,0),0)/100,"") | Z16: =SUM(V16:Y16) | AA16: =IFERROR(VLOOKUP($D16,BS별도,MATCH(AA$1,BS별도H,0),0)/100,"") | AB16: =IFERROR(VLOOKUP($D16,BS별도,MATCH(AB$1,BS별도H,0),0)/100,"") | AC16: =IFERROR(AC9+AC11+AC14+AC15,"") | AD16: =IFERROR(AD9+AD11+AD14+AD15,"") | AE16: =SUM(AA16:AD16) | AF16: =IFERROR(AF9+AF11+AF14+AF15,"") | AG16: =IFERROR(AG9+AG11+AG14+AG15,"") | AH16: =IFERROR(AH9+AH11+AH14+AH15,"") | AI16: =IFERROR(AI9+AI11+AI14+AI15,"") | AJ16: =SUM(AF16:AI16) | AK16: =IFERROR(AK9+AK11+AK14+AK15,"") | AL16: =IFERROR(AL9+AL11+AL14+AL15,"") | AM16: =IFERROR(AM9+AM11+AM14+AM15,"") | AN16: =IFERROR(AN9+AN11+AN14+AN15,"") | AO16: =SUM(AK16:AN16)
A17: 법인세비용 | B17: 손익 | C17: 억원 | D17: 법인세비용 | E17: =IFERROR(VLOOKUP($D17,BS별도,MATCH(E$1,BS별도H,0),0)/100,"") | G17: =IFERROR(VLOOKUP($D17,BS별도,MATCH(G$1,BS별도H,0),0)/100,"") | H17: =IFERROR(VLOOKUP($D17,BS별도,MATCH(H$1,BS별도H,0),0)/100,"") | I17: =IFERROR(VLOOKUP($D17,BS별도,MATCH(I$1,BS별도H,0),0)/100,"") | J17: =IFERROR(VLOOKUP($D17,BS별도,MATCH(J$1,BS별도H,0),0)/100,"") | K17: =SUM(G17:J17) | L17: =IFERROR(VLOOKUP($D17,BS별도,MATCH(L$1,BS별도H,0),0)/100,"") | M17: =IFERROR(VLOOKUP($D17,BS별도,MATCH(M$1,BS별도H,0),0)/100,"") | P17: =SUM(L17:O17) | S17: =IFERROR(VLOOKUP($D17,BS별도,MATCH(S$1,BS별도H,0),0)/100,"") | T17: =IFERROR(VLOOKUP($D17,BS별도,MATCH(T$1,BS별도H,0),0)/100,"") | U17: =SUM(Q17:T17) | X17: =IFERROR(VLOOKUP($D17,BS별도,MATCH(X$1,BS별도H,0),0)/100,"") | Y17: =IFERROR(VLOOKUP($D17,BS별도,MATCH(Y$1,BS별도H,0),0)/100,"") | Z17: =SUM(V17:Y17) | AC17: =IFERROR(MAX(AC16,0)*변수!AC27,"") | AD17: =IFERROR(MAX(AD16,0)*변수!AD27,"") | AE17: =SUM(AA17:AD17) | AF17: =IFERROR(MAX(AF16,0)*변수!AF27,"") | AG17: =IFERROR(MAX(AG16,0)*변수!AG27,"") | AH17: =IFERROR(MAX(AH16,0)*변수!AH27,"") | AI17: =IFERROR(MAX(AI16,0)*변수!AI27,"") | AJ17: =SUM(AF17:AI17) | AK17: =IFERROR(MAX(AK16,0)*변수!AK27,"") | AL17: =IFERROR(MAX(AL16,0)*변수!AL27,"") | AM17: =IFERROR(MAX(AM16,0)*변수!AM27,"") | AN17: =IFERROR(MAX(AN16,0)*변수!AN27,"") | AO17: =SUM(AK17:AN17)
A18: 당기순이익 | B18: 손익 | C18: 억원 | D18: 당기순이익 | E18: =IFERROR(VLOOKUP($D18,BS별도,MATCH(E$1,BS별도H,0),0)/100,"") | G18: =IFERROR(VLOOKUP($D18,BS별도,MATCH(G$1,BS별도H,0),0)/100,"") | H18: =IFERROR(VLOOKUP($D18,BS별도,MATCH(H$1,BS별도H,0),0)/100,"") | I18: =IFERROR(VLOOKUP($D18,BS별도,MATCH(I$1,BS별도H,0),0)/100,"") | J18: =IFERROR(VLOOKUP($D18,BS별도,MATCH(J$1,BS별도H,0),0)/100,"") | K18: =SUM(G18:J18) | L18: =IFERROR(VLOOKUP($D18,BS별도,MATCH(L$1,BS별도H,0),0)/100,"") | M18: =IFERROR(VLOOKUP($D18,BS별도,MATCH(M$1,BS별도H,0),0)/100,"") | N18: =IFERROR(VLOOKUP($D18,BS별도,MATCH(N$1,BS별도H,0),0)/100,"") | O18: =IFERROR(VLOOKUP($D18,BS별도,MATCH(O$1,BS별도H,0),0)/100,"") | P18: =SUM(L18:O18) | Q18: =IFERROR(VLOOKUP($D18,BS별도,MATCH(Q$1,BS별도H,0),0)/100,"") | R18: =IFERROR(VLOOKUP($D18,BS별도,MATCH(R$1,BS별도H,0),0)/100,"") | S18: =IFERROR(VLOOKUP($D18,BS별도,MATCH(S$1,BS별도H,0),0)/100,"") | T18: =IFERROR(VLOOKUP($D18,BS별도,MATCH(T$1,BS별도H,0),0)/100,"") | U18: =SUM(Q18:T18) | V18: =IFERROR(VLOOKUP($D18,BS별도,MATCH(V$1,BS별도H,0),0)/100,"") | W18: =IFERROR(VLOOKUP($D18,BS별도,MATCH(W$1,BS별도H,0),0)/100,"") | X18: =IFERROR(VLOOKUP($D18,BS별도,MATCH(X$1,BS별도H,0),0)/100,"") | Y18: =IFERROR(VLOOKUP($D18,BS별도,MATCH(Y$1,BS별도H,0),0)/100,"") | Z18: =SUM(V18:Y18) | AA18: =IFERROR(VLOOKUP($D18,BS별도,MATCH(AA$1,BS별도H,0),0)/100,"") | AB18: =IFERROR(VLOOKUP($D18,BS별도,MATCH(AB$1,BS별도H,0),0)/100,"") | AC18: =IFERROR(AC16-AC17,"") | AD18: =IFERROR(AD16-AD17,"") | AE18: =SUM(AA18:AD18) | AF18: =IFERROR(AF16-AF17,"") | AG18: =IFERROR(AG16-AG17,"") | AH18: =IFERROR(AH16-AH17,"") | AI18: =IFERROR(AI16-AI17,"") | AJ18: =SUM(AF18:AI18) | AK18: =IFERROR(AK16-AK17,"") | AL18: =IFERROR(AL16-AL17,"") | AM18: =IFERROR(AM16-AM17,"") | AN18: =IFERROR(AN16-AN17,"") | AO18: =SUM(AK18:AN18)
A19: 지배주주순이익 | B19: 손익 | C19: 억원 | D19: (지배주주지분)당기순이익 | E19: =IFERROR(VLOOKUP($D19,BS별도,MATCH(E$1,BS별도H,0),0)/100,"") | G19: =IFERROR(VLOOKUP($D19,BS별도,MATCH(G$1,BS별도H,0),0)/100,"") | H19: =IFERROR(VLOOKUP($D19,BS별도,MATCH(H$1,BS별도H,0),0)/100,"") | I19: =IFERROR(VLOOKUP($D19,BS별도,MATCH(I$1,BS별도H,0),0)/100,"") | J19: =IFERROR(VLOOKUP($D19,BS별도,MATCH(J$1,BS별도H,0),0)/100,"") | K19: =SUM(G19:J19) | L19: =IFERROR(VLOOKUP($D19,BS별도,MATCH(L$1,BS별도H,0),0)/100,"") | M19: =IFERROR(VLOOKUP($D19,BS별도,MATCH(M$1,BS별도H,0),0)/100,"") | N19: =IFERROR(VLOOKUP($D19,BS별도,MATCH(N$1,BS별도H,0),0)/100,"") | O19: =IFERROR(VLOOKUP($D19,BS별도,MATCH(O$1,BS별도H,0),0)/100,"") | P19: =SUM(L19:O19) | Q19: =IFERROR(VLOOKUP($D19,BS별도,MATCH(Q$1,BS별도H,0),0)/100,"") | R19: =IFERROR(VLOOKUP($D19,BS별도,MATCH(R$1,BS별도H,0),0)/100,"") | S19: =IFERROR(VLOOKUP($D19,BS별도,MATCH(S$1,BS별도H,0),0)/100,"") | T19: =IFERROR(VLOOKUP($D19,BS별도,MATCH(T$1,BS별도H,0),0)/100,"") | U19: =SUM(Q19:T19) | V19: =IFERROR(VLOOKUP($D19,BS별도,MATCH(V$1,BS별도H,0),0)/100,"") | W19: =IFERROR(VLOOKUP($D19,BS별도,MATCH(W$1,BS별도H,0),0)/100,"") | X19: =IFERROR(VLOOKUP($D19,BS별도,MATCH(X$1,BS별도H,0),0)/100,"") | Y19: =IFERROR(VLOOKUP($D19,BS별도,MATCH(Y$1,BS별도H,0),0)/100,"") | Z19: =SUM(V19:Y19) | AA19: =IFERROR(VLOOKUP($D19,BS별도,MATCH(AA$1,BS별도H,0),0)/100,"") | AB19: =IFERROR(VLOOKUP($D19,BS별도,MATCH(AB$1,BS별도H,0),0)/100,"") | AC19: =IFERROR(AC18*변수!AC28,"") | AD19: =IFERROR(AD18*변수!AD28,"") | AE19: =SUM(AA19:AD19) | AF19: =IFERROR(AF18*변수!AF28,"") | AG19: =IFERROR(AG18*변수!AG28,"") | AH19: =IFERROR(AH18*변수!AH28,"") | AI19: =IFERROR(AI18*변수!AI28,"") | AJ19: =SUM(AF19:AI19) | AK19: =IFERROR(AK18*변수!AK28,"") | AL19: =IFERROR(AL18*변수!AL28,"") | AM19: =IFERROR(AM18*변수!AM28,"") | AN19: =IFERROR(AN18*변수!AN28,"") | AO19: =SUM(AK19:AN19)
A20: 자산총계 | B20: 재무상태 | C20: 억원 | D20: 자산총계 | E20: =IFERROR(VLOOKUP($D20,BS별도,MATCH(E$1,BS별도H,0),0)/100,"") | F20: 501.95 | G20: =IFERROR(VLOOKUP($D20,BS별도,MATCH(G$1,BS별도H,0),0)/100,"") | H20: =IFERROR(VLOOKUP($D20,BS별도,MATCH(H$1,BS별도H,0),0)/100,"") | I20: =IFERROR(VLOOKUP($D20,BS별도,MATCH(I$1,BS별도H,0),0)/100,"") | J20: =IFERROR(VLOOKUP($D20,BS별도,MATCH(J$1,BS별도H,0),0)/100,"") | K20: =J20 | L20: =IFERROR(VLOOKUP($D20,BS별도,MATCH(L$1,BS별도H,0),0)/100,"") | M20: =IFERROR(VLOOKUP($D20,BS별도,MATCH(M$1,BS별도H,0),0)/100,"") | N20: =IFERROR(VLOOKUP($D20,BS별도,MATCH(N$1,BS별도H,0),0)/100,"") | O20: =IFERROR(VLOOKUP($D20,BS별도,MATCH(O$1,BS별도H,0),0)/100,"") | P20: =O20 | Q20: =IFERROR(VLOOKUP($D20,BS별도,MATCH(Q$1,BS별도H,0),0)/100,"") | R20: =IFERROR(VLOOKUP($D20,BS별도,MATCH(R$1,BS별도H,0),0)/100,"") | S20: =IFERROR(VLOOKUP($D20,BS별도,MATCH(S$1,BS별도H,0),0)/100,"") | T20: =IFERROR(VLOOKUP($D20,BS별도,MATCH(T$1,BS별도H,0),0)/100,"") | U20: =T20 | V20: =IFERROR(VLOOKUP($D20,BS별도,MATCH(V$1,BS별도H,0),0)/100,"") | W20: =IFERROR(VLOOKUP($D20,BS별도,MATCH(W$1,BS별도H,0),0)/100,"") | X20: =IFERROR(VLOOKUP($D20,BS별도,MATCH(X$1,BS별도H,0),0)/100,"") | Y20: =IFERROR(VLOOKUP($D20,BS별도,MATCH(Y$1,BS별도H,0),0)/100,"") | Z20: =Y20 | AA20: =IFERROR(VLOOKUP($D20,BS별도,MATCH(AA$1,BS별도H,0),0)/100,"") | AB20: =IFERROR(VLOOKUP($D20,BS별도,MATCH(AB$1,BS별도H,0),0)/100,"") | AC20: =IFERROR(AC21+AC22,"") | AD20: =IFERROR(AD21+AD22,"") | AE20: =AD20 | AF20: =IFERROR(AF21+AF22,"") | AG20: =IFERROR(AG21+AG22,"") | AH20: =IFERROR(AH21+AH22,"") | AI20: =IFERROR(AI21+AI22,"") | AJ20: =AI20 | AK20: =IFERROR(AK21+AK22,"") | AL20: =IFERROR(AL21+AL22,"") | AM20: =IFERROR(AM21+AM22,"") | AN20: =IFERROR(AN21+AN22,"") | AO20: =AN20
A21: 부채총계 | B21: 재무상태 | C21: 억원 | D21: 부채총계 | E21: =IFERROR(VLOOKUP($D21,BS별도,MATCH(E$1,BS별도H,0),0)/100,"") | F21: 221.33 | G21: =IFERROR(VLOOKUP($D21,BS별도,MATCH(G$1,BS별도H,0),0)/100,"") | H21: =IFERROR(VLOOKUP($D21,BS별도,MATCH(H$1,BS별도H,0),0)/100,"") | I21: =IFERROR(VLOOKUP($D21,BS별도,MATCH(I$1,BS별도H,0),0)/100,"") | J21: =IFERROR(VLOOKUP($D21,BS별도,MATCH(J$1,BS별도H,0),0)/100,"") | K21: =J21 | L21: =IFERROR(VLOOKUP($D21,BS별도,MATCH(L$1,BS별도H,0),0)/100,"") | M21: =IFERROR(VLOOKUP($D21,BS별도,MATCH(M$1,BS별도H,0),0)/100,"") | N21: =IFERROR(VLOOKUP($D21,BS별도,MATCH(N$1,BS별도H,0),0)/100,"") | O21: =IFERROR(VLOOKUP($D21,BS별도,MATCH(O$1,BS별도H,0),0)/100,"") | P21: =O21 | Q21: =IFERROR(VLOOKUP($D21,BS별도,MATCH(Q$1,BS별도H,0),0)/100,"") | R21: =IFERROR(VLOOKUP($D21,BS별도,MATCH(R$1,BS별도H,0),0)/100,"") | S21: =IFERROR(VLOOKUP($D21,BS별도,MATCH(S$1,BS별도H,0),0)/100,"") | T21: =IFERROR(VLOOKUP($D21,BS별도,MATCH(T$1,BS별도H,0),0)/100,"") | U21: =T21 | V21: =IFERROR(VLOOKUP($D21,BS별도,MATCH(V$1,BS별도H,0),0)/100,"") | W21: =IFERROR(VLOOKUP($D21,BS별도,MATCH(W$1,BS별도H,0),0)/100,"") | X21: =IFERROR(VLOOKUP($D21,BS별도,MATCH(X$1,BS별도H,0),0)/100,"") | Y21: =IFERROR(VLOOKUP($D21,BS별도,MATCH(Y$1,BS별도H,0),0)/100,"") | Z21: =Y21 | AA21: =IFERROR(VLOOKUP($D21,BS별도,MATCH(AA$1,BS별도H,0),0)/100,"") | AB21: =IFERROR(VLOOKUP($D21,BS별도,MATCH(AB$1,BS별도H,0),0)/100,"") | AC21: =IFERROR(AB21*(1+변수!AC29),"") | AD21: =IFERROR(AC21*(1+변수!AD29),"") | AE21: =AD21 | AF21: =IFERROR(AD21*(1+변수!AF29),"") | AG21: =IFERROR(AF21*(1+변수!AG29),"") | AH21: =IFERROR(AG21*(1+변수!AH29),"") | AI21: =IFERROR(AH21*(1+변수!AI29),"") | AJ21: =AI21 | AK21: =IFERROR(AI21*(1+변수!AK29),"") | AL21: =IFERROR(AK21*(1+변수!AL29),"") | AM21: =IFERROR(AL21*(1+변수!AM29),"") | AN21: =IFERROR(AM21*(1+변수!AN29),"") | AO21: =AN21
A22: 자본총계 | B22: 재무상태 | C22: 억원 | D22: 자본총계 | E22: =IFERROR(VLOOKUP($D22,BS별도,MATCH(E$1,BS별도H,0),0)/100,"") | F22: 280.62 | G22: =IFERROR(VLOOKUP($D22,BS별도,MATCH(G$1,BS별도H,0),0)/100,"") | H22: =IFERROR(VLOOKUP($D22,BS별도,MATCH(H$1,BS별도H,0),0)/100,"") | I22: =IFERROR(VLOOKUP($D22,BS별도,MATCH(I$1,BS별도H,0),0)/100,"") | J22: =IFERROR(VLOOKUP($D22,BS별도,MATCH(J$1,BS별도H,0),0)/100,"") | K22: =J22 | L22: =IFERROR(VLOOKUP($D22,BS별도,MATCH(L$1,BS별도H,0),0)/100,"") | M22: =IFERROR(VLOOKUP($D22,BS별도,MATCH(M$1,BS별도H,0),0)/100,"") | N22: =IFERROR(VLOOKUP($D22,BS별도,MATCH(N$1,BS별도H,0),0)/100,"") | O22: =IFERROR(VLOOKUP($D22,BS별도,MATCH(O$1,BS별도H,0),0)/100,"") | P22: =O22 | Q22: =IFERROR(VLOOKUP($D22,BS별도,MATCH(Q$1,BS별도H,0),0)/100,"") | R22: =IFERROR(VLOOKUP($D22,BS별도,MATCH(R$1,BS별도H,0),0)/100,"") | S22: =IFERROR(VLOOKUP($D22,BS별도,MATCH(S$1,BS별도H,0),0)/100,"") | T22: =IFERROR(VLOOKUP($D22,BS별도,MATCH(T$1,BS별도H,0),0)/100,"") | U22: =T22 | V22: =IFERROR(VLOOKUP($D22,BS별도,MATCH(V$1,BS별도H,0),0)/100,"") | W22: =IFERROR(VLOOKUP($D22,BS별도,MATCH(W$1,BS별도H,0),0)/100,"") | X22: =IFERROR(VLOOKUP($D22,BS별도,MATCH(X$1,BS별도H,0),0)/100,"") | Y22: =IFERROR(VLOOKUP($D22,BS별도,MATCH(Y$1,BS별도H,0),0)/100,"") | Z22: =Y22 | AA22: =IFERROR(VLOOKUP($D22,BS별도,MATCH(AA$1,BS별도H,0),0)/100,"") | AB22: =IFERROR(VLOOKUP($D22,BS별도,MATCH(AB$1,BS별도H,0),0)/100,"") | AC22: =IFERROR(AB22+AC18-변수!AC30,"") | AD22: =IFERROR(AC22+AD18-변수!AD30,"") | AE22: =AD22 | AF22: =IFERROR(AD22+AF18-변수!AF30,"") | AG22: =IFERROR(AF22+AG18-변수!AG30,"") | AH22: =IFERROR(AG22+AH18-변수!AH30,"") | AI22: =IFERROR(AH22+AI18-변수!AI30,"") | AJ22: =AI22 | AK22: =IFERROR(AI22+AK18-변수!AK30,"") | AL22: =IFERROR(AK22+AL18-변수!AL30,"") | AM22: =IFERROR(AL22+AM18-변수!AM30,"") | AN22: =IFERROR(AM22+AN18-변수!AN30,"") | AO22: =AN22
A23: 지배주주지분 | B23: 재무상태 | C23: 억원 | D23: 지배주주지분 | E23: =IFERROR(VLOOKUP($D23,BS별도,MATCH(E$1,BS별도H,0),0)/100,"") | F23: 280.62 | G23: =IFERROR(VLOOKUP($D23,BS별도,MATCH(G$1,BS별도H,0),0)/100,"") | H23: =IFERROR(VLOOKUP($D23,BS별도,MATCH(H$1,BS별도H,0),0)/100,"") | I23: =IFERROR(VLOOKUP($D23,BS별도,MATCH(I$1,BS별도H,0),0)/100,"") | J23: =IFERROR(VLOOKUP($D23,BS별도,MATCH(J$1,BS별도H,0),0)/100,"") | K23: =J23 | L23: =IFERROR(VLOOKUP($D23,BS별도,MATCH(L$1,BS별도H,0),0)/100,"") | M23: =IFERROR(VLOOKUP($D23,BS별도,MATCH(M$1,BS별도H,0),0)/100,"") | N23: =IFERROR(VLOOKUP($D23,BS별도,MATCH(N$1,BS별도H,0),0)/100,"") | O23: =IFERROR(VLOOKUP($D23,BS별도,MATCH(O$1,BS별도H,0),0)/100,"") | P23: =O23 | Q23: =IFERROR(VLOOKUP($D23,BS별도,MATCH(Q$1,BS별도H,0),0)/100,"") | R23: =IFERROR(VLOOKUP($D23,BS별도,MATCH(R$1,BS별도H,0),0)/100,"") | S23: =IFERROR(VLOOKUP($D23,BS별도,MATCH(S$1,BS별도H,0),0)/100,"") | T23: =IFERROR(VLOOKUP($D23,BS별도,MATCH(T$1,BS별도H,0),0)/100,"") | U23: =T23 | V23: =IFERROR(VLOOKUP($D23,BS별도,MATCH(V$1,BS별도H,0),0)/100,"") | W23: =IFERROR(VLOOKUP($D23,BS별도,MATCH(W$1,BS별도H,0),0)/100,"") | X23: =IFERROR(VLOOKUP($D23,BS별도,MATCH(X$1,BS별도H,0),0)/100,"") | Y23: =IFERROR(VLOOKUP($D23,BS별도,MATCH(Y$1,BS별도H,0),0)/100,"") | Z23: =Y23 | AA23: =IFERROR(VLOOKUP($D23,BS별도,MATCH(AA$1,BS별도H,0),0)/100,"") | AB23: =IFERROR(VLOOKUP($D23,BS별도,MATCH(AB$1,BS별도H,0),0)/100,"") | AC23: =IFERROR(AB23+AC19-변수!AC31,"") | AD23: =IFERROR(AC23+AD19-변수!AD31,"") | AE23: =AD23 | AF23: =IFERROR(AD23+AF19-변수!AF31,"") | AG23: =IFERROR(AF23+AG19-변수!AG31,"") | AH23: =IFERROR(AG23+AH19-변수!AH31,"") | AI23: =IFERROR(AH23+AI19-변수!AI31,"") | AJ23: =AI23 | AK23: =IFERROR(AI23+AK19-변수!AK31,"") | AL23: =IFERROR(AK23+AL19-변수!AL31,"") | AM23: =IFERROR(AL23+AM19-변수!AM31,"") | AN23: =IFERROR(AM23+AN19-변수!AN31,"") | AO23: =AN23
A24: 총차입금 | B24: 재무상태 | C24: 억원 | D24: 총차입금 | E24: =IFERROR(VLOOKUP($D24,BS별도,MATCH(E$1,BS별도H,0),0)/100,"") | F24: 168.25 | G24: =IFERROR(VLOOKUP($D24,BS별도,MATCH(G$1,BS별도H,0),0)/100,"") | H24: =IFERROR(VLOOKUP($D24,BS별도,MATCH(H$1,BS별도H,0),0)/100,"") | I24: =IFERROR(VLOOKUP($D24,BS별도,MATCH(I$1,BS별도H,0),0)/100,"") | J24: =IFERROR(VLOOKUP($D24,BS별도,MATCH(J$1,BS별도H,0),0)/100,"") | K24: =J24 | L24: =IFERROR(VLOOKUP($D24,BS별도,MATCH(L$1,BS별도H,0),0)/100,"") | M24: =IFERROR(VLOOKUP($D24,BS별도,MATCH(M$1,BS별도H,0),0)/100,"") | N24: =IFERROR(VLOOKUP($D24,BS별도,MATCH(N$1,BS별도H,0),0)/100,"") | O24: =IFERROR(VLOOKUP($D24,BS별도,MATCH(O$1,BS별도H,0),0)/100,"") | P24: =O24 | Q24: =IFERROR(VLOOKUP($D24,BS별도,MATCH(Q$1,BS별도H,0),0)/100,"") | R24: =IFERROR(VLOOKUP($D24,BS별도,MATCH(R$1,BS별도H,0),0)/100,"") | S24: =IFERROR(VLOOKUP($D24,BS별도,MATCH(S$1,BS별도H,0),0)/100,"") | T24: =IFERROR(VLOOKUP($D24,BS별도,MATCH(T$1,BS별도H,0),0)/100,"") | U24: =T24 | V24: =IFERROR(VLOOKUP($D24,BS별도,MATCH(V$1,BS별도H,0),0)/100,"") | W24: =IFERROR(VLOOKUP($D24,BS별도,MATCH(W$1,BS별도H,0),0)/100,"") | X24: =IFERROR(VLOOKUP($D24,BS별도,MATCH(X$1,BS별도H,0),0)/100,"") | Y24: =IFERROR(VLOOKUP($D24,BS별도,MATCH(Y$1,BS별도H,0),0)/100,"") | Z24: =Y24 | AA24: =IFERROR(VLOOKUP($D24,BS별도,MATCH(AA$1,BS별도H,0),0)/100,"") | AB24: =IFERROR(VLOOKUP($D24,BS별도,MATCH(AB$1,BS별도H,0),0)/100,"") | AC24: =IFERROR(AB24*(1+변수!AC32),"") | AD24: =IFERROR(AC24*(1+변수!AD32),"") | AE24: =AD24 | AF24: =IFERROR(AD24*(1+변수!AF32),"") | AG24: =IFERROR(AF24*(1+변수!AG32),"") | AH24: =IFERROR(AG24*(1+변수!AH32),"") | AI24: =IFERROR(AH24*(1+변수!AI32),"") | AJ24: =AI24 | AK24: =IFERROR(AI24*(1+변수!AK32),"") | AL24: =IFERROR(AK24*(1+변수!AL32),"") | AM24: =IFERROR(AL24*(1+변수!AM32),"") | AN24: =IFERROR(AM24*(1+변수!AN32),"") | AO24: =AN24
A25: 순차입금 | B25: 재무상태 | C25: 억원 | D25: 순차입금 | E25: =IFERROR(VLOOKUP($D25,BS별도,MATCH(E$1,BS별도H,0),0)/100,"") | F25: 137.6 | G25: =IFERROR(VLOOKUP($D25,BS별도,MATCH(G$1,BS별도H,0),0)/100,"") | H25: =IFERROR(VLOOKUP($D25,BS별도,MATCH(H$1,BS별도H,0),0)/100,"") | I25: =IFERROR(VLOOKUP($D25,BS별도,MATCH(I$1,BS별도H,0),0)/100,"") | J25: =IFERROR(VLOOKUP($D25,BS별도,MATCH(J$1,BS별도H,0),0)/100,"") | K25: =J25 | L25: =IFERROR(VLOOKUP($D25,BS별도,MATCH(L$1,BS별도H,0),0)/100,"") | M25: =IFERROR(VLOOKUP($D25,BS별도,MATCH(M$1,BS별도H,0),0)/100,"") | N25: =IFERROR(VLOOKUP($D25,BS별도,MATCH(N$1,BS별도H,0),0)/100,"") | O25: =IFERROR(VLOOKUP($D25,BS별도,MATCH(O$1,BS별도H,0),0)/100,"") | P25: =O25 | Q25: =IFERROR(VLOOKUP($D25,BS별도,MATCH(Q$1,BS별도H,0),0)/100,"") | R25: =IFERROR(VLOOKUP($D25,BS별도,MATCH(R$1,BS별도H,0),0)/100,"") | S25: =IFERROR(VLOOKUP($D25,BS별도,MATCH(S$1,BS별도H,0),0)/100,"") | T25: =IFERROR(VLOOKUP($D25,BS별도,MATCH(T$1,BS별도H,0),0)/100,"") | U25: =T25 | V25: =IFERROR(VLOOKUP($D25,BS별도,MATCH(V$1,BS별도H,0),0)/100,"") | W25: =IFERROR(VLOOKUP($D25,BS별도,MATCH(W$1,BS별도H,0),0)/100,"") | X25: =IFERROR(VLOOKUP($D25,BS별도,MATCH(X$1,BS별도H,0),0)/100,"") | Y25: =IFERROR(VLOOKUP($D25,BS별도,MATCH(Y$1,BS별도H,0),0)/100,"") | Z25: =Y25 | AA25: =IFERROR(VLOOKUP($D25,BS별도,MATCH(AA$1,BS별도H,0),0)/100,"") | AB25: =IFERROR(VLOOKUP($D25,BS별도,MATCH(AB$1,BS별도H,0),0)/100,"") | AC25: =IFERROR(AB25*(1+변수!AC33),"") | AD25: =IFERROR(AC25*(1+변수!AD33),"") | AE25: =AD25 | AF25: =IFERROR(AD25*(1+변수!AF33),"") | AG25: =IFERROR(AF25*(1+변수!AG33),"") | AH25: =IFERROR(AG25*(1+변수!AH33),"") | AI25: =IFERROR(AH25*(1+변수!AI33),"") | AJ25: =AI25 | AK25: =IFERROR(AI25*(1+변수!AK33),"") | AL25: =IFERROR(AK25*(1+변수!AL33),"") | AM25: =IFERROR(AL25*(1+변수!AM33),"") | AN25: =IFERROR(AM25*(1+변수!AN33),"") | AO25: =AN25
A26: 이자발생자산 | B26: 재무상태 | C26: 억원 | D26: 이자발생자산 | E26: =IFERROR(VLOOKUP($D26,BS별도,MATCH(E$1,BS별도H,0),0)/100,"") | F26: 41.65 | G26: =IFERROR(VLOOKUP($D26,BS별도,MATCH(G$1,BS별도H,0),0)/100,"") | H26: =IFERROR(VLOOKUP($D26,BS별도,MATCH(H$1,BS별도H,0),0)/100,"") | I26: =IFERROR(VLOOKUP($D26,BS별도,MATCH(I$1,BS별도H,0),0)/100,"") | J26: =IFERROR(VLOOKUP($D26,BS별도,MATCH(J$1,BS별도H,0),0)/100,"") | K26: =J26 | L26: =IFERROR(VLOOKUP($D26,BS별도,MATCH(L$1,BS별도H,0),0)/100,"") | M26: =IFERROR(VLOOKUP($D26,BS별도,MATCH(M$1,BS별도H,0),0)/100,"") | N26: =IFERROR(VLOOKUP($D26,BS별도,MATCH(N$1,BS별도H,0),0)/100,"") | O26: =IFERROR(VLOOKUP($D26,BS별도,MATCH(O$1,BS별도H,0),0)/100,"") | P26: =O26 | Q26: =IFERROR(VLOOKUP($D26,BS별도,MATCH(Q$1,BS별도H,0),0)/100,"") | R26: =IFERROR(VLOOKUP($D26,BS별도,MATCH(R$1,BS별도H,0),0)/100,"") | S26: =IFERROR(VLOOKUP($D26,BS별도,MATCH(S$1,BS별도H,0),0)/100,"") | T26: =IFERROR(VLOOKUP($D26,BS별도,MATCH(T$1,BS별도H,0),0)/100,"") | U26: =T26 | V26: =IFERROR(VLOOKUP($D26,BS별도,MATCH(V$1,BS별도H,0),0)/100,"") | W26: =IFERROR(VLOOKUP($D26,BS별도,MATCH(W$1,BS별도H,0),0)/100,"") | X26: =IFERROR(VLOOKUP($D26,BS별도,MATCH(X$1,BS별도H,0),0)/100,"") | Y26: =IFERROR(VLOOKUP($D26,BS별도,MATCH(Y$1,BS별도H,0),0)/100,"") | Z26: =Y26 | AA26: =IFERROR(VLOOKUP($D26,BS별도,MATCH(AA$1,BS별도H,0),0)/100,"") | AB26: =IFERROR(VLOOKUP($D26,BS별도,MATCH(AB$1,BS별도H,0),0)/100,"") | AC26: =IFERROR(AB26*(1+변수!AC34),"") | AD26: =IFERROR(AC26*(1+변수!AD34),"") | AE26: =AD26 | AF26: =IFERROR(AD26*(1+변수!AF34),"") | AG26: =IFERROR(AF26*(1+변수!AG34),"") | AH26: =IFERROR(AG26*(1+변수!AH34),"") | AI26: =IFERROR(AH26*(1+변수!AI34),"") | AJ26: =AI26 | AK26: =IFERROR(AI26*(1+변수!AK34),"") | AL26: =IFERROR(AK26*(1+변수!AL34),"") | AM26: =IFERROR(AL26*(1+변수!AM34),"") | AN26: =IFERROR(AM26*(1+변수!AN34),"") | AO26: =AN26
A27: 현금및현금성자산 | B27: 재무상태 | C27: 억원 | D27: 현금및현금성자산 | E27: =IFERROR(VLOOKUP($D27,BS별도,MATCH(E$1,BS별도H,0),0)/100,"") | F27: 0.65 | G27: =IFERROR(VLOOKUP($D27,BS별도,MATCH(G$1,BS별도H,0),0)/100,"") | H27: =IFERROR(VLOOKUP($D27,BS별도,MATCH(H$1,BS별도H,0),0)/100,"") | I27: =IFERROR(VLOOKUP($D27,BS별도,MATCH(I$1,BS별도H,0),0)/100,"") | J27: =IFERROR(VLOOKUP($D27,BS별도,MATCH(J$1,BS별도H,0),0)/100,"") | K27: =J27 | L27: =IFERROR(VLOOKUP($D27,BS별도,MATCH(L$1,BS별도H,0),0)/100,"") | M27: =IFERROR(VLOOKUP($D27,BS별도,MATCH(M$1,BS별도H,0),0)/100,"") | N27: =IFERROR(VLOOKUP($D27,BS별도,MATCH(N$1,BS별도H,0),0)/100,"") | O27: =IFERROR(VLOOKUP($D27,BS별도,MATCH(O$1,BS별도H,0),0)/100,"") | P27: =O27 | Q27: =IFERROR(VLOOKUP($D27,BS별도,MATCH(Q$1,BS별도H,0),0)/100,"") | R27: =IFERROR(VLOOKUP($D27,BS별도,MATCH(R$1,BS별도H,0),0)/100,"") | S27: =IFERROR(VLOOKUP($D27,BS별도,MATCH(S$1,BS별도H,0),0)/100,"") | T27: =IFERROR(VLOOKUP($D27,BS별도,MATCH(T$1,BS별도H,0),0)/100,"") | U27: =T27 | V27: =IFERROR(VLOOKUP($D27,BS별도,MATCH(V$1,BS별도H,0),0)/100,"") | W27: =IFERROR(VLOOKUP($D27,BS별도,MATCH(W$1,BS별도H,0),0)/100,"") | X27: =IFERROR(VLOOKUP($D27,BS별도,MATCH(X$1,BS별도H,0),0)/100,"") | Y27: =IFERROR(VLOOKUP($D27,BS별도,MATCH(Y$1,BS별도H,0),0)/100,"") | Z27: =Y27 | AA27: =IFERROR(VLOOKUP($D27,BS별도,MATCH(AA$1,BS별도H,0),0)/100,"") | AB27: =IFERROR(VLOOKUP($D27,BS별도,MATCH(AB$1,BS별도H,0),0)/100,"") | AE27: =AD27 | AJ27: =AI27 | AO27: =AN27
A28: CAPEX | B28: 현금흐름 | C28: 억원 | D28: CAPEX | E28: =IFERROR(VLOOKUP($D28,BS별도,MATCH(E$1,BS별도H,0),0)/100,"") | G28: =IFERROR(VLOOKUP($D28,BS별도,MATCH(G$1,BS별도H,0),0)/100,"") | H28: =IFERROR(VLOOKUP($D28,BS별도,MATCH(H$1,BS별도H,0),0)/100,"") | I28: =IFERROR(VLOOKUP($D28,BS별도,MATCH(I$1,BS별도H,0),0)/100,"") | J28: =IFERROR(VLOOKUP($D28,BS별도,MATCH(J$1,BS별도H,0),0)/100,"") | K28: =SUM(G28:J28) | L28: =IFERROR(VLOOKUP($D28,BS별도,MATCH(L$1,BS별도H,0),0)/100,"") | M28: =IFERROR(VLOOKUP($D28,BS별도,MATCH(M$1,BS별도H,0),0)/100,"") | N28: =IFERROR(VLOOKUP($D28,BS별도,MATCH(N$1,BS별도H,0),0)/100,"") | O28: =IFERROR(VLOOKUP($D28,BS별도,MATCH(O$1,BS별도H,0),0)/100,"") | P28: =SUM(L28:O28) | Q28: =IFERROR(VLOOKUP($D28,BS별도,MATCH(Q$1,BS별도H,0),0)/100,"") | R28: =IFERROR(VLOOKUP($D28,BS별도,MATCH(R$1,BS별도H,0),0)/100,"") | S28: =IFERROR(VLOOKUP($D28,BS별도,MATCH(S$1,BS별도H,0),0)/100,"") | T28: =IFERROR(VLOOKUP($D28,BS별도,MATCH(T$1,BS별도H,0),0)/100,"") | U28: =SUM(Q28:T28) | V28: =IFERROR(VLOOKUP($D28,BS별도,MATCH(V$1,BS별도H,0),0)/100,"") | W28: =IFERROR(VLOOKUP($D28,BS별도,MATCH(W$1,BS별도H,0),0)/100,"") | X28: =IFERROR(VLOOKUP($D28,BS별도,MATCH(X$1,BS별도H,0),0)/100,"") | Y28: =IFERROR(VLOOKUP($D28,BS별도,MATCH(Y$1,BS별도H,0),0)/100,"") | Z28: =SUM(V28:Y28) | AA28: =IFERROR(VLOOKUP($D28,BS별도,MATCH(AA$1,BS별도H,0),0)/100,"") | AB28: =IFERROR(VLOOKUP($D28,BS별도,MATCH(AB$1,BS별도H,0),0)/100,"") | AC28: =IFERROR(X28*(1+변수!AC36),"") | AD28: =IFERROR(Y28*(1+변수!AD36),"") | AE28: =SUM(AA28:AD28) | AF28: =IFERROR(AA28*(1+변수!AF36),"") | AG28: =IFERROR(AB28*(1+변수!AG36),"") | AH28: =IFERROR(AC28*(1+변수!AH36),"") | AI28: =IFERROR(AD28*(1+변수!AI36),"") | AJ28: =SUM(AF28:AI28) | AK28: =IFERROR(AF28*(1+변수!AK36),"") | AL28: =IFERROR(AG28*(1+변수!AL36),"") | AM28: =IFERROR(AH28*(1+변수!AM36),"") | AN28: =IFERROR(AI28*(1+변수!AN36),"") | AO28: =SUM(AK28:AN28)
A29: 영업활동현금흐름 | B29: 현금흐름 | C29: 억원 | D29: 영업활동으로인한현금흐름 | E29: =IFERROR(VLOOKUP($D29,BS별도,MATCH(E$1,BS별도H,0),0)/100,"") | G29: =IFERROR(VLOOKUP($D29,BS별도,MATCH(G$1,BS별도H,0),0)/100,"") | H29: =IFERROR(VLOOKUP($D29,BS별도,MATCH(H$1,BS별도H,0),0)/100,"") | I29: =IFERROR(VLOOKUP($D29,BS별도,MATCH(I$1,BS별도H,0),0)/100,"") | J29: =IFERROR(VLOOKUP($D29,BS별도,MATCH(J$1,BS별도H,0),0)/100,"") | K29: =SUM(G29:J29) | L29: =IFERROR(VLOOKUP($D29,BS별도,MATCH(L$1,BS별도H,0),0)/100,"") | M29: =IFERROR(VLOOKUP($D29,BS별도,MATCH(M$1,BS별도H,0),0)/100,"") | N29: =IFERROR(VLOOKUP($D29,BS별도,MATCH(N$1,BS별도H,0),0)/100,"") | O29: =IFERROR(VLOOKUP($D29,BS별도,MATCH(O$1,BS별도H,0),0)/100,"") | P29: =SUM(L29:O29) | Q29: =IFERROR(VLOOKUP($D29,BS별도,MATCH(Q$1,BS별도H,0),0)/100,"") | R29: =IFERROR(VLOOKUP($D29,BS별도,MATCH(R$1,BS별도H,0),0)/100,"") | S29: =IFERROR(VLOOKUP($D29,BS별도,MATCH(S$1,BS별도H,0),0)/100,"") | T29: =IFERROR(VLOOKUP($D29,BS별도,MATCH(T$1,BS별도H,0),0)/100,"") | U29: =SUM(Q29:T29) | V29: =IFERROR(VLOOKUP($D29,BS별도,MATCH(V$1,BS별도H,0),0)/100,"") | W29: =IFERROR(VLOOKUP($D29,BS별도,MATCH(W$1,BS별도H,0),0)/100,"") | X29: =IFERROR(VLOOKUP($D29,BS별도,MATCH(X$1,BS별도H,0),0)/100,"") | Y29: =IFERROR(VLOOKUP($D29,BS별도,MATCH(Y$1,BS별도H,0),0)/100,"") | Z29: =SUM(V29:Y29) | AA29: =IFERROR(VLOOKUP($D29,BS별도,MATCH(AA$1,BS별도H,0),0)/100,"") | AB29: =IFERROR(VLOOKUP($D29,BS별도,MATCH(AB$1,BS별도H,0),0)/100,"") | AE29: =SUM(AA29:AD29) | AJ29: =SUM(AF29:AI29) | AO29: =SUM(AK29:AN29)
A30: 주식수 | B30: 주당 | C30: 백만주 | D30: 유통주식수 | E30: 11.145 | F30: =E30 | G30: 11.145 | H30: 11.145 | I30: 11.145 | J30: 11.145 | K30: =J30 | L30: 11.145 | M30: 11.145 | N30: 11.145 | O30: 11.145 | P30: =O30 | Q30: 11.145 | R30: 11.145 | S30: 11.145 | T30: 11.145 | U30: =T30 | V30: 11.145 | W30: 11.145 | X30: 11.145 | Y30: 11.145 | Z30: =Y30 | AA30: 11.145 | AB30: 11.145 | AC30: =IFERROR(AB30*(1+변수!AC38),"") | AD30: =IFERROR(AC30*(1+변수!AD38),"") | AE30: =AD30 | AF30: =IFERROR(AD30*(1+변수!AF38),"") | AG30: =IFERROR(AF30*(1+변수!AG38),"") | AH30: =IFERROR(AG30*(1+변수!AH38),"") | AI30: =IFERROR(AH30*(1+변수!AI38),"") | AJ30: =AI30 | AK30: =IFERROR(AI30*(1+변수!AK38),"") | AL30: =IFERROR(AK30*(1+변수!AL38),"") | AM30: =IFERROR(AL30*(1+변수!AM38),"") | AN30: =IFERROR(AM30*(1+변수!AN38),"") | AO30: =AN30
A31: EPS | B31: 주당 | C31: 원 | D31: EPS | E31: =IFERROR(E19*100/E30,"") | G31: =IFERROR(G19*100/G30,"") | H31: =IFERROR(H19*100/H30,"") | I31: =IFERROR(I19*100/I30,"") | J31: =IFERROR(J19*100/J30,"") | K31: =SUM(G31:J31) | L31: =IFERROR(L19*100/L30,"") | M31: =IFERROR(M19*100/M30,"") | N31: =IFERROR(N19*100/N30,"") | O31: =IFERROR(O19*100/O30,"") | P31: =SUM(L31:O31) | Q31: =IFERROR(Q19*100/Q30,"") | R31: =IFERROR(R19*100/R30,"") | S31: =IFERROR(S19*100/S30,"") | T31: =IFERROR(T19*100/T30,"") | U31: =SUM(Q31:T31) | V31: =IFERROR(V19*100/V30,"") | W31: =IFERROR(W19*100/W30,"") | X31: =IFERROR(X19*100/X30,"") | Y31: =IFERROR(Y19*100/Y30,"") | Z31: =SUM(V31:Y31) | AA31: =IFERROR(AA19*100/AA30,"") | AB31: =IFERROR(AB19*100/AB30,"") | AC31: =IFERROR(AC19*100/AC30,"") | AD31: =IFERROR(AD19*100/AD30,"") | AE31: =SUM(AA31:AD31) | AF31: =IFERROR(AF19*100/AF30,"") | AG31: =IFERROR(AG19*100/AG30,"") | AH31: =IFERROR(AH19*100/AH30,"") | AI31: =IFERROR(AI19*100/AI30,"") | AJ31: =SUM(AF31:AI31) | AK31: =IFERROR(AK19*100/AK30,"") | AL31: =IFERROR(AL19*100/AL30,"") | AM31: =IFERROR(AM19*100/AM30,"") | AN31: =IFERROR(AN19*100/AN30,"") | AO31: =SUM(AK31:AN31)
A32: BPS | B32: 주당 | C32: 원 | D32: BPS | E32: =IFERROR(E23*100/E30,"") | F32: =E32 | G32: =IFERROR(G23*100/G30,"") | H32: =IFERROR(H23*100/H30,"") | I32: =IFERROR(I23*100/I30,"") | J32: =IFERROR(J23*100/J30,"") | K32: =J32 | L32: =IFERROR(L23*100/L30,"") | M32: =IFERROR(M23*100/M30,"") | N32: =IFERROR(N23*100/N30,"") | O32: =IFERROR(O23*100/O30,"") | P32: =O32 | Q32: =IFERROR(Q23*100/Q30,"") | R32: =IFERROR(R23*100/R30,"") | S32: =IFERROR(S23*100/S30,"") | T32: =IFERROR(T23*100/T30,"") | U32: =T32 | V32: =IFERROR(V23*100/V30,"") | W32: =IFERROR(W23*100/W30,"") | X32: =IFERROR(X23*100/X30,"") | Y32: =IFERROR(Y23*100/Y30,"") | Z32: =Y32 | AA32: =IFERROR(AA23*100/AA30,"") | AB32: =IFERROR(AB23*100/AB30,"") | AC32: =IFERROR(AC23*100/AC30,"") | AD32: =IFERROR(AD23*100/AD30,"") | AE32: =AD32 | AF32: =IFERROR(AF23*100/AF30,"") | AG32: =IFERROR(AG23*100/AG30,"") | AH32: =IFERROR(AH23*100/AH30,"") | AI32: =IFERROR(AI23*100/AI30,"") | AJ32: =AI32 | AK32: =IFERROR(AK23*100/AK30,"") | AL32: =IFERROR(AL23*100/AL30,"") | AM32: =IFERROR(AM23*100/AM30,"") | AN32: =IFERROR(AN23*100/AN30,"") | AO32: =AN32
A33: DPS | B33: 주당 | C33: 원 | D33: DPS(보통주) | E33: 0 | F33: 0 | J33: 0 | K33: =SUM(G33:J33) | O33: 0 | P33: =SUM(L33:O33) | T33: 0 | U33: =SUM(Q33:T33) | Y33: 0 | Z33: =SUM(V33:Y33) | AD33: =변수!AD39 | AE33: =SUM(AA33:AD33) | AI33: =변수!AI39 | AJ33: =SUM(AF33:AI33) | AN33: =변수!AN39 | AO33: =SUM(AK33:AN33)
A34: PER | B34: 주당 | C34: 배 | D34: PER | F34: =E34 | I34: =IFERROR(변수!I18/(E31+G31+H31+I31),"") | J34: =IFERROR(변수!J18/(G31+H31+I31+J31),"") | K34: =J34 | M34: =IFERROR(변수!M18/(I31+J31+L31+M31),"") | N34: =IFERROR(변수!N18/(J31+L31+M31+N31),"") | O34: =IFERROR(변수!O18/(L31+M31+N31+O31),"") | P34: =O34 | Q34: =IFERROR(변수!Q18/(M31+N31+O31+Q31),"") | R34: =IFERROR(변수!R18/(N31+O31+Q31+R31),"") | S34: =IFERROR(변수!S18/(O31+Q31+R31+S31),"") | T34: =IFERROR(변수!T18/(Q31+R31+S31+T31),"") | U34: =T34 | V34: =IFERROR(변수!V18/(R31+S31+T31+V31),"") | W34: =IFERROR(변수!W18/(S31+T31+V31+W31),"") | X34: =IFERROR(변수!X18/(T31+V31+W31+X31),"") | Z34: =Y34 | AD34: =IFERROR(변수!$D$42/(AA31+AB31+AC31+AD31),"") | AE34: =AD34 | AF34: =IFERROR(변수!$D$42/(AB31+AC31+AD31+AF31),"") | AG34: =IFERROR(변수!$D$42/(AC31+AD31+AF31+AG31),"") | AH34: =IFERROR(변수!$D$42/(AD31+AF31+AG31+AH31),"") | AI34: =IFERROR(변수!$D$42/(AF31+AG31+AH31+AI31),"") | AJ34: =AI34 | AK34: =IFERROR(변수!$D$42/(AG31+AH31+AI31+AK31),"") | AL34: =IFERROR(변수!$D$42/(AH31+AI31+AK31+AL31),"") | AM34: =IFERROR(변수!$D$42/(AI31+AK31+AL31+AM31),"") | AN34: =IFERROR(변수!$D$42/(AK31+AL31+AM31+AN31),"") | AO34: =AN34
A35: PBR | B35: 주당 | C35: 배 | D35: PBR | E35: =IFERROR(변수!E18/E32,"") | F35: =E35 | G35: =IFERROR(변수!G18/G32,"") | H35: =IFERROR(변수!H18/H32,"") | I35: =IFERROR(변수!I18/I32,"") | J35: =IFERROR(변수!J18/J32,"") | K35: =J35 | L35: =IFERROR(변수!L18/L32,"") | M35: =IFERROR(변수!M18/M32,"") | N35: =IFERROR(변수!N18/N32,"") | O35: =IFERROR(변수!O18/O32,"") | P35: =O35 | Q35: =IFERROR(변수!Q18/Q32,"") | R35: =IFERROR(변수!R18/R32,"") | S35: =IFERROR(변수!S18/S32,"") | T35: =IFERROR(변수!T18/T32,"") | U35: =T35 | V35: =IFERROR(변수!V18/V32,"") | W35: =IFERROR(변수!W18/W32,"") | X35: =IFERROR(변수!X18/X32,"") | Y35: =IFERROR(변수!Y18/Y32,"") | Z35: =Y35 | AA35: =IFERROR(변수!AA18/AA32,"") | AB35: =IFERROR(변수!AB18/AB32,"") | AC35: =IFERROR(변수!$D$42/AC32,"") | AD35: =IFERROR(변수!$D$42/AD32,"") | AE35: =AD35 | AF35: =IFERROR(변수!$D$42/AF32,"") | AG35: =IFERROR(변수!$D$42/AG32,"") | AH35: =IFERROR(변수!$D$42/AH32,"") | AI35: =IFERROR(변수!$D$42/AI32,"") | AJ35: =AI35 | AK35: =IFERROR(변수!$D$42/AK32,"") | AL35: =IFERROR(변수!$D$42/AL32,"") | AM35: =IFERROR(변수!$D$42/AM32,"") | AN35: =IFERROR(변수!$D$42/AN32,"") | AO35: =AN35
A36: 매출전사 | B36: 사업부 | C36: 억원 | D36: 매출 전사(부문 미분리) | E36: 135.39 | G36: 132.95 | H36: 136.75 | I36: 118.01 | J36: 156 | K36: =SUM(G36:J36) | L36: 124.48 | M36: 114.73 | N36: 136.82 | O36: 162.08 | P36: =SUM(L36:O36) | Q36: 116.71 | R36: 118.63 | S36: 99.5 | T36: 138 | U36: =SUM(Q36:T36) | V36: 94.24 | W36: 116.73 | X36: 97.77 | Y36: 89.99 | Z36: =SUM(V36:Y36) | AA36: 88.26 | AB36: 110.76 | AC36: =IFERROR(AC5,"") | AD36: =IFERROR(AD5,"") | AE36: =SUM(AA36:AD36) | AF36: =IFERROR(AF5,"") | AG36: =IFERROR(AG5,"") | AH36: =IFERROR(AH5,"") | AI36: =IFERROR(AI5,"") | AJ36: =SUM(AF36:AI36) | AK36: =IFERROR(AK5,"") | AL36: =IFERROR(AL5,"") | AM36: =IFERROR(AM5,"") | AN36: =IFERROR(AN5,"") | AO36: =SUM(AK36:AN36)
A37: OP전사 | B37: 사업부 | C37: 억원 | D37: OP 전사(부문 미분리) | E37: -4.19 | G37: -6.84 | H37: 0.66 | I37: -1.2 | J37: 2.2 | K37: =SUM(G37:J37) | L37: 2.58 | M37: 5.7 | N37: 9.2 | O37: 6.7 | P37: =SUM(L37:O37) | Q37: 0.62 | R37: 3.2 | S37: -3.15 | T37: 10.08 | U37: =SUM(Q37:T37) | V37: 0.74 | W37: 3.54 | X37: -3.27 | Y37: -2.78 | Z37: =SUM(V37:Y37) | AA37: 0.59 | AB37: 1.53 | AC37: =IFERROR(AC9,"") | AD37: =IFERROR(AD9,"") | AE37: =SUM(AA37:AD37) | AF37: =IFERROR(AF9,"") | AG37: =IFERROR(AG9,"") | AH37: =IFERROR(AH9,"") | AI37: =IFERROR(AI9,"") | AJ37: =SUM(AF37:AI37) | AK37: =IFERROR(AK9,"") | AL37: =IFERROR(AL9,"") | AM37: =IFERROR(AM9,"") | AN37: =IFERROR(AN9,"") | AO37: =SUM(AK37:AN37)
B38: 비율(참고)
A39: NPM | C39: % | D39: 지배주주순이익 / 매출액 | E39: =IFERROR(E19/E5,"") | F39: =IFERROR(F19/F5,"") | G39: =IFERROR(G19/G5,"") | H39: =IFERROR(H19/H5,"") | I39: =IFERROR(I19/I5,"") | J39: =IFERROR(J19/J5,"") | K39: =IFERROR(K19/K5,"") | L39: =IFERROR(L19/L5,"") | ... AO39: =IFERROR(AO19/AO5,"")
A40: 매출원가율 | C40: % | D40: 매출원가 / 매출액 | E40: =IFERROR(E6/E5,"") | F40: =IFERROR(F6/F5,"") | G40: =IFERROR(G6/G5,"") | H40: =IFERROR(H6/H5,"") | I40: =IFERROR(I6/I5,"") | J40: =IFERROR(J6/J5,"") | K40: =IFERROR(K6/K5,"") | L40: =IFERROR(L6/L5,"") | ... AO40: =IFERROR(AO6/AO5,"")
A41: 판관비율 | C41: % | D41: 판관비 / 매출액 | E41: =IFERROR(E8/E5,"") | F41: =IFERROR(F8/F5,"") | G41: =IFERROR(G8/G5,"") | H41: =IFERROR(H8/H5,"") | I41: =IFERROR(I8/I5,"") | J41: =IFERROR(J8/J5,"") | K41: =IFERROR(K8/K5,"") | L41: =IFERROR(L8/L5,"") | ... AO41: =IFERROR(AO8/AO5,"")

Sheet 분기
C1: 이름: 분기H — subQ 를 이름으로 VLOOKUP(억원) | E1: 4Q21 | F1: 1Q22 | G1: 2Q22 | H1: 3Q22 | I1: 4Q22 | J1: 1Q23 | K1: 2Q23 | L1: 3Q23 | M1: 4Q23 | N1: 1Q24 | O1: 2Q24 | P1: 3Q24 | Q1: 4Q24 | R1: 1Q25 | S1: 2Q25 | T1: 3Q25 | U1: 4Q25 | V1: 1Q26 | W1: 2Q26 | X1: 3Q26 | Y1: 4Q26 | Z1: 1Q27 | AA1: 2Q27 | AB1: 3Q27 | AC1: 4Q27 | AD1: 1Q28 | AE1: 2Q28 | AF1: 3Q28 | AG1: 4Q28
C2: 종가: | D2: =변수!D42
C3: 기준일: | D3: 20261014 | E3: 1 | F3: 2 | G3: 3 | H3: 4 | I3: 5 | J3: 6 | K3: 7 | L3: 8 | M3: 9 | N3: 10 | O3: 11 | P3: 12 | Q3: 13 | R3: 14 | S3: 15 | T3: 16 | U3: 17 | V3: 18 | W3: 19 | X3: 20 | Y3: 21 | Z3: 22 | AA3: 23 | AB3: 24 | AC3: 25 | AD3: 26 | AE3: 27 | AF3: 28 | AG3: 29
E4: 2021.12 | F4: 2022.03 | G4: 2022.06 | H4: 2022.09 | I4: 2022.12 | J4: 2023.03 | K4: 2023.06 | L4: 2023.09 | M4: 2023.12 | N4: 2024.03 | O4: 2024.06 | P4: 2024.09 | Q4: 2024.12 | R4: 2025.03 | S4: 2025.06 | T4: 2025.09 | U4: 2025.12 | V4: 2026.03 | W4: 2026.06 | X4: 2026.09 | Y4: 2026.12 | Z4: 2027.03 | AA4: 2027.06 | AB4: 2027.09 | AC4: 2027.12 | AD4: 2028.03 | AE4: 2028.06 | AF4: 2028.09 | AG4: 2028.12
A5: 매출액 | D5: 매출액 | E5: =IFERROR(VLOOKUP($A5,subQ,MATCH(E$1,SUBQH,0),0),"") | F5: =IFERROR(VLOOKUP($A5,subQ,MATCH(F$1,SUBQH,0),0),"") | G5: =IFERROR(VLOOKUP($A5,subQ,MATCH(G$1,SUBQH,0),0),"") | H5: =IFERROR(VLOOKUP($A5,subQ,MATCH(H$1,SUBQH,0),0),"") | I5: =IFERROR(VLOOKUP($A5,subQ,MATCH(I$1,SUBQH,0),0),"") | J5: =IFERROR(VLOOKUP($A5,subQ,MATCH(J$1,SUBQH,0),0),"") | K5: =IFERROR(VLOOKUP($A5,subQ,MATCH(K$1,SUBQH,0),0),"") | L5: =IFERROR(VLOOKUP($A5,subQ,MATCH(L$1,SUBQH,0),0),"") | ... AG5: =IFERROR(VLOOKUP($A5,subQ,MATCH(AG$1,SUBQH,0),0),"")
A6: 매출원가 | D6: 매출원가 | E6: =IFERROR(VLOOKUP($A6,subQ,MATCH(E$1,SUBQH,0),0),"") | F6: =IFERROR(VLOOKUP($A6,subQ,MATCH(F$1,SUBQH,0),0),"") | G6: =IFERROR(VLOOKUP($A6,subQ,MATCH(G$1,SUBQH,0),0),"") | H6: =IFERROR(VLOOKUP($A6,subQ,MATCH(H$1,SUBQH,0),0),"") | I6: =IFERROR(VLOOKUP($A6,subQ,MATCH(I$1,SUBQH,0),0),"") | J6: =IFERROR(VLOOKUP($A6,subQ,MATCH(J$1,SUBQH,0),0),"") | K6: =IFERROR(VLOOKUP($A6,subQ,MATCH(K$1,SUBQH,0),0),"") | L6: =IFERROR(VLOOKUP($A6,subQ,MATCH(L$1,SUBQH,0),0),"") | ... AG6: =IFERROR(VLOOKUP($A6,subQ,MATCH(AG$1,SUBQH,0),0),"")
A7: 매출총이익 | D7: 매출총이익 | E7: =IFERROR(VLOOKUP($A7,subQ,MATCH(E$1,SUBQH,0),0),"") | F7: =IFERROR(VLOOKUP($A7,subQ,MATCH(F$1,SUBQH,0),0),"") | G7: =IFERROR(VLOOKUP($A7,subQ,MATCH(G$1,SUBQH,0),0),"") | H7: =IFERROR(VLOOKUP($A7,subQ,MATCH(H$1,SUBQH,0),0),"") | I7: =IFERROR(VLOOKUP($A7,subQ,MATCH(I$1,SUBQH,0),0),"") | J7: =IFERROR(VLOOKUP($A7,subQ,MATCH(J$1,SUBQH,0),0),"") | K7: =IFERROR(VLOOKUP($A7,subQ,MATCH(K$1,SUBQH,0),0),"") | L7: =IFERROR(VLOOKUP($A7,subQ,MATCH(L$1,SUBQH,0),0),"") | ... AG7: =IFERROR(VLOOKUP($A7,subQ,MATCH(AG$1,SUBQH,0),0),"")
A8: 판관비 | D8: 판매비와관리비 | E8: =IFERROR(VLOOKUP($A8,subQ,MATCH(E$1,SUBQH,0),0),"") | F8: =IFERROR(VLOOKUP($A8,subQ,MATCH(F$1,SUBQH,0),0),"") | G8: =IFERROR(VLOOKUP($A8,subQ,MATCH(G$1,SUBQH,0),0),"") | H8: =IFERROR(VLOOKUP($A8,subQ,MATCH(H$1,SUBQH,0),0),"") | I8: =IFERROR(VLOOKUP($A8,subQ,MATCH(I$1,SUBQH,0),0),"") | J8: =IFERROR(VLOOKUP($A8,subQ,MATCH(J$1,SUBQH,0),0),"") | K8: =IFERROR(VLOOKUP($A8,subQ,MATCH(K$1,SUBQH,0),0),"") | L8: =IFERROR(VLOOKUP($A8,subQ,MATCH(L$1,SUBQH,0),0),"") | ... AG8: =IFERROR(VLOOKUP($A8,subQ,MATCH(AG$1,SUBQH,0),0),"")
A9: 영업이익 | D9: 영업이익 | E9: =IFERROR(VLOOKUP($A9,subQ,MATCH(E$1,SUBQH,0),0),"") | F9: =IFERROR(VLOOKUP($A9,subQ,MATCH(F$1,SUBQH,0),0),"") | G9: =IFERROR(VLOOKUP($A9,subQ,MATCH(G$1,SUBQH,0),0),"") | H9: =IFERROR(VLOOKUP($A9,subQ,MATCH(H$1,SUBQH,0),0),"") | I9: =IFERROR(VLOOKUP($A9,subQ,MATCH(I$1,SUBQH,0),0),"") | J9: =IFERROR(VLOOKUP($A9,subQ,MATCH(J$1,SUBQH,0),0),"") | K9: =IFERROR(VLOOKUP($A9,subQ,MATCH(K$1,SUBQH,0),0),"") | L9: =IFERROR(VLOOKUP($A9,subQ,MATCH(L$1,SUBQH,0),0),"") | ... AG9: =IFERROR(VLOOKUP($A9,subQ,MATCH(AG$1,SUBQH,0),0),"")
A10: OPM | D10: 영업이익률 | E10: =IFERROR(VLOOKUP($A10,subQ,MATCH(E$1,SUBQH,0),0),"") | F10: =IFERROR(VLOOKUP($A10,subQ,MATCH(F$1,SUBQH,0),0),"") | G10: =IFERROR(VLOOKUP($A10,subQ,MATCH(G$1,SUBQH,0),0),"") | H10: =IFERROR(VLOOKUP($A10,subQ,MATCH(H$1,SUBQH,0),0),"") | I10: =IFERROR(VLOOKUP($A10,subQ,MATCH(I$1,SUBQH,0),0),"") | J10: =IFERROR(VLOOKUP($A10,subQ,MATCH(J$1,SUBQH,0),0),"") | K10: =IFERROR(VLOOKUP($A10,subQ,MATCH(K$1,SUBQH,0),0),"") | L10: =IFERROR(VLOOKUP($A10,subQ,MATCH(L$1,SUBQH,0),0),"") | ... AG10: =IFERROR(VLOOKUP($A10,subQ,MATCH(AG$1,SUBQH,0),0),"")
A11: 금융손익 | D11: 금융손익(이자·환 포함) | E11: =IFERROR(VLOOKUP($A11,subQ,MATCH(E$1,SUBQH,0),0),"") | F11: =IFERROR(VLOOKUP($A11,subQ,MATCH(F$1,SUBQH,0),0),"") | G11: =IFERROR(VLOOKUP($A11,subQ,MATCH(G$1,SUBQH,0),0),"") | H11: =IFERROR(VLOOKUP($A11,subQ,MATCH(H$1,SUBQH,0),0),"") | I11: =IFERROR(VLOOKUP($A11,subQ,MATCH(I$1,SUBQH,0),0),"") | J11: =IFERROR(VLOOKUP($A11,subQ,MATCH(J$1,SUBQH,0),0),"") | K11: =IFERROR(VLOOKUP($A11,subQ,MATCH(K$1,SUBQH,0),0),"") | L11: =IFERROR(VLOOKUP($A11,subQ,MATCH(L$1,SUBQH,0),0),"") | ... AG11: =IFERROR(VLOOKUP($A11,subQ,MATCH(AG$1,SUBQH,0),0),"")
A12: 이자손익 | D12: 이자손익(이자수익 − 이자비용) | E12: =IFERROR(VLOOKUP($A12,subQ,MATCH(E$1,SUBQH,0),0),"") | F12: =IFERROR(VLOOKUP($A12,subQ,MATCH(F$1,SUBQH,0),0),"") | G12: =IFERROR(VLOOKUP($A12,subQ,MATCH(G$1,SUBQH,0),0),"") | H12: =IFERROR(VLOOKUP($A12,subQ,MATCH(H$1,SUBQH,0),0),"") | I12: =IFERROR(VLOOKUP($A12,subQ,MATCH(I$1,SUBQH,0),0),"") | J12: =IFERROR(VLOOKUP($A12,subQ,MATCH(J$1,SUBQH,0),0),"") | K12: =IFERROR(VLOOKUP($A12,subQ,MATCH(K$1,SUBQH,0),0),"") | L12: =IFERROR(VLOOKUP($A12,subQ,MATCH(L$1,SUBQH,0),0),"") | ... AG12: =IFERROR(VLOOKUP($A12,subQ,MATCH(AG$1,SUBQH,0),0),"")
A13: 외환손익 | D13: 외환손익(실적만; 추정 환효과는 환관련손익) | E13: =IFERROR(VLOOKUP($A13,subQ,MATCH(E$1,SUBQH,0),0),"") | F13: =IFERROR(VLOOKUP($A13,subQ,MATCH(F$1,SUBQH,0),0),"") | G13: =IFERROR(VLOOKUP($A13,subQ,MATCH(G$1,SUBQH,0),0),"") | H13: =IFERROR(VLOOKUP($A13,subQ,MATCH(H$1,SUBQH,0),0),"") | I13: =IFERROR(VLOOKUP($A13,subQ,MATCH(I$1,SUBQH,0),0),"") | J13: =IFERROR(VLOOKUP($A13,subQ,MATCH(J$1,SUBQH,0),0),"") | K13: =IFERROR(VLOOKUP($A13,subQ,MATCH(K$1,SUBQH,0),0),"") | L13: =IFERROR(VLOOKUP($A13,subQ,MATCH(L$1,SUBQH,0),0),"") | ... AG13: =IFERROR(VLOOKUP($A13,subQ,MATCH(AG$1,SUBQH,0),0),"")
A14: 기타영업외손익 | D14: 기타영업외손익 | E14: =IFERROR(VLOOKUP($A14,subQ,MATCH(E$1,SUBQH,0),0),"") | F14: =IFERROR(VLOOKUP($A14,subQ,MATCH(F$1,SUBQH,0),0),"") | G14: =IFERROR(VLOOKUP($A14,subQ,MATCH(G$1,SUBQH,0),0),"") | H14: =IFERROR(VLOOKUP($A14,subQ,MATCH(H$1,SUBQH,0),0),"") | I14: =IFERROR(VLOOKUP($A14,subQ,MATCH(I$1,SUBQH,0),0),"") | J14: =IFERROR(VLOOKUP($A14,subQ,MATCH(J$1,SUBQH,0),0),"") | K14: =IFERROR(VLOOKUP($A14,subQ,MATCH(K$1,SUBQH,0),0),"") | L14: =IFERROR(VLOOKUP($A14,subQ,MATCH(L$1,SUBQH,0),0),"") | ... AG14: =IFERROR(VLOOKUP($A14,subQ,MATCH(AG$1,SUBQH,0),0),"")
A15: 지분법손익 | D15: 지분법손익 | E15: =IFERROR(VLOOKUP($A15,subQ,MATCH(E$1,SUBQH,0),0),"") | F15: =IFERROR(VLOOKUP($A15,subQ,MATCH(F$1,SUBQH,0),0),"") | G15: =IFERROR(VLOOKUP($A15,subQ,MATCH(G$1,SUBQH,0),0),"") | H15: =IFERROR(VLOOKUP($A15,subQ,MATCH(H$1,SUBQH,0),0),"") | I15: =IFERROR(VLOOKUP($A15,subQ,MATCH(I$1,SUBQH,0),0),"") | J15: =IFERROR(VLOOKUP($A15,subQ,MATCH(J$1,SUBQH,0),0),"") | K15: =IFERROR(VLOOKUP($A15,subQ,MATCH(K$1,SUBQH,0),0),"") | L15: =IFERROR(VLOOKUP($A15,subQ,MATCH(L$1,SUBQH,0),0),"") | ... AG15: =IFERROR(VLOOKUP($A15,subQ,MATCH(AG$1,SUBQH,0),0),"")
A16: 세전이익 | D16: 법인세비용차감전이익 | E16: =IFERROR(VLOOKUP($A16,subQ,MATCH(E$1,SUBQH,0),0),"") | F16: =IFERROR(VLOOKUP($A16,subQ,MATCH(F$1,SUBQH,0),0),"") | G16: =IFERROR(VLOOKUP($A16,subQ,MATCH(G$1,SUBQH,0),0),"") | H16: =IFERROR(VLOOKUP($A16,subQ,MATCH(H$1,SUBQH,0),0),"") | I16: =IFERROR(VLOOKUP($A16,subQ,MATCH(I$1,SUBQH,0),0),"") | J16: =IFERROR(VLOOKUP($A16,subQ,MATCH(J$1,SUBQH,0),0),"") | K16: =IFERROR(VLOOKUP($A16,subQ,MATCH(K$1,SUBQH,0),0),"") | L16: =IFERROR(VLOOKUP($A16,subQ,MATCH(L$1,SUBQH,0),0),"") | ... AG16: =IFERROR(VLOOKUP($A16,subQ,MATCH(AG$1,SUBQH,0),0),"")
... A38: NPM | D38: NPM | E38: =IFERROR(VLOOKUP($A38,subQ,MATCH(E$1,SUBQH,0),0),"") | F38: =IFERROR(VLOOKUP($A38,subQ,MATCH(F$1,SUBQH,0),0),"") | G38: =IFERROR(VLOOKUP($A38,subQ,MATCH(G$1,SUBQH,0),0),"") | H38: =IFERROR(VLOOKUP($A38,subQ,MATCH(H$1,SUBQH,0),0),"") | I38: =IFERROR(VLOOKUP($A38,subQ,MATCH(I$1,SUBQH,0),0),"") | J38: =IFERROR(VLOOKUP($A38,subQ,MATCH(J$1,SUBQH,0),0),"") | K38: =IFERROR(VLOOKUP($A38,subQ,MATCH(K$1,SUBQH,0),0),"") | L38: =IFERROR(VLOOKUP($A38,subQ,MATCH(L$1,SUBQH,0),0),"") | ... AG38: =IFERROR(VLOOKUP($A38,subQ,MATCH(AG$1,SUBQH,0),0),"")
A39: 매출액 YoY | D39: 매출액 YoY | I39: =IFERROR(I5/E5-1,"") | J39: =IFERROR(J5/F5-1,"") | K39: =IFERROR(K5/G5-1,"") | L39: =IFERROR(L5/H5-1,"") | M39: =IFERROR(M5/I5-1,"") | N39: =IFERROR(N5/J5-1,"") | O39: =IFERROR(O5/K5-1,"") | P39: =IFERROR(P5/L5-1,"") | ... AG39: =IFERROR(AG5/AC5-1,"")
A40: 영업이익 YoY | D40: 영업이익 YoY | I40: =IFERROR(I9/E9-1,"") | J40: =IFERROR(J9/F9-1,"") | K40: =IFERROR(K9/G9-1,"") | L40: =IFERROR(L9/H9-1,"") | M40: =IFERROR(M9/I9-1,"") | N40: =IFERROR(N9/J9-1,"") | O40: =IFERROR(O9/K9-1,"") | P40: =IFERROR(P9/L9-1,"") | ... AG40: =IFERROR(AG9/AC9-1,"")
A41: 지배주주순이익 YoY | D41: 지배주주순이익 YoY | I41: =IFERROR(I19/E19-1,"") | J41: =IFERROR(J19/F19-1,"") | K41: =IFERROR(K19/G19-1,"") | L41: =IFERROR(L19/H19-1,"") | M41: =IFERROR(M19/I19-1,"") | N41: =IFERROR(N19/J19-1,"") | O41: =IFERROR(O19/K19-1,"") | P41: =IFERROR(P19/L19-1,"") | ... AG41: =IFERROR(AG19/AC19-1,"")

Sheet 연간예상
C1: 이름: 연간예상H — subQ 를 이름으로 VLOOKUP(억원) | E1: 2021 | F1: 2022 | G1: 2023 | H1: 2024 | I1: 2025 | J1: 2026 | K1: 2027 | L1: 2028
C2: 종가: | D2: =변수!D42
C3: 기준일: | D3: 20261014 | E3: 1 | F3: 2 | G3: 3 | H3: 4 | I3: 5 | J3: 6 | K3: 7 | L3: 8
E4: 2021.12A | F4: 2022.12A | G4: 2023.12A | H4: 2024.12A | I4: 2025.12A | J4: 2026.12A | K4: 2027.12A | L4: 2028.12A
A5: 매출액 | D5: 매출액 | E5: =IFERROR(VLOOKUP($A5,subQ,MATCH(E$1,SUBQH,0),0),"") | F5: =IFERROR(VLOOKUP($A5,subQ,MATCH(F$1,SUBQH,0),0),"") | G5: =IFERROR(VLOOKUP($A5,subQ,MATCH(G$1,SUBQH,0),0),"") | H5: =IFERROR(VLOOKUP($A5,subQ,MATCH(H$1,SUBQH,0),0),"") | I5: =IFERROR(VLOOKUP($A5,subQ,MATCH(I$1,SUBQH,0),0),"") | J5: =IFERROR(VLOOKUP($A5,subQ,MATCH(J$1,SUBQH,0),0),"") | K5: =IFERROR(VLOOKUP($A5,subQ,MATCH(K$1,SUBQH,0),0),"") | L5: =IFERROR(VLOOKUP($A5,subQ,MATCH(L$1,SUBQH,0),0),"")
A6: 매출원가 | D6: 매출원가 | E6: =IFERROR(VLOOKUP($A6,subQ,MATCH(E$1,SUBQH,0),0),"") | F6: =IFERROR(VLOOKUP($A6,subQ,MATCH(F$1,SUBQH,0),0),"") | G6: =IFERROR(VLOOKUP($A6,subQ,MATCH(G$1,SUBQH,0),0),"") | H6: =IFERROR(VLOOKUP($A6,subQ,MATCH(H$1,SUBQH,0),0),"") | I6: =IFERROR(VLOOKUP($A6,subQ,MATCH(I$1,SUBQH,0),0),"") | J6: =IFERROR(VLOOKUP($A6,subQ,MATCH(J$1,SUBQH,0),0),"") | K6: =IFERROR(VLOOKUP($A6,subQ,MATCH(K$1,SUBQH,0),0),"") | L6: =IFERROR(VLOOKUP($A6,subQ,MATCH(L$1,SUBQH,0),0),"")
A7: 매출총이익 | D7: 매출총이익 | E7: =IFERROR(VLOOKUP($A7,subQ,MATCH(E$1,SUBQH,0),0),"") | F7: =IFERROR(VLOOKUP($A7,subQ,MATCH(F$1,SUBQH,0),0),"") | G7: =IFERROR(VLOOKUP($A7,subQ,MATCH(G$1,SUBQH,0),0),"") | H7: =IFERROR(VLOOKUP($A7,subQ,MATCH(H$1,SUBQH,0),0),"") | I7: =IFERROR(VLOOKUP($A7,subQ,MATCH(I$1,SUBQH,0),0),"") | J7: =IFERROR(VLOOKUP($A7,subQ,MATCH(J$1,SUBQH,0),0),"") | K7: =IFERROR(VLOOKUP($A7,subQ,MATCH(K$1,SUBQH,0),0),"") | L7: =IFERROR(VLOOKUP($A7,subQ,MATCH(L$1,SUBQH,0),0),"")
A8: 판관비 | D8: 판매비와관리비 | E8: =IFERROR(VLOOKUP($A8,subQ,MATCH(E$1,SUBQH,0),0),"") | F8: =IFERROR(VLOOKUP($A8,subQ,MATCH(F$1,SUBQH,0),0),"") | G8: =IFERROR(VLOOKUP($A8,subQ,MATCH(G$1,SUBQH,0),0),"") | H8: =IFERROR(VLOOKUP($A8,subQ,MATCH(H$1,SUBQH,0),0),"") | I8: =IFERROR(VLOOKUP($A8,subQ,MATCH(I$1,SUBQH,0),0),"") | J8: =IFERROR(VLOOKUP($A8,subQ,MATCH(J$1,SUBQH,0),0),"") | K8: =IFERROR(VLOOKUP($A8,subQ,MATCH(K$1,SUBQH,0),0),"") | L8: =IFERROR(VLOOKUP($A8,subQ,MATCH(L$1,SUBQH,0),0),"")
A9: 영업이익 | D9: 영업이익 | E9: =IFERROR(VLOOKUP($A9,subQ,MATCH(E$1,SUBQH,0),0),"") | F9: =IFERROR(VLOOKUP($A9,subQ,MATCH(F$1,SUBQH,0),0),"") | G9: =IFERROR(VLOOKUP($A9,subQ,MATCH(G$1,SUBQH,0),0),"") | H9: =IFERROR(VLOOKUP($A9,subQ,MATCH(H$1,SUBQH,0),0),"") | I9: =IFERROR(VLOOKUP($A9,subQ,MATCH(I$1,SUBQH,0),0),"") | J9: =IFERROR(VLOOKUP($A9,subQ,MATCH(J$1,SUBQH,0),0),"") | K9: =IFERROR(VLOOKUP($A9,subQ,MATCH(K$1,SUBQH,0),0),"") | L9: =IFERROR(VLOOKUP($A9,subQ,MATCH(L$1,SUBQH,0),0),"")
A10: OPM | D10: 영업이익률 | E10: =IFERROR(VLOOKUP($A10,subQ,MATCH(E$1,SUBQH,0),0),"") | F10: =IFERROR(VLOOKUP($A10,subQ,MATCH(F$1,SUBQH,0),0),"") | G10: =IFERROR(VLOOKUP($A10,subQ,MATCH(G$1,SUBQH,0),0),"") | H10: =IFERROR(VLOOKUP($A10,subQ,MATCH(H$1,SUBQH,0),0),"") | I10: =IFERROR(VLOOKUP($A10,subQ,MATCH(I$1,SUBQH,0),0),"") | J10: =IFERROR(VLOOKUP($A10,subQ,MATCH(J$1,SUBQH,0),0),"") | K10: =IFERROR(VLOOKUP($A10,subQ,MATCH(K$1,SUBQH,0),0),"") | L10: =IFERROR(VLOOKUP($A10,subQ,MATCH(L$1,SUBQH,0),0),"")
A11: 금융손익 | D11: 금융손익(이자·환 포함) | E11: =IFERROR(VLOOKUP($A11,subQ,MATCH(E$1,SUBQH,0),0),"") | F11: =IFERROR(VLOOKUP($A11,subQ,MATCH(F$1,SUBQH,0),0),"") | G11: =IFERROR(VLOOKUP($A11,subQ,MATCH(G$1,SUBQH,0),0),"") | H11: =IFERROR(VLOOKUP($A11,subQ,MATCH(H$1,SUBQH,0),0),"") | I11: =IFERROR(VLOOKUP($A11,subQ,MATCH(I$1,SUBQH,0),0),"") | J11: =IFERROR(VLOOKUP($A11,subQ,MATCH(J$1,SUBQH,0),0),"") | K11: =IFERROR(VLOOKUP($A11,subQ,MATCH(K$1,SUBQH,0),0),"") | L11: =IFERROR(VLOOKUP($A11,subQ,MATCH(L$1,SUBQH,0),0),"")
A12: 이자손익 | D12: 이자손익(이자수익 − 이자비용) | E12: =IFERROR(VLOOKUP($A12,subQ,MATCH(E$1,SUBQH,0),0),"") | F12: =IFERROR(VLOOKUP($A12,subQ,MATCH(F$1,SUBQH,0),0),"") | G12: =IFERROR(VLOOKUP($A12,subQ,MATCH(G$1,SUBQH,0),0),"") | H12: =IFERROR(VLOOKUP($A12,subQ,MATCH(H$1,SUBQH,0),0),"") | I12: =IFERROR(VLOOKUP($A12,subQ,MATCH(I$1,SUBQH,0),0),"") | J12: =IFERROR(VLOOKUP($A12,subQ,MATCH(J$1,SUBQH,0),0),"") | K12: =IFERROR(VLOOKUP($A12,subQ,MATCH(K$1,SUBQH,0),0),"") | L12: =IFERROR(VLOOKUP($A12,subQ,MATCH(L$1,SUBQH,0),0),"")
A13: 외환손익 | D13: 외환손익(실적만; 추정 환효과는 환관련손익) | E13: =IFERROR(VLOOKUP($A13,subQ,MATCH(E$1,SUBQH,0),0),"") | F13: =IFERROR(VLOOKUP($A13,subQ,MATCH(F$1,SUBQH,0),0),"") | G13: =IFERROR(VLOOKUP($A13,subQ,MATCH(G$1,SUBQH,0),0),"") | H13: =IFERROR(VLOOKUP($A13,subQ,MATCH(H$1,SUBQH,0),0),"") | I13: =IFERROR(VLOOKUP($A13,subQ,MATCH(I$1,SUBQH,0),0),"") | J13: =IFERROR(VLOOKUP($A13,subQ,MATCH(J$1,SUBQH,0),0),"") | K13: =IFERROR(VLOOKUP($A13,subQ,MATCH(K$1,SUBQH,0),0),"") | L13: =IFERROR(VLOOKUP($A13,subQ,MATCH(L$1,SUBQH,0),0),"")
A14: 기타영업외손익 | D14: 기타영업외손익 | E14: =IFERROR(VLOOKUP($A14,subQ,MATCH(E$1,SUBQH,0),0),"") | F14: =IFERROR(VLOOKUP($A14,subQ,MATCH(F$1,SUBQH,0),0),"") | G14: =IFERROR(VLOOKUP($A14,subQ,MATCH(G$1,SUBQH,0),0),"") | H14: =IFERROR(VLOOKUP($A14,subQ,MATCH(H$1,SUBQH,0),0),"") | I14: =IFERROR(VLOOKUP($A14,subQ,MATCH(I$1,SUBQH,0),0),"") | J14: =IFERROR(VLOOKUP($A14,subQ,MATCH(J$1,SUBQH,0),0),"") | K14: =IFERROR(VLOOKUP($A14,subQ,MATCH(K$1,SUBQH,0),0),"") | L14: =IFERROR(VLOOKUP($A14,subQ,MATCH(L$1,SUBQH,0),0),"")
A15: 지분법손익 | D15: 지분법손익 | E15: =IFERROR(VLOOKUP($A15,subQ,MATCH(E$1,SUBQH,0),0),"") | F15: =IFERROR(VLOOKUP($A15,subQ,MATCH(F$1,SUBQH,0),0),"") | G15: =IFERROR(VLOOKUP($A15,subQ,MATCH(G$1,SUBQH,0),0),"") | H15: =IFERROR(VLOOKUP($A15,subQ,MATCH(H$1,SUBQH,0),0),"") | I15: =IFERROR(VLOOKUP($A15,subQ,MATCH(I$1,SUBQH,0),0),"") | J15: =IFERROR(VLOOKUP($A15,subQ,MATCH(J$1,SUBQH,0),0),"") | K15: =IFERROR(VLOOKUP($A15,subQ,MATCH(K$1,SUBQH,0),0),"") | L15: =IFERROR(VLOOKUP($A15,subQ,MATCH(L$1,SUBQH,0),0),"")
A16: 세전이익 | D16: 법인세비용차감전이익 | E16: =IFERROR(VLOOKUP($A16,subQ,MATCH(E$1,SUBQH,0),0),"") | F16: =IFERROR(VLOOKUP($A16,subQ,MATCH(F$1,SUBQH,0),0),"") | G16: =IFERROR(VLOOKUP($A16,subQ,MATCH(G$1,SUBQH,0),0),"") | H16: =IFERROR(VLOOKUP($A16,subQ,MATCH(H$1,SUBQH,0),0),"") | I16: =IFERROR(VLOOKUP($A16,subQ,MATCH(I$1,SUBQH,0),0),"") | J16: =IFERROR(VLOOKUP($A16,subQ,MATCH(J$1,SUBQH,0),0),"") | K16: =IFERROR(VLOOKUP($A16,subQ,MATCH(K$1,SUBQH,0),0),"") | L16: =IFERROR(VLOOKUP($A16,subQ,MATCH(L$1,SUBQH,0),0),"")
... A38: NPM | D38: NPM | E38: =IFERROR(VLOOKUP($A38,subQ,MATCH(E$1,SUBQH,0),0),"") | F38: =IFERROR(VLOOKUP($A38,subQ,MATCH(F$1,SUBQH,0),0),"") | G38: =IFERROR(VLOOKUP($A38,subQ,MATCH(G$1,SUBQH,0),0),"") | H38: =IFERROR(VLOOKUP($A38,subQ,MATCH(H$1,SUBQH,0),0),"") | I38: =IFERROR(VLOOKUP($A38,subQ,MATCH(I$1,SUBQH,0),0),"") | J38: =IFERROR(VLOOKUP($A38,subQ,MATCH(J$1,SUBQH,0),0),"") | K38: =IFERROR(VLOOKUP($A38,subQ,MATCH(K$1,SUBQH,0),0),"") | L38: =IFERROR(VLOOKUP($A38,subQ,MATCH(L$1,SUBQH,0),0),"")
A39: 매출액 YoY | D39: 매출액 YoY | F39: =IFERROR(F5/E5-1,"") | G39: =IFERROR(G5/F5-1,"") | H39: =IFERROR(H5/G5-1,"") | I39: =IFERROR(I5/H5-1,"") | J39: =IFERROR(J5/I5-1,"") | K39: =IFERROR(K5/J5-1,"") | L39: =IFERROR(L5/K5-1,"")
A40: 영업이익 YoY | D40: 영업이익 YoY | F40: =IFERROR(F9/E9-1,"") | G40: =IFERROR(G9/F9-1,"") | H40: =IFERROR(H9/G9-1,"") | I40: =IFERROR(I9/H9-1,"") | J40: =IFERROR(J9/I9-1,"") | K40: =IFERROR(K9/J9-1,"") | L40: =IFERROR(L9/K9-1,"")
A41: 지배주주순이익 YoY | D41: 지배주주순이익 YoY | F41: =IFERROR(F19/E19-1,"") | G41: =IFERROR(G19/F19-1,"") | H41: =IFERROR(H19/G19-1,"") | I41: =IFERROR(I19/H19-1,"") | J41: =IFERROR(J19/I19-1,"") | K41: =IFERROR(K19/J19-1,"") | L41: =IFERROR(L19/K19-1,"")

Sheet TP
B1: 종가 | C1: =변수!D42
B2: 기준일 | C2: =변수!D43
B3: 모델 산출값 — 목표주가·추천 아님. 밴드·COE 는 변수 시트 3절의 가정
C5: FY | D5: 2025 | E5: 2026 | F5: 2027 | G5: 2028
D6: A | E6: E | F6: E | G6: E
C7: EPS(원) | D7: =IFERROR(VLOOKUP("EPS",subQ,MATCH(D$5,SUBQH,0),0),"") | E7: =IFERROR(VLOOKUP("EPS",subQ,MATCH(E$5,SUBQH,0),0),"") | F7: =IFERROR(VLOOKUP("EPS",subQ,MATCH(F$5,SUBQH,0),0),"") | G7: =IFERROR(VLOOKUP("EPS",subQ,MATCH(G$5,SUBQH,0),0),"")
C8: BPS(원) | D8: =IFERROR(VLOOKUP("BPS",subQ,MATCH(D$5,SUBQH,0),0),"") | E8: =IFERROR(VLOOKUP("BPS",subQ,MATCH(E$5,SUBQH,0),0),"") | F8: =IFERROR(VLOOKUP("BPS",subQ,MATCH(F$5,SUBQH,0),0),"") | G8: =IFERROR(VLOOKUP("BPS",subQ,MATCH(G$5,SUBQH,0),0),"")
C9: 지배주주순이익(억원) | D9: =IFERROR(VLOOKUP("지배주주순이익",subQ,MATCH(D$5,SUBQH,0),0),"") | E9: =IFERROR(VLOOKUP("지배주주순이익",subQ,MATCH(E$5,SUBQH,0),0),"") | F9: =IFERROR(VLOOKUP("지배주주순이익",subQ,MATCH(F$5,SUBQH,0),0),"") | G9: =IFERROR(VLOOKUP("지배주주순이익",subQ,MATCH(G$5,SUBQH,0),0),"")
C10: 영업이익(억원) | D10: =IFERROR(VLOOKUP("영업이익",subQ,MATCH(D$5,SUBQH,0),0),"") | E10: =IFERROR(VLOOKUP("영업이익",subQ,MATCH(E$5,SUBQH,0),0),"") | F10: =IFERROR(VLOOKUP("영업이익",subQ,MATCH(F$5,SUBQH,0),0),"") | G10: =IFERROR(VLOOKUP("영업이익",subQ,MATCH(G$5,SUBQH,0),0),"")
C11: ROE(EPS/기초BPS) | E11: =IFERROR(E7/D8,"") | F11: =IFERROR(F7/E8,"") | G11: =IFERROR(G7/F8,"")
B13: PER
C14: 12M fwd EPS | D14: =IFERROR(E7*변수!D48+F7*(1-변수!D48),"")
C15: 적정가치 @PER_lo | D15: =변수!D45 | E15: =IFERROR(ROUND($D$14*D15,-2),"") | F15: =IFERROR(E15/$C$1-1,"") | G15: 배 · 원 · 종가 대비
C16: 적정가치 @PER_mid | D16: =변수!D46 | E16: =IFERROR(ROUND($D$14*D16,-2),"") | F16: =IFERROR(E16/$C$1-1,"") | G16: 배 · 원 · 종가 대비
C17: 적정가치 @PER_hi | D17: =변수!D47 | E17: =IFERROR(ROUND($D$14*D17,-2),"") | F17: =IFERROR(E17/$C$1-1,"") | G17: 배 · 원 · 종가 대비
C18: 현재 PER(종가/12M fwd EPS) | D18: =IFERROR($C$1/$D$14,"")
B20: PBR
C21: 최근 BPS(마지막 실적 분기) | D21: =IFERROR(VLOOKUP("BPS",subQ,MATCH("2Q26",SUBQH,0),0),"")
C22: ROE fwd(12M fwd EPS / BPS) | D22: =IFERROR($D$14/$D$21,"")
C23: COE | D23: =변수!D44
C24: 적정 PBR = ROE/COE | D24: =IFERROR(D22/D23,"")
C25: 적정가치(PBR) = BPS × 적정PBR | D25: =IFERROR(ROUND(D21*D24,-2),"") | E25: =IFERROR(D25/$C$1-1,"")
C26: 현재 PBR(종가/BPS) | D26: =IFERROR($C$1/D21,"")
B28: 모델 json valuation(참고)
C29: eps_fwd12m | D29: 1.9
C30: bps_latest | D30: 3000.9
C31: per_now | D31: 1315.79
C32: pbr_now | D32: 0.83
C33: roe_fwd | D33: 0.0006
C34: fair_pbr | D34: 0.01
C35: fair_value_pbr | D35: 0
C36: ev_ebitda
C37: note | D37: 모델 산출값 — 목표주가·추천 아님

Sheet 외화
C1: 이름: 외화QH — 환율 QoQ · 외화 순노출 × Δ기말환율 | E1: 4Q21 | F1: 1Q22 | G1: 2Q22 | H1: 3Q22 | I1: 4Q22 | J1: 1Q23 | K1: 2Q23 | L1: 3Q23 | M1: 4Q23 | N1: 1Q24 | O1: 2Q24 | P1: 3Q24 | Q1: 4Q24 | R1: 1Q25 | S1: 2Q25 | T1: 3Q25 | U1: 4Q25 | V1: 1Q26 | W1: 2Q26 | X1: 3Q26 | Y1: 4Q26 | Z1: 1Q27 | AA1: 2Q27 | AB1: 3Q27 | AC1: 4Q27 | AD1: 1Q28 | AE1: 2Q28 | AF1: 3Q28 | AG1: 4Q28
E3: 1 | F3: 2 | G3: 3 | H3: 4 | I3: 5 | J3: 6 | K3: 7 | L3: 8 | M3: 9 | N3: 10 | O3: 11 | P3: 12 | Q3: 13 | R3: 14 | S3: 15 | T3: 16 | U3: 17 | V3: 18 | W3: 19 | X3: 20 | Y3: 21 | Z3: 22 | AA3: 23 | AB3: 24 | AC3: 25 | AD3: 26 | AE3: 27 | AF3: 28 | AG3: 29
E4: 2021.12 | F4: 2022.03 | G4: 2022.06 | H4: 2022.09 | I4: 2022.12 | J4: 2023.03 | K4: 2023.06 | L4: 2023.09 | M4: 2023.12 | N4: 2024.03 | O4: 2024.06 | P4: 2024.09 | Q4: 2024.12 | R4: 2025.03 | S4: 2025.06 | T4: 2025.09 | U4: 2025.12 | V4: 2026.03 | W4: 2026.06 | X4: 2026.09 | Y4: 2026.12 | Z4: 2027.03 | AA4: 2027.06 | AB4: 2027.09 | AC4: 2027.12 | AD4: 2028.03 | AE4: 2028.06 | AF4: 2028.09 | AG4: 2028.12
D5: 원/달러(평균) | E5: =IFERROR(VLOOKUP($D5,환율,MATCH(E$1,변수H,0),0),"") | F5: =IFERROR(VLOOKUP($D5,환율,MATCH(F$1,변수H,0),0),"") | G5: =IFERROR(VLOOKUP($D5,환율,MATCH(G$1,변수H,0),0),"") | H5: =IFERROR(VLOOKUP($D5,환율,MATCH(H$1,변수H,0),0),"") | I5: =IFERROR(VLOOKUP($D5,환율,MATCH(I$1,변수H,0),0),"") | J5: =IFERROR(VLOOKUP($D5,환율,MATCH(J$1,변수H,0),0),"") | K5: =IFERROR(VLOOKUP($D5,환율,MATCH(K$1,변수H,0),0),"") | L5: =IFERROR(VLOOKUP($D5,환율,MATCH(L$1,변수H,0),0),"") | ... AG5: =IFERROR(VLOOKUP($D5,환율,MATCH(AG$1,변수H,0),0),"")
A6: 원/달러(평균) QoQ | F6: =IFERROR(F5/E5-1,"") | G6: =IFERROR(G5/F5-1,"") | H6: =IFERROR(H5/G5-1,"") | I6: =IFERROR(I5/H5-1,"") | J6: =IFERROR(J5/I5-1,"") | K6: =IFERROR(K5/J5-1,"") | L6: =IFERROR(L5/K5-1,"") | M6: =IFERROR(M5/L5-1,"") | ... AG6: =IFERROR(AG5/AF5-1,"")
D7: 원/달러(기말) | E7: =IFERROR(VLOOKUP($D7,환율,MATCH(E$1,변수H,0),0),"") | F7: =IFERROR(VLOOKUP($D7,환율,MATCH(F$1,변수H,0),0),"") | G7: =IFERROR(VLOOKUP($D7,환율,MATCH(G$1,변수H,0),0),"") | H7: =IFERROR(VLOOKUP($D7,환율,MATCH(H$1,변수H,0),0),"") | I7: =IFERROR(VLOOKUP($D7,환율,MATCH(I$1,변수H,0),0),"") | J7: =IFERROR(VLOOKUP($D7,환율,MATCH(J$1,변수H,0),0),"") | K7: =IFERROR(VLOOKUP($D7,환율,MATCH(K$1,변수H,0),0),"") | L7: =IFERROR(VLOOKUP($D7,환율,MATCH(L$1,변수H,0),0),"") | ... AG7: =IFERROR(VLOOKUP($D7,환율,MATCH(AG$1,변수H,0),0),"")
A8: 원/달러(기말) QoQ | F8: =IFERROR(F7/E7-1,"") | G8: =IFERROR(G7/F7-1,"") | H8: =IFERROR(H7/G7-1,"") | I8: =IFERROR(I7/H7-1,"") | J8: =IFERROR(J7/I7-1,"") | K8: =IFERROR(K7/J7-1,"") | L8: =IFERROR(L7/K7-1,"") | M8: =IFERROR(M7/L7-1,"") | ... AG8: =IFERROR(AG7/AF7-1,"")
D9: W/Euro(평균) | E9: =IFERROR(VLOOKUP($D9,환율,MATCH(E$1,변수H,0),0),"") | F9: =IFERROR(VLOOKUP($D9,환율,MATCH(F$1,변수H,0),0),"") | G9: =IFERROR(VLOOKUP($D9,환율,MATCH(G$1,변수H,0),0),"") | H9: =IFERROR(VLOOKUP($D9,환율,MATCH(H$1,변수H,0),0),"") | I9: =IFERROR(VLOOKUP($D9,환율,MATCH(I$1,변수H,0),0),"") | J9: =IFERROR(VLOOKUP($D9,환율,MATCH(J$1,변수H,0),0),"") | K9: =IFERROR(VLOOKUP($D9,환율,MATCH(K$1,변수H,0),0),"") | L9: =IFERROR(VLOOKUP($D9,환율,MATCH(L$1,변수H,0),0),"") | ... AG9: =IFERROR(VLOOKUP($D9,환율,MATCH(AG$1,변수H,0),0),"")
A10: W/Euro(평균) QoQ | F10: =IFERROR(F9/E9-1,"") | G10: =IFERROR(G9/F9-1,"") | H10: =IFERROR(H9/G9-1,"") | I10: =IFERROR(I9/H9-1,"") | J10: =IFERROR(J9/I9-1,"") | K10: =IFERROR(K9/J9-1,"") | L10: =IFERROR(L9/K9-1,"") | M10: =IFERROR(M9/L9-1,"") | ... AG10: =IFERROR(AG9/AF9-1,"")
D11: W/Euro(기말) | E11: =IFERROR(VLOOKUP($D11,환율,MATCH(E$1,변수H,0),0),"") | F11: =IFERROR(VLOOKUP($D11,환율,MATCH(F$1,변수H,0),0),"") | G11: =IFERROR(VLOOKUP($D11,환율,MATCH(G$1,변수H,0),0),"") | H11: =IFERROR(VLOOKUP($D11,환율,MATCH(H$1,변수H,0),0),"") | I11: =IFERROR(VLOOKUP($D11,환율,MATCH(I$1,변수H,0),0),"") | J11: =IFERROR(VLOOKUP($D11,환율,MATCH(J$1,변수H,0),0),"") | K11: =IFERROR(VLOOKUP($D11,환율,MATCH(K$1,변수H,0),0),"") | L11: =IFERROR(VLOOKUP($D11,환율,MATCH(L$1,변수H,0),0),"") | ... AG11: =IFERROR(VLOOKUP($D11,환율,MATCH(AG$1,변수H,0),0),"")
A12: W/Euro(기말) QoQ | F12: =IFERROR(F11/E11-1,"") | G12: =IFERROR(G11/F11-1,"") | H12: =IFERROR(H11/G11-1,"") | I12: =IFERROR(I11/H11-1,"") | J12: =IFERROR(J11/I11-1,"") | K12: =IFERROR(K11/J11-1,"") | L12: =IFERROR(L11/K11-1,"") | M12: =IFERROR(M11/L11-1,"") | ... AG12: =IFERROR(AG11/AF11-1,"")
D13: 원/100Y(기말) | E13: =IFERROR(VLOOKUP($D13,환율,MATCH(E$1,변수H,0),0),"") | F13: =IFERROR(VLOOKUP($D13,환율,MATCH(F$1,변수H,0),0),"") | G13: =IFERROR(VLOOKUP($D13,환율,MATCH(G$1,변수H,0),0),"") | H13: =IFERROR(VLOOKUP($D13,환율,MATCH(H$1,변수H,0),0),"") | I13: =IFERROR(VLOOKUP($D13,환율,MATCH(I$1,변수H,0),0),"") | J13: =IFERROR(VLOOKUP($D13,환율,MATCH(J$1,변수H,0),0),"") | K13: =IFERROR(VLOOKUP($D13,환율,MATCH(K$1,변수H,0),0),"") | L13: =IFERROR(VLOOKUP($D13,환율,MATCH(L$1,변수H,0),0),"") | ... AG13: =IFERROR(VLOOKUP($D13,환율,MATCH(AG$1,변수H,0),0),"")
A14: 원/100Y(기말) QoQ | F14: =IFERROR(F13/E13-1,"") | G14: =IFERROR(G13/F13-1,"") | H14: =IFERROR(H13/G13-1,"") | I14: =IFERROR(I13/H13-1,"") | J14: =IFERROR(J13/I13-1,"") | K14: =IFERROR(K13/J13-1,"") | L14: =IFERROR(L13/K13-1,"") | M14: =IFERROR(M13/L13-1,"") | ... AG14: =IFERROR(AG13/AF13-1,"")
A16: 외화순노출 | C16: 외화 순노출(백만$) | D16: =변수!D55 | E16: 외화 순노출 × Δ기말환율 (외화 시트 방식)
A17: 환관련손익추정 | C17: 환관련손익 추정(억원) = 순노출 × Δ원/달러(기말) / 100 | F17: =IFERROR($D$16*(F7-E7)/100,"") | G17: =IFERROR($D$16*(G7-F7)/100,"") | H17: =IFERROR($D$16*(H7-G7)/100,"") | I17: =IFERROR($D$16*(I7-H7)/100,"") | J17: =IFERROR($D$16*(J7-I7)/100,"") | K17: =IFERROR($D$16*(K7-J7)/100,"") | L17: =IFERROR($D$16*(L7-K7)/100,"") | M17: =IFERROR($D$16*(M7-L7)/100,"") | ... AG17: =IFERROR($D$16*(AG7-AF7)/100,"")
A18: fx_pnl.by_q | C18: 모델 fx_pnl.by_q(억원, 참고)
C19: 외화 순노출 미공시(face) → 0 + 표기
