Workbook
Name 변수H: 변수!$C$1:$AO$1
Name 환율: 변수!$C$6:$AO$13
Name BS연결H: BS연결!$C$1:$AO$1
Name BS연결: BS연결!$C$5:$AO$122
Name BS별도H: BS별도!$C$1:$AO$1
Name BS별도: BS별도!$C$5:$AO$104
Name SUBQH: subQ!$A$1:$AO$1
Name subQ: subQ!$A$5:$AO$44

Sheet README
A1: 두산에너빌리티(034020) 실적 모델 — ARGUS 한국조선
A2: 기준 분기 2026Q2 · 마지막 실적 2026Q2 · 생성 2026-10-19
A3: 모든 수치는 모델 산출값(DART 공개 재무제표 + 우리 추정)이다 — 목표주가·투자 추천 아님. 참고용 · 투자조언 아님.
A5: 시트
A6: 변수 가정 시계열. 환율 8행(ECB via frankfurter — L2 fx.json; 추정 분기 = 노란 가정), 추정 드라이버(노란 셀 = 모델값에서 역산한 가정, 바꾸면 재계산; 연녹 셀 = 3절 스칼라 참조 수식), 3절 스칼라 가정(세율·판관비율·지배주주비중·이자율·종가·PER 밴드·COE·외화 순노출·헤지비율)
A7: BS연결/BS별도 FnGuide 계정명 × 기간 값 덤프(백만원). 행1 분기라벨, 행4 YYYY.MM / YYYY.12A. 이름정의 BS연결H·BS연결(계정명 C열부터)
A8: subQ 분기 서브모델(억원 = 백만원/100). 확정 행: =IFERROR(VLOOKUP($D행,BS연결,MATCH(E$1,BS연결H,0),0)/100,"") 추정 행: 변수 시트 가정 셀 참조 수식. 외환손익·파생상품손익은 BS 계정 합·차, 기타금융손익은 잔차, OPM·EPS·BPS·PER·PBR 은 파생 수식
A9: SLS 선표(조선사만, sls json 있을 때): 요약 행(sls 저장값) + 계약별 스케줄(백만$) × (헤지비율 × 헤지환율 + (1−헤지비율) × 건조시점 환율[변수 원/달러(평균)]) → 원화 수식 블록 → 합계 행이 subQ 매출조선에 연결
A10: 시나리오 신규수주 보수/기준/낙관(forecast_panel 패널, 모델에 scenarios 가 있을 때만): 매출액·영업이익 = subQ 기준값 ± (시나리오 신규 − base 신규) × OPM. base 만 subQ 행에 포함, 나머지는 합산 안 함
A11: 분기/연간예상 subQ 를 이름(A열 key)으로 VLOOKUP 한 보고서 표(억원)
A12: TP PER 밴드 × 12M fwd EPS, PBR = ROE/COE × BPS — 모델 산출값 구간, 목표주가·추천 아님
A13: 외화 환율 QoQ, 외화 순노출 × Δ기말환율 → 환관련손익 추정
... A34: 백테스트: {"freeze": "2025Q2", "horizon": 4, "revenue_wape_pct": 13.1, "op_wape_pct": 20.0, "n": 4, "note": "단일 회사 4분기 — 통계 아님", "driver_at_freeze": "trend_seasonal", "selection_oos_at_freeze": null, "frozen_inputs": "fin(연결/별도)·고객 조선사 모델·지주 자회사 모델은 2025Q2 까지의 분기만; 선표는 체결일 ≤ 2025Q2 말일 계약(원장 최신 금액·코호트 등급, 환산 없음); 잔고는 yards_cache 2025Q2; 시세·환율 forward·prices·forecast_panel 신규수주 미사용. 고객 가중치(suppliers.json 언급 비중)와 합병 체인링크는 현재 지식; 고객 연동 채택은 동결 모델 안에서도 자기 la−4분기 OOS 규칙(selection_oos_at_freeze)", "detail": [{"q": "2025Q3", "rev_pred": 32075.61, "rev_act": 38803.5, "op_pred": 1931.83, "op_act": 1370.59}, {"q": "2025Q4", "rev_pred": 43350.38, "rev_act": 48599.31, "op_pred": 2610.89, "op_act": 2120.72}, {"q": "2026Q1", "rev_pred": 35410.21, "rev_act": 42611.3, "op_pred": 2132.67, "op_act": 2335.14}, {"q": "2026Q2", "rev_pred": 43160.41, "rev_act": 47248.08, "op_pred": 2599.44, "op_act": 3142.6}]}

Sheet 변수
C1: 이름: 변수H | E1: 4Q21 | F1: 2021 | G1: 1Q22 | H1: 2Q22 | I1: 3Q22 | J1: 4Q22 | K1: 2022 | L1: 1Q23 | M1: 2Q23 | N1: 3Q23 | O1: 4Q23 | P1: 2023 | Q1: 1Q24 | R1: 2Q24 | S1: 3Q24 | T1: 4Q24 | U1: 2024 | V1: 1Q25 | W1: 2Q25 | X1: 3Q25 | Y1: 4Q25 | Z1: 2025 | AA1: 1Q26 | AB1: 2Q26 | AC1: 3Q26 | AD1: 4Q26 | AE1: 2026 | AF1: 1Q27 | AG1: 2Q27 | AH1: 3Q27 | AI1: 4Q27 | AJ1: 2027 | AK1: 1Q28 | AL1: 2Q28 | AM1: 3Q28 | AN1: 4Q28 | AO1: 2028
A2: 가정 시계열 — 노란 셀은 추정 가정(모델값에서 역산), 연녹 셀은 3절 스칼라 참조 수식. 바꾸면 subQ·분기·연간예상·TP·시나리오가 재계산됩니다.
E3: 1 | F3: 2 | G3: 3 | H3: 4 | I3: 5 | J3: 6 | K3: 7 | L3: 8 | M3: 9 | N3: 10 | O3: 11 | P3: 12 | Q3: 13 | R3: 14 | S3: 15 | T3: 16 | U3: 17 | V3: 18 | W3: 19 | X3: 20 | Y3: 21 | Z3: 22 | AA3: 23 | AB3: 24 | AC3: 25 | AD3: 26 | AE3: 27 | AF3: 28 | AG3: 29 | AH3: 30 | AI3: 31 | AJ3: 32 | AK3: 33 | AL3: 34 | AM3: 35 | AN3: 36 | AO3: 37
E4: 2021.12 | F4: 2021.12A | G4: 2022.03 | H4: 2022.06 | I4: 2022.09 | J4: 2022.12 | K4: 2022.12A | L4: 2023.03 | M4: 2023.06 | N4: 2023.09 | O4: 2023.12 | P4: 2023.12A | Q4: 2024.03 | R4: 2024.06 | S4: 2024.09 | T4: 2024.12 | U4: 2024.12A | V4: 2025.03 | W4: 2025.06 | X4: 2025.09 | Y4: 2025.12 | Z4: 2025.12A | AA4: 2026.03 | AB4: 2026.06 | AC4: 2026.09 | AD4: 2026.12 | AE4: 2026.12A | AF4: 2027.03 | AG4: 2027.06 | AH4: 2027.09 | AI4: 2027.12 | AJ4: 2027.12A | AK4: 2028.03 | AL4: 2028.06 | AM4: 2028.09 | AN4: 2028.12 | AO4: 2028.12A
B5: 1. FX | C5: 이름: 환율
A6: USDKRW_avg | C6: 원/달러(평균) | E6: 1183.5 | F6: 1145.51 | G6: 1205.78 | H6: 1262.09 | I6: 1341.93 | J6: 1360.12 | K6: 1292.98 | L6: 1276.95 | M6: 1315.69 | N6: 1313.62 | O6: 1322.01 | P6: 1306.85 | Q6: 1330.14 | R6: 1371.28 | S6: 1356.22 | T6: 1396.3 | U6: 1363.53 | V6: 1452.28 | W6: 1398.52 | X6: 1386.95 | Y6: 1449.19 | Z6: 1421.52 | AA6: 1466.12 | AB6: 1501.75 | AC6: 1418.75 | AD6: 1342.11 | AE6: 1454.27 | AF6: 1332.1 | AG6: 1332.1 | AH6: 1332.1 | AI6: 1332.1 | AK6: 1332.1 | AL6: 1332.1 | AM6: 1332.1 | AN6: 1332.1
A7: USDKRW_end | C7: 원/달러(기말) | E7: 1188.75 | F7: 1188.75 | G7: 1213.74 | H7: 1301.24 | I7: 1436.9 | J7: 1260.16 | K7: 1260.16 | L7: 1305.99 | M7: 1321.44 | N7: 1345.35 | O7: 1297.43 | P7: 1297.43 | Q7: 1349.25 | R7: 1377.73 | S7: 1312.17 | T7: 1474.78 | U7: 1474.78 | V7: 1474.54 | W7: 1355.13 | X7: 1403.67 | Y7: 1444.2 | Z7: 1444.2 | AA7: 1524.8 | AB7: 1550.89 | AC7: 1355.4 | AD7: 1332.1 | AE7: 1332.1 | AF7: 1332.1 | AG7: 1332.1 | AH7: 1332.1 | AI7: 1332.1 | AK7: 1332.1 | AL7: 1332.1 | AM7: 1332.1 | AN7: 1332.1
A8: JPY100KRW_avg | C8: 원/100Y(평균) | E8: 1041.02 | F8: 1042.74 | G8: 1036.79 | H8: 972.23 | I8: 970.61 | J8: 961.03 | K8: 985.1 | L8: 964.89 | M8: 957.36 | N8: 909 | O8: 893.22 | P8: 931.11 | Q8: 896.29 | R8: 880.14 | S8: 909.35 | T8: 917.25 | U8: 900.92 | V8: 952.59 | W8: 967.92 | X8: 940.32 | Y8: 940.77 | Z8: 950.17 | AA8: 934.39 | AB8: 942.16 | AC8: 890.41 | AD8: 848.59 | AE8: 917.39 | AF8: 842.99 | AG8: 842.99 | AH8: 842.99 | AI8: 842.99 | AK8: 842.99 | AL8: 842.99 | AM8: 842.99 | AN8: 842.99
A9: JPY100KRW_end | C9: 원/100Y(기말) | E9: 1032.62 | F9: 1032.62 | G9: 996.83 | H9: 954.9 | I9: 993.29 | J9: 955.54 | K9: 955.54 | L9: 980.62 | M9: 913.67 | N9: 901.47 | O9: 917.04 | P9: 917.04 | Q9: 892.42 | R9: 857.76 | S9: 919.21 | T9: 939.65 | U9: 939.65 | V9: 986.84 | W9: 938.85 | X9: 948.49 | Y9: 921.81 | Z9: 921.81 | AA9: 955.99 | AB9: 954.75 | AC9: 863.31 | AD9: 842.99 | AE9: 842.99 | AF9: 842.99 | AG9: 842.99 | AH9: 842.99 | AI9: 842.99 | AK9: 842.99 | AL9: 842.99 | AM9: 842.99 | AN9: 842.99
A10: EURKRW_avg | C10: W/Euro(평균) | E10: 1353.32 | F10: 1354.06 | G10: 1352.29 | H10: 1343.31 | I10: 1350.63 | J10: 1386.07 | K10: 1358.07 | L10: 1369.93 | M10: 1432.41 | N10: 1429.41 | O10: 1420.91 | P10: 1412.88 | Q10: 1444.21 | R10: 1476.42 | S10: 1489.3 | T10: 1490.78 | U10: 1475.4 | V10: 1528.33 | W10: 1585.13 | X10: 1620.04 | Y10: 1686.02 | Z10: 1605.45 | AA10: 1715.47 | AB10: 1746.09 | AC10: 1631.97 | AD10: 1505.3 | AE10: 1685.25 | AF10: 1499.02 | AG10: 1499.02 | AH10: 1499.02 | AI10: 1499.02 | AK10: 1499.02 | AL10: 1499.02 | AM10: 1499.02 | AN10: 1499.02
A11: EURKRW_end | C11: W/Euro(기말) | E11: 1346.38 | F11: 1346.38 | G11: 1347.37 | H11: 1351.6 | I11: 1400.62 | J11: 1344.08 | K11: 1344.08 | L11: 1420.26 | M11: 1435.88 | N11: 1425.26 | O11: 1433.66 | P11: 1433.66 | Q11: 1458.68 | R11: 1474.86 | S11: 1469.1 | T11: 1532.14 | U11: 1532.14 | V11: 1594.72 | W11: 1588.22 | X11: 1648.04 | Y11: 1696.94 | Z11: 1696.94 | AA11: 1753.21 | AB11: 1767.09 | AC11: 1539.06 | AD11: 1499.02 | AE11: 1499.02 | AF11: 1499.02 | AG11: 1499.02 | AH11: 1499.02 | AI11: 1499.02 | AK11: 1499.02 | AL11: 1499.02 | AM11: 1499.02 | AN11: 1499.02
A12: CNYKRW_avg | C12: 원/중국원(평균) | E12: 185.14 | F12: 177.65 | G12: 189.93 | H12: 190.76 | I12: 195.79 | J12: 191.09 | K12: 191.93 | L12: 186.59 | M12: 187.45 | N12: 181.28 | O12: 182.86 | P12: 184.52 | Q12: 185.04 | R12: 189.35 | S12: 189.24 | T12: 194.24 | U12: 189.49 | V12: 199.63 | W12: 193.41 | X12: 193.79 | Y12: 204.38 | Z12: 197.8 | AA12: 211.75 | AB12: 220.8 | AC12: 210.43 | AD12: 200.38 | AE12: 213.41 | AF12: 199.23 | AG12: 199.23 | AH12: 199.23 | AI12: 199.23 | AK12: 199.23 | AL12: 199.23 | AM12: 199.23 | AN12: 199.23
A13: CNYKRW_end | C13: 원/중국원(기말) | E13: 187.13 | F13: 187.13 | G13: 191.38 | H13: 194.13 | I13: 201.92 | J13: 182.67 | K13: 182.67 | L13: 189.97 | M13: 181.8 | N13: 184.26 | O13: 182.61 | P13: 182.61 | Q13: 186.66 | R13: 189.7 | S13: 187.12 | T13: 202.04 | U13: 202.04 | V13: 203.3 | W13: 189.14 | X13: 197.16 | Y13: 206.28 | Z13: 206.28 | AA13: 220.97 | AB13: 228.56 | AC13: 202.16 | AD13: 199.23 | AE13: 199.23 | AF13: 199.23 | AG13: 199.23 | AH13: 199.23 | AI13: 199.23 | AK13: 199.23 | AL13: 199.23 | AM13: 199.23 | AN13: 199.23
B14: 1b. 종가
A15: price_close_end | C15: 종가(기말) | E15: 20400 | G15: 20450 | H15: 19400 | I15: 14250 | J15: 15400 | L15: 17000 | M15: 18110 | N15: 16430 | O15: 15900 | Q15: 17220 | R15: 20100 | S15: 17910 | T15: 17550 | V15: 23450 | W15: 68400 | X15: 62700 | Y15: 75300 | AA15: 91800 | AB15: 86800 | AC15: 81900 | AD15: 66600
A16: price_high | C16: 종가(최고) | E16: 26687 | G16: 23900 | H16: 22200 | I16: 23050 | J16: 17500 | L16: 18370 | M16: 20200 | N16: 19180 | O16: 16380 | Q16: 18920 | R16: 22000 | S16: 25000 | T16: 22800 | V16: 30900 | W16: 72200 | X16: 70600 | Y16: 97400 | AA16: 112100 | AB16: 139200 | AC16: 94400 | AD16: 84300
A17: price_low | C17: 종가(최저) | E17: 17421 | G17: 15200 | H17: 16000 | I17: 13950 | J17: 12450 | L17: 14750 | M17: 15060 | N17: 15940 | O17: 13350 | Q17: 14300 | R17: 14320 | S17: 15150 | T17: 16910 | V17: 17600 | W17: 19960 | X17: 51100 | Y17: 62700 | AA17: 74600 | AB17: 79300 | AC17: 57000 | AD17: 61300
A18: price_avg | C18: 종가(평균) | E18: 21812.5 | G18: 19779.7 | H18: 19798.4 | I18: 18645.2 | J18: 15288.7 | L18: 16365 | M18: 17236.7 | N18: 17161.6 | O18: 14864.7 | Q18: 15996.9 | R18: 18054.8 | S18: 18635 | T18: 19717.7 | V18: 24437.1 | W18: 38210 | X18: 63169.2 | Y18: 78511.9 | AA18: 95247.5 | AB18: 106186.9 | AC18: 78645.2 | AD18: 73100
B20: 2. 추정 드라이버 | C20: 실적 열 = subQ 실현값(수식), 추정 열 = 가정(노란 = 모델값 역산, 연녹 = 3절 스칼라 참조)
A21: drv:매출액 | B21: yoy | C21: 매출액 YoY | J21: =IFERROR(subQ!J5/subQ!E5-1,"") | L21: =IFERROR(subQ!L5/subQ!G5-1,"") | M21: =IFERROR(subQ!M5/subQ!H5-1,"") | N21: =IFERROR(subQ!N5/subQ!I5-1,"") | O21: =IFERROR(subQ!O5/subQ!J5-1,"") | Q21: =IFERROR(subQ!Q5/subQ!L5-1,"") | R21: =IFERROR(subQ!R5/subQ!M5-1,"") | S21: =IFERROR(subQ!S5/subQ!N5-1,"") | T21: =IFERROR(subQ!T5/subQ!O5-1,"") | V21: =IFERROR(subQ!V5/subQ!Q5-1,"") | W21: =IFERROR(subQ!W5/subQ!R5-1,"") | X21: =IFERROR(subQ!X5/subQ!S5-1,"") | Y21: =IFERROR(subQ!Y5/subQ!T5-1,"") | AA21: =IFERROR(subQ!AA5/subQ!V5-1,"") | AB21: =IFERROR(subQ!AB5/subQ!W5-1,"") | AC21: 0.087344956 | AD21: 0.087344861 | AF21: 0.087344906 | AG21: 0.087344925 | AH21: 0.04367239 | AI21: 0.043672523 | AK21: 0.043672591 | AL21: 0.043672443 | AM21: 0.021836271 | AN21: 0.021836178
A22: drv:판관비 | B22: ratio | C22: 판관비율(/매출) | E22: =IFERROR(subQ!E8/subQ!E5,"") | F22: =IFERROR(subQ!F8/subQ!F5,"") | G22: =IFERROR(subQ!G8/subQ!G5,"") | H22: =IFERROR(subQ!H8/subQ!H5,"") | I22: =IFERROR(subQ!I8/subQ!I5,"") | J22: =IFERROR(subQ!J8/subQ!J5,"") | K22: =IFERROR(subQ!K8/subQ!K5,"") | L22: =IFERROR(subQ!L8/subQ!L5,"") | ... AB22: =IFERROR(subQ!AB8/subQ!AB5,"") | AC22: =$D$53 | AD22: =$D$53 | AE22: =IFERROR(subQ!AE8/subQ!AE5,"") | AF22: =$D$53 | AG22: =$D$53 | AH22: =$D$53 | AI22: =$D$53 | AJ22: =IFERROR(subQ!AJ8/subQ!AJ5,"") | AK22: =$D$53 | AL22: =$D$53 | AM22: =$D$53 | AN22: =$D$53 | AO22: =IFERROR(subQ!AO8/subQ!AO5,"")
A23: drv:영업이익 | B23: ratio | C23: 영업이익률(OPM) | E23: =IFERROR(subQ!E9/subQ!E5,"") | F23: =IFERROR(subQ!F9/subQ!F5,"") | G23: =IFERROR(subQ!G9/subQ!G5,"") | H23: =IFERROR(subQ!H9/subQ!H5,"") | I23: =IFERROR(subQ!I9/subQ!I5,"") | J23: =IFERROR(subQ!J9/subQ!J5,"") | K23: =IFERROR(subQ!K9/subQ!K5,"") | L23: =IFERROR(subQ!L9/subQ!L5,"") | ... AB23: =IFERROR(subQ!AB9/subQ!AB5,"") | AC23: 0.047416869 | AD23: 0.047416926 | AE23: =IFERROR(subQ!AE9/subQ!AE5,"") | AF23: 0.047416776 | AG23: 0.047416874 | AH23: 0.047416797 | AI23: 0.047416914 | AJ23: =IFERROR(subQ!AJ9/subQ!AJ5,"") | AK23: 0.04741683 | AL23: 0.047416915 | AM23: 0.047416918 | AN23: 0.047416831 | AO23: =IFERROR(subQ!AO9/subQ!AO5,"")
A24: drv:외환손익 | B24: abs | C24: 외환손익 (가정, 억원) | E24: =subQ!E13 | F24: =subQ!F13 | G24: =subQ!G13 | H24: =subQ!H13 | I24: =subQ!I13 | J24: =subQ!J13 | K24: =subQ!K13 | L24: =subQ!L13 | ... AB24: =subQ!AB13 | AC24: 0 | AD24: 0 | AE24: =subQ!AE13 | AF24: 0 | AG24: 0 | AH24: 0 | AI24: 0 | AJ24: =subQ!AJ13 | AK24: 0 | AL24: 0 | AM24: 0 | AN24: 0 | AO24: =subQ!AO13
A25: drv:파생상품손익 | B25: abs | C25: 파생상품손익 (가정, 억원) | E25: =subQ!E14 | F25: =subQ!F14 | G25: =subQ!G14 | H25: =subQ!H14 | I25: =subQ!I14 | J25: =subQ!J14 | K25: =subQ!K14 | L25: =subQ!L14 | ... AB25: =subQ!AB14 | AC25: 0 | AD25: 0 | AE25: =subQ!AE14 | AF25: 0 | AG25: 0 | AH25: 0 | AI25: 0 | AJ25: =subQ!AJ14 | AK25: 0 | AL25: 0 | AM25: 0 | AN25: 0 | AO25: =subQ!AO14
A26: drv:기타금융손익 | B26: abs | C26: 기타금융손익 (가정, 억원) | E26: =subQ!E15 | F26: =subQ!F15 | G26: =subQ!G15 | H26: =subQ!H15 | I26: =subQ!I15 | J26: =subQ!J15 | K26: =subQ!K15 | L26: =subQ!L15 | ... AB26: =subQ!AB15 | AC26: 0 | AD26: 0 | AE26: =subQ!AE15 | AF26: 0 | AG26: 0 | AH26: 0 | AI26: 0 | AJ26: =subQ!AJ15 | AK26: 0 | AL26: 0 | AM26: 0 | AN26: 0 | AO26: =subQ!AO15
A27: drv:기타영업외손익 | B27: abs | C27: 기타영업외손익 (가정, 억원) | E27: =subQ!E16 | F27: =subQ!F16 | G27: =subQ!G16 | H27: =subQ!H16 | I27: =subQ!I16 | J27: =subQ!J16 | K27: =subQ!K16 | L27: =subQ!L16 | ... AB27: =subQ!AB16 | AC27: 0 | AD27: 0 | AE27: =subQ!AE16 | AF27: 0 | AG27: 0 | AH27: 0 | AI27: 0 | AJ27: =subQ!AJ16 | AK27: 0 | AL27: 0 | AM27: 0 | AN27: 0 | AO27: =subQ!AO16
A28: drv:지분법손익 | B28: abs | C28: 지분법손익 (가정, 억원) | E28: =subQ!E17 | F28: =subQ!F17 | G28: =subQ!G17 | H28: =subQ!H17 | I28: =subQ!I17 | J28: =subQ!J17 | K28: =subQ!K17 | L28: =subQ!L17 | ... AB28: =subQ!AB17 | AC28: 143.3 | AD28: 143.3 | AE28: =subQ!AE17 | AF28: 143.3 | AG28: 143.3 | AH28: 143.3 | AI28: 143.3 | AJ28: =subQ!AJ17 | AK28: 143.3 | AL28: 143.3 | AM28: 143.3 | AN28: 143.3 | AO28: =subQ!AO17
A29: drv:법인세비용 | B29: tax | C29: 법인세율(/세전) — 법인세 = MAX(세전,0) × 세율 | E29: =IFERROR(subQ!E19/subQ!E18,"") | F29: =IFERROR(subQ!F19/subQ!F18,"") | G29: =IFERROR(subQ!G19/subQ!G18,"") | H29: =IFERROR(subQ!H19/subQ!H18,"") | I29: =IFERROR(subQ!I19/subQ!I18,"") | J29: =IFERROR(subQ!J19/subQ!J18,"") | K29: =IFERROR(subQ!K19/subQ!K18,"") | L29: =IFERROR(subQ!L19/subQ!L18,"") | ... AB29: =IFERROR(subQ!AB19/subQ!AB18,"") | AC29: =$D$52 | AD29: =$D$52 | AE29: =IFERROR(subQ!AE19/subQ!AE18,"") | AF29: =$D$52 | AG29: =$D$52 | AH29: =$D$52 | AI29: =$D$52 | AJ29: =IFERROR(subQ!AJ19/subQ!AJ18,"") | AK29: =$D$52 | AL29: =$D$52 | AM29: =$D$52 | AN29: =$D$52 | AO29: =IFERROR(subQ!AO19/subQ!AO18,"")
A30: drv:지배주주순이익 | B30: ratio | C30: 지배주주 비중(/당기순이익) | E30: =IFERROR(subQ!E21/subQ!E20,"") | F30: =IFERROR(subQ!F21/subQ!F20,"") | G30: =IFERROR(subQ!G21/subQ!G20,"") | H30: =IFERROR(subQ!H21/subQ!H20,"") | I30: =IFERROR(subQ!I21/subQ!I20,"") | J30: =IFERROR(subQ!J21/subQ!J20,"") | K30: =IFERROR(subQ!K21/subQ!K20,"") | L30: =IFERROR(subQ!L21/subQ!L20,"") | ... AB30: =IFERROR(subQ!AB21/subQ!AB20,"") | AC30: =$D$54 | AD30: =$D$54 | AE30: =IFERROR(subQ!AE21/subQ!AE20,"") | AF30: =$D$54 | AG30: =$D$54 | AH30: =$D$54 | AI30: =$D$54 | AJ30: =IFERROR(subQ!AJ21/subQ!AJ20,"") | AK30: =$D$54 | AL30: =$D$54 | AM30: =$D$54 | AN30: =$D$54 | AO30: =IFERROR(subQ!AO21/subQ!AO20,"")
A31: drv:중단사업이익 | B31: abs | C31: 중단사업이익 (가정, 억원) | E31: =subQ!E22 | F31: =subQ!F22 | G31: =subQ!G22 | H31: =subQ!H22 | I31: =subQ!I22 | J31: =subQ!J22 | K31: =subQ!K22 | L31: =subQ!L22 | ... AB31: =subQ!AB22 | AE31: =subQ!AE22 | AJ31: =subQ!AJ22 | AO31: =subQ!AO22
A32: drv:부채총계 | B32: qoq | C32: 부채총계 QoQ | G32: =IFERROR(subQ!G24/subQ!E24-1,"") | H32: =IFERROR(subQ!H24/subQ!G24-1,"") | I32: =IFERROR(subQ!I24/subQ!H24-1,"") | J32: =IFERROR(subQ!J24/subQ!I24-1,"") | L32: =IFERROR(subQ!L24/subQ!J24-1,"") | M32: =IFERROR(subQ!M24/subQ!L24-1,"") | N32: =IFERROR(subQ!N24/subQ!M24-1,"") | O32: =IFERROR(subQ!O24/subQ!N24-1,"") | Q32: =IFERROR(subQ!Q24/subQ!O24-1,"") | R32: =IFERROR(subQ!R24/subQ!Q24-1,"") | S32: =IFERROR(subQ!S24/subQ!R24-1,"") | T32: =IFERROR(subQ!T24/subQ!S24-1,"") | V32: =IFERROR(subQ!V24/subQ!T24-1,"") | W32: =IFERROR(subQ!W24/subQ!V24-1,"") | X32: =IFERROR(subQ!X24/subQ!W24-1,"") | Y32: =IFERROR(subQ!Y24/subQ!X24-1,"") | AA32: =IFERROR(subQ!AA24/subQ!Y24-1,"") | AB32: =IFERROR(subQ!AB24/subQ!AA24-1,"") | AC32: 0 | AD32: 0 | AF32: 0 | AG32: 0 | AH32: 0 | AI32: 0 | AK32: 0 | AL32: 0 | AM32: 0 | AN32: 0
A33: drv:자본총계 | B33: roll | C33: 자본총계 기타변동(배당 등, 억원) | G33: =IFERROR(subQ!E25+subQ!G20-subQ!G25,"") | H33: =IFERROR(subQ!G25+subQ!H20-subQ!H25,"") | I33: =IFERROR(subQ!H25+subQ!I20-subQ!I25,"") | J33: =IFERROR(subQ!I25+subQ!J20-subQ!J25,"") | L33: =IFERROR(subQ!J25+subQ!L20-subQ!L25,"") | M33: =IFERROR(subQ!L25+subQ!M20-subQ!M25,"") | N33: =IFERROR(subQ!M25+subQ!N20-subQ!N25,"") | O33: =IFERROR(subQ!N25+subQ!O20-subQ!O25,"") | Q33: =IFERROR(subQ!O25+subQ!Q20-subQ!Q25,"") | R33: =IFERROR(subQ!Q25+subQ!R20-subQ!R25,"") | S33: =IFERROR(subQ!R25+subQ!S20-subQ!S25,"") | T33: =IFERROR(subQ!S25+subQ!T20-subQ!T25,"") | V33: =IFERROR(subQ!T25+subQ!V20-subQ!V25,"") | W33: =IFERROR(subQ!V25+subQ!W20-subQ!W25,"") | X33: =IFERROR(subQ!W25+subQ!X20-subQ!X25,"") | Y33: =IFERROR(subQ!X25+subQ!Y20-subQ!Y25,"") | AA33: =IFERROR(subQ!Y25+subQ!AA20-subQ!AA25,"") | AB33: =IFERROR(subQ!AA25+subQ!AB20-subQ!AB25,"") | AC33: 0.001784146 | AD33: 0.002733647 | AF33: 0.000334227 | AG33: 0.006426239 | AH33: -0.005099701 | AI33: 0.006238169 | AK33: 0.004711386 | AL33: 0.002967662 | AM33: 0.004180576 | AN33: -0.003043825
A34: drv:지배주주지분 | B34: roll | C34: 지배주주지분 기타변동(배당 등, 억원) | G34: =IFERROR(subQ!E26+subQ!G21-subQ!G26,"") | H34: =IFERROR(subQ!G26+subQ!H21-subQ!H26,"") | I34: =IFERROR(subQ!H26+subQ!I21-subQ!I26,"") | J34: =IFERROR(subQ!I26+subQ!J21-subQ!J26,"") | L34: =IFERROR(subQ!J26+subQ!L21-subQ!L26,"") | M34: =IFERROR(subQ!L26+subQ!M21-subQ!M26,"") | N34: =IFERROR(subQ!M26+subQ!N21-subQ!N26,"") | O34: =IFERROR(subQ!N26+subQ!O21-subQ!O26,"") | Q34: =IFERROR(subQ!O26+subQ!Q21-subQ!Q26,"") | R34: =IFERROR(subQ!Q26+subQ!R21-subQ!R26,"") | S34: =IFERROR(subQ!R26+subQ!S21-subQ!S26,"") | T34: =IFERROR(subQ!S26+subQ!T21-subQ!T26,"") | V34: =IFERROR(subQ!T26+subQ!V21-subQ!V26,"") | W34: =IFERROR(subQ!V26+subQ!W21-subQ!W26,"") | X34: =IFERROR(subQ!W26+subQ!X21-subQ!X26,"") | Y34: =IFERROR(subQ!X26+subQ!Y21-subQ!Y26,"") | AA34: =IFERROR(subQ!Y26+subQ!AA21-subQ!AA26,"") | AB34: =IFERROR(subQ!AA26+subQ!AB21-subQ!AB26,"")
A35: drv:총차입금 | B35: qoq | C35: 총차입금 QoQ | G35: =IFERROR(subQ!G27/subQ!E27-1,"") | H35: =IFERROR(subQ!H27/subQ!G27-1,"") | I35: =IFERROR(subQ!I27/subQ!H27-1,"") | J35: =IFERROR(subQ!J27/subQ!I27-1,"") | L35: =IFERROR(subQ!L27/subQ!J27-1,"") | M35: =IFERROR(subQ!M27/subQ!L27-1,"") | N35: =IFERROR(subQ!N27/subQ!M27-1,"") | O35: =IFERROR(subQ!O27/subQ!N27-1,"") | Q35: =IFERROR(subQ!Q27/subQ!O27-1,"") | R35: =IFERROR(subQ!R27/subQ!Q27-1,"") | S35: =IFERROR(subQ!S27/subQ!R27-1,"") | T35: =IFERROR(subQ!T27/subQ!S27-1,"") | V35: =IFERROR(subQ!V27/subQ!T27-1,"") | W35: =IFERROR(subQ!W27/subQ!V27-1,"") | X35: =IFERROR(subQ!X27/subQ!W27-1,"") | Y35: =IFERROR(subQ!Y27/subQ!X27-1,"") | AA35: =IFERROR(subQ!AA27/subQ!Y27-1,"") | AB35: =IFERROR(subQ!AB27/subQ!AA27-1,"") | AC35: 0 | AD35: 0 | AF35: 0 | AG35: 0 | AH35: 0 | AI35: 0 | AK35: 0 | AL35: 0 | AM35: 0 | AN35: 0
A36: drv:순차입금 | B36: qoq | C36: 순차입금 QoQ | G36: =IFERROR(subQ!G28/subQ!E28-1,"") | H36: =IFERROR(subQ!H28/subQ!G28-1,"") | I36: =IFERROR(subQ!I28/subQ!H28-1,"") | J36: =IFERROR(subQ!J28/subQ!I28-1,"") | L36: =IFERROR(subQ!L28/subQ!J28-1,"") | M36: =IFERROR(subQ!M28/subQ!L28-1,"") | N36: =IFERROR(subQ!N28/subQ!M28-1,"") | O36: =IFERROR(subQ!O28/subQ!N28-1,"") | Q36: =IFERROR(subQ!Q28/subQ!O28-1,"") | R36: =IFERROR(subQ!R28/subQ!Q28-1,"") | S36: =IFERROR(subQ!S28/subQ!R28-1,"") | T36: =IFERROR(subQ!T28/subQ!S28-1,"") | V36: =IFERROR(subQ!V28/subQ!T28-1,"") | W36: =IFERROR(subQ!W28/subQ!V28-1,"") | X36: =IFERROR(subQ!X28/subQ!W28-1,"") | Y36: =IFERROR(subQ!Y28/subQ!X28-1,"") | AA36: =IFERROR(subQ!AA28/subQ!Y28-1,"") | AB36: =IFERROR(subQ!AB28/subQ!AA28-1,"") | AC36: -0.029576887 | AD36: -0.04114798 | AF36: -0.036400565 | AG36: -0.043344324 | AH36: -0.037310784 | AI36: -0.05184946 | AK36: -0.046612876 | AL36: -0.055880439 | AM36: -0.047727226 | AN36: -0.066587778
A37: drv:이자발생자산 | B37: qoq | C37: 이자발생자산 QoQ | G37: =IFERROR(subQ!G29/subQ!E29-1,"") | H37: =IFERROR(subQ!H29/subQ!G29-1,"") | I37: =IFERROR(subQ!I29/subQ!H29-1,"") | J37: =IFERROR(subQ!J29/subQ!I29-1,"") | L37: =IFERROR(subQ!L29/subQ!J29-1,"") | M37: =IFERROR(subQ!M29/subQ!L29-1,"") | N37: =IFERROR(subQ!N29/subQ!M29-1,"") | O37: =IFERROR(subQ!O29/subQ!N29-1,"") | Q37: =IFERROR(subQ!Q29/subQ!O29-1,"") | R37: =IFERROR(subQ!R29/subQ!Q29-1,"") | S37: =IFERROR(subQ!S29/subQ!R29-1,"") | T37: =IFERROR(subQ!T29/subQ!S29-1,"") | V37: =IFERROR(subQ!V29/subQ!T29-1,"") | W37: =IFERROR(subQ!W29/subQ!V29-1,"") | X37: =IFERROR(subQ!X29/subQ!W29-1,"") | Y37: =IFERROR(subQ!Y29/subQ!X29-1,"") | AA37: =IFERROR(subQ!AA29/subQ!Y29-1,"") | AB37: =IFERROR(subQ!AB29/subQ!AA29-1,"") | AC37: 0.032228 | AD37: 0.042151681 | AF37: 0.034307981 | AG37: 0.03805975 | AH37: 0.03019266 | AI37: 0.03920838 | AK37: 0.032159938 | AL37: 0.035611593 | AM37: 0.027728596 | AN37: 0.035845871
A38: drv:현금및현금성자산 | B38: qoq | C38: 현금및현금성자산 QoQ | G38: =IFERROR(subQ!G30/subQ!E30-1,"") | H38: =IFERROR(subQ!H30/subQ!G30-1,"") | I38: =IFERROR(subQ!I30/subQ!H30-1,"") | J38: =IFERROR(subQ!J30/subQ!I30-1,"") | L38: =IFERROR(subQ!L30/subQ!J30-1,"") | M38: =IFERROR(subQ!M30/subQ!L30-1,"") | N38: =IFERROR(subQ!N30/subQ!M30-1,"") | O38: =IFERROR(subQ!O30/subQ!N30-1,"") | Q38: =IFERROR(subQ!Q30/subQ!O30-1,"") | R38: =IFERROR(subQ!R30/subQ!Q30-1,"") | S38: =IFERROR(subQ!S30/subQ!R30-1,"") | T38: =IFERROR(subQ!T30/subQ!S30-1,"") | V38: =IFERROR(subQ!V30/subQ!T30-1,"") | W38: =IFERROR(subQ!W30/subQ!V30-1,"") | X38: =IFERROR(subQ!X30/subQ!W30-1,"") | Y38: =IFERROR(subQ!Y30/subQ!X30-1,"") | AA38: =IFERROR(subQ!AA30/subQ!Y30-1,"") | AB38: =IFERROR(subQ!AB30/subQ!AA30-1,"")
A39: drv:CAPEX | B39: yoy | C39: CAPEX YoY | J39: =IFERROR(subQ!J31/subQ!E31-1,"") | L39: =IFERROR(subQ!L31/subQ!G31-1,"") | M39: =IFERROR(subQ!M31/subQ!H31-1,"") | N39: =IFERROR(subQ!N31/subQ!I31-1,"") | O39: =IFERROR(subQ!O31/subQ!J31-1,"") | Q39: =IFERROR(subQ!Q31/subQ!L31-1,"") | R39: =IFERROR(subQ!R31/subQ!M31-1,"") | S39: =IFERROR(subQ!S31/subQ!N31-1,"") | T39: =IFERROR(subQ!T31/subQ!O31-1,"") | V39: =IFERROR(subQ!V31/subQ!Q31-1,"") | W39: =IFERROR(subQ!W31/subQ!R31-1,"") | X39: =IFERROR(subQ!X31/subQ!S31-1,"") | Y39: =IFERROR(subQ!Y31/subQ!T31-1,"") | AA39: =IFERROR(subQ!AA31/subQ!V31-1,"") | AB39: =IFERROR(subQ!AB31/subQ!W31-1,"") | AC39: -0.22409699 | AD39: -0.050420653 | AF39: 0.056069206 | AG39: 0.74366506 | AH39: 0 | AI39: 0 | AK39: 0 | AL39: 0 | AM39: 0 | AN39: 0
A40: drv:영업활동현금흐름 | B40: yoy | C40: 영업활동현금흐름 YoY | J40: =IFERROR(subQ!J32/subQ!E32-1,"") | L40: =IFERROR(subQ!L32/subQ!G32-1,"") | M40: =IFERROR(subQ!M32/subQ!H32-1,"") | N40: =IFERROR(subQ!N32/subQ!I32-1,"") | O40: =IFERROR(subQ!O32/subQ!J32-1,"") | Q40: =IFERROR(subQ!Q32/subQ!L32-1,"") | R40: =IFERROR(subQ!R32/subQ!M32-1,"") | S40: =IFERROR(subQ!S32/subQ!N32-1,"") | T40: =IFERROR(subQ!T32/subQ!O32-1,"") | V40: =IFERROR(subQ!V32/subQ!Q32-1,"") | W40: =IFERROR(subQ!W32/subQ!R32-1,"") | X40: =IFERROR(subQ!X32/subQ!S32-1,"") | Y40: =IFERROR(subQ!Y32/subQ!T32-1,"") | AA40: =IFERROR(subQ!AA32/subQ!V32-1,"") | AB40: =IFERROR(subQ!AB32/subQ!W32-1,"")
A41: drv:주식수 | B41: qoq | C41: 주식수 QoQ | G41: =IFERROR(subQ!G33/subQ!E33-1,"") | H41: =IFERROR(subQ!H33/subQ!G33-1,"") | I41: =IFERROR(subQ!I33/subQ!H33-1,"") | J41: =IFERROR(subQ!J33/subQ!I33-1,"") | L41: =IFERROR(subQ!L33/subQ!J33-1,"") | M41: =IFERROR(subQ!M33/subQ!L33-1,"") | N41: =IFERROR(subQ!N33/subQ!M33-1,"") | O41: =IFERROR(subQ!O33/subQ!N33-1,"") | Q41: =IFERROR(subQ!Q33/subQ!O33-1,"") | R41: =IFERROR(subQ!R33/subQ!Q33-1,"") | S41: =IFERROR(subQ!S33/subQ!R33-1,"") | T41: =IFERROR(subQ!T33/subQ!S33-1,"") | V41: =IFERROR(subQ!V33/subQ!T33-1,"") | W41: =IFERROR(subQ!W33/subQ!V33-1,"") | X41: =IFERROR(subQ!X33/subQ!W33-1,"") | Y41: =IFERROR(subQ!Y33/subQ!X33-1,"") | AA41: =IFERROR(subQ!AA33/subQ!Y33-1,"") | AB41: =IFERROR(subQ!AB33/subQ!AA33-1,"") | AC41: 0 | AD41: 0 | AF41: 0 | AG41: 0 | AH41: 0 | AI41: 0 | AK41: 0 | AL41: 0 | AM41: 0 | AN41: 0
A42: drv:DPS | B42: abs | C42: DPS (가정, 원) | E42: =subQ!E36 | F42: =subQ!F36 | G42: =subQ!G36 | H42: =subQ!H36 | I42: =subQ!I36 | J42: =subQ!J36 | K42: =subQ!K36 | L42: =subQ!L36 | ... AB42: =subQ!AB36 | AD42: 0 | AE42: =subQ!AE36 | AI42: 0 | AJ42: =subQ!AJ36 | AN42: 0 | AO42: =subQ!AO36
B44: 3. 밸류에이션·스칼라 | C44: 노란 셀 = 가정. '연결' 표시는 추정 전 분기 수식이 이 셀을 참조한다는 뜻
A45: sc:종가 | C45: 종가 | D45: 66600 | E45: 원 — 네이버 정규장 종가(aik 확정종가 대조 · aik 63,300원)
A46: sc:기준일 | C46: 기준일 | D46: 20261019 | E46: 종가 기준일
A47: sc:COE | C47: COE | D47: 0.09 | E47: 자기자본비용(가정) — TP 적정 PBR = ROE/COE
A48: sc:PER_lo | C48: PER_lo | D48: 10 | E48: PER 밴드 하단(배) — sector_default(레퍼런스 TP_PE PB 예시 10/15/20배; 과거 PER 중위 171.3배가 3~40 밖(턴어라운드 왜곡))
A49: sc:PER_mid | C49: PER_mid | D49: 15 | E49: PER 밴드 중단(배)
A50: sc:PER_hi | C50: PER_hi | D50: 20 | E50: PER 밴드 상단(배)
A51: sc:EPS_Y1가중 | C51: EPS_Y1가중 | D51: 0.5 | E51: 12M fwd EPS = FY(last_actual연도)E × w + FY+1E × (1−w) — 기준 분기 2Q 이면 0.5(가정)
A52: sc:세율 | C52: 세율 | D52: 0.2200008 | E52: 연결 — 법인세 = MAX(세전,0) × 세율(역산, 재현 오차 ≤ 0.05억 · 모델 assumptions 0.22) · 최근 12분기 유효세율 34.8% 가 5~27% 밖; 세전 > 0 분기 중위 42.9% 도 5~27% 밖 → 법정세율 근사 22% 가정
A53: sc:판관비율 | C53: 판관비율 | D53: 0.12016448 | E53: 연결 — 판관비 = 매출액 × 판관비율(역산, 재현 오차 ≤ 0.05억 · 모델 assumptions 0.1202)
A54: sc:지배주주비중 | C54: 지배주주비중 | D54: 0.40000014 | E54: 연결 — 지배주주순이익 = 당기순이익 × 비중(역산, 재현 오차 ≤ 0.05억)
A55: sc:이자율_자산 | C55: 이자율_자산 | D55: 0.023763451 | E55: 연결 — 이자손익 = (전분기 이자발생자산 × 자산이자율 − 전분기 총차입금 × 부채이자율)/4(역산, 재현 오차 ≤ 0.05억 · 모델 assumptions 0.0238)
A56: sc:이자율_부채 | C56: 이자율_부채 | D56: 0.051780542 | E56: 연결 — 같은 수식의 부채 쪽(총차입금 행이 없으면 0)(역산, 재현 오차 ≤ 0.05억 · 모델 assumptions 0.0518)
A57: sc:배당성향 | C57: 배당성향 | D57: 0 | E57: 배당성향(참고 — 모델은 직전 DPS 유지·Q2 지급 가정)
A58: sc:외화순노출_백만$ | C58: 외화순노출_백만$ | E58: 외화 순노출 × Δ기말환율 (외화 시트 방식) — 외화 순노출 미공시(face) → 0 + 표기
A59: sc:헤지비율 | C59: 헤지비율 | E59: sls 없음
A60: sc:헤지환율_약정 | C60: 헤지환율_약정 | E60: sls 없음

Sheet BS연결
B1: (백만원) | C1: 이름: BS연결H | E1: 4Q21 | F1: 2021 | G1: 1Q22 | H1: 2Q22 | I1: 3Q22 | J1: 4Q22 | K1: 2022 | L1: 1Q23 | M1: 2Q23 | N1: 3Q23 | O1: 4Q23 | P1: 2023 | Q1: 1Q24 | R1: 2Q24 | S1: 3Q24 | T1: 4Q24 | U1: 2024 | V1: 1Q25 | W1: 2Q25 | X1: 3Q25 | Y1: 4Q25 | Z1: 2025 | AA1: 1Q26 | AB1: 2Q26 | AC1: 3Q26 | AD1: 4Q26 | AE1: 2026 | AF1: 1Q27 | AG1: 2Q27 | AH1: 3Q27 | AI1: 4Q27 | AJ1: 2027 | AK1: 1Q28 | AL1: 2Q28 | AM1: 3Q28 | AN1: 4Q28 | AO1: 2028
B2: 연결 | D2: fin json(kship_fin.py)
B3: 두산에너빌리티(연) | C3: UPDATE: 26-10-19 | E3: 1 | F3: 2 | G3: 3 | H3: 4 | I3: 5 | J3: 6 | K3: 7 | L3: 8 | M3: 9 | N3: 10 | O3: 11 | P3: 12 | Q3: 13 | R3: 14 | S3: 15 | T3: 16 | U3: 17 | V3: 18 | W3: 19 | X3: 20 | Y3: 21 | Z3: 22 | AA3: 23 | AB3: 24 | AC3: 25 | AD3: 26 | AE3: 27 | AF3: 28 | AG3: 29 | AH3: 30 | AI3: 31 | AJ3: 32 | AK3: 33 | AL3: 34 | AM3: 35 | AN3: 36 | AO3: 37
B4: Account Code | C4: AccountNAME | E4: 2021.12 | F4: 2021.12A | G4: 2022.03 | H4: 2022.06 | I4: 2022.09 | J4: 2022.12 | K4: 2022.12A | L4: 2023.03 | M4: 2023.06 | N4: 2023.09 | O4: 2023.12 | P4: 2023.12A | Q4: 2024.03 | R4: 2024.06 | S4: 2024.09 | T4: 2024.12 | U4: 2024.12A | V4: 2025.03 | W4: 2025.06 | X4: 2025.09 | Y4: 2025.12 | Z4: 2025.12A | AA4: 2026.03 | AB4: 2026.06 | AC4: 2026.09 | AD4: 2026.12 | AE4: 2026.12A | AF4: 2027.03 | AG4: 2027.06 | AH4: 2027.09 | AI4: 2027.12 | AJ4: 2027.12A | AK4: 2028.03 | AL4: 2028.06 | AM4: 2028.09 | AN4: 2028.12 | AO4: 2028.12A
A5: 1 | C5: 유동자산 | E5: 8417624.1 | F5: 8417624.1 | G5: 8671301.2 | H5: 8759163.8 | I5: 8917729 | J5: 8098893.7 | K5: 8098893.7 | L5: 8606257.3 | M5: 10004790 | N5: 9550625.1 | O5: 9641568.2 | P5: 9641568.2 | Q5: 10332148 | R5: 10355218 | S5: 9675110 | T5: 10049022 | U5: 10049022 | V5: 10508418 | W5: 9989814 | X5: 10510110 | Y5: 10771711 | Z5: 10771711 | AA5: 11598608 | AB5: 12466920
A6: 1 | C6: 현금및현금성자산 | E6: 1908604 | F6: 1908604 | G6: 1588251 | H6: 1097413.5 | I6: 1467025 | J6: 1395837.6 | K6: 1395837.6 | L6: 1591895.4 | M6: 2724522.5 | N6: 2270177.3 | O6: 2620187 | P6: 2620187 | Q6: 2920099.8 | R6: 2585775.2 | S6: 2287606.9 | T6: 2898298 | U6: 2898298 | V6: 2609660 | W6: 2274305 | X6: 2404201 | Y6: 3080997 | Z6: 3080997 | AA6: 3090530 | AB6: 2541888
A7: 1 | C7: 단기금융상품 | E7: 519150.03 | F7: 519150.03 | G7: 307771.09 | H7: 146932.43 | I7: 160221.94 | J7: 105780.37 | K7: 105780.37 | L7: 77697.17 | M7: 78595.5 | N7: 102386.09 | O7: 118271.68 | P7: 118271.68 | Q7: 135114.04 | R7: 101225.77 | S7: 100781.04 | T7: 143577 | U7: 143577 | V7: 151970 | W7: 120126 | X7: 111532 | Y7: 107870 | Z7: 107870 | AA7: 108861 | AB7: 276246
A8: 1 | C8: 단기금융자산 | E8: 627154.23 | F8: 627154.23 | G8: 417385.52 | H8: 298653.58 | I8: 381714.59 | J8: 234608.48 | K8: 234608.48 | L8: 212411.69 | M8: 230469.24 | N8: 280614.4 | O8: 202997.84 | P8: 202997.84 | Q8: 252855.81 | R8: 254431.49 | S8: 173669.12 | T8: 285438 | U8: 285438 | V8: 289516 | W8: 170366 | X8: 178197 | Y8: 186426 | Z8: 186426 | AA8: 267810 | AB8: 493666
A9: 1 | C9: 단기투자자산(공정가치) | E9: 197197.2 | F9: 197197.2 | G9: 159405.42 | H9: 64795.04 | I9: 23717.09 | J9: 23775.91 | K9: 23775.91 | L9: 23140.21 | M9: 76853.67 | N9: 77122.42 | O9: 84976.78 | P9: 84976.78 | Q9: 80576.85 | R9: 351.19 | S9: 353.11 | T9: 0 | U9: 0 | V9: 0 | AB9: 75014
A10: 1 | C10: 매출채권및기타채권 | E10: 1128705.6 | F10: 1128705.6 | G10: 1340359.6 | H10: 1669760.6 | I10: 1716473.6 | J10: 1827688 | K10: 1827688 | L10: 1965339 | M10: 2077400.5 | N10: 1973318.3 | O10: 1812811 | P10: 1812811 | Q10: 1982359.7 | R10: 1951260 | S10: 1815503.5 | T10: 1767747 | U10: 1767747 | V10: 1990236 | W10: 2080255 | X10: 2255515 | Y10: 2279608 | Z10: 2279608 | AA10: 2393923 | AB10: 2787121
A11: 1 | C11: 계약자산 | E11: 1632887.6 | F11: 1632887.6 | G11: 1684090.4 | H11: 1470566.8 | I11: 1435796.9 | J11: 1156934.2 | K11: 1156934.2 | L11: 1126730.3 | M11: 1158383.4 | N11: 1307173.3 | O11: 1485570.4 | P11: 1485570.4 | Q11: 1456205 | R11: 1616743.1 | S11: 1586905.5 | T11: 1594506 | U11: 1594506 | V11: 1785013 | W11: 1890548 | X11: 1721431 | Y11: 1713692 | Z11: 1713692 | AA11: 1980736 | AB11: 2455840
A12: 1 | C12: 선급금 | E12: 499609.56 | F12: 499609.56 | G12: 601993.48 | H12: 699551.83 | I12: 667630.39 | J12: 609869.21 | K12: 609869.21 | L12: 582950.49 | M12: 613369.11 | N12: 564148.43 | O12: 508209.82 | P12: 508209.82 | Q12: 454596.04 | R12: 530718.51 | S12: 368887.7 | T12: 360750 | U12: 360750 | V12: 377116 | W12: 372830 | X12: 454337 | Y12: 510532 | Z12: 510532 | AA12: 469171 | AB12: 451081
A13: 1 | C13: 선급금등 | E13: 499609.56 | F13: 499609.56 | G13: 601993.48 | H13: 699551.83 | I13: 667630.39 | J13: 609869.21 | K13: 609869.21 | L13: 582950.49 | M13: 613369.11 | N13: 564148.43 | O13: 508209.82 | P13: 508209.82 | Q13: 454596.04 | R13: 530718.51 | S13: 368887.7 | T13: 360750 | U13: 360750 | V13: 377116 | W13: 372830 | X13: 454337 | Y13: 510532 | Z13: 510532 | AA13: 469171 | AB13: 451081
A14: 1 | C14: 기타유동자산 | E14: 784772.44 | F14: 784772.44 | G14: 915231.71 | H14: 1002515.8 | I14: 995620.14 | J14: 923853.7 | K14: 923853.7 | L14: 951495.08 | M14: 977095.05 | N14: 914075.95 | O14: 831622.46 | P14: 831622.46 | Q14: 790035.44 | R14: 878485.5 | S14: 721963.24 | T14: 729689 | U14: 729689 | V14: 777171 | W14: 773824 | X14: 868614 | Y14: 936872 | Z14: 936872 | AA14: 915781 | AB14: 915499
A15: 1 | C15: 단기대여금 | E15: 62126.81 | F15: 62126.81 | G15: 57901.48 | H15: 61196.01 | I15: 59057.92 | J15: 73900.53 | K15: 73900.53 | L15: 69759.04 | M15: 89995.93 | N15: 102701.8 | O15: 47332.37 | P15: 47332.37 | Q15: 49839.12 | R15: 67987.83 | S15: 24364.08 | T15: 27611 | U15: 27611 | V15: 28796 | W15: 13192 | X15: 12937 | Y15: 12699 | Z15: 12699 | AA15: 28254 | AB15: 38866
A16: 1 | C16: 유동확정계약자산 | E16: 45877.39 | F16: 45877.39 | G16: 51712.95 | H16: 90525.14 | I16: 162434.73 | J16: 54927.58 | K16: 54927.58 | L16: 64955.48 | M16: 61877.81 | N16: 75526.51 | O16: 37393.79 | P16: 37393.79 | Q16: 67902.65 | R16: 85217.89 | S16: 48524 | T16: 114250 | U16: 114250 | V16: 108750 | W16: 37048 | X16: 53728 | Y16: 65857 | Z16: 65857 | AA16: 130695 | AB16: 178554
A17: 1 | C17: 재고자산 | E17: 1788420.2 | F17: 1788420.2 | G17: 2203137 | H17: 2327838.6 | I17: 2660766 | J17: 2459026 | K17: 2459026 | L17: 2653226.1 | M17: 2679270.3 | N17: 2691408.4 | O17: 2539004.4 | P17: 2539004.4 | Q17: 2790504.7 | R17: 3049889.2 | S17: 3071098.3 | T17: 2733933 | U17: 2733933 | V17: 3037819 | W17: 2719745 | X17: 2771060 | Y17: 2544025 | Z17: 2544025 | AA17: 2828194 | AB17: 3144625
A18: 1 | C18: 매각예정비유동자산및처분자산 | E18: 319607.73 | F18: 319607.73 | G18: 329114.59 | H18: 759705.53 | I18: 30644.74 | J18: 4684.77 | K18: 4684.77 | L18: 15238.93 | M18: 14265.03 | N18: 14265.03 | O18: 44183.59 | P18: 44183.59 | Q18: 44188.19 | R18: 1505.81 | S18: 1505.81 | T18: 1506 | U18: 1506 | V18: 1291 | W18: 0 | X18: 264654 | Y18: 0 | Z18: 0 | AA18: 84218
A19: 1 | C19: 비유동자산 | E19: 15302922 | F19: 15302922 | G19: 15474502 | H19: 15512187 | I19: 16253183 | J19: 14950888 | K19: 14950888 | L19: 15392072 | M19: 15302681 | N19: 15389294 | O19: 14999266 | P19: 14999266 | Q19: 15324973 | R19: 15758886 | S19: 15589487 | T19: 16265813 | U19: 16265813 | V19: 16388575 | W19: 16315382 | X19: 16517793 | Y19: 16741512 | Z19: 16741512 | AA19: 17096447 | AB19: 17480822
A20: 1 | C20: 장기금융자산 | E20: 330981.78 | F20: 330981.78 | G20: 341610.11 | H20: 361434.62 | I20: 387940.7 | J20: 352607.3 | K20: 352607.3 | L20: 358710.15 | M20: 274444.31 | N20: 270458.36 | O20: 247214.42 | P20: 247214.42 | Q20: 262341.07 | R20: 381874.22 | S20: 367362.09 | T20: 461718 | U20: 461718 | V20: 479843 | W20: 600020 | X20: 628449 | Y20: 491644 | Z20: 491644 | AA20: 487980 | AB20: 503046
A21: 1 | C21: 투자자산 | E21: 978622.22 | F21: 978622.22 | G21: 1014080.6 | H21: 1088113.3 | I21: 1242709.5 | J21: 790337.32 | K21: 790337.32 | L21: 975412.05 | M21: 910037.28 | N21: 887378.2 | O21: 774812.07 | P21: 774812.07 | Q21: 854459.2 | R21: 1029268 | S21: 1054127.1 | T21: 994606 | U21: 994606 | V21: 987513 | W21: 1151603 | X21: 1190482 | Y21: 1025298 | Z21: 1025298 | AA21: 1056140 | AB21: 1238382
A22: 1 | C22: 종속기업및관계기업투자 | E22: 582045.11 | F22: 582045.11 | G22: 600360.64 | H22: 610282.45 | I22: 683056.03 | J22: 355954.92 | K22: 355954.92 | L22: 377073.95 | M22: 394718.45 | N22: 370318.2 | O22: 316869.59 | P22: 316869.59 | Q22: 362439.33 | R22: 403890.58 | S22: 416340.43 | T22: 347660 | U22: 347660 | V22: 348456 | W22: 358134 | X22: 382629 | Y22: 352647 | Z22: 352647 | AA22: 372988 | AB22: 394865
A23: 1 | C23: 장기대여금 | E23: 44703.08 | F23: 44703.08 | G23: 46690.4 | H23: 53226.25 | I23: 53326.31 | J23: 41235.87 | K23: 41235.87 | L23: 193743.84 | M23: 198198.25 | N23: 200100.13 | O23: 184879.26 | P23: 184879.26 | Q23: 209128.49 | R23: 216572.23 | S23: 260807.85 | T23: 171691 | U23: 171691 | V23: 148235 | W23: 164398 | X23: 134483 | Y23: 118354 | Z23: 118354 | AA23: 103326 | AB23: 102065
A24: 1 | C24: 유형자산 | E24: 5436969.4 | F24: 5436969.4 | G24: 5442606.2 | H24: 5232674.8 | I24: 5342548.8 | J24: 5022147.6 | K24: 5022147.6 | L24: 5082049.5 | M24: 5070278.1 | N24: 5106593.6 | O24: 5225149.3 | P24: 5225149.3 | Q24: 5262427.7 | R24: 5359626.9 | S24: 5376205.8 | T24: 5703049 | U24: 5703049 | V24: 5716936 | W24: 5681822 | X24: 5658171 | Y24: 5776625 | Z24: 5776625 | AA24: 5822454 | AB24: 5916940
A25: 1 | C25: 무형자산 | E25: 8015980.1 | F25: 8015980.1 | G25: 8112119.7 | H25: 8282884.8 | I25: 8732222.8 | J25: 7772723.6 | K25: 7772723.6 | L25: 8009456 | M25: 8063006.7 | N25: 8158771.5 | O25: 7892981.7 | P25: 7892981.7 | Q25: 8080508.8 | R25: 8268439.5 | S25: 8088419.9 | T25: 8397290 | U25: 8397290 | V25: 8515804 | W25: 8360155 | X25: 8574522 | Y25: 8723585 | Z25: 8723585 | AA25: 8986009 | AB25: 9102599
A26: 1 | C26: 투자부동산 | E26: 72920.33 | F26: 72920.33 | G26: 72447.44 | H26: 71430.68 | I26: 79680.81 | J26: 274446.28 | K26: 274446.28 | L26: 251276.15 | M26: 282378.93 | N26: 280931.12 | O26: 208608.26 | P26: 208608.26 | Q26: 208380.54 | R26: 206782.51 | S26: 205891.8 | T26: 228288 | U26: 228288 | V26: 226689 | W26: 225138 | X26: 223511 | Y26: 219139 | Z26: 219139 | AA26: 217719 | AB26: 211745
A27: 1 | C27: 비유동확정계약자산 | E27: 20892.25 | F27: 20892.25 | G27: 25419.48 | H27: 63169.94 | I27: 118386.42 | J27: 40539.23 | K27: 40539.23 | L27: 45884.11 | M27: 42676.27 | N27: 46501.51 | O27: 25848.8 | P27: 25848.8 | Q27: 20550.31 | R27: 26930.95 | S27: 9616.76 | T27: 13537 | U27: 13537 | V27: 10979 | W27: 29051 | X27: 44921 | Y27: 62653 | Z27: 62653 | AA27: 91846 | AB27: 238406
A28: 1 | C28: 기타비유동자산 | E28: 454215.34 | F28: 454215.34 | G28: 483260.24 | H28: 452160.73 | I28: 486929.83 | J28: 553730.24 | K28: 553730.24 | L28: 558265.53 | M28: 555786.9 | N28: 517524.53 | O28: 377623.09 | P28: 377623.09 | Q28: 400187.15 | R28: 402710.11 | S28: 395090.56 | T28: 368647 | U28: 368647 | V28: 357835 | W28: 344944 | X28: 327561 | Y28: 317311 | Z28: 317311 | AA28: 351759 | AB28: 356551
A29: 1 | C29: 이연법인세자산 | E29: 232791.07 | F29: 232791.07 | G29: 234520.85 | H29: 241882.48 | I29: 241047.78 | J29: 416706.17 | K29: 416706.17 | L29: 402249.29 | M29: 406413.55 | N29: 412826.67 | O29: 502987.74 | P29: 502987.74 | Q29: 497080.61 | R29: 482406.48 | S29: 462161.1 | T29: 556161 | U29: 556161 | V29: 557815 | W29: 508774 | X29: 517775 | Y29: 628403 | Z29: 628403 | AA29: 616930 | AB29: 611231
A30: 1 | C30: 자산총계 | E30: 23720546 | F30: 23720546 | G30: 24145803 | H30: 24271351 | I30: 25170912 | J30: 23049782 | K30: 23049782 | L30: 23998329 | M30: 25307471 | N30: 24939919 | O30: 24640834 | P30: 24640834 | Q30: 25657121 | R30: 26114105 | S30: 25264597 | T30: 26314835 | U30: 26314835 | V30: 26896993 | W30: 26305196 | X30: 27027903 | Y30: 27513223 | Z30: 27513223 | AA30: 28695055 | AB30: 29947742
... A41: 1 | C41: 단기충당부채 | E41: 320457.9 | F41: 320457.9 | G41: 313783.96 | H41: 300348.18 | I41: 318120.64 | J41: 319218.54 | K41: 319218.54 | L41: 323242.45 | M41: 300733.1 | N41: 283930.45 | O41: 257968.84 | P41: 257968.84 | Q41: 219131.3 | R41: 211200.26 | S41: 204355.35 | T41: 241923 | U41: 241923 | V41: 236405 | W41: 229223 | X41: 247369 | Y41: 270809 | Z41: 270809 | AA41: 272614 | AB41: 300035
A42: 1 | C42: 유동리스부채 | E42: 64880.16 | F42: 64880.16 | G42: 66229.69 | J42: 76193.14 | K42: 76193.14 | L42: 79664.02 | M42: 82753.51 | O42: 78987.4 | P42: 78987.4 | Q42: 88399.96 | R42: 90060.74 | S42: 92513.56 | T42: 102853 | U42: 102853 | V42: 101479 | W42: 97964 | X42: 100433 | Y42: 100745 | Z42: 100745 | AA42: 103703 | AB42: 108847
A43: 1 | C43: 리스부채 | E43: 381187.32 | F43: 381187.32 | G43: 368071.26 | H43: 322162.05 | I43: 332673.62 | J43: 393893.74 | K43: 393893.74 | L43: 395706.2 | M43: 404843.26 | N43: 313951.82 | O43: 388067.78 | P43: 388067.78 | Q43: 390867.73 | R43: 383803.83 | S43: 379226.34 | T43: 404885 | U43: 404885 | V43: 389848 | W43: 374716 | X43: 373218 | Y43: 361872 | Z43: 361872 | AA43: 402794 | AB43: 405593
A44: 1 | C44: 비유동부채 | E44: 4787184.4 | F44: 4787184.4 | G44: 5355238.7 | H44: 5124973.6 | I44: 5089208.5 | J44: 4910036 | K44: 4910036 | L44: 4769842.5 | M44: 4667291.7 | N44: 4580739.4 | O44: 4202575.4 | P44: 4202575.4 | Q44: 4781204.6 | R44: 4945377.1 | S44: 4991623.2 | T44: 5707923 | U44: 5707923 | V44: 5643218 | W44: 5843723 | X44: 5591781 | Y44: 5396786 | Z44: 5396786 | AA44: 5084121 | AB44: 5209227
A45: 1 | C45: 사채 | E45: 848257.26 | F45: 848257.26 | G45: 918636.53 | H45: 649547 | I45: 329192.22 | J45: 356347.78 | K45: 356347.78 | L45: 313840.25 | M45: 296303.17 | N45: 528632.16 | O45: 493916.91 | P45: 493916.91 | Q45: 646739.73 | R45: 667920.12 | S45: 863778.79 | T45: 906758 | U45: 906758 | V45: 818317 | W45: 908843 | X45: 456865 | Y45: 499127 | Z45: 499127 | AA45: 438536 | AB45: 328608
A46: 1 | C46: 장기차입금 | E46: 1516918.5 | F46: 1516918.5 | G46: 2024704.1 | H46: 2118759.4 | I46: 2154106.3 | J46: 2350867.6 | K46: 2350867.6 | L46: 2176489.5 | M46: 2041640.3 | N46: 1747865.3 | O46: 1457749.4 | P46: 1457749.4 | Q46: 1865275.8 | R46: 1947862.4 | S46: 1927284.6 | T46: 2434534 | U46: 2434534 | V46: 2513424 | W46: 2554775 | X46: 2721533 | Y46: 2336139 | Z46: 2336139 | AA46: 2060904 | AB46: 2068141
A47: 1 | C47: 장기매입채무및기타채무 | E47: 14522.4 | F47: 14522.4 | G47: 9276.7 | H47: 9718.71 | I47: 10424.75 | J47: 11278.27 | K47: 11278.27 | L47: 10687.17 | M47: 11238.29 | N47: 11254.27 | O47: 11673.97 | P47: 11673.97 | Q47: 11753.55 | R47: 11764.76 | S47: 11970.31 | T47: 11189 | U47: 11189 | V47: 12016 | W47: 13650 | X47: 14649 | Y47: 22940 | Z47: 22940 | AA47: 25389 | AB47: 29250
A48: 1 | C48: 확정급여부채 | E48: 540496.54 | F48: 540496.54 | G48: 586394.6 | H48: 590166.73 | I48: 643844.69 | J48: 452352.77 | K48: 452352.77 | L48: 472131.68 | M48: 412889.2 | N48: 395807.59 | O48: 472216.38 | P48: 472216.38 | Q48: 498560.1 | R48: 509380.95 | S48: 499092.33 | T48: 570726 | U48: 570726 | V48: 573151 | W48: 566941 | X48: 574016 | Y48: 581488 | Z48: 581488 | AA48: 584972 | AB48: 594613
A49: 1 | C49: 장기파생상품부채 | E49: 5651.86 | F49: 5651.86 | G49: 5537.29 | H49: 4033.03 | I49: 4322.3 | J49: 6307.16 | K49: 6307.16 | L49: 6270.63 | M49: 11607.48 | N49: 3801.75 | O49: 13447.73 | P49: 13447.73 | Q49: 3646.17 | R49: 3511.97 | S49: 3169.65 | T49: 2457 | U49: 2457 | V49: 4173 | W49: 20834 | X49: 11345 | Y49: 35233 | Z49: 35233 | AA49: 3093 | AB49: 2593
A50: 1 | C50: 장기금융부채 | E50: 321959.02 | F50: 321959.02 | G50: 307378.86 | H50: 326195.08 | I50: 336995.92 | J50: 324007.76 | K50: 324007.76 | L50: 322312.81 | M50: 333697.23 | N50: 317753.57 | O50: 322528.11 | P50: 322528.11 | Q50: 306113.94 | R50: 297255.06 | S50: 289882.43 | T50: 304489 | U50: 304489 | V50: 292542 | W50: 297586 | X50: 284130 | Y50: 296360 | Z50: 296360 | AA50: 302184 | AB50: 299339
A51: 1 | C51: 이연법인세부채 | E51: 462047.65 | F51: 462047.65 | G51: 476397.34 | H51: 515113.89 | I51: 590878.19 | J51: 502157.75 | K51: 502157.75 | L51: 526525.98 | M51: 561848.51 | N51: 547841.99 | O51: 477395.35 | P51: 477395.35 | Q51: 503341.84 | R51: 524944.01 | S51: 472325.85 | T51: 510165 | U51: 510165 | V51: 494409 | W51: 477961 | X51: 547599 | Y51: 603328 | Z51: 603328 | AA51: 640984 | AB51: 714062
A52: 1 | C52: 장기충당부채 | E52: 312515.74 | F52: 312515.74 | G52: 310908.19 | H52: 323822.51 | I52: 341062.18 | J52: 380357.59 | K52: 380357.59 | L52: 383686.76 | M52: 385467.71 | N52: 387590.65 | O52: 372326.69 | P52: 372326.69 | Q52: 377966.8 | R52: 390695 | S52: 380695.91 | T52: 364830 | U52: 364830 | V52: 365578 | W52: 360990 | X52: 350264 | Y52: 350178 | Z52: 350178 | AA52: 366161 | AB52: 382889
A53: 1 | C53: 비유동리스부채 | E53: 316307.16 | F53: 316307.16 | G53: 301841.57 | H53: 322162.05 | I53: 332673.62 | J53: 317700.6 | K53: 317700.6 | L53: 316042.18 | M53: 322089.75 | N53: 313951.82 | O53: 309080.38 | P53: 309080.38 | Q53: 302467.77 | R53: 293743.09 | S53: 286712.78 | T53: 302032 | U53: 302032 | V53: 288369 | W53: 276752 | X53: 272785 | Y53: 261127 | Z53: 261127 | AA53: 299091 | AB53: 296746
A54: 1 | C54: 기타비유동부채 | E54: 402221.52 | F54: 402221.52 | G54: 369365.03 | H54: 132020.05 | I54: 126915.19 | J54: 123709.67 | K54: 123709.67 | L54: 134038.73 | M54: 137810.03 | N54: 142447.48 | O54: 144420.11 | P54: 144420.11 | Q54: 154753.91 | R54: 178804.18 | S54: 174899.54 | T54: 229537 | U54: 229537 | V54: 246252 | W54: 254167 | X54: 259965 | Y54: 316298 | Z54: 316298 | AA54: 280640 | AB54: 274498
A55: 1 | C55: 부채총계 | E55: 14912950 | F55: 14912950 | G55: 13837794 | H55: 13752762 | I55: 14134037 | J55: 12969492 | K55: 12969492 | L55: 13501424 | M55: 14279957 | N55: 13778618 | O55: 13799325 | P55: 13799325 | Q55: 14404726 | R55: 14456376 | S55: 13894712 | T55: 14653743 | U55: 14653743 | V55: 15153864 | W55: 14676911 | X55: 15161713 | Y55: 15503853 | Z55: 15503853 | AA55: 16251439 | AB55: 17281259
A56: 1 | C56: 지배주주지분 | E56: 6091427.2 | F56: 6091427.2 | G56: 7566091.2 | H56: 7633483.7 | I56: 8037426.5 | J56: 7113272.7 | K56: 7113272.7 | L56: 7369090.6 | N56: 7474798.3
A57: 1 | C57: 자본금 | E57: 2675625 | F57: 2675625 | G57: 3193488.9 | H57: 3240986.3 | I57: 3256061.2 | J57: 3256061.2 | K57: 3256061.2 | L57: 3267326.8 | M57: 3267326.8 | N57: 3267326.8 | O57: 3267326.8 | P57: 3267326.8 | Q57: 3267326.8 | R57: 3267326.8 | S57: 3267326.8 | T57: 3267327 | U57: 3267327 | V57: 3267327 | W57: 3267327 | X57: 3267327 | Y57: 3267327 | Z57: 3267327 | AA57: 3267327 | AB57: 3267327
A58: 1 | C58: 자본잉여금 | E58: 1865083.2 | F58: 1865083.2 | G58: 2781514.4 | H58: 2853611 | I58: 2870037.8 | J58: 2870068.2 | K58: 2870068.2 | L58: 1732323.8 | M58: 1712672.7 | N58: 1712769.6 | O58: 1712764.1 | P58: 1712764.1 | Q58: 1563501.2 | R58: 1563778 | S58: 1563778 | T58: 1572095 | U58: 1572095 | V58: 1441555 | W58: 1440483 | X58: 1440483 | Y58: 1441574 | Z58: 1441574 | AA58: 1440992 | AB58: 1440992
A59: 1 | C59: 기타자본 | E59: 46159.35 | F59: 46159.35 | G59: 45570.94 | H59: 45662.45 | I59: 45618.81 | J59: 45676.12 | K59: 45676.12 | L59: 45676.57 | M59: 45767.3 | N59: 45914.72 | O59: 46056.9 | P59: 46056.9 | Q59: 46020.14 | R59: 46374.88 | S59: 46650.57 | T59: 46766 | U59: 46766 | V59: 45455 | W59: 45455 | X59: 45594 | Y59: 45529 | Z59: 45529 | AA59: 84725 | AB59: -30058
A60: 1 | C60: 기타포괄이익누계액 | E60: 731324.74 | F60: 731324.74 | G60: 806170.54 | H60: 919753 | I60: 1213524.6 | J60: 882653.39 | K60: 882653.39 | L60: 1044046.6 | M60: 1013967.6 | N60: 1041575.2 | O60: 906691.29 | P60: 906691.29 | Q60: 990981.42 | R60: 1089268.9 | S60: 973975.3 | T60: 1215926 | U60: 1215926 | V60: 1300764 | W60: 1145032 | X60: 1257763 | Y60: 1334986 | Z60: 1334986 | AA60: 1526330 | AB60: 1607242
A61: 1 | C61: 이익잉여금 | E61: 773234.89 | F61: 773234.89 | G61: 739346.44 | H61: 567256.73 | I61: 652184.1 | J61: 58813.72 | K61: 58813.72 | L61: 1279716.9 | M61: 1389714 | N61: 1407212 | O61: 1184531.9 | P61: 1184531.9 | Q61: 1479859 | R61: 1623038.8 | S61: 1577068.9 | T61: 1394448 | U61: 1394448 | V61: 1548618 | W61: 1682687 | X61: 1634980 | Y61: 1696327 | Z61: 1696327 | AA61: 1713607 | AB61: 1874130
A62: 1 | C62: 비지배주주지분 | E62: 2716168.5 | F62: 2716168.5 | G62: 2741918.1 | H62: 2885105.7 | I62: 2999448.4 | J62: 2967017.6 | K62: 2967017.6 | L62: 3127814.6 | M62: 3598066.4 | N62: 3686502.1 | O62: 3724138 | P62: 3724138 | Q62: 3900653.4 | R62: 4067941.1 | S62: 3941085.6 | T62: 4164530 | U62: 4164530 | V62: 4139410 | W62: 4047301 | X62: 4161294 | Y62: 4223627 | Z62: 4223627 | AA62: 4410635 | AB62: 4506850
A63: 1 | C63: 자본총계 | E63: 8807595.6 | F63: 8807595.6 | G63: 10308009 | H63: 10518589 | I63: 11036875 | J63: 10080290 | K63: 10080290 | L63: 10496905 | M63: 11027515 | N63: 11161300 | O63: 10841509 | P63: 10841509 | Q63: 11252394 | R63: 11657728 | S63: 11369885 | T63: 11661092 | U63: 11661092 | V63: 11743129 | W63: 11628285 | X63: 11866190 | Y63: 12009370 | Z63: 12009370 | AA63: 12443616 | AB63: 12666483
A64: 1 | C64: 부채와자본총계 | E64: 23720546 | F64: 23720546 | G64: 24145803 | H64: 24271351 | I64: 25170912 | J64: 23049782 | K64: 23049782 | L64: 23998329 | M64: 25307471 | N64: 24939919 | O64: 24640834 | P64: 24640834 | Q64: 25657121 | R64: 26114105 | S64: 25264597 | T64: 26314835 | U64: 26314835 | V64: 26896993 | W64: 26305196 | X64: 27027903 | Y64: 27513223 | Z64: 27513223 | AA64: 28695055 | AB64: 29947742
A65: 1 | C65: 총차입금 | E65: 7212521.6 | F65: 7212521.6 | G65: 5555792.5 | H65: 5009198.6 | I65: 5194407 | J65: 4911792.9 | K65: 4911792.9 | L65: 5158710.1 | M65: 5086903.5 | N65: 4789737 | O65: 4714615.1 | P65: 4714615.1 | Q65: 4860699.9 | R65: 5280006.8 | S65: 5982488.8 | T65: 5880769 | U65: 5880769 | V65: 6327710 | W65: 6107478 | X65: 6640146 | Y65: 5748685 | Z65: 5748685 | AA65: 6555731 | AB65: 6891335
A66: 1 | C66: 순차입금 | E66: 4676763.4 | F66: 4676763.4 | G66: 3550155.9 | H66: 3613131.5 | I66: 3345667.4 | J66: 3281346.8 | K66: 3281346.8 | L66: 3354403 | M66: 2131911.8 | N66: 2238945.3 | O66: 1891430.2 | P66: 1891430.2 | Q66: 1687744.3 | R66: 2439800.1 | S66: 3521212.8 | T66: 2697033 | U66: 2697033 | V66: 3428534 | W66: 3662807 | X66: 4057748 | Y66: 2481262 | Z66: 2481262 | AA66: 3197391 | AB66: 3855781
A67: 1 | C67: 이자발생자산 | E67: 2866740 | F67: 2866740 | G67: 2347246.7 | H67: 1757501.7 | I67: 2236680.3 | J67: 1983053.4 | K67: 1983053.4 | L67: 2163017.3 | M67: 3229436 | N67: 2821250 | O67: 3070399.2 | P67: 3070399.2 | Q67: 3435296.7 | R67: 3222080.9 | S67: 2828638.1 | T67: 3645454 | U67: 3645454 | V67: 3379019 | W67: 3044691 | X67: 3210847 | Y67: 3759067 | Z67: 3759067 | AA67: 3846320 | AB67: 3538600
A68: 1 | C68: 매출액(수익) | E68: 2170787.2 | G68: 3071285 | H68: 3834655.8 | I68: 3960324.1 | J68: 4621768.3 | K68: 15488033 | L68: 4041041.8 | M68: 4539361.8 | N68: 4154979.8 | O68: 4854504.3 | P68: 17589888 | Q68: 4097866.7 | R68: 4150487.3 | S68: 3395568.9 | T68: 4589132 | U68: 16233055 | V68: 3748574 | W68: 4569021 | X68: 3880350 | Y68: 4859931 | Z68: 17057876 | AA68: 4261130 | AB68: 4724808
A69: 1 | C69: 매출원가 | E69: 1828642.7 | G69: 2551539.8 | H69: 3169295.5 | I69: 3289452.9 | J69: 3915683.1 | K69: 12925971 | L69: 3324948.1 | M69: 3723833.2 | N69: 3445958.6 | O69: 4078146.3 | P69: 14572886 | Q69: 3350758.5 | R69: 3421309 | S69: 2871437.7 | T69: 3859830.8 | U69: 13503336 | V69: 3150914 | W69: 3822574 | X69: 3276221 | Y69: 4064857 | Z69: 14314566 | AA69: 3516988 | AB69: 3838343
A70: 1 | C70: 매출총이익 | E70: 342144.51 | G70: 519745.29 | H70: 665360.28 | I70: 670871.25 | J70: 706085.22 | K70: 2562062 | L70: 716093.62 | M70: 815528.58 | N70: 709021.23 | O70: 776358.06 | P70: 3017001.5 | Q70: 747108.18 | R70: 729178.33 | S70: 524131.26 | T70: 729301.22 | U70: 2729719 | V70: 597660 | W70: 746447 | X70: 604129 | Y70: 795074 | Z70: 2743310 | AA70: 744142 | AB70: 886465
A71: 1 | C71: 판관비 | E71: 215162.51 | G71: 327605.36 | H71: 337023.73 | I71: 356302.15 | J71: 434378 | K71: 1455309.2 | L71: 351519.13 | M71: 320878.27 | N71: 397631.83 | O71: 479653.92 | P71: 1549683.1 | Q71: 389037.24 | R71: 419388.1 | S71: 409341.68 | T71: 494351.98 | U71: 1712119 | V71: 455185 | W71: 475341 | X71: 467070 | Y71: 583002 | Z71: 1980598 | AA71: 510628 | AB71: 572205
A72: 1 | C72: 영업이익 | E72: 126982 | G72: 192139.94 | H72: 328336.56 | I72: 314569.1 | J72: 271707.22 | K72: 1106752.8 | L72: 364574.49 | M72: 494650.31 | N72: 311389.4 | O72: 296704.14 | P72: 1467318.3 | Q72: 358070.95 | R72: 309790.23 | S72: 114789.58 | T72: 234949.24 | U72: 1017600 | V72: 142475 | W72: 271106 | X72: 137059 | Y72: 212072 | Z72: 762712 | AA72: 233514 | AB72: 314260
A73: 1 | C73: 금융손익 | E73: -72452.62 | G73: -128514.08 | H73: -225785.51 | I73: -143902.21 | J73: 15716.89 | K73: -482484.91 | L73: -58023.38 | M73: -54070.41 | N73: -76427.16 | O73: -79430.34 | P73: -267951.29 | Q73: -14694.97 | R73: -41622.22 | S73: -70831.61 | T73: -54103.21 | U73: -181252.01 | V73: -79445 | W73: -73142 | X73: -131221 | Y73: -61261 | Z73: -345069 | AA73: -110583 | AB73: 21652
A74: 1 | C74: 금융수익 | E74: 80622.68 | G74: 140669.96 | H74: 382664.15 | I74: 650758.59 | J74: -425967.02 | K74: 748125.68 | L74: 275199.55 | M74: 172215.56 | N74: 182182.16 | O74: -34486.06 | P74: 595111.21 | Q74: 349957.8 | R74: 266122.19 | S74: -72836.4 | T74: 612560.41 | U74: 1155804 | V74: 269121 | W74: 394506 | X74: -12083 | Y74: 223940 | Z74: 875484 | AA74: 536170 | AB74: 348911
A75: 1 | C75: 금융비용 | E75: 153075.31 | G75: 269184.04 | H75: 608449.65 | I75: 794660.8 | J75: -441683.92 | K75: 1230610.6 | L75: 333222.93 | M75: 226285.97 | N75: 258609.32 | O75: 44944.28 | P75: 863062.5 | Q75: 364652.77 | R75: 307744.41 | S75: -2004.79 | T75: 666663.62 | U75: 1337056 | V75: 348566 | W75: 467648 | X75: 119138 | Y75: 285201 | Z75: 1220553 | AA75: 646753 | AB75: 327259
A76: 1 | C76: 기타영업외손익 | E76: 5163.62 | G76: 3792.58 | H76: 52438.98 | I76: 4599.96 | J76: -640439.17 | K76: -579607.65 | L76: -40279.98 | M76: -40772.25 | N76: -14166.91 | O76: -326978.55 | P76: -422197.69 | Q76: 18931.68 | R76: 27602.66 | S76: -8927.25 | T76: -236660.09 | U76: -199053 | V76: -34702 | W76: 107222 | X76: -40163 | Y76: -145997 | Z76: -113640 | AA76: -17239 | AB76: -2931
A77: 1 | C77: 기타영업외수익 | E77: 28567.56 | G77: 36387.01 | H77: 61424.15 | I77: 25650.11 | J77: 37209.45 | K77: 160670.72 | L77: 4638.83 | M77: 4591.88 | N77: 3752.4 | O77: 36320.67 | P77: 49303.78 | Q77: 36345.69 | R77: 42917.39 | S77: 3156.83 | T77: 61348.09 | U77: 143768 | V77: 4624 | W77: 108912 | X77: -5654 | Y77: -5071 | Z77: 102811 | AA77: 6851 | AB77: 19536
A78: 1 | C78: 기타영업외비용 | E78: 23403.94 | G78: 32594.43 | H78: 8985.17 | I78: 21050.15 | J78: 677648.63 | K78: 740278.38 | L78: 44918.8 | M78: 45364.13 | N78: 17919.31 | O78: 363299.21 | P78: 471501.45 | Q78: 17414.01 | R78: 15314.73 | S78: 12084.08 | T78: 298008.18 | U78: 342821 | V78: 39326 | W78: 1690 | X78: 34509 | Y78: 140926 | Z78: 216451 | AA78: 24090 | AB78: 22467
A79: 1 | C79: 종속기업,공동지배기업및관계기업관련손익 | E79: 1572.87 | G79: -6447.45 | H79: -3900.61 | I79: 1602.24 | J79: -221137.38 | K79: -229883.2 | L79: 21305.04 | M79: 15316.26 | N79: -23797.57 | O79: -51511.36 | P79: -38687.63 | Q79: 6529.85 | R79: 20927.35 | S79: 3542.18 | T79: -10515.38 | U79: 20484 | V79: 1879 | W79: 5350 | X79: 16392 | Y79: -817 | Z79: 22804 | AA79: 13762 | AB79: 14897
... A83: 1 | C83: 계속사업이익 | E83: 124124.39 | G83: 11520.19 | H83: 67388.2 | I83: 72901.9 | J83: -484095.51 | K83: -332285.22 | L83: 170714.85 | M83: 262790.06 | N83: 120356.31 | O83: -36339.31 | P83: 517521.91 | Q83: 261052.33 | R83: 220766.64 | S83: -26474.41 | T83: -60655.56 | U83: 394689 | V83: -21157 | W83: 197809 | X83: -24028 | Y83: 52539 | Z83: 205163 | AA83: 60226 | AB83: 226368
A84: 1 | C84: 중단사업이익 | E84: -40979.54 | G84: -512.54 | H84: -191924.26 | I84: 71619.5 | J84: -47.32 | K84: -120864.62
A85: 1 | C85: 당기순이익 | E85: 83144.85 | G85: 11007.64 | H85: -124536.07 | I85: 144521.4 | J85: -484142.85 | K85: -453149.88 | L85: 170714.85 | M85: 262790.06 | N85: 120356.31 | O85: -36339.31 | P85: 517521.91 | Q85: 261052.33 | R85: 220766.64 | S85: -26474.41 | T85: -60655.56 | U85: 394689 | V85: -21157 | W85: 197809 | X85: -24028 | Y85: 52539 | Z85: 205163 | AA85: 60226 | AB85: 226368
A86: 1 | C86: (지배주주지분)당기순이익 | E86: 175987.49 | G86: -38346.9 | H86: -193696.1 | I86: 86149.59 | J86: -626599.19 | K86: -772492.6 | L86: 69549.73 | M86: 107389.6 | N86: 21737.5 | O86: -143078.87 | P86: 55597.96 | Q86: 144160.09 | R86: 136170.49 | S86: -55024.91 | T86: -113940.67 | U86: 111365 | V86: -68860 | W86: 130927 | X86: -50078 | Y86: 72773 | Z86: 84762 | AA86: 758 | AB86: 157619
A87: 1 | C87: (비지배주주지분)당기순이익 | E87: -92842.65 | G87: 49354.55 | H87: 69160.03 | I87: 58371.81 | J87: 142456.34 | K87: 319342.73 | L87: 101165.11 | M87: 155400.46 | N87: 98618.8 | O87: 106739.57 | P87: 461923.94 | Q87: 116892.23 | R87: 84596.16 | S87: 28550.5 | T87: 53285.11 | U87: 283324 | V87: 47703 | W87: 66882 | X87: 26050 | Y87: -20234 | Z87: 120401 | AA87: 59468 | AB87: 68749
A88: 1 | C88: 총포괄손익 | E88: 284602.5 | G88: 126852.8 | H88: 91102.36 | I88: 619941.39 | J88: -956755.08 | K88: -118858.53 | L88: 431033.8 | M88: 249783.37 | N88: 176542.08 | O88: -320086.29 | P88: 537272.96 | Q88: 453762.59 | R88: 407894.96 | S88: -245315.71 | T88: 356624.17 | U88: 972966.01 | V88: 115214 | W88: -89214 | X88: 264028 | Y88: 237348 | Z88: 527376 | AA88: 419382 | AB88: 384149
A89: 1 | C89: 이자수익 | G89: 1525 | H89: 11596 | I89: 5126 | J89: 6965 | K89: 25212 | L89: 10010 | M89: 18252 | N89: 26119 | O89: 25839 | P89: 80220 | Q89: 26415 | R89: 29655 | S89: 25366 | T89: 27766 | U89: 109202 | V89: 20212 | W89: 21739 | X89: 20075 | Y89: 24720 | Z89: 86746 | AA89: 18062 | AB89: 22427
A90: 1 | C90: 배당금수익 | G90: 696 | H90: 2659 | I90: 456 | J90: 0 | K90: 3811 | L90: 2092 | M90: 682 | N90: 67 | O90: 64 | P90: 2905 | Q90: 240 | R90: 743 | S90: 8 | T90: 1418 | U90: 2409 | V90: 698 | W90: 541 | X90: 26 | Y90: 2325 | Z90: 3590 | AA90: 1756 | AB90: 873
A91: 1 | C91: 이자비용 | G91: 68842 | H91: 58608 | I91: 59942 | J91: 73141 | K91: 260533 | L91: 76045 | M91: 82880 | N91: 78689 | O91: 83277 | P91: 320891 | Q91: 78944 | R91: 80594 | S91: 79432 | T91: 90107 | U91: 329077 | V91: 79983 | W91: 78493 | X91: 84636 | Y91: 82836 | Z91: 325948 | AA91: 76908 | AB91: 90073
A92: 1 | C92: 외환차익 | G92: 22925 | H92: 35552 | I92: 125132 | J92: 122180 | K92: 305789 | L92: 72124 | M92: 92654 | N92: 49267 | O92: 56116 | P92: 270161 | Q92: 52180 | R92: 77851 | S92: 45633 | T92: 84902 | U92: 260566 | V92: 44941 | W92: 65166 | X92: 111280 | Y92: 60040 | Z92: 281427 | AA92: 53166 | AB92: 69639
A93: 1 | C93: 외환차손 | G93: 20603 | H93: 30936 | I93: 113128 | J93: 177528 | K93: 342195 | L93: 56705 | M93: 67068 | N93: 59850 | O93: 77522 | P93: 261145 | Q93: 47524 | R93: 66911 | S93: 44516 | T93: 100599 | U93: 259550 | V93: 44772 | W93: 111132 | X93: 81370 | Y93: 63078 | Z93: 300352 | AA93: 113198 | AB93: 2422
A94: 1 | C94: 외화환산이익 | G94: 29117 | H94: 104836 | I94: 180252 | J94: -196768 | K94: 117437 | L94: 70868 | M94: 7490 | N94: 25059 | O94: -48517 | P94: 54900 | Q94: 93975 | R94: 52019 | S94: -57284 | T94: 239243 | U94: 327953 | V94: 79447 | W94: 118348 | X94: -71306 | Y94: 5144 | Z94: 131633 | AA94: 146237 | AB94: 40330
A95: 1 | C95: 외화환산손실 | G95: 86992 | H95: 222274 | I95: 349052 | J95: -364841 | K95: 293477 | L95: 81674 | M95: 18810 | N95: 39732 | O95: -72568 | P95: 67648 | Q95: 75245 | R95: 52952 | S95: -49871 | T95: 193313 | U95: 271639 | V95: 88297 | W95: 82989 | X95: 20103 | Y95: 9913 | Z95: 201302 | AA95: 127914 | AB95: 16407
A96: 1 | C96: 파생상품이익 | G96: 52900 | H96: 99478 | I96: 133081 | J96: -50817 | K96: 234642 | L96: 49521 | M96: 42124 | N96: 25241 | O96: 26081 | P96: 142967 | Q96: 77950 | R96: 53120 | S96: 11685 | T96: 78182 | U96: 220937 | V96: 108613 | W96: 184185 | X96: -87178 | Y96: 74566 | Z96: 280186 | AA96: 73472 | AB96: 50788
A97: 1 | C97: 파생상품손실 | G97: 69239 | H97: 255613 | I97: 242261 | J97: -369668 | K97: 197445 | L97: 97929 | M97: 35665 | N97: 73516 | O97: -55979 | P97: 151131 | Q97: 141624 | R97: 93354 | S97: -81409 | T97: 236306 | U97: 389875 | V97: 123829 | W97: 32885 | X97: 40792 | Y97: 103249 | Z97: 300755 | AA97: 288806 | AB97: 204374
A98: 1 | C98: 이자손익 | G98: -67317 | H98: -47012 | I98: -54816 | J98: -66176 | K98: -235321 | L98: -66035 | M98: -64628 | N98: -52570 | O98: -57438 | P98: -240671 | Q98: -52529 | R98: -50939 | S98: -54066 | T98: -62341 | U98: -219875 | V98: -59771 | W98: -56754 | X98: -64561 | Y98: -58116 | Z98: -239202 | AA98: -58846 | AB98: -67646
A99: 1 | C99: 영업활동으로인한현금흐름 | E99: 691487.4 | G99: -269827.27 | H99: 319975.05 | I99: 505198.46 | J99: 69731.48 | K99: 625077.72 | L99: 233046.24 | M99: 1025689.7 | N99: 153622.84 | O99: 658274.52 | P99: 2070633.3 | Q99: 344383.65 | R99: -477065.35 | S99: -815354.02 | T99: 1190239.7 | U99: 242204 | V99: -572034 | W99: -12808 | X99: -60085 | Y99: 1396728 | Z99: 751801 | AA99: -565522 | AB99: -321130
A100: 1 | C100: 이자수취(CF) | E100: 5643.21 | G100: 2457 | H100: 3476.25 | I100: 4392.67 | J100: 7686.58 | K100: 18012.5 | L100: 7085.48 | M100: 7617.81 | N100: 19064.14 | O100: 20440.44 | P100: 54207.87 | Q100: 26476.45 | R100: 28410.11 | S100: 15668.88 | T100: 20106.56 | U100: 90662 | V100: 17413 | W100: 20101 | X100: 27264 | Y100: 23078 | Z100: 87856 | AA100: 15388 | AB100: 16171
A101: 1 | C101: 이자지급(CF) | E101: -90503.5 | G101: -63465.11 | H101: -71102.49 | I101: -63050.56 | J101: -82119.43 | K101: -279737.59 | L101: -84161.85 | M101: -88532.25 | Q101: -90670.69 | R101: -92267.66 | S101: -95945.9 | T101: -104145.75 | U101: -383030 | V101: -104168 | W101: -82034 | X101: -98004 | Y101: -88103 | Z101: -372309 | AA101: -81236 | AB101: -88413
A102: 1 | C102: 배당금수취(CF) | E102: 0 | G102: 78 | H102: 3691.69 | I102: 567.53 | J102: 0 | K102: 4337.22 | L102: 2014.59 | M102: 2253.2 | N102: 1791.4 | O102: 64.13 | P102: 6123.32 | Q102: 2089.81 | R102: 1131.69 | S102: 395.76 | T102: 388.74 | U102: 4006 | V102: 850 | W102: 562 | X102: 998 | Y102: 101 | Z102: 2511 | AA102: 1280 | AB102: 217
A103: 1 | C103: 법인세납부(CF) | E103: -33710.82 | G103: -16652.38 | H103: -91112.6 | I103: -84340.59 | J103: -107600.73 | K103: -299706.3 | L103: -43821.27 | M103: -144560.16 | N103: -64151.35 | O103: -96545.42 | P103: -349078.2 | Q103: -18834.99 | R103: -191470.92 | S103: -85138.63 | T103: -21511.46 | U103: -316956 | V103: -53768 | W103: -143996 | X103: 603 | Y103: -16917 | Z103: -214078 | AA103: -33742 | AB103: -101241
A104: 1 | C104: 투자활동으로인한현금흐름 | E104: 157755.36 | G104: 185500.96 | H104: -127940.49 | I104: -46961.04 | J104: -81729.98 | K104: -71130.55 | L104: -249734.64 | M104: -109699.58 | N104: -217970.98 | O104: -239223.27 | P104: -816628.47 | Q104: -154250.07 | R104: -186315.7 | S104: -125953.82 | T104: -354879.41 | U104: -821399 | V104: -150166 | W104: -106593 | X104: -205398 | Y104: 151586 | Z104: -310571 | AA104: -170805 | AB104: -349054
A105: 1 | C105: 유형자산의감소 | E105: 13564.32 | G105: 3311.65 | H105: 22505.98 | J105: 5274.6 | L105: 411.03 | M105: 4545 | N105: 666.09 | O105: 3260.74 | P105: 8882.86 | Q105: 1098.56 | R105: 4367.51 | S105: 1173.65 | T105: 2714.28 | U105: 9354 | V105: 4383 | X105: 1769 | Y105: 3253 | AA105: 1310 | AB105: 1022
A106: 1 | C106: 무형자산의감소 | E106: 80 | J106: 73.38 | N106: 1681.81 | O106: 26.57 | S106: 0 | T106: 1399 | V106: 302 | W106: 1090 | Y106: 55 | AA106: 60 | AB106: 435
A107: 1 | C107: 유형자산의증가 | E107: 111852.59 | G107: 64044.24 | H107: 75168.59 | I107: 82299.78 | J107: 127191.49 | K107: 348704.1 | L107: 84735.36 | M107: 87812.61 | N107: 96794.49 | O107: 126253.6 | P107: 395596.06 | Q107: 87641.41 | R107: 112202.88 | S107: 125837.54 | T107: 135815.17 | U107: 461497 | V107: 89838 | W107: 55944 | X107: 140259 | Y107: 117054 | Z107: 403095 | AA107: 115089 | AB107: 48651
A108: 1 | C108: CAPEX | E108: 183048.87 | G108: 108015.16 | H108: 123777.78 | I108: 128281.83 | J108: 184636.06 | K108: 544710.83 | L108: 125145.94 | M108: 134067.78 | N108: 159386.51 | O108: 184593.07 | P108: 603193.3 | Q108: 128617.21 | R108: 161364.35 | S108: 159774.86 | T108: 203891.58 | U108: 653648 | V108: 131389 | W108: 142734 | X108: 233332 | Y108: 190656 | Z108: 698111 | AA108: 171431 | AB108: 103829
A109: 1 | C109: 무형자산의증가 | E109: 71196.28 | G109: 43970.92 | H109: 48609.19 | I109: 45982.05 | J109: 57444.57 | K109: 196006.73 | L109: 40410.58 | M109: 46255.17 | N109: 62592.02 | O109: 58339.47 | P109: 207597.24 | Q109: 40975.8 | R109: 49161.47 | S109: 33937.32 | T109: 68076.41 | U109: 192151 | V109: 41551 | W109: 86790 | X109: 93073 | Y109: 73602 | Z109: 295016 | AA109: 56342 | AB109: 55178
A110: 1 | C110: 재무활동으로인한현금흐름 | E110: -725298.89 | G110: -261633.54 | H110: -700634.45 | I110: -228278.38 | J110: 58093.74 | K110: -1132452.6 | L110: 165390.92 | M110: 200327.56 | N110: -410177.67 | O110: -8477.29 | P110: -52936.48 | Q110: 38177.47 | R110: 278842.46 | S110: 718708.26 | T110: -427306.19 | U110: 608422 | V110: 420526 | W110: -107658 | X110: 401926 | Y110: -1002739 | Z110: -287945 | AA110: 666065 | AB110: 76716
A111: 1 | C111: 사채의증가 | E111: 14988.7 | G111: 110000 | H111: 80000 | I111: 149740.03 | J111: 27417.07 | K111: 367157.1 | L111: 57000 | M111: 79671.26 | N111: 372527 | O111: 0 | P111: 509198.26 | Q111: 177240.29 | R111: 66844.99 | S111: 229285.71 | T111: 551.01 | U111: 473922 | V111: 55736 | W111: 128006 | X111: 61729 | Y111: 40763 | Z111: 286234 | AA111: 9980 | AB111: 9982
A112: 1 | C112: 장기차입금의증가 | E112: 359225.3 | G112: 500000 | H112: 1409482.2 | I112: 37025.79 | J112: 619867.69 | K112: 2566375.6 | L112: 342331.24 | M112: 147539.3 | N112: 16043.05 | O112: 140152.34 | P112: 646065.93 | Q112: 570000 | R112: 142067.5 | S112: 483477.21 | T112: 142964.29 | U112: 1338509 | V112: 619295 | X112: 70110 | AA112: 160000 | AB112: 0
A113: 1 | C113: 단기차입금의감소 | E113: 287622.79 | G113: 1935769.6 | H113: 241855.52 | I113: 190635.03 | J113: 28.29 | K113: 2368288.5 | L113: 22971.1 | M113: 188658.4 | N113: 17158.17 | O113: 13603.23 | P113: 242390.9 | Q113: 0 | R113: 0 | S113: 0 | T113: 0 | U113: 0
...

Sheet BS별도
B1: (백만원) | C1: 이름: BS별도H | E1: 4Q21 | F1: 2021 | G1: 1Q22 | H1: 2Q22 | I1: 3Q22 | J1: 4Q22 | K1: 2022 | L1: 1Q23 | M1: 2Q23 | N1: 3Q23 | O1: 4Q23 | P1: 2023 | Q1: 1Q24 | R1: 2Q24 | S1: 3Q24 | T1: 4Q24 | U1: 2024 | V1: 1Q25 | W1: 2Q25 | X1: 3Q25 | Y1: 4Q25 | Z1: 2025 | AA1: 1Q26 | AB1: 2Q26 | AC1: 3Q26 | AD1: 4Q26 | AE1: 2026 | AF1: 1Q27 | AG1: 2Q27 | AH1: 3Q27 | AI1: 4Q27 | AJ1: 2027 | AK1: 1Q28 | AL1: 2Q28 | AM1: 3Q28 | AN1: 4Q28 | AO1: 2028
B2: 별도 | D2: fin json(kship_fin.py)
B3: 두산에너빌리티(별) | C3: UPDATE: 26-10-19 | E3: 1 | F3: 2 | G3: 3 | H3: 4 | I3: 5 | J3: 6 | K3: 7 | L3: 8 | M3: 9 | N3: 10 | O3: 11 | P3: 12 | Q3: 13 | R3: 14 | S3: 15 | T3: 16 | U3: 17 | V3: 18 | W3: 19 | X3: 20 | Y3: 21 | Z3: 22 | AA3: 23 | AB3: 24 | AC3: 25 | AD3: 26 | AE3: 27 | AF3: 28 | AG3: 29 | AH3: 30 | AI3: 31 | AJ3: 32 | AK3: 33 | AL3: 34 | AM3: 35 | AN3: 36 | AO3: 37
B4: Account Code | C4: AccountNAME | E4: 2021.12 | F4: 2021.12A | G4: 2022.03 | H4: 2022.06 | I4: 2022.09 | J4: 2022.12 | K4: 2022.12A | L4: 2023.03 | M4: 2023.06 | N4: 2023.09 | O4: 2023.12 | P4: 2023.12A | Q4: 2024.03 | R4: 2024.06 | S4: 2024.09 | T4: 2024.12 | U4: 2024.12A | V4: 2025.03 | W4: 2025.06 | X4: 2025.09 | Y4: 2025.12 | Z4: 2025.12A | AA4: 2026.03 | AB4: 2026.06 | AC4: 2026.09 | AD4: 2026.12 | AE4: 2026.12A | AF4: 2027.03 | AG4: 2027.06 | AH4: 2027.09 | AI4: 2027.12 | AJ4: 2027.12A | AK4: 2028.03 | AL4: 2028.06 | AM4: 2028.09 | AN4: 2028.12 | AO4: 2028.12A
A5: 1 | C5: 유동자산 | E5: 3683979.6 | F5: 3683979.6 | G5: 3731421.5 | H5: 4024955.2 | I5: 4155125.6 | J5: 3537609.7 | K5: 3537609.7 | L5: 3623666.7 | M5: 4377781.4 | N5: 4034350.5 | O5: 4051761.9 | P5: 4051761.9 | Q5: 4186297.7 | R5: 4024291.9 | S5: 3961773.5 | T5: 4048371 | U5: 4048371 | V5: 4306084 | W5: 4154258 | X5: 4582507 | Y5: 4910318 | Z5: 4910318 | AA5: 5146742 | AB5: 5543025
A6: 1 | C6: 현금및현금성자산 | E6: 423695.21 | F6: 423695.21 | G6: 193962.04 | H6: 270131.74 | I6: 458471.13 | J6: 307351.16 | K6: 307351.16 | L6: 251008.89 | M6: 1079473.7 | N6: 472850.36 | O6: 733013.69 | P6: 733013.69 | Q6: 666934.56 | R6: 434503.47 | S6: 260735.4 | T6: 645087 | U6: 645087 | V6: 306065 | W6: 127071 | X6: 184653 | Y6: 760602 | Z6: 760602 | AA6: 543226 | AB6: 319656
A7: 1 | C7: 단기금융상품 | E7: 446816.82 | F7: 446816.82 | G7: 236859.26 | H7: 119564.84 | I7: 124044.9 | J7: 84578.98 | K7: 84578.98 | L7: 55589.3 | M7: 57458.24 | N7: 75108.84 | O7: 72594.87 | P7: 72594.87 | Q7: 73710.74 | R7: 48997.39 | S7: 49558.82 | T7: 49400 | U7: 49400 | V7: 44316 | W7: 46256 | X7: 45954 | Y7: 41745 | Z7: 41745 | AA7: 42782 | AB7: 43006
A8: 1 | C8: 단기금융자산 | E8: 637724.61 | F8: 637724.61 | G8: 635193.27 | H8: 564747.9 | I8: 655686.54 | J8: 516617.55 | K8: 516617.55 | L8: 513929.88 | M8: 273077.84 | N8: 363369 | O8: 204461.71 | P8: 204461.71 | Q8: 282374.36 | R8: 349494.83 | S8: 325140.31 | T8: 248012 | U8: 248012 | V8: 230313 | W8: 147838 | X8: 171246 | Y8: 119634 | Z8: 119634 | AA8: 204269 | AB8: 259233
A9: 1 | C9: 매출채권및기타채권 | E9: 418825.89 | F9: 418825.89 | G9: 615432.65 | H9: 740555.69 | I9: 677392.46 | J9: 757107.42 | K9: 757107.42 | L9: 931859.2 | M9: 1035261.7 | N9: 1184692.5 | O9: 978610.81 | P9: 978610.81 | Q9: 1143138 | R9: 923528.95 | S9: 1127886.3 | T9: 990147 | U9: 990147 | V9: 1072607 | W9: 1216499 | X9: 1383541 | Y9: 1452042 | Z9: 1452042 | AA9: 1507459 | AB9: 1612515
A10: 1 | C10: 계약자산 | E10: 1297216.4 | F10: 1297216.4 | G10: 1347622.8 | H10: 1290134.4 | I10: 1222346.4 | J10: 970226.75 | K10: 970226.75 | L10: 938454.18 | M10: 963461.19 | N10: 1079691.6 | O10: 1259649.8 | P10: 1259649.8 | Q10: 1241807.1 | R10: 1387780.9 | S10: 1355902.4 | T10: 1345091 | U10: 1345091 | V10: 1539245 | W10: 1662052 | X10: 1552255 | Y10: 1524720 | Z10: 1524720 | AA10: 1762128 | AB10: 2221080
A11: 1 | C11: 선급금 | E11: 373337.56 | F11: 373337.56 | G11: 460509.05 | H11: 580780.91 | I11: 532117.26 | J11: 501387.14 | K11: 501387.14 | L11: 476453.35 | M11: 506059.44 | N11: 472044.98 | O11: 429084.44 | P11: 429084.44 | Q11: 381822.07 | R11: 430762.23 | S11: 383172.01 | T11: 328694 | U11: 328694 | V11: 338158 | W11: 335549 | X11: 425905 | Y11: 485334 | Z11: 485334 | AA11: 447490 | AB11: 429122
A12: 1 | C12: 선급금등 | E12: 373337.56 | F12: 373337.56 | G12: 460509.05 | H12: 580780.91 | I12: 532117.26 | J12: 501387.14 | K12: 501387.14 | L12: 476453.35 | M12: 506059.44 | N12: 472044.98 | O12: 429084.44 | P12: 429084.44 | Q12: 381822.07 | R12: 430762.23 | S12: 383172.01 | T12: 328694 | U12: 328694 | V12: 338158 | W12: 335549 | X12: 425905 | Y12: 485334 | Z12: 485334 | AA12: 447490 | AB12: 429122
A13: 1 | C13: 기타유동자산 | E13: 482562.41 | F13: 482562.41 | G13: 565702.37 | H13: 691902.47 | I13: 640899.52 | J13: 596080.05 | K13: 596080.05 | L13: 587745.56 | M13: 624744.31 | N13: 585743.75 | O13: 533538.69 | P13: 533538.69 | Q13: 498249.17 | R13: 548427.23 | S13: 505566.08 | T13: 446076 | U13: 446076 | V13: 480267 | W13: 470065 | X13: 557517 | Y13: 601669 | Z13: 601669 | AA13: 583747 | AB13: 560660
A14: 1 | C14: 단기대여금 | E14: 146163.47 | F14: 146163.47 | G14: 348292.85 | H14: 354657.92 | I14: 369206.91 | J14: 377110.99 | K14: 377110.99 | L14: 393385.1 | M14: 153741.79 | N14: 212733.65 | O14: 94473.05 | P14: 94473.05 | Q14: 140760.97 | R14: 215279.55 | S14: 227057.49 | T14: 84362 | U14: 84362 | V14: 77247 | W14: 64534 | X14: 71564 | Y14: 12032 | Z14: 12032 | AA14: 30792 | AB14: 37673
A15: 1 | C15: 유동확정계약자산 | E15: 44744.32 | F15: 44744.32 | G15: 50041.16 | H15: 90525.14 | I15: 162434.73 | J15: 54927.58 | K15: 54927.58 | L15: 64955.48 | M15: 61877.81 | N15: 75526.51 | O15: 37393.79 | P15: 37393.79 | Q15: 67902.65 | R15: 85217.89 | S15: 48524 | T15: 114250 | U15: 114250 | V15: 108750 | W15: 37048 | X15: 53728 | Y15: 65857 | Z15: 65857 | AA15: 130695 | AB15: 178554
A16: 1 | C16: 재고자산 | E16: 361059.87 | F16: 361059.87 | G16: 336326.98 | H16: 278501.23 | I16: 298286.37 | J16: 326311.36 | K16: 326311.36 | L16: 327472.95 | M16: 325100.34 | N16: 303856.78 | O16: 290947.64 | P16: 290947.64 | Q16: 331144.94 | R16: 364262.25 | S16: 370871.45 | T16: 335840 | U16: 335840 | V16: 660725 | W16: 457186 | X16: 493306 | Y16: 429105 | Z16: 429105 | AA16: 514031 | AB16: 529928
A17: 1 | C17: 매각예정비유동자산및처분자산 | E17: 42569.44 | F17: 42569.44 | G17: 12169.44 | H17: 127245.5 | I17: 11545.16 | J17: 1967.25 | K17: 1967.25 | L17: 23642.86 | M17: 23642.86 | N17: 23642.86 | O17: 33587.41 | P17: 33587.41 | Q17: 8456.05 | R17: 1505.81 | S17: 1505.81 | T17: 1506 | U17: 1506 | V17: 1291 | W17: 0 | X17: 203038 | Y17: 0 | Z17: 0
A18: 1 | C18: 비유동자산 | E18: 10347891 | F18: 10347891 | G18: 10393594 | H18: 10192249 | I18: 10493476 | J18: 9651930.8 | K18: 9651930.8 | L18: 9838058.8 | M18: 9768162.7 | N18: 9766515.8 | O18: 9632747.1 | P18: 9632747.1 | Q18: 9711131.4 | R18: 9770506.5 | S18: 9777250.2 | T18: 9708503 | U18: 9708503 | V18: 9624371 | W18: 9799013 | X18: 9643867 | Y18: 9956057 | Z18: 9956057 | AA18: 9989650 | AB18: 10227684
A19: 1 | C19: 장기금융자산 | E19: 199368.29 | F19: 199368.29 | G19: 205019.86 | H19: 219017.65 | I19: 238082.12 | J19: 209318.25 | K19: 209318.25 | L19: 212123.57 | M19: 201299.88 | N19: 193491.94 | O19: 176082.93 | P19: 176082.93 | Q19: 188575.48 | R19: 227775.77 | S19: 218576.27 | T19: 301918 | U19: 301918 | V19: 321554 | W19: 447841 | X19: 474434 | Y19: 346555 | Z19: 346555 | AA19: 339668 | AB19: 354175
A20: 1 | C20: 투자자산 | E20: 5614808.3 | F20: 5614808.3 | G20: 5650814.1 | H20: 5460625.4 | I20: 5752141.5 | J20: 4788334.2 | K20: 4788334.2 | L20: 4994808.2 | M20: 5001156.9 | N20: 4963556.4 | O20: 4772350.3 | P20: 4772350.3 | Q20: 4843861.4 | R20: 4910078.8 | S20: 4923755.7 | T20: 4708227 | U20: 4708227 | V20: 4617892 | W20: 4791270 | X20: 4614472 | Y20: 4747740 | Z20: 4747740 | AA20: 4755685 | AB20: 4972683
A21: 1 | C21: 종속기업및관계기업투자 | E21: 5349988.2 | F21: 5349988.2 | G21: 5374338.8 | H21: 5126704.3 | I21: 5343994.6 | J21: 4499041.8 | K21: 4499041.8 | L21: 4545014.9 | M21: 4561073 | N21: 4525296.4 | O21: 4302259.4 | P21: 4302259.4 | Q21: 4335337.6 | R21: 4346737.6 | S21: 4347997.6 | T21: 4071935 | U21: 4071935 | V21: 4072795 | W21: 4074435 | X21: 3869105 | Y21: 4216247 | Z21: 4216247 | AA21: 4218027 | AB21: 4221287
A22: 1 | C22: 장기대여금 | E22: 44758.9 | F22: 44758.9 | G22: 46249.15 | H22: 51733.54 | I22: 51678.33 | J22: 39434.96 | K22: 39434.96 | L22: 191785.65 | M22: 196107.76 | N22: 198266.57 | O22: 268159.19 | P22: 268159.19 | Q22: 299397.97 | R22: 308634.46 | S22: 347565.01 | T22: 320837 | U22: 320837 | V22: 212564 | W22: 239943 | X22: 226012 | Y22: 122285 | Z22: 122285 | AA22: 106144 | AB22: 158815
A23: 1 | C23: 유형자산 | E23: 3309494.9 | F23: 3309494.9 | G23: 3287673.2 | H23: 3272493 | I23: 3258987.2 | J23: 3152146.6 | K23: 3152146.6 | L23: 3148703.9 | M23: 3141078.2 | N23: 3131315.6 | O23: 3151464.9 | P23: 3151464.9 | Q23: 3140276.5 | R23: 3135273.9 | S23: 3139029.8 | T23: 3152671 | U23: 3152671 | V23: 3138421 | W23: 3135148 | X23: 3145939 | Y23: 3171422 | Z23: 3171422 | AA23: 3211132 | AB23: 3226375
A24: 1 | C24: 무형자산 | E24: 974589.54 | F24: 974589.54 | G24: 992294.43 | H24: 1013556.3 | I24: 1029539.2 | J24: 1002660.8 | K24: 1002660.8 | L24: 1024189.8 | M24: 1055101.7 | N24: 1086660 | O24: 1113633.7 | P24: 1113633.7 | Q24: 1135970.5 | R24: 1158327.3 | S24: 1169356.7 | T24: 1214831 | U24: 1214831 | V24: 1235632 | W24: 1262229 | X24: 1275193 | Y24: 1287875 | Z24: 1287875 | AA24: 1292723 | AB24: 1302982
A25: 1 | C25: 투자부동산 | E25: 79533.76 | F25: 79533.76 | G25: 79113.72 | H25: 78150.69 | I25: 86455.41 | J25: 159698.02 | K25: 159698.02 | L25: 136652.59 | M25: 135289.01 | N25: 133894.23 | O25: 93373.2 | P25: 93373.2 | Q25: 94091.78 | R25: 92634.99 | S25: 91162.37 | T25: 113710 | U25: 113710 | V25: 112269 | W25: 110812 | X25: 109340 | Y25: 104282 | Z25: 104282 | AA25: 103017 | AB25: 97230
A26: 1 | C26: 비유동확정계약자산 | E26: 20692.91 | F26: 20692.91 | G26: 25206.32 | H26: 63169.94 | I26: 118386.42 | J26: 40539.23 | K26: 40539.23 | L26: 45884.11 | M26: 42676.27 | N26: 46501.51 | O26: 25848.8 | P26: 25848.8 | Q26: 20550.31 | R26: 26930.95 | S26: 9616.76 | T26: 13537 | U26: 13537 | V26: 10979 | W26: 29051 | X26: 44921 | Y26: 62653 | Z26: 62653 | AA26: 91846 | AB26: 238406
A27: 1 | C27: 이연법인세자산 | E27: 180001.25 | F27: 180001.25 | G27: 180001.25 | H27: 180001.25 | I27: 180001.25 | J27: 345731.25 | K27: 345731.25 | L27: 345731.25 | M27: 345731.25 | N27: 345731.25 | O27: 427399.45 | P27: 427399.45 | Q27: 416544.7 | R27: 405715.93 | S27: 385598.09 | T27: 448269 | U27: 448269 | V27: 448269 | W27: 408192 | X27: 424011 | Y27: 547449 | Z27: 547449 | AA27: 533814 | AB27: 514926
A28: 1 | C28: 기타비유동자산 | E28: 78983.6 | F28: 78983.6 | G28: 88828.19 | H28: 39441.36 | I28: 43547.84 | J28: 36690.65 | K28: 36690.65 | L28: 34045.87 | M28: 39404.31 | N28: 43824.72 | O28: 47239.1 | P28: 47239.1 | Q28: 48490.68 | R28: 54105.63 | S28: 53132.36 | T28: 45985 | U28: 45985 | V28: 39617 | W28: 40712 | X28: 41625 | Y28: 40014 | Z28: 40014 | AA28: 46227 | AB28: 63064
A29: 1 | C29: 자산총계 | E29: 14031871 | F29: 14031871 | G29: 14125015 | H29: 14217204 | I29: 14648601 | J29: 13189540 | K29: 13189540 | L29: 13461725 | M29: 14145944 | N29: 13800866 | O29: 13684509 | P29: 13684509 | Q29: 13897429 | R29: 13794798 | S29: 13739024 | T29: 13756874 | U29: 13756874 | V29: 13930455 | W29: 13953271 | X29: 14226374 | Y29: 14866375 | Z29: 14866375 | AA29: 15136392 | AB29: 15770709
... A36: 1 | C36: 유동성장기부채 | E36: 899500.41 | F36: 899500.41 | G36: 672291.56 | H36: 586147.99 | I36: 1055267 | J36: 641666.91 | K36: 641666.91 | L36: 1113477.9 | M36: 1369171.1 | N36: 1104494.6 | O36: 1403847.4 | P36: 1403847.4 | Q36: 703673.73 | R36: 684076.67 | S36: 521799.68 | T36: 222000 | U36: 222000 | V36: 223000 | W36: 158000 | X36: 661660 | Y36: 721470 | Z36: 721470 | AA36: 1239020 | AB36: 1273450
A37: 1 | C37: 유동리스부채 | E37: 26140.81 | F37: 26140.81 | G37: 26949.05 | J37: 29843.9 | K37: 29843.9 | L37: 29268.62 | M37: 27258.28 | O37: 26198.91 | P37: 26198.91 | Q37: 33867.26 | R37: 34046.18
A38: 1 | C38: 리스부채 | E38: 183629.45 | F38: 183629.45 | G38: 180297.89 | H38: 152199.19 | I38: 147410.71 | J38: 172304.34 | K38: 172304.34 | L38: 168751.41 | M38: 162200.93 | N38: 130592.16 | O38: 155411.79 | P38: 155411.79 | Q38: 157127.98 | R38: 153580.31 | S38: 114815.78 | T38: 116086 | U38: 116086 | V38: 110908 | W38: 107323 | X38: 105084 | Y38: 94869 | Z38: 94869 | AA38: 124718 | AB38: 123839
A39: 1 | C39: 단기금융부채 | E39: 35276.16 | F39: 35276.16 | G39: 34101.89 | H39: 7777.93 | I39: 6516.6 | J39: 46379.59 | K39: 46379.59 | L39: 40145.96 | M39: 39794.09 | N39: 6521.49 | O39: 37860.17 | P39: 37860.17 | Q39: 39463.89 | R39: 39876.85 | S39: 6932.58 | T39: 5893 | U39: 5893 | V39: 2796 | W39: 35143 | X39: 14597 | Y39: 17107 | Z39: 17107 | AA39: 2750 | AB39: 2640
A40: 1 | C40: 단기파생상품부채 | E40: 9135.35 | F40: 9135.35 | G40: 7152.84 | H40: 7777.93 | I40: 6516.6 | J40: 16535.69 | K40: 16535.69 | L40: 10877.34 | M40: 12535.81 | N40: 6521.49 | O40: 11661.26 | P40: 11661.26 | Q40: 5596.63 | R40: 5830.67 | S40: 6932.58 | T40: 5893 | U40: 5893 | V40: 2796 | W40: 35143 | X40: 14597 | Y40: 17107 | Z40: 17107 | AA40: 2750 | AB40: 2640
A41: 1 | C41: 단기충당부채 | E41: 196415.92 | F41: 196415.92 | G41: 189121.64 | H41: 175199.44 | I41: 185611.17 | J41: 182202.92 | K41: 182202.92 | L41: 176357.54 | M41: 158405.05 | N41: 147174.01 | O41: 122643.67 | P41: 122643.67 | Q41: 71551.42 | R41: 64678.15 | S41: 55535.43 | T41: 72200 | U41: 72200 | V41: 58553 | W41: 49079 | X41: 50997 | Y41: 151935 | Z41: 151935 | AA41: 63637 | AB41: 68269
A42: 1 | C42: 비유동부채 | E42: 1186291.2 | F42: 1186291.2 | G42: 1683175.7 | H42: 1934363.5 | I42: 1709006.4 | J42: 2016603.6 | K42: 2016603.6 | L42: 1768978.7 | M42: 1560075.6 | N42: 1722730.5 | O42: 1441867.6 | P42: 1441867.6 | Q42: 1913283.6 | R42: 1891793 | S42: 2042534.2 | T42: 2332951 | U42: 2332951 | V42: 2387149 | W42: 2743709 | X42: 2402318 | Y42: 2272402 | Z42: 2272402 | AA42: 1894927 | AB42: 1970710
A43: 1 | C43: 사채 | E43: 422363.43 | F43: 422363.43 | G43: 484881.46 | H43: 574722.91 | I43: 259433.67 | J43: 259132.25 | K43: 259132.25 | L43: 216581.52 | M43: 136799.07 | N43: 438935.51 | O43: 423103.27 | P43: 423103.27 | Q43: 498191.63 | R43: 511361.75 | S43: 640768.93 | T43: 686148 | U43: 686148 | V43: 642843 | W43: 738737 | X43: 269574 | Y43: 270349 | Z43: 270349 | AA43: 214044 | AB43: 168873
A44: 1 | C44: 장기차입금 | E44: 122492.71 | F44: 122492.71 | G44: 567663.36 | H44: 667663.36 | I44: 667663.36 | J44: 1113279.5 | K44: 1113279.5 | L44: 893331.12 | M44: 751806.76 | N44: 592331.94 | O44: 287188.57 | P44: 287188.57 | Q44: 700000 | R44: 639351.45 | S44: 679593.85 | T44: 819840 | U44: 819840 | V44: 950000 | W44: 1145000 | X44: 1271250 | Y44: 1057500 | Z44: 1057500 | AA44: 733750 | AB44: 730000
A45: 1 | C45: 장기매입채무및기타채무 | E45: 13601.34 | F45: 13601.34 | G45: 8184.91 | H45: 8647.52 | I45: 9147.45 | J45: 9509.9 | K45: 9509.9 | L45: 9472.1 | M45: 9809.38 | N45: 9894.42 | O45: 10016.33 | P45: 10016.33 | Q45: 10052.26 | R45: 10052.16 | S45: 10133.04 | T45: 9451 | U45: 9451 | V45: 10169 | W45: 11694 | X45: 12798 | Y45: 20951 | Z45: 20951 | AA45: 22900 | AB45: 24896
A46: 1 | C46: 확정급여부채 | E46: 105513.44 | F46: 105513.44 | G46: 137883.95 | H46: 136960.01 | I46: 143514.13 | J46: 113117.1 | K46: 113117.1 | L46: 121330.02 | M46: 127198.83 | N46: 134108.87 | O46: 192863.55 | P46: 192863.55 | Q46: 204259.37 | R46: 213065.26 | S46: 220903.31 | T46: 298291 | U46: 298291 | V46: 304253 | W46: 314071 | X46: 322670 | Y46: 341458 | Z46: 341458 | AA46: 354804 | AB46: 366938
A47: 1 | C47: 비유동리스부채 | E47: 157488.64 | F47: 157488.64 | G47: 153348.84 | H47: 152199.19 | I47: 147410.71 | J47: 142460.44 | K47: 142460.44 | L47: 139482.79 | M47: 134942.65 | N47: 130592.16 | O47: 129212.88 | P47: 129212.88 | Q47: 123260.72 | R47: 119534.13 | S47: 114815.78 | T47: 116086 | U47: 116086 | V47: 110908 | W47: 107323 | X47: 105084 | Y47: 94869 | Z47: 94869 | AA47: 124718 | AB47: 123839
A48: 1 | C48: 장기금융부채 | E48: 162706.22 | F48: 162706.22 | G48: 158775.76 | H48: 156232.22 | I48: 151733.01 | J48: 148767.6 | K48: 148767.6 | L48: 145753.42 | M48: 146550.13 | N48: 134393.91 | O48: 142660.61 | P48: 142660.61 | Q48: 126906.89 | R48: 123046.1 | S48: 117985.43 | T48: 118543 | U48: 118543 | V48: 115081 | W48: 128157 | X48: 116429 | Y48: 130102 | Z48: 130102 | AA48: 127811 | AB48: 126432
A49: 1 | C49: 장기파생상품부채 | E49: 5217.58 | F49: 5217.58 | G49: 5426.92 | H49: 4033.03 | I49: 4322.3 | J49: 6307.16 | K49: 6307.16 | L49: 6270.63 | M49: 11607.48 | N49: 3801.75 | O49: 13447.73 | P49: 13447.73 | Q49: 3646.17 | R49: 3511.97 | S49: 3169.65 | T49: 2457 | U49: 2457 | V49: 4173 | W49: 20834 | X49: 11345 | Y49: 35233 | Z49: 35233 | AA49: 3093 | AB49: 2593
... A63: 1 | C63: 이자발생자산 | E63: 1260788.1 | F63: 1260788.1 | G63: 1034175.2 | H63: 1053897.3 | I63: 1352239.8 | J63: 1033287 | K63: 1033287 | L63: 977062.34 | M63: 1553851.4 | N63: 1029711.3 | O63: 1113558.3 | P63: 1113558.3 | Q63: 1137884.4 | R63: 1011774.1 | S63: 804451.98 | T63: 1195017 | U63: 1195017 | V63: 857932 | W63: 722750 | X63: 830333 | Y63: 1226791 | Z63: 1226791 | AA63: 1087163 | AB63: 933064
A64: 1 | C64: 장기매출채권및기타채권 | H64: 5000 | I64: 15000 | J64: 48236 | K64: 48236 | L64: 42428.83 | M64: 37428.83 | N64: 37428.83 | O64: 10916 | P64: 10916 | Q64: 10416 | R64: 5416 | S64: 8738.41 | T64: 9542 | U64: 9542 | V64: 9036 | W64: 8926 | X64: 9488 | Y64: 10342 | Z64: 10342 | AA64: 9720 | AB64: 9748
A65: 1 | C65: 당기법인세부채(미지급법인세) | N65: 187.07 | O65: 1090.37 | P65: 1090.37 | Q65: 2828.72 | R65: 1415.19 | S65: 0 | T65: 1039 | U65: 1039 | V65: 1299 | W65: 1559 | X65: 1818 | Y65: 10665 | Z65: 10665 | AA65: 6453 | AB65: 105
A66: 1 | C66: 매출액(수익) | E66: 1053714.2 | G66: 1126263.9 | H66: 1320100.8 | I66: 1233930.6 | J66: 1604144.1 | K66: 5284439.4 | L66: 1390656.1 | M66: 1615492.6 | N66: 1513033.4 | O66: 2132680.3 | P66: 6651862.5 | Q66: 1429821.7 | R66: 1555700.2 | S66: 1349498 | T66: 1985284.2 | U66: 6320304 | V66: 1441969 | W66: 2076059 | X66: 1507134 | Y66: 2091861 | Z66: 7117023 | AA66: 1714038 | AB66: 2046572
A67: 1 | C67: 매출원가 | E67: 979283.05 | G67: 967523.68 | H67: 1192687.6 | I67: 1110082.7 | J67: 1510864.4 | K67: 4781158.3 | L67: 1216255.8 | M67: 1412117.9 | N67: 1362484.1 | O67: 1811758.9 | P67: 5802616.6 | Q67: 1285172.2 | R67: 1345120.4 | S67: 1179224.9 | T67: 1669877.5 | U67: 5479395 | V67: 1287590 | W67: 1807089 | X67: 1308855 | Y67: 1700519 | Z67: 6104053 | AA67: 1492548 | AB67: 1755943
A68: 1 | C68: 매출총이익 | E68: 74431.2 | G68: 158740.18 | H68: 127413.16 | I68: 123847.95 | J68: 93279.78 | K68: 503281.07 | L68: 174400.34 | M68: 203374.7 | N68: 150549.35 | O68: 320921.44 | P68: 849245.83 | Q68: 144649.54 | R68: 210579.77 | S68: 170273.07 | T68: 315406.63 | U68: 840909.01 | V68: 154379 | W68: 268970 | X68: 198279 | Y68: 391342 | Z68: 1012970 | AA68: 221490 | AB68: 290629
A69: 1 | C69: 판관비 | E69: 104029.56 | G69: 103383.48 | H69: 106705.65 | I69: 80431.3 | J69: 127455.24 | K69: 417975.67 | L69: 81435.13 | M69: 99980.89 | N69: 94846.13 | O69: 118125.4 | P69: 394387.55 | Q69: 81881.45 | R69: 93097.54 | S69: 94428.79 | T69: 178074.22 | U69: 447482 | V69: 108341 | W69: 123335 | X69: 118213 | Y69: 167075 | Z69: 516964 | AA69: 134966 | AB69: 177513
A70: 1 | C70: 영업이익 | E70: -29598.36 | G70: 55356.7 | H70: 20707.51 | I70: 43416.64 | J70: -34175.46 | K70: 85305.39 | L70: 92965.22 | M70: 103393.81 | N70: 55703.21 | O70: 202796.04 | P70: 454858.28 | Q70: 62768.08 | R70: 117482.22 | S70: 75844.28 | T70: 137332.41 | U70: 393426.99 | V70: 46038 | W70: 145635 | X70: 80066 | Y70: 224267 | Z70: 496006 | AA70: 86524 | AB70: 113116
A71: 1 | C71: 금융손익 | E71: -50598.66 | G71: -70937.01 | H71: -123038.31 | I71: -62833.09 | J71: 24898.46 | K71: -231909.95 | L71: -34254.83 | M71: -27537.68 | N71: -42130.32 | O71: -33284 | P71: -137206.83 | Q71: -14854.07 | R71: -39342.66 | S71: -25275.08 | T71: -69582.19 | U71: -149054 | V71: -38997 | W71: 22019 | X71: -90824 | Y71: -24834 | Z71: -132636 | AA71: -101583 | AB71: 26922
A72: 1 | C72: 금융수익 | E72: 28515.04 | G72: 108586.21 | H72: 319193.52 | I72: 533885.34 | J72: -388869.17 | K72: 572795.9 | L72: 220348.24 | M72: 139885.25 | N72: 155422.13 | O72: -57330.46 | P72: 458325.16 | Q72: 288620.9 | R72: 206253.4 | S72: -103250.06 | T72: 521591.75 | U72: 913215.99 | V72: 177241 | W72: 342746 | X72: -26611 | Y72: 207502 | Z72: 700878 | AA72: 473603 | AB72: 313250
A73: 1 | C73: 금융비용 | E73: 79113.7 | G73: 179523.22 | H73: 442231.83 | I73: 596718.43 | J73: -413767.63 | K73: 804705.85 | L73: 254603.08 | M73: 167422.93 | N73: 197552.45 | O73: -24046.45 | P73: 595532.01 | Q73: 303474.97 | R73: 245596.05 | S73: -77974.97 | T73: 591173.95 | U73: 1062270 | V73: 216238 | W73: 320727 | X73: 64213 | Y73: 232336 | Z73: 833514 | AA73: 575186 | AB73: 286328
A74: 1 | C74: 기타영업외손익 | E74: -230996.58 | G74: 3037.67 | H74: -131526.99 | I74: -71102.52 | J74: -974294.05 | K74: -1173885.9 | L74: -29832.17 | M74: 15541.98 | N74: -49042.48 | O74: -489016.98 | P74: -552349.65 | Q74: 15684.99 | R74: 45750.24 | S74: -8925.5 | T74: -469968.73 | U74: -417459 | V74: -31009 | W74: 107611 | X74: -39983 | Y74: 17235 | Z74: 53854 | AA74: -13851 | AB74: -59470
A75: 1 | C75: 기타영업외수익 | E75: 11616.93 | G75: 25395.81 | H75: 65777.24 | I75: 23104.76 | J75: 272.85 | K75: 114550.66 | L75: 3427.7 | M75: 39756.35 | N75: 3072.79 | O75: 23982.05 | P75: 70238.89 | Q75: 43238.63 | R75: 56086.19 | S75: 1361.75 | T75: 56128.43 | U75: 156815 | V75: 3984 | W75: 109754 | X75: -9915 | Y75: 447459 | Z75: 551282 | AA75: 4253 | AB75: 19746
A76: 1 | C76: 기타영업외비용 | E76: 242613.51 | G76: 22358.15 | H76: 197304.24 | I76: 94207.28 | J76: 974566.89 | K76: 1288436.6 | L76: 33259.87 | M76: 24214.37 | N76: 52115.28 | O76: 512999.03 | P76: 622588.55 | Q76: 27553.64 | R76: 10335.96 | S76: 10287.24 | T76: 526097.16 | U76: 574274 | V76: 34993 | W76: 2143 | X76: 30068 | Y76: 430224 | Z76: 497428 | AA76: 18104 | AB76: 79216
A77: 1 | C77: 법인세비용차감전계속사업이익 | E77: -311193.61 | G77: -12542.65 | H77: -233857.79 | I77: -90518.97 | J77: -983571.04 | K77: -1320490.4 | L77: 28878.22 | M77: 91398.11 | N77: -35469.59 | O77: -319504.95 | P77: -234698.21 | Q77: 63599 | R77: 123889.81 | S77: 41643.7 | T77: -402218.51 | U77: -173086 | V77: -23968 | W77: 275265 | X77: -50741 | Y77: 216668 | Z77: 417224 | AA77: -28910 | AB77: 80568
A78: 1 | C78: 법인세비용 | E78: -210112.42 | G78: 832.24 | H78: -2796 | I78: -5147.45 | J78: -101535.86 | K78: -108647.07 | L78: -501.1 | M78: 8130.17 | N78: -308.03 | O78: -137839.93 | P78: -130518.89 | Q78: 14327.68 | R78: 12415.31 | S78: 27383.96 | T78: -56907.95 | U78: -2781 | V78: 1243 | W78: 50385 | X78: -18696 | Y78: -123374 | Z78: -90442 | AA78: -3151 | AB78: 19343
A79: 1 | C79: 당기순이익 | E79: -101081.18 | G79: -13374.89 | H79: -231061.79 | I79: -85371.52 | J79: -882035.17 | K79: -1211843.4 | L79: 29379.32 | M79: 83267.95 | N79: -35161.56 | O79: -181665.01 | P79: -104179.3 | Q79: 49271.32 | R79: 111474.5 | S79: 14259.74 | T79: -345310.56 | U79: -170305 | V79: -25211 | W79: 224880 | X79: -32045 | Y79: 340042 | Z79: 507666 | AB79: 61225
A80: 1 | C80: (지배주주지분)당기순이익 | E80: -101081.18 | G80: -13374.89 | H80: -231061.79 | I80: -85371.52 | J80: -882035.17 | K80: -1211843.4 | L80: 29379.32 | M80: 83267.95 | N80: -35161.56 | O80: -181665.01 | P80: -104179.3 | Q80: 49271.32 | R80: 111474.5 | S80: 14259.74 | T80: -345310.56 | U80: -170305 | V80: -25211 | W80: 224880 | X80: -32045 | Y80: 340042 | Z80: 507666 | AB80: 61225
A81: 1 | C81: 계속사업이익 | E81: -101081.18 | G81: -13374.89 | H81: -231061.79 | I81: -85371.52 | J81: -882035.17 | K81: -1211843.4 | L81: 29379.32 | M81: 83267.95 | N81: -35161.56 | O81: -181665.01 | P81: -104179.3 | Q81: 49271.32 | R81: 111474.5 | S81: 14259.74 | T81: -345310.56 | U81: -170305 | V81: -25211 | W81: 224880 | X81: -32045 | Y81: 340042 | Z81: 507666 | AB81: 61225
A82: 1 | C82: 총포괄손익 | E82: 44866.64 | G82: -9887.28 | H82: -213665.78 | I82: -43859.17 | J82: -901178.04 | K82: -1168590.3 | L82: 45963.73 | M82: 65238.58 | N82: -27058.26 | O82: -297567.61 | P82: -213423.56 | Q82: 59557.27 | R82: 119780.5 | S82: 5762.92 | T82: -373516.69 | U82: -188416 | V82: -10140 | W82: 179975 | X82: -6617 | Y82: 300784 | Z82: 464002 | AA82: 33251 | AB82: 75039
A83: 1 | C83: 영업활동으로인한현금흐름 | E83: 563731.61 | G83: -138219.47 | H83: 208242.93 | I83: 246845.32 | J83: -45125.18 | K83: 271743.6 | L83: 6966.18 | M83: 714295.2 | N83: -315316.79 | O83: 460033.4 | P83: 865977.99 | Q83: 32708.38 | R83: -257345.17 | S83: -593915.13 | T83: 704831.92 | U83: -113720 | V83: -759580 | W83: -187923 | X83: -215790 | Y83: 1011602 | Z83: -151691 | AA83: -628342 | AB83: -199377
A84: 1 | C84: 이자수취(CF) | E84: 1499.19 | G84: 1144.67 | H84: 1350.09 | I84: 1395.22 | J84: 2986.31 | K84: 6876.29 | L84: 1550.14 | M84: 1104.94 | N84: 1637.79 | O84: 4301.58 | P84: 8594.45 | Q84: 2092.76 | R84: 3451.28 | S84: 2685.54 | T84: 4780.42 | U84: 13010 | V84: 1957 | W84: 1893 | X84: 7593 | Y84: 3766 | Z84: 15209 | AA84: 1572 | AB84: 1305
A85: 1 | C85: 이자지급(CF) | E85: -45625.06 | G85: -36246.65 | H85: -31137.49 | I85: -34607.93 | J85: -42792.76 | K85: -144784.83 | L85: -47698.86 | M85: -48543.35 | Q85: -50325.21 | R85: -48947.27 | S85: -50779.61 | T85: -51573.91 | U85: -201626 | V85: -50817 | W85: -50136 | X85: -52600 | Y85: -50572 | Z85: -204125 | AA85: -46483 | AB85: -53445
A86: 1 | C86: 배당금수취(CF) | E86: 0 | G86: 78 | H86: 83459.35 | I86: 30825.75 | J86: 0 | K86: 114363.1 | L86: 831.5 | M86: 105866.56 | N86: 38665.27 | O86: 64782 | P86: 210145.33 | Q86: 2497.81 | R86: 107256.32 | S86: 37329.37 | T86: 4520.5 | U86: 151604 | V86: 1503 | W86: 95585 | X86: 21365 | Y86: 18470 | Z86: 136923 | AA86: 909 | AB86: 41647
A87: 1 | C87: 법인세납부(CF) | E87: -2509.04 | G87: -2142.94 | H87: -2451.04 | I87: -8528.55 | J87: -29299.67 | K87: -42422.2 | L87: -1905.68 | M87: -1525.36 | N87: -1076.08 | O87: -157.4 | P87: -4664.52 | Q87: -8114.96 | R87: -5534.51 | S87: -5196.18 | T87: 7512.65 | U87: -11333 | V87: -3965 | W87: -5332 | X87: 5238 | Y87: -3823 | Z87: -7882 | AA87: -6921 | AB87: -9743
A88: 1 | C88: 투자활동으로인한현금흐름 | E88: -72016.14 | G88: -6582.96 | H88: -254191.29 | I88: -132056.24 | J88: -37780.04 | K88: -430610.53 | L88: -174297.76 | M88: 228585.53 | N88: -120561.78 | O88: -165306.73 | P88: -231580.74 | Q88: -133299.25 | R88: -98484.61 | S88: -64969.63 | T88: -94484.51 | U88: -391238 | V88: 16664 | W88: -52716 | X88: -92071 | Y88: 319757 | Z88: 191634 | AA88: -169872 | AB88: -172687
A89: 1 | C89: 유형자산의감소 | E89: 166.7 | G89: 116 | H89: 1558.73 | I89: 468.88 | J89: 1736.65 | K89: 3880.26 | L89: 351.6 | M89: 2771.77 | N89: 2.25 | O89: 832.31 | P89: 3957.93 | Q89: 255.95 | R89: 1783.82 | S89: 1174.11 | T89: 619.12 | U89: 3833 | V89: 175 | X89: 129 | Y89: 3291 | AA89: 0 | AB89: 829
A90: 1 | C90: 유형자산의증가 | E90: 24839.8 | G90: 5571.08 | H90: 4805.9 | I90: 18017.55 | J90: 26260.14 | K90: 54654.67 | L90: 13913.83 | M90: 19531.67 | N90: 23111.46 | O90: 36684.98 | P90: 93241.94 | Q90: 10093.49 | R90: 17932.67 | S90: 24348.47 | T90: 50064.37 | U90: 102439 | V90: 11582 | X90: 63804 | Y90: 36200 | AA90: 40424 | AB90: 27837
A91: 1 | C91: CAPEX | E91: 71139.76 | G91: 32660.85 | H91: 35792.28 | I91: 42672.85 | J91: 61879.3 | K91: 173005.28 | L91: 38017.46 | M91: 48934.85 | N91: 44518.35 | O91: 59694.03 | P91: 191164.69 | Q91: 26900.45 | R91: 42850.24 | S91: 35604.83 | T91: 82230.48 | U91: 187586 | V91: 29320 | W91: 19705 | X91: 95344 | Y91: 74127 | Z91: 218496 | AA91: 74431 | AB91: 56149
A92: 1 | C92: 무형자산의증가 | E92: 46299.96 | G92: 27089.77 | H92: 30986.38 | I92: 24655.3 | J92: 35619.16 | K92: 118350.61 | L92: 24103.63 | M92: 29403.18 | N92: 21406.89 | O92: 23009.05 | P92: 97922.75 | Q92: 16806.96 | R92: 24917.57 | S92: 11256.36 | T92: 32166.11 | U92: 85147 | V92: 17738 | W92: 21632 | X92: 31540 | Y92: 37927 | Z92: 108837 | AA92: 34007 | AB92: 28312
A93: 1 | C93: 재무활동으로인한현금흐름 | E93: -543842.97 | G93: -86988.82 | H93: 110714.37 | I93: 29958.26 | J93: -21307.26 | K93: 32376.55 | L93: 102849.3 | M93: -115741.63 | N93: -167272.88 | O93: -32098.89 | P93: -212264.1 | Q93: 22076.8 | R93: 117235.14 | S93: 499915.35 | T93: -294678.29 | U93: 344549 | V93: 404393 | W93: 67641 | X93: 367389 | Y93: -753929 | Z93: 85494 | AA93: 568932 | AB93: 148260
A94: 1 | C94: 장기차입금의증가 | E94: 300000 | G94: 500000 | H94: 100000 | I94: 0 | J94: 544345 | K94: 1144345 | N94: 0 | O94: 100000 | Q94: 570000 | R94: 19100 | S94: 240000 | T94: 310000 | U94: 1139100 | V94: 630000 | X94: 70000 | Y94: 0 | AA94: 160000 | AB94: 0
A95: 1 | C95: 사채의증가 | E95: 15000 | G95: 110000 | H95: 80000 | I95: 80000 | J95: 0 | K95: 270000 | L95: 57000 | M95: 0 | N95: 372527 | O95: 0 | P95: 429527 | Q95: 99562.14 | R95: 0 | S95: 149413.97 | T95: -0.11 | U95: 248976 | V95: 0 | W95: 128000 | X95: 0 | Y95: 0 | Z95: 128000
A96: 1 | C96: 단기차입금의감소 | E96: 497300.64 | G96: 1778859.4 | H96: 56808.15 | I96: 60038.08 | J96: 128642.7 | K96: 2024348.3 | L96: 97678.39 | M96: 136944.13 | N96: 22923.67 | O96: 24731.88 | P96: 282278.07 | Q96: 0 | R96: 0 | S96: 0 | T96: 0 | U96: 0
A97: 1 | C97: 유동성장기부채의감소 | E97: 378575.51 | G97: 333821.39 | H97: 114731.44 | I97: 5.36 | J97: 419684.47 | K97: 868242.66 | L97: 113550.5 | M97: 15000 | N97: 429877.14 | O97: 100000 | P97: 658427.64 | Q97: 743000 | R97: 100000 | S97: 162663.36 | T97: 399999.64 | U97: 1405663 | V97: 42000 | W97: 80000 | Y97: 3750 | AA97: 46750 | AB97: 23750
A98: 1 | C98: 리스부채의상환 | E98: 6468.53 | G98: 5002.73 | H98: 4909.18 | I98: 4942.22 | J98: 4925.08 | K98: 19779.21 | L98: 6779.82 | M98: 6737.72 | N98: 6484.78 | O98: 7367 | P98: 27369.32 | Q98: 6158.72 | R98: 6116.74 | S98: 6265 | T98: 14128.54 | U98: 32669 | V98: 8362 | W98: 8588 | X98: 9415 | Y98: 11053 | Z98: 37418 | AA98: 7973 | AB98: 8416
A99: 1 | C99: 자기주식의취득 | E99: 0
A100: 1 | C100: 현금및현금성자산의증감 | E100: -46832.73 | G100: -229733.17 | H100: 76169.71 | I100: 188339.38 | J100: -151119.97 | K100: -116344.05 | L100: -56342.26 | M100: 828464.78 | N100: -606623.31 | O100: 260163.32 | P100: 425662.53 | Q100: -66079.13 | R100: -232431.09 | S100: -173768.07 | T100: 384351.29 | U100: -87927 | V100: -339022 | W100: -178994 | X100: 57582 | Y100: 575949 | Z100: 115515 | AA100: -217376 | AB100: -223570
A101: 1 | C101: 기말현금및현금성자산 | E101: -46832.73 | G101: 193962.04 | H101: 76169.7 | I101: 188339.39 | J101: -151119.97 | K101: 307351.16 | L101: 251008.89 | M101: 828464.78 | N101: -606623.31 | O101: 260163.33 | P101: 733013.69 | Q101: 666934.56 | R101: -232431.09 | S101: -173768.07 | T101: 384351.6 | U101: 645087 | V101: 306065 | W101: -178994 | X101: 57582 | Y101: 575949 | Z101: 760602 | AA101: 543226 | AB101: -223570
A102: 1 | C102: 무형자산의감소 | J102: 0 | N102: 1681.81 | O102: 0 | S102: 0 | T102: 0 | X102: 100 | Y102: 0
A103: 1 | C103: 장기차입금의감소 | L103: 263858 | N103: 80514.29 | O103: 0 | Q103: 164032 | R103: 0 | S103: 200000 | T103: 70000 | U103: 434032 | V103: 500000 | X103: 0 | Y103: 160000 | AA103: 0 | AB103: 0
A104: 1 | C104: 단기차입금의증가 | Q104: 265705.38 | R104: 204251.89 | S104: 479429.74 | V104: 324755 | X104: 230554 | AA104: 463655 | AB104: 310834

Sheet subQ
A1: YQ | C1: subQ 분기 서브모델(억원, U=100) | E1: 4Q21 | F1: 2021 | G1: 1Q22 | H1: 2Q22 | I1: 3Q22 | J1: 4Q22 | K1: 2022 | L1: 1Q23 | M1: 2Q23 | N1: 3Q23 | O1: 4Q23 | P1: 2023 | Q1: 1Q24 | R1: 2Q24 | S1: 3Q24 | T1: 4Q24 | U1: 2024 | V1: 1Q25 | W1: 2Q25 | X1: 3Q25 | Y1: 4Q25 | Z1: 2025 | AA1: 1Q26 | AB1: 2Q26 | AC1: 3Q26 | AD1: 4Q26 | AE1: 2026 | AF1: 1Q27 | AG1: 2Q27 | AH1: 3Q27 | AI1: 4Q27 | AJ1: 2027 | AK1: 1Q28 | AL1: 2Q28 | AM1: 3Q28 | AN1: 4Q28 | AO1: 2028
A2: A=이름(key) B=그룹 C=단위 D=FnGuide 계정명(VLOOKUP 키). 확정=VLOOKUP(BS), 추정=변수 가정 참조
E3: 1 | F3: 2 | G3: 3 | H3: 4 | I3: 5 | J3: 6 | K3: 7 | L3: 8 | M3: 9 | N3: 10 | O3: 11 | P3: 12 | Q3: 13 | R3: 14 | S3: 15 | T3: 16 | U3: 17 | V3: 18 | W3: 19 | X3: 20 | Y3: 21 | Z3: 22 | AA3: 23 | AB3: 24 | AC3: 25 | AD3: 26 | AE3: 27 | AF3: 28 | AG3: 29 | AH3: 30 | AI3: 31 | AJ3: 32 | AK3: 33 | AL3: 34 | AM3: 35 | AN3: 36 | AO3: 37
E4: 2021.12 | F4: 2021.12A | G4: 2022.03 | H4: 2022.06 | I4: 2022.09 | J4: 2022.12 | K4: 2022.12A | L4: 2023.03 | M4: 2023.06 | N4: 2023.09 | O4: 2023.12 | P4: 2023.12A | Q4: 2024.03 | R4: 2024.06 | S4: 2024.09 | T4: 2024.12 | U4: 2024.12A | V4: 2025.03 | W4: 2025.06 | X4: 2025.09 | Y4: 2025.12 | Z4: 2025.12A | AA4: 2026.03 | AB4: 2026.06 | AC4: 2026.09 | AD4: 2026.12 | AE4: 2026.12A | AF4: 2027.03 | AG4: 2027.06 | AH4: 2027.09 | AI4: 2027.12 | AJ4: 2027.12A | AK4: 2028.03 | AL4: 2028.06 | AM4: 2028.09 | AN4: 2028.12 | AO4: 2028.12A
A5: 매출액 | B5: 손익 | C5: 억원 | D5: 매출액(수익) | E5: =IFERROR(VLOOKUP($D5,BS연결,MATCH(E$1,BS연결H,0),0)/100,"") | G5: =IFERROR(VLOOKUP($D5,BS연결,MATCH(G$1,BS연결H,0),0)/100,"") | H5: =IFERROR(VLOOKUP($D5,BS연결,MATCH(H$1,BS연결H,0),0)/100,"") | I5: =IFERROR(VLOOKUP($D5,BS연결,MATCH(I$1,BS연결H,0),0)/100,"") | J5: =IFERROR(VLOOKUP($D5,BS연결,MATCH(J$1,BS연결H,0),0)/100,"") | K5: =IFERROR(VLOOKUP($D5,BS연결,MATCH(K$1,BS연결H,0),0)/100,"") | L5: =IFERROR(VLOOKUP($D5,BS연결,MATCH(L$1,BS연결H,0),0)/100,"") | M5: =IFERROR(VLOOKUP($D5,BS연결,MATCH(M$1,BS연결H,0),0)/100,"") | N5: =IFERROR(VLOOKUP($D5,BS연결,MATCH(N$1,BS연결H,0),0)/100,"") | ... AB5: =IFERROR(VLOOKUP($D5,BS연결,MATCH(AB$1,BS연결H,0),0)/100,"") | AC5: =IFERROR(X5*(1+변수!AC21),"") | AD5: =IFERROR(Y5*(1+변수!AD21),"") | AE5: =SUM(AA5:AD5) | AF5: =IFERROR(AA5*(1+변수!AF21),"") | AG5: =IFERROR(AB5*(1+변수!AG21),"") | AH5: =IFERROR(AC5*(1+변수!AH21),"") | AI5: =IFERROR(AD5*(1+변수!AI21),"") | AJ5: =SUM(AF5:AI5) | AK5: =IFERROR(AF5*(1+변수!AK21),"") | AL5: =IFERROR(AG5*(1+변수!AL21),"") | AM5: =IFERROR(AH5*(1+변수!AM21),"") | AN5: =IFERROR(AI5*(1+변수!AN21),"") | AO5: =SUM(AK5:AN5)
A6: 매출원가 | B6: 손익 | C6: 억원 | D6: 매출원가 | E6: =IFERROR(VLOOKUP($D6,BS연결,MATCH(E$1,BS연결H,0),0)/100,"") | G6: =IFERROR(VLOOKUP($D6,BS연결,MATCH(G$1,BS연결H,0),0)/100,"") | H6: =IFERROR(VLOOKUP($D6,BS연결,MATCH(H$1,BS연결H,0),0)/100,"") | I6: =IFERROR(VLOOKUP($D6,BS연결,MATCH(I$1,BS연결H,0),0)/100,"") | J6: =IFERROR(VLOOKUP($D6,BS연결,MATCH(J$1,BS연결H,0),0)/100,"") | K6: =IFERROR(VLOOKUP($D6,BS연결,MATCH(K$1,BS연결H,0),0)/100,"") | L6: =IFERROR(VLOOKUP($D6,BS연결,MATCH(L$1,BS연결H,0),0)/100,"") | M6: =IFERROR(VLOOKUP($D6,BS연결,MATCH(M$1,BS연결H,0),0)/100,"") | N6: =IFERROR(VLOOKUP($D6,BS연결,MATCH(N$1,BS연결H,0),0)/100,"") | ... AB6: =IFERROR(VLOOKUP($D6,BS연결,MATCH(AB$1,BS연결H,0),0)/100,"") | AC6: =IFERROR(AC5-AC7,"") | AD6: =IFERROR(AD5-AD7,"") | AE6: =SUM(AA6:AD6) | AF6: =IFERROR(AF5-AF7,"") | AG6: =IFERROR(AG5-AG7,"") | AH6: =IFERROR(AH5-AH7,"") | AI6: =IFERROR(AI5-AI7,"") | AJ6: =SUM(AF6:AI6) | AK6: =IFERROR(AK5-AK7,"") | AL6: =IFERROR(AL5-AL7,"") | AM6: =IFERROR(AM5-AM7,"") | AN6: =IFERROR(AN5-AN7,"") | AO6: =SUM(AK6:AN6)
A7: 매출총이익 | B7: 손익 | C7: 억원 | D7: 매출총이익 | E7: =IFERROR(VLOOKUP($D7,BS연결,MATCH(E$1,BS연결H,0),0)/100,"") | G7: =IFERROR(VLOOKUP($D7,BS연결,MATCH(G$1,BS연결H,0),0)/100,"") | H7: =IFERROR(VLOOKUP($D7,BS연결,MATCH(H$1,BS연결H,0),0)/100,"") | I7: =IFERROR(VLOOKUP($D7,BS연결,MATCH(I$1,BS연결H,0),0)/100,"") | J7: =IFERROR(VLOOKUP($D7,BS연결,MATCH(J$1,BS연결H,0),0)/100,"") | K7: =IFERROR(VLOOKUP($D7,BS연결,MATCH(K$1,BS연결H,0),0)/100,"") | L7: =IFERROR(VLOOKUP($D7,BS연결,MATCH(L$1,BS연결H,0),0)/100,"") | M7: =IFERROR(VLOOKUP($D7,BS연결,MATCH(M$1,BS연결H,0),0)/100,"") | N7: =IFERROR(VLOOKUP($D7,BS연결,MATCH(N$1,BS연결H,0),0)/100,"") | ... AB7: =IFERROR(VLOOKUP($D7,BS연결,MATCH(AB$1,BS연결H,0),0)/100,"") | AC7: =IFERROR(AC9+AC8,"") | AD7: =IFERROR(AD9+AD8,"") | AE7: =SUM(AA7:AD7) | AF7: =IFERROR(AF9+AF8,"") | AG7: =IFERROR(AG9+AG8,"") | AH7: =IFERROR(AH9+AH8,"") | AI7: =IFERROR(AI9+AI8,"") | AJ7: =SUM(AF7:AI7) | AK7: =IFERROR(AK9+AK8,"") | AL7: =IFERROR(AL9+AL8,"") | AM7: =IFERROR(AM9+AM8,"") | AN7: =IFERROR(AN9+AN8,"") | AO7: =SUM(AK7:AN7)
A8: 판관비 | B8: 손익 | C8: 억원 | D8: 판관비 | E8: =IFERROR(VLOOKUP($D8,BS연결,MATCH(E$1,BS연결H,0),0)/100,"") | G8: =IFERROR(VLOOKUP($D8,BS연결,MATCH(G$1,BS연결H,0),0)/100,"") | H8: =IFERROR(VLOOKUP($D8,BS연결,MATCH(H$1,BS연결H,0),0)/100,"") | I8: =IFERROR(VLOOKUP($D8,BS연결,MATCH(I$1,BS연결H,0),0)/100,"") | J8: =IFERROR(VLOOKUP($D8,BS연결,MATCH(J$1,BS연결H,0),0)/100,"") | K8: =IFERROR(VLOOKUP($D8,BS연결,MATCH(K$1,BS연결H,0),0)/100,"") | L8: =IFERROR(VLOOKUP($D8,BS연결,MATCH(L$1,BS연결H,0),0)/100,"") | M8: =IFERROR(VLOOKUP($D8,BS연결,MATCH(M$1,BS연결H,0),0)/100,"") | N8: =IFERROR(VLOOKUP($D8,BS연결,MATCH(N$1,BS연결H,0),0)/100,"") | ... AB8: =IFERROR(VLOOKUP($D8,BS연결,MATCH(AB$1,BS연결H,0),0)/100,"") | AC8: =IFERROR(AC5*변수!AC22,"") | AD8: =IFERROR(AD5*변수!AD22,"") | AE8: =SUM(AA8:AD8) | AF8: =IFERROR(AF5*변수!AF22,"") | AG8: =IFERROR(AG5*변수!AG22,"") | AH8: =IFERROR(AH5*변수!AH22,"") | AI8: =IFERROR(AI5*변수!AI22,"") | AJ8: =SUM(AF8:AI8) | AK8: =IFERROR(AK5*변수!AK22,"") | AL8: =IFERROR(AL5*변수!AL22,"") | AM8: =IFERROR(AM5*변수!AM22,"") | AN8: =IFERROR(AN5*변수!AN22,"") | AO8: =SUM(AK8:AN8)
A9: 영업이익 | B9: 손익 | C9: 억원 | D9: 영업이익 | E9: =IFERROR(VLOOKUP($D9,BS연결,MATCH(E$1,BS연결H,0),0)/100,"") | G9: =IFERROR(VLOOKUP($D9,BS연결,MATCH(G$1,BS연결H,0),0)/100,"") | H9: =IFERROR(VLOOKUP($D9,BS연결,MATCH(H$1,BS연결H,0),0)/100,"") | I9: =IFERROR(VLOOKUP($D9,BS연결,MATCH(I$1,BS연결H,0),0)/100,"") | J9: =IFERROR(VLOOKUP($D9,BS연결,MATCH(J$1,BS연결H,0),0)/100,"") | K9: =IFERROR(VLOOKUP($D9,BS연결,MATCH(K$1,BS연결H,0),0)/100,"") | L9: =IFERROR(VLOOKUP($D9,BS연결,MATCH(L$1,BS연결H,0),0)/100,"") | M9: =IFERROR(VLOOKUP($D9,BS연결,MATCH(M$1,BS연결H,0),0)/100,"") | N9: =IFERROR(VLOOKUP($D9,BS연결,MATCH(N$1,BS연결H,0),0)/100,"") | ... AB9: =IFERROR(VLOOKUP($D9,BS연결,MATCH(AB$1,BS연결H,0),0)/100,"") | AC9: =IFERROR(AC5*변수!AC23,"") | AD9: =IFERROR(AD5*변수!AD23,"") | AE9: =SUM(AA9:AD9) | AF9: =IFERROR(AF5*변수!AF23,"") | AG9: =IFERROR(AG5*변수!AG23,"") | AH9: =IFERROR(AH5*변수!AH23,"") | AI9: =IFERROR(AI5*변수!AI23,"") | AJ9: =SUM(AF9:AI9) | AK9: =IFERROR(AK5*변수!AK23,"") | AL9: =IFERROR(AL5*변수!AL23,"") | AM9: =IFERROR(AM5*변수!AM23,"") | AN9: =IFERROR(AN5*변수!AN23,"") | AO9: =SUM(AK9:AN9)
A10: OPM | B10: 손익 | C10: % | D10: 영업이익률 | E10: =IFERROR(E9/E5,"") | G10: =IFERROR(G9/G5,"") | H10: =IFERROR(H9/H5,"") | I10: =IFERROR(I9/I5,"") | J10: =IFERROR(J9/J5,"") | K10: =IFERROR(K9/K5,"") | L10: =IFERROR(L9/L5,"") | M10: =IFERROR(M9/M5,"") | N10: =IFERROR(N9/N5,"") | ... AO10: =IFERROR(AO9/AO5,"")
A11: 금융손익 | B11: 손익 | C11: 억원 | D11: 금융손익 | E11: =IFERROR(VLOOKUP($D11,BS연결,MATCH(E$1,BS연결H,0),0)/100,"") | G11: =IFERROR(VLOOKUP($D11,BS연결,MATCH(G$1,BS연결H,0),0)/100,"") | H11: =IFERROR(VLOOKUP($D11,BS연결,MATCH(H$1,BS연결H,0),0)/100,"") | I11: =IFERROR(VLOOKUP($D11,BS연결,MATCH(I$1,BS연결H,0),0)/100,"") | J11: =IFERROR(VLOOKUP($D11,BS연결,MATCH(J$1,BS연결H,0),0)/100,"") | K11: =IFERROR(VLOOKUP($D11,BS연결,MATCH(K$1,BS연결H,0),0)/100,"") | L11: =IFERROR(VLOOKUP($D11,BS연결,MATCH(L$1,BS연결H,0),0)/100,"") | M11: =IFERROR(VLOOKUP($D11,BS연결,MATCH(M$1,BS연결H,0),0)/100,"") | N11: =IFERROR(VLOOKUP($D11,BS연결,MATCH(N$1,BS연결H,0),0)/100,"") | ... AB11: =IFERROR(VLOOKUP($D11,BS연결,MATCH(AB$1,BS연결H,0),0)/100,"") | AC11: =IFERROR(AC12+AC13+AC14+AC15,"") | AD11: =IFERROR(AD12+AD13+AD14+AD15,"") | AE11: =SUM(AA11:AD11) | AF11: =IFERROR(AF12+AF13+AF14+AF15,"") | AG11: =IFERROR(AG12+AG13+AG14+AG15,"") | AH11: =IFERROR(AH12+AH13+AH14+AH15,"") | AI11: =IFERROR(AI12+AI13+AI14+AI15,"") | AJ11: =SUM(AF11:AI11) | AK11: =IFERROR(AK12+AK13+AK14+AK15,"") | AL11: =IFERROR(AL12+AL13+AL14+AL15,"") | AM11: =IFERROR(AM12+AM13+AM14+AM15,"") | AN11: =IFERROR(AN12+AN13+AN14+AN15,"") | AO11: =SUM(AK11:AN11)
A12: 이자손익 | B12: 손익 | C12: 억원 | D12: 이자손익 | G12: =IFERROR(VLOOKUP($D12,BS연결,MATCH(G$1,BS연결H,0),0)/100,"") | H12: =IFERROR(VLOOKUP($D12,BS연결,MATCH(H$1,BS연결H,0),0)/100,"") | I12: =IFERROR(VLOOKUP($D12,BS연결,MATCH(I$1,BS연결H,0),0)/100,"") | J12: =IFERROR(VLOOKUP($D12,BS연결,MATCH(J$1,BS연결H,0),0)/100,"") | K12: =IFERROR(VLOOKUP($D12,BS연결,MATCH(K$1,BS연결H,0),0)/100,"") | L12: =IFERROR(VLOOKUP($D12,BS연결,MATCH(L$1,BS연결H,0),0)/100,"") | M12: =IFERROR(VLOOKUP($D12,BS연결,MATCH(M$1,BS연결H,0),0)/100,"") | N12: =IFERROR(VLOOKUP($D12,BS연결,MATCH(N$1,BS연결H,0),0)/100,"") | ... AB12: =IFERROR(VLOOKUP($D12,BS연결,MATCH(AB$1,BS연결H,0),0)/100,"") | AC12: =IFERROR((AB29*변수!$D$55-AB27*변수!$D$56)/4,"") | AD12: =IFERROR((AC29*변수!$D$55-AC27*변수!$D$56)/4,"") | AE12: =SUM(AA12:AD12) | AF12: =IFERROR((AD29*변수!$D$55-AD27*변수!$D$56)/4,"") | AG12: =IFERROR((AF29*변수!$D$55-AF27*변수!$D$56)/4,"") | AH12: =IFERROR((AG29*변수!$D$55-AG27*변수!$D$56)/4,"") | AI12: =IFERROR((AH29*변수!$D$55-AH27*변수!$D$56)/4,"") | AJ12: =SUM(AF12:AI12) | AK12: =IFERROR((AI29*변수!$D$55-AI27*변수!$D$56)/4,"") | AL12: =IFERROR((AK29*변수!$D$55-AK27*변수!$D$56)/4,"") | AM12: =IFERROR((AL29*변수!$D$55-AL27*변수!$D$56)/4,"") | AN12: =IFERROR((AM29*변수!$D$55-AM27*변수!$D$56)/4,"") | AO12: =SUM(AK12:AN12)
A13: 외환손익 | B13: 손익 | C13: 억원 | D13: 외환손익(실적만; 추정 환효과는 환관련손익) | G13: =IFERROR((VLOOKUP("외환차익",BS연결,MATCH(G$1,BS연결H,0),0)-VLOOKUP("외환차손",BS연결,MATCH(G$1,BS연결H,0),0)+VLOOKUP("외화환산이익",BS연결,MATCH(G$1,BS연결H,0),0)-VLOOKUP("외화환산손실",BS연결,MATCH(G$1,BS연결H,0),0))/100,"") | H13: =IFERROR((VLOOKUP("외환차익",BS연결,MATCH(H$1,BS연결H,0),0)-VLOOKUP("외환차손",BS연결,MATCH(H$1,BS연결H,0),0)+VLOOKUP("외화환산이익",BS연결,MATCH(H$1,BS연결H,0),0)-VLOOKUP("외화환산손실",BS연결,MATCH(H$1,BS연결H,0),0))/100,"") | I13: =IFERROR((VLOOKUP("외환차익",BS연결,MATCH(I$1,BS연결H,0),0)-VLOOKUP("외환차손",BS연결,MATCH(I$1,BS연결H,0),0)+VLOOKUP("외화환산이익",BS연결,MATCH(I$1,BS연결H,0),0)-VLOOKUP("외화환산손실",BS연결,MATCH(I$1,BS연결H,0),0))/100,"") | J13: =IFERROR((VLOOKUP("외환차익",BS연결,MATCH(J$1,BS연결H,0),0)-VLOOKUP("외환차손",BS연결,MATCH(J$1,BS연결H,0),0)+VLOOKUP("외화환산이익",BS연결,MATCH(J$1,BS연결H,0),0)-VLOOKUP("외화환산손실",BS연결,MATCH(J$1,BS연결H,0),0))/100,"") | K13: =SUM(G13:J13) | L13: =IFERROR((VLOOKUP("외환차익",BS연결,MATCH(L$1,BS연결H,0),0)-VLOOKUP("외환차손",BS연결,MATCH(L$1,BS연결H,0),0)+VLOOKUP("외화환산이익",BS연결,MATCH(L$1,BS연결H,0),0)-VLOOKUP("외화환산손실",BS연결,MATCH(L$1,BS연결H,0),0))/100,"") | M13: =IFERROR((VLOOKUP("외환차익",BS연결,MATCH(M$1,BS연결H,0),0)-VLOOKUP("외환차손",BS연결,MATCH(M$1,BS연결H,0),0)+VLOOKUP("외화환산이익",BS연결,MATCH(M$1,BS연결H,0),0)-VLOOKUP("외화환산손실",BS연결,MATCH(M$1,BS연결H,0),0))/100,"") | N13: =IFERROR((VLOOKUP("외환차익",BS연결,MATCH(N$1,BS연결H,0),0)-VLOOKUP("외환차손",BS연결,MATCH(N$1,BS연결H,0),0)+VLOOKUP("외화환산이익",BS연결,MATCH(N$1,BS연결H,0),0)-VLOOKUP("외화환산손실",BS연결,MATCH(N$1,BS연결H,0),0))/100,"") | O13: =IFERROR((VLOOKUP("외환차익",BS연결,MATCH(O$1,BS연결H,0),0)-VLOOKUP("외환차손",BS연결,MATCH(O$1,BS연결H,0),0)+VLOOKUP("외화환산이익",BS연결,MATCH(O$1,BS연결H,0),0)-VLOOKUP("외화환산손실",BS연결,MATCH(O$1,BS연결H,0),0))/100,"") | P13: =SUM(L13:O13) | Q13: =IFERROR((VLOOKUP("외환차익",BS연결,MATCH(Q$1,BS연결H,0),0)-VLOOKUP("외환차손",BS연결,MATCH(Q$1,BS연결H,0),0)+VLOOKUP("외화환산이익",BS연결,MATCH(Q$1,BS연결H,0),0)-VLOOKUP("외화환산손실",BS연결,MATCH(Q$1,BS연결H,0),0))/100,"") | R13: =IFERROR((VLOOKUP("외환차익",BS연결,MATCH(R$1,BS연결H,0),0)-VLOOKUP("외환차손",BS연결,MATCH(R$1,BS연결H,0),0)+VLOOKUP("외화환산이익",BS연결,MATCH(R$1,BS연결H,0),0)-VLOOKUP("외화환산손실",BS연결,MATCH(R$1,BS연결H,0),0))/100,"") | S13: =IFERROR((VLOOKUP("외환차익",BS연결,MATCH(S$1,BS연결H,0),0)-VLOOKUP("외환차손",BS연결,MATCH(S$1,BS연결H,0),0)+VLOOKUP("외화환산이익",BS연결,MATCH(S$1,BS연결H,0),0)-VLOOKUP("외화환산손실",BS연결,MATCH(S$1,BS연결H,0),0))/100,"") | T13: =IFERROR((VLOOKUP("외환차익",BS연결,MATCH(T$1,BS연결H,0),0)-VLOOKUP("외환차손",BS연결,MATCH(T$1,BS연결H,0),0)+VLOOKUP("외화환산이익",BS연결,MATCH(T$1,BS연결H,0),0)-VLOOKUP("외화환산손실",BS연결,MATCH(T$1,BS연결H,0),0))/100,"") | U13: =SUM(Q13:T13) | V13: =IFERROR((VLOOKUP("외환차익",BS연결,MATCH(V$1,BS연결H,0),0)-VLOOKUP("외환차손",BS연결,MATCH(V$1,BS연결H,0),0)+VLOOKUP("외화환산이익",BS연결,MATCH(V$1,BS연결H,0),0)-VLOOKUP("외화환산손실",BS연결,MATCH(V$1,BS연결H,0),0))/100,"") | W13: =IFERROR((VLOOKUP("외환차익",BS연결,MATCH(W$1,BS연결H,0),0)-VLOOKUP("외환차손",BS연결,MATCH(W$1,BS연결H,0),0)+VLOOKUP("외화환산이익",BS연결,MATCH(W$1,BS연결H,0),0)-VLOOKUP("외화환산손실",BS연결,MATCH(W$1,BS연결H,0),0))/100,"") | X13: =IFERROR((VLOOKUP("외환차익",BS연결,MATCH(X$1,BS연결H,0),0)-VLOOKUP("외환차손",BS연결,MATCH(X$1,BS연결H,0),0)+VLOOKUP("외화환산이익",BS연결,MATCH(X$1,BS연결H,0),0)-VLOOKUP("외화환산손실",BS연결,MATCH(X$1,BS연결H,0),0))/100,"") | Y13: =IFERROR((VLOOKUP("외환차익",BS연결,MATCH(Y$1,BS연결H,0),0)-VLOOKUP("외환차손",BS연결,MATCH(Y$1,BS연결H,0),0)+VLOOKUP("외화환산이익",BS연결,MATCH(Y$1,BS연결H,0),0)-VLOOKUP("외화환산손실",BS연결,MATCH(Y$1,BS연결H,0),0))/100,"") | Z13: =SUM(V13:Y13) | AA13: =IFERROR((VLOOKUP("외환차익",BS연결,MATCH(AA$1,BS연결H,0),0)-VLOOKUP("외환차손",BS연결,MATCH(AA$1,BS연결H,0),0)+VLOOKUP("외화환산이익",BS연결,MATCH(AA$1,BS연결H,0),0)-VLOOKUP("외화환산손실",BS연결,MATCH(AA$1,BS연결H,0),0))/100,"") | AB13: =IFERROR((VLOOKUP("외환차익",BS연결,MATCH(AB$1,BS연결H,0),0)-VLOOKUP("외환차손",BS연결,MATCH(AB$1,BS연결H,0),0)+VLOOKUP("외화환산이익",BS연결,MATCH(AB$1,BS연결H,0),0)-VLOOKUP("외화환산손실",BS연결,MATCH(AB$1,BS연결H,0),0))/100,"") | AC13: =변수!AC24 | AD13: =변수!AD24 | AE13: =SUM(AA13:AD13) | AF13: =변수!AF24 | AG13: =변수!AG24 | AH13: =변수!AH24 | AI13: =변수!AI24 | AJ13: =SUM(AF13:AI13) | AK13: =변수!AK24 | AL13: =변수!AL24 | AM13: =변수!AM24 | AN13: =변수!AN24 | AO13: =SUM(AK13:AN13)
A14: 파생상품손익 | B14: 손익 | C14: 억원 | D14: 파생상품손익 | G14: =IFERROR((VLOOKUP("파생상품이익",BS연결,MATCH(G$1,BS연결H,0),0)-VLOOKUP("파생상품손실",BS연결,MATCH(G$1,BS연결H,0),0))/100,"") | H14: =IFERROR((VLOOKUP("파생상품이익",BS연결,MATCH(H$1,BS연결H,0),0)-VLOOKUP("파생상품손실",BS연결,MATCH(H$1,BS연결H,0),0))/100,"") | I14: =IFERROR((VLOOKUP("파생상품이익",BS연결,MATCH(I$1,BS연결H,0),0)-VLOOKUP("파생상품손실",BS연결,MATCH(I$1,BS연결H,0),0))/100,"") | J14: =IFERROR((VLOOKUP("파생상품이익",BS연결,MATCH(J$1,BS연결H,0),0)-VLOOKUP("파생상품손실",BS연결,MATCH(J$1,BS연결H,0),0))/100,"") | K14: =SUM(G14:J14) | L14: =IFERROR((VLOOKUP("파생상품이익",BS연결,MATCH(L$1,BS연결H,0),0)-VLOOKUP("파생상품손실",BS연결,MATCH(L$1,BS연결H,0),0))/100,"") | M14: =IFERROR((VLOOKUP("파생상품이익",BS연결,MATCH(M$1,BS연결H,0),0)-VLOOKUP("파생상품손실",BS연결,MATCH(M$1,BS연결H,0),0))/100,"") | N14: =IFERROR((VLOOKUP("파생상품이익",BS연결,MATCH(N$1,BS연결H,0),0)-VLOOKUP("파생상품손실",BS연결,MATCH(N$1,BS연결H,0),0))/100,"") | O14: =IFERROR((VLOOKUP("파생상품이익",BS연결,MATCH(O$1,BS연결H,0),0)-VLOOKUP("파생상품손실",BS연결,MATCH(O$1,BS연결H,0),0))/100,"") | P14: =SUM(L14:O14) | Q14: =IFERROR((VLOOKUP("파생상품이익",BS연결,MATCH(Q$1,BS연결H,0),0)-VLOOKUP("파생상품손실",BS연결,MATCH(Q$1,BS연결H,0),0))/100,"") | R14: =IFERROR((VLOOKUP("파생상품이익",BS연결,MATCH(R$1,BS연결H,0),0)-VLOOKUP("파생상품손실",BS연결,MATCH(R$1,BS연결H,0),0))/100,"") | S14: =IFERROR((VLOOKUP("파생상품이익",BS연결,MATCH(S$1,BS연결H,0),0)-VLOOKUP("파생상품손실",BS연결,MATCH(S$1,BS연결H,0),0))/100,"") | T14: =IFERROR((VLOOKUP("파생상품이익",BS연결,MATCH(T$1,BS연결H,0),0)-VLOOKUP("파생상품손실",BS연결,MATCH(T$1,BS연결H,0),0))/100,"") | U14: =SUM(Q14:T14) | V14: =IFERROR((VLOOKUP("파생상품이익",BS연결,MATCH(V$1,BS연결H,0),0)-VLOOKUP("파생상품손실",BS연결,MATCH(V$1,BS연결H,0),0))/100,"") | W14: =IFERROR((VLOOKUP("파생상품이익",BS연결,MATCH(W$1,BS연결H,0),0)-VLOOKUP("파생상품손실",BS연결,MATCH(W$1,BS연결H,0),0))/100,"") | X14: =IFERROR((VLOOKUP("파생상품이익",BS연결,MATCH(X$1,BS연결H,0),0)-VLOOKUP("파생상품손실",BS연결,MATCH(X$1,BS연결H,0),0))/100,"") | Y14: =IFERROR((VLOOKUP("파생상품이익",BS연결,MATCH(Y$1,BS연결H,0),0)-VLOOKUP("파생상품손실",BS연결,MATCH(Y$1,BS연결H,0),0))/100,"") | Z14: =SUM(V14:Y14) | AA14: =IFERROR((VLOOKUP("파생상품이익",BS연결,MATCH(AA$1,BS연결H,0),0)-VLOOKUP("파생상품손실",BS연결,MATCH(AA$1,BS연결H,0),0))/100,"") | AB14: =IFERROR((VLOOKUP("파생상품이익",BS연결,MATCH(AB$1,BS연결H,0),0)-VLOOKUP("파생상품손실",BS연결,MATCH(AB$1,BS연결H,0),0))/100,"") | AC14: =변수!AC25 | AD14: =변수!AD25 | AE14: =SUM(AA14:AD14) | AF14: =변수!AF25 | AG14: =변수!AG25 | AH14: =변수!AH25 | AI14: =변수!AI25 | AJ14: =SUM(AF14:AI14) | AK14: =변수!AK25 | AL14: =변수!AL25 | AM14: =변수!AM25 | AN14: =변수!AN25 | AO14: =SUM(AK14:AN14)
A15: 기타금융손익 | B15: 손익 | C15: 억원 | D15: 기타금융손익(금융손익 잔차) | G15: =IFERROR(G11-G12-G13-G14,"") | H15: =IFERROR(H11-H12-H13-H14,"") | I15: =IFERROR(I11-I12-I13-I14,"") | J15: =IFERROR(J11-J12-J13-J14,"") | K15: =SUM(G15:J15) | L15: =IFERROR(L11-L12-L13-L14,"") | M15: =IFERROR(M11-M12-M13-M14,"") | N15: =IFERROR(N11-N12-N13-N14,"") | O15: =IFERROR(O11-O12-O13-O14,"") | P15: =SUM(L15:O15) | Q15: =IFERROR(Q11-Q12-Q13-Q14,"") | R15: =IFERROR(R11-R12-R13-R14,"") | S15: =IFERROR(S11-S12-S13-S14,"") | T15: =IFERROR(T11-T12-T13-T14,"") | U15: =SUM(Q15:T15) | V15: =IFERROR(V11-V12-V13-V14,"") | W15: =IFERROR(W11-W12-W13-W14,"") | X15: =IFERROR(X11-X12-X13-X14,"") | Y15: =IFERROR(Y11-Y12-Y13-Y14,"") | Z15: =SUM(V15:Y15) | AA15: =IFERROR(AA11-AA12-AA13-AA14,"") | AB15: =IFERROR(AB11-AB12-AB13-AB14,"") | AC15: =변수!AC26 | AD15: =변수!AD26 | AE15: =SUM(AA15:AD15) | AF15: =변수!AF26 | AG15: =변수!AG26 | AH15: =변수!AH26 | AI15: =변수!AI26 | AJ15: =SUM(AF15:AI15) | AK15: =변수!AK26 | AL15: =변수!AL26 | AM15: =변수!AM26 | AN15: =변수!AN26 | AO15: =SUM(AK15:AN15)
A16: 기타영업외손익 | B16: 손익 | C16: 억원 | D16: 기타영업외손익 | E16: =IFERROR(VLOOKUP($D16,BS연결,MATCH(E$1,BS연결H,0),0)/100,"") | G16: =IFERROR(VLOOKUP($D16,BS연결,MATCH(G$1,BS연결H,0),0)/100,"") | H16: =IFERROR(VLOOKUP($D16,BS연결,MATCH(H$1,BS연결H,0),0)/100,"") | I16: =IFERROR(VLOOKUP($D16,BS연결,MATCH(I$1,BS연결H,0),0)/100,"") | J16: =IFERROR(VLOOKUP($D16,BS연결,MATCH(J$1,BS연결H,0),0)/100,"") | K16: =IFERROR(VLOOKUP($D16,BS연결,MATCH(K$1,BS연결H,0),0)/100,"") | L16: =IFERROR(VLOOKUP($D16,BS연결,MATCH(L$1,BS연결H,0),0)/100,"") | M16: =IFERROR(VLOOKUP($D16,BS연결,MATCH(M$1,BS연결H,0),0)/100,"") | N16: =IFERROR(VLOOKUP($D16,BS연결,MATCH(N$1,BS연결H,0),0)/100,"") | ... AB16: =IFERROR(VLOOKUP($D16,BS연결,MATCH(AB$1,BS연결H,0),0)/100,"") | AC16: =변수!AC27 | AD16: =변수!AD27 | AE16: =SUM(AA16:AD16) | AF16: =변수!AF27 | AG16: =변수!AG27 | AH16: =변수!AH27 | AI16: =변수!AI27 | AJ16: =SUM(AF16:AI16) | AK16: =변수!AK27 | AL16: =변수!AL27 | AM16: =변수!AM27 | AN16: =변수!AN27 | AO16: =SUM(AK16:AN16)
A17: 지분법손익 | B17: 손익 | C17: 억원 | D17: 종속기업,공동지배기업및관계기업관련손익 | E17: =IFERROR(VLOOKUP($D17,BS연결,MATCH(E$1,BS연결H,0),0)/100,"") | G17: =IFERROR(VLOOKUP($D17,BS연결,MATCH(G$1,BS연결H,0),0)/100,"") | H17: =IFERROR(VLOOKUP($D17,BS연결,MATCH(H$1,BS연결H,0),0)/100,"") | I17: =IFERROR(VLOOKUP($D17,BS연결,MATCH(I$1,BS연결H,0),0)/100,"") | J17: =IFERROR(VLOOKUP($D17,BS연결,MATCH(J$1,BS연결H,0),0)/100,"") | K17: =IFERROR(VLOOKUP($D17,BS연결,MATCH(K$1,BS연결H,0),0)/100,"") | L17: =IFERROR(VLOOKUP($D17,BS연결,MATCH(L$1,BS연결H,0),0)/100,"") | M17: =IFERROR(VLOOKUP($D17,BS연결,MATCH(M$1,BS연결H,0),0)/100,"") | N17: =IFERROR(VLOOKUP($D17,BS연결,MATCH(N$1,BS연결H,0),0)/100,"") | ... AB17: =IFERROR(VLOOKUP($D17,BS연결,MATCH(AB$1,BS연결H,0),0)/100,"") | AC17: =변수!AC28 | AD17: =변수!AD28 | AE17: =SUM(AA17:AD17) | AF17: =변수!AF28 | AG17: =변수!AG28 | AH17: =변수!AH28 | AI17: =변수!AI28 | AJ17: =SUM(AF17:AI17) | AK17: =변수!AK28 | AL17: =변수!AL28 | AM17: =변수!AM28 | AN17: =변수!AN28 | AO17: =SUM(AK17:AN17)
A18: 세전이익 | B18: 손익 | C18: 억원 | D18: 법인세비용차감전계속사업이익 | E18: =IFERROR(VLOOKUP($D18,BS연결,MATCH(E$1,BS연결H,0),0)/100,"") | G18: =IFERROR(VLOOKUP($D18,BS연결,MATCH(G$1,BS연결H,0),0)/100,"") | H18: =IFERROR(VLOOKUP($D18,BS연결,MATCH(H$1,BS연결H,0),0)/100,"") | I18: =IFERROR(VLOOKUP($D18,BS연결,MATCH(I$1,BS연결H,0),0)/100,"") | J18: =IFERROR(VLOOKUP($D18,BS연결,MATCH(J$1,BS연결H,0),0)/100,"") | K18: =IFERROR(VLOOKUP($D18,BS연결,MATCH(K$1,BS연결H,0),0)/100,"") | L18: =IFERROR(VLOOKUP($D18,BS연결,MATCH(L$1,BS연결H,0),0)/100,"") | M18: =IFERROR(VLOOKUP($D18,BS연결,MATCH(M$1,BS연결H,0),0)/100,"") | N18: =IFERROR(VLOOKUP($D18,BS연결,MATCH(N$1,BS연결H,0),0)/100,"") | ... AB18: =IFERROR(VLOOKUP($D18,BS연결,MATCH(AB$1,BS연결H,0),0)/100,"") | AC18: =IFERROR(AC9+AC11+AC16+AC17,"") | AD18: =IFERROR(AD9+AD11+AD16+AD17,"") | AE18: =SUM(AA18:AD18) | AF18: =IFERROR(AF9+AF11+AF16+AF17,"") | AG18: =IFERROR(AG9+AG11+AG16+AG17,"") | AH18: =IFERROR(AH9+AH11+AH16+AH17,"") | AI18: =IFERROR(AI9+AI11+AI16+AI17,"") | AJ18: =SUM(AF18:AI18) | AK18: =IFERROR(AK9+AK11+AK16+AK17,"") | AL18: =IFERROR(AL9+AL11+AL16+AL17,"") | AM18: =IFERROR(AM9+AM11+AM16+AM17,"") | AN18: =IFERROR(AN9+AN11+AN16+AN17,"") | AO18: =SUM(AK18:AN18)
A19: 법인세비용 | B19: 손익 | C19: 억원 | D19: 법인세비용 | E19: =IFERROR(VLOOKUP($D19,BS연결,MATCH(E$1,BS연결H,0),0)/100,"") | G19: =IFERROR(VLOOKUP($D19,BS연결,MATCH(G$1,BS연결H,0),0)/100,"") | H19: =IFERROR(VLOOKUP($D19,BS연결,MATCH(H$1,BS연결H,0),0)/100,"") | I19: =IFERROR(VLOOKUP($D19,BS연결,MATCH(I$1,BS연결H,0),0)/100,"") | J19: =IFERROR(VLOOKUP($D19,BS연결,MATCH(J$1,BS연결H,0),0)/100,"") | K19: =IFERROR(VLOOKUP($D19,BS연결,MATCH(K$1,BS연결H,0),0)/100,"") | L19: =IFERROR(VLOOKUP($D19,BS연결,MATCH(L$1,BS연결H,0),0)/100,"") | M19: =IFERROR(VLOOKUP($D19,BS연결,MATCH(M$1,BS연결H,0),0)/100,"") | N19: =IFERROR(VLOOKUP($D19,BS연결,MATCH(N$1,BS연결H,0),0)/100,"") | ... AB19: =IFERROR(VLOOKUP($D19,BS연결,MATCH(AB$1,BS연결H,0),0)/100,"") | AC19: =IFERROR(MAX(AC18,0)*변수!AC29,"") | AD19: =IFERROR(MAX(AD18,0)*변수!AD29,"") | AE19: =SUM(AA19:AD19) | AF19: =IFERROR(MAX(AF18,0)*변수!AF29,"") | AG19: =IFERROR(MAX(AG18,0)*변수!AG29,"") | AH19: =IFERROR(MAX(AH18,0)*변수!AH29,"") | AI19: =IFERROR(MAX(AI18,0)*변수!AI29,"") | AJ19: =SUM(AF19:AI19) | AK19: =IFERROR(MAX(AK18,0)*변수!AK29,"") | AL19: =IFERROR(MAX(AL18,0)*변수!AL29,"") | AM19: =IFERROR(MAX(AM18,0)*변수!AM29,"") | AN19: =IFERROR(MAX(AN18,0)*변수!AN29,"") | AO19: =SUM(AK19:AN19)
A20: 당기순이익 | B20: 손익 | C20: 억원 | D20: 당기순이익 | E20: =IFERROR(VLOOKUP($D20,BS연결,MATCH(E$1,BS연결H,0),0)/100,"") | G20: =IFERROR(VLOOKUP($D20,BS연결,MATCH(G$1,BS연결H,0),0)/100,"") | H20: =IFERROR(VLOOKUP($D20,BS연결,MATCH(H$1,BS연결H,0),0)/100,"") | I20: =IFERROR(VLOOKUP($D20,BS연결,MATCH(I$1,BS연결H,0),0)/100,"") | J20: =IFERROR(VLOOKUP($D20,BS연결,MATCH(J$1,BS연결H,0),0)/100,"") | K20: =IFERROR(VLOOKUP($D20,BS연결,MATCH(K$1,BS연결H,0),0)/100,"") | L20: =IFERROR(VLOOKUP($D20,BS연결,MATCH(L$1,BS연결H,0),0)/100,"") | M20: =IFERROR(VLOOKUP($D20,BS연결,MATCH(M$1,BS연결H,0),0)/100,"") | N20: =IFERROR(VLOOKUP($D20,BS연결,MATCH(N$1,BS연결H,0),0)/100,"") | ... AB20: =IFERROR(VLOOKUP($D20,BS연결,MATCH(AB$1,BS연결H,0),0)/100,"") | AC20: =IFERROR(AC18-AC19,"") | AD20: =IFERROR(AD18-AD19,"") | AE20: =SUM(AA20:AD20) | AF20: =IFERROR(AF18-AF19,"") | AG20: =IFERROR(AG18-AG19,"") | AH20: =IFERROR(AH18-AH19,"") | AI20: =IFERROR(AI18-AI19,"") | AJ20: =SUM(AF20:AI20) | AK20: =IFERROR(AK18-AK19,"") | AL20: =IFERROR(AL18-AL19,"") | AM20: =IFERROR(AM18-AM19,"") | AN20: =IFERROR(AN18-AN19,"") | AO20: =SUM(AK20:AN20)
A21: 지배주주순이익 | B21: 손익 | C21: 억원 | D21: (지배주주지분)당기순이익 | E21: =IFERROR(VLOOKUP($D21,BS연결,MATCH(E$1,BS연결H,0),0)/100,"") | G21: =IFERROR(VLOOKUP($D21,BS연결,MATCH(G$1,BS연결H,0),0)/100,"") | H21: =IFERROR(VLOOKUP($D21,BS연결,MATCH(H$1,BS연결H,0),0)/100,"") | I21: =IFERROR(VLOOKUP($D21,BS연결,MATCH(I$1,BS연결H,0),0)/100,"") | J21: =IFERROR(VLOOKUP($D21,BS연결,MATCH(J$1,BS연결H,0),0)/100,"") | K21: =IFERROR(VLOOKUP($D21,BS연결,MATCH(K$1,BS연결H,0),0)/100,"") | L21: =IFERROR(VLOOKUP($D21,BS연결,MATCH(L$1,BS연결H,0),0)/100,"") | M21: =IFERROR(VLOOKUP($D21,BS연결,MATCH(M$1,BS연결H,0),0)/100,"") | N21: =IFERROR(VLOOKUP($D21,BS연결,MATCH(N$1,BS연결H,0),0)/100,"") | ... AB21: =IFERROR(VLOOKUP($D21,BS연결,MATCH(AB$1,BS연결H,0),0)/100,"") | AC21: =IFERROR(AC20*변수!AC30,"") | AD21: =IFERROR(AD20*변수!AD30,"") | AE21: =SUM(AA21:AD21) | AF21: =IFERROR(AF20*변수!AF30,"") | AG21: =IFERROR(AG20*변수!AG30,"") | AH21: =IFERROR(AH20*변수!AH30,"") | AI21: =IFERROR(AI20*변수!AI30,"") | AJ21: =SUM(AF21:AI21) | AK21: =IFERROR(AK20*변수!AK30,"") | AL21: =IFERROR(AL20*변수!AL30,"") | AM21: =IFERROR(AM20*변수!AM30,"") | AN21: =IFERROR(AN20*변수!AN30,"") | AO21: =SUM(AK21:AN21)
A22: 중단사업이익 | B22: 손익 | C22: 억원 | D22: 중단사업이익 | E22: =IFERROR(VLOOKUP($D22,BS연결,MATCH(E$1,BS연결H,0),0)/100,"") | G22: =IFERROR(VLOOKUP($D22,BS연결,MATCH(G$1,BS연결H,0),0)/100,"") | H22: =IFERROR(VLOOKUP($D22,BS연결,MATCH(H$1,BS연결H,0),0)/100,"") | I22: =IFERROR(VLOOKUP($D22,BS연결,MATCH(I$1,BS연결H,0),0)/100,"") | J22: =IFERROR(VLOOKUP($D22,BS연결,MATCH(J$1,BS연결H,0),0)/100,"") | K22: =IFERROR(VLOOKUP($D22,BS연결,MATCH(K$1,BS연결H,0),0)/100,"") | P22: =SUM(L22:O22) | U22: =SUM(Q22:T22) | Z22: =SUM(V22:Y22) | AE22: =SUM(AA22:AD22) | AJ22: =SUM(AF22:AI22) | AO22: =SUM(AK22:AN22)
A23: 자산총계 | B23: 재무상태 | C23: 억원 | D23: 자산총계 | E23: =IFERROR(VLOOKUP($D23,BS연결,MATCH(E$1,BS연결H,0),0)/100,"") | F23: =IFERROR(VLOOKUP($D23,BS연결,MATCH(F$1,BS연결H,0),0)/100,"") | G23: =IFERROR(VLOOKUP($D23,BS연결,MATCH(G$1,BS연결H,0),0)/100,"") | H23: =IFERROR(VLOOKUP($D23,BS연결,MATCH(H$1,BS연결H,0),0)/100,"") | I23: =IFERROR(VLOOKUP($D23,BS연결,MATCH(I$1,BS연결H,0),0)/100,"") | J23: =IFERROR(VLOOKUP($D23,BS연결,MATCH(J$1,BS연결H,0),0)/100,"") | K23: =IFERROR(VLOOKUP($D23,BS연결,MATCH(K$1,BS연결H,0),0)/100,"") | L23: =IFERROR(VLOOKUP($D23,BS연결,MATCH(L$1,BS연결H,0),0)/100,"") | ... AB23: =IFERROR(VLOOKUP($D23,BS연결,MATCH(AB$1,BS연결H,0),0)/100,"") | AC23: =IFERROR(AC24+AC25,"") | AD23: =IFERROR(AD24+AD25,"") | AE23: =AD23 | AF23: =IFERROR(AF24+AF25,"") | AG23: =IFERROR(AG24+AG25,"") | AH23: =IFERROR(AH24+AH25,"") | AI23: =IFERROR(AI24+AI25,"") | AJ23: =AI23 | AK23: =IFERROR(AK24+AK25,"") | AL23: =IFERROR(AL24+AL25,"") | AM23: =IFERROR(AM24+AM25,"") | AN23: =IFERROR(AN24+AN25,"") | AO23: =AN23
A24: 부채총계 | B24: 재무상태 | C24: 억원 | D24: 부채총계 | E24: =IFERROR(VLOOKUP($D24,BS연결,MATCH(E$1,BS연결H,0),0)/100,"") | F24: =IFERROR(VLOOKUP($D24,BS연결,MATCH(F$1,BS연결H,0),0)/100,"") | G24: =IFERROR(VLOOKUP($D24,BS연결,MATCH(G$1,BS연결H,0),0)/100,"") | H24: =IFERROR(VLOOKUP($D24,BS연결,MATCH(H$1,BS연결H,0),0)/100,"") | I24: =IFERROR(VLOOKUP($D24,BS연결,MATCH(I$1,BS연결H,0),0)/100,"") | J24: =IFERROR(VLOOKUP($D24,BS연결,MATCH(J$1,BS연결H,0),0)/100,"") | K24: =IFERROR(VLOOKUP($D24,BS연결,MATCH(K$1,BS연결H,0),0)/100,"") | L24: =IFERROR(VLOOKUP($D24,BS연결,MATCH(L$1,BS연결H,0),0)/100,"") | ... AB24: =IFERROR(VLOOKUP($D24,BS연결,MATCH(AB$1,BS연결H,0),0)/100,"") | AC24: =IFERROR(AB24*(1+변수!AC32),"") | AD24: =IFERROR(AC24*(1+변수!AD32),"") | AE24: =AD24 | AF24: =IFERROR(AD24*(1+변수!AF32),"") | AG24: =IFERROR(AF24*(1+변수!AG32),"") | AH24: =IFERROR(AG24*(1+변수!AH32),"") | AI24: =IFERROR(AH24*(1+변수!AI32),"") | AJ24: =AI24 | AK24: =IFERROR(AI24*(1+변수!AK32),"") | AL24: =IFERROR(AK24*(1+변수!AL32),"") | AM24: =IFERROR(AL24*(1+변수!AM32),"") | AN24: =IFERROR(AM24*(1+변수!AN32),"") | AO24: =AN24
A25: 자본총계 | B25: 재무상태 | C25: 억원 | D25: 자본총계 | E25: =IFERROR(VLOOKUP($D25,BS연결,MATCH(E$1,BS연결H,0),0)/100,"") | F25: =IFERROR(VLOOKUP($D25,BS연결,MATCH(F$1,BS연결H,0),0)/100,"") | G25: =IFERROR(VLOOKUP($D25,BS연결,MATCH(G$1,BS연결H,0),0)/100,"") | H25: =IFERROR(VLOOKUP($D25,BS연결,MATCH(H$1,BS연결H,0),0)/100,"") | I25: =IFERROR(VLOOKUP($D25,BS연결,MATCH(I$1,BS연결H,0),0)/100,"") | J25: =IFERROR(VLOOKUP($D25,BS연결,MATCH(J$1,BS연결H,0),0)/100,"") | K25: =IFERROR(VLOOKUP($D25,BS연결,MATCH(K$1,BS연결H,0),0)/100,"") | L25: =IFERROR(VLOOKUP($D25,BS연결,MATCH(L$1,BS연결H,0),0)/100,"") | ... AB25: =IFERROR(VLOOKUP($D25,BS연결,MATCH(AB$1,BS연결H,0),0)/100,"") | AC25: =IFERROR(AB25+AC20-변수!AC33,"") | AD25: =IFERROR(AC25+AD20-변수!AD33,"") | AE25: =AD25 | AF25: =IFERROR(AD25+AF20-변수!AF33,"") | AG25: =IFERROR(AF25+AG20-변수!AG33,"") | AH25: =IFERROR(AG25+AH20-변수!AH33,"") | AI25: =IFERROR(AH25+AI20-변수!AI33,"") | AJ25: =AI25 | AK25: =IFERROR(AI25+AK20-변수!AK33,"") | AL25: =IFERROR(AK25+AL20-변수!AL33,"") | AM25: =IFERROR(AL25+AM20-변수!AM33,"") | AN25: =IFERROR(AM25+AN20-변수!AN33,"") | AO25: =AN25
A26: 지배주주지분 | B26: 재무상태 | C26: 억원 | D26: 지배주주지분 | E26: =IFERROR(VLOOKUP($D26,BS연결,MATCH(E$1,BS연결H,0),0)/100,"") | F26: =IFERROR(VLOOKUP($D26,BS연결,MATCH(F$1,BS연결H,0),0)/100,"") | G26: =IFERROR(VLOOKUP($D26,BS연결,MATCH(G$1,BS연결H,0),0)/100,"") | H26: =IFERROR(VLOOKUP($D26,BS연결,MATCH(H$1,BS연결H,0),0)/100,"") | I26: =IFERROR(VLOOKUP($D26,BS연결,MATCH(I$1,BS연결H,0),0)/100,"") | J26: =IFERROR(VLOOKUP($D26,BS연결,MATCH(J$1,BS연결H,0),0)/100,"") | K26: =IFERROR(VLOOKUP($D26,BS연결,MATCH(K$1,BS연결H,0),0)/100,"") | L26: =IFERROR(VLOOKUP($D26,BS연결,MATCH(L$1,BS연결H,0),0)/100,"") | N26: =IFERROR(VLOOKUP($D26,BS연결,MATCH(N$1,BS연결H,0),0)/100,"") | P26: =O26 | U26: =T26 | Z26: =Y26 | AE26: =AD26 | AJ26: =AI26 | AO26: =AN26
A27: 총차입금 | B27: 재무상태 | C27: 억원 | D27: 총차입금 | E27: =IFERROR(VLOOKUP($D27,BS연결,MATCH(E$1,BS연결H,0),0)/100,"") | F27: =IFERROR(VLOOKUP($D27,BS연결,MATCH(F$1,BS연결H,0),0)/100,"") | G27: =IFERROR(VLOOKUP($D27,BS연결,MATCH(G$1,BS연결H,0),0)/100,"") | H27: =IFERROR(VLOOKUP($D27,BS연결,MATCH(H$1,BS연결H,0),0)/100,"") | I27: =IFERROR(VLOOKUP($D27,BS연결,MATCH(I$1,BS연결H,0),0)/100,"") | J27: =IFERROR(VLOOKUP($D27,BS연결,MATCH(J$1,BS연결H,0),0)/100,"") | K27: =IFERROR(VLOOKUP($D27,BS연결,MATCH(K$1,BS연결H,0),0)/100,"") | L27: =IFERROR(VLOOKUP($D27,BS연결,MATCH(L$1,BS연결H,0),0)/100,"") | ... AB27: =IFERROR(VLOOKUP($D27,BS연결,MATCH(AB$1,BS연결H,0),0)/100,"") | AC27: =IFERROR(AB27*(1+변수!AC35),"") | AD27: =IFERROR(AC27*(1+변수!AD35),"") | AE27: =AD27 | AF27: =IFERROR(AD27*(1+변수!AF35),"") | AG27: =IFERROR(AF27*(1+변수!AG35),"") | AH27: =IFERROR(AG27*(1+변수!AH35),"") | AI27: =IFERROR(AH27*(1+변수!AI35),"") | AJ27: =AI27 | AK27: =IFERROR(AI27*(1+변수!AK35),"") | AL27: =IFERROR(AK27*(1+변수!AL35),"") | AM27: =IFERROR(AL27*(1+변수!AM35),"") | AN27: =IFERROR(AM27*(1+변수!AN35),"") | AO27: =AN27
A28: 순차입금 | B28: 재무상태 | C28: 억원 | D28: 순차입금 | E28: =IFERROR(VLOOKUP($D28,BS연결,MATCH(E$1,BS연결H,0),0)/100,"") | F28: =IFERROR(VLOOKUP($D28,BS연결,MATCH(F$1,BS연결H,0),0)/100,"") | G28: =IFERROR(VLOOKUP($D28,BS연결,MATCH(G$1,BS연결H,0),0)/100,"") | H28: =IFERROR(VLOOKUP($D28,BS연결,MATCH(H$1,BS연결H,0),0)/100,"") | I28: =IFERROR(VLOOKUP($D28,BS연결,MATCH(I$1,BS연결H,0),0)/100,"") | J28: =IFERROR(VLOOKUP($D28,BS연결,MATCH(J$1,BS연결H,0),0)/100,"") | K28: =IFERROR(VLOOKUP($D28,BS연결,MATCH(K$1,BS연결H,0),0)/100,"") | L28: =IFERROR(VLOOKUP($D28,BS연결,MATCH(L$1,BS연결H,0),0)/100,"") | ... AB28: =IFERROR(VLOOKUP($D28,BS연결,MATCH(AB$1,BS연결H,0),0)/100,"") | AC28: =IFERROR(AB28*(1+변수!AC36),"") | AD28: =IFERROR(AC28*(1+변수!AD36),"") | AE28: =AD28 | AF28: =IFERROR(AD28*(1+변수!AF36),"") | AG28: =IFERROR(AF28*(1+변수!AG36),"") | AH28: =IFERROR(AG28*(1+변수!AH36),"") | AI28: =IFERROR(AH28*(1+변수!AI36),"") | AJ28: =AI28 | AK28: =IFERROR(AI28*(1+변수!AK36),"") | AL28: =IFERROR(AK28*(1+변수!AL36),"") | AM28: =IFERROR(AL28*(1+변수!AM36),"") | AN28: =IFERROR(AM28*(1+변수!AN36),"") | AO28: =AN28
A29: 이자발생자산 | B29: 재무상태 | C29: 억원 | D29: 이자발생자산 | E29: =IFERROR(VLOOKUP($D29,BS연결,MATCH(E$1,BS연결H,0),0)/100,"") | F29: =IFERROR(VLOOKUP($D29,BS연결,MATCH(F$1,BS연결H,0),0)/100,"") | G29: =IFERROR(VLOOKUP($D29,BS연결,MATCH(G$1,BS연결H,0),0)/100,"") | H29: =IFERROR(VLOOKUP($D29,BS연결,MATCH(H$1,BS연결H,0),0)/100,"") | I29: =IFERROR(VLOOKUP($D29,BS연결,MATCH(I$1,BS연결H,0),0)/100,"") | J29: =IFERROR(VLOOKUP($D29,BS연결,MATCH(J$1,BS연결H,0),0)/100,"") | K29: =IFERROR(VLOOKUP($D29,BS연결,MATCH(K$1,BS연결H,0),0)/100,"") | L29: =IFERROR(VLOOKUP($D29,BS연결,MATCH(L$1,BS연결H,0),0)/100,"") | ... AB29: =IFERROR(VLOOKUP($D29,BS연결,MATCH(AB$1,BS연결H,0),0)/100,"") | AC29: =IFERROR(AB29*(1+변수!AC37),"") | AD29: =IFERROR(AC29*(1+변수!AD37),"") | AE29: =AD29 | AF29: =IFERROR(AD29*(1+변수!AF37),"") | AG29: =IFERROR(AF29*(1+변수!AG37),"") | AH29: =IFERROR(AG29*(1+변수!AH37),"") | AI29: =IFERROR(AH29*(1+변수!AI37),"") | AJ29: =AI29 | AK29: =IFERROR(AI29*(1+변수!AK37),"") | AL29: =IFERROR(AK29*(1+변수!AL37),"") | AM29: =IFERROR(AL29*(1+변수!AM37),"") | AN29: =IFERROR(AM29*(1+변수!AN37),"") | AO29: =AN29
A30: 현금및현금성자산 | B30: 재무상태 | C30: 억원 | D30: 현금및현금성자산 | E30: =IFERROR(VLOOKUP($D30,BS연결,MATCH(E$1,BS연결H,0),0)/100,"") | F30: =IFERROR(VLOOKUP($D30,BS연결,MATCH(F$1,BS연결H,0),0)/100,"") | G30: =IFERROR(VLOOKUP($D30,BS연결,MATCH(G$1,BS연결H,0),0)/100,"") | H30: =IFERROR(VLOOKUP($D30,BS연결,MATCH(H$1,BS연결H,0),0)/100,"") | I30: =IFERROR(VLOOKUP($D30,BS연결,MATCH(I$1,BS연결H,0),0)/100,"") | J30: =IFERROR(VLOOKUP($D30,BS연결,MATCH(J$1,BS연결H,0),0)/100,"") | K30: =IFERROR(VLOOKUP($D30,BS연결,MATCH(K$1,BS연결H,0),0)/100,"") | L30: =IFERROR(VLOOKUP($D30,BS연결,MATCH(L$1,BS연결H,0),0)/100,"") | ... AB30: =IFERROR(VLOOKUP($D30,BS연결,MATCH(AB$1,BS연결H,0),0)/100,"") | AE30: =AD30 | AJ30: =AI30 | AO30: =AN30
A31: CAPEX | B31: 현금흐름 | C31: 억원 | D31: CAPEX | E31: =IFERROR(VLOOKUP($D31,BS연결,MATCH(E$1,BS연결H,0),0)/100,"") | G31: =IFERROR(VLOOKUP($D31,BS연결,MATCH(G$1,BS연결H,0),0)/100,"") | H31: =IFERROR(VLOOKUP($D31,BS연결,MATCH(H$1,BS연결H,0),0)/100,"") | I31: =IFERROR(VLOOKUP($D31,BS연결,MATCH(I$1,BS연결H,0),0)/100,"") | J31: =IFERROR(VLOOKUP($D31,BS연결,MATCH(J$1,BS연결H,0),0)/100,"") | K31: =IFERROR(VLOOKUP($D31,BS연결,MATCH(K$1,BS연결H,0),0)/100,"") | L31: =IFERROR(VLOOKUP($D31,BS연결,MATCH(L$1,BS연결H,0),0)/100,"") | M31: =IFERROR(VLOOKUP($D31,BS연결,MATCH(M$1,BS연결H,0),0)/100,"") | N31: =IFERROR(VLOOKUP($D31,BS연결,MATCH(N$1,BS연결H,0),0)/100,"") | ... AB31: =IFERROR(VLOOKUP($D31,BS연결,MATCH(AB$1,BS연결H,0),0)/100,"") | AC31: =IFERROR(X31*(1+변수!AC39),"") | AD31: =IFERROR(Y31*(1+변수!AD39),"") | AE31: =SUM(AA31:AD31) | AF31: =IFERROR(AA31*(1+변수!AF39),"") | AG31: =IFERROR(AB31*(1+변수!AG39),"") | AH31: =IFERROR(AC31*(1+변수!AH39),"") | AI31: =IFERROR(AD31*(1+변수!AI39),"") | AJ31: =SUM(AF31:AI31) | AK31: =IFERROR(AF31*(1+변수!AK39),"") | AL31: =IFERROR(AG31*(1+변수!AL39),"") | AM31: =IFERROR(AH31*(1+변수!AM39),"") | AN31: =IFERROR(AI31*(1+변수!AN39),"") | AO31: =SUM(AK31:AN31)
A32: 영업활동현금흐름 | B32: 현금흐름 | C32: 억원 | D32: 영업활동으로인한현금흐름 | E32: =IFERROR(VLOOKUP($D32,BS연결,MATCH(E$1,BS연결H,0),0)/100,"") | G32: =IFERROR(VLOOKUP($D32,BS연결,MATCH(G$1,BS연결H,0),0)/100,"") | H32: =IFERROR(VLOOKUP($D32,BS연결,MATCH(H$1,BS연결H,0),0)/100,"") | I32: =IFERROR(VLOOKUP($D32,BS연결,MATCH(I$1,BS연결H,0),0)/100,"") | J32: =IFERROR(VLOOKUP($D32,BS연결,MATCH(J$1,BS연결H,0),0)/100,"") | K32: =IFERROR(VLOOKUP($D32,BS연결,MATCH(K$1,BS연결H,0),0)/100,"") | L32: =IFERROR(VLOOKUP($D32,BS연결,MATCH(L$1,BS연결H,0),0)/100,"") | M32: =IFERROR(VLOOKUP($D32,BS연결,MATCH(M$1,BS연결H,0),0)/100,"") | N32: =IFERROR(VLOOKUP($D32,BS연결,MATCH(N$1,BS연결H,0),0)/100,"") | ... AB32: =IFERROR(VLOOKUP($D32,BS연결,MATCH(AB$1,BS연결H,0),0)/100,"") | AE32: =SUM(AA32:AD32) | AJ32: =SUM(AF32:AI32) | AO32: =SUM(AK32:AN32)
A33: 주식수 | B33: 주당 | C33: 백만주 | D33: 유통주식수 | E33: 522.125 | F33: =E33 | G33: 625.698 | H33: 635.197 | I33: 635.197 | J33: 638.212 | K33: =J33 | L33: 640.465 | M33: 640.465 | N33: 640.465 | O33: 640.465 | P33: =O33 | Q33: 640.465 | R33: 640.465 | S33: 640.465 | T33: 640.465 | U33: =T33 | V33: 640.465 | W33: 640.465 | X33: 640.465 | Y33: 640.465 | Z33: =Y33 | AA33: 640.465 | AB33: 639.133 | AC33: =IFERROR(AB33*(1+변수!AC41),"") | AD33: =IFERROR(AC33*(1+변수!AD41),"") | AE33: =AD33 | AF33: =IFERROR(AD33*(1+변수!AF41),"") | AG33: =IFERROR(AF33*(1+변수!AG41),"") | AH33: =IFERROR(AG33*(1+변수!AH41),"") | AI33: =IFERROR(AH33*(1+변수!AI41),"") | AJ33: =AI33 | AK33: =IFERROR(AI33*(1+변수!AK41),"") | AL33: =IFERROR(AK33*(1+변수!AL41),"") | AM33: =IFERROR(AL33*(1+변수!AM41),"") | AN33: =IFERROR(AM33*(1+변수!AN41),"") | AO33: =AN33
A34: EPS | B34: 주당 | C34: 원 | D34: EPS | E34: =IFERROR(E21*100/E33,"") | G34: =IFERROR(G21*100/G33,"") | H34: =IFERROR(H21*100/H33,"") | I34: =IFERROR(I21*100/I33,"") | J34: =IFERROR(J21*100/J33,"") | K34: =SUM(G34:J34) | L34: =IFERROR(L21*100/L33,"") | M34: =IFERROR(M21*100/M33,"") | N34: =IFERROR(N21*100/N33,"") | O34: =IFERROR(O21*100/O33,"") | P34: =SUM(L34:O34) | Q34: =IFERROR(Q21*100/Q33,"") | R34: =IFERROR(R21*100/R33,"") | S34: =IFERROR(S21*100/S33,"") | T34: =IFERROR(T21*100/T33,"") | U34: =SUM(Q34:T34) | V34: =IFERROR(V21*100/V33,"") | W34: =IFERROR(W21*100/W33,"") | X34: =IFERROR(X21*100/X33,"") | Y34: =IFERROR(Y21*100/Y33,"") | Z34: =SUM(V34:Y34) | AA34: =IFERROR(AA21*100/AA33,"") | AB34: =IFERROR(AB21*100/AB33,"") | AC34: =IFERROR(AC21*100/AC33,"") | AD34: =IFERROR(AD21*100/AD33,"") | AE34: =SUM(AA34:AD34) | AF34: =IFERROR(AF21*100/AF33,"") | AG34: =IFERROR(AG21*100/AG33,"") | AH34: =IFERROR(AH21*100/AH33,"") | AI34: =IFERROR(AI21*100/AI33,"") | AJ34: =SUM(AF34:AI34) | AK34: =IFERROR(AK21*100/AK33,"") | AL34: =IFERROR(AL21*100/AL33,"") | AM34: =IFERROR(AM21*100/AM33,"") | AN34: =IFERROR(AN21*100/AN33,"") | AO34: =SUM(AK34:AN34)
A35: BPS | B35: 주당 | C35: 원 | D35: BPS | E35: =IFERROR(E26*100/E33,"") | F35: =E35 | G35: =IFERROR(G26*100/G33,"") | H35: =IFERROR(H26*100/H33,"") | I35: =IFERROR(I26*100/I33,"") | J35: =IFERROR(J26*100/J33,"") | K35: =J35 | L35: =IFERROR(L26*100/L33,"") | N35: =IFERROR(N26*100/N33,"") | P35: =O35 | U35: =T35 | Z35: =Y35 | AC35: =IFERROR(AC26*100/AC33,"") | AD35: =IFERROR(AD26*100/AD33,"") | AE35: =AD35 | AF35: =IFERROR(AF26*100/AF33,"") | AG35: =IFERROR(AG26*100/AG33,"") | AH35: =IFERROR(AH26*100/AH33,"") | AI35: =IFERROR(AI26*100/AI33,"") | AJ35: =AI35 | AK35: =IFERROR(AK26*100/AK33,"") | AL35: =IFERROR(AL26*100/AL33,"") | AM35: =IFERROR(AM26*100/AM33,"") | AN35: =IFERROR(AN26*100/AN33,"") | AO35: =AN35
A36: DPS | B36: 주당 | C36: 원 | D36: DPS(보통주) | E36: 0 | F36: 0 | J36: 0 | K36: =SUM(G36:J36) | O36: 0 | P36: =SUM(L36:O36) | T36: 0 | U36: =SUM(Q36:T36) | Y36: 0 | Z36: =SUM(V36:Y36) | AD36: =변수!AD42 | AE36: =SUM(AA36:AD36) | AI36: =변수!AI42 | AJ36: =SUM(AF36:AI36) | AN36: =변수!AN42 | AO36: =SUM(AK36:AN36)
A37: PER | B37: 주당 | C37: 배 | D37: PER | F37: =E37 | I37: =IFERROR(변수!I18/(E34+G34+H34+I34),"") | K37: =J37 | O37: =IFERROR(변수!O18/(L34+M34+N34+O34),"") | P37: =O37 | Q37: =IFERROR(변수!Q18/(M34+N34+O34+Q34),"") | R37: =IFERROR(변수!R18/(N34+O34+Q34+R34),"") | S37: =IFERROR(변수!S18/(O34+Q34+R34+S34),"") | T37: =IFERROR(변수!T18/(Q34+R34+S34+T34),"") | U37: =T37 | Y37: =IFERROR(변수!Y18/(V34+W34+X34+Y34),"") | Z37: =Y37 | AA37: =IFERROR(변수!AA18/(W34+X34+Y34+AA34),"") | AB37: =IFERROR(변수!AB18/(X34+Y34+AA34+AB34),"") | AC37: =IFERROR(변수!$D$45/(Y34+AA34+AB34+AC34),"") | AD37: =IFERROR(변수!$D$45/(AA34+AB34+AC34+AD34),"") | AE37: =AD37 | AF37: =IFERROR(변수!$D$45/(AB34+AC34+AD34+AF34),"") | AG37: =IFERROR(변수!$D$45/(AC34+AD34+AF34+AG34),"") | AH37: =IFERROR(변수!$D$45/(AD34+AF34+AG34+AH34),"") | AI37: =IFERROR(변수!$D$45/(AF34+AG34+AH34+AI34),"") | AJ37: =AI37 | AK37: =IFERROR(변수!$D$45/(AG34+AH34+AI34+AK34),"") | AL37: =IFERROR(변수!$D$45/(AH34+AI34+AK34+AL34),"") | AM37: =IFERROR(변수!$D$45/(AI34+AK34+AL34+AM34),"") | AN37: =IFERROR(변수!$D$45/(AK34+AL34+AM34+AN34),"") | AO37: =AN37
A38: PBR | B38: 주당 | C38: 배 | D38: PBR | E38: =IFERROR(변수!E18/E35,"") | F38: =E38 | G38: =IFERROR(변수!G18/G35,"") | H38: =IFERROR(변수!H18/H35,"") | I38: =IFERROR(변수!I18/I35,"") | J38: =IFERROR(변수!J18/J35,"") | K38: =J38 | L38: =IFERROR(변수!L18/L35,"") | N38: =IFERROR(변수!N18/N35,"") | P38: =O38 | U38: =T38 | Z38: =Y38 | AE38: =AD38 | AJ38: =AI38 | AO38: =AN38
A39: 매출전사 | B39: 사업부 | C39: 억원 | D39: 매출 전사(부문 미분리) | E39: 21707.87 | G39: 30712.85 | H39: 38346.56 | I39: 39603.24 | J39: 46217.68 | K39: =SUM(G39:J39) | L39: 40410.42 | M39: 45393.62 | N39: 41549.8 | O39: 48545.04 | P39: =SUM(L39:O39) | Q39: 40978.67 | R39: 41504.87 | S39: 33955.69 | T39: 45891.32 | U39: =SUM(Q39:T39) | V39: 37485.74 | W39: 45690.21 | X39: 38803.5 | Y39: 48599.31 | Z39: =SUM(V39:Y39) | AA39: 42611.3 | AB39: 47248.08 | AC39: =IFERROR(AC5,"") | AD39: =IFERROR(AD5,"") | AE39: =SUM(AA39:AD39) | AF39: =IFERROR(AF5,"") | AG39: =IFERROR(AG5,"") | AH39: =IFERROR(AH5,"") | AI39: =IFERROR(AI5,"") | AJ39: =SUM(AF39:AI39) | AK39: =IFERROR(AK5,"") | AL39: =IFERROR(AL5,"") | AM39: =IFERROR(AM5,"") | AN39: =IFERROR(AN5,"") | AO39: =SUM(AK39:AN39)
A40: OP전사 | B40: 사업부 | C40: 억원 | D40: OP 전사(부문 미분리) | E40: 1269.82 | G40: 1921.4 | H40: 3283.37 | I40: 3145.69 | J40: 2717.07 | K40: =SUM(G40:J40) | L40: 3645.74 | M40: 4946.5 | N40: 3113.89 | O40: 2967.04 | P40: =SUM(L40:O40) | Q40: 3580.71 | R40: 3097.9 | S40: 1147.9 | T40: 2349.49 | U40: =SUM(Q40:T40) | V40: 1424.75 | W40: 2711.06 | X40: 1370.59 | Y40: 2120.72 | Z40: =SUM(V40:Y40) | AA40: 2335.14 | AB40: 3142.6 | AC40: =IFERROR(AC9,"") | AD40: =IFERROR(AD9,"") | AE40: =SUM(AA40:AD40) | AF40: =IFERROR(AF9,"") | AG40: =IFERROR(AG9,"") | AH40: =IFERROR(AH9,"") | AI40: =IFERROR(AI9,"") | AJ40: =SUM(AF40:AI40) | AK40: =IFERROR(AK9,"") | AL40: =IFERROR(AL9,"") | AM40: =IFERROR(AM9,"") | AN40: =IFERROR(AN9,"") | AO40: =SUM(AK40:AN40)
B41: 비율(참고)
A42: NPM | C42: % | D42: 지배주주순이익 / 매출액 | E42: =IFERROR(E21/E5,"") | F42: =IFERROR(F21/F5,"") | G42: =IFERROR(G21/G5,"") | H42: =IFERROR(H21/H5,"") | I42: =IFERROR(I21/I5,"") | J42: =IFERROR(J21/J5,"") | K42: =IFERROR(K21/K5,"") | L42: =IFERROR(L21/L5,"") | ... AO42: =IFERROR(AO21/AO5,"")
A43: 매출원가율 | C43: % | D43: 매출원가 / 매출액 | E43: =IFERROR(E6/E5,"") | F43: =IFERROR(F6/F5,"") | G43: =IFERROR(G6/G5,"") | H43: =IFERROR(H6/H5,"") | I43: =IFERROR(I6/I5,"") | J43: =IFERROR(J6/J5,"") | K43: =IFERROR(K6/K5,"") | L43: =IFERROR(L6/L5,"") | ... AO43: =IFERROR(AO6/AO5,"")
A44: 판관비율 | C44: % | D44: 판관비 / 매출액 | E44: =IFERROR(E8/E5,"") | F44: =IFERROR(F8/F5,"") | G44: =IFERROR(G8/G5,"") | H44: =IFERROR(H8/H5,"") | I44: =IFERROR(I8/I5,"") | J44: =IFERROR(J8/J5,"") | K44: =IFERROR(K8/K5,"") | L44: =IFERROR(L8/L5,"") | ... AO44: =IFERROR(AO8/AO5,"")

Sheet 분기
C1: 이름: 분기H — subQ 를 이름으로 VLOOKUP(억원) | E1: 4Q21 | F1: 1Q22 | G1: 2Q22 | H1: 3Q22 | I1: 4Q22 | J1: 1Q23 | K1: 2Q23 | L1: 3Q23 | M1: 4Q23 | N1: 1Q24 | O1: 2Q24 | P1: 3Q24 | Q1: 4Q24 | R1: 1Q25 | S1: 2Q25 | T1: 3Q25 | U1: 4Q25 | V1: 1Q26 | W1: 2Q26 | X1: 3Q26 | Y1: 4Q26 | Z1: 1Q27 | AA1: 2Q27 | AB1: 3Q27 | AC1: 4Q27 | AD1: 1Q28 | AE1: 2Q28 | AF1: 3Q28 | AG1: 4Q28
C2: 종가: | D2: =변수!D45
C3: 기준일: | D3: 20261019 | E3: 1 | F3: 2 | G3: 3 | H3: 4 | I3: 5 | J3: 6 | K3: 7 | L3: 8 | M3: 9 | N3: 10 | O3: 11 | P3: 12 | Q3: 13 | R3: 14 | S3: 15 | T3: 16 | U3: 17 | V3: 18 | W3: 19 | X3: 20 | Y3: 21 | Z3: 22 | AA3: 23 | AB3: 24 | AC3: 25 | AD3: 26 | AE3: 27 | AF3: 28 | AG3: 29
E4: 2021.12 | F4: 2022.03 | G4: 2022.06 | H4: 2022.09 | I4: 2022.12 | J4: 2023.03 | K4: 2023.06 | L4: 2023.09 | M4: 2023.12 | N4: 2024.03 | O4: 2024.06 | P4: 2024.09 | Q4: 2024.12 | R4: 2025.03 | S4: 2025.06 | T4: 2025.09 | U4: 2025.12 | V4: 2026.03 | W4: 2026.06 | X4: 2026.09 | Y4: 2026.12 | Z4: 2027.03 | AA4: 2027.06 | AB4: 2027.09 | AC4: 2027.12 | AD4: 2028.03 | AE4: 2028.06 | AF4: 2028.09 | AG4: 2028.12
A5: 매출액 | D5: 매출액 | E5: =IFERROR(VLOOKUP($A5,subQ,MATCH(E$1,SUBQH,0),0),"") | F5: =IFERROR(VLOOKUP($A5,subQ,MATCH(F$1,SUBQH,0),0),"") | G5: =IFERROR(VLOOKUP($A5,subQ,MATCH(G$1,SUBQH,0),0),"") | H5: =IFERROR(VLOOKUP($A5,subQ,MATCH(H$1,SUBQH,0),0),"") | I5: =IFERROR(VLOOKUP($A5,subQ,MATCH(I$1,SUBQH,0),0),"") | J5: =IFERROR(VLOOKUP($A5,subQ,MATCH(J$1,SUBQH,0),0),"") | K5: =IFERROR(VLOOKUP($A5,subQ,MATCH(K$1,SUBQH,0),0),"") | L5: =IFERROR(VLOOKUP($A5,subQ,MATCH(L$1,SUBQH,0),0),"") | ... AG5: =IFERROR(VLOOKUP($A5,subQ,MATCH(AG$1,SUBQH,0),0),"")
A6: 매출원가 | D6: 매출원가 | E6: =IFERROR(VLOOKUP($A6,subQ,MATCH(E$1,SUBQH,0),0),"") | F6: =IFERROR(VLOOKUP($A6,subQ,MATCH(F$1,SUBQH,0),0),"") | G6: =IFERROR(VLOOKUP($A6,subQ,MATCH(G$1,SUBQH,0),0),"") | H6: =IFERROR(VLOOKUP($A6,subQ,MATCH(H$1,SUBQH,0),0),"") | I6: =IFERROR(VLOOKUP($A6,subQ,MATCH(I$1,SUBQH,0),0),"") | J6: =IFERROR(VLOOKUP($A6,subQ,MATCH(J$1,SUBQH,0),0),"") | K6: =IFERROR(VLOOKUP($A6,subQ,MATCH(K$1,SUBQH,0),0),"") | L6: =IFERROR(VLOOKUP($A6,subQ,MATCH(L$1,SUBQH,0),0),"") | ... AG6: =IFERROR(VLOOKUP($A6,subQ,MATCH(AG$1,SUBQH,0),0),"")
A7: 매출총이익 | D7: 매출총이익 | E7: =IFERROR(VLOOKUP($A7,subQ,MATCH(E$1,SUBQH,0),0),"") | F7: =IFERROR(VLOOKUP($A7,subQ,MATCH(F$1,SUBQH,0),0),"") | G7: =IFERROR(VLOOKUP($A7,subQ,MATCH(G$1,SUBQH,0),0),"") | H7: =IFERROR(VLOOKUP($A7,subQ,MATCH(H$1,SUBQH,0),0),"") | I7: =IFERROR(VLOOKUP($A7,subQ,MATCH(I$1,SUBQH,0),0),"") | J7: =IFERROR(VLOOKUP($A7,subQ,MATCH(J$1,SUBQH,0),0),"") | K7: =IFERROR(VLOOKUP($A7,subQ,MATCH(K$1,SUBQH,0),0),"") | L7: =IFERROR(VLOOKUP($A7,subQ,MATCH(L$1,SUBQH,0),0),"") | ... AG7: =IFERROR(VLOOKUP($A7,subQ,MATCH(AG$1,SUBQH,0),0),"")
A8: 판관비 | D8: 판매비와관리비 | E8: =IFERROR(VLOOKUP($A8,subQ,MATCH(E$1,SUBQH,0),0),"") | F8: =IFERROR(VLOOKUP($A8,subQ,MATCH(F$1,SUBQH,0),0),"") | G8: =IFERROR(VLOOKUP($A8,subQ,MATCH(G$1,SUBQH,0),0),"") | H8: =IFERROR(VLOOKUP($A8,subQ,MATCH(H$1,SUBQH,0),0),"") | I8: =IFERROR(VLOOKUP($A8,subQ,MATCH(I$1,SUBQH,0),0),"") | J8: =IFERROR(VLOOKUP($A8,subQ,MATCH(J$1,SUBQH,0),0),"") | K8: =IFERROR(VLOOKUP($A8,subQ,MATCH(K$1,SUBQH,0),0),"") | L8: =IFERROR(VLOOKUP($A8,subQ,MATCH(L$1,SUBQH,0),0),"") | ... AG8: =IFERROR(VLOOKUP($A8,subQ,MATCH(AG$1,SUBQH,0),0),"")
A9: 영업이익 | D9: 영업이익 | E9: =IFERROR(VLOOKUP($A9,subQ,MATCH(E$1,SUBQH,0),0),"") | F9: =IFERROR(VLOOKUP($A9,subQ,MATCH(F$1,SUBQH,0),0),"") | G9: =IFERROR(VLOOKUP($A9,subQ,MATCH(G$1,SUBQH,0),0),"") | H9: =IFERROR(VLOOKUP($A9,subQ,MATCH(H$1,SUBQH,0),0),"") | I9: =IFERROR(VLOOKUP($A9,subQ,MATCH(I$1,SUBQH,0),0),"") | J9: =IFERROR(VLOOKUP($A9,subQ,MATCH(J$1,SUBQH,0),0),"") | K9: =IFERROR(VLOOKUP($A9,subQ,MATCH(K$1,SUBQH,0),0),"") | L9: =IFERROR(VLOOKUP($A9,subQ,MATCH(L$1,SUBQH,0),0),"") | ... AG9: =IFERROR(VLOOKUP($A9,subQ,MATCH(AG$1,SUBQH,0),0),"")
A10: OPM | D10: 영업이익률 | E10: =IFERROR(VLOOKUP($A10,subQ,MATCH(E$1,SUBQH,0),0),"") | F10: =IFERROR(VLOOKUP($A10,subQ,MATCH(F$1,SUBQH,0),0),"") | G10: =IFERROR(VLOOKUP($A10,subQ,MATCH(G$1,SUBQH,0),0),"") | H10: =IFERROR(VLOOKUP($A10,subQ,MATCH(H$1,SUBQH,0),0),"") | I10: =IFERROR(VLOOKUP($A10,subQ,MATCH(I$1,SUBQH,0),0),"") | J10: =IFERROR(VLOOKUP($A10,subQ,MATCH(J$1,SUBQH,0),0),"") | K10: =IFERROR(VLOOKUP($A10,subQ,MATCH(K$1,SUBQH,0),0),"") | L10: =IFERROR(VLOOKUP($A10,subQ,MATCH(L$1,SUBQH,0),0),"") | ... AG10: =IFERROR(VLOOKUP($A10,subQ,MATCH(AG$1,SUBQH,0),0),"")
A11: 금융손익 | D11: 금융손익(이자·환 포함) | E11: =IFERROR(VLOOKUP($A11,subQ,MATCH(E$1,SUBQH,0),0),"") | F11: =IFERROR(VLOOKUP($A11,subQ,MATCH(F$1,SUBQH,0),0),"") | G11: =IFERROR(VLOOKUP($A11,subQ,MATCH(G$1,SUBQH,0),0),"") | H11: =IFERROR(VLOOKUP($A11,subQ,MATCH(H$1,SUBQH,0),0),"") | I11: =IFERROR(VLOOKUP($A11,subQ,MATCH(I$1,SUBQH,0),0),"") | J11: =IFERROR(VLOOKUP($A11,subQ,MATCH(J$1,SUBQH,0),0),"") | K11: =IFERROR(VLOOKUP($A11,subQ,MATCH(K$1,SUBQH,0),0),"") | L11: =IFERROR(VLOOKUP($A11,subQ,MATCH(L$1,SUBQH,0),0),"") | ... AG11: =IFERROR(VLOOKUP($A11,subQ,MATCH(AG$1,SUBQH,0),0),"")
A12: 이자손익 | D12: 이자손익(이자수익 − 이자비용) | E12: =IFERROR(VLOOKUP($A12,subQ,MATCH(E$1,SUBQH,0),0),"") | F12: =IFERROR(VLOOKUP($A12,subQ,MATCH(F$1,SUBQH,0),0),"") | G12: =IFERROR(VLOOKUP($A12,subQ,MATCH(G$1,SUBQH,0),0),"") | H12: =IFERROR(VLOOKUP($A12,subQ,MATCH(H$1,SUBQH,0),0),"") | I12: =IFERROR(VLOOKUP($A12,subQ,MATCH(I$1,SUBQH,0),0),"") | J12: =IFERROR(VLOOKUP($A12,subQ,MATCH(J$1,SUBQH,0),0),"") | K12: =IFERROR(VLOOKUP($A12,subQ,MATCH(K$1,SUBQH,0),0),"") | L12: =IFERROR(VLOOKUP($A12,subQ,MATCH(L$1,SUBQH,0),0),"") | ... AG12: =IFERROR(VLOOKUP($A12,subQ,MATCH(AG$1,SUBQH,0),0),"")
A13: 외환손익 | D13: 외환손익(실적만; 추정 환효과는 환관련손익) | E13: =IFERROR(VLOOKUP($A13,subQ,MATCH(E$1,SUBQH,0),0),"") | F13: =IFERROR(VLOOKUP($A13,subQ,MATCH(F$1,SUBQH,0),0),"") | G13: =IFERROR(VLOOKUP($A13,subQ,MATCH(G$1,SUBQH,0),0),"") | H13: =IFERROR(VLOOKUP($A13,subQ,MATCH(H$1,SUBQH,0),0),"") | I13: =IFERROR(VLOOKUP($A13,subQ,MATCH(I$1,SUBQH,0),0),"") | J13: =IFERROR(VLOOKUP($A13,subQ,MATCH(J$1,SUBQH,0),0),"") | K13: =IFERROR(VLOOKUP($A13,subQ,MATCH(K$1,SUBQH,0),0),"") | L13: =IFERROR(VLOOKUP($A13,subQ,MATCH(L$1,SUBQH,0),0),"") | ... AG13: =IFERROR(VLOOKUP($A13,subQ,MATCH(AG$1,SUBQH,0),0),"")
A14: 파생상품손익 | D14: 파생상품손익 | E14: =IFERROR(VLOOKUP($A14,subQ,MATCH(E$1,SUBQH,0),0),"") | F14: =IFERROR(VLOOKUP($A14,subQ,MATCH(F$1,SUBQH,0),0),"") | G14: =IFERROR(VLOOKUP($A14,subQ,MATCH(G$1,SUBQH,0),0),"") | H14: =IFERROR(VLOOKUP($A14,subQ,MATCH(H$1,SUBQH,0),0),"") | I14: =IFERROR(VLOOKUP($A14,subQ,MATCH(I$1,SUBQH,0),0),"") | J14: =IFERROR(VLOOKUP($A14,subQ,MATCH(J$1,SUBQH,0),0),"") | K14: =IFERROR(VLOOKUP($A14,subQ,MATCH(K$1,SUBQH,0),0),"") | L14: =IFERROR(VLOOKUP($A14,subQ,MATCH(L$1,SUBQH,0),0),"") | ... AG14: =IFERROR(VLOOKUP($A14,subQ,MATCH(AG$1,SUBQH,0),0),"")
A15: 기타금융손익 | D15: 기타금융손익(금융손익 잔차) | E15: =IFERROR(VLOOKUP($A15,subQ,MATCH(E$1,SUBQH,0),0),"") | F15: =IFERROR(VLOOKUP($A15,subQ,MATCH(F$1,SUBQH,0),0),"") | G15: =IFERROR(VLOOKUP($A15,subQ,MATCH(G$1,SUBQH,0),0),"") | H15: =IFERROR(VLOOKUP($A15,subQ,MATCH(H$1,SUBQH,0),0),"") | I15: =IFERROR(VLOOKUP($A15,subQ,MATCH(I$1,SUBQH,0),0),"") | J15: =IFERROR(VLOOKUP($A15,subQ,MATCH(J$1,SUBQH,0),0),"") | K15: =IFERROR(VLOOKUP($A15,subQ,MATCH(K$1,SUBQH,0),0),"") | L15: =IFERROR(VLOOKUP($A15,subQ,MATCH(L$1,SUBQH,0),0),"") | ... AG15: =IFERROR(VLOOKUP($A15,subQ,MATCH(AG$1,SUBQH,0),0),"")
A16: 기타영업외손익 | D16: 기타영업외손익 | E16: =IFERROR(VLOOKUP($A16,subQ,MATCH(E$1,SUBQH,0),0),"") | F16: =IFERROR(VLOOKUP($A16,subQ,MATCH(F$1,SUBQH,0),0),"") | G16: =IFERROR(VLOOKUP($A16,subQ,MATCH(G$1,SUBQH,0),0),"") | H16: =IFERROR(VLOOKUP($A16,subQ,MATCH(H$1,SUBQH,0),0),"") | I16: =IFERROR(VLOOKUP($A16,subQ,MATCH(I$1,SUBQH,0),0),"") | J16: =IFERROR(VLOOKUP($A16,subQ,MATCH(J$1,SUBQH,0),0),"") | K16: =IFERROR(VLOOKUP($A16,subQ,MATCH(K$1,SUBQH,0),0),"") | L16: =IFERROR(VLOOKUP($A16,subQ,MATCH(L$1,SUBQH,0),0),"") | ... AG16: =IFERROR(VLOOKUP($A16,subQ,MATCH(AG$1,SUBQH,0),0),"")
... A41: NPM | D41: NPM | E41: =IFERROR(VLOOKUP($A41,subQ,MATCH(E$1,SUBQH,0),0),"") | F41: =IFERROR(VLOOKUP($A41,subQ,MATCH(F$1,SUBQH,0),0),"") | G41: =IFERROR(VLOOKUP($A41,subQ,MATCH(G$1,SUBQH,0),0),"") | H41: =IFERROR(VLOOKUP($A41,subQ,MATCH(H$1,SUBQH,0),0),"") | I41: =IFERROR(VLOOKUP($A41,subQ,MATCH(I$1,SUBQH,0),0),"") | J41: =IFERROR(VLOOKUP($A41,subQ,MATCH(J$1,SUBQH,0),0),"") | K41: =IFERROR(VLOOKUP($A41,subQ,MATCH(K$1,SUBQH,0),0),"") | L41: =IFERROR(VLOOKUP($A41,subQ,MATCH(L$1,SUBQH,0),0),"") | ... AG41: =IFERROR(VLOOKUP($A41,subQ,MATCH(AG$1,SUBQH,0),0),"")
A42: 매출액 YoY | D42: 매출액 YoY | I42: =IFERROR(I5/E5-1,"") | J42: =IFERROR(J5/F5-1,"") | K42: =IFERROR(K5/G5-1,"") | L42: =IFERROR(L5/H5-1,"") | M42: =IFERROR(M5/I5-1,"") | N42: =IFERROR(N5/J5-1,"") | O42: =IFERROR(O5/K5-1,"") | P42: =IFERROR(P5/L5-1,"") | ... AG42: =IFERROR(AG5/AC5-1,"")
A43: 영업이익 YoY | D43: 영업이익 YoY | I43: =IFERROR(I9/E9-1,"") | J43: =IFERROR(J9/F9-1,"") | K43: =IFERROR(K9/G9-1,"") | L43: =IFERROR(L9/H9-1,"") | M43: =IFERROR(M9/I9-1,"") | N43: =IFERROR(N9/J9-1,"") | O43: =IFERROR(O9/K9-1,"") | P43: =IFERROR(P9/L9-1,"") | ... AG43: =IFERROR(AG9/AC9-1,"")
A44: 지배주주순이익 YoY | D44: 지배주주순이익 YoY | I44: =IFERROR(I21/E21-1,"") | J44: =IFERROR(J21/F21-1,"") | K44: =IFERROR(K21/G21-1,"") | L44: =IFERROR(L21/H21-1,"") | M44: =IFERROR(M21/I21-1,"") | N44: =IFERROR(N21/J21-1,"") | O44: =IFERROR(O21/K21-1,"") | P44: =IFERROR(P21/L21-1,"") | ... AG44: =IFERROR(AG21/AC21-1,"")

Sheet 연간예상
C1: 이름: 연간예상H — subQ 를 이름으로 VLOOKUP(억원) | E1: 2021 | F1: 2022 | G1: 2023 | H1: 2024 | I1: 2025 | J1: 2026 | K1: 2027 | L1: 2028
C2: 종가: | D2: =변수!D45
C3: 기준일: | D3: 20261019 | E3: 1 | F3: 2 | G3: 3 | H3: 4 | I3: 5 | J3: 6 | K3: 7 | L3: 8
E4: 2021.12A | F4: 2022.12A | G4: 2023.12A | H4: 2024.12A | I4: 2025.12A | J4: 2026.12A | K4: 2027.12A | L4: 2028.12A
A5: 매출액 | D5: 매출액 | E5: =IFERROR(VLOOKUP($A5,subQ,MATCH(E$1,SUBQH,0),0),"") | F5: =IFERROR(VLOOKUP($A5,subQ,MATCH(F$1,SUBQH,0),0),"") | G5: =IFERROR(VLOOKUP($A5,subQ,MATCH(G$1,SUBQH,0),0),"") | H5: =IFERROR(VLOOKUP($A5,subQ,MATCH(H$1,SUBQH,0),0),"") | I5: =IFERROR(VLOOKUP($A5,subQ,MATCH(I$1,SUBQH,0),0),"") | J5: =IFERROR(VLOOKUP($A5,subQ,MATCH(J$1,SUBQH,0),0),"") | K5: =IFERROR(VLOOKUP($A5,subQ,MATCH(K$1,SUBQH,0),0),"") | L5: =IFERROR(VLOOKUP($A5,subQ,MATCH(L$1,SUBQH,0),0),"")
A6: 매출원가 | D6: 매출원가 | E6: =IFERROR(VLOOKUP($A6,subQ,MATCH(E$1,SUBQH,0),0),"") | F6: =IFERROR(VLOOKUP($A6,subQ,MATCH(F$1,SUBQH,0),0),"") | G6: =IFERROR(VLOOKUP($A6,subQ,MATCH(G$1,SUBQH,0),0),"") | H6: =IFERROR(VLOOKUP($A6,subQ,MATCH(H$1,SUBQH,0),0),"") | I6: =IFERROR(VLOOKUP($A6,subQ,MATCH(I$1,SUBQH,0),0),"") | J6: =IFERROR(VLOOKUP($A6,subQ,MATCH(J$1,SUBQH,0),0),"") | K6: =IFERROR(VLOOKUP($A6,subQ,MATCH(K$1,SUBQH,0),0),"") | L6: =IFERROR(VLOOKUP($A6,subQ,MATCH(L$1,SUBQH,0),0),"")
A7: 매출총이익 | D7: 매출총이익 | E7: =IFERROR(VLOOKUP($A7,subQ,MATCH(E$1,SUBQH,0),0),"") | F7: =IFERROR(VLOOKUP($A7,subQ,MATCH(F$1,SUBQH,0),0),"") | G7: =IFERROR(VLOOKUP($A7,subQ,MATCH(G$1,SUBQH,0),0),"") | H7: =IFERROR(VLOOKUP($A7,subQ,MATCH(H$1,SUBQH,0),0),"") | I7: =IFERROR(VLOOKUP($A7,subQ,MATCH(I$1,SUBQH,0),0),"") | J7: =IFERROR(VLOOKUP($A7,subQ,MATCH(J$1,SUBQH,0),0),"") | K7: =IFERROR(VLOOKUP($A7,subQ,MATCH(K$1,SUBQH,0),0),"") | L7: =IFERROR(VLOOKUP($A7,subQ,MATCH(L$1,SUBQH,0),0),"")
A8: 판관비 | D8: 판매비와관리비 | E8: =IFERROR(VLOOKUP($A8,subQ,MATCH(E$1,SUBQH,0),0),"") | F8: =IFERROR(VLOOKUP($A8,subQ,MATCH(F$1,SUBQH,0),0),"") | G8: =IFERROR(VLOOKUP($A8,subQ,MATCH(G$1,SUBQH,0),0),"") | H8: =IFERROR(VLOOKUP($A8,subQ,MATCH(H$1,SUBQH,0),0),"") | I8: =IFERROR(VLOOKUP($A8,subQ,MATCH(I$1,SUBQH,0),0),"") | J8: =IFERROR(VLOOKUP($A8,subQ,MATCH(J$1,SUBQH,0),0),"") | K8: =IFERROR(VLOOKUP($A8,subQ,MATCH(K$1,SUBQH,0),0),"") | L8: =IFERROR(VLOOKUP($A8,subQ,MATCH(L$1,SUBQH,0),0),"")
A9: 영업이익 | D9: 영업이익 | E9: =IFERROR(VLOOKUP($A9,subQ,MATCH(E$1,SUBQH,0),0),"") | F9: =IFERROR(VLOOKUP($A9,subQ,MATCH(F$1,SUBQH,0),0),"") | G9: =IFERROR(VLOOKUP($A9,subQ,MATCH(G$1,SUBQH,0),0),"") | H9: =IFERROR(VLOOKUP($A9,subQ,MATCH(H$1,SUBQH,0),0),"") | I9: =IFERROR(VLOOKUP($A9,subQ,MATCH(I$1,SUBQH,0),0),"") | J9: =IFERROR(VLOOKUP($A9,subQ,MATCH(J$1,SUBQH,0),0),"") | K9: =IFERROR(VLOOKUP($A9,subQ,MATCH(K$1,SUBQH,0),0),"") | L9: =IFERROR(VLOOKUP($A9,subQ,MATCH(L$1,SUBQH,0),0),"")
A10: OPM | D10: 영업이익률 | E10: =IFERROR(VLOOKUP($A10,subQ,MATCH(E$1,SUBQH,0),0),"") | F10: =IFERROR(VLOOKUP($A10,subQ,MATCH(F$1,SUBQH,0),0),"") | G10: =IFERROR(VLOOKUP($A10,subQ,MATCH(G$1,SUBQH,0),0),"") | H10: =IFERROR(VLOOKUP($A10,subQ,MATCH(H$1,SUBQH,0),0),"") | I10: =IFERROR(VLOOKUP($A10,subQ,MATCH(I$1,SUBQH,0),0),"") | J10: =IFERROR(VLOOKUP($A10,subQ,MATCH(J$1,SUBQH,0),0),"") | K10: =IFERROR(VLOOKUP($A10,subQ,MATCH(K$1,SUBQH,0),0),"") | L10: =IFERROR(VLOOKUP($A10,subQ,MATCH(L$1,SUBQH,0),0),"")
A11: 금융손익 | D11: 금융손익(이자·환 포함) | E11: =IFERROR(VLOOKUP($A11,subQ,MATCH(E$1,SUBQH,0),0),"") | F11: =IFERROR(VLOOKUP($A11,subQ,MATCH(F$1,SUBQH,0),0),"") | G11: =IFERROR(VLOOKUP($A11,subQ,MATCH(G$1,SUBQH,0),0),"") | H11: =IFERROR(VLOOKUP($A11,subQ,MATCH(H$1,SUBQH,0),0),"") | I11: =IFERROR(VLOOKUP($A11,subQ,MATCH(I$1,SUBQH,0),0),"") | J11: =IFERROR(VLOOKUP($A11,subQ,MATCH(J$1,SUBQH,0),0),"") | K11: =IFERROR(VLOOKUP($A11,subQ,MATCH(K$1,SUBQH,0),0),"") | L11: =IFERROR(VLOOKUP($A11,subQ,MATCH(L$1,SUBQH,0),0),"")
A12: 이자손익 | D12: 이자손익(이자수익 − 이자비용) | E12: =IFERROR(VLOOKUP($A12,subQ,MATCH(E$1,SUBQH,0),0),"") | F12: =IFERROR(VLOOKUP($A12,subQ,MATCH(F$1,SUBQH,0),0),"") | G12: =IFERROR(VLOOKUP($A12,subQ,MATCH(G$1,SUBQH,0),0),"") | H12: =IFERROR(VLOOKUP($A12,subQ,MATCH(H$1,SUBQH,0),0),"") | I12: =IFERROR(VLOOKUP($A12,subQ,MATCH(I$1,SUBQH,0),0),"") | J12: =IFERROR(VLOOKUP($A12,subQ,MATCH(J$1,SUBQH,0),0),"") | K12: =IFERROR(VLOOKUP($A12,subQ,MATCH(K$1,SUBQH,0),0),"") | L12: =IFERROR(VLOOKUP($A12,subQ,MATCH(L$1,SUBQH,0),0),"")
A13: 외환손익 | D13: 외환손익(실적만; 추정 환효과는 환관련손익) | E13: =IFERROR(VLOOKUP($A13,subQ,MATCH(E$1,SUBQH,0),0),"") | F13: =IFERROR(VLOOKUP($A13,subQ,MATCH(F$1,SUBQH,0),0),"") | G13: =IFERROR(VLOOKUP($A13,subQ,MATCH(G$1,SUBQH,0),0),"") | H13: =IFERROR(VLOOKUP($A13,subQ,MATCH(H$1,SUBQH,0),0),"") | I13: =IFERROR(VLOOKUP($A13,subQ,MATCH(I$1,SUBQH,0),0),"") | J13: =IFERROR(VLOOKUP($A13,subQ,MATCH(J$1,SUBQH,0),0),"") | K13: =IFERROR(VLOOKUP($A13,subQ,MATCH(K$1,SUBQH,0),0),"") | L13: =IFERROR(VLOOKUP($A13,subQ,MATCH(L$1,SUBQH,0),0),"")
A14: 파생상품손익 | D14: 파생상품손익 | E14: =IFERROR(VLOOKUP($A14,subQ,MATCH(E$1,SUBQH,0),0),"") | F14: =IFERROR(VLOOKUP($A14,subQ,MATCH(F$1,SUBQH,0),0),"") | G14: =IFERROR(VLOOKUP($A14,subQ,MATCH(G$1,SUBQH,0),0),"") | H14: =IFERROR(VLOOKUP($A14,subQ,MATCH(H$1,SUBQH,0),0),"") | I14: =IFERROR(VLOOKUP($A14,subQ,MATCH(I$1,SUBQH,0),0),"") | J14: =IFERROR(VLOOKUP($A14,subQ,MATCH(J$1,SUBQH,0),0),"") | K14: =IFERROR(VLOOKUP($A14,subQ,MATCH(K$1,SUBQH,0),0),"") | L14: =IFERROR(VLOOKUP($A14,subQ,MATCH(L$1,SUBQH,0),0),"")
A15: 기타금융손익 | D15: 기타금융손익(금융손익 잔차) | E15: =IFERROR(VLOOKUP($A15,subQ,MATCH(E$1,SUBQH,0),0),"") | F15: =IFERROR(VLOOKUP($A15,subQ,MATCH(F$1,SUBQH,0),0),"") | G15: =IFERROR(VLOOKUP($A15,subQ,MATCH(G$1,SUBQH,0),0),"") | H15: =IFERROR(VLOOKUP($A15,subQ,MATCH(H$1,SUBQH,0),0),"") | I15: =IFERROR(VLOOKUP($A15,subQ,MATCH(I$1,SUBQH,0),0),"") | J15: =IFERROR(VLOOKUP($A15,subQ,MATCH(J$1,SUBQH,0),0),"") | K15: =IFERROR(VLOOKUP($A15,subQ,MATCH(K$1,SUBQH,0),0),"") | L15: =IFERROR(VLOOKUP($A15,subQ,MATCH(L$1,SUBQH,0),0),"")
A16: 기타영업외손익 | D16: 기타영업외손익 | E16: =IFERROR(VLOOKUP($A16,subQ,MATCH(E$1,SUBQH,0),0),"") | F16: =IFERROR(VLOOKUP($A16,subQ,MATCH(F$1,SUBQH,0),0),"") | G16: =IFERROR(VLOOKUP($A16,subQ,MATCH(G$1,SUBQH,0),0),"") | H16: =IFERROR(VLOOKUP($A16,subQ,MATCH(H$1,SUBQH,0),0),"") | I16: =IFERROR(VLOOKUP($A16,subQ,MATCH(I$1,SUBQH,0),0),"") | J16: =IFERROR(VLOOKUP($A16,subQ,MATCH(J$1,SUBQH,0),0),"") | K16: =IFERROR(VLOOKUP($A16,subQ,MATCH(K$1,SUBQH,0),0),"") | L16: =IFERROR(VLOOKUP($A16,subQ,MATCH(L$1,SUBQH,0),0),"")
... A41: NPM | D41: NPM | E41: =IFERROR(VLOOKUP($A41,subQ,MATCH(E$1,SUBQH,0),0),"") | F41: =IFERROR(VLOOKUP($A41,subQ,MATCH(F$1,SUBQH,0),0),"") | G41: =IFERROR(VLOOKUP($A41,subQ,MATCH(G$1,SUBQH,0),0),"") | H41: =IFERROR(VLOOKUP($A41,subQ,MATCH(H$1,SUBQH,0),0),"") | I41: =IFERROR(VLOOKUP($A41,subQ,MATCH(I$1,SUBQH,0),0),"") | J41: =IFERROR(VLOOKUP($A41,subQ,MATCH(J$1,SUBQH,0),0),"") | K41: =IFERROR(VLOOKUP($A41,subQ,MATCH(K$1,SUBQH,0),0),"") | L41: =IFERROR(VLOOKUP($A41,subQ,MATCH(L$1,SUBQH,0),0),"")
A42: 매출액 YoY | D42: 매출액 YoY | F42: =IFERROR(F5/E5-1,"") | G42: =IFERROR(G5/F5-1,"") | H42: =IFERROR(H5/G5-1,"") | I42: =IFERROR(I5/H5-1,"") | J42: =IFERROR(J5/I5-1,"") | K42: =IFERROR(K5/J5-1,"") | L42: =IFERROR(L5/K5-1,"")
A43: 영업이익 YoY | D43: 영업이익 YoY | F43: =IFERROR(F9/E9-1,"") | G43: =IFERROR(G9/F9-1,"") | H43: =IFERROR(H9/G9-1,"") | I43: =IFERROR(I9/H9-1,"") | J43: =IFERROR(J9/I9-1,"") | K43: =IFERROR(K9/J9-1,"") | L43: =IFERROR(L9/K9-1,"")
A44: 지배주주순이익 YoY | D44: 지배주주순이익 YoY | F44: =IFERROR(F21/E21-1,"") | G44: =IFERROR(G21/F21-1,"") | H44: =IFERROR(H21/G21-1,"") | I44: =IFERROR(I21/H21-1,"") | J44: =IFERROR(J21/I21-1,"") | K44: =IFERROR(K21/J21-1,"") | L44: =IFERROR(L21/K21-1,"")

Sheet TP
B1: 종가 | C1: =변수!D45
B2: 기준일 | C2: =변수!D46
B3: 모델 산출값 — 목표주가·추천 아님. 밴드·COE 는 변수 시트 3절의 가정
C5: FY | D5: 2025 | E5: 2026 | F5: 2027 | G5: 2028
D6: A | E6: E | F6: E | G6: E
C7: EPS(원) | D7: =IFERROR(VLOOKUP("EPS",subQ,MATCH(D$5,SUBQH,0),0),"") | E7: =IFERROR(VLOOKUP("EPS",subQ,MATCH(E$5,SUBQH,0),0),"") | F7: =IFERROR(VLOOKUP("EPS",subQ,MATCH(F$5,SUBQH,0),0),"") | G7: =IFERROR(VLOOKUP("EPS",subQ,MATCH(G$5,SUBQH,0),0),"")
C8: BPS(원) | D8: =IFERROR(VLOOKUP("BPS",subQ,MATCH(D$5,SUBQH,0),0),"") | E8: =IFERROR(VLOOKUP("BPS",subQ,MATCH(E$5,SUBQH,0),0),"") | F8: =IFERROR(VLOOKUP("BPS",subQ,MATCH(F$5,SUBQH,0),0),"") | G8: =IFERROR(VLOOKUP("BPS",subQ,MATCH(G$5,SUBQH,0),0),"")
C9: 지배주주순이익(억원) | D9: =IFERROR(VLOOKUP("지배주주순이익",subQ,MATCH(D$5,SUBQH,0),0),"") | E9: =IFERROR(VLOOKUP("지배주주순이익",subQ,MATCH(E$5,SUBQH,0),0),"") | F9: =IFERROR(VLOOKUP("지배주주순이익",subQ,MATCH(F$5,SUBQH,0),0),"") | G9: =IFERROR(VLOOKUP("지배주주순이익",subQ,MATCH(G$5,SUBQH,0),0),"")
C10: 영업이익(억원) | D10: =IFERROR(VLOOKUP("영업이익",subQ,MATCH(D$5,SUBQH,0),0),"") | E10: =IFERROR(VLOOKUP("영업이익",subQ,MATCH(E$5,SUBQH,0),0),"") | F10: =IFERROR(VLOOKUP("영업이익",subQ,MATCH(F$5,SUBQH,0),0),"") | G10: =IFERROR(VLOOKUP("영업이익",subQ,MATCH(G$5,SUBQH,0),0),"")
C11: ROE(EPS/기초BPS) | E11: =IFERROR(E7/D8,"") | F11: =IFERROR(F7/E8,"") | G11: =IFERROR(G7/F8,"")
B13: PER
C14: 12M fwd EPS | D14: =IFERROR(E7*변수!D51+F7*(1-변수!D51),"")
C15: 적정가치 @PER_lo | D15: =변수!D48 | E15: =IFERROR(ROUND($D$14*D15,-2),"") | F15: =IFERROR(E15/$C$1-1,"") | G15: 배 · 원 · 종가 대비
C16: 적정가치 @PER_mid | D16: =변수!D49 | E16: =IFERROR(ROUND($D$14*D16,-2),"") | F16: =IFERROR(E16/$C$1-1,"") | G16: 배 · 원 · 종가 대비
C17: 적정가치 @PER_hi | D17: =변수!D50 | E17: =IFERROR(ROUND($D$14*D17,-2),"") | F17: =IFERROR(E17/$C$1-1,"") | G17: 배 · 원 · 종가 대비
C18: 현재 PER(종가/12M fwd EPS) | D18: =IFERROR($C$1/$D$14,"")
B20: PBR
C21: 최근 BPS(마지막 실적 분기) | D21: =IFERROR(VLOOKUP("BPS",subQ,MATCH("2Q26",SUBQH,0),0),"")
C22: ROE fwd(12M fwd EPS / BPS) | D22: =IFERROR($D$14/$D$21,"")
C23: COE | D23: =변수!D47
C24: 적정 PBR = ROE/COE | D24: =IFERROR(D22/D23,"")
C25: 적정가치(PBR) = BPS × 적정PBR | D25: =IFERROR(ROUND(D21*D24,-2),"") | E25: =IFERROR(D25/$C$1-1,"")
C26: 현재 PBR(종가/BPS) | D26: =IFERROR($C$1/D21,"")
B28: 모델 json valuation(참고)
C29: eps_fwd12m | D29: 343.3
C30: bps_latest
C31: per_now | D31: 194
C32: pbr_now
C33: roe_fwd
C34: fair_pbr
C35: fair_value_pbr
C36: ev_ebitda
C37: note | D37: 모델 산출값 — 목표주가·추천 아님

Sheet 외화
C1: 이름: 외화QH — 환율 QoQ · 외화 순노출 × Δ기말환율 | E1: 4Q21 | F1: 1Q22 | G1: 2Q22 | H1: 3Q22 | I1: 4Q22 | J1: 1Q23 | K1: 2Q23 | L1: 3Q23 | M1: 4Q23 | N1: 1Q24 | O1: 2Q24 | P1: 3Q24 | Q1: 4Q24 | R1: 1Q25 | S1: 2Q25 | T1: 3Q25 | U1: 4Q25 | V1: 1Q26 | W1: 2Q26 | X1: 3Q26 | Y1: 4Q26 | Z1: 1Q27 | AA1: 2Q27 | AB1: 3Q27 | AC1: 4Q27 | AD1: 1Q28 | AE1: 2Q28 | AF1: 3Q28 | AG1: 4Q28
E3: 1 | F3: 2 | G3: 3 | H3: 4 | I3: 5 | J3: 6 | K3: 7 | L3: 8 | M3: 9 | N3: 10 | O3: 11 | P3: 12 | Q3: 13 | R3: 14 | S3: 15 | T3: 16 | U3: 17 | V3: 18 | W3: 19 | X3: 20 | Y3: 21 | Z3: 22 | AA3: 23 | AB3: 24 | AC3: 25 | AD3: 26 | AE3: 27 | AF3: 28 | AG3: 29
E4: 2021.12 | F4: 2022.03 | G4: 2022.06 | H4: 2022.09 | I4: 2022.12 | J4: 2023.03 | K4: 2023.06 | L4: 2023.09 | M4: 2023.12 | N4: 2024.03 | O4: 2024.06 | P4: 2024.09 | Q4: 2024.12 | R4: 2025.03 | S4: 2025.06 | T4: 2025.09 | U4: 2025.12 | V4: 2026.03 | W4: 2026.06 | X4: 2026.09 | Y4: 2026.12 | Z4: 2027.03 | AA4: 2027.06 | AB4: 2027.09 | AC4: 2027.12 | AD4: 2028.03 | AE4: 2028.06 | AF4: 2028.09 | AG4: 2028.12
D5: 원/달러(평균) | E5: =IFERROR(VLOOKUP($D5,환율,MATCH(E$1,변수H,0),0),"") | F5: =IFERROR(VLOOKUP($D5,환율,MATCH(F$1,변수H,0),0),"") | G5: =IFERROR(VLOOKUP($D5,환율,MATCH(G$1,변수H,0),0),"") | H5: =IFERROR(VLOOKUP($D5,환율,MATCH(H$1,변수H,0),0),"") | I5: =IFERROR(VLOOKUP($D5,환율,MATCH(I$1,변수H,0),0),"") | J5: =IFERROR(VLOOKUP($D5,환율,MATCH(J$1,변수H,0),0),"") | K5: =IFERROR(VLOOKUP($D5,환율,MATCH(K$1,변수H,0),0),"") | L5: =IFERROR(VLOOKUP($D5,환율,MATCH(L$1,변수H,0),0),"") | ... AG5: =IFERROR(VLOOKUP($D5,환율,MATCH(AG$1,변수H,0),0),"")
A6: 원/달러(평균) QoQ | F6: =IFERROR(F5/E5-1,"") | G6: =IFERROR(G5/F5-1,"") | H6: =IFERROR(H5/G5-1,"") | I6: =IFERROR(I5/H5-1,"") | J6: =IFERROR(J5/I5-1,"") | K6: =IFERROR(K5/J5-1,"") | L6: =IFERROR(L5/K5-1,"") | M6: =IFERROR(M5/L5-1,"") | ... AG6: =IFERROR(AG5/AF5-1,"")
D7: 원/달러(기말) | E7: =IFERROR(VLOOKUP($D7,환율,MATCH(E$1,변수H,0),0),"") | F7: =IFERROR(VLOOKUP($D7,환율,MATCH(F$1,변수H,0),0),"") | G7: =IFERROR(VLOOKUP($D7,환율,MATCH(G$1,변수H,0),0),"") | H7: =IFERROR(VLOOKUP($D7,환율,MATCH(H$1,변수H,0),0),"") | I7: =IFERROR(VLOOKUP($D7,환율,MATCH(I$1,변수H,0),0),"") | J7: =IFERROR(VLOOKUP($D7,환율,MATCH(J$1,변수H,0),0),"") | K7: =IFERROR(VLOOKUP($D7,환율,MATCH(K$1,변수H,0),0),"") | L7: =IFERROR(VLOOKUP($D7,환율,MATCH(L$1,변수H,0),0),"") | ... AG7: =IFERROR(VLOOKUP($D7,환율,MATCH(AG$1,변수H,0),0),"")
A8: 원/달러(기말) QoQ | F8: =IFERROR(F7/E7-1,"") | G8: =IFERROR(G7/F7-1,"") | H8: =IFERROR(H7/G7-1,"") | I8: =IFERROR(I7/H7-1,"") | J8: =IFERROR(J7/I7-1,"") | K8: =IFERROR(K7/J7-1,"") | L8: =IFERROR(L7/K7-1,"") | M8: =IFERROR(M7/L7-1,"") | ... AG8: =IFERROR(AG7/AF7-1,"")
D9: W/Euro(평균) | E9: =IFERROR(VLOOKUP($D9,환율,MATCH(E$1,변수H,0),0),"") | F9: =IFERROR(VLOOKUP($D9,환율,MATCH(F$1,변수H,0),0),"") | G9: =IFERROR(VLOOKUP($D9,환율,MATCH(G$1,변수H,0),0),"") | H9: =IFERROR(VLOOKUP($D9,환율,MATCH(H$1,변수H,0),0),"") | I9: =IFERROR(VLOOKUP($D9,환율,MATCH(I$1,변수H,0),0),"") | J9: =IFERROR(VLOOKUP($D9,환율,MATCH(J$1,변수H,0),0),"") | K9: =IFERROR(VLOOKUP($D9,환율,MATCH(K$1,변수H,0),0),"") | L9: =IFERROR(VLOOKUP($D9,환율,MATCH(L$1,변수H,0),0),"") | ... AG9: =IFERROR(VLOOKUP($D9,환율,MATCH(AG$1,변수H,0),0),"")
A10: W/Euro(평균) QoQ | F10: =IFERROR(F9/E9-1,"") | G10: =IFERROR(G9/F9-1,"") | H10: =IFERROR(H9/G9-1,"") | I10: =IFERROR(I9/H9-1,"") | J10: =IFERROR(J9/I9-1,"") | K10: =IFERROR(K9/J9-1,"") | L10: =IFERROR(L9/K9-1,"") | M10: =IFERROR(M9/L9-1,"") | ... AG10: =IFERROR(AG9/AF9-1,"")
D11: W/Euro(기말) | E11: =IFERROR(VLOOKUP($D11,환율,MATCH(E$1,변수H,0),0),"") | F11: =IFERROR(VLOOKUP($D11,환율,MATCH(F$1,변수H,0),0),"") | G11: =IFERROR(VLOOKUP($D11,환율,MATCH(G$1,변수H,0),0),"") | H11: =IFERROR(VLOOKUP($D11,환율,MATCH(H$1,변수H,0),0),"") | I11: =IFERROR(VLOOKUP($D11,환율,MATCH(I$1,변수H,0),0),"") | J11: =IFERROR(VLOOKUP($D11,환율,MATCH(J$1,변수H,0),0),"") | K11: =IFERROR(VLOOKUP($D11,환율,MATCH(K$1,변수H,0),0),"") | L11: =IFERROR(VLOOKUP($D11,환율,MATCH(L$1,변수H,0),0),"") | ... AG11: =IFERROR(VLOOKUP($D11,환율,MATCH(AG$1,변수H,0),0),"")
A12: W/Euro(기말) QoQ | F12: =IFERROR(F11/E11-1,"") | G12: =IFERROR(G11/F11-1,"") | H12: =IFERROR(H11/G11-1,"") | I12: =IFERROR(I11/H11-1,"") | J12: =IFERROR(J11/I11-1,"") | K12: =IFERROR(K11/J11-1,"") | L12: =IFERROR(L11/K11-1,"") | M12: =IFERROR(M11/L11-1,"") | ... AG12: =IFERROR(AG11/AF11-1,"")
D13: 원/100Y(기말) | E13: =IFERROR(VLOOKUP($D13,환율,MATCH(E$1,변수H,0),0),"") | F13: =IFERROR(VLOOKUP($D13,환율,MATCH(F$1,변수H,0),0),"") | G13: =IFERROR(VLOOKUP($D13,환율,MATCH(G$1,변수H,0),0),"") | H13: =IFERROR(VLOOKUP($D13,환율,MATCH(H$1,변수H,0),0),"") | I13: =IFERROR(VLOOKUP($D13,환율,MATCH(I$1,변수H,0),0),"") | J13: =IFERROR(VLOOKUP($D13,환율,MATCH(J$1,변수H,0),0),"") | K13: =IFERROR(VLOOKUP($D13,환율,MATCH(K$1,변수H,0),0),"") | L13: =IFERROR(VLOOKUP($D13,환율,MATCH(L$1,변수H,0),0),"") | ... AG13: =IFERROR(VLOOKUP($D13,환율,MATCH(AG$1,변수H,0),0),"")
A14: 원/100Y(기말) QoQ | F14: =IFERROR(F13/E13-1,"") | G14: =IFERROR(G13/F13-1,"") | H14: =IFERROR(H13/G13-1,"") | I14: =IFERROR(I13/H13-1,"") | J14: =IFERROR(J13/I13-1,"") | K14: =IFERROR(K13/J13-1,"") | L14: =IFERROR(L13/K13-1,"") | M14: =IFERROR(M13/L13-1,"") | ... AG14: =IFERROR(AG13/AF13-1,"")
A16: 외화순노출 | C16: 외화 순노출(백만$) | D16: =변수!D58 | E16: 외화 순노출 × Δ기말환율 (외화 시트 방식)
A17: 환관련손익추정 | C17: 환관련손익 추정(억원) = 순노출 × Δ원/달러(기말) / 100 | F17: =IFERROR($D$16*(F7-E7)/100,"") | G17: =IFERROR($D$16*(G7-F7)/100,"") | H17: =IFERROR($D$16*(H7-G7)/100,"") | I17: =IFERROR($D$16*(I7-H7)/100,"") | J17: =IFERROR($D$16*(J7-I7)/100,"") | K17: =IFERROR($D$16*(K7-J7)/100,"") | L17: =IFERROR($D$16*(L7-K7)/100,"") | M17: =IFERROR($D$16*(M7-L7)/100,"") | ... AG17: =IFERROR($D$16*(AG7-AF7)/100,"")
A18: fx_pnl.by_q | C18: 모델 fx_pnl.by_q(억원, 참고)
C19: 외화 순노출 미공시(face) → 0 + 표기
