Workbook
Name 변수H: 변수!$C$1:$AO$1
Name 환율: 변수!$C$6:$AO$13
Name BS연결H: BS연결!$C$1:$AO$1
Name BS연결: BS연결!$C$5:$AO$119
Name BS별도H: BS별도!$C$1:$AO$1
Name BS별도: BS별도!$C$5:$AO$103
Name SUBQH: subQ!$A$1:$AO$1
Name subQ: subQ!$A$5:$AO$47
Name SLS_H: SLS!$A$1:$BS$1

Sheet README
A1: 한화오션(042660) 실적 모델 — ARGUS 한국조선
A2: 기준 분기 2026Q2 · 마지막 실적 2026Q2 · 생성 2026-10-12
A3: 모든 수치는 모델 산출값(DART 공개 재무제표 + 우리 추정)이다 — 목표주가·투자 추천 아님. 참고용 · 투자조언 아님.
A5: 시트
A6: 변수 가정 시계열. 환율 8행(ECB via frankfurter — L2 fx.json; 추정 분기 = 노란 가정), 추정 드라이버(노란 셀 = 모델값에서 역산한 가정, 바꾸면 재계산; 연녹 셀 = 3절 스칼라 참조 수식), 3절 스칼라 가정(세율·판관비율·지배주주비중·이자율·종가·PER 밴드·COE·외화 순노출·헤지비율)
A7: BS연결/BS별도 FnGuide 계정명 × 기간 값 덤프(백만원). 행1 분기라벨, 행4 YYYY.MM / YYYY.12A. 이름정의 BS연결H·BS연결(계정명 C열부터)
A8: subQ 분기 서브모델(억원 = 백만원/100). 확정 행: =IFERROR(VLOOKUP($D행,BS연결,MATCH(E$1,BS연결H,0),0)/100,"") 추정 행: 변수 시트 가정 셀 참조 수식. 외환손익·파생상품손익은 BS 계정 합·차, 기타금융손익은 잔차, OPM·EPS·BPS·PER·PBR 은 파생 수식
A9: SLS 선표(조선사만, sls json 있을 때): 요약 행(sls 저장값) + 계약별 스케줄(백만$) × (헤지비율 × 헤지환율 + (1−헤지비율) × 건조시점 환율[변수 원/달러(평균)]) → 원화 수식 블록 → 합계 행이 subQ 매출조선에 연결
A10: 시나리오 신규수주 보수/기준/낙관(forecast_panel 패널, 모델에 scenarios 가 있을 때만): 매출액·영업이익 = subQ 기준값 ± (시나리오 신규 − base 신규) × OPM. base 만 subQ 행에 포함, 나머지는 합산 안 함
A11: 분기/연간예상 subQ 를 이름(A열 key)으로 VLOOKUP 한 보고서 표(억원)
A12: TP PER 밴드 × 12M fwd EPS, PBR = ROE/COE × BPS — 모델 산출값 구간, 목표주가·추천 아님
A13: 외화 환율 QoQ, 외화 순노출 × Δ기말환율 → 환관련손익 추정
... A36: 백테스트: {"freeze": "2025Q2", "horizon": 4, "revenue_wape_pct": 17.8, "op_wape_pct": 51.2, "n": 4, "note": "단일 회사 4분기 — 통계 아님", "driver_at_freeze": "sls_marine_plus_uncovered_backlog_runoff", "selection_oos_at_freeze": null, "frozen_inputs": "fin(연결/별도)·고객 조선사 모델·지주 자회사 모델은 2025Q2 까지의 분기만; 선표는 체결일 ≤ 2025Q2 말일 계약(원장 최신 금액·코호트 등급, 환산 없음); 잔고는 yards_cache 2025Q2; 시세·환율 forward·prices·forecast_panel 신규수주 미사용. 고객 가중치(suppliers.json 언급 비중)와 합병 체인링크는 현재 지식; 고객 연동 채택은 동결 모델 안에서도 자기 la−4분기 OOS 규칙(selection_oos_at_freeze)", "detail": [{"q": "2025Q3", "rev_pred": 31776.86, "rev_act": 30233.58, "op_pred": 2132.75, "op_act": 2897.59}, {"q": "2025Q4", "rev_pred": 31776.86, "rev_act": 33229.51, "op_pred": 2132.75, "op_act": 2475.19}, {"q": "2026Q1", "rev_pred": 31609.47, "rev_act": 32099.4, "op_pred": 2103.87, "op_act": 4410.65}, {"q": "2026Q2", "rev_pred": 31245.58, "rev_act": 54431.71, "op_pred": 2005.63, "op_act": 7361.14}]}

Sheet 변수
C1: 이름: 변수H | E1: 4Q21 | F1: 2021 | G1: 1Q22 | H1: 2Q22 | I1: 3Q22 | J1: 4Q22 | K1: 2022 | L1: 1Q23 | M1: 2Q23 | N1: 3Q23 | O1: 4Q23 | P1: 2023 | Q1: 1Q24 | R1: 2Q24 | S1: 3Q24 | T1: 4Q24 | U1: 2024 | V1: 1Q25 | W1: 2Q25 | X1: 3Q25 | Y1: 4Q25 | Z1: 2025 | AA1: 1Q26 | AB1: 2Q26 | AC1: 3Q26 | AD1: 4Q26 | AE1: 2026 | AF1: 1Q27 | AG1: 2Q27 | AH1: 3Q27 | AI1: 4Q27 | AJ1: 2027 | AK1: 1Q28 | AL1: 2Q28 | AM1: 3Q28 | AN1: 4Q28 | AO1: 2028
A2: 가정 시계열 — 노란 셀은 추정 가정(모델값에서 역산), 연녹 셀은 3절 스칼라 참조 수식. 바꾸면 subQ·분기·연간예상·TP·시나리오가 재계산됩니다.
E3: 1 | F3: 2 | G3: 3 | H3: 4 | I3: 5 | J3: 6 | K3: 7 | L3: 8 | M3: 9 | N3: 10 | O3: 11 | P3: 12 | Q3: 13 | R3: 14 | S3: 15 | T3: 16 | U3: 17 | V3: 18 | W3: 19 | X3: 20 | Y3: 21 | Z3: 22 | AA3: 23 | AB3: 24 | AC3: 25 | AD3: 26 | AE3: 27 | AF3: 28 | AG3: 29 | AH3: 30 | AI3: 31 | AJ3: 32 | AK3: 33 | AL3: 34 | AM3: 35 | AN3: 36 | AO3: 37
E4: 2021.12 | F4: 2021.12A | G4: 2022.03 | H4: 2022.06 | I4: 2022.09 | J4: 2022.12 | K4: 2022.12A | L4: 2023.03 | M4: 2023.06 | N4: 2023.09 | O4: 2023.12 | P4: 2023.12A | Q4: 2024.03 | R4: 2024.06 | S4: 2024.09 | T4: 2024.12 | U4: 2024.12A | V4: 2025.03 | W4: 2025.06 | X4: 2025.09 | Y4: 2025.12 | Z4: 2025.12A | AA4: 2026.03 | AB4: 2026.06 | AC4: 2026.09 | AD4: 2026.12 | AE4: 2026.12A | AF4: 2027.03 | AG4: 2027.06 | AH4: 2027.09 | AI4: 2027.12 | AJ4: 2027.12A | AK4: 2028.03 | AL4: 2028.06 | AM4: 2028.09 | AN4: 2028.12 | AO4: 2028.12A
B5: 1. FX | C5: 이름: 환율
A6: USDKRW_avg | C6: 원/달러(평균) | E6: 1183.5 | F6: 1145.51 | G6: 1205.78 | H6: 1262.09 | I6: 1341.93 | J6: 1360.12 | K6: 1292.98 | L6: 1276.95 | M6: 1315.69 | N6: 1313.62 | O6: 1322.01 | P6: 1306.85 | Q6: 1330.14 | R6: 1371.28 | S6: 1356.22 | T6: 1396.3 | U6: 1363.53 | V6: 1452.28 | W6: 1398.52 | X6: 1386.95 | Y6: 1449.19 | Z6: 1421.52 | AA6: 1466.12 | AB6: 1501.75 | AC6: 1418.75 | AD6: 1345.14 | AE6: 1457.21 | AF6: 1341.49 | AG6: 1341.49 | AH6: 1341.49 | AI6: 1341.49 | AK6: 1341.49 | AL6: 1341.49 | AM6: 1341.49 | AN6: 1341.49
A7: USDKRW_end | C7: 원/달러(기말) | E7: 1188.75 | F7: 1188.75 | G7: 1213.74 | H7: 1301.24 | I7: 1436.9 | J7: 1260.16 | K7: 1260.16 | L7: 1305.99 | M7: 1321.44 | N7: 1345.35 | O7: 1297.43 | P7: 1297.43 | Q7: 1349.25 | R7: 1377.73 | S7: 1312.17 | T7: 1474.78 | U7: 1474.78 | V7: 1474.54 | W7: 1355.13 | X7: 1403.67 | Y7: 1444.2 | Z7: 1444.2 | AA7: 1524.8 | AB7: 1550.89 | AC7: 1355.4 | AD7: 1341.49 | AE7: 1341.49 | AF7: 1341.49 | AG7: 1341.49 | AH7: 1341.49 | AI7: 1341.49 | AK7: 1341.49 | AL7: 1341.49 | AM7: 1341.49 | AN7: 1341.49
A8: JPY100KRW_avg | C8: 원/100Y(평균) | E8: 1041.02 | F8: 1042.74 | G8: 1036.79 | H8: 972.23 | I8: 970.61 | J8: 961.03 | K8: 985.1 | L8: 964.89 | M8: 957.36 | N8: 909 | O8: 893.22 | P8: 931.11 | Q8: 896.29 | R8: 880.14 | S8: 909.35 | T8: 917.25 | U8: 900.92 | V8: 952.59 | W8: 967.92 | X8: 940.32 | Y8: 940.77 | Z8: 950.17 | AA8: 934.39 | AB8: 942.16 | AC8: 890.41 | AD8: 850.79 | AE8: 919.21 | AF8: 847.7 | AG8: 847.7 | AH8: 847.7 | AI8: 847.7 | AK8: 847.7 | AL8: 847.7 | AM8: 847.7 | AN8: 847.7
A9: JPY100KRW_end | C9: 원/100Y(기말) | E9: 1032.62 | F9: 1032.62 | G9: 996.83 | H9: 954.9 | I9: 993.29 | J9: 955.54 | K9: 955.54 | L9: 980.62 | M9: 913.67 | N9: 901.47 | O9: 917.04 | P9: 917.04 | Q9: 892.42 | R9: 857.76 | S9: 919.21 | T9: 939.65 | U9: 939.65 | V9: 986.84 | W9: 938.85 | X9: 948.49 | Y9: 921.81 | Z9: 921.81 | AA9: 955.99 | AB9: 954.75 | AC9: 863.31 | AD9: 847.7 | AE9: 847.7 | AF9: 847.7 | AG9: 847.7 | AH9: 847.7 | AI9: 847.7 | AK9: 847.7 | AL9: 847.7 | AM9: 847.7 | AN9: 847.7
A10: EURKRW_avg | C10: W/Euro(평균) | E10: 1353.32 | F10: 1354.06 | G10: 1352.29 | H10: 1343.31 | I10: 1350.63 | J10: 1386.07 | K10: 1358.07 | L10: 1369.93 | M10: 1432.41 | N10: 1429.41 | O10: 1420.91 | P10: 1412.88 | Q10: 1444.21 | R10: 1476.42 | S10: 1489.3 | T10: 1490.78 | U10: 1475.4 | V10: 1528.33 | W10: 1585.13 | X10: 1620.04 | Y10: 1686.02 | Z10: 1605.45 | AA10: 1715.47 | AB10: 1746.09 | AC10: 1631.97 | AD10: 1509.74 | AE10: 1689.95 | AF10: 1503.27 | AG10: 1503.27 | AH10: 1503.27 | AI10: 1503.27 | AK10: 1503.27 | AL10: 1503.27 | AM10: 1503.27 | AN10: 1503.27
A11: EURKRW_end | C11: W/Euro(기말) | E11: 1346.38 | F11: 1346.38 | G11: 1347.37 | H11: 1351.6 | I11: 1400.62 | J11: 1344.08 | K11: 1344.08 | L11: 1420.26 | M11: 1435.88 | N11: 1425.26 | O11: 1433.66 | P11: 1433.66 | Q11: 1458.68 | R11: 1474.86 | S11: 1469.1 | T11: 1532.14 | U11: 1532.14 | V11: 1594.72 | W11: 1588.22 | X11: 1648.04 | Y11: 1696.94 | Z11: 1696.94 | AA11: 1753.21 | AB11: 1767.09 | AC11: 1539.06 | AD11: 1503.27 | AE11: 1503.27 | AF11: 1503.27 | AG11: 1503.27 | AH11: 1503.27 | AI11: 1503.27 | AK11: 1503.27 | AL11: 1503.27 | AM11: 1503.27 | AN11: 1503.27
A12: CNYKRW_avg | C12: 원/중국원(평균) | E12: 185.14 | F12: 177.65 | G12: 189.93 | H12: 190.76 | I12: 195.79 | J12: 191.09 | K12: 191.93 | L12: 186.59 | M12: 187.45 | N12: 181.28 | O12: 182.86 | P12: 184.52 | Q12: 185.04 | R12: 189.35 | S12: 189.24 | T12: 194.24 | U12: 189.49 | V12: 199.63 | W12: 193.41 | X12: 193.79 | Y12: 204.38 | Z12: 197.8 | AA12: 211.75 | AB12: 220.8 | AC12: 210.43 | AD12: 200.69 | AE12: 213.75 | AF12: 200.46 | AG12: 200.46 | AH12: 200.46 | AI12: 200.46 | AK12: 200.46 | AL12: 200.46 | AM12: 200.46 | AN12: 200.46
A13: CNYKRW_end | C13: 원/중국원(기말) | E13: 187.13 | F13: 187.13 | G13: 191.38 | H13: 194.13 | I13: 201.92 | J13: 182.67 | K13: 182.67 | L13: 189.97 | M13: 181.8 | N13: 184.26 | O13: 182.61 | P13: 182.61 | Q13: 186.66 | R13: 189.7 | S13: 187.12 | T13: 202.04 | U13: 202.04 | V13: 203.3 | W13: 189.14 | X13: 197.16 | Y13: 206.28 | Z13: 206.28 | AA13: 220.97 | AB13: 228.56 | AC13: 202.16 | AD13: 200.46 | AE13: 200.46 | AF13: 200.46 | AG13: 200.46 | AH13: 200.46 | AI13: 200.46 | AK13: 200.46 | AL13: 200.46 | AM13: 200.46 | AN13: 200.46
B14: 1b. 종가
A15: price_close_end | C15: 종가(기말) | E15: 20478 | G15: 22032 | H15: 21322 | I15: 16835 | J15: 16835 | L15: 21766 | M15: 33493 | N15: 30950 | O15: 25100 | Q15: 27600 | R15: 30550 | S15: 30550 | T15: 37350 | V15: 67100 | W15: 79400 | X15: 110300 | Y15: 113600 | AA15: 120200 | AB15: 100300 | AC15: 78800 | AD15: 67100
A16: price_high | C16: 종가(최고) | E16: 24298 | G16: 25453 | H16: 25764 | I16: 23098 | J16: 18923 | L16: 24164 | M16: 35980 | N16: 44332 | O16: 30900 | Q16: 30900 | R16: 36400 | S16: 35300 | T16: 41050 | V16: 87200 | W16: 95800 | X16: 123800 | Y16: 151600 | AA16: 154800 | AB16: 141900 | AC16: 123000 | AD16: 79200
A17: price_low | C17: 종가(최저) | E17: 19856 | G17: 16258 | H17: 17412 | I17: 16169 | J17: 15325 | L17: 15636 | M17: 21677 | N17: 29000 | O17: 21900 | Q17: 21050 | R17: 24850 | S17: 25400 | T17: 26100 | V17: 36300 | W17: 62350 | X17: 71500 | Y17: 99600 | AA17: 108500 | AB17: 95500 | AC17: 71300 | AD17: 67000
A18: price_avg | C18: 종가(평균) | E18: 21658.5 | G18: 20964 | H18: 20935.4 | I18: 18116.1 | J18: 16754.1 | L18: 20254.7 | M18: 25770.2 | N18: 35815.9 | O18: 25825.8 | Q18: 24048.4 | R18: 30870 | S18: 31184.7 | T18: 33018 | V18: 64850 | W18: 79135 | X18: 101701.5 | Y18: 118854.2 | AA18: 133781.4 | AB18: 121616.4 | AC18: 86733.9 | AD18: 74650
B20: 2. 추정 드라이버 | C20: 실적 열 = subQ 실현값(수식), 추정 열 = 가정(노란 = 모델값 역산, 연녹 = 3절 스칼라 참조)
A21: drv:판관비 | B21: ratio | C21: 판관비율(/매출) | E21: =IFERROR(subQ!E8/subQ!E5,"") | F21: =IFERROR(subQ!F8/subQ!F5,"") | G21: =IFERROR(subQ!G8/subQ!G5,"") | H21: =IFERROR(subQ!H8/subQ!H5,"") | I21: =IFERROR(subQ!I8/subQ!I5,"") | J21: =IFERROR(subQ!J8/subQ!J5,"") | K21: =IFERROR(subQ!K8/subQ!K5,"") | L21: =IFERROR(subQ!L8/subQ!L5,"") | ... AB21: =IFERROR(subQ!AB8/subQ!AB5,"") | AC21: =$D$55 | AD21: =$D$55 | AE21: =IFERROR(subQ!AE8/subQ!AE5,"") | AF21: =$D$55 | AG21: =$D$55 | AH21: =$D$55 | AI21: =$D$55 | AJ21: =IFERROR(subQ!AJ8/subQ!AJ5,"") | AK21: =$D$55 | AL21: =$D$55 | AM21: =$D$55 | AN21: =$D$55 | AO21: =IFERROR(subQ!AO8/subQ!AO5,"")
A22: drv:외환손익 | B22: abs | C22: 외환손익 (가정, 억원) | E22: =subQ!E13 | F22: =subQ!F13 | G22: =subQ!G13 | H22: =subQ!H13 | I22: =subQ!I13 | J22: =subQ!J13 | K22: =subQ!K13 | L22: =subQ!L13 | ... AB22: =subQ!AB13 | AC22: 0 | AD22: 0 | AE22: =subQ!AE13 | AF22: 0 | AG22: 0 | AH22: 0 | AI22: 0 | AJ22: =subQ!AJ13 | AK22: 0 | AL22: 0 | AM22: 0 | AN22: 0 | AO22: =subQ!AO13
A23: drv:파생상품손익 | B23: abs | C23: 파생상품손익 (가정, 억원) | E23: =subQ!E14 | F23: =subQ!F14 | G23: =subQ!G14 | H23: =subQ!H14 | I23: =subQ!I14 | J23: =subQ!J14 | K23: =subQ!K14 | L23: =subQ!L14 | ... AB23: =subQ!AB14 | AC23: 0 | AD23: 0 | AE23: =subQ!AE14 | AF23: 0 | AG23: 0 | AH23: 0 | AI23: 0 | AJ23: =subQ!AJ14 | AK23: 0 | AL23: 0 | AM23: 0 | AN23: 0 | AO23: =subQ!AO14
A24: drv:기타금융손익 | B24: abs | C24: 기타금융손익 (가정, 억원) | E24: =subQ!E15 | F24: =subQ!F15 | G24: =subQ!G15 | H24: =subQ!H15 | I24: =subQ!I15 | J24: =subQ!J15 | K24: =subQ!K15 | L24: =subQ!L15 | ... AB24: =subQ!AB15 | AC24: 2.92 | AD24: 2.92 | AE24: =subQ!AE15 | AF24: 2.92 | AG24: 2.92 | AH24: 2.92 | AI24: 2.92 | AJ24: =subQ!AJ15 | AK24: 2.92 | AL24: 2.92 | AM24: 2.92 | AN24: 2.92 | AO24: =subQ!AO15
A25: drv:기타영업외손익 | B25: abs | C25: 기타영업외손익 (가정, 억원) | E25: =subQ!E16 | F25: =subQ!F16 | G25: =subQ!G16 | H25: =subQ!H16 | I25: =subQ!I16 | J25: =subQ!J16 | K25: =subQ!K16 | L25: =subQ!L16 | ... AB25: =subQ!AB16 | AC25: 0 | AD25: 0 | AE25: =subQ!AE16 | AF25: 0 | AG25: 0 | AH25: 0 | AI25: 0 | AJ25: =subQ!AJ16 | AK25: 0 | AL25: 0 | AM25: 0 | AN25: 0 | AO25: =subQ!AO16
A26: drv:지분법손익 | B26: abs | C26: 지분법손익 (가정, 억원) | E26: =subQ!E17 | F26: =subQ!F17 | G26: =subQ!G17 | H26: =subQ!H17 | I26: =subQ!I17 | J26: =subQ!J17 | K26: =subQ!K17 | L26: =subQ!L17 | ... AB26: =subQ!AB17 | AC26: -447.53 | AD26: -447.53 | AE26: =subQ!AE17 | AF26: -447.53 | AG26: -447.53 | AH26: -447.53 | AI26: -447.53 | AJ26: =subQ!AJ17 | AK26: -447.53 | AL26: -447.53 | AM26: -447.53 | AN26: -447.53 | AO26: =subQ!AO17
A27: drv:법인세비용 | B27: tax | C27: 법인세율(/세전) — 법인세 = MAX(세전,0) × 분기별 세율(이월결손 램프, assumptions.tax_schedule) | E27: =IFERROR(subQ!E19/subQ!E18,"") | F27: =IFERROR(subQ!F19/subQ!F18,"") | G27: =IFERROR(subQ!G19/subQ!G18,"") | H27: =IFERROR(subQ!H19/subQ!H18,"") | I27: =IFERROR(subQ!I19/subQ!I18,"") | J27: =IFERROR(subQ!J19/subQ!J18,"") | K27: =IFERROR(subQ!K19/subQ!K18,"") | L27: =IFERROR(subQ!L19/subQ!L18,"") | ... AB27: =IFERROR(subQ!AB19/subQ!AB18,"") | AC27: 0.006752619 | AD27: 0.006754059 | AE27: =IFERROR(subQ!AE19/subQ!AE18,"") | AF27: 0.033408819 | AG27: 0.060065587 | AH27: 0.086720205 | AI27: 0.11337725 | AJ27: =IFERROR(subQ!AJ19/subQ!AJ18,"") | AK27: 0.14003202 | AL27: 0.16668801 | AM27: 0.19334419 | AN27: 0.21999949 | AO27: =IFERROR(subQ!AO19/subQ!AO18,"")
A28: drv:지배주주순이익 | B28: ratio | C28: 지배주주 비중(/당기순이익) | E28: =IFERROR(subQ!E21/subQ!E20,"") | F28: =IFERROR(subQ!F21/subQ!F20,"") | G28: =IFERROR(subQ!G21/subQ!G20,"") | H28: =IFERROR(subQ!H21/subQ!H20,"") | I28: =IFERROR(subQ!I21/subQ!I20,"") | J28: =IFERROR(subQ!J21/subQ!J20,"") | K28: =IFERROR(subQ!K21/subQ!K20,"") | L28: =IFERROR(subQ!L21/subQ!L20,"") | ... AB28: =IFERROR(subQ!AB21/subQ!AB20,"") | AC28: =$D$56 | AD28: =$D$56 | AE28: =IFERROR(subQ!AE21/subQ!AE20,"") | AF28: =$D$56 | AG28: =$D$56 | AH28: =$D$56 | AI28: =$D$56 | AJ28: =IFERROR(subQ!AJ21/subQ!AJ20,"") | AK28: =$D$56 | AL28: =$D$56 | AM28: =$D$56 | AN28: =$D$56 | AO28: =IFERROR(subQ!AO21/subQ!AO20,"")
A29: drv:부채총계 | B29: qoq | C29: 부채총계 QoQ | G29: =IFERROR(subQ!G23/subQ!E23-1,"") | H29: =IFERROR(subQ!H23/subQ!G23-1,"") | I29: =IFERROR(subQ!I23/subQ!H23-1,"") | J29: =IFERROR(subQ!J23/subQ!I23-1,"") | L29: =IFERROR(subQ!L23/subQ!J23-1,"") | M29: =IFERROR(subQ!M23/subQ!L23-1,"") | N29: =IFERROR(subQ!N23/subQ!M23-1,"") | O29: =IFERROR(subQ!O23/subQ!N23-1,"") | Q29: =IFERROR(subQ!Q23/subQ!O23-1,"") | R29: =IFERROR(subQ!R23/subQ!Q23-1,"") | S29: =IFERROR(subQ!S23/subQ!R23-1,"") | T29: =IFERROR(subQ!T23/subQ!S23-1,"") | V29: =IFERROR(subQ!V23/subQ!T23-1,"") | W29: =IFERROR(subQ!W23/subQ!V23-1,"") | X29: =IFERROR(subQ!X23/subQ!W23-1,"") | Y29: =IFERROR(subQ!Y23/subQ!X23-1,"") | AA29: =IFERROR(subQ!AA23/subQ!Y23-1,"") | AB29: =IFERROR(subQ!AB23/subQ!AA23-1,"") | AC29: 3.9e-08 | AD29: 0 | AF29: 0 | AG29: 0 | AH29: 0 | AI29: 0 | AK29: 0 | AL29: 0 | AM29: 0 | AN29: 0
A30: drv:자본총계 | B30: roll | C30: 자본총계 기타변동(배당 등, 억원) | G30: =IFERROR(subQ!E24+subQ!G20-subQ!G24,"") | H30: =IFERROR(subQ!G24+subQ!H20-subQ!H24,"") | I30: =IFERROR(subQ!H24+subQ!I20-subQ!I24,"") | J30: =IFERROR(subQ!I24+subQ!J20-subQ!J24,"") | L30: =IFERROR(subQ!J24+subQ!L20-subQ!L24,"") | M30: =IFERROR(subQ!L24+subQ!M20-subQ!M24,"") | N30: =IFERROR(subQ!M24+subQ!N20-subQ!N24,"") | O30: =IFERROR(subQ!N24+subQ!O20-subQ!O24,"") | Q30: =IFERROR(subQ!O24+subQ!Q20-subQ!Q24,"") | R30: =IFERROR(subQ!Q24+subQ!R20-subQ!R24,"") | S30: =IFERROR(subQ!R24+subQ!S20-subQ!S24,"") | T30: =IFERROR(subQ!S24+subQ!T20-subQ!T24,"") | V30: =IFERROR(subQ!T24+subQ!V20-subQ!V24,"") | W30: =IFERROR(subQ!V24+subQ!W20-subQ!W24,"") | X30: =IFERROR(subQ!W24+subQ!X20-subQ!X24,"") | Y30: =IFERROR(subQ!X24+subQ!Y20-subQ!Y24,"") | AA30: =IFERROR(subQ!Y24+subQ!AA20-subQ!AA24,"") | AB30: =IFERROR(subQ!AA24+subQ!AB20-subQ!AB24,"") | AC30: -0.01662006 | AD30: -0.010357283 | AF30: 0.004744529 | AG30: -0.015303061 | AH30: -0.008136676 | AI30: -0.006513659 | AK30: -0.003354116 | AL30: 0.001469314 | AM30: 3.5952e-05 | AN30: -0.001256641
A31: drv:지배주주지분 | B31: roll | C31: 지배주주지분 기타변동(배당 등, 억원) | G31: =IFERROR(subQ!E25+subQ!G21-subQ!G25,"") | H31: =IFERROR(subQ!G25+subQ!H21-subQ!H25,"") | I31: =IFERROR(subQ!H25+subQ!I21-subQ!I25,"") | J31: =IFERROR(subQ!I25+subQ!J21-subQ!J25,"") | L31: =IFERROR(subQ!J25+subQ!L21-subQ!L25,"") | M31: =IFERROR(subQ!L25+subQ!M21-subQ!M25,"") | N31: =IFERROR(subQ!M25+subQ!N21-subQ!N25,"") | O31: =IFERROR(subQ!N25+subQ!O21-subQ!O25,"") | Q31: =IFERROR(subQ!O25+subQ!Q21-subQ!Q25,"") | R31: =IFERROR(subQ!Q25+subQ!R21-subQ!R25,"") | S31: =IFERROR(subQ!R25+subQ!S21-subQ!S25,"") | T31: =IFERROR(subQ!S25+subQ!T21-subQ!T25,"") | V31: =IFERROR(subQ!T25+subQ!V21-subQ!V25,"") | W31: =IFERROR(subQ!V25+subQ!W21-subQ!W25,"") | X31: =IFERROR(subQ!W25+subQ!X21-subQ!X25,"") | Y31: =IFERROR(subQ!X25+subQ!Y21-subQ!Y25,"") | AA31: =IFERROR(subQ!Y25+subQ!AA21-subQ!AA25,"") | AB31: =IFERROR(subQ!AA25+subQ!AB21-subQ!AB25,"") | AC31: -0.009763957 | AD31: -0.0078098 | AF31: -0.000155394 | AG31: -0.013661483 | AH31: -0.003030048 | AI31: 0.001194955 | AK31: -0.003740682 | AL31: 0.002175579 | AM31: 0.004347552 | AN31: 0.004252885
A32: drv:총차입금 | B32: qoq | C32: 총차입금 QoQ | G32: =IFERROR(subQ!G26/subQ!E26-1,"") | H32: =IFERROR(subQ!H26/subQ!G26-1,"") | I32: =IFERROR(subQ!I26/subQ!H26-1,"") | J32: =IFERROR(subQ!J26/subQ!I26-1,"") | L32: =IFERROR(subQ!L26/subQ!J26-1,"") | M32: =IFERROR(subQ!M26/subQ!L26-1,"") | N32: =IFERROR(subQ!N26/subQ!M26-1,"") | O32: =IFERROR(subQ!O26/subQ!N26-1,"") | Q32: =IFERROR(subQ!Q26/subQ!O26-1,"") | R32: =IFERROR(subQ!R26/subQ!Q26-1,"") | S32: =IFERROR(subQ!S26/subQ!R26-1,"") | T32: =IFERROR(subQ!T26/subQ!S26-1,"") | V32: =IFERROR(subQ!V26/subQ!T26-1,"") | W32: =IFERROR(subQ!W26/subQ!V26-1,"") | X32: =IFERROR(subQ!X26/subQ!W26-1,"") | Y32: =IFERROR(subQ!Y26/subQ!X26-1,"") | AA32: =IFERROR(subQ!AA26/subQ!Y26-1,"") | AB32: =IFERROR(subQ!AB26/subQ!AA26-1,"") | AC32: 8e-09 | AD32: 0 | AF32: 0 | AG32: 0 | AH32: 0 | AI32: 0 | AK32: 0 | AL32: 0 | AM32: 0 | AN32: 0
A33: drv:순차입금 | B33: qoq | C33: 순차입금 QoQ | G33: =IFERROR(subQ!G27/subQ!E27-1,"") | H33: =IFERROR(subQ!H27/subQ!G27-1,"") | I33: =IFERROR(subQ!I27/subQ!H27-1,"") | J33: =IFERROR(subQ!J27/subQ!I27-1,"") | L33: =IFERROR(subQ!L27/subQ!J27-1,"") | M33: =IFERROR(subQ!M27/subQ!L27-1,"") | N33: =IFERROR(subQ!N27/subQ!M27-1,"") | O33: =IFERROR(subQ!O27/subQ!N27-1,"") | Q33: =IFERROR(subQ!Q27/subQ!O27-1,"") | R33: =IFERROR(subQ!R27/subQ!Q27-1,"") | S33: =IFERROR(subQ!S27/subQ!R27-1,"") | T33: =IFERROR(subQ!T27/subQ!S27-1,"") | V33: =IFERROR(subQ!V27/subQ!T27-1,"") | W33: =IFERROR(subQ!W27/subQ!V27-1,"") | X33: =IFERROR(subQ!X27/subQ!W27-1,"") | Y33: =IFERROR(subQ!Y27/subQ!X27-1,"") | AA33: =IFERROR(subQ!AA27/subQ!Y27-1,"") | AB33: =IFERROR(subQ!AB27/subQ!AA27-1,"") | AC33: -0.091654624 | AD33: -0.10459747 | AF33: -0.11479349 | AG33: -0.13277575 | AH33: -0.159848 | AI33: -0.19934754 | AK33: -0.26140158 | AL33: -0.26855885 | AM33: -0.27173449 | AN33: -0.40744694
A34: drv:이자발생자산 | B34: qoq | C34: 이자발생자산 QoQ | G34: =IFERROR(subQ!G28/subQ!E28-1,"") | H34: =IFERROR(subQ!H28/subQ!G28-1,"") | I34: =IFERROR(subQ!I28/subQ!H28-1,"") | J34: =IFERROR(subQ!J28/subQ!I28-1,"") | L34: =IFERROR(subQ!L28/subQ!J28-1,"") | M34: =IFERROR(subQ!M28/subQ!L28-1,"") | N34: =IFERROR(subQ!N28/subQ!M28-1,"") | O34: =IFERROR(subQ!O28/subQ!N28-1,"") | Q34: =IFERROR(subQ!Q28/subQ!O28-1,"") | R34: =IFERROR(subQ!R28/subQ!Q28-1,"") | S34: =IFERROR(subQ!S28/subQ!R28-1,"") | T34: =IFERROR(subQ!T28/subQ!S28-1,"") | V34: =IFERROR(subQ!V28/subQ!T28-1,"") | W34: =IFERROR(subQ!W28/subQ!V28-1,"") | X34: =IFERROR(subQ!X28/subQ!W28-1,"") | Y34: =IFERROR(subQ!Y28/subQ!X28-1,"") | AA34: =IFERROR(subQ!AA28/subQ!Y28-1,"") | AB34: =IFERROR(subQ!AB28/subQ!AA28-1,"") | AC34: 0.23515572 | AD34: 0.19735658 | AF34: 0.16197297 | AG34: 0.14272255 | AH34: 0.13039822 | AI34: 0.12086533 | AK34: 0.11321104 | AL34: 0.077170791 | AM34: 0.053021488 | AN34: 0.054983289
A35: drv:현금및현금성자산 | B35: qoq | C35: 현금및현금성자산 QoQ | G35: =IFERROR(subQ!G29/subQ!E29-1,"") | H35: =IFERROR(subQ!H29/subQ!G29-1,"") | I35: =IFERROR(subQ!I29/subQ!H29-1,"") | J35: =IFERROR(subQ!J29/subQ!I29-1,"") | L35: =IFERROR(subQ!L29/subQ!J29-1,"") | M35: =IFERROR(subQ!M29/subQ!L29-1,"") | N35: =IFERROR(subQ!N29/subQ!M29-1,"") | O35: =IFERROR(subQ!O29/subQ!N29-1,"") | Q35: =IFERROR(subQ!Q29/subQ!O29-1,"") | R35: =IFERROR(subQ!R29/subQ!Q29-1,"") | S35: =IFERROR(subQ!S29/subQ!R29-1,"") | T35: =IFERROR(subQ!T29/subQ!S29-1,"") | V35: =IFERROR(subQ!V29/subQ!T29-1,"") | W35: =IFERROR(subQ!W29/subQ!V29-1,"") | X35: =IFERROR(subQ!X29/subQ!W29-1,"") | Y35: =IFERROR(subQ!Y29/subQ!X29-1,"") | AA35: =IFERROR(subQ!AA29/subQ!Y29-1,"") | AB35: =IFERROR(subQ!AB29/subQ!AA29-1,"")
A36: drv:CAPEX | B36: yoy | C36: CAPEX YoY | J36: =IFERROR(subQ!J30/subQ!E30-1,"") | L36: =IFERROR(subQ!L30/subQ!G30-1,"") | M36: =IFERROR(subQ!M30/subQ!H30-1,"") | N36: =IFERROR(subQ!N30/subQ!I30-1,"") | O36: =IFERROR(subQ!O30/subQ!J30-1,"") | Q36: =IFERROR(subQ!Q30/subQ!L30-1,"") | R36: =IFERROR(subQ!R30/subQ!M30-1,"") | S36: =IFERROR(subQ!S30/subQ!N30-1,"") | T36: =IFERROR(subQ!T30/subQ!O30-1,"") | V36: =IFERROR(subQ!V30/subQ!Q30-1,"") | W36: =IFERROR(subQ!W30/subQ!R30-1,"") | X36: =IFERROR(subQ!X30/subQ!S30-1,"") | Y36: =IFERROR(subQ!Y30/subQ!T30-1,"") | AA36: =IFERROR(subQ!AA30/subQ!V30-1,"") | AB36: =IFERROR(subQ!AB30/subQ!W30-1,"") | AC36: -0.078054236 | AD36: -0.32138768 | AF36: 1.0178982 | AG36: 0.092489521 | AH36: 0 | AI36: 0 | AK36: 0 | AL36: 0 | AM36: 0 | AN36: 0
A37: drv:영업활동현금흐름 | B37: yoy | C37: 영업활동현금흐름 YoY | J37: =IFERROR(subQ!J31/subQ!E31-1,"") | L37: =IFERROR(subQ!L31/subQ!G31-1,"") | M37: =IFERROR(subQ!M31/subQ!H31-1,"") | N37: =IFERROR(subQ!N31/subQ!I31-1,"") | O37: =IFERROR(subQ!O31/subQ!J31-1,"") | Q37: =IFERROR(subQ!Q31/subQ!L31-1,"") | R37: =IFERROR(subQ!R31/subQ!M31-1,"") | S37: =IFERROR(subQ!S31/subQ!N31-1,"") | T37: =IFERROR(subQ!T31/subQ!O31-1,"") | V37: =IFERROR(subQ!V31/subQ!Q31-1,"") | W37: =IFERROR(subQ!W31/subQ!R31-1,"") | X37: =IFERROR(subQ!X31/subQ!S31-1,"") | Y37: =IFERROR(subQ!Y31/subQ!T31-1,"") | AA37: =IFERROR(subQ!AA31/subQ!V31-1,"") | AB37: =IFERROR(subQ!AB31/subQ!W31-1,"")
A38: drv:주식수 | B38: qoq | C38: 주식수 QoQ | G38: =IFERROR(subQ!G32/subQ!E32-1,"") | H38: =IFERROR(subQ!H32/subQ!G32-1,"") | I38: =IFERROR(subQ!I32/subQ!H32-1,"") | J38: =IFERROR(subQ!J32/subQ!I32-1,"") | L38: =IFERROR(subQ!L32/subQ!J32-1,"") | M38: =IFERROR(subQ!M32/subQ!L32-1,"") | N38: =IFERROR(subQ!N32/subQ!M32-1,"") | O38: =IFERROR(subQ!O32/subQ!N32-1,"") | Q38: =IFERROR(subQ!Q32/subQ!O32-1,"") | R38: =IFERROR(subQ!R32/subQ!Q32-1,"") | S38: =IFERROR(subQ!S32/subQ!R32-1,"") | T38: =IFERROR(subQ!T32/subQ!S32-1,"") | V38: =IFERROR(subQ!V32/subQ!T32-1,"") | W38: =IFERROR(subQ!W32/subQ!V32-1,"") | X38: =IFERROR(subQ!X32/subQ!W32-1,"") | Y38: =IFERROR(subQ!Y32/subQ!X32-1,"") | AA38: =IFERROR(subQ!AA32/subQ!Y32-1,"") | AB38: =IFERROR(subQ!AB32/subQ!AA32-1,"") | AC38: 0 | AD38: 0 | AF38: 0 | AG38: 0 | AH38: 0 | AI38: 0 | AK38: 0 | AL38: 0 | AM38: 0 | AN38: 0
A39: drv:DPS | B39: abs | C39: DPS (가정, 원) | E39: =subQ!E35 | F39: =subQ!F35 | G39: =subQ!G35 | H39: =subQ!H35 | I39: =subQ!I35 | J39: =subQ!J35 | K39: =subQ!K35 | L39: =subQ!L35 | ... AB39: =subQ!AB35 | AD39: 0 | AE39: =subQ!AE35 | AI39: 0 | AJ39: =subQ!AJ35 | AN39: 0 | AO39: =subQ!AO35
A40: drv:매출조선 | B40: sls_link | C40: 원장 밖 잔고 소진(억원) — 매출조선 = SLS 원화/100 + 이 행 + 매출조선신규 | E40: =IFERROR(subQ!E38-SLS!O107/100,"") | G40: =IFERROR(subQ!G38-SLS!P107/100,"") | H40: =IFERROR(subQ!H38-SLS!Q107/100,"") | I40: =IFERROR(subQ!I38-SLS!R107/100,"") | J40: =IFERROR(subQ!J38-SLS!S107/100,"") | L40: =IFERROR(subQ!L38-SLS!T107/100,"") | M40: =IFERROR(subQ!M38-SLS!U107/100,"") | N40: =IFERROR(subQ!N38-SLS!V107/100,"") | O40: =IFERROR(subQ!O38-SLS!W107/100,"") | Q40: =IFERROR(subQ!Q38-SLS!X107/100,"") | R40: =IFERROR(subQ!R38-SLS!Y107/100,"") | S40: =IFERROR(subQ!S38-SLS!Z107/100,"") | T40: =IFERROR(subQ!T38-SLS!AA107/100,"") | V40: =IFERROR(subQ!V38-SLS!AB107/100,"") | W40: =IFERROR(subQ!W38-SLS!AC107/100,"") | X40: =IFERROR(subQ!X38-SLS!AD107/100,"") | Y40: =IFERROR(subQ!Y38-SLS!AE107/100,"") | AA40: =IFERROR(subQ!AA38-SLS!AF107/100,"") | AB40: =IFERROR(subQ!AB38-SLS!AG107/100,"") | AC40: 27459.151 | AD40: 29203.284 | AF40: 29130.658 | AG40: 29163.549 | AH40: 29196.571 | AI40: 29196.566 | AK40: 29163.558 | AL40: 15338.36 | AM40: 3035.4749 | AN40: 3035.5571
A41: drv:매출조선신규 | B41: abs | C41: 매출조선신규 (forecast_panel base · 공시 상계 신규수주 매출, 억원 — 가정) | E41: =subQ!E39 | F41: =subQ!F39 | G41: =subQ!G39 | H41: =subQ!H39 | I41: =subQ!I39 | J41: =subQ!J39 | K41: =subQ!K39 | L41: =subQ!L39 | ... AB41: =subQ!AB39 | AC41: 0 | AD41: 0 | AE41: =subQ!AE39 | AF41: 525.42 | AG41: 1989.58 | AH41: 4224.28 | AI41: 7061.37 | AJ41: =subQ!AJ39 | AK41: 10332.65 | AL41: 13869.95 | AM41: 17505.09 | AN41: 21069.91 | AO41: =subQ!AO39
A42: drv:OP조선 | B42: ratio | C42: OP조선 마진(/매출조선) | E42: =IFERROR(subQ!E40/subQ!E38,"") | F42: =IFERROR(subQ!F40/subQ!F38,"") | G42: =IFERROR(subQ!G40/subQ!G38,"") | H42: =IFERROR(subQ!H40/subQ!H38,"") | I42: =IFERROR(subQ!I40/subQ!I38,"") | J42: =IFERROR(subQ!J40/subQ!J38,"") | K42: =IFERROR(subQ!K40/subQ!K38,"") | L42: =IFERROR(subQ!L40/subQ!L38,"") | ... AB42: =IFERROR(subQ!AB40/subQ!AB38,"") | AC42: 0.11883145 | AD42: 0.11900748 | AE42: =IFERROR(subQ!AE40/subQ!AE38,"") | AF42: 0.12023067 | AG42: 0.12088259 | AH42: 0.12088124 | AI42: 0.12089326 | AJ42: =IFERROR(subQ!AJ40/subQ!AJ38,"") | AK42: 0.12079303 | AL42: 0.12079985 | AM42: 0.12086983 | AN42: 0.12089018 | AO42: =IFERROR(subQ!AO40/subQ!AO38,"")
A43: drv:매출기타 | B43: yoy | C43: 매출기타 YoY | J43: =IFERROR(subQ!J42/subQ!E42-1,"") | L43: =IFERROR(subQ!L42/subQ!G42-1,"") | M43: =IFERROR(subQ!M42/subQ!H42-1,"") | N43: =IFERROR(subQ!N42/subQ!I42-1,"") | O43: =IFERROR(subQ!O42/subQ!J42-1,"") | Q43: =IFERROR(subQ!Q42/subQ!L42-1,"") | R43: =IFERROR(subQ!R42/subQ!M42-1,"") | S43: =IFERROR(subQ!S42/subQ!N42-1,"") | T43: =IFERROR(subQ!T42/subQ!O42-1,"") | V43: =IFERROR(subQ!V42/subQ!Q42-1,"") | W43: =IFERROR(subQ!W42/subQ!R42-1,"") | X43: =IFERROR(subQ!X42/subQ!S42-1,"") | Y43: =IFERROR(subQ!Y42/subQ!T42-1,"") | AA43: =IFERROR(subQ!AA42/subQ!V42-1,"") | AB43: =IFERROR(subQ!AB42/subQ!W42-1,"") | AC43: -0.5000059 | AD43: -0.69953138 | AF43: 0 | AG43: 0 | AH43: 0 | AI43: 0 | AK43: 0 | AL43: 0 | AM43: 0 | AN43: 0
A44: drv:OP기타 | B44: ratio | C44: OP기타 마진(/매출기타) | E44: =IFERROR(subQ!E43/subQ!E42,"") | F44: =IFERROR(subQ!F43/subQ!F42,"") | G44: =IFERROR(subQ!G43/subQ!G42,"") | H44: =IFERROR(subQ!H43/subQ!H42,"") | I44: =IFERROR(subQ!I43/subQ!I42,"") | J44: =IFERROR(subQ!J43/subQ!J42,"") | K44: =IFERROR(subQ!K43/subQ!K42,"") | L44: =IFERROR(subQ!L43/subQ!L42,"") | ... AB44: =IFERROR(subQ!AB43/subQ!AB42,"") | AC44: 0.11882403 | AD44: 0.11901279 | AE44: =IFERROR(subQ!AE43/subQ!AE42,"") | AF44: 0.12023972 | AG44: 0.12087679 | AH44: 0.12087679 | AI44: 0.12090038 | AJ44: =IFERROR(subQ!AJ43/subQ!AJ42,"") | AK44: 0.12078241 | AL44: 0.120806 | AM44: 0.12087679 | AN44: 0.12090038 | AO44: =IFERROR(subQ!AO43/subQ!AO42,"")
B46: 3. 밸류에이션·스칼라 | C46: 노란 셀 = 가정. '연결' 표시는 추정 전 분기 수식이 이 셀을 참조한다는 뜻
A47: sc:종가 | C47: 종가 | D47: 67100 | E47: 원 — 네이버 정규장 종가(aik 확정종가 대조 · aik 74,100원)
A48: sc:기준일 | C48: 기준일 | D48: 20261012 | E48: 종가 기준일
A49: sc:COE | C49: COE | D49: 0.09 | E49: 자기자본비용(가정) — TP 적정 PBR = ROE/COE
A50: sc:PER_lo | C50: PER_lo | D50: 19.2 | E50: PER 밴드 하단(배) — hist_quarterly(분기 평균가 ÷ TTM EPS, 10분기, 25/50/75 백분위)
A51: sc:PER_mid | C51: PER_mid | D51: 26.2 | E51: PER 밴드 중단(배)
A52: sc:PER_hi | C52: PER_hi | D52: 28.7 | E52: PER 밴드 상단(배)
A53: sc:EPS_Y1가중 | C53: EPS_Y1가중 | D53: 0.5 | E53: 12M fwd EPS = FY(last_actual연도)E × w + FY+1E × (1−w) — 기준 분기 2Q 이면 0.5(가정)
A54: sc:세율 | C54: 세율 | D54: 0.0068 | E54: 참고(연결 안 됨: 이월결손 램프(assumptions.tax_schedule, 0.68%→22%) — 분기별 세율 드라이버 행 사용) — 모델 assumptions 값(시작 0.68% → terminal 22%, 2026Q4 까지 유지 → 2027Q1~2028Q4 선형 램프 — 분기별 값은 2절 drv:법인세비용 행) · 최근 8분기 중 세전 > 0 인 7분기(2024Q4~2026Q2) 법인세/세전 중위 0.7%·최근 4분기 중위 -1.2% 가 모두 5% 미만 → 이월결손 공제 중으로 보고 0.7% 를 2026Q4 까지 유지, 2027Q1~2028Q4 선형 램프로 법정세율 근사 22% 수렴
A55: sc:판관비율 | C55: 판관비율 | D55: 0.055591269 | E55: 연결 — 판관비 = 매출액 × 판관비율(역산, 재현 오차 ≤ 0.05억 · 모델 assumptions 0.0556)
A56: sc:지배주주비중 | C56: 지배주주비중 | D56: 0.99996574 | E56: 연결 — 지배주주순이익 = 당기순이익 × 비중(역산, 재현 오차 ≤ 0.05억)
A57: sc:이자율_자산 | C57: 이자율_자산 | D57: 0.057778137 | E57: 연결 — 이자손익 = (전분기 이자발생자산 × 자산이자율 − 전분기 총차입금 × 부채이자율)/4(역산, 재현 오차 ≤ 0.05억 · 모델 assumptions 0.0578)
A58: sc:이자율_부채 | C58: 이자율_부채 | D58: 0.035681768 | E58: 연결 — 같은 수식의 부채 쪽(총차입금 행이 없으면 0)(역산, 재현 오차 ≤ 0.05억 · 모델 assumptions 0.0357)
A59: sc:배당성향 | C59: 배당성향 | D59: 0 | E59: 배당성향(참고 — 모델은 직전 DPS 유지·Q2 지급 가정)
A60: sc:외화순노출_백만$ | C60: 외화순노출_백만$ | E60: 외화 순노출 × Δ기말환율 (외화 시트 방식) — 외화 순노출 미공시(face) → 0 + 표기
A61: sc:헤지비율 | C61: 헤지비율 | D61: 0.1717 | E61: SLS 원화 = Σ 스케줄 × (헤지비율 × 헤지환율 + (1−헤지비율) × 건조시점 환율[원/달러(평균)]) — measured · usd_sell_m ÷ (기말 수주잔고 원화 ÷ 평균약정환율), 2026Q2 정기보고서 위험관리 절 — kship_page.yard_summary 방식
A62: sc:헤지환율_약정 | C62: 헤지환율_약정 | D62: 1472.04 | E62: 정기보고서 평균 약정환율(measured) — 비어 있으면 계약별 수주시점 환율(fx_at_sign)을 쓴다

Sheet BS연결
B1: (백만원) | C1: 이름: BS연결H | E1: 4Q21 | F1: 2021 | G1: 1Q22 | H1: 2Q22 | I1: 3Q22 | J1: 4Q22 | K1: 2022 | L1: 1Q23 | M1: 2Q23 | N1: 3Q23 | O1: 4Q23 | P1: 2023 | Q1: 1Q24 | R1: 2Q24 | S1: 3Q24 | T1: 4Q24 | U1: 2024 | V1: 1Q25 | W1: 2Q25 | X1: 3Q25 | Y1: 4Q25 | Z1: 2025 | AA1: 1Q26 | AB1: 2Q26 | AC1: 3Q26 | AD1: 4Q26 | AE1: 2026 | AF1: 1Q27 | AG1: 2Q27 | AH1: 3Q27 | AI1: 4Q27 | AJ1: 2027 | AK1: 1Q28 | AL1: 2Q28 | AM1: 3Q28 | AN1: 4Q28 | AO1: 2028
B2: 연결 | D2: fin json(kship_fin.py)
B3: 한화오션(연) | C3: UPDATE: 26-10-12 | E3: 1 | F3: 2 | G3: 3 | H3: 4 | I3: 5 | J3: 6 | K3: 7 | L3: 8 | M3: 9 | N3: 10 | O3: 11 | P3: 12 | Q3: 13 | R3: 14 | S3: 15 | T3: 16 | U3: 17 | V3: 18 | W3: 19 | X3: 20 | Y3: 21 | Z3: 22 | AA3: 23 | AB3: 24 | AC3: 25 | AD3: 26 | AE3: 27 | AF3: 28 | AG3: 29 | AH3: 30 | AI3: 31 | AJ3: 32 | AK3: 33 | AL3: 34 | AM3: 35 | AN3: 36 | AO3: 37
B4: Account Code | C4: AccountNAME | E4: 2021.12 | F4: 2021.12A | G4: 2022.03 | H4: 2022.06 | I4: 2022.09 | J4: 2022.12 | K4: 2022.12A | L4: 2023.03 | M4: 2023.06 | N4: 2023.09 | O4: 2023.12 | P4: 2023.12A | Q4: 2024.03 | R4: 2024.06 | S4: 2024.09 | T4: 2024.12 | U4: 2024.12A | V4: 2025.03 | W4: 2025.06 | X4: 2025.09 | Y4: 2025.12 | Z4: 2025.12A | AA4: 2026.03 | AB4: 2026.06 | AC4: 2026.09 | AD4: 2026.12 | AE4: 2026.12A | AF4: 2027.03 | AG4: 2027.06 | AH4: 2027.09 | AI4: 2027.12 | AJ4: 2027.12A | AK4: 2028.03 | AL4: 2028.06 | AM4: 2028.09 | AN4: 2028.12 | AO4: 2028.12A
A5: 1 | C5: 유동자산 | E5: 6481079.2 | F5: 6481079.2 | G5: 6529546.2 | H5: 7600539.7 | I5: 7609361.8 | J5: 7822464.5 | K5: 7822464.5 | L5: 7842922.3 | M5: 9286501.9 | N5: 8707670.1 | O5: 9217523.9 | P5: 9217523.9 | Q5: 9983392.9 | R5: 10812814 | S5: 10676937 | T5: 11246034 | U5: 11246034 | V5: 11568534 | W5: 11517407 | X5: 11387275 | Y5: 12082155 | Z5: 12082155 | AA5: 12289555 | AB5: 11356552
A6: 1 | C6: 현금및현금성자산 | E6: 1778939.7 | F6: 1778939.7 | G6: 1174446.6 | H6: 1106062.7 | I6: 684185.72 | J6: 659721.35 | K6: 659721.35 | L6: 270117.31 | M6: 1564490.4 | N6: 978618.34 | O6: 1799307.8 | P6: 1799307.8 | Q6: 1648803.9 | R6: 1824756.8 | S6: 1016613.3 | T6: 588259.74 | U6: 588259.74 | V6: 973241.31 | W6: 1037648.5 | X6: 429500.56 | Y6: 778471.16 | Z6: 778471.16 | AA6: 1058396.7 | AB6: 1446204.4
A7: 1 | C7: 단기금융상품 | E7: 310692.72 | F7: 310692.72 | G7: 266882.64 | H7: 169595.43 | I7: 466379.27 | J7: 492238.3 | K7: 492238.3
A8: 1 | C8: 단기금융자산 | E8: 310692.72 | F8: 310692.72 | G8: 266882.64 | H8: 169611.58 | I8: 466395.42 | J8: 492254.45 | K8: 492254.45 | AA8: 11835.59 | AB8: 60826.78
A9: 1 | C9: 매출채권및기타채권 | E9: 345121.59 | F9: 345121.59 | G9: 445003 | H9: 401269.91 | I9: 205292.22 | J9: 404741.92 | K9: 404741.92 | L9: 234682.14 | M9: 191888.47 | N9: 257126.78 | O9: 332546.69 | P9: 332546.69 | Q9: 158647.11 | R9: 320681.34 | S9: 714442.7 | T9: 894491.36 | U9: 894491.36 | V9: 1088908.1 | W9: 737068.29 | X9: 869273.09 | Y9: 965182.46 | Z9: 965182.46 | AA9: 849821.3 | AB9: 621607.55
A10: 1 | C10: 계약자산 | E10: 1936517.1 | F10: 1936517.1 | G10: 2295770.7 | H10: 2788096.1 | I10: 2705615 | J10: 2566075 | K10: 2566075 | L10: 2799855.6 | M10: 2587496.3 | N10: 2607014.9 | O10: 2517851.3 | P10: 2517851.3 | Q10: 3463023.3 | R10: 4172601.8 | S10: 4406915 | T10: 4986595.9 | U10: 4986595.9 | V10: 5049134.2 | W10: 5448042.5 | X10: 5457909.1 | Y10: 5506124.9 | Z10: 5506124.9 | AA10: 5455115.3 | AB10: 5899780.6
A11: 1 | C11: 재고자산 | E11: 1139095.9 | F11: 1139095.9 | G11: 1124060.9 | H11: 1711064.1 | I11: 1985849 | J11: 2202075.9 | K11: 2202075.9 | L11: 2509502.7 | M11: 2780399.2 | N11: 3041200 | O11: 2890783.3 | P11: 2890783.3 | Q11: 2977779 | R11: 2834661.6 | S11: 2843596.8 | T11: 2779695.4 | U11: 2779695.4 | V11: 2653888.7 | W11: 2620480.6 | X11: 2781920.6 | Y11: 3040398.5 | Z11: 3040398.5 | AA11: 3103900.7 | AB11: 1583621.9
A12: 1 | C12: 당기법인세자산(선급법인세) | E12: 90.46 | F12: 90.46 | G12: 1024.23 | H12: 3876.31 | I12: 4899 | J12: 5831.76 | K12: 5831.76 | L12: 6660.63 | M12: 2473.87 | N12: 3938.08 | O12: 5494.68 | P12: 5494.68 | Q12: 8246.49 | R12: 5897.16 | S12: 7711.05 | T12: 8632.12 | U12: 8632.12 | V12: 9478.41 | W12: 1977.06 | X12: 2624.95 | Y12: 2126.1 | Z12: 2126.1 | AA12: 1488.07 | AB12: 5511.81
A13: 1 | C13: 기타유동자산 | E13: 773335.85 | F13: 773335.85 | G13: 989546.24 | H13: 1107041.4 | I13: 1255423 | J13: 1288871.6 | K13: 1288871.6 | L13: 1358136.7 | M13: 1439825.9 | N13: 1359720.7 | O13: 1315290.5 | P13: 1315290.5 | Q13: 1337389.5 | R13: 1371864.5 | S13: 1480128.6 | T13: 1597417.1 | U13: 1597417.1 | V13: 1547557.5 | W13: 1579496.4 | X13: 1784388.6 | Y13: 1719764.4 | Z13: 1719764.4 | AA13: 1739483.8 | AB13: 1713534.9
A14: 1 | C14: 매각예정비유동자산및처분자산 | E14: 161964.11 | F14: 161964.11 | G14: 161964.11 | H14: 161964.11 | I14: 282.96 | J14: 282.96 | K14: 282.96
A15: 1 | C15: 비유동자산 | E15: 4142130.3 | F15: 4142130.3 | G15: 4229720 | H15: 4421919.2 | I15: 4889807.6 | J15: 4413200.8 | K15: 4413200.8 | L15: 4476180.1 | M15: 4354243.7 | N15: 4562093 | O15: 4727248.8 | P15: 4727248.8 | Q15: 4911047.2 | R15: 5415567.9 | S15: 5690065.4 | T15: 6597774.8 | U15: 6597774.8 | V15: 6609139.1 | W15: 6786305.9 | X15: 7146651.2 | Y15: 8058758.5 | Z15: 8058758.5 | AA15: 8506992.4 | AB15: 8789634.7
A16: 1 | C16: 장기금융자산 | E16: 233164.7 | F16: 233164.7 | G16: 228342.2 | H16: 78023.41 | I16: 40222.99 | J16: 40246.06 | K16: 40246.06 | M16: 39272.25 | N16: 40704.47 | O16: 39489.68 | P16: 39489.68 | Q16: 41142.97 | R16: 80916.18 | S16: 189040.92 | T16: 254635.47 | U16: 254635.47 | V16: 254224.05 | W16: 268713.11 | X16: 224837.95 | Y16: 190795.74 | Z16: 190795.74 | AA16: 258426.71 | AB16: 258768.03
A17: 1 | C17: 투자자산 | E17: 467405.5 | F17: 467405.5 | G17: 469626.43 | H17: 675758.42 | I17: 1089919.4 | J17: 277304.56 | K17: 277304.56 | L17: 312265.32 | M17: 280519.73 | N17: 247708.23 | O17: 130942.13 | P17: 130942.13 | Q17: 188202.4 | R17: 344053.4 | S17: 354794.18 | T17: 616573.29 | U17: 616573.29 | V17: 594718.5 | W17: 665236.01 | X17: 712876.88 | Y17: 1196058.2 | Z17: 1196058.2 | AA17: 1537413.4 | AB17: 1603017.3
A18: 1 | C18: 종속기업및관계기업투자 | E18: 3989.4 | F18: 3989.4 | G18: 3317.45 | H18: 3151.38 | I18: 3426.68 | J18: 3694.66 | K18: 3694.66 | L18: 3117.16 | M18: 3514.45 | N18: 4021.53 | O18: 4243.08 | P18: 4243.08 | Q18: 3734.04 | R18: 102014.56 | S18: 109742.37 | T18: 324219.32 | U18: 324219.32 | V18: 340494.45 | W18: 396510.09 | X18: 486620.43 | Y18: 1000398.2 | Z18: 1000398.2 | AA18: 1203439.3 | AB18: 1235379.4
A19: 1 | C19: 장기매출채권및기타채권 | E19: 103932.42 | F19: 103932.42 | G19: 189282.71 | H19: 181675.85 | I19: 228283.68 | J19: 203539.47 | K19: 203539.47 | L19: 206740.99 | M19: 204543.59 | N19: 207471.46 | O19: 273802.16 | P19: 273802.16 | Q19: 280814.74 | R19: 294202.34 | S19: 300864.12 | T19: 267215.33 | U19: 267215.33 | V19: 224199.73 | W19: 228172.29 | X19: 356635.77 | Y19: 96905.28 | Z19: 96905.28 | AA19: 95044.24 | AB19: 97716.52
A20: 1 | C20: 비유동확정계약자산 | E20: 230251.4 | F20: 230251.4 | G20: 237966.78 | H20: 594583.63 | I20: 1046269.8 | J20: 233363.84 | K20: 233363.84 | L20: 309148.16 | M20: 237733.03 | N20: 202982.23 | O20: 87209.37 | P20: 87209.37 | Q20: 143325.39 | R20: 161122.66 | S20: 56010.89 | T20: 37718.5 | U20: 37718.5 | AA20: 75547.43 | AB20: 108869.93
A21: 1 | C21: 유형자산 | E21: 3469402.8 | F21: 3469402.8 | G21: 3462311.1 | H21: 3460717.6 | I21: 3477467.3 | J21: 3786679.5 | K21: 3786679.5 | L21: 3779589.1 | M21: 3771452.5 | N21: 4006438.4 | O21: 4062170.7 | P21: 4062170.7 | Q21: 4178534.9 | R21: 4521690.6 | S21: 4555285.7 | T21: 4648353.7 | U21: 4648353.7 | V21: 4721666.7 | W21: 4845759.8 | X21: 5025252.8 | Y21: 5273172.8 | Z21: 5273172.8 | AA21: 5385181.5 | AB21: 5546064.2
A22: 1 | C22: 무형자산 | E22: 1207.78 | F22: 1207.78 | G22: 1549.95 | H22: 1887.38 | I22: 2626.9 | J22: 1532.33 | K22: 1532.33 | L22: 2247.37 | M22: 2482.89 | N22: 3200.92 | O22: 4343.85 | P22: 4343.85 | Q22: 4945.74 | R22: 5828.69 | S22: 236920.02 | T22: 394140.1 | U22: 394140.1 | V22: 393622.22 | W22: 378103.51 | X22: 376918.67 | Y22: 362397.28 | Z22: 362397.28 | AA22: 357671.72 | AB22: 352438.93
A23: 1 | C23: 이연법인세자산 | E23: 352.58 | F23: 352.58 | G23: 62.68 | H23: 419.38 | I23: 193.04 | J23: 267.52 | K23: 267.52 | L23: 90.96 | O23: 164100.77 | P23: 164100.77 | Q23: 164039.62 | R23: 154280.07 | S23: 154367.13 | T23: 506573.93 | U23: 506573.93 | V23: 506573.93 | W23: 498189.16 | X23: 502055.36 | Y23: 949984.61 | Z23: 949984.61 | AA23: 950011.75 | AB23: 965854.76
A24: 1 | C24: 사용권자산 | E24: 82802.61 | F24: 82802.61 | G24: 86151.07 | H24: 81146.6 | I24: 79715.49 | J24: 71585.23 | K24: 71585.23 | L24: 68282.44 | M24: 82580.83 | N24: 84122.07 | O24: 76561.76 | P24: 76561.76 | Q24: 78875.74 | R24: 81362.69 | S24: 73177 | T24: 133041.57 | U24: 133041.57 | V24: 136787.44 | W24: 138515.32 | X24: 140716.69 | Y24: 138173.29 | Z24: 138173.29 | AA24: 124078.23 | AB24: 151508.55
A25: 1 | C25: 기타비유동자산 | E25: 98307.42 | F25: 98307.42 | G25: 105091.93 | H25: 99962.44 | I25: 91317.26 | J25: 143085.17 | K25: 143085.17 | L25: 133912.79 | M25: 95245.03 | N25: 97274.02 | O25: 91889.12 | P25: 91889.12 | Q25: 94509.77 | R25: 95512.76 | S25: 87083.08 | T25: 164918.56 | U25: 164918.56 | V25: 168358.06 | W25: 170845.13 | X25: 172911.7 | Y25: 180240.37 | Z25: 180240.37 | AA25: 181669.77 | AB25: 224542.98
A26: 1 | C26: 자산총계 | E26: 10623210 | F26: 10623210 | G26: 10759266 | H26: 12022459 | I26: 12499169 | J26: 12235665 | K26: 12235665 | L26: 12319102 | M26: 13640746 | N26: 13269763 | O26: 13944773 | P26: 13944773 | Q26: 14894440 | R26: 16228382 | S26: 16367003 | T26: 17843809 | U26: 17843809 | V26: 18177673 | W26: 18303713 | X26: 18533926 | Y26: 20140914 | Z26: 20140914 | AA26: 20796547 | AB26: 20146187
A27: 1 | C27: 유동부채 | E27: 7464467.9 | F27: 7464467.9 | G27: 8148435.4 | H27: 9288994.3 | I27: 10028905 | J27: 10672486 | K27: 10672486 | L27: 10837186 | M27: 8882481.6 | N27: 8104192.6 | O27: 7459444.1 | P27: 7459444.1 | Q27: 8240962.1 | R27: 9540282.7 | S27: 9904381.8 | T27: 10346614 | U27: 10346614 | V27: 10339707 | W27: 10456875 | X27: 10274686 | Y27: 11200499 | Z27: 11200499 | AA27: 10825510 | AB27: 9364479.7
A28: 1 | C28: 단기차입금 | E28: 1137945.7 | F28: 1137945.7 | G28: 1347185.3 | H28: 1424089.7 | I28: 1411648.9 | J28: 1283430.9 | K28: 1283430.9 | L28: 1707126.5 | M28: 713220.26 | N28: 576236.23 | O28: 526449.92 | P28: 526449.92 | Q28: 1713714.7 | R28: 2519938.4 | S28: 3179562.5 | T28: 3237744 | U28: 3237744 | V28: 3371868.6 | W28: 3030820.2 | X28: 3051187.3 | Y28: 3300054.5 | Z28: 3300054.5 | AA28: 3529081.7 | AB28: 3387397.6
A29: 1 | C29: 매입채무및기타채무 | E29: 669851.32 | F29: 669851.32 | G29: 649354.86 | H29: 690954.1 | I29: 720459.37 | J29: 921458.49 | K29: 921458.49 | L29: 919163.14 | M29: 985040.94 | N29: 953132.56 | O29: 1176410.9 | P29: 1176410.9 | Q29: 1152124.3 | R29: 1285395.1 | S29: 1254663.3 | T29: 1671989.5 | U29: 1671989.5 | V29: 1350338.1 | W29: 1525558.9 | X29: 1619500.6 | Y29: 1856322.3 | Z29: 1856322.3 | AA29: 1693852.1 | AB29: 1626179.9
A30: 1 | C30: 유동성장기부채 | E30: 1329495.2 | F30: 1329495.2 | G30: 1360748.2 | H30: 1443944.3 | I30: 1506874 | J30: 1304098.3 | K30: 1304098.3 | L30: 1276920.8
A31: 1 | C31: 계약부채 | E31: 2094172.3 | F31: 2094172.3 | G31: 2277141.9 | H31: 3168104.7 | I31: 3538940 | J31: 4681596.5 | K31: 4681596.5 | L31: 4662527.2 | M31: 5037872.4 | N31: 4631146.7 | O31: 4366249.5 | P31: 4366249.5 | Q31: 4101558.4 | R31: 4552346.1 | S31: 4498055.9 | T31: 4315343.9 | U31: 4315343.9 | V31: 4682275.5 | W31: 5211566 | X31: 4921540 | Y31: 5195941.5 | Z31: 5195941.5 | AA31: 5010726.1 | AB31: 3747953.8
A32: 1 | C32: 단기충당부채 | E32: 1758206.8 | F32: 1758206.8 | G32: 1945101.9 | H32: 1639502.9 | I32: 1738772.5 | J32: 1570254.8 | K32: 1570254.8 | L32: 1295722.6 | M32: 1131567.3 | N32: 817880.83 | O32: 715250.6 | P32: 715250.6 | Q32: 479182.01 | R32: 367066.55 | S32: 314386.63 | T32: 364183.97 | U32: 364183.97 | V32: 242337.4 | W32: 220674.22 | X32: 215275.04 | Y32: 416851.88 | Z32: 416851.88 | AA32: 144786 | AB32: 140709.67
A33: 1 | C33: 당기법인세부채(미지급법인세) | E33: 2336.39 | F33: 2336.39 | G33: 2444.39 | H33: 1045.1 | I33: 1134.74 | J33: 1386.7 | K33: 1386.7 | L33: 1425.36 | M33: 891.6 | N33: 711.69 | O33: 837.31 | P33: 837.31 | Q33: 2559.42 | R33: 2416.28 | S33: 1180.4 | T33: 3007.76 | U33: 3007.76 | V33: 1774.07 | W33: 2184.69 | X33: 3600.88 | Y33: 4896.14 | Z33: 4896.14 | AA33: 4913.69 | AB33: 2854.65
A34: 1 | C34: 기타유동부채 | E34: 402287.76 | F34: 402287.76 | G34: 431136.91 | H34: 601537.43 | I34: 551816.25 | J34: 565985.94 | K34: 565985.94 | L34: 580939.25 | M34: 585268.81 | N34: 591927.09 | O34: 422464.75 | P34: 422464.75 | Q34: 432172.3 | R34: 458795.92 | S34: 491527.18 | T34: 376263.58 | U34: 376263.58 | V34: 297043.49 | W34: 272295.45 | X34: 283238.69 | Y34: 319985.15 | Z34: 319985.15 | AA34: 334609.54 | AB34: 314600.48
A35: 1 | C35: 비유동부채 | E35: 941158.24 | F35: 941158.24 | G35: 884271.99 | H35: 1185083.6 | I35: 1571579 | J35: 818206.99 | K35: 818206.99 | L35: 852856.75 | M35: 2426056.9 | N35: 2491792.8 | O35: 2173171.5 | P35: 2173171.5 | Q35: 2290157.1 | R35: 2350442.5 | S35: 2281849.1 | T35: 2633844.8 | U35: 2633844.8 | V35: 2749394.4 | W35: 2621061.4 | X35: 2783182.8 | Y35: 2765407.8 | Z35: 2765407.8 | AA35: 3145064.3 | AB35: 3253494.8
A36: 1 | C36: 사채 | E36: 111743.39 | F36: 111743.39 | G36: 56393.11
A37: 1 | C37: 장기차입금 | E37: 122512.94 | F37: 122512.94 | G37: 116822.03 | H37: 111833.68 | I37: 116209.29 | J37: 99715.36 | K37: 99715.36 | L37: 93931.58 | M37: 1626788.7 | N37: 1738732.9 | O37: 1664742.4 | P37: 1664742.4 | Q37: 1714421.2 | R37: 1749480.7 | S37: 1708893.8 | T37: 2028126 | U37: 2028126 | V37: 2148801.1 | W37: 1997395.7 | X37: 2121094.7 | Y37: 2346290.4 | Z37: 2346290.4 | AA37: 2613874.1 | AB37: 2650095.3
A38: 1 | C38: 장기매입채무및기타채무 | E38: 6993.08 | F38: 6993.08 | G38: 7112.83 | H38: 4888.31 | I38: 5429.07 | J38: 5244.47 | K38: 5244.47 | L38: 5401.6 | M38: 5431.72 | N38: 5552.15 | O38: 5234.39 | P38: 5234.39 | Q38: 7873 | R38: 11510.58 | S38: 12468.92 | T38: 15320.02 | U38: 15320.02 | V38: 45782.77 | W38: 48419.3 | X38: 68685.18 | Y38: 72938.29 | Z38: 72938.29 | AA38: 80988.66 | AB38: 72323.77
A39: 1 | C39: 장기충당부채 | E39: 334794.55 | F39: 334794.55 | G39: 322340.27 | H39: 360892.5 | I39: 362692.78 | J39: 328991.34 | K39: 328991.34 | L39: 305459.49 | M39: 288476.34 | N39: 244465.91 | O39: 229959.7 | P39: 229959.7 | Q39: 230121.95 | R39: 234804.46 | S39: 232901.09 | T39: 187901.66 | U39: 187901.66 | V39: 188013.52 | W39: 190682.12 | X39: 195341.35 | Y39: 80308.65 | Z39: 80308.65 | AA39: 80927.94 | AB39: 84805.87
A40: 1 | C40: 비유동리스부채 | E40: 61166.93 | F40: 61166.93 | G40: 61499.05 | H40: 56743.12 | I40: 53365.03 | J40: 48605.25 | K40: 48605.25 | L40: 44450.98 | M40: 55958.79 | N40: 55011.27 | O40: 51346.2 | P40: 51346.2 | Q40: 50602.76 | R40: 42414.97 | S40: 37540.68 | T40: 98270.13 | U40: 98270.13 | V40: 100806.86 | W40: 97641.45 | X40: 94814.23 | Y40: 93427.17 | Z40: 93427.17 | AA40: 89058.33 | AB40: 109164.2
A41: 1 | C41: 리스부채 | E41: 61166.93 | F41: 61166.93 | G41: 61499.05 | H41: 56743.12 | I41: 53365.03 | J41: 48605.25 | K41: 48605.25 | L41: 44450.98 | M41: 55958.79 | N41: 55011.27 | O41: 51346.2 | P41: 51346.2 | Q41: 50602.76 | R41: 42414.97 | S41: 37540.68 | T41: 98270.13 | U41: 98270.13 | V41: 100806.86 | W41: 97641.45 | X41: 94814.23 | Y41: 93427.17 | Z41: 93427.17 | AA41: 89058.33 | AB41: 149966.01
A42: 1 | C42: 장기금융부채 | E42: 62229.92 | F42: 62229.92 | G42: 61892.28 | H42: 57027.47 | I42: 53365.03 | J42: 48674.54 | K42: 48674.54 | L42: 44602.83 | M42: 55958.79 | N42: 55011.27 | O42: 51346.2 | P42: 51346.2 | Q42: 50602.76 | R42: 42414.97 | S42: 39826.52 | T42: 98270.13 | U42: 98270.13 | V42: 100806.86 | W42: 97641.45 | X42: 94814.23 | Y42: 98305.2 | Z42: 98305.2 | AA42: 162833.98 | AB42: 221928.05
A43: 1 | C43: 장기파생상품부채 | E43: 1062.99 | F43: 1062.99 | G43: 393.23 | H43: 284.35 | J43: 69.29 | K43: 69.29 | L43: 151.85 | S43: 2285.84 | Y43: 4878.03 | Z43: 4878.03 | AA43: 73775.65 | AB43: 112763.85
A44: 1 | C44: 이연법인세부채 | E44: 63891.94 | F44: 63891.94 | G44: 63929.46 | H44: 77221.08 | I44: 41342.46 | J44: 118975.5 | K44: 118975.5 | L44: 119325.08 | M44: 128397.52 | N44: 141772.34 | O44: 19851.73 | P44: 19851.73 | Q44: 20093.29 | R44: 20263.09 | S44: 19285.18 | T44: 22814.53 | U44: 22814.53 | V44: 23560.75 | W44: 23391.38 | X44: 22733.81 | Y44: 34406.02 | Z44: 34406.02 | AA44: 40774.95 | AB44: 37842.67
A45: 1 | C45: 부채총계 | E45: 8405626.1 | F45: 8405626.1 | G45: 9032707.4 | H45: 10474078 | I45: 11600484 | J45: 11490693 | K45: 11490693 | L45: 11690042 | M45: 11308539 | N45: 10595985 | O45: 9632615.6 | P45: 9632615.6 | Q45: 10531119 | R45: 11890725 | S45: 12186231 | T45: 12980459 | U45: 12980459 | V45: 13089101 | W45: 13077936 | X45: 13057869 | Y45: 13965907 | Z45: 13965907 | AA45: 13970575 | AB45: 12617975
A46: 1 | C46: 지배주주지분 | E46: 2217583.5 | F46: 2217583.5 | G46: 1726558.9 | H46: 1548381 | I46: 898685.87 | J46: 744971.93 | K46: 744971.93 | L46: 629060.1 | M46: 2332207 | N46: 2669774.9 | O46: 4307452.7 | P46: 4307452.7 | Q46: 4358727.7 | R46: 4332926.7 | S46: 4176003.1 | T46: 4858676.1 | U46: 4858676.1 | V46: 5083866.4 | W46: 5221010.5 | X46: 5471256.5 | Y46: 6170251.5 | Z46: 6170251.5 | AA46: 6821190.3 | AB46: 7523412.2
A47: 1 | C47: 자본금 | E47: 541453.34 | F47: 541453.34 | G47: 541453.34 | H47: 541453.34 | I47: 541453.34 | J47: 541453.34 | K47: 541453.34 | L47: 541453.34 | M47: 1089367 | N47: 1089367 | O47: 1536794.5 | P47: 1536794.5 | Q47: 1536794.5 | R47: 1536794.5 | S47: 1537067 | T47: 1537067 | U47: 1537067 | V47: 1537067 | W47: 1537067 | X47: 1537067 | Y47: 1537067 | Z47: 1537067 | AA47: 1537067 | AB47: 1537067
A48: 1 | C48: 자본잉여금 | E48: 16929.21 | F48: 16929.21 | G48: 16929.21 | H48: 16929.21 | I48: 16929.21 | J48: 16929.21 | K48: 16929.21 | L48: 16929.21 | M48: 1600761.6 | N48: 1707154.9 | O48: 2740229.8 | P48: 2740229.8 | Q48: 111751.88 | R48: 111751.88 | S48: 117591.48 | T48: 118688.52 | U48: 118688.52 | V48: 131643.11 | W48: 149889.9 | X48: 153434.15 | Y48: 181868.13 | Z48: 181868.13 | AA48: 207048.01 | AB48: 209082.59
A49: 1 | C49: 기타자본 | E49: 2660477 | F49: 2660477 | G49: 2662471.2 | H49: 2661141.3 | I49: 2613833.8 | J49: 2887300.4 | K49: 2887300.4 | L49: 2892892.8 | M49: 2339632.6 | N49: 2339632.6 | O49: 2339632.6 | P49: 2339632.6 | Q49: 2341308.4 | R49: 2344138.9 | S49: 2339288.8 | T49: 2339288.8 | U49: 2339288.8 | V49: 2339288.8 | W49: 2339288.8 | X49: 2339288.8 | Y49: 2339288.8 | Z49: 2339288.8 | AA49: 2334380.2 | AB49: 2334176.3
A50: 1 | C50: 이익잉여금 | E50: -1001276.2 | F50: -1001276.2 | G50: -1494294.9 | H50: -1671142.9 | I50: -2273530.5 | J50: -2700711 | K50: -2700711 | L50: -2822215.3 | M50: -3256684.5 | N50: -3030709.5 | O50: -2868157.1 | P50: -2868157.1 | Q50: -196345.48 | R50: -230551.14 | S50: -311959.83 | T50: 236448.28 | U50: 236448.28 | V50: 444624.8 | W50: 585536.57 | X50: 846227.71 | Y50: 1551926.2 | Z50: 1551926.2 | AA50: 2031007.6 | AB50: 2703669.9
A51: 1 | C51: 자본총계 | E51: 2217583.5 | F51: 2217583.5 | G51: 1726558.9 | H51: 1548381 | I51: 898685.87 | J51: 744971.93 | K51: 744971.93 | L51: 629060.1 | M51: 2332207 | N51: 2673777.8 | O51: 4312157.1 | P51: 4312157.1 | Q51: 4363321 | R51: 4337656.8 | S51: 4180771.6 | T51: 4863349.9 | U51: 4863349.9 | V51: 5088572.5 | W51: 5225776.4 | X51: 5476057.5 | Y51: 6175007 | Z51: 6175007 | AA51: 6825972.8 | AB51: 7528212.3
A52: 1 | C52: 부채와자본총계 | E52: 10623210 | F52: 10623210 | G52: 10759266 | H52: 12022459 | I52: 12499169 | J52: 12235665 | K52: 12235665 | L52: 12319102 | M52: 13640746 | N52: 13269763 | O52: 13944773 | P52: 13944773 | Q52: 14894440 | R52: 16228382 | S52: 16367003 | T52: 17843809 | U52: 17843809 | V52: 18177673 | W52: 18303713 | X52: 18533926 | Y52: 20140914 | Z52: 20140914 | AA52: 20796547 | AB52: 20146187
A53: 1 | C53: 총차입금 | E53: 2701697.3 | F53: 2701697.3 | G53: 2881148.6 | H53: 2979867.7 | I53: 3034732.1 | J53: 2687244.6 | K53: 2687244.6 | L53: 3077978.9 | M53: 2340008.9 | N53: 2314969.1 | O53: 2191192.4 | P53: 2191192.4 | Q53: 3428135.9 | R53: 4269419.1 | S53: 4888456.3 | T53: 5265870.1 | U53: 5265870.1 | V53: 5520669.8 | W53: 5028215.9 | X53: 5172282 | Y53: 5646345 | Z53: 5646345 | AA53: 6142955.9 | AB53: 6037493
A54: 1 | C54: 순차입금 | E54: 612064.89 | F54: 612064.89 | G54: 1439819.4 | H54: 1704193.4 | I54: 1884151 | J54: 1535268.8 | K54: 1535268.8 | L54: 2807861.5 | M54: 775518.56 | N54: 1336350.8 | O54: 391884.62 | P54: 391884.62 | Q54: 1779332 | R54: 2444662.3 | S54: 3871842.9 | T54: 4677610.3 | U54: 4677610.3 | V54: 4547428.5 | W54: 3990567.4 | X54: 4742781.5 | Y54: 4867873.8 | Z54: 4867873.8 | AA54: 5072723.6 | AB54: 4530461.8
A55: 1 | C55: 이자발생자산 | E55: 2322797.1 | F55: 2322797.1 | G55: 1669671.4 | H55: 1353697.7 | I55: 1190804.1 | J55: 1192221.9 | K55: 1192221.9 | L55: 270117.31 | M55: 1603762.6 | N55: 1019322.8 | O55: 1838797.4 | P55: 1838797.4 | Q55: 1689946.9 | R55: 1905672.9 | S55: 1205654.3 | T55: 842895.21 | U55: 842895.21 | V55: 1227465.4 | W55: 1306361.6 | X55: 654338.51 | Y55: 969266.9 | Z55: 969266.9 | AA55: 1328659 | AB55: 1765799.2
A56: 1 | C56: 기타유동금융부채 | H56: 25751.28 | I56: 50921.84 | J56: 31440.48 | K56: 31440.48 | L56: 28739.37 | M56: 16702.79
A57: 1 | C57: 단기금융부채 | H57: 25751.28 | I57: 50921.84 | J57: 31440.48 | K57: 31440.48 | L57: 28739.37 | M57: 16702.79 | W57: 155113.83 | X57: 142423.97 | Y57: 68957.1 | Z57: 68957.1 | AA57: 74104.37 | AB57: 144534.63
A58: 1 | C58: 기타유동금융자산 | L58: 427146.69 | M58: 442305.34 | N58: 112800.78 | O58: 124947.86 | P58: 124947.86 | Q58: 135970.66 | R58: 48489.08 | S58: 20699.87 | T58: 46003.53 | U58: 46003.53 | V58: 15219.09 | W58: 9163.17 | X58: 11472.76 | Y58: 10204.24 | Z58: 10204.24 | AA58: 14360.34 | AB58: 25464.24
A59: 1 | C59: 단기금융부채(face) | M59: 713220.26 | N59: 576236.23 | O59: 526449.92 | P59: 526449.92 | Q59: 1713714.7 | R59: 2519938.4 | S59: 3179562.5 | T59: 3237744 | U59: 3237744 | V59: 3371868.6 | W59: 3030820.2 | X59: 3051187.3 | Y59: 3300054.5 | Z59: 3300054.5 | AA59: 3529081.7 | AB59: 3387397.6
A60: 1 | C60: 장기금융부채(face) | M60: 1626788.7 | T60: 2028126 | U60: 2028126 | V60: 2148801.1 | W60: 1997395.7 | X60: 2121094.7 | Y60: 2346290.4 | Z60: 2346290.4 | AA60: 2613874.1 | AB60: 2650095.3
A61: 1 | C61: 기타포괄이익누계액 | M61: 559130.37 | N61: 564329.98 | O61: 558952.94 | P61: 558952.94 | Q61: 565218.41 | R61: 570792.59 | S61: 494015.74 | T61: 627183.51 | U61: 627183.51 | V61: 631242.74 | W61: 609228.28 | X61: 595238.89 | Y61: 560101.42 | Z61: 560101.42 | AA61: 711687.51 | AB61: 739416.48
A62: 1 | C62: 비지배주주지분 | N62: 4002.94 | O62: 4704.47 | P62: 4704.47 | Q62: 4593.27 | R62: 4730.03 | S62: 4768.43 | T62: 4673.82 | U62: 4673.82 | V62: 4706.11 | W62: 4765.92 | X62: 4800.95 | Y62: 4755.45 | Z62: 4755.45 | AA62: 4782.51 | AB62: 4800.08
A63: 1 | C63: 확정급여부채 | V63: 85122.85 | W63: 86777.56 | X63: 88520.34 | Y63: 119161.33 | Z63: 119161.33 | AA63: 121099.73 | AB63: 185016.91
A64: 1 | C64: 비유동파생상품자산 | W64: 12.81 | X64: 1418.5 | Y64: 4864.26 | Z64: 4864.26
A65: 1 | C65: 단기파생상품부채 | W65: 155113.83 | X65: 142423.97 | Y65: 68957.1 | Z65: 68957.1 | AA65: 74104.37 | AB65: 103732.82
A66: 1 | C66: 유동파생상품자산 | AA66: 11835.59 | AB66: 14682.83
A67: 1 | C67: 유동확정계약자산 | AB67: 46143.95
A68: 1 | C68: 유동리스부채 | AB68: 40801.81
A69: 1 | C69: 매출액(수익) | E69: 1355717.1 | G69: 1245450.6 | H69: 1184054.4 | I69: 981451.63 | J69: 1449193.5 | K69: 4860150.2 | L69: 1439835.4 | M69: 1820700.7 | N69: 1916837.2 | O69: 2230938.9 | P69: 7408312.3 | Q69: 2283627.1 | R69: 2536090.8 | S69: 2703108.9 | T69: 3253178.1 | U69: 10776005 | V69: 3143089.5 | W69: 3294113.5 | X69: 3023357.9 | Y69: 3322951.5 | Z69: 12783512 | AA69: 3209940.2 | AB69: 5443171.5
A70: 1 | C70: 매출원가 | E70: 1802832.8 | G70: 1659893.5 | H70: 1219428.9 | I70: 1548191.2 | J70: 1779518.8 | K70: 6207032.5 | L70: 1446589.8 | M70: 1893734.8 | N70: 1774958 | O70: 2194221.2 | P70: 7309503.8 | Q70: 2148520.2 | R70: 2459322.5 | S70: 2570106.7 | T70: 2914129.3 | U70: 10092079 | V70: 2720749.4 | W70: 2766608 | X70: 2569308.1 | Y70: 2886548.9 | Z70: 10943214 | AA70: 2583679.5 | AB70: 4493612.1
A71: 1 | C71: 매출총이익 | E71: -447115.72 | G71: -414442.91 | H71: -35374.47 | I71: -566739.62 | J71: -330325.28 | K71: -1346882.3 | L71: -6754.33 | M71: -73034.08 | N71: 141879.17 | O71: 36717.69 | P71: 98808.45 | Q71: 135106.89 | R71: 76768.33 | S71: 133002.18 | T71: 339048.83 | U71: 683926.23 | V71: 422340.15 | W71: 527505.5 | X71: 454049.75 | Y71: 436402.6 | Z71: 1840298 | AA71: 626260.73 | AB71: 949559.42
A72: 1 | C72: 판관비 | E72: 68219.78 | G72: 55662.48 | H72: 64133.72 | I72: 61079.18 | J72: 85806.88 | K72: 266682.26 | L72: 56040.41 | M72: 85975.65 | N72: 67744.58 | O72: 85546.1 | P72: 295306.74 | Q72: 82170.62 | R72: 86427.02 | S72: 107420.65 | T72: 170031.56 | U72: 446049.85 | V72: 163731.98 | W72: 155801.85 | X72: 164290.54 | Y72: 188883.48 | Z72: 672707.85 | AA72: 185195.61 | AB72: 213445.78
A73: 1 | C73: 영업이익 | E73: -515335.5 | G73: -470105.39 | H73: -99508.19 | I73: -627818.8 | J73: -416132.15 | K73: -1613564.5 | L73: -62794.75 | M73: -159009.73 | N73: 74134.58 | Q73: 52936.27 | R73: -9658.69 | S73: 25581.53 | T73: 169017.27 | U73: 237876.38 | V73: 258608.17 | W73: 371703.65 | X73: 289759.21 | Y73: 247519.12 | Z73: 1167590.1 | AA73: 441065.12 | AB73: 736113.64
A74: 1 | C74: 금융수익 | E74: 32326.26 | G74: 84990.13 | H74: 182181.81 | I74: 286338.6 | J74: -13382.55 | K74: 540127.99 | L74: 195057.33 | M74: 88427.42 | N74: 188976.27 | O74: 80217.71 | P74: 552678.73 | Q74: 303207.17 | R74: 41316.34 | S74: -11215.92 | T74: 363192.87 | U74: 696500.46 | V74: 135685.01 | W74: 398614.68 | X74: -39683.94 | Y74: 147942.3 | Z74: 642558.05 | AA74: 430821.32 | AB74: 186387.59
A75: 1 | C75: 금융비용 | E75: 84074.39 | G75: 159855.07 | H75: 756892.75 | I75: 1169912 | J75: -949616.59 | K75: 1137043.2 | L75: 437292.19 | M75: 243231.05 | N75: 326552.74 | O75: -108182.88 | P75: 898893.1 | Q75: 478115.2 | R75: 146284.99 | S75: -21896.44 | T75: 569685.79 | U75: 1172189.5 | V75: 179662.64 | W75: 530933.86 | X75: -42642.23 | Y75: 99017.93 | Z75: 766972.2 | AA75: 459011.23 | AB75: 269057.3
A76: 1 | C76: 기타영업외수익 | E76: 181067.85 | G76: 71928.09 | H76: 512228.61 | I76: 834614.45 | J76: -908154.13 | K76: 510617.02 | L76: 193705.35 | M76: 82638.04 | N76: 306853.12 | O76: -28147.88 | P76: 555048.63 | Q76: 178304.91 | R76: 92630.85 | S76: -107919.08 | T76: 341249.83 | U76: 504266.51 | V76: 28721.13 | W76: 2742.97 | X76: 9727.05 | Y76: 19933.87 | Z76: 61125.02 | AA76: 160253.64 | AB76: 60198.21
A77: 1 | C77: 기타영업외비용 | E77: 23328.25 | G77: 18291.92 | H77: 13600.81 | I77: 5784.43 | J77: 57016.17 | K77: 94693.33 | L77: 8961.63 | M77: 6105.84 | N77: 12316.52 | O77: 102729.55 | P77: 130113.54 | Q77: 2771.41 | R77: 3518.77 | S77: 8382.2 | T77: 86197.16 | U77: 100869.54 | V77: 28662.46 | W77: 80449.56 | X77: 11912.51 | Y77: 63900.2 | Z77: 184924.73 | AA77: 19900.51 | AB77: 2395.31
A78: 1 | C78: 종속기업,공동지배기업및관계기업관련손익 | E78: -197.59 | G78: -147.55 | H78: -166.07 | I78: 275.3 | J78: 267.97 | K78: 229.65 | L78: 372.5 | M78: 397.3 | N78: 507.08 | O78: 221.54 | P78: 1498.42 | Q78: 364.96 | R78: 358.25 | S78: 7111.04 | T78: 7616.56 | U78: 15450.81 | V78: 2503.39 | W78: -10936.61 | X78: -17933.14 | Y78: -50640.36 | Z78: -77006.72 | AA78: -46783.21 | AB78: -42722.72
A79: 1 | C79: 지분법관련손익 | E79: -197.59 | G79: -147.55 | H79: -166.07 | I79: 275.3 | J79: 267.97 | K79: 229.65 | L79: 372.5 | M79: 397.3 | N79: 507.08 | O79: 221.54 | P79: 1498.42 | Q79: 364.96 | R79: 358.25 | S79: 7111.04 | T79: 7616.56 | U79: 15450.81 | V79: 2503.39 | W79: -10936.61 | X79: -17933.14 | Y79: -50640.36 | Z79: -77006.72 | AA79: -46783.21 | AB79: -42722.72
A80: 1 | C80: 법인세비용차감전계속사업이익 | E80: -409541.62 | G80: -491481.72 | H80: -175757.39 | I80: -682286.89 | J80: -444800.44 | K80: -1794326.4 | L80: -119913.39 | M80: -236883.87 | N80: 231601.79 | O80: 8916.3 | P80: -116279.17 | Q80: 53926.71 | R80: -25157.02 | S80: -72928.19 | T80: 225193.57 | U80: 181035.07 | V80: 217192.61 | W80: 150741.27 | X80: 272598.9 | Y80: 201836.79 | Z80: 842369.57 | AA80: 506445.12 | AB80: 668524.12
A81: 1 | C81: 법인세비용 | E81: -11139.89 | G81: 316.21 | H81: 324.47 | I81: -35659.11 | J81: -14529.56 | K81: -49547.99 | L81: 495.62 | M81: 326.36 | N81: -3.91 | O81: -277141.11 | P81: -276323.04 | Q81: 2905.83 | R81: 2225.89 | S81: 1918.78 | T81: -354228.33 | U81: -347177.83 | V81: 1466.69 | W81: 2265.15 | X81: 3211.73 | Y81: -410495.54 | Z81: -403551.97 | AA81: 6408.4 | AB81: -24064.98
A82: 1 | C82: 당기순이익 | E82: -398401.72 | G82: -491797.92 | H82: -176081.86 | I82: -646627.78 | J82: -430270.88 | K82: -1744778.4 | L82: -120409.02 | M82: -237210.23 | N82: 231605.7 | O82: 286057.4 | P82: 160043.85 | Q82: 51020.88 | R82: -27382.91 | S82: -74846.97 | T82: 579421.9 | U82: 528212.9 | V82: 215725.91 | W82: 148476.12 | X82: 269387.17 | Y82: 612332.33 | Z82: 1245921.5 | AA82: 500036.73 | AB82: 692589.09
A83: 1 | C83: (지배주주지분)당기순이익 | E83: -398401.72 | G83: -491797.92 | H83: -176081.86 | I83: -646627.78 | J83: -430270.88 | K83: -1744778.4 | L83: -120409.02 | M83: -237210.23 | N83: 231519.94 | O83: 285985.26 | P83: 159885.95 | Q83: 51034.87 | R83: -27519.67 | S83: -74885.37 | T83: 579489.28 | U83: 528119.11 | V83: 215693.63 | W83: 148431.76 | X83: 269352.29 | Y83: 612360.82 | Z83: 1245838.5 | AA83: 500005.98 | AB83: 692571.51
A84: 1 | C84: 금융손익 | E84: -51748.13 | G84: -74864.94 | H84: -574710.94 | I84: -883573.41 | J84: 936234.04 | K84: -596915.25 | L84: -242234.86 | M84: -154803.63 | N84: -137576.47 | O84: 188400.59 | P84: -346214.37 | Q84: -174908.03 | R84: -104968.65 | S84: 10680.52 | T84: -206492.92 | U84: -475689.08 | V84: -43977.63 | W84: -132319.18 | X84: 2958.29 | Y84: 48924.37 | Z84: -124414.15 | AA84: -28189.91 | AB84: -82669.71
A85: 1 | C85: 기타영업외손익 | E85: 157739.6 | G85: 53636.17 | H85: 498627.8 | I85: 828830.02 | J85: -965170.3 | K85: 415923.69 | L85: 184743.72 | M85: 76532.2 | N85: 294536.6 | O85: -130877.43 | P85: 424935.09 | Q85: 175533.5 | R85: 89112.08 | S85: -116301.28 | T85: 255052.67 | U85: 403396.97 | V85: 58.67 | W85: -77706.59 | X85: -2185.46 | Y85: -43966.33 | Z85: -123799.71 | AA85: 140353.13 | AB85: 57802.9
A86: 1 | C86: 계속사업이익 | E86: -398401.72 | G86: -491797.92 | H86: -176081.86 | I86: -646627.78 | J86: -430270.88 | K86: -1744778.4 | L86: -120409.02 | M86: -237210.23 | N86: 231605.7 | O86: 286057.4 | P86: 160043.85 | Q86: 51020.88 | R86: -27382.91 | S86: -74846.97 | T86: 579421.9 | U86: 528212.9 | V86: 215725.91 | W86: 148476.12 | X86: 269387.17 | Y86: 612332.33 | Z86: 1245921.5 | AA86: 500036.73 | AB86: 692589.09
A87: 1 | C87: 총포괄손익 | E87: -359954.48 | G87: -491024.59 | H87: -178177.9 | I87: -649695.09 | J87: -153713.94 | K87: -1472611.5 | L87: -115911.83 | M87: -294106.79 | N87: 237092.44 | Q87: 55529.22 | R87: -22662.65 | S87: -152315.06 | T87: 687847.89 | U87: 568399.4 | V87: 218098.6 | W87: 124783.11 | X87: 252585.49 | Y87: 671020.3 | Z87: 1266487.5 | AA87: 636529.59 | AB87: 706240.87
A88: 1 | C88: 이자수익 | G88: 14338 | H88: 14445 | I88: 17751 | J88: 19659 | K88: 66193 | L88: 24009 | M88: 18134 | N88: 24644 | O88: 50977 | P88: 117764 | Q88: 22627 | R88: 24380 | S88: 19162 | T88: -1895 | U88: 64274 | V88: 17967 | W88: 17323 | X88: 11726 | Y88: 28820 | Z88: 75836 | AA88: 9995 | AB88: 17609
A89: 1 | C89: 배당금수익 | G89: 46 | H89: 15 | I89: 0 | J89: 0 | K89: 61 | L89: 65 | M89: 8 | N89: 0 | O89: 0 | P89: 73 | Q89: 42 | R89: 138 | S89: 24 | T89: -24 | U89: 180 | V89: 19 | W89: 1 | X89: 2 | Y89: 7 | Z89: 29 | AA89: 172 | AB89: 1
A90: 1 | C90: 이자비용 | G90: 25198 | H90: 27463 | I90: 32927 | J90: 36227 | K90: 121815 | L90: 41593 | M90: 41735 | N90: 35878 | O90: 39827 | P90: 159033 | Q90: 38982 | R90: 50689 | S90: 51808 | T90: 31036 | U90: 172515 | V90: 51493 | W90: 52609 | X90: 52080 | Y90: 39548 | Z90: 195730 | AA90: 56339 | AB90: 57194
A91: 1 | C91: 외환차익 | G91: 40349 | H91: 82858 | I91: 191808 | J91: 86685 | K91: 401700 | L91: 97721 | M91: 90052 | N91: 117712 | O91: 72732 | P91: 378217 | Q91: 196178 | R91: -22099 | S91: 60422 | T91: 142740 | U91: 377241 | V91: 86914 | W91: 77318 | X91: 50378 | Y91: 137811 | Z91: 352421 | AA91: 170749 | AB91: 123524
A92: 1 | C92: 외환차손 | G92: 16300 | H92: 69798 | I92: 134593 | J92: 98313 | K92: 319004 | L92: 88769 | M92: 77002 | N92: 82041 | O92: 67542 | P92: 315354 | Q92: 147113 | R92: -79298 | S92: 76480 | T92: 87226 | U92: 231521 | V92: 100622 | W92: 189793 | X92: 103540 | Y92: 84738 | Z92: 478693 | AA92: 89671 | AB92: 75007
A93: 1 | C93: 외화환산이익 | G93: 24927 | H93: 85740 | I93: 72772 | J93: -122079 | K93: 61360 | L93: 62628 | M93: -28149 | N93: 24914 | O93: -54692 | P93: 4701 | Q93: 84015 | R93: 34744 | S93: -94289 | T93: 219930 | U93: 244400 | V93: 29834 | W93: 146180 | X93: -30542 | Y93: -8947 | Z93: 136525 | AA93: 248259 | AB93: 40822
A94: 1 | C94: 외화환산손실 | G94: 43997 | H94: 150361 | I94: 232205 | J94: -230247 | K94: 196316 | L94: 79922 | M94: 11721 | N94: 20088 | O94: -60601 | P94: 51130 | Q94: 78497 | R94: 57386 | S94: -30504 | T94: 150785 | U94: 256164 | V94: 12719 | W94: 303104 | X94: -199276 | Y94: -34343 | Z94: 82204 | AA94: 146145 | AB94: 49400
A95: 1 | C95: 이자손익 | G95: -10860 | H95: -13018 | I95: -15176 | J95: -16568 | K95: -55622 | L95: -17584 | M95: -23601 | N95: -11234 | O95: 11150 | P95: -41269 | Q95: -16355 | R95: -26309 | S95: -32646 | T95: -32931 | U95: -108241 | V95: -33526 | W95: -35286 | X95: -40354 | Y95: -10728 | Z95: -119894 | AA95: -46344 | AB95: -39585
A96: 1 | C96: (비지배주주지분)당기순이익 | N96: 85.76 | O96: 72.14 | Q96: -14 | R96: 136.76 | S96: 38.4 | T96: -67.38 | U96: 93.78 | V96: 32.29 | W96: 44.36 | X96: 34.87 | Y96: -28.48 | Z96: 83.04 | AA96: 30.75 | AB96: 17.58
A97: 1 | C97: 파생상품이익 | W97: 157782 | X97: -71331 | Y97: -9779 | AA97: 1318 | AB97: 3864
A98: 1 | C98: 파생상품손실 | W98: -14573 | X98: 1014 | Y98: 9075 | AA98: 166856 | AB98: 87408
A99: 1 | C99: 영업활동으로인한현금흐름 | E99: 28365.93 | G99: -725825.81 | H99: -279038.48 | I99: -178055.47 | J99: 117487.13 | K99: -1065432.6 | L99: -776346.72 | M99: 18351.27 | N99: -726049.36 | O99: -455110.5 | P99: -1939155.3 | Q99: -1164444.9 | R99: -502494.72 | S99: -982928.98 | T99: -254705.88 | U99: -2904574.5 | V99: 222413.2 | W99: 625473.29 | X99: -340157.92 | Y99: 806943.01 | Z99: 1314671.6 | AA99: 221996.29 | AB99: 818214.29
A100: 1 | C100: 배당금수취(CF) | E100: 0 | G100: 570.89 | H100: 14.85 | I100: 0 | J100: 0 | K100: 585.74 | L100: 950 | M100: 73.25 | N100: 0 | O100: 0 | P100: 1023.25 | Q100: 874 | R100: 180.29 | S100: 23.91 | T100: -23.91 | U100: 1054.29 | X100: 3.19 | Y100: 6.75 | AA100: 121.28 | AB100: 51.64
...

Sheet BS별도
B1: (백만원) | C1: 이름: BS별도H | E1: 4Q21 | F1: 2021 | G1: 1Q22 | H1: 2Q22 | I1: 3Q22 | J1: 4Q22 | K1: 2022 | L1: 1Q23 | M1: 2Q23 | N1: 3Q23 | O1: 4Q23 | P1: 2023 | Q1: 1Q24 | R1: 2Q24 | S1: 3Q24 | T1: 4Q24 | U1: 2024 | V1: 1Q25 | W1: 2Q25 | X1: 3Q25 | Y1: 4Q25 | Z1: 2025 | AA1: 1Q26 | AB1: 2Q26 | AC1: 3Q26 | AD1: 4Q26 | AE1: 2026 | AF1: 1Q27 | AG1: 2Q27 | AH1: 3Q27 | AI1: 4Q27 | AJ1: 2027 | AK1: 1Q28 | AL1: 2Q28 | AM1: 3Q28 | AN1: 4Q28 | AO1: 2028
B2: 별도 | D2: fin json(kship_fin.py)
B3: 한화오션(별) | C3: UPDATE: 26-10-12 | E3: 1 | F3: 2 | G3: 3 | H3: 4 | I3: 5 | J3: 6 | K3: 7 | L3: 8 | M3: 9 | N3: 10 | O3: 11 | P3: 12 | Q3: 13 | R3: 14 | S3: 15 | T3: 16 | U3: 17 | V3: 18 | W3: 19 | X3: 20 | Y3: 21 | Z3: 22 | AA3: 23 | AB3: 24 | AC3: 25 | AD3: 26 | AE3: 27 | AF3: 28 | AG3: 29 | AH3: 30 | AI3: 31 | AJ3: 32 | AK3: 33 | AL3: 34 | AM3: 35 | AN3: 36 | AO3: 37
B4: Account Code | C4: AccountNAME | E4: 2021.12 | F4: 2021.12A | G4: 2022.03 | H4: 2022.06 | I4: 2022.09 | J4: 2022.12 | K4: 2022.12A | L4: 2023.03 | M4: 2023.06 | N4: 2023.09 | O4: 2023.12 | P4: 2023.12A | Q4: 2024.03 | R4: 2024.06 | S4: 2024.09 | T4: 2024.12 | U4: 2024.12A | V4: 2025.03 | W4: 2025.06 | X4: 2025.09 | Y4: 2025.12 | Z4: 2025.12A | AA4: 2026.03 | AB4: 2026.06 | AC4: 2026.09 | AD4: 2026.12 | AE4: 2026.12A | AF4: 2027.03 | AG4: 2027.06 | AH4: 2027.09 | AI4: 2027.12 | AJ4: 2027.12A | AK4: 2028.03 | AL4: 2028.06 | AM4: 2028.09 | AN4: 2028.12 | AO4: 2028.12A
A5: 1 | C5: 유동자산 | E5: 6419034.5 | F5: 6419034.5 | G5: 6471133.1 | H5: 7533299.2 | I5: 7530412.8 | J5: 7738158.4 | K5: 7738158.4 | L5: 7747259.5 | M5: 9179285.2 | N5: 8572249.7 | O5: 9096135.8 | P5: 9096135.8 | Q5: 9801677.7 | R5: 11012667 | S5: 10776728 | T5: 11238634 | U5: 11238634 | V5: 11610034 | W5: 11198945 | X5: 11068721 | Y5: 11799386 | Z5: 11799386 | AA5: 11997575 | AB5: 11119990
A6: 1 | C6: 현금및현금성자산 | E6: 1748494.8 | F6: 1748494.8 | G6: 1151228.9 | H6: 1087001.7 | I6: 657427.68 | J6: 633463.93 | K6: 633463.93 | L6: 237007.28 | M6: 1534482.3 | N6: 954975.09 | O6: 1770497 | P6: 1770497 | Q6: 1588821.7 | R6: 1725153.8 | S6: 887993.05 | T6: 414334.46 | U6: 414334.46 | V6: 762712.6 | W6: 818753.66 | X6: 219142.42 | Y6: 602024.39 | Z6: 602024.39 | AA6: 884912.28 | AB6: 1231282.7
A7: 1 | C7: 단기금융상품 | E7: 291503.12 | F7: 291503.12 | G7: 247348.39 | H7: 152490.45 | I7: 451006.79 | J7: 479194.05 | K7: 479194.05
A8: 1 | C8: 단기금융자산 | E8: 291503.12 | F8: 291503.12 | G8: 247348.39 | H8: 152506.6 | I8: 451022.94 | J8: 479210.2 | K8: 479210.2 | AA8: 11835.59 | AB8: 14682.83
A9: 1 | C9: 매출채권및기타채권 | E9: 345269.04 | F9: 345269.04 | G9: 445066.21 | H9: 402475.13 | I9: 204727.96 | J9: 403485.85 | K9: 403485.85 | L9: 235303.52 | M9: 191266.95 | N9: 254729.22 | O9: 334564.92 | P9: 334564.92 | Q9: 160761.3 | R9: 433357.79 | S9: 700923.3 | T9: 897795.51 | U9: 897795.51 | V9: 1095379.7 | W9: 741005.15 | X9: 832147.03 | Y9: 977825.54 | Z9: 977825.54 | AA9: 859187.67 | AB9: 749539.27
A10: 1 | C10: 계약자산 | E10: 1919963 | F10: 1919963 | G10: 2269458.8 | H10: 2745622 | I10: 2658816.7 | J10: 2515400.1 | K10: 2515400.1 | L10: 2748256.9 | M10: 2536190.1 | N10: 2558208.5 | O10: 2481791.4 | P10: 2481791.4 | Q10: 3396193.3 | R10: 4107241.3 | S10: 4358647 | T10: 4933931.2 | U10: 4933931.2 | V10: 5010517.7 | W10: 5413984 | X10: 5437949.5 | Y10: 5488624.9 | Z10: 5488624.9 | AA10: 5423702.4 | AB10: 5838294.1
A11: 1 | C11: 재고자산 | E11: 1128875.9 | F11: 1128875.9 | G11: 1112559.9 | H11: 1699608 | I11: 1971772.1 | J11: 2190744.4 | K11: 2190744.4 | L11: 2496506 | M11: 2767691.8 | N11: 3007566.7 | O11: 2852678.4 | P11: 2852678.4 | Q11: 2957415.9 | R11: 3128696.1 | S11: 3149764.7 | T11: 3045973.2 | U11: 3045973.2 | V11: 2968494.8 | W11: 2599463.7 | X11: 2753035.8 | Y11: 3021715.7 | Z11: 3021715.7 | AA11: 3093619.9 | AB11: 1592827
A12: 1 | C12: 기타유동자산 | E12: 787642.55 | F12: 787642.55 | G12: 1011710.6 | H12: 1128772.5 | I12: 1280124.5 | J12: 1307209.9 | K12: 1307209.9 | L12: 1372088.2 | M12: 1440032.1 | N12: 1353992.4 | O12: 1311734.4 | P12: 1311734.4 | Q12: 1327728.7 | R12: 1367952.7 | S12: 1474452.9 | T12: 1582054.3 | U12: 1582054.3 | V12: 1521410.4 | W12: 1535558.9 | X12: 1768944.7 | Y12: 1644907.5 | Z12: 1644907.5 | AA12: 1664678.6 | AB12: 1630873.5
A13: 1 | C13: 매각예정비유동자산및처분자산 | E13: 161964.11 | F13: 161964.11 | G13: 161964.11 | H13: 161964.11 | I13: 282.96 | J13: 282.96 | K13: 282.96
A14: 1 | C14: 비유동자산 | E14: 4021762.5 | F14: 4021762.5 | G14: 4107310 | H14: 4297169.3 | I14: 4757264.6 | J14: 4308672 | K14: 4308672 | L14: 4364667.4 | M14: 4248653.8 | N14: 4260477 | O14: 4407021.4 | P14: 4407021.4 | Q14: 4632772.3 | R14: 4834004.9 | S14: 5282975.7 | T14: 6168576.2 | U14: 6168576.2 | V14: 6145995 | W14: 6683540.7 | X14: 7028521.8 | Y14: 7925260.3 | Z14: 7925260.3 | AA14: 8242357 | AB14: 8444164.2
A15: 1 | C15: 장기금융자산 | E15: 233164.7 | F15: 233164.7 | G15: 228342.2 | H15: 78023.41 | I15: 40222.99 | J15: 40246.06 | K15: 40246.06 | M15: 39272.25 | N15: 40653.63 | O15: 39438.84 | P15: 39438.84 | Q15: 40492.13 | R15: 51092.14 | S15: 51684.41 | T15: 55154.82 | U15: 55154.82 | V15: 53416.43 | W15: 53394.9 | X15: 54493.26 | Y15: 54797.44 | Z15: 54797.44 | AA15: 54997.5 | AB15: 54808.07
A16: 1 | C16: 투자자산 | E16: 467092.83 | F16: 467092.83 | G16: 469985.71 | H16: 675996.63 | I16: 1089754.6 | J16: 276540.52 | K16: 276540.52 | L16: 312078.78 | M16: 277005.28 | N16: 243635.86 | O16: 126648.21 | P16: 126648.21 | Q16: 183817.52 | R16: 212214.8 | S16: 107695.3 | T16: 92873.32 | U16: 92873.32 | V16: 53416.43 | W16: 53407.71 | X16: 55911.76 | Y16: 59661.7 | Z16: 59661.7 | AA16: 130544.93 | AB16: 163678
A17: 1 | C17: 종속기업및관계기업투자 | E17: 3676.73 | F17: 3676.73 | G17: 3676.73 | H17: 3389.59 | I17: 3261.85 | J17: 2930.62 | K17: 2930.62 | L17: 2930.62
A18: 1 | C18: 장기매출채권및기타채권 | E18: 103840.03 | F18: 103840.03 | G18: 189211.28 | H18: 181603.42 | I18: 228208.7 | J18: 201864.23 | K18: 201864.23 | L18: 205033.07 | M18: 202868.35 | N18: 205730.54 | O18: 272708.61 | P18: 272708.61 | Q18: 279721.19 | R18: 293002.15 | S18: 299657.43 | T18: 276375.56 | U18: 276375.56 | V18: 233909.93 | W18: 667579.9 | X18: 823921.34 | Y18: 533759.12 | Z18: 533759.12 | AA18: 555503.72 | AB18: 571401.21
A19: 1 | C19: 비유동확정계약자산 | E19: 230251.4 | F19: 230251.4 | G19: 237966.78 | H19: 594583.63 | I19: 1046269.8 | J19: 233363.84 | K19: 233363.84 | L19: 309148.16 | M19: 237733.03 | N19: 202982.23 | O19: 87209.37 | P19: 87209.37 | Q19: 143325.39 | R19: 161122.66 | S19: 56010.89 | T19: 37718.5 | U19: 37718.5 | AA19: 75547.43 | AB19: 108869.93
A20: 1 | C20: 유형자산 | E20: 3375716 | F20: 3375716 | G20: 3365911.8 | H20: 3362698.6 | I20: 3372984.2 | J20: 3709724.7 | K20: 3709724.7 | L20: 3696116.5 | M20: 3693149.4 | N20: 3720090 | O20: 3755171.6 | P20: 3755171.6 | Q20: 3764663.5 | R20: 3785538.1 | S20: 3809674.9 | T20: 3903542.2 | U20: 3903542.2 | V20: 3937946.9 | W20: 4011494.1 | X20: 4099370.9 | Y20: 4273894.1 | Z20: 4273894.1 | AA20: 4298682.2 | AB20: 4357892.4
A21: 1 | C21: 사용권자산 | E21: 59107.24 | F21: 59107.24 | G21: 62155.11 | H21: 56986.19 | I21: 54875.71 | J21: 49181.93 | K21: 49181.93 | L21: 45106.53 | M21: 60260.87 | N21: 55460.18 | O21: 50059.79 | P21: 50059.79 | Q21: 48834.6 | R21: 47343.23 | S21: 41430.49 | T21: 101723.7 | U21: 101723.7 | V21: 99560.12 | W21: 100534.77 | X21: 103592.44 | Y21: 95455.46 | Z21: 95455.46 | AA21: 81419.3 | AB21: 102886.33
A22: 1 | C22: 기타비유동자산 | E22: 72921.31 | F22: 72921.31 | G22: 79388.94 | H22: 74088.56 | I22: 64721.32 | J22: 119102.99 | K22: 119102.99 | L22: 109108.84 | M22: 71383.57 | N22: 66345.52 | O22: 62792.95 | P22: 62792.95 | Q22: 62028.47 | R22: 59493.22 | S22: 53508.65 | T22: 130595.97 | U22: 130595.97 | V22: 129368.88 | W22: 132814.96 | X22: 136472.19 | Y22: 138313.72 | Z22: 138313.72 | AA22: 139965.68 | AB22: 174253.38
A23: 1 | C23: 무형자산 | E23: 670.53 | F23: 670.53 | G23: 1017.11 | H23: 1284.03 | I23: 1595.82 | J23: 647.28 | K23: 647.28 | L23: 996.67 | M23: 1316.61 | N23: 1744.43 | O23: 2877 | P23: 2877 | Q23: 3518.57 | R23: 4277.35 | S23: 235292.98 | T23: 390391.94 | U23: 390391.94 | V23: 389944.2 | W23: 374480.63 | X23: 371858.37 | Y23: 358470.04 | Z23: 358470.04 | AA23: 353394.45 | AB23: 348093.24
A24: 1 | C24: 자산총계 | E24: 10440797 | F24: 10440797 | G24: 10578443 | H24: 11830469 | I24: 12287677 | J24: 12046830 | K24: 12046830 | L24: 12111927 | M24: 13427939 | N24: 12832727 | O24: 13503157 | P24: 13503157 | Q24: 14434450 | R24: 15846672 | S24: 16059704 | T24: 17407210 | U24: 17407210 | V24: 17756029 | W24: 17882486 | X24: 18097243 | Y24: 19724646 | Z24: 19724646 | AA24: 20239932 | AB24: 19564154
A25: 1 | C25: 유동부채 | E25: 7375443.8 | F25: 7375443.8 | G25: 8061432.7 | H25: 9194975.1 | I25: 9919624.2 | J25: 10586129 | K25: 10586129 | L25: 10739485 | M25: 8793766.2 | N25: 8006557.3 | O25: 7382284.1 | P25: 7382284.1 | Q25: 8156375.4 | R25: 9553757.1 | S25: 9924653.3 | T25: 10350506 | U25: 10350506 | V25: 10369622 | W25: 10414427 | X25: 10188854 | Y25: 11074709 | Z25: 11074709 | AA25: 10698134 | AB25: 9247942.2
A26: 1 | C26: 단기차입금 | E26: 1073379.9 | F26: 1073379.9 | G26: 1281417.6 | H26: 1356016.2 | I26: 1339627.5 | J26: 1218458.8 | K26: 1218458.8 | L26: 1639742.1 | M26: 647468.41 | N26: 544631.12 | O26: 494162.6 | P26: 494162.6 | Q26: 1679649.3 | R26: 2485199 | S26: 3145042.2 | T26: 3201449.9 | U26: 3201449.9 | V26: 3335499.9 | W26: 2983414.4 | X26: 2978045.8 | Y26: 3220177.3 | Z26: 3220177.3 | AA26: 3443704.2 | AB26: 3292402.7
A27: 1 | C27: 매입채무및기타채무 | E27: 651183.86 | F27: 651183.86 | G27: 636868.02 | H27: 668798.62 | I27: 687454.28 | J27: 903964.73 | K27: 903964.73 | L27: 895991.44 | M27: 968038.14 | N27: 923584.96 | O27: 1150433.9 | P27: 1150433.9 | Q27: 1121404.3 | R27: 1251719.7 | S27: 1223413.3 | T27: 1630444.3 | U27: 1630444.3 | V27: 1324943.1 | W27: 1491765.5 | X27: 1574282.2 | Y27: 1804696.1 | Z27: 1804696.1 | AA27: 1643941.2 | AB27: 1555708.4
A28: 1 | C28: 당기법인세부채(미지급법인세) | E28: 982.56 | F28: 982.56 | G28: 982.56 | Y28: 3408.6 | Z28: 3408.6 | AA28: 3408.6
A29: 1 | C29: 유동성장기부채 | E29: 1329495.2 | F29: 1329495.2 | G29: 1360748.2 | H29: 1443944.3 | I29: 1506874 | J29: 1304098.3 | K29: 1304098.3 | L29: 1276920.8
A30: 1 | C30: 계약부채 | E30: 2094094.5 | F30: 2094094.5 | G30: 2277142.8 | H30: 3169024.5 | I30: 3540061.2 | J30: 4682119.5 | K30: 4682119.5 | L30: 4662523.2 | M30: 5037881.6 | N30: 4604437.1 | O30: 4365449.7 | P30: 4365449.7 | Q30: 4101018.2 | R30: 4657647.4 | S30: 4605264.6 | T30: 4422479.9 | U30: 4422479.9 | V30: 4788895.1 | W30: 5269693.3 | X30: 4974156.5 | Y30: 5254126.4 | Z30: 5254126.4 | AA30: 5069368.6 | AB30: 3822369.3
A31: 1 | C31: 단기충당부채 | E31: 1755561 | F31: 1755561 | G31: 1943149.9 | H31: 1638583.2 | I31: 1738772.5 | J31: 1569847.1 | K31: 1569847.1 | L31: 1295297.6 | M31: 1131374.1 | N31: 816777.92 | O31: 705053.76 | P31: 705053.76 | Q31: 468667.71 | R31: 356247.77 | S31: 303744.34 | T31: 349740.72 | U31: 349740.72 | V31: 237274.54 | W31: 214217.13 | X31: 208556.47 | Y31: 409292.06 | Z31: 409292.06 | AA31: 136711.52 | AB31: 132329.85
A32: 1 | C32: 기타유동부채 | E32: 400574.43 | F32: 400574.43 | G32: 425801.55 | H32: 598792.01 | I32: 547575.95 | J32: 563366.29 | K32: 563366.29 | L32: 575649.55 | M32: 580588.11 | N32: 588072.2 | O32: 418231.06 | P32: 418231.06 | Q32: 429188.77 | R32: 456027.45 | S32: 488216.65 | T32: 373077.27 | U32: 373077.27 | V32: 293049.35 | W32: 269478.75 | X32: 280364.57 | Y32: 283425.42 | Z32: 283425.42 | AA32: 298717.24 | AB32: 309857
A33: 1 | C33: 비유동부채 | E33: 937703.48 | F33: 937703.48 | G33: 881022.85 | H33: 1180996.4 | I33: 1566807.2 | J33: 816841.24 | K33: 816841.24 | L33: 851316.64 | M33: 2423628.5 | N33: 2398275.8 | O33: 2075932.7 | P33: 2075932.7 | Q33: 2192625.3 | R33: 2255314.1 | S33: 2189934 | T33: 2541510.2 | U33: 2541510.2 | V33: 2651736.6 | W33: 2529937 | X33: 2690677.4 | Y33: 2655619.5 | Z33: 2655619.5 | AA33: 3027660.1 | AB33: 3123003.8
A34: 1 | C34: 사채 | E34: 111743.39 | F34: 111743.39 | G34: 56393.11
A35: 1 | C35: 장기차입금 | E35: 122512.94 | F35: 122512.94 | G35: 116822.03 | H35: 111833.68 | I35: 116209.29 | J35: 99715.36 | K35: 99715.36 | L35: 93931.58 | M35: 1626788.7 | N35: 1662132.4 | O35: 1589951.4 | P35: 1589951.4 | Q35: 1642727.8 | R35: 1679814.5 | S35: 1641248.3 | T35: 1962264.7 | U35: 1962264.7 | V35: 2084982 | W35: 1939124.9 | X35: 2061122 | Y35: 2286006.4 | Z35: 2286006.4 | AA35: 2555723.6 | AB35: 2578512.4
A36: 1 | C36: 장기매입채무및기타채무 | E36: 6993.08 | F36: 6993.08 | G36: 7112.83 | H36: 4888.31 | I36: 5429.07 | J36: 4853.78 | K36: 4853.78 | L36: 5010.91 | M36: 5041.04 | N36: 5156.47 | O36: 4956.63 | P36: 4956.63 | Q36: 7207.96 | R36: 10850.1 | S36: 11861.16 | T36: 15320.02 | U36: 15320.02 | V36: 45782.77 | W36: 48212.9 | X36: 68427 | Y36: 72279.87 | Z36: 72279.87 | AA36: 78307.42 | AB36: 68000.37
A37: 1 | C37: 장기충당부채 | E37: 334794.55 | F37: 334794.55 | G37: 322340.27 | H37: 360892.5 | I37: 362692.78 | J37: 328991.34 | K37: 328991.34 | L37: 305459.49 | M37: 288476.34 | N37: 244465.91 | O37: 229959.7 | P37: 229959.7 | Q37: 230121.95 | R37: 234804.46 | S37: 232901.09 | T37: 187901.66 | U37: 187901.66 | V37: 188013.52 | W37: 190682.12 | X37: 195341.35 | Y37: 80308.65 | Z37: 80308.65 | AA37: 80927.94 | AB37: 84805.87
A38: 1 | C38: 비유동리스부채 | E38: 61166.93 | F38: 61166.93 | G38: 61499.05 | H38: 56743.12 | I38: 53365.03 | J38: 48605.25 | K38: 48605.25 | L38: 44450.98 | M38: 55851.5 | N38: 52719 | O38: 49361.21 | P38: 49361.21 | Q38: 45868.28 | R38: 38284.48 | S38: 33941.18 | T38: 95156.12 | U38: 95156.12 | V38: 91238.04 | W38: 89698.49 | X38: 87190.03 | Y38: 80584.42 | Z38: 80584.42 | AA38: 75718.56 | AB38: 95057.7
A39: 1 | C39: 리스부채 | E39: 61166.93 | F39: 61166.93 | G39: 61499.05 | H39: 56743.12 | I39: 53365.03 | J39: 48605.25 | K39: 48605.25 | L39: 44450.98 | M39: 55851.5 | N39: 52719 | O39: 49361.21 | P39: 49361.21 | Q39: 45868.28 | R39: 38284.48 | S39: 33941.18 | T39: 95156.12 | U39: 95156.12 | V39: 91238.04 | W39: 89698.49 | X39: 87190.03 | Y39: 110804.24 | Z39: 110804.24 | AA39: 75718.56 | AB39: 126350.75
A40: 1 | C40: 장기금융부채 | E40: 62229.92 | F40: 62229.92 | G40: 61892.28 | H40: 57027.47 | I40: 53365.03 | J40: 48674.54 | K40: 48674.54 | L40: 44602.83 | M40: 55851.5 | N40: 52719 | O40: 49361.21 | P40: 49361.21 | Q40: 45868.28 | R40: 38284.48 | S40: 36227.02 | T40: 95156.12 | U40: 95156.12 | V40: 91238.04 | W40: 89698.49 | X40: 87190.03 | Y40: 85462.45 | Z40: 85462.45 | AA40: 149494.21 | AB40: 207821.55
A41: 1 | C41: 장기파생상품부채 | E41: 1062.99 | F41: 1062.99 | G41: 393.23 | H41: 284.35 | J41: 69.29 | K41: 69.29 | L41: 151.85 | S41: 2285.84 | Y41: 4878.03 | Z41: 4878.03 | AA41: 73775.65 | AB41: 112763.85
A42: 1 | C42: 이연법인세부채 | E42: 60437.62 | F42: 60437.62 | G42: 60437.62 | H42: 73172.12 | I42: 36901.12 | J42: 118380.57 | K42: 118380.57 | L42: 118364.76 | M42: 127453.62 | N42: 127720.83
A43: 1 | C43: 부채총계 | E43: 8313147.2 | F43: 8313147.2 | G43: 8942455.5 | H43: 10375972 | I43: 11486431 | J43: 11402971 | K43: 11402971 | L43: 11590802 | M43: 11217395 | N43: 10404833 | O43: 9458216.8 | P43: 9458216.8 | Q43: 10349001 | R43: 11809071 | S43: 12114587 | T43: 12892017 | U43: 12892017 | V43: 13021358 | W43: 12944364 | X43: 12879531 | Y43: 13730328 | Z43: 13730328 | AA43: 13725795 | AB43: 12370946
A44: 1 | C44: 자본금 | E44: 541453.34 | F44: 541453.34 | G44: 541453.34 | H44: 541453.34 | I44: 541453.34 | J44: 541453.34 | K44: 541453.34 | L44: 541453.34 | M44: 1089367 | N44: 1089367 | O44: 1536794.5 | P44: 1536794.5 | Q44: 1536794.5 | R44: 1536794.5 | S44: 1537067 | T44: 1537067 | U44: 1537067 | V44: 1537067 | W44: 1537067 | X44: 1537067 | Y44: 1537067 | Z44: 1537067 | AA44: 1537067 | AB44: 1537067
A45: 1 | C45: 자본잉여금 | E45: -714.45 | F45: -714.45 | G45: -714.45 | H45: -714.45 | I45: -714.45 | J45: -714.45 | K45: -714.45 | L45: -714.45 | M45: 1594965.5 | N45: 1594965 | O45: 2628374.2 | P45: 2628374.2 | Q45: 0 | R45: 0 | S45: 5839.6 | T45: 23477.33 | U45: 23477.33 | V45: 36431.91 | W45: 54678.7 | X45: 58222.95 | Y45: 86656.93 | Z45: 86656.93 | AA45: 111709.32 | AB45: 113743.9
A46: 1 | C46: 기타자본 | E46: 2649143 | F46: 2649143 | G46: 2649129.5 | H46: 2650568.6 | I46: 2605756.9 | J46: 2887329.3 | K46: 2887329.3 | L46: 2886938.1 | M46: 2327785.1 | N46: 2327785.1 | O46: 2327785.1 | P46: 2327785.1 | Q46: 2329460.9 | R46: 2332291.4 | S46: 2327441.3 | T46: 2327441.3 | U46: 2327441.3 | V46: 2327441.3 | W46: 2327441.3 | X46: 2327441.3 | Y46: 2327441.3 | Z46: 2327441.3 | AA46: 2322532.7 | AB46: 2322328.8
A47: 1 | C47: 이익잉여금 | E47: -1062232.2 | F47: -1062232.2 | G47: -1553880.9 | H47: -1736810.4 | I47: -2345249.8 | J47: -2784208.5 | K47: -2784208.5 | L47: -2906552.1 | M47: -3354914.6 | N47: -3138940.8 | O47: -3001572.4 | P47: -3001572.4 | Q47: -334450.25 | R47: -384877.35 | S47: -479215.28 | T47: 73450.79 | U47: 73450.79 | V47: 280083.97 | W47: 455059.88 | X47: 731159.55 | Y47: 1488301.8 | Z47: 1488301.8 | AA47: 1989235.4 | AB47: 2666816.9
A48: 1 | C48: 자본총계 | E48: 2127649.7 | F48: 2127649.7 | G48: 1635987.5 | H48: 1454497 | I48: 801245.94 | J48: 643859.73 | K48: 643859.73 | L48: 521124.82 | M48: 2210544.3 | N48: 2427893.6 | O48: 4044940.3 | P48: 4044940.3 | Q48: 4085449.2 | R48: 4037600.3 | S48: 3945116.1 | T48: 4515193.3 | U48: 4515193.3 | V48: 4734670.4 | W48: 4938122.4 | X48: 5217711.9 | Y48: 5994317.6 | Z48: 5994317.6 | AA48: 6514137.1 | AB48: 7193208.5
A49: 1 | C49: 부채와자본총계 | E49: 10440797 | F49: 10440797 | G49: 10578443 | H49: 11830469 | I49: 12287677 | J49: 12046830 | K49: 12046830 | L49: 12111927 | M49: 13427939 | N49: 12832727 | O49: 13503157 | P49: 13503157 | Q49: 14434450 | R49: 15846672 | S49: 16059704 | T49: 17407210 | U49: 17407210 | V49: 17756029 | W49: 17882486 | X49: 18097243 | Y49: 19724646 | Z49: 19724646 | AA49: 20239932 | AB49: 19564154
A50: 1 | C50: 지배주주지분 | E50: 2127649.7 | F50: 2127649.7 | G50: 1635987.5 | H50: 1454497 | I50: 801245.94 | J50: 643859.73 | K50: 643859.73 | L50: 521124.82 | M50: 2210544.3 | N50: 2427893.6 | O50: 4044940.3 | P50: 4044940.3 | Q50: 4085449.2 | R50: 4037600.3 | S50: 3945116.1 | T50: 4515193.3 | U50: 4515193.3 | V50: 4734670.4 | W50: 4938122.4 | X50: 5217711.9 | Y50: 5994317.6 | Z50: 5994317.6 | AA50: 6514137.1 | AB50: 7193208.5
A51: 1 | C51: 총차입금 | E51: 2637131.5 | F51: 2637131.5 | G51: 2815381 | H51: 2911794.3 | I51: 2962710.8 | J51: 2622272.4 | K51: 2622272.4 | L51: 3010594.5 | M51: 2274257.1 | N51: 2206763.5 | O51: 2084114 | P51: 2084114 | Q51: 3322377 | R51: 4165013.5 | S51: 4786290.5 | T51: 5163714.5 | U51: 5163714.5 | V51: 5420482 | W51: 4922539.3 | X51: 5039167.8 | Y51: 5506183.6 | Z51: 5506183.6 | AA51: 5999427.8 | AB51: 5870915.1
A52: 1 | C52: 순차입금 | E52: 597133.5 | F52: 597133.5 | G52: 1416803.7 | H52: 1672286 | I52: 1854260.1 | J52: 1509598.3 | K52: 1509598.3 | L52: 2773587.2 | M52: 739774.79 | N52: 1251788.4 | O52: 313617.03 | P52: 313617.03 | Q52: 1733555.3 | R52: 2439859.8 | S52: 3898297.4 | T52: 4749380.1 | U52: 4749380.1 | V52: 4657769.4 | W52: 4103785.6 | X52: 4820025.4 | Y52: 4904159.2 | Z52: 4904159.2 | AA52: 5102679.9 | AB52: 4624949.6
A53: 1 | C53: 이자발생자산 | E53: 2273162.6 | F53: 2273162.6 | G53: 1626919.5 | H53: 1317531.7 | I53: 1148673.6 | J53: 1152920.2 | K53: 1152920.2 | L53: 237007.28 | M53: 1573754.6 | N53: 995628.72 | O53: 1809935.8 | P53: 1809935.8 | Q53: 1629313.9 | R53: 1776245.9 | S53: 939677.46 | T53: 469489.28 | U53: 469489.28 | V53: 816129.03 | W53: 872148.56 | X53: 273635.68 | Y53: 656821.83 | Z53: 656821.83 | AA53: 951745.37 | AB53: 1300773.6
A54: 1 | C54: 당기법인세자산(선급법인세) | G54: 948.34 | H54: 3795.75 | I54: 4818.44 | J54: 5751.49 | K54: 5751.49 | L54: 6576.28 | M54: 2389.52 | N54: 3792.54 | O54: 5328.55 | P54: 5328.55 | Q54: 7961.76 | R54: 5622.7 | S54: 7125.81 | T54: 8150.98 | U54: 8150.98 | V54: 8948.76 | W54: 1897.41 | X54: 2481.71 | AB54: 1835.03
A55: 1 | C55: 기타유동금융부채 | H55: 25751.28 | I55: 50921.84 | J55: 31440.48 | K55: 31440.48 | L55: 28739.37 | M55: 16702.79
A56: 1 | C56: 단기금융부채 | H56: 25751.28 | I56: 50921.84 | J56: 31440.48 | K56: 31440.48 | L56: 28739.37 | M56: 16702.79 | W56: 155113.83 | X56: 142423.97 | Y56: 99176.92 | Z56: 99176.92 | AA56: 74104.37 | AB56: 135025.87
A57: 1 | C57: 기타유동금융자산 | L57: 414700.74 | M57: 429609.86 | N57: 91734.81 | O57: 108239.3 | P57: 108239.3 | Q57: 109262.09 | R57: 10780.51 | S57: 10991.31 | T57: 11454.87 | U57: 11454.87 | V57: 11462.79 | W57: 4752.2 | X57: 4834.52 | Y57: 4404 | Z57: 4404 | AA57: 4485 | AB57: 14512
A58: 1 | C58: 확정급여부채 | L58: 21558.39 | V58: 157130.47 | W58: 175991.71 | X58: 190644.95 | Y58: 129805.8 | Z58: 129805.8 | AA58: 41662.76 | AB58: 182381.4
A59: 1 | C59: 단기금융부채(face) | M59: 647468.41 | N59: 544631.12 | O59: 494162.6 | P59: 494162.6 | Q59: 1679649.3 | R59: 2485199 | S59: 3145042.2 | T59: 3201449.9 | U59: 3201449.9 | V59: 3335499.9 | W59: 2983414.4 | X59: 2978045.8 | Y59: 3220177.3 | Z59: 3220177.3 | AA59: 3443704.2 | AB59: 3292402.7
A60: 1 | C60: 장기금융부채(face) | M60: 1626788.7 | N60: 1662132.4 | T60: 1962264.7 | U60: 1962264.7 | V60: 2084982 | W60: 1939124.9 | X60: 2061122 | Y60: 2286006.4 | Z60: 2286006.4 | AA60: 2555723.6 | AB60: 2578512.4
A61: 1 | C61: 기타포괄이익누계액 | M61: 553341.31 | N61: 554717.39 | O61: 553559.04 | P61: 553559.04 | Q61: 553644.09 | R61: 553391.75 | S61: 553983.56 | T61: 553756.89 | U61: 553756.89 | V61: 553646.26 | W61: 563875.53 | X61: 563821.14 | Y61: 554850.56 | Z61: 554850.56 | AA61: 553592.82 | AB61: 553251.93
A62: 1 | C62: 이연법인세자산 | O62: 163892.42 | P62: 163892.42 | Q62: 163892.42 | R62: 154090.12 | S62: 154090.12 | T62: 506573.93 | U62: 506573.93 | V62: 506573.93 | W62: 498512.13 | X62: 498484.85 | Y62: 950308.59 | Z62: 950308.59 | AA62: 950335.73 | AB62: 950335.73
A63: 1 | C63: 비유동파생상품자산 | W63: 12.81 | X63: 1418.5 | Y63: 4864.26 | Z63: 4864.26
A64: 1 | C64: 단기파생상품부채 | W64: 155113.83 | X64: 142423.97 | Y64: 68957.1 | Z64: 68957.1 | AA64: 74104.37 | AB64: 103732.82
A65: 1 | C65: 유동리스부채 | Y65: 30219.82 | Z65: 30219.82 | AB65: 31293.05
A66: 1 | C66: 유동파생상품자산 | AA66: 11835.59 | AB66: 14682.83
A67: 1 | C67: 매출액(수익) | E67: 1345672.5 | G67: 1235139.6 | H67: 1173752.1 | I67: 972632.91 | J67: 1436137.7 | K67: 4817662.2 | L67: 1439385.4 | M67: 1820371 | N67: 1951556 | O67: 2214666.4 | P67: 7425978.8 | Q67: 2252955.1 | R67: 2542676.8 | S67: 2707050.6 | T67: 3262074.5 | U67: 10764757 | V67: 3167008.3 | W67: 3415079.7 | X67: 2993621 | Y67: 3327885.4 | Z67: 12903594 | AA67: 3165781.4 | AB67: 5443697
A68: 1 | C68: 매출원가 | E68: 1790458.9 | G68: 1647326 | H68: 1219866.3 | I68: 1549039.6 | J68: 1783315.4 | K68: 6199547.3 | L68: 1447233.9 | M68: 1909569.9 | N68: 1821678.7 | O68: 2201010 | P68: 7379492.6 | Q68: 2127454.5 | R68: 2484848.3 | S68: 2584347.9 | T68: 2927071.3 | U68: 10123722 | V68: 2756743.5 | W68: 2882951.9 | X68: 2561383 | Y68: 2884430.9 | Z68: 11085509 | AA68: 2581263.6 | AB68: 4515716.8
A69: 1 | C69: 매출총이익 | E69: -444786.43 | G69: -412186.43 | H69: -46114.2 | I69: -576406.72 | J69: -347177.71 | K69: -1381885.1 | L69: -7848.46 | M69: -89198.94 | N69: 129877.27 | O69: 13656.35 | P69: 46486.22 | Q69: 125500.53 | R69: 57828.48 | S69: 122702.78 | T69: 335003.2 | U69: 641034.99 | V69: 410264.77 | W69: 532127.87 | X69: 432237.97 | Y69: 443454.52 | Z69: 1818085.1 | AA69: 584517.71 | AB69: 927980.27
A70: 1 | C70: 판관비 | E70: 65764.68 | G70: 58100.42 | H70: 60675.98 | I70: 59045.06 | J70: 83594.54 | K70: 261416 | L70: 58190.82 | M70: 81670.74 | N70: 66478.82 | O70: 78650.73 | P70: 284991.11 | Q70: 80111.91 | R70: 83963.42 | S70: 102803.52 | T70: 163381.99 | U70: 430260.84 | V70: 151541.7 | W70: 142583.85 | X70: 154268.67 | Y70: 215688.06 | Z70: 664082.28 | AA70: 183642.8 | AB70: 212163.11
A71: 1 | C71: 영업이익 | E71: -510551.11 | G71: -470286.86 | H71: -106790.18 | I71: -635451.78 | J71: -430772.25 | K71: -1643301.1 | L71: -66039.28 | M71: -170869.68 | N71: 63398.45 | Q71: 45388.62 | R71: -26134.94 | S71: 19899.26 | T71: 171621.21 | U71: 210774.15 | V71: 258723.08 | W71: 389544.02 | X71: 277969.3 | Y71: 227766.46 | Z71: 1154002.9 | AA71: 400874.92 | AB71: 715817.16
A72: 1 | C72: 금융수익 | E72: 31007.76 | G72: 84781.61 | H72: 176651.16 | I72: 279295.79 | J72: -13707.45 | K72: 527021.11 | L72: 193374.05 | M72: 88877.88 | N72: 186761.51 | O72: 79695.92 | P72: 548709.36 | Q72: 302656.15 | R72: 39297.12 | S72: -13116.52 | T72: 358271.97 | U72: 687108.72 | V72: 133400.33 | W72: 400166.71 | X72: -35659.11 | Y72: 151224.05 | Z72: 649131.98 | AA72: 435412.42 | AB72: 190399.76
A73: 1 | C73: 금융비용 | E73: 81573.28 | G73: 158494.24 | H73: 750343.84 | I73: 1161436.4 | J73: -950766.47 | K73: 1119508 | L73: 433246.62 | M73: 241869.88 | N73: 323054.75 | O73: -110999.29 | P73: 887171.96 | Q73: 476428.69 | R73: 144687.61 | S73: -24945.68 | T73: 569161.64 | U73: 1165332.3 | V73: 177489.57 | W73: 528838.62 | X73: -44353.36 | Y73: 95794.41 | Z73: 757769.24 | AA73: 455691.26 | AB73: 266102.31
A74: 1 | C74: 기타영업외수익 | E74: 180395.98 | G74: 71854.3 | H74: 512190.41 | I74: 834529.09 | J74: -908600.17 | K74: 509973.63 | L74: 193557.18 | M74: 78763.03 | N74: 306726.68 | O74: -141946.96 | P74: 437099.93 | Q74: 178055.51 | R74: 91530.29 | S74: -109766.49 | T74: 346932.22 | U74: 506751.53 | V74: 28113.62 | W74: 2048.05 | X74: 9407.52 | Y74: 19671.85 | Z74: 59241.04 | AA74: 160700.58 | AB74: 59962.75
A75: 1 | C75: 기타영업외비용 | E75: 21840.57 | G75: 18282.73 | H75: 13870.93 | I75: 5887.32 | J75: 50902.28 | K75: 88943.26 | L75: 8909.52 | M75: 6004.78 | N75: 12313.18 | O75: 10836.07 | P75: 38063.55 | Q75: 2506.79 | R75: 3278.46 | S75: 6787.68 | T75: 85559.65 | U75: 98132.58 | V75: 28394.54 | W75: 80238.43 | X75: 10833.9 | Y75: 62462.31 | Z75: 181929.18 | AA75: 19350.72 | AB75: 2974.32
A76: 1 | C76: 법인세비용차감전계속사업이익 | E76: -402561.21 | G76: -490427.92 | H76: -182163.38 | I76: -688950.62 | J76: -453215.69 | K76: -1814757.6 | L76: -121264.19 | M76: -251103.43 | N76: 221518.71 | O76: -27082.2 | P76: -177931.11 | Q76: 47164.81 | R76: -43273.6 | S76: -84825.75 | T76: 222104.1 | U76: 141169.56 | V76: 214352.92 | W76: 182681.74 | X76: 285237.18 | Y76: 240405.65 | Z76: 922677.49 | AA76: 521945.94 | AB76: 697103.04
A77: 1 | C77: 법인세비용 | E77: -12723.4 | I77: -36271 | J77: -11166.73 | L77: -15.81 | O77: -287747.22 | Q77: 827.6 | R77: 467.5 | S77: 2988.86 | T77: -360664.67 | U77: -356380.71 | V77: 201.11 | W77: 179.74 | X77: 434.12 | Y77: -422336.13 | Z77: -421521.16 | AA77: 87.11 | AB77: -387.78
A78: 1 | C78: 당기순이익 | E78: -389837.81 | G78: -490427.92 | H78: -182163.38 | I78: -652679.62 | J78: -442048.96 | K78: -1767319.9 | L78: -121248.38 | M78: -251103.43 | N78: 221518.71 | O78: 260665.03 | P78: 109831.93 | Q78: 46337.21 | R78: -43741.1 | S78: -87814.62 | T78: 582768.78 | U78: 497550.27 | V78: 214151.81 | W78: 182502 | X78: 284803.06 | Y78: 662741.77 | Z78: 1344198.6 | AA78: 521858.83 | AB78: 697490.82
A79: 1 | C79: 금융손익 | E79: -50565.52 | G79: -73712.63 | H79: -573692.68 | I79: -882140.61 | J79: 937059.02 | K79: -592486.9 | L79: -239872.57 | M79: -152992 | N79: -136293.24 | O79: 190695.21 | P79: -338462.6 | Q79: -173772.54 | R79: -105390.49 | S79: 11829.16 | T79: -210889.67 | U79: -478223.54 | V79: -44089.24 | W79: -128671.91 | X79: 8694.25 | Y79: 55429.64 | Z79: -108637.26 | AA79: -20278.84 | AB79: -75702.55
A80: 1 | C80: 기타영업외손익 | E80: 158555.41 | G80: 53571.57 | H80: 498319.48 | I80: 828641.77 | J80: -959502.45 | K80: 421030.37 | L80: 184647.66 | M80: 72758.25 | N80: 294413.5 | O80: -152783.03 | P80: 399036.38 | Q80: 175548.72 | R80: 88251.83 | S80: -116554.17 | T80: 261372.57 | U80: 408618.95 | V80: -280.92 | W80: -78190.38 | X80: -1426.38 | Y80: -42790.46 | Z80: -122688.14 | AA80: 141349.86 | AB80: 56988.43
A81: 1 | C81: (지배주주지분)당기순이익 | E81: -389837.81 | G81: -490427.92 | H81: -182163.38 | I81: -652679.62 | J81: -442048.96 | K81: -1767319.9 | L81: -121248.38 | M81: -251103.43 | N81: 221518.71 | O81: 260665.03 | P81: 109831.93 | Q81: 46337.21 | R81: -43741.1 | S81: -87814.62 | T81: 582768.78 | U81: 497550.27 | V81: 214151.81 | W81: 182502 | X81: 284803.06 | Y81: 662741.77 | Z81: 1344198.6 | AA81: 521858.83 | AB81: 697490.82
A82: 1 | C82: 계속사업이익 | E82: -389837.81 | G82: -490427.92 | H82: -182163.38 | I82: -652679.62 | J82: -442048.96 | K82: -1767319.9 | L82: -121248.38 | M82: -251103.43 | N82: 221518.71 | O82: 260665.03 | P82: 109831.93 | Q82: 46337.21 | R82: -43741.1 | S82: -87814.62 | T82: 582768.78 | U82: 497550.27 | V82: 214151.81 | W82: 182502 | X82: 284803.06 | Y82: 662741.77 | Z82: 1344198.6 | AA82: 521858.83 | AB82: 697490.82
A83: 1 | C83: 총포괄손익 | E83: -354793.95 | G83: -491662.21 | H83: -181490.5 | I83: -653251.08 | J83: -157386.21 | K83: -1483790 | L83: -122734.9 | M83: -307834.27 | N83: 223181.92 | Q83: 44665.14 | R83: -44847.35 | S83: -87914.05 | T83: 558271.48 | U83: 470175.22 | V83: 212354.63 | W83: 191037.26 | X83: 281877.37 | Y83: 748693.08 | Z83: 1433962.3 | AA83: 505507.85 | AB83: 683072.74
A84: 1 | C84: 영업활동으로인한현금흐름 | E84: 15595 | G84: -718763.51 | H84: -271683.55 | I84: -183310.16 | J84: 113658.75 | K84: -1060098.5 | L84: -781625.04 | M84: 18079.37 | N84: -749837.96 | O84: -464874.69 | P84: -1978258.3 | Q84: -1159238 | R84: -540495.32 | S84: -884188.37 | T84: -269876.99 | U84: -2853798.7 | V84: 184821.86 | W84: 688047.04 | X84: -418553.55 | Y84: 713837.59 | Z84: 1168152.9 | AA84: 187700.08 | AB84: 714530.78
A85: 1 | C85: 배당금수취(CF) | E85: 682.18 | G85: 570.89 | H85: 14.85 | I85: 0 | J85: 0 | K85: 585.74 | L85: 950 | M85: 73.25 | N85: 0 | O85: 0 | P85: 1023.25 | Q85: 874 | R85: 180.29 | S85: 0 | T85: 0 | U85: 1054.29 | X85: 0 | Y85: 6.75 | AA85: 121.28 | AB85: 50.57
A86: 1 | C86: 이자수취(CF) | E86: 6977.89 | G86: 8088.17 | H86: 20049.47 | I86: 8606.66 | J86: 10613.89 | K86: 47358.19 | L86: 11646.91 | M86: 1898.26 | N86: 15326.04 | O86: 23152.88 | P86: 52024.09 | Q86: 17065.29 | R86: 15872.19 | S86: 12949.64 | T86: 7553.63 | U86: 53440.75 | V86: 5676.73 | W86: 7218.37 | X86: 3450.51 | Y86: 6929.02 | Z86: 23274.63 | AA86: 21390.02 | AB86: 6844.3
A87: 1 | C87: 이자지급(CF) | E87: -16899.6 | G87: -11809.81 | H87: -17110.57 | I87: -21245.77 | J87: -23380.8 | K87: -73546.95 | L87: -37176.56 | M87: -41510.62 | N87: -26266.07 | O87: -30325.78 | P87: -135279.03 | Q87: -27541.88 | R87: -39615.5 | S87: -41565.66 | T87: -44032.69 | U87: -152755.73 | V87: -44679.8 | W87: -46869.41 | X87: -43006.31 | Y87: -31371.71 | Z87: -165927.23 | AA87: -48671.13 | AB87: -55327.65
A88: 1 | C88: 법인세납부(CF) | E88: -757.86 | G88: -948.34 | H88: 8904.53 | I88: -1022.7 | J88: -933.04 | K88: 6000.45 | L88: -824.79 | M88: 13275.62 | N88: -1135.81 | O88: -5402.03 | P88: 5912.99 | Q88: -3460.81 | R88: -4752.24 | S88: 4491.97 | T88: 5616.15 | U88: 1895.07 | V88: -998.88 | W88: 11157.43 | X88: -1018.43 | Y88: -16955.89 | Z88: -7815.77 | AA88: -87.11 | AB88: 5030.07
A89: 1 | C89: 투자활동으로인한현금흐름 | E89: 47749.54 | G89: -13359.35 | H89: 221158.27 | I89: -127616.36 | J89: 5345.74 | K89: 85528.3 | L89: 59095.76 | M89: -33072.35 | N89: 277765.62 | O89: -116423.3 | P89: 187365.73 | Q89: -186709.4 | R89: -106732.27 | S89: -629227.05 | T89: -400226.34 | U89: -1322895.1 | V89: -79055.63 | W89: -248842.07 | X89: -220837.95 | Y89: -732878.72 | Z89: -1281614.4 | AA89: -264152.58 | AB89: -183344.38
A90: 1 | C90: 재무활동으로인한현금흐름 | E90: 43708.47 | G90: 134627.27 | H90: -13498.7 | I90: -133723.18 | J90: -117185.87 | K90: -129780.48 | L90: 325443.03 | M90: 1314513.8 | N90: -110984.72 | O90: 1401986.3 | P90: 2930958.4 | Q90: 1163977.2 | R90: 783556.06 | S90: 676584.66 | T90: 195827.42 | U90: 2819945.3 | V90: 242586.4 | W90: -381638.79 | X90: 38110.07 | Y90: 405316.36 | Z90: 304374.04 | AA90: 357380.15 | AB90: -182875.2
A91: 1 | C91: 단기차입금의증가 | E91: 107250.23 | G91: 201791.78 | H91: 53934.47 | L91: 424426.52 | M91: 495573.48 | N91: 0 | O91: 0 | P91: 920000 | Q91: 1200000 | R91: 800000 | S91: 500000 | T91: 20000 | U91: 2520000 | V91: 146738.1 | W91: 0 | X91: 398648.12 | Y91: 93620 | Z91: 639006.22 | AA91: 272085.21 | AB91: 220000
A92: 1 | C92: 유동성장기부채의감소 | E92: 0 | G92: 4.03 | H92: 0 | I92: 8348.75 | J92: 8348.74 | K92: 16701.52 | L92: 8418.64 | M92: 8414.61 | N92: 0 | O92: 16829.22 | P92: 33662.47 | Q92: 8436.44 | R92: 8432.4 | S92: 8432.4 | T92: 8432.41 | U92: 33733.65 | V92: 8581.85 | W92: 8577.82 | X92: 8577.82 | Y92: 8577.82 | Z92: 34315.31 | AA92: 8553.59 | AB92: 8549.56
A93: 1 | C93: 리스부채의상환 | E93: 4788.95 | G93: 4815.98 | H93: 5794.73 | I93: 5954.99 | J93: 6019.43 | K93: 22585.13 | L93: 5415.34 | M93: 6394.35 | N93: 7134.4 | O93: 7280.03 | P93: 26224.12 | Q93: 6808.33 | R93: 7518.08 | S93: 8554.28 | T93: 8404.36 | U93: 31285.05 | V93: 7292.63 | W93: 8018.82 | X93: 7886.37 | Y93: 8844.84 | Z93: 32042.66 | AA93: 8211.17 | AB93: 8580.89
A94: 1 | C94: 현금및현금성자산의증감 | E94: 107053.01 | G94: -597495.6 | H94: -64023.98 | I94: -444649.69 | J94: 1818.62 | K94: -1104350.6 | L94: -397086.26 | M94: 1299520.8 | N94: -583057.07 | O94: 820688.33 | P94: 1140065.8 | S94: -836830.76 | T94: -474275.91 | V94: 348352.64 | W94: 57566.17 | X94: -601281.43 | Y94: 386275.23 | Z94: 190912.61 | AA94: 280927.65 | AB94: 348311.19
A95: 1 | C95: 기말현금및현금성자산 | E95: 105768.7 | G95: 1151228.9 | H95: -64227.24 | I95: -429573.99 | J95: -23963.75 | K95: 633463.93 | L95: 237007.28 | M95: 1297475 | N95: -579507.21 | O95: 815521.9 | P95: 1770497 | Q95: 1588821.7 | R95: 136332.02 | S95: -837160.71 | T95: -473658.59 | U95: 414334.46 | V95: 762712.6 | W95: 56041.06 | X95: -599611.24 | Y95: 382881.97 | Z95: 602024.39 | AA95: 884912.28 | AB95: 346370.43
A96: 1 | C96: 단기차입금의감소 | L96: 23203.62 | M96: 1163614.2 | N96: 98017.74 | O96: 48909.04 | P96: 1333744.6 | Q96: 14945.97 | S96: 6991.93 | V96: 150000 | W96: 500000 | X96: 520000 | Y96: 100000 | Z96: 1270000 | AA96: 250000 | AB96: 310000
A97: 1 | C97: 유형자산의감소 | Q97: 291.34 | R97: 170.11 | S97: 45.59 | T97: 166.79 | U97: 673.83 | V97: 460.74 | W97: 961.72 | X97: 457.23 | Y97: 718.51 | Z97: 2598.2 | AA97: 166.24 | AB97: 554.14
A98: 1 | C98: 유형자산의증가 | Q98: 33035.34 | R98: 43266.84 | S98: 59706.39 | T98: 116445 | U98: 252453.57 | V98: 50688.68 | W98: 95321.86 | X98: 105843.1 | Y98: 198351.52 | Z98: 450205.16 | AA98: 61111.84 | AB98: 96363.99
A99: 1 | C99: CAPEX | Q99: 33731.89 | R99: 44095.39 | S99: 61591.66 | T99: 118451.24 | U99: 257870.18 | V99: 53293.89 | W99: 96315.84 | X99: 106305.85 | Y99: 199535.49 | Z99: 455451.07 | AA99: 61722.83 | AB99: 96767.19
A100: 1 | C100: 무형자산의증가 | Q100: 696.55 | R100: 828.55 | S100: 1885.27 | T100: 2006.24 | U100: 5416.61 | V100: 2605.21 | W100: 993.98 | X100: 462.75 | Y100: 1183.97 | Z100: 5245.91 | AA100: 610.99 | AB100: 403.2
...

Sheet subQ
A1: YQ | C1: subQ 분기 서브모델(억원, U=100) | E1: 4Q21 | F1: 2021 | G1: 1Q22 | H1: 2Q22 | I1: 3Q22 | J1: 4Q22 | K1: 2022 | L1: 1Q23 | M1: 2Q23 | N1: 3Q23 | O1: 4Q23 | P1: 2023 | Q1: 1Q24 | R1: 2Q24 | S1: 3Q24 | T1: 4Q24 | U1: 2024 | V1: 1Q25 | W1: 2Q25 | X1: 3Q25 | Y1: 4Q25 | Z1: 2025 | AA1: 1Q26 | AB1: 2Q26 | AC1: 3Q26 | AD1: 4Q26 | AE1: 2026 | AF1: 1Q27 | AG1: 2Q27 | AH1: 3Q27 | AI1: 4Q27 | AJ1: 2027 | AK1: 1Q28 | AL1: 2Q28 | AM1: 3Q28 | AN1: 4Q28 | AO1: 2028
A2: A=이름(key) B=그룹 C=단위 D=FnGuide 계정명(VLOOKUP 키). 확정=VLOOKUP(BS), 추정=변수 가정 참조
E3: 1 | F3: 2 | G3: 3 | H3: 4 | I3: 5 | J3: 6 | K3: 7 | L3: 8 | M3: 9 | N3: 10 | O3: 11 | P3: 12 | Q3: 13 | R3: 14 | S3: 15 | T3: 16 | U3: 17 | V3: 18 | W3: 19 | X3: 20 | Y3: 21 | Z3: 22 | AA3: 23 | AB3: 24 | AC3: 25 | AD3: 26 | AE3: 27 | AF3: 28 | AG3: 29 | AH3: 30 | AI3: 31 | AJ3: 32 | AK3: 33 | AL3: 34 | AM3: 35 | AN3: 36 | AO3: 37
E4: 2021.12 | F4: 2021.12A | G4: 2022.03 | H4: 2022.06 | I4: 2022.09 | J4: 2022.12 | K4: 2022.12A | L4: 2023.03 | M4: 2023.06 | N4: 2023.09 | O4: 2023.12 | P4: 2023.12A | Q4: 2024.03 | R4: 2024.06 | S4: 2024.09 | T4: 2024.12 | U4: 2024.12A | V4: 2025.03 | W4: 2025.06 | X4: 2025.09 | Y4: 2025.12 | Z4: 2025.12A | AA4: 2026.03 | AB4: 2026.06 | AC4: 2026.09 | AD4: 2026.12 | AE4: 2026.12A | AF4: 2027.03 | AG4: 2027.06 | AH4: 2027.09 | AI4: 2027.12 | AJ4: 2027.12A | AK4: 2028.03 | AL4: 2028.06 | AM4: 2028.09 | AN4: 2028.12 | AO4: 2028.12A
A5: 매출액 | B5: 손익 | C5: 억원 | D5: 매출액(수익) | E5: =IFERROR(VLOOKUP($D5,BS연결,MATCH(E$1,BS연결H,0),0)/100,"") | G5: =IFERROR(VLOOKUP($D5,BS연결,MATCH(G$1,BS연결H,0),0)/100,"") | H5: =IFERROR(VLOOKUP($D5,BS연결,MATCH(H$1,BS연결H,0),0)/100,"") | I5: =IFERROR(VLOOKUP($D5,BS연결,MATCH(I$1,BS연결H,0),0)/100,"") | J5: =IFERROR(VLOOKUP($D5,BS연결,MATCH(J$1,BS연결H,0),0)/100,"") | K5: =IFERROR(VLOOKUP($D5,BS연결,MATCH(K$1,BS연결H,0),0)/100,"") | L5: =IFERROR(VLOOKUP($D5,BS연결,MATCH(L$1,BS연결H,0),0)/100,"") | M5: =IFERROR(VLOOKUP($D5,BS연결,MATCH(M$1,BS연결H,0),0)/100,"") | N5: =IFERROR(VLOOKUP($D5,BS연결,MATCH(N$1,BS연결H,0),0)/100,"") | ... AB5: =IFERROR(VLOOKUP($D5,BS연결,MATCH(AB$1,BS연결H,0),0)/100,"") | AC5: =IFERROR(AC38+AC42,"") | AD5: =IFERROR(AD38+AD42,"") | AE5: =SUM(AA5:AD5) | AF5: =IFERROR(AF38+AF42,"") | AG5: =IFERROR(AG38+AG42,"") | AH5: =IFERROR(AH38+AH42,"") | AI5: =IFERROR(AI38+AI42,"") | AJ5: =SUM(AF5:AI5) | AK5: =IFERROR(AK38+AK42,"") | AL5: =IFERROR(AL38+AL42,"") | AM5: =IFERROR(AM38+AM42,"") | AN5: =IFERROR(AN38+AN42,"") | AO5: =SUM(AK5:AN5)
A6: 매출원가 | B6: 손익 | C6: 억원 | D6: 매출원가 | E6: =IFERROR(VLOOKUP($D6,BS연결,MATCH(E$1,BS연결H,0),0)/100,"") | G6: =IFERROR(VLOOKUP($D6,BS연결,MATCH(G$1,BS연결H,0),0)/100,"") | H6: =IFERROR(VLOOKUP($D6,BS연결,MATCH(H$1,BS연결H,0),0)/100,"") | I6: =IFERROR(VLOOKUP($D6,BS연결,MATCH(I$1,BS연결H,0),0)/100,"") | J6: =IFERROR(VLOOKUP($D6,BS연결,MATCH(J$1,BS연결H,0),0)/100,"") | K6: =IFERROR(VLOOKUP($D6,BS연결,MATCH(K$1,BS연결H,0),0)/100,"") | L6: =IFERROR(VLOOKUP($D6,BS연결,MATCH(L$1,BS연결H,0),0)/100,"") | M6: =IFERROR(VLOOKUP($D6,BS연결,MATCH(M$1,BS연결H,0),0)/100,"") | N6: =IFERROR(VLOOKUP($D6,BS연결,MATCH(N$1,BS연결H,0),0)/100,"") | ... AB6: =IFERROR(VLOOKUP($D6,BS연결,MATCH(AB$1,BS연결H,0),0)/100,"") | AC6: =IFERROR(AC5-AC7,"") | AD6: =IFERROR(AD5-AD7,"") | AE6: =SUM(AA6:AD6) | AF6: =IFERROR(AF5-AF7,"") | AG6: =IFERROR(AG5-AG7,"") | AH6: =IFERROR(AH5-AH7,"") | AI6: =IFERROR(AI5-AI7,"") | AJ6: =SUM(AF6:AI6) | AK6: =IFERROR(AK5-AK7,"") | AL6: =IFERROR(AL5-AL7,"") | AM6: =IFERROR(AM5-AM7,"") | AN6: =IFERROR(AN5-AN7,"") | AO6: =SUM(AK6:AN6)
A7: 매출총이익 | B7: 손익 | C7: 억원 | D7: 매출총이익 | E7: =IFERROR(VLOOKUP($D7,BS연결,MATCH(E$1,BS연결H,0),0)/100,"") | G7: =IFERROR(VLOOKUP($D7,BS연결,MATCH(G$1,BS연결H,0),0)/100,"") | H7: =IFERROR(VLOOKUP($D7,BS연결,MATCH(H$1,BS연결H,0),0)/100,"") | I7: =IFERROR(VLOOKUP($D7,BS연결,MATCH(I$1,BS연결H,0),0)/100,"") | J7: =IFERROR(VLOOKUP($D7,BS연결,MATCH(J$1,BS연결H,0),0)/100,"") | K7: =IFERROR(VLOOKUP($D7,BS연결,MATCH(K$1,BS연결H,0),0)/100,"") | L7: =IFERROR(VLOOKUP($D7,BS연결,MATCH(L$1,BS연결H,0),0)/100,"") | M7: =IFERROR(VLOOKUP($D7,BS연결,MATCH(M$1,BS연결H,0),0)/100,"") | N7: =IFERROR(VLOOKUP($D7,BS연결,MATCH(N$1,BS연결H,0),0)/100,"") | ... AB7: =IFERROR(VLOOKUP($D7,BS연결,MATCH(AB$1,BS연결H,0),0)/100,"") | AC7: =IFERROR(AC9+AC8,"") | AD7: =IFERROR(AD9+AD8,"") | AE7: =SUM(AA7:AD7) | AF7: =IFERROR(AF9+AF8,"") | AG7: =IFERROR(AG9+AG8,"") | AH7: =IFERROR(AH9+AH8,"") | AI7: =IFERROR(AI9+AI8,"") | AJ7: =SUM(AF7:AI7) | AK7: =IFERROR(AK9+AK8,"") | AL7: =IFERROR(AL9+AL8,"") | AM7: =IFERROR(AM9+AM8,"") | AN7: =IFERROR(AN9+AN8,"") | AO7: =SUM(AK7:AN7)
A8: 판관비 | B8: 손익 | C8: 억원 | D8: 판관비 | E8: =IFERROR(VLOOKUP($D8,BS연결,MATCH(E$1,BS연결H,0),0)/100,"") | G8: =IFERROR(VLOOKUP($D8,BS연결,MATCH(G$1,BS연결H,0),0)/100,"") | H8: =IFERROR(VLOOKUP($D8,BS연결,MATCH(H$1,BS연결H,0),0)/100,"") | I8: =IFERROR(VLOOKUP($D8,BS연결,MATCH(I$1,BS연결H,0),0)/100,"") | J8: =IFERROR(VLOOKUP($D8,BS연결,MATCH(J$1,BS연결H,0),0)/100,"") | K8: =IFERROR(VLOOKUP($D8,BS연결,MATCH(K$1,BS연결H,0),0)/100,"") | L8: =IFERROR(VLOOKUP($D8,BS연결,MATCH(L$1,BS연결H,0),0)/100,"") | M8: =IFERROR(VLOOKUP($D8,BS연결,MATCH(M$1,BS연결H,0),0)/100,"") | N8: =IFERROR(VLOOKUP($D8,BS연결,MATCH(N$1,BS연결H,0),0)/100,"") | ... AB8: =IFERROR(VLOOKUP($D8,BS연결,MATCH(AB$1,BS연결H,0),0)/100,"") | AC8: =IFERROR(AC5*변수!AC21,"") | AD8: =IFERROR(AD5*변수!AD21,"") | AE8: =SUM(AA8:AD8) | AF8: =IFERROR(AF5*변수!AF21,"") | AG8: =IFERROR(AG5*변수!AG21,"") | AH8: =IFERROR(AH5*변수!AH21,"") | AI8: =IFERROR(AI5*변수!AI21,"") | AJ8: =SUM(AF8:AI8) | AK8: =IFERROR(AK5*변수!AK21,"") | AL8: =IFERROR(AL5*변수!AL21,"") | AM8: =IFERROR(AM5*변수!AM21,"") | AN8: =IFERROR(AN5*변수!AN21,"") | AO8: =SUM(AK8:AN8)
A9: 영업이익 | B9: 손익 | C9: 억원 | D9: 영업이익 | E9: =IFERROR(VLOOKUP($D9,BS연결,MATCH(E$1,BS연결H,0),0)/100,"") | G9: =IFERROR(VLOOKUP($D9,BS연결,MATCH(G$1,BS연결H,0),0)/100,"") | H9: =IFERROR(VLOOKUP($D9,BS연결,MATCH(H$1,BS연결H,0),0)/100,"") | I9: =IFERROR(VLOOKUP($D9,BS연결,MATCH(I$1,BS연결H,0),0)/100,"") | J9: =IFERROR(VLOOKUP($D9,BS연결,MATCH(J$1,BS연결H,0),0)/100,"") | K9: =IFERROR(VLOOKUP($D9,BS연결,MATCH(K$1,BS연결H,0),0)/100,"") | L9: =IFERROR(VLOOKUP($D9,BS연결,MATCH(L$1,BS연결H,0),0)/100,"") | M9: =IFERROR(VLOOKUP($D9,BS연결,MATCH(M$1,BS연결H,0),0)/100,"") | N9: =IFERROR(VLOOKUP($D9,BS연결,MATCH(N$1,BS연결H,0),0)/100,"") | P9: =SUM(L9:O9) | Q9: =IFERROR(VLOOKUP($D9,BS연결,MATCH(Q$1,BS연결H,0),0)/100,"") | R9: =IFERROR(VLOOKUP($D9,BS연결,MATCH(R$1,BS연결H,0),0)/100,"") | S9: =IFERROR(VLOOKUP($D9,BS연결,MATCH(S$1,BS연결H,0),0)/100,"") | T9: =IFERROR(VLOOKUP($D9,BS연결,MATCH(T$1,BS연결H,0),0)/100,"") | U9: =IFERROR(VLOOKUP($D9,BS연결,MATCH(U$1,BS연결H,0),0)/100,"") | V9: =IFERROR(VLOOKUP($D9,BS연결,MATCH(V$1,BS연결H,0),0)/100,"") | W9: =IFERROR(VLOOKUP($D9,BS연결,MATCH(W$1,BS연결H,0),0)/100,"") | X9: =IFERROR(VLOOKUP($D9,BS연결,MATCH(X$1,BS연결H,0),0)/100,"") | ... AB9: =IFERROR(VLOOKUP($D9,BS연결,MATCH(AB$1,BS연결H,0),0)/100,"") | AC9: =IFERROR(AC40+AC43,"") | AD9: =IFERROR(AD40+AD43,"") | AE9: =SUM(AA9:AD9) | AF9: =IFERROR(AF40+AF43,"") | AG9: =IFERROR(AG40+AG43,"") | AH9: =IFERROR(AH40+AH43,"") | AI9: =IFERROR(AI40+AI43,"") | AJ9: =SUM(AF9:AI9) | AK9: =IFERROR(AK40+AK43,"") | AL9: =IFERROR(AL40+AL43,"") | AM9: =IFERROR(AM40+AM43,"") | AN9: =IFERROR(AN40+AN43,"") | AO9: =SUM(AK9:AN9)
A10: OPM | B10: 손익 | C10: % | D10: 영업이익률 | E10: =IFERROR(E9/E5,"") | G10: =IFERROR(G9/G5,"") | H10: =IFERROR(H9/H5,"") | I10: =IFERROR(I9/I5,"") | J10: =IFERROR(J9/J5,"") | K10: =IFERROR(K9/K5,"") | L10: =IFERROR(L9/L5,"") | M10: =IFERROR(M9/M5,"") | N10: =IFERROR(N9/N5,"") | P10: =IFERROR(P9/P5,"") | Q10: =IFERROR(Q9/Q5,"") | R10: =IFERROR(R9/R5,"") | S10: =IFERROR(S9/S5,"") | T10: =IFERROR(T9/T5,"") | U10: =IFERROR(U9/U5,"") | V10: =IFERROR(V9/V5,"") | W10: =IFERROR(W9/W5,"") | ... AO10: =IFERROR(AO9/AO5,"")
A11: 금융손익 | B11: 손익 | C11: 억원 | D11: 금융손익 | E11: =IFERROR(VLOOKUP($D11,BS연결,MATCH(E$1,BS연결H,0),0)/100,"") | G11: =IFERROR(VLOOKUP($D11,BS연결,MATCH(G$1,BS연결H,0),0)/100,"") | H11: =IFERROR(VLOOKUP($D11,BS연결,MATCH(H$1,BS연결H,0),0)/100,"") | I11: =IFERROR(VLOOKUP($D11,BS연결,MATCH(I$1,BS연결H,0),0)/100,"") | J11: =IFERROR(VLOOKUP($D11,BS연결,MATCH(J$1,BS연결H,0),0)/100,"") | K11: =IFERROR(VLOOKUP($D11,BS연결,MATCH(K$1,BS연결H,0),0)/100,"") | L11: =IFERROR(VLOOKUP($D11,BS연결,MATCH(L$1,BS연결H,0),0)/100,"") | M11: =IFERROR(VLOOKUP($D11,BS연결,MATCH(M$1,BS연결H,0),0)/100,"") | N11: =IFERROR(VLOOKUP($D11,BS연결,MATCH(N$1,BS연결H,0),0)/100,"") | ... AB11: =IFERROR(VLOOKUP($D11,BS연결,MATCH(AB$1,BS연결H,0),0)/100,"") | AC11: =IFERROR(AC12+AC13+AC14+AC15,"") | AD11: =IFERROR(AD12+AD13+AD14+AD15,"") | AE11: =SUM(AA11:AD11) | AF11: =IFERROR(AF12+AF13+AF14+AF15,"") | AG11: =IFERROR(AG12+AG13+AG14+AG15,"") | AH11: =IFERROR(AH12+AH13+AH14+AH15,"") | AI11: =IFERROR(AI12+AI13+AI14+AI15,"") | AJ11: =SUM(AF11:AI11) | AK11: =IFERROR(AK12+AK13+AK14+AK15,"") | AL11: =IFERROR(AL12+AL13+AL14+AL15,"") | AM11: =IFERROR(AM12+AM13+AM14+AM15,"") | AN11: =IFERROR(AN12+AN13+AN14+AN15,"") | AO11: =SUM(AK11:AN11)
A12: 이자손익 | B12: 손익 | C12: 억원 | D12: 이자손익 | G12: =IFERROR(VLOOKUP($D12,BS연결,MATCH(G$1,BS연결H,0),0)/100,"") | H12: =IFERROR(VLOOKUP($D12,BS연결,MATCH(H$1,BS연결H,0),0)/100,"") | I12: =IFERROR(VLOOKUP($D12,BS연결,MATCH(I$1,BS연결H,0),0)/100,"") | J12: =IFERROR(VLOOKUP($D12,BS연결,MATCH(J$1,BS연결H,0),0)/100,"") | K12: =IFERROR(VLOOKUP($D12,BS연결,MATCH(K$1,BS연결H,0),0)/100,"") | L12: =IFERROR(VLOOKUP($D12,BS연결,MATCH(L$1,BS연결H,0),0)/100,"") | M12: =IFERROR(VLOOKUP($D12,BS연결,MATCH(M$1,BS연결H,0),0)/100,"") | N12: =IFERROR(VLOOKUP($D12,BS연결,MATCH(N$1,BS연결H,0),0)/100,"") | ... AB12: =IFERROR(VLOOKUP($D12,BS연결,MATCH(AB$1,BS연결H,0),0)/100,"") | AC12: =IFERROR((AB28*변수!$D$57-AB26*변수!$D$58)/4,"") | AD12: =IFERROR((AC28*변수!$D$57-AC26*변수!$D$58)/4,"") | AE12: =SUM(AA12:AD12) | AF12: =IFERROR((AD28*변수!$D$57-AD26*변수!$D$58)/4,"") | AG12: =IFERROR((AF28*변수!$D$57-AF26*변수!$D$58)/4,"") | AH12: =IFERROR((AG28*변수!$D$57-AG26*변수!$D$58)/4,"") | AI12: =IFERROR((AH28*변수!$D$57-AH26*변수!$D$58)/4,"") | AJ12: =SUM(AF12:AI12) | AK12: =IFERROR((AI28*변수!$D$57-AI26*변수!$D$58)/4,"") | AL12: =IFERROR((AK28*변수!$D$57-AK26*변수!$D$58)/4,"") | AM12: =IFERROR((AL28*변수!$D$57-AL26*변수!$D$58)/4,"") | AN12: =IFERROR((AM28*변수!$D$57-AM26*변수!$D$58)/4,"") | AO12: =SUM(AK12:AN12)
A13: 외환손익 | B13: 손익 | C13: 억원 | D13: 외환손익(실적만; 추정 환효과는 환관련손익) | G13: =IFERROR((VLOOKUP("외환차익",BS연결,MATCH(G$1,BS연결H,0),0)-VLOOKUP("외환차손",BS연결,MATCH(G$1,BS연결H,0),0)+VLOOKUP("외화환산이익",BS연결,MATCH(G$1,BS연결H,0),0)-VLOOKUP("외화환산손실",BS연결,MATCH(G$1,BS연결H,0),0))/100,"") | H13: =IFERROR((VLOOKUP("외환차익",BS연결,MATCH(H$1,BS연결H,0),0)-VLOOKUP("외환차손",BS연결,MATCH(H$1,BS연결H,0),0)+VLOOKUP("외화환산이익",BS연결,MATCH(H$1,BS연결H,0),0)-VLOOKUP("외화환산손실",BS연결,MATCH(H$1,BS연결H,0),0))/100,"") | I13: =IFERROR((VLOOKUP("외환차익",BS연결,MATCH(I$1,BS연결H,0),0)-VLOOKUP("외환차손",BS연결,MATCH(I$1,BS연결H,0),0)+VLOOKUP("외화환산이익",BS연결,MATCH(I$1,BS연결H,0),0)-VLOOKUP("외화환산손실",BS연결,MATCH(I$1,BS연결H,0),0))/100,"") | J13: =IFERROR((VLOOKUP("외환차익",BS연결,MATCH(J$1,BS연결H,0),0)-VLOOKUP("외환차손",BS연결,MATCH(J$1,BS연결H,0),0)+VLOOKUP("외화환산이익",BS연결,MATCH(J$1,BS연결H,0),0)-VLOOKUP("외화환산손실",BS연결,MATCH(J$1,BS연결H,0),0))/100,"") | K13: =SUM(G13:J13) | L13: =IFERROR((VLOOKUP("외환차익",BS연결,MATCH(L$1,BS연결H,0),0)-VLOOKUP("외환차손",BS연결,MATCH(L$1,BS연결H,0),0)+VLOOKUP("외화환산이익",BS연결,MATCH(L$1,BS연결H,0),0)-VLOOKUP("외화환산손실",BS연결,MATCH(L$1,BS연결H,0),0))/100,"") | M13: =IFERROR((VLOOKUP("외환차익",BS연결,MATCH(M$1,BS연결H,0),0)-VLOOKUP("외환차손",BS연결,MATCH(M$1,BS연결H,0),0)+VLOOKUP("외화환산이익",BS연결,MATCH(M$1,BS연결H,0),0)-VLOOKUP("외화환산손실",BS연결,MATCH(M$1,BS연결H,0),0))/100,"") | N13: =IFERROR((VLOOKUP("외환차익",BS연결,MATCH(N$1,BS연결H,0),0)-VLOOKUP("외환차손",BS연결,MATCH(N$1,BS연결H,0),0)+VLOOKUP("외화환산이익",BS연결,MATCH(N$1,BS연결H,0),0)-VLOOKUP("외화환산손실",BS연결,MATCH(N$1,BS연결H,0),0))/100,"") | O13: =IFERROR((VLOOKUP("외환차익",BS연결,MATCH(O$1,BS연결H,0),0)-VLOOKUP("외환차손",BS연결,MATCH(O$1,BS연결H,0),0)+VLOOKUP("외화환산이익",BS연결,MATCH(O$1,BS연결H,0),0)-VLOOKUP("외화환산손실",BS연결,MATCH(O$1,BS연결H,0),0))/100,"") | P13: =SUM(L13:O13) | Q13: =IFERROR((VLOOKUP("외환차익",BS연결,MATCH(Q$1,BS연결H,0),0)-VLOOKUP("외환차손",BS연결,MATCH(Q$1,BS연결H,0),0)+VLOOKUP("외화환산이익",BS연결,MATCH(Q$1,BS연결H,0),0)-VLOOKUP("외화환산손실",BS연결,MATCH(Q$1,BS연결H,0),0))/100,"") | R13: =IFERROR((VLOOKUP("외환차익",BS연결,MATCH(R$1,BS연결H,0),0)-VLOOKUP("외환차손",BS연결,MATCH(R$1,BS연결H,0),0)+VLOOKUP("외화환산이익",BS연결,MATCH(R$1,BS연결H,0),0)-VLOOKUP("외화환산손실",BS연결,MATCH(R$1,BS연결H,0),0))/100,"") | S13: =IFERROR((VLOOKUP("외환차익",BS연결,MATCH(S$1,BS연결H,0),0)-VLOOKUP("외환차손",BS연결,MATCH(S$1,BS연결H,0),0)+VLOOKUP("외화환산이익",BS연결,MATCH(S$1,BS연결H,0),0)-VLOOKUP("외화환산손실",BS연결,MATCH(S$1,BS연결H,0),0))/100,"") | T13: =IFERROR((VLOOKUP("외환차익",BS연결,MATCH(T$1,BS연결H,0),0)-VLOOKUP("외환차손",BS연결,MATCH(T$1,BS연결H,0),0)+VLOOKUP("외화환산이익",BS연결,MATCH(T$1,BS연결H,0),0)-VLOOKUP("외화환산손실",BS연결,MATCH(T$1,BS연결H,0),0))/100,"") | U13: =SUM(Q13:T13) | V13: =IFERROR((VLOOKUP("외환차익",BS연결,MATCH(V$1,BS연결H,0),0)-VLOOKUP("외환차손",BS연결,MATCH(V$1,BS연결H,0),0)+VLOOKUP("외화환산이익",BS연결,MATCH(V$1,BS연결H,0),0)-VLOOKUP("외화환산손실",BS연결,MATCH(V$1,BS연결H,0),0))/100,"") | W13: =IFERROR((VLOOKUP("외환차익",BS연결,MATCH(W$1,BS연결H,0),0)-VLOOKUP("외환차손",BS연결,MATCH(W$1,BS연결H,0),0)+VLOOKUP("외화환산이익",BS연결,MATCH(W$1,BS연결H,0),0)-VLOOKUP("외화환산손실",BS연결,MATCH(W$1,BS연결H,0),0))/100,"") | X13: =IFERROR((VLOOKUP("외환차익",BS연결,MATCH(X$1,BS연결H,0),0)-VLOOKUP("외환차손",BS연결,MATCH(X$1,BS연결H,0),0)+VLOOKUP("외화환산이익",BS연결,MATCH(X$1,BS연결H,0),0)-VLOOKUP("외화환산손실",BS연결,MATCH(X$1,BS연결H,0),0))/100,"") | Y13: =IFERROR((VLOOKUP("외환차익",BS연결,MATCH(Y$1,BS연결H,0),0)-VLOOKUP("외환차손",BS연결,MATCH(Y$1,BS연결H,0),0)+VLOOKUP("외화환산이익",BS연결,MATCH(Y$1,BS연결H,0),0)-VLOOKUP("외화환산손실",BS연결,MATCH(Y$1,BS연결H,0),0))/100,"") | Z13: =SUM(V13:Y13) | AA13: =IFERROR((VLOOKUP("외환차익",BS연결,MATCH(AA$1,BS연결H,0),0)-VLOOKUP("외환차손",BS연결,MATCH(AA$1,BS연결H,0),0)+VLOOKUP("외화환산이익",BS연결,MATCH(AA$1,BS연결H,0),0)-VLOOKUP("외화환산손실",BS연결,MATCH(AA$1,BS연결H,0),0))/100,"") | AB13: =IFERROR((VLOOKUP("외환차익",BS연결,MATCH(AB$1,BS연결H,0),0)-VLOOKUP("외환차손",BS연결,MATCH(AB$1,BS연결H,0),0)+VLOOKUP("외화환산이익",BS연결,MATCH(AB$1,BS연결H,0),0)-VLOOKUP("외화환산손실",BS연결,MATCH(AB$1,BS연결H,0),0))/100,"") | AC13: =변수!AC22 | AD13: =변수!AD22 | AE13: =SUM(AA13:AD13) | AF13: =변수!AF22 | AG13: =변수!AG22 | AH13: =변수!AH22 | AI13: =변수!AI22 | AJ13: =SUM(AF13:AI13) | AK13: =변수!AK22 | AL13: =변수!AL22 | AM13: =변수!AM22 | AN13: =변수!AN22 | AO13: =SUM(AK13:AN13)
A14: 파생상품손익 | B14: 손익 | C14: 억원 | D14: 파생상품손익 | K14: =SUM(G14:J14) | P14: =SUM(L14:O14) | U14: =SUM(Q14:T14) | W14: =IFERROR((VLOOKUP("파생상품이익",BS연결,MATCH(W$1,BS연결H,0),0)-VLOOKUP("파생상품손실",BS연결,MATCH(W$1,BS연결H,0),0))/100,"") | X14: =IFERROR((VLOOKUP("파생상품이익",BS연결,MATCH(X$1,BS연결H,0),0)-VLOOKUP("파생상품손실",BS연결,MATCH(X$1,BS연결H,0),0))/100,"") | Y14: =IFERROR((VLOOKUP("파생상품이익",BS연결,MATCH(Y$1,BS연결H,0),0)-VLOOKUP("파생상품손실",BS연결,MATCH(Y$1,BS연결H,0),0))/100,"") | Z14: =SUM(V14:Y14) | AA14: =IFERROR((VLOOKUP("파생상품이익",BS연결,MATCH(AA$1,BS연결H,0),0)-VLOOKUP("파생상품손실",BS연결,MATCH(AA$1,BS연결H,0),0))/100,"") | AB14: =IFERROR((VLOOKUP("파생상품이익",BS연결,MATCH(AB$1,BS연결H,0),0)-VLOOKUP("파생상품손실",BS연결,MATCH(AB$1,BS연결H,0),0))/100,"") | AC14: =변수!AC23 | AD14: =변수!AD23 | AE14: =SUM(AA14:AD14) | AF14: =변수!AF23 | AG14: =변수!AG23 | AH14: =변수!AH23 | AI14: =변수!AI23 | AJ14: =SUM(AF14:AI14) | AK14: =변수!AK23 | AL14: =변수!AL23 | AM14: =변수!AM23 | AN14: =변수!AN23 | AO14: =SUM(AK14:AN14)
A15: 기타금융손익 | B15: 손익 | C15: 억원 | D15: 기타금융손익(금융손익 잔차) | K15: =SUM(G15:J15) | P15: =SUM(L15:O15) | U15: =SUM(Q15:T15) | W15: =IFERROR(W11-W12-W13-W14,"") | X15: =IFERROR(X11-X12-X13-X14,"") | Y15: =IFERROR(Y11-Y12-Y13-Y14,"") | Z15: =SUM(V15:Y15) | AA15: =IFERROR(AA11-AA12-AA13-AA14,"") | AB15: =IFERROR(AB11-AB12-AB13-AB14,"") | AC15: =변수!AC24 | AD15: =변수!AD24 | AE15: =SUM(AA15:AD15) | AF15: =변수!AF24 | AG15: =변수!AG24 | AH15: =변수!AH24 | AI15: =변수!AI24 | AJ15: =SUM(AF15:AI15) | AK15: =변수!AK24 | AL15: =변수!AL24 | AM15: =변수!AM24 | AN15: =변수!AN24 | AO15: =SUM(AK15:AN15)
A16: 기타영업외손익 | B16: 손익 | C16: 억원 | D16: 기타영업외손익 | E16: =IFERROR(VLOOKUP($D16,BS연결,MATCH(E$1,BS연결H,0),0)/100,"") | G16: =IFERROR(VLOOKUP($D16,BS연결,MATCH(G$1,BS연결H,0),0)/100,"") | H16: =IFERROR(VLOOKUP($D16,BS연결,MATCH(H$1,BS연결H,0),0)/100,"") | I16: =IFERROR(VLOOKUP($D16,BS연결,MATCH(I$1,BS연결H,0),0)/100,"") | J16: =IFERROR(VLOOKUP($D16,BS연결,MATCH(J$1,BS연결H,0),0)/100,"") | K16: =IFERROR(VLOOKUP($D16,BS연결,MATCH(K$1,BS연결H,0),0)/100,"") | L16: =IFERROR(VLOOKUP($D16,BS연결,MATCH(L$1,BS연결H,0),0)/100,"") | M16: =IFERROR(VLOOKUP($D16,BS연결,MATCH(M$1,BS연결H,0),0)/100,"") | N16: =IFERROR(VLOOKUP($D16,BS연결,MATCH(N$1,BS연결H,0),0)/100,"") | ... AB16: =IFERROR(VLOOKUP($D16,BS연결,MATCH(AB$1,BS연결H,0),0)/100,"") | AC16: =변수!AC25 | AD16: =변수!AD25 | AE16: =SUM(AA16:AD16) | AF16: =변수!AF25 | AG16: =변수!AG25 | AH16: =변수!AH25 | AI16: =변수!AI25 | AJ16: =SUM(AF16:AI16) | AK16: =변수!AK25 | AL16: =변수!AL25 | AM16: =변수!AM25 | AN16: =변수!AN25 | AO16: =SUM(AK16:AN16)
A17: 지분법손익 | B17: 손익 | C17: 억원 | D17: 종속기업,공동지배기업및관계기업관련손익 | E17: =IFERROR(VLOOKUP($D17,BS연결,MATCH(E$1,BS연결H,0),0)/100,"") | G17: =IFERROR(VLOOKUP($D17,BS연결,MATCH(G$1,BS연결H,0),0)/100,"") | H17: =IFERROR(VLOOKUP($D17,BS연결,MATCH(H$1,BS연결H,0),0)/100,"") | I17: =IFERROR(VLOOKUP($D17,BS연결,MATCH(I$1,BS연결H,0),0)/100,"") | J17: =IFERROR(VLOOKUP($D17,BS연결,MATCH(J$1,BS연결H,0),0)/100,"") | K17: =IFERROR(VLOOKUP($D17,BS연결,MATCH(K$1,BS연결H,0),0)/100,"") | L17: =IFERROR(VLOOKUP($D17,BS연결,MATCH(L$1,BS연결H,0),0)/100,"") | M17: =IFERROR(VLOOKUP($D17,BS연결,MATCH(M$1,BS연결H,0),0)/100,"") | N17: =IFERROR(VLOOKUP($D17,BS연결,MATCH(N$1,BS연결H,0),0)/100,"") | ... AB17: =IFERROR(VLOOKUP($D17,BS연결,MATCH(AB$1,BS연결H,0),0)/100,"") | AC17: =변수!AC26 | AD17: =변수!AD26 | AE17: =SUM(AA17:AD17) | AF17: =변수!AF26 | AG17: =변수!AG26 | AH17: =변수!AH26 | AI17: =변수!AI26 | AJ17: =SUM(AF17:AI17) | AK17: =변수!AK26 | AL17: =변수!AL26 | AM17: =변수!AM26 | AN17: =변수!AN26 | AO17: =SUM(AK17:AN17)
A18: 세전이익 | B18: 손익 | C18: 억원 | D18: 법인세비용차감전계속사업이익 | E18: =IFERROR(VLOOKUP($D18,BS연결,MATCH(E$1,BS연결H,0),0)/100,"") | G18: =IFERROR(VLOOKUP($D18,BS연결,MATCH(G$1,BS연결H,0),0)/100,"") | H18: =IFERROR(VLOOKUP($D18,BS연결,MATCH(H$1,BS연결H,0),0)/100,"") | I18: =IFERROR(VLOOKUP($D18,BS연결,MATCH(I$1,BS연결H,0),0)/100,"") | J18: =IFERROR(VLOOKUP($D18,BS연결,MATCH(J$1,BS연결H,0),0)/100,"") | K18: =IFERROR(VLOOKUP($D18,BS연결,MATCH(K$1,BS연결H,0),0)/100,"") | L18: =IFERROR(VLOOKUP($D18,BS연결,MATCH(L$1,BS연결H,0),0)/100,"") | M18: =IFERROR(VLOOKUP($D18,BS연결,MATCH(M$1,BS연결H,0),0)/100,"") | N18: =IFERROR(VLOOKUP($D18,BS연결,MATCH(N$1,BS연결H,0),0)/100,"") | ... AB18: =IFERROR(VLOOKUP($D18,BS연결,MATCH(AB$1,BS연결H,0),0)/100,"") | AC18: =IFERROR(AC9+AC11+AC16+AC17,"") | AD18: =IFERROR(AD9+AD11+AD16+AD17,"") | AE18: =SUM(AA18:AD18) | AF18: =IFERROR(AF9+AF11+AF16+AF17,"") | AG18: =IFERROR(AG9+AG11+AG16+AG17,"") | AH18: =IFERROR(AH9+AH11+AH16+AH17,"") | AI18: =IFERROR(AI9+AI11+AI16+AI17,"") | AJ18: =SUM(AF18:AI18) | AK18: =IFERROR(AK9+AK11+AK16+AK17,"") | AL18: =IFERROR(AL9+AL11+AL16+AL17,"") | AM18: =IFERROR(AM9+AM11+AM16+AM17,"") | AN18: =IFERROR(AN9+AN11+AN16+AN17,"") | AO18: =SUM(AK18:AN18)
A19: 법인세비용 | B19: 손익 | C19: 억원 | D19: 법인세비용 | E19: =IFERROR(VLOOKUP($D19,BS연결,MATCH(E$1,BS연결H,0),0)/100,"") | G19: =IFERROR(VLOOKUP($D19,BS연결,MATCH(G$1,BS연결H,0),0)/100,"") | H19: =IFERROR(VLOOKUP($D19,BS연결,MATCH(H$1,BS연결H,0),0)/100,"") | I19: =IFERROR(VLOOKUP($D19,BS연결,MATCH(I$1,BS연결H,0),0)/100,"") | J19: =IFERROR(VLOOKUP($D19,BS연결,MATCH(J$1,BS연결H,0),0)/100,"") | K19: =IFERROR(VLOOKUP($D19,BS연결,MATCH(K$1,BS연결H,0),0)/100,"") | L19: =IFERROR(VLOOKUP($D19,BS연결,MATCH(L$1,BS연결H,0),0)/100,"") | M19: =IFERROR(VLOOKUP($D19,BS연결,MATCH(M$1,BS연결H,0),0)/100,"") | N19: =IFERROR(VLOOKUP($D19,BS연결,MATCH(N$1,BS연결H,0),0)/100,"") | ... AB19: =IFERROR(VLOOKUP($D19,BS연결,MATCH(AB$1,BS연결H,0),0)/100,"") | AC19: =IFERROR(MAX(AC18,0)*변수!AC27,"") | AD19: =IFERROR(MAX(AD18,0)*변수!AD27,"") | AE19: =SUM(AA19:AD19) | AF19: =IFERROR(MAX(AF18,0)*변수!AF27,"") | AG19: =IFERROR(MAX(AG18,0)*변수!AG27,"") | AH19: =IFERROR(MAX(AH18,0)*변수!AH27,"") | AI19: =IFERROR(MAX(AI18,0)*변수!AI27,"") | AJ19: =SUM(AF19:AI19) | AK19: =IFERROR(MAX(AK18,0)*변수!AK27,"") | AL19: =IFERROR(MAX(AL18,0)*변수!AL27,"") | AM19: =IFERROR(MAX(AM18,0)*변수!AM27,"") | AN19: =IFERROR(MAX(AN18,0)*변수!AN27,"") | AO19: =SUM(AK19:AN19)
A20: 당기순이익 | B20: 손익 | C20: 억원 | D20: 당기순이익 | E20: =IFERROR(VLOOKUP($D20,BS연결,MATCH(E$1,BS연결H,0),0)/100,"") | G20: =IFERROR(VLOOKUP($D20,BS연결,MATCH(G$1,BS연결H,0),0)/100,"") | H20: =IFERROR(VLOOKUP($D20,BS연결,MATCH(H$1,BS연결H,0),0)/100,"") | I20: =IFERROR(VLOOKUP($D20,BS연결,MATCH(I$1,BS연결H,0),0)/100,"") | J20: =IFERROR(VLOOKUP($D20,BS연결,MATCH(J$1,BS연결H,0),0)/100,"") | K20: =IFERROR(VLOOKUP($D20,BS연결,MATCH(K$1,BS연결H,0),0)/100,"") | L20: =IFERROR(VLOOKUP($D20,BS연결,MATCH(L$1,BS연결H,0),0)/100,"") | M20: =IFERROR(VLOOKUP($D20,BS연결,MATCH(M$1,BS연결H,0),0)/100,"") | N20: =IFERROR(VLOOKUP($D20,BS연결,MATCH(N$1,BS연결H,0),0)/100,"") | ... AB20: =IFERROR(VLOOKUP($D20,BS연결,MATCH(AB$1,BS연결H,0),0)/100,"") | AC20: =IFERROR(AC18-AC19,"") | AD20: =IFERROR(AD18-AD19,"") | AE20: =SUM(AA20:AD20) | AF20: =IFERROR(AF18-AF19,"") | AG20: =IFERROR(AG18-AG19,"") | AH20: =IFERROR(AH18-AH19,"") | AI20: =IFERROR(AI18-AI19,"") | AJ20: =SUM(AF20:AI20) | AK20: =IFERROR(AK18-AK19,"") | AL20: =IFERROR(AL18-AL19,"") | AM20: =IFERROR(AM18-AM19,"") | AN20: =IFERROR(AN18-AN19,"") | AO20: =SUM(AK20:AN20)
A21: 지배주주순이익 | B21: 손익 | C21: 억원 | D21: (지배주주지분)당기순이익 | E21: =IFERROR(VLOOKUP($D21,BS연결,MATCH(E$1,BS연결H,0),0)/100,"") | G21: =IFERROR(VLOOKUP($D21,BS연결,MATCH(G$1,BS연결H,0),0)/100,"") | H21: =IFERROR(VLOOKUP($D21,BS연결,MATCH(H$1,BS연결H,0),0)/100,"") | I21: =IFERROR(VLOOKUP($D21,BS연결,MATCH(I$1,BS연결H,0),0)/100,"") | J21: =IFERROR(VLOOKUP($D21,BS연결,MATCH(J$1,BS연결H,0),0)/100,"") | K21: =IFERROR(VLOOKUP($D21,BS연결,MATCH(K$1,BS연결H,0),0)/100,"") | L21: =IFERROR(VLOOKUP($D21,BS연결,MATCH(L$1,BS연결H,0),0)/100,"") | M21: =IFERROR(VLOOKUP($D21,BS연결,MATCH(M$1,BS연결H,0),0)/100,"") | N21: =IFERROR(VLOOKUP($D21,BS연결,MATCH(N$1,BS연결H,0),0)/100,"") | ... AB21: =IFERROR(VLOOKUP($D21,BS연결,MATCH(AB$1,BS연결H,0),0)/100,"") | AC21: =IFERROR(AC20*변수!AC28,"") | AD21: =IFERROR(AD20*변수!AD28,"") | AE21: =SUM(AA21:AD21) | AF21: =IFERROR(AF20*변수!AF28,"") | AG21: =IFERROR(AG20*변수!AG28,"") | AH21: =IFERROR(AH20*변수!AH28,"") | AI21: =IFERROR(AI20*변수!AI28,"") | AJ21: =SUM(AF21:AI21) | AK21: =IFERROR(AK20*변수!AK28,"") | AL21: =IFERROR(AL20*변수!AL28,"") | AM21: =IFERROR(AM20*변수!AM28,"") | AN21: =IFERROR(AN20*변수!AN28,"") | AO21: =SUM(AK21:AN21)
A22: 자산총계 | B22: 재무상태 | C22: 억원 | D22: 자산총계 | E22: =IFERROR(VLOOKUP($D22,BS연결,MATCH(E$1,BS연결H,0),0)/100,"") | F22: =IFERROR(VLOOKUP($D22,BS연결,MATCH(F$1,BS연결H,0),0)/100,"") | G22: =IFERROR(VLOOKUP($D22,BS연결,MATCH(G$1,BS연결H,0),0)/100,"") | H22: =IFERROR(VLOOKUP($D22,BS연결,MATCH(H$1,BS연결H,0),0)/100,"") | I22: =IFERROR(VLOOKUP($D22,BS연결,MATCH(I$1,BS연결H,0),0)/100,"") | J22: =IFERROR(VLOOKUP($D22,BS연결,MATCH(J$1,BS연결H,0),0)/100,"") | K22: =IFERROR(VLOOKUP($D22,BS연결,MATCH(K$1,BS연결H,0),0)/100,"") | L22: =IFERROR(VLOOKUP($D22,BS연결,MATCH(L$1,BS연결H,0),0)/100,"") | ... AB22: =IFERROR(VLOOKUP($D22,BS연결,MATCH(AB$1,BS연결H,0),0)/100,"") | AC22: =IFERROR(AC23+AC24,"") | AD22: =IFERROR(AD23+AD24,"") | AE22: =AD22 | AF22: =IFERROR(AF23+AF24,"") | AG22: =IFERROR(AG23+AG24,"") | AH22: =IFERROR(AH23+AH24,"") | AI22: =IFERROR(AI23+AI24,"") | AJ22: =AI22 | AK22: =IFERROR(AK23+AK24,"") | AL22: =IFERROR(AL23+AL24,"") | AM22: =IFERROR(AM23+AM24,"") | AN22: =IFERROR(AN23+AN24,"") | AO22: =AN22
A23: 부채총계 | B23: 재무상태 | C23: 억원 | D23: 부채총계 | E23: =IFERROR(VLOOKUP($D23,BS연결,MATCH(E$1,BS연결H,0),0)/100,"") | F23: =IFERROR(VLOOKUP($D23,BS연결,MATCH(F$1,BS연결H,0),0)/100,"") | G23: =IFERROR(VLOOKUP($D23,BS연결,MATCH(G$1,BS연결H,0),0)/100,"") | H23: =IFERROR(VLOOKUP($D23,BS연결,MATCH(H$1,BS연결H,0),0)/100,"") | I23: =IFERROR(VLOOKUP($D23,BS연결,MATCH(I$1,BS연결H,0),0)/100,"") | J23: =IFERROR(VLOOKUP($D23,BS연결,MATCH(J$1,BS연결H,0),0)/100,"") | K23: =IFERROR(VLOOKUP($D23,BS연결,MATCH(K$1,BS연결H,0),0)/100,"") | L23: =IFERROR(VLOOKUP($D23,BS연결,MATCH(L$1,BS연결H,0),0)/100,"") | ... AB23: =IFERROR(VLOOKUP($D23,BS연결,MATCH(AB$1,BS연결H,0),0)/100,"") | AC23: =IFERROR(AB23*(1+변수!AC29),"") | AD23: =IFERROR(AC23*(1+변수!AD29),"") | AE23: =AD23 | AF23: =IFERROR(AD23*(1+변수!AF29),"") | AG23: =IFERROR(AF23*(1+변수!AG29),"") | AH23: =IFERROR(AG23*(1+변수!AH29),"") | AI23: =IFERROR(AH23*(1+변수!AI29),"") | AJ23: =AI23 | AK23: =IFERROR(AI23*(1+변수!AK29),"") | AL23: =IFERROR(AK23*(1+변수!AL29),"") | AM23: =IFERROR(AL23*(1+변수!AM29),"") | AN23: =IFERROR(AM23*(1+변수!AN29),"") | AO23: =AN23
A24: 자본총계 | B24: 재무상태 | C24: 억원 | D24: 자본총계 | E24: =IFERROR(VLOOKUP($D24,BS연결,MATCH(E$1,BS연결H,0),0)/100,"") | F24: =IFERROR(VLOOKUP($D24,BS연결,MATCH(F$1,BS연결H,0),0)/100,"") | G24: =IFERROR(VLOOKUP($D24,BS연결,MATCH(G$1,BS연결H,0),0)/100,"") | H24: =IFERROR(VLOOKUP($D24,BS연결,MATCH(H$1,BS연결H,0),0)/100,"") | I24: =IFERROR(VLOOKUP($D24,BS연결,MATCH(I$1,BS연결H,0),0)/100,"") | J24: =IFERROR(VLOOKUP($D24,BS연결,MATCH(J$1,BS연결H,0),0)/100,"") | K24: =IFERROR(VLOOKUP($D24,BS연결,MATCH(K$1,BS연결H,0),0)/100,"") | L24: =IFERROR(VLOOKUP($D24,BS연결,MATCH(L$1,BS연결H,0),0)/100,"") | ... AB24: =IFERROR(VLOOKUP($D24,BS연결,MATCH(AB$1,BS연결H,0),0)/100,"") | AC24: =IFERROR(AB24+AC20-변수!AC30,"") | AD24: =IFERROR(AC24+AD20-변수!AD30,"") | AE24: =AD24 | AF24: =IFERROR(AD24+AF20-변수!AF30,"") | AG24: =IFERROR(AF24+AG20-변수!AG30,"") | AH24: =IFERROR(AG24+AH20-변수!AH30,"") | AI24: =IFERROR(AH24+AI20-변수!AI30,"") | AJ24: =AI24 | AK24: =IFERROR(AI24+AK20-변수!AK30,"") | AL24: =IFERROR(AK24+AL20-변수!AL30,"") | AM24: =IFERROR(AL24+AM20-변수!AM30,"") | AN24: =IFERROR(AM24+AN20-변수!AN30,"") | AO24: =AN24
A25: 지배주주지분 | B25: 재무상태 | C25: 억원 | D25: 지배주주지분 | E25: =IFERROR(VLOOKUP($D25,BS연결,MATCH(E$1,BS연결H,0),0)/100,"") | F25: =IFERROR(VLOOKUP($D25,BS연결,MATCH(F$1,BS연결H,0),0)/100,"") | G25: =IFERROR(VLOOKUP($D25,BS연결,MATCH(G$1,BS연결H,0),0)/100,"") | H25: =IFERROR(VLOOKUP($D25,BS연결,MATCH(H$1,BS연결H,0),0)/100,"") | I25: =IFERROR(VLOOKUP($D25,BS연결,MATCH(I$1,BS연결H,0),0)/100,"") | J25: =IFERROR(VLOOKUP($D25,BS연결,MATCH(J$1,BS연결H,0),0)/100,"") | K25: =IFERROR(VLOOKUP($D25,BS연결,MATCH(K$1,BS연결H,0),0)/100,"") | L25: =IFERROR(VLOOKUP($D25,BS연결,MATCH(L$1,BS연결H,0),0)/100,"") | ... AB25: =IFERROR(VLOOKUP($D25,BS연결,MATCH(AB$1,BS연결H,0),0)/100,"") | AC25: =IFERROR(AB25+AC21-변수!AC31,"") | AD25: =IFERROR(AC25+AD21-변수!AD31,"") | AE25: =AD25 | AF25: =IFERROR(AD25+AF21-변수!AF31,"") | AG25: =IFERROR(AF25+AG21-변수!AG31,"") | AH25: =IFERROR(AG25+AH21-변수!AH31,"") | AI25: =IFERROR(AH25+AI21-변수!AI31,"") | AJ25: =AI25 | AK25: =IFERROR(AI25+AK21-변수!AK31,"") | AL25: =IFERROR(AK25+AL21-변수!AL31,"") | AM25: =IFERROR(AL25+AM21-변수!AM31,"") | AN25: =IFERROR(AM25+AN21-변수!AN31,"") | AO25: =AN25
A26: 총차입금 | B26: 재무상태 | C26: 억원 | D26: 총차입금 | E26: =IFERROR(VLOOKUP($D26,BS연결,MATCH(E$1,BS연결H,0),0)/100,"") | F26: =IFERROR(VLOOKUP($D26,BS연결,MATCH(F$1,BS연결H,0),0)/100,"") | G26: =IFERROR(VLOOKUP($D26,BS연결,MATCH(G$1,BS연결H,0),0)/100,"") | H26: =IFERROR(VLOOKUP($D26,BS연결,MATCH(H$1,BS연결H,0),0)/100,"") | I26: =IFERROR(VLOOKUP($D26,BS연결,MATCH(I$1,BS연결H,0),0)/100,"") | J26: =IFERROR(VLOOKUP($D26,BS연결,MATCH(J$1,BS연결H,0),0)/100,"") | K26: =IFERROR(VLOOKUP($D26,BS연결,MATCH(K$1,BS연결H,0),0)/100,"") | L26: =IFERROR(VLOOKUP($D26,BS연결,MATCH(L$1,BS연결H,0),0)/100,"") | ... AB26: =IFERROR(VLOOKUP($D26,BS연결,MATCH(AB$1,BS연결H,0),0)/100,"") | AC26: =IFERROR(AB26*(1+변수!AC32),"") | AD26: =IFERROR(AC26*(1+변수!AD32),"") | AE26: =AD26 | AF26: =IFERROR(AD26*(1+변수!AF32),"") | AG26: =IFERROR(AF26*(1+변수!AG32),"") | AH26: =IFERROR(AG26*(1+변수!AH32),"") | AI26: =IFERROR(AH26*(1+변수!AI32),"") | AJ26: =AI26 | AK26: =IFERROR(AI26*(1+변수!AK32),"") | AL26: =IFERROR(AK26*(1+변수!AL32),"") | AM26: =IFERROR(AL26*(1+변수!AM32),"") | AN26: =IFERROR(AM26*(1+변수!AN32),"") | AO26: =AN26
A27: 순차입금 | B27: 재무상태 | C27: 억원 | D27: 순차입금 | E27: =IFERROR(VLOOKUP($D27,BS연결,MATCH(E$1,BS연결H,0),0)/100,"") | F27: =IFERROR(VLOOKUP($D27,BS연결,MATCH(F$1,BS연결H,0),0)/100,"") | G27: =IFERROR(VLOOKUP($D27,BS연결,MATCH(G$1,BS연결H,0),0)/100,"") | H27: =IFERROR(VLOOKUP($D27,BS연결,MATCH(H$1,BS연결H,0),0)/100,"") | I27: =IFERROR(VLOOKUP($D27,BS연결,MATCH(I$1,BS연결H,0),0)/100,"") | J27: =IFERROR(VLOOKUP($D27,BS연결,MATCH(J$1,BS연결H,0),0)/100,"") | K27: =IFERROR(VLOOKUP($D27,BS연결,MATCH(K$1,BS연결H,0),0)/100,"") | L27: =IFERROR(VLOOKUP($D27,BS연결,MATCH(L$1,BS연결H,0),0)/100,"") | ... AB27: =IFERROR(VLOOKUP($D27,BS연결,MATCH(AB$1,BS연결H,0),0)/100,"") | AC27: =IFERROR(AB27*(1+변수!AC33),"") | AD27: =IFERROR(AC27*(1+변수!AD33),"") | AE27: =AD27 | AF27: =IFERROR(AD27*(1+변수!AF33),"") | AG27: =IFERROR(AF27*(1+변수!AG33),"") | AH27: =IFERROR(AG27*(1+변수!AH33),"") | AI27: =IFERROR(AH27*(1+변수!AI33),"") | AJ27: =AI27 | AK27: =IFERROR(AI27*(1+변수!AK33),"") | AL27: =IFERROR(AK27*(1+변수!AL33),"") | AM27: =IFERROR(AL27*(1+변수!AM33),"") | AN27: =IFERROR(AM27*(1+변수!AN33),"") | AO27: =AN27
A28: 이자발생자산 | B28: 재무상태 | C28: 억원 | D28: 이자발생자산 | E28: =IFERROR(VLOOKUP($D28,BS연결,MATCH(E$1,BS연결H,0),0)/100,"") | F28: =IFERROR(VLOOKUP($D28,BS연결,MATCH(F$1,BS연결H,0),0)/100,"") | G28: =IFERROR(VLOOKUP($D28,BS연결,MATCH(G$1,BS연결H,0),0)/100,"") | H28: =IFERROR(VLOOKUP($D28,BS연결,MATCH(H$1,BS연결H,0),0)/100,"") | I28: =IFERROR(VLOOKUP($D28,BS연결,MATCH(I$1,BS연결H,0),0)/100,"") | J28: =IFERROR(VLOOKUP($D28,BS연결,MATCH(J$1,BS연결H,0),0)/100,"") | K28: =IFERROR(VLOOKUP($D28,BS연결,MATCH(K$1,BS연결H,0),0)/100,"") | L28: =IFERROR(VLOOKUP($D28,BS연결,MATCH(L$1,BS연결H,0),0)/100,"") | ... AB28: =IFERROR(VLOOKUP($D28,BS연결,MATCH(AB$1,BS연결H,0),0)/100,"") | AC28: =IFERROR(AB28*(1+변수!AC34),"") | AD28: =IFERROR(AC28*(1+변수!AD34),"") | AE28: =AD28 | AF28: =IFERROR(AD28*(1+변수!AF34),"") | AG28: =IFERROR(AF28*(1+변수!AG34),"") | AH28: =IFERROR(AG28*(1+변수!AH34),"") | AI28: =IFERROR(AH28*(1+변수!AI34),"") | AJ28: =AI28 | AK28: =IFERROR(AI28*(1+변수!AK34),"") | AL28: =IFERROR(AK28*(1+변수!AL34),"") | AM28: =IFERROR(AL28*(1+변수!AM34),"") | AN28: =IFERROR(AM28*(1+변수!AN34),"") | AO28: =AN28
A29: 현금및현금성자산 | B29: 재무상태 | C29: 억원 | D29: 현금및현금성자산 | E29: =IFERROR(VLOOKUP($D29,BS연결,MATCH(E$1,BS연결H,0),0)/100,"") | F29: =IFERROR(VLOOKUP($D29,BS연결,MATCH(F$1,BS연결H,0),0)/100,"") | G29: =IFERROR(VLOOKUP($D29,BS연결,MATCH(G$1,BS연결H,0),0)/100,"") | H29: =IFERROR(VLOOKUP($D29,BS연결,MATCH(H$1,BS연결H,0),0)/100,"") | I29: =IFERROR(VLOOKUP($D29,BS연결,MATCH(I$1,BS연결H,0),0)/100,"") | J29: =IFERROR(VLOOKUP($D29,BS연결,MATCH(J$1,BS연결H,0),0)/100,"") | K29: =IFERROR(VLOOKUP($D29,BS연결,MATCH(K$1,BS연결H,0),0)/100,"") | L29: =IFERROR(VLOOKUP($D29,BS연결,MATCH(L$1,BS연결H,0),0)/100,"") | ... AB29: =IFERROR(VLOOKUP($D29,BS연결,MATCH(AB$1,BS연결H,0),0)/100,"") | AE29: =AD29 | AJ29: =AI29 | AO29: =AN29
A30: CAPEX | B30: 현금흐름 | C30: 억원 | D30: CAPEX | K30: =SUM(G30:J30) | P30: =SUM(L30:O30) | Q30: =IFERROR(VLOOKUP($D30,BS연결,MATCH(Q$1,BS연결H,0),0)/100,"") | R30: =IFERROR(VLOOKUP($D30,BS연결,MATCH(R$1,BS연결H,0),0)/100,"") | S30: =IFERROR(VLOOKUP($D30,BS연결,MATCH(S$1,BS연결H,0),0)/100,"") | T30: =IFERROR(VLOOKUP($D30,BS연결,MATCH(T$1,BS연결H,0),0)/100,"") | U30: =IFERROR(VLOOKUP($D30,BS연결,MATCH(U$1,BS연결H,0),0)/100,"") | V30: =IFERROR(VLOOKUP($D30,BS연결,MATCH(V$1,BS연결H,0),0)/100,"") | W30: =IFERROR(VLOOKUP($D30,BS연결,MATCH(W$1,BS연결H,0),0)/100,"") | X30: =IFERROR(VLOOKUP($D30,BS연결,MATCH(X$1,BS연결H,0),0)/100,"") | ... AB30: =IFERROR(VLOOKUP($D30,BS연결,MATCH(AB$1,BS연결H,0),0)/100,"") | AC30: =IFERROR(X30*(1+변수!AC36),"") | AD30: =IFERROR(Y30*(1+변수!AD36),"") | AE30: =SUM(AA30:AD30) | AF30: =IFERROR(AA30*(1+변수!AF36),"") | AG30: =IFERROR(AB30*(1+변수!AG36),"") | AH30: =IFERROR(AC30*(1+변수!AH36),"") | AI30: =IFERROR(AD30*(1+변수!AI36),"") | AJ30: =SUM(AF30:AI30) | AK30: =IFERROR(AF30*(1+변수!AK36),"") | AL30: =IFERROR(AG30*(1+변수!AL36),"") | AM30: =IFERROR(AH30*(1+변수!AM36),"") | AN30: =IFERROR(AI30*(1+변수!AN36),"") | AO30: =SUM(AK30:AN30)
A31: 영업활동현금흐름 | B31: 현금흐름 | C31: 억원 | D31: 영업활동으로인한현금흐름 | E31: =IFERROR(VLOOKUP($D31,BS연결,MATCH(E$1,BS연결H,0),0)/100,"") | G31: =IFERROR(VLOOKUP($D31,BS연결,MATCH(G$1,BS연결H,0),0)/100,"") | H31: =IFERROR(VLOOKUP($D31,BS연결,MATCH(H$1,BS연결H,0),0)/100,"") | I31: =IFERROR(VLOOKUP($D31,BS연결,MATCH(I$1,BS연결H,0),0)/100,"") | J31: =IFERROR(VLOOKUP($D31,BS연결,MATCH(J$1,BS연결H,0),0)/100,"") | K31: =IFERROR(VLOOKUP($D31,BS연결,MATCH(K$1,BS연결H,0),0)/100,"") | L31: =IFERROR(VLOOKUP($D31,BS연결,MATCH(L$1,BS연결H,0),0)/100,"") | M31: =IFERROR(VLOOKUP($D31,BS연결,MATCH(M$1,BS연결H,0),0)/100,"") | N31: =IFERROR(VLOOKUP($D31,BS연결,MATCH(N$1,BS연결H,0),0)/100,"") | ... AB31: =IFERROR(VLOOKUP($D31,BS연결,MATCH(AB$1,BS연결H,0),0)/100,"") | AE31: =SUM(AA31:AD31) | AJ31: =SUM(AF31:AI31) | AO31: =SUM(AK31:AN31)
A32: 주식수 | B32: 주당 | C32: 백만주 | D32: 유통주식수 | E32: 107.274 | F32: =E32 | G32: 107.274 | H32: 107.274 | I32: 107.274 | J32: 107.274 | K32: =J32 | L32: 107.274 | M32: 216.857 | N32: 216.857 | O32: 306.343 | P32: =O32 | Q32: 306.343 | R32: 306.343 | S32: 306.343 | T32: 306.397 | U32: =T32 | V32: 306.397 | W32: 306.397 | X32: 306.397 | Y32: 306.397 | Z32: =Y32 | AA32: 306.397 | AB32: 306.358 | AC32: =IFERROR(AB32*(1+변수!AC38),"") | AD32: =IFERROR(AC32*(1+변수!AD38),"") | AE32: =AD32 | AF32: =IFERROR(AD32*(1+변수!AF38),"") | AG32: =IFERROR(AF32*(1+변수!AG38),"") | AH32: =IFERROR(AG32*(1+변수!AH38),"") | AI32: =IFERROR(AH32*(1+변수!AI38),"") | AJ32: =AI32 | AK32: =IFERROR(AI32*(1+변수!AK38),"") | AL32: =IFERROR(AK32*(1+변수!AL38),"") | AM32: =IFERROR(AL32*(1+변수!AM38),"") | AN32: =IFERROR(AM32*(1+변수!AN38),"") | AO32: =AN32
A33: EPS | B33: 주당 | C33: 원 | D33: EPS | E33: =IFERROR(E21*100/E32,"") | G33: =IFERROR(G21*100/G32,"") | H33: =IFERROR(H21*100/H32,"") | I33: =IFERROR(I21*100/I32,"") | J33: =IFERROR(J21*100/J32,"") | K33: =SUM(G33:J33) | L33: =IFERROR(L21*100/L32,"") | M33: =IFERROR(M21*100/M32,"") | N33: =IFERROR(N21*100/N32,"") | O33: =IFERROR(O21*100/O32,"") | P33: =SUM(L33:O33) | Q33: =IFERROR(Q21*100/Q32,"") | R33: =IFERROR(R21*100/R32,"") | S33: =IFERROR(S21*100/S32,"") | T33: =IFERROR(T21*100/T32,"") | U33: =SUM(Q33:T33) | V33: =IFERROR(V21*100/V32,"") | W33: =IFERROR(W21*100/W32,"") | X33: =IFERROR(X21*100/X32,"") | Y33: =IFERROR(Y21*100/Y32,"") | Z33: =SUM(V33:Y33) | AA33: =IFERROR(AA21*100/AA32,"") | AB33: =IFERROR(AB21*100/AB32,"") | AC33: =IFERROR(AC21*100/AC32,"") | AD33: =IFERROR(AD21*100/AD32,"") | AE33: =SUM(AA33:AD33) | AF33: =IFERROR(AF21*100/AF32,"") | AG33: =IFERROR(AG21*100/AG32,"") | AH33: =IFERROR(AH21*100/AH32,"") | AI33: =IFERROR(AI21*100/AI32,"") | AJ33: =SUM(AF33:AI33) | AK33: =IFERROR(AK21*100/AK32,"") | AL33: =IFERROR(AL21*100/AL32,"") | AM33: =IFERROR(AM21*100/AM32,"") | AN33: =IFERROR(AN21*100/AN32,"") | AO33: =SUM(AK33:AN33)
A34: BPS | B34: 주당 | C34: 원 | D34: BPS | E34: =IFERROR(E25*100/E32,"") | F34: =E34 | G34: =IFERROR(G25*100/G32,"") | H34: =IFERROR(H25*100/H32,"") | I34: =IFERROR(I25*100/I32,"") | J34: =IFERROR(J25*100/J32,"") | K34: =J34 | L34: =IFERROR(L25*100/L32,"") | M34: =IFERROR(M25*100/M32,"") | N34: =IFERROR(N25*100/N32,"") | O34: =IFERROR(O25*100/O32,"") | P34: =O34 | Q34: =IFERROR(Q25*100/Q32,"") | R34: =IFERROR(R25*100/R32,"") | S34: =IFERROR(S25*100/S32,"") | T34: =IFERROR(T25*100/T32,"") | U34: =T34 | V34: =IFERROR(V25*100/V32,"") | W34: =IFERROR(W25*100/W32,"") | X34: =IFERROR(X25*100/X32,"") | Y34: =IFERROR(Y25*100/Y32,"") | Z34: =Y34 | AA34: =IFERROR(AA25*100/AA32,"") | AB34: =IFERROR(AB25*100/AB32,"") | AC34: =IFERROR(AC25*100/AC32,"") | AD34: =IFERROR(AD25*100/AD32,"") | AE34: =AD34 | AF34: =IFERROR(AF25*100/AF32,"") | AG34: =IFERROR(AG25*100/AG32,"") | AH34: =IFERROR(AH25*100/AH32,"") | AI34: =IFERROR(AI25*100/AI32,"") | AJ34: =AI34 | AK34: =IFERROR(AK25*100/AK32,"") | AL34: =IFERROR(AL25*100/AL32,"") | AM34: =IFERROR(AM25*100/AM32,"") | AN34: =IFERROR(AN25*100/AN32,"") | AO34: =AN34
A35: DPS | B35: 주당 | C35: 원 | D35: DPS(보통주) | E35: 0 | F35: 0 | J35: 0 | K35: =SUM(G35:J35) | O35: 0 | P35: =SUM(L35:O35) | T35: 0 | U35: =SUM(Q35:T35) | Y35: 0 | Z35: =SUM(V35:Y35) | AD35: =변수!AD39 | AE35: =SUM(AA35:AD35) | AI35: =변수!AI39 | AJ35: =SUM(AF35:AI35) | AN35: =변수!AN39 | AO35: =SUM(AK35:AN35)
A36: PER | B36: 주당 | C36: 배 | D36: PER | F36: =E36 | K36: =J36 | P36: =O36 | Q36: =IFERROR(변수!Q18/(M33+N33+O33+Q33),"") | R36: =IFERROR(변수!R18/(N33+O33+Q33+R33),"") | S36: =IFERROR(변수!S18/(O33+Q33+R33+S33),"") | T36: =IFERROR(변수!T18/(Q33+R33+S33+T33),"") | U36: =T36 | V36: =IFERROR(변수!V18/(R33+S33+T33+V33),"") | W36: =IFERROR(변수!W18/(S33+T33+V33+W33),"") | X36: =IFERROR(변수!X18/(T33+V33+W33+X33),"") | Y36: =IFERROR(변수!Y18/(V33+W33+X33+Y33),"") | Z36: =Y36 | AA36: =IFERROR(변수!AA18/(W33+X33+Y33+AA33),"") | AB36: =IFERROR(변수!AB18/(X33+Y33+AA33+AB33),"") | AC36: =IFERROR(변수!$D$47/(Y33+AA33+AB33+AC33),"") | AD36: =IFERROR(변수!$D$47/(AA33+AB33+AC33+AD33),"") | AE36: =AD36 | AF36: =IFERROR(변수!$D$47/(AB33+AC33+AD33+AF33),"") | AG36: =IFERROR(변수!$D$47/(AC33+AD33+AF33+AG33),"") | AH36: =IFERROR(변수!$D$47/(AD33+AF33+AG33+AH33),"") | AI36: =IFERROR(변수!$D$47/(AF33+AG33+AH33+AI33),"") | AJ36: =AI36 | AK36: =IFERROR(변수!$D$47/(AG33+AH33+AI33+AK33),"") | AL36: =IFERROR(변수!$D$47/(AH33+AI33+AK33+AL33),"") | AM36: =IFERROR(변수!$D$47/(AI33+AK33+AL33+AM33),"") | AN36: =IFERROR(변수!$D$47/(AK33+AL33+AM33+AN33),"") | AO36: =AN36
A37: PBR | B37: 주당 | C37: 배 | D37: PBR | E37: =IFERROR(변수!E18/E34,"") | F37: =E37 | G37: =IFERROR(변수!G18/G34,"") | H37: =IFERROR(변수!H18/H34,"") | I37: =IFERROR(변수!I18/I34,"") | J37: =IFERROR(변수!J18/J34,"") | K37: =J37 | L37: =IFERROR(변수!L18/L34,"") | M37: =IFERROR(변수!M18/M34,"") | N37: =IFERROR(변수!N18/N34,"") | O37: =IFERROR(변수!O18/O34,"") | P37: =O37 | Q37: =IFERROR(변수!Q18/Q34,"") | R37: =IFERROR(변수!R18/R34,"") | S37: =IFERROR(변수!S18/S34,"") | T37: =IFERROR(변수!T18/T34,"") | U37: =T37 | V37: =IFERROR(변수!V18/V34,"") | W37: =IFERROR(변수!W18/W34,"") | X37: =IFERROR(변수!X18/X34,"") | Y37: =IFERROR(변수!Y18/Y34,"") | Z37: =Y37 | AA37: =IFERROR(변수!AA18/AA34,"") | AB37: =IFERROR(변수!AB18/AB34,"") | AC37: =IFERROR(변수!$D$47/AC34,"") | AD37: =IFERROR(변수!$D$47/AD34,"") | AE37: =AD37 | AF37: =IFERROR(변수!$D$47/AF34,"") | AG37: =IFERROR(변수!$D$47/AG34,"") | AH37: =IFERROR(변수!$D$47/AH34,"") | AI37: =IFERROR(변수!$D$47/AI34,"") | AJ37: =AI37 | AK37: =IFERROR(변수!$D$47/AK34,"") | AL37: =IFERROR(변수!$D$47/AL34,"") | AM37: =IFERROR(변수!$D$47/AM34,"") | AN37: =IFERROR(변수!$D$47/AN34,"") | AO37: =AN37
A38: 매출조선 | B38: 사업부 | C38: 억원 | D38: 매출 조선·해양(상선·해양및특수선·EP및특수선) | G38: 12481.38 | H38: 11968.94 | I38: 10004.17 | J38: 14764.33 | K38: =SUM(G38:J38) | L38: 14705.8 | M38: 18569.45 | N38: 20122.5 | O38: 23387.72 | P38: =SUM(L38:O38) | Q38: 23615.5 | R38: 26384.44 | S38: 26576.3 | T38: 31615.57 | U38: =SUM(Q38:T38) | V38: 31027.59 | W38: 33310.22 | X38: 29385.93 | Y38: 31818.98 | Z38: =SUM(V38:Y38) | AA38: 33219.6 | AB38: 56347.33 | AC38: =IFERROR(SLS!AH107/100+변수!AC40+AC39,"") | AD38: =IFERROR(SLS!AI107/100+변수!AD40+AD39,"") | AE38: =SUM(AA38:AD38) | AF38: =IFERROR(SLS!AJ107/100+변수!AF40+AF39,"") | AG38: =IFERROR(SLS!AK107/100+변수!AG40+AG39,"") | AH38: =IFERROR(SLS!AL107/100+변수!AH40+AH39,"") | AI38: =IFERROR(SLS!AM107/100+변수!AI40+AI39,"") | AJ38: =SUM(AF38:AI38) | AK38: =IFERROR(SLS!AN107/100+변수!AK40+AK39,"") | AL38: =IFERROR(SLS!AO107/100+변수!AL40+AL39,"") | AM38: =IFERROR(SLS!AP107/100+변수!AM40+AM39,"") | AN38: =IFERROR(SLS!AQ107/100+변수!AN40+AN39,"") | AO38: =SUM(AK38:AN38)
A39: 매출조선신규 | B39: 사업부 | C39: 억원 | D39: 매출 조선·해양(상선·해양및특수선·EP및특수선) 신규수주(forecast_panel base(공시 상계) — 매출조선에 포함) | K39: =SUM(G39:J39) | P39: =SUM(L39:O39) | U39: =SUM(Q39:T39) | Z39: =SUM(V39:Y39) | AA39: 0 | AB39: 0 | AC39: =변수!AC41 | AD39: =변수!AD41 | AE39: =SUM(AA39:AD39) | AF39: =변수!AF41 | AG39: =변수!AG41 | AH39: =변수!AH41 | AI39: =변수!AI41 | AJ39: =SUM(AF39:AI39) | AK39: =변수!AK41 | AL39: =변수!AL41 | AM39: =변수!AM41 | AN39: =변수!AN41 | AO39: =SUM(AK39:AN39)
A40: OP조선 | B40: 사업부 | C40: 억원 | D40: OP 조선·해양(상선·해양및특수선·EP및특수선) | K40: =SUM(G40:J40) | P40: =SUM(L40:O40) | U40: =SUM(Q40:T40) | Z40: =SUM(V40:Y40) | AC40: =IFERROR(AC38*변수!AC42,"") | AD40: =IFERROR(AD38*변수!AD42,"") | AE40: =SUM(AA40:AD40) | AF40: =IFERROR(AF38*변수!AF42,"") | AG40: =IFERROR(AG38*변수!AG42,"") | AH40: =IFERROR(AH38*변수!AH42,"") | AI40: =IFERROR(AI38*변수!AI42,"") | AJ40: =SUM(AF40:AI40) | AK40: =IFERROR(AK38*변수!AK42,"") | AL40: =IFERROR(AL38*변수!AL42,"") | AM40: =IFERROR(AM38*변수!AM42,"") | AN40: =IFERROR(AN38*변수!AN42,"") | AO40: =SUM(AK40:AN40)
A41: OP조선신규 | B41: 사업부 | C41: 억원 | D41: OP 조선·해양(상선·해양및특수선·EP및특수선) 신규수주(매출조선신규 × OPM — OP조선에 포함) | K41: =SUM(G41:J41) | P41: =SUM(L41:O41) | U41: =SUM(Q41:T41) | Z41: =SUM(V41:Y41) | AA41: 0 | AB41: 0 | AC41: =IFERROR(AC39*변수!AC42,"") | AD41: =IFERROR(AD39*변수!AD42,"") | AE41: =SUM(AA41:AD41) | AF41: =IFERROR(AF39*변수!AF42,"") | AG41: =IFERROR(AG39*변수!AG42,"") | AH41: =IFERROR(AH39*변수!AH42,"") | AI41: =IFERROR(AI39*변수!AI42,"") | AJ41: =SUM(AF41:AI41) | AK41: =IFERROR(AK39*변수!AK42,"") | AL41: =IFERROR(AL39*변수!AL42,"") | AM41: =IFERROR(AM39*변수!AM42,"") | AN41: =IFERROR(AN39*변수!AN42,"") | AO41: =SUM(AK41:AN41)
A42: 매출기타 | B42: 사업부 | C42: 억원 | D42: 매출 기타 부문(총매출 − 조선) | G42: 0 | H42: 0 | I42: 0 | J42: 0 | K42: =SUM(G42:J42) | L42: 0 | M42: 0 | N42: 0 | O42: 0 | P42: =SUM(L42:O42) | Q42: 0 | R42: 0 | S42: 454.79 | T42: 916.21 | U42: =SUM(Q42:T42) | V42: 403.31 | W42: 0 | X42: 847.65 | Y42: 1410.53 | Z42: =SUM(V42:Y42) | AA42: 0 | AB42: 0 | AC42: =IFERROR(X42*(1+변수!AC43),"") | AD42: =IFERROR(Y42*(1+변수!AD43),"") | AE42: =SUM(AA42:AD42) | AF42: =IFERROR(AD42*(1+변수!AF43),"") | AG42: =IFERROR(AF42*(1+변수!AG43),"") | AH42: =IFERROR(AC42*(1+변수!AH43),"") | AI42: =IFERROR(AD42*(1+변수!AI43),"") | AJ42: =SUM(AF42:AI42) | AK42: =IFERROR(AF42*(1+변수!AK43),"") | AL42: =IFERROR(AG42*(1+변수!AL43),"") | AM42: =IFERROR(AH42*(1+변수!AM43),"") | AN42: =IFERROR(AI42*(1+변수!AN43),"") | AO42: =SUM(AK42:AN42)
A43: OP기타 | B43: 사업부 | C43: 억원 | D43: OP 기타 부문(총매출 − 조선) | K43: =SUM(G43:J43) | P43: =SUM(L43:O43) | U43: =SUM(Q43:T43) | Z43: =SUM(V43:Y43) | AC43: =IFERROR(AC42*변수!AC44,"") | AD43: =IFERROR(AD42*변수!AD44,"") | AE43: =SUM(AA43:AD43) | AF43: =IFERROR(AF42*변수!AF44,"") | AG43: =IFERROR(AG42*변수!AG44,"") | AH43: =IFERROR(AH42*변수!AH44,"") | AI43: =IFERROR(AI42*변수!AI44,"") | AJ43: =SUM(AF43:AI43) | AK43: =IFERROR(AK42*변수!AK44,"") | AL43: =IFERROR(AL42*변수!AL44,"") | AM43: =IFERROR(AM42*변수!AM44,"") | AN43: =IFERROR(AN42*변수!AN44,"") | AO43: =SUM(AK43:AN43)
B44: 비율(참고)
A45: NPM | C45: % | D45: 지배주주순이익 / 매출액 | E45: =IFERROR(E21/E5,"") | F45: =IFERROR(F21/F5,"") | G45: =IFERROR(G21/G5,"") | H45: =IFERROR(H21/H5,"") | I45: =IFERROR(I21/I5,"") | J45: =IFERROR(J21/J5,"") | K45: =IFERROR(K21/K5,"") | L45: =IFERROR(L21/L5,"") | ... AO45: =IFERROR(AO21/AO5,"")
A46: 매출원가율 | C46: % | D46: 매출원가 / 매출액 | E46: =IFERROR(E6/E5,"") | F46: =IFERROR(F6/F5,"") | G46: =IFERROR(G6/G5,"") | H46: =IFERROR(H6/H5,"") | I46: =IFERROR(I6/I5,"") | J46: =IFERROR(J6/J5,"") | K46: =IFERROR(K6/K5,"") | L46: =IFERROR(L6/L5,"") | ... AO46: =IFERROR(AO6/AO5,"")
A47: 판관비율 | C47: % | D47: 판관비 / 매출액 | E47: =IFERROR(E8/E5,"") | F47: =IFERROR(F8/F5,"") | G47: =IFERROR(G8/G5,"") | H47: =IFERROR(H8/H5,"") | I47: =IFERROR(I8/I5,"") | J47: =IFERROR(J8/J5,"") | K47: =IFERROR(K8/K5,"") | L47: =IFERROR(L8/L5,"") | ... AO47: =IFERROR(AO8/AO5,"")

Sheet SLS
C1: 이름: SLS_H · 선표 매출인식(백만$) — sls json origin 2026Q2 | E1: 2Q19 | F1: 3Q19 | G1: 4Q19 | H1: 1Q20 | I1: 2Q20 | J1: 3Q20 | K1: 4Q20 | L1: 1Q21 | M1: 2Q21 | N1: 3Q21 | O1: 4Q21 | P1: 1Q22 | Q1: 2Q22 | R1: 3Q22 | S1: 4Q22 | T1: 1Q23 | U1: 2Q23 | V1: 3Q23 | W1: 4Q23 | X1: 1Q24 | Y1: 2Q24 | Z1: 3Q24 | AA1: 4Q24 | AB1: 1Q25 | AC1: 2Q25 | AD1: 3Q25 | AE1: 4Q25 | AF1: 1Q26 | AG1: 2Q26 | AH1: 3Q26 | AI1: 4Q26 | AJ1: 1Q27 | AK1: 2Q27 | AL1: 3Q27 | AM1: 4Q27 | AN1: 1Q28 | AO1: 2Q28 | AP1: 3Q28 | AQ1: 4Q28 | AR1: 1Q29 | AS1: 2Q29 | AT1: 3Q29 | AU1: 4Q29 | AV1: 1Q30 | AW1: 2Q30 | AX1: 3Q30 | AY1: 4Q30 | AZ1: 1Q31 | BA1: 2Q31 | BB1: 3Q31 | BC1: 4Q31 | BD1: 1Q32 | BE1: 2Q32 | BF1: 2019 | BG1: 2020 | BH1: 2021 | BI1: 2022 | BJ1: 2023 | BK1: 2024 | BL1: 2025 | BM1: 2026 | BN1: 2027 | BO1: 2028 | BP1: 2029 | BQ1: 2030 | BR1: 2031 | BS1: 2032
A2: 코호트 표(레퍼런스 실측 캘리브레이션): ①적자 −1.1% ②BEP 1% ③중마진 4.3% ④호황 5.4% ⑤초호황 10.8% — 회사별 캘리브레이션은 target_opm.basis 참조 · 코호트 모드 reference_anchor(대안 ledger_relative) · 잔고 캡 미적용
E3: 1 | F3: 2 | G3: 3 | H3: 4 | I3: 5 | J3: 6 | K3: 7 | L3: 8 | M3: 9 | N3: 10 | O3: 11 | P3: 12 | Q3: 13 | R3: 14 | S3: 15 | T3: 16 | U3: 17 | V3: 18 | W3: 19 | X3: 20 | Y3: 21 | Z3: 22 | AA3: 23 | AB3: 24 | AC3: 25 | AD3: 26 | AE3: 27 | AF3: 28 | AG3: 29 | AH3: 30 | AI3: 31 | AJ3: 32 | AK3: 33 | AL3: 34 | AM3: 35 | AN3: 36 | AO3: 37 | AP3: 38 | AQ3: 39 | AR3: 40 | AS3: 41 | AT3: 42 | AU3: 43 | AV3: 44 | AW3: 45 | AX3: 46 | AY3: 47 | AZ3: 48 | BA3: 49 | BB3: 50 | BC3: 51 | BD3: 52 | BE3: 53 | BF3: 54 | BG3: 55 | BH3: 56 | BI3: 57 | BJ3: 58 | BK3: 59 | BL3: 60 | BM3: 61 | BN3: 62 | BO3: 63 | BP3: 64 | BQ3: 65 | BR3: 66 | BS3: 67
E4: 2019.06 | F4: 2019.09 | G4: 2019.12 | H4: 2020.03 | I4: 2020.06 | J4: 2020.09 | K4: 2020.12 | L4: 2021.03 | M4: 2021.06 | N4: 2021.09 | O4: 2021.12 | P4: 2022.03 | Q4: 2022.06 | R4: 2022.09 | S4: 2022.12 | T4: 2023.03 | U4: 2023.06 | V4: 2023.09 | W4: 2023.12 | X4: 2024.03 | Y4: 2024.06 | Z4: 2024.09 | AA4: 2024.12 | AB4: 2025.03 | AC4: 2025.06 | AD4: 2025.09 | AE4: 2025.12 | AF4: 2026.03 | AG4: 2026.06 | AH4: 2026.09 | AI4: 2026.12 | AJ4: 2027.03 | AK4: 2027.06 | AL4: 2027.09 | AM4: 2027.12 | AN4: 2028.03 | AO4: 2028.06 | AP4: 2028.09 | AQ4: 2028.12 | AR4: 2029.03 | AS4: 2029.06 | AT4: 2029.09 | AU4: 2029.12 | AV4: 2030.03 | AW4: 2030.06 | AX4: 2030.09 | AY4: 2030.12 | AZ4: 2031.03 | BA4: 2031.06 | BB4: 2031.09 | BC4: 2031.12 | BD4: 2032.03 | BE4: 2032.06 | BF4: 2019.12A | BG4: 2020.12A | BH4: 2021.12A | BI4: 2022.12A | BJ4: 2023.12A | BK4: 2024.12A | BL4: 2025.12A | BM4: 2026.12A | BN4: 2027.12A | BO4: 2028.12A | BP4: 2029.12A | BQ4: 2030.12A | BR4: 2031.12A | BS4: 2032.12A
A5: usd_m | D5: 매출인식 합계(백만$) | E5: 54.677 | F5: 62.879 | G5: 62.879 | H5: 62.195 | I5: 62.195 | J5: 62.879 | K5: 62.879 | L5: 61.512 | M5: 71.649 | N5: 106.364 | O5: 106.364 | P5: 127.452 | Q5: 141.299 | R5: 142.852 | S5: 142.852 | T5: 147.897 | U5: 111.682 | V5: 109.737 | W5: 114.931 | X5: 134.461 | Y5: 162.704 | Z5: 223.455 | AA5: 223.455 | AB5: 228.15 | AC5: 245.862 | AD5: 271.543 | AE5: 470.389 | AF5: 804.147 | AG5: 923.066 | AH5: 1092.713 | AI5: 1191.468 | AJ5: 1110.708 | AK5: 1056.11 | AL5: 1061.697 | AM5: 1051.744 | AN5: 1023.937 | AO5: 964.53 | AP5: 920.793 | AQ5: 906.138 | AR5: 818.302 | AS5: 702.384 | AT5: 308.065 | AU5: 154.724 | AV5: 87.957 | AW5: 44.519 | AX5: 45.008 | AY5: 39.608 | AZ5: 24.588 | BA5: 24.861 | BB5: 25.135 | BC5: 25.135 | BD5: 24.861 | BE5: 24.861 | BF5: 180.435 | BG5: 250.148 | BH5: 345.889 | BI5: 554.455 | BJ5: 484.247 | BK5: 744.075 | BL5: 1215.944 | BM5: 4011.394 | BN5: 4280.259 | BO5: 3815.398 | BP5: 1983.475 | BQ5: 217.092 | BR5: 99.719 | BS5: 49.722
A6: marine_usd_m | D6: 해양(type≠OTHER) 합계(백만$) | E6: 54.677 | F6: 62.879 | G6: 62.879 | H6: 62.195 | I6: 62.195 | J6: 62.879 | K6: 62.879 | L6: 61.512 | M6: 71.649 | N6: 106.364 | O6: 106.364 | P6: 104.051 | Q6: 105.207 | R6: 106.364 | S6: 106.364 | T6: 112.201 | U6: 75.59 | V6: 73.248 | W6: 78.443 | X6: 98.369 | Y6: 126.612 | Z6: 186.967 | AA6: 186.967 | AB6: 182.902 | AC6: 184.934 | AD6: 209.946 | AE6: 408.792 | AF6: 743.889 | AG6: 862.138 | AH6: 1031.115 | AI6: 1129.871 | AJ6: 1050.45 | AK6: 1030.084 | AL6: 1036.588 | AM6: 1026.636 | AN6: 1015.477 | AO6: 964.53 | AP6: 920.793 | AQ6: 906.138 | AR6: 818.302 | AS6: 702.384 | AT6: 308.065 | AU6: 154.724 | AV6: 87.957 | AW6: 44.519 | AX6: 45.008 | AY6: 39.608 | AZ6: 24.588 | BA6: 24.861 | BB6: 25.135 | BC6: 25.135 | BD6: 24.861 | BE6: 24.861 | BF6: 180.435 | BG6: 250.148 | BH6: 345.889 | BI6: 421.986 | BJ6: 339.482 | BK6: 598.915 | BL6: 986.574 | BM6: 3767.013 | BN6: 4143.758 | BO6: 3806.938 | BP6: 1983.475 | BQ6: 217.092 | BR6: 99.719 | BS6: 49.722
A7: type:NAVAL | D7: 선종 NAVAL | E7: 54.677 | F7: 62.879 | G7: 62.879 | H7: 62.195 | I7: 62.195 | J7: 62.879 | K7: 62.879 | L7: 61.512 | M7: 62.195 | N7: 62.879 | O7: 62.879 | P7: 61.512 | Q7: 62.195 | R7: 62.879 | S7: 62.879 | T7: 61.512 | U7: 4.101 | AH7: 16.938 | AI7: 25.135 | AJ7: 24.588 | AK7: 24.861 | AL7: 25.135 | AM7: 25.135 | AN7: 24.861 | AO7: 24.861 | AP7: 25.135 | AQ7: 25.135 | AR7: 24.588 | AS7: 24.861 | AT7: 25.135 | AU7: 25.135 | AV7: 24.588 | AW7: 24.861 | AX7: 25.135 | AY7: 25.135 | AZ7: 24.588 | BA7: 24.861 | BB7: 25.135 | BC7: 25.135 | BD7: 24.861 | BE7: 24.861 | BF7: 180.435 | BG7: 250.148 | BH7: 249.465 | BI7: 249.465 | BJ7: 65.613 | BM7: 42.073 | BN7: 99.719 | BO7: 99.992 | BP7: 99.719 | BQ7: 99.719 | BR7: 99.719 | BS7: 49.722
A8: type:OFFSH | D8: 선종 OFFSH | M8: 9.453 | N8: 43.485 | O8: 43.485 | P8: 42.539 | Q8: 43.012 | R8: 43.485 | S8: 43.485 | T8: 42.539 | U8: 43.012 | V8: 43.485 | W8: 43.485 | X8: 43.012 | Y8: 43.012 | Z8: 43.485 | AA8: 43.485 | AB8: 42.539 | AC8: 43.012 | AD8: 43.485 | AE8: 54.147 | AF8: 171.965 | AG8: 196.434 | AH8: 198.593 | AI8: 198.593 | AJ8: 168.752 | AK8: 153.422 | AL8: 155.108 | AM8: 155.108 | AN8: 153.422 | AO8: 134.83 | AP8: 98.091 | AQ8: 98.091 | AR8: 95.959 | AS8: 85.297 | BH8: 96.423 | BI8: 172.521 | BJ8: 172.521 | BK8: 172.994 | BL8: 183.183 | BM8: 765.585 | BN8: 632.39 | BO8: 484.434 | BP8: 181.256
A9: type:OTHER | D9: 선종 OTHER | P9: 23.4 | Q9: 36.092 | R9: 36.489 | S9: 36.489 | T9: 35.695 | U9: 36.092 | V9: 36.489 | W9: 36.489 | X9: 36.092 | Y9: 36.092 | Z9: 36.489 | AA9: 36.489 | AB9: 45.248 | AC9: 60.928 | AD9: 61.597 | AE9: 61.597 | AF9: 60.258 | AG9: 60.928 | AH9: 61.597 | AI9: 61.597 | AJ9: 60.258 | AK9: 26.026 | AL9: 25.109 | AM9: 25.109 | AN9: 8.461 | BI9: 132.47 | BJ9: 144.765 | BK9: 145.162 | BL9: 229.37 | BM9: 244.38 | BN9: 136.502 | BO9: 8.461
A10: type:LNGC | D10: 선종 LNGC | T10: 8.15 | U10: 28.477 | V10: 29.764 | W10: 29.764 | X10: 29.44 | Y10: 29.44 | Z10: 29.764 | AA10: 29.764 | AB10: 29.117 | AC10: 29.44 | AD10: 37.298 | AE10: 97.964 | AF10: 229.874 | AG10: 280.708 | AH10: 327.877 | AI10: 363.286 | AJ10: 355.389 | AK10: 344.505 | AL10: 343.475 | AM10: 333.523 | AN10: 329.897 | AO10: 297.544 | AP10: 284.697 | AQ10: 284.697 | AR10: 278.508 | AS10: 256.374 | AT10: 57.247 | AU10: 13.911 | BJ10: 96.155 | BK10: 118.408 | BL10: 193.819 | BM10: 1201.745 | BN10: 1376.892 | BO10: 1196.835 | BP10: 606.04
A11: type:VLGC | D11: 선종 VLGC | W11: 5.194 | X11: 12.439 | Y11: 20.912 | Z11: 26.749 | AA11: 26.749 | AB11: 26.168 | AC11: 26.458 | AD11: 26.749 | AE11: 26.749 | AF11: 26.168 | AG11: 35.334 | AH11: 37.306 | AI11: 42.78 | AJ11: 41.85 | AK11: 42.315 | AL11: 42.78 | AM11: 42.78 | AN11: 42.315 | AO11: 42.315 | AP11: 42.78 | AQ11: 42.78 | AR11: 41.85 | AS11: 42.315 | AT11: 42.78 | AU11: 42.78 | AV11: 23.177 | AW11: 19.658 | AX11: 19.874 | AY11: 14.473 | BJ11: 5.194 | BK11: 86.849 | BL11: 106.124 | BM11: 141.588 | BN11: 169.725 | BO11: 170.19 | BP11: 169.725 | BQ11: 77.182
A12: type:VLCC | D12: 선종 VLCC | X12: 13.478 | Y12: 33.248 | Z12: 86.969 | AA12: 86.969 | AB12: 85.079 | AC12: 86.024 | AD12: 86.969 | AE12: 113.475 | AF12: 167.337 | AG12: 199.465 | AH12: 250.829 | AI12: 228.302 | AJ12: 194.005 | AK12: 196.16 | AL12: 198.316 | AM12: 198.316 | AN12: 196.16 | AO12: 196.16 | AP12: 198.316 | AQ12: 183.661 | AR12: 130.778 | AS12: 112.105 | AT12: 72.898 | AU12: 72.898 | AV12: 40.192 | BK12: 220.664 | BL12: 371.547 | BM12: 845.933 | BN12: 786.797 | BO12: 774.297 | BP12: 388.679 | BQ12: 40.192
A13: type:CONT | D13: 선종 CONT | AD13: 15.445 | AE13: 116.457 | AF13: 148.546 | AG13: 150.196 | AH13: 180.058 | AI13: 241.345 | AJ13: 236.099 | AK13: 238.722 | AL13: 241.345 | AM13: 241.345 | AN13: 238.722 | AO13: 238.722 | AP13: 241.345 | AQ13: 241.345 | AR13: 216.852 | AS13: 151.334 | AT13: 89.499 | BL13: 131.902 | BM13: 720.145 | BN13: 957.511 | BO13: 960.134 | BP13: 457.685
A14: type:PC | D14: 선종 PC | AH14: 19.514 | AI14: 30.429 | AJ14: 29.767 | AK14: 30.098 | AL14: 30.429 | AM14: 30.429 | AN14: 30.098 | AO14: 30.098 | AP14: 30.429 | AQ14: 30.429 | AR14: 29.767 | AS14: 30.098 | AT14: 20.506 | BM14: 49.943 | BN14: 120.723 | BO14: 121.054 | BP14: 80.371
A15: cohort:③중마진 | D15: 코호트 ③중마진 | E15: 54.677 | F15: 62.879 | G15: 62.879 | H15: 62.195 | I15: 62.195 | J15: 62.879 | K15: 62.879 | L15: 61.512 | M15: 62.195 | N15: 62.879 | O15: 62.879 | P15: 61.512 | Q15: 62.195 | R15: 62.879 | S15: 62.879 | T15: 61.512 | U15: 4.101 | BF15: 180.435 | BG15: 250.148 | BH15: 249.465 | BI15: 249.465 | BJ15: 65.613
A16: cohort:④호황 | D16: 코호트 ④호황 | M16: 9.453 | N16: 43.485 | O16: 43.485 | P16: 42.539 | Q16: 43.012 | R16: 43.485 | S16: 43.485 | T16: 42.539 | U16: 43.012 | V16: 43.485 | W16: 43.485 | X16: 43.012 | Y16: 43.012 | Z16: 43.485 | AA16: 43.485 | AB16: 42.539 | AC16: 43.012 | AD16: 43.485 | AE16: 43.485 | AF16: 42.539 | AG16: 43.012 | AH16: 43.485 | AI16: 43.485 | AJ16: 17.016 | BH16: 96.423 | BI16: 172.521 | BJ16: 172.521 | BK16: 172.994 | BL16: 172.521 | BM16: 172.521 | BN16: 17.016
A17: cohort:등급없음 | D17: 코호트 등급없음 | P17: 23.4 | Q17: 36.092 | R17: 36.489 | S17: 36.489 | T17: 35.695 | U17: 36.092 | V17: 36.489 | W17: 36.489 | X17: 36.092 | Y17: 36.092 | Z17: 36.489 | AA17: 36.489 | AB17: 45.248 | AC17: 60.928 | AD17: 61.597 | AE17: 72.26 | AF17: 156.217 | AG17: 157.953 | AH17: 196.141 | AI17: 215.252 | AJ17: 210.572 | AK17: 178.01 | AL17: 178.763 | AM17: 178.763 | AN17: 160.445 | AO17: 151.984 | AP17: 153.654 | AQ17: 153.654 | AR17: 150.314 | AS17: 140.256 | AT17: 45.641 | AU17: 25.135 | AV17: 24.588 | AW17: 24.861 | AX17: 25.135 | AY17: 25.135 | AZ17: 24.588 | BA17: 24.861 | BB17: 25.135 | BC17: 25.135 | BD17: 24.861 | BE17: 24.861 | BI17: 132.47 | BJ17: 144.765 | BK17: 145.162 | BL17: 240.033 | BM17: 725.563 | BN17: 746.108 | BO17: 619.737 | BP17: 361.346 | BQ17: 99.719 | BR17: 99.719 | BS17: 49.722
A18: cohort:⑤초호황 | D18: 코호트 ⑤초호황 | T18: 8.15 | U18: 28.477 | V18: 29.764 | W18: 34.958 | X18: 55.357 | Y18: 83.6 | Z18: 143.482 | AA18: 143.482 | AB18: 140.363 | AC18: 141.922 | AD18: 166.461 | AE18: 354.645 | AF18: 605.391 | AG18: 722.1 | AH18: 853.087 | AI18: 932.732 | AJ18: 883.12 | AK18: 878.1 | AL18: 882.934 | AM18: 872.981 | AN18: 863.492 | AO18: 812.546 | AP18: 767.138 | AQ18: 752.484 | AR18: 667.988 | AS18: 562.128 | AT18: 262.424 | AU18: 129.589 | AV18: 63.369 | AW18: 19.658 | AX18: 19.874 | AY18: 14.473 | BJ18: 101.349 | BK18: 425.921 | BL18: 803.391 | BM18: 3113.31 | BN18: 3517.135 | BO18: 3195.66 | BP18: 1622.129 | BQ18: 117.374
A19: hedge_ratio | D19: 헤지비율 | E19: 0.1717 | F19: 0.1717 | G19: 0.1717 | H19: 0.1717 | I19: 0.1717 | J19: 0.1717 | K19: 0.1717 | L19: 0.1717 | M19: 0.1717 | N19: 0.1717 | O19: 0.1717 | P19: 0.1717 | Q19: 0.1717 | R19: 0.1717 | S19: 0.1717 | T19: 0.1717 | U19: 0.1717 | V19: 0.1717 | W19: 0.1717 | X19: 0.1717 | Y19: 0.1717 | Z19: 0.1717 | AA19: 0.1717 | AB19: 0.1717 | AC19: 0.1717 | AD19: 0.1717 | AE19: 0.1717 | AF19: 0.1717 | AG19: 0.1717 | AH19: 0.1717 | AI19: 0.1717 | AJ19: 0.1717 | AK19: 0.1717 | AL19: 0.1717 | AM19: 0.1717 | AN19: 0.1717 | AO19: 0.1717 | AP19: 0.1717 | AQ19: 0.1717 | AR19: 0.1717 | AS19: 0.1717 | AT19: 0.1717 | AU19: 0.1717 | AV19: 0.1717 | AW19: 0.1717 | AX19: 0.1717 | AY19: 0.1717 | AZ19: 0.1717 | BA19: 0.1717 | BB19: 0.1717 | BC19: 0.1717 | BD19: 0.1717 | BE19: 0.1717
A20: hedge_rate | D20: 헤지환율(가중) | E20: 1472.04 | F20: 1472.04 | G20: 1472.04 | H20: 1472.04 | I20: 1472.04 | J20: 1472.04 | K20: 1472.04 | L20: 1472.04 | M20: 1472.04 | N20: 1472.04 | O20: 1472.04 | P20: 1472.04 | Q20: 1472.04 | R20: 1472.04 | S20: 1472.04 | T20: 1472.04 | U20: 1472.04 | V20: 1472.04 | W20: 1472.04 | X20: 1472.04 | Y20: 1472.04 | Z20: 1472.04 | AA20: 1472.04 | AB20: 1472.04 | AC20: 1472.04 | AD20: 1472.04 | AE20: 1472.04 | AF20: 1472.04 | AG20: 1472.04 | AH20: 1472.04 | AI20: 1472.04 | AJ20: 1472.04 | AK20: 1472.04 | AL20: 1472.04 | AM20: 1472.04 | AN20: 1472.04 | AO20: 1472.04 | AP20: 1472.04 | AQ20: 1472.04 | AR20: 1472.04 | AS20: 1472.04 | AT20: 1472.04 | AU20: 1472.04 | AV20: 1472.04 | AW20: 1472.04 | AX20: 1472.04 | AY20: 1472.04 | AZ20: 1472.04 | BA20: 1472.04 | BB20: 1472.04 | BC20: 1472.04 | BD20: 1472.04 | BE20: 1472.04
A21: spot_assumed | D21: 건조시점 환율(sls 가정) | E21: 1167.69 | F21: 1193.96 | G21: 1176.23 | H21: 1193.92 | I21: 1219.69 | J21: 1187.81 | K21: 1117.97 | L21: 1114.99 | M21: 1121.13 | N21: 1159.91 | O21: 1183.5 | P21: 1205.78 | Q21: 1262.09 | R21: 1341.93 | S21: 1360.12 | T21: 1276.95 | U21: 1315.69 | V21: 1313.62 | W21: 1322.01 | X21: 1330.14 | Y21: 1371.28 | Z21: 1356.22 | AA21: 1396.3 | AB21: 1452.28 | AC21: 1398.52 | AD21: 1386.95 | AE21: 1449.19 | AF21: 1466.12 | AG21: 1501.75 | AH21: 1418.75 | AI21: 1345.14 | AJ21: 1341.49 | AK21: 1341.49 | AL21: 1341.49 | AM21: 1341.49 | AN21: 1341.49 | AO21: 1341.49 | AP21: 1341.49 | AQ21: 1341.49 | AR21: 1341.49 | AS21: 1341.49 | AT21: 1341.49 | AU21: 1341.49 | AV21: 1341.49 | AW21: 1341.49 | AX21: 1341.49 | AY21: 1341.49 | AZ21: 1341.49 | BA21: 1341.49 | BB21: 1341.49 | BC21: 1341.49 | BD21: 1341.49 | BE21: 1341.49
A22: applied_rate | D22: 적용환율 | E22: 1219.95 | F22: 1241.71 | G22: 1227.02 | H22: 1241.67 | I22: 1263.02 | J22: 1236.61 | K22: 1178.76 | L22: 1176.3 | M22: 1181.38 | N22: 1213.5 | O22: 1233.04 | P22: 1251.5 | Q22: 1298.14 | R22: 1364.27 | S22: 1379.34 | T22: 1310.45 | U22: 1342.54 | V22: 1340.82 | W22: 1347.77 | X22: 1354.5 | Y22: 1388.58 | Z22: 1376.11 | AA22: 1409.3 | AB22: 1455.67 | AC22: 1411.14 | AD22: 1401.56 | AE22: 1453.11 | AF22: 1467.14 | AG22: 1496.65 | AH22: 1427.9 | AI22: 1366.93 | AJ22: 1363.91 | AK22: 1363.91 | AL22: 1363.91 | AM22: 1363.91 | AN22: 1363.91 | AO22: 1363.91 | AP22: 1363.91 | AQ22: 1363.91 | AR22: 1363.91 | AS22: 1363.91 | AT22: 1363.91 | AU22: 1363.91 | AV22: 1363.91 | AW22: 1363.91 | AX22: 1363.91 | AY22: 1363.91 | AZ22: 1363.91 | BA22: 1363.91 | BB22: 1363.91 | BC22: 1363.91 | BD22: 1363.91 | BE22: 1363.91
A23: hedged_krw_m | D23: 헤지적용 원화매출(백만원) | E23: 66703.4 | F23: 78077.1 | G23: 77153.7 | H23: 77226.4 | I23: 78554 | J23: 77756.8 | K23: 74119.4 | L23: 72356.3 | M23: 84644.4 | N23: 129072.5 | O23: 131150.8 | P23: 159505.3 | Q23: 183426.3 | R23: 194889 | S23: 197041.3 | T23: 193810.7 | U23: 149936.8 | V23: 147137.6 | W23: 154901 | X23: 182128.1 | Y23: 225927.6 | Z23: 307498.3 | AA23: 314916.6 | AB23: 332111.5 | AC23: 346947 | AD23: 380584.3 | AE23: 683529.2 | AF23: 1179793.6 | AG23: 1381504.9 | AH23: 1560284.1 | AI23: 1628651.9 | AJ23: 1514901 | AK23: 1440433.7 | AL23: 1448053.9 | AM23: 1434480 | AN23: 1396553.5 | AO23: 1315528.3 | AP23: 1255874.1 | AQ23: 1235886.4 | AR23: 1116086 | AS23: 957985.8 | AT23: 420171.3 | AU23: 211028.2 | AV23: 119965.2 | AW23: 60719.9 | AX23: 61387.1 | AY23: 54021.4 | AZ23: 33535.9 | BA23: 33908.5 | BB23: 34281.1 | BC23: 34281.1 | BD23: 33908.5 | BE23: 33908.5 | BF23: 221934.2 | BG23: 307656.6 | BH23: 417224 | BI23: 734861.9 | BJ23: 645786.1 | BK23: 1030470.6 | BL23: 1743172 | BM23: 5750234.5 | BN23: 5837868.6 | BO23: 5203842.3 | BP23: 2705271.3 | BQ23: 296093.6 | BR23: 136006.6 | BS23: 67817
A24: marine_hedged_krw_m | D24: 해양 원화(백만원) | E24: 66703.4 | F24: 78077.1 | G24: 77153.7 | H24: 77226.4 | I24: 78554 | J24: 77756.8 | K24: 74119.4 | L24: 72356.3 | M24: 84644.4 | N24: 129072.5 | O24: 131150.8 | P24: 130219.9 | Q24: 136573.9 | R24: 145108.7 | S24: 146711.2 | T24: 147033.8 | U24: 101482 | V24: 98212.9 | W24: 105722.7 | X24: 133241.3 | Y24: 175810.9 | Z24: 257286 | AA24: 263493 | AB24: 266245.8 | AC24: 260969 | AD24: 294251.8 | AE24: 594021.2 | AF24: 1091386.4 | AG24: 1290317.3 | AH24: 1472329.2 | AI24: 1544452.6 | AJ24: 1432714.3 | AK24: 1404937.1 | AL24: 1413807.9 | AM24: 1400234 | AN24: 1385014.1 | AO24: 1315528.3 | AP24: 1255874.1 | AQ24: 1235886.4 | AR24: 1116086 | AS24: 957985.8 | AT24: 420171.3 | AU24: 211028.2 | AV24: 119965.2 | AW24: 60719.9 | AX24: 61387.1 | AY24: 54021.4 | AZ24: 33535.9 | BA24: 33908.5 | BB24: 34281.1 | BC24: 34281.1 | BD24: 33908.5 | BE24: 33908.5 | BF24: 221934.2 | BG24: 307656.6 | BH24: 417224 | BI24: 558613.7 | BJ24: 452451.4 | BK24: 829831.2 | BL24: 1415487.8 | BM24: 5398485.5 | BN24: 5651693.3 | BO24: 5192302.9 | BP24: 2705271.3 | BQ24: 296093.6 | BR24: 136006.6 | BS24: 67817
A25: marine_hedged_krw_m_signed_by_origin | D25: 해양 원화 — origin 분기말까지 체결분(백만원) | E25: 66703.4 | F25: 78077.1 | G25: 77153.7 | H25: 77226.4 | I25: 78554 | J25: 77756.8 | K25: 74119.4 | L25: 72356.3 | M25: 84644.4 | N25: 129072.5 | O25: 131150.8 | P25: 130219.9 | Q25: 136573.9 | R25: 145108.7 | S25: 146711.2 | T25: 147033.8 | U25: 101482 | V25: 98212.9 | W25: 105722.7 | X25: 133241.3 | Y25: 175810.9 | Z25: 257286 | AA25: 263493 | AB25: 266245.8 | AC25: 260969 | AD25: 294251.8 | AE25: 594021.2 | AF25: 1091386.4 | AG25: 1290317.3 | AH25: 1342515.1 | AI25: 1240229.3 | AJ25: 1135762.8 | AK25: 1104686.1 | AL25: 1110257.5 | AM25: 1096683.6 | AN25: 1084763.1 | AO25: 1015277.3 | AP25: 952323.7 | AQ25: 932336 | AR25: 819134.5 | AS25: 657734.8 | AT25: 130154.1 | AU25: 104969.1 | AV25: 34772.4 | AW25: 0 | AX25: 0 | AY25: 0 | AZ25: 0 | BA25: 0 | BB25: 0 | BC25: 0 | BD25: 0 | BE25: 0
A26: marine_hedged_krw_m_post_origin | D26: 해양 원화 — origin 이후 체결분(백만원) | E26: 0 | F26: 0 | G26: 0 | H26: 0 | I26: 0 | J26: 0 | K26: 0 | L26: 0 | M26: 0 | N26: 0 | O26: 0 | P26: 0 | Q26: 0 | R26: 0 | S26: 0 | T26: 0 | U26: 0 | V26: 0 | W26: 0 | X26: 0 | Y26: 0 | Z26: 0 | AA26: 0 | AB26: 0 | AC26: 0 | AD26: 0 | AE26: 0 | AF26: 0 | AG26: 0 | AH26: 129814.1 | AI26: 304223.3 | AJ26: 296951.5 | AK26: 300251 | AL26: 303550.4 | AM26: 303550.4 | AN26: 300251 | AO26: 300251 | AP26: 303550.4 | AQ26: 303550.4 | AR26: 296951.5 | AS26: 300251 | AT26: 290017.3 | AU26: 106059.2 | AV26: 85192.8 | AW26: 60719.9 | AX26: 61387.1 | AY26: 54021.4 | AZ26: 33535.9 | BA26: 33908.5 | BB26: 34281.1 | BC26: 34281.1 | BD26: 33908.5 | BE26: 33908.5
A27: target_opm | D27: 타겟 OPM(코호트) | E27: 0.0426 | F27: 0.0426 | G27: 0.0426 | H27: 0.0426 | I27: 0.0426 | J27: 0.0426 | K27: 0.0426 | L27: 0.0426 | M27: 0.0441 | N27: 0.0473 | O27: 0.0473 | P27: 0.0473 | Q27: 0.0473 | R27: 0.0473 | S27: 0.0473 | T27: 0.0517 | U27: 0.0737 | V27: 0.0759 | W27: 0.0781 | X27: 0.0844 | Y27: 0.0897 | Z27: 0.0954 | AA27: 0.0954 | AB27: 0.0954 | AC27: 0.0954 | AD27: 0.0968 | AE27: 0.1021 | AF27: 0.1045 | AG27: 0.105 | AH27: 0.1054 | AI27: 0.1056 | AJ27: 0.107 | AK27: 0.108 | AL27: 0.108 | AM27: 0.108 | AN27: 0.108 | AO27: 0.108 | AP27: 0.108 | AQ27: 0.108 | AR27: 0.108 | AS27: 0.108 | AT27: 0.108 | AU27: 0.108 | AV27: 0.108 | AW27: 0.108 | AX27: 0.108 | AY27: 0.108
A29: 선표 연결(수식) — 원화(백만원) = 스케줄(백만$) × 포함 × (1 + (캡배율 − 1) × origin 이후) × (헤지비율 × 헤지환율 + (1 − 헤지비율) × 건조시점 환율) | J29: subQ 매출조선 = 합계/100 + 변수 잔고 소진 + 매출조선신규
A30: 헤지비율 | D30: =변수!$D$61 | E30: 변수 3절 '헤지비율' 참조 — usd_sell_m ÷ (기말 수주잔고 원화 ÷ 평균약정환율), 2026Q2 정기보고서 위험관리 절 — kship_page.yard_summary 방식
A31: 헤지환율 방식 | D31: 정기보고서 평균 약정환율(measured) 1472.04 — 전 계약 공통
A32: spot_krw | D32: 건조시점 원/달러(평균) — 변수 환율 행 참조, 변수 범위 밖 분기는 sls spot_assumed | E32: =IFERROR(VLOOKUP(" 원/달러(평균)",환율,MATCH(E$1,변수H,0),0),1167.69) | F32: =IFERROR(VLOOKUP(" 원/달러(평균)",환율,MATCH(F$1,변수H,0),0),1193.96) | G32: =IFERROR(VLOOKUP(" 원/달러(평균)",환율,MATCH(G$1,변수H,0),0),1176.23) | H32: =IFERROR(VLOOKUP(" 원/달러(평균)",환율,MATCH(H$1,변수H,0),0),1193.92) | I32: =IFERROR(VLOOKUP(" 원/달러(평균)",환율,MATCH(I$1,변수H,0),0),1219.69) | J32: =IFERROR(VLOOKUP(" 원/달러(평균)",환율,MATCH(J$1,변수H,0),0),1187.81) | K32: =IFERROR(VLOOKUP(" 원/달러(평균)",환율,MATCH(K$1,변수H,0),0),1117.97) | L32: =IFERROR(VLOOKUP(" 원/달러(평균)",환율,MATCH(L$1,변수H,0),0),1114.99) | M32: =IFERROR(VLOOKUP(" 원/달러(평균)",환율,MATCH(M$1,변수H,0),0),1121.13) | N32: =IFERROR(VLOOKUP(" 원/달러(평균)",환율,MATCH(N$1,변수H,0),0),1159.91) | O32: =IFERROR(VLOOKUP(" 원/달러(평균)",환율,MATCH(O$1,변수H,0),0),1183.5) | P32: =IFERROR(VLOOKUP(" 원/달러(평균)",환율,MATCH(P$1,변수H,0),0),1205.78) | Q32: =IFERROR(VLOOKUP(" 원/달러(평균)",환율,MATCH(Q$1,변수H,0),0),1262.09) | R32: =IFERROR(VLOOKUP(" 원/달러(평균)",환율,MATCH(R$1,변수H,0),0),1341.93) | S32: =IFERROR(VLOOKUP(" 원/달러(평균)",환율,MATCH(S$1,변수H,0),0),1360.12) | T32: =IFERROR(VLOOKUP(" 원/달러(평균)",환율,MATCH(T$1,변수H,0),0),1276.95) | U32: =IFERROR(VLOOKUP(" 원/달러(평균)",환율,MATCH(U$1,변수H,0),0),1315.69) | V32: =IFERROR(VLOOKUP(" 원/달러(평균)",환율,MATCH(V$1,변수H,0),0),1313.62) | W32: =IFERROR(VLOOKUP(" 원/달러(평균)",환율,MATCH(W$1,변수H,0),0),1322.01) | X32: =IFERROR(VLOOKUP(" 원/달러(평균)",환율,MATCH(X$1,변수H,0),0),1330.14) | Y32: =IFERROR(VLOOKUP(" 원/달러(평균)",환율,MATCH(Y$1,변수H,0),0),1371.28) | Z32: =IFERROR(VLOOKUP(" 원/달러(평균)",환율,MATCH(Z$1,변수H,0),0),1356.22) | AA32: =IFERROR(VLOOKUP(" 원/달러(평균)",환율,MATCH(AA$1,변수H,0),0),1396.3) | AB32: =IFERROR(VLOOKUP(" 원/달러(평균)",환율,MATCH(AB$1,변수H,0),0),1452.28) | AC32: =IFERROR(VLOOKUP(" 원/달러(평균)",환율,MATCH(AC$1,변수H,0),0),1398.52) | AD32: =IFERROR(VLOOKUP(" 원/달러(평균)",환율,MATCH(AD$1,변수H,0),0),1386.95) | AE32: =IFERROR(VLOOKUP(" 원/달러(평균)",환율,MATCH(AE$1,변수H,0),0),1449.19) | AF32: =IFERROR(VLOOKUP(" 원/달러(평균)",환율,MATCH(AF$1,변수H,0),0),1466.12) | AG32: =IFERROR(VLOOKUP(" 원/달러(평균)",환율,MATCH(AG$1,변수H,0),0),1501.75) | AH32: =IFERROR(VLOOKUP(" 원/달러(평균)",환율,MATCH(AH$1,변수H,0),0),1418.75) | AI32: =IFERROR(VLOOKUP(" 원/달러(평균)",환율,MATCH(AI$1,변수H,0),0),1345.14) | AJ32: =IFERROR(VLOOKUP(" 원/달러(평균)",환율,MATCH(AJ$1,변수H,0),0),1341.49) | AK32: =IFERROR(VLOOKUP(" 원/달러(평균)",환율,MATCH(AK$1,변수H,0),0),1341.49) | AL32: =IFERROR(VLOOKUP(" 원/달러(평균)",환율,MATCH(AL$1,변수H,0),0),1341.49) | AM32: =IFERROR(VLOOKUP(" 원/달러(평균)",환율,MATCH(AM$1,변수H,0),0),1341.49) | AN32: =IFERROR(VLOOKUP(" 원/달러(평균)",환율,MATCH(AN$1,변수H,0),0),1341.49) | AO32: =IFERROR(VLOOKUP(" 원/달러(평균)",환율,MATCH(AO$1,변수H,0),0),1341.49) | AP32: =IFERROR(VLOOKUP(" 원/달러(평균)",환율,MATCH(AP$1,변수H,0),0),1341.49) | AQ32: =IFERROR(VLOOKUP(" 원/달러(평균)",환율,MATCH(AQ$1,변수H,0),0),1341.49) | ... BE32: =IFERROR(VLOOKUP(" 원/달러(평균)",환율,MATCH(BE$1,변수H,0),0),1341.49)
A33: after_origin | D33: origin(2026Q2) 이후 분기 = 1 (잔고 캡 배율 적용 구간) | E33: 0 | F33: 0 | G33: 0 | H33: 0 | I33: 0 | J33: 0 | K33: 0 | L33: 0 | M33: 0 | N33: 0 | O33: 0 | P33: 0 | Q33: 0 | R33: 0 | S33: 0 | T33: 0 | U33: 0 | V33: 0 | W33: 0 | X33: 0 | Y33: 0 | Z33: 0 | AA33: 0 | AB33: 0 | AC33: 0 | AD33: 0 | AE33: 0 | AF33: 0 | AG33: 0 | AH33: 1 | AI33: 1 | AJ33: 1 | AK33: 1 | AL33: 1 | AM33: 1 | AN33: 1 | AO33: 1 | AP33: 1 | AQ33: 1 | AR33: 1 | AS33: 1 | AT33: 1 | AU33: 1 | AV33: 1 | AW33: 1 | AX33: 1 | AY33: 1 | AZ33: 1 | BA33: 1 | BB33: 1 | BC33: 1 | BD33: 1 | BE33: 1
A35: ① 계약별 매출인식 스케줄(백만$, sls 저장값) | B35: type | C35: ships | D35: name | BU35: 포함(1/0) | BV35: 헤지환율 | BW35: 캡배율 | BX35: 체결일 | BY35: origin이내 | BZ35: 코호트 | CA35: 계약액(백만$) | CB35: 종료
A36: 20250905800030 | B36: LNGC | C36: 1 | D36: LNGC 1척 | AD36: 7.273 | AE36: 24.783 | AF36: 24.244 | AG36: 24.514 | AH36: 24.783 | AI36: 24.783 | AJ36: 24.244 | AK36: 24.514 | AL36: 24.783 | AM36: 24.783 | AN36: 24.513 | BU36: 1 | BV36: 1472.04 | BW36: 1 | BX36: 2025-09-04 | BY36: 1 | BZ36: ⑤초호황 | CA36: 253.217 | CB36: 2028-03-31
A37: 20250915800507 | B37: OFFSH | C37: 1 | D37: FPSO 1기 | M37: 9.453 | N37: 43.485 | O37: 43.485 | P37: 42.539 | Q37: 43.012 | R37: 43.485 | S37: 43.485 | T37: 42.539 | U37: 43.012 | V37: 43.485 | W37: 43.485 | X37: 43.012 | Y37: 43.012 | Z37: 43.485 | AA37: 43.485 | AB37: 42.539 | AC37: 43.012 | AD37: 43.485 | AE37: 43.485 | AF37: 42.539 | AG37: 43.012 | AH37: 43.485 | AI37: 43.485 | AJ37: 17.014 | BU37: 1 | BV37: 1472.04 | BW37: 1 | BX37: 2021-06-11 | BY37: 1 | BZ37: ④호황 | CA37: 976.515 | CB37: 2027-02-05
A38: 20250917800008 | B38: CONT | C38: 7 | D38: 컨테이너선 7척 | AD38: 15.445 | AE38: 94.727 | AF38: 92.668 | AG38: 93.698 | AH38: 94.727 | AI38: 94.727 | AJ38: 92.668 | AK38: 93.698 | AL38: 94.727 | AM38: 94.727 | AN38: 93.698 | AO38: 93.698 | AP38: 94.727 | AQ38: 94.727 | AR38: 92.668 | AS38: 62.808 | BU38: 1 | BV38: 1472.04 | BW38: 1 | BX38: 2025-09-16 | BY38: 1 | BZ38: ⑤초호황 | CA38: 1394.138 | CB38: 2029-05-31
A39: 20251001800067 | B39: LNGC | C39: 1 | D39: LNGC 1척 | AD39: 0.261 | AE39: 24.043 | AF39: 23.52 | AG39: 23.782 | AH39: 24.043 | AI39: 24.043 | AJ39: 23.52 | AK39: 23.782 | AL39: 24.043 | AM39: 24.043 | AN39: 23.782 | AO39: 15.942 | BU39: 1 | BV39: 1472.04 | BW39: 1 | BX39: 2025-09-30 | BY39: 1 | BZ39: ⑤초호황 | CA39: 254.804 | CB39: 2028-05-31
A40: 20251010800428 | B40: VLGC | C40: 1 | D40: 초대형 LPG/AMMONIA 운반선 1척 | W40: 5.194 | X40: 12.439 | Y40: 12.439 | Z40: 12.576 | AA40: 12.576 | AB40: 12.302 | AC40: 12.439 | AD40: 12.576 | AE40: 12.576 | AF40: 12.302 | AG40: 5.878 | BU40: 1 | BV40: 1472.04 | BW40: 1 | BX40: 2023-11-24 | BY40: 1 | BZ40: ⑤초호황 | CA40: 123.297 | CB40: 2026-05-13
A41: 20251124800090 | B41: VLCC | C41: 4 | D41: VLCC 4척 | AE41: 19.382 | AF41: 42.546 | AG41: 43.019 | AH41: 43.492 | AI41: 43.492 | AJ41: 42.546 | AK41: 43.019 | AL41: 43.492 | AM41: 43.492 | AN41: 43.019 | AO41: 43.019 | AP41: 43.492 | AQ41: 28.834 | BU41: 1 | BV41: 1472.04 | BW41: 1 | BX41: 2025-11-21 | BY41: 1 | BZ41: ⑤초호황 | CA41: 522.844 | CB41: 2028-11-30
A42: 20251127800598 | B42: VLCC | C42: 2 | D42: 초대형 원유운반선 2척 | X42: 13.478 | Y42: 31.448 | Z42: 31.794 | AA42: 31.794 | AB42: 31.103 | AC42: 31.448 | AD42: 31.794 | AE42: 31.794 | AF42: 22.463 | BU42: 1 | BV42: 1472.04 | BW42: 1 | BX42: 2024-02-22 | BY42: 1 | BZ42: ⑤초호황 | CA42: 257.116 | CB42: 2026-03-06
A43: 20251128800098 | B43: CONT | C43: 4 | D43: 컨테이너선 4척 | AE43: 21.73 | AF43: 55.878 | AG43: 56.499 | AH43: 57.119 | AI43: 57.119 | AJ43: 55.878 | AK43: 56.499 | AL43: 57.119 | AM43: 57.119 | AN43: 56.499 | AO43: 56.499 | AP43: 57.119 | AQ43: 57.119 | AR43: 36.631 | BU43: 1 | BV43: 1472.04 | BW43: 1 | BX43: 2025-11-27 | BY43: 1 | BZ43: ⑤초호황 | CA43: 738.827 | CB43: 2029-02-28
A44: 20251202800041 | B44: VLCC | C44: 2 | D44: VLCC 2척 | AE44: 7.123 | AF44: 20.681 | AG44: 20.911 | AH44: 21.141 | AI44: 21.141 | AJ44: 20.681 | AK44: 20.911 | AL44: 21.141 | AM44: 21.141 | AN44: 20.911 | AO44: 20.911 | AP44: 21.141 | AQ44: 21.138 | BU44: 1 | BV44: 1472.04 | BW44: 1 | BX44: 2025-12-01 | BY44: 1 | BZ44: ⑤초호황 | CA44: 258.972 | CB44: 2028-12-31
A45: 20251219800049 | B45: LNGC | C45: 7 | D45: LNGC 7척 | AE45: 19.374 | AF45: 124.549 | AG45: 125.933 | AH45: 127.317 | AI45: 127.317 | AJ45: 124.549 | AK45: 125.933 | AL45: 127.317 | AM45: 127.317 | AN45: 125.933 | AO45: 125.933 | AP45: 127.317 | AQ45: 127.317 | AR45: 124.549 | AS45: 125.929 | BU45: 1 | BV45: 1472.04 | BW45: 1 | BX45: 2025-12-18 | BY45: 1 | BZ45: ⑤초호황 | CA45: 1786.584 | CB45: 2029-06-30
A46: 20251223800047 | B46: OFFSH | D46: 신안우이해상풍력 발전소 설계·구매·시공(EPC) 계약 | AE46: 10.662 | AF46: 95.959 | AG46: 97.025 | AH46: 98.091 | AI46: 98.091 | AJ46: 95.959 | AK46: 97.025 | AL46: 98.091 | AM46: 98.091 | AN46: 97.025 | AO46: 97.025 | AP46: 98.091 | AQ46: 98.091 | AR46: 95.959 | AS46: 85.299 | BU46: 1 | BV46: 1472.04 | BW46: 1 | BX46: 2025-12-22 | BY46: 1 | CA46: 1360.484 | CB46: 2029-06-19
A47: 20260115800042 | B47: VLCC | C47: 3 | D47: VLCC 3척 | AF47: 24.981 | AG47: 29.523 | AH47: 29.847 | AI47: 29.847 | AJ47: 29.198 | AK47: 29.523 | AL47: 29.847 | AM47: 29.847 | AN47: 29.523 | AO47: 29.523 | AP47: 29.847 | AQ47: 29.847 | AR47: 29.198 | AS47: 9.731 | BU47: 1 | BV47: 1472.04 | BW47: 1 | BX47: 2026-01-14 | BY47: 1 | BZ47: ⑤초호황 | CA47: 390.282 | CB47: 2029-04-30
A48: 20260121800115 | B48: LNGC | C48: 2 | D48: LNGC 2척 | AF48: 28.444 | AG48: 36.456 | AH48: 36.857 | AI48: 36.857 | AJ48: 36.055 | AK48: 36.456 | AL48: 36.857 | AM48: 36.857 | AN48: 36.456 | AO48: 36.456 | AP48: 36.857 | AQ48: 36.857 | AR48: 36.055 | AS48: 36.054 | BU48: 1 | BV48: 1472.04 | BW48: 1 | BX48: 2026-01-20 | BY48: 1 | BZ48: ⑤초호황 | CA48: 503.574 | CB48: 2029-06-29
A49: 20260206800258 | B49: OFFSH | C49: 1 | D49: 해상풍력발전기 설치선 1척 | AF49: 33.467 | AG49: 56.397 | AH49: 57.017 | AI49: 57.017 | AJ49: 55.778 | AK49: 56.397 | AL49: 57.017 | AM49: 57.017 | AN49: 56.397 | AO49: 37.805 | BU49: 1 | BV49: 1472.04 | BW49: 1 | BX49: 2026-02-06 | BY49: 1 | BZ49: ⑤초호황 | CA49: 524.309 | CB49: 2028-05-31
A50: 20260220801130 | B50: LNGC | C50: 1 | D50: LNG 운반선 1척 | U50: 13.644 | V50: 14.768 | W50: 14.768 | X50: 14.607 | Y50: 14.607 | Z50: 14.768 | AA50: 14.768 | AB50: 14.447 | AC50: 14.607 | AD50: 14.768 | AE50: 14.768 | AF50: 14.447 | AG50: 14.607 | AH50: 14.768 | AI50: 14.768 | AJ50: 14.447 | AK50: 14.607 | AL50: 9.952 | BU50: 1 | BV50: 1472.04 | BW50: 1 | BX50: 2023-04-07 | BY50: 1 | BZ50: ⑤초호황 | CA50: 258.116 | CB50: 2027-08-31
A51: 20260220801140 | B51: LNGC | C51: 1 | D51: LNG 운반선 1척 | T51: 8.15 | U51: 14.833 | V51: 14.996 | W51: 14.996 | X51: 14.833 | Y51: 14.833 | Z51: 14.996 | AA51: 14.996 | AB51: 14.67 | AC51: 14.833 | AD51: 14.996 | AE51: 14.996 | AF51: 14.67 | AG51: 14.833 | AH51: 14.996 | AI51: 14.996 | AJ51: 14.667 | BU51: 1 | BV51: 1472.04 | BW51: 1 | BX51: 2023-02-10 | BY51: 1 | BZ51: ⑤초호황 | CA51: 246.29 | CB51: 2027-03-31
A52: 20260325800201 | B52: VLCC | C52: 3 | D52: VLCC 3척 | AF52: 2.69 | AG52: 30.603 | AH52: 30.939 | AI52: 30.939 | AJ52: 30.267 | AK52: 30.603 | AL52: 30.939 | AM52: 30.939 | AN52: 30.603 | AO52: 30.603 | AP52: 30.939 | AQ52: 30.939 | AR52: 30.267 | AS52: 30.266 | BU52: 1 | BV52: 1472.04 | BW52: 1 | BX52: 2026-03-24 | BY52: 1 | BZ52: ⑤초호황 | CA52: 401.536 | CB52: 2029-06-29
A53: 20260331803529 | B53: NAVAL | C53: 3 | D53: 잠수함 3척 | E53: 54.677 | F53: 62.879 | G53: 62.879 | H53: 62.195 | I53: 62.195 | J53: 62.879 | K53: 62.879 | L53: 61.512 | M53: 62.195 | N53: 62.879 | O53: 62.879 | P53: 61.512 | Q53: 62.195 | R53: 62.879 | S53: 62.879 | T53: 61.512 | U53: 4.102 | BU53: 1 | BV53: 1472.04 | BW53: 1 | BX53: 2019-04-12 | BY53: 1 | BZ53: ③중마진 | CA53: 995.127 | CB53: 2023-04-06
A54: 20260408801023 | B54: VLGC | C54: 1 | D54: LPG 운반선 1척 | Y54: 8.473 | Z54: 14.173 | AA54: 14.173 | AB54: 13.865 | AC54: 14.019 | AD54: 14.173 | AE54: 14.173 | AF54: 13.865 | AG54: 14.019 | AH54: 7.706 | BU54: 1 | BV54: 1472.04 | BW54: 1 | BX54: 2024-04-16 | BY54: 1 | BZ54: ⑤초호황 | CA54: 128.639 | CB54: 2026-08-19
A55: 20260409800345 | B55: VLCC | C55: 2 | D55: VLCC 2척 | AG55: 16.081 | AH55: 17.613 | AI55: 17.613 | AJ55: 17.23 | AK55: 17.421 | AL55: 17.613 | AM55: 17.613 | AN55: 17.421 | AO55: 17.421 | AP55: 17.613 | AQ55: 17.613 | AR55: 17.23 | AS55: 17.421 | AT55: 17.613 | AU55: 17.613 | AV55: 0.765 | BU55: 1 | BV55: 1472.04 | BW55: 1 | BX55: 2026-04-08 | BY55: 1 | BZ55: ⑤초호황 | CA55: 261.894 | CB55: 2030-01-04
A56: 20260504800235 | B56: VLGC | C56: 3 | D56: VLAC 3척 | AG56: 15.437 | AH56: 22.907 | AI56: 22.907 | AJ56: 22.409 | AK56: 22.658 | AL56: 22.907 | AM56: 22.907 | AN56: 22.658 | AO56: 22.658 | AP56: 22.907 | AQ56: 22.907 | AR56: 22.409 | AS56: 22.658 | AT56: 22.907 | AU56: 22.907 | AV56: 3.729 | BU56: 1 | BV56: 1472.04 | BW56: 1 | BX56: 2026-04-30 | BY56: 1 | BZ56: ⑤초호황 | CA56: 337.872 | CB56: 2030-01-15
A57: 20260511800175 | B57: LNGC | C57: 1 | D57: LNGC 1척 | AG57: 11.507 | AH57: 19.604 | AI57: 19.604 | AJ57: 19.178 | AK57: 19.391 | AL57: 19.604 | AM57: 19.604 | AN57: 19.391 | AO57: 19.391 | AP57: 19.604 | AQ57: 19.604 | AR57: 19.178 | AS57: 16.191 | BU57: 1 | BV57: 1472.04 | BW57: 1 | BX57: 2026-05-08 | BY57: 1 | BZ57: ⑤초호황 | CA57: 241.851 | CB57: 2029-06-15
A58: 20260518800002 | B58: LNGC | C58: 2 | D58: LNGC 2척 | AG58: 22.101 | AH58: 43.262 | AI58: 43.262 | AJ58: 42.321 | AK58: 42.792 | AL58: 43.262 | AM58: 43.262 | AN58: 42.792 | AO58: 42.792 | AP58: 43.262 | AQ58: 43.262 | AR58: 42.321 | AS58: 21.16 | BU58: 1 | BV58: 1472.04 | BW58: 1 | BX58: 2026-03-24 | BY58: 1 | BZ58: ⑤초호황 | CA58: 515.851 | CB58: 2029-05-15
A59: 20260528800927 | B59: OTHER | D59: MCS Plant 구축 공사 | AB59: 9.552 | AC59: 24.836 | AD59: 25.109 | AE59: 25.109 | AF59: 24.563 | AG59: 24.836 | AH59: 25.109 | AI59: 25.109 | AJ59: 24.563 | AK59: 24.836 | AL59: 25.109 | AM59: 25.109 | AN59: 8.459 | BU59: 0 | BV59: 1472.04 | BW59: 1 | BX59: 2025-02-25 | BY59: 1 | CA59: 292.299 | CB59: 2028-01-31
A60: 20260529800152 | B60: LNGC | C60: 1 | D60: LNGC 1척 | AG60: 6.976 | AH60: 18.876 | AI60: 18.876 | AJ60: 18.465 | AK60: 18.671 | AL60: 18.876 | AM60: 18.876 | AN60: 18.671 | AO60: 18.671 | AP60: 18.876 | AQ60: 18.876 | AR60: 18.465 | AS60: 18.671 | AT60: 18.462 | BU60: 1 | BV60: 1472.04 | BW60: 1 | BX60: 2026-05-28 | BY60: 1 | BZ60: ⑤초호황 | CA60: 250.308 | CB60: 2029-09-28
A61: 20260619800742 | B61: VLCC | C61: 4 | D61: VLCC 4척 | AG61: 4.753 | AH61: 36.443 | AI61: 36.443 | AJ61: 35.651 | AK61: 36.047 | AL61: 36.443 | AM61: 36.443 | AN61: 36.047 | AO61: 36.047 | AP61: 36.443 | AQ61: 36.443 | AR61: 35.651 | AS61: 36.047 | AT61: 36.443 | AU61: 36.443 | AV61: 20.991 | BU61: 1 | BV61: 1472.04 | BW61: 1 | BX61: 2026-06-12 | BY61: 1 | BZ61: ⑤초호황 | CA61: 532.778 | CB61: 2030-02-22
A62: 20260715800071 | B62: VLCC | C62: 2 | D62: VLCC 2척 | AH62: 16.18 | AI62: 18.842 | AJ62: 18.432 | AK62: 18.637 | AL62: 18.842 | AM62: 18.842 | AN62: 18.637 | AO62: 18.637 | AP62: 18.842 | AQ62: 18.842 | AR62: 18.432 | AS62: 18.637 | AT62: 18.842 | AU62: 18.842 | AV62: 18.435 | BU62: 0 | BV62: 1472.04 | BW62: 1 | BX62: 2026-07-14 | BY62: 0 | BZ62: ⑤초호황 | CA62: 277.921 | CB62: 2030-03-31
A63: 20260731800216 | B63: NAVAL | D63: 구축함(KDDX) 상세설계 및 선도함 건조 사업 | AH63: 16.938 | AI63: 25.135 | AJ63: 24.588 | AK63: 24.861 | AL63: 25.135 | AM63: 25.135 | AN63: 24.861 | AO63: 24.861 | AP63: 25.135 | AQ63: 25.135 | AR63: 24.588 | AS63: 24.861 | AT63: 25.135 | AU63: 25.135 | AV63: 24.588 | AW63: 24.861 | AX63: 25.135 | AY63: 25.135 | AZ63: 24.588 | BA63: 24.861 | BB63: 25.135 | BC63: 25.135 | BD63: 24.861 | BE63: 24.859 | BU63: 0 | BV63: 1472.04 | BW63: 1 | BX63: 2026-07-31 | BY63: 0 | CA63: 590.661 | CB63: 2032-06-30
A64: 20260803800706 | B64: PC | D64: 여수에코에너지 LNG 집단에너지 사업(490MW) EPC 계약 | AH64: 19.514 | AI64: 30.429 | AJ64: 29.767 | AK64: 30.098 | AL64: 30.429 | AM64: 30.429 | AN64: 30.098 | AO64: 30.098 | AP64: 30.429 | AQ64: 30.429 | AR64: 29.767 | AS64: 30.098 | AT64: 20.503 | BU64: 0 | BV64: 1472.04 | BW64: 1 | BX64: 2026-08-03 | BY64: 0 | CA64: 372.088 | CB64: 2029-08-31
A65: 20260825800541 | B65: OTHER | C65: 1 | D65: FCS(필드제어설비) 1기 | P65: 23.4 | Q65: 36.092 | R65: 36.489 | S65: 36.489 | T65: 35.695 | U65: 36.092 | V65: 36.489 | W65: 36.489 | X65: 36.092 | Y65: 36.092 | Z65: 36.489 | AA65: 36.489 | AB65: 35.695 | AC65: 36.092 | AD65: 36.489 | AE65: 36.489 | AF65: 35.695 | AG65: 36.092 | AH65: 36.489 | AI65: 36.489 | AJ65: 35.695 | AK65: 1.188 | BU65: 0 | BV65: 1472.04 | BW65: 1 | BX65: 2022-01-10 | BY65: 1 | CA65: 748.81 | CB65: 2027-04-03
A66: 20260901800108 | B66: VLGC | C66: 3 | D66: VLGC 3척 | AH66: 6.697 | AI66: 19.874 | AJ66: 19.442 | AK66: 19.658 | AL66: 19.874 | AM66: 19.874 | AN66: 19.658 | AO66: 19.658 | AP66: 19.874 | AQ66: 19.874 | AR66: 19.442 | AS66: 19.658 | AT66: 19.874 | AU66: 19.874 | AV66: 19.442 | AW66: 19.658 | AX66: 19.874 | AY66: 14.47 | BU66: 0 | BV66: 1472.04 | BW66: 1 | BX66: 2026-08-31 | BY66: 0 | BZ66: ⑤초호황 | CA66: 336.775 | CB66: 2030-12-06
A67: 20260903800002 | B67: CONT | C67: 6 | D67: 컨테이너선 6척 | AH67: 28.212 | AI67: 89.499 | AJ67: 87.553 | AK67: 88.526 | AL67: 89.499 | AM67: 89.499 | AN67: 88.526 | AO67: 88.526 | AP67: 89.499 | AQ67: 89.499 | AR67: 87.553 | AS67: 88.526 | AT67: 89.497 | BU67: 0 | BV67: 1472.04 | BW67: 1 | BX67: 2026-09-02 | BY67: 0 | BZ67: ⑤초호황 | CA67: 1094.414 | CB67: 2029-09-30
A68: 20260921800302 | B68: VLCC | C68: 4 | D68: VLCC 4척 | Y68: 1.799 | Z68: 55.175 | AA68: 55.175 | AB68: 53.976 | AC68: 54.576 | AD68: 55.175 | AE68: 55.175 | AF68: 53.976 | AG68: 54.576 | AH68: 55.175 | AI68: 29.987 | BU68: 1 | BV68: 1472.04 | BW68: 1 | BX68: 2024-06-28 | BY68: 1 | BZ68: ⑤초호황 | CA68: 524.765 | CB68: 2026-11-19
A69: 20260928800496 | B69: LNGC | C69: 2 | D69: LNGC 2척 | AH69: 3.372 | AI69: 38.782 | AJ69: 37.939 | AK69: 38.36 | AL69: 38.782 | AM69: 38.782 | AN69: 38.36 | AO69: 38.36 | AP69: 38.782 | AQ69: 38.782 | AR69: 37.939 | AS69: 38.36 | AT69: 38.782 | AU69: 13.913 | BU69: 0 | BV69: 1472.04 | BW69: 1 | BX69: 2026-09-23 | BY69: 0 | BZ69: ⑤초호황 | CA69: 479.295 | CB69: 2029-11-02
A71: ② 계약별 원화(백만원, 수식) | B71: type | C71: ships | D71: name
A72: 20250905800030 | B72: LNGC | C72: 1 | D72: LNGC 1척 | AD72: =IFERROR(AD36*$BU36*(1+($BW36-1)*AD$33)*($D$30*$BV36+(1-$D$30)*AD$32),"") | AE72: =IFERROR(AE36*$BU36*(1+($BW36-1)*AE$33)*($D$30*$BV36+(1-$D$30)*AE$32),"") | AF72: =IFERROR(AF36*$BU36*(1+($BW36-1)*AF$33)*($D$30*$BV36+(1-$D$30)*AF$32),"") | AG72: =IFERROR(AG36*$BU36*(1+($BW36-1)*AG$33)*($D$30*$BV36+(1-$D$30)*AG$32),"") | AH72: =IFERROR(AH36*$BU36*(1+($BW36-1)*AH$33)*($D$30*$BV36+(1-$D$30)*AH$32),"") | AI72: =IFERROR(AI36*$BU36*(1+($BW36-1)*AI$33)*($D$30*$BV36+(1-$D$30)*AI$32),"") | AJ72: =IFERROR(AJ36*$BU36*(1+($BW36-1)*AJ$33)*($D$30*$BV36+(1-$D$30)*AJ$32),"") | AK72: =IFERROR(AK36*$BU36*(1+($BW36-1)*AK$33)*($D$30*$BV36+(1-$D$30)*AK$32),"") | ... AN72: =IFERROR(AN36*$BU36*(1+($BW36-1)*AN$33)*($D$30*$BV36+(1-$D$30)*AN$32),"")
A73: 20250915800507 | B73: OFFSH | C73: 1 | D73: FPSO 1기 | M73: =IFERROR(M37*$BU37*(1+($BW37-1)*M$33)*($D$30*$BV37+(1-$D$30)*M$32),"") | N73: =IFERROR(N37*$BU37*(1+($BW37-1)*N$33)*($D$30*$BV37+(1-$D$30)*N$32),"") | O73: =IFERROR(O37*$BU37*(1+($BW37-1)*O$33)*($D$30*$BV37+(1-$D$30)*O$32),"") | P73: =IFERROR(P37*$BU37*(1+($BW37-1)*P$33)*($D$30*$BV37+(1-$D$30)*P$32),"") | Q73: =IFERROR(Q37*$BU37*(1+($BW37-1)*Q$33)*($D$30*$BV37+(1-$D$30)*Q$32),"") | R73: =IFERROR(R37*$BU37*(1+($BW37-1)*R$33)*($D$30*$BV37+(1-$D$30)*R$32),"") | S73: =IFERROR(S37*$BU37*(1+($BW37-1)*S$33)*($D$30*$BV37+(1-$D$30)*S$32),"") | T73: =IFERROR(T37*$BU37*(1+($BW37-1)*T$33)*($D$30*$BV37+(1-$D$30)*T$32),"") | ... AJ73: =IFERROR(AJ37*$BU37*(1+($BW37-1)*AJ$33)*($D$30*$BV37+(1-$D$30)*AJ$32),"")
A74: 20250917800008 | B74: CONT | C74: 7 | D74: 컨테이너선 7척 | AD74: =IFERROR(AD38*$BU38*(1+($BW38-1)*AD$33)*($D$30*$BV38+(1-$D$30)*AD$32),"") | AE74: =IFERROR(AE38*$BU38*(1+($BW38-1)*AE$33)*($D$30*$BV38+(1-$D$30)*AE$32),"") | AF74: =IFERROR(AF38*$BU38*(1+($BW38-1)*AF$33)*($D$30*$BV38+(1-$D$30)*AF$32),"") | AG74: =IFERROR(AG38*$BU38*(1+($BW38-1)*AG$33)*($D$30*$BV38+(1-$D$30)*AG$32),"") | AH74: =IFERROR(AH38*$BU38*(1+($BW38-1)*AH$33)*($D$30*$BV38+(1-$D$30)*AH$32),"") | AI74: =IFERROR(AI38*$BU38*(1+($BW38-1)*AI$33)*($D$30*$BV38+(1-$D$30)*AI$32),"") | AJ74: =IFERROR(AJ38*$BU38*(1+($BW38-1)*AJ$33)*($D$30*$BV38+(1-$D$30)*AJ$32),"") | AK74: =IFERROR(AK38*$BU38*(1+($BW38-1)*AK$33)*($D$30*$BV38+(1-$D$30)*AK$32),"") | ... AS74: =IFERROR(AS38*$BU38*(1+($BW38-1)*AS$33)*($D$30*$BV38+(1-$D$30)*AS$32),"")
A75: 20251001800067 | B75: LNGC | C75: 1 | D75: LNGC 1척 | AD75: =IFERROR(AD39*$BU39*(1+($BW39-1)*AD$33)*($D$30*$BV39+(1-$D$30)*AD$32),"") | AE75: =IFERROR(AE39*$BU39*(1+($BW39-1)*AE$33)*($D$30*$BV39+(1-$D$30)*AE$32),"") | AF75: =IFERROR(AF39*$BU39*(1+($BW39-1)*AF$33)*($D$30*$BV39+(1-$D$30)*AF$32),"") | AG75: =IFERROR(AG39*$BU39*(1+($BW39-1)*AG$33)*($D$30*$BV39+(1-$D$30)*AG$32),"") | AH75: =IFERROR(AH39*$BU39*(1+($BW39-1)*AH$33)*($D$30*$BV39+(1-$D$30)*AH$32),"") | AI75: =IFERROR(AI39*$BU39*(1+($BW39-1)*AI$33)*($D$30*$BV39+(1-$D$30)*AI$32),"") | AJ75: =IFERROR(AJ39*$BU39*(1+($BW39-1)*AJ$33)*($D$30*$BV39+(1-$D$30)*AJ$32),"") | AK75: =IFERROR(AK39*$BU39*(1+($BW39-1)*AK$33)*($D$30*$BV39+(1-$D$30)*AK$32),"") | ... AO75: =IFERROR(AO39*$BU39*(1+($BW39-1)*AO$33)*($D$30*$BV39+(1-$D$30)*AO$32),"")
A76: 20251010800428 | B76: VLGC | C76: 1 | D76: 초대형 LPG/AMMONIA 운반선 1척 | W76: =IFERROR(W40*$BU40*(1+($BW40-1)*W$33)*($D$30*$BV40+(1-$D$30)*W$32),"") | X76: =IFERROR(X40*$BU40*(1+($BW40-1)*X$33)*($D$30*$BV40+(1-$D$30)*X$32),"") | Y76: =IFERROR(Y40*$BU40*(1+($BW40-1)*Y$33)*($D$30*$BV40+(1-$D$30)*Y$32),"") | Z76: =IFERROR(Z40*$BU40*(1+($BW40-1)*Z$33)*($D$30*$BV40+(1-$D$30)*Z$32),"") | AA76: =IFERROR(AA40*$BU40*(1+($BW40-1)*AA$33)*($D$30*$BV40+(1-$D$30)*AA$32),"") | AB76: =IFERROR(AB40*$BU40*(1+($BW40-1)*AB$33)*($D$30*$BV40+(1-$D$30)*AB$32),"") | AC76: =IFERROR(AC40*$BU40*(1+($BW40-1)*AC$33)*($D$30*$BV40+(1-$D$30)*AC$32),"") | AD76: =IFERROR(AD40*$BU40*(1+($BW40-1)*AD$33)*($D$30*$BV40+(1-$D$30)*AD$32),"") | ... AG76: =IFERROR(AG40*$BU40*(1+($BW40-1)*AG$33)*($D$30*$BV40+(1-$D$30)*AG$32),"")
A77: 20251124800090 | B77: VLCC | C77: 4 | D77: VLCC 4척 | AE77: =IFERROR(AE41*$BU41*(1+($BW41-1)*AE$33)*($D$30*$BV41+(1-$D$30)*AE$32),"") | AF77: =IFERROR(AF41*$BU41*(1+($BW41-1)*AF$33)*($D$30*$BV41+(1-$D$30)*AF$32),"") | AG77: =IFERROR(AG41*$BU41*(1+($BW41-1)*AG$33)*($D$30*$BV41+(1-$D$30)*AG$32),"") | AH77: =IFERROR(AH41*$BU41*(1+($BW41-1)*AH$33)*($D$30*$BV41+(1-$D$30)*AH$32),"") | AI77: =IFERROR(AI41*$BU41*(1+($BW41-1)*AI$33)*($D$30*$BV41+(1-$D$30)*AI$32),"") | AJ77: =IFERROR(AJ41*$BU41*(1+($BW41-1)*AJ$33)*($D$30*$BV41+(1-$D$30)*AJ$32),"") | AK77: =IFERROR(AK41*$BU41*(1+($BW41-1)*AK$33)*($D$30*$BV41+(1-$D$30)*AK$32),"") | AL77: =IFERROR(AL41*$BU41*(1+($BW41-1)*AL$33)*($D$30*$BV41+(1-$D$30)*AL$32),"") | ... AQ77: =IFERROR(AQ41*$BU41*(1+($BW41-1)*AQ$33)*($D$30*$BV41+(1-$D$30)*AQ$32),"")
A78: 20251127800598 | B78: VLCC | C78: 2 | D78: 초대형 원유운반선 2척 | X78: =IFERROR(X42*$BU42*(1+($BW42-1)*X$33)*($D$30*$BV42+(1-$D$30)*X$32),"") | Y78: =IFERROR(Y42*$BU42*(1+($BW42-1)*Y$33)*($D$30*$BV42+(1-$D$30)*Y$32),"") | Z78: =IFERROR(Z42*$BU42*(1+($BW42-1)*Z$33)*($D$30*$BV42+(1-$D$30)*Z$32),"") | AA78: =IFERROR(AA42*$BU42*(1+($BW42-1)*AA$33)*($D$30*$BV42+(1-$D$30)*AA$32),"") | AB78: =IFERROR(AB42*$BU42*(1+($BW42-1)*AB$33)*($D$30*$BV42+(1-$D$30)*AB$32),"") | AC78: =IFERROR(AC42*$BU42*(1+($BW42-1)*AC$33)*($D$30*$BV42+(1-$D$30)*AC$32),"") | AD78: =IFERROR(AD42*$BU42*(1+($BW42-1)*AD$33)*($D$30*$BV42+(1-$D$30)*AD$32),"") | AE78: =IFERROR(AE42*$BU42*(1+($BW42-1)*AE$33)*($D$30*$BV42+(1-$D$30)*AE$32),"") | AF78: =IFERROR(AF42*$BU42*(1+($BW42-1)*AF$33)*($D$30*$BV42+(1-$D$30)*AF$32),"")
A79: 20251128800098 | B79: CONT | C79: 4 | D79: 컨테이너선 4척 | AE79: =IFERROR(AE43*$BU43*(1+($BW43-1)*AE$33)*($D$30*$BV43+(1-$D$30)*AE$32),"") | AF79: =IFERROR(AF43*$BU43*(1+($BW43-1)*AF$33)*($D$30*$BV43+(1-$D$30)*AF$32),"") | AG79: =IFERROR(AG43*$BU43*(1+($BW43-1)*AG$33)*($D$30*$BV43+(1-$D$30)*AG$32),"") | AH79: =IFERROR(AH43*$BU43*(1+($BW43-1)*AH$33)*($D$30*$BV43+(1-$D$30)*AH$32),"") | AI79: =IFERROR(AI43*$BU43*(1+($BW43-1)*AI$33)*($D$30*$BV43+(1-$D$30)*AI$32),"") | AJ79: =IFERROR(AJ43*$BU43*(1+($BW43-1)*AJ$33)*($D$30*$BV43+(1-$D$30)*AJ$32),"") | AK79: =IFERROR(AK43*$BU43*(1+($BW43-1)*AK$33)*($D$30*$BV43+(1-$D$30)*AK$32),"") | AL79: =IFERROR(AL43*$BU43*(1+($BW43-1)*AL$33)*($D$30*$BV43+(1-$D$30)*AL$32),"") | ... AR79: =IFERROR(AR43*$BU43*(1+($BW43-1)*AR$33)*($D$30*$BV43+(1-$D$30)*AR$32),"")
A80: 20251202800041 | B80: VLCC | C80: 2 | D80: VLCC 2척 | AE80: =IFERROR(AE44*$BU44*(1+($BW44-1)*AE$33)*($D$30*$BV44+(1-$D$30)*AE$32),"") | AF80: =IFERROR(AF44*$BU44*(1+($BW44-1)*AF$33)*($D$30*$BV44+(1-$D$30)*AF$32),"") | AG80: =IFERROR(AG44*$BU44*(1+($BW44-1)*AG$33)*($D$30*$BV44+(1-$D$30)*AG$32),"") | AH80: =IFERROR(AH44*$BU44*(1+($BW44-1)*AH$33)*($D$30*$BV44+(1-$D$30)*AH$32),"") | AI80: =IFERROR(AI44*$BU44*(1+($BW44-1)*AI$33)*($D$30*$BV44+(1-$D$30)*AI$32),"") | AJ80: =IFERROR(AJ44*$BU44*(1+($BW44-1)*AJ$33)*($D$30*$BV44+(1-$D$30)*AJ$32),"") | AK80: =IFERROR(AK44*$BU44*(1+($BW44-1)*AK$33)*($D$30*$BV44+(1-$D$30)*AK$32),"") | AL80: =IFERROR(AL44*$BU44*(1+($BW44-1)*AL$33)*($D$30*$BV44+(1-$D$30)*AL$32),"") | ... AQ80: =IFERROR(AQ44*$BU44*(1+($BW44-1)*AQ$33)*($D$30*$BV44+(1-$D$30)*AQ$32),"")
A81: 20251219800049 | B81: LNGC | C81: 7 | D81: LNGC 7척 | AE81: =IFERROR(AE45*$BU45*(1+($BW45-1)*AE$33)*($D$30*$BV45+(1-$D$30)*AE$32),"") | AF81: =IFERROR(AF45*$BU45*(1+($BW45-1)*AF$33)*($D$30*$BV45+(1-$D$30)*AF$32),"") | AG81: =IFERROR(AG45*$BU45*(1+($BW45-1)*AG$33)*($D$30*$BV45+(1-$D$30)*AG$32),"") | AH81: =IFERROR(AH45*$BU45*(1+($BW45-1)*AH$33)*($D$30*$BV45+(1-$D$30)*AH$32),"") | AI81: =IFERROR(AI45*$BU45*(1+($BW45-1)*AI$33)*($D$30*$BV45+(1-$D$30)*AI$32),"") | AJ81: =IFERROR(AJ45*$BU45*(1+($BW45-1)*AJ$33)*($D$30*$BV45+(1-$D$30)*AJ$32),"") | AK81: =IFERROR(AK45*$BU45*(1+($BW45-1)*AK$33)*($D$30*$BV45+(1-$D$30)*AK$32),"") | AL81: =IFERROR(AL45*$BU45*(1+($BW45-1)*AL$33)*($D$30*$BV45+(1-$D$30)*AL$32),"") | ... AS81: =IFERROR(AS45*$BU45*(1+($BW45-1)*AS$33)*($D$30*$BV45+(1-$D$30)*AS$32),"")
A82: 20251223800047 | B82: OFFSH | D82: 신안우이해상풍력 발전소 설계·구매·시공(EPC) 계약 | AE82: =IFERROR(AE46*$BU46*(1+($BW46-1)*AE$33)*($D$30*$BV46+(1-$D$30)*AE$32),"") | AF82: =IFERROR(AF46*$BU46*(1+($BW46-1)*AF$33)*($D$30*$BV46+(1-$D$30)*AF$32),"") | AG82: =IFERROR(AG46*$BU46*(1+($BW46-1)*AG$33)*($D$30*$BV46+(1-$D$30)*AG$32),"") | AH82: =IFERROR(AH46*$BU46*(1+($BW46-1)*AH$33)*($D$30*$BV46+(1-$D$30)*AH$32),"") | AI82: =IFERROR(AI46*$BU46*(1+($BW46-1)*AI$33)*($D$30*$BV46+(1-$D$30)*AI$32),"") | AJ82: =IFERROR(AJ46*$BU46*(1+($BW46-1)*AJ$33)*($D$30*$BV46+(1-$D$30)*AJ$32),"") | AK82: =IFERROR(AK46*$BU46*(1+($BW46-1)*AK$33)*($D$30*$BV46+(1-$D$30)*AK$32),"") | AL82: =IFERROR(AL46*$BU46*(1+($BW46-1)*AL$33)*($D$30*$BV46+(1-$D$30)*AL$32),"") | ... AS82: =IFERROR(AS46*$BU46*(1+($BW46-1)*AS$33)*($D$30*$BV46+(1-$D$30)*AS$32),"")
A83: 20260115800042 | B83: VLCC | C83: 3 | D83: VLCC 3척 | AF83: =IFERROR(AF47*$BU47*(1+($BW47-1)*AF$33)*($D$30*$BV47+(1-$D$30)*AF$32),"") | AG83: =IFERROR(AG47*$BU47*(1+($BW47-1)*AG$33)*($D$30*$BV47+(1-$D$30)*AG$32),"") | AH83: =IFERROR(AH47*$BU47*(1+($BW47-1)*AH$33)*($D$30*$BV47+(1-$D$30)*AH$32),"") | AI83: =IFERROR(AI47*$BU47*(1+($BW47-1)*AI$33)*($D$30*$BV47+(1-$D$30)*AI$32),"") | AJ83: =IFERROR(AJ47*$BU47*(1+($BW47-1)*AJ$33)*($D$30*$BV47+(1-$D$30)*AJ$32),"") | AK83: =IFERROR(AK47*$BU47*(1+($BW47-1)*AK$33)*($D$30*$BV47+(1-$D$30)*AK$32),"") | AL83: =IFERROR(AL47*$BU47*(1+($BW47-1)*AL$33)*($D$30*$BV47+(1-$D$30)*AL$32),"") | AM83: =IFERROR(AM47*$BU47*(1+($BW47-1)*AM$33)*($D$30*$BV47+(1-$D$30)*AM$32),"") | ... AS83: =IFERROR(AS47*$BU47*(1+($BW47-1)*AS$33)*($D$30*$BV47+(1-$D$30)*AS$32),"")
A84: 20260121800115 | B84: LNGC | C84: 2 | D84: LNGC 2척 | AF84: =IFERROR(AF48*$BU48*(1+($BW48-1)*AF$33)*($D$30*$BV48+(1-$D$30)*AF$32),"") | AG84: =IFERROR(AG48*$BU48*(1+($BW48-1)*AG$33)*($D$30*$BV48+(1-$D$30)*AG$32),"") | AH84: =IFERROR(AH48*$BU48*(1+($BW48-1)*AH$33)*($D$30*$BV48+(1-$D$30)*AH$32),"") | AI84: =IFERROR(AI48*$BU48*(1+($BW48-1)*AI$33)*($D$30*$BV48+(1-$D$30)*AI$32),"") | AJ84: =IFERROR(AJ48*$BU48*(1+($BW48-1)*AJ$33)*($D$30*$BV48+(1-$D$30)*AJ$32),"") | AK84: =IFERROR(AK48*$BU48*(1+($BW48-1)*AK$33)*($D$30*$BV48+(1-$D$30)*AK$32),"") | AL84: =IFERROR(AL48*$BU48*(1+($BW48-1)*AL$33)*($D$30*$BV48+(1-$D$30)*AL$32),"") | AM84: =IFERROR(AM48*$BU48*(1+($BW48-1)*AM$33)*($D$30*$BV48+(1-$D$30)*AM$32),"") | ... AS84: =IFERROR(AS48*$BU48*(1+($BW48-1)*AS$33)*($D$30*$BV48+(1-$D$30)*AS$32),"")
A85: 20260206800258 | B85: OFFSH | C85: 1 | D85: 해상풍력발전기 설치선 1척 | AF85: =IFERROR(AF49*$BU49*(1+($BW49-1)*AF$33)*($D$30*$BV49+(1-$D$30)*AF$32),"") | AG85: =IFERROR(AG49*$BU49*(1+($BW49-1)*AG$33)*($D$30*$BV49+(1-$D$30)*AG$32),"") | AH85: =IFERROR(AH49*$BU49*(1+($BW49-1)*AH$33)*($D$30*$BV49+(1-$D$30)*AH$32),"") | AI85: =IFERROR(AI49*$BU49*(1+($BW49-1)*AI$33)*($D$30*$BV49+(1-$D$30)*AI$32),"") | AJ85: =IFERROR(AJ49*$BU49*(1+($BW49-1)*AJ$33)*($D$30*$BV49+(1-$D$30)*AJ$32),"") | AK85: =IFERROR(AK49*$BU49*(1+($BW49-1)*AK$33)*($D$30*$BV49+(1-$D$30)*AK$32),"") | AL85: =IFERROR(AL49*$BU49*(1+($BW49-1)*AL$33)*($D$30*$BV49+(1-$D$30)*AL$32),"") | AM85: =IFERROR(AM49*$BU49*(1+($BW49-1)*AM$33)*($D$30*$BV49+(1-$D$30)*AM$32),"") | ... AO85: =IFERROR(AO49*$BU49*(1+($BW49-1)*AO$33)*($D$30*$BV49+(1-$D$30)*AO$32),"")
A86: 20260220801130 | B86: LNGC | C86: 1 | D86: LNG 운반선 1척 | U86: =IFERROR(U50*$BU50*(1+($BW50-1)*U$33)*($D$30*$BV50+(1-$D$30)*U$32),"") | V86: =IFERROR(V50*$BU50*(1+($BW50-1)*V$33)*($D$30*$BV50+(1-$D$30)*V$32),"") | W86: =IFERROR(W50*$BU50*(1+($BW50-1)*W$33)*($D$30*$BV50+(1-$D$30)*W$32),"") | X86: =IFERROR(X50*$BU50*(1+($BW50-1)*X$33)*($D$30*$BV50+(1-$D$30)*X$32),"") | Y86: =IFERROR(Y50*$BU50*(1+($BW50-1)*Y$33)*($D$30*$BV50+(1-$D$30)*Y$32),"") | Z86: =IFERROR(Z50*$BU50*(1+($BW50-1)*Z$33)*($D$30*$BV50+(1-$D$30)*Z$32),"") | AA86: =IFERROR(AA50*$BU50*(1+($BW50-1)*AA$33)*($D$30*$BV50+(1-$D$30)*AA$32),"") | AB86: =IFERROR(AB50*$BU50*(1+($BW50-1)*AB$33)*($D$30*$BV50+(1-$D$30)*AB$32),"") | ... AL86: =IFERROR(AL50*$BU50*(1+($BW50-1)*AL$33)*($D$30*$BV50+(1-$D$30)*AL$32),"")
A87: 20260220801140 | B87: LNGC | C87: 1 | D87: LNG 운반선 1척 | T87: =IFERROR(T51*$BU51*(1+($BW51-1)*T$33)*($D$30*$BV51+(1-$D$30)*T$32),"") | U87: =IFERROR(U51*$BU51*(1+($BW51-1)*U$33)*($D$30*$BV51+(1-$D$30)*U$32),"") | V87: =IFERROR(V51*$BU51*(1+($BW51-1)*V$33)*($D$30*$BV51+(1-$D$30)*V$32),"") | W87: =IFERROR(W51*$BU51*(1+($BW51-1)*W$33)*($D$30*$BV51+(1-$D$30)*W$32),"") | X87: =IFERROR(X51*$BU51*(1+($BW51-1)*X$33)*($D$30*$BV51+(1-$D$30)*X$32),"") | Y87: =IFERROR(Y51*$BU51*(1+($BW51-1)*Y$33)*($D$30*$BV51+(1-$D$30)*Y$32),"") | Z87: =IFERROR(Z51*$BU51*(1+($BW51-1)*Z$33)*($D$30*$BV51+(1-$D$30)*Z$32),"") | AA87: =IFERROR(AA51*$BU51*(1+($BW51-1)*AA$33)*($D$30*$BV51+(1-$D$30)*AA$32),"") | ... AJ87: =IFERROR(AJ51*$BU51*(1+($BW51-1)*AJ$33)*($D$30*$BV51+(1-$D$30)*AJ$32),"")
A88: 20260325800201 | B88: VLCC | C88: 3 | D88: VLCC 3척 | AF88: =IFERROR(AF52*$BU52*(1+($BW52-1)*AF$33)*($D$30*$BV52+(1-$D$30)*AF$32),"") | AG88: =IFERROR(AG52*$BU52*(1+($BW52-1)*AG$33)*($D$30*$BV52+(1-$D$30)*AG$32),"") | AH88: =IFERROR(AH52*$BU52*(1+($BW52-1)*AH$33)*($D$30*$BV52+(1-$D$30)*AH$32),"") | AI88: =IFERROR(AI52*$BU52*(1+($BW52-1)*AI$33)*($D$30*$BV52+(1-$D$30)*AI$32),"") | AJ88: =IFERROR(AJ52*$BU52*(1+($BW52-1)*AJ$33)*($D$30*$BV52+(1-$D$30)*AJ$32),"") | AK88: =IFERROR(AK52*$BU52*(1+($BW52-1)*AK$33)*($D$30*$BV52+(1-$D$30)*AK$32),"") | AL88: =IFERROR(AL52*$BU52*(1+($BW52-1)*AL$33)*($D$30*$BV52+(1-$D$30)*AL$32),"") | AM88: =IFERROR(AM52*$BU52*(1+($BW52-1)*AM$33)*($D$30*$BV52+(1-$D$30)*AM$32),"") | ... AS88: =IFERROR(AS52*$BU52*(1+($BW52-1)*AS$33)*($D$30*$BV52+(1-$D$30)*AS$32),"")
A89: 20260331803529 | B89: NAVAL | C89: 3 | D89: 잠수함 3척 | E89: =IFERROR(E53*$BU53*(1+($BW53-1)*E$33)*($D$30*$BV53+(1-$D$30)*E$32),"") | F89: =IFERROR(F53*$BU53*(1+($BW53-1)*F$33)*($D$30*$BV53+(1-$D$30)*F$32),"") | G89: =IFERROR(G53*$BU53*(1+($BW53-1)*G$33)*($D$30*$BV53+(1-$D$30)*G$32),"") | H89: =IFERROR(H53*$BU53*(1+($BW53-1)*H$33)*($D$30*$BV53+(1-$D$30)*H$32),"") | I89: =IFERROR(I53*$BU53*(1+($BW53-1)*I$33)*($D$30*$BV53+(1-$D$30)*I$32),"") | J89: =IFERROR(J53*$BU53*(1+($BW53-1)*J$33)*($D$30*$BV53+(1-$D$30)*J$32),"") | K89: =IFERROR(K53*$BU53*(1+($BW53-1)*K$33)*($D$30*$BV53+(1-$D$30)*K$32),"") | L89: =IFERROR(L53*$BU53*(1+($BW53-1)*L$33)*($D$30*$BV53+(1-$D$30)*L$32),"") | ... U89: =IFERROR(U53*$BU53*(1+($BW53-1)*U$33)*($D$30*$BV53+(1-$D$30)*U$32),"")
A90: 20260408801023 | B90: VLGC | C90: 1 | D90: LPG 운반선 1척 | Y90: =IFERROR(Y54*$BU54*(1+($BW54-1)*Y$33)*($D$30*$BV54+(1-$D$30)*Y$32),"") | Z90: =IFERROR(Z54*$BU54*(1+($BW54-1)*Z$33)*($D$30*$BV54+(1-$D$30)*Z$32),"") | AA90: =IFERROR(AA54*$BU54*(1+($BW54-1)*AA$33)*($D$30*$BV54+(1-$D$30)*AA$32),"") | AB90: =IFERROR(AB54*$BU54*(1+($BW54-1)*AB$33)*($D$30*$BV54+(1-$D$30)*AB$32),"") | AC90: =IFERROR(AC54*$BU54*(1+($BW54-1)*AC$33)*($D$30*$BV54+(1-$D$30)*AC$32),"") | AD90: =IFERROR(AD54*$BU54*(1+($BW54-1)*AD$33)*($D$30*$BV54+(1-$D$30)*AD$32),"") | AE90: =IFERROR(AE54*$BU54*(1+($BW54-1)*AE$33)*($D$30*$BV54+(1-$D$30)*AE$32),"") | AF90: =IFERROR(AF54*$BU54*(1+($BW54-1)*AF$33)*($D$30*$BV54+(1-$D$30)*AF$32),"") | ... AH90: =IFERROR(AH54*$BU54*(1+($BW54-1)*AH$33)*($D$30*$BV54+(1-$D$30)*AH$32),"")
A91: 20260409800345 | B91: VLCC | C91: 2 | D91: VLCC 2척 | AG91: =IFERROR(AG55*$BU55*(1+($BW55-1)*AG$33)*($D$30*$BV55+(1-$D$30)*AG$32),"") | AH91: =IFERROR(AH55*$BU55*(1+($BW55-1)*AH$33)*($D$30*$BV55+(1-$D$30)*AH$32),"") | AI91: =IFERROR(AI55*$BU55*(1+($BW55-1)*AI$33)*($D$30*$BV55+(1-$D$30)*AI$32),"") | AJ91: =IFERROR(AJ55*$BU55*(1+($BW55-1)*AJ$33)*($D$30*$BV55+(1-$D$30)*AJ$32),"") | AK91: =IFERROR(AK55*$BU55*(1+($BW55-1)*AK$33)*($D$30*$BV55+(1-$D$30)*AK$32),"") | AL91: =IFERROR(AL55*$BU55*(1+($BW55-1)*AL$33)*($D$30*$BV55+(1-$D$30)*AL$32),"") | AM91: =IFERROR(AM55*$BU55*(1+($BW55-1)*AM$33)*($D$30*$BV55+(1-$D$30)*AM$32),"") | AN91: =IFERROR(AN55*$BU55*(1+($BW55-1)*AN$33)*($D$30*$BV55+(1-$D$30)*AN$32),"") | ... AV91: =IFERROR(AV55*$BU55*(1+($BW55-1)*AV$33)*($D$30*$BV55+(1-$D$30)*AV$32),"")
A92: 20260504800235 | B92: VLGC | C92: 3 | D92: VLAC 3척 | AG92: =IFERROR(AG56*$BU56*(1+($BW56-1)*AG$33)*($D$30*$BV56+(1-$D$30)*AG$32),"") | AH92: =IFERROR(AH56*$BU56*(1+($BW56-1)*AH$33)*($D$30*$BV56+(1-$D$30)*AH$32),"") | AI92: =IFERROR(AI56*$BU56*(1+($BW56-1)*AI$33)*($D$30*$BV56+(1-$D$30)*AI$32),"") | AJ92: =IFERROR(AJ56*$BU56*(1+($BW56-1)*AJ$33)*($D$30*$BV56+(1-$D$30)*AJ$32),"") | AK92: =IFERROR(AK56*$BU56*(1+($BW56-1)*AK$33)*($D$30*$BV56+(1-$D$30)*AK$32),"") | AL92: =IFERROR(AL56*$BU56*(1+($BW56-1)*AL$33)*($D$30*$BV56+(1-$D$30)*AL$32),"") | AM92: =IFERROR(AM56*$BU56*(1+($BW56-1)*AM$33)*($D$30*$BV56+(1-$D$30)*AM$32),"") | AN92: =IFERROR(AN56*$BU56*(1+($BW56-1)*AN$33)*($D$30*$BV56+(1-$D$30)*AN$32),"") | ... AV92: =IFERROR(AV56*$BU56*(1+($BW56-1)*AV$33)*($D$30*$BV56+(1-$D$30)*AV$32),"")
A93: 20260511800175 | B93: LNGC | C93: 1 | D93: LNGC 1척 | AG93: =IFERROR(AG57*$BU57*(1+($BW57-1)*AG$33)*($D$30*$BV57+(1-$D$30)*AG$32),"") | AH93: =IFERROR(AH57*$BU57*(1+($BW57-1)*AH$33)*($D$30*$BV57+(1-$D$30)*AH$32),"") | AI93: =IFERROR(AI57*$BU57*(1+($BW57-1)*AI$33)*($D$30*$BV57+(1-$D$30)*AI$32),"") | AJ93: =IFERROR(AJ57*$BU57*(1+($BW57-1)*AJ$33)*($D$30*$BV57+(1-$D$30)*AJ$32),"") | AK93: =IFERROR(AK57*$BU57*(1+($BW57-1)*AK$33)*($D$30*$BV57+(1-$D$30)*AK$32),"") | AL93: =IFERROR(AL57*$BU57*(1+($BW57-1)*AL$33)*($D$30*$BV57+(1-$D$30)*AL$32),"") | AM93: =IFERROR(AM57*$BU57*(1+($BW57-1)*AM$33)*($D$30*$BV57+(1-$D$30)*AM$32),"") | AN93: =IFERROR(AN57*$BU57*(1+($BW57-1)*AN$33)*($D$30*$BV57+(1-$D$30)*AN$32),"") | ... AS93: =IFERROR(AS57*$BU57*(1+($BW57-1)*AS$33)*($D$30*$BV57+(1-$D$30)*AS$32),"")
A94: 20260518800002 | B94: LNGC | C94: 2 | D94: LNGC 2척 | AG94: =IFERROR(AG58*$BU58*(1+($BW58-1)*AG$33)*($D$30*$BV58+(1-$D$30)*AG$32),"") | AH94: =IFERROR(AH58*$BU58*(1+($BW58-1)*AH$33)*($D$30*$BV58+(1-$D$30)*AH$32),"") | AI94: =IFERROR(AI58*$BU58*(1+($BW58-1)*AI$33)*($D$30*$BV58+(1-$D$30)*AI$32),"") | AJ94: =IFERROR(AJ58*$BU58*(1+($BW58-1)*AJ$33)*($D$30*$BV58+(1-$D$30)*AJ$32),"") | AK94: =IFERROR(AK58*$BU58*(1+($BW58-1)*AK$33)*($D$30*$BV58+(1-$D$30)*AK$32),"") | AL94: =IFERROR(AL58*$BU58*(1+($BW58-1)*AL$33)*($D$30*$BV58+(1-$D$30)*AL$32),"") | AM94: =IFERROR(AM58*$BU58*(1+($BW58-1)*AM$33)*($D$30*$BV58+(1-$D$30)*AM$32),"") | AN94: =IFERROR(AN58*$BU58*(1+($BW58-1)*AN$33)*($D$30*$BV58+(1-$D$30)*AN$32),"") | ... AS94: =IFERROR(AS58*$BU58*(1+($BW58-1)*AS$33)*($D$30*$BV58+(1-$D$30)*AS$32),"")
A95: 20260528800927 | B95: OTHER | D95: MCS Plant 구축 공사 | AB95: =IFERROR(AB59*$BU59*(1+($BW59-1)*AB$33)*($D$30*$BV59+(1-$D$30)*AB$32),"") | AC95: =IFERROR(AC59*$BU59*(1+($BW59-1)*AC$33)*($D$30*$BV59+(1-$D$30)*AC$32),"") | AD95: =IFERROR(AD59*$BU59*(1+($BW59-1)*AD$33)*($D$30*$BV59+(1-$D$30)*AD$32),"") | AE95: =IFERROR(AE59*$BU59*(1+($BW59-1)*AE$33)*($D$30*$BV59+(1-$D$30)*AE$32),"") | AF95: =IFERROR(AF59*$BU59*(1+($BW59-1)*AF$33)*($D$30*$BV59+(1-$D$30)*AF$32),"") | AG95: =IFERROR(AG59*$BU59*(1+($BW59-1)*AG$33)*($D$30*$BV59+(1-$D$30)*AG$32),"") | AH95: =IFERROR(AH59*$BU59*(1+($BW59-1)*AH$33)*($D$30*$BV59+(1-$D$30)*AH$32),"") | AI95: =IFERROR(AI59*$BU59*(1+($BW59-1)*AI$33)*($D$30*$BV59+(1-$D$30)*AI$32),"") | ... AN95: =IFERROR(AN59*$BU59*(1+($BW59-1)*AN$33)*($D$30*$BV59+(1-$D$30)*AN$32),"")
A96: 20260529800152 | B96: LNGC | C96: 1 | D96: LNGC 1척 | AG96: =IFERROR(AG60*$BU60*(1+($BW60-1)*AG$33)*($D$30*$BV60+(1-$D$30)*AG$32),"") | AH96: =IFERROR(AH60*$BU60*(1+($BW60-1)*AH$33)*($D$30*$BV60+(1-$D$30)*AH$32),"") | AI96: =IFERROR(AI60*$BU60*(1+($BW60-1)*AI$33)*($D$30*$BV60+(1-$D$30)*AI$32),"") | AJ96: =IFERROR(AJ60*$BU60*(1+($BW60-1)*AJ$33)*($D$30*$BV60+(1-$D$30)*AJ$32),"") | AK96: =IFERROR(AK60*$BU60*(1+($BW60-1)*AK$33)*($D$30*$BV60+(1-$D$30)*AK$32),"") | AL96: =IFERROR(AL60*$BU60*(1+($BW60-1)*AL$33)*($D$30*$BV60+(1-$D$30)*AL$32),"") | AM96: =IFERROR(AM60*$BU60*(1+($BW60-1)*AM$33)*($D$30*$BV60+(1-$D$30)*AM$32),"") | AN96: =IFERROR(AN60*$BU60*(1+($BW60-1)*AN$33)*($D$30*$BV60+(1-$D$30)*AN$32),"") | ... AT96: =IFERROR(AT60*$BU60*(1+($BW60-1)*AT$33)*($D$30*$BV60+(1-$D$30)*AT$32),"")
A97: 20260619800742 | B97: VLCC | C97: 4 | D97: VLCC 4척 | AG97: =IFERROR(AG61*$BU61*(1+($BW61-1)*AG$33)*($D$30*$BV61+(1-$D$30)*AG$32),"") | AH97: =IFERROR(AH61*$BU61*(1+($BW61-1)*AH$33)*($D$30*$BV61+(1-$D$30)*AH$32),"") | AI97: =IFERROR(AI61*$BU61*(1+($BW61-1)*AI$33)*($D$30*$BV61+(1-$D$30)*AI$32),"") | AJ97: =IFERROR(AJ61*$BU61*(1+($BW61-1)*AJ$33)*($D$30*$BV61+(1-$D$30)*AJ$32),"") | AK97: =IFERROR(AK61*$BU61*(1+($BW61-1)*AK$33)*($D$30*$BV61+(1-$D$30)*AK$32),"") | AL97: =IFERROR(AL61*$BU61*(1+($BW61-1)*AL$33)*($D$30*$BV61+(1-$D$30)*AL$32),"") | AM97: =IFERROR(AM61*$BU61*(1+($BW61-1)*AM$33)*($D$30*$BV61+(1-$D$30)*AM$32),"") | AN97: =IFERROR(AN61*$BU61*(1+($BW61-1)*AN$33)*($D$30*$BV61+(1-$D$30)*AN$32),"") | ... AV97: =IFERROR(AV61*$BU61*(1+($BW61-1)*AV$33)*($D$30*$BV61+(1-$D$30)*AV$32),"")
A98: 20260715800071 | B98: VLCC | C98: 2 | D98: VLCC 2척 | AH98: =IFERROR(AH62*$BU62*(1+($BW62-1)*AH$33)*($D$30*$BV62+(1-$D$30)*AH$32),"") | AI98: =IFERROR(AI62*$BU62*(1+($BW62-1)*AI$33)*($D$30*$BV62+(1-$D$30)*AI$32),"") | AJ98: =IFERROR(AJ62*$BU62*(1+($BW62-1)*AJ$33)*($D$30*$BV62+(1-$D$30)*AJ$32),"") | AK98: =IFERROR(AK62*$BU62*(1+($BW62-1)*AK$33)*($D$30*$BV62+(1-$D$30)*AK$32),"") | AL98: =IFERROR(AL62*$BU62*(1+($BW62-1)*AL$33)*($D$30*$BV62+(1-$D$30)*AL$32),"") | AM98: =IFERROR(AM62*$BU62*(1+($BW62-1)*AM$33)*($D$30*$BV62+(1-$D$30)*AM$32),"") | AN98: =IFERROR(AN62*$BU62*(1+($BW62-1)*AN$33)*($D$30*$BV62+(1-$D$30)*AN$32),"") | AO98: =IFERROR(AO62*$BU62*(1+($BW62-1)*AO$33)*($D$30*$BV62+(1-$D$30)*AO$32),"") | ... AV98: =IFERROR(AV62*$BU62*(1+($BW62-1)*AV$33)*($D$30*$BV62+(1-$D$30)*AV$32),"")
A99: 20260731800216 | B99: NAVAL | D99: 구축함(KDDX) 상세설계 및 선도함 건조 사업 | AH99: =IFERROR(AH63*$BU63*(1+($BW63-1)*AH$33)*($D$30*$BV63+(1-$D$30)*AH$32),"") | AI99: =IFERROR(AI63*$BU63*(1+($BW63-1)*AI$33)*($D$30*$BV63+(1-$D$30)*AI$32),"") | AJ99: =IFERROR(AJ63*$BU63*(1+($BW63-1)*AJ$33)*($D$30*$BV63+(1-$D$30)*AJ$32),"") | AK99: =IFERROR(AK63*$BU63*(1+($BW63-1)*AK$33)*($D$30*$BV63+(1-$D$30)*AK$32),"") | AL99: =IFERROR(AL63*$BU63*(1+($BW63-1)*AL$33)*($D$30*$BV63+(1-$D$30)*AL$32),"") | AM99: =IFERROR(AM63*$BU63*(1+($BW63-1)*AM$33)*($D$30*$BV63+(1-$D$30)*AM$32),"") | AN99: =IFERROR(AN63*$BU63*(1+($BW63-1)*AN$33)*($D$30*$BV63+(1-$D$30)*AN$32),"") | AO99: =IFERROR(AO63*$BU63*(1+($BW63-1)*AO$33)*($D$30*$BV63+(1-$D$30)*AO$32),"") | ... BE99: =IFERROR(BE63*$BU63*(1+($BW63-1)*BE$33)*($D$30*$BV63+(1-$D$30)*BE$32),"")
A100: 20260803800706 | B100: PC | D100: 여수에코에너지 LNG 집단에너지 사업(490MW) EPC 계약 | AH100: =IFERROR(AH64*$BU64*(1+($BW64-1)*AH$33)*($D$30*$BV64+(1-$D$30)*AH$32),"") | AI100: =IFERROR(AI64*$BU64*(1+($BW64-1)*AI$33)*($D$30*$BV64+(1-$D$30)*AI$32),"") | AJ100: =IFERROR(AJ64*$BU64*(1+($BW64-1)*AJ$33)*($D$30*$BV64+(1-$D$30)*AJ$32),"") | AK100: =IFERROR(AK64*$BU64*(1+($BW64-1)*AK$33)*($D$30*$BV64+(1-$D$30)*AK$32),"") | AL100: =IFERROR(AL64*$BU64*(1+($BW64-1)*AL$33)*($D$30*$BV64+(1-$D$30)*AL$32),"") | AM100: =IFERROR(AM64*$BU64*(1+($BW64-1)*AM$33)*($D$30*$BV64+(1-$D$30)*AM$32),"") | AN100: =IFERROR(AN64*$BU64*(1+($BW64-1)*AN$33)*($D$30*$BV64+(1-$D$30)*AN$32),"") | AO100: =IFERROR(AO64*$BU64*(1+($BW64-1)*AO$33)*($D$30*$BV64+(1-$D$30)*AO$32),"") | ... AT100: =IFERROR(AT64*$BU64*(1+($BW64-1)*AT$33)*($D$30*$BV64+(1-$D$30)*AT$32),"")
A101: 20260825800541 | B101: OTHER | C101: 1 | D101: FCS(필드제어설비) 1기 | P101: =IFERROR(P65*$BU65*(1+($BW65-1)*P$33)*($D$30*$BV65+(1-$D$30)*P$32),"") | Q101: =IFERROR(Q65*$BU65*(1+($BW65-1)*Q$33)*($D$30*$BV65+(1-$D$30)*Q$32),"") | R101: =IFERROR(R65*$BU65*(1+($BW65-1)*R$33)*($D$30*$BV65+(1-$D$30)*R$32),"") | S101: =IFERROR(S65*$BU65*(1+($BW65-1)*S$33)*($D$30*$BV65+(1-$D$30)*S$32),"") | T101: =IFERROR(T65*$BU65*(1+($BW65-1)*T$33)*($D$30*$BV65+(1-$D$30)*T$32),"") | U101: =IFERROR(U65*$BU65*(1+($BW65-1)*U$33)*($D$30*$BV65+(1-$D$30)*U$32),"") | V101: =IFERROR(V65*$BU65*(1+($BW65-1)*V$33)*($D$30*$BV65+(1-$D$30)*V$32),"") | W101: =IFERROR(W65*$BU65*(1+($BW65-1)*W$33)*($D$30*$BV65+(1-$D$30)*W$32),"") | ... AK101: =IFERROR(AK65*$BU65*(1+($BW65-1)*AK$33)*($D$30*$BV65+(1-$D$30)*AK$32),"")
A102: 20260901800108 | B102: VLGC | C102: 3 | D102: VLGC 3척 | AH102: =IFERROR(AH66*$BU66*(1+($BW66-1)*AH$33)*($D$30*$BV66+(1-$D$30)*AH$32),"") | AI102: =IFERROR(AI66*$BU66*(1+($BW66-1)*AI$33)*($D$30*$BV66+(1-$D$30)*AI$32),"") | AJ102: =IFERROR(AJ66*$BU66*(1+($BW66-1)*AJ$33)*($D$30*$BV66+(1-$D$30)*AJ$32),"") | AK102: =IFERROR(AK66*$BU66*(1+($BW66-1)*AK$33)*($D$30*$BV66+(1-$D$30)*AK$32),"") | AL102: =IFERROR(AL66*$BU66*(1+($BW66-1)*AL$33)*($D$30*$BV66+(1-$D$30)*AL$32),"") | AM102: =IFERROR(AM66*$BU66*(1+($BW66-1)*AM$33)*($D$30*$BV66+(1-$D$30)*AM$32),"") | AN102: =IFERROR(AN66*$BU66*(1+($BW66-1)*AN$33)*($D$30*$BV66+(1-$D$30)*AN$32),"") | AO102: =IFERROR(AO66*$BU66*(1+($BW66-1)*AO$33)*($D$30*$BV66+(1-$D$30)*AO$32),"") | ... AY102: =IFERROR(AY66*$BU66*(1+($BW66-1)*AY$33)*($D$30*$BV66+(1-$D$30)*AY$32),"")
