Workbook
Name 변수H: 변수!$C$1:$AO$1
Name 환율: 변수!$C$6:$AO$13
Name BS연결H: BS연결!$C$1:$AO$1
Name BS연결: BS연결!$C$5:$AO$100
Name BS별도H: BS별도!$C$1:$AO$1
Name BS별도: BS별도!$C$5:$AO$85
Name SUBQH: subQ!$A$1:$AO$1
Name subQ: subQ!$A$5:$AO$41

Sheet README
A1: 메디콕스(054180) 실적 모델 — ARGUS 한국조선
A2: 기준 분기 2026Q2 · 마지막 실적 2026Q2 · 생성 2026-10-11
A3: 모든 수치는 모델 산출값(DART 공개 재무제표 + 우리 추정)이다 — 목표주가·투자 추천 아님. 참고용 · 투자조언 아님.
A5: 시트
A6: 변수 가정 시계열. 환율 8행(ECB via frankfurter — L2 fx.json; 추정 분기 = 노란 가정), 추정 드라이버(노란 셀 = 모델값에서 역산한 가정, 바꾸면 재계산; 연녹 셀 = 3절 스칼라 참조 수식), 3절 스칼라 가정(세율·판관비율·지배주주비중·이자율·종가·PER 밴드·COE·외화 순노출·헤지비율)
A7: BS연결/BS별도 FnGuide 계정명 × 기간 값 덤프(백만원). 행1 분기라벨, 행4 YYYY.MM / YYYY.12A. 이름정의 BS연결H·BS연결(계정명 C열부터)
A8: subQ 분기 서브모델(억원 = 백만원/100). 확정 행: =IFERROR(VLOOKUP($D행,BS연결,MATCH(E$1,BS연결H,0),0)/100,"") 추정 행: 변수 시트 가정 셀 참조 수식. 외환손익·파생상품손익은 BS 계정 합·차, 기타금융손익은 잔차, OPM·EPS·BPS·PER·PBR 은 파생 수식
A9: SLS 선표(조선사만, sls json 있을 때): 요약 행(sls 저장값) + 계약별 스케줄(백만$) × (헤지비율 × 헤지환율 + (1−헤지비율) × 건조시점 환율[변수 원/달러(평균)]) → 원화 수식 블록 → 합계 행이 subQ 매출조선에 연결
A10: 시나리오 신규수주 보수/기준/낙관(forecast_panel 패널, 모델에 scenarios 가 있을 때만): 매출액·영업이익 = subQ 기준값 ± (시나리오 신규 − base 신규) × OPM. base 만 subQ 행에 포함, 나머지는 합산 안 함
A11: 분기/연간예상 subQ 를 이름(A열 key)으로 VLOOKUP 한 보고서 표(억원)
A12: TP PER 밴드 × 12M fwd EPS, PBR = ROE/COE × BPS — 모델 산출값 구간, 목표주가·추천 아님
A13: 외화 환율 QoQ, 외화 순노출 × Δ기말환율 → 환관련손익 추정
... A34: 백테스트: {"freeze": "2025Q2", "horizon": 4, "revenue_wape_pct": 32.3, "op_wape_pct": 58.4, "n": 4, "note": "단일 회사 4분기 — 통계 아님", "driver_at_freeze": "customer_yard_revenue_weighted", "selection_oos_at_freeze": {"freeze": "2024Q2", "n": 4, "wape_link": 4.2, "wape_trend": 9.9, "adopted": true, "decision": "adopted"}, "frozen_inputs": "fin(연결/별도)·고객 조선사 모델·지주 자회사 모델은 2025Q2 까지의 분기만; 선표는 체결일 ≤ 2025Q2 말일 계약(원장 최신 금액·코호트 등급, 환산 없음); 잔고는 yards_cache 2025Q2; 시세·환율 forward·prices·forecast_panel 신규수주 미사용. 고객 가중치(suppliers.json 언급 비중)와 합병 체인링크는 현재 지식; 고객 연동 채택은 동결 모델 안에서도 자기 la−4분기 OOS 규칙(selection_oos_at_freeze)", "detail": [{"q": "2025Q3", "rev_pred": 87.78, "rev_act": 66.85, "op_pred": -17.56, "op_act": -9.23}, {"q": "2025Q4", "rev_pred": 92.29, "rev_act": 69.81, "op_pred": -18.46, "op_act": -13.47}, {"q": "2026Q1", "rev_pred": 77.47, "rev_act": 63.29, "op_pred": -15.49, "op_act": -10.33}, {"q": "2026Q2", "rev_pred": 92.3, "rev_act": 64.43, "op_pred": -18.46, "op_act": -11.14}]}

Sheet 변수
C1: 이름: 변수H | E1: 4Q21 | F1: 2021 | G1: 1Q22 | H1: 2Q22 | I1: 3Q22 | J1: 4Q22 | K1: 2022 | L1: 1Q23 | M1: 2Q23 | N1: 3Q23 | O1: 4Q23 | P1: 2023 | Q1: 1Q24 | R1: 2Q24 | S1: 3Q24 | T1: 4Q24 | U1: 2024 | V1: 1Q25 | W1: 2Q25 | X1: 3Q25 | Y1: 4Q25 | Z1: 2025 | AA1: 1Q26 | AB1: 2Q26 | AC1: 3Q26 | AD1: 4Q26 | AE1: 2026 | AF1: 1Q27 | AG1: 2Q27 | AH1: 3Q27 | AI1: 4Q27 | AJ1: 2027 | AK1: 1Q28 | AL1: 2Q28 | AM1: 3Q28 | AN1: 4Q28 | AO1: 2028
A2: 가정 시계열 — 노란 셀은 추정 가정(모델값에서 역산), 연녹 셀은 3절 스칼라 참조 수식. 바꾸면 subQ·분기·연간예상·TP·시나리오가 재계산됩니다.
E3: 1 | F3: 2 | G3: 3 | H3: 4 | I3: 5 | J3: 6 | K3: 7 | L3: 8 | M3: 9 | N3: 10 | O3: 11 | P3: 12 | Q3: 13 | R3: 14 | S3: 15 | T3: 16 | U3: 17 | V3: 18 | W3: 19 | X3: 20 | Y3: 21 | Z3: 22 | AA3: 23 | AB3: 24 | AC3: 25 | AD3: 26 | AE3: 27 | AF3: 28 | AG3: 29 | AH3: 30 | AI3: 31 | AJ3: 32 | AK3: 33 | AL3: 34 | AM3: 35 | AN3: 36 | AO3: 37
E4: 2021.12 | F4: 2021.12A | G4: 2022.03 | H4: 2022.06 | I4: 2022.09 | J4: 2022.12 | K4: 2022.12A | L4: 2023.03 | M4: 2023.06 | N4: 2023.09 | O4: 2023.12 | P4: 2023.12A | Q4: 2024.03 | R4: 2024.06 | S4: 2024.09 | T4: 2024.12 | U4: 2024.12A | V4: 2025.03 | W4: 2025.06 | X4: 2025.09 | Y4: 2025.12 | Z4: 2025.12A | AA4: 2026.03 | AB4: 2026.06 | AC4: 2026.09 | AD4: 2026.12 | AE4: 2026.12A | AF4: 2027.03 | AG4: 2027.06 | AH4: 2027.09 | AI4: 2027.12 | AJ4: 2027.12A | AK4: 2028.03 | AL4: 2028.06 | AM4: 2028.09 | AN4: 2028.12 | AO4: 2028.12A
B5: 1. FX | C5: 이름: 환율
A6: USDKRW_avg | C6: 원/달러(평균) | E6: 1183.5 | F6: 1145.51 | G6: 1205.78 | H6: 1262.09 | I6: 1341.93 | J6: 1360.12 | K6: 1292.98 | L6: 1276.95 | M6: 1315.69 | N6: 1313.62 | O6: 1322.01 | P6: 1306.85 | Q6: 1330.14 | R6: 1371.28 | S6: 1356.22 | T6: 1396.3 | U6: 1363.53 | V6: 1452.28 | W6: 1398.52 | X6: 1386.95 | Y6: 1449.19 | Z6: 1421.52 | AA6: 1466.12 | AB6: 1501.75 | AC6: 1418.75 | AD6: 1345.14 | AE6: 1457.21 | AF6: 1341.49 | AG6: 1341.49 | AH6: 1341.49 | AI6: 1341.49 | AK6: 1341.49 | AL6: 1341.49 | AM6: 1341.49 | AN6: 1341.49
A7: USDKRW_end | C7: 원/달러(기말) | E7: 1188.75 | F7: 1188.75 | G7: 1213.74 | H7: 1301.24 | I7: 1436.9 | J7: 1260.16 | K7: 1260.16 | L7: 1305.99 | M7: 1321.44 | N7: 1345.35 | O7: 1297.43 | P7: 1297.43 | Q7: 1349.25 | R7: 1377.73 | S7: 1312.17 | T7: 1474.78 | U7: 1474.78 | V7: 1474.54 | W7: 1355.13 | X7: 1403.67 | Y7: 1444.2 | Z7: 1444.2 | AA7: 1524.8 | AB7: 1550.89 | AC7: 1355.4 | AD7: 1341.49 | AE7: 1341.49 | AF7: 1341.49 | AG7: 1341.49 | AH7: 1341.49 | AI7: 1341.49 | AK7: 1341.49 | AL7: 1341.49 | AM7: 1341.49 | AN7: 1341.49
A8: JPY100KRW_avg | C8: 원/100Y(평균) | E8: 1041.02 | F8: 1042.74 | G8: 1036.79 | H8: 972.23 | I8: 970.61 | J8: 961.03 | K8: 985.1 | L8: 964.89 | M8: 957.36 | N8: 909 | O8: 893.22 | P8: 931.11 | Q8: 896.29 | R8: 880.14 | S8: 909.35 | T8: 917.25 | U8: 900.92 | V8: 952.59 | W8: 967.92 | X8: 940.32 | Y8: 940.77 | Z8: 950.17 | AA8: 934.39 | AB8: 942.16 | AC8: 890.41 | AD8: 850.79 | AE8: 919.21 | AF8: 847.7 | AG8: 847.7 | AH8: 847.7 | AI8: 847.7 | AK8: 847.7 | AL8: 847.7 | AM8: 847.7 | AN8: 847.7
A9: JPY100KRW_end | C9: 원/100Y(기말) | E9: 1032.62 | F9: 1032.62 | G9: 996.83 | H9: 954.9 | I9: 993.29 | J9: 955.54 | K9: 955.54 | L9: 980.62 | M9: 913.67 | N9: 901.47 | O9: 917.04 | P9: 917.04 | Q9: 892.42 | R9: 857.76 | S9: 919.21 | T9: 939.65 | U9: 939.65 | V9: 986.84 | W9: 938.85 | X9: 948.49 | Y9: 921.81 | Z9: 921.81 | AA9: 955.99 | AB9: 954.75 | AC9: 863.31 | AD9: 847.7 | AE9: 847.7 | AF9: 847.7 | AG9: 847.7 | AH9: 847.7 | AI9: 847.7 | AK9: 847.7 | AL9: 847.7 | AM9: 847.7 | AN9: 847.7
A10: EURKRW_avg | C10: W/Euro(평균) | E10: 1353.32 | F10: 1354.06 | G10: 1352.29 | H10: 1343.31 | I10: 1350.63 | J10: 1386.07 | K10: 1358.07 | L10: 1369.93 | M10: 1432.41 | N10: 1429.41 | O10: 1420.91 | P10: 1412.88 | Q10: 1444.21 | R10: 1476.42 | S10: 1489.3 | T10: 1490.78 | U10: 1475.4 | V10: 1528.33 | W10: 1585.13 | X10: 1620.04 | Y10: 1686.02 | Z10: 1605.45 | AA10: 1715.47 | AB10: 1746.09 | AC10: 1631.97 | AD10: 1509.74 | AE10: 1689.95 | AF10: 1503.27 | AG10: 1503.27 | AH10: 1503.27 | AI10: 1503.27 | AK10: 1503.27 | AL10: 1503.27 | AM10: 1503.27 | AN10: 1503.27
A11: EURKRW_end | C11: W/Euro(기말) | E11: 1346.38 | F11: 1346.38 | G11: 1347.37 | H11: 1351.6 | I11: 1400.62 | J11: 1344.08 | K11: 1344.08 | L11: 1420.26 | M11: 1435.88 | N11: 1425.26 | O11: 1433.66 | P11: 1433.66 | Q11: 1458.68 | R11: 1474.86 | S11: 1469.1 | T11: 1532.14 | U11: 1532.14 | V11: 1594.72 | W11: 1588.22 | X11: 1648.04 | Y11: 1696.94 | Z11: 1696.94 | AA11: 1753.21 | AB11: 1767.09 | AC11: 1539.06 | AD11: 1503.27 | AE11: 1503.27 | AF11: 1503.27 | AG11: 1503.27 | AH11: 1503.27 | AI11: 1503.27 | AK11: 1503.27 | AL11: 1503.27 | AM11: 1503.27 | AN11: 1503.27
A12: CNYKRW_avg | C12: 원/중국원(평균) | E12: 185.14 | F12: 177.65 | G12: 189.93 | H12: 190.76 | I12: 195.79 | J12: 191.09 | K12: 191.93 | L12: 186.59 | M12: 187.45 | N12: 181.28 | O12: 182.86 | P12: 184.52 | Q12: 185.04 | R12: 189.35 | S12: 189.24 | T12: 194.24 | U12: 189.49 | V12: 199.63 | W12: 193.41 | X12: 193.79 | Y12: 204.38 | Z12: 197.8 | AA12: 211.75 | AB12: 220.8 | AC12: 210.43 | AD12: 200.69 | AE12: 213.75 | AF12: 200.46 | AG12: 200.46 | AH12: 200.46 | AI12: 200.46 | AK12: 200.46 | AL12: 200.46 | AM12: 200.46 | AN12: 200.46
A13: CNYKRW_end | C13: 원/중국원(기말) | E13: 187.13 | F13: 187.13 | G13: 191.38 | H13: 194.13 | I13: 201.92 | J13: 182.67 | K13: 182.67 | L13: 189.97 | M13: 181.8 | N13: 184.26 | O13: 182.61 | P13: 182.61 | Q13: 186.66 | R13: 189.7 | S13: 187.12 | T13: 202.04 | U13: 202.04 | V13: 203.3 | W13: 189.14 | X13: 197.16 | Y13: 206.28 | Z13: 206.28 | AA13: 220.97 | AB13: 228.56 | AC13: 202.16 | AD13: 200.46 | AE13: 200.46 | AF13: 200.46 | AG13: 200.46 | AH13: 200.46 | AI13: 200.46 | AK13: 200.46 | AL13: 200.46 | AM13: 200.46 | AN13: 200.46
B14: 1b. 종가
A15: price_close_end | C15: 종가(기말) | E15: 74625 | G15: 64755 | H15: 40620 | I15: 79965 | J15: 50625 | L15: 22425 | M15: 21225 | N15: 13770 | O15: 16575 | Q15: 11550 | R15: 7860 | S15: 6165 | T15: 4800 | V15: 4155 | W15: 2220 | X15: 2295
A16: price_high | C16: 종가(최고) | E16: 99282 | G16: 80099 | H16: 71010 | I16: 112260 | J16: 85980 | L16: 52050 | M16: 33150 | N16: 32400 | O16: 23400 | Q16: 16980 | R16: 11925 | S16: 12690 | T16: 7650 | V16: 6195 | W16: 5355 | X16: 2835
A17: price_low | C17: 종가(최저) | E17: 67006 | G17: 57975 | H17: 38355 | I17: 40320 | J17: 44925 | L17: 18450 | M17: 19620 | N17: 13485 | O17: 9750 | Q17: 10275 | R17: 6255 | S17: 6060 | T17: 4035 | V17: 3240 | W17: 1545 | X17: 2235
A18: price_avg | C18: 종가(평균) | E18: 77024.5 | G18: 64962.7 | H18: 54767.9 | I18: 70696.4 | J18: 62443.5 | L18: 28652.2 | M18: 24994.4 | N18: 21750.5 | O18: 15252.2 | Q18: 12587.2 | R18: 9094.2 | S18: 8530.6 | T18: 5222.5 | V18: 4258.2 | W18: 3177 | X18: 2430
B20: 2. 추정 드라이버 | C20: 실적 열 = subQ 실현값(수식), 추정 열 = 가정(노란 = 모델값 역산, 연녹 = 3절 스칼라 참조)
A21: drv:매출액 | B21: yoy | C21: 매출액 YoY | J21: =IFERROR(subQ!J5/subQ!E5-1,"") | L21: =IFERROR(subQ!L5/subQ!G5-1,"") | M21: =IFERROR(subQ!M5/subQ!H5-1,"") | N21: =IFERROR(subQ!N5/subQ!I5-1,"") | O21: =IFERROR(subQ!O5/subQ!J5-1,"") | Q21: =IFERROR(subQ!Q5/subQ!L5-1,"") | R21: =IFERROR(subQ!R5/subQ!M5-1,"") | S21: =IFERROR(subQ!S5/subQ!N5-1,"") | T21: =IFERROR(subQ!T5/subQ!O5-1,"") | V21: =IFERROR(subQ!V5/subQ!Q5-1,"") | W21: =IFERROR(subQ!W5/subQ!R5-1,"") | X21: =IFERROR(subQ!X5/subQ!S5-1,"") | Y21: =IFERROR(subQ!Y5/subQ!T5-1,"") | AA21: =IFERROR(subQ!AA5/subQ!V5-1,"") | AB21: =IFERROR(subQ!AB5/subQ!W5-1,"") | AC21: -0.12671725 | AD21: -0.12672513 | AF21: -0.12668102 | AG21: -0.1268097 | AH21: -0.063377869 | AI21: -0.06332021 | AK21: -0.063506423 | AL21: -0.06327764 | AM21: -0.031638625 | AN21: -0.031698774
A22: drv:판관비 | B22: ratio | C22: 판관비율(/매출) | E22: =IFERROR(subQ!E8/subQ!E5,"") | F22: =IFERROR(subQ!F8/subQ!F5,"") | G22: =IFERROR(subQ!G8/subQ!G5,"") | H22: =IFERROR(subQ!H8/subQ!H5,"") | I22: =IFERROR(subQ!I8/subQ!I5,"") | J22: =IFERROR(subQ!J8/subQ!J5,"") | K22: =IFERROR(subQ!K8/subQ!K5,"") | L22: =IFERROR(subQ!L8/subQ!L5,"") | ... AB22: =IFERROR(subQ!AB8/subQ!AB5,"") | AC22: =$D$51 | AD22: =$D$51 | AE22: =IFERROR(subQ!AE8/subQ!AE5,"") | AF22: =$D$51 | AG22: =$D$51 | AH22: =$D$51 | AI22: =$D$51 | AJ22: =IFERROR(subQ!AJ8/subQ!AJ5,"") | AK22: =$D$51 | AL22: =$D$51 | AM22: =$D$51 | AN22: =$D$51 | AO22: =IFERROR(subQ!AO8/subQ!AO5,"")
A23: drv:영업이익 | B23: ratio | C23: 영업이익률(OPM) | E23: =IFERROR(subQ!E9/subQ!E5,"") | F23: =IFERROR(subQ!F9/subQ!F5,"") | G23: =IFERROR(subQ!G9/subQ!G5,"") | H23: =IFERROR(subQ!H9/subQ!H5,"") | I23: =IFERROR(subQ!I9/subQ!I5,"") | J23: =IFERROR(subQ!J9/subQ!J5,"") | K23: =IFERROR(subQ!K9/subQ!K5,"") | L23: =IFERROR(subQ!L9/subQ!L5,"") | ... AB23: =IFERROR(subQ!AB9/subQ!AB5,"") | AC23: -0.19116136 | AD23: -0.19110892 | AE23: =IFERROR(subQ!AE9/subQ!AE5,"") | AF23: -0.19124299 | AG23: -0.19125489 | AH23: -0.19111192 | AI23: -0.19124343 | AJ23: =IFERROR(subQ!AJ9/subQ!AJ5,"") | AK23: -0.19126739 | AL23: -0.19127135 | AM23: -0.1911237 | AN23: -0.19117381 | AO23: =IFERROR(subQ!AO9/subQ!AO5,"")
A24: drv:파생상품손익 | B24: abs | C24: 파생상품손익 (가정, 억원) | E24: =subQ!E13 | F24: =subQ!F13 | G24: =subQ!G13 | H24: =subQ!H13 | I24: =subQ!I13 | J24: =subQ!J13 | K24: =subQ!K13 | L24: =subQ!L13 | ... AB24: =subQ!AB13 | AC24: 0 | AD24: 0 | AE24: =subQ!AE13 | AF24: 0 | AG24: 0 | AH24: 0 | AI24: 0 | AJ24: =subQ!AJ13 | AK24: 0 | AL24: 0 | AM24: 0 | AN24: 0 | AO24: =subQ!AO13
A25: drv:기타영업외손익 | B25: abs | C25: 기타영업외손익 (가정, 억원) | E25: =subQ!E14 | F25: =subQ!F14 | G25: =subQ!G14 | H25: =subQ!H14 | I25: =subQ!I14 | J25: =subQ!J14 | K25: =subQ!K14 | L25: =subQ!L14 | ... AB25: =subQ!AB14 | AC25: 0 | AD25: 0 | AE25: =subQ!AE14 | AF25: 0 | AG25: 0 | AH25: 0 | AI25: 0 | AJ25: =subQ!AJ14 | AK25: 0 | AL25: 0 | AM25: 0 | AN25: 0 | AO25: =subQ!AO14
A26: drv:지분법손익 | B26: abs | C26: 지분법손익 (가정, 억원) | E26: =subQ!E15 | F26: =subQ!F15 | G26: =subQ!G15 | H26: =subQ!H15 | I26: =subQ!I15 | J26: =subQ!J15 | K26: =subQ!K15 | L26: =subQ!L15 | ... AB26: =subQ!AB15 | AC26: 1.71 | AD26: 1.71 | AE26: =subQ!AE15 | AF26: 1.71 | AG26: 1.71 | AH26: 1.71 | AI26: 1.71 | AJ26: =subQ!AJ15 | AK26: 1.71 | AL26: 1.71 | AM26: 1.71 | AN26: 1.71 | AO26: =subQ!AO15
A27: drv:법인세비용 | B27: ratio | C27: 법인세율(/세전) | E27: =IFERROR(subQ!E17/subQ!E16,"") | F27: =IFERROR(subQ!F17/subQ!F16,"") | G27: =IFERROR(subQ!G17/subQ!G16,"") | H27: =IFERROR(subQ!H17/subQ!H16,"") | I27: =IFERROR(subQ!I17/subQ!I16,"") | J27: =IFERROR(subQ!J17/subQ!J16,"") | K27: =IFERROR(subQ!K17/subQ!K16,"") | L27: =IFERROR(subQ!L17/subQ!L16,"") | ... AB27: =IFERROR(subQ!AB17/subQ!AB16,"") | AC27: 0 | AD27: 0 | AE27: =IFERROR(subQ!AE17/subQ!AE16,"") | AF27: 0 | AG27: 0 | AH27: 0 | AI27: 0 | AJ27: =IFERROR(subQ!AJ17/subQ!AJ16,"") | AK27: 0 | AL27: 0 | AM27: 0 | AN27: 0 | AO27: =IFERROR(subQ!AO17/subQ!AO16,"")
A28: drv:지배주주순이익 | B28: ratio | C28: 지배주주 비중(/당기순이익) | E28: =IFERROR(subQ!E19/subQ!E18,"") | F28: =IFERROR(subQ!F19/subQ!F18,"") | G28: =IFERROR(subQ!G19/subQ!G18,"") | H28: =IFERROR(subQ!H19/subQ!H18,"") | I28: =IFERROR(subQ!I19/subQ!I18,"") | J28: =IFERROR(subQ!J19/subQ!J18,"") | K28: =IFERROR(subQ!K19/subQ!K18,"") | L28: =IFERROR(subQ!L19/subQ!L18,"") | ... AB28: =IFERROR(subQ!AB19/subQ!AB18,"") | AC28: =$D$52 | AD28: =$D$52 | AE28: =IFERROR(subQ!AE19/subQ!AE18,"") | AF28: =$D$52 | AG28: =$D$52 | AH28: =$D$52 | AI28: =$D$52 | AJ28: =IFERROR(subQ!AJ19/subQ!AJ18,"") | AK28: =$D$52 | AL28: =$D$52 | AM28: =$D$52 | AN28: =$D$52 | AO28: =IFERROR(subQ!AO19/subQ!AO18,"")
A29: drv:중단사업이익 | B29: abs | C29: 중단사업이익 (가정, 억원) | E29: =subQ!E20 | F29: =subQ!F20 | G29: =subQ!G20 | H29: =subQ!H20 | I29: =subQ!I20 | J29: =subQ!J20 | K29: =subQ!K20 | L29: =subQ!L20 | ... AB29: =subQ!AB20 | AE29: =subQ!AE20 | AJ29: =subQ!AJ20 | AO29: =subQ!AO20
A30: drv:부채총계 | B30: qoq | C30: 부채총계 QoQ | G30: =IFERROR(subQ!G22/subQ!E22-1,"") | H30: =IFERROR(subQ!H22/subQ!G22-1,"") | I30: =IFERROR(subQ!I22/subQ!H22-1,"") | J30: =IFERROR(subQ!J22/subQ!I22-1,"") | L30: =IFERROR(subQ!L22/subQ!J22-1,"") | M30: =IFERROR(subQ!M22/subQ!L22-1,"") | N30: =IFERROR(subQ!N22/subQ!M22-1,"") | O30: =IFERROR(subQ!O22/subQ!N22-1,"") | Q30: =IFERROR(subQ!Q22/subQ!O22-1,"") | R30: =IFERROR(subQ!R22/subQ!Q22-1,"") | S30: =IFERROR(subQ!S22/subQ!R22-1,"") | T30: =IFERROR(subQ!T22/subQ!S22-1,"") | V30: =IFERROR(subQ!V22/subQ!T22-1,"") | W30: =IFERROR(subQ!W22/subQ!V22-1,"") | X30: =IFERROR(subQ!X22/subQ!W22-1,"") | Y30: =IFERROR(subQ!Y22/subQ!X22-1,"") | AA30: =IFERROR(subQ!AA22/subQ!Y22-1,"") | AB30: =IFERROR(subQ!AB22/subQ!AA22-1,"") | AC30: -1.8154e-05 | AD30: 0 | AF30: 0 | AG30: 0 | AH30: 0 | AI30: 0 | AK30: 0 | AL30: 0 | AM30: 0 | AN30: 0
A31: drv:자본총계 | B31: roll | C31: 자본총계 기타변동(배당 등, 억원) | G31: =IFERROR(subQ!E23+subQ!G18-subQ!G23,"") | H31: =IFERROR(subQ!G23+subQ!H18-subQ!H23,"") | I31: =IFERROR(subQ!H23+subQ!I18-subQ!I23,"") | J31: =IFERROR(subQ!I23+subQ!J18-subQ!J23,"") | L31: =IFERROR(subQ!J23+subQ!L18-subQ!L23,"") | M31: =IFERROR(subQ!L23+subQ!M18-subQ!M23,"") | N31: =IFERROR(subQ!M23+subQ!N18-subQ!N23,"") | O31: =IFERROR(subQ!N23+subQ!O18-subQ!O23,"") | Q31: =IFERROR(subQ!O23+subQ!Q18-subQ!Q23,"") | R31: =IFERROR(subQ!Q23+subQ!R18-subQ!R23,"") | S31: =IFERROR(subQ!R23+subQ!S18-subQ!S23,"") | T31: =IFERROR(subQ!S23+subQ!T18-subQ!T23,"") | V31: =IFERROR(subQ!T23+subQ!V18-subQ!V23,"") | W31: =IFERROR(subQ!V23+subQ!W18-subQ!W23,"") | X31: =IFERROR(subQ!W23+subQ!X18-subQ!X23,"") | Y31: =IFERROR(subQ!X23+subQ!Y18-subQ!Y23,"") | AA31: =IFERROR(subQ!Y23+subQ!AA18-subQ!AA23,"") | AB31: =IFERROR(subQ!AA23+subQ!AB18-subQ!AB23,"") | AC31: 0.006608144 | AD31: 0.005593092 | AF31: -0.005400047 | AG31: 0.003723751 | AH31: -0.000524779 | AI31: -0.00277102 | AK31: -0.001340295 | AL31: -0.000319556 | AM31: -0.002565808 | AN31: 0.003396439
A32: drv:지배주주지분 | B32: roll | C32: 지배주주지분 기타변동(배당 등, 억원) | G32: =IFERROR(subQ!E24+subQ!G19-subQ!G24,"") | H32: =IFERROR(subQ!G24+subQ!H19-subQ!H24,"") | I32: =IFERROR(subQ!H24+subQ!I19-subQ!I24,"") | J32: =IFERROR(subQ!I24+subQ!J19-subQ!J24,"") | L32: =IFERROR(subQ!J24+subQ!L19-subQ!L24,"") | M32: =IFERROR(subQ!L24+subQ!M19-subQ!M24,"") | N32: =IFERROR(subQ!M24+subQ!N19-subQ!N24,"") | O32: =IFERROR(subQ!N24+subQ!O19-subQ!O24,"") | Q32: =IFERROR(subQ!O24+subQ!Q19-subQ!Q24,"") | R32: =IFERROR(subQ!Q24+subQ!R19-subQ!R24,"") | S32: =IFERROR(subQ!R24+subQ!S19-subQ!S24,"") | T32: =IFERROR(subQ!S24+subQ!T19-subQ!T24,"") | V32: =IFERROR(subQ!T24+subQ!V19-subQ!V24,"") | W32: =IFERROR(subQ!V24+subQ!W19-subQ!W24,"") | X32: =IFERROR(subQ!W24+subQ!X19-subQ!X24,"") | Y32: =IFERROR(subQ!X24+subQ!Y19-subQ!Y24,"") | AA32: =IFERROR(subQ!Y24+subQ!AA19-subQ!AA24,"") | AB32: =IFERROR(subQ!AA24+subQ!AB19-subQ!AB24,"") | AC32: 0.006608144 | AD32: 0.005593092 | AF32: -0.005400047 | AG32: 0.003723751 | AH32: -0.000524779 | AI32: -0.00277102 | AK32: -0.001340295 | AL32: -0.000319556 | AM32: -0.002565808 | AN32: 0.003396439
A33: drv:총차입금 | B33: qoq | C33: 총차입금 QoQ | G33: =IFERROR(subQ!G25/subQ!E25-1,"") | H33: =IFERROR(subQ!H25/subQ!G25-1,"") | I33: =IFERROR(subQ!I25/subQ!H25-1,"") | J33: =IFERROR(subQ!J25/subQ!I25-1,"") | L33: =IFERROR(subQ!L25/subQ!J25-1,"") | M33: =IFERROR(subQ!M25/subQ!L25-1,"") | N33: =IFERROR(subQ!N25/subQ!M25-1,"") | O33: =IFERROR(subQ!O25/subQ!N25-1,"") | Q33: =IFERROR(subQ!Q25/subQ!O25-1,"") | R33: =IFERROR(subQ!R25/subQ!Q25-1,"") | S33: =IFERROR(subQ!S25/subQ!R25-1,"") | T33: =IFERROR(subQ!T25/subQ!S25-1,"") | V33: =IFERROR(subQ!V25/subQ!T25-1,"") | W33: =IFERROR(subQ!W25/subQ!V25-1,"") | X33: =IFERROR(subQ!X25/subQ!W25-1,"") | Y33: =IFERROR(subQ!Y25/subQ!X25-1,"") | AA33: =IFERROR(subQ!AA25/subQ!Y25-1,"") | AB33: =IFERROR(subQ!AB25/subQ!AA25-1,"") | AC33: 4.5884e-05 | AD33: 0 | AF33: 0 | AG33: 0 | AH33: 0 | AI33: 0 | AK33: 0 | AL33: 0 | AM33: 0 | AN33: 0
A34: drv:순차입금 | B34: qoq | C34: 순차입금 QoQ | G34: =IFERROR(subQ!G26/subQ!E26-1,"") | H34: =IFERROR(subQ!H26/subQ!G26-1,"") | I34: =IFERROR(subQ!I26/subQ!H26-1,"") | J34: =IFERROR(subQ!J26/subQ!I26-1,"") | L34: =IFERROR(subQ!L26/subQ!J26-1,"") | M34: =IFERROR(subQ!M26/subQ!L26-1,"") | N34: =IFERROR(subQ!N26/subQ!M26-1,"") | O34: =IFERROR(subQ!O26/subQ!N26-1,"") | Q34: =IFERROR(subQ!Q26/subQ!O26-1,"") | R34: =IFERROR(subQ!R26/subQ!Q26-1,"") | S34: =IFERROR(subQ!S26/subQ!R26-1,"") | T34: =IFERROR(subQ!T26/subQ!S26-1,"") | V34: =IFERROR(subQ!V26/subQ!T26-1,"") | W34: =IFERROR(subQ!W26/subQ!V26-1,"") | X34: =IFERROR(subQ!X26/subQ!W26-1,"") | Y34: =IFERROR(subQ!Y26/subQ!X26-1,"") | AA34: =IFERROR(subQ!AA26/subQ!Y26-1,"") | AB34: =IFERROR(subQ!AB26/subQ!AA26-1,"") | AC34: 0.14142322 | AD34: 0.1303755 | AF34: 0.10652315 | AG34: 0.098784067 | AH34: 0.088605663 | AI34: 0.085459899 | AK34: 0.072983272 | AL34: 0.069764642 | AM34: 0.066227774 | AN34: 0.06512217
A35: drv:이자발생자산 | B35: qoq | C35: 이자발생자산 QoQ | G35: =IFERROR(subQ!G27/subQ!E27-1,"") | H35: =IFERROR(subQ!H27/subQ!G27-1,"") | I35: =IFERROR(subQ!I27/subQ!H27-1,"") | J35: =IFERROR(subQ!J27/subQ!I27-1,"") | L35: =IFERROR(subQ!L27/subQ!J27-1,"") | M35: =IFERROR(subQ!M27/subQ!L27-1,"") | N35: =IFERROR(subQ!N27/subQ!M27-1,"") | O35: =IFERROR(subQ!O27/subQ!N27-1,"") | Q35: =IFERROR(subQ!Q27/subQ!O27-1,"") | R35: =IFERROR(subQ!R27/subQ!Q27-1,"") | S35: =IFERROR(subQ!S27/subQ!R27-1,"") | T35: =IFERROR(subQ!T27/subQ!S27-1,"") | V35: =IFERROR(subQ!V27/subQ!T27-1,"") | W35: =IFERROR(subQ!W27/subQ!V27-1,"") | X35: =IFERROR(subQ!X27/subQ!W27-1,"") | Y35: =IFERROR(subQ!Y27/subQ!X27-1,"") | AA35: =IFERROR(subQ!AA27/subQ!Y27-1,"") | AB35: =IFERROR(subQ!AB27/subQ!AA27-1,"") | AC35: -0.89405096 | AD35: -8.8785714 | AF35: 1.0398912 | AG35: 0.524 | AH35: 0.33829105 | AI35: 0.26585313 | AK35: 0.19435359 | AL35: 0.16719516 | AM35: 0.14534453 | AN35: 0.132938
A36: drv:현금및현금성자산 | B36: qoq | C36: 현금및현금성자산 QoQ | G36: =IFERROR(subQ!G28/subQ!E28-1,"") | H36: =IFERROR(subQ!H28/subQ!G28-1,"") | I36: =IFERROR(subQ!I28/subQ!H28-1,"") | J36: =IFERROR(subQ!J28/subQ!I28-1,"") | L36: =IFERROR(subQ!L28/subQ!J28-1,"") | M36: =IFERROR(subQ!M28/subQ!L28-1,"") | N36: =IFERROR(subQ!N28/subQ!M28-1,"") | O36: =IFERROR(subQ!O28/subQ!N28-1,"") | Q36: =IFERROR(subQ!Q28/subQ!O28-1,"") | R36: =IFERROR(subQ!R28/subQ!Q28-1,"") | S36: =IFERROR(subQ!S28/subQ!R28-1,"") | T36: =IFERROR(subQ!T28/subQ!S28-1,"") | V36: =IFERROR(subQ!V28/subQ!T28-1,"") | W36: =IFERROR(subQ!W28/subQ!V28-1,"") | X36: =IFERROR(subQ!X28/subQ!W28-1,"") | Y36: =IFERROR(subQ!Y28/subQ!X28-1,"") | AA36: =IFERROR(subQ!AA28/subQ!Y28-1,"") | AB36: =IFERROR(subQ!AB28/subQ!AA28-1,"")
A37: drv:CAPEX | B37: yoy | C37: CAPEX YoY | J37: =IFERROR(subQ!J29/subQ!E29-1,"") | L37: =IFERROR(subQ!L29/subQ!G29-1,"") | M37: =IFERROR(subQ!M29/subQ!H29-1,"") | N37: =IFERROR(subQ!N29/subQ!I29-1,"") | O37: =IFERROR(subQ!O29/subQ!J29-1,"") | Q37: =IFERROR(subQ!Q29/subQ!L29-1,"") | R37: =IFERROR(subQ!R29/subQ!M29-1,"") | S37: =IFERROR(subQ!S29/subQ!N29-1,"") | T37: =IFERROR(subQ!T29/subQ!O29-1,"") | V37: =IFERROR(subQ!V29/subQ!Q29-1,"") | W37: =IFERROR(subQ!W29/subQ!R29-1,"") | X37: =IFERROR(subQ!X29/subQ!S29-1,"") | Y37: =IFERROR(subQ!Y29/subQ!T29-1,"") | AA37: =IFERROR(subQ!AA29/subQ!V29-1,"") | AB37: =IFERROR(subQ!AB29/subQ!W29-1,"") | AC37: -0.35615206 | AD37: 2.4412955 | AF37: 1.2331691 | AG37: -0.4374819 | AH37: 0 | AI37: 0 | AK37: 0 | AL37: 0 | AM37: 0 | AN37: 0
A38: drv:영업활동현금흐름 | B38: yoy | C38: 영업활동현금흐름 YoY | J38: =IFERROR(subQ!J30/subQ!E30-1,"") | L38: =IFERROR(subQ!L30/subQ!G30-1,"") | M38: =IFERROR(subQ!M30/subQ!H30-1,"") | N38: =IFERROR(subQ!N30/subQ!I30-1,"") | O38: =IFERROR(subQ!O30/subQ!J30-1,"") | Q38: =IFERROR(subQ!Q30/subQ!L30-1,"") | R38: =IFERROR(subQ!R30/subQ!M30-1,"") | S38: =IFERROR(subQ!S30/subQ!N30-1,"") | T38: =IFERROR(subQ!T30/subQ!O30-1,"") | V38: =IFERROR(subQ!V30/subQ!Q30-1,"") | W38: =IFERROR(subQ!W30/subQ!R30-1,"") | X38: =IFERROR(subQ!X30/subQ!S30-1,"") | Y38: =IFERROR(subQ!Y30/subQ!T30-1,"") | AA38: =IFERROR(subQ!AA30/subQ!V30-1,"") | AB38: =IFERROR(subQ!AB30/subQ!W30-1,"")
A39: drv:주식수 | B39: qoq | C39: 주식수 QoQ | G39: =IFERROR(subQ!G31/subQ!E31-1,"") | H39: =IFERROR(subQ!H31/subQ!G31-1,"") | I39: =IFERROR(subQ!I31/subQ!H31-1,"") | J39: =IFERROR(subQ!J31/subQ!I31-1,"") | L39: =IFERROR(subQ!L31/subQ!J31-1,"") | M39: =IFERROR(subQ!M31/subQ!L31-1,"") | N39: =IFERROR(subQ!N31/subQ!M31-1,"") | O39: =IFERROR(subQ!O31/subQ!N31-1,"") | Q39: =IFERROR(subQ!Q31/subQ!O31-1,"") | R39: =IFERROR(subQ!R31/subQ!Q31-1,"") | S39: =IFERROR(subQ!S31/subQ!R31-1,"") | T39: =IFERROR(subQ!T31/subQ!S31-1,"") | V39: =IFERROR(subQ!V31/subQ!T31-1,"") | W39: =IFERROR(subQ!W31/subQ!V31-1,"") | X39: =IFERROR(subQ!X31/subQ!W31-1,"") | Y39: =IFERROR(subQ!Y31/subQ!X31-1,"") | AA39: =IFERROR(subQ!AA31/subQ!Y31-1,"") | AB39: =IFERROR(subQ!AB31/subQ!AA31-1,"") | AC39: 0 | AD39: 0 | AF39: 0 | AG39: 0 | AH39: 0 | AI39: 0 | AK39: 0 | AL39: 0 | AM39: 0 | AN39: 0
A40: drv:DPS | B40: abs | C40: DPS (가정, 원) | E40: =subQ!E34 | F40: =subQ!F34 | G40: =subQ!G34 | H40: =subQ!H34 | I40: =subQ!I34 | J40: =subQ!J34 | K40: =subQ!K34 | L40: =subQ!L34 | ... AB40: =subQ!AB34 | AD40: 0 | AE40: =subQ!AE34 | AI40: 0 | AJ40: =subQ!AJ34 | AN40: 0 | AO40: =subQ!AO34
B42: 3. 밸류에이션·스칼라 | C42: 노란 셀 = 가정. '연결' 표시는 추정 전 분기 수식이 이 셀을 참조한다는 뜻
A43: sc:종가 | C43: 종가 | D43: 2295 | E43: 원 — 네이버 정규장 종가(aik 확정종가 대조 · aik 2,295원)
A44: sc:기준일 | C44: 기준일 | D44: 20261008 | E44: 종가 기준일
A45: sc:COE | C45: COE | D45: 0.09 | E45: 자기자본비용(가정) — TP 적정 PBR = ROE/COE
A46: sc:PER_lo | C46: PER_lo | D46: 10 | E46: PER 밴드 하단(배) — sector_default(레퍼런스 TP_PE PB 예시 10/15/20배; 과거 양(+)EPS 분기 0개 < 4)
A47: sc:PER_mid | C47: PER_mid | D47: 15 | E47: PER 밴드 중단(배)
A48: sc:PER_hi | C48: PER_hi | D48: 20 | E48: PER 밴드 상단(배)
A49: sc:EPS_Y1가중 | C49: EPS_Y1가중 | D49: 0.5 | E49: 12M fwd EPS = FY(last_actual연도)E × w + FY+1E × (1−w) — 기준 분기 2Q 이면 0.5(가정)
A50: sc:세율 | C50: 세율 | D50: 0.22 | E50: 참고(연결 안 됨: MAX(세전,0)×단일 세율로 재현 불가(지주 자회사 합산 등) → 분기별 역산) — 모델 assumptions 값 · 최근 12분기 세전 합 ≤ 0; 최근 8분기에 세전 > 0 분기 없음 → 법정세율 근사 22% 가정
A51: sc:판관비율 | C51: 판관비율 | D51: 0.23102548 | E51: 연결 — 판관비 = 매출액 × 판관비율(역산, 재현 오차 ≤ 0.05억 · 모델 assumptions 0.2311)
A52: sc:지배주주비중 | C52: 지배주주비중 | D52: 1 | E52: 연결 — 지배주주순이익 = 당기순이익 × 비중(역산, 재현 오차 ≤ 0.05억)
A53: sc:이자율_자산 | C53: 이자율_자산 | D53: 0.042153867 | E53: 연결 — 이자손익 = (전분기 이자발생자산 × 자산이자율 − 전분기 총차입금 × 부채이자율)/4(역산, 재현 오차 ≤ 0.05억 · 모델 assumptions 0.0421)
A54: sc:이자율_부채 | C54: 이자율_부채 | D54: 0.11760756 | E54: 연결 — 같은 수식의 부채 쪽(총차입금 행이 없으면 0)(역산, 재현 오차 ≤ 0.05억 · 모델 assumptions 0.1176)
A55: sc:배당성향 | C55: 배당성향 | E55: 배당성향(참고 — 모델은 직전 DPS 유지·Q2 지급 가정)
A56: sc:외화순노출_백만$ | C56: 외화순노출_백만$ | E56: 외화 순노출 × Δ기말환율 (외화 시트 방식) — 외화 순노출 미공시(face) → 0 + 표기
A57: sc:헤지비율 | C57: 헤지비율 | E57: sls 없음
A58: sc:헤지환율_약정 | C58: 헤지환율_약정 | E58: sls 없음

Sheet BS연결
B1: (백만원) | C1: 이름: BS연결H | E1: 4Q21 | F1: 2021 | G1: 1Q22 | H1: 2Q22 | I1: 3Q22 | J1: 4Q22 | K1: 2022 | L1: 1Q23 | M1: 2Q23 | N1: 3Q23 | O1: 4Q23 | P1: 2023 | Q1: 1Q24 | R1: 2Q24 | S1: 3Q24 | T1: 4Q24 | U1: 2024 | V1: 1Q25 | W1: 2Q25 | X1: 3Q25 | Y1: 4Q25 | Z1: 2025 | AA1: 1Q26 | AB1: 2Q26 | AC1: 3Q26 | AD1: 4Q26 | AE1: 2026 | AF1: 1Q27 | AG1: 2Q27 | AH1: 3Q27 | AI1: 4Q27 | AJ1: 2027 | AK1: 1Q28 | AL1: 2Q28 | AM1: 3Q28 | AN1: 4Q28 | AO1: 2028
B2: 연결 | D2: fin json(kship_fin.py)
B3: 메디콕스(연) | C3: UPDATE: 26-10-11 | E3: 1 | F3: 2 | G3: 3 | H3: 4 | I3: 5 | J3: 6 | K3: 7 | L3: 8 | M3: 9 | N3: 10 | O3: 11 | P3: 12 | Q3: 13 | R3: 14 | S3: 15 | T3: 16 | U3: 17 | V3: 18 | W3: 19 | X3: 20 | Y3: 21 | Z3: 22 | AA3: 23 | AB3: 24 | AC3: 25 | AD3: 26 | AE3: 27 | AF3: 28 | AG3: 29 | AH3: 30 | AI3: 31 | AJ3: 32 | AK3: 33 | AL3: 34 | AM3: 35 | AN3: 36 | AO3: 37
B4: Account Code | C4: AccountNAME | E4: 2021.12 | F4: 2021.12A | G4: 2022.03 | H4: 2022.06 | I4: 2022.09 | J4: 2022.12 | K4: 2022.12A | L4: 2023.03 | M4: 2023.06 | N4: 2023.09 | O4: 2023.12 | P4: 2023.12A | Q4: 2024.03 | R4: 2024.06 | S4: 2024.09 | T4: 2024.12 | U4: 2024.12A | V4: 2025.03 | W4: 2025.06 | X4: 2025.09 | Y4: 2025.12 | Z4: 2025.12A | AA4: 2026.03 | AB4: 2026.06 | AC4: 2026.09 | AD4: 2026.12 | AE4: 2026.12A | AF4: 2027.03 | AG4: 2027.06 | AH4: 2027.09 | AI4: 2027.12 | AJ4: 2027.12A | AK4: 2028.03 | AL4: 2028.06 | AM4: 2028.09 | AN4: 2028.12 | AO4: 2028.12A
A5: 1 | C5: 유동자산 | E5: 26272.5 | F5: 26272.5 | G5: 25703.45 | H5: 26466.24 | I5: 32117.9 | J5: 43389.2 | K5: 43389.2 | L5: 42227.6 | M5: 51848.17 | N5: 38767.23 | O5: 30036.83 | P5: 30036.83 | Q5: 26330.28 | R5: 20475.61 | S5: 17267.64 | T5: 13255.67 | U5: 13255.67 | V5: 16443.99 | W5: 12188.47 | X5: 9412.37 | Y5: 7493.7 | Z5: 7493.7 | AA5: 8879.12 | AB5: 8317.05
A6: 1 | C6: 현금및현금성자산 | E6: 4191.05 | F6: 4191.05 | G6: 6343.7 | H6: 1677.26 | I6: 3218.69 | J6: 2979.33 | K6: 2979.33 | L6: 1884.8 | M6: 7374.47 | N6: 2140.85 | O6: 1809.98 | P6: 1809.98 | Q6: 4506.62 | R6: 1017.41 | S6: 435.9 | T6: 1228.46 | U6: 1228.46 | V6: 4618.99 | W6: 588.85 | X6: 585 | Y6: 376.6 | Z6: 376.6 | AA6: 35.59 | AB6: 40.2
A7: 1 | C7: 단기금융상품 | E7: 300 | F7: 300 | G7: 300 | H7: 300 | I7: 300 | J7: 1800 | K7: 1800 | L7: 1800 | M7: 1800 | N7: 1800 | O7: 300 | P7: 300 | Q7: 300 | R7: 2803.82 | S7: 2809.74 | T7: 3015.02 | U7: 3015.02 | V7: 2833.56 | W7: 1415.55 | X7: 50 | Y7: 100 | Z7: 100 | AA7: 100 | AB7: 106.68
A8: 1 | C8: 단기금융자산 | E8: 4011.57 | F8: 4011.57 | G8: 4011.57 | H8: 3010.05 | I8: 890.93 | J8: 10344.72 | K8: 10344.72 | L8: 10344.72 | M8: 8182.91 | N8: 4324.13 | O8: 4664.26 | P8: 4664.26 | Q8: 300 | R8: 2803.82 | S8: 2809.74 | T8: 3015.02 | U8: 3015.02 | V8: 2833.56 | W8: 1415.55 | X8: 50 | Y8: 100 | Z8: 100 | AA8: 100 | AB8: 106.68
A9: 1 | C9: 매출채권및기타채권 | E9: 2653.92 | F9: 2653.92 | G9: 2870.06 | H9: 2355 | I9: 4230.06 | J9: 6508.25 | K9: 6508.25 | L9: 5690.23 | M9: 4483.85 | N9: 4204.54 | O9: 5082.8 | P9: 5082.8 | Q9: 5441.03 | R9: 3865.23 | S9: 3895.13 | T9: 5271.27 | U9: 5271.27 | V9: 5233.61 | W9: 5004.16 | X9: 3042.81 | Y9: 2558.08 | Z9: 2558.08 | AA9: 4180.9 | AB9: 3987.68
A10: 1 | C10: 기타유동금융자산 | E10: 14250.75 | F10: 14250.75 | G10: 11450.75 | H10: 11452.33 | I10: 13745.49 | J10: 19988.79 | K10: 19988.79 | L10: 21894.39 | M10: 22134.87 | N10: 22945.92 | O10: 15578.98 | P10: 15578.98 | Q10: 13479.55 | R10: 10091.9 | S10: 7651.64
A11: 1 | C11: 유동파생상품자산 | E11: 3711.57 | F11: 3711.57 | G11: 3711.57 | H11: 2710.05 | I11: 590.93 | J11: 8544.72 | K11: 8544.72 | L11: 8544.72 | M11: 6382.91 | N11: 2524.13 | O11: 4364.26 | P11: 4364.26
A12: 1 | C12: 재고자산 | E12: 918.56 | F12: 918.56 | G12: 808.44 | H12: 1732.74 | I12: 1382.07 | J12: 1437.6 | K12: 1437.6 | L12: 1853.22 | M12: 1811.1 | N12: 2318.89 | O12: 1772.09 | P12: 1772.09 | Q12: 1795.61 | R12: 1837.04 | S12: 2076.32 | T12: 1053.93 | U12: 1053.93 | V12: 1212.42 | W12: 1115.09 | X12: 1288.83 | Y12: 1178.42 | Z12: 1178.42 | AA12: 1188.2 | AB12: 802.91
A13: 1 | C13: 기타유동자산 | E13: 235.63 | F13: 235.63 | G13: 204.42 | H13: 1214.7 | I13: 3614.26 | J13: 558.77 | K13: 558.77 | L13: 463.12 | M13: 518.68 | N13: 577.81 | O13: 1043.02 | P13: 1043.02 | Q13: 692.66 | R13: 759.28 | S13: 242.15 | T13: 689.44 | U13: 689.44 | V13: 650.11 | W13: 737.51 | X13: 1192.39 | Y13: 123.69 | Z13: 123.69 | AA13: 153.79 | AB13: 257.84
A14: 1 | C14: 당기법인세자산(선급법인세) | E14: 11.03 | F14: 11.03 | G14: 14.51 | H14: 39.96 | I14: 52.19 | J14: 71.75 | K14: 71.75 | L14: 97.12 | M14: 47.09 | N14: 63.37 | O14: 85.71 | P14: 85.71 | Q14: 114.81 | R14: 100.93 | S14: 156.78 | T14: 212.88 | U14: 212.88 | V14: 267.3 | W14: 186.71 | X14: 236.11 | Y14: 140.05 | Z14: 140.05 | AA14: 203.79 | AB14: 104.88
A15: 1 | C15: 비유동자산 | E15: 76206.74 | F15: 76206.74 | G15: 78180.61 | H15: 77491.46 | I15: 74533.26 | J15: 67044.93 | K15: 67044.93 | L15: 65576.49 | M15: 53695.88 | N15: 53000.98 | O15: 67722.71 | P15: 67722.71 | Q15: 67850.23 | R15: 63262.3 | S15: 62084.39 | T15: 68163.5 | U15: 68163.5 | V15: 67112.73 | W15: 65307.88 | X15: 62782.27 | Y15: 60760.94 | Z15: 60760.94 | AA15: 60376.72 | AB15: 60422.04
A16: 1 | C16: 장기금융자산 | E16: 5476.76 | F16: 5476.76 | G16: 5480.56 | H16: 5502.04 | I16: 4322.57 | J16: 11093.65 | K16: 11093.65 | L16: 11093.65 | M16: 4283.22 | N16: 4282.93 | O16: 6604.08 | P16: 6604.08 | Q16: 7216.1 | R16: 1113.21 | S16: 1834.25 | T16: 5968.38 | U16: 5968.38 | V16: 5548.37 | W16: 900.46 | X16: 800.46 | Y16: 1174.44 | Z16: 1174.44 | AA16: 1174.44 | AB16: 1174.51
A17: 1 | C17: 투자자산 | E17: 27974.43 | F17: 27974.43 | G17: 29107.19 | H17: 19752.38 | I17: 18281.45 | J17: 12793.65 | K17: 12793.65 | L17: 12793.65 | M17: 5071.18 | N17: 5070.89 | O17: 16020.2 | P17: 16020.2 | Q17: 16762.67 | R17: 8647.96 | S17: 8484.25 | T17: 16010.52 | U17: 16010.52 | V17: 15159.47 | W17: 10583.28 | X17: 10935.99 | Y17: 9502.52 | Z17: 9502.52 | AA17: 9502.52 | AB17: 9696.92
A18: 1 | C18: 장기매출채권및기타채권 | E18: 1264.33 | F18: 1264.33 | G18: 2072.55 | H18: 6081.85 | I18: 4464.82 | J18: 3584.91 | K18: 3584.91 | L18: 2516.12 | M18: 849.92 | N18: 819.27 | O18: 174.52 | P18: 174.52 | Q18: 82.88 | R18: 70.78 | S18: 72.23 | T18: 73.55 | U18: 73.55 | V18: 75.03 | W18: 425.44 | X18: 607.29 | Y18: 541.88 | Z18: 541.88 | AA18: 552.03 | AB18: 658.64
A19: 1 | C19: 유형자산 | E19: 46959.77 | F19: 46959.77 | G19: 46993.26 | H19: 49529.19 | I19: 49659.56 | J19: 48516.4 | K19: 48516.4 | L19: 48138.82 | M19: 47729.6 | N19: 47102.95 | O19: 51476.39 | P19: 51476.39 | Q19: 50982.53 | R19: 50868.08 | S19: 50438.62 | T19: 52063.18 | U19: 52063.18 | V19: 51864.04 | W19: 49157.06 | X19: 44799 | Y19: 44278.59 | Z19: 44278.59 | AA19: 43886.13 | AB19: 43632.37
A20: 1 | C20: 무형자산 | E20: 8.21 | F20: 8.21 | G20: 7.61 | H20: 2128.03 | I20: 2127.42 | J20: 2129.12 | K20: 2129.12 | L20: 2127.9 | M20: 45.18 | N20: 7.86 | O20: 24.22 | P20: 24.22 | Q20: 22.15 | R20: 20.46 | S20: 18.36 | T20: 16.25 | U20: 16.25 | V20: 14.18 | W20: 12.1 | X20: 9.99 | Y20: 7.94 | Z20: 7.94 | AA20: 6.03 | AB20: 4.11
A21: 1 | C21: 종속기업및관계기업투자 | E21: 22497.67 | F21: 22497.67 | G21: 23626.63 | H21: 14250.34 | I21: 13958.88 | J21: 1700 | K21: 1700 | L21: 1700 | M21: 787.96 | N21: 787.96 | O21: 9416.12 | P21: 9416.12 | Q21: 9546.57 | R21: 7534.75 | S21: 6650 | T21: 10042.14 | U21: 10042.14 | V21: 9611.1 | W21: 9682.82 | X21: 10135.53 | Y21: 8328.08 | Z21: 8328.08 | AA21: 8328.08 | AB21: 8522.41
A22: 1 | C22: 자산총계 | E22: 102479.25 | F22: 102479.25 | G22: 103884.06 | H22: 103957.69 | I22: 106651.16 | J22: 110434.13 | K22: 110434.13 | L22: 107804.09 | M22: 105544.05 | N22: 91768.21 | O22: 97759.54 | P22: 97759.54 | Q22: 94180.51 | R22: 83737.91 | S22: 79352.03 | T22: 81419.17 | U22: 81419.17 | V22: 83556.72 | W22: 77496.35 | X22: 72194.63 | Y22: 68254.63 | Z22: 68254.63 | AA22: 69255.84 | AB22: 68739.09
A23: 1 | C23: 유동부채 | E23: 33417.43 | F23: 33417.43 | G23: 34807.63 | H23: 40650.36 | I23: 27975.57 | J23: 44154.04 | K23: 44154.04 | L23: 44007.38 | M23: 42815.02 | N23: 34107.97 | O23: 30638.94 | P23: 30638.94 | Q23: 26019.19 | R23: 25258.78 | S23: 24170.21 | T23: 23801.5 | U23: 23801.5 | V23: 22267.13 | W23: 19239.74 | X23: 15750.18 | Y23: 15978.57 | Z23: 15978.57 | AA23: 18744.63 | AB23: 19472.3
... A25: 1 | C25: 기타유동부채 | E25: 822.88 | F25: 822.88 | G25: 5194.24 | H25: 5379.29 | I25: 5669.03 | J25: 3807.59 | K25: 3807.59 | L25: 2838.87 | M25: 2993.82 | N25: 965.08 | O25: 442.86 | P25: 442.86 | Q25: 288 | R25: 238.11 | S25: 272.34 | T25: 610.98 | U25: 610.98 | V25: 1221.4 | W25: 1283.37 | X25: 570.12 | Y25: 721.24 | Z25: 721.24 | AA25: 916.17 | AB25: 995.26
A26: 1 | C26: 단기차입금 | E26: 3000 | F26: 3000 | H26: 1185 | I26: 12016.58 | J26: 104 | K26: 104 | L26: 428 | M26: 115 | N26: 118 | O26: 3063 | P26: 3063 | Q26: 15946.72 | R26: 16705.78 | S26: 16352.76 | T26: 15095.09 | U26: 15095.09 | V26: 13056.42 | W26: 9992.75 | X26: 8467.49 | Y26: 8461.69 | Z26: 8461.69 | AA26: 8499.42 | AB26: 8499.61
A27: 1 | C27: 유동성장기부채 | E27: 15470.8 | F27: 15470.8 | G27: 15901.13 | H27: 20515.56 | I27: 4277.9 | J27: 16166.14 | K27: 16166.14 | L27: 16968.91 | M27: 18473.85 | N27: 18984.81 | O27: 12188.88 | P27: 12188.88 | Q27: 2135.45 | R27: 2245.27 | S27: 2362.48 | T27: 2486.27 | U27: 2486.27 | V27: 2614.1 | W27: 1475.63 | X27: 251.31
A28: 1 | C28: 단기파생상품부채 | E28: 10610.06 | F28: 10610.06 | G28: 10439.73 | H28: 9943.32 | I28: 2698.77 | J28: 18271.59 | K28: 18271.59 | L28: 18271.59 | M28: 15503.61 | N28: 8374.35 | O28: 9308.32 | P28: 9308.32 | Q28: 1647.31 | R28: 314.57 | S28: 314.57 | T28: 186.56 | U28: 186.56 | V28: 186.56 | W28: 52.49 | X28: 8.49
A29: 1 | C29: 단기금융부채 | E29: 10610.06 | F29: 10610.06 | G29: 10439.73 | H29: 9943.32 | I29: 2698.77 | J29: 18271.59 | K29: 18271.59 | L29: 18271.59 | M29: 15503.61 | N29: 8374.35 | O29: 9308.32 | P29: 9308.32 | Q29: 1647.31 | R29: 314.57 | S29: 314.57 | T29: 186.56 | U29: 186.56 | V29: 186.56 | W29: 52.49 | X29: 8.49
A30: 1 | C30: 단기충당부채 | E30: 617.11 | F30: 617.11 | G30: 667.94 | H30: 696.72 | I30: 22.78 | J30: 22.92 | K30: 22.92 | M30: 28.16 | N30: 45.41 | O30: 45.64 | P30: 45.64 | Q30: 28.6 | R30: 27.22 | S30: 27.62 | T30: 28.03 | U30: 28.03 | V30: 28.43 | W30: 28.7 | X30: 28.7
A31: 1 | C31: 비유동부채 | E31: 2861.15 | F31: 2861.15 | G31: 3018.01 | H31: 3087.72 | I31: 2997.21 | J31: 3040.32 | K31: 3040.32 | L31: 3209.05 | M31: 3152.33 | N31: 3237.46 | O31: 3816.15 | P31: 3816.15 | Q31: 3817.06 | R31: 4036 | S31: 4141.63 | T31: 5172.28 | U31: 5172.28 | V31: 5071.09 | W31: 5946.8 | X31: 5803.04 | Y31: 5167.31 | Z31: 5167.31 | AA31: 4875.3 | AB31: 4765.14
A32: 1 | C32: 비유동리스부채 | E32: 325.47 | F32: 325.47 | G32: 434.43 | H32: 595.62 | I32: 483.24 | J32: 612.97 | K32: 612.97 | L32: 588.11 | M32: 562.01 | N32: 606.32 | O32: 428.68 | P32: 428.68 | Q32: 335.54 | R32: 445.04 | S32: 408.81 | T32: 481.21 | U32: 481.21 | V32: 526.32 | W32: 1357.26 | X32: 1942.65 | Y32: 1112.32 | Z32: 1112.32 | AA32: 853.02 | AB32: 697.05
A33: 1 | C33: 리스부채 | E33: 325.47 | F33: 325.47 | G33: 434.43 | H33: 595.62 | I33: 483.24 | J33: 612.97 | K33: 612.97 | L33: 588.11 | M33: 562.01 | N33: 606.32 | O33: 428.68 | P33: 428.68 | Q33: 335.54 | R33: 445.04 | S33: 408.81 | T33: 481.21 | U33: 481.21 | V33: 526.32 | W33: 1357.26 | X33: 1942.65 | Y33: 1112.32 | Z33: 1112.32 | AA33: 853.02 | AB33: 697.05
A34: 1 | C34: 장기금융부채 | E34: 325.47 | F34: 325.47 | G34: 434.43 | H34: 595.62 | I34: 483.24 | J34: 612.97 | K34: 612.97 | L34: 588.11 | M34: 562.01 | N34: 606.32 | O34: 428.68 | P34: 428.68 | Q34: 335.54 | R34: 445.04 | S34: 408.81 | T34: 481.21 | U34: 481.21 | V34: 526.32 | W34: 1357.26 | X34: 1942.65 | Y34: 1112.32 | Z34: 1112.32 | AA34: 853.02 | AB34: 697.05
A35: 1 | C35: 확정급여부채 | E35: 141.72 | F35: 141.72 | G35: 212.01 | H35: 92.94 | I35: 97.89 | J35: 39.38 | K35: 39.38 | L35: 233.07 | M35: 230.67 | N35: 288.73 | Q35: 94.19 | R35: 203.71 | S35: 345.6 | T35: 595.61 | U35: 595.61 | V35: 449.31 | W35: 469.04 | X35: 503.66 | Y35: 509.22 | Z35: 509.22 | AA35: 475.74 | AB35: 520.77
A36: 1 | C36: 장기충당부채 | E36: 22.38 | F36: 22.38 | H36: 27.59 | I36: 44.51 | J36: 44.74 | K36: 44.74 | L36: 44.96 | M36: 17.02 | W36: 25.03 | X36: 61.89 | Y36: 65.75 | Z36: 65.75 | AA36: 66.51 | AB36: 67.3
A37: 1 | C37: 이연법인세부채 | E37: 2371.58 | F37: 2371.58 | G37: 2371.58 | H37: 2371.58 | I37: 2371.58 | J37: 2263.78 | K37: 2263.78 | L37: 2263.78 | M37: 2263.78 | N37: 2263.78 | O37: 3309 | P37: 3309 | Q37: 3309 | R37: 3309 | S37: 3309 | T37: 4095.46 | U37: 4095.46 | V37: 4095.46 | W37: 4095.46 | X37: 3294.14 | Y37: 3473.02 | Z37: 3473.02 | AA37: 3473.02 | AB37: 3473.02
A38: 1 | C38: 부채총계 | E38: 36278.58 | F38: 36278.58 | G38: 37825.64 | H38: 43738.08 | I38: 30972.79 | J38: 47194.37 | K38: 47194.37 | L38: 47216.43 | M38: 45967.34 | N38: 37345.43 | O38: 34455.09 | P38: 34455.09 | Q38: 29836.25 | R38: 29294.78 | S38: 28311.85 | T38: 28973.78 | U38: 28973.78 | V38: 27338.23 | W38: 25186.54 | X38: 21553.22 | Y38: 21145.88 | Z38: 21145.88 | AA38: 23619.92 | AB38: 24237.44
A39: 1 | C39: 지배주주지분 | E39: 66203.82 | F39: 66203.82 | G39: 66058.42 | H39: 60219.61 | I39: 75678.37 | J39: 63239.76 | K39: 63239.76 | L39: 60587.65 | M39: 59576.71 | N39: 54422.78 | O39: 63304.44 | P39: 63304.44 | Q39: 64344.26 | R39: 54443.13 | S39: 51040.19 | T39: 52445.39 | U39: 52445.39 | V39: 56218.5 | W39: 52309.81 | X39: 50641.42 | Y39: 47108.75 | Z39: 47108.75 | AA39: 45635.92 | AB39: 44501.64
A40: 1 | C40: 자본금 | E40: 47303.95 | F40: 47303.95 | G40: 48143.08 | H40: 4814.31 | I40: 6052.83 | J40: 12773.66 | K40: 12773.66 | L40: 13092.34 | M40: 14858.61 | N40: 15038.73 | O40: 26138.72 | P40: 26138.72 | Q40: 28575.58 | R40: 28575.58 | S40: 29439.14 | T40: 34439.14 | U40: 34439.14 | V40: 41439.14 | W40: 41439.14 | X40: 2763.99 | Y40: 2763.99 | Z40: 2763.99 | AA40: 2763.99 | AB40: 2763.99
A41: 1 | C41: 기타자본 | E41: 59933.08 | F41: 59933.08 | G41: 60546.18 | H41: 103679.84 | I41: 132585.7 | J41: 133907.81 | K41: 133907.81 | L41: 134582.99 | M41: 141313.24 | N41: 98599.01 | O41: 111811.54 | P41: 111811.54 | Q41: 111321.28 | R41: 108861 | S41: 108406.91 | T41: 114203.1 | U41: 114203.1 | V41: 113709.54 | W41: 113425.7 | X41: 113728.15 | Y41: 113574.78 | Z41: 113574.78 | AA41: 113574.78 | AB41: 113574.78
A42: 1 | C42: 이익잉여금 | E42: -41033.21 | F42: -41033.21 | G42: -42630.83 | H42: -48274.54 | I42: -62960.16 | J42: -83441.71 | K42: -83441.71 | L42: -87087.68 | M42: -96595.14 | N42: -59214.96 | O42: -74645.81 | P42: -74645.81 | Q42: -75552.6 | R42: -82993.46 | S42: -86805.86 | T42: -96196.85 | U42: -96196.85 | V42: -98930.18 | W42: -102555.04 | X42: -65850.72 | Y42: -69230.02 | Z42: -69230.02 | AA42: -70702.85 | AB42: -71837.13
A43: 1 | C43: 비지배주주지분 | E43: -3.15 | F43: -3.15
A44: 1 | C44: 자본총계 | E44: 66200.67 | F44: 66200.67 | G44: 66058.42 | H44: 60219.61 | I44: 75678.37 | J44: 63239.76 | K44: 63239.76 | L44: 60587.65 | M44: 59576.71 | N44: 54422.78 | O44: 63304.44 | P44: 63304.44 | Q44: 64344.26 | R44: 54443.13 | S44: 51040.19 | T44: 52445.39 | U44: 52445.39 | V44: 56218.5 | W44: 52309.81 | X44: 50641.42 | Y44: 47108.75 | Z44: 47108.75 | AA44: 45635.92 | AB44: 44501.64
A45: 1 | C45: 부채와자본총계 | E45: 102479.25 | F45: 102479.25 | G45: 103884.06 | H45: 103957.69 | I45: 106651.16 | J45: 110434.13 | K45: 110434.13 | L45: 107804.09 | M45: 105544.05 | N45: 91768.21 | O45: 97759.54 | P45: 97759.54 | Q45: 94180.51 | R45: 83737.91 | S45: 79352.03 | T45: 81419.17 | U45: 81419.17 | V45: 83556.72 | W45: 77496.35 | X45: 72194.63 | Y45: 68254.63 | Z45: 68254.63 | AA45: 69255.84 | AB45: 68739.09
A46: 1 | C46: 총차입금 | E46: 18470.8 | F46: 18470.8 | G46: 15901.13 | H46: 21700.56 | I46: 16294.48 | J46: 16270.14 | K46: 16270.14 | L46: 17396.91 | M46: 18588.85 | N46: 19102.81 | O46: 15251.88 | P46: 15251.88 | Q46: 18082.17 | R46: 18951.05 | S46: 18715.24 | T46: 17581.36 | U46: 17581.36 | V46: 15670.52 | W46: 11468.38 | X46: 8718.8 | Y46: 8461.69 | Z46: 8461.69 | AA46: 8499.42 | AB46: 8499.61
A47: 1 | C47: 순차입금 | E47: 10268.18 | F47: 10268.18 | G47: 5545.86 | H47: 17013.25 | I47: 12184.86 | J47: 2946.09 | K47: 2946.09 | L47: 5167.39 | M47: 3031.47 | N47: 12637.83 | O47: 8777.64 | P47: 8777.64 | Q47: 13275.55 | R47: 15129.82 | S47: 15469.6 | T47: 13337.88 | U47: 13337.88 | V47: 8217.97 | W47: 9463.98 | X47: 8083.8 | Y47: 7985.09 | Z47: 7985.09 | AA47: 8363.83 | AB47: 8352.73
A48: 1 | C48: 이자발생자산 | E48: 13679.38 | F48: 13679.38 | G48: 15835.83 | H48: 10189.35 | I48: 8432.19 | J48: 24417.7 | K48: 24417.7 | L48: 23323.17 | M48: 19840.6 | N48: 10747.91 | O48: 13078.32 | P48: 13078.32 | Q48: 12022.72 | R48: 4934.44 | S48: 5079.89 | T48: 10211.86 | U48: 10211.86 | V48: 13000.92 | W48: 2904.86 | X48: 1435.46 | Y48: 1651.04 | Z48: 1651.04 | AA48: 1310.03 | AB48: 1321.39
A49: 1 | C49: 매각예정비유동자산및처분자산 | H49: 4984.2 | I49: 4984.2 | J49: 1500 | K49: 1500 | M49: 7295.21 | N49: 2191.7
A50: 1 | C50: 기타비유동자산 | J50: 20.85 | K50: 20.85 | O50: 27.37 | P50: 27.37 | W50: 5130 | X50: 6430 | Y50: 6430 | Z50: 6430 | AA50: 6430 | AB50: 6430
A51: 1 | C51: 기타비유동부채 | J51: 79.47 | K51: 79.47 | L51: 79.13 | M51: 78.85 | N51: 78.64 | O51: 78.47 | P51: 78.47 | Q51: 78.33 | R51: 78.24 | S51: 78.22 | X51: 0.7 | Y51: 7 | Z51: 7 | AA51: 7 | AB51: 7
A52: 1 | C52: 단기투자자산(공정가치) | T52: 1784.66 | U52: 1784.66 | V52: 1628 | W52: 3140.6 | X52: 3017.22 | Y52: 3016.86 | Z52: 3016.86 | AA52: 3016.86 | AB52: 3016.86
A53: 1 | C53: 매출액(수익) | E53: 4809.42 | G53: 4597.83 | H53: 5553.56 | I53: 5839.84 | J53: 5825.87 | K53: 21817.1 | L53: 5404.06 | M53: 7635.73 | N53: 6755.32 | O53: 7080.08 | P53: 26875.19 | Q53: 7467.41 | R53: 7364.21 | S53: 7604.77 | T53: 8174.78 | U53: 30611.17 | V53: 6820.42 | W53: 7674.79 | X53: 6685.12 | Y53: 6980.62 | Z53: 28160.95 | AA53: 6328.73 | AB53: 6443.04
A54: 1 | C54: 매출원가 | E54: 5013.7 | G54: 4430 | H54: 5271.69 | I54: 5731.14 | J54: 5725.16 | K54: 21157.99 | L54: 4849.87 | M54: 6739.24 | N54: 6227.6 | O54: 7137.58 | P54: 24954.29 | Q54: 6759.95 | R54: 7073.95 | S54: 7105.5 | T54: 7634.25 | U54: 28573.65 | V54: 6236.07 | W54: 6913.34 | X54: 5845.2 | Y54: 6998.24 | Z54: 25992.85 | AA54: 5776.2 | AB54: 6193.69
A55: 1 | C55: 매출총이익 | E55: -204.28 | G55: 167.83 | H55: 281.87 | I55: 108.71 | J55: 100.71 | K55: 659.12 | L55: 554.18 | M55: 896.49 | N55: 527.72 | O55: -57.49 | P55: 1920.9 | Q55: 707.46 | R55: 290.26 | S55: 499.27 | T55: 540.53 | U55: 2037.52 | V55: 584.36 | W55: 761.45 | X55: 839.92 | Y55: -17.62 | Z55: 2168.11 | AA55: 552.53 | AB55: 249.35
A56: 1 | C56: 판관비 | E56: 2634.04 | G56: 2536.73 | H56: 2230.47 | I56: 3080.86 | J56: 5143.03 | K56: 12991.09 | L56: 3537.22 | M56: 2838.66 | N56: 3408.53 | O56: 2794.7 | P56: 12579.11 | Q56: 4075.94 | R56: 2583 | S56: 2740.67 | T56: 2683.71 | U56: 12083.32 | V56: 2607.25 | W56: 2215.07 | X56: 1762.98 | Y56: 1329.54 | Z56: 7914.84 | AA56: 1585.8 | AB56: 1362.9
A57: 1 | C57: 영업이익 | E57: -2838.33 | G57: -2368.9 | H57: -1948.6 | I57: -2972.15 | J57: -5042.31 | K57: -12331.96 | L57: -2983.04 | M57: -1942.17 | N57: -2880.81 | O57: -2852.2 | P57: -10658.22 | Q57: -3368.48 | R57: -2292.74 | S57: -2241.4 | T57: -2143.17 | U57: -10045.79 | V57: -2022.89 | W57: -1453.62 | X57: -923.06 | Y57: -1347.17 | Z57: -5746.74 | AA57: -1033.27 | AB57: -1113.54
A58: 1 | C58: 금융수익 | E58: 3372.23 | G58: 336.26 | H58: 3307.63 | I58: -233.44 | J58: 5218.29 | K58: 8628.74 | L58: 365.24 | M58: 2513.92 | N58: 7569.04 | O58: -4478.1 | P58: 5970.1 | Q58: 458.14 | R58: 1097.83 | S58: -204.38 | T58: 833.78 | U58: 2185.37 | V58: 79.13 | W58: 89.74 | X58: 23.78 | Y58: 30.87 | Z58: 223.52 | AA58: 11.23 | AB58: 10.52
A59: 1 | C59: 금융비용 | E59: 8967.86 | G59: 745.7 | H59: 2842.97 | I59: 11958.03 | J59: 9330.46 | K59: 24877.16 | L59: 925.13 | M59: 7154.58 | N59: 11639.57 | O59: 4065.08 | P59: 23784.36 | Q59: 1316.39 | R59: 2987.89 | S59: 416.62 | T59: 3035.54 | U59: 7756.44 | V59: 660.61 | W59: 1260.14 | X59: 473.47 | Y59: 766.53 | Z59: 3160.75 | AA59: 237.51 | AB59: 236.49
A60: 1 | C60: 기타영업외수익 | E60: 17.53 | G60: 109.02 | H60: 121.39 | I60: 682.23 | J60: 872.61 | K60: 1785.25 | L60: 15.98 | M60: 8.49 | N60: 1.65 | O60: -3.38 | P60: 22.74 | Q60: 3.75 | R60: 62.98 | S60: 11.74 | T60: 21.99 | U60: 100.46 | V60: 189.76 | W60: 308.6 | X60: 7 | Y60: 442.56 | Z60: 947.92 | AA60: 21.39 | AB60: 133.09
A61: 1 | C61: 기타영업외비용 | E61: 681.41 | G61: 28.52 | H61: 71.99 | I61: -21.1 | J61: 4333.13 | K61: 4412.54 | L61: 8.93 | M61: 0.04 | N61: 117.95 | O61: 9.41 | P61: 136.33 | Q61: 1.52 | R61: 26.56 | S61: 0.01 | T61: 2833.54 | U61: 2861.63 | V61: 36.88 | W61: 998.86 | X61: 404.48 | Y61: -376.36 | Z61: 1063.86 | AA61: 331.15 | AB61: 59.44
A62: 1 | C62: 종속기업,공동지배기업및관계기업관련손익 | E62: -606.45 | G62: 1593.59 | H62: 291.95 | I62: -317.79 | J62: 317.79 | K62: 1885.54 | M62: 912.04 | O62: 1440.45 | Q62: 1362.93 | R62: -1362.93 | S62: 884.74 | T62: 676.47 | U62: 1561.21 | V62: 8.49 | W62: -141.66 | X62: 147.29 | Y62: 2235.63 | Z62: 2249.75 | AB62: 194.33
A63: 1 | C63: 지분법관련손익 | E63: -606.45 | G63: 1593.59 | H63: 291.95 | I63: -317.79 | J63: 317.79 | K63: 1885.54 | M63: 912.04 | O63: 1440.45 | Q63: 1362.93 | R63: -1362.93 | S63: 884.74 | T63: 676.47 | U63: 1561.21 | V63: 8.49 | W63: -141.66 | X63: 147.29 | Y63: 2235.63 | Z63: 2249.75 | AB63: 194.33
A64: 1 | C64: 법인세비용차감전계속사업이익 | E64: -12320.43 | G64: -1569.02 | H64: -5828.65 | I64: -14762.79 | J64: -20458.16 | K64: -42618.62 | L64: -3537.37 | M64: -9531 | N64: -5966.22 | O64: -12117.71 | P64: -31152.3 | Q64: -3037.41 | R64: -7320.18 | S64: -3791 | T64: -7348.12 | U64: -21496.71 | V64: -2882.53 | W64: -3724.17 | X64: -1917.52 | Y64: -3241.36 | Z64: -11765.58 | AA64: -1569.31 | AB64: -1071.55
A65: 1 | C65: 당기순이익 | E65: -12320.43 | G65: -1569.02 | H65: -5828.65 | I65: -14762.79 | J65: -20458.16 | K65: -42618.62 | L65: -3537.37 | M65: -9531 | N65: -5966.22 | O65: -15392.08 | P65: -34426.67 | Q65: -2948.07 | R65: -7420.18 | S65: -3791 | T65: -7275.67 | U65: -21434.92 | V65: -2882.53 | W65: -3724.17 | X65: -1917.52 | Y65: -3371.12 | Z65: -11895.34 | AA65: -1569.31 | AB65: -1071.55
A66: 1 | C66: 총포괄손익 | E66: -12299.76 | G66: -1489.17 | H66: -5747.72 | I66: -14675 | J66: -21619.58 | K66: -43531.47 | L66: -3645.96 | M66: -9507.46 | N66: -5948.59 | O66: -12669.59 | P66: -31771.6 | Q66: -2740.52 | R66: -9901.13 | S66: -4396.5 | T66: -4770.54 | U66: -21808.69 | V66: -3186.89 | W66: -3908.19 | X66: -1653.8 | Y66: -3532.67 | Z66: -12281.55 | AA66: -1472.83 | AB66: -1134.27
A67: 1 | C67: (지배주주지분)당기순이익 | E67: -12317.28 | G67: -1642.51 | H67: -5792.25 | I67: -14762.38 | J67: -20421.47 | K67: -42618.61 | L67: -3537.37 | M67: -9531 | N67: -5966.22 | O67: -15392.08 | P67: -34426.67 | Q67: -2948.07 | R67: -7420.18 | S67: -3791 | T67: -7275.67 | U67: -21434.92 | V67: -2882.53 | W67: -3724.17 | X67: -1917.52 | Y67: -3371.12 | Z67: -11895.34 | AA67: -1569.31 | AB67: -1071.55
A68: 1 | C68: 금융손익 | E68: -5595.63 | G68: -409.44 | H68: 464.66 | I68: -12191.47 | J68: -4112.17 | K68: -16248.42 | L68: -559.89 | M68: -4640.66 | N68: -4070.53 | O68: -8543.18 | P68: -17814.26 | Q68: -858.25 | R68: -1890.06 | S68: -621 | T68: -2201.76 | U68: -5571.07 | V68: -581.48 | W68: -1170.4 | X68: -449.69 | Y68: -735.66 | Z68: -2937.23 | AA68: -226.28 | AB68: -225.97
A69: 1 | C69: 기타영업외손익 | E69: -663.88 | G69: 80.5 | H69: 49.4 | I69: 703.33 | J69: -3460.52 | K69: -2627.29 | L69: 7.05 | M69: 8.45 | N69: -116.3 | O69: -12.79 | P69: -113.59 | Q69: 2.23 | R69: 36.42 | S69: 11.73 | T69: -2811.55 | U69: -2761.17 | V69: 152.88 | W69: -690.26 | X69: -397.48 | Y69: 818.92 | Z69: -115.94 | AA69: -309.76 | AB69: 73.65
A70: 1 | C70: 계속사업이익 | E70: -12320.43 | G70: -1569.02 | H70: -5828.65 | I70: -14762.79 | J70: -20458.16 | K70: -42618.62 | L70: -3537.37 | M70: -9531 | N70: -5966.22 | O70: -12117.71 | P70: -31152.3 | Q70: -3037.41 | R70: -7320.18 | S70: -3791 | T70: -7275.67 | U70: -21424.26 | V70: -2882.53 | W70: -3724.17 | X70: -1917.52 | Y70: -3371.12 | Z70: -11895.34 | AA70: -1569.31 | AB70: -1071.55
A71: 1 | C71: (비지배주주지분)당기순이익 | G71: 73.5 | H71: -36.39 | I71: -0.41
A72: 1 | C72: 이자수익 | G72: 267.89 | H72: -118.92 | I72: 70.78 | J72: 67.09 | K72: 286.84 | L72: 208.44 | M72: 71.14 | N72: 116.87 | O72: 77.32 | P72: 473.77 | Q72: 93.67 | R72: 66.85 | S72: 45.63 | T72: 45.21 | U72: 251.36 | V72: 45.58 | W72: 41.58 | X72: 23.79 | Y72: 14.71 | Z72: 125.66 | AA72: 11.23 | AB72: 10.45
A73: 1 | C73: 이자비용 | G73: 744.69 | H73: 868.11 | I73: 556.91 | J73: 523.46 | K73: 2693.17 | L73: 924.98 | M73: 991.97 | N73: 1041.97 | O73: 989.5 | P73: 3948.42 | Q73: 602.78 | R73: 530.4 | S73: 605.61 | T73: 569.74 | U73: 2308.53 | V73: 503.95 | W73: 417.01 | X73: 275.38 | Y73: 255.53 | Z73: 1451.87 | AA73: 237.51 | AB73: 236.48
A74: 1 | C74: 외환차손 | G74: 0.46 | H74: 0.07 | I74: 0 | J74: 0 | K74: 0.53 | L74: 0.15 | M74: 0.22 | N74: 0 | O74: 0.04 | P74: 0.41 | S74: 0.03 | T74: 0.01 | Y74: 0.64
A75: 1 | C75: 외화환산손실 | G75: 0.04 | H75: -0.04 | I75: 1.58 | J75: 0 | K75: 1.58 | S75: 0 | T75: 0
A76: 1 | C76: 파생상품이익 | G76: 68.36 | H76: 3032.4 | I76: -1759.14 | J76: -164.84 | K76: 1176.78 | M76: 1199.03 | N76: 8686.6 | O76: -5709.99 | Q76: 85.6 | R76: 904.89 | S76: 0 | T76: 128.01 | U76: 1118.5 | X76: 0 | Y76: 0
A77: 1 | C77: 이자손익 | G77: -476.8 | H77: -987.03 | I77: -486.13 | J77: -456.37 | K77: -2406.33 | L77: -716.54 | M77: -920.83 | N77: -925.1 | O77: -912.18 | P77: -3474.65 | Q77: -509.11 | R77: -463.55 | S77: -559.98 | T77: -524.53 | U77: -2057.17 | V77: -458.37 | W77: -375.43 | X77: -251.59 | Y77: -240.82 | Z77: -1326.21 | AA77: -226.28 | AB77: -226.03
A78: 1 | C78: 외환차익 | H78: 0.1 | I78: 0 | J78: 0.47 | S78: 0.54 | T78: 0
A79: 1 | C79: 파생상품손실 | H79: 1974.74 | I79: 11399.54 | J79: 3726.4 | M79: 2020.16 | N79: 5804.27 | O79: -1067.32 | Q79: 339.23
A80: 1 | C80: 외화환산이익 | L80: 0.08 | M80: -0.08
A81: 1 | C81: 중단사업이익 | O81: -3274.37 | Q81: 89.35 | R81: -100 | T81: 0
A82: 1 | C82: 배당금수익 | S82: 0 | T82: 0
A83: 1 | C83: 영업활동으로인한현금흐름 | E83: -2387.98 | G83: -1733.61 | H83: -3096.92 | I83: -4514.04 | J83: 188.71 | K83: -9155.86 | L83: -1684.15 | M83: -933.5 | N83: -2185.25 | O83: -4088.91 | P83: -8891.81 | Q83: -2478.68 | R83: -2037.53 | S83: -1587.31 | T83: -529.95 | U83: -6633.47 | V83: -2257.47 | W83: -286.45 | X83: -809.81 | Y83: -78.73 | Z83: -3432.46 | AA83: -112.17 | AB83: 836.05
A84: 1 | C84: 이자수취(CF) | E84: 34.9 | G84: 256.98 | H84: -134.19 | I84: 46.22 | J84: 61.37 | K84: 230.38 | L84: 174.75 | M84: 60.53 | N84: 71.47 | O84: 146.37 | P84: 453.12 | Q84: 82.07 | R84: 59.45 | S84: 22.75 | T84: 35.06 | U84: 199.33 | V84: 16.36 | W84: 51.86 | X84: 16.49 | Y84: 7.58 | Z84: 92.29 | AA84: 4.78 | AB84: 3.15
A85: 1 | C85: 이자지급(CF) | E85: -126.88 | G85: -189.66 | H85: -149.41 | I85: -239.16 | J85: -440.36 | K85: -1018.59 | L85: -103.8 | M85: -94.62 | N85: -18.19 | O85: -207.73 | P85: -424.34 | Q85: -170.37 | R85: -400.14 | S85: -469.41 | T85: -412.92 | U85: -1452.84 | V85: -359.75 | W85: -282.48 | X85: -210.9 | Y85: -217.25 | Z85: -1070.38 | AA85: -207.78 | AB85: -210.18
A86: 1 | C86: 법인세납부(CF) | E86: -9.7 | G86: -3.48 | H86: -25.41 | I86: -12.24 | J86: -19.56 | K86: -60.69 | L86: -25.37 | M86: 50.03 | N86: -16.29 | O86: -22.62 | P86: -14.25 | Q86: -30.48 | R86: 15.25 | S86: -55.85 | T86: -56.1 | U86: -127.18 | V86: -54.42 | W86: 80.59 | X86: -49.4 | Y86: 96.06 | Z86: 72.83 | AA86: -63.73 | AB86: 98.91
A87: 1 | C87: 투자활동으로인한현금흐름 | E87: -12705.11 | G87: 1724.51 | H87: -5143.28 | I87: -1142.86 | J87: -10940.66 | K87: -15502.29 | L87: -313.95 | M87: -355.9 | N87: -2857.7 | O87: -6812.76 | P87: -10340.31 | Q87: 1804.1 | R87: -1864.19 | S87: 642.66 | T87: 886.39 | U87: 1468.96 | V87: 993.83 | W87: 794.98 | X87: 4089.3 | Y87: 108.84 | Z87: 5986.95 | AA87: 101.09 | AB87: -455.44
A88: 1 | C88: 유형자산의증가 | E88: 127.39 | G88: 71.18 | H88: 527.53 | I88: 685.9 | J88: 2414.94 | K88: 3699.55 | L88: 9.33 | M88: 199.6 | N88: 145.39 | O88: 93.43 | P88: 447.75 | Q88: 73.42 | R88: 83.97 | S88: 119.18 | T88: 89.89 | U88: 366.46 | V88: 20.61 | W88: 502.66 | X88: 211.23 | Y88: 39.52 | Z88: 774.02 | AA88: 60.9 | AB88: 241.77
A89: 1 | C89: CAPEX | E89: 127.39 | G89: 71.18 | H89: 534.03 | I89: 685.9 | J89: 5176.54 | K89: 6467.65 | L89: 9.33 | M89: 228.6 | N89: 147.09 | O89: 111.43 | P89: 496.45 | Q89: 73.42 | R89: 84.36 | S89: 119.18 | T89: 89.89 | U89: 366.85 | V89: 20.61 | W89: 502.66 | X89: 211.23 | Y89: 39.52 | Z89: 774.02 | AA89: 60.9 | AB89: 241.77
A90: 1 | C90: 유형자산의감소 | E90: 24 | J90: 0.87 | O90: 0 | S90: 0 | T90: 20 | V90: 142 | W90: 3488.31 | X90: 4378.98 | Y90: 18.36 | Z90: 8027.65 | AA90: 6.9 | AB90: 0.88
A91: 1 | C91: 재무활동으로인한현금흐름 | E91: 16076.98 | G91: 2161.75 | H91: 3573.77 | I91: 7198.32 | J91: 10512.58 | K91: 23446.42 | L91: 903.58 | M91: 7090.97 | N91: -409.16 | O91: 10477.38 | P91: 18062.77 | Q91: 3371.22 | R91: 412.51 | S91: 363.13 | T91: 436.15 | U91: 4583.01 | V91: 4654.17 | W91: -4538.68 | X91: -3283.33 | Y91: -238.51 | Z91: -3406.35 | AA91: -329.94 | AB91: -375.99
A92: 1 | C92: 단기차입금의증가 | E92: 3499.99 | I92: 13188.03 | J92: 6185.55 | L92: 347 | M92: 150 | N92: 5 | O92: 11000 | P92: 11502 | Q92: 13055.53 | R92: 2133.24 | S92: 4019.34 | T92: 718.03 | U92: 19926.14 | V92: 133.77 | W92: 353.95 | X92: 1511.31 | Y92: 73.23 | Z92: 2072.26 | AA92: 67.74 | AB92: 40.62
A93: 1 | C93: 단기차입금의감소 | E93: 499.99 | G93: 3000 | H93: 0 | I93: 2356.45 | J93: 18098.13 | K93: 23454.58 | L93: 23 | M93: 359 | N93: 2 | O93: 8055 | P93: 8439 | Q93: 108.81 | R93: 1437.17 | S93: 4372.37 | T93: 1975.7 | U93: 7894.05 | V93: 2172.44 | W93: 3287.52 | X93: 3036.57 | Y93: 79.03 | Z93: 8575.56 | AA93: 30 | AB93: 40.44
A94: 1 | C94: 장기차입금의증가 | E94: 0
A95: 1 | C95: 장기차입금의감소 | E95: 0
A96: 1 | C96: 현금및현금성자산의증감 | E96: 983.88 | G96: 2152.65 | H96: -4666.44 | I96: 1541.43 | J96: -239.36 | K96: -1211.72 | L96: -1094.52 | M96: 5801.56 | N96: -5452.1 | O96: -424.29 | P96: -1169.35 | Q96: 2696.64 | R96: -3489.2 | S96: -581.52 | T96: 792.57 | U96: -581.51 | V96: 3390.53 | W96: -4030.14 | X96: -3.85 | Y96: -208.4 | Z96: -851.86 | AA96: -341.02 | AB96: 4.62
A97: 1 | C97: 기말현금및현금성자산 | E97: 983.88 | G97: 6343.7 | H97: -4666.44 | I97: 1541.43 | J97: -239.36 | K97: 2979.33 | L97: 1884.8 | M97: 5489.67 | N97: -5233.62 | O97: -330.87 | P97: 1809.98 | Q97: 4506.62 | R97: -3489.21 | S97: -581.51 | T97: 792.56 | U97: 1228.46 | V97: 4618.99 | W97: -4030.14 | X97: -3.85 | Y97: -208.4 | Z97: 376.6 | AA97: 35.59 | AB97: 4.61
A98: 1 | C98: 무형자산의증가 | I98: 0 | J98: 2761.6 | N98: 1.7 | O98: 18 | S98: 0 | T98: 0
A99: 1 | C99: 자기주식의취득 | I99: -0.01 | J99: 0 | Y99: 0
A100: 1 | C100: 배당금수취(CF) | S100: 0 | T100: 0

Sheet BS별도
B1: (백만원) | C1: 이름: BS별도H | E1: 4Q21 | F1: 2021 | G1: 1Q22 | H1: 2Q22 | I1: 3Q22 | J1: 4Q22 | K1: 2022 | L1: 1Q23 | M1: 2Q23 | N1: 3Q23 | O1: 4Q23 | P1: 2023 | Q1: 1Q24 | R1: 2Q24 | S1: 3Q24 | T1: 4Q24 | U1: 2024 | V1: 1Q25 | W1: 2Q25 | X1: 3Q25 | Y1: 4Q25 | Z1: 2025 | AA1: 1Q26 | AB1: 2Q26 | AC1: 3Q26 | AD1: 4Q26 | AE1: 2026 | AF1: 1Q27 | AG1: 2Q27 | AH1: 3Q27 | AI1: 4Q27 | AJ1: 2027 | AK1: 1Q28 | AL1: 2Q28 | AM1: 3Q28 | AN1: 4Q28 | AO1: 2028
B2: 별도 | D2: fin json(kship_fin.py)
B3: 메디콕스(별) | C3: UPDATE: 26-10-11 | E3: 1 | F3: 2 | G3: 3 | H3: 4 | I3: 5 | J3: 6 | K3: 7 | L3: 8 | M3: 9 | N3: 10 | O3: 11 | P3: 12 | Q3: 13 | R3: 14 | S3: 15 | T3: 16 | U3: 17 | V3: 18 | W3: 19 | X3: 20 | Y3: 21 | Z3: 22 | AA3: 23 | AB3: 24 | AC3: 25 | AD3: 26 | AE3: 27 | AF3: 28 | AG3: 29 | AH3: 30 | AI3: 31 | AJ3: 32 | AK3: 33 | AL3: 34 | AM3: 35 | AN3: 36 | AO3: 37
B4: Account Code | C4: AccountNAME | E4: 2021.12 | F4: 2021.12A | G4: 2022.03 | H4: 2022.06 | I4: 2022.09 | J4: 2022.12 | K4: 2022.12A | L4: 2023.03 | M4: 2023.06 | N4: 2023.09 | O4: 2023.12 | P4: 2023.12A | Q4: 2024.03 | R4: 2024.06 | S4: 2024.09 | T4: 2024.12 | U4: 2024.12A | V4: 2025.03 | W4: 2025.06 | X4: 2025.09 | Y4: 2025.12 | Z4: 2025.12A | AA4: 2026.03 | AB4: 2026.06 | AC4: 2026.09 | AD4: 2026.12 | AE4: 2026.12A | AF4: 2027.03 | AG4: 2027.06 | AH4: 2027.09 | AI4: 2027.12 | AJ4: 2027.12A | AK4: 2028.03 | AL4: 2028.06 | AM4: 2028.09 | AN4: 2028.12 | AO4: 2028.12A
A5: 1 | C5: 유동자산 | E5: 18368.91 | F5: 18368.91 | G5: 20649.05 | H5: 25559.66 | I5: 30567.02 | J5: 41186.85 | K5: 41186.85 | L5: 39273.29 | M5: 50490.19 | N5: 38680.6 | O5: 29911 | P5: 29911 | Q5: 26308.96 | R5: 20353.79 | S5: 17155.19 | T5: 13097.94 | U5: 13097.94 | V5: 15998.95 | W5: 11889.02 | X5: 9201.47 | Y5: 6904.69 | Z5: 6904.69 | AA5: 8206.17 | AB5: 7710.19
A6: 1 | C6: 현금및현금성자산 | E6: 4109.15 | F6: 4109.15 | G6: 6316.21 | H6: 1418.3 | I6: 2938.17 | J6: 2775.6 | K6: 2775.6 | L6: 1741.41 | M6: 7364.88 | N6: 2134.24 | O6: 1776.74 | P6: 1776.74 | Q6: 4500.85 | R6: 1013.72 | S6: 432.05 | T6: 1224.83 | U6: 1224.83 | V6: 4377.78 | W6: 462.07 | X6: 569.84 | Y6: 316.63 | Z6: 316.63 | AA6: 35.09 | AB6: 39.81
A7: 1 | C7: 단기금융상품 | E7: 300 | F7: 300 | G7: 300 | H7: 300 | I7: 300 | J7: 1800 | K7: 1800 | L7: 1800 | M7: 1800 | N7: 1800 | O7: 300 | P7: 300 | Q7: 300 | R7: 2803.82 | S7: 2809.74 | T7: 3015.02 | U7: 3015.02 | V7: 2833.56 | W7: 1415.55 | X7: 50 | Y7: 100 | Z7: 100 | AA7: 100 | AB7: 106.68
A8: 1 | C8: 단기금융자산 | E8: 4011.57 | F8: 4011.57 | G8: 4011.57 | H8: 3010.05 | I8: 890.93 | J8: 10344.72 | K8: 10344.72 | L8: 10344.72 | M8: 8182.91 | N8: 4324.13 | O8: 4664.26 | P8: 4664.26 | Q8: 300 | R8: 2803.82 | S8: 2809.74 | T8: 3015.02 | U8: 3015.02 | V8: 2833.56 | W8: 1415.55 | X8: 50 | Y8: 100 | Z8: 100 | AA8: 100 | AB8: 106.68
A9: 1 | C9: 매출채권및기타채권 | E9: 2633.48 | F9: 2633.48 | G9: 2843.19 | H9: 3758.86 | I9: 5009.55 | J9: 6670.75 | K9: 6670.75 | L9: 5086.97 | M9: 6036.58 | N9: 4469.06 | O9: 4995.83 | P9: 4995.83 | Q9: 5440.88 | R9: 3809.49 | S9: 3894.98 | T9: 5271.12 | U9: 5271.12 | V9: 5233.46 | W9: 5004.01 | X9: 3022.62 | Y9: 2196.4 | Z9: 2196.4 | AA9: 3774.76 | AB9: 3579.03
A10: 1 | C10: 기타유동금융자산 | E10: 6452.33 | F10: 6452.33 | G10: 6452.33 | H10: 9452.33 | I10: 11745.49 | J10: 17988.79 | K10: 17988.79 | L10: 19894.39 | M10: 22134.87 | N10: 22945.92 | O10: 15578.98 | P10: 15578.98 | Q10: 13479.55 | R10: 10091.9 | S10: 7651.64
A11: 1 | C11: 유동파생상품자산 | E11: 3711.57 | F11: 3711.57 | G11: 3711.57 | H11: 2710.05 | I11: 590.93 | J11: 8544.72 | K11: 8544.72 | L11: 8544.72 | M11: 6382.91 | N11: 2524.13 | O11: 4364.26 | P11: 4364.26
A12: 1 | C12: 재고자산 | E12: 918.56 | F12: 918.56 | G12: 808.44 | H12: 1732.74 | I12: 1382.07 | J12: 1437.6 | K12: 1437.6 | L12: 1853.22 | M12: 1811.1 | N12: 2318.89 | O12: 1772.09 | P12: 1772.09 | Q12: 1795.61 | R12: 1837.04 | S12: 2076.32 | T12: 1053.93 | U12: 1053.93 | V12: 1212.42 | W12: 1115.09 | X12: 1288.83 | Y12: 1178.42 | Z12: 1178.42 | AA12: 1188.2 | AB12: 802.91
A13: 1 | C13: 기타유동자산 | E13: 232.79 | F13: 232.79 | G13: 202.8 | H13: 1151.4 | I13: 3552.64 | J13: 401.17 | K13: 401.17 | L13: 259.01 | M13: 341.14 | N13: 425.79 | O13: 1038.76 | P13: 1038.76 | Q13: 692.08 | R13: 758.51 | S13: 241.75 | T13: 689.09 | U13: 689.09 | V13: 649.87 | W13: 678.75 | X13: 1172.98 | Y13: 67.67 | Z13: 67.67 | AA13: 61.46 | AB13: 161.18
A14: 1 | C14: 당기법인세자산(선급법인세) | E14: 11.03 | F14: 11.03 | G14: 14.5 | H14: 36.47 | I14: 48.66 | J14: 68.22 | K14: 68.22 | L14: 93.58 | M14: 46.28 | N14: 62.57 | O14: 84.34 | P14: 84.34 | Q14: 99.99 | R14: 39.31 | S14: 48.73 | T14: 59.28 | U14: 59.28 | V14: 63.86 | W14: 72.95 | X14: 79.97 | Y14: 28.71 | Z14: 28.71 | AA14: 29.81 | AB14: 3.73
A15: 1 | C15: 비유동자산 | E15: 83605.21 | F15: 83605.21 | G15: 79541.94 | H15: 74570.55 | I15: 73537.04 | J15: 66250.11 | K15: 66250.11 | L15: 65878.21 | M15: 53103.71 | N15: 52618.57 | O15: 66539.02 | P15: 66539.02 | Q15: 67402.24 | R15: 63622.92 | S15: 62700.25 | T15: 68190.76 | U15: 68190.76 | V15: 67646.59 | W15: 65465.26 | X15: 62924.84 | Y15: 61353.27 | Z15: 61353.27 | AA15: 61125.19 | AB15: 60943.72
A16: 1 | C16: 장기금융자산 | E16: 2476.76 | F16: 2476.76 | G16: 2480.56 | H16: 2427.04 | I16: 1322.57 | J16: 8093.65 | K16: 8093.65 | L16: 8093.65 | M16: 4283.22 | N16: 4282.93 | O16: 6604.08 | P16: 6604.08 | Q16: 7216.1 | R16: 1113.21 | S16: 1834.25 | T16: 5968.38 | U16: 5968.38 | V16: 5548.37 | W16: 900.46 | X16: 800.46 | Y16: 1174.44 | Z16: 1174.44 | AA16: 1174.44 | AB16: 1174.51
A17: 1 | C17: 투자자산 | E17: 35407.98 | F17: 35407.98 | G17: 30495.55 | H17: 22286.72 | I17: 21181.82 | J17: 15923.23 | K17: 15923.23 | L17: 15922.74 | M17: 5071.18 | N17: 5070.89 | O17: 14951.59 | P17: 14951.59 | Q17: 16316.1 | R17: 9009.71 | S17: 9100.95 | T17: 16038.32 | U17: 16038.32 | V17: 15693.58 | W17: 10635.72 | X17: 10973.61 | Y17: 9551.58 | Z17: 9551.58 | AA17: 9551.58 | AB17: 9513.53
A18: 1 | C18: 장기매출채권및기타채권 | E18: 1264.24 | F18: 1264.24 | G18: 2072.46 | H18: 2881.76 | I18: 3087.28 | J18: 2306.58 | K18: 2306.58 | L18: 2337.43 | M18: 670.85 | N18: 718.67 | O18: 173.92 | P18: 173.92 | Q18: 82.83 | R18: 70.73 | S18: 72.18 | T18: 73.5 | U18: 73.5 | V18: 74.98 | W18: 1660.39 | X18: 2142.24 | Y18: 2557.83 | Z18: 2557.83 | AA18: 2721.98 | AB18: 2832.09
A19: 1 | C19: 유형자산 | E19: 46924.78 | F19: 46924.78 | G19: 46966.32 | H19: 49392.79 | I19: 49259.27 | J19: 47991.38 | K19: 47991.38 | L19: 47610.59 | M19: 47354.82 | N19: 46821.14 | O19: 51361.9 | P19: 51361.9 | Q19: 50981.16 | R19: 50867 | S19: 50437.84 | T19: 52062.69 | U19: 52062.69 | V19: 51863.83 | W19: 49157.06 | X19: 44799 | Y19: 44235.92 | Z19: 44235.92 | AA19: 43845.59 | AB19: 43593.99
A20: 1 | C20: 무형자산 | E20: 8.21 | F20: 8.21 | G20: 7.61 | H20: 9.27 | I20: 8.66 | J20: 8.06 | K20: 8.06 | L20: 7.46 | M20: 6.86 | N20: 7.86 | O20: 24.22 | P20: 24.22 | Q20: 22.15 | R20: 20.46 | S20: 18.36 | T20: 16.25 | U20: 16.25 | V20: 14.18 | W20: 12.1 | X20: 9.99 | Y20: 7.94 | Z20: 7.94 | AA20: 6.03 | AB20: 4.11
A21: 1 | C21: 종속기업및관계기업투자 | E21: 32931.22 | F21: 32931.22 | G21: 28014.99 | H21: 19859.68 | I21: 19859.25 | J21: 7829.58 | K21: 7829.58 | L21: 7829.09 | M21: 787.96 | N21: 787.96 | O21: 8347.51 | P21: 8347.51 | Q21: 9100 | R21: 7896.5 | S21: 7266.7 | T21: 10069.94 | U21: 10069.94 | V21: 10145.21 | W21: 9735.26 | X21: 10173.15 | Y21: 8377.14 | Z21: 8377.14 | AA21: 8377.14 | AB21: 8339.02
A22: 1 | C22: 자산총계 | E22: 101974.12 | F22: 101974.12 | G22: 100190.99 | H22: 100130.2 | I22: 104104.06 | J22: 107436.95 | K22: 107436.95 | L22: 105151.51 | M22: 103593.9 | N22: 91299.16 | O22: 96450.02 | P22: 96450.02 | Q22: 93711.2 | R22: 83976.71 | S22: 79855.44 | T22: 81288.7 | U22: 81288.7 | V22: 83645.53 | W22: 77354.28 | X22: 72126.3 | Y22: 68257.96 | Z22: 68257.96 | AA22: 69331.36 | AB22: 68653.91
A23: 1 | C23: 유동부채 | E23: 32910.78 | F23: 32910.78 | G23: 32363.17 | H23: 36702.27 | I23: 24819.29 | J23: 41015.24 | K23: 41015.24 | L23: 40622.62 | M23: 39739.2 | N23: 33353.16 | O23: 30354.98 | P23: 30354.98 | Q23: 25804.51 | R23: 24992.32 | S23: 23849.55 | T23: 23426.13 | U23: 23426.13 | V23: 21861.59 | W23: 19060.5 | X23: 15678.44 | Y23: 15733.17 | Z23: 15733.17 | AA23: 18427.35 | AB23: 18968.87
... A25: 1 | C25: 기타유동부채 | E25: 349.72 | F25: 349.72 | G25: 2772.38 | H25: 2704.78 | I25: 2987.02 | J25: 1274.21 | K25: 1274.21 | L25: 186.92 | M25: 492.96 | N25: 899.02 | O25: 442.86 | P25: 442.86 | Q25: 288 | R25: 238.11 | S25: 272.34 | T25: 610.98 | U25: 610.98 | V25: 1221.4 | W25: 1283.19 | X25: 569.76 | Y25: 710.18 | Z25: 710.18 | AA25: 886.5 | AB25: 940.99
A26: 1 | C26: 단기차입금 | E26: 3000 | F26: 3000 | I26: 11876.58 | O26: 3000 | P26: 3000 | Q26: 15734.06 | R26: 16440.05 | S26: 16032.97 | T26: 14720.85 | U26: 14720.85 | V26: 12643.12 | W26: 9809.46 | X26: 8309.2 | Y26: 8268.39 | Z26: 8268.39 | AA26: 8285.22 | AB26: 8281.51
A27: 1 | C27: 유동성장기부채 | E27: 15470.8 | F27: 15470.8 | G27: 15901.13 | H27: 20515.56 | I27: 4277.9 | J27: 16166.14 | K27: 16166.14 | L27: 16968.91 | M27: 18473.85 | N27: 18984.81 | O27: 12188.88 | P27: 12188.88 | Q27: 2135.45 | R27: 2245.27 | S27: 2362.48 | T27: 2486.27 | U27: 2486.27 | V27: 2614.1 | W27: 1475.63 | X27: 251.31
A28: 1 | C28: 단기파생상품부채 | E28: 10610.06 | F28: 10610.06 | G28: 10439.73 | H28: 9943.32 | I28: 2698.77 | J28: 18271.59 | K28: 18271.59 | L28: 18271.59 | M28: 15503.61 | N28: 8374.35 | O28: 9308.32 | P28: 9308.32 | Q28: 1647.31 | R28: 314.57 | S28: 314.57 | T28: 186.56 | U28: 186.56 | V28: 186.56 | W28: 52.49 | X28: 8.49
A29: 1 | C29: 단기금융부채 | E29: 10610.06 | F29: 10610.06 | G29: 10439.73 | H29: 9943.32 | I29: 2698.77 | J29: 18271.59 | K29: 18271.59 | L29: 18271.59 | M29: 15503.61 | N29: 8374.35 | O29: 9308.32 | P29: 9308.32 | Q29: 1647.31 | R29: 314.57 | S29: 314.57 | T29: 186.56 | U29: 186.56 | V29: 186.56 | W29: 52.49 | X29: 8.49
A30: 1 | C30: 단기충당부채 | E30: 617.11 | F30: 617.11 | G30: 667.94 | H30: 696.72 | I30: 22.78 | J30: 22.92 | K30: 22.92 | M30: 28.16 | N30: 28.31 | O30: 28.46 | P30: 28.46 | Q30: 28.6 | R30: 27.22 | S30: 27.62 | T30: 28.03 | U30: 28.03 | V30: 28.43 | W30: 28.7 | X30: 28.7
A31: 1 | C31: 비유동부채 | E31: 2861.15 | F31: 2861.15 | G31: 3018.01 | H31: 3056.04 | I31: 2881.51 | J31: 2807.62 | K31: 2807.62 | L31: 2996.86 | M31: 3013.48 | N31: 3122.95 | O31: 3777.86 | P31: 3777.86 | Q31: 3817.06 | R31: 4036 | S31: 4141.63 | T31: 5172.28 | U31: 5172.28 | V31: 5071.09 | W31: 5946.8 | X31: 5803.04 | Y31: 5127.18 | Z31: 5127.18 | AA31: 4837.21 | AB31: 4716.35
A32: 1 | C32: 비유동리스부채 | E32: 325.47 | F32: 325.47 | G32: 434.43 | H32: 589.05 | I32: 415.04 | J32: 436.49 | K32: 436.49 | L32: 438.87 | M32: 440.19 | N32: 499.08 | O32: 390.39 | P32: 390.39 | Q32: 335.54 | R32: 445.04 | S32: 408.81 | T32: 481.21 | U32: 481.21 | V32: 526.32 | W32: 1357.26 | X32: 1942.65 | Y32: 1077.54 | Z32: 1077.54 | AA32: 820.29 | AB32: 666.38
A33: 1 | C33: 리스부채 | E33: 325.47 | F33: 325.47 | G33: 434.43 | H33: 589.05 | I33: 415.04 | J33: 436.49 | K33: 436.49 | L33: 438.87 | M33: 440.19 | N33: 499.08 | O33: 390.39 | P33: 390.39 | Q33: 335.54 | R33: 445.04 | S33: 408.81 | T33: 481.21 | U33: 481.21 | V33: 526.32 | W33: 1357.26 | X33: 1942.65 | Y33: 1077.54 | Z33: 1077.54 | AA33: 820.29 | AB33: 666.38
A34: 1 | C34: 장기금융부채 | E34: 325.47 | F34: 325.47 | G34: 434.43 | H34: 589.05 | I34: 415.04 | J34: 436.49 | K34: 436.49 | L34: 438.87 | M34: 440.19 | N34: 499.08 | O34: 390.39 | P34: 390.39 | Q34: 335.54 | R34: 445.04 | S34: 408.81 | T34: 481.21 | U34: 481.21 | V34: 526.32 | W34: 1357.26 | X34: 1942.65 | Y34: 1077.54 | Z34: 1077.54 | AA34: 820.29 | AB34: 666.38
A35: 1 | C35: 확정급여부채 | E35: 141.72 | F35: 141.72 | G35: 212.01 | H35: 67.83 | I35: 67.15 | L35: 187.07 | M35: 230.67 | N35: 281.46 | Q35: 94.19 | R35: 203.71 | S35: 345.6 | T35: 595.61 | U35: 595.61 | V35: 449.31 | W35: 469.04 | X35: 503.66 | Y35: 503.87 | Z35: 503.87 | AA35: 470.39 | AB35: 502.65
A36: 1 | C36: 장기충당부채 | E36: 22.38 | F36: 22.38 | H36: 27.59 | I36: 27.73 | J36: 27.88 | K36: 27.88 | L36: 28.02 | W36: 25.03 | X36: 61.89 | Y36: 65.75 | Z36: 65.75 | AA36: 66.51 | AB36: 67.3
A37: 1 | C37: 이연법인세부채 | E37: 2371.58 | F37: 2371.58 | G37: 2371.58 | H37: 2371.58 | I37: 2371.58 | J37: 2263.78 | K37: 2263.78 | L37: 2263.78 | M37: 2263.78 | N37: 2263.78 | O37: 3309 | P37: 3309 | Q37: 3309 | R37: 3309 | S37: 3309 | T37: 4095.46 | U37: 4095.46 | V37: 4095.46 | W37: 4095.46 | X37: 3294.14 | Y37: 3473.02 | Z37: 3473.02 | AA37: 3473.02 | AB37: 3473.02
A38: 1 | C38: 부채총계 | E38: 35771.93 | F38: 35771.93 | G38: 35381.18 | H38: 39758.31 | I38: 27700.79 | J38: 43822.86 | K38: 43822.86 | L38: 43619.48 | M38: 42752.68 | N38: 36476.11 | O38: 34132.84 | P38: 34132.84 | Q38: 29621.57 | R38: 29028.31 | S38: 27991.18 | T38: 28598.41 | U38: 28598.41 | V38: 26932.68 | W38: 25007.3 | X38: 21481.48 | Y38: 20860.36 | Z38: 20860.36 | AA38: 23264.55 | AB38: 23685.22
A39: 1 | C39: 자본금 | E39: 47303.95 | F39: 47303.95 | G39: 48143.08 | H39: 4814.31 | I39: 6052.83 | J39: 12773.66 | K39: 12773.66 | L39: 13092.34 | M39: 14858.61 | N39: 15038.73 | O39: 26138.72 | P39: 26138.72 | Q39: 28575.58 | R39: 28575.58 | S39: 29439.14 | T39: 34439.14 | U39: 34439.14 | V39: 41439.14 | W39: 41439.14 | X39: 2763.99 | Y39: 2763.99 | Z39: 2763.99 | AA39: 2763.99 | AB39: 2763.99
A40: 1 | C40: 기타자본 | E40: 58753.15 | F40: 58753.15 | G40: 59331.29 | H40: 102617.43 | I40: 131512.25 | J40: 132626.24 | K40: 132626.24 | L40: 133301.42 | M40: 140031.66 | N40: 97317.44 | O40: 110529.97 | P40: 110529.97 | Q40: 110039.7 | R40: 107579.43 | S40: 107125.33 | T40: 112921.53 | U40: 112921.53 | V40: 112427.96 | W40: 112144.13 | X40: 112446.57 | Y40: 112293.2 | Z40: 112293.2 | AA40: 112293.2 | AB40: 112293.2
A41: 1 | C41: 이익잉여금 | E41: -39854.91 | F41: -39854.91 | G41: -42664.56 | H41: -47059.84 | I41: -61161.82 | J41: -81785.81 | K41: -81785.81 | L41: -84861.73 | M41: -94049.05 | N41: -57533.11 | O41: -74351.51 | P41: -74351.51 | Q41: -74525.65 | R41: -81206.61 | S41: -84700.21 | T41: -94670.38 | U41: -94670.38 | V41: -97154.25 | W41: -101236.29 | X41: -64565.74 | Y41: -67659.59 | Z41: -67659.59 | AA41: -68990.38 | AB41: -70088.5
A42: 1 | C42: 자본총계 | E42: 66202.19 | F42: 66202.19 | G42: 64809.81 | H42: 60371.89 | I42: 76403.27 | J42: 63614.09 | K42: 63614.09 | L42: 61532.03 | M42: 60841.22 | N42: 54823.05 | O42: 62317.18 | P42: 62317.18 | Q42: 64089.63 | R42: 54948.4 | S42: 51864.26 | T42: 52690.29 | U42: 52690.29 | V42: 56712.85 | W42: 52346.98 | X42: 50644.83 | Y42: 47397.6 | Z42: 47397.6 | AA42: 46066.81 | AB42: 44968.69
A43: 1 | C43: 부채와자본총계 | E43: 101974.12 | F43: 101974.12 | G43: 100190.99 | H43: 100130.2 | I43: 104104.06 | J43: 107436.95 | K43: 107436.95 | L43: 105151.51 | M43: 103593.9 | N43: 91299.16 | O43: 96450.02 | P43: 96450.02 | Q43: 93711.2 | R43: 83976.71 | S43: 79855.44 | T43: 81288.7 | U43: 81288.7 | V43: 83645.53 | W43: 77354.28 | X43: 72126.3 | Y43: 68257.96 | Z43: 68257.96 | AA43: 69331.36 | AB43: 68653.91
A44: 1 | C44: 지배주주지분 | E44: 66202.19 | F44: 66202.19 | G44: 64809.81 | H44: 60371.89 | I44: 76403.27 | J44: 63614.09 | K44: 63614.09 | L44: 61532.03 | M44: 60841.22 | N44: 54823.05 | O44: 62317.18 | P44: 62317.18 | Q44: 64089.63 | R44: 54948.4 | S44: 51864.26 | T44: 52690.29 | U44: 52690.29 | V44: 56712.85 | W44: 52346.98 | X44: 50644.83 | Y44: 47397.6 | Z44: 47397.6 | AA44: 46066.81 | AB44: 44968.69
A45: 1 | C45: 총차입금 | E45: 18470.8 | F45: 18470.8 | G45: 15901.13 | H45: 20515.56 | I45: 16154.48 | J45: 16166.14 | K45: 16166.14 | L45: 16968.91 | M45: 18473.85 | N45: 18984.81 | O45: 15188.88 | P45: 15188.88 | Q45: 17869.51 | R45: 18685.32 | S45: 18395.45 | T45: 17207.12 | U45: 17207.12 | V45: 15257.22 | W45: 11285.09 | X45: 8560.51 | Y45: 8268.39 | Z45: 8268.39 | AA45: 8285.22 | AB45: 8281.51
A46: 1 | C46: 순차입금 | E46: 10350.08 | F46: 10350.08 | G46: 5573.35 | H46: 16087.21 | I46: 12325.38 | J46: 3045.82 | K46: 3045.82 | L46: 4882.78 | M46: 2926.06 | N46: 12526.44 | O46: 8747.88 | P46: 8747.88 | Q46: 13068.66 | R46: 14867.78 | S46: 15153.66 | T46: 12967.27 | U46: 12967.27 | V46: 8045.88 | W46: 9407.47 | X46: 7940.67 | Y46: 7851.76 | Z46: 7851.76 | AA46: 8150.13 | AB46: 8135.02
A47: 1 | C47: 이자발생자산 | E47: 10597.48 | F47: 10597.48 | G47: 12808.34 | H47: 6855.39 | I47: 5151.67 | J47: 21213.97 | K47: 21213.97 | L47: 20179.78 | M47: 19831.01 | N47: 10741.3 | O47: 13045.08 | P47: 13045.08 | Q47: 12016.95 | R47: 4930.75 | S47: 5076.04 | T47: 10208.23 | U47: 10208.23 | V47: 12759.71 | W47: 2778.08 | X47: 1420.3 | Y47: 1591.07 | Z47: 1591.07 | AA47: 1309.53 | AB47: 1321
A48: 1 | C48: 매각예정비유동자산및처분자산 | H48: 4999.5 | I48: 4999.5 | J48: 1500 | K48: 1500 | M48: 4572.44 | N48: 2000
A49: 1 | C49: 기타비유동자산 | J49: 20.85 | K49: 20.85 | O49: 27.37 | P49: 27.37 | W49: 4000 | X49: 5000 | Y49: 5000 | Z49: 5000 | AA49: 5000 | AB49: 5000
A50: 1 | C50: 기타비유동부채 | J50: 79.47 | K50: 79.47 | L50: 79.13 | M50: 78.85 | N50: 78.64 | O50: 78.47 | P50: 78.47 | Q50: 78.33 | R50: 78.24 | S50: 78.22 | X50: 0.7 | Y50: 7 | Z50: 7 | AA50: 7 | AB50: 7
A51: 1 | C51: 단기투자자산(공정가치) | T51: 1784.66 | U51: 1784.66 | V51: 1628 | W51: 3140.6 | X51: 3017.22 | Y51: 3016.86 | Z51: 3016.86 | AA51: 3016.86 | AB51: 3016.86
A52: 1 | C52: 매출액(수익) | E52: 4809.42 | G52: 4597.83 | H52: 5333.94 | I52: 5121.01 | J52: 5243.14 | K52: 20295.92 | L52: 5292.24 | M52: 7493.3 | N52: 6597.21 | O52: 7492.43 | P52: 26875.18 | Q52: 7467.41 | R52: 7364.21 | S52: 7604.77 | T52: 8174.78 | U52: 30611.17 | V52: 6820.42 | W52: 7674.79 | X52: 6685.12 | Y52: 6980.62 | Z52: 28160.95 | AA52: 6317.8 | AB52: 6443.03
A53: 1 | C53: 매출원가 | E53: 5013.7 | G53: 4430 | H53: 5070.01 | I53: 5028.15 | J53: 5198.81 | K53: 19726.97 | L53: 4747.31 | M53: 6643.42 | N53: 6090.32 | O53: 7473.24 | P53: 24954.29 | Q53: 6759.95 | R53: 7073.95 | S53: 7105.5 | T53: 7634.25 | U53: 28573.65 | V53: 6236.07 | W53: 6913.34 | X53: 5845.2 | Y53: 6998.24 | Z53: 25992.85 | AA53: 5776.2 | AB53: 6193.69
A54: 1 | C54: 매출총이익 | E54: -204.28 | G54: 167.83 | H54: 263.93 | I54: 92.86 | J54: 44.33 | K54: 568.95 | L54: 544.93 | M54: 849.88 | N54: 506.89 | O54: 19.2 | P54: 1920.9 | Q54: 707.46 | R54: 290.26 | S54: 499.27 | T54: 540.53 | U54: 2037.52 | V54: 584.36 | W54: 761.45 | X54: 839.92 | Y54: -17.62 | Z54: 2168.11 | AA54: 541.6 | AB54: 249.35
A55: 1 | C55: 판관비 | E55: 2616.51 | G55: 2517.4 | H55: 2055.13 | I55: 2808.68 | J55: 4660.07 | K55: 12041.28 | L55: 2919.14 | M55: 2438.55 | N55: 3011.36 | O55: 4196.4 | P55: 12565.45 | Q55: 3778.18 | R55: 2581.68 | S55: 2739.68 | T55: 2682.62 | U55: 11782.16 | V55: 2493.83 | W55: 2123.82 | X55: 1714.39 | Y55: 1115.36 | Z55: 7447.4 | AA55: 1364.71 | AB55: 1144.47
A56: 1 | C56: 영업이익 | E56: -2820.78 | G56: -2349.58 | H56: -1791.21 | I56: -2715.82 | J56: -4615.73 | K56: -11472.34 | L56: -2374.2 | M56: -1588.67 | N56: -2504.47 | O56: -4177.2 | P56: -10644.54 | Q56: -3070.71 | R56: -2291.42 | S56: -2240.4 | T56: -2142.09 | U56: -9744.62 | V56: -1909.47 | W56: -1362.37 | X56: -874.47 | Y56: -1132.98 | Z56: -5279.29 | AA56: -823.11 | AB56: -895.13
A57: 1 | C57: 금융수익 | E57: 3359.23 | G57: 92.1 | H57: 3214.06 | I57: -220.28 | J57: 5233.24 | K57: 8319.12 | L57: 318.02 | M57: 2537.46 | N57: 7568.99 | O57: -4485.78 | P57: 5938.69 | Q57: 458.14 | R57: 1097.83 | S57: -204.38 | T57: 833.77 | U57: 2185.36 | V57: 79.13 | W57: 89.71 | X57: 23.74 | Y57: 28.29 | Z57: 220.87 | AA57: 8.12 | AB57: 6.83
A58: 1 | C58: 금융비용 | E58: 8861.53 | G58: 750.23 | H58: 2839.34 | I58: 11951.42 | J58: 9290.51 | K58: 24831.5 | L58: 914.93 | M58: 7121.98 | N58: 11634.78 | O58: 4057.64 | P58: 23729.33 | Q58: 1314.2 | R58: 2982.02 | S58: 409.34 | T58: 3026.89 | U58: 7732.45 | V58: 680.88 | W58: 1326.86 | X58: 540.97 | Y58: 833.98 | Z58: 3382.69 | AA58: 302.8 | AB58: 181.94
A59: 1 | C59: 기타영업외수익 | E59: 17.51 | G59: 88.94 | H59: 125.74 | I59: 680.05 | J59: 872.59 | K59: 1767.32 | L59: 15.74 | M59: 4.62 | N59: 0.39 | O59: 1.98 | P59: 22.73 | Q59: 3.75 | R59: 7.37 | S59: 11.74 | T59: 21.97 | U59: 44.83 | V59: 189.76 | W59: 308.58 | X59: 7 | Y59: 442.53 | Z59: 947.87 | AA59: 21.38 | AB59: 133.07
A60: 1 | C60: 기타영업외비용 | E60: 649.61 | G60: 28.52 | H60: 35.63 | I60: -30.32 | J60: 4322.87 | K60: 4356.7 | L60: 8.93 | M60: 0.01 | N60: 16.61 | O60: 110.78 | P60: 136.33 | Q60: 1.52 | R60: 26.56 | S60: 0.01 | T60: 2833.54 | U60: 2861.63 | V60: 36.88 | W60: 998.86 | X60: 404.47 | Y60: -376.47 | Z60: 1063.74 | AA60: 330.86 | AB60: 59.2
A61: 1 | C61: 법인세비용차감전계속사업이익 | E61: -12311.42 | G61: -2854.54 | H61: -4525.01 | I61: -14177.15 | J61: -20548.07 | K61: -42104.77 | L61: -2965.8 | M61: -9203.97 | N61: -6835.31 | O61: -16752.53 | P61: -35757.61 | Q61: -3284.03 | R61: -6660.28 | S61: -3472.2 | T61: -6858.7 | U61: -20275.21 | V61: -2633.07 | W61: -4181.36 | X61: -1951.29 | Y61: -3085.68 | Z61: -11851.4 | AA61: -1427.27 | AB61: -1034.47
A62: 1 | C62: 당기순이익 | E62: -12311.42 | G62: -2854.54 | H62: -4525.01 | I62: -14177.15 | J62: -20548.07 | K62: -42104.77 | L62: -2965.8 | M62: -9203.97 | N62: -6835.31 | O62: -16752.53 | P62: -35757.61 | Q62: -3284.03 | R62: -6660.28 | S62: -3472.2 | T62: -6786.24 | U62: -20202.75 | V62: -2633.07 | W62: -4181.36 | X62: -1951.29 | Y62: -3085.68 | Z62: -11851.4 | AA62: -1427.27 | AB62: -1034.47
A63: 1 | C63: 총포괄손익 | E63: -12298.88 | G63: -2809.65 | H63: -4395.28 | I63: -14101.97 | J63: -20516.19 | K63: -41823.09 | L63: -3075.92 | M63: -9187.33 | N63: -6812.82 | O63: -14057.14 | P63: -33133.21 | Q63: -3076.49 | R63: -9141.24 | S63: -4077.7 | T63: -4281.12 | U63: -20576.55 | V63: -2937.43 | W63: -4365.37 | X63: -1687.56 | Y63: -3247.22 | Z63: -12237.58 | AA63: -1330.79 | AB63: -1098.12
... A74: 1 | C74: CAPEX | E74: 127.39 | G74: 71.18 | H74: 534.03 | I74: 524.31 | J74: 5146.95 | K74: 6276.47 | L74: 9.33 | M74: 199.6 | N74: 140 | O74: 111.44 | P74: 460.37 | Q74: 73.42 | R74: 84.36 | S74: 119.18 | T74: 89.89 | U74: 366.85 | V74: 20.61 | W74: 502.66 | X74: 211.23 | Y74: 39.52 | Z74: 774.02 | AA74: 60.9 | AB74: 241.77
A75: 1 | C75: 유형자산의감소 | E75: 24 | J75: 0.87 | O75: 0 | S75: 0 | T75: 20 | V75: 142 | W75: 3488.31 | X75: 4378.98 | Y75: 18.36 | Z75: 8027.65 | AA75: 6.9 | AB75: 0.88
A76: 1 | C76: 재무활동으로인한현금흐름 | E76: 15611.32 | G76: 256.08 | H76: 2653.68 | I76: 8276.24 | J76: 10380.09 | K76: 21566.09 | L76: 630.88 | M76: 7353.79 | N76: -358.31 | O76: 10566.23 | P76: 18192.59 | Q76: 3162.17 | R76: 422.44 | S76: 309.08 | T76: 381.69 | U76: 4275.38 | V76: 4615.11 | W76: -4308.68 | X76: -3258.33 | Y76: -272.72 | Z76: -3224.62 | AA76: -348.4 | AB76: -377.46
A77: 1 | C77: 단기차입금의증가 | E77: 3499.99 | J77: 6140.55 | Q77: 13055.53 | R77: 2133.24 | S77: 4019.34 | T77: 718.03 | U77: 19926.14 | V77: 133.77 | W77: 583.95 | X77: 1536.31 | Y77: 73.23 | Z77: 2327.26 | AA77: 66.74 | AB77: 117.72
A78: 1 | C78: 단기차입금의감소 | E78: 499.99 | G78: 3000 | H78: 0 | I78: 2356.45 | J78: 18017.13 | K78: 23373.58 | Q78: 321.47 | R78: 1427.25 | S78: 4426.42 | T78: 2030.15 | U78: 8205.29 | V78: 2211.5 | W78: 3287.52 | X78: 3036.56 | Y78: 114.04 | Z78: 8649.62 | AA78: 49.9 | AB78: 121.44
A79: 1 | C79: 장기차입금의증가 | E79: 0
A80: 1 | C80: 장기차입금의감소 | E80: 0
A81: 1 | C81: 현금및현금성자산의증감 | E81: 1008.83 | G81: 2207.06 | H81: -4897.91 | I81: 1519.87 | J81: -162.57 | K81: -1333.55 | L81: -1034.19 | M81: 5623.47 | N81: -5230.64 | O81: -357.5 | P81: -998.86 | Q81: 2724.11 | R81: -3487.13 | S81: -581.68 | T81: 792.79 | U81: -551.91 | V81: 3152.95 | W81: -3915.71 | X81: 107.77 | Y81: -253.21 | Z81: -908.2 | AA81: -281.55 | AB81: 4.73
A82: 1 | C82: 기말현금및현금성자산 | E82: 1008.82 | G82: 6316.21 | H82: -4897.91 | I82: 1519.87 | J82: -162.57 | K82: 2775.6 | L82: 1741.41 | M82: 5623.47 | N82: -5230.64 | O82: -357.5 | P82: 1776.74 | Q82: 4500.85 | R82: -3487.13 | S82: -581.67 | T82: 792.78 | U82: 1224.83 | V82: 4377.78 | W82: -3915.71 | X82: 107.77 | Y82: -253.21 | Z82: 316.63 | AA82: 35.09 | AB82: 4.72
A83: 1 | C83: 무형자산의증가 | I83: 0 | J83: 2749 | O83: 18 | S83: 0 | T83: 0
A84: 1 | C84: 자기주식의취득 | I84: -0.01 | Y84: 0
A85: 1 | C85: 배당금수취(CF) | J85: 0 | S85: 0 | T85: 0

Sheet subQ
A1: YQ | C1: subQ 분기 서브모델(억원, U=100) | E1: 4Q21 | F1: 2021 | G1: 1Q22 | H1: 2Q22 | I1: 3Q22 | J1: 4Q22 | K1: 2022 | L1: 1Q23 | M1: 2Q23 | N1: 3Q23 | O1: 4Q23 | P1: 2023 | Q1: 1Q24 | R1: 2Q24 | S1: 3Q24 | T1: 4Q24 | U1: 2024 | V1: 1Q25 | W1: 2Q25 | X1: 3Q25 | Y1: 4Q25 | Z1: 2025 | AA1: 1Q26 | AB1: 2Q26 | AC1: 3Q26 | AD1: 4Q26 | AE1: 2026 | AF1: 1Q27 | AG1: 2Q27 | AH1: 3Q27 | AI1: 4Q27 | AJ1: 2027 | AK1: 1Q28 | AL1: 2Q28 | AM1: 3Q28 | AN1: 4Q28 | AO1: 2028
A2: A=이름(key) B=그룹 C=단위 D=FnGuide 계정명(VLOOKUP 키). 확정=VLOOKUP(BS), 추정=변수 가정 참조
E3: 1 | F3: 2 | G3: 3 | H3: 4 | I3: 5 | J3: 6 | K3: 7 | L3: 8 | M3: 9 | N3: 10 | O3: 11 | P3: 12 | Q3: 13 | R3: 14 | S3: 15 | T3: 16 | U3: 17 | V3: 18 | W3: 19 | X3: 20 | Y3: 21 | Z3: 22 | AA3: 23 | AB3: 24 | AC3: 25 | AD3: 26 | AE3: 27 | AF3: 28 | AG3: 29 | AH3: 30 | AI3: 31 | AJ3: 32 | AK3: 33 | AL3: 34 | AM3: 35 | AN3: 36 | AO3: 37
E4: 2021.12 | F4: 2021.12A | G4: 2022.03 | H4: 2022.06 | I4: 2022.09 | J4: 2022.12 | K4: 2022.12A | L4: 2023.03 | M4: 2023.06 | N4: 2023.09 | O4: 2023.12 | P4: 2023.12A | Q4: 2024.03 | R4: 2024.06 | S4: 2024.09 | T4: 2024.12 | U4: 2024.12A | V4: 2025.03 | W4: 2025.06 | X4: 2025.09 | Y4: 2025.12 | Z4: 2025.12A | AA4: 2026.03 | AB4: 2026.06 | AC4: 2026.09 | AD4: 2026.12 | AE4: 2026.12A | AF4: 2027.03 | AG4: 2027.06 | AH4: 2027.09 | AI4: 2027.12 | AJ4: 2027.12A | AK4: 2028.03 | AL4: 2028.06 | AM4: 2028.09 | AN4: 2028.12 | AO4: 2028.12A
A5: 매출액 | B5: 손익 | C5: 억원 | D5: 매출액(수익) | E5: =IFERROR(VLOOKUP($D5,BS연결,MATCH(E$1,BS연결H,0),0)/100,"") | G5: =IFERROR(VLOOKUP($D5,BS연결,MATCH(G$1,BS연결H,0),0)/100,"") | H5: =IFERROR(VLOOKUP($D5,BS연결,MATCH(H$1,BS연결H,0),0)/100,"") | I5: =IFERROR(VLOOKUP($D5,BS연결,MATCH(I$1,BS연결H,0),0)/100,"") | J5: =IFERROR(VLOOKUP($D5,BS연결,MATCH(J$1,BS연결H,0),0)/100,"") | K5: =IFERROR(VLOOKUP($D5,BS연결,MATCH(K$1,BS연결H,0),0)/100,"") | L5: =IFERROR(VLOOKUP($D5,BS연결,MATCH(L$1,BS연결H,0),0)/100,"") | M5: =IFERROR(VLOOKUP($D5,BS연결,MATCH(M$1,BS연결H,0),0)/100,"") | N5: =IFERROR(VLOOKUP($D5,BS연결,MATCH(N$1,BS연결H,0),0)/100,"") | ... AB5: =IFERROR(VLOOKUP($D5,BS연결,MATCH(AB$1,BS연결H,0),0)/100,"") | AC5: =IFERROR(X5*(1+변수!AC21),"") | AD5: =IFERROR(Y5*(1+변수!AD21),"") | AE5: =SUM(AA5:AD5) | AF5: =IFERROR(AA5*(1+변수!AF21),"") | AG5: =IFERROR(AB5*(1+변수!AG21),"") | AH5: =IFERROR(AC5*(1+변수!AH21),"") | AI5: =IFERROR(AD5*(1+변수!AI21),"") | AJ5: =SUM(AF5:AI5) | AK5: =IFERROR(AF5*(1+변수!AK21),"") | AL5: =IFERROR(AG5*(1+변수!AL21),"") | AM5: =IFERROR(AH5*(1+변수!AM21),"") | AN5: =IFERROR(AI5*(1+변수!AN21),"") | AO5: =SUM(AK5:AN5)
A6: 매출원가 | B6: 손익 | C6: 억원 | D6: 매출원가 | E6: =IFERROR(VLOOKUP($D6,BS연결,MATCH(E$1,BS연결H,0),0)/100,"") | G6: =IFERROR(VLOOKUP($D6,BS연결,MATCH(G$1,BS연결H,0),0)/100,"") | H6: =IFERROR(VLOOKUP($D6,BS연결,MATCH(H$1,BS연결H,0),0)/100,"") | I6: =IFERROR(VLOOKUP($D6,BS연결,MATCH(I$1,BS연결H,0),0)/100,"") | J6: =IFERROR(VLOOKUP($D6,BS연결,MATCH(J$1,BS연결H,0),0)/100,"") | K6: =IFERROR(VLOOKUP($D6,BS연결,MATCH(K$1,BS연결H,0),0)/100,"") | L6: =IFERROR(VLOOKUP($D6,BS연결,MATCH(L$1,BS연결H,0),0)/100,"") | M6: =IFERROR(VLOOKUP($D6,BS연결,MATCH(M$1,BS연결H,0),0)/100,"") | N6: =IFERROR(VLOOKUP($D6,BS연결,MATCH(N$1,BS연결H,0),0)/100,"") | ... AB6: =IFERROR(VLOOKUP($D6,BS연결,MATCH(AB$1,BS연결H,0),0)/100,"") | AC6: =IFERROR(AC5-AC7,"") | AD6: =IFERROR(AD5-AD7,"") | AE6: =SUM(AA6:AD6) | AF6: =IFERROR(AF5-AF7,"") | AG6: =IFERROR(AG5-AG7,"") | AH6: =IFERROR(AH5-AH7,"") | AI6: =IFERROR(AI5-AI7,"") | AJ6: =SUM(AF6:AI6) | AK6: =IFERROR(AK5-AK7,"") | AL6: =IFERROR(AL5-AL7,"") | AM6: =IFERROR(AM5-AM7,"") | AN6: =IFERROR(AN5-AN7,"") | AO6: =SUM(AK6:AN6)
A7: 매출총이익 | B7: 손익 | C7: 억원 | D7: 매출총이익 | E7: =IFERROR(VLOOKUP($D7,BS연결,MATCH(E$1,BS연결H,0),0)/100,"") | G7: =IFERROR(VLOOKUP($D7,BS연결,MATCH(G$1,BS연결H,0),0)/100,"") | H7: =IFERROR(VLOOKUP($D7,BS연결,MATCH(H$1,BS연결H,0),0)/100,"") | I7: =IFERROR(VLOOKUP($D7,BS연결,MATCH(I$1,BS연결H,0),0)/100,"") | J7: =IFERROR(VLOOKUP($D7,BS연결,MATCH(J$1,BS연결H,0),0)/100,"") | K7: =IFERROR(VLOOKUP($D7,BS연결,MATCH(K$1,BS연결H,0),0)/100,"") | L7: =IFERROR(VLOOKUP($D7,BS연결,MATCH(L$1,BS연결H,0),0)/100,"") | M7: =IFERROR(VLOOKUP($D7,BS연결,MATCH(M$1,BS연결H,0),0)/100,"") | N7: =IFERROR(VLOOKUP($D7,BS연결,MATCH(N$1,BS연결H,0),0)/100,"") | ... Y7: =IFERROR(VLOOKUP($D7,BS연결,MATCH(Y$1,BS연결H,0),0)/100,"") | Z7: =SUM(V7:Y7) | AA7: =IFERROR(VLOOKUP($D7,BS연결,MATCH(AA$1,BS연결H,0),0)/100,"") | AB7: =IFERROR(VLOOKUP($D7,BS연결,MATCH(AB$1,BS연결H,0),0)/100,"") | AC7: =IFERROR(AC9+AC8,"") | AD7: =IFERROR(AD9+AD8,"") | AE7: =SUM(AA7:AD7) | AF7: =IFERROR(AF9+AF8,"") | AG7: =IFERROR(AG9+AG8,"") | AH7: =IFERROR(AH9+AH8,"") | AI7: =IFERROR(AI9+AI8,"") | AJ7: =SUM(AF7:AI7) | AK7: =IFERROR(AK9+AK8,"") | AL7: =IFERROR(AL9+AL8,"") | AM7: =IFERROR(AM9+AM8,"") | AN7: =IFERROR(AN9+AN8,"") | AO7: =SUM(AK7:AN7)
A8: 판관비 | B8: 손익 | C8: 억원 | D8: 판관비 | E8: =IFERROR(VLOOKUP($D8,BS연결,MATCH(E$1,BS연결H,0),0)/100,"") | G8: =IFERROR(VLOOKUP($D8,BS연결,MATCH(G$1,BS연결H,0),0)/100,"") | H8: =IFERROR(VLOOKUP($D8,BS연결,MATCH(H$1,BS연결H,0),0)/100,"") | I8: =IFERROR(VLOOKUP($D8,BS연결,MATCH(I$1,BS연결H,0),0)/100,"") | J8: =IFERROR(VLOOKUP($D8,BS연결,MATCH(J$1,BS연결H,0),0)/100,"") | K8: =IFERROR(VLOOKUP($D8,BS연결,MATCH(K$1,BS연결H,0),0)/100,"") | L8: =IFERROR(VLOOKUP($D8,BS연결,MATCH(L$1,BS연결H,0),0)/100,"") | M8: =IFERROR(VLOOKUP($D8,BS연결,MATCH(M$1,BS연결H,0),0)/100,"") | N8: =IFERROR(VLOOKUP($D8,BS연결,MATCH(N$1,BS연결H,0),0)/100,"") | ... AB8: =IFERROR(VLOOKUP($D8,BS연결,MATCH(AB$1,BS연결H,0),0)/100,"") | AC8: =IFERROR(AC5*변수!AC22,"") | AD8: =IFERROR(AD5*변수!AD22,"") | AE8: =SUM(AA8:AD8) | AF8: =IFERROR(AF5*변수!AF22,"") | AG8: =IFERROR(AG5*변수!AG22,"") | AH8: =IFERROR(AH5*변수!AH22,"") | AI8: =IFERROR(AI5*변수!AI22,"") | AJ8: =SUM(AF8:AI8) | AK8: =IFERROR(AK5*변수!AK22,"") | AL8: =IFERROR(AL5*변수!AL22,"") | AM8: =IFERROR(AM5*변수!AM22,"") | AN8: =IFERROR(AN5*변수!AN22,"") | AO8: =SUM(AK8:AN8)
A9: 영업이익 | B9: 손익 | C9: 억원 | D9: 영업이익 | E9: =IFERROR(VLOOKUP($D9,BS연결,MATCH(E$1,BS연결H,0),0)/100,"") | G9: =IFERROR(VLOOKUP($D9,BS연결,MATCH(G$1,BS연결H,0),0)/100,"") | H9: =IFERROR(VLOOKUP($D9,BS연결,MATCH(H$1,BS연결H,0),0)/100,"") | I9: =IFERROR(VLOOKUP($D9,BS연결,MATCH(I$1,BS연결H,0),0)/100,"") | J9: =IFERROR(VLOOKUP($D9,BS연결,MATCH(J$1,BS연결H,0),0)/100,"") | K9: =IFERROR(VLOOKUP($D9,BS연결,MATCH(K$1,BS연결H,0),0)/100,"") | L9: =IFERROR(VLOOKUP($D9,BS연결,MATCH(L$1,BS연결H,0),0)/100,"") | M9: =IFERROR(VLOOKUP($D9,BS연결,MATCH(M$1,BS연결H,0),0)/100,"") | N9: =IFERROR(VLOOKUP($D9,BS연결,MATCH(N$1,BS연결H,0),0)/100,"") | ... AB9: =IFERROR(VLOOKUP($D9,BS연결,MATCH(AB$1,BS연결H,0),0)/100,"") | AC9: =IFERROR(AC5*변수!AC23,"") | AD9: =IFERROR(AD5*변수!AD23,"") | AE9: =SUM(AA9:AD9) | AF9: =IFERROR(AF5*변수!AF23,"") | AG9: =IFERROR(AG5*변수!AG23,"") | AH9: =IFERROR(AH5*변수!AH23,"") | AI9: =IFERROR(AI5*변수!AI23,"") | AJ9: =SUM(AF9:AI9) | AK9: =IFERROR(AK5*변수!AK23,"") | AL9: =IFERROR(AL5*변수!AL23,"") | AM9: =IFERROR(AM5*변수!AM23,"") | AN9: =IFERROR(AN5*변수!AN23,"") | AO9: =SUM(AK9:AN9)
A10: OPM | B10: 손익 | C10: % | D10: 영업이익률 | E10: =IFERROR(E9/E5,"") | G10: =IFERROR(G9/G5,"") | H10: =IFERROR(H9/H5,"") | I10: =IFERROR(I9/I5,"") | J10: =IFERROR(J9/J5,"") | K10: =IFERROR(K9/K5,"") | L10: =IFERROR(L9/L5,"") | M10: =IFERROR(M9/M5,"") | N10: =IFERROR(N9/N5,"") | ... AO10: =IFERROR(AO9/AO5,"")
A11: 금융손익 | B11: 손익 | C11: 억원 | D11: 금융손익 | E11: =IFERROR(VLOOKUP($D11,BS연결,MATCH(E$1,BS연결H,0),0)/100,"") | G11: =IFERROR(VLOOKUP($D11,BS연결,MATCH(G$1,BS연결H,0),0)/100,"") | H11: =IFERROR(VLOOKUP($D11,BS연결,MATCH(H$1,BS연결H,0),0)/100,"") | I11: =IFERROR(VLOOKUP($D11,BS연결,MATCH(I$1,BS연결H,0),0)/100,"") | J11: =IFERROR(VLOOKUP($D11,BS연결,MATCH(J$1,BS연결H,0),0)/100,"") | K11: =SUM(G11:J11) | L11: =IFERROR(VLOOKUP($D11,BS연결,MATCH(L$1,BS연결H,0),0)/100,"") | M11: =IFERROR(VLOOKUP($D11,BS연결,MATCH(M$1,BS연결H,0),0)/100,"") | N11: =IFERROR(VLOOKUP($D11,BS연결,MATCH(N$1,BS연결H,0),0)/100,"") | O11: =IFERROR(VLOOKUP($D11,BS연결,MATCH(O$1,BS연결H,0),0)/100,"") | P11: =IFERROR(VLOOKUP($D11,BS연결,MATCH(P$1,BS연결H,0),0)/100,"") | Q11: =IFERROR(VLOOKUP($D11,BS연결,MATCH(Q$1,BS연결H,0),0)/100,"") | R11: =IFERROR(VLOOKUP($D11,BS연결,MATCH(R$1,BS연결H,0),0)/100,"") | S11: =IFERROR(VLOOKUP($D11,BS연결,MATCH(S$1,BS연결H,0),0)/100,"") | ... AB11: =IFERROR(VLOOKUP($D11,BS연결,MATCH(AB$1,BS연결H,0),0)/100,"") | AC11: =IFERROR(AC12+AC13,"") | AD11: =IFERROR(AD12+AD13,"") | AE11: =SUM(AA11:AD11) | AF11: =IFERROR(AF12+AF13,"") | AG11: =IFERROR(AG12+AG13,"") | AH11: =IFERROR(AH12+AH13,"") | AI11: =IFERROR(AI12+AI13,"") | AJ11: =SUM(AF11:AI11) | AK11: =IFERROR(AK12+AK13,"") | AL11: =IFERROR(AL12+AL13,"") | AM11: =IFERROR(AM12+AM13,"") | AN11: =IFERROR(AN12+AN13,"") | AO11: =SUM(AK11:AN11)
A12: 이자손익 | B12: 손익 | C12: 억원 | D12: 이자손익 | G12: =IFERROR(VLOOKUP($D12,BS연결,MATCH(G$1,BS연결H,0),0)/100,"") | H12: =IFERROR(VLOOKUP($D12,BS연결,MATCH(H$1,BS연결H,0),0)/100,"") | I12: =IFERROR(VLOOKUP($D12,BS연결,MATCH(I$1,BS연결H,0),0)/100,"") | J12: =IFERROR(VLOOKUP($D12,BS연결,MATCH(J$1,BS연결H,0),0)/100,"") | K12: =IFERROR(VLOOKUP($D12,BS연결,MATCH(K$1,BS연결H,0),0)/100,"") | L12: =IFERROR(VLOOKUP($D12,BS연결,MATCH(L$1,BS연결H,0),0)/100,"") | M12: =IFERROR(VLOOKUP($D12,BS연결,MATCH(M$1,BS연결H,0),0)/100,"") | N12: =IFERROR(VLOOKUP($D12,BS연결,MATCH(N$1,BS연결H,0),0)/100,"") | ... AB12: =IFERROR(VLOOKUP($D12,BS연결,MATCH(AB$1,BS연결H,0),0)/100,"") | AC12: =IFERROR((AB27*변수!$D$53-AB25*변수!$D$54)/4,"") | AD12: =IFERROR((AC27*변수!$D$53-AC25*변수!$D$54)/4,"") | AE12: =SUM(AA12:AD12) | AF12: =IFERROR((AD27*변수!$D$53-AD25*변수!$D$54)/4,"") | AG12: =IFERROR((AF27*변수!$D$53-AF25*변수!$D$54)/4,"") | AH12: =IFERROR((AG27*변수!$D$53-AG25*변수!$D$54)/4,"") | AI12: =IFERROR((AH27*변수!$D$53-AH25*변수!$D$54)/4,"") | AJ12: =SUM(AF12:AI12) | AK12: =IFERROR((AI27*변수!$D$53-AI25*변수!$D$54)/4,"") | AL12: =IFERROR((AK27*변수!$D$53-AK25*변수!$D$54)/4,"") | AM12: =IFERROR((AL27*변수!$D$53-AL25*변수!$D$54)/4,"") | AN12: =IFERROR((AM27*변수!$D$53-AM25*변수!$D$54)/4,"") | AO12: =SUM(AK12:AN12)
A13: 파생상품손익 | B13: 손익 | C13: 억원 | D13: 파생상품손익 | H13: =IFERROR((VLOOKUP("파생상품이익",BS연결,MATCH(H$1,BS연결H,0),0)-VLOOKUP("파생상품손실",BS연결,MATCH(H$1,BS연결H,0),0))/100,"") | I13: =IFERROR((VLOOKUP("파생상품이익",BS연결,MATCH(I$1,BS연결H,0),0)-VLOOKUP("파생상품손실",BS연결,MATCH(I$1,BS연결H,0),0))/100,"") | J13: =IFERROR((VLOOKUP("파생상품이익",BS연결,MATCH(J$1,BS연결H,0),0)-VLOOKUP("파생상품손실",BS연결,MATCH(J$1,BS연결H,0),0))/100,"") | K13: =SUM(G13:J13) | M13: =IFERROR((VLOOKUP("파생상품이익",BS연결,MATCH(M$1,BS연결H,0),0)-VLOOKUP("파생상품손실",BS연결,MATCH(M$1,BS연결H,0),0))/100,"") | N13: =IFERROR((VLOOKUP("파생상품이익",BS연결,MATCH(N$1,BS연결H,0),0)-VLOOKUP("파생상품손실",BS연결,MATCH(N$1,BS연결H,0),0))/100,"") | O13: =IFERROR((VLOOKUP("파생상품이익",BS연결,MATCH(O$1,BS연결H,0),0)-VLOOKUP("파생상품손실",BS연결,MATCH(O$1,BS연결H,0),0))/100,"") | P13: =SUM(L13:O13) | Q13: =IFERROR((VLOOKUP("파생상품이익",BS연결,MATCH(Q$1,BS연결H,0),0)-VLOOKUP("파생상품손실",BS연결,MATCH(Q$1,BS연결H,0),0))/100,"") | U13: =SUM(Q13:T13) | Z13: =SUM(V13:Y13) | AC13: =변수!AC24 | AD13: =변수!AD24 | AE13: =SUM(AA13:AD13) | AF13: =변수!AF24 | AG13: =변수!AG24 | AH13: =변수!AH24 | AI13: =변수!AI24 | AJ13: =SUM(AF13:AI13) | AK13: =변수!AK24 | AL13: =변수!AL24 | AM13: =변수!AM24 | AN13: =변수!AN24 | AO13: =SUM(AK13:AN13)
A14: 기타영업외손익 | B14: 손익 | C14: 억원 | D14: 기타영업외손익 | E14: =IFERROR(VLOOKUP($D14,BS연결,MATCH(E$1,BS연결H,0),0)/100,"") | G14: =IFERROR(VLOOKUP($D14,BS연결,MATCH(G$1,BS연결H,0),0)/100,"") | H14: =IFERROR(VLOOKUP($D14,BS연결,MATCH(H$1,BS연결H,0),0)/100,"") | I14: =IFERROR(VLOOKUP($D14,BS연결,MATCH(I$1,BS연결H,0),0)/100,"") | J14: =IFERROR(VLOOKUP($D14,BS연결,MATCH(J$1,BS연결H,0),0)/100,"") | K14: =IFERROR(VLOOKUP($D14,BS연결,MATCH(K$1,BS연결H,0),0)/100,"") | L14: =IFERROR(VLOOKUP($D14,BS연결,MATCH(L$1,BS연결H,0),0)/100,"") | M14: =IFERROR(VLOOKUP($D14,BS연결,MATCH(M$1,BS연결H,0),0)/100,"") | N14: =IFERROR(VLOOKUP($D14,BS연결,MATCH(N$1,BS연결H,0),0)/100,"") | ... AB14: =IFERROR(VLOOKUP($D14,BS연결,MATCH(AB$1,BS연결H,0),0)/100,"") | AC14: =변수!AC25 | AD14: =변수!AD25 | AE14: =SUM(AA14:AD14) | AF14: =변수!AF25 | AG14: =변수!AG25 | AH14: =변수!AH25 | AI14: =변수!AI25 | AJ14: =SUM(AF14:AI14) | AK14: =변수!AK25 | AL14: =변수!AL25 | AM14: =변수!AM25 | AN14: =변수!AN25 | AO14: =SUM(AK14:AN14)
A15: 지분법손익 | B15: 손익 | C15: 억원 | D15: 종속기업,공동지배기업및관계기업관련손익 | E15: =IFERROR(VLOOKUP($D15,BS연결,MATCH(E$1,BS연결H,0),0)/100,"") | G15: =IFERROR(VLOOKUP($D15,BS연결,MATCH(G$1,BS연결H,0),0)/100,"") | H15: =IFERROR(VLOOKUP($D15,BS연결,MATCH(H$1,BS연결H,0),0)/100,"") | I15: =IFERROR(VLOOKUP($D15,BS연결,MATCH(I$1,BS연결H,0),0)/100,"") | J15: =IFERROR(VLOOKUP($D15,BS연결,MATCH(J$1,BS연결H,0),0)/100,"") | K15: =IFERROR(VLOOKUP($D15,BS연결,MATCH(K$1,BS연결H,0),0)/100,"") | M15: =IFERROR(VLOOKUP($D15,BS연결,MATCH(M$1,BS연결H,0),0)/100,"") | O15: =IFERROR(VLOOKUP($D15,BS연결,MATCH(O$1,BS연결H,0),0)/100,"") | P15: =SUM(L15:O15) | Q15: =IFERROR(VLOOKUP($D15,BS연결,MATCH(Q$1,BS연결H,0),0)/100,"") | R15: =IFERROR(VLOOKUP($D15,BS연결,MATCH(R$1,BS연결H,0),0)/100,"") | S15: =IFERROR(VLOOKUP($D15,BS연결,MATCH(S$1,BS연결H,0),0)/100,"") | T15: =IFERROR(VLOOKUP($D15,BS연결,MATCH(T$1,BS연결H,0),0)/100,"") | U15: =IFERROR(VLOOKUP($D15,BS연결,MATCH(U$1,BS연결H,0),0)/100,"") | V15: =IFERROR(VLOOKUP($D15,BS연결,MATCH(V$1,BS연결H,0),0)/100,"") | W15: =IFERROR(VLOOKUP($D15,BS연결,MATCH(W$1,BS연결H,0),0)/100,"") | X15: =IFERROR(VLOOKUP($D15,BS연결,MATCH(X$1,BS연결H,0),0)/100,"") | ... Z15: =IFERROR(VLOOKUP($D15,BS연결,MATCH(Z$1,BS연결H,0),0)/100,"") | AB15: =IFERROR(VLOOKUP($D15,BS연결,MATCH(AB$1,BS연결H,0),0)/100,"") | AC15: =변수!AC26 | AD15: =변수!AD26 | AE15: =SUM(AA15:AD15) | AF15: =변수!AF26 | AG15: =변수!AG26 | AH15: =변수!AH26 | AI15: =변수!AI26 | AJ15: =SUM(AF15:AI15) | AK15: =변수!AK26 | AL15: =변수!AL26 | AM15: =변수!AM26 | AN15: =변수!AN26 | AO15: =SUM(AK15:AN15)
A16: 세전이익 | B16: 손익 | C16: 억원 | D16: 법인세비용차감전계속사업이익 | E16: =IFERROR(VLOOKUP($D16,BS연결,MATCH(E$1,BS연결H,0),0)/100,"") | G16: =IFERROR(VLOOKUP($D16,BS연결,MATCH(G$1,BS연결H,0),0)/100,"") | H16: =IFERROR(VLOOKUP($D16,BS연결,MATCH(H$1,BS연결H,0),0)/100,"") | I16: =IFERROR(VLOOKUP($D16,BS연결,MATCH(I$1,BS연결H,0),0)/100,"") | J16: =IFERROR(VLOOKUP($D16,BS연결,MATCH(J$1,BS연결H,0),0)/100,"") | K16: =IFERROR(VLOOKUP($D16,BS연결,MATCH(K$1,BS연결H,0),0)/100,"") | L16: =IFERROR(VLOOKUP($D16,BS연결,MATCH(L$1,BS연결H,0),0)/100,"") | M16: =IFERROR(VLOOKUP($D16,BS연결,MATCH(M$1,BS연결H,0),0)/100,"") | N16: =IFERROR(VLOOKUP($D16,BS연결,MATCH(N$1,BS연결H,0),0)/100,"") | ... AB16: =IFERROR(VLOOKUP($D16,BS연결,MATCH(AB$1,BS연결H,0),0)/100,"") | AC16: =IFERROR(AC9+AC11+AC14+AC15,"") | AD16: =IFERROR(AD9+AD11+AD14+AD15,"") | AE16: =SUM(AA16:AD16) | AF16: =IFERROR(AF9+AF11+AF14+AF15,"") | AG16: =IFERROR(AG9+AG11+AG14+AG15,"") | AH16: =IFERROR(AH9+AH11+AH14+AH15,"") | AI16: =IFERROR(AI9+AI11+AI14+AI15,"") | AJ16: =SUM(AF16:AI16) | AK16: =IFERROR(AK9+AK11+AK14+AK15,"") | AL16: =IFERROR(AL9+AL11+AL14+AL15,"") | AM16: =IFERROR(AM9+AM11+AM14+AM15,"") | AN16: =IFERROR(AN9+AN11+AN14+AN15,"") | AO16: =SUM(AK16:AN16)
A17: 법인세비용 | B17: 손익 | C17: 억원 | D17: 법인세비용 | K17: =SUM(G17:J17) | P17: =SUM(L17:O17) | U17: =SUM(Q17:T17) | Z17: =SUM(V17:Y17) | AC17: =IFERROR(AC16*변수!AC27,"") | AD17: =IFERROR(AD16*변수!AD27,"") | AE17: =SUM(AA17:AD17) | AF17: =IFERROR(AF16*변수!AF27,"") | AG17: =IFERROR(AG16*변수!AG27,"") | AH17: =IFERROR(AH16*변수!AH27,"") | AI17: =IFERROR(AI16*변수!AI27,"") | AJ17: =SUM(AF17:AI17) | AK17: =IFERROR(AK16*변수!AK27,"") | AL17: =IFERROR(AL16*변수!AL27,"") | AM17: =IFERROR(AM16*변수!AM27,"") | AN17: =IFERROR(AN16*변수!AN27,"") | AO17: =SUM(AK17:AN17)
A18: 당기순이익 | B18: 손익 | C18: 억원 | D18: 당기순이익 | E18: =IFERROR(VLOOKUP($D18,BS연결,MATCH(E$1,BS연결H,0),0)/100,"") | G18: =IFERROR(VLOOKUP($D18,BS연결,MATCH(G$1,BS연결H,0),0)/100,"") | H18: =IFERROR(VLOOKUP($D18,BS연결,MATCH(H$1,BS연결H,0),0)/100,"") | I18: =IFERROR(VLOOKUP($D18,BS연결,MATCH(I$1,BS연결H,0),0)/100,"") | J18: =IFERROR(VLOOKUP($D18,BS연결,MATCH(J$1,BS연결H,0),0)/100,"") | K18: =IFERROR(VLOOKUP($D18,BS연결,MATCH(K$1,BS연결H,0),0)/100,"") | L18: =IFERROR(VLOOKUP($D18,BS연결,MATCH(L$1,BS연결H,0),0)/100,"") | M18: =IFERROR(VLOOKUP($D18,BS연결,MATCH(M$1,BS연결H,0),0)/100,"") | N18: =IFERROR(VLOOKUP($D18,BS연결,MATCH(N$1,BS연결H,0),0)/100,"") | ... AB18: =IFERROR(VLOOKUP($D18,BS연결,MATCH(AB$1,BS연결H,0),0)/100,"") | AC18: =IFERROR(AC16-AC17,"") | AD18: =IFERROR(AD16-AD17,"") | AE18: =SUM(AA18:AD18) | AF18: =IFERROR(AF16-AF17,"") | AG18: =IFERROR(AG16-AG17,"") | AH18: =IFERROR(AH16-AH17,"") | AI18: =IFERROR(AI16-AI17,"") | AJ18: =SUM(AF18:AI18) | AK18: =IFERROR(AK16-AK17,"") | AL18: =IFERROR(AL16-AL17,"") | AM18: =IFERROR(AM16-AM17,"") | AN18: =IFERROR(AN16-AN17,"") | AO18: =SUM(AK18:AN18)
A19: 지배주주순이익 | B19: 손익 | C19: 억원 | D19: (지배주주지분)당기순이익 | E19: =IFERROR(VLOOKUP($D19,BS연결,MATCH(E$1,BS연결H,0),0)/100,"") | G19: =IFERROR(VLOOKUP($D19,BS연결,MATCH(G$1,BS연결H,0),0)/100,"") | H19: =IFERROR(VLOOKUP($D19,BS연결,MATCH(H$1,BS연결H,0),0)/100,"") | I19: =IFERROR(VLOOKUP($D19,BS연결,MATCH(I$1,BS연결H,0),0)/100,"") | J19: =IFERROR(VLOOKUP($D19,BS연결,MATCH(J$1,BS연결H,0),0)/100,"") | K19: =IFERROR(VLOOKUP($D19,BS연결,MATCH(K$1,BS연결H,0),0)/100,"") | L19: =IFERROR(VLOOKUP($D19,BS연결,MATCH(L$1,BS연결H,0),0)/100,"") | M19: =IFERROR(VLOOKUP($D19,BS연결,MATCH(M$1,BS연결H,0),0)/100,"") | N19: =IFERROR(VLOOKUP($D19,BS연결,MATCH(N$1,BS연결H,0),0)/100,"") | ... AB19: =IFERROR(VLOOKUP($D19,BS연결,MATCH(AB$1,BS연결H,0),0)/100,"") | AC19: =IFERROR(AC18*변수!AC28,"") | AD19: =IFERROR(AD18*변수!AD28,"") | AE19: =SUM(AA19:AD19) | AF19: =IFERROR(AF18*변수!AF28,"") | AG19: =IFERROR(AG18*변수!AG28,"") | AH19: =IFERROR(AH18*변수!AH28,"") | AI19: =IFERROR(AI18*변수!AI28,"") | AJ19: =SUM(AF19:AI19) | AK19: =IFERROR(AK18*변수!AK28,"") | AL19: =IFERROR(AL18*변수!AL28,"") | AM19: =IFERROR(AM18*변수!AM28,"") | AN19: =IFERROR(AN18*변수!AN28,"") | AO19: =SUM(AK19:AN19)
A20: 중단사업이익 | B20: 손익 | C20: 억원 | D20: 중단사업이익 | K20: =SUM(G20:J20) | O20: =IFERROR(VLOOKUP($D20,BS연결,MATCH(O$1,BS연결H,0),0)/100,"") | P20: =SUM(L20:O20) | Q20: =IFERROR(VLOOKUP($D20,BS연결,MATCH(Q$1,BS연결H,0),0)/100,"") | R20: =IFERROR(VLOOKUP($D20,BS연결,MATCH(R$1,BS연결H,0),0)/100,"") | T20: =IFERROR(VLOOKUP($D20,BS연결,MATCH(T$1,BS연결H,0),0)/100,"") | U20: =SUM(Q20:T20) | Z20: =SUM(V20:Y20) | AE20: =SUM(AA20:AD20) | AJ20: =SUM(AF20:AI20) | AO20: =SUM(AK20:AN20)
A21: 자산총계 | B21: 재무상태 | C21: 억원 | D21: 자산총계 | E21: =IFERROR(VLOOKUP($D21,BS연결,MATCH(E$1,BS연결H,0),0)/100,"") | F21: =IFERROR(VLOOKUP($D21,BS연결,MATCH(F$1,BS연결H,0),0)/100,"") | G21: =IFERROR(VLOOKUP($D21,BS연결,MATCH(G$1,BS연결H,0),0)/100,"") | H21: =IFERROR(VLOOKUP($D21,BS연결,MATCH(H$1,BS연결H,0),0)/100,"") | I21: =IFERROR(VLOOKUP($D21,BS연결,MATCH(I$1,BS연결H,0),0)/100,"") | J21: =IFERROR(VLOOKUP($D21,BS연결,MATCH(J$1,BS연결H,0),0)/100,"") | K21: =IFERROR(VLOOKUP($D21,BS연결,MATCH(K$1,BS연결H,0),0)/100,"") | L21: =IFERROR(VLOOKUP($D21,BS연결,MATCH(L$1,BS연결H,0),0)/100,"") | ... AB21: =IFERROR(VLOOKUP($D21,BS연결,MATCH(AB$1,BS연결H,0),0)/100,"") | AC21: =IFERROR(AC22+AC23,"") | AD21: =IFERROR(AD22+AD23,"") | AE21: =AD21 | AF21: =IFERROR(AF22+AF23,"") | AG21: =IFERROR(AG22+AG23,"") | AH21: =IFERROR(AH22+AH23,"") | AI21: =IFERROR(AI22+AI23,"") | AJ21: =AI21 | AK21: =IFERROR(AK22+AK23,"") | AL21: =IFERROR(AL22+AL23,"") | AM21: =IFERROR(AM22+AM23,"") | AN21: =IFERROR(AN22+AN23,"") | AO21: =AN21
A22: 부채총계 | B22: 재무상태 | C22: 억원 | D22: 부채총계 | E22: =IFERROR(VLOOKUP($D22,BS연결,MATCH(E$1,BS연결H,0),0)/100,"") | F22: =IFERROR(VLOOKUP($D22,BS연결,MATCH(F$1,BS연결H,0),0)/100,"") | G22: =IFERROR(VLOOKUP($D22,BS연결,MATCH(G$1,BS연결H,0),0)/100,"") | H22: =IFERROR(VLOOKUP($D22,BS연결,MATCH(H$1,BS연결H,0),0)/100,"") | I22: =IFERROR(VLOOKUP($D22,BS연결,MATCH(I$1,BS연결H,0),0)/100,"") | J22: =IFERROR(VLOOKUP($D22,BS연결,MATCH(J$1,BS연결H,0),0)/100,"") | K22: =IFERROR(VLOOKUP($D22,BS연결,MATCH(K$1,BS연결H,0),0)/100,"") | L22: =IFERROR(VLOOKUP($D22,BS연결,MATCH(L$1,BS연결H,0),0)/100,"") | ... AB22: =IFERROR(VLOOKUP($D22,BS연결,MATCH(AB$1,BS연결H,0),0)/100,"") | AC22: =IFERROR(AB22*(1+변수!AC30),"") | AD22: =IFERROR(AC22*(1+변수!AD30),"") | AE22: =AD22 | AF22: =IFERROR(AD22*(1+변수!AF30),"") | AG22: =IFERROR(AF22*(1+변수!AG30),"") | AH22: =IFERROR(AG22*(1+변수!AH30),"") | AI22: =IFERROR(AH22*(1+변수!AI30),"") | AJ22: =AI22 | AK22: =IFERROR(AI22*(1+변수!AK30),"") | AL22: =IFERROR(AK22*(1+변수!AL30),"") | AM22: =IFERROR(AL22*(1+변수!AM30),"") | AN22: =IFERROR(AM22*(1+변수!AN30),"") | AO22: =AN22
A23: 자본총계 | B23: 재무상태 | C23: 억원 | D23: 자본총계 | E23: =IFERROR(VLOOKUP($D23,BS연결,MATCH(E$1,BS연결H,0),0)/100,"") | F23: =IFERROR(VLOOKUP($D23,BS연결,MATCH(F$1,BS연결H,0),0)/100,"") | G23: =IFERROR(VLOOKUP($D23,BS연결,MATCH(G$1,BS연결H,0),0)/100,"") | H23: =IFERROR(VLOOKUP($D23,BS연결,MATCH(H$1,BS연결H,0),0)/100,"") | I23: =IFERROR(VLOOKUP($D23,BS연결,MATCH(I$1,BS연결H,0),0)/100,"") | J23: =IFERROR(VLOOKUP($D23,BS연결,MATCH(J$1,BS연결H,0),0)/100,"") | K23: =IFERROR(VLOOKUP($D23,BS연결,MATCH(K$1,BS연결H,0),0)/100,"") | L23: =IFERROR(VLOOKUP($D23,BS연결,MATCH(L$1,BS연결H,0),0)/100,"") | ... AB23: =IFERROR(VLOOKUP($D23,BS연결,MATCH(AB$1,BS연결H,0),0)/100,"") | AC23: =IFERROR(AB23+AC18-변수!AC31,"") | AD23: =IFERROR(AC23+AD18-변수!AD31,"") | AE23: =AD23 | AF23: =IFERROR(AD23+AF18-변수!AF31,"") | AG23: =IFERROR(AF23+AG18-변수!AG31,"") | AH23: =IFERROR(AG23+AH18-변수!AH31,"") | AI23: =IFERROR(AH23+AI18-변수!AI31,"") | AJ23: =AI23 | AK23: =IFERROR(AI23+AK18-변수!AK31,"") | AL23: =IFERROR(AK23+AL18-변수!AL31,"") | AM23: =IFERROR(AL23+AM18-변수!AM31,"") | AN23: =IFERROR(AM23+AN18-변수!AN31,"") | AO23: =AN23
A24: 지배주주지분 | B24: 재무상태 | C24: 억원 | D24: 지배주주지분 | E24: =IFERROR(VLOOKUP($D24,BS연결,MATCH(E$1,BS연결H,0),0)/100,"") | F24: =IFERROR(VLOOKUP($D24,BS연결,MATCH(F$1,BS연결H,0),0)/100,"") | G24: =IFERROR(VLOOKUP($D24,BS연결,MATCH(G$1,BS연결H,0),0)/100,"") | H24: =IFERROR(VLOOKUP($D24,BS연결,MATCH(H$1,BS연결H,0),0)/100,"") | I24: =IFERROR(VLOOKUP($D24,BS연결,MATCH(I$1,BS연결H,0),0)/100,"") | J24: =IFERROR(VLOOKUP($D24,BS연결,MATCH(J$1,BS연결H,0),0)/100,"") | K24: =IFERROR(VLOOKUP($D24,BS연결,MATCH(K$1,BS연결H,0),0)/100,"") | L24: =IFERROR(VLOOKUP($D24,BS연결,MATCH(L$1,BS연결H,0),0)/100,"") | ... AB24: =IFERROR(VLOOKUP($D24,BS연결,MATCH(AB$1,BS연결H,0),0)/100,"") | AC24: =IFERROR(AB24+AC19-변수!AC32,"") | AD24: =IFERROR(AC24+AD19-변수!AD32,"") | AE24: =AD24 | AF24: =IFERROR(AD24+AF19-변수!AF32,"") | AG24: =IFERROR(AF24+AG19-변수!AG32,"") | AH24: =IFERROR(AG24+AH19-변수!AH32,"") | AI24: =IFERROR(AH24+AI19-변수!AI32,"") | AJ24: =AI24 | AK24: =IFERROR(AI24+AK19-변수!AK32,"") | AL24: =IFERROR(AK24+AL19-변수!AL32,"") | AM24: =IFERROR(AL24+AM19-변수!AM32,"") | AN24: =IFERROR(AM24+AN19-변수!AN32,"") | AO24: =AN24
A25: 총차입금 | B25: 재무상태 | C25: 억원 | D25: 총차입금 | E25: =IFERROR(VLOOKUP($D25,BS연결,MATCH(E$1,BS연결H,0),0)/100,"") | F25: =IFERROR(VLOOKUP($D25,BS연결,MATCH(F$1,BS연결H,0),0)/100,"") | G25: =IFERROR(VLOOKUP($D25,BS연결,MATCH(G$1,BS연결H,0),0)/100,"") | H25: =IFERROR(VLOOKUP($D25,BS연결,MATCH(H$1,BS연결H,0),0)/100,"") | I25: =IFERROR(VLOOKUP($D25,BS연결,MATCH(I$1,BS연결H,0),0)/100,"") | J25: =IFERROR(VLOOKUP($D25,BS연결,MATCH(J$1,BS연결H,0),0)/100,"") | K25: =IFERROR(VLOOKUP($D25,BS연결,MATCH(K$1,BS연결H,0),0)/100,"") | L25: =IFERROR(VLOOKUP($D25,BS연결,MATCH(L$1,BS연결H,0),0)/100,"") | ... AB25: =IFERROR(VLOOKUP($D25,BS연결,MATCH(AB$1,BS연결H,0),0)/100,"") | AC25: =IFERROR(AB25*(1+변수!AC33),"") | AD25: =IFERROR(AC25*(1+변수!AD33),"") | AE25: =AD25 | AF25: =IFERROR(AD25*(1+변수!AF33),"") | AG25: =IFERROR(AF25*(1+변수!AG33),"") | AH25: =IFERROR(AG25*(1+변수!AH33),"") | AI25: =IFERROR(AH25*(1+변수!AI33),"") | AJ25: =AI25 | AK25: =IFERROR(AI25*(1+변수!AK33),"") | AL25: =IFERROR(AK25*(1+변수!AL33),"") | AM25: =IFERROR(AL25*(1+변수!AM33),"") | AN25: =IFERROR(AM25*(1+변수!AN33),"") | AO25: =AN25
A26: 순차입금 | B26: 재무상태 | C26: 억원 | D26: 순차입금 | E26: =IFERROR(VLOOKUP($D26,BS연결,MATCH(E$1,BS연결H,0),0)/100,"") | F26: =IFERROR(VLOOKUP($D26,BS연결,MATCH(F$1,BS연결H,0),0)/100,"") | G26: =IFERROR(VLOOKUP($D26,BS연결,MATCH(G$1,BS연결H,0),0)/100,"") | H26: =IFERROR(VLOOKUP($D26,BS연결,MATCH(H$1,BS연결H,0),0)/100,"") | I26: =IFERROR(VLOOKUP($D26,BS연결,MATCH(I$1,BS연결H,0),0)/100,"") | J26: =IFERROR(VLOOKUP($D26,BS연결,MATCH(J$1,BS연결H,0),0)/100,"") | K26: =IFERROR(VLOOKUP($D26,BS연결,MATCH(K$1,BS연결H,0),0)/100,"") | L26: =IFERROR(VLOOKUP($D26,BS연결,MATCH(L$1,BS연결H,0),0)/100,"") | ... AB26: =IFERROR(VLOOKUP($D26,BS연결,MATCH(AB$1,BS연결H,0),0)/100,"") | AC26: =IFERROR(AB26*(1+변수!AC34),"") | AD26: =IFERROR(AC26*(1+변수!AD34),"") | AE26: =AD26 | AF26: =IFERROR(AD26*(1+변수!AF34),"") | AG26: =IFERROR(AF26*(1+변수!AG34),"") | AH26: =IFERROR(AG26*(1+변수!AH34),"") | AI26: =IFERROR(AH26*(1+변수!AI34),"") | AJ26: =AI26 | AK26: =IFERROR(AI26*(1+변수!AK34),"") | AL26: =IFERROR(AK26*(1+변수!AL34),"") | AM26: =IFERROR(AL26*(1+변수!AM34),"") | AN26: =IFERROR(AM26*(1+변수!AN34),"") | AO26: =AN26
A27: 이자발생자산 | B27: 재무상태 | C27: 억원 | D27: 이자발생자산 | E27: =IFERROR(VLOOKUP($D27,BS연결,MATCH(E$1,BS연결H,0),0)/100,"") | F27: =IFERROR(VLOOKUP($D27,BS연결,MATCH(F$1,BS연결H,0),0)/100,"") | G27: =IFERROR(VLOOKUP($D27,BS연결,MATCH(G$1,BS연결H,0),0)/100,"") | H27: =IFERROR(VLOOKUP($D27,BS연결,MATCH(H$1,BS연결H,0),0)/100,"") | I27: =IFERROR(VLOOKUP($D27,BS연결,MATCH(I$1,BS연결H,0),0)/100,"") | J27: =IFERROR(VLOOKUP($D27,BS연결,MATCH(J$1,BS연결H,0),0)/100,"") | K27: =IFERROR(VLOOKUP($D27,BS연결,MATCH(K$1,BS연결H,0),0)/100,"") | L27: =IFERROR(VLOOKUP($D27,BS연결,MATCH(L$1,BS연결H,0),0)/100,"") | ... AB27: =IFERROR(VLOOKUP($D27,BS연결,MATCH(AB$1,BS연결H,0),0)/100,"") | AC27: =IFERROR(AB27*(1+변수!AC35),"") | AD27: =IFERROR(AC27*(1+변수!AD35),"") | AE27: =AD27 | AF27: =IFERROR(AD27*(1+변수!AF35),"") | AG27: =IFERROR(AF27*(1+변수!AG35),"") | AH27: =IFERROR(AG27*(1+변수!AH35),"") | AI27: =IFERROR(AH27*(1+변수!AI35),"") | AJ27: =AI27 | AK27: =IFERROR(AI27*(1+변수!AK35),"") | AL27: =IFERROR(AK27*(1+변수!AL35),"") | AM27: =IFERROR(AL27*(1+변수!AM35),"") | AN27: =IFERROR(AM27*(1+변수!AN35),"") | AO27: =AN27
A28: 현금및현금성자산 | B28: 재무상태 | C28: 억원 | D28: 현금및현금성자산 | E28: =IFERROR(VLOOKUP($D28,BS연결,MATCH(E$1,BS연결H,0),0)/100,"") | F28: =IFERROR(VLOOKUP($D28,BS연결,MATCH(F$1,BS연결H,0),0)/100,"") | G28: =IFERROR(VLOOKUP($D28,BS연결,MATCH(G$1,BS연결H,0),0)/100,"") | H28: =IFERROR(VLOOKUP($D28,BS연결,MATCH(H$1,BS연결H,0),0)/100,"") | I28: =IFERROR(VLOOKUP($D28,BS연결,MATCH(I$1,BS연결H,0),0)/100,"") | J28: =IFERROR(VLOOKUP($D28,BS연결,MATCH(J$1,BS연결H,0),0)/100,"") | K28: =IFERROR(VLOOKUP($D28,BS연결,MATCH(K$1,BS연결H,0),0)/100,"") | L28: =IFERROR(VLOOKUP($D28,BS연결,MATCH(L$1,BS연결H,0),0)/100,"") | ... AB28: =IFERROR(VLOOKUP($D28,BS연결,MATCH(AB$1,BS연결H,0),0)/100,"") | AE28: =AD28 | AJ28: =AI28 | AO28: =AN28
A29: CAPEX | B29: 현금흐름 | C29: 억원 | D29: CAPEX | E29: =IFERROR(VLOOKUP($D29,BS연결,MATCH(E$1,BS연결H,0),0)/100,"") | G29: =IFERROR(VLOOKUP($D29,BS연결,MATCH(G$1,BS연결H,0),0)/100,"") | H29: =IFERROR(VLOOKUP($D29,BS연결,MATCH(H$1,BS연결H,0),0)/100,"") | I29: =IFERROR(VLOOKUP($D29,BS연결,MATCH(I$1,BS연결H,0),0)/100,"") | J29: =IFERROR(VLOOKUP($D29,BS연결,MATCH(J$1,BS연결H,0),0)/100,"") | K29: =IFERROR(VLOOKUP($D29,BS연결,MATCH(K$1,BS연결H,0),0)/100,"") | L29: =IFERROR(VLOOKUP($D29,BS연결,MATCH(L$1,BS연결H,0),0)/100,"") | M29: =IFERROR(VLOOKUP($D29,BS연결,MATCH(M$1,BS연결H,0),0)/100,"") | N29: =IFERROR(VLOOKUP($D29,BS연결,MATCH(N$1,BS연결H,0),0)/100,"") | ... AB29: =IFERROR(VLOOKUP($D29,BS연결,MATCH(AB$1,BS연결H,0),0)/100,"") | AC29: =IFERROR(X29*(1+변수!AC37),"") | AD29: =IFERROR(Y29*(1+변수!AD37),"") | AE29: =SUM(AA29:AD29) | AF29: =IFERROR(AA29*(1+변수!AF37),"") | AG29: =IFERROR(AB29*(1+변수!AG37),"") | AH29: =IFERROR(AC29*(1+변수!AH37),"") | AI29: =IFERROR(AD29*(1+변수!AI37),"") | AJ29: =SUM(AF29:AI29) | AK29: =IFERROR(AF29*(1+변수!AK37),"") | AL29: =IFERROR(AG29*(1+변수!AL37),"") | AM29: =IFERROR(AH29*(1+변수!AM37),"") | AN29: =IFERROR(AI29*(1+변수!AN37),"") | AO29: =SUM(AK29:AN29)
A30: 영업활동현금흐름 | B30: 현금흐름 | C30: 억원 | D30: 영업활동으로인한현금흐름 | E30: =IFERROR(VLOOKUP($D30,BS연결,MATCH(E$1,BS연결H,0),0)/100,"") | G30: =IFERROR(VLOOKUP($D30,BS연결,MATCH(G$1,BS연결H,0),0)/100,"") | H30: =IFERROR(VLOOKUP($D30,BS연결,MATCH(H$1,BS연결H,0),0)/100,"") | I30: =IFERROR(VLOOKUP($D30,BS연결,MATCH(I$1,BS연결H,0),0)/100,"") | J30: =IFERROR(VLOOKUP($D30,BS연결,MATCH(J$1,BS연결H,0),0)/100,"") | K30: =IFERROR(VLOOKUP($D30,BS연결,MATCH(K$1,BS연결H,0),0)/100,"") | L30: =IFERROR(VLOOKUP($D30,BS연결,MATCH(L$1,BS연결H,0),0)/100,"") | M30: =IFERROR(VLOOKUP($D30,BS연결,MATCH(M$1,BS연결H,0),0)/100,"") | N30: =IFERROR(VLOOKUP($D30,BS연결,MATCH(N$1,BS연결H,0),0)/100,"") | ... AB30: =IFERROR(VLOOKUP($D30,BS연결,MATCH(AB$1,BS연결H,0),0)/100,"") | AE30: =SUM(AA30:AD30) | AJ30: =SUM(AF30:AI30) | AO30: =SUM(AK30:AN30)
A31: 주식수 | B31: 주당 | C31: 백만주 | D31: 유통주식수 | E31: 1.2613894 | F31: =E31 | G31: 1.283766 | H31: 1.2828747 | I31: 1.6131475 | J31: 1.7026849 | K31: =J31 | L31: 1.7451748 | M31: 1.9806777 | N31: 2.0046931 | O31: 3.4846918 | P31: =O31 | Q31: 3.8096075 | R31: 3.8096075 | S31: 3.9247485 | T31: 4.5914152 | U31: =T31 | V31: 5.5247485 | W31: 5.5247485 | X31: 5.518 | Y31: 5.518 | Z31: =Y31 | AA31: 5.518 | AB31: 5.518 | AC31: =IFERROR(AB31*(1+변수!AC39),"") | AD31: =IFERROR(AC31*(1+변수!AD39),"") | AE31: =AD31 | AF31: =IFERROR(AD31*(1+변수!AF39),"") | AG31: =IFERROR(AF31*(1+변수!AG39),"") | AH31: =IFERROR(AG31*(1+변수!AH39),"") | AI31: =IFERROR(AH31*(1+변수!AI39),"") | AJ31: =AI31 | AK31: =IFERROR(AI31*(1+변수!AK39),"") | AL31: =IFERROR(AK31*(1+변수!AL39),"") | AM31: =IFERROR(AL31*(1+변수!AM39),"") | AN31: =IFERROR(AM31*(1+변수!AN39),"") | AO31: =AN31
A32: EPS | B32: 주당 | C32: 원 | D32: EPS | E32: =IFERROR(E19*100/E31,"") | G32: =IFERROR(G19*100/G31,"") | H32: =IFERROR(H19*100/H31,"") | I32: =IFERROR(I19*100/I31,"") | J32: =IFERROR(J19*100/J31,"") | K32: =SUM(G32:J32) | L32: =IFERROR(L19*100/L31,"") | M32: =IFERROR(M19*100/M31,"") | N32: =IFERROR(N19*100/N31,"") | O32: =IFERROR(O19*100/O31,"") | P32: =SUM(L32:O32) | Q32: =IFERROR(Q19*100/Q31,"") | R32: =IFERROR(R19*100/R31,"") | S32: =IFERROR(S19*100/S31,"") | T32: =IFERROR(T19*100/T31,"") | U32: =SUM(Q32:T32) | V32: =IFERROR(V19*100/V31,"") | W32: =IFERROR(W19*100/W31,"") | X32: =IFERROR(X19*100/X31,"") | Y32: =IFERROR(Y19*100/Y31,"") | Z32: =SUM(V32:Y32) | AA32: =IFERROR(AA19*100/AA31,"") | AB32: =IFERROR(AB19*100/AB31,"") | AC32: =IFERROR(AC19*100/AC31,"") | AD32: =IFERROR(AD19*100/AD31,"") | AE32: =SUM(AA32:AD32) | AF32: =IFERROR(AF19*100/AF31,"") | AG32: =IFERROR(AG19*100/AG31,"") | AH32: =IFERROR(AH19*100/AH31,"") | AI32: =IFERROR(AI19*100/AI31,"") | AJ32: =SUM(AF32:AI32) | AK32: =IFERROR(AK19*100/AK31,"") | AL32: =IFERROR(AL19*100/AL31,"") | AM32: =IFERROR(AM19*100/AM31,"") | AN32: =IFERROR(AN19*100/AN31,"") | AO32: =SUM(AK32:AN32)
A33: BPS | B33: 주당 | C33: 원 | D33: BPS | E33: =IFERROR(E24*100/E31,"") | F33: =E33 | G33: =IFERROR(G24*100/G31,"") | H33: =IFERROR(H24*100/H31,"") | I33: =IFERROR(I24*100/I31,"") | J33: =IFERROR(J24*100/J31,"") | K33: =J33 | L33: =IFERROR(L24*100/L31,"") | M33: =IFERROR(M24*100/M31,"") | N33: =IFERROR(N24*100/N31,"") | O33: =IFERROR(O24*100/O31,"") | P33: =O33 | Q33: =IFERROR(Q24*100/Q31,"") | R33: =IFERROR(R24*100/R31,"") | S33: =IFERROR(S24*100/S31,"") | T33: =IFERROR(T24*100/T31,"") | U33: =T33 | V33: =IFERROR(V24*100/V31,"") | W33: =IFERROR(W24*100/W31,"") | X33: =IFERROR(X24*100/X31,"") | Y33: =IFERROR(Y24*100/Y31,"") | Z33: =Y33 | AA33: =IFERROR(AA24*100/AA31,"") | AB33: =IFERROR(AB24*100/AB31,"") | AC33: =IFERROR(AC24*100/AC31,"") | AD33: =IFERROR(AD24*100/AD31,"") | AE33: =AD33 | AF33: =IFERROR(AF24*100/AF31,"") | AG33: =IFERROR(AG24*100/AG31,"") | AH33: =IFERROR(AH24*100/AH31,"") | AI33: =IFERROR(AI24*100/AI31,"") | AJ33: =AI33 | AK33: =IFERROR(AK24*100/AK31,"") | AL33: =IFERROR(AL24*100/AL31,"") | AM33: =IFERROR(AM24*100/AM31,"") | AN33: =IFERROR(AN24*100/AN31,"") | AO33: =AN33
A34: DPS | B34: 주당 | C34: 원 | D34: DPS(보통주) | E34: 0 | F34: 0 | J34: 0 | K34: =SUM(G34:J34) | O34: 0 | P34: =SUM(L34:O34) | T34: 0 | U34: =SUM(Q34:T34) | Y34: 0 | Z34: =SUM(V34:Y34) | AD34: =변수!AD40 | AE34: =SUM(AA34:AD34) | AI34: =변수!AI40 | AJ34: =SUM(AF34:AI34) | AN34: =변수!AN40 | AO34: =SUM(AK34:AN34)
A35: PBR | B35: 주당 | C35: 배 | D35: PBR | E35: =IFERROR(변수!E18/E33,"") | F35: =E35 | G35: =IFERROR(변수!G18/G33,"") | H35: =IFERROR(변수!H18/H33,"") | I35: =IFERROR(변수!I18/I33,"") | J35: =IFERROR(변수!J18/J33,"") | K35: =J35 | L35: =IFERROR(변수!L18/L33,"") | M35: =IFERROR(변수!M18/M33,"") | N35: =IFERROR(변수!N18/N33,"") | O35: =IFERROR(변수!O18/O33,"") | P35: =O35 | Q35: =IFERROR(변수!Q18/Q33,"") | R35: =IFERROR(변수!R18/R33,"") | S35: =IFERROR(변수!S18/S33,"") | T35: =IFERROR(변수!T18/T33,"") | U35: =T35 | V35: =IFERROR(변수!V18/V33,"") | W35: =IFERROR(변수!W18/W33,"") | X35: =IFERROR(변수!X18/X33,"") | Z35: =Y35 | AC35: =IFERROR(변수!$D$43/AC33,"") | AD35: =IFERROR(변수!$D$43/AD33,"") | AE35: =AD35 | AF35: =IFERROR(변수!$D$43/AF33,"") | AG35: =IFERROR(변수!$D$43/AG33,"") | AH35: =IFERROR(변수!$D$43/AH33,"") | AI35: =IFERROR(변수!$D$43/AI33,"") | AJ35: =AI35 | AK35: =IFERROR(변수!$D$43/AK33,"") | AL35: =IFERROR(변수!$D$43/AL33,"") | AM35: =IFERROR(변수!$D$43/AM33,"") | AN35: =IFERROR(변수!$D$43/AN33,"") | AO35: =AN35
A36: 매출전사 | B36: 사업부 | C36: 억원 | D36: 매출 전사(부문 미분리) | E36: 48.09 | G36: 45.98 | H36: 55.54 | I36: 58.4 | J36: 58.26 | K36: =SUM(G36:J36) | L36: 54.04 | M36: 76.36 | N36: 67.55 | O36: 70.8 | P36: =SUM(L36:O36) | Q36: 74.67 | R36: 73.64 | S36: 76.05 | T36: 81.75 | U36: =SUM(Q36:T36) | V36: 68.2 | W36: 76.75 | X36: 66.85 | Y36: 69.81 | Z36: =SUM(V36:Y36) | AA36: 63.29 | AB36: 64.43 | AC36: =IFERROR(AC5,"") | AD36: =IFERROR(AD5,"") | AE36: =SUM(AA36:AD36) | AF36: =IFERROR(AF5,"") | AG36: =IFERROR(AG5,"") | AH36: =IFERROR(AH5,"") | AI36: =IFERROR(AI5,"") | AJ36: =SUM(AF36:AI36) | AK36: =IFERROR(AK5,"") | AL36: =IFERROR(AL5,"") | AM36: =IFERROR(AM5,"") | AN36: =IFERROR(AN5,"") | AO36: =SUM(AK36:AN36)
A37: OP전사 | B37: 사업부 | C37: 억원 | D37: OP 전사(부문 미분리) | E37: -28.38 | G37: -23.69 | H37: -19.49 | I37: -29.72 | J37: -50.42 | K37: =SUM(G37:J37) | L37: -29.83 | M37: -19.42 | N37: -28.81 | O37: -28.52 | P37: =SUM(L37:O37) | Q37: -33.68 | R37: -22.93 | S37: -22.41 | T37: -21.43 | U37: =SUM(Q37:T37) | V37: -20.23 | W37: -14.54 | X37: -9.23 | Y37: -13.47 | Z37: =SUM(V37:Y37) | AA37: -10.33 | AB37: -11.14 | AC37: =IFERROR(AC9,"") | AD37: =IFERROR(AD9,"") | AE37: =SUM(AA37:AD37) | AF37: =IFERROR(AF9,"") | AG37: =IFERROR(AG9,"") | AH37: =IFERROR(AH9,"") | AI37: =IFERROR(AI9,"") | AJ37: =SUM(AF37:AI37) | AK37: =IFERROR(AK9,"") | AL37: =IFERROR(AL9,"") | AM37: =IFERROR(AM9,"") | AN37: =IFERROR(AN9,"") | AO37: =SUM(AK37:AN37)
B38: 비율(참고)
A39: NPM | C39: % | D39: 지배주주순이익 / 매출액 | E39: =IFERROR(E19/E5,"") | F39: =IFERROR(F19/F5,"") | G39: =IFERROR(G19/G5,"") | H39: =IFERROR(H19/H5,"") | I39: =IFERROR(I19/I5,"") | J39: =IFERROR(J19/J5,"") | K39: =IFERROR(K19/K5,"") | L39: =IFERROR(L19/L5,"") | ... AO39: =IFERROR(AO19/AO5,"")
A40: 매출원가율 | C40: % | D40: 매출원가 / 매출액 | E40: =IFERROR(E6/E5,"") | F40: =IFERROR(F6/F5,"") | G40: =IFERROR(G6/G5,"") | H40: =IFERROR(H6/H5,"") | I40: =IFERROR(I6/I5,"") | J40: =IFERROR(J6/J5,"") | K40: =IFERROR(K6/K5,"") | L40: =IFERROR(L6/L5,"") | ... AO40: =IFERROR(AO6/AO5,"")
A41: 판관비율 | C41: % | D41: 판관비 / 매출액 | E41: =IFERROR(E8/E5,"") | F41: =IFERROR(F8/F5,"") | G41: =IFERROR(G8/G5,"") | H41: =IFERROR(H8/H5,"") | I41: =IFERROR(I8/I5,"") | J41: =IFERROR(J8/J5,"") | K41: =IFERROR(K8/K5,"") | L41: =IFERROR(L8/L5,"") | ... AO41: =IFERROR(AO8/AO5,"")

Sheet 분기
C1: 이름: 분기H — subQ 를 이름으로 VLOOKUP(억원) | E1: 4Q21 | F1: 1Q22 | G1: 2Q22 | H1: 3Q22 | I1: 4Q22 | J1: 1Q23 | K1: 2Q23 | L1: 3Q23 | M1: 4Q23 | N1: 1Q24 | O1: 2Q24 | P1: 3Q24 | Q1: 4Q24 | R1: 1Q25 | S1: 2Q25 | T1: 3Q25 | U1: 4Q25 | V1: 1Q26 | W1: 2Q26 | X1: 3Q26 | Y1: 4Q26 | Z1: 1Q27 | AA1: 2Q27 | AB1: 3Q27 | AC1: 4Q27 | AD1: 1Q28 | AE1: 2Q28 | AF1: 3Q28 | AG1: 4Q28
C2: 종가: | D2: =변수!D43
C3: 기준일: | D3: 20261008 | E3: 1 | F3: 2 | G3: 3 | H3: 4 | I3: 5 | J3: 6 | K3: 7 | L3: 8 | M3: 9 | N3: 10 | O3: 11 | P3: 12 | Q3: 13 | R3: 14 | S3: 15 | T3: 16 | U3: 17 | V3: 18 | W3: 19 | X3: 20 | Y3: 21 | Z3: 22 | AA3: 23 | AB3: 24 | AC3: 25 | AD3: 26 | AE3: 27 | AF3: 28 | AG3: 29
E4: 2021.12 | F4: 2022.03 | G4: 2022.06 | H4: 2022.09 | I4: 2022.12 | J4: 2023.03 | K4: 2023.06 | L4: 2023.09 | M4: 2023.12 | N4: 2024.03 | O4: 2024.06 | P4: 2024.09 | Q4: 2024.12 | R4: 2025.03 | S4: 2025.06 | T4: 2025.09 | U4: 2025.12 | V4: 2026.03 | W4: 2026.06 | X4: 2026.09 | Y4: 2026.12 | Z4: 2027.03 | AA4: 2027.06 | AB4: 2027.09 | AC4: 2027.12 | AD4: 2028.03 | AE4: 2028.06 | AF4: 2028.09 | AG4: 2028.12
A5: 매출액 | D5: 매출액 | E5: =IFERROR(VLOOKUP($A5,subQ,MATCH(E$1,SUBQH,0),0),"") | F5: =IFERROR(VLOOKUP($A5,subQ,MATCH(F$1,SUBQH,0),0),"") | G5: =IFERROR(VLOOKUP($A5,subQ,MATCH(G$1,SUBQH,0),0),"") | H5: =IFERROR(VLOOKUP($A5,subQ,MATCH(H$1,SUBQH,0),0),"") | I5: =IFERROR(VLOOKUP($A5,subQ,MATCH(I$1,SUBQH,0),0),"") | J5: =IFERROR(VLOOKUP($A5,subQ,MATCH(J$1,SUBQH,0),0),"") | K5: =IFERROR(VLOOKUP($A5,subQ,MATCH(K$1,SUBQH,0),0),"") | L5: =IFERROR(VLOOKUP($A5,subQ,MATCH(L$1,SUBQH,0),0),"") | ... AG5: =IFERROR(VLOOKUP($A5,subQ,MATCH(AG$1,SUBQH,0),0),"")
A6: 매출원가 | D6: 매출원가 | E6: =IFERROR(VLOOKUP($A6,subQ,MATCH(E$1,SUBQH,0),0),"") | F6: =IFERROR(VLOOKUP($A6,subQ,MATCH(F$1,SUBQH,0),0),"") | G6: =IFERROR(VLOOKUP($A6,subQ,MATCH(G$1,SUBQH,0),0),"") | H6: =IFERROR(VLOOKUP($A6,subQ,MATCH(H$1,SUBQH,0),0),"") | I6: =IFERROR(VLOOKUP($A6,subQ,MATCH(I$1,SUBQH,0),0),"") | J6: =IFERROR(VLOOKUP($A6,subQ,MATCH(J$1,SUBQH,0),0),"") | K6: =IFERROR(VLOOKUP($A6,subQ,MATCH(K$1,SUBQH,0),0),"") | L6: =IFERROR(VLOOKUP($A6,subQ,MATCH(L$1,SUBQH,0),0),"") | ... AG6: =IFERROR(VLOOKUP($A6,subQ,MATCH(AG$1,SUBQH,0),0),"")
A7: 매출총이익 | D7: 매출총이익 | E7: =IFERROR(VLOOKUP($A7,subQ,MATCH(E$1,SUBQH,0),0),"") | F7: =IFERROR(VLOOKUP($A7,subQ,MATCH(F$1,SUBQH,0),0),"") | G7: =IFERROR(VLOOKUP($A7,subQ,MATCH(G$1,SUBQH,0),0),"") | H7: =IFERROR(VLOOKUP($A7,subQ,MATCH(H$1,SUBQH,0),0),"") | I7: =IFERROR(VLOOKUP($A7,subQ,MATCH(I$1,SUBQH,0),0),"") | J7: =IFERROR(VLOOKUP($A7,subQ,MATCH(J$1,SUBQH,0),0),"") | K7: =IFERROR(VLOOKUP($A7,subQ,MATCH(K$1,SUBQH,0),0),"") | L7: =IFERROR(VLOOKUP($A7,subQ,MATCH(L$1,SUBQH,0),0),"") | ... AG7: =IFERROR(VLOOKUP($A7,subQ,MATCH(AG$1,SUBQH,0),0),"")
A8: 판관비 | D8: 판매비와관리비 | E8: =IFERROR(VLOOKUP($A8,subQ,MATCH(E$1,SUBQH,0),0),"") | F8: =IFERROR(VLOOKUP($A8,subQ,MATCH(F$1,SUBQH,0),0),"") | G8: =IFERROR(VLOOKUP($A8,subQ,MATCH(G$1,SUBQH,0),0),"") | H8: =IFERROR(VLOOKUP($A8,subQ,MATCH(H$1,SUBQH,0),0),"") | I8: =IFERROR(VLOOKUP($A8,subQ,MATCH(I$1,SUBQH,0),0),"") | J8: =IFERROR(VLOOKUP($A8,subQ,MATCH(J$1,SUBQH,0),0),"") | K8: =IFERROR(VLOOKUP($A8,subQ,MATCH(K$1,SUBQH,0),0),"") | L8: =IFERROR(VLOOKUP($A8,subQ,MATCH(L$1,SUBQH,0),0),"") | ... AG8: =IFERROR(VLOOKUP($A8,subQ,MATCH(AG$1,SUBQH,0),0),"")
A9: 영업이익 | D9: 영업이익 | E9: =IFERROR(VLOOKUP($A9,subQ,MATCH(E$1,SUBQH,0),0),"") | F9: =IFERROR(VLOOKUP($A9,subQ,MATCH(F$1,SUBQH,0),0),"") | G9: =IFERROR(VLOOKUP($A9,subQ,MATCH(G$1,SUBQH,0),0),"") | H9: =IFERROR(VLOOKUP($A9,subQ,MATCH(H$1,SUBQH,0),0),"") | I9: =IFERROR(VLOOKUP($A9,subQ,MATCH(I$1,SUBQH,0),0),"") | J9: =IFERROR(VLOOKUP($A9,subQ,MATCH(J$1,SUBQH,0),0),"") | K9: =IFERROR(VLOOKUP($A9,subQ,MATCH(K$1,SUBQH,0),0),"") | L9: =IFERROR(VLOOKUP($A9,subQ,MATCH(L$1,SUBQH,0),0),"") | ... AG9: =IFERROR(VLOOKUP($A9,subQ,MATCH(AG$1,SUBQH,0),0),"")
A10: OPM | D10: 영업이익률 | E10: =IFERROR(VLOOKUP($A10,subQ,MATCH(E$1,SUBQH,0),0),"") | F10: =IFERROR(VLOOKUP($A10,subQ,MATCH(F$1,SUBQH,0),0),"") | G10: =IFERROR(VLOOKUP($A10,subQ,MATCH(G$1,SUBQH,0),0),"") | H10: =IFERROR(VLOOKUP($A10,subQ,MATCH(H$1,SUBQH,0),0),"") | I10: =IFERROR(VLOOKUP($A10,subQ,MATCH(I$1,SUBQH,0),0),"") | J10: =IFERROR(VLOOKUP($A10,subQ,MATCH(J$1,SUBQH,0),0),"") | K10: =IFERROR(VLOOKUP($A10,subQ,MATCH(K$1,SUBQH,0),0),"") | L10: =IFERROR(VLOOKUP($A10,subQ,MATCH(L$1,SUBQH,0),0),"") | ... AG10: =IFERROR(VLOOKUP($A10,subQ,MATCH(AG$1,SUBQH,0),0),"")
A11: 금융손익 | D11: 금융손익(이자·환 포함) | E11: =IFERROR(VLOOKUP($A11,subQ,MATCH(E$1,SUBQH,0),0),"") | F11: =IFERROR(VLOOKUP($A11,subQ,MATCH(F$1,SUBQH,0),0),"") | G11: =IFERROR(VLOOKUP($A11,subQ,MATCH(G$1,SUBQH,0),0),"") | H11: =IFERROR(VLOOKUP($A11,subQ,MATCH(H$1,SUBQH,0),0),"") | I11: =IFERROR(VLOOKUP($A11,subQ,MATCH(I$1,SUBQH,0),0),"") | J11: =IFERROR(VLOOKUP($A11,subQ,MATCH(J$1,SUBQH,0),0),"") | K11: =IFERROR(VLOOKUP($A11,subQ,MATCH(K$1,SUBQH,0),0),"") | L11: =IFERROR(VLOOKUP($A11,subQ,MATCH(L$1,SUBQH,0),0),"") | ... AG11: =IFERROR(VLOOKUP($A11,subQ,MATCH(AG$1,SUBQH,0),0),"")
A12: 이자손익 | D12: 이자손익(이자수익 − 이자비용) | E12: =IFERROR(VLOOKUP($A12,subQ,MATCH(E$1,SUBQH,0),0),"") | F12: =IFERROR(VLOOKUP($A12,subQ,MATCH(F$1,SUBQH,0),0),"") | G12: =IFERROR(VLOOKUP($A12,subQ,MATCH(G$1,SUBQH,0),0),"") | H12: =IFERROR(VLOOKUP($A12,subQ,MATCH(H$1,SUBQH,0),0),"") | I12: =IFERROR(VLOOKUP($A12,subQ,MATCH(I$1,SUBQH,0),0),"") | J12: =IFERROR(VLOOKUP($A12,subQ,MATCH(J$1,SUBQH,0),0),"") | K12: =IFERROR(VLOOKUP($A12,subQ,MATCH(K$1,SUBQH,0),0),"") | L12: =IFERROR(VLOOKUP($A12,subQ,MATCH(L$1,SUBQH,0),0),"") | ... AG12: =IFERROR(VLOOKUP($A12,subQ,MATCH(AG$1,SUBQH,0),0),"")
A13: 파생상품손익 | D13: 파생상품손익 | E13: =IFERROR(VLOOKUP($A13,subQ,MATCH(E$1,SUBQH,0),0),"") | F13: =IFERROR(VLOOKUP($A13,subQ,MATCH(F$1,SUBQH,0),0),"") | G13: =IFERROR(VLOOKUP($A13,subQ,MATCH(G$1,SUBQH,0),0),"") | H13: =IFERROR(VLOOKUP($A13,subQ,MATCH(H$1,SUBQH,0),0),"") | I13: =IFERROR(VLOOKUP($A13,subQ,MATCH(I$1,SUBQH,0),0),"") | J13: =IFERROR(VLOOKUP($A13,subQ,MATCH(J$1,SUBQH,0),0),"") | K13: =IFERROR(VLOOKUP($A13,subQ,MATCH(K$1,SUBQH,0),0),"") | L13: =IFERROR(VLOOKUP($A13,subQ,MATCH(L$1,SUBQH,0),0),"") | ... AG13: =IFERROR(VLOOKUP($A13,subQ,MATCH(AG$1,SUBQH,0),0),"")
A14: 기타영업외손익 | D14: 기타영업외손익 | E14: =IFERROR(VLOOKUP($A14,subQ,MATCH(E$1,SUBQH,0),0),"") | F14: =IFERROR(VLOOKUP($A14,subQ,MATCH(F$1,SUBQH,0),0),"") | G14: =IFERROR(VLOOKUP($A14,subQ,MATCH(G$1,SUBQH,0),0),"") | H14: =IFERROR(VLOOKUP($A14,subQ,MATCH(H$1,SUBQH,0),0),"") | I14: =IFERROR(VLOOKUP($A14,subQ,MATCH(I$1,SUBQH,0),0),"") | J14: =IFERROR(VLOOKUP($A14,subQ,MATCH(J$1,SUBQH,0),0),"") | K14: =IFERROR(VLOOKUP($A14,subQ,MATCH(K$1,SUBQH,0),0),"") | L14: =IFERROR(VLOOKUP($A14,subQ,MATCH(L$1,SUBQH,0),0),"") | ... AG14: =IFERROR(VLOOKUP($A14,subQ,MATCH(AG$1,SUBQH,0),0),"")
A15: 지분법손익 | D15: 지분법손익 | E15: =IFERROR(VLOOKUP($A15,subQ,MATCH(E$1,SUBQH,0),0),"") | F15: =IFERROR(VLOOKUP($A15,subQ,MATCH(F$1,SUBQH,0),0),"") | G15: =IFERROR(VLOOKUP($A15,subQ,MATCH(G$1,SUBQH,0),0),"") | H15: =IFERROR(VLOOKUP($A15,subQ,MATCH(H$1,SUBQH,0),0),"") | I15: =IFERROR(VLOOKUP($A15,subQ,MATCH(I$1,SUBQH,0),0),"") | J15: =IFERROR(VLOOKUP($A15,subQ,MATCH(J$1,SUBQH,0),0),"") | K15: =IFERROR(VLOOKUP($A15,subQ,MATCH(K$1,SUBQH,0),0),"") | L15: =IFERROR(VLOOKUP($A15,subQ,MATCH(L$1,SUBQH,0),0),"") | ... AG15: =IFERROR(VLOOKUP($A15,subQ,MATCH(AG$1,SUBQH,0),0),"")
A16: 세전이익 | D16: 법인세비용차감전이익 | E16: =IFERROR(VLOOKUP($A16,subQ,MATCH(E$1,SUBQH,0),0),"") | F16: =IFERROR(VLOOKUP($A16,subQ,MATCH(F$1,SUBQH,0),0),"") | G16: =IFERROR(VLOOKUP($A16,subQ,MATCH(G$1,SUBQH,0),0),"") | H16: =IFERROR(VLOOKUP($A16,subQ,MATCH(H$1,SUBQH,0),0),"") | I16: =IFERROR(VLOOKUP($A16,subQ,MATCH(I$1,SUBQH,0),0),"") | J16: =IFERROR(VLOOKUP($A16,subQ,MATCH(J$1,SUBQH,0),0),"") | K16: =IFERROR(VLOOKUP($A16,subQ,MATCH(K$1,SUBQH,0),0),"") | L16: =IFERROR(VLOOKUP($A16,subQ,MATCH(L$1,SUBQH,0),0),"") | ... AG16: =IFERROR(VLOOKUP($A16,subQ,MATCH(AG$1,SUBQH,0),0),"")
... A38: NPM | D38: NPM | E38: =IFERROR(VLOOKUP($A38,subQ,MATCH(E$1,SUBQH,0),0),"") | F38: =IFERROR(VLOOKUP($A38,subQ,MATCH(F$1,SUBQH,0),0),"") | G38: =IFERROR(VLOOKUP($A38,subQ,MATCH(G$1,SUBQH,0),0),"") | H38: =IFERROR(VLOOKUP($A38,subQ,MATCH(H$1,SUBQH,0),0),"") | I38: =IFERROR(VLOOKUP($A38,subQ,MATCH(I$1,SUBQH,0),0),"") | J38: =IFERROR(VLOOKUP($A38,subQ,MATCH(J$1,SUBQH,0),0),"") | K38: =IFERROR(VLOOKUP($A38,subQ,MATCH(K$1,SUBQH,0),0),"") | L38: =IFERROR(VLOOKUP($A38,subQ,MATCH(L$1,SUBQH,0),0),"") | ... AG38: =IFERROR(VLOOKUP($A38,subQ,MATCH(AG$1,SUBQH,0),0),"")
A39: 매출액 YoY | D39: 매출액 YoY | I39: =IFERROR(I5/E5-1,"") | J39: =IFERROR(J5/F5-1,"") | K39: =IFERROR(K5/G5-1,"") | L39: =IFERROR(L5/H5-1,"") | M39: =IFERROR(M5/I5-1,"") | N39: =IFERROR(N5/J5-1,"") | O39: =IFERROR(O5/K5-1,"") | P39: =IFERROR(P5/L5-1,"") | ... AG39: =IFERROR(AG5/AC5-1,"")
A40: 영업이익 YoY | D40: 영업이익 YoY | I40: =IFERROR(I9/E9-1,"") | J40: =IFERROR(J9/F9-1,"") | K40: =IFERROR(K9/G9-1,"") | L40: =IFERROR(L9/H9-1,"") | M40: =IFERROR(M9/I9-1,"") | N40: =IFERROR(N9/J9-1,"") | O40: =IFERROR(O9/K9-1,"") | P40: =IFERROR(P9/L9-1,"") | ... AG40: =IFERROR(AG9/AC9-1,"")
A41: 지배주주순이익 YoY | D41: 지배주주순이익 YoY | I41: =IFERROR(I19/E19-1,"") | J41: =IFERROR(J19/F19-1,"") | K41: =IFERROR(K19/G19-1,"") | L41: =IFERROR(L19/H19-1,"") | M41: =IFERROR(M19/I19-1,"") | N41: =IFERROR(N19/J19-1,"") | O41: =IFERROR(O19/K19-1,"") | P41: =IFERROR(P19/L19-1,"") | ... AG41: =IFERROR(AG19/AC19-1,"")

Sheet 연간예상
C1: 이름: 연간예상H — subQ 를 이름으로 VLOOKUP(억원) | E1: 2021 | F1: 2022 | G1: 2023 | H1: 2024 | I1: 2025 | J1: 2026 | K1: 2027 | L1: 2028
C2: 종가: | D2: =변수!D43
C3: 기준일: | D3: 20261008 | E3: 1 | F3: 2 | G3: 3 | H3: 4 | I3: 5 | J3: 6 | K3: 7 | L3: 8
E4: 2021.12A | F4: 2022.12A | G4: 2023.12A | H4: 2024.12A | I4: 2025.12A | J4: 2026.12A | K4: 2027.12A | L4: 2028.12A
A5: 매출액 | D5: 매출액 | E5: =IFERROR(VLOOKUP($A5,subQ,MATCH(E$1,SUBQH,0),0),"") | F5: =IFERROR(VLOOKUP($A5,subQ,MATCH(F$1,SUBQH,0),0),"") | G5: =IFERROR(VLOOKUP($A5,subQ,MATCH(G$1,SUBQH,0),0),"") | H5: =IFERROR(VLOOKUP($A5,subQ,MATCH(H$1,SUBQH,0),0),"") | I5: =IFERROR(VLOOKUP($A5,subQ,MATCH(I$1,SUBQH,0),0),"") | J5: =IFERROR(VLOOKUP($A5,subQ,MATCH(J$1,SUBQH,0),0),"") | K5: =IFERROR(VLOOKUP($A5,subQ,MATCH(K$1,SUBQH,0),0),"") | L5: =IFERROR(VLOOKUP($A5,subQ,MATCH(L$1,SUBQH,0),0),"")
A6: 매출원가 | D6: 매출원가 | E6: =IFERROR(VLOOKUP($A6,subQ,MATCH(E$1,SUBQH,0),0),"") | F6: =IFERROR(VLOOKUP($A6,subQ,MATCH(F$1,SUBQH,0),0),"") | G6: =IFERROR(VLOOKUP($A6,subQ,MATCH(G$1,SUBQH,0),0),"") | H6: =IFERROR(VLOOKUP($A6,subQ,MATCH(H$1,SUBQH,0),0),"") | I6: =IFERROR(VLOOKUP($A6,subQ,MATCH(I$1,SUBQH,0),0),"") | J6: =IFERROR(VLOOKUP($A6,subQ,MATCH(J$1,SUBQH,0),0),"") | K6: =IFERROR(VLOOKUP($A6,subQ,MATCH(K$1,SUBQH,0),0),"") | L6: =IFERROR(VLOOKUP($A6,subQ,MATCH(L$1,SUBQH,0),0),"")
A7: 매출총이익 | D7: 매출총이익 | E7: =IFERROR(VLOOKUP($A7,subQ,MATCH(E$1,SUBQH,0),0),"") | F7: =IFERROR(VLOOKUP($A7,subQ,MATCH(F$1,SUBQH,0),0),"") | G7: =IFERROR(VLOOKUP($A7,subQ,MATCH(G$1,SUBQH,0),0),"") | H7: =IFERROR(VLOOKUP($A7,subQ,MATCH(H$1,SUBQH,0),0),"") | I7: =IFERROR(VLOOKUP($A7,subQ,MATCH(I$1,SUBQH,0),0),"") | J7: =IFERROR(VLOOKUP($A7,subQ,MATCH(J$1,SUBQH,0),0),"") | K7: =IFERROR(VLOOKUP($A7,subQ,MATCH(K$1,SUBQH,0),0),"") | L7: =IFERROR(VLOOKUP($A7,subQ,MATCH(L$1,SUBQH,0),0),"")
A8: 판관비 | D8: 판매비와관리비 | E8: =IFERROR(VLOOKUP($A8,subQ,MATCH(E$1,SUBQH,0),0),"") | F8: =IFERROR(VLOOKUP($A8,subQ,MATCH(F$1,SUBQH,0),0),"") | G8: =IFERROR(VLOOKUP($A8,subQ,MATCH(G$1,SUBQH,0),0),"") | H8: =IFERROR(VLOOKUP($A8,subQ,MATCH(H$1,SUBQH,0),0),"") | I8: =IFERROR(VLOOKUP($A8,subQ,MATCH(I$1,SUBQH,0),0),"") | J8: =IFERROR(VLOOKUP($A8,subQ,MATCH(J$1,SUBQH,0),0),"") | K8: =IFERROR(VLOOKUP($A8,subQ,MATCH(K$1,SUBQH,0),0),"") | L8: =IFERROR(VLOOKUP($A8,subQ,MATCH(L$1,SUBQH,0),0),"")
A9: 영업이익 | D9: 영업이익 | E9: =IFERROR(VLOOKUP($A9,subQ,MATCH(E$1,SUBQH,0),0),"") | F9: =IFERROR(VLOOKUP($A9,subQ,MATCH(F$1,SUBQH,0),0),"") | G9: =IFERROR(VLOOKUP($A9,subQ,MATCH(G$1,SUBQH,0),0),"") | H9: =IFERROR(VLOOKUP($A9,subQ,MATCH(H$1,SUBQH,0),0),"") | I9: =IFERROR(VLOOKUP($A9,subQ,MATCH(I$1,SUBQH,0),0),"") | J9: =IFERROR(VLOOKUP($A9,subQ,MATCH(J$1,SUBQH,0),0),"") | K9: =IFERROR(VLOOKUP($A9,subQ,MATCH(K$1,SUBQH,0),0),"") | L9: =IFERROR(VLOOKUP($A9,subQ,MATCH(L$1,SUBQH,0),0),"")
A10: OPM | D10: 영업이익률 | E10: =IFERROR(VLOOKUP($A10,subQ,MATCH(E$1,SUBQH,0),0),"") | F10: =IFERROR(VLOOKUP($A10,subQ,MATCH(F$1,SUBQH,0),0),"") | G10: =IFERROR(VLOOKUP($A10,subQ,MATCH(G$1,SUBQH,0),0),"") | H10: =IFERROR(VLOOKUP($A10,subQ,MATCH(H$1,SUBQH,0),0),"") | I10: =IFERROR(VLOOKUP($A10,subQ,MATCH(I$1,SUBQH,0),0),"") | J10: =IFERROR(VLOOKUP($A10,subQ,MATCH(J$1,SUBQH,0),0),"") | K10: =IFERROR(VLOOKUP($A10,subQ,MATCH(K$1,SUBQH,0),0),"") | L10: =IFERROR(VLOOKUP($A10,subQ,MATCH(L$1,SUBQH,0),0),"")
A11: 금융손익 | D11: 금융손익(이자·환 포함) | E11: =IFERROR(VLOOKUP($A11,subQ,MATCH(E$1,SUBQH,0),0),"") | F11: =IFERROR(VLOOKUP($A11,subQ,MATCH(F$1,SUBQH,0),0),"") | G11: =IFERROR(VLOOKUP($A11,subQ,MATCH(G$1,SUBQH,0),0),"") | H11: =IFERROR(VLOOKUP($A11,subQ,MATCH(H$1,SUBQH,0),0),"") | I11: =IFERROR(VLOOKUP($A11,subQ,MATCH(I$1,SUBQH,0),0),"") | J11: =IFERROR(VLOOKUP($A11,subQ,MATCH(J$1,SUBQH,0),0),"") | K11: =IFERROR(VLOOKUP($A11,subQ,MATCH(K$1,SUBQH,0),0),"") | L11: =IFERROR(VLOOKUP($A11,subQ,MATCH(L$1,SUBQH,0),0),"")
A12: 이자손익 | D12: 이자손익(이자수익 − 이자비용) | E12: =IFERROR(VLOOKUP($A12,subQ,MATCH(E$1,SUBQH,0),0),"") | F12: =IFERROR(VLOOKUP($A12,subQ,MATCH(F$1,SUBQH,0),0),"") | G12: =IFERROR(VLOOKUP($A12,subQ,MATCH(G$1,SUBQH,0),0),"") | H12: =IFERROR(VLOOKUP($A12,subQ,MATCH(H$1,SUBQH,0),0),"") | I12: =IFERROR(VLOOKUP($A12,subQ,MATCH(I$1,SUBQH,0),0),"") | J12: =IFERROR(VLOOKUP($A12,subQ,MATCH(J$1,SUBQH,0),0),"") | K12: =IFERROR(VLOOKUP($A12,subQ,MATCH(K$1,SUBQH,0),0),"") | L12: =IFERROR(VLOOKUP($A12,subQ,MATCH(L$1,SUBQH,0),0),"")
A13: 파생상품손익 | D13: 파생상품손익 | E13: =IFERROR(VLOOKUP($A13,subQ,MATCH(E$1,SUBQH,0),0),"") | F13: =IFERROR(VLOOKUP($A13,subQ,MATCH(F$1,SUBQH,0),0),"") | G13: =IFERROR(VLOOKUP($A13,subQ,MATCH(G$1,SUBQH,0),0),"") | H13: =IFERROR(VLOOKUP($A13,subQ,MATCH(H$1,SUBQH,0),0),"") | I13: =IFERROR(VLOOKUP($A13,subQ,MATCH(I$1,SUBQH,0),0),"") | J13: =IFERROR(VLOOKUP($A13,subQ,MATCH(J$1,SUBQH,0),0),"") | K13: =IFERROR(VLOOKUP($A13,subQ,MATCH(K$1,SUBQH,0),0),"") | L13: =IFERROR(VLOOKUP($A13,subQ,MATCH(L$1,SUBQH,0),0),"")
A14: 기타영업외손익 | D14: 기타영업외손익 | E14: =IFERROR(VLOOKUP($A14,subQ,MATCH(E$1,SUBQH,0),0),"") | F14: =IFERROR(VLOOKUP($A14,subQ,MATCH(F$1,SUBQH,0),0),"") | G14: =IFERROR(VLOOKUP($A14,subQ,MATCH(G$1,SUBQH,0),0),"") | H14: =IFERROR(VLOOKUP($A14,subQ,MATCH(H$1,SUBQH,0),0),"") | I14: =IFERROR(VLOOKUP($A14,subQ,MATCH(I$1,SUBQH,0),0),"") | J14: =IFERROR(VLOOKUP($A14,subQ,MATCH(J$1,SUBQH,0),0),"") | K14: =IFERROR(VLOOKUP($A14,subQ,MATCH(K$1,SUBQH,0),0),"") | L14: =IFERROR(VLOOKUP($A14,subQ,MATCH(L$1,SUBQH,0),0),"")
A15: 지분법손익 | D15: 지분법손익 | E15: =IFERROR(VLOOKUP($A15,subQ,MATCH(E$1,SUBQH,0),0),"") | F15: =IFERROR(VLOOKUP($A15,subQ,MATCH(F$1,SUBQH,0),0),"") | G15: =IFERROR(VLOOKUP($A15,subQ,MATCH(G$1,SUBQH,0),0),"") | H15: =IFERROR(VLOOKUP($A15,subQ,MATCH(H$1,SUBQH,0),0),"") | I15: =IFERROR(VLOOKUP($A15,subQ,MATCH(I$1,SUBQH,0),0),"") | J15: =IFERROR(VLOOKUP($A15,subQ,MATCH(J$1,SUBQH,0),0),"") | K15: =IFERROR(VLOOKUP($A15,subQ,MATCH(K$1,SUBQH,0),0),"") | L15: =IFERROR(VLOOKUP($A15,subQ,MATCH(L$1,SUBQH,0),0),"")
A16: 세전이익 | D16: 법인세비용차감전이익 | E16: =IFERROR(VLOOKUP($A16,subQ,MATCH(E$1,SUBQH,0),0),"") | F16: =IFERROR(VLOOKUP($A16,subQ,MATCH(F$1,SUBQH,0),0),"") | G16: =IFERROR(VLOOKUP($A16,subQ,MATCH(G$1,SUBQH,0),0),"") | H16: =IFERROR(VLOOKUP($A16,subQ,MATCH(H$1,SUBQH,0),0),"") | I16: =IFERROR(VLOOKUP($A16,subQ,MATCH(I$1,SUBQH,0),0),"") | J16: =IFERROR(VLOOKUP($A16,subQ,MATCH(J$1,SUBQH,0),0),"") | K16: =IFERROR(VLOOKUP($A16,subQ,MATCH(K$1,SUBQH,0),0),"") | L16: =IFERROR(VLOOKUP($A16,subQ,MATCH(L$1,SUBQH,0),0),"")
... A38: NPM | D38: NPM | E38: =IFERROR(VLOOKUP($A38,subQ,MATCH(E$1,SUBQH,0),0),"") | F38: =IFERROR(VLOOKUP($A38,subQ,MATCH(F$1,SUBQH,0),0),"") | G38: =IFERROR(VLOOKUP($A38,subQ,MATCH(G$1,SUBQH,0),0),"") | H38: =IFERROR(VLOOKUP($A38,subQ,MATCH(H$1,SUBQH,0),0),"") | I38: =IFERROR(VLOOKUP($A38,subQ,MATCH(I$1,SUBQH,0),0),"") | J38: =IFERROR(VLOOKUP($A38,subQ,MATCH(J$1,SUBQH,0),0),"") | K38: =IFERROR(VLOOKUP($A38,subQ,MATCH(K$1,SUBQH,0),0),"") | L38: =IFERROR(VLOOKUP($A38,subQ,MATCH(L$1,SUBQH,0),0),"")
A39: 매출액 YoY | D39: 매출액 YoY | F39: =IFERROR(F5/E5-1,"") | G39: =IFERROR(G5/F5-1,"") | H39: =IFERROR(H5/G5-1,"") | I39: =IFERROR(I5/H5-1,"") | J39: =IFERROR(J5/I5-1,"") | K39: =IFERROR(K5/J5-1,"") | L39: =IFERROR(L5/K5-1,"")
A40: 영업이익 YoY | D40: 영업이익 YoY | F40: =IFERROR(F9/E9-1,"") | G40: =IFERROR(G9/F9-1,"") | H40: =IFERROR(H9/G9-1,"") | I40: =IFERROR(I9/H9-1,"") | J40: =IFERROR(J9/I9-1,"") | K40: =IFERROR(K9/J9-1,"") | L40: =IFERROR(L9/K9-1,"")
A41: 지배주주순이익 YoY | D41: 지배주주순이익 YoY | F41: =IFERROR(F19/E19-1,"") | G41: =IFERROR(G19/F19-1,"") | H41: =IFERROR(H19/G19-1,"") | I41: =IFERROR(I19/H19-1,"") | J41: =IFERROR(J19/I19-1,"") | K41: =IFERROR(K19/J19-1,"") | L41: =IFERROR(L19/K19-1,"")

Sheet TP
B1: 종가 | C1: =변수!D43
B2: 기준일 | C2: =변수!D44
B3: 모델 산출값 — 목표주가·추천 아님. 밴드·COE 는 변수 시트 3절의 가정
C5: FY | D5: 2025 | E5: 2026 | F5: 2027 | G5: 2028
D6: A | E6: E | F6: E | G6: E
C7: EPS(원) | D7: =IFERROR(VLOOKUP("EPS",subQ,MATCH(D$5,SUBQH,0),0),"") | E7: =IFERROR(VLOOKUP("EPS",subQ,MATCH(E$5,SUBQH,0),0),"") | F7: =IFERROR(VLOOKUP("EPS",subQ,MATCH(F$5,SUBQH,0),0),"") | G7: =IFERROR(VLOOKUP("EPS",subQ,MATCH(G$5,SUBQH,0),0),"")
C8: BPS(원) | D8: =IFERROR(VLOOKUP("BPS",subQ,MATCH(D$5,SUBQH,0),0),"") | E8: =IFERROR(VLOOKUP("BPS",subQ,MATCH(E$5,SUBQH,0),0),"") | F8: =IFERROR(VLOOKUP("BPS",subQ,MATCH(F$5,SUBQH,0),0),"") | G8: =IFERROR(VLOOKUP("BPS",subQ,MATCH(G$5,SUBQH,0),0),"")
C9: 지배주주순이익(억원) | D9: =IFERROR(VLOOKUP("지배주주순이익",subQ,MATCH(D$5,SUBQH,0),0),"") | E9: =IFERROR(VLOOKUP("지배주주순이익",subQ,MATCH(E$5,SUBQH,0),0),"") | F9: =IFERROR(VLOOKUP("지배주주순이익",subQ,MATCH(F$5,SUBQH,0),0),"") | G9: =IFERROR(VLOOKUP("지배주주순이익",subQ,MATCH(G$5,SUBQH,0),0),"")
C10: 영업이익(억원) | D10: =IFERROR(VLOOKUP("영업이익",subQ,MATCH(D$5,SUBQH,0),0),"") | E10: =IFERROR(VLOOKUP("영업이익",subQ,MATCH(E$5,SUBQH,0),0),"") | F10: =IFERROR(VLOOKUP("영업이익",subQ,MATCH(F$5,SUBQH,0),0),"") | G10: =IFERROR(VLOOKUP("영업이익",subQ,MATCH(G$5,SUBQH,0),0),"")
C11: ROE(EPS/기초BPS) | E11: =IFERROR(E7/D8,"") | F11: =IFERROR(F7/E8,"") | G11: =IFERROR(G7/F8,"")
B13: PER
C14: 12M fwd EPS | D14: =IFERROR(E7*변수!D49+F7*(1-변수!D49),"")
C15: 적정가치 @PER_lo | D15: =변수!D46 | E15: =IFERROR(ROUND($D$14*D15,-2),"") | F15: =IFERROR(E15/$C$1-1,"") | G15: 배 · 원 · 종가 대비
C16: 적정가치 @PER_mid | D16: =변수!D47 | E16: =IFERROR(ROUND($D$14*D16,-2),"") | F16: =IFERROR(E16/$C$1-1,"") | G16: 배 · 원 · 종가 대비
C17: 적정가치 @PER_hi | D17: =변수!D48 | E17: =IFERROR(ROUND($D$14*D17,-2),"") | F17: =IFERROR(E17/$C$1-1,"") | G17: 배 · 원 · 종가 대비
C18: 현재 PER(종가/12M fwd EPS) | D18: =IFERROR($C$1/$D$14,"")
B20: PBR
C21: 최근 BPS(마지막 실적 분기) | D21: =IFERROR(VLOOKUP("BPS",subQ,MATCH("2Q26",SUBQH,0),0),"")
C22: ROE fwd(12M fwd EPS / BPS) | D22: =IFERROR($D$14/$D$21,"")
C23: COE | D23: =변수!D45
C24: 적정 PBR = ROE/COE | D24: =IFERROR(D22/D23,"")
C25: 적정가치(PBR) = BPS × 적정PBR | D25: =IFERROR(ROUND(D21*D24,-2),"") | E25: =IFERROR(D25/$C$1-1,"")
C26: 현재 PBR(종가/BPS) | D26: =IFERROR($C$1/D21,"")
B28: 모델 json valuation(참고)
C29: eps_fwd12m | D29: -860.9
C30: bps_latest | D30: 8064.4
C31: per_now
C32: pbr_now | D32: 0.28
C33: roe_fwd | D33: -0.1068
C34: fair_pbr
C35: fair_value_pbr
C36: ev_ebitda
C37: note | D37: 모델 산출값 — 목표주가·추천 아님

Sheet 외화
C1: 이름: 외화QH — 환율 QoQ · 외화 순노출 × Δ기말환율 | E1: 4Q21 | F1: 1Q22 | G1: 2Q22 | H1: 3Q22 | I1: 4Q22 | J1: 1Q23 | K1: 2Q23 | L1: 3Q23 | M1: 4Q23 | N1: 1Q24 | O1: 2Q24 | P1: 3Q24 | Q1: 4Q24 | R1: 1Q25 | S1: 2Q25 | T1: 3Q25 | U1: 4Q25 | V1: 1Q26 | W1: 2Q26 | X1: 3Q26 | Y1: 4Q26 | Z1: 1Q27 | AA1: 2Q27 | AB1: 3Q27 | AC1: 4Q27 | AD1: 1Q28 | AE1: 2Q28 | AF1: 3Q28 | AG1: 4Q28
E3: 1 | F3: 2 | G3: 3 | H3: 4 | I3: 5 | J3: 6 | K3: 7 | L3: 8 | M3: 9 | N3: 10 | O3: 11 | P3: 12 | Q3: 13 | R3: 14 | S3: 15 | T3: 16 | U3: 17 | V3: 18 | W3: 19 | X3: 20 | Y3: 21 | Z3: 22 | AA3: 23 | AB3: 24 | AC3: 25 | AD3: 26 | AE3: 27 | AF3: 28 | AG3: 29
E4: 2021.12 | F4: 2022.03 | G4: 2022.06 | H4: 2022.09 | I4: 2022.12 | J4: 2023.03 | K4: 2023.06 | L4: 2023.09 | M4: 2023.12 | N4: 2024.03 | O4: 2024.06 | P4: 2024.09 | Q4: 2024.12 | R4: 2025.03 | S4: 2025.06 | T4: 2025.09 | U4: 2025.12 | V4: 2026.03 | W4: 2026.06 | X4: 2026.09 | Y4: 2026.12 | Z4: 2027.03 | AA4: 2027.06 | AB4: 2027.09 | AC4: 2027.12 | AD4: 2028.03 | AE4: 2028.06 | AF4: 2028.09 | AG4: 2028.12
D5: 원/달러(평균) | E5: =IFERROR(VLOOKUP($D5,환율,MATCH(E$1,변수H,0),0),"") | F5: =IFERROR(VLOOKUP($D5,환율,MATCH(F$1,변수H,0),0),"") | G5: =IFERROR(VLOOKUP($D5,환율,MATCH(G$1,변수H,0),0),"") | H5: =IFERROR(VLOOKUP($D5,환율,MATCH(H$1,변수H,0),0),"") | I5: =IFERROR(VLOOKUP($D5,환율,MATCH(I$1,변수H,0),0),"") | J5: =IFERROR(VLOOKUP($D5,환율,MATCH(J$1,변수H,0),0),"") | K5: =IFERROR(VLOOKUP($D5,환율,MATCH(K$1,변수H,0),0),"") | L5: =IFERROR(VLOOKUP($D5,환율,MATCH(L$1,변수H,0),0),"") | ... AG5: =IFERROR(VLOOKUP($D5,환율,MATCH(AG$1,변수H,0),0),"")
A6: 원/달러(평균) QoQ | F6: =IFERROR(F5/E5-1,"") | G6: =IFERROR(G5/F5-1,"") | H6: =IFERROR(H5/G5-1,"") | I6: =IFERROR(I5/H5-1,"") | J6: =IFERROR(J5/I5-1,"") | K6: =IFERROR(K5/J5-1,"") | L6: =IFERROR(L5/K5-1,"") | M6: =IFERROR(M5/L5-1,"") | ... AG6: =IFERROR(AG5/AF5-1,"")
D7: 원/달러(기말) | E7: =IFERROR(VLOOKUP($D7,환율,MATCH(E$1,변수H,0),0),"") | F7: =IFERROR(VLOOKUP($D7,환율,MATCH(F$1,변수H,0),0),"") | G7: =IFERROR(VLOOKUP($D7,환율,MATCH(G$1,변수H,0),0),"") | H7: =IFERROR(VLOOKUP($D7,환율,MATCH(H$1,변수H,0),0),"") | I7: =IFERROR(VLOOKUP($D7,환율,MATCH(I$1,변수H,0),0),"") | J7: =IFERROR(VLOOKUP($D7,환율,MATCH(J$1,변수H,0),0),"") | K7: =IFERROR(VLOOKUP($D7,환율,MATCH(K$1,변수H,0),0),"") | L7: =IFERROR(VLOOKUP($D7,환율,MATCH(L$1,변수H,0),0),"") | ... AG7: =IFERROR(VLOOKUP($D7,환율,MATCH(AG$1,변수H,0),0),"")
A8: 원/달러(기말) QoQ | F8: =IFERROR(F7/E7-1,"") | G8: =IFERROR(G7/F7-1,"") | H8: =IFERROR(H7/G7-1,"") | I8: =IFERROR(I7/H7-1,"") | J8: =IFERROR(J7/I7-1,"") | K8: =IFERROR(K7/J7-1,"") | L8: =IFERROR(L7/K7-1,"") | M8: =IFERROR(M7/L7-1,"") | ... AG8: =IFERROR(AG7/AF7-1,"")
D9: W/Euro(평균) | E9: =IFERROR(VLOOKUP($D9,환율,MATCH(E$1,변수H,0),0),"") | F9: =IFERROR(VLOOKUP($D9,환율,MATCH(F$1,변수H,0),0),"") | G9: =IFERROR(VLOOKUP($D9,환율,MATCH(G$1,변수H,0),0),"") | H9: =IFERROR(VLOOKUP($D9,환율,MATCH(H$1,변수H,0),0),"") | I9: =IFERROR(VLOOKUP($D9,환율,MATCH(I$1,변수H,0),0),"") | J9: =IFERROR(VLOOKUP($D9,환율,MATCH(J$1,변수H,0),0),"") | K9: =IFERROR(VLOOKUP($D9,환율,MATCH(K$1,변수H,0),0),"") | L9: =IFERROR(VLOOKUP($D9,환율,MATCH(L$1,변수H,0),0),"") | ... AG9: =IFERROR(VLOOKUP($D9,환율,MATCH(AG$1,변수H,0),0),"")
A10: W/Euro(평균) QoQ | F10: =IFERROR(F9/E9-1,"") | G10: =IFERROR(G9/F9-1,"") | H10: =IFERROR(H9/G9-1,"") | I10: =IFERROR(I9/H9-1,"") | J10: =IFERROR(J9/I9-1,"") | K10: =IFERROR(K9/J9-1,"") | L10: =IFERROR(L9/K9-1,"") | M10: =IFERROR(M9/L9-1,"") | ... AG10: =IFERROR(AG9/AF9-1,"")
D11: W/Euro(기말) | E11: =IFERROR(VLOOKUP($D11,환율,MATCH(E$1,변수H,0),0),"") | F11: =IFERROR(VLOOKUP($D11,환율,MATCH(F$1,변수H,0),0),"") | G11: =IFERROR(VLOOKUP($D11,환율,MATCH(G$1,변수H,0),0),"") | H11: =IFERROR(VLOOKUP($D11,환율,MATCH(H$1,변수H,0),0),"") | I11: =IFERROR(VLOOKUP($D11,환율,MATCH(I$1,변수H,0),0),"") | J11: =IFERROR(VLOOKUP($D11,환율,MATCH(J$1,변수H,0),0),"") | K11: =IFERROR(VLOOKUP($D11,환율,MATCH(K$1,변수H,0),0),"") | L11: =IFERROR(VLOOKUP($D11,환율,MATCH(L$1,변수H,0),0),"") | ... AG11: =IFERROR(VLOOKUP($D11,환율,MATCH(AG$1,변수H,0),0),"")
A12: W/Euro(기말) QoQ | F12: =IFERROR(F11/E11-1,"") | G12: =IFERROR(G11/F11-1,"") | H12: =IFERROR(H11/G11-1,"") | I12: =IFERROR(I11/H11-1,"") | J12: =IFERROR(J11/I11-1,"") | K12: =IFERROR(K11/J11-1,"") | L12: =IFERROR(L11/K11-1,"") | M12: =IFERROR(M11/L11-1,"") | ... AG12: =IFERROR(AG11/AF11-1,"")
D13: 원/100Y(기말) | E13: =IFERROR(VLOOKUP($D13,환율,MATCH(E$1,변수H,0),0),"") | F13: =IFERROR(VLOOKUP($D13,환율,MATCH(F$1,변수H,0),0),"") | G13: =IFERROR(VLOOKUP($D13,환율,MATCH(G$1,변수H,0),0),"") | H13: =IFERROR(VLOOKUP($D13,환율,MATCH(H$1,변수H,0),0),"") | I13: =IFERROR(VLOOKUP($D13,환율,MATCH(I$1,변수H,0),0),"") | J13: =IFERROR(VLOOKUP($D13,환율,MATCH(J$1,변수H,0),0),"") | K13: =IFERROR(VLOOKUP($D13,환율,MATCH(K$1,변수H,0),0),"") | L13: =IFERROR(VLOOKUP($D13,환율,MATCH(L$1,변수H,0),0),"") | ... AG13: =IFERROR(VLOOKUP($D13,환율,MATCH(AG$1,변수H,0),0),"")
A14: 원/100Y(기말) QoQ | F14: =IFERROR(F13/E13-1,"") | G14: =IFERROR(G13/F13-1,"") | H14: =IFERROR(H13/G13-1,"") | I14: =IFERROR(I13/H13-1,"") | J14: =IFERROR(J13/I13-1,"") | K14: =IFERROR(K13/J13-1,"") | L14: =IFERROR(L13/K13-1,"") | M14: =IFERROR(M13/L13-1,"") | ... AG14: =IFERROR(AG13/AF13-1,"")
A16: 외화순노출 | C16: 외화 순노출(백만$) | D16: =변수!D56 | E16: 외화 순노출 × Δ기말환율 (외화 시트 방식)
A17: 환관련손익추정 | C17: 환관련손익 추정(억원) = 순노출 × Δ원/달러(기말) / 100 | F17: =IFERROR($D$16*(F7-E7)/100,"") | G17: =IFERROR($D$16*(G7-F7)/100,"") | H17: =IFERROR($D$16*(H7-G7)/100,"") | I17: =IFERROR($D$16*(I7-H7)/100,"") | J17: =IFERROR($D$16*(J7-I7)/100,"") | K17: =IFERROR($D$16*(K7-J7)/100,"") | L17: =IFERROR($D$16*(L7-K7)/100,"") | M17: =IFERROR($D$16*(M7-L7)/100,"") | ... AG17: =IFERROR($D$16*(AG7-AF7)/100,"")
A18: fx_pnl.by_q | C18: 모델 fx_pnl.by_q(억원, 참고)
C19: 외화 순노출 미공시(face) → 0 + 표기
