Workbook
Name 변수H: 변수!$C$1:$AO$1
Name 환율: 변수!$C$6:$AO$13
Name BS연결H: BS연결!$C$1:$AO$1
Name BS연결: BS연결!$C$5:$AO$106
Name BS별도H: BS별도!$C$1:$AO$1
Name BS별도: BS별도!$C$5:$AO$96
Name SUBQH: subQ!$A$1:$AO$1
Name subQ: subQ!$A$5:$AO$42

Sheet README
A1: 삼영엠텍(054540) 실적 모델 — ARGUS 한국조선
A2: 기준 분기 2026Q2 · 마지막 실적 2026Q2 · 생성 2026-10-12
A3: 모든 수치는 모델 산출값(DART 공개 재무제표 + 우리 추정)이다 — 목표주가·투자 추천 아님. 참고용 · 투자조언 아님.
A5: 시트
A6: 변수 가정 시계열. 환율 8행(ECB via frankfurter — L2 fx.json; 추정 분기 = 노란 가정), 추정 드라이버(노란 셀 = 모델값에서 역산한 가정, 바꾸면 재계산; 연녹 셀 = 3절 스칼라 참조 수식), 3절 스칼라 가정(세율·판관비율·지배주주비중·이자율·종가·PER 밴드·COE·외화 순노출·헤지비율)
A7: BS연결/BS별도 FnGuide 계정명 × 기간 값 덤프(백만원). 행1 분기라벨, 행4 YYYY.MM / YYYY.12A. 이름정의 BS연결H·BS연결(계정명 C열부터)
A8: subQ 분기 서브모델(억원 = 백만원/100). 확정 행: =IFERROR(VLOOKUP($D행,BS연결,MATCH(E$1,BS연결H,0),0)/100,"") 추정 행: 변수 시트 가정 셀 참조 수식. 외환손익·파생상품손익은 BS 계정 합·차, 기타금융손익은 잔차, OPM·EPS·BPS·PER·PBR 은 파생 수식
A9: SLS 선표(조선사만, sls json 있을 때): 요약 행(sls 저장값) + 계약별 스케줄(백만$) × (헤지비율 × 헤지환율 + (1−헤지비율) × 건조시점 환율[변수 원/달러(평균)]) → 원화 수식 블록 → 합계 행이 subQ 매출조선에 연결
A10: 시나리오 신규수주 보수/기준/낙관(forecast_panel 패널, 모델에 scenarios 가 있을 때만): 매출액·영업이익 = subQ 기준값 ± (시나리오 신규 − base 신규) × OPM. base 만 subQ 행에 포함, 나머지는 합산 안 함
A11: 분기/연간예상 subQ 를 이름(A열 key)으로 VLOOKUP 한 보고서 표(억원)
A12: TP PER 밴드 × 12M fwd EPS, PBR = ROE/COE × BPS — 모델 산출값 구간, 목표주가·추천 아님
A13: 외화 환율 QoQ, 외화 순노출 × Δ기말환율 → 환관련손익 추정
... A34: 백테스트: {"freeze": "2025Q2", "horizon": 4, "revenue_wape_pct": 62.3, "op_wape_pct": 35.9, "n": 4, "note": "단일 회사 4분기 — 통계 아님", "driver_at_freeze": "customer_yard_revenue_weighted", "selection_oos_at_freeze": {"freeze": "2024Q2", "n": 4, "wape_link": 5.6, "wape_trend": 19.9, "adopted": true, "decision": "adopted"}, "frozen_inputs": "fin(연결/별도)·고객 조선사 모델·지주 자회사 모델은 2025Q2 까지의 분기만; 선표는 체결일 ≤ 2025Q2 말일 계약(원장 최신 금액·코호트 등급, 환산 없음); 잔고는 yards_cache 2025Q2; 시세·환율 forward·prices·forecast_panel 신규수주 미사용. 고객 가중치(suppliers.json 언급 비중)와 합병 체인링크는 현재 지식; 고객 연동 채택은 동결 모델 안에서도 자기 la−4분기 OOS 규칙(selection_oos_at_freeze)", "detail": [{"q": "2025Q3", "rev_pred": 348.44, "rev_act": 294.69, "op_pred": 34.47, "op_act": 34.11}, {"q": "2025Q4", "rev_pred": 345.4, "rev_act": 330.21, "op_pred": 34.17, "op_act": 15.02}, {"q": "2026Q1", "rev_pred": 307.05, "rev_act": 1309.1, "op_pred": 30.38, "op_act": 56.09}, {"q": "2026Q2", "rev_pred": 361.15, "rev_act": 1313.93, "op_pred": 35.73, "op_act": 31.76}]}

Sheet 변수
C1: 이름: 변수H | E1: 4Q21 | F1: 2021 | G1: 1Q22 | H1: 2Q22 | I1: 3Q22 | J1: 4Q22 | K1: 2022 | L1: 1Q23 | M1: 2Q23 | N1: 3Q23 | O1: 4Q23 | P1: 2023 | Q1: 1Q24 | R1: 2Q24 | S1: 3Q24 | T1: 4Q24 | U1: 2024 | V1: 1Q25 | W1: 2Q25 | X1: 3Q25 | Y1: 4Q25 | Z1: 2025 | AA1: 1Q26 | AB1: 2Q26 | AC1: 3Q26 | AD1: 4Q26 | AE1: 2026 | AF1: 1Q27 | AG1: 2Q27 | AH1: 3Q27 | AI1: 4Q27 | AJ1: 2027 | AK1: 1Q28 | AL1: 2Q28 | AM1: 3Q28 | AN1: 4Q28 | AO1: 2028
A2: 가정 시계열 — 노란 셀은 추정 가정(모델값에서 역산), 연녹 셀은 3절 스칼라 참조 수식. 바꾸면 subQ·분기·연간예상·TP·시나리오가 재계산됩니다.
E3: 1 | F3: 2 | G3: 3 | H3: 4 | I3: 5 | J3: 6 | K3: 7 | L3: 8 | M3: 9 | N3: 10 | O3: 11 | P3: 12 | Q3: 13 | R3: 14 | S3: 15 | T3: 16 | U3: 17 | V3: 18 | W3: 19 | X3: 20 | Y3: 21 | Z3: 22 | AA3: 23 | AB3: 24 | AC3: 25 | AD3: 26 | AE3: 27 | AF3: 28 | AG3: 29 | AH3: 30 | AI3: 31 | AJ3: 32 | AK3: 33 | AL3: 34 | AM3: 35 | AN3: 36 | AO3: 37
E4: 2021.12 | F4: 2021.12A | G4: 2022.03 | H4: 2022.06 | I4: 2022.09 | J4: 2022.12 | K4: 2022.12A | L4: 2023.03 | M4: 2023.06 | N4: 2023.09 | O4: 2023.12 | P4: 2023.12A | Q4: 2024.03 | R4: 2024.06 | S4: 2024.09 | T4: 2024.12 | U4: 2024.12A | V4: 2025.03 | W4: 2025.06 | X4: 2025.09 | Y4: 2025.12 | Z4: 2025.12A | AA4: 2026.03 | AB4: 2026.06 | AC4: 2026.09 | AD4: 2026.12 | AE4: 2026.12A | AF4: 2027.03 | AG4: 2027.06 | AH4: 2027.09 | AI4: 2027.12 | AJ4: 2027.12A | AK4: 2028.03 | AL4: 2028.06 | AM4: 2028.09 | AN4: 2028.12 | AO4: 2028.12A
B5: 1. FX | C5: 이름: 환율
A6: USDKRW_avg | C6: 원/달러(평균) | E6: 1183.5 | F6: 1145.51 | G6: 1205.78 | H6: 1262.09 | I6: 1341.93 | J6: 1360.12 | K6: 1292.98 | L6: 1276.95 | M6: 1315.69 | N6: 1313.62 | O6: 1322.01 | P6: 1306.85 | Q6: 1330.14 | R6: 1371.28 | S6: 1356.22 | T6: 1396.3 | U6: 1363.53 | V6: 1452.28 | W6: 1398.52 | X6: 1386.95 | Y6: 1449.19 | Z6: 1421.52 | AA6: 1466.12 | AB6: 1501.75 | AC6: 1418.75 | AD6: 1345.14 | AE6: 1457.21 | AF6: 1341.49 | AG6: 1341.49 | AH6: 1341.49 | AI6: 1341.49 | AK6: 1341.49 | AL6: 1341.49 | AM6: 1341.49 | AN6: 1341.49
A7: USDKRW_end | C7: 원/달러(기말) | E7: 1188.75 | F7: 1188.75 | G7: 1213.74 | H7: 1301.24 | I7: 1436.9 | J7: 1260.16 | K7: 1260.16 | L7: 1305.99 | M7: 1321.44 | N7: 1345.35 | O7: 1297.43 | P7: 1297.43 | Q7: 1349.25 | R7: 1377.73 | S7: 1312.17 | T7: 1474.78 | U7: 1474.78 | V7: 1474.54 | W7: 1355.13 | X7: 1403.67 | Y7: 1444.2 | Z7: 1444.2 | AA7: 1524.8 | AB7: 1550.89 | AC7: 1355.4 | AD7: 1341.49 | AE7: 1341.49 | AF7: 1341.49 | AG7: 1341.49 | AH7: 1341.49 | AI7: 1341.49 | AK7: 1341.49 | AL7: 1341.49 | AM7: 1341.49 | AN7: 1341.49
A8: JPY100KRW_avg | C8: 원/100Y(평균) | E8: 1041.02 | F8: 1042.74 | G8: 1036.79 | H8: 972.23 | I8: 970.61 | J8: 961.03 | K8: 985.1 | L8: 964.89 | M8: 957.36 | N8: 909 | O8: 893.22 | P8: 931.11 | Q8: 896.29 | R8: 880.14 | S8: 909.35 | T8: 917.25 | U8: 900.92 | V8: 952.59 | W8: 967.92 | X8: 940.32 | Y8: 940.77 | Z8: 950.17 | AA8: 934.39 | AB8: 942.16 | AC8: 890.41 | AD8: 850.79 | AE8: 919.21 | AF8: 847.7 | AG8: 847.7 | AH8: 847.7 | AI8: 847.7 | AK8: 847.7 | AL8: 847.7 | AM8: 847.7 | AN8: 847.7
A9: JPY100KRW_end | C9: 원/100Y(기말) | E9: 1032.62 | F9: 1032.62 | G9: 996.83 | H9: 954.9 | I9: 993.29 | J9: 955.54 | K9: 955.54 | L9: 980.62 | M9: 913.67 | N9: 901.47 | O9: 917.04 | P9: 917.04 | Q9: 892.42 | R9: 857.76 | S9: 919.21 | T9: 939.65 | U9: 939.65 | V9: 986.84 | W9: 938.85 | X9: 948.49 | Y9: 921.81 | Z9: 921.81 | AA9: 955.99 | AB9: 954.75 | AC9: 863.31 | AD9: 847.7 | AE9: 847.7 | AF9: 847.7 | AG9: 847.7 | AH9: 847.7 | AI9: 847.7 | AK9: 847.7 | AL9: 847.7 | AM9: 847.7 | AN9: 847.7
A10: EURKRW_avg | C10: W/Euro(평균) | E10: 1353.32 | F10: 1354.06 | G10: 1352.29 | H10: 1343.31 | I10: 1350.63 | J10: 1386.07 | K10: 1358.07 | L10: 1369.93 | M10: 1432.41 | N10: 1429.41 | O10: 1420.91 | P10: 1412.88 | Q10: 1444.21 | R10: 1476.42 | S10: 1489.3 | T10: 1490.78 | U10: 1475.4 | V10: 1528.33 | W10: 1585.13 | X10: 1620.04 | Y10: 1686.02 | Z10: 1605.45 | AA10: 1715.47 | AB10: 1746.09 | AC10: 1631.97 | AD10: 1509.74 | AE10: 1689.95 | AF10: 1503.27 | AG10: 1503.27 | AH10: 1503.27 | AI10: 1503.27 | AK10: 1503.27 | AL10: 1503.27 | AM10: 1503.27 | AN10: 1503.27
A11: EURKRW_end | C11: W/Euro(기말) | E11: 1346.38 | F11: 1346.38 | G11: 1347.37 | H11: 1351.6 | I11: 1400.62 | J11: 1344.08 | K11: 1344.08 | L11: 1420.26 | M11: 1435.88 | N11: 1425.26 | O11: 1433.66 | P11: 1433.66 | Q11: 1458.68 | R11: 1474.86 | S11: 1469.1 | T11: 1532.14 | U11: 1532.14 | V11: 1594.72 | W11: 1588.22 | X11: 1648.04 | Y11: 1696.94 | Z11: 1696.94 | AA11: 1753.21 | AB11: 1767.09 | AC11: 1539.06 | AD11: 1503.27 | AE11: 1503.27 | AF11: 1503.27 | AG11: 1503.27 | AH11: 1503.27 | AI11: 1503.27 | AK11: 1503.27 | AL11: 1503.27 | AM11: 1503.27 | AN11: 1503.27
A12: CNYKRW_avg | C12: 원/중국원(평균) | E12: 185.14 | F12: 177.65 | G12: 189.93 | H12: 190.76 | I12: 195.79 | J12: 191.09 | K12: 191.93 | L12: 186.59 | M12: 187.45 | N12: 181.28 | O12: 182.86 | P12: 184.52 | Q12: 185.04 | R12: 189.35 | S12: 189.24 | T12: 194.24 | U12: 189.49 | V12: 199.63 | W12: 193.41 | X12: 193.79 | Y12: 204.38 | Z12: 197.8 | AA12: 211.75 | AB12: 220.8 | AC12: 210.43 | AD12: 200.69 | AE12: 213.75 | AF12: 200.46 | AG12: 200.46 | AH12: 200.46 | AI12: 200.46 | AK12: 200.46 | AL12: 200.46 | AM12: 200.46 | AN12: 200.46
A13: CNYKRW_end | C13: 원/중국원(기말) | E13: 187.13 | F13: 187.13 | G13: 191.38 | H13: 194.13 | I13: 201.92 | J13: 182.67 | K13: 182.67 | L13: 189.97 | M13: 181.8 | N13: 184.26 | O13: 182.61 | P13: 182.61 | Q13: 186.66 | R13: 189.7 | S13: 187.12 | T13: 202.04 | U13: 202.04 | V13: 203.3 | W13: 189.14 | X13: 197.16 | Y13: 206.28 | Z13: 206.28 | AA13: 220.97 | AB13: 228.56 | AC13: 202.16 | AD13: 200.46 | AE13: 200.46 | AF13: 200.46 | AG13: 200.46 | AH13: 200.46 | AI13: 200.46 | AK13: 200.46 | AL13: 200.46 | AM13: 200.46 | AN13: 200.46
B14: 1b. 종가
A15: price_close_end | C15: 종가(기말) | E15: 4480 | G15: 4985 | H15: 4380 | I15: 4100 | J15: 3650 | L15: 3735 | M15: 4120 | N15: 3965 | O15: 4215 | Q15: 3960 | R15: 4695 | S15: 4150 | T15: 4605 | V15: 4420 | W15: 5850 | X15: 11590 | Y15: 13750 | AA15: 10480 | AB15: 7330 | AC15: 6800 | AD15: 6290
A16: price_high | C16: 종가(최고) | E16: 5460 | G16: 5610 | H16: 6810 | I16: 6170 | J16: 4340 | L16: 4550 | M16: 4320 | N16: 4720 | O16: 4670 | Q16: 4860 | R16: 4745 | S16: 6110 | T16: 4825 | V16: 5430 | W16: 6270 | X16: 16400 | Y16: 22800 | AA16: 16820 | AB16: 15840 | AC16: 8170 | AD16: 7470
A17: price_low | C17: 종가(최저) | E17: 3925 | G17: 3930 | H17: 3735 | I17: 3930 | J17: 3620 | L17: 3390 | M17: 3540 | N17: 3800 | O17: 3580 | Q17: 3860 | R17: 3575 | S17: 3830 | T17: 3575 | V17: 4420 | W17: 4310 | X17: 5000 | Y17: 10760 | AA17: 10300 | AB17: 6750 | AC17: 5160 | AD17: 6250
A18: price_avg | C18: 종가(평균) | E18: 4685.2 | G18: 4567.9 | H18: 4971.8 | I18: 5121.1 | J18: 4022.3 | L18: 3852.3 | M18: 3907.4 | N18: 4167.3 | O18: 4048.8 | Q18: 4004 | R18: 4221.4 | S18: 4674.1 | T18: 4204 | V18: 4864 | W18: 5246.2 | X18: 8077.4 | Y18: 15289.7 | AA18: 13559.5 | AB18: 10661.1 | AC18: 6596.1 | AD18: 6911.7
B20: 2. 추정 드라이버 | C20: 실적 열 = subQ 실현값(수식), 추정 열 = 가정(노란 = 모델값 역산, 연녹 = 3절 스칼라 참조)
A21: drv:매출액 | B21: yoy | C21: 매출액 YoY | J21: =IFERROR(subQ!J5/subQ!E5-1,"") | L21: =IFERROR(subQ!L5/subQ!G5-1,"") | M21: =IFERROR(subQ!M5/subQ!H5-1,"") | N21: =IFERROR(subQ!N5/subQ!I5-1,"") | O21: =IFERROR(subQ!O5/subQ!J5-1,"") | Q21: =IFERROR(subQ!Q5/subQ!L5-1,"") | R21: =IFERROR(subQ!R5/subQ!M5-1,"") | S21: =IFERROR(subQ!S5/subQ!N5-1,"") | T21: =IFERROR(subQ!T5/subQ!O5-1,"") | V21: =IFERROR(subQ!V5/subQ!Q5-1,"") | W21: =IFERROR(subQ!W5/subQ!R5-1,"") | X21: =IFERROR(subQ!X5/subQ!S5-1,"") | Y21: =IFERROR(subQ!Y5/subQ!T5-1,"") | AA21: =IFERROR(subQ!AA5/subQ!V5-1,"") | AB21: =IFERROR(subQ!AB5/subQ!W5-1,"") | AC21: 1.9437884 | AD21: 1.7361903 | AF21: -0.30103781 | AG21: -0.28538882 | AH21: 0.13837305 | AI21: 0.15340173 | AK21: 0.21059879 | AL21: 0.25269716 | AM21: 0.26398663 | AN21: 0.25295794
A22: drv:판관비 | B22: ratio | C22: 판관비율(/매출) | E22: =IFERROR(subQ!E8/subQ!E5,"") | F22: =IFERROR(subQ!F8/subQ!F5,"") | G22: =IFERROR(subQ!G8/subQ!G5,"") | H22: =IFERROR(subQ!H8/subQ!H5,"") | I22: =IFERROR(subQ!I8/subQ!I5,"") | J22: =IFERROR(subQ!J8/subQ!J5,"") | K22: =IFERROR(subQ!K8/subQ!K5,"") | L22: =IFERROR(subQ!L8/subQ!L5,"") | ... AB22: =IFERROR(subQ!AB8/subQ!AB5,"") | AC22: =$D$51 | AD22: =$D$51 | AE22: =IFERROR(subQ!AE8/subQ!AE5,"") | AF22: =$D$51 | AG22: =$D$51 | AH22: =$D$51 | AI22: =$D$51 | AJ22: =IFERROR(subQ!AJ8/subQ!AJ5,"") | AK22: =$D$51 | AL22: =$D$51 | AM22: =$D$51 | AN22: =$D$51 | AO22: =IFERROR(subQ!AO8/subQ!AO5,"")
A23: drv:영업이익 | B23: ratio | C23: 영업이익률(OPM) | E23: =IFERROR(subQ!E9/subQ!E5,"") | F23: =IFERROR(subQ!F9/subQ!F5,"") | G23: =IFERROR(subQ!G9/subQ!G5,"") | H23: =IFERROR(subQ!H9/subQ!H5,"") | I23: =IFERROR(subQ!I9/subQ!I5,"") | J23: =IFERROR(subQ!J9/subQ!J5,"") | K23: =IFERROR(subQ!K9/subQ!K5,"") | L23: =IFERROR(subQ!L9/subQ!L5,"") | ... AB23: =IFERROR(subQ!AB9/subQ!AB5,"") | AC23: 0.089255455 | AD23: 0.089262985 | AE23: =IFERROR(subQ!AE9/subQ!AE5,"") | AF23: 0.089255855 | AG23: 0.089259279 | AH23: 0.089261303 | AI23: 0.08926121 | AJ23: =IFERROR(subQ!AJ9/subQ!AJ5,"") | AK23: 0.089256213 | AL23: 0.089260512 | AM23: 0.089260965 | AN23: 0.089253439 | AO23: =IFERROR(subQ!AO9/subQ!AO5,"")
A24: drv:외환손익 | B24: abs | C24: 외환손익 (가정, 억원) | E24: =subQ!E13 | F24: =subQ!F13 | G24: =subQ!G13 | H24: =subQ!H13 | I24: =subQ!I13 | J24: =subQ!J13 | K24: =subQ!K13 | L24: =subQ!L13 | ... AB24: =subQ!AB13 | AC24: 0 | AD24: 0 | AE24: =subQ!AE13 | AF24: 0 | AG24: 0 | AH24: 0 | AI24: 0 | AJ24: =subQ!AJ13 | AK24: 0 | AL24: 0 | AM24: 0 | AN24: 0 | AO24: =subQ!AO13
A25: drv:파생상품손익 | B25: abs | C25: 파생상품손익 (가정, 억원) | E25: =subQ!E14 | F25: =subQ!F14 | G25: =subQ!G14 | H25: =subQ!H14 | I25: =subQ!I14 | J25: =subQ!J14 | K25: =subQ!K14 | L25: =subQ!L14 | ... AB25: =subQ!AB14 | AC25: 0 | AD25: 0 | AE25: =subQ!AE14 | AF25: 0 | AG25: 0 | AH25: 0 | AI25: 0 | AJ25: =subQ!AJ14 | AK25: 0 | AL25: 0 | AM25: 0 | AN25: 0 | AO25: =subQ!AO14
A26: drv:기타금융손익 | B26: abs | C26: 기타금융손익 (가정, 억원) | E26: =subQ!E15 | F26: =subQ!F15 | G26: =subQ!G15 | H26: =subQ!H15 | I26: =subQ!I15 | J26: =subQ!J15 | K26: =subQ!K15 | L26: =subQ!L15 | ... AB26: =subQ!AB15 | AC26: -4.7 | AD26: -4.7 | AE26: =subQ!AE15 | AF26: -4.7 | AG26: -4.7 | AH26: -4.7 | AI26: -4.7 | AJ26: =subQ!AJ15 | AK26: -4.7 | AL26: -4.7 | AM26: -4.7 | AN26: -4.7 | AO26: =subQ!AO15
A27: drv:기타영업외손익 | B27: abs | C27: 기타영업외손익 (가정, 억원) | E27: =subQ!E16 | F27: =subQ!F16 | G27: =subQ!G16 | H27: =subQ!H16 | I27: =subQ!I16 | J27: =subQ!J16 | K27: =subQ!K16 | L27: =subQ!L16 | ... AB27: =subQ!AB16 | AC27: 0 | AD27: 0 | AE27: =subQ!AE16 | AF27: 0 | AG27: 0 | AH27: 0 | AI27: 0 | AJ27: =subQ!AJ16 | AK27: 0 | AL27: 0 | AM27: 0 | AN27: 0 | AO27: =subQ!AO16
A28: drv:법인세비용 | B28: tax | C28: 법인세율(/세전) — 법인세 = MAX(세전,0) × 세율 | E28: =IFERROR(subQ!E18/subQ!E17,"") | F28: =IFERROR(subQ!F18/subQ!F17,"") | G28: =IFERROR(subQ!G18/subQ!G17,"") | H28: =IFERROR(subQ!H18/subQ!H17,"") | I28: =IFERROR(subQ!I18/subQ!I17,"") | J28: =IFERROR(subQ!J18/subQ!J17,"") | K28: =IFERROR(subQ!K18/subQ!K17,"") | L28: =IFERROR(subQ!L18/subQ!L17,"") | ... AB28: =IFERROR(subQ!AB18/subQ!AB17,"") | AC28: =$D$50 | AD28: =$D$50 | AE28: =IFERROR(subQ!AE18/subQ!AE17,"") | AF28: =$D$50 | AG28: =$D$50 | AH28: =$D$50 | AI28: =$D$50 | AJ28: =IFERROR(subQ!AJ18/subQ!AJ17,"") | AK28: =$D$50 | AL28: =$D$50 | AM28: =$D$50 | AN28: =$D$50 | AO28: =IFERROR(subQ!AO18/subQ!AO17,"")
A29: drv:지배주주순이익 | B29: ratio | C29: 지배주주 비중(/당기순이익) | E29: =IFERROR(subQ!E20/subQ!E19,"") | F29: =IFERROR(subQ!F20/subQ!F19,"") | G29: =IFERROR(subQ!G20/subQ!G19,"") | H29: =IFERROR(subQ!H20/subQ!H19,"") | I29: =IFERROR(subQ!I20/subQ!I19,"") | J29: =IFERROR(subQ!J20/subQ!J19,"") | K29: =IFERROR(subQ!K20/subQ!K19,"") | L29: =IFERROR(subQ!L20/subQ!L19,"") | ... AB29: =IFERROR(subQ!AB20/subQ!AB19,"") | AC29: =$D$52 | AD29: =$D$52 | AE29: =IFERROR(subQ!AE20/subQ!AE19,"") | AF29: =$D$52 | AG29: =$D$52 | AH29: =$D$52 | AI29: =$D$52 | AJ29: =IFERROR(subQ!AJ20/subQ!AJ19,"") | AK29: =$D$52 | AL29: =$D$52 | AM29: =$D$52 | AN29: =$D$52 | AO29: =IFERROR(subQ!AO20/subQ!AO19,"")
A30: drv:부채총계 | B30: qoq | C30: 부채총계 QoQ | G30: =IFERROR(subQ!G22/subQ!E22-1,"") | H30: =IFERROR(subQ!H22/subQ!G22-1,"") | I30: =IFERROR(subQ!I22/subQ!H22-1,"") | J30: =IFERROR(subQ!J22/subQ!I22-1,"") | L30: =IFERROR(subQ!L22/subQ!J22-1,"") | M30: =IFERROR(subQ!M22/subQ!L22-1,"") | N30: =IFERROR(subQ!N22/subQ!M22-1,"") | O30: =IFERROR(subQ!O22/subQ!N22-1,"") | Q30: =IFERROR(subQ!Q22/subQ!O22-1,"") | R30: =IFERROR(subQ!R22/subQ!Q22-1,"") | S30: =IFERROR(subQ!S22/subQ!R22-1,"") | T30: =IFERROR(subQ!T22/subQ!S22-1,"") | V30: =IFERROR(subQ!V22/subQ!T22-1,"") | W30: =IFERROR(subQ!W22/subQ!V22-1,"") | X30: =IFERROR(subQ!X22/subQ!W22-1,"") | Y30: =IFERROR(subQ!Y22/subQ!X22-1,"") | AA30: =IFERROR(subQ!AA22/subQ!Y22-1,"") | AB30: =IFERROR(subQ!AB22/subQ!AA22-1,"") | AC30: 2.14e-07 | AD30: 0 | AF30: 0 | AG30: 0 | AH30: 0 | AI30: 0 | AK30: 0 | AL30: 0 | AM30: 0 | AN30: 0
A31: drv:자본총계 | B31: roll | C31: 자본총계 기타변동(배당 등, 억원) | G31: =IFERROR(subQ!E23+subQ!G19-subQ!G23,"") | H31: =IFERROR(subQ!G23+subQ!H19-subQ!H23,"") | I31: =IFERROR(subQ!H23+subQ!I19-subQ!I23,"") | J31: =IFERROR(subQ!I23+subQ!J19-subQ!J23,"") | L31: =IFERROR(subQ!J23+subQ!L19-subQ!L23,"") | M31: =IFERROR(subQ!L23+subQ!M19-subQ!M23,"") | N31: =IFERROR(subQ!M23+subQ!N19-subQ!N23,"") | O31: =IFERROR(subQ!N23+subQ!O19-subQ!O23,"") | Q31: =IFERROR(subQ!O23+subQ!Q19-subQ!Q23,"") | R31: =IFERROR(subQ!Q23+subQ!R19-subQ!R23,"") | S31: =IFERROR(subQ!R23+subQ!S19-subQ!S23,"") | T31: =IFERROR(subQ!S23+subQ!T19-subQ!T23,"") | V31: =IFERROR(subQ!T23+subQ!V19-subQ!V23,"") | W31: =IFERROR(subQ!V23+subQ!W19-subQ!W23,"") | X31: =IFERROR(subQ!W23+subQ!X19-subQ!X23,"") | Y31: =IFERROR(subQ!X23+subQ!Y19-subQ!Y23,"") | AA31: =IFERROR(subQ!Y23+subQ!AA19-subQ!AA23,"") | AB31: =IFERROR(subQ!AA23+subQ!AB19-subQ!AB23,"") | AC31: -0.007330743 | AD31: 0.002684832 | AF31: 0.002550687 | AG31: 21.446243 | AH31: -0.001202619 | AI31: -0.004803738 | AK31: 0.003342605 | AL31: 21.44367 | AM31: 0.000849031 | AN31: -0.006215851
A32: drv:지배주주지분 | B32: roll | C32: 지배주주지분 기타변동(배당 등, 억원) | G32: =IFERROR(subQ!E24+subQ!G20-subQ!G24,"") | H32: =IFERROR(subQ!G24+subQ!H20-subQ!H24,"") | I32: =IFERROR(subQ!H24+subQ!I20-subQ!I24,"") | J32: =IFERROR(subQ!I24+subQ!J20-subQ!J24,"") | L32: =IFERROR(subQ!J24+subQ!L20-subQ!L24,"") | M32: =IFERROR(subQ!L24+subQ!M20-subQ!M24,"") | N32: =IFERROR(subQ!M24+subQ!N20-subQ!N24,"") | O32: =IFERROR(subQ!N24+subQ!O20-subQ!O24,"") | Q32: =IFERROR(subQ!O24+subQ!Q20-subQ!Q24,"") | R32: =IFERROR(subQ!Q24+subQ!R20-subQ!R24,"") | S32: =IFERROR(subQ!R24+subQ!S20-subQ!S24,"") | T32: =IFERROR(subQ!S24+subQ!T20-subQ!T24,"") | V32: =IFERROR(subQ!T24+subQ!V20-subQ!V24,"") | W32: =IFERROR(subQ!V24+subQ!W20-subQ!W24,"") | X32: =IFERROR(subQ!W24+subQ!X20-subQ!X24,"") | Y32: =IFERROR(subQ!X24+subQ!Y20-subQ!Y24,"") | AA32: =IFERROR(subQ!Y24+subQ!AA20-subQ!AA24,"") | AB32: =IFERROR(subQ!AA24+subQ!AB20-subQ!AB24,"") | AC32: -0.004046783 | AD32: -0.000106951 | AF32: -0.002995979 | AG32: 21.450091 | AH32: -0.003836866 | AI32: -0.000233978 | AK32: -0.006792382 | AL32: 21.452987 | AM32: -0.000677417 | AN32: -0.01129232
A33: drv:총차입금 | B33: qoq | C33: 총차입금 QoQ | G33: =IFERROR(subQ!G25/subQ!E25-1,"") | H33: =IFERROR(subQ!H25/subQ!G25-1,"") | I33: =IFERROR(subQ!I25/subQ!H25-1,"") | J33: =IFERROR(subQ!J25/subQ!I25-1,"") | L33: =IFERROR(subQ!L25/subQ!J25-1,"") | M33: =IFERROR(subQ!M25/subQ!L25-1,"") | N33: =IFERROR(subQ!N25/subQ!M25-1,"") | O33: =IFERROR(subQ!O25/subQ!N25-1,"") | Q33: =IFERROR(subQ!Q25/subQ!O25-1,"") | R33: =IFERROR(subQ!R25/subQ!Q25-1,"") | S33: =IFERROR(subQ!S25/subQ!R25-1,"") | T33: =IFERROR(subQ!T25/subQ!S25-1,"") | V33: =IFERROR(subQ!V25/subQ!T25-1,"") | W33: =IFERROR(subQ!W25/subQ!V25-1,"") | X33: =IFERROR(subQ!X25/subQ!W25-1,"") | Y33: =IFERROR(subQ!Y25/subQ!X25-1,"") | AA33: =IFERROR(subQ!AA25/subQ!Y25-1,"") | AB33: =IFERROR(subQ!AB25/subQ!AA25-1,"") | AC33: 2.422e-06 | AD33: 0 | AF33: 0 | AG33: 0 | AH33: 0 | AI33: 0 | AK33: 0 | AL33: 0 | AM33: 0 | AN33: 0
A34: drv:순차입금 | B34: qoq | C34: 순차입금 QoQ | G34: =IFERROR(subQ!G26/subQ!E26-1,"") | H34: =IFERROR(subQ!H26/subQ!G26-1,"") | I34: =IFERROR(subQ!I26/subQ!H26-1,"") | J34: =IFERROR(subQ!J26/subQ!I26-1,"") | L34: =IFERROR(subQ!L26/subQ!J26-1,"") | M34: =IFERROR(subQ!M26/subQ!L26-1,"") | N34: =IFERROR(subQ!N26/subQ!M26-1,"") | O34: =IFERROR(subQ!O26/subQ!N26-1,"") | Q34: =IFERROR(subQ!Q26/subQ!O26-1,"") | R34: =IFERROR(subQ!R26/subQ!Q26-1,"") | S34: =IFERROR(subQ!S26/subQ!R26-1,"") | T34: =IFERROR(subQ!T26/subQ!S26-1,"") | V34: =IFERROR(subQ!V26/subQ!T26-1,"") | W34: =IFERROR(subQ!W26/subQ!V26-1,"") | X34: =IFERROR(subQ!X26/subQ!W26-1,"") | Y34: =IFERROR(subQ!Y26/subQ!X26-1,"") | AA34: =IFERROR(subQ!AA26/subQ!Y26-1,"") | AB34: =IFERROR(subQ!AB26/subQ!AA26-1,"") | AC34: -0.040829623 | AD34: -0.045074493 | AF34: -0.048227337 | AG34: -0.033992095 | AH34: -0.058128451 | AI34: -0.066184193 | AK34: -0.076590393 | AL34: -0.065670154 | AM34: -0.1028394 | AN34: -0.12129818
A35: drv:이자발생자산 | B35: qoq | C35: 이자발생자산 QoQ | G35: =IFERROR(subQ!G27/subQ!E27-1,"") | H35: =IFERROR(subQ!H27/subQ!G27-1,"") | I35: =IFERROR(subQ!I27/subQ!H27-1,"") | J35: =IFERROR(subQ!J27/subQ!I27-1,"") | L35: =IFERROR(subQ!L27/subQ!J27-1,"") | M35: =IFERROR(subQ!M27/subQ!L27-1,"") | N35: =IFERROR(subQ!N27/subQ!M27-1,"") | O35: =IFERROR(subQ!O27/subQ!N27-1,"") | Q35: =IFERROR(subQ!Q27/subQ!O27-1,"") | R35: =IFERROR(subQ!R27/subQ!Q27-1,"") | S35: =IFERROR(subQ!S27/subQ!R27-1,"") | T35: =IFERROR(subQ!T27/subQ!S27-1,"") | V35: =IFERROR(subQ!V27/subQ!T27-1,"") | W35: =IFERROR(subQ!W27/subQ!V27-1,"") | X35: =IFERROR(subQ!X27/subQ!W27-1,"") | Y35: =IFERROR(subQ!Y27/subQ!X27-1,"") | AA35: =IFERROR(subQ!AA27/subQ!Y27-1,"") | AB35: =IFERROR(subQ!AB27/subQ!AA27-1,"") | AC35: 0.0681236 | AD35: 0.067535755 | AF35: 0.064637309 | AG35: 0.040728597 | AH35: 0.064647758 | AI35: 0.065118551 | AK35: 0.066067523 | AL35: 0.049067218 | AM35: 0.068435248 | AN35: 0.067779221
A36: drv:현금및현금성자산 | B36: qoq | C36: 현금및현금성자산 QoQ | G36: =IFERROR(subQ!G28/subQ!E28-1,"") | H36: =IFERROR(subQ!H28/subQ!G28-1,"") | I36: =IFERROR(subQ!I28/subQ!H28-1,"") | J36: =IFERROR(subQ!J28/subQ!I28-1,"") | L36: =IFERROR(subQ!L28/subQ!J28-1,"") | M36: =IFERROR(subQ!M28/subQ!L28-1,"") | N36: =IFERROR(subQ!N28/subQ!M28-1,"") | O36: =IFERROR(subQ!O28/subQ!N28-1,"") | Q36: =IFERROR(subQ!Q28/subQ!O28-1,"") | R36: =IFERROR(subQ!R28/subQ!Q28-1,"") | S36: =IFERROR(subQ!S28/subQ!R28-1,"") | T36: =IFERROR(subQ!T28/subQ!S28-1,"") | V36: =IFERROR(subQ!V28/subQ!T28-1,"") | W36: =IFERROR(subQ!W28/subQ!V28-1,"") | X36: =IFERROR(subQ!X28/subQ!W28-1,"") | Y36: =IFERROR(subQ!Y28/subQ!X28-1,"") | AA36: =IFERROR(subQ!AA28/subQ!Y28-1,"") | AB36: =IFERROR(subQ!AB28/subQ!AA28-1,"")
A37: drv:CAPEX | B37: yoy | C37: CAPEX YoY | J37: =IFERROR(subQ!J29/subQ!E29-1,"") | L37: =IFERROR(subQ!L29/subQ!G29-1,"") | M37: =IFERROR(subQ!M29/subQ!H29-1,"") | N37: =IFERROR(subQ!N29/subQ!I29-1,"") | O37: =IFERROR(subQ!O29/subQ!J29-1,"") | Q37: =IFERROR(subQ!Q29/subQ!L29-1,"") | R37: =IFERROR(subQ!R29/subQ!M29-1,"") | S37: =IFERROR(subQ!S29/subQ!N29-1,"") | T37: =IFERROR(subQ!T29/subQ!O29-1,"") | V37: =IFERROR(subQ!V29/subQ!Q29-1,"") | W37: =IFERROR(subQ!W29/subQ!R29-1,"") | X37: =IFERROR(subQ!X29/subQ!S29-1,"") | Y37: =IFERROR(subQ!Y29/subQ!T29-1,"") | AA37: =IFERROR(subQ!AA29/subQ!V29-1,"") | AB37: =IFERROR(subQ!AB29/subQ!W29-1,"") | AC37: 0.063829787 | AD37: 0 | AF37: 0 | AG37: 0 | AH37: 0 | AI37: 0 | AK37: 0 | AL37: 0 | AM37: 0 | AN37: 0
A38: drv:영업활동현금흐름 | B38: yoy | C38: 영업활동현금흐름 YoY | J38: =IFERROR(subQ!J30/subQ!E30-1,"") | L38: =IFERROR(subQ!L30/subQ!G30-1,"") | M38: =IFERROR(subQ!M30/subQ!H30-1,"") | N38: =IFERROR(subQ!N30/subQ!I30-1,"") | O38: =IFERROR(subQ!O30/subQ!J30-1,"") | Q38: =IFERROR(subQ!Q30/subQ!L30-1,"") | R38: =IFERROR(subQ!R30/subQ!M30-1,"") | S38: =IFERROR(subQ!S30/subQ!N30-1,"") | T38: =IFERROR(subQ!T30/subQ!O30-1,"") | V38: =IFERROR(subQ!V30/subQ!Q30-1,"") | W38: =IFERROR(subQ!W30/subQ!R30-1,"") | X38: =IFERROR(subQ!X30/subQ!S30-1,"") | Y38: =IFERROR(subQ!Y30/subQ!T30-1,"") | AA38: =IFERROR(subQ!AA30/subQ!V30-1,"") | AB38: =IFERROR(subQ!AB30/subQ!W30-1,"")
A39: drv:주식수 | B39: qoq | C39: 주식수 QoQ | G39: =IFERROR(subQ!G31/subQ!E31-1,"") | H39: =IFERROR(subQ!H31/subQ!G31-1,"") | I39: =IFERROR(subQ!I31/subQ!H31-1,"") | J39: =IFERROR(subQ!J31/subQ!I31-1,"") | L39: =IFERROR(subQ!L31/subQ!J31-1,"") | M39: =IFERROR(subQ!M31/subQ!L31-1,"") | N39: =IFERROR(subQ!N31/subQ!M31-1,"") | O39: =IFERROR(subQ!O31/subQ!N31-1,"") | Q39: =IFERROR(subQ!Q31/subQ!O31-1,"") | R39: =IFERROR(subQ!R31/subQ!Q31-1,"") | S39: =IFERROR(subQ!S31/subQ!R31-1,"") | T39: =IFERROR(subQ!T31/subQ!S31-1,"") | V39: =IFERROR(subQ!V31/subQ!T31-1,"") | W39: =IFERROR(subQ!W31/subQ!V31-1,"") | X39: =IFERROR(subQ!X31/subQ!W31-1,"") | Y39: =IFERROR(subQ!Y31/subQ!X31-1,"") | AA39: =IFERROR(subQ!AA31/subQ!Y31-1,"") | AB39: =IFERROR(subQ!AB31/subQ!AA31-1,"") | AC39: 0 | AD39: 0 | AF39: 0 | AG39: 0 | AH39: 0 | AI39: 0 | AK39: 0 | AL39: 0 | AM39: 0 | AN39: 0
A40: drv:DPS | B40: abs | C40: DPS (가정, 원) | E40: =subQ!E34 | F40: =subQ!F34 | G40: =subQ!G34 | H40: =subQ!H34 | I40: =subQ!I34 | J40: =subQ!J34 | K40: =subQ!K34 | L40: =subQ!L34 | ... AB40: =subQ!AB34 | AD40: 165 | AE40: =subQ!AE34 | AI40: 165 | AJ40: =subQ!AJ34 | AN40: 165 | AO40: =subQ!AO34
B42: 3. 밸류에이션·스칼라 | C42: 노란 셀 = 가정. '연결' 표시는 추정 전 분기 수식이 이 셀을 참조한다는 뜻
A43: sc:종가 | C43: 종가 | D43: 6290 | E43: 원 — 네이버 정규장 종가(aik 확정종가 대조 · aik 7,070원)
A44: sc:기준일 | C44: 기준일 | D44: 20261012 | E44: 종가 기준일
A45: sc:COE | C45: COE | D45: 0.09 | E45: 자기자본비용(가정) — TP 적정 PBR = ROE/COE
A46: sc:PER_lo | C46: PER_lo | D46: 8.2 | E46: PER 밴드 하단(배) — hist_quarterly(분기 평균가 ÷ TTM EPS, 12분기, 25/50/75 백분위)
A47: sc:PER_mid | C47: PER_mid | D47: 9 | E47: PER 밴드 중단(배)
A48: sc:PER_hi | C48: PER_hi | D48: 11.4 | E48: PER 밴드 상단(배)
A49: sc:EPS_Y1가중 | C49: EPS_Y1가중 | D49: 0.5 | E49: 12M fwd EPS = FY(last_actual연도)E × w + FY+1E × (1−w) — 기준 분기 2Q 이면 0.5(가정)
A50: sc:세율 | C50: 세율 | D50: 0.11947583 | E50: 연결 — 법인세 = MAX(세전,0) × 세율(역산, 재현 오차 ≤ 0.05억 · 모델 assumptions 0.1195) · 최근 12분기 유효세율 11.9%(5~27% 안 — 그대로)
A51: sc:판관비율 | C51: 판관비율 | D51: 0.097959121 | E51: 연결 — 판관비 = 매출액 × 판관비율(역산, 재현 오차 ≤ 0.05억 · 모델 assumptions 0.098)
A52: sc:지배주주비중 | C52: 지배주주비중 | D52: 0.94178985 | E52: 연결 — 지배주주순이익 = 당기순이익 × 비중(역산, 재현 오차 ≤ 0.05억)
A53: sc:이자율_자산 | C53: 이자율_자산 | D53: 0.027987832 | E53: 연결 — 이자손익 = (전분기 이자발생자산 × 자산이자율 − 전분기 총차입금 × 부채이자율)/4(역산, 재현 오차 ≤ 0.05억 · 모델 assumptions 0.028)
A54: sc:이자율_부채 | C54: 이자율_부채 | D54: 0.034383643 | E54: 연결 — 같은 수식의 부채 쪽(총차입금 행이 없으면 0)(역산, 재현 오차 ≤ 0.05억 · 모델 assumptions 0.0344)
A55: sc:배당성향 | C55: 배당성향 | D55: 0.1663 | E55: 배당성향(참고 — 모델은 직전 DPS 유지·Q2 지급 가정)
A56: sc:외화순노출_백만$ | C56: 외화순노출_백만$ | E56: 외화 순노출 × Δ기말환율 (외화 시트 방식) — 외화 순노출 미공시(face) → 0 + 표기
A57: sc:헤지비율 | C57: 헤지비율 | E57: sls 없음
A58: sc:헤지환율_약정 | C58: 헤지환율_약정 | E58: sls 없음

Sheet BS연결
B1: (백만원) | C1: 이름: BS연결H | E1: 4Q21 | F1: 2021 | G1: 1Q22 | H1: 2Q22 | I1: 3Q22 | J1: 4Q22 | K1: 2022 | L1: 1Q23 | M1: 2Q23 | N1: 3Q23 | O1: 4Q23 | P1: 2023 | Q1: 1Q24 | R1: 2Q24 | S1: 3Q24 | T1: 4Q24 | U1: 2024 | V1: 1Q25 | W1: 2Q25 | X1: 3Q25 | Y1: 4Q25 | Z1: 2025 | AA1: 1Q26 | AB1: 2Q26 | AC1: 3Q26 | AD1: 4Q26 | AE1: 2026 | AF1: 1Q27 | AG1: 2Q27 | AH1: 3Q27 | AI1: 4Q27 | AJ1: 2027 | AK1: 1Q28 | AL1: 2Q28 | AM1: 3Q28 | AN1: 4Q28 | AO1: 2028
B2: 연결 | D2: fin json(kship_fin.py)
B3: 삼영엠텍(연) | C3: UPDATE: 26-10-12 | E3: 1 | F3: 2 | G3: 3 | H3: 4 | I3: 5 | J3: 6 | K3: 7 | L3: 8 | M3: 9 | N3: 10 | O3: 11 | P3: 12 | Q3: 13 | R3: 14 | S3: 15 | T3: 16 | U3: 17 | V3: 18 | W3: 19 | X3: 20 | Y3: 21 | Z3: 22 | AA3: 23 | AB3: 24 | AC3: 25 | AD3: 26 | AE3: 27 | AF3: 28 | AG3: 29 | AH3: 30 | AI3: 31 | AJ3: 32 | AK3: 33 | AL3: 34 | AM3: 35 | AN3: 36 | AO3: 37
B4: Account Code | C4: AccountNAME | E4: 2021.12 | F4: 2021.12A | G4: 2022.03 | H4: 2022.06 | I4: 2022.09 | J4: 2022.12 | K4: 2022.12A | L4: 2023.03 | M4: 2023.06 | N4: 2023.09 | O4: 2023.12 | P4: 2023.12A | Q4: 2024.03 | R4: 2024.06 | S4: 2024.09 | T4: 2024.12 | U4: 2024.12A | V4: 2025.03 | W4: 2025.06 | X4: 2025.09 | Y4: 2025.12 | Z4: 2025.12A | AA4: 2026.03 | AB4: 2026.06 | AC4: 2026.09 | AD4: 2026.12 | AE4: 2026.12A | AF4: 2027.03 | AG4: 2027.06 | AH4: 2027.09 | AI4: 2027.12 | AJ4: 2027.12A | AK4: 2028.03 | AL4: 2028.06 | AM4: 2028.09 | AN4: 2028.12 | AO4: 2028.12A
A5: 1 | C5: 유동자산 | E5: 66115.28 | F5: 66115.28 | G5: 68321.55 | H5: 67763.99 | I5: 65204.7 | J5: 61900.88 | K5: 61900.88 | L5: 64135.79 | M5: 65842.46 | N5: 68500.11 | O5: 67455.23 | P5: 67455.23 | Q5: 69422.17 | R5: 61773.77 | S5: 69383.8 | T5: 70562.19 | U5: 70562.19 | V5: 79385.56 | W5: 72386.59 | X5: 100659.79 | Y5: 261304.09 | Z5: 261304.09 | AA5: 285093.91 | AB5: 297811.82
A6: 1 | C6: 현금및현금성자산 | E6: 8344.33 | F6: 8344.33 | G6: 9845.85 | H6: 11440.69 | I6: 6596.69 | J6: 8768.12 | K6: 8768.12 | L6: 7219.26 | M6: 5413.48 | N6: 6313.86 | O6: 4307.41 | P6: 4307.41 | Q6: 2369.61 | R6: 7857.36 | S6: 4656.4 | T6: 4712.28 | U6: 4712.28 | V6: 3231.07 | W6: 6781.86 | X6: 19986.86 | Y6: 46662.02 | Z6: 46662.02 | AA6: 40278.7 | AB6: 35038.03
A7: 1 | C7: 단기금융상품 | E7: 18627.05 | F7: 18627.05 | G7: 12270.36 | H7: 12520.98 | I7: 12988.94 | J7: 16124.88 | K7: 16124.88 | L7: 17090.87 | M7: 16612 | N7: 18498.02 | O7: 19477.53 | P7: 19477.53 | Q7: 16510.34 | R7: 5525.85 | S7: 19368.36 | T7: 15092.93 | U7: 15092.93 | V7: 19068.95 | W7: 13443.49 | X7: 26151.56 | Y7: 17127.88 | Z7: 17127.88 | AA7: 28697.66 | AB7: 30735.66
A8: 1 | C8: 단기금융자산 | E8: 18662.12 | F8: 18662.12 | G8: 12298.52 | H8: 12520.98 | I8: 12988.94 | J8: 16124.88 | K8: 16124.88 | L8: 17096.12 | M8: 16638.23 | N8: 18541.39 | O8: 19555.14 | P8: 19555.14 | Q8: 16510.34 | R8: 5525.85 | S8: 19401.5 | T8: 15105.11 | U8: 15105.11 | V8: 19068.95 | W8: 13582.44 | X8: 26155.63 | Y8: 18441.08 | Z8: 18441.08 | AA8: 29932.44 | AB8: 31108
A9: 1 | C9: 매출채권및기타채권 | E9: 13017.97 | F9: 13017.97 | G9: 18380.6 | H9: 15786.37 | I9: 19257.31 | J9: 12463.08 | K9: 12463.08 | L9: 13901.91 | M9: 15570.77 | N9: 15938.39 | O9: 14296.89 | P9: 14296.89 | Q9: 16314.26 | R9: 17675.63 | S9: 14943.47 | T9: 16618.93 | U9: 16618.93 | V9: 20101.02 | W9: 17560.17 | X9: 19106.4 | Y9: 103450.64 | Z9: 103450.64 | AA9: 114379.45 | AB9: 121879.38
A10: 1 | C10: 재고자산 | E10: 24819.29 | F10: 24819.29 | G10: 26178.57 | H10: 26353.15 | I10: 25323.12 | J10: 23378.41 | K10: 23378.41 | L10: 24612.95 | M10: 27232.05 | N10: 26019.01 | O10: 27007.79 | P10: 27007.79 | Q10: 32697.32 | R10: 29704.24 | S10: 28938.97 | T10: 32729.84 | U10: 32729.84 | V10: 35640.97 | W10: 33471.31 | X10: 34023.32 | Y10: 78602.59 | Z10: 78602.59 | AA10: 85173.08 | AB10: 92139.11
A11: 1 | C11: 유동파생상품자산 | E11: 35.07 | F11: 35.07 | G11: 28.16 | H11: 0 | I11: 0 | J11: 0 | K11: 0 | L11: 5.25 | M11: 26.23 | N11: 43.37 | O11: 77.61 | P11: 77.61 | Q11: 0 | R11: 0 | S11: 33.14 | T11: 12.18 | U11: 12.18 | V11: 0 | W11: 138.95 | X11: 4.07 | Y11: 1313.2 | Z11: 1313.2 | AA11: 1234.78 | AB11: 372.34
A12: 1 | C12: 당기법인세자산(선급법인세) | E12: 0 | F12: 0 | I12: 74.03 | J12: 74.16 | K12: 74.16 | L12: 74.16 | M12: 0 | N12: 0 | O12: 102.11 | P12: 102.11 | Q12: 102.11 | R12: 0 | S12: 0 | T12: 0 | U12: 0 | V12: 0 | Y12: 2010.88 | Z12: 2010.88 | AA12: 2150.93 | AB12: 1877.46
A13: 1 | C13: 기타유동자산 | E13: 1271.58 | F13: 1271.58 | G13: 1618 | H13: 1662.81 | I13: 964.61 | J13: 1092.22 | K13: 1092.22 | L13: 1231.37 | M13: 987.93 | N13: 1687.47 | O13: 2185.89 | P13: 2185.89 | Q13: 1428.53 | R13: 1010.69 | S13: 1443.45 | T13: 1396.03 | U13: 1396.03 | V13: 1343.56 | W13: 990.81 | X13: 1387.58 | Y13: 12136.88 | Z13: 12136.88 | AA13: 13179.31 | AB13: 15769.84
A14: 1 | C14: 비유동자산 | E14: 44266.75 | F14: 44266.75 | G14: 43745.76 | H14: 43061.26 | I14: 43465.6 | J14: 39400.74 | K14: 39400.74 | L14: 40688.77 | M14: 41087.81 | N14: 40629.04 | O14: 44126.11 | P14: 44126.11 | Q14: 44256.28 | R14: 45949.57 | S14: 45865.61 | T14: 45323.36 | U14: 45323.36 | V14: 49274.7 | W14: 47034.17 | X14: 45929.3 | Y14: 282810.78 | Z14: 282810.78 | AA14: 283205.27 | AB14: 282133.85
A15: 1 | C15: 장기금융자산 | E15: 12100.86 | F15: 12100.86 | G15: 11726.14 | H15: 9731.29 | I15: 7949.7 | J15: 8073.83 | K15: 8073.83 | L15: 9585.16 | M15: 10395.24 | N15: 9564.18 | O15: 9681.59 | P15: 9681.59 | Q15: 9987.92 | R15: 11078.65 | S15: 10582.52 | T15: 10390.73 | U15: 10390.73 | V15: 15706.26 | W15: 14607.8 | X15: 14667.95 | Y15: 13697.59 | Z15: 13697.59 | AA15: 12514.29 | AB15: 12995.56
A16: 1 | C16: 투자자산 | E16: 12100.86 | F16: 12100.86 | G16: 11726.14 | H16: 9731.29 | I16: 7949.7 | J16: 8073.83 | K16: 8073.83 | L16: 9585.16 | M16: 10395.24 | N16: 9564.18 | O16: 9681.59 | P16: 9681.59 | Q16: 9987.92 | R16: 11078.65 | S16: 10582.52 | T16: 10390.73 | U16: 10390.73 | V16: 15706.26 | W16: 14607.8 | X16: 14667.95 | Y16: 13697.59 | Z16: 13697.59 | AA16: 12514.29 | AB16: 12995.56
A17: 1 | C17: 장기매출채권및기타채권 | E17: 1003.28 | F17: 1003.28 | G17: 1021.64 | H17: 1018.04 | I17: 842.16 | J17: 883.93 | K17: 883.93 | L17: 922.33 | M17: 807.45 | N17: 772.83 | O17: 2797.97 | P17: 2797.97 | Q17: 2847.07 | R17: 2760.23 | Y17: 2589.04 | Z17: 2589.04 | AB17: 2056.84
A18: 1 | C18: 유형자산 | E18: 28248.53 | F18: 28248.53 | G18: 28090.26 | H18: 28663.24 | I18: 29544.03 | J18: 25419.86 | K18: 25419.86 | L18: 25586.14 | M18: 25477.46 | N18: 25647.57 | O18: 26143.03 | P18: 26143.03 | Q18: 26181.58 | R18: 26355.22 | S18: 26012.12 | T18: 26242.92 | U18: 26242.92 | V18: 26282.63 | W18: 26150.02 | X18: 25992.45 | Y18: 182318.33 | Z18: 182318.33 | AA18: 181886.15 | AB18: 183578.74
A19: 1 | C19: 사용권자산 | E19: 397.38 | F19: 397.38 | G19: 378.31 | H19: 357.37 | I19: 438.08 | J19: 93.94 | K19: 93.94 | L19: 77.56 | M19: 61.19 | N19: 44.81 | O19: 28.43 | P19: 28.43 | Q19: 173.85 | R19: 160.94 | S19: 143.09 | T19: 129.65 | U19: 129.65 | V19: 112.07 | W19: 91.56 | X19: 87.56 | Y19: 9859.68 | Z19: 9859.68 | AA19: 9888.55 | AB19: 9912.18
A20: 1 | C20: 기타비유동자산 | E20: 413.7 | F20: 413.7 | G20: 384.97 | H20: 357.37 | I20: 438.08 | J20: 93.94 | K20: 93.94 | L20: 77.56 | M20: 61.19 | N20: 44.81 | O20: 28.43 | P20: 28.43 | Q20: 173.85 | R20: 191 | S20: 170.33 | T20: 181.27 | U20: 181.27 | V20: 158.83 | W20: 130.76 | X20: 123.5 | Y20: 10800.82 | Z20: 10800.82 | AA20: 10715.49 | AB20: 10630.35
A21: 1 | C21: 무형자산 | E21: 317.53 | F21: 317.53 | G21: 317.53 | H21: 317.53 | I21: 558.89 | J21: 549.95 | K21: 549.95 | L21: 541.01 | M21: 532.07 | N21: 523.13 | O21: 512.19 | P21: 512.19 | Q21: 503.26 | R21: 417.55 | S21: 408.61 | T21: 1104.67 | U21: 1104.67 | V21: 1097.46 | W21: 1111.67 | X21: 1108.36 | Y21: 64210.13 | Z21: 64210.13 | AA21: 62059.76 | AB21: 60719.62
A22: 1 | C22: 투자부동산 | E22: 1951.11 | F22: 1951.11 | G22: 1942.48 | H22: 1933.85 | I22: 1925.22 | J22: 1916.6 | K22: 1916.6 | L22: 1907.97 | M22: 1899.34 | N22: 1890.71 | O22: 1882.08 | P22: 1882.08 | Q22: 1873.45 | R22: 1864.82 | S22: 1856.19 | T22: 1847.57 | U22: 1847.57 | V22: 1838.94 | W22: 1830.31 | X22: 1821.68 | Y22: 3305.39 | Z22: 3305.39 | AA22: 3324.91 | AB22: 3410.19
A23: 1 | C23: 이연법인세자산 | E23: 141.66 | F23: 141.66 | G23: 262.74 | H23: 1039.93 | I23: 2207.51 | J23: 2056.18 | K23: 2056.18 | L23: 1816.82 | M23: 1915.06 | N23: 2185.8 | O23: 2037.2 | P23: 2037.2 | Q23: 2037.2 | R23: 2617.71 | S23: 2894.42 | T23: 1678.2 | U23: 1678.2 | V23: 1308.5 | W23: 927.17 | X23: 666.49 | Y23: 5622.58 | Z23: 5622.58 | AA23: 8518.12 | AB23: 6243.89
A24: 1 | C24: 자산총계 | E24: 110382.02 | F24: 110382.02 | G24: 112067.31 | H24: 110825.25 | I24: 108670.3 | J24: 101301.62 | K24: 101301.62 | L24: 104824.56 | M24: 106930.27 | N24: 109129.15 | O24: 111581.33 | P24: 111581.33 | Q24: 113678.45 | R24: 107723.34 | S24: 115249.4 | T24: 115885.55 | U24: 115885.55 | V24: 128660.27 | W24: 119420.76 | X24: 146589.1 | Y24: 544114.87 | Z24: 544114.87 | AA24: 568299.17 | AB24: 579945.67
A25: 1 | C25: 유동부채 | E25: 35307.11 | F25: 35307.11 | G25: 37332.24 | H25: 38201.86 | I25: 38721.47 | J25: 36855.52 | K25: 36855.52 | L25: 38328.11 | M25: 39380.29 | N25: 40159.3 | O25: 42256.96 | P25: 42256.96 | Q25: 43746.19 | R25: 37521.81 | S25: 42228.3 | T25: 41132.79 | U25: 41132.79 | V25: 52034.44 | W25: 40415.49 | X25: 64388.4 | Y25: 226467.65 | Z25: 226467.65 | AA25: 241716.32 | AB25: 224351.87
A26: 1 | C26: 매입채무및기타채무 | E26: 7279.85 | F26: 7279.85 | G26: 7371.71 | H26: 6770.66 | I26: 7226.53 | J26: 7781.38 | K26: 7781.38 | L26: 7517.65 | M26: 7868.12 | N26: 7685.44 | O26: 8962.08 | P26: 8962.08 | Q26: 11316.23 | R26: 7989.79 | S26: 8710.36 | T26: 10931.03 | U26: 10931.03 | V26: 11416.28 | W26: 8325.52 | X26: 8653.52 | Y26: 64807.58 | Z26: 64807.58 | AA26: 65161.74 | AB26: 68137.94
A27: 1 | C27: 단기차입금 | E27: 24750.15 | F27: 24750.15 | G27: 24825.14 | H27: 25174.49 | I27: 25670.18 | J27: 23790.97 | K27: 23790.97 | L27: 25177.48 | M27: 25735.19 | N27: 27311.76 | O27: 27150.91 | P27: 27150.91 | Q27: 21311.19 | R27: 16927.92 | S27: 19298.83 | T27: 19859.48 | U27: 19859.48 | V27: 26868.3 | W27: 18399.76 | X27: 42341 | Y27: 140129.43 | Z27: 140129.43 | AA27: 148952.62 | AB27: 130647.56
A28: 1 | C28: 유동성장기부채 | E28: 513.52 | F28: 513.52 | G28: 13.52 | H28: 13.52 | I28: 1513.52 | J28: 1500 | K28: 1500 | L28: 1500 | M28: 1500 | N28: 0 | O28: 0 | P28: 0 | Q28: 0 | R28: 500 | S28: 500 | T28: 500 | U28: 500 | V28: 0 | W28: 0 | X28: 0 | Y28: 0 | Z28: 0 | AA28: 0 | AB28: 1083.35
A29: 1 | C29: 당기법인세부채(미지급법인세) | E29: 21.25 | F29: 21.25 | G29: 38.46 | H29: 27.55 | I29: 0 | J29: 0 | K29: 0 | L29: 119.59 | M29: 392.51 | N29: 777.75 | O29: 0 | P29: 0 | Q29: 199.25 | R29: 904.73 | S29: 1524.86 | T29: 82.62 | U29: 82.62 | V29: 145.57 | W29: 337.45 | X29: 561.34 | Y29: 2864.36 | Z29: 2864.36 | AA29: 3645.82
A30: 1 | C30: 단기충당부채 | E30: 221.46 | F30: 221.46 | G30: 199.47 | H30: 198.44 | I30: 1682.99 | J30: 1696.88 | K30: 1696.88 | L30: 1532.68 | M30: 1573.66 | N30: 1605.79 | O30: 1584 | P30: 1584 | Q30: 1492.11 | R30: 3659.61 | S30: 3712.34 | T30: 1610.17 | U30: 1610.17 | V30: 1433.01 | W30: 1501.87 | X30: 1525.84 | Y30: 1543.17 | Z30: 1543.17 | AA30: 1603.14 | AB30: 1487.59
A31: 1 | C31: 유동리스부채 | E31: 151.04 | F31: 151.04 | G31: 133.61 | H31: 114.95 | I31: 152.83 | J31: 212.03 | K31: 212.03 | L31: 135.2 | M31: 110.89 | N31: 82.24 | O31: 51.74 | P31: 51.74 | Q31: 66.32 | R31: 67.78 | S31: 68.33 | T31: 68.69 | U31: 68.69 | V31: 66.57 | W31: 62.45 | X31: 71.97 | Y31: 133.48 | Z31: 133.48 | AA31: 120.69 | AB31: 123.64
A32: 1 | C32: 리스부채 | E32: 254.4 | F32: 254.4 | G32: 212.29 | H32: 168.3 | I32: 228.85 | J32: 331.02 | K32: 331.02 | L32: 169.55 | M32: 126.17 | N32: 94.64 | O32: 61.24 | P32: 61.24 | Q32: 178.16 | R32: 163.65 | S32: 146.42 | T32: 133.5 | U32: 133.5 | V32: 116.17 | W32: 95.57 | X32: 90.86 | Y32: 507.18 | Z32: 507.18 | AA32: 460.92 | AB32: 472.28
A33: 1 | C33: 단기금융부채 | E33: 212.51 | F33: 212.51 | G33: 270.27 | H33: 397.76 | I33: 152.83 | J33: 212.03 | K33: 212.03 | L33: 354.07 | M33: 286.18 | N33: 265.03 | O33: 128.88 | P33: 128.88 | Q33: 462.56 | R33: 674.33 | S33: 285.68 | T33: 822.19 | U33: 822.19 | V33: 799.31 | W33: 424.56 | X33: 847.5 | Y33: 5885.84 | Z33: 5885.84 | AA33: 6179.9 | AB33: 2504.73
A34: 1 | C34: 단기파생상품부채 | E34: 61.47 | F34: 61.47 | G34: 136.66 | H34: 282.81 | I34: 0 | J34: 0 | K34: 0 | L34: 218.87 | M34: 175.29 | N34: 182.79 | O34: 77.14 | P34: 77.14 | Q34: 396.24 | R34: 606.55 | S34: 217.35 | T34: 753.5 | U34: 753.5 | V34: 732.74 | W34: 362.11 | X34: 775.53 | Y34: 5752.36 | Z34: 5752.36 | AA34: 6059.21 | AB34: 2381.09
A35: 1 | C35: 기타유동부채 | E35: 2308.37 | F35: 2308.37 | G35: 4613.69 | H35: 5619.43 | I35: 2475.42 | J35: 1874.27 | K35: 1874.27 | L35: 2126.63 | M35: 2024.62 | N35: 2513.53 | O35: 4431.09 | P35: 4431.09 | Q35: 8964.85 | R35: 6865.43 | S35: 8196.23 | T35: 7327.32 | U35: 7327.32 | V35: 11371.96 | W35: 11426.33 | X35: 10459.2 | Y35: 11237.28 | Z35: 11237.28 | AA35: 16173.1 | AB35: 19117.42
A36: 1 | C36: 비유동부채 | E36: 2041.45 | F36: 2041.45 | G36: 2068.24 | H36: 2697.87 | I36: 1416.27 | J36: 1017.66 | K36: 1017.66 | L36: 947.04 | M36: 1549.39 | N36: 1690.66 | O36: 960.22 | P36: 960.22 | Q36: 1086.59 | R36: 596.4 | S36: 592.18 | T36: 531.12 | U36: 531.12 | V36: 1522.87 | W36: 2507.25 | X36: 2519.23 | Y36: 74818.16 | Z36: 74818.16 | AA36: 78901.95 | AB36: 103265.06
A37: 1 | C37: 장기매입채무및기타채무 | E37: 216.46 | F37: 216.46 | G37: 221.96 | H37: 226.91 | I37: 233.76 | J37: 238.99 | K37: 238.99 | L37: 246.99 | M37: 250.85 | N37: 238.33 | O37: 270.29 | P37: 270.29 | Q37: 288.45 | R37: 288.07 | S37: 295.09 | T37: 254.28 | U37: 254.28 | V37: 242.75 | W37: 250.8 | X37: 258.24 | Y37: 792.06 | Z37: 792.06 | AA37: 845.29 | AB37: 865.69
A38: 1 | C38: 장기차입금 | E38: 1537.18 | F38: 1537.18 | G38: 1533.8 | H38: 2030.42 | I38: 527.04 | J38: 500 | K38: 500 | L38: 500 | M38: 500 | N38: 500 | O38: 500 | P38: 500 | Q38: 500 | R38: 0 | S38: 0 | T38: 0 | U38: 0 | V38: 1000 | W38: 2000 | X38: 2000 | Y38: 34007.91 | Z38: 34007.91 | AA38: 34826.94 | AB38: 58357.32
A39: 1 | C39: 비유동리스부채 | E39: 103.36 | F39: 103.36 | G39: 78.68 | H39: 53.35 | I39: 76.02 | J39: 118.99 | K39: 118.99 | L39: 34.35 | M39: 15.28 | N39: 12.4 | O39: 9.5 | P39: 9.5 | Q39: 111.84 | R39: 95.87 | S39: 78.09 | T39: 64.81 | U39: 64.81 | V39: 49.6 | W39: 33.12 | X39: 18.89 | Y39: 373.7 | Z39: 373.7 | AA39: 340.23 | AB39: 348.64
A40: 1 | C40: 장기금융부채 | E40: 103.36 | F40: 103.36 | G40: 78.68 | H40: 53.35 | I40: 76.02 | J40: 118.99 | K40: 118.99 | L40: 34.35 | M40: 15.28 | N40: 12.4 | O40: 9.5 | P40: 9.5 | Q40: 111.84 | R40: 95.87 | S40: 78.09 | T40: 64.81 | U40: 64.81 | V40: 49.6 | W40: 33.12 | X40: 18.89 | Y40: 3006.47 | Z40: 3006.47 | AA40: 2973 | AB40: 4024.06
A41: 1 | C41: 이연법인세부채 | E41: 0 | F41: 0 | I41: 0 | J41: 0 | K41: 0 | Y41: 29183.12 | Z41: 29183.12 | AA41: 30212.91 | AB41: 29407.68
A42: 1 | C42: 기타비유동부채 | E42: 184.45 | F42: 184.45 | G42: 158.48 | H42: 146.41 | I42: 155.4 | J42: 159.68 | K42: 159.68 | L42: 165.7 | M42: 174.02 | N42: 166.66 | O42: 180.43 | P42: 180.43 | Q42: 186.3 | R42: 212.47 | S42: 219 | T42: 212.03 | U42: 212.03 | V42: 230.52 | W42: 223.33 | X42: 242.09 | Y42: 240.96 | Z42: 240.96 | AA42: 222.23 | AB42: 240.34
A43: 1 | C43: 부채총계 | E43: 37348.56 | F43: 37348.56 | G43: 39400.49 | H43: 40899.74 | I43: 40137.74 | J43: 37873.18 | K43: 37873.18 | L43: 39275.14 | M43: 40929.68 | N43: 41849.96 | O43: 43217.18 | P43: 43217.18 | Q43: 44832.78 | R43: 38118.22 | S43: 42820.47 | T43: 41663.92 | U43: 41663.92 | V43: 53557.31 | W43: 42922.75 | X43: 66907.63 | Y43: 301285.81 | Z43: 301285.81 | AA43: 320618.27 | AB43: 327616.93
A44: 1 | C44: 지배주주지분 | E44: 71464.99 | F44: 71464.99 | G44: 71035.5 | H44: 68307.9 | I44: 66849.57 | J44: 62362.09 | K44: 62362.09 | L44: 64344.77 | M44: 64846.13 | N44: 66046.09 | O44: 67123.81 | P44: 67123.81 | Q44: 67524.02 | R44: 68280.06 | S44: 71054.67 | T44: 72781.83 | U44: 72781.83 | V44: 73531.29 | W44: 75021.25 | X44: 78041.11 | Y44: 84993.67 | Z44: 84993.67 | AA44: 89588.54 | AB44: 94355.91
A45: 1 | C45: 자본금 | E45: 7513.15 | F45: 7513.15 | G45: 7513.15 | H45: 7513.15 | I45: 7513.15 | J45: 7513.15 | K45: 7513.15 | L45: 7513.15 | M45: 7513.15 | N45: 7513.15 | O45: 7513.15 | P45: 7513.15 | Q45: 7513.15 | R45: 7513.15 | S45: 7513.15 | T45: 7513.15 | U45: 7513.15 | V45: 7513.15 | W45: 7513.15 | X45: 7513.15 | Y45: 7513.15 | Z45: 7513.15 | AA45: 7513.15 | AB45: 7513.15
A46: 1 | C46: 보통주자본금 | E46: 7513.15 | F46: 7513.15 | G46: 7513.15 | H46: 7513.15 | I46: 7513.15 | J46: 7513.15 | K46: 7513.15 | L46: 7513.15 | M46: 7513.15 | N46: 7513.15 | O46: 7513.15 | P46: 7513.15 | Q46: 7513.15 | R46: 7513.15 | S46: 7513.15 | T46: 7513.15 | U46: 7513.15 | V46: 7513.15 | W46: 7513.15 | X46: 7513.15 | Y46: 7513.15 | Z46: 7513.15 | AA46: 7513.15 | AB46: 7513.15
A47: 1 | C47: 자본잉여금 | E47: 18508.34 | F47: 18508.34 | G47: 18508.34 | H47: 18508.34 | I47: 18508.34 | J47: 18508.34 | K47: 18508.34 | L47: 18508.34 | M47: 18508.34 | N47: 18508.34 | O47: 18508.34 | P47: 18508.34 | Q47: 18508.34 | R47: 18508.34 | S47: 18508.34 | T47: 18508.34 | U47: 18508.34 | V47: 18508.34 | W47: 18508.34 | X47: 18508.34 | Y47: 25062.12 | Z47: 25062.12 | AA47: 25062.12 | AB47: 25062.12
A48: 1 | C48: 기타자본 | E48: -1087.86 | F48: -1087.86 | G48: -1087.86 | H48: -1087.86 | I48: -1087.86 | J48: -1087.86 | K48: -1087.86 | L48: -1087.86 | M48: -1087.86 | N48: -1087.86 | O48: -1087.86 | P48: -1087.86 | Q48: -1087.86 | R48: -1087.86 | S48: -1087.86 | T48: -1087.86 | U48: -1087.86 | V48: -1087.86 | W48: -1087.86 | X48: -1087.86 | Y48: -6882.58 | Z48: -6882.58 | AA48: -6882.58 | AB48: -6882.58
A49: 1 | C49: 기타포괄이익누계액 | E49: 1166.13 | F49: 1166.13 | G49: 1414.11 | H49: 1592.82 | I49: 2051.11 | J49: 1061.56 | K49: 1061.56 | L49: 1418.9 | M49: 1019.48 | N49: 1184.82 | O49: 1007.89 | P49: 1007.89 | Q49: 1269.49 | R49: 1517.44 | S49: 1428.71 | T49: 2118.57 | U49: 2118.57 | V49: 2154.67 | W49: 1406.01 | X49: 1885.47 | Y49: 2441.66 | Z49: 2441.66 | AA49: 5249.69 | AB49: 7051.42
A50: 1 | C50: 이익잉여금 | E50: 45365.23 | F50: 45365.23 | G50: 44687.76 | H50: 41781.45 | I50: 39864.83 | J50: 36366.9 | K50: 36366.9 | L50: 37992.24 | M50: 38893.02 | N50: 39927.64 | O50: 41182.29 | P50: 41182.29 | Q50: 41320.9 | R50: 41829 | S50: 44692.32 | T50: 45729.63 | U50: 45729.63 | V50: 46442.98 | W50: 48681.6 | X50: 51222.01 | Y50: 56859.32 | Z50: 56859.32 | AA50: 58646.16 | AB50: 61611.8
A51: 1 | C51: 비지배주주지분 | E51: 1568.48 | F51: 1568.48 | G51: 1631.32 | H51: 1617.61 | I51: 1682.99 | J51: 1066.35 | K51: 1066.35 | L51: 1204.64 | M51: 1154.46 | N51: 1233.11 | O51: 1240.35 | P51: 1240.35 | Q51: 1321.65 | R51: 1325.06 | S51: 1374.26 | T51: 1439.81 | U51: 1439.81 | V51: 1571.67 | W51: 1476.77 | X51: 1640.36 | Y51: 157835.39 | Z51: 157835.39 | AA51: 158092.37 | AB51: 157972.82
A52: 1 | C52: 자본총계 | E52: 73033.47 | F52: 73033.47 | G52: 72666.82 | H52: 69925.51 | I52: 68532.56 | J52: 63428.43 | K52: 63428.43 | L52: 65549.41 | M52: 66000.59 | N52: 67279.2 | O52: 68364.15 | P52: 68364.15 | Q52: 68845.67 | R52: 69605.13 | S52: 72428.93 | T52: 74221.64 | U52: 74221.64 | V52: 75102.96 | W52: 76498.02 | X52: 79681.47 | Y52: 242829.06 | Z52: 242829.06 | AA52: 247680.91 | AB52: 252328.74
A53: 1 | C53: 부채와자본총계 | E53: 110382.02 | F53: 110382.02 | G53: 112067.31 | H53: 110825.25 | I53: 108670.3 | J53: 101301.62 | K53: 101301.62 | L53: 104824.56 | M53: 106930.27 | N53: 109129.15 | O53: 111581.33 | P53: 111581.33 | Q53: 113678.45 | R53: 107723.34 | S53: 115249.4 | T53: 115885.55 | U53: 115885.55 | V53: 128660.27 | W53: 119420.76 | X53: 146589.1 | Y53: 544114.87 | Z53: 544114.87 | AA53: 568299.17 | AB53: 579945.67
... A56: 1 | C56: 이자발생자산 | E56: 39107.31 | F56: 39107.31 | G56: 33870.51 | H56: 33692.96 | I56: 27535.33 | J56: 32966.83 | K56: 32966.83 | L56: 33900.54 | M56: 32446.95 | N56: 34419.43 | O56: 33544.14 | P56: 33544.14 | Q56: 28867.87 | R56: 24461.86 | S56: 34640.42 | T56: 30208.12 | U56: 30208.12 | V56: 38006.28 | W56: 34972.1 | X56: 60810.44 | Y56: 78800.69 | Z56: 78800.69 | AA56: 82725.43 | AB56: 79141.59
A57: 1 | C57: 확정급여부채 | G57: 75.32 | H57: 240.79 | I57: 424.04 | J57: 0 | K57: 0 | L57: 0 | M57: 609.25 | N57: 773.27 | Q57: 0 | V57: 0
A58: 1 | C58: 장기금융부채(face) | S58: 0 | T58: 0 | U58: 0
A59: 1 | C59: 사채 | Y59: 7587.63 | Z59: 7587.63 | AA59: 7845.53 | AB59: 8106.29
A60: 1 | C60: 장기파생상품부채 | Y60: 2632.77 | Z60: 2632.77 | AA60: 2632.77 | AB60: 3675.42
A61: 1 | C61: 매출액(수익) | E61: 16559.94 | G61: 20316.73 | H61: 22798.47 | I61: 23829.65 | J61: 23732.09 | K61: 90676.94 | L61: 20984.76 | M61: 23488.54 | N61: 26379.77 | O61: 24896.4 | P61: 95749.47 | Q61: 26521.26 | R61: 34057.66 | S61: 28580.76 | T61: 28861.09 | U61: 118020.77 | V61: 26340.53 | W61: 29631.69 | X61: 29469.17 | Y61: 33020.73 | Z61: 118462.12 | AA61: 130909.8 | AB61: 131393.13
A62: 1 | C62: 매출원가 | E62: 14980.7 | G62: 17989.9 | H62: 22007.81 | I62: 19898.12 | J62: 20215.1 | K62: 80110.93 | L62: 18214.23 | M62: 19292.66 | N62: 21146.92 | O62: 21252.76 | P62: 79906.57 | Q62: 20366.37 | R62: 27879.31 | S62: 23321.52 | T62: 22884.83 | U62: 94452.03 | V62: 20466.64 | W62: 23578.67 | X62: 23311.42 | Y62: 27786.29 | Z62: 95143.02 | AA62: 112820.43 | AB62: 115001.75
A63: 1 | C63: 매출총이익 | E63: 1579.24 | G63: 2326.83 | H63: 790.66 | I63: 3931.53 | J63: 3516.99 | K63: 10566.01 | L63: 2770.52 | M63: 4195.88 | N63: 5232.85 | O63: 3643.64 | P63: 15842.89 | Q63: 6154.89 | R63: 6178.35 | S63: 5259.24 | T63: 5976.26 | U63: 23568.74 | V63: 5873.88 | W63: 6053.03 | X63: 6157.75 | Y63: 5234.44 | Z63: 23319.1 | AA63: 18089.37 | AB63: 16391.38
A64: 1 | C64: 판관비 | E64: 2268.48 | G64: 2144.14 | H64: 2102.23 | I64: 7219.01 | J64: 2281.72 | K64: 13747.1 | L64: 1986.11 | M64: 2788.87 | N64: 2509.57 | O64: 2564.7 | P64: 9849.25 | Q64: 3458.97 | R64: 4750.37 | S64: 2509.08 | T64: 2553.44 | U64: 13271.86 | V64: 3006.09 | W64: 3614.63 | X64: 2747.21 | Y64: 3732.57 | Z64: 13100.5 | AA64: 12480.74 | AB64: 13215.19
A65: 1 | C65: 영업이익 | E65: -689.24 | G65: 182.7 | H65: -1311.57 | I65: -3287.48 | J65: 1235.26 | K65: -3181.09 | L65: 784.42 | M65: 1407.01 | N65: 2723.28 | O65: 1078.94 | P65: 5993.65 | Q65: 2695.92 | R65: 1427.98 | S65: 2750.16 | T65: 3422.82 | U65: 10296.88 | V65: 2867.79 | W65: 2438.4 | X65: 3410.54 | Y65: 1501.87 | Z65: 10218.6 | AA65: 5608.63 | AB65: 3176.2
A66: 1 | C66: 기타영업외수익 | E66: 207.72 | G66: 223.95 | H66: 388.48 | I66: -68.24 | J66: 170.1 | K66: 714.29 | L66: 348.86 | M66: 130.26 | N66: 105.39 | O66: 146.59 | P66: 731.1 | Q66: 195.62 | R66: 164.35 | S66: 129.24 | T66: 151.31 | U66: 640.52 | V66: 168.28 | W66: 128.7 | X66: 288.24 | Y66: 5100.75 | Z66: 5685.97 | AA66: 2082.46 | AB66: 1572.72
A67: 1 | C67: 기타영업외비용 | E67: 9113.87 | G67: 18.34 | H67: 8.65 | I67: 24.14 | J67: 4487.35 | K67: 4538.48 | L67: 8.64 | M67: 28.3 | N67: 8.43 | O67: 22.25 | P67: 67.62 | Q67: 58.63 | R67: 8.63 | S67: 9.18 | T67: 139.03 | U67: 215.47 | V67: 40.95 | W67: 58.46 | X67: 68.95 | Y67: 34.39 | Z67: 202.75 | AA67: 316.32 | AB67: 1989.21
A68: 1 | C68: 금융수익 | E68: -450.45 | G68: 458.95 | H68: 567.85 | I68: 984.66 | J68: -3.6 | K68: 2007.86 | L68: 2323.14 | M68: 290.38 | N68: -768.08 | O68: 673.92 | P68: 2519.36 | Q68: 380.68 | R68: 394.05 | S68: 578.1 | T68: 379.63 | U68: 1732.46 | V68: 844.6 | W68: 643.03 | X68: 368.82 | Y68: 732.57 | Z68: 2589.02 | AA68: 5220.17 | AB68: 6449.85
A69: 1 | C69: 금융비용 | E69: 138.85 | G69: 710.95 | H69: 3322.32 | I69: 719.84 | J69: 833.86 | K69: 5586.97 | L69: 722.23 | M69: 671.52 | N69: 803.51 | O69: 496.15 | P69: 2693.41 | Q69: 1563.94 | R69: 1322.75 | S69: 133.42 | T69: 2490.4 | U69: 5510.51 | V69: 680.23 | W69: 223.03 | X69: 840.67 | Y69: 2479.39 | Z69: 4223.32 | AA69: 7448.95 | AB69: 6384.8
A70: 1 | C70: 법인세비용차감전계속사업이익 | E70: -10184.69 | G70: 136.3 | H70: -3686.21 | I70: -3115.04 | J70: -3919.45 | K70: -10584.4 | L70: 2725.55 | M70: 1127.83 | N70: 1248.64 | O70: 1381.06 | P70: 6483.08 | Q70: 1649.66 | R70: 655 | S70: 3314.9 | T70: 1324.33 | U70: 6943.89 | V70: 3159.49 | W70: 2928.63 | X70: 3157.97 | Y70: 4821.41 | Z70: 14067.5 | AA70: 5145.99 | AB70: 2824.76
A71: 1 | C71: 법인세비용 | E71: -721.72 | G71: -68.15 | H71: -744.55 | I71: -1208.32 | J71: 159.78 | K71: -1861.24 | L71: 398.67 | M71: 228.87 | N71: 155.39 | O71: -511.49 | P71: 271.44 | Q71: 248.42 | R71: 173.51 | S71: 391.63 | T71: 88.35 | U71: 901.91 | V71: 499.14 | W71: 694.27 | X71: 512.03 | Y71: -762.79 | Z71: 942.65 | AA71: 923.44 | AB71: 1364.83
A72: 1 | C72: 계속사업이익 | E72: -9462.96 | G72: 204.45 | H72: -2941.66 | I72: -1906.73 | J72: -4079.23 | K72: -8723.17 | L72: 2326.87 | M72: 898.96 | N72: 1093.25 | O72: 1892.54 | P72: 6211.62 | Q72: 1401.24 | R72: 481.49 | S72: 2923.27 | T72: 1235.99 | U72: 6041.99 | V72: 2660.35 | W72: 2234.36 | X72: 2645.94 | Y72: 5584.18 | Z72: 13124.83 | AA72: 4222.56 | AB72: 1459.94
... A78: 1 | C78: 기타영업외손익 | E78: -8906.15 | G78: 205.61 | H78: 379.83 | I78: -92.38 | J78: -4317.25 | K78: -3824.19 | L78: 340.22 | M78: 101.96 | N78: 96.96 | O78: 124.34 | P78: 663.48 | Q78: 136.99 | R78: 155.72 | S78: 120.06 | T78: 12.28 | U78: 425.05 | V78: 127.33 | W78: 70.24 | X78: 219.29 | Y78: 5066.36 | Z78: 5483.22 | AA78: 1766.14 | AB78: -416.49
A79: 1 | C79: 이자수익 | G79: 145.35 | H79: 144.33 | I79: 226.25 | J79: 237.17 | K79: 753.1 | L79: 350.12 | M79: 289.95 | N79: 322.16 | O79: 298.99 | P79: 1261.22 | Q79: 310.6 | R79: 200.63 | S79: 267.57 | T79: 283.02 | U79: 1061.82 | V79: 277.3 | W79: 271.94 | X79: 147.28 | Y79: 515.7 | Z79: 1212.22 | AA79: 755.01 | AB79: 692.62
A80: 1 | C80: 배당금수익 | G80: 4.47 | H80: 60.91 | I80: 0 | J80: 0 | K80: 65.38 | M80: 68.61 | N80: 0 | O80: 0 | R80: 76.16 | S80: 0 | T80: 0 | W80: 89.83 | X80: 0 | Y80: 0 | AA80: 156.7 | AB80: -48.21
A81: 1 | C81: 이자비용 | G81: 98.93 | H81: 135.14 | I81: 181.09 | J81: 238.35 | K81: 653.51 | L81: 310.46 | M81: 328.85 | N81: 333.57 | O81: 332.11 | P81: 1304.99 | Q81: 319.09 | R81: 217.7 | S81: 212.31 | T81: 221.83 | U81: 970.93 | V81: 276.49 | W81: 226.23 | X81: 207.87 | Y81: 682.11 | Z81: 1392.7 | AA81: 2235.88 | AB81: 2169.92
A82: 1 | C82: 외환차익 | G82: 155.96 | H82: 158.22 | I82: 157.9 | J82: 611.39 | K82: 1083.47 | L82: 257.74 | M82: 187.9 | N82: 118.89 | O82: 131.97 | P82: 696.5 | Q82: 52.81 | R82: 89.35 | S82: 120.51 | T82: 128.37 | U82: 391.04 | V82: 44.48 | W82: 124.26 | X82: 72.79 | Y82: 264.85 | Z82: 506.38 | AA82: 898.65 | AB82: 1051.98
A83: 1 | C83: 외환차손 | G83: 58.7 | H83: 87.55 | I83: -30.1 | J83: 698.4 | K83: 814.55 | L83: 137.63 | M83: 80.69 | N83: 127.76 | O83: 194.51 | P83: 540.59 | Q83: 37.24 | R83: 45.43 | S83: 113.16 | T83: 123.32 | U83: 319.15 | V83: 53.63 | W83: 158.12 | X83: 35.99 | Y83: 93.01 | Z83: 340.75 | AA83: 918.73 | AB83: 96.15
A84: 1 | C84: 외화환산이익 | G84: 140.83 | H84: 171.09 | I84: 583.84 | J84: -870.06 | K84: 25.7 | L84: 170.69 | M84: -87.56 | N84: -28.74 | O84: -38.82 | P84: 15.57 | Q84: 13.59 | R84: 10.42 | S84: 34.39 | T84: -39.21 | U84: 19.19 | V84: 38.36 | W84: 7.15 | X84: 76.95 | Y84: -64.89 | Z84: 57.57 | AA84: 3296.41 | AB84: 1517.44
A85: 1 | C85: 외화환산손실 | G85: 83.34 | H85: 317.07 | I85: 165.34 | J85: 11.31 | K85: 577.06 | L85: 11.15 | M85: 175.28 | N85: 44.67 | O85: -130.28 | P85: 100.82 | Q85: 35.49 | R85: 36.86 | S85: -54.07 | T85: 50.93 | U85: 69.21 | V85: 1.92 | W85: 39.86 | X85: -29.01 | Y85: 56.34 | Z85: 69.11 | AA85: 2157.55 | AB85: -293.5
A86: 1 | C86: 파생상품손실 | G86: 82.1 | H86: 290.81 | I86: 72.82 | J86: 0 | K86: 445.73 | L86: 240.4 | M86: 86.23 | N86: 61.11 | O86: 21.51 | P86: 409.25 | Q86: 432.88 | R86: 458.24 | S86: -281.79 | T86: 788.58 | U86: 1397.91 | V86: 260.34 | W86: -160.96 | X86: 535.52 | Y86: 728.35 | Z86: 1363.25 | AA86: 660.69 | AB86: 1762.2
A87: 1 | C87: 이자손익 | G87: 46.42 | H87: 9.19 | I87: 45.16 | J87: -1.18 | K87: 99.59 | L87: 39.66 | M87: -38.9 | N87: -11.41 | O87: -33.12 | P87: -43.77 | Q87: -8.49 | R87: -17.07 | S87: 55.26 | T87: 61.19 | U87: 90.89 | V87: 0.81 | W87: 45.71 | X87: -60.59 | Y87: -166.41 | Z87: -180.48 | AA87: -1480.87 | AB87: -1477.3
A88: 1 | C88: 파생상품이익 | H88: 35.23 | I88: 0 | J88: 0 | L88: 5.25 | M88: 20.98 | N88: 17.14 | O88: 82 | P88: 125.37 | S88: 33.14 | T88: -20.96 | V88: 48.58 | W88: 262.33 | X88: -121.99 | Y88: 139.67 | Z88: 328.59 | AA88: 8.14 | AB88: 0
A89: 1 | C89: 영업활동으로인한현금흐름 | E89: -6645.05 | G89: -4187.12 | H89: 3626.11 | I89: -4561.52 | J89: 7686.54 | K89: 2564.01 | L89: -1323.36 | M89: -980.88 | N89: 3924.14 | O89: 1793.55 | P89: 3413.45 | Q89: 2497.93 | R89: 2426.17 | S89: 7869.93 | T89: -1881.52 | U89: 10912.51 | V89: -49 | W89: 5706.65 | X89: 1848.18 | Y89: -17303.59 | Z89: -9797.76 | AA89: 2594.22 | AB89: -3358.15
A90: 1 | C90: 배당금수취(CF) | E90: 0 | G90: 4.47 | H90: 60.91 | I90: 0 | J90: 0 | K90: 65.38 | L90: 0 | M90: 68.61 | N90: 0 | O90: 0 | P90: 68.61 | Q90: 0 | R90: 76.16 | S90: 0 | T90: 0 | U90: 76.16 | X90: 0 | Y90: 0 | AA90: 156.7 | AB90: -48.21
A91: 1 | C91: 법인세납부(CF) | E91: -22.91 | G91: -35.72 | H91: -43.55 | I91: -60.84 | J91: -31.04 | K91: -171.15 | L91: -39.72 | M91: 19.96 | N91: -40.89 | O91: -58.79 | P91: -119.44 | Q91: -49.16 | R91: 53.55 | S91: -48.2 | T91: -257.13 | U91: -300.94 | V91: -66.49 | W91: -121.06 | X91: -27.45 | Y91: -138.14 | Z91: -353.14 | AA91: -620.17 | AB91: -1535.09
A92: 1 | C92: 투자활동으로인한현금흐름 | E92: 5378.32 | G92: 6234.19 | H92: -1307.8 | I92: -392.99 | J92: -4208.17 | K92: 325.23 | L92: -1496.27 | M92: -689.79 | N92: -2978.31 | O92: -3784.56 | P92: -8948.93 | Q92: 1578.71 | R92: 8834.89 | S92: -13565.3 | T92: 1913.79 | U92: -1237.91 | V92: -8906.37 | W92: 6721.84 | X92: -12305.08 | Y92: -66259.1 | Z92: -80748.71 | AA92: -11333.34 | AB92: -9279.08
A93: 1 | C93: 재무활동으로인한현금흐름 | E93: 2950.44 | G93: -548.23 | H93: -777.72 | I93: -54.66 | J93: -943.5 | K93: -2324.11 | L93: 1237.65 | M93: -70.97 | N93: -52.14 | O93: -38.25 | P93: 1076.29 | Q93: -6020.79 | R93: -5795.75 | S93: 2487.59 | T93: 7.11 | U93: -9321.84 | V93: 7465.85 | W93: -8831.06 | X93: 23609.27 | Y93: 90619.38 | Z93: 112863.44 | AA93: 5957.42 | AB93: 142.26
A94: 1 | C94: 단기차입금의증가 | E94: 3000 | G94: 0 | H94: 0 | I94: 0 | J94: 0 | K94: 0 | L94: 1292.12 | M94: 575.88 | Q94: 0 | R94: 2800.95 | S94: 2512.6 | T94: 24.45 | U94: 5338 | V94: 9000 | W94: 1500 | X94: 27843.2 | Y94: 48219.16 | Z94: 86562.36 | AA94: 58358.34 | AB94: 20501.13
A95: 1 | C95: 장기차입금의증가 | E95: 0 | I95: 0 | J95: 0 | N95: 0 | O95: 0 | V95: 1000 | W95: 1000 | X95: 0 | Y95: 30000 | Z95: 32000 | AA95: 0 | AB95: 25000
A96: 1 | C96: 단기차입금의감소 | E96: 0 | J96: 1221.39 | O96: 0 | Q96: 6000 | R96: 7367.3 | S96: 8.4 | T96: 16.3 | U96: 13392 | V96: 2000 | W96: 9500 | X96: 4216.43 | Y96: 11015.44 | Z96: 26731.87 | AA96: 52366.12 | AB96: 40893.1
A97: 1 | C97: 배당금지급 | E97: 0 | I97: 0 | J97: 0 | N97: 0 | O97: 0 | S97: 0 | T97: 0 | X97: 0 | Y97: 0 | AA97: 0 | AB97: 4353.32
A98: 1 | C98: 장기차입금의감소 | E98: 3.38 | G98: 503.38 | H98: 383.46 | I98: 6.98 | L98: 0 | M98: 0 | N98: 0 | O98: 0 | P98: 0 | Q98: 0 | R98: 0 | AA98: 15.39 | AB98: 15.55
A99: 1 | C99: 자기주식의취득 | E99: 0 | J99: 0
A100: 1 | C100: 현금및현금성자산의증감 | E100: 1683.71 | G100: 1498.84 | H100: 1540.59 | I100: -5009.18 | J100: 2534.88 | K100: 565.13 | L100: -1581.99 | M100: -1741.63 | N100: 893.68 | O100: -2029.25 | P100: -4459.19 | Q100: -1944.15 | R100: 5465.31 | S100: -3207.78 | T100: 39.38 | U100: 352.76 | V100: -1489.52 | W100: 3597.42 | X100: 13152.38 | Y100: 26652.21 | Z100: 41912.49 | AA100: -7970.15 | AB100: -5778.66
A101: 1 | C101: 기말현금및현금성자산 | E101: 1653.96 | G101: 9845.85 | H101: 1594.84 | I101: -4844 | J101: 2171.43 | K101: 8768.12 | L101: 7219.26 | M101: -1805.78 | N101: 900.38 | O101: -2006.45 | P101: 4307.41 | Q101: 6830.32 | R101: 1027.04 | S101: -3200.96 | T101: 55.88 | U101: 4712.28 | V101: 3231.07 | W101: 3550.79 | X101: 13205 | Y101: 26675.16 | Z101: 46662.02 | AA101: 40278.7 | AB101: -5240.67
A102: 1 | C102: 이자수취(CF) | O102: 278.77 | Q102: 336.33 | R102: 258.33 | S102: 231.38 | T102: 301.04 | U102: 1127.08 | V102: 216.58 | W102: 341.04 | X102: 209.98 | Y102: 522.76 | Z102: 1290.36 | AA102: 742.96 | AB102: 688.46
A103: 1 | C103: 무형자산의감소 | S103: 0 | T103: 0 | X103: 0 | Y103: 0 | AA103: 0 | AB103: 399.09
A104: 1 | C104: 무형자산의증가 | V104: 1.73 | W104: 23.14 | X104: 5.64
A105: 1 | C105: CAPEX | V105: 1.73 | W105: 23.14 | X105: 5.64
A106: 1 | C106: 차입금의감소 | V106: 500 | W106: 0 | X106: 0

Sheet BS별도
B1: (백만원) | C1: 이름: BS별도H | E1: 4Q21 | F1: 2021 | G1: 1Q22 | H1: 2Q22 | I1: 3Q22 | J1: 4Q22 | K1: 2022 | L1: 1Q23 | M1: 2Q23 | N1: 3Q23 | O1: 4Q23 | P1: 2023 | Q1: 1Q24 | R1: 2Q24 | S1: 3Q24 | T1: 4Q24 | U1: 2024 | V1: 1Q25 | W1: 2Q25 | X1: 3Q25 | Y1: 4Q25 | Z1: 2025 | AA1: 1Q26 | AB1: 2Q26 | AC1: 3Q26 | AD1: 4Q26 | AE1: 2026 | AF1: 1Q27 | AG1: 2Q27 | AH1: 3Q27 | AI1: 4Q27 | AJ1: 2027 | AK1: 1Q28 | AL1: 2Q28 | AM1: 3Q28 | AN1: 4Q28 | AO1: 2028
B2: 별도 | D2: fin json(kship_fin.py)
B3: 삼영엠텍(별) | C3: UPDATE: 26-10-12 | E3: 1 | F3: 2 | G3: 3 | H3: 4 | I3: 5 | J3: 6 | K3: 7 | L3: 8 | M3: 9 | N3: 10 | O3: 11 | P3: 12 | Q3: 13 | R3: 14 | S3: 15 | T3: 16 | U3: 17 | V3: 18 | W3: 19 | X3: 20 | Y3: 21 | Z3: 22 | AA3: 23 | AB3: 24 | AC3: 25 | AD3: 26 | AE3: 27 | AF3: 28 | AG3: 29 | AH3: 30 | AI3: 31 | AJ3: 32 | AK3: 33 | AL3: 34 | AM3: 35 | AN3: 36 | AO3: 37
B4: Account Code | C4: AccountNAME | E4: 2021.12 | F4: 2021.12A | G4: 2022.03 | H4: 2022.06 | I4: 2022.09 | J4: 2022.12 | K4: 2022.12A | L4: 2023.03 | M4: 2023.06 | N4: 2023.09 | O4: 2023.12 | P4: 2023.12A | Q4: 2024.03 | R4: 2024.06 | S4: 2024.09 | T4: 2024.12 | U4: 2024.12A | V4: 2025.03 | W4: 2025.06 | X4: 2025.09 | Y4: 2025.12 | Z4: 2025.12A | AA4: 2026.03 | AB4: 2026.06 | AC4: 2026.09 | AD4: 2026.12 | AE4: 2026.12A | AF4: 2027.03 | AG4: 2027.06 | AH4: 2027.09 | AI4: 2027.12 | AJ4: 2027.12A | AK4: 2028.03 | AL4: 2028.06 | AM4: 2028.09 | AN4: 2028.12 | AO4: 2028.12A
A5: 1 | C5: 유동자산 | E5: 50904.61 | F5: 50904.61 | G5: 53450.99 | H5: 49019.12 | I5: 45782.18 | J5: 44818.75 | K5: 44818.75 | L5: 47565.18 | M5: 49590.73 | N5: 51165.17 | O5: 50383.06 | P5: 50383.06 | Q5: 51894.13 | R5: 43087.14 | S5: 50521.04 | T5: 49762.02 | U5: 49762.02 | V5: 57099.58 | W5: 51734.43 | X5: 76185.06 | Y5: 41211.58 | Z5: 41211.58 | AA5: 51341.38 | AB5: 55353.75
A6: 1 | C6: 현금및현금성자산 | E6: 6028.82 | F6: 6028.82 | G6: 6718.53 | H6: 7148.99 | I6: 4588.54 | J6: 5223.45 | K6: 5223.45 | L6: 6270.1 | M6: 4292.09 | N6: 5736.93 | O6: 3690.9 | P6: 3690.9 | Q6: 2165.35 | R6: 5617.32 | S6: 2385.96 | T6: 4296.79 | U6: 4296.79 | V6: 2646.74 | W6: 5804.48 | X6: 19064.89 | Y6: 2465.88 | Z6: 2465.88 | AA6: 4469.18 | AB6: 2834.91
A7: 1 | C7: 단기금융상품 | E7: 15935.08 | F7: 15935.08 | G7: 11427.9 | H7: 11411.1 | I7: 10375.12 | J7: 15823.83 | K7: 15823.83 | L7: 16783.95 | M7: 16294.84 | N7: 18177.28 | O7: 19162.76 | P7: 19162.76 | Q7: 16183.86 | R7: 5186.73 | S7: 19032.25 | T7: 14724.98 | U7: 14724.98 | V7: 18700.77 | W7: 13443.49 | X7: 26151.56 | Y7: 1399.58 | Z7: 1399.58 | AA7: 2057.45 | AB7: 1072.99
A8: 1 | C8: 단기금융자산 | E8: 15970.15 | F8: 15970.15 | G8: 11456.06 | H8: 11411.1 | I8: 10375.12 | J8: 15823.83 | K8: 15823.83 | L8: 16789.2 | M8: 16321.07 | N8: 18220.65 | O8: 19240.37 | P8: 19240.37 | Q8: 16183.86 | R8: 5186.73 | S8: 19065.39 | T8: 14737.16 | U8: 14737.16 | V8: 18700.77 | W8: 13582.44 | X8: 26155.63 | Y8: 2712.78 | Z8: 2712.78 | AA8: 3292.23 | AB8: 1445.33
A9: 1 | C9: 매출채권및기타채권 | E9: 10986.4 | F9: 10986.4 | G9: 14863.67 | H9: 9957.76 | I9: 12669.76 | J9: 7500.63 | K9: 7500.63 | L9: 7949.77 | M9: 10860.06 | N9: 10998.93 | O9: 8184.82 | P9: 8184.82 | Q9: 9673.86 | R9: 11180.87 | S9: 8690.55 | T9: 7928.13 | U9: 7928.13 | V9: 10603.01 | W9: 9808.73 | X9: 9137.24 | Y9: 12403.59 | Z9: 12403.59 | AA9: 15130.83 | AB9: 16965.18
A10: 1 | C10: 재고자산 | E10: 16692.86 | F10: 16692.86 | G10: 18868.33 | H10: 19005.02 | I10: 17211.16 | J10: 15377.22 | K10: 15377.22 | L10: 15588.26 | M10: 17394.16 | N10: 14814.01 | O10: 17218.24 | P10: 17218.24 | Q10: 22604.94 | R10: 20369.85 | S10: 19303.78 | T10: 21691.84 | U10: 21691.84 | V10: 23951.84 | W10: 21697.98 | X10: 20595.42 | Y10: 22030.84 | Z10: 22030.84 | AA10: 26925.92 | AB10: 31585.37
A11: 1 | C11: 유동파생상품자산 | E11: 35.07 | F11: 35.07 | G11: 28.16 | H11: 0 | I11: 0 | J11: 0 | K11: 0 | L11: 5.25 | M11: 26.23 | N11: 43.37 | O11: 77.61 | P11: 77.61 | Q11: 0 | R11: 0 | S11: 33.14 | T11: 12.18 | U11: 12.18 | V11: 0 | W11: 138.95 | X11: 4.07 | Y11: 1313.2 | Z11: 1313.2 | AA11: 1234.78 | AB11: 372.34
A12: 1 | C12: 기타유동자산 | E12: 1226.39 | F12: 1226.39 | G12: 1544.39 | H12: 1496.24 | I12: 863.58 | J12: 819.47 | K12: 819.47 | L12: 893.68 | M12: 723.35 | N12: 1394.66 | O12: 1946.63 | P12: 1946.63 | Q12: 1164.01 | R12: 732.36 | S12: 1075.35 | T12: 1108.09 | U12: 1108.09 | V12: 1197.23 | W12: 840.81 | X12: 1231.88 | Y12: 1598.48 | Z12: 1598.48 | AA12: 1523.23 | AB12: 2522.96
A13: 1 | C13: 비유동자산 | E13: 55070.65 | F13: 55070.65 | G13: 54422.44 | H13: 56630.57 | I13: 56800.68 | J13: 49979.88 | K13: 49979.88 | L13: 48407.37 | M13: 48786.61 | N13: 48269.87 | O13: 51663.81 | P13: 51663.81 | Q13: 51624.67 | R13: 53110.29 | S13: 53179.06 | T13: 52306.59 | U13: 52306.59 | V13: 56271.08 | W13: 54044.9 | X13: 52858.08 | Y13: 140894.47 | Z13: 140894.47 | AA13: 139079.26 | AB13: 138007.69
A14: 1 | C14: 장기금융자산 | E14: 12100.86 | F14: 12100.86 | G14: 11726.14 | H14: 9731.29 | I14: 7949.7 | J14: 8073.83 | K14: 8073.83 | L14: 9585.16 | M14: 10395.24 | N14: 9564.18 | O14: 9681.59 | P14: 9681.59 | Q14: 9987.92 | R14: 11078.65 | S14: 10582.52 | T14: 10390.73 | U14: 10390.73 | V14: 15706.26 | W14: 14607.8 | X14: 14667.95 | Y14: 11265 | Z14: 11265 | AA14: 9836.28 | AB14: 10314.2
A15: 1 | C15: 투자자산 | E15: 27861.89 | F15: 27861.89 | G15: 27487.17 | H15: 25492.32 | I15: 23710.73 | J15: 16779.46 | K15: 16779.46 | L15: 18290.79 | M15: 19100.87 | N15: 18269.81 | O15: 18387.22 | P15: 18387.22 | Q15: 18693.55 | R15: 19784.28 | S15: 19288.15 | T15: 19096.36 | U15: 19096.36 | V15: 24411.89 | W15: 23313.43 | X15: 23373.58 | Y15: 109337.66 | Z15: 109337.66 | AA15: 107908.94 | AB15: 108386.86
A16: 1 | C16: 장기매출채권및기타채권 | E16: 965.65 | F16: 965.65 | G16: 983.25 | H16: 3870.35 | I16: 3796.73 | J16: 3568.88 | K16: 3568.88 | L16: 884.12 | M16: 770.88 | N16: 735.61 | O16: 2761.44 | P16: 2761.44 | Q16: 2786.7 | R16: 2698.34 | AB16: 825.6
A17: 1 | C17: 종속기업및관계기업투자 | E17: 15761.03 | F17: 15761.03 | G17: 15761.03 | H17: 15761.03 | I17: 15761.03 | J17: 8705.63 | K17: 8705.63 | L17: 8705.63 | M17: 8705.63 | N17: 8705.63 | O17: 8705.63 | P17: 8705.63 | Q17: 8705.63 | R17: 8705.63 | S17: 8705.63 | T17: 8705.63 | U17: 8705.63 | V17: 8705.63 | W17: 8705.63 | X17: 8705.63 | Y17: 98072.66 | Z17: 98072.66 | AA17: 98072.66 | AB17: 98072.66
A18: 1 | C18: 유형자산 | E18: 23625.95 | F18: 23625.95 | G18: 23326.02 | H18: 23886.87 | I18: 24525.42 | J18: 24608.42 | K18: 24608.42 | L18: 24637.31 | M18: 24507.21 | N18: 24620 | O18: 25011.63 | P18: 25011.63 | Q18: 24981.44 | R18: 24973.78 | S18: 24772.32 | T18: 24698.02 | U18: 24698.02 | V18: 24738.69 | W18: 24598.42 | X18: 24352.45 | Y18: 24028.44 | Z18: 24028.44 | AA18: 23415.6 | AB18: 23172.14
A19: 1 | C19: 사용권자산 | E19: 116.77 | F19: 116.77 | G19: 103.24 | H19: 89.71 | I19: 76.18 | J19: 93.94 | K19: 93.94 | L19: 77.56 | M19: 61.19 | N19: 44.81 | O19: 28.43 | P19: 28.43 | Q19: 97.12 | R19: 89.42 | S19: 79.3 | T19: 69.18 | U19: 69.18 | V19: 59.06 | W19: 48.93 | X19: 50.6 | Y19: 40.38 | Z19: 40.38 | AA19: 30.15 | AB19: 68.82
A20: 1 | C20: 기타비유동자산 | E20: 116.77 | F20: 116.77 | G20: 103.24 | H20: 89.71 | I20: 76.18 | J20: 93.94 | K20: 93.94 | L20: 77.56 | M20: 61.19 | N20: 44.81 | O20: 28.43 | P20: 28.43 | Q20: 97.12 | R20: 89.42 | S20: 79.3 | T20: 69.18 | U20: 69.18 | V20: 59.06 | W20: 48.93 | X20: 50.6 | Y20: 40.38 | Z20: 40.38 | AA20: 30.15 | AB20: 68.82
A21: 1 | C21: 무형자산 | E21: 317.53 | F21: 317.53 | G21: 317.53 | H21: 317.53 | I21: 558.89 | J21: 549.95 | K21: 549.95 | L21: 541.01 | M21: 532.07 | N21: 523.13 | O21: 512.19 | P21: 512.19 | Q21: 503.26 | R21: 417.55 | S21: 408.61 | T21: 1104.67 | U21: 1104.67 | V21: 1097.46 | W21: 1111.67 | X21: 1108.36 | Y21: 1203.77 | Z21: 1203.77 | AA21: 1201.48 | AB21: 1032.77
A22: 1 | C22: 투자부동산 | E22: 1951.11 | F22: 1951.11 | G22: 1942.48 | H22: 1933.85 | I22: 1925.22 | J22: 1916.6 | K22: 1916.6 | L22: 1907.97 | M22: 1899.34 | N22: 1890.71 | O22: 1882.08 | P22: 1882.08 | Q22: 1873.45 | R22: 1864.82 | S22: 1856.19 | T22: 1847.57 | U22: 1847.57 | V22: 1838.94 | W22: 1830.31 | X22: 1821.68 | Y22: 1813.05 | Z22: 1813.05 | AA22: 1804.42 | AB22: 1795.79
A23: 1 | C23: 이연법인세자산 | E23: 141.66 | F23: 141.66 | G23: 262.74 | H23: 1039.93 | I23: 2207.51 | J23: 2056.18 | K23: 2056.18 | L23: 1816.82 | M23: 1915.06 | N23: 2185.8 | O23: 2037.2 | P23: 2037.2 | Q23: 2037.2 | R23: 2617.71 | S23: 2894.42 | T23: 1678.2 | U23: 1678.2 | V23: 1308.5 | W23: 927.17 | X23: 666.49 | Y23: 1607.99 | Z23: 1607.99 | AA23: 1710.86 | AB23: 227.04
A24: 1 | C24: 자산총계 | E24: 105975.26 | F24: 105975.26 | G24: 107873.43 | H24: 105649.69 | I24: 102582.86 | J24: 94798.63 | K24: 94798.63 | L24: 95972.55 | M24: 98377.33 | N24: 99435.04 | O24: 102046.87 | P24: 102046.87 | Q24: 103518.8 | R24: 96197.43 | S24: 103700.1 | T24: 102068.61 | U24: 102068.61 | V24: 113370.66 | W24: 105779.33 | X24: 129043.14 | Y24: 182106.04 | Z24: 182106.04 | AA24: 190420.64 | AB24: 193361.44
A25: 1 | C25: 유동부채 | E25: 29656 | F25: 29656 | G25: 32651.42 | H25: 32383.2 | I25: 32640.41 | J25: 31727.71 | K25: 31727.71 | L25: 32067.51 | M25: 32933.9 | N25: 33299.71 | O25: 35626.43 | P25: 35626.43 | Q25: 37302.69 | R25: 29746.85 | S25: 34876.07 | T25: 32120.67 | U25: 32120.67 | V25: 42756.5 | W25: 31884.1 | X25: 53471.84 | Y25: 78968.45 | Z25: 78968.45 | AA25: 88291.91 | AB25: 89174.87
A26: 1 | C26: 매입채무및기타채무 | E26: 6515.92 | F26: 6515.92 | G26: 7636.24 | H26: 6356.84 | I26: 6960 | J26: 6843.81 | K26: 6843.81 | L26: 6613.77 | M26: 7268.89 | N26: 6736.02 | O26: 8126.95 | P26: 8126.95 | Q26: 10821.45 | R26: 7359.1 | S26: 8393.79 | T26: 9583.68 | U26: 9583.68 | V26: 9956.39 | W26: 6985.24 | X26: 7883 | Y26: 11541.67 | Z26: 11541.67 | AA26: 10342.09 | AB26: 11462.54
A27: 1 | C27: 단기차입금 | E27: 20000 | F27: 20000 | G27: 20000 | H27: 20000 | I27: 20000 | J27: 20000 | K27: 20000 | L27: 20000 | M27: 20000 | N27: 21500 | O27: 21500 | P27: 21500 | Q27: 15500 | R27: 10000 | S27: 12500 | T27: 12500 | U27: 12500 | V27: 19500 | W27: 11500 | X27: 32500 | Y27: 47640.06 | Z27: 47640.06 | AA27: 52506.33 | AB27: 54380.26
A28: 1 | C28: 유동성장기부채 | E28: 513.52 | F28: 513.52 | G28: 13.52 | H28: 13.52 | I28: 1513.52 | J28: 1500 | K28: 1500 | L28: 1500 | M28: 1500 | N28: 0 | Q28: 0 | R28: 500 | S28: 500 | T28: 500 | U28: 500 | V28: 0 | X28: 0 | AA28: 0 | AB28: 1000
A29: 1 | C29: 단기파생상품부채 | E29: 61.47 | F29: 61.47 | G29: 136.66 | H29: 282.81 | I29: 0 | J29: 0 | K29: 0 | L29: 218.87 | M29: 175.29 | N29: 182.79 | O29: 77.14 | P29: 77.14 | Q29: 396.24 | R29: 606.55 | S29: 217.35 | T29: 753.5 | U29: 753.5 | V29: 732.74 | W29: 362.11 | X29: 775.53 | Y29: 5752.36 | Z29: 5752.36 | AA29: 6059.21 | AB29: 2381.09
A30: 1 | C30: 단기금융부채 | E30: 114.81 | F30: 114.81 | G30: 190.17 | H30: 336.5 | I30: 53.87 | J30: 65.16 | K30: 65.16 | L30: 279.29 | M30: 222.31 | N30: 216.36 | O30: 97.23 | P30: 97.23 | Q30: 435.8 | R30: 646.52 | S30: 257.74 | T30: 791.98 | U30: 791.98 | V30: 768.63 | W30: 395.39 | X30: 816.73 | Y30: 5791.74 | Z30: 5791.74 | AA30: 6090.94 | AB30: 2421.76
A31: 1 | C31: 단기충당부채 | E31: 221.46 | F31: 221.46 | G31: 199.47 | H31: 198.44 | I31: 1682.99 | J31: 1696.88 | K31: 1696.88 | L31: 1532.68 | M31: 1573.66 | N31: 1605.79 | O31: 1584 | P31: 1584 | Q31: 1492.11 | R31: 3659.61 | S31: 3712.34 | T31: 1610.17 | U31: 1610.17 | V31: 1433.01 | W31: 1501.87 | X31: 1525.84 | Y31: 1543.17 | Z31: 1543.17 | AA31: 1603.14 | AB31: 1487.59
A32: 1 | C32: 유동리스부채 | E32: 53.34 | F32: 53.34 | G32: 53.51 | H32: 53.69 | I32: 53.87 | J32: 65.16 | K32: 65.16 | L32: 60.42 | M32: 47.02 | N32: 33.57 | O32: 20.09 | P32: 20.09 | Q32: 39.56 | R32: 39.97 | S32: 40.39 | T32: 38.48 | U32: 38.48 | V32: 35.89 | W32: 33.28 | X32: 41.2 | Y32: 39.38 | Z32: 39.38 | AA32: 31.73 | AB32: 40.67
A33: 1 | C33: 리스부채 | E33: 116 | F33: 116 | G33: 102.73 | H33: 89.42 | I33: 76.07 | J33: 94.75 | K33: 94.75 | L33: 78.56 | M33: 62.3 | N33: 45.97 | O33: 29.59 | P33: 29.59 | Q33: 100.92 | R33: 91.18 | S33: 81.34 | T33: 71.4 | U33: 71.4 | V33: 61.35 | W33: 51.21 | X33: 52.14 | Y33: 41.97 | Z33: 41.97 | AA33: 31.73 | AB33: 70.61
A34: 1 | C34: 당기법인세부채(미지급법인세) | E34: 21.25 | F34: 21.25 | G34: 38.46 | H34: 27.55 | I34: 0 | J34: 0 | K34: 0 | L34: 119.59 | M34: 392.51 | N34: 777.75 | O34: 0 | P34: 0 | Q34: 199.25 | R34: 904.73 | S34: 1524.7 | T34: 80.73 | U34: 80.73 | V34: 145.58 | W34: 337.46 | X34: 561.35 | Y34: 2475.37 | Z34: 2475.37 | AA34: 2841.42 | AB34: 558.86
A35: 1 | C35: 기타유동부채 | E35: 2269.04 | F35: 2269.04 | G35: 4573.57 | H35: 5450.34 | I35: 2430.03 | J35: 1621.85 | K35: 1621.85 | L35: 2022.18 | M35: 1976.53 | N35: 2463.79 | O35: 4318.26 | P35: 4318.26 | Q35: 8854.07 | R35: 6676.89 | S35: 7987.51 | T35: 7054.12 | U35: 7054.12 | V35: 10952.89 | W35: 11164.15 | X35: 10184.92 | Y35: 9976.45 | Z35: 9976.45 | AA35: 14907.99 | AB35: 17863.87
A36: 1 | C36: 비유동부채 | E36: 1903.13 | F36: 1903.13 | G36: 1939.19 | H36: 2598.06 | I36: 1272.26 | J36: 850.62 | K36: 850.62 | L36: 844.24 | M36: 1465.51 | N36: 1608.33 | O36: 873.98 | P36: 873.98 | Q36: 942.47 | R36: 449.07 | S36: 455.26 | T36: 393.33 | U36: 393.33 | V36: 1399.19 | W36: 2406.46 | X36: 2413.78 | Y36: 17614.19 | Z36: 17614.19 | AA36: 17844.37 | AB36: 18191.78
A37: 1 | C37: 장기매입채무및기타채무 | E37: 169.89 | F37: 169.89 | G37: 174.46 | H37: 178.72 | I37: 183.59 | J37: 193.63 | K37: 193.63 | L37: 199.71 | M37: 205.58 | N37: 192.26 | O37: 225.08 | P37: 225.08 | Q37: 232.72 | R37: 240.46 | S37: 247.91 | T37: 187.02 | U37: 187.02 | V37: 192.33 | W37: 198.14 | X37: 203.45 | Y37: 192.8 | Z37: 192.8 | AA37: 198.67 | AB37: 203.74
A38: 1 | C38: 장기차입금 | E38: 1537.18 | F38: 1537.18 | G38: 1533.8 | H38: 2030.42 | I38: 527.04 | J38: 500 | K38: 500 | L38: 500 | M38: 500 | N38: 500 | O38: 500 | P38: 500 | Q38: 500 | R38: 0 | S38: 0 | T38: 0 | U38: 0 | V38: 1000 | W38: 2000 | X38: 2000 | Y38: 7000 | Z38: 7000 | AA38: 7000 | AB38: 6000
A39: 1 | C39: 확정급여부채 | E39: 0 | F39: 0 | G39: 75.32 | H39: 240.79 | I39: 424.04 | J39: 0 | K39: 0 | M39: 609.25 | N39: 773.27 | O39: 0 | P39: 0
A40: 1 | C40: 비유동리스부채 | E40: 62.66 | F40: 62.66 | G40: 49.22 | H40: 35.73 | I40: 22.2 | J40: 29.59 | K40: 29.59 | L40: 18.14 | M40: 15.28 | N40: 12.4 | O40: 9.5 | P40: 9.5 | Q40: 61.36 | R40: 51.21 | S40: 40.95 | T40: 32.92 | U40: 32.92 | V40: 25.46 | W40: 17.93 | X40: 10.94 | Y40: 2.59 | Z40: 2.59 | AA40: 0 | AB40: 29.94
A41: 1 | C41: 장기금융부채 | E41: 62.66 | F41: 62.66 | G41: 49.22 | H41: 35.73 | I41: 22.2 | J41: 29.59 | K41: 29.59 | L41: 18.14 | M41: 15.28 | N41: 12.4 | O41: 9.5 | P41: 9.5 | Q41: 61.36 | R41: 51.21 | S41: 40.95 | T41: 32.92 | U41: 32.92 | V41: 25.46 | W41: 17.93 | X41: 10.94 | Y41: 2635.36 | Z41: 2635.36 | AA41: 2632.77 | AB41: 3705.36
A42: 1 | C42: 이연법인세부채 | E42: 0 | F42: 0 | G42: 0 | I42: 0 | J42: 0 | K42: 0 | N42: 0 | O42: 0 | P42: 0 | T42: 0 | U42: 0
A43: 1 | C43: 기타비유동부채 | E43: 133.4 | F43: 133.4 | G43: 106.4 | H43: 112.4 | I43: 115.4 | J43: 127.4 | K43: 127.4 | L43: 126.4 | M43: 135.4 | N43: 130.4 | O43: 139.4 | P43: 139.4 | Q43: 148.4 | R43: 157.4 | S43: 166.4 | T43: 173.4 | U43: 173.4 | V43: 181.4 | W43: 190.4 | X43: 199.4 | Y43: 198.4 | Z43: 198.4 | AA43: 167.4 | AB43: 176.4
A44: 1 | C44: 부채총계 | E44: 31559.13 | F44: 31559.13 | G44: 34590.62 | H44: 34981.25 | I44: 33912.67 | J44: 32578.32 | K44: 32578.32 | L44: 32911.75 | M44: 34399.41 | N44: 34908.04 | O44: 36500.41 | P44: 36500.41 | Q44: 38245.16 | R44: 30195.92 | S44: 35331.33 | T44: 32514.01 | U44: 32514.01 | V44: 44155.69 | W44: 34290.57 | X44: 55885.62 | Y44: 96582.64 | Z44: 96582.64 | AA44: 106136.28 | AB44: 107366.66
A45: 1 | C45: 자본금 | E45: 7513.15 | F45: 7513.15 | G45: 7513.15 | H45: 7513.15 | I45: 7513.15 | J45: 7513.15 | K45: 7513.15 | L45: 7513.15 | M45: 7513.15 | N45: 7513.15 | O45: 7513.15 | P45: 7513.15 | Q45: 7513.15 | R45: 7513.15 | S45: 7513.15 | T45: 7513.15 | U45: 7513.15 | V45: 7513.15 | W45: 7513.15 | X45: 7513.15 | Y45: 7513.15 | Z45: 7513.15 | AA45: 7513.15 | AB45: 7513.15
A46: 1 | C46: 보통주자본금 | E46: 7513.15 | F46: 7513.15 | G46: 7513.15 | H46: 7513.15 | I46: 7513.15 | J46: 7513.15 | K46: 7513.15 | L46: 7513.15 | M46: 7513.15 | N46: 7513.15 | O46: 7513.15 | P46: 7513.15 | Q46: 7513.15 | R46: 7513.15 | S46: 7513.15 | T46: 7513.15 | U46: 7513.15 | V46: 7513.15 | W46: 7513.15 | X46: 7513.15 | Y46: 7513.15 | Z46: 7513.15 | AA46: 7513.15 | AB46: 7513.15
A47: 1 | C47: 자본잉여금 | E47: 18151.65 | F47: 18151.65 | G47: 18151.65 | H47: 18151.65 | I47: 18151.65 | J47: 18151.65 | K47: 18151.65 | L47: 18151.65 | M47: 18151.65 | N47: 18151.65 | O47: 18151.65 | P47: 18151.65 | Q47: 18151.65 | R47: 18151.65 | S47: 18151.65 | T47: 18151.65 | U47: 18151.65 | V47: 18151.65 | W47: 18151.65 | X47: 18151.65 | Y47: 24705.43 | Z47: 24705.43 | AA47: 24705.43 | AB47: 24705.43
A48: 1 | C48: 기타자본 | E48: -1072.81 | F48: -1072.81 | G48: -1072.81 | H48: -1072.81 | I48: -1072.81 | J48: -1072.81 | K48: -1072.81 | L48: -1072.81 | M48: -1072.81 | N48: -1072.81 | O48: -1072.81 | P48: -1072.81 | Q48: -1072.81 | R48: -1072.81 | S48: -1072.81 | T48: -1072.81 | U48: -1072.81 | V48: -1072.81 | W48: -1072.81 | X48: -1072.81 | Y48: 3379.7 | Z48: 3379.7 | AA48: 3379.7 | AB48: 3379.7
A49: 1 | C49: 기타포괄이익누계액 | E49: 0 | F49: 0 | G49: 0 | H49: 0 | J49: 0 | K49: 0 | M49: 0 | O49: 0 | P49: 0 | T49: 0 | U49: 0
A50: 1 | C50: 이익잉여금 | E50: 49824.14 | F50: 49824.14 | G50: 48690.82 | H50: 46076.45 | I50: 44078.21 | J50: 37628.32 | K50: 37628.32 | L50: 38468.8 | M50: 39385.94 | N50: 39935.01 | O50: 40954.48 | P50: 40954.48 | Q50: 40681.65 | R50: 41409.52 | S50: 43776.78 | T50: 44962.62 | U50: 44962.62 | V50: 44622.98 | W50: 46896.77 | X50: 48565.53 | Y50: 49925.13 | Z50: 49925.13 | AA50: 48686.08 | AB50: 50396.51
A51: 1 | C51: 자본총계 | E51: 74416.13 | F51: 74416.13 | G51: 73282.81 | H51: 70668.44 | I51: 68670.2 | J51: 62220.31 | K51: 62220.31 | L51: 63060.79 | M51: 63977.93 | N51: 64527 | O51: 65546.46 | P51: 65546.46 | Q51: 65273.64 | R51: 66001.51 | S51: 68368.76 | T51: 69554.61 | U51: 69554.61 | V51: 69214.97 | W51: 71488.76 | X51: 73157.52 | Y51: 85523.4 | Z51: 85523.4 | AA51: 84284.36 | AB51: 85994.79
A52: 1 | C52: 부채와자본총계 | E52: 105975.26 | F52: 105975.26 | G52: 107873.43 | H52: 105649.69 | I52: 102582.86 | J52: 94798.63 | K52: 94798.63 | L52: 95972.55 | M52: 98377.33 | N52: 99435.04 | O52: 102046.87 | P52: 102046.87 | Q52: 103518.8 | R52: 96197.43 | S52: 103700.1 | T52: 102068.61 | U52: 102068.61 | V52: 113370.66 | W52: 105779.33 | X52: 129043.14 | Y52: 182106.04 | Z52: 182106.04 | AA52: 190420.64 | AB52: 193361.44
A53: 1 | C53: 지배주주지분 | E53: 74416.13 | F53: 74416.13 | G53: 73282.81 | H53: 70668.44 | I53: 68670.2 | J53: 62220.31 | K53: 62220.31 | L53: 63060.79 | M53: 63977.93 | N53: 64527 | O53: 65546.46 | P53: 65546.46 | Q53: 65273.64 | R53: 66001.51 | S53: 68368.76 | T53: 69554.61 | U53: 69554.61 | V53: 69214.97 | W53: 71488.76 | X53: 73157.52 | Y53: 85523.4 | Z53: 85523.4 | AA53: 84284.36 | AB53: 85994.79
A54: 1 | C54: 총차입금 | E54: 22050.7 | F54: 22050.7 | G54: 21547.32 | H54: 22043.94 | I54: 22040.56 | J54: 22000 | K54: 22000 | L54: 22000 | M54: 22000 | N54: 22000 | O54: 22000 | P54: 22000 | Q54: 16000 | R54: 10500 | S54: 13000 | T54: 13000 | U54: 13000 | V54: 20500 | W54: 13500 | X54: 34500 | Y54: 62227.69 | Z54: 62227.69 | AA54: 67351.86 | AB54: 69486.55
A55: 1 | C55: 순차입금 | E55: 51.73 | F55: 51.73 | G55: 3372.73 | H55: 3483.85 | I55: 7076.9 | J55: 952.72 | K55: 952.72 | L55: -1059.3 | M55: 1386.84 | N55: -1957.58 | O55: -931.27 | P55: -931.27 | Q55: -2349.21 | R55: -304.05 | S55: -8451.35 | T55: -6033.95 | U55: -6033.95 | V55: -847.51 | W55: -5886.92 | X55: -10720.52 | Y55: 57049.03 | Z55: 57049.03 | AA55: 59590.45 | AB55: 65206.31
A56: 1 | C56: 이자발생자산 | E56: 34099.83 | F56: 34099.83 | G56: 29900.73 | H56: 28291.38 | I56: 22913.36 | J56: 29121.11 | K56: 29121.11 | L56: 32644.46 | M56: 31008.4 | N56: 33521.76 | O56: 32612.86 | P56: 32612.86 | Q56: 28337.13 | R56: 21882.7 | S56: 32033.87 | T56: 29424.68 | U56: 29424.68 | V56: 37053.77 | W56: 33994.72 | X56: 59888.47 | Y56: 16443.66 | Z56: 16443.66 | AA56: 17597.69 | AB56: 14594.44
A57: 1 | C57: 당기법인세자산(선급법인세) | I57: 74.03 | J57: 74.15 | K57: 74.15 | L57: 74.15 | M57: 0 | N57: 0 | O57: 102.1 | P57: 102.1 | Q57: 102.1 | R57: 0 | S57: 0 | T57: 0 | U57: 0 | Y57: 0 | Z57: 0 | AA57: 0 | AB57: 0
A58: 1 | C58: 단기금융부채(face) | N58: 21500 | O58: 21500 | P58: 21500 | Q58: 15500 | R58: 10000 | S58: 12500 | T58: 12500 | U58: 12500 | V58: 19500 | W58: 11500 | X58: 32500 | Y58: 47640.06 | Z58: 47640.06 | AA58: 52506.33 | AB58: 54380.26
A59: 1 | C59: 장기금융부채(face) | S59: 0 | T59: 0 | U59: 0 | V59: 1000 | W59: 2000 | X59: 2000
A60: 1 | C60: 사채 | Y60: 7587.63 | Z60: 7587.63 | AA60: 7845.53 | AB60: 8106.29
A61: 1 | C61: 장기파생상품부채 | Y61: 2632.77 | Z61: 2632.77 | AA61: 2632.77 | AB61: 3675.42
A62: 1 | C62: 매출액(수익) | E62: 12592.2 | G62: 16351.31 | H62: 18893.8 | I62: 19806.51 | J62: 20133 | K62: 75184.62 | L62: 15853.74 | M62: 19359.46 | N62: 22667.71 | O62: 19221.79 | P62: 77102.7 | Q62: 21966.57 | R62: 28602.2 | S62: 23528.73 | T62: 23289.28 | U62: 97386.78 | V62: 19251.53 | W62: 23767.26 | X62: 23691.57 | Y62: 26246.19 | Z62: 92956.55 | AA62: 28094.81 | AB62: 21552.34
A63: 1 | C63: 매출원가 | E63: 11859.21 | G63: 14896.61 | H63: 18471.73 | I63: 16816.11 | J63: 16990.81 | K63: 67175.26 | L63: 14071.67 | M63: 15952.25 | N63: 18380.82 | O63: 16609.85 | P63: 65014.59 | Q63: 16680.64 | R63: 23000.81 | S63: 19280.15 | T63: 18491.12 | U63: 77452.72 | V63: 15316.89 | W63: 19379.88 | X63: 18967.33 | Y63: 21752.48 | Z63: 75416.58 | AA63: 23407.98 | AB63: 17844.5
A64: 1 | C64: 매출총이익 | E64: 732.99 | G64: 1454.7 | H64: 422.07 | I64: 2990.4 | J64: 3142.19 | K64: 8009.36 | L64: 1782.07 | M64: 3407.21 | N64: 4286.89 | O64: 2611.93 | P64: 12088.1 | Q64: 5285.93 | R64: 5601.39 | S64: 4248.58 | T64: 4798.16 | U64: 19934.06 | V64: 3934.64 | W64: 4387.38 | X64: 4724.24 | Y64: 4493.71 | Z64: 17539.97 | AA64: 4686.84 | AB64: 3707.84
A65: 1 | C65: 판관비 | E65: 1774.25 | G65: 1824.95 | H65: 1663.45 | I65: 6846.78 | J65: 1893.62 | K65: 12228.8 | L65: 1717.5 | M65: 2427.28 | N65: 2195.93 | O65: 2016.14 | P65: 8356.85 | Q65: 3129.66 | R65: 4308.96 | S65: 2025.76 | T65: 1717.93 | U65: 11182.31 | V65: 2342.36 | W65: 2320.1 | X65: 2296.21 | Y65: 2882.12 | Z65: 9840.79 | AA65: 2031.98 | AB65: 1890.16
A66: 1 | C66: 영업이익 | E66: -1041.26 | G66: -370.25 | H66: -1241.38 | I66: -3856.38 | J66: 1248.57 | K66: -4219.44 | L66: 64.56 | M66: 979.93 | N66: 2090.97 | O66: 595.79 | P66: 3731.25 | Q66: 2156.27 | R66: 1292.43 | S66: 2222.81 | T66: 3080.22 | U66: 8751.73 | V66: 1592.28 | W66: 2067.28 | X66: 2428.02 | Y66: 1611.59 | Z66: 7699.17 | AA66: 2654.85 | AB66: 1817.68
A67: 1 | C67: 기타영업외수익 | E67: 381.27 | G67: 220.68 | H67: 376.55 | I67: 146.65 | J67: 350.51 | K67: 1094.39 | L67: 219.66 | M67: 317.24 | N67: 105.14 | O67: 368.43 | P67: 1010.47 | Q67: 162.32 | R67: 446.14 | S67: 107.82 | T67: 447.81 | U67: 1164.09 | V67: 167 | W67: 428.11 | X67: 220.84 | Y67: 490.11 | Z67: 1306.06 | AA67: 501.61 | AB67: 659.06
A68: 1 | C68: 기타영업외비용 | E68: 12700.99 | G68: 8.63 | H68: 8.63 | I68: 8.63 | J68: 7069.43 | K68: 7095.32 | L68: 8.64 | M68: 9.6 | N68: 8.63 | O68: 10.63 | P68: 37.5 | Q68: 58.63 | R68: 8.63 | S68: 9.18 | T68: 134.06 | U68: 210.5 | V68: 21.01 | W68: 9.53 | X68: 69.17 | Y68: 25.63 | Z68: 125.34 | AA68: 142.64 | AB68: 8.63
A69: 1 | C69: 금융수익 | E69: -460.43 | G69: 470.77 | H69: 593.55 | I69: 970.82 | J69: -139.84 | K69: 1895.3 | L69: 2135.08 | M69: 287.73 | N69: -825.6 | O69: 581.06 | P69: 2178.27 | Q69: 373.47 | R69: 372.97 | S69: 477.13 | T69: 375.88 | U69: 1599.45 | V69: 819.7 | W69: 603.89 | X69: 358.14 | Y69: 663.1 | Z69: 2444.83 | AA69: 313.24 | AB69: 3539.2
A70: 1 | C70: 금융비용 | E70: 107.23 | G70: 664.93 | H70: 3079.02 | I70: 459.01 | J70: 764.4 | K70: 4967.36 | L70: 565.01 | M70: 429.29 | N70: 657.4 | O70: 417.44 | P70: 2069.14 | Q70: 1444.85 | R70: 1201.53 | S70: 40.06 | T70: 2280.94 | U70: 4967.38 | V70: 579.29 | W70: 121.91 | X70: 757.05 | Y70: 2195.51 | Z70: 3653.76 | AA70: 2144.94 | AB70: 3855.61
A71: 1 | C71: 법인세비용차감전계속사업이익 | E71: -13928.62 | G71: -352.36 | H71: -3358.92 | I71: -3206.56 | J71: -6374.58 | K71: -13292.42 | L71: 1845.66 | M71: 1146.01 | N71: 704.47 | O71: 1117.22 | P71: 4813.36 | Q71: 1188.59 | R71: 901.38 | S71: 2758.51 | T71: 1488.91 | U71: 6337.39 | V71: 1978.68 | W71: 2967.84 | X71: 2180.79 | Y71: 543.66 | Z71: 7670.97 | AA71: 1182.12 | AB71: 2151.7
A72: 1 | C72: 법인세비용 | E72: -721.72 | G72: -68.15 | H72: -744.55 | I72: -1208.32 | J72: 159.78 | K72: -1861.24 | L72: 398.67 | M72: 228.87 | N72: 155.39 | O72: -511.49 | P72: 271.44 | Q72: 248.42 | R72: 173.51 | S72: 391.26 | T72: 86.41 | U72: 899.6 | V72: 498.83 | W72: 694.04 | X72: 512.03 | Y72: -762.78 | Z72: 942.12 | AA72: 276.16 | AB72: 441.27
A73: 1 | C73: 당기순이익 | E73: -13206.9 | G73: -284.22 | H73: -2614.37 | I73: -1998.24 | J73: -6534.36 | K73: -11431.19 | L73: 1446.99 | M73: 917.13 | N73: 549.08 | O73: 1628.7 | P73: 4541.9 | Q73: 940.17 | R73: 727.87 | S73: 2367.26 | T73: 1402.5 | U73: 5437.8 | V73: 1479.86 | W73: 2273.8 | X73: 1668.76 | Y73: 1306.44 | Z73: 6728.86 | AA73: 905.96 | AB73: 1710.43
... A83: 1 | C83: 재무활동으로인한현금흐름 | E83: 2982.4 | G83: -516.65 | H83: -365.79 | I83: -16.74 | J83: -56.01 | K83: -955.19 | L83: -16.19 | M83: -622.76 | N83: -16.32 | O83: -16.39 | P83: -671.66 | Q83: -6014.37 | R83: -6722.73 | S83: 2490.16 | T83: -9.94 | U83: -10256.88 | V83: 7489.96 | W83: -8829.65 | X83: 20989.74 | Y83: 46566.12 | Z83: 66216.17 | AA83: 4856.04 | AB83: -290.86
A84: 1 | C84: 단기차입금의증가 | E84: 3000 | G84: 0 | H84: 0 | I84: 0 | J84: 0 | K84: 0 | L84: 0 | Q84: 0 | R84: 0 | S84: 2500 | T84: 0 | U84: 2500 | V84: 9000 | W84: 1500 | X84: 21000 | Y84: 23140.06 | Z84: 54640.06 | AA84: 16796.96 | AB84: 17789.68
A85: 1 | C85: 장기차입금의증가 | E85: 0 | I85: 0 | J85: 0 | N85: 0 | O85: 0 | V85: 1000 | W85: 1000 | X85: 0 | Y85: 5000 | Z85: 7000 | AA85: 0 | AB85: 0
A86: 1 | C86: 단기차입금의감소 | E86: 0 | Q86: 6000 | R86: 5500 | S86: 0 | T86: 0 | U86: 11500 | V86: 2000 | W86: 9500 | X86: 0 | Y86: 8000 | Z86: 19500 | AA86: 11930.68 | AB86: 15915.76
A87: 1 | C87: 장기차입금의감소 | E87: 3.38 | G87: 503.38 | H87: 3.38 | I87: 3.38 | J87: 40.56 | K87: 550.7 | L87: 0 | M87: 0 | N87: 0 | O87: 0 | P87: 0 | Q87: 0 | R87: 0 | AA87: 0 | AB87: 0
A88: 1 | C88: 배당금지급 | E88: 0 | I88: 0 | J88: 0 | N88: 0 | O88: 0 | S88: 0 | T88: 0 | X88: 0 | Y88: 0 | AA88: 0 | AB88: 2145
A89: 1 | C89: 자기주식의취득 | E89: 0 | J89: 0
A90: 1 | C90: 현금및현금성자산의증감 | E90: 797.3 | G90: 734.49 | H90: 430.63 | I90: -2684.29 | J90: 723.84 | K90: -795.33 | L90: 1048.85 | M90: -1958.53 | N90: 1457.01 | O90: -2077.16 | P90: -1529.83 | Q90: -1518.76 | R90: 3470.88 | S90: -3256.91 | T90: 1907.92 | U90: 603.13 | V90: -1652.76 | W90: 3163.19 | X90: 13247.76 | Y90: -16586.43 | Z90: -1828.24 | AA90: 1989.25 | AB90: -1620.35
A91: 1 | C91: 기말현금및현금성자산 | E91: 711.26 | G91: 6718.53 | H91: 430.46 | I91: -2560.45 | J91: 634.91 | K91: 5223.45 | L91: 6270.1 | M91: -1978.01 | N91: 1444.84 | O91: -2046.03 | P91: 3690.9 | Q91: 2165.35 | R91: 3451.97 | S91: -3231.36 | T91: 1910.83 | U91: 4296.79 | V91: 2646.74 | W91: 3157.74 | X91: 13260.41 | Y91: -16599.01 | Z91: 2465.88 | AA91: 4469.18 | AB91: -1634.27
A92: 1 | C92: 이자수취(CF) | O92: 271.34 | Q92: 335.78 | R92: 254.83 | S92: 228.65 | T92: 292.36 | U92: 1111.62 | V92: 215.73 | W92: 334.68 | X92: 208.93 | Y92: 455.15 | Z92: 1214.49 | AA92: 99.37 | AB92: 94.33
A93: 1 | C93: 무형자산의감소 | S93: 0 | T93: 0 | X93: 0 | Y93: 0 | AA93: 0 | AB93: 237.27
A94: 1 | C94: 무형자산의증가 | V94: 1.73 | W94: 23.14 | X94: 5.64
A95: 1 | C95: CAPEX | V95: 1.73 | W95: 23.14 | X95: 5.64
A96: 1 | C96: 차입금의감소 | V96: 500 | W96: 0 | X96: 0

Sheet subQ
A1: YQ | C1: subQ 분기 서브모델(억원, U=100) | E1: 4Q21 | F1: 2021 | G1: 1Q22 | H1: 2Q22 | I1: 3Q22 | J1: 4Q22 | K1: 2022 | L1: 1Q23 | M1: 2Q23 | N1: 3Q23 | O1: 4Q23 | P1: 2023 | Q1: 1Q24 | R1: 2Q24 | S1: 3Q24 | T1: 4Q24 | U1: 2024 | V1: 1Q25 | W1: 2Q25 | X1: 3Q25 | Y1: 4Q25 | Z1: 2025 | AA1: 1Q26 | AB1: 2Q26 | AC1: 3Q26 | AD1: 4Q26 | AE1: 2026 | AF1: 1Q27 | AG1: 2Q27 | AH1: 3Q27 | AI1: 4Q27 | AJ1: 2027 | AK1: 1Q28 | AL1: 2Q28 | AM1: 3Q28 | AN1: 4Q28 | AO1: 2028
A2: A=이름(key) B=그룹 C=단위 D=FnGuide 계정명(VLOOKUP 키). 확정=VLOOKUP(BS), 추정=변수 가정 참조
E3: 1 | F3: 2 | G3: 3 | H3: 4 | I3: 5 | J3: 6 | K3: 7 | L3: 8 | M3: 9 | N3: 10 | O3: 11 | P3: 12 | Q3: 13 | R3: 14 | S3: 15 | T3: 16 | U3: 17 | V3: 18 | W3: 19 | X3: 20 | Y3: 21 | Z3: 22 | AA3: 23 | AB3: 24 | AC3: 25 | AD3: 26 | AE3: 27 | AF3: 28 | AG3: 29 | AH3: 30 | AI3: 31 | AJ3: 32 | AK3: 33 | AL3: 34 | AM3: 35 | AN3: 36 | AO3: 37
E4: 2021.12 | F4: 2021.12A | G4: 2022.03 | H4: 2022.06 | I4: 2022.09 | J4: 2022.12 | K4: 2022.12A | L4: 2023.03 | M4: 2023.06 | N4: 2023.09 | O4: 2023.12 | P4: 2023.12A | Q4: 2024.03 | R4: 2024.06 | S4: 2024.09 | T4: 2024.12 | U4: 2024.12A | V4: 2025.03 | W4: 2025.06 | X4: 2025.09 | Y4: 2025.12 | Z4: 2025.12A | AA4: 2026.03 | AB4: 2026.06 | AC4: 2026.09 | AD4: 2026.12 | AE4: 2026.12A | AF4: 2027.03 | AG4: 2027.06 | AH4: 2027.09 | AI4: 2027.12 | AJ4: 2027.12A | AK4: 2028.03 | AL4: 2028.06 | AM4: 2028.09 | AN4: 2028.12 | AO4: 2028.12A
A5: 매출액 | B5: 손익 | C5: 억원 | D5: 매출액(수익) | E5: =IFERROR(VLOOKUP($D5,BS연결,MATCH(E$1,BS연결H,0),0)/100,"") | G5: =IFERROR(VLOOKUP($D5,BS연결,MATCH(G$1,BS연결H,0),0)/100,"") | H5: =IFERROR(VLOOKUP($D5,BS연결,MATCH(H$1,BS연결H,0),0)/100,"") | I5: =IFERROR(VLOOKUP($D5,BS연결,MATCH(I$1,BS연결H,0),0)/100,"") | J5: =IFERROR(VLOOKUP($D5,BS연결,MATCH(J$1,BS연결H,0),0)/100,"") | K5: =IFERROR(VLOOKUP($D5,BS연결,MATCH(K$1,BS연결H,0),0)/100,"") | L5: =IFERROR(VLOOKUP($D5,BS연결,MATCH(L$1,BS연결H,0),0)/100,"") | M5: =IFERROR(VLOOKUP($D5,BS연결,MATCH(M$1,BS연결H,0),0)/100,"") | N5: =IFERROR(VLOOKUP($D5,BS연결,MATCH(N$1,BS연결H,0),0)/100,"") | ... AB5: =IFERROR(VLOOKUP($D5,BS연결,MATCH(AB$1,BS연결H,0),0)/100,"") | AC5: =IFERROR(X5*(1+변수!AC21),"") | AD5: =IFERROR(Y5*(1+변수!AD21),"") | AE5: =SUM(AA5:AD5) | AF5: =IFERROR(AA5*(1+변수!AF21),"") | AG5: =IFERROR(AB5*(1+변수!AG21),"") | AH5: =IFERROR(AC5*(1+변수!AH21),"") | AI5: =IFERROR(AD5*(1+변수!AI21),"") | AJ5: =SUM(AF5:AI5) | AK5: =IFERROR(AF5*(1+변수!AK21),"") | AL5: =IFERROR(AG5*(1+변수!AL21),"") | AM5: =IFERROR(AH5*(1+변수!AM21),"") | AN5: =IFERROR(AI5*(1+변수!AN21),"") | AO5: =SUM(AK5:AN5)
A6: 매출원가 | B6: 손익 | C6: 억원 | D6: 매출원가 | E6: =IFERROR(VLOOKUP($D6,BS연결,MATCH(E$1,BS연결H,0),0)/100,"") | G6: =IFERROR(VLOOKUP($D6,BS연결,MATCH(G$1,BS연결H,0),0)/100,"") | H6: =IFERROR(VLOOKUP($D6,BS연결,MATCH(H$1,BS연결H,0),0)/100,"") | I6: =IFERROR(VLOOKUP($D6,BS연결,MATCH(I$1,BS연결H,0),0)/100,"") | J6: =IFERROR(VLOOKUP($D6,BS연결,MATCH(J$1,BS연결H,0),0)/100,"") | K6: =IFERROR(VLOOKUP($D6,BS연결,MATCH(K$1,BS연결H,0),0)/100,"") | L6: =IFERROR(VLOOKUP($D6,BS연결,MATCH(L$1,BS연결H,0),0)/100,"") | M6: =IFERROR(VLOOKUP($D6,BS연결,MATCH(M$1,BS연결H,0),0)/100,"") | N6: =IFERROR(VLOOKUP($D6,BS연결,MATCH(N$1,BS연결H,0),0)/100,"") | ... AB6: =IFERROR(VLOOKUP($D6,BS연결,MATCH(AB$1,BS연결H,0),0)/100,"") | AC6: =IFERROR(AC5-AC7,"") | AD6: =IFERROR(AD5-AD7,"") | AE6: =SUM(AA6:AD6) | AF6: =IFERROR(AF5-AF7,"") | AG6: =IFERROR(AG5-AG7,"") | AH6: =IFERROR(AH5-AH7,"") | AI6: =IFERROR(AI5-AI7,"") | AJ6: =SUM(AF6:AI6) | AK6: =IFERROR(AK5-AK7,"") | AL6: =IFERROR(AL5-AL7,"") | AM6: =IFERROR(AM5-AM7,"") | AN6: =IFERROR(AN5-AN7,"") | AO6: =SUM(AK6:AN6)
A7: 매출총이익 | B7: 손익 | C7: 억원 | D7: 매출총이익 | E7: =IFERROR(VLOOKUP($D7,BS연결,MATCH(E$1,BS연결H,0),0)/100,"") | G7: =IFERROR(VLOOKUP($D7,BS연결,MATCH(G$1,BS연결H,0),0)/100,"") | H7: =IFERROR(VLOOKUP($D7,BS연결,MATCH(H$1,BS연결H,0),0)/100,"") | I7: =IFERROR(VLOOKUP($D7,BS연결,MATCH(I$1,BS연결H,0),0)/100,"") | J7: =IFERROR(VLOOKUP($D7,BS연결,MATCH(J$1,BS연결H,0),0)/100,"") | K7: =IFERROR(VLOOKUP($D7,BS연결,MATCH(K$1,BS연결H,0),0)/100,"") | L7: =IFERROR(VLOOKUP($D7,BS연결,MATCH(L$1,BS연결H,0),0)/100,"") | M7: =IFERROR(VLOOKUP($D7,BS연결,MATCH(M$1,BS연결H,0),0)/100,"") | N7: =IFERROR(VLOOKUP($D7,BS연결,MATCH(N$1,BS연결H,0),0)/100,"") | ... AB7: =IFERROR(VLOOKUP($D7,BS연결,MATCH(AB$1,BS연결H,0),0)/100,"") | AC7: =IFERROR(AC9+AC8,"") | AD7: =IFERROR(AD9+AD8,"") | AE7: =SUM(AA7:AD7) | AF7: =IFERROR(AF9+AF8,"") | AG7: =IFERROR(AG9+AG8,"") | AH7: =IFERROR(AH9+AH8,"") | AI7: =IFERROR(AI9+AI8,"") | AJ7: =SUM(AF7:AI7) | AK7: =IFERROR(AK9+AK8,"") | AL7: =IFERROR(AL9+AL8,"") | AM7: =IFERROR(AM9+AM8,"") | AN7: =IFERROR(AN9+AN8,"") | AO7: =SUM(AK7:AN7)
A8: 판관비 | B8: 손익 | C8: 억원 | D8: 판관비 | E8: =IFERROR(VLOOKUP($D8,BS연결,MATCH(E$1,BS연결H,0),0)/100,"") | G8: =IFERROR(VLOOKUP($D8,BS연결,MATCH(G$1,BS연결H,0),0)/100,"") | H8: =IFERROR(VLOOKUP($D8,BS연결,MATCH(H$1,BS연결H,0),0)/100,"") | I8: =IFERROR(VLOOKUP($D8,BS연결,MATCH(I$1,BS연결H,0),0)/100,"") | J8: =IFERROR(VLOOKUP($D8,BS연결,MATCH(J$1,BS연결H,0),0)/100,"") | K8: =IFERROR(VLOOKUP($D8,BS연결,MATCH(K$1,BS연결H,0),0)/100,"") | L8: =IFERROR(VLOOKUP($D8,BS연결,MATCH(L$1,BS연결H,0),0)/100,"") | M8: =IFERROR(VLOOKUP($D8,BS연결,MATCH(M$1,BS연결H,0),0)/100,"") | N8: =IFERROR(VLOOKUP($D8,BS연결,MATCH(N$1,BS연결H,0),0)/100,"") | ... AB8: =IFERROR(VLOOKUP($D8,BS연결,MATCH(AB$1,BS연결H,0),0)/100,"") | AC8: =IFERROR(AC5*변수!AC22,"") | AD8: =IFERROR(AD5*변수!AD22,"") | AE8: =SUM(AA8:AD8) | AF8: =IFERROR(AF5*변수!AF22,"") | AG8: =IFERROR(AG5*변수!AG22,"") | AH8: =IFERROR(AH5*변수!AH22,"") | AI8: =IFERROR(AI5*변수!AI22,"") | AJ8: =SUM(AF8:AI8) | AK8: =IFERROR(AK5*변수!AK22,"") | AL8: =IFERROR(AL5*변수!AL22,"") | AM8: =IFERROR(AM5*변수!AM22,"") | AN8: =IFERROR(AN5*변수!AN22,"") | AO8: =SUM(AK8:AN8)
A9: 영업이익 | B9: 손익 | C9: 억원 | D9: 영업이익 | E9: =IFERROR(VLOOKUP($D9,BS연결,MATCH(E$1,BS연결H,0),0)/100,"") | G9: =IFERROR(VLOOKUP($D9,BS연결,MATCH(G$1,BS연결H,0),0)/100,"") | H9: =IFERROR(VLOOKUP($D9,BS연결,MATCH(H$1,BS연결H,0),0)/100,"") | I9: =IFERROR(VLOOKUP($D9,BS연결,MATCH(I$1,BS연결H,0),0)/100,"") | J9: =IFERROR(VLOOKUP($D9,BS연결,MATCH(J$1,BS연결H,0),0)/100,"") | K9: =IFERROR(VLOOKUP($D9,BS연결,MATCH(K$1,BS연결H,0),0)/100,"") | L9: =IFERROR(VLOOKUP($D9,BS연결,MATCH(L$1,BS연결H,0),0)/100,"") | M9: =IFERROR(VLOOKUP($D9,BS연결,MATCH(M$1,BS연결H,0),0)/100,"") | N9: =IFERROR(VLOOKUP($D9,BS연결,MATCH(N$1,BS연결H,0),0)/100,"") | ... AB9: =IFERROR(VLOOKUP($D9,BS연결,MATCH(AB$1,BS연결H,0),0)/100,"") | AC9: =IFERROR(AC5*변수!AC23,"") | AD9: =IFERROR(AD5*변수!AD23,"") | AE9: =SUM(AA9:AD9) | AF9: =IFERROR(AF5*변수!AF23,"") | AG9: =IFERROR(AG5*변수!AG23,"") | AH9: =IFERROR(AH5*변수!AH23,"") | AI9: =IFERROR(AI5*변수!AI23,"") | AJ9: =SUM(AF9:AI9) | AK9: =IFERROR(AK5*변수!AK23,"") | AL9: =IFERROR(AL5*변수!AL23,"") | AM9: =IFERROR(AM5*변수!AM23,"") | AN9: =IFERROR(AN5*변수!AN23,"") | AO9: =SUM(AK9:AN9)
A10: OPM | B10: 손익 | C10: % | D10: 영업이익률 | E10: =IFERROR(E9/E5,"") | G10: =IFERROR(G9/G5,"") | H10: =IFERROR(H9/H5,"") | I10: =IFERROR(I9/I5,"") | J10: =IFERROR(J9/J5,"") | K10: =IFERROR(K9/K5,"") | L10: =IFERROR(L9/L5,"") | M10: =IFERROR(M9/M5,"") | N10: =IFERROR(N9/N5,"") | ... AO10: =IFERROR(AO9/AO5,"")
A11: 금융손익 | B11: 손익 | C11: 억원 | D11: 금융손익 | E11: =IFERROR(VLOOKUP($D11,BS연결,MATCH(E$1,BS연결H,0),0)/100,"") | G11: =IFERROR(VLOOKUP($D11,BS연결,MATCH(G$1,BS연결H,0),0)/100,"") | H11: =IFERROR(VLOOKUP($D11,BS연결,MATCH(H$1,BS연결H,0),0)/100,"") | I11: =IFERROR(VLOOKUP($D11,BS연결,MATCH(I$1,BS연결H,0),0)/100,"") | J11: =IFERROR(VLOOKUP($D11,BS연결,MATCH(J$1,BS연결H,0),0)/100,"") | K11: =SUM(G11:J11) | L11: =IFERROR(VLOOKUP($D11,BS연결,MATCH(L$1,BS연결H,0),0)/100,"") | M11: =IFERROR(VLOOKUP($D11,BS연결,MATCH(M$1,BS연결H,0),0)/100,"") | N11: =IFERROR(VLOOKUP($D11,BS연결,MATCH(N$1,BS연결H,0),0)/100,"") | O11: =IFERROR(VLOOKUP($D11,BS연결,MATCH(O$1,BS연결H,0),0)/100,"") | P11: =IFERROR(VLOOKUP($D11,BS연결,MATCH(P$1,BS연결H,0),0)/100,"") | Q11: =IFERROR(VLOOKUP($D11,BS연결,MATCH(Q$1,BS연결H,0),0)/100,"") | R11: =IFERROR(VLOOKUP($D11,BS연결,MATCH(R$1,BS연결H,0),0)/100,"") | S11: =IFERROR(VLOOKUP($D11,BS연결,MATCH(S$1,BS연결H,0),0)/100,"") | ... AB11: =IFERROR(VLOOKUP($D11,BS연결,MATCH(AB$1,BS연결H,0),0)/100,"") | AC11: =IFERROR(AC12+AC13+AC14+AC15,"") | AD11: =IFERROR(AD12+AD13+AD14+AD15,"") | AE11: =SUM(AA11:AD11) | AF11: =IFERROR(AF12+AF13+AF14+AF15,"") | AG11: =IFERROR(AG12+AG13+AG14+AG15,"") | AH11: =IFERROR(AH12+AH13+AH14+AH15,"") | AI11: =IFERROR(AI12+AI13+AI14+AI15,"") | AJ11: =SUM(AF11:AI11) | AK11: =IFERROR(AK12+AK13+AK14+AK15,"") | AL11: =IFERROR(AL12+AL13+AL14+AL15,"") | AM11: =IFERROR(AM12+AM13+AM14+AM15,"") | AN11: =IFERROR(AN12+AN13+AN14+AN15,"") | AO11: =SUM(AK11:AN11)
A12: 이자손익 | B12: 손익 | C12: 억원 | D12: 이자손익 | G12: =IFERROR(VLOOKUP($D12,BS연결,MATCH(G$1,BS연결H,0),0)/100,"") | H12: =IFERROR(VLOOKUP($D12,BS연결,MATCH(H$1,BS연결H,0),0)/100,"") | I12: =IFERROR(VLOOKUP($D12,BS연결,MATCH(I$1,BS연결H,0),0)/100,"") | J12: =IFERROR(VLOOKUP($D12,BS연결,MATCH(J$1,BS연결H,0),0)/100,"") | K12: =IFERROR(VLOOKUP($D12,BS연결,MATCH(K$1,BS연결H,0),0)/100,"") | L12: =IFERROR(VLOOKUP($D12,BS연결,MATCH(L$1,BS연결H,0),0)/100,"") | M12: =IFERROR(VLOOKUP($D12,BS연결,MATCH(M$1,BS연결H,0),0)/100,"") | N12: =IFERROR(VLOOKUP($D12,BS연결,MATCH(N$1,BS연결H,0),0)/100,"") | ... AB12: =IFERROR(VLOOKUP($D12,BS연결,MATCH(AB$1,BS연결H,0),0)/100,"") | AC12: =IFERROR((AB27*변수!$D$53-AB25*변수!$D$54)/4,"") | AD12: =IFERROR((AC27*변수!$D$53-AC25*변수!$D$54)/4,"") | AE12: =SUM(AA12:AD12) | AF12: =IFERROR((AD27*변수!$D$53-AD25*변수!$D$54)/4,"") | AG12: =IFERROR((AF27*변수!$D$53-AF25*변수!$D$54)/4,"") | AH12: =IFERROR((AG27*변수!$D$53-AG25*변수!$D$54)/4,"") | AI12: =IFERROR((AH27*변수!$D$53-AH25*변수!$D$54)/4,"") | AJ12: =SUM(AF12:AI12) | AK12: =IFERROR((AI27*변수!$D$53-AI25*변수!$D$54)/4,"") | AL12: =IFERROR((AK27*변수!$D$53-AK25*변수!$D$54)/4,"") | AM12: =IFERROR((AL27*변수!$D$53-AL25*변수!$D$54)/4,"") | AN12: =IFERROR((AM27*변수!$D$53-AM25*변수!$D$54)/4,"") | AO12: =SUM(AK12:AN12)
A13: 외환손익 | B13: 손익 | C13: 억원 | D13: 외환손익(실적만; 추정 환효과는 환관련손익) | G13: =IFERROR((VLOOKUP("외환차익",BS연결,MATCH(G$1,BS연결H,0),0)-VLOOKUP("외환차손",BS연결,MATCH(G$1,BS연결H,0),0)+VLOOKUP("외화환산이익",BS연결,MATCH(G$1,BS연결H,0),0)-VLOOKUP("외화환산손실",BS연결,MATCH(G$1,BS연결H,0),0))/100,"") | H13: =IFERROR((VLOOKUP("외환차익",BS연결,MATCH(H$1,BS연결H,0),0)-VLOOKUP("외환차손",BS연결,MATCH(H$1,BS연결H,0),0)+VLOOKUP("외화환산이익",BS연결,MATCH(H$1,BS연결H,0),0)-VLOOKUP("외화환산손실",BS연결,MATCH(H$1,BS연결H,0),0))/100,"") | I13: =IFERROR((VLOOKUP("외환차익",BS연결,MATCH(I$1,BS연결H,0),0)-VLOOKUP("외환차손",BS연결,MATCH(I$1,BS연결H,0),0)+VLOOKUP("외화환산이익",BS연결,MATCH(I$1,BS연결H,0),0)-VLOOKUP("외화환산손실",BS연결,MATCH(I$1,BS연결H,0),0))/100,"") | J13: =IFERROR((VLOOKUP("외환차익",BS연결,MATCH(J$1,BS연결H,0),0)-VLOOKUP("외환차손",BS연결,MATCH(J$1,BS연결H,0),0)+VLOOKUP("외화환산이익",BS연결,MATCH(J$1,BS연결H,0),0)-VLOOKUP("외화환산손실",BS연결,MATCH(J$1,BS연결H,0),0))/100,"") | K13: =SUM(G13:J13) | L13: =IFERROR((VLOOKUP("외환차익",BS연결,MATCH(L$1,BS연결H,0),0)-VLOOKUP("외환차손",BS연결,MATCH(L$1,BS연결H,0),0)+VLOOKUP("외화환산이익",BS연결,MATCH(L$1,BS연결H,0),0)-VLOOKUP("외화환산손실",BS연결,MATCH(L$1,BS연결H,0),0))/100,"") | M13: =IFERROR((VLOOKUP("외환차익",BS연결,MATCH(M$1,BS연결H,0),0)-VLOOKUP("외환차손",BS연결,MATCH(M$1,BS연결H,0),0)+VLOOKUP("외화환산이익",BS연결,MATCH(M$1,BS연결H,0),0)-VLOOKUP("외화환산손실",BS연결,MATCH(M$1,BS연결H,0),0))/100,"") | N13: =IFERROR((VLOOKUP("외환차익",BS연결,MATCH(N$1,BS연결H,0),0)-VLOOKUP("외환차손",BS연결,MATCH(N$1,BS연결H,0),0)+VLOOKUP("외화환산이익",BS연결,MATCH(N$1,BS연결H,0),0)-VLOOKUP("외화환산손실",BS연결,MATCH(N$1,BS연결H,0),0))/100,"") | O13: =IFERROR((VLOOKUP("외환차익",BS연결,MATCH(O$1,BS연결H,0),0)-VLOOKUP("외환차손",BS연결,MATCH(O$1,BS연결H,0),0)+VLOOKUP("외화환산이익",BS연결,MATCH(O$1,BS연결H,0),0)-VLOOKUP("외화환산손실",BS연결,MATCH(O$1,BS연결H,0),0))/100,"") | P13: =SUM(L13:O13) | Q13: =IFERROR((VLOOKUP("외환차익",BS연결,MATCH(Q$1,BS연결H,0),0)-VLOOKUP("외환차손",BS연결,MATCH(Q$1,BS연결H,0),0)+VLOOKUP("외화환산이익",BS연결,MATCH(Q$1,BS연결H,0),0)-VLOOKUP("외화환산손실",BS연결,MATCH(Q$1,BS연결H,0),0))/100,"") | R13: =IFERROR((VLOOKUP("외환차익",BS연결,MATCH(R$1,BS연결H,0),0)-VLOOKUP("외환차손",BS연결,MATCH(R$1,BS연결H,0),0)+VLOOKUP("외화환산이익",BS연결,MATCH(R$1,BS연결H,0),0)-VLOOKUP("외화환산손실",BS연결,MATCH(R$1,BS연결H,0),0))/100,"") | S13: =IFERROR((VLOOKUP("외환차익",BS연결,MATCH(S$1,BS연결H,0),0)-VLOOKUP("외환차손",BS연결,MATCH(S$1,BS연결H,0),0)+VLOOKUP("외화환산이익",BS연결,MATCH(S$1,BS연결H,0),0)-VLOOKUP("외화환산손실",BS연결,MATCH(S$1,BS연결H,0),0))/100,"") | T13: =IFERROR((VLOOKUP("외환차익",BS연결,MATCH(T$1,BS연결H,0),0)-VLOOKUP("외환차손",BS연결,MATCH(T$1,BS연결H,0),0)+VLOOKUP("외화환산이익",BS연결,MATCH(T$1,BS연결H,0),0)-VLOOKUP("외화환산손실",BS연결,MATCH(T$1,BS연결H,0),0))/100,"") | U13: =SUM(Q13:T13) | V13: =IFERROR((VLOOKUP("외환차익",BS연결,MATCH(V$1,BS연결H,0),0)-VLOOKUP("외환차손",BS연결,MATCH(V$1,BS연결H,0),0)+VLOOKUP("외화환산이익",BS연결,MATCH(V$1,BS연결H,0),0)-VLOOKUP("외화환산손실",BS연결,MATCH(V$1,BS연결H,0),0))/100,"") | W13: =IFERROR((VLOOKUP("외환차익",BS연결,MATCH(W$1,BS연결H,0),0)-VLOOKUP("외환차손",BS연결,MATCH(W$1,BS연결H,0),0)+VLOOKUP("외화환산이익",BS연결,MATCH(W$1,BS연결H,0),0)-VLOOKUP("외화환산손실",BS연결,MATCH(W$1,BS연결H,0),0))/100,"") | X13: =IFERROR((VLOOKUP("외환차익",BS연결,MATCH(X$1,BS연결H,0),0)-VLOOKUP("외환차손",BS연결,MATCH(X$1,BS연결H,0),0)+VLOOKUP("외화환산이익",BS연결,MATCH(X$1,BS연결H,0),0)-VLOOKUP("외화환산손실",BS연결,MATCH(X$1,BS연결H,0),0))/100,"") | Y13: =IFERROR((VLOOKUP("외환차익",BS연결,MATCH(Y$1,BS연결H,0),0)-VLOOKUP("외환차손",BS연결,MATCH(Y$1,BS연결H,0),0)+VLOOKUP("외화환산이익",BS연결,MATCH(Y$1,BS연결H,0),0)-VLOOKUP("외화환산손실",BS연결,MATCH(Y$1,BS연결H,0),0))/100,"") | Z13: =SUM(V13:Y13) | AA13: =IFERROR((VLOOKUP("외환차익",BS연결,MATCH(AA$1,BS연결H,0),0)-VLOOKUP("외환차손",BS연결,MATCH(AA$1,BS연결H,0),0)+VLOOKUP("외화환산이익",BS연결,MATCH(AA$1,BS연결H,0),0)-VLOOKUP("외화환산손실",BS연결,MATCH(AA$1,BS연결H,0),0))/100,"") | AB13: =IFERROR((VLOOKUP("외환차익",BS연결,MATCH(AB$1,BS연결H,0),0)-VLOOKUP("외환차손",BS연결,MATCH(AB$1,BS연결H,0),0)+VLOOKUP("외화환산이익",BS연결,MATCH(AB$1,BS연결H,0),0)-VLOOKUP("외화환산손실",BS연결,MATCH(AB$1,BS연결H,0),0))/100,"") | AC13: =변수!AC24 | AD13: =변수!AD24 | AE13: =SUM(AA13:AD13) | AF13: =변수!AF24 | AG13: =변수!AG24 | AH13: =변수!AH24 | AI13: =변수!AI24 | AJ13: =SUM(AF13:AI13) | AK13: =변수!AK24 | AL13: =변수!AL24 | AM13: =변수!AM24 | AN13: =변수!AN24 | AO13: =SUM(AK13:AN13)
A14: 파생상품손익 | B14: 손익 | C14: 억원 | D14: 파생상품손익 | H14: =IFERROR((VLOOKUP("파생상품이익",BS연결,MATCH(H$1,BS연결H,0),0)-VLOOKUP("파생상품손실",BS연결,MATCH(H$1,BS연결H,0),0))/100,"") | I14: =IFERROR((VLOOKUP("파생상품이익",BS연결,MATCH(I$1,BS연결H,0),0)-VLOOKUP("파생상품손실",BS연결,MATCH(I$1,BS연결H,0),0))/100,"") | J14: =IFERROR((VLOOKUP("파생상품이익",BS연결,MATCH(J$1,BS연결H,0),0)-VLOOKUP("파생상품손실",BS연결,MATCH(J$1,BS연결H,0),0))/100,"") | K14: =SUM(G14:J14) | L14: =IFERROR((VLOOKUP("파생상품이익",BS연결,MATCH(L$1,BS연결H,0),0)-VLOOKUP("파생상품손실",BS연결,MATCH(L$1,BS연결H,0),0))/100,"") | M14: =IFERROR((VLOOKUP("파생상품이익",BS연결,MATCH(M$1,BS연결H,0),0)-VLOOKUP("파생상품손실",BS연결,MATCH(M$1,BS연결H,0),0))/100,"") | N14: =IFERROR((VLOOKUP("파생상품이익",BS연결,MATCH(N$1,BS연결H,0),0)-VLOOKUP("파생상품손실",BS연결,MATCH(N$1,BS연결H,0),0))/100,"") | O14: =IFERROR((VLOOKUP("파생상품이익",BS연결,MATCH(O$1,BS연결H,0),0)-VLOOKUP("파생상품손실",BS연결,MATCH(O$1,BS연결H,0),0))/100,"") | P14: =SUM(L14:O14) | S14: =IFERROR((VLOOKUP("파생상품이익",BS연결,MATCH(S$1,BS연결H,0),0)-VLOOKUP("파생상품손실",BS연결,MATCH(S$1,BS연결H,0),0))/100,"") | T14: =IFERROR((VLOOKUP("파생상품이익",BS연결,MATCH(T$1,BS연결H,0),0)-VLOOKUP("파생상품손실",BS연결,MATCH(T$1,BS연결H,0),0))/100,"") | U14: =SUM(Q14:T14) | V14: =IFERROR((VLOOKUP("파생상품이익",BS연결,MATCH(V$1,BS연결H,0),0)-VLOOKUP("파생상품손실",BS연결,MATCH(V$1,BS연결H,0),0))/100,"") | W14: =IFERROR((VLOOKUP("파생상품이익",BS연결,MATCH(W$1,BS연결H,0),0)-VLOOKUP("파생상품손실",BS연결,MATCH(W$1,BS연결H,0),0))/100,"") | X14: =IFERROR((VLOOKUP("파생상품이익",BS연결,MATCH(X$1,BS연결H,0),0)-VLOOKUP("파생상품손실",BS연결,MATCH(X$1,BS연결H,0),0))/100,"") | Y14: =IFERROR((VLOOKUP("파생상품이익",BS연결,MATCH(Y$1,BS연결H,0),0)-VLOOKUP("파생상품손실",BS연결,MATCH(Y$1,BS연결H,0),0))/100,"") | Z14: =SUM(V14:Y14) | AA14: =IFERROR((VLOOKUP("파생상품이익",BS연결,MATCH(AA$1,BS연결H,0),0)-VLOOKUP("파생상품손실",BS연결,MATCH(AA$1,BS연결H,0),0))/100,"") | AB14: =IFERROR((VLOOKUP("파생상품이익",BS연결,MATCH(AB$1,BS연결H,0),0)-VLOOKUP("파생상품손실",BS연결,MATCH(AB$1,BS연결H,0),0))/100,"") | AC14: =변수!AC25 | AD14: =변수!AD25 | AE14: =SUM(AA14:AD14) | AF14: =변수!AF25 | AG14: =변수!AG25 | AH14: =변수!AH25 | AI14: =변수!AI25 | AJ14: =SUM(AF14:AI14) | AK14: =변수!AK25 | AL14: =변수!AL25 | AM14: =변수!AM25 | AN14: =변수!AN25 | AO14: =SUM(AK14:AN14)
A15: 기타금융손익 | B15: 손익 | C15: 억원 | D15: 기타금융손익(금융손익 잔차) | H15: =IFERROR(H11-H12-H13-H14,"") | I15: =IFERROR(I11-I12-I13-I14,"") | J15: =IFERROR(J11-J12-J13-J14,"") | K15: =SUM(G15:J15) | L15: =IFERROR(L11-L12-L13-L14,"") | M15: =IFERROR(M11-M12-M13-M14,"") | N15: =IFERROR(N11-N12-N13-N14,"") | O15: =IFERROR(O11-O12-O13-O14,"") | P15: =SUM(L15:O15) | S15: =IFERROR(S11-S12-S13-S14,"") | T15: =IFERROR(T11-T12-T13-T14,"") | U15: =SUM(Q15:T15) | V15: =IFERROR(V11-V12-V13-V14,"") | W15: =IFERROR(W11-W12-W13-W14,"") | X15: =IFERROR(X11-X12-X13-X14,"") | Y15: =IFERROR(Y11-Y12-Y13-Y14,"") | Z15: =SUM(V15:Y15) | AA15: =IFERROR(AA11-AA12-AA13-AA14,"") | AB15: =IFERROR(AB11-AB12-AB13-AB14,"") | AC15: =변수!AC26 | AD15: =변수!AD26 | AE15: =SUM(AA15:AD15) | AF15: =변수!AF26 | AG15: =변수!AG26 | AH15: =변수!AH26 | AI15: =변수!AI26 | AJ15: =SUM(AF15:AI15) | AK15: =변수!AK26 | AL15: =변수!AL26 | AM15: =변수!AM26 | AN15: =변수!AN26 | AO15: =SUM(AK15:AN15)
A16: 기타영업외손익 | B16: 손익 | C16: 억원 | D16: 기타영업외손익 | E16: =IFERROR(VLOOKUP($D16,BS연결,MATCH(E$1,BS연결H,0),0)/100,"") | G16: =IFERROR(VLOOKUP($D16,BS연결,MATCH(G$1,BS연결H,0),0)/100,"") | H16: =IFERROR(VLOOKUP($D16,BS연결,MATCH(H$1,BS연결H,0),0)/100,"") | I16: =IFERROR(VLOOKUP($D16,BS연결,MATCH(I$1,BS연결H,0),0)/100,"") | J16: =IFERROR(VLOOKUP($D16,BS연결,MATCH(J$1,BS연결H,0),0)/100,"") | K16: =SUM(G16:J16) | L16: =IFERROR(VLOOKUP($D16,BS연결,MATCH(L$1,BS연결H,0),0)/100,"") | M16: =IFERROR(VLOOKUP($D16,BS연결,MATCH(M$1,BS연결H,0),0)/100,"") | N16: =IFERROR(VLOOKUP($D16,BS연결,MATCH(N$1,BS연결H,0),0)/100,"") | O16: =IFERROR(VLOOKUP($D16,BS연결,MATCH(O$1,BS연결H,0),0)/100,"") | P16: =IFERROR(VLOOKUP($D16,BS연결,MATCH(P$1,BS연결H,0),0)/100,"") | Q16: =IFERROR(VLOOKUP($D16,BS연결,MATCH(Q$1,BS연결H,0),0)/100,"") | R16: =IFERROR(VLOOKUP($D16,BS연결,MATCH(R$1,BS연결H,0),0)/100,"") | S16: =IFERROR(VLOOKUP($D16,BS연결,MATCH(S$1,BS연결H,0),0)/100,"") | ... Y16: =IFERROR(VLOOKUP($D16,BS연결,MATCH(Y$1,BS연결H,0),0)/100,"") | Z16: =SUM(V16:Y16) | AA16: =IFERROR(VLOOKUP($D16,BS연결,MATCH(AA$1,BS연결H,0),0)/100,"") | AB16: =IFERROR(VLOOKUP($D16,BS연결,MATCH(AB$1,BS연결H,0),0)/100,"") | AC16: =변수!AC27 | AD16: =변수!AD27 | AE16: =SUM(AA16:AD16) | AF16: =변수!AF27 | AG16: =변수!AG27 | AH16: =변수!AH27 | AI16: =변수!AI27 | AJ16: =SUM(AF16:AI16) | AK16: =변수!AK27 | AL16: =변수!AL27 | AM16: =변수!AM27 | AN16: =변수!AN27 | AO16: =SUM(AK16:AN16)
A17: 세전이익 | B17: 손익 | C17: 억원 | D17: 법인세비용차감전계속사업이익 | E17: =IFERROR(VLOOKUP($D17,BS연결,MATCH(E$1,BS연결H,0),0)/100,"") | G17: =IFERROR(VLOOKUP($D17,BS연결,MATCH(G$1,BS연결H,0),0)/100,"") | H17: =IFERROR(VLOOKUP($D17,BS연결,MATCH(H$1,BS연결H,0),0)/100,"") | I17: =IFERROR(VLOOKUP($D17,BS연결,MATCH(I$1,BS연결H,0),0)/100,"") | J17: =IFERROR(VLOOKUP($D17,BS연결,MATCH(J$1,BS연결H,0),0)/100,"") | K17: =IFERROR(VLOOKUP($D17,BS연결,MATCH(K$1,BS연결H,0),0)/100,"") | L17: =IFERROR(VLOOKUP($D17,BS연결,MATCH(L$1,BS연결H,0),0)/100,"") | M17: =IFERROR(VLOOKUP($D17,BS연결,MATCH(M$1,BS연결H,0),0)/100,"") | N17: =IFERROR(VLOOKUP($D17,BS연결,MATCH(N$1,BS연결H,0),0)/100,"") | ... AB17: =IFERROR(VLOOKUP($D17,BS연결,MATCH(AB$1,BS연결H,0),0)/100,"") | AC17: =IFERROR(AC9+AC11+AC16,"") | AD17: =IFERROR(AD9+AD11+AD16,"") | AE17: =SUM(AA17:AD17) | AF17: =IFERROR(AF9+AF11+AF16,"") | AG17: =IFERROR(AG9+AG11+AG16,"") | AH17: =IFERROR(AH9+AH11+AH16,"") | AI17: =IFERROR(AI9+AI11+AI16,"") | AJ17: =SUM(AF17:AI17) | AK17: =IFERROR(AK9+AK11+AK16,"") | AL17: =IFERROR(AL9+AL11+AL16,"") | AM17: =IFERROR(AM9+AM11+AM16,"") | AN17: =IFERROR(AN9+AN11+AN16,"") | AO17: =SUM(AK17:AN17)
A18: 법인세비용 | B18: 손익 | C18: 억원 | D18: 법인세비용 | E18: =IFERROR(VLOOKUP($D18,BS연결,MATCH(E$1,BS연결H,0),0)/100,"") | G18: =IFERROR(VLOOKUP($D18,BS연결,MATCH(G$1,BS연결H,0),0)/100,"") | H18: =IFERROR(VLOOKUP($D18,BS연결,MATCH(H$1,BS연결H,0),0)/100,"") | I18: =IFERROR(VLOOKUP($D18,BS연결,MATCH(I$1,BS연결H,0),0)/100,"") | J18: =IFERROR(VLOOKUP($D18,BS연결,MATCH(J$1,BS연결H,0),0)/100,"") | K18: =IFERROR(VLOOKUP($D18,BS연결,MATCH(K$1,BS연결H,0),0)/100,"") | L18: =IFERROR(VLOOKUP($D18,BS연결,MATCH(L$1,BS연결H,0),0)/100,"") | M18: =IFERROR(VLOOKUP($D18,BS연결,MATCH(M$1,BS연결H,0),0)/100,"") | N18: =IFERROR(VLOOKUP($D18,BS연결,MATCH(N$1,BS연결H,0),0)/100,"") | ... AB18: =IFERROR(VLOOKUP($D18,BS연결,MATCH(AB$1,BS연결H,0),0)/100,"") | AC18: =IFERROR(MAX(AC17,0)*변수!AC28,"") | AD18: =IFERROR(MAX(AD17,0)*변수!AD28,"") | AE18: =SUM(AA18:AD18) | AF18: =IFERROR(MAX(AF17,0)*변수!AF28,"") | AG18: =IFERROR(MAX(AG17,0)*변수!AG28,"") | AH18: =IFERROR(MAX(AH17,0)*변수!AH28,"") | AI18: =IFERROR(MAX(AI17,0)*변수!AI28,"") | AJ18: =SUM(AF18:AI18) | AK18: =IFERROR(MAX(AK17,0)*변수!AK28,"") | AL18: =IFERROR(MAX(AL17,0)*변수!AL28,"") | AM18: =IFERROR(MAX(AM17,0)*변수!AM28,"") | AN18: =IFERROR(MAX(AN17,0)*변수!AN28,"") | AO18: =SUM(AK18:AN18)
A19: 당기순이익 | B19: 손익 | C19: 억원 | D19: 당기순이익 | E19: =IFERROR(VLOOKUP($D19,BS연결,MATCH(E$1,BS연결H,0),0)/100,"") | G19: =IFERROR(VLOOKUP($D19,BS연결,MATCH(G$1,BS연결H,0),0)/100,"") | H19: =IFERROR(VLOOKUP($D19,BS연결,MATCH(H$1,BS연결H,0),0)/100,"") | I19: =IFERROR(VLOOKUP($D19,BS연결,MATCH(I$1,BS연결H,0),0)/100,"") | J19: =IFERROR(VLOOKUP($D19,BS연결,MATCH(J$1,BS연결H,0),0)/100,"") | K19: =IFERROR(VLOOKUP($D19,BS연결,MATCH(K$1,BS연결H,0),0)/100,"") | L19: =IFERROR(VLOOKUP($D19,BS연결,MATCH(L$1,BS연결H,0),0)/100,"") | M19: =IFERROR(VLOOKUP($D19,BS연결,MATCH(M$1,BS연결H,0),0)/100,"") | N19: =IFERROR(VLOOKUP($D19,BS연결,MATCH(N$1,BS연결H,0),0)/100,"") | ... AB19: =IFERROR(VLOOKUP($D19,BS연결,MATCH(AB$1,BS연결H,0),0)/100,"") | AC19: =IFERROR(AC17-AC18,"") | AD19: =IFERROR(AD17-AD18,"") | AE19: =SUM(AA19:AD19) | AF19: =IFERROR(AF17-AF18,"") | AG19: =IFERROR(AG17-AG18,"") | AH19: =IFERROR(AH17-AH18,"") | AI19: =IFERROR(AI17-AI18,"") | AJ19: =SUM(AF19:AI19) | AK19: =IFERROR(AK17-AK18,"") | AL19: =IFERROR(AL17-AL18,"") | AM19: =IFERROR(AM17-AM18,"") | AN19: =IFERROR(AN17-AN18,"") | AO19: =SUM(AK19:AN19)
A20: 지배주주순이익 | B20: 손익 | C20: 억원 | D20: (지배주주지분)당기순이익 | E20: =IFERROR(VLOOKUP($D20,BS연결,MATCH(E$1,BS연결H,0),0)/100,"") | G20: =IFERROR(VLOOKUP($D20,BS연결,MATCH(G$1,BS연결H,0),0)/100,"") | H20: =IFERROR(VLOOKUP($D20,BS연결,MATCH(H$1,BS연결H,0),0)/100,"") | I20: =IFERROR(VLOOKUP($D20,BS연결,MATCH(I$1,BS연결H,0),0)/100,"") | J20: =IFERROR(VLOOKUP($D20,BS연결,MATCH(J$1,BS연결H,0),0)/100,"") | K20: =IFERROR(VLOOKUP($D20,BS연결,MATCH(K$1,BS연결H,0),0)/100,"") | L20: =IFERROR(VLOOKUP($D20,BS연결,MATCH(L$1,BS연결H,0),0)/100,"") | M20: =IFERROR(VLOOKUP($D20,BS연결,MATCH(M$1,BS연결H,0),0)/100,"") | N20: =IFERROR(VLOOKUP($D20,BS연결,MATCH(N$1,BS연결H,0),0)/100,"") | ... AB20: =IFERROR(VLOOKUP($D20,BS연결,MATCH(AB$1,BS연결H,0),0)/100,"") | AC20: =IFERROR(AC19*변수!AC29,"") | AD20: =IFERROR(AD19*변수!AD29,"") | AE20: =SUM(AA20:AD20) | AF20: =IFERROR(AF19*변수!AF29,"") | AG20: =IFERROR(AG19*변수!AG29,"") | AH20: =IFERROR(AH19*변수!AH29,"") | AI20: =IFERROR(AI19*변수!AI29,"") | AJ20: =SUM(AF20:AI20) | AK20: =IFERROR(AK19*변수!AK29,"") | AL20: =IFERROR(AL19*변수!AL29,"") | AM20: =IFERROR(AM19*변수!AM29,"") | AN20: =IFERROR(AN19*변수!AN29,"") | AO20: =SUM(AK20:AN20)
A21: 자산총계 | B21: 재무상태 | C21: 억원 | D21: 자산총계 | E21: =IFERROR(VLOOKUP($D21,BS연결,MATCH(E$1,BS연결H,0),0)/100,"") | F21: =IFERROR(VLOOKUP($D21,BS연결,MATCH(F$1,BS연결H,0),0)/100,"") | G21: =IFERROR(VLOOKUP($D21,BS연결,MATCH(G$1,BS연결H,0),0)/100,"") | H21: =IFERROR(VLOOKUP($D21,BS연결,MATCH(H$1,BS연결H,0),0)/100,"") | I21: =IFERROR(VLOOKUP($D21,BS연결,MATCH(I$1,BS연결H,0),0)/100,"") | J21: =IFERROR(VLOOKUP($D21,BS연결,MATCH(J$1,BS연결H,0),0)/100,"") | K21: =IFERROR(VLOOKUP($D21,BS연결,MATCH(K$1,BS연결H,0),0)/100,"") | L21: =IFERROR(VLOOKUP($D21,BS연결,MATCH(L$1,BS연결H,0),0)/100,"") | ... AB21: =IFERROR(VLOOKUP($D21,BS연결,MATCH(AB$1,BS연결H,0),0)/100,"") | AC21: =IFERROR(AC22+AC23,"") | AD21: =IFERROR(AD22+AD23,"") | AE21: =AD21 | AF21: =IFERROR(AF22+AF23,"") | AG21: =IFERROR(AG22+AG23,"") | AH21: =IFERROR(AH22+AH23,"") | AI21: =IFERROR(AI22+AI23,"") | AJ21: =AI21 | AK21: =IFERROR(AK22+AK23,"") | AL21: =IFERROR(AL22+AL23,"") | AM21: =IFERROR(AM22+AM23,"") | AN21: =IFERROR(AN22+AN23,"") | AO21: =AN21
A22: 부채총계 | B22: 재무상태 | C22: 억원 | D22: 부채총계 | E22: =IFERROR(VLOOKUP($D22,BS연결,MATCH(E$1,BS연결H,0),0)/100,"") | F22: =IFERROR(VLOOKUP($D22,BS연결,MATCH(F$1,BS연결H,0),0)/100,"") | G22: =IFERROR(VLOOKUP($D22,BS연결,MATCH(G$1,BS연결H,0),0)/100,"") | H22: =IFERROR(VLOOKUP($D22,BS연결,MATCH(H$1,BS연결H,0),0)/100,"") | I22: =IFERROR(VLOOKUP($D22,BS연결,MATCH(I$1,BS연결H,0),0)/100,"") | J22: =IFERROR(VLOOKUP($D22,BS연결,MATCH(J$1,BS연결H,0),0)/100,"") | K22: =IFERROR(VLOOKUP($D22,BS연결,MATCH(K$1,BS연결H,0),0)/100,"") | L22: =IFERROR(VLOOKUP($D22,BS연결,MATCH(L$1,BS연결H,0),0)/100,"") | ... AB22: =IFERROR(VLOOKUP($D22,BS연결,MATCH(AB$1,BS연결H,0),0)/100,"") | AC22: =IFERROR(AB22*(1+변수!AC30),"") | AD22: =IFERROR(AC22*(1+변수!AD30),"") | AE22: =AD22 | AF22: =IFERROR(AD22*(1+변수!AF30),"") | AG22: =IFERROR(AF22*(1+변수!AG30),"") | AH22: =IFERROR(AG22*(1+변수!AH30),"") | AI22: =IFERROR(AH22*(1+변수!AI30),"") | AJ22: =AI22 | AK22: =IFERROR(AI22*(1+변수!AK30),"") | AL22: =IFERROR(AK22*(1+변수!AL30),"") | AM22: =IFERROR(AL22*(1+변수!AM30),"") | AN22: =IFERROR(AM22*(1+변수!AN30),"") | AO22: =AN22
A23: 자본총계 | B23: 재무상태 | C23: 억원 | D23: 자본총계 | E23: =IFERROR(VLOOKUP($D23,BS연결,MATCH(E$1,BS연결H,0),0)/100,"") | F23: =IFERROR(VLOOKUP($D23,BS연결,MATCH(F$1,BS연결H,0),0)/100,"") | G23: =IFERROR(VLOOKUP($D23,BS연결,MATCH(G$1,BS연결H,0),0)/100,"") | H23: =IFERROR(VLOOKUP($D23,BS연결,MATCH(H$1,BS연결H,0),0)/100,"") | I23: =IFERROR(VLOOKUP($D23,BS연결,MATCH(I$1,BS연결H,0),0)/100,"") | J23: =IFERROR(VLOOKUP($D23,BS연결,MATCH(J$1,BS연결H,0),0)/100,"") | K23: =IFERROR(VLOOKUP($D23,BS연결,MATCH(K$1,BS연결H,0),0)/100,"") | L23: =IFERROR(VLOOKUP($D23,BS연결,MATCH(L$1,BS연결H,0),0)/100,"") | ... AB23: =IFERROR(VLOOKUP($D23,BS연결,MATCH(AB$1,BS연결H,0),0)/100,"") | AC23: =IFERROR(AB23+AC19-변수!AC31,"") | AD23: =IFERROR(AC23+AD19-변수!AD31,"") | AE23: =AD23 | AF23: =IFERROR(AD23+AF19-변수!AF31,"") | AG23: =IFERROR(AF23+AG19-변수!AG31,"") | AH23: =IFERROR(AG23+AH19-변수!AH31,"") | AI23: =IFERROR(AH23+AI19-변수!AI31,"") | AJ23: =AI23 | AK23: =IFERROR(AI23+AK19-변수!AK31,"") | AL23: =IFERROR(AK23+AL19-변수!AL31,"") | AM23: =IFERROR(AL23+AM19-변수!AM31,"") | AN23: =IFERROR(AM23+AN19-변수!AN31,"") | AO23: =AN23
A24: 지배주주지분 | B24: 재무상태 | C24: 억원 | D24: 지배주주지분 | E24: =IFERROR(VLOOKUP($D24,BS연결,MATCH(E$1,BS연결H,0),0)/100,"") | F24: =IFERROR(VLOOKUP($D24,BS연결,MATCH(F$1,BS연결H,0),0)/100,"") | G24: =IFERROR(VLOOKUP($D24,BS연결,MATCH(G$1,BS연결H,0),0)/100,"") | H24: =IFERROR(VLOOKUP($D24,BS연결,MATCH(H$1,BS연결H,0),0)/100,"") | I24: =IFERROR(VLOOKUP($D24,BS연결,MATCH(I$1,BS연결H,0),0)/100,"") | J24: =IFERROR(VLOOKUP($D24,BS연결,MATCH(J$1,BS연결H,0),0)/100,"") | K24: =IFERROR(VLOOKUP($D24,BS연결,MATCH(K$1,BS연결H,0),0)/100,"") | L24: =IFERROR(VLOOKUP($D24,BS연결,MATCH(L$1,BS연결H,0),0)/100,"") | ... AB24: =IFERROR(VLOOKUP($D24,BS연결,MATCH(AB$1,BS연결H,0),0)/100,"") | AC24: =IFERROR(AB24+AC20-변수!AC32,"") | AD24: =IFERROR(AC24+AD20-변수!AD32,"") | AE24: =AD24 | AF24: =IFERROR(AD24+AF20-변수!AF32,"") | AG24: =IFERROR(AF24+AG20-변수!AG32,"") | AH24: =IFERROR(AG24+AH20-변수!AH32,"") | AI24: =IFERROR(AH24+AI20-변수!AI32,"") | AJ24: =AI24 | AK24: =IFERROR(AI24+AK20-변수!AK32,"") | AL24: =IFERROR(AK24+AL20-변수!AL32,"") | AM24: =IFERROR(AL24+AM20-변수!AM32,"") | AN24: =IFERROR(AM24+AN20-변수!AN32,"") | AO24: =AN24
A25: 총차입금 | B25: 재무상태 | C25: 억원 | D25: 총차입금 | E25: =IFERROR(VLOOKUP($D25,BS연결,MATCH(E$1,BS연결H,0),0)/100,"") | F25: =IFERROR(VLOOKUP($D25,BS연결,MATCH(F$1,BS연결H,0),0)/100,"") | G25: =IFERROR(VLOOKUP($D25,BS연결,MATCH(G$1,BS연결H,0),0)/100,"") | H25: =IFERROR(VLOOKUP($D25,BS연결,MATCH(H$1,BS연결H,0),0)/100,"") | I25: =IFERROR(VLOOKUP($D25,BS연결,MATCH(I$1,BS연결H,0),0)/100,"") | J25: =IFERROR(VLOOKUP($D25,BS연결,MATCH(J$1,BS연결H,0),0)/100,"") | K25: =IFERROR(VLOOKUP($D25,BS연결,MATCH(K$1,BS연결H,0),0)/100,"") | L25: =IFERROR(VLOOKUP($D25,BS연결,MATCH(L$1,BS연결H,0),0)/100,"") | ... AB25: =IFERROR(VLOOKUP($D25,BS연결,MATCH(AB$1,BS연결H,0),0)/100,"") | AC25: =IFERROR(AB25*(1+변수!AC33),"") | AD25: =IFERROR(AC25*(1+변수!AD33),"") | AE25: =AD25 | AF25: =IFERROR(AD25*(1+변수!AF33),"") | AG25: =IFERROR(AF25*(1+변수!AG33),"") | AH25: =IFERROR(AG25*(1+변수!AH33),"") | AI25: =IFERROR(AH25*(1+변수!AI33),"") | AJ25: =AI25 | AK25: =IFERROR(AI25*(1+변수!AK33),"") | AL25: =IFERROR(AK25*(1+변수!AL33),"") | AM25: =IFERROR(AL25*(1+변수!AM33),"") | AN25: =IFERROR(AM25*(1+변수!AN33),"") | AO25: =AN25
A26: 순차입금 | B26: 재무상태 | C26: 억원 | D26: 순차입금 | E26: =IFERROR(VLOOKUP($D26,BS연결,MATCH(E$1,BS연결H,0),0)/100,"") | F26: =IFERROR(VLOOKUP($D26,BS연결,MATCH(F$1,BS연결H,0),0)/100,"") | G26: =IFERROR(VLOOKUP($D26,BS연결,MATCH(G$1,BS연결H,0),0)/100,"") | H26: =IFERROR(VLOOKUP($D26,BS연결,MATCH(H$1,BS연결H,0),0)/100,"") | I26: =IFERROR(VLOOKUP($D26,BS연결,MATCH(I$1,BS연결H,0),0)/100,"") | J26: =IFERROR(VLOOKUP($D26,BS연결,MATCH(J$1,BS연결H,0),0)/100,"") | K26: =IFERROR(VLOOKUP($D26,BS연결,MATCH(K$1,BS연결H,0),0)/100,"") | L26: =IFERROR(VLOOKUP($D26,BS연결,MATCH(L$1,BS연결H,0),0)/100,"") | ... AB26: =IFERROR(VLOOKUP($D26,BS연결,MATCH(AB$1,BS연결H,0),0)/100,"") | AC26: =IFERROR(AB26*(1+변수!AC34),"") | AD26: =IFERROR(AC26*(1+변수!AD34),"") | AE26: =AD26 | AF26: =IFERROR(AD26*(1+변수!AF34),"") | AG26: =IFERROR(AF26*(1+변수!AG34),"") | AH26: =IFERROR(AG26*(1+변수!AH34),"") | AI26: =IFERROR(AH26*(1+변수!AI34),"") | AJ26: =AI26 | AK26: =IFERROR(AI26*(1+변수!AK34),"") | AL26: =IFERROR(AK26*(1+변수!AL34),"") | AM26: =IFERROR(AL26*(1+변수!AM34),"") | AN26: =IFERROR(AM26*(1+변수!AN34),"") | AO26: =AN26
A27: 이자발생자산 | B27: 재무상태 | C27: 억원 | D27: 이자발생자산 | E27: =IFERROR(VLOOKUP($D27,BS연결,MATCH(E$1,BS연결H,0),0)/100,"") | F27: =IFERROR(VLOOKUP($D27,BS연결,MATCH(F$1,BS연결H,0),0)/100,"") | G27: =IFERROR(VLOOKUP($D27,BS연결,MATCH(G$1,BS연결H,0),0)/100,"") | H27: =IFERROR(VLOOKUP($D27,BS연결,MATCH(H$1,BS연결H,0),0)/100,"") | I27: =IFERROR(VLOOKUP($D27,BS연결,MATCH(I$1,BS연결H,0),0)/100,"") | J27: =IFERROR(VLOOKUP($D27,BS연결,MATCH(J$1,BS연결H,0),0)/100,"") | K27: =IFERROR(VLOOKUP($D27,BS연결,MATCH(K$1,BS연결H,0),0)/100,"") | L27: =IFERROR(VLOOKUP($D27,BS연결,MATCH(L$1,BS연결H,0),0)/100,"") | ... AB27: =IFERROR(VLOOKUP($D27,BS연결,MATCH(AB$1,BS연결H,0),0)/100,"") | AC27: =IFERROR(AB27*(1+변수!AC35),"") | AD27: =IFERROR(AC27*(1+변수!AD35),"") | AE27: =AD27 | AF27: =IFERROR(AD27*(1+변수!AF35),"") | AG27: =IFERROR(AF27*(1+변수!AG35),"") | AH27: =IFERROR(AG27*(1+변수!AH35),"") | AI27: =IFERROR(AH27*(1+변수!AI35),"") | AJ27: =AI27 | AK27: =IFERROR(AI27*(1+변수!AK35),"") | AL27: =IFERROR(AK27*(1+변수!AL35),"") | AM27: =IFERROR(AL27*(1+변수!AM35),"") | AN27: =IFERROR(AM27*(1+변수!AN35),"") | AO27: =AN27
A28: 현금및현금성자산 | B28: 재무상태 | C28: 억원 | D28: 현금및현금성자산 | E28: =IFERROR(VLOOKUP($D28,BS연결,MATCH(E$1,BS연결H,0),0)/100,"") | F28: =IFERROR(VLOOKUP($D28,BS연결,MATCH(F$1,BS연결H,0),0)/100,"") | G28: =IFERROR(VLOOKUP($D28,BS연결,MATCH(G$1,BS연결H,0),0)/100,"") | H28: =IFERROR(VLOOKUP($D28,BS연결,MATCH(H$1,BS연결H,0),0)/100,"") | I28: =IFERROR(VLOOKUP($D28,BS연결,MATCH(I$1,BS연결H,0),0)/100,"") | J28: =IFERROR(VLOOKUP($D28,BS연결,MATCH(J$1,BS연결H,0),0)/100,"") | K28: =IFERROR(VLOOKUP($D28,BS연결,MATCH(K$1,BS연결H,0),0)/100,"") | L28: =IFERROR(VLOOKUP($D28,BS연결,MATCH(L$1,BS연결H,0),0)/100,"") | ... AB28: =IFERROR(VLOOKUP($D28,BS연결,MATCH(AB$1,BS연결H,0),0)/100,"") | AE28: =AD28 | AJ28: =AI28 | AO28: =AN28
A29: CAPEX | B29: 현금흐름 | C29: 억원 | D29: CAPEX | K29: =SUM(G29:J29) | P29: =SUM(L29:O29) | U29: =SUM(Q29:T29) | V29: =IFERROR(VLOOKUP($D29,BS연결,MATCH(V$1,BS연결H,0),0)/100,"") | W29: =IFERROR(VLOOKUP($D29,BS연결,MATCH(W$1,BS연결H,0),0)/100,"") | X29: =IFERROR(VLOOKUP($D29,BS연결,MATCH(X$1,BS연결H,0),0)/100,"") | Z29: =SUM(V29:Y29) | AC29: =IFERROR(X29*(1+변수!AC37),"") | AD29: =IFERROR(AC29*(1+변수!AD37),"") | AE29: =SUM(AA29:AD29) | AF29: =IFERROR(AD29*(1+변수!AF37),"") | AG29: =IFERROR(AF29*(1+변수!AG37),"") | AH29: =IFERROR(AC29*(1+변수!AH37),"") | AI29: =IFERROR(AD29*(1+변수!AI37),"") | AJ29: =SUM(AF29:AI29) | AK29: =IFERROR(AF29*(1+변수!AK37),"") | AL29: =IFERROR(AG29*(1+변수!AL37),"") | AM29: =IFERROR(AH29*(1+변수!AM37),"") | AN29: =IFERROR(AI29*(1+변수!AN37),"") | AO29: =SUM(AK29:AN29)
A30: 영업활동현금흐름 | B30: 현금흐름 | C30: 억원 | D30: 영업활동으로인한현금흐름 | E30: =IFERROR(VLOOKUP($D30,BS연결,MATCH(E$1,BS연결H,0),0)/100,"") | G30: =IFERROR(VLOOKUP($D30,BS연결,MATCH(G$1,BS연결H,0),0)/100,"") | H30: =IFERROR(VLOOKUP($D30,BS연결,MATCH(H$1,BS연결H,0),0)/100,"") | I30: =IFERROR(VLOOKUP($D30,BS연결,MATCH(I$1,BS연결H,0),0)/100,"") | J30: =IFERROR(VLOOKUP($D30,BS연결,MATCH(J$1,BS연결H,0),0)/100,"") | K30: =IFERROR(VLOOKUP($D30,BS연결,MATCH(K$1,BS연결H,0),0)/100,"") | L30: =IFERROR(VLOOKUP($D30,BS연결,MATCH(L$1,BS연결H,0),0)/100,"") | M30: =IFERROR(VLOOKUP($D30,BS연결,MATCH(M$1,BS연결H,0),0)/100,"") | N30: =IFERROR(VLOOKUP($D30,BS연결,MATCH(N$1,BS연결H,0),0)/100,"") | ... AB30: =IFERROR(VLOOKUP($D30,BS연결,MATCH(AB$1,BS연결H,0),0)/100,"") | AE30: =SUM(AA30:AD30) | AJ30: =SUM(AF30:AI30) | AO30: =SUM(AK30:AN30)
A31: 주식수 | B31: 주당 | C31: 백만주 | D31: 유통주식수 | E31: 12.13 | F31: =E31 | G31: 12.13 | H31: 12.13 | I31: 12.13 | J31: 12.13 | K31: =J31 | L31: 12.13 | M31: 12.13 | N31: 12.13 | O31: 12.13 | P31: =O31 | Q31: 12.13 | R31: 12.13 | S31: 12.13 | T31: 12.13 | U31: =T31 | V31: 12.13 | W31: 12.13 | X31: 12.13 | Y31: 13 | Z31: =Y31 | AA31: 13 | AB31: 13 | AC31: =IFERROR(AB31*(1+변수!AC39),"") | AD31: =IFERROR(AC31*(1+변수!AD39),"") | AE31: =AD31 | AF31: =IFERROR(AD31*(1+변수!AF39),"") | AG31: =IFERROR(AF31*(1+변수!AG39),"") | AH31: =IFERROR(AG31*(1+변수!AH39),"") | AI31: =IFERROR(AH31*(1+변수!AI39),"") | AJ31: =AI31 | AK31: =IFERROR(AI31*(1+변수!AK39),"") | AL31: =IFERROR(AK31*(1+변수!AL39),"") | AM31: =IFERROR(AL31*(1+변수!AM39),"") | AN31: =IFERROR(AM31*(1+변수!AN39),"") | AO31: =AN31
A32: EPS | B32: 주당 | C32: 원 | D32: EPS | E32: =IFERROR(E20*100/E31,"") | G32: =IFERROR(G20*100/G31,"") | H32: =IFERROR(H20*100/H31,"") | I32: =IFERROR(I20*100/I31,"") | J32: =IFERROR(J20*100/J31,"") | K32: =SUM(G32:J32) | L32: =IFERROR(L20*100/L31,"") | M32: =IFERROR(M20*100/M31,"") | N32: =IFERROR(N20*100/N31,"") | O32: =IFERROR(O20*100/O31,"") | P32: =SUM(L32:O32) | Q32: =IFERROR(Q20*100/Q31,"") | R32: =IFERROR(R20*100/R31,"") | S32: =IFERROR(S20*100/S31,"") | T32: =IFERROR(T20*100/T31,"") | U32: =SUM(Q32:T32) | V32: =IFERROR(V20*100/V31,"") | W32: =IFERROR(W20*100/W31,"") | X32: =IFERROR(X20*100/X31,"") | Y32: =IFERROR(Y20*100/Y31,"") | Z32: =SUM(V32:Y32) | AA32: =IFERROR(AA20*100/AA31,"") | AB32: =IFERROR(AB20*100/AB31,"") | AC32: =IFERROR(AC20*100/AC31,"") | AD32: =IFERROR(AD20*100/AD31,"") | AE32: =SUM(AA32:AD32) | AF32: =IFERROR(AF20*100/AF31,"") | AG32: =IFERROR(AG20*100/AG31,"") | AH32: =IFERROR(AH20*100/AH31,"") | AI32: =IFERROR(AI20*100/AI31,"") | AJ32: =SUM(AF32:AI32) | AK32: =IFERROR(AK20*100/AK31,"") | AL32: =IFERROR(AL20*100/AL31,"") | AM32: =IFERROR(AM20*100/AM31,"") | AN32: =IFERROR(AN20*100/AN31,"") | AO32: =SUM(AK32:AN32)
A33: BPS | B33: 주당 | C33: 원 | D33: BPS | E33: =IFERROR(E24*100/E31,"") | F33: =E33 | G33: =IFERROR(G24*100/G31,"") | H33: =IFERROR(H24*100/H31,"") | I33: =IFERROR(I24*100/I31,"") | J33: =IFERROR(J24*100/J31,"") | K33: =J33 | L33: =IFERROR(L24*100/L31,"") | M33: =IFERROR(M24*100/M31,"") | N33: =IFERROR(N24*100/N31,"") | O33: =IFERROR(O24*100/O31,"") | P33: =O33 | Q33: =IFERROR(Q24*100/Q31,"") | R33: =IFERROR(R24*100/R31,"") | S33: =IFERROR(S24*100/S31,"") | T33: =IFERROR(T24*100/T31,"") | U33: =T33 | V33: =IFERROR(V24*100/V31,"") | W33: =IFERROR(W24*100/W31,"") | X33: =IFERROR(X24*100/X31,"") | Y33: =IFERROR(Y24*100/Y31,"") | Z33: =Y33 | AA33: =IFERROR(AA24*100/AA31,"") | AB33: =IFERROR(AB24*100/AB31,"") | AC33: =IFERROR(AC24*100/AC31,"") | AD33: =IFERROR(AD24*100/AD31,"") | AE33: =AD33 | AF33: =IFERROR(AF24*100/AF31,"") | AG33: =IFERROR(AG24*100/AG31,"") | AH33: =IFERROR(AH24*100/AH31,"") | AI33: =IFERROR(AI24*100/AI31,"") | AJ33: =AI33 | AK33: =IFERROR(AK24*100/AK31,"") | AL33: =IFERROR(AL24*100/AL31,"") | AM33: =IFERROR(AM24*100/AM31,"") | AN33: =IFERROR(AN24*100/AN31,"") | AO33: =AN33
A34: DPS | B34: 주당 | C34: 원 | D34: DPS(보통주) | E34: 70 | F34: 70 | J34: 50 | K34: =SUM(G34:J34) | O34: 100 | P34: =SUM(L34:O34) | T34: 150 | U34: =SUM(Q34:T34) | Y34: 165 | Z34: =SUM(V34:Y34) | AD34: =변수!AD40 | AE34: =SUM(AA34:AD34) | AI34: =변수!AI40 | AJ34: =SUM(AF34:AI34) | AN34: =변수!AN40 | AO34: =SUM(AK34:AN34)
A35: PER | B35: 주당 | C35: 배 | D35: PER | F35: =E35 | K35: =J35 | N35: =IFERROR(변수!N18/(J32+L32+M32+N32),"") | O35: =IFERROR(변수!O18/(L32+M32+N32+O32),"") | P35: =O35 | Q35: =IFERROR(변수!Q18/(M32+N32+O32+Q32),"") | R35: =IFERROR(변수!R18/(N32+O32+Q32+R32),"") | S35: =IFERROR(변수!S18/(O32+Q32+R32+S32),"") | T35: =IFERROR(변수!T18/(Q32+R32+S32+T32),"") | U35: =T35 | V35: =IFERROR(변수!V18/(R32+S32+T32+V32),"") | W35: =IFERROR(변수!W18/(S32+T32+V32+W32),"") | X35: =IFERROR(변수!X18/(T32+V32+W32+X32),"") | Y35: =IFERROR(변수!Y18/(V32+W32+X32+Y32),"") | Z35: =Y35 | AA35: =IFERROR(변수!AA18/(W32+X32+Y32+AA32),"") | AB35: =IFERROR(변수!AB18/(X32+Y32+AA32+AB32),"") | AC35: =IFERROR(변수!$D$43/(Y32+AA32+AB32+AC32),"") | AD35: =IFERROR(변수!$D$43/(AA32+AB32+AC32+AD32),"") | AE35: =AD35 | AF35: =IFERROR(변수!$D$43/(AB32+AC32+AD32+AF32),"") | AG35: =IFERROR(변수!$D$43/(AC32+AD32+AF32+AG32),"") | AH35: =IFERROR(변수!$D$43/(AD32+AF32+AG32+AH32),"") | AI35: =IFERROR(변수!$D$43/(AF32+AG32+AH32+AI32),"") | AJ35: =AI35 | AK35: =IFERROR(변수!$D$43/(AG32+AH32+AI32+AK32),"") | AL35: =IFERROR(변수!$D$43/(AH32+AI32+AK32+AL32),"") | AM35: =IFERROR(변수!$D$43/(AI32+AK32+AL32+AM32),"") | AN35: =IFERROR(변수!$D$43/(AK32+AL32+AM32+AN32),"") | AO35: =AN35
A36: PBR | B36: 주당 | C36: 배 | D36: PBR | E36: =IFERROR(변수!E18/E33,"") | F36: =E36 | G36: =IFERROR(변수!G18/G33,"") | H36: =IFERROR(변수!H18/H33,"") | I36: =IFERROR(변수!I18/I33,"") | J36: =IFERROR(변수!J18/J33,"") | K36: =J36 | L36: =IFERROR(변수!L18/L33,"") | M36: =IFERROR(변수!M18/M33,"") | N36: =IFERROR(변수!N18/N33,"") | O36: =IFERROR(변수!O18/O33,"") | P36: =O36 | Q36: =IFERROR(변수!Q18/Q33,"") | R36: =IFERROR(변수!R18/R33,"") | S36: =IFERROR(변수!S18/S33,"") | T36: =IFERROR(변수!T18/T33,"") | U36: =T36 | V36: =IFERROR(변수!V18/V33,"") | W36: =IFERROR(변수!W18/W33,"") | X36: =IFERROR(변수!X18/X33,"") | Y36: =IFERROR(변수!Y18/Y33,"") | Z36: =Y36 | AA36: =IFERROR(변수!AA18/AA33,"") | AB36: =IFERROR(변수!AB18/AB33,"") | AC36: =IFERROR(변수!$D$43/AC33,"") | AD36: =IFERROR(변수!$D$43/AD33,"") | AE36: =AD36 | AF36: =IFERROR(변수!$D$43/AF33,"") | AG36: =IFERROR(변수!$D$43/AG33,"") | AH36: =IFERROR(변수!$D$43/AH33,"") | AI36: =IFERROR(변수!$D$43/AI33,"") | AJ36: =AI36 | AK36: =IFERROR(변수!$D$43/AK33,"") | AL36: =IFERROR(변수!$D$43/AL33,"") | AM36: =IFERROR(변수!$D$43/AM33,"") | AN36: =IFERROR(변수!$D$43/AN33,"") | AO36: =AN36
A37: 매출전사 | B37: 사업부 | C37: 억원 | D37: 매출 전사(부문 미분리) | E37: 165.6 | G37: 203.17 | H37: 227.98 | I37: 238.3 | J37: 237.32 | K37: =SUM(G37:J37) | L37: 209.85 | M37: 234.89 | N37: 263.8 | O37: 248.96 | P37: =SUM(L37:O37) | Q37: 265.21 | R37: 340.58 | S37: 285.81 | T37: 288.61 | U37: =SUM(Q37:T37) | V37: 263.41 | W37: 296.32 | X37: 294.69 | Y37: 330.21 | Z37: =SUM(V37:Y37) | AA37: 1309.1 | AB37: 1313.93 | AC37: =IFERROR(AC5,"") | AD37: =IFERROR(AD5,"") | AE37: =SUM(AA37:AD37) | AF37: =IFERROR(AF5,"") | AG37: =IFERROR(AG5,"") | AH37: =IFERROR(AH5,"") | AI37: =IFERROR(AI5,"") | AJ37: =SUM(AF37:AI37) | AK37: =IFERROR(AK5,"") | AL37: =IFERROR(AL5,"") | AM37: =IFERROR(AM5,"") | AN37: =IFERROR(AN5,"") | AO37: =SUM(AK37:AN37)
A38: OP전사 | B38: 사업부 | C38: 억원 | D38: OP 전사(부문 미분리) | E38: -6.89 | G38: 1.83 | H38: -13.12 | I38: -32.87 | J38: 12.35 | K38: =SUM(G38:J38) | L38: 7.84 | M38: 14.07 | N38: 27.23 | O38: 10.79 | P38: =SUM(L38:O38) | Q38: 26.96 | R38: 14.28 | S38: 27.5 | T38: 34.23 | U38: =SUM(Q38:T38) | V38: 28.68 | W38: 24.38 | X38: 34.11 | Y38: 15.02 | Z38: =SUM(V38:Y38) | AA38: 56.09 | AB38: 31.76 | AC38: =IFERROR(AC9,"") | AD38: =IFERROR(AD9,"") | AE38: =SUM(AA38:AD38) | AF38: =IFERROR(AF9,"") | AG38: =IFERROR(AG9,"") | AH38: =IFERROR(AH9,"") | AI38: =IFERROR(AI9,"") | AJ38: =SUM(AF38:AI38) | AK38: =IFERROR(AK9,"") | AL38: =IFERROR(AL9,"") | AM38: =IFERROR(AM9,"") | AN38: =IFERROR(AN9,"") | AO38: =SUM(AK38:AN38)
B39: 비율(참고)
A40: NPM | C40: % | D40: 지배주주순이익 / 매출액 | E40: =IFERROR(E20/E5,"") | F40: =IFERROR(F20/F5,"") | G40: =IFERROR(G20/G5,"") | H40: =IFERROR(H20/H5,"") | I40: =IFERROR(I20/I5,"") | J40: =IFERROR(J20/J5,"") | K40: =IFERROR(K20/K5,"") | L40: =IFERROR(L20/L5,"") | ... AO40: =IFERROR(AO20/AO5,"")
A41: 매출원가율 | C41: % | D41: 매출원가 / 매출액 | E41: =IFERROR(E6/E5,"") | F41: =IFERROR(F6/F5,"") | G41: =IFERROR(G6/G5,"") | H41: =IFERROR(H6/H5,"") | I41: =IFERROR(I6/I5,"") | J41: =IFERROR(J6/J5,"") | K41: =IFERROR(K6/K5,"") | L41: =IFERROR(L6/L5,"") | ... AO41: =IFERROR(AO6/AO5,"")
A42: 판관비율 | C42: % | D42: 판관비 / 매출액 | E42: =IFERROR(E8/E5,"") | F42: =IFERROR(F8/F5,"") | G42: =IFERROR(G8/G5,"") | H42: =IFERROR(H8/H5,"") | I42: =IFERROR(I8/I5,"") | J42: =IFERROR(J8/J5,"") | K42: =IFERROR(K8/K5,"") | L42: =IFERROR(L8/L5,"") | ... AO42: =IFERROR(AO8/AO5,"")

Sheet 분기
C1: 이름: 분기H — subQ 를 이름으로 VLOOKUP(억원) | E1: 4Q21 | F1: 1Q22 | G1: 2Q22 | H1: 3Q22 | I1: 4Q22 | J1: 1Q23 | K1: 2Q23 | L1: 3Q23 | M1: 4Q23 | N1: 1Q24 | O1: 2Q24 | P1: 3Q24 | Q1: 4Q24 | R1: 1Q25 | S1: 2Q25 | T1: 3Q25 | U1: 4Q25 | V1: 1Q26 | W1: 2Q26 | X1: 3Q26 | Y1: 4Q26 | Z1: 1Q27 | AA1: 2Q27 | AB1: 3Q27 | AC1: 4Q27 | AD1: 1Q28 | AE1: 2Q28 | AF1: 3Q28 | AG1: 4Q28
C2: 종가: | D2: =변수!D43
C3: 기준일: | D3: 20261012 | E3: 1 | F3: 2 | G3: 3 | H3: 4 | I3: 5 | J3: 6 | K3: 7 | L3: 8 | M3: 9 | N3: 10 | O3: 11 | P3: 12 | Q3: 13 | R3: 14 | S3: 15 | T3: 16 | U3: 17 | V3: 18 | W3: 19 | X3: 20 | Y3: 21 | Z3: 22 | AA3: 23 | AB3: 24 | AC3: 25 | AD3: 26 | AE3: 27 | AF3: 28 | AG3: 29
E4: 2021.12 | F4: 2022.03 | G4: 2022.06 | H4: 2022.09 | I4: 2022.12 | J4: 2023.03 | K4: 2023.06 | L4: 2023.09 | M4: 2023.12 | N4: 2024.03 | O4: 2024.06 | P4: 2024.09 | Q4: 2024.12 | R4: 2025.03 | S4: 2025.06 | T4: 2025.09 | U4: 2025.12 | V4: 2026.03 | W4: 2026.06 | X4: 2026.09 | Y4: 2026.12 | Z4: 2027.03 | AA4: 2027.06 | AB4: 2027.09 | AC4: 2027.12 | AD4: 2028.03 | AE4: 2028.06 | AF4: 2028.09 | AG4: 2028.12
A5: 매출액 | D5: 매출액 | E5: =IFERROR(VLOOKUP($A5,subQ,MATCH(E$1,SUBQH,0),0),"") | F5: =IFERROR(VLOOKUP($A5,subQ,MATCH(F$1,SUBQH,0),0),"") | G5: =IFERROR(VLOOKUP($A5,subQ,MATCH(G$1,SUBQH,0),0),"") | H5: =IFERROR(VLOOKUP($A5,subQ,MATCH(H$1,SUBQH,0),0),"") | I5: =IFERROR(VLOOKUP($A5,subQ,MATCH(I$1,SUBQH,0),0),"") | J5: =IFERROR(VLOOKUP($A5,subQ,MATCH(J$1,SUBQH,0),0),"") | K5: =IFERROR(VLOOKUP($A5,subQ,MATCH(K$1,SUBQH,0),0),"") | L5: =IFERROR(VLOOKUP($A5,subQ,MATCH(L$1,SUBQH,0),0),"") | ... AG5: =IFERROR(VLOOKUP($A5,subQ,MATCH(AG$1,SUBQH,0),0),"")
A6: 매출원가 | D6: 매출원가 | E6: =IFERROR(VLOOKUP($A6,subQ,MATCH(E$1,SUBQH,0),0),"") | F6: =IFERROR(VLOOKUP($A6,subQ,MATCH(F$1,SUBQH,0),0),"") | G6: =IFERROR(VLOOKUP($A6,subQ,MATCH(G$1,SUBQH,0),0),"") | H6: =IFERROR(VLOOKUP($A6,subQ,MATCH(H$1,SUBQH,0),0),"") | I6: =IFERROR(VLOOKUP($A6,subQ,MATCH(I$1,SUBQH,0),0),"") | J6: =IFERROR(VLOOKUP($A6,subQ,MATCH(J$1,SUBQH,0),0),"") | K6: =IFERROR(VLOOKUP($A6,subQ,MATCH(K$1,SUBQH,0),0),"") | L6: =IFERROR(VLOOKUP($A6,subQ,MATCH(L$1,SUBQH,0),0),"") | ... AG6: =IFERROR(VLOOKUP($A6,subQ,MATCH(AG$1,SUBQH,0),0),"")
A7: 매출총이익 | D7: 매출총이익 | E7: =IFERROR(VLOOKUP($A7,subQ,MATCH(E$1,SUBQH,0),0),"") | F7: =IFERROR(VLOOKUP($A7,subQ,MATCH(F$1,SUBQH,0),0),"") | G7: =IFERROR(VLOOKUP($A7,subQ,MATCH(G$1,SUBQH,0),0),"") | H7: =IFERROR(VLOOKUP($A7,subQ,MATCH(H$1,SUBQH,0),0),"") | I7: =IFERROR(VLOOKUP($A7,subQ,MATCH(I$1,SUBQH,0),0),"") | J7: =IFERROR(VLOOKUP($A7,subQ,MATCH(J$1,SUBQH,0),0),"") | K7: =IFERROR(VLOOKUP($A7,subQ,MATCH(K$1,SUBQH,0),0),"") | L7: =IFERROR(VLOOKUP($A7,subQ,MATCH(L$1,SUBQH,0),0),"") | ... AG7: =IFERROR(VLOOKUP($A7,subQ,MATCH(AG$1,SUBQH,0),0),"")
A8: 판관비 | D8: 판매비와관리비 | E8: =IFERROR(VLOOKUP($A8,subQ,MATCH(E$1,SUBQH,0),0),"") | F8: =IFERROR(VLOOKUP($A8,subQ,MATCH(F$1,SUBQH,0),0),"") | G8: =IFERROR(VLOOKUP($A8,subQ,MATCH(G$1,SUBQH,0),0),"") | H8: =IFERROR(VLOOKUP($A8,subQ,MATCH(H$1,SUBQH,0),0),"") | I8: =IFERROR(VLOOKUP($A8,subQ,MATCH(I$1,SUBQH,0),0),"") | J8: =IFERROR(VLOOKUP($A8,subQ,MATCH(J$1,SUBQH,0),0),"") | K8: =IFERROR(VLOOKUP($A8,subQ,MATCH(K$1,SUBQH,0),0),"") | L8: =IFERROR(VLOOKUP($A8,subQ,MATCH(L$1,SUBQH,0),0),"") | ... AG8: =IFERROR(VLOOKUP($A8,subQ,MATCH(AG$1,SUBQH,0),0),"")
A9: 영업이익 | D9: 영업이익 | E9: =IFERROR(VLOOKUP($A9,subQ,MATCH(E$1,SUBQH,0),0),"") | F9: =IFERROR(VLOOKUP($A9,subQ,MATCH(F$1,SUBQH,0),0),"") | G9: =IFERROR(VLOOKUP($A9,subQ,MATCH(G$1,SUBQH,0),0),"") | H9: =IFERROR(VLOOKUP($A9,subQ,MATCH(H$1,SUBQH,0),0),"") | I9: =IFERROR(VLOOKUP($A9,subQ,MATCH(I$1,SUBQH,0),0),"") | J9: =IFERROR(VLOOKUP($A9,subQ,MATCH(J$1,SUBQH,0),0),"") | K9: =IFERROR(VLOOKUP($A9,subQ,MATCH(K$1,SUBQH,0),0),"") | L9: =IFERROR(VLOOKUP($A9,subQ,MATCH(L$1,SUBQH,0),0),"") | ... AG9: =IFERROR(VLOOKUP($A9,subQ,MATCH(AG$1,SUBQH,0),0),"")
A10: OPM | D10: 영업이익률 | E10: =IFERROR(VLOOKUP($A10,subQ,MATCH(E$1,SUBQH,0),0),"") | F10: =IFERROR(VLOOKUP($A10,subQ,MATCH(F$1,SUBQH,0),0),"") | G10: =IFERROR(VLOOKUP($A10,subQ,MATCH(G$1,SUBQH,0),0),"") | H10: =IFERROR(VLOOKUP($A10,subQ,MATCH(H$1,SUBQH,0),0),"") | I10: =IFERROR(VLOOKUP($A10,subQ,MATCH(I$1,SUBQH,0),0),"") | J10: =IFERROR(VLOOKUP($A10,subQ,MATCH(J$1,SUBQH,0),0),"") | K10: =IFERROR(VLOOKUP($A10,subQ,MATCH(K$1,SUBQH,0),0),"") | L10: =IFERROR(VLOOKUP($A10,subQ,MATCH(L$1,SUBQH,0),0),"") | ... AG10: =IFERROR(VLOOKUP($A10,subQ,MATCH(AG$1,SUBQH,0),0),"")
A11: 금융손익 | D11: 금융손익(이자·환 포함) | E11: =IFERROR(VLOOKUP($A11,subQ,MATCH(E$1,SUBQH,0),0),"") | F11: =IFERROR(VLOOKUP($A11,subQ,MATCH(F$1,SUBQH,0),0),"") | G11: =IFERROR(VLOOKUP($A11,subQ,MATCH(G$1,SUBQH,0),0),"") | H11: =IFERROR(VLOOKUP($A11,subQ,MATCH(H$1,SUBQH,0),0),"") | I11: =IFERROR(VLOOKUP($A11,subQ,MATCH(I$1,SUBQH,0),0),"") | J11: =IFERROR(VLOOKUP($A11,subQ,MATCH(J$1,SUBQH,0),0),"") | K11: =IFERROR(VLOOKUP($A11,subQ,MATCH(K$1,SUBQH,0),0),"") | L11: =IFERROR(VLOOKUP($A11,subQ,MATCH(L$1,SUBQH,0),0),"") | ... AG11: =IFERROR(VLOOKUP($A11,subQ,MATCH(AG$1,SUBQH,0),0),"")
A12: 이자손익 | D12: 이자손익(이자수익 − 이자비용) | E12: =IFERROR(VLOOKUP($A12,subQ,MATCH(E$1,SUBQH,0),0),"") | F12: =IFERROR(VLOOKUP($A12,subQ,MATCH(F$1,SUBQH,0),0),"") | G12: =IFERROR(VLOOKUP($A12,subQ,MATCH(G$1,SUBQH,0),0),"") | H12: =IFERROR(VLOOKUP($A12,subQ,MATCH(H$1,SUBQH,0),0),"") | I12: =IFERROR(VLOOKUP($A12,subQ,MATCH(I$1,SUBQH,0),0),"") | J12: =IFERROR(VLOOKUP($A12,subQ,MATCH(J$1,SUBQH,0),0),"") | K12: =IFERROR(VLOOKUP($A12,subQ,MATCH(K$1,SUBQH,0),0),"") | L12: =IFERROR(VLOOKUP($A12,subQ,MATCH(L$1,SUBQH,0),0),"") | ... AG12: =IFERROR(VLOOKUP($A12,subQ,MATCH(AG$1,SUBQH,0),0),"")
A13: 외환손익 | D13: 외환손익(실적만; 추정 환효과는 환관련손익) | E13: =IFERROR(VLOOKUP($A13,subQ,MATCH(E$1,SUBQH,0),0),"") | F13: =IFERROR(VLOOKUP($A13,subQ,MATCH(F$1,SUBQH,0),0),"") | G13: =IFERROR(VLOOKUP($A13,subQ,MATCH(G$1,SUBQH,0),0),"") | H13: =IFERROR(VLOOKUP($A13,subQ,MATCH(H$1,SUBQH,0),0),"") | I13: =IFERROR(VLOOKUP($A13,subQ,MATCH(I$1,SUBQH,0),0),"") | J13: =IFERROR(VLOOKUP($A13,subQ,MATCH(J$1,SUBQH,0),0),"") | K13: =IFERROR(VLOOKUP($A13,subQ,MATCH(K$1,SUBQH,0),0),"") | L13: =IFERROR(VLOOKUP($A13,subQ,MATCH(L$1,SUBQH,0),0),"") | ... AG13: =IFERROR(VLOOKUP($A13,subQ,MATCH(AG$1,SUBQH,0),0),"")
A14: 파생상품손익 | D14: 파생상품손익 | E14: =IFERROR(VLOOKUP($A14,subQ,MATCH(E$1,SUBQH,0),0),"") | F14: =IFERROR(VLOOKUP($A14,subQ,MATCH(F$1,SUBQH,0),0),"") | G14: =IFERROR(VLOOKUP($A14,subQ,MATCH(G$1,SUBQH,0),0),"") | H14: =IFERROR(VLOOKUP($A14,subQ,MATCH(H$1,SUBQH,0),0),"") | I14: =IFERROR(VLOOKUP($A14,subQ,MATCH(I$1,SUBQH,0),0),"") | J14: =IFERROR(VLOOKUP($A14,subQ,MATCH(J$1,SUBQH,0),0),"") | K14: =IFERROR(VLOOKUP($A14,subQ,MATCH(K$1,SUBQH,0),0),"") | L14: =IFERROR(VLOOKUP($A14,subQ,MATCH(L$1,SUBQH,0),0),"") | ... AG14: =IFERROR(VLOOKUP($A14,subQ,MATCH(AG$1,SUBQH,0),0),"")
A15: 기타금융손익 | D15: 기타금융손익(금융손익 잔차) | E15: =IFERROR(VLOOKUP($A15,subQ,MATCH(E$1,SUBQH,0),0),"") | F15: =IFERROR(VLOOKUP($A15,subQ,MATCH(F$1,SUBQH,0),0),"") | G15: =IFERROR(VLOOKUP($A15,subQ,MATCH(G$1,SUBQH,0),0),"") | H15: =IFERROR(VLOOKUP($A15,subQ,MATCH(H$1,SUBQH,0),0),"") | I15: =IFERROR(VLOOKUP($A15,subQ,MATCH(I$1,SUBQH,0),0),"") | J15: =IFERROR(VLOOKUP($A15,subQ,MATCH(J$1,SUBQH,0),0),"") | K15: =IFERROR(VLOOKUP($A15,subQ,MATCH(K$1,SUBQH,0),0),"") | L15: =IFERROR(VLOOKUP($A15,subQ,MATCH(L$1,SUBQH,0),0),"") | ... AG15: =IFERROR(VLOOKUP($A15,subQ,MATCH(AG$1,SUBQH,0),0),"")
A16: 기타영업외손익 | D16: 기타영업외손익 | E16: =IFERROR(VLOOKUP($A16,subQ,MATCH(E$1,SUBQH,0),0),"") | F16: =IFERROR(VLOOKUP($A16,subQ,MATCH(F$1,SUBQH,0),0),"") | G16: =IFERROR(VLOOKUP($A16,subQ,MATCH(G$1,SUBQH,0),0),"") | H16: =IFERROR(VLOOKUP($A16,subQ,MATCH(H$1,SUBQH,0),0),"") | I16: =IFERROR(VLOOKUP($A16,subQ,MATCH(I$1,SUBQH,0),0),"") | J16: =IFERROR(VLOOKUP($A16,subQ,MATCH(J$1,SUBQH,0),0),"") | K16: =IFERROR(VLOOKUP($A16,subQ,MATCH(K$1,SUBQH,0),0),"") | L16: =IFERROR(VLOOKUP($A16,subQ,MATCH(L$1,SUBQH,0),0),"") | ... AG16: =IFERROR(VLOOKUP($A16,subQ,MATCH(AG$1,SUBQH,0),0),"")
... A39: NPM | D39: NPM | E39: =IFERROR(VLOOKUP($A39,subQ,MATCH(E$1,SUBQH,0),0),"") | F39: =IFERROR(VLOOKUP($A39,subQ,MATCH(F$1,SUBQH,0),0),"") | G39: =IFERROR(VLOOKUP($A39,subQ,MATCH(G$1,SUBQH,0),0),"") | H39: =IFERROR(VLOOKUP($A39,subQ,MATCH(H$1,SUBQH,0),0),"") | I39: =IFERROR(VLOOKUP($A39,subQ,MATCH(I$1,SUBQH,0),0),"") | J39: =IFERROR(VLOOKUP($A39,subQ,MATCH(J$1,SUBQH,0),0),"") | K39: =IFERROR(VLOOKUP($A39,subQ,MATCH(K$1,SUBQH,0),0),"") | L39: =IFERROR(VLOOKUP($A39,subQ,MATCH(L$1,SUBQH,0),0),"") | ... AG39: =IFERROR(VLOOKUP($A39,subQ,MATCH(AG$1,SUBQH,0),0),"")
A40: 매출액 YoY | D40: 매출액 YoY | I40: =IFERROR(I5/E5-1,"") | J40: =IFERROR(J5/F5-1,"") | K40: =IFERROR(K5/G5-1,"") | L40: =IFERROR(L5/H5-1,"") | M40: =IFERROR(M5/I5-1,"") | N40: =IFERROR(N5/J5-1,"") | O40: =IFERROR(O5/K5-1,"") | P40: =IFERROR(P5/L5-1,"") | ... AG40: =IFERROR(AG5/AC5-1,"")
A41: 영업이익 YoY | D41: 영업이익 YoY | I41: =IFERROR(I9/E9-1,"") | J41: =IFERROR(J9/F9-1,"") | K41: =IFERROR(K9/G9-1,"") | L41: =IFERROR(L9/H9-1,"") | M41: =IFERROR(M9/I9-1,"") | N41: =IFERROR(N9/J9-1,"") | O41: =IFERROR(O9/K9-1,"") | P41: =IFERROR(P9/L9-1,"") | ... AG41: =IFERROR(AG9/AC9-1,"")
A42: 지배주주순이익 YoY | D42: 지배주주순이익 YoY | I42: =IFERROR(I20/E20-1,"") | J42: =IFERROR(J20/F20-1,"") | K42: =IFERROR(K20/G20-1,"") | L42: =IFERROR(L20/H20-1,"") | M42: =IFERROR(M20/I20-1,"") | N42: =IFERROR(N20/J20-1,"") | O42: =IFERROR(O20/K20-1,"") | P42: =IFERROR(P20/L20-1,"") | ... AG42: =IFERROR(AG20/AC20-1,"")

Sheet 연간예상
C1: 이름: 연간예상H — subQ 를 이름으로 VLOOKUP(억원) | E1: 2021 | F1: 2022 | G1: 2023 | H1: 2024 | I1: 2025 | J1: 2026 | K1: 2027 | L1: 2028
C2: 종가: | D2: =변수!D43
C3: 기준일: | D3: 20261012 | E3: 1 | F3: 2 | G3: 3 | H3: 4 | I3: 5 | J3: 6 | K3: 7 | L3: 8
E4: 2021.12A | F4: 2022.12A | G4: 2023.12A | H4: 2024.12A | I4: 2025.12A | J4: 2026.12A | K4: 2027.12A | L4: 2028.12A
A5: 매출액 | D5: 매출액 | E5: =IFERROR(VLOOKUP($A5,subQ,MATCH(E$1,SUBQH,0),0),"") | F5: =IFERROR(VLOOKUP($A5,subQ,MATCH(F$1,SUBQH,0),0),"") | G5: =IFERROR(VLOOKUP($A5,subQ,MATCH(G$1,SUBQH,0),0),"") | H5: =IFERROR(VLOOKUP($A5,subQ,MATCH(H$1,SUBQH,0),0),"") | I5: =IFERROR(VLOOKUP($A5,subQ,MATCH(I$1,SUBQH,0),0),"") | J5: =IFERROR(VLOOKUP($A5,subQ,MATCH(J$1,SUBQH,0),0),"") | K5: =IFERROR(VLOOKUP($A5,subQ,MATCH(K$1,SUBQH,0),0),"") | L5: =IFERROR(VLOOKUP($A5,subQ,MATCH(L$1,SUBQH,0),0),"")
A6: 매출원가 | D6: 매출원가 | E6: =IFERROR(VLOOKUP($A6,subQ,MATCH(E$1,SUBQH,0),0),"") | F6: =IFERROR(VLOOKUP($A6,subQ,MATCH(F$1,SUBQH,0),0),"") | G6: =IFERROR(VLOOKUP($A6,subQ,MATCH(G$1,SUBQH,0),0),"") | H6: =IFERROR(VLOOKUP($A6,subQ,MATCH(H$1,SUBQH,0),0),"") | I6: =IFERROR(VLOOKUP($A6,subQ,MATCH(I$1,SUBQH,0),0),"") | J6: =IFERROR(VLOOKUP($A6,subQ,MATCH(J$1,SUBQH,0),0),"") | K6: =IFERROR(VLOOKUP($A6,subQ,MATCH(K$1,SUBQH,0),0),"") | L6: =IFERROR(VLOOKUP($A6,subQ,MATCH(L$1,SUBQH,0),0),"")
A7: 매출총이익 | D7: 매출총이익 | E7: =IFERROR(VLOOKUP($A7,subQ,MATCH(E$1,SUBQH,0),0),"") | F7: =IFERROR(VLOOKUP($A7,subQ,MATCH(F$1,SUBQH,0),0),"") | G7: =IFERROR(VLOOKUP($A7,subQ,MATCH(G$1,SUBQH,0),0),"") | H7: =IFERROR(VLOOKUP($A7,subQ,MATCH(H$1,SUBQH,0),0),"") | I7: =IFERROR(VLOOKUP($A7,subQ,MATCH(I$1,SUBQH,0),0),"") | J7: =IFERROR(VLOOKUP($A7,subQ,MATCH(J$1,SUBQH,0),0),"") | K7: =IFERROR(VLOOKUP($A7,subQ,MATCH(K$1,SUBQH,0),0),"") | L7: =IFERROR(VLOOKUP($A7,subQ,MATCH(L$1,SUBQH,0),0),"")
A8: 판관비 | D8: 판매비와관리비 | E8: =IFERROR(VLOOKUP($A8,subQ,MATCH(E$1,SUBQH,0),0),"") | F8: =IFERROR(VLOOKUP($A8,subQ,MATCH(F$1,SUBQH,0),0),"") | G8: =IFERROR(VLOOKUP($A8,subQ,MATCH(G$1,SUBQH,0),0),"") | H8: =IFERROR(VLOOKUP($A8,subQ,MATCH(H$1,SUBQH,0),0),"") | I8: =IFERROR(VLOOKUP($A8,subQ,MATCH(I$1,SUBQH,0),0),"") | J8: =IFERROR(VLOOKUP($A8,subQ,MATCH(J$1,SUBQH,0),0),"") | K8: =IFERROR(VLOOKUP($A8,subQ,MATCH(K$1,SUBQH,0),0),"") | L8: =IFERROR(VLOOKUP($A8,subQ,MATCH(L$1,SUBQH,0),0),"")
A9: 영업이익 | D9: 영업이익 | E9: =IFERROR(VLOOKUP($A9,subQ,MATCH(E$1,SUBQH,0),0),"") | F9: =IFERROR(VLOOKUP($A9,subQ,MATCH(F$1,SUBQH,0),0),"") | G9: =IFERROR(VLOOKUP($A9,subQ,MATCH(G$1,SUBQH,0),0),"") | H9: =IFERROR(VLOOKUP($A9,subQ,MATCH(H$1,SUBQH,0),0),"") | I9: =IFERROR(VLOOKUP($A9,subQ,MATCH(I$1,SUBQH,0),0),"") | J9: =IFERROR(VLOOKUP($A9,subQ,MATCH(J$1,SUBQH,0),0),"") | K9: =IFERROR(VLOOKUP($A9,subQ,MATCH(K$1,SUBQH,0),0),"") | L9: =IFERROR(VLOOKUP($A9,subQ,MATCH(L$1,SUBQH,0),0),"")
A10: OPM | D10: 영업이익률 | E10: =IFERROR(VLOOKUP($A10,subQ,MATCH(E$1,SUBQH,0),0),"") | F10: =IFERROR(VLOOKUP($A10,subQ,MATCH(F$1,SUBQH,0),0),"") | G10: =IFERROR(VLOOKUP($A10,subQ,MATCH(G$1,SUBQH,0),0),"") | H10: =IFERROR(VLOOKUP($A10,subQ,MATCH(H$1,SUBQH,0),0),"") | I10: =IFERROR(VLOOKUP($A10,subQ,MATCH(I$1,SUBQH,0),0),"") | J10: =IFERROR(VLOOKUP($A10,subQ,MATCH(J$1,SUBQH,0),0),"") | K10: =IFERROR(VLOOKUP($A10,subQ,MATCH(K$1,SUBQH,0),0),"") | L10: =IFERROR(VLOOKUP($A10,subQ,MATCH(L$1,SUBQH,0),0),"")
A11: 금융손익 | D11: 금융손익(이자·환 포함) | E11: =IFERROR(VLOOKUP($A11,subQ,MATCH(E$1,SUBQH,0),0),"") | F11: =IFERROR(VLOOKUP($A11,subQ,MATCH(F$1,SUBQH,0),0),"") | G11: =IFERROR(VLOOKUP($A11,subQ,MATCH(G$1,SUBQH,0),0),"") | H11: =IFERROR(VLOOKUP($A11,subQ,MATCH(H$1,SUBQH,0),0),"") | I11: =IFERROR(VLOOKUP($A11,subQ,MATCH(I$1,SUBQH,0),0),"") | J11: =IFERROR(VLOOKUP($A11,subQ,MATCH(J$1,SUBQH,0),0),"") | K11: =IFERROR(VLOOKUP($A11,subQ,MATCH(K$1,SUBQH,0),0),"") | L11: =IFERROR(VLOOKUP($A11,subQ,MATCH(L$1,SUBQH,0),0),"")
A12: 이자손익 | D12: 이자손익(이자수익 − 이자비용) | E12: =IFERROR(VLOOKUP($A12,subQ,MATCH(E$1,SUBQH,0),0),"") | F12: =IFERROR(VLOOKUP($A12,subQ,MATCH(F$1,SUBQH,0),0),"") | G12: =IFERROR(VLOOKUP($A12,subQ,MATCH(G$1,SUBQH,0),0),"") | H12: =IFERROR(VLOOKUP($A12,subQ,MATCH(H$1,SUBQH,0),0),"") | I12: =IFERROR(VLOOKUP($A12,subQ,MATCH(I$1,SUBQH,0),0),"") | J12: =IFERROR(VLOOKUP($A12,subQ,MATCH(J$1,SUBQH,0),0),"") | K12: =IFERROR(VLOOKUP($A12,subQ,MATCH(K$1,SUBQH,0),0),"") | L12: =IFERROR(VLOOKUP($A12,subQ,MATCH(L$1,SUBQH,0),0),"")
A13: 외환손익 | D13: 외환손익(실적만; 추정 환효과는 환관련손익) | E13: =IFERROR(VLOOKUP($A13,subQ,MATCH(E$1,SUBQH,0),0),"") | F13: =IFERROR(VLOOKUP($A13,subQ,MATCH(F$1,SUBQH,0),0),"") | G13: =IFERROR(VLOOKUP($A13,subQ,MATCH(G$1,SUBQH,0),0),"") | H13: =IFERROR(VLOOKUP($A13,subQ,MATCH(H$1,SUBQH,0),0),"") | I13: =IFERROR(VLOOKUP($A13,subQ,MATCH(I$1,SUBQH,0),0),"") | J13: =IFERROR(VLOOKUP($A13,subQ,MATCH(J$1,SUBQH,0),0),"") | K13: =IFERROR(VLOOKUP($A13,subQ,MATCH(K$1,SUBQH,0),0),"") | L13: =IFERROR(VLOOKUP($A13,subQ,MATCH(L$1,SUBQH,0),0),"")
A14: 파생상품손익 | D14: 파생상품손익 | E14: =IFERROR(VLOOKUP($A14,subQ,MATCH(E$1,SUBQH,0),0),"") | F14: =IFERROR(VLOOKUP($A14,subQ,MATCH(F$1,SUBQH,0),0),"") | G14: =IFERROR(VLOOKUP($A14,subQ,MATCH(G$1,SUBQH,0),0),"") | H14: =IFERROR(VLOOKUP($A14,subQ,MATCH(H$1,SUBQH,0),0),"") | I14: =IFERROR(VLOOKUP($A14,subQ,MATCH(I$1,SUBQH,0),0),"") | J14: =IFERROR(VLOOKUP($A14,subQ,MATCH(J$1,SUBQH,0),0),"") | K14: =IFERROR(VLOOKUP($A14,subQ,MATCH(K$1,SUBQH,0),0),"") | L14: =IFERROR(VLOOKUP($A14,subQ,MATCH(L$1,SUBQH,0),0),"")
A15: 기타금융손익 | D15: 기타금융손익(금융손익 잔차) | E15: =IFERROR(VLOOKUP($A15,subQ,MATCH(E$1,SUBQH,0),0),"") | F15: =IFERROR(VLOOKUP($A15,subQ,MATCH(F$1,SUBQH,0),0),"") | G15: =IFERROR(VLOOKUP($A15,subQ,MATCH(G$1,SUBQH,0),0),"") | H15: =IFERROR(VLOOKUP($A15,subQ,MATCH(H$1,SUBQH,0),0),"") | I15: =IFERROR(VLOOKUP($A15,subQ,MATCH(I$1,SUBQH,0),0),"") | J15: =IFERROR(VLOOKUP($A15,subQ,MATCH(J$1,SUBQH,0),0),"") | K15: =IFERROR(VLOOKUP($A15,subQ,MATCH(K$1,SUBQH,0),0),"") | L15: =IFERROR(VLOOKUP($A15,subQ,MATCH(L$1,SUBQH,0),0),"")
A16: 기타영업외손익 | D16: 기타영업외손익 | E16: =IFERROR(VLOOKUP($A16,subQ,MATCH(E$1,SUBQH,0),0),"") | F16: =IFERROR(VLOOKUP($A16,subQ,MATCH(F$1,SUBQH,0),0),"") | G16: =IFERROR(VLOOKUP($A16,subQ,MATCH(G$1,SUBQH,0),0),"") | H16: =IFERROR(VLOOKUP($A16,subQ,MATCH(H$1,SUBQH,0),0),"") | I16: =IFERROR(VLOOKUP($A16,subQ,MATCH(I$1,SUBQH,0),0),"") | J16: =IFERROR(VLOOKUP($A16,subQ,MATCH(J$1,SUBQH,0),0),"") | K16: =IFERROR(VLOOKUP($A16,subQ,MATCH(K$1,SUBQH,0),0),"") | L16: =IFERROR(VLOOKUP($A16,subQ,MATCH(L$1,SUBQH,0),0),"")
... A39: NPM | D39: NPM | E39: =IFERROR(VLOOKUP($A39,subQ,MATCH(E$1,SUBQH,0),0),"") | F39: =IFERROR(VLOOKUP($A39,subQ,MATCH(F$1,SUBQH,0),0),"") | G39: =IFERROR(VLOOKUP($A39,subQ,MATCH(G$1,SUBQH,0),0),"") | H39: =IFERROR(VLOOKUP($A39,subQ,MATCH(H$1,SUBQH,0),0),"") | I39: =IFERROR(VLOOKUP($A39,subQ,MATCH(I$1,SUBQH,0),0),"") | J39: =IFERROR(VLOOKUP($A39,subQ,MATCH(J$1,SUBQH,0),0),"") | K39: =IFERROR(VLOOKUP($A39,subQ,MATCH(K$1,SUBQH,0),0),"") | L39: =IFERROR(VLOOKUP($A39,subQ,MATCH(L$1,SUBQH,0),0),"")
A40: 매출액 YoY | D40: 매출액 YoY | F40: =IFERROR(F5/E5-1,"") | G40: =IFERROR(G5/F5-1,"") | H40: =IFERROR(H5/G5-1,"") | I40: =IFERROR(I5/H5-1,"") | J40: =IFERROR(J5/I5-1,"") | K40: =IFERROR(K5/J5-1,"") | L40: =IFERROR(L5/K5-1,"")
A41: 영업이익 YoY | D41: 영업이익 YoY | F41: =IFERROR(F9/E9-1,"") | G41: =IFERROR(G9/F9-1,"") | H41: =IFERROR(H9/G9-1,"") | I41: =IFERROR(I9/H9-1,"") | J41: =IFERROR(J9/I9-1,"") | K41: =IFERROR(K9/J9-1,"") | L41: =IFERROR(L9/K9-1,"")
A42: 지배주주순이익 YoY | D42: 지배주주순이익 YoY | F42: =IFERROR(F20/E20-1,"") | G42: =IFERROR(G20/F20-1,"") | H42: =IFERROR(H20/G20-1,"") | I42: =IFERROR(I20/H20-1,"") | J42: =IFERROR(J20/I20-1,"") | K42: =IFERROR(K20/J20-1,"") | L42: =IFERROR(L20/K20-1,"")

Sheet TP
B1: 종가 | C1: =변수!D43
B2: 기준일 | C2: =변수!D44
B3: 모델 산출값 — 목표주가·추천 아님. 밴드·COE 는 변수 시트 3절의 가정
C5: FY | D5: 2025 | E5: 2026 | F5: 2027 | G5: 2028
D6: A | E6: E | F6: E | G6: E
C7: EPS(원) | D7: =IFERROR(VLOOKUP("EPS",subQ,MATCH(D$5,SUBQH,0),0),"") | E7: =IFERROR(VLOOKUP("EPS",subQ,MATCH(E$5,SUBQH,0),0),"") | F7: =IFERROR(VLOOKUP("EPS",subQ,MATCH(F$5,SUBQH,0),0),"") | G7: =IFERROR(VLOOKUP("EPS",subQ,MATCH(G$5,SUBQH,0),0),"")
C8: BPS(원) | D8: =IFERROR(VLOOKUP("BPS",subQ,MATCH(D$5,SUBQH,0),0),"") | E8: =IFERROR(VLOOKUP("BPS",subQ,MATCH(E$5,SUBQH,0),0),"") | F8: =IFERROR(VLOOKUP("BPS",subQ,MATCH(F$5,SUBQH,0),0),"") | G8: =IFERROR(VLOOKUP("BPS",subQ,MATCH(G$5,SUBQH,0),0),"")
C9: 지배주주순이익(억원) | D9: =IFERROR(VLOOKUP("지배주주순이익",subQ,MATCH(D$5,SUBQH,0),0),"") | E9: =IFERROR(VLOOKUP("지배주주순이익",subQ,MATCH(E$5,SUBQH,0),0),"") | F9: =IFERROR(VLOOKUP("지배주주순이익",subQ,MATCH(F$5,SUBQH,0),0),"") | G9: =IFERROR(VLOOKUP("지배주주순이익",subQ,MATCH(G$5,SUBQH,0),0),"")
C10: 영업이익(억원) | D10: =IFERROR(VLOOKUP("영업이익",subQ,MATCH(D$5,SUBQH,0),0),"") | E10: =IFERROR(VLOOKUP("영업이익",subQ,MATCH(E$5,SUBQH,0),0),"") | F10: =IFERROR(VLOOKUP("영업이익",subQ,MATCH(F$5,SUBQH,0),0),"") | G10: =IFERROR(VLOOKUP("영업이익",subQ,MATCH(G$5,SUBQH,0),0),"")
C11: ROE(EPS/기초BPS) | E11: =IFERROR(E7/D8,"") | F11: =IFERROR(F7/E8,"") | G11: =IFERROR(G7/F8,"")
B13: PER
C14: 12M fwd EPS | D14: =IFERROR(E7*변수!D49+F7*(1-변수!D49),"")
C15: 적정가치 @PER_lo | D15: =변수!D46 | E15: =IFERROR(ROUND($D$14*D15,-2),"") | F15: =IFERROR(E15/$C$1-1,"") | G15: 배 · 원 · 종가 대비
C16: 적정가치 @PER_mid | D16: =변수!D47 | E16: =IFERROR(ROUND($D$14*D16,-2),"") | F16: =IFERROR(E16/$C$1-1,"") | G16: 배 · 원 · 종가 대비
C17: 적정가치 @PER_hi | D17: =변수!D48 | E17: =IFERROR(ROUND($D$14*D17,-2),"") | F17: =IFERROR(E17/$C$1-1,"") | G17: 배 · 원 · 종가 대비
C18: 현재 PER(종가/12M fwd EPS) | D18: =IFERROR($C$1/$D$14,"")
B20: PBR
C21: 최근 BPS(마지막 실적 분기) | D21: =IFERROR(VLOOKUP("BPS",subQ,MATCH("2Q26",SUBQH,0),0),"")
C22: ROE fwd(12M fwd EPS / BPS) | D22: =IFERROR($D$14/$D$21,"")
C23: COE | D23: =변수!D45
C24: 적정 PBR = ROE/COE | D24: =IFERROR(D22/D23,"")
C25: 적정가치(PBR) = BPS × 적정PBR | D25: =IFERROR(ROUND(D21*D24,-2),"") | E25: =IFERROR(D25/$C$1-1,"")
C26: 현재 PBR(종가/BPS) | D26: =IFERROR($C$1/D21,"")
B28: 모델 json valuation(참고)
C29: eps_fwd12m | D29: 1665.6
C30: bps_latest | D30: 7258.1
C31: per_now | D31: 3.78
C32: pbr_now | D32: 0.87
C33: roe_fwd | D33: 0.2295
C34: fair_pbr | D34: 2.55
C35: fair_value_pbr | D35: 18500
C36: ev_ebitda
C37: note | D37: 모델 산출값 — 목표주가·추천 아님

Sheet 외화
C1: 이름: 외화QH — 환율 QoQ · 외화 순노출 × Δ기말환율 | E1: 4Q21 | F1: 1Q22 | G1: 2Q22 | H1: 3Q22 | I1: 4Q22 | J1: 1Q23 | K1: 2Q23 | L1: 3Q23 | M1: 4Q23 | N1: 1Q24 | O1: 2Q24 | P1: 3Q24 | Q1: 4Q24 | R1: 1Q25 | S1: 2Q25 | T1: 3Q25 | U1: 4Q25 | V1: 1Q26 | W1: 2Q26 | X1: 3Q26 | Y1: 4Q26 | Z1: 1Q27 | AA1: 2Q27 | AB1: 3Q27 | AC1: 4Q27 | AD1: 1Q28 | AE1: 2Q28 | AF1: 3Q28 | AG1: 4Q28
E3: 1 | F3: 2 | G3: 3 | H3: 4 | I3: 5 | J3: 6 | K3: 7 | L3: 8 | M3: 9 | N3: 10 | O3: 11 | P3: 12 | Q3: 13 | R3: 14 | S3: 15 | T3: 16 | U3: 17 | V3: 18 | W3: 19 | X3: 20 | Y3: 21 | Z3: 22 | AA3: 23 | AB3: 24 | AC3: 25 | AD3: 26 | AE3: 27 | AF3: 28 | AG3: 29
E4: 2021.12 | F4: 2022.03 | G4: 2022.06 | H4: 2022.09 | I4: 2022.12 | J4: 2023.03 | K4: 2023.06 | L4: 2023.09 | M4: 2023.12 | N4: 2024.03 | O4: 2024.06 | P4: 2024.09 | Q4: 2024.12 | R4: 2025.03 | S4: 2025.06 | T4: 2025.09 | U4: 2025.12 | V4: 2026.03 | W4: 2026.06 | X4: 2026.09 | Y4: 2026.12 | Z4: 2027.03 | AA4: 2027.06 | AB4: 2027.09 | AC4: 2027.12 | AD4: 2028.03 | AE4: 2028.06 | AF4: 2028.09 | AG4: 2028.12
D5: 원/달러(평균) | E5: =IFERROR(VLOOKUP($D5,환율,MATCH(E$1,변수H,0),0),"") | F5: =IFERROR(VLOOKUP($D5,환율,MATCH(F$1,변수H,0),0),"") | G5: =IFERROR(VLOOKUP($D5,환율,MATCH(G$1,변수H,0),0),"") | H5: =IFERROR(VLOOKUP($D5,환율,MATCH(H$1,변수H,0),0),"") | I5: =IFERROR(VLOOKUP($D5,환율,MATCH(I$1,변수H,0),0),"") | J5: =IFERROR(VLOOKUP($D5,환율,MATCH(J$1,변수H,0),0),"") | K5: =IFERROR(VLOOKUP($D5,환율,MATCH(K$1,변수H,0),0),"") | L5: =IFERROR(VLOOKUP($D5,환율,MATCH(L$1,변수H,0),0),"") | ... AG5: =IFERROR(VLOOKUP($D5,환율,MATCH(AG$1,변수H,0),0),"")
A6: 원/달러(평균) QoQ | F6: =IFERROR(F5/E5-1,"") | G6: =IFERROR(G5/F5-1,"") | H6: =IFERROR(H5/G5-1,"") | I6: =IFERROR(I5/H5-1,"") | J6: =IFERROR(J5/I5-1,"") | K6: =IFERROR(K5/J5-1,"") | L6: =IFERROR(L5/K5-1,"") | M6: =IFERROR(M5/L5-1,"") | ... AG6: =IFERROR(AG5/AF5-1,"")
D7: 원/달러(기말) | E7: =IFERROR(VLOOKUP($D7,환율,MATCH(E$1,변수H,0),0),"") | F7: =IFERROR(VLOOKUP($D7,환율,MATCH(F$1,변수H,0),0),"") | G7: =IFERROR(VLOOKUP($D7,환율,MATCH(G$1,변수H,0),0),"") | H7: =IFERROR(VLOOKUP($D7,환율,MATCH(H$1,변수H,0),0),"") | I7: =IFERROR(VLOOKUP($D7,환율,MATCH(I$1,변수H,0),0),"") | J7: =IFERROR(VLOOKUP($D7,환율,MATCH(J$1,변수H,0),0),"") | K7: =IFERROR(VLOOKUP($D7,환율,MATCH(K$1,변수H,0),0),"") | L7: =IFERROR(VLOOKUP($D7,환율,MATCH(L$1,변수H,0),0),"") | ... AG7: =IFERROR(VLOOKUP($D7,환율,MATCH(AG$1,변수H,0),0),"")
A8: 원/달러(기말) QoQ | F8: =IFERROR(F7/E7-1,"") | G8: =IFERROR(G7/F7-1,"") | H8: =IFERROR(H7/G7-1,"") | I8: =IFERROR(I7/H7-1,"") | J8: =IFERROR(J7/I7-1,"") | K8: =IFERROR(K7/J7-1,"") | L8: =IFERROR(L7/K7-1,"") | M8: =IFERROR(M7/L7-1,"") | ... AG8: =IFERROR(AG7/AF7-1,"")
D9: W/Euro(평균) | E9: =IFERROR(VLOOKUP($D9,환율,MATCH(E$1,변수H,0),0),"") | F9: =IFERROR(VLOOKUP($D9,환율,MATCH(F$1,변수H,0),0),"") | G9: =IFERROR(VLOOKUP($D9,환율,MATCH(G$1,변수H,0),0),"") | H9: =IFERROR(VLOOKUP($D9,환율,MATCH(H$1,변수H,0),0),"") | I9: =IFERROR(VLOOKUP($D9,환율,MATCH(I$1,변수H,0),0),"") | J9: =IFERROR(VLOOKUP($D9,환율,MATCH(J$1,변수H,0),0),"") | K9: =IFERROR(VLOOKUP($D9,환율,MATCH(K$1,변수H,0),0),"") | L9: =IFERROR(VLOOKUP($D9,환율,MATCH(L$1,변수H,0),0),"") | ... AG9: =IFERROR(VLOOKUP($D9,환율,MATCH(AG$1,변수H,0),0),"")
A10: W/Euro(평균) QoQ | F10: =IFERROR(F9/E9-1,"") | G10: =IFERROR(G9/F9-1,"") | H10: =IFERROR(H9/G9-1,"") | I10: =IFERROR(I9/H9-1,"") | J10: =IFERROR(J9/I9-1,"") | K10: =IFERROR(K9/J9-1,"") | L10: =IFERROR(L9/K9-1,"") | M10: =IFERROR(M9/L9-1,"") | ... AG10: =IFERROR(AG9/AF9-1,"")
D11: W/Euro(기말) | E11: =IFERROR(VLOOKUP($D11,환율,MATCH(E$1,변수H,0),0),"") | F11: =IFERROR(VLOOKUP($D11,환율,MATCH(F$1,변수H,0),0),"") | G11: =IFERROR(VLOOKUP($D11,환율,MATCH(G$1,변수H,0),0),"") | H11: =IFERROR(VLOOKUP($D11,환율,MATCH(H$1,변수H,0),0),"") | I11: =IFERROR(VLOOKUP($D11,환율,MATCH(I$1,변수H,0),0),"") | J11: =IFERROR(VLOOKUP($D11,환율,MATCH(J$1,변수H,0),0),"") | K11: =IFERROR(VLOOKUP($D11,환율,MATCH(K$1,변수H,0),0),"") | L11: =IFERROR(VLOOKUP($D11,환율,MATCH(L$1,변수H,0),0),"") | ... AG11: =IFERROR(VLOOKUP($D11,환율,MATCH(AG$1,변수H,0),0),"")
A12: W/Euro(기말) QoQ | F12: =IFERROR(F11/E11-1,"") | G12: =IFERROR(G11/F11-1,"") | H12: =IFERROR(H11/G11-1,"") | I12: =IFERROR(I11/H11-1,"") | J12: =IFERROR(J11/I11-1,"") | K12: =IFERROR(K11/J11-1,"") | L12: =IFERROR(L11/K11-1,"") | M12: =IFERROR(M11/L11-1,"") | ... AG12: =IFERROR(AG11/AF11-1,"")
D13: 원/100Y(기말) | E13: =IFERROR(VLOOKUP($D13,환율,MATCH(E$1,변수H,0),0),"") | F13: =IFERROR(VLOOKUP($D13,환율,MATCH(F$1,변수H,0),0),"") | G13: =IFERROR(VLOOKUP($D13,환율,MATCH(G$1,변수H,0),0),"") | H13: =IFERROR(VLOOKUP($D13,환율,MATCH(H$1,변수H,0),0),"") | I13: =IFERROR(VLOOKUP($D13,환율,MATCH(I$1,변수H,0),0),"") | J13: =IFERROR(VLOOKUP($D13,환율,MATCH(J$1,변수H,0),0),"") | K13: =IFERROR(VLOOKUP($D13,환율,MATCH(K$1,변수H,0),0),"") | L13: =IFERROR(VLOOKUP($D13,환율,MATCH(L$1,변수H,0),0),"") | ... AG13: =IFERROR(VLOOKUP($D13,환율,MATCH(AG$1,변수H,0),0),"")
A14: 원/100Y(기말) QoQ | F14: =IFERROR(F13/E13-1,"") | G14: =IFERROR(G13/F13-1,"") | H14: =IFERROR(H13/G13-1,"") | I14: =IFERROR(I13/H13-1,"") | J14: =IFERROR(J13/I13-1,"") | K14: =IFERROR(K13/J13-1,"") | L14: =IFERROR(L13/K13-1,"") | M14: =IFERROR(M13/L13-1,"") | ... AG14: =IFERROR(AG13/AF13-1,"")
A16: 외화순노출 | C16: 외화 순노출(백만$) | D16: =변수!D56 | E16: 외화 순노출 × Δ기말환율 (외화 시트 방식)
A17: 환관련손익추정 | C17: 환관련손익 추정(억원) = 순노출 × Δ원/달러(기말) / 100 | F17: =IFERROR($D$16*(F7-E7)/100,"") | G17: =IFERROR($D$16*(G7-F7)/100,"") | H17: =IFERROR($D$16*(H7-G7)/100,"") | I17: =IFERROR($D$16*(I7-H7)/100,"") | J17: =IFERROR($D$16*(J7-I7)/100,"") | K17: =IFERROR($D$16*(K7-J7)/100,"") | L17: =IFERROR($D$16*(L7-K7)/100,"") | M17: =IFERROR($D$16*(M7-L7)/100,"") | ... AG17: =IFERROR($D$16*(AG7-AF7)/100,"")
A18: fx_pnl.by_q | C18: 모델 fx_pnl.by_q(억원, 참고)
C19: 외화 순노출 미공시(face) → 0 + 표기
