Workbook
Name 변수H: 변수!$C$1:$AO$1
Name 환율: 변수!$C$6:$AO$13
Name BS연결H: BS연결!$C$1:$AO$1
Name BS연결: BS연결!$C$5:$AO$5
Name BS별도H: BS별도!$C$1:$AO$1
Name BS별도: BS별도!$C$5:$AO$88
Name SUBQH: subQ!$A$1:$AO$1
Name subQ: subQ!$A$5:$AO$41

Sheet README
A1: 해성에어로보틱스(059270) 실적 모델 — ARGUS 한국조선
A2: 기준 분기 2026Q2 · 마지막 실적 2026Q2 · 생성 2026-10-14
A3: 모든 수치는 모델 산출값(DART 공개 재무제표 + 우리 추정)이다 — 목표주가·투자 추천 아님. 참고용 · 투자조언 아님.
A5: 시트
A6: 변수 가정 시계열. 환율 8행(ECB via frankfurter — L2 fx.json; 추정 분기 = 노란 가정), 추정 드라이버(노란 셀 = 모델값에서 역산한 가정, 바꾸면 재계산; 연녹 셀 = 3절 스칼라 참조 수식), 3절 스칼라 가정(세율·판관비율·지배주주비중·이자율·종가·PER 밴드·COE·외화 순노출·헤지비율)
A7: BS연결/BS별도 FnGuide 계정명 × 기간 값 덤프(백만원). 행1 분기라벨, 행4 YYYY.MM / YYYY.12A. 이름정의 BS연결H·BS연결(계정명 C열부터)
A8: subQ 분기 서브모델(억원 = 백만원/100). 확정 행: =IFERROR(VLOOKUP($D행,BS연결,MATCH(E$1,BS연결H,0),0)/100,"") 추정 행: 변수 시트 가정 셀 참조 수식. 외환손익·파생상품손익은 BS 계정 합·차, 기타금융손익은 잔차, OPM·EPS·BPS·PER·PBR 은 파생 수식, 조정EPS 는 EPS 참조(일회성 의심 분기만 산식 셀)
A9: SLS 선표(조선사만, sls json 있을 때): 요약 행(sls 저장값) + 계약별 스케줄(백만$) × (헤지비율 × 헤지환율 + (1−헤지비율) × 건조시점 환율[변수 원/달러(평균)]) → 원화 수식 블록 → 합계 행이 subQ 매출조선에 연결
A10: 시나리오 신규수주 보수/기준/낙관(forecast_panel 패널, 모델에 scenarios 가 있을 때만): 매출액·영업이익 = subQ 기준값 ± (시나리오 신규 − base 신규) × OPM. base 만 subQ 행에 포함, 나머지는 합산 안 함
A11: 분기/연간예상 subQ 를 이름(A열 key)으로 VLOOKUP 한 보고서 표(억원)
A12: TP PER 밴드 × 12M fwd EPS, PBR = ROE/COE × BPS — 모델 산출값 구간, 목표주가·추천 아님
A13: 외화 환율 QoQ, 외화 순노출 × Δ기말환율 → 환관련손익 추정
... A35: 백테스트: {"freeze": "2025Q2", "horizon": 4, "revenue_wape_pct": 14.0, "op_wape_pct": 60.1, "n": 4, "note": "단일 회사 4분기 — 통계 아님", "driver_at_freeze": "trend_seasonal", "selection_oos_at_freeze": {"wape_link": null, "wape_trend": null, "adopted": false, "decision": "rejected", "note": "유의성 조건 미달 → OOS 비교 전 기각"}, "frozen_inputs": "fin(연결/별도)·고객 조선사 모델·지주 자회사 모델은 2025Q2 까지의 분기만; 선표는 체결일 ≤ 2025Q2 말일 계약(원장 최신 금액·코호트 등급, 환산 없음); 잔고는 yards_cache 2025Q2; 시세·환율 forward·prices·forecast_panel 신규수주 미사용. 고객 가중치(suppliers.json 언급 비중)와 합병 체인링크는 현재 지식; 고객 연동 채택은 동결 모델 안에서도 자기 la−4분기 OOS 규칙(selection_oos_at_freeze)", "detail": [{"q": "2025Q3", "rev_pred": 33.32, "rev_act": 38.02, "op_pred": -2.52, "op_act": -0.27}, {"q": "2025Q4", "rev_pred": 35.25, "rev_act": 42.11, "op_pred": -2.67, "op_act": -2.29}, {"q": "2026Q1", "rev_pred": 30.03, "rev_act": 32.86, "op_pred": -2.27, "op_act": -3.04}, {"q": "2026Q2", "rev_pred": 39.2, "rev_act": 33.15, "op_pred": -2.97, "op_act": -7.36}]}

Sheet 변수
C1: 이름: 변수H | E1: 4Q21 | F1: 2021 | G1: 1Q22 | H1: 2Q22 | I1: 3Q22 | J1: 4Q22 | K1: 2022 | L1: 1Q23 | M1: 2Q23 | N1: 3Q23 | O1: 4Q23 | P1: 2023 | Q1: 1Q24 | R1: 2Q24 | S1: 3Q24 | T1: 4Q24 | U1: 2024 | V1: 1Q25 | W1: 2Q25 | X1: 3Q25 | Y1: 4Q25 | Z1: 2025 | AA1: 1Q26 | AB1: 2Q26 | AC1: 3Q26 | AD1: 4Q26 | AE1: 2026 | AF1: 1Q27 | AG1: 2Q27 | AH1: 3Q27 | AI1: 4Q27 | AJ1: 2027 | AK1: 1Q28 | AL1: 2Q28 | AM1: 3Q28 | AN1: 4Q28 | AO1: 2028
A2: 가정 시계열 — 노란 셀은 추정 가정(모델값에서 역산), 연녹 셀은 3절 스칼라 참조 수식. 바꾸면 subQ·분기·연간예상·TP·시나리오가 재계산됩니다.
E3: 1 | F3: 2 | G3: 3 | H3: 4 | I3: 5 | J3: 6 | K3: 7 | L3: 8 | M3: 9 | N3: 10 | O3: 11 | P3: 12 | Q3: 13 | R3: 14 | S3: 15 | T3: 16 | U3: 17 | V3: 18 | W3: 19 | X3: 20 | Y3: 21 | Z3: 22 | AA3: 23 | AB3: 24 | AC3: 25 | AD3: 26 | AE3: 27 | AF3: 28 | AG3: 29 | AH3: 30 | AI3: 31 | AJ3: 32 | AK3: 33 | AL3: 34 | AM3: 35 | AN3: 36 | AO3: 37
E4: 2021.12 | F4: 2021.12A | G4: 2022.03 | H4: 2022.06 | I4: 2022.09 | J4: 2022.12 | K4: 2022.12A | L4: 2023.03 | M4: 2023.06 | N4: 2023.09 | O4: 2023.12 | P4: 2023.12A | Q4: 2024.03 | R4: 2024.06 | S4: 2024.09 | T4: 2024.12 | U4: 2024.12A | V4: 2025.03 | W4: 2025.06 | X4: 2025.09 | Y4: 2025.12 | Z4: 2025.12A | AA4: 2026.03 | AB4: 2026.06 | AC4: 2026.09 | AD4: 2026.12 | AE4: 2026.12A | AF4: 2027.03 | AG4: 2027.06 | AH4: 2027.09 | AI4: 2027.12 | AJ4: 2027.12A | AK4: 2028.03 | AL4: 2028.06 | AM4: 2028.09 | AN4: 2028.12 | AO4: 2028.12A
B5: 1. FX | C5: 이름: 환율
A6: USDKRW_avg | C6: 원/달러(평균) | E6: 1183.5 | F6: 1145.51 | G6: 1205.78 | H6: 1262.09 | I6: 1341.93 | J6: 1360.12 | K6: 1292.98 | L6: 1276.95 | M6: 1315.69 | N6: 1313.62 | O6: 1322.01 | P6: 1306.85 | Q6: 1330.14 | R6: 1371.28 | S6: 1356.22 | T6: 1396.3 | U6: 1363.53 | V6: 1452.28 | W6: 1398.52 | X6: 1386.95 | Y6: 1449.19 | Z6: 1421.52 | AA6: 1466.12 | AB6: 1501.75 | AC6: 1418.75 | AD6: 1343.39 | AE6: 1456.01 | AF6: 1341.45 | AG6: 1341.45 | AH6: 1341.45 | AI6: 1341.45 | AK6: 1341.45 | AL6: 1341.45 | AM6: 1341.45 | AN6: 1341.45
A7: USDKRW_end | C7: 원/달러(기말) | E7: 1188.75 | F7: 1188.75 | G7: 1213.74 | H7: 1301.24 | I7: 1436.9 | J7: 1260.16 | K7: 1260.16 | L7: 1305.99 | M7: 1321.44 | N7: 1345.35 | O7: 1297.43 | P7: 1297.43 | Q7: 1349.25 | R7: 1377.73 | S7: 1312.17 | T7: 1474.78 | U7: 1474.78 | V7: 1474.54 | W7: 1355.13 | X7: 1403.67 | Y7: 1444.2 | Z7: 1444.2 | AA7: 1524.8 | AB7: 1550.89 | AC7: 1355.4 | AD7: 1341.45 | AE7: 1341.45 | AF7: 1341.45 | AG7: 1341.45 | AH7: 1341.45 | AI7: 1341.45 | AK7: 1341.45 | AL7: 1341.45 | AM7: 1341.45 | AN7: 1341.45
A8: JPY100KRW_avg | C8: 원/100Y(평균) | E8: 1041.02 | F8: 1042.74 | G8: 1036.79 | H8: 972.23 | I8: 970.61 | J8: 961.03 | K8: 985.1 | L8: 964.89 | M8: 957.36 | N8: 909 | O8: 893.22 | P8: 931.11 | Q8: 896.29 | R8: 880.14 | S8: 909.35 | T8: 917.25 | U8: 900.92 | V8: 952.59 | W8: 967.92 | X8: 940.32 | Y8: 940.77 | Z8: 950.17 | AA8: 934.39 | AB8: 942.16 | AC8: 890.41 | AD8: 849.39 | AE8: 918.46 | AF8: 848.37 | AG8: 848.37 | AH8: 848.37 | AI8: 848.37 | AK8: 848.37 | AL8: 848.37 | AM8: 848.37 | AN8: 848.37
A9: JPY100KRW_end | C9: 원/100Y(기말) | E9: 1032.62 | F9: 1032.62 | G9: 996.83 | H9: 954.9 | I9: 993.29 | J9: 955.54 | K9: 955.54 | L9: 980.62 | M9: 913.67 | N9: 901.47 | O9: 917.04 | P9: 917.04 | Q9: 892.42 | R9: 857.76 | S9: 919.21 | T9: 939.65 | U9: 939.65 | V9: 986.84 | W9: 938.85 | X9: 948.49 | Y9: 921.81 | Z9: 921.81 | AA9: 955.99 | AB9: 954.75 | AC9: 863.31 | AD9: 848.37 | AE9: 848.37 | AF9: 848.37 | AG9: 848.37 | AH9: 848.37 | AI9: 848.37 | AK9: 848.37 | AL9: 848.37 | AM9: 848.37 | AN9: 848.37
A10: EURKRW_avg | C10: W/Euro(평균) | E10: 1353.32 | F10: 1354.06 | G10: 1352.29 | H10: 1343.31 | I10: 1350.63 | J10: 1386.07 | K10: 1358.07 | L10: 1369.93 | M10: 1432.41 | N10: 1429.41 | O10: 1420.91 | P10: 1412.88 | Q10: 1444.21 | R10: 1476.42 | S10: 1489.3 | T10: 1490.78 | U10: 1475.4 | V10: 1528.33 | W10: 1585.13 | X10: 1620.04 | Y10: 1686.02 | Z10: 1605.45 | AA10: 1715.47 | AB10: 1746.09 | AC10: 1631.97 | AD10: 1506.62 | AE10: 1688.01 | AF10: 1500.82 | AG10: 1500.82 | AH10: 1500.82 | AI10: 1500.82 | AK10: 1500.82 | AL10: 1500.82 | AM10: 1500.82 | AN10: 1500.82
A11: EURKRW_end | C11: W/Euro(기말) | E11: 1346.38 | F11: 1346.38 | G11: 1347.37 | H11: 1351.6 | I11: 1400.62 | J11: 1344.08 | K11: 1344.08 | L11: 1420.26 | M11: 1435.88 | N11: 1425.26 | O11: 1433.66 | P11: 1433.66 | Q11: 1458.68 | R11: 1474.86 | S11: 1469.1 | T11: 1532.14 | U11: 1532.14 | V11: 1594.72 | W11: 1588.22 | X11: 1648.04 | Y11: 1696.94 | Z11: 1696.94 | AA11: 1753.21 | AB11: 1767.09 | AC11: 1539.06 | AD11: 1500.82 | AE11: 1500.82 | AF11: 1500.82 | AG11: 1500.82 | AH11: 1500.82 | AI11: 1500.82 | AK11: 1500.82 | AL11: 1500.82 | AM11: 1500.82 | AN11: 1500.82
A12: CNYKRW_avg | C12: 원/중국원(평균) | E12: 185.14 | F12: 177.65 | G12: 189.93 | H12: 190.76 | I12: 195.79 | J12: 191.09 | K12: 191.93 | L12: 186.59 | M12: 187.45 | N12: 181.28 | O12: 182.86 | P12: 184.52 | Q12: 185.04 | R12: 189.35 | S12: 189.24 | T12: 194.24 | U12: 189.49 | V12: 199.63 | W12: 193.41 | X12: 193.79 | Y12: 204.38 | Z12: 197.8 | AA12: 211.75 | AB12: 220.8 | AC12: 210.43 | AD12: 200.49 | AE12: 213.61 | AF12: 200.4 | AG12: 200.4 | AH12: 200.4 | AI12: 200.4 | AK12: 200.4 | AL12: 200.4 | AM12: 200.4 | AN12: 200.4
A13: CNYKRW_end | C13: 원/중국원(기말) | E13: 187.13 | F13: 187.13 | G13: 191.38 | H13: 194.13 | I13: 201.92 | J13: 182.67 | K13: 182.67 | L13: 189.97 | M13: 181.8 | N13: 184.26 | O13: 182.61 | P13: 182.61 | Q13: 186.66 | R13: 189.7 | S13: 187.12 | T13: 202.04 | U13: 202.04 | V13: 203.3 | W13: 189.14 | X13: 197.16 | Y13: 206.28 | Z13: 206.28 | AA13: 220.97 | AB13: 228.56 | AC13: 202.16 | AD13: 200.4 | AE13: 200.4 | AF13: 200.4 | AG13: 200.4 | AH13: 200.4 | AI13: 200.4 | AK13: 200.4 | AL13: 200.4 | AM13: 200.4 | AN13: 200.4
B14: 1b. 종가
A15: price_close_end | C15: 종가(기말) | E15: 9350 | G15: 9290 | H15: 6030 | I15: 8070 | J15: 5440 | L15: 8150 | M15: 7330 | N15: 6900 | O15: 7720 | Q15: 11090 | R15: 9730 | S15: 7980 | T15: 5230 | V15: 5720 | W15: 5810 | X15: 7130 | Y15: 9520 | AA15: 9680 | AB15: 6470 | AC15: 5460 | AD15: 4740
A16: price_high | C16: 종가(최고) | E16: 13950 | G16: 10500 | H16: 11500 | I16: 9500 | J16: 9330 | L16: 9900 | M16: 8590 | N16: 8100 | O16: 7750 | Q16: 19740 | R16: 12110 | S16: 14680 | T16: 9160 | V16: 9040 | W16: 7160 | X16: 7840 | Y16: 11350 | AA16: 21400 | AB16: 11650 | AC16: 6690 | AD16: 5640
A17: price_low | C17: 종가(최저) | E17: 6110 | G17: 6990 | H17: 5550 | I17: 5580 | J17: 5320 | L17: 5140 | M17: 6250 | N17: 5900 | O17: 5470 | Q17: 7140 | R17: 6680 | S17: 7660 | T17: 4700 | V17: 5430 | W17: 5430 | X17: 5000 | Y17: 6680 | AA17: 8730 | AB17: 5740 | AC17: 3980 | AD17: 4550
A18: price_avg | C18: 종가(평균) | E18: 8276.9 | G18: 8093.9 | H18: 8123.5 | I18: 7234 | J18: 6898.9 | L18: 7075.8 | M18: 7369.5 | N18: 6881.9 | O18: 6315.7 | Q18: 11433.4 | R18: 8840 | S18: 10702.7 | T18: 5805.4 | V18: 6676 | W18: 6135.7 | X18: 5837.1 | Y18: 8761.2 | AA18: 12345.9 | AB18: 9176.6 | AC18: 5525.9 | AD18: 5165
B20: 2. 추정 드라이버 | C20: 실적 열 = subQ 실현값(수식), 추정 열 = 가정(노란 = 모델값 역산, 연녹 = 3절 스칼라 참조)
A21: drv:매출액 | B21: yoy | C21: 매출액 YoY | J21: =IFERROR(subQ!J5/subQ!E5-1,"") | L21: =IFERROR(subQ!L5/subQ!G5-1,"") | M21: =IFERROR(subQ!M5/subQ!H5-1,"") | N21: =IFERROR(subQ!N5/subQ!I5-1,"") | O21: =IFERROR(subQ!O5/subQ!J5-1,"") | Q21: =IFERROR(subQ!Q5/subQ!L5-1,"") | R21: =IFERROR(subQ!R5/subQ!M5-1,"") | S21: =IFERROR(subQ!S5/subQ!N5-1,"") | T21: =IFERROR(subQ!T5/subQ!O5-1,"") | V21: =IFERROR(subQ!V5/subQ!Q5-1,"") | W21: =IFERROR(subQ!W5/subQ!R5-1,"") | X21: =IFERROR(subQ!X5/subQ!S5-1,"") | Y21: =IFERROR(subQ!Y5/subQ!T5-1,"") | AA21: =IFERROR(subQ!AA5/subQ!V5-1,"") | AB21: =IFERROR(subQ!AB5/subQ!W5-1,"") | AC21: 0.039041662 | AD21: 0.039034446 | AF21: 0.039101758 | AG21: 0.039109111 | AH21: 0.019493671 | AI21: 0.019428571 | AK21: 0.019332162 | AL21: 0.019448476 | AM21: 0.009684629 | AN21: 0.009865471
A22: drv:판관비 | B22: ratio | C22: 판관비율(/매출) | E22: =IFERROR(subQ!E8/subQ!E5,"") | F22: =IFERROR(subQ!F8/subQ!F5,"") | G22: =IFERROR(subQ!G8/subQ!G5,"") | H22: =IFERROR(subQ!H8/subQ!H5,"") | I22: =IFERROR(subQ!I8/subQ!I5,"") | J22: =IFERROR(subQ!J8/subQ!J5,"") | K22: =IFERROR(subQ!K8/subQ!K5,"") | L22: =IFERROR(subQ!L8/subQ!L5,"") | ... AB22: =IFERROR(subQ!AB8/subQ!AB5,"") | AC22: =$D$49 | AD22: =$D$49 | AE22: =IFERROR(subQ!AE8/subQ!AE5,"") | AF22: =$D$49 | AG22: =$D$49 | AH22: =$D$49 | AI22: =$D$49 | AJ22: =IFERROR(subQ!AJ8/subQ!AJ5,"") | AK22: =$D$49 | AL22: =$D$49 | AM22: =$D$49 | AN22: =$D$49 | AO22: =IFERROR(subQ!AO8/subQ!AO5,"")
A23: drv:영업이익 | B23: ratio | C23: 영업이익률(OPM) | E23: =IFERROR(subQ!E9/subQ!E5,"") | F23: =IFERROR(subQ!F9/subQ!F5,"") | G23: =IFERROR(subQ!G9/subQ!G5,"") | H23: =IFERROR(subQ!H9/subQ!H5,"") | I23: =IFERROR(subQ!I9/subQ!I5,"") | J23: =IFERROR(subQ!J9/subQ!J5,"") | K23: =IFERROR(subQ!K9/subQ!K5,"") | L23: =IFERROR(subQ!L9/subQ!L5,"") | ... AB23: =IFERROR(subQ!AB9/subQ!AB5,"") | AC23: -0.057974684 | AD23: -0.057828571 | AE23: =IFERROR(subQ!AE9/subQ!AE5,"") | AF23: -0.057996485 | AG23: -0.057764877 | AH23: -0.057859449 | AI23: -0.057847534 | AJ23: =IFERROR(subQ!AJ9/subQ!AJ5,"") | AK23: -0.057758621 | AL23: -0.057801822 | AM23: -0.05779636 | AN23: -0.05794849 | AO23: =IFERROR(subQ!AO9/subQ!AO5,"")
A24: drv:외환손익 | B24: abs | C24: 외환손익 (가정, 억원) | E24: =subQ!E13 | F24: =subQ!F13 | G24: =subQ!G13 | H24: =subQ!H13 | I24: =subQ!I13 | J24: =subQ!J13 | K24: =subQ!K13 | L24: =subQ!L13 | ... AB24: =subQ!AB13 | AC24: 0 | AD24: 0 | AE24: =subQ!AE13 | AF24: 0 | AG24: 0 | AH24: 0 | AI24: 0 | AJ24: =subQ!AJ13 | AK24: 0 | AL24: 0 | AM24: 0 | AN24: 0 | AO24: =subQ!AO13
A25: drv:기타영업외손익 | B25: abs | C25: 기타영업외손익 (가정, 억원) | E25: =subQ!E14 | F25: =subQ!F14 | G25: =subQ!G14 | H25: =subQ!H14 | I25: =subQ!I14 | J25: =subQ!J14 | K25: =subQ!K14 | L25: =subQ!L14 | ... AB25: =subQ!AB14 | AC25: 0 | AD25: 0 | AE25: =subQ!AE14 | AF25: 0 | AG25: 0 | AH25: 0 | AI25: 0 | AJ25: =subQ!AJ14 | AK25: 0 | AL25: 0 | AM25: 0 | AN25: 0 | AO25: =subQ!AO14
A26: drv:법인세비용 | B26: ratio | C26: 법인세율(/세전) | E26: =IFERROR(subQ!E16/subQ!E15,"") | F26: =IFERROR(subQ!F16/subQ!F15,"") | G26: =IFERROR(subQ!G16/subQ!G15,"") | H26: =IFERROR(subQ!H16/subQ!H15,"") | I26: =IFERROR(subQ!I16/subQ!I15,"") | J26: =IFERROR(subQ!J16/subQ!J15,"") | K26: =IFERROR(subQ!K16/subQ!K15,"") | L26: =IFERROR(subQ!L16/subQ!L15,"") | ... AB26: =IFERROR(subQ!AB16/subQ!AB15,"") | AC26: 0 | AD26: 0 | AE26: =IFERROR(subQ!AE16/subQ!AE15,"") | AF26: 0 | AG26: 0 | AH26: 0 | AI26: 0 | AJ26: =IFERROR(subQ!AJ16/subQ!AJ15,"") | AK26: 0 | AL26: 0 | AM26: 0 | AN26: 0 | AO26: =IFERROR(subQ!AO16/subQ!AO15,"")
A27: drv:지배주주순이익 | B27: ratio | C27: 지배주주 비중(/당기순이익) | E27: =IFERROR(subQ!E18/subQ!E17,"") | F27: =IFERROR(subQ!F18/subQ!F17,"") | G27: =IFERROR(subQ!G18/subQ!G17,"") | H27: =IFERROR(subQ!H18/subQ!H17,"") | I27: =IFERROR(subQ!I18/subQ!I17,"") | J27: =IFERROR(subQ!J18/subQ!J17,"") | K27: =IFERROR(subQ!K18/subQ!K17,"") | L27: =IFERROR(subQ!L18/subQ!L17,"") | ... AB27: =IFERROR(subQ!AB18/subQ!AB17,"") | AC27: =$D$50 | AD27: =$D$50 | AE27: =IFERROR(subQ!AE18/subQ!AE17,"") | AF27: =$D$50 | AG27: =$D$50 | AH27: =$D$50 | AI27: =$D$50 | AJ27: =IFERROR(subQ!AJ18/subQ!AJ17,"") | AK27: =$D$50 | AL27: =$D$50 | AM27: =$D$50 | AN27: =$D$50 | AO27: =IFERROR(subQ!AO18/subQ!AO17,"")
A28: drv:부채총계 | B28: qoq | C28: 부채총계 QoQ | G28: =IFERROR(subQ!G20/subQ!E20-1,"") | H28: =IFERROR(subQ!H20/subQ!G20-1,"") | I28: =IFERROR(subQ!I20/subQ!H20-1,"") | J28: =IFERROR(subQ!J20/subQ!I20-1,"") | L28: =IFERROR(subQ!L20/subQ!J20-1,"") | M28: =IFERROR(subQ!M20/subQ!L20-1,"") | N28: =IFERROR(subQ!N20/subQ!M20-1,"") | O28: =IFERROR(subQ!O20/subQ!N20-1,"") | Q28: =IFERROR(subQ!Q20/subQ!O20-1,"") | R28: =IFERROR(subQ!R20/subQ!Q20-1,"") | S28: =IFERROR(subQ!S20/subQ!R20-1,"") | T28: =IFERROR(subQ!T20/subQ!S20-1,"") | V28: =IFERROR(subQ!V20/subQ!T20-1,"") | W28: =IFERROR(subQ!W20/subQ!V20-1,"") | X28: =IFERROR(subQ!X20/subQ!W20-1,"") | Y28: =IFERROR(subQ!Y20/subQ!X20-1,"") | AA28: =IFERROR(subQ!AA20/subQ!Y20-1,"") | AB28: =IFERROR(subQ!AB20/subQ!AA20-1,"") | AC28: 3.886e-06 | AD28: 0 | AF28: 0 | AG28: 0 | AH28: 0 | AI28: 0 | AK28: 0 | AL28: 0 | AM28: 0 | AN28: 0
A29: drv:자본총계 | B29: roll | C29: 자본총계 기타변동(배당 등, 억원) | G29: =IFERROR(subQ!E21+subQ!G17-subQ!G21,"") | H29: =IFERROR(subQ!G21+subQ!H17-subQ!H21,"") | I29: =IFERROR(subQ!H21+subQ!I17-subQ!I21,"") | J29: =IFERROR(subQ!I21+subQ!J17-subQ!J21,"") | L29: =IFERROR(subQ!J21+subQ!L17-subQ!L21,"") | M29: =IFERROR(subQ!L21+subQ!M17-subQ!M21,"") | N29: =IFERROR(subQ!M21+subQ!N17-subQ!N21,"") | O29: =IFERROR(subQ!N21+subQ!O17-subQ!O21,"") | Q29: =IFERROR(subQ!O21+subQ!Q17-subQ!Q21,"") | R29: =IFERROR(subQ!Q21+subQ!R17-subQ!R21,"") | S29: =IFERROR(subQ!R21+subQ!S17-subQ!S21,"") | T29: =IFERROR(subQ!S21+subQ!T17-subQ!T21,"") | V29: =IFERROR(subQ!T21+subQ!V17-subQ!V21,"") | W29: =IFERROR(subQ!V21+subQ!W17-subQ!W21,"") | X29: =IFERROR(subQ!W21+subQ!X17-subQ!X21,"") | Y29: =IFERROR(subQ!X21+subQ!Y17-subQ!Y21,"") | AA29: =IFERROR(subQ!Y21+subQ!AA17-subQ!AA21,"") | AB29: =IFERROR(subQ!AA21+subQ!AB17-subQ!AB21,"") | AC29: -0.00516687 | AD29: 0.005630982 | AF29: -0.001542672 | AG29: 0.004327036 | AH29: 3.3723e-05 | AI29: 0.003892652 | AK29: -0.003661401 | AL29: 0.001827925 | AM29: 0.007208527 | AN29: -0.009149914
A30: drv:지배주주지분 | B30: roll | C30: 지배주주지분 기타변동(배당 등, 억원) | G30: =IFERROR(subQ!E22+subQ!G18-subQ!G22,"") | H30: =IFERROR(subQ!G22+subQ!H18-subQ!H22,"") | I30: =IFERROR(subQ!H22+subQ!I18-subQ!I22,"") | J30: =IFERROR(subQ!I22+subQ!J18-subQ!J22,"") | L30: =IFERROR(subQ!J22+subQ!L18-subQ!L22,"") | M30: =IFERROR(subQ!L22+subQ!M18-subQ!M22,"") | N30: =IFERROR(subQ!M22+subQ!N18-subQ!N22,"") | O30: =IFERROR(subQ!N22+subQ!O18-subQ!O22,"") | Q30: =IFERROR(subQ!O22+subQ!Q18-subQ!Q22,"") | R30: =IFERROR(subQ!Q22+subQ!R18-subQ!R22,"") | S30: =IFERROR(subQ!R22+subQ!S18-subQ!S22,"") | T30: =IFERROR(subQ!S22+subQ!T18-subQ!T22,"") | V30: =IFERROR(subQ!T22+subQ!V18-subQ!V22,"") | W30: =IFERROR(subQ!V22+subQ!W18-subQ!W22,"") | X30: =IFERROR(subQ!W22+subQ!X18-subQ!X22,"") | Y30: =IFERROR(subQ!X22+subQ!Y18-subQ!Y22,"") | AA30: =IFERROR(subQ!Y22+subQ!AA18-subQ!AA22,"") | AB30: =IFERROR(subQ!AA22+subQ!AB18-subQ!AB22,"") | AC30: -0.00516687 | AD30: 0.005630982 | AF30: -0.001542672 | AG30: 0.004327036 | AH30: 3.3723e-05 | AI30: 0.003892652 | AK30: -0.003661401 | AL30: 0.001827925 | AM30: 0.007208527 | AN30: -0.009149914
A31: drv:총차입금 | B31: qoq | C31: 총차입금 QoQ | G31: =IFERROR(subQ!G23/subQ!E23-1,"") | H31: =IFERROR(subQ!H23/subQ!G23-1,"") | I31: =IFERROR(subQ!I23/subQ!H23-1,"") | J31: =IFERROR(subQ!J23/subQ!I23-1,"") | L31: =IFERROR(subQ!L23/subQ!J23-1,"") | M31: =IFERROR(subQ!M23/subQ!L23-1,"") | N31: =IFERROR(subQ!N23/subQ!M23-1,"") | O31: =IFERROR(subQ!O23/subQ!N23-1,"") | Q31: =IFERROR(subQ!Q23/subQ!O23-1,"") | R31: =IFERROR(subQ!R23/subQ!Q23-1,"") | S31: =IFERROR(subQ!S23/subQ!R23-1,"") | T31: =IFERROR(subQ!T23/subQ!S23-1,"") | V31: =IFERROR(subQ!V23/subQ!T23-1,"") | W31: =IFERROR(subQ!W23/subQ!V23-1,"") | X31: =IFERROR(subQ!X23/subQ!W23-1,"") | Y31: =IFERROR(subQ!Y23/subQ!X23-1,"") | AA31: =IFERROR(subQ!AA23/subQ!Y23-1,"") | AB31: =IFERROR(subQ!AB23/subQ!AA23-1,"") | AC31: 1.5582e-05 | AD31: 0 | AF31: 0 | AG31: 0 | AH31: 0 | AI31: 0 | AK31: 0 | AL31: 0 | AM31: 0 | AN31: 0
A32: drv:순차입금 | B32: qoq | C32: 순차입금 QoQ | G32: =IFERROR(subQ!G24/subQ!E24-1,"") | H32: =IFERROR(subQ!H24/subQ!G24-1,"") | I32: =IFERROR(subQ!I24/subQ!H24-1,"") | J32: =IFERROR(subQ!J24/subQ!I24-1,"") | L32: =IFERROR(subQ!L24/subQ!J24-1,"") | M32: =IFERROR(subQ!M24/subQ!L24-1,"") | N32: =IFERROR(subQ!N24/subQ!M24-1,"") | O32: =IFERROR(subQ!O24/subQ!N24-1,"") | Q32: =IFERROR(subQ!Q24/subQ!O24-1,"") | R32: =IFERROR(subQ!R24/subQ!Q24-1,"") | S32: =IFERROR(subQ!S24/subQ!R24-1,"") | T32: =IFERROR(subQ!T24/subQ!S24-1,"") | V32: =IFERROR(subQ!V24/subQ!T24-1,"") | W32: =IFERROR(subQ!W24/subQ!V24-1,"") | X32: =IFERROR(subQ!X24/subQ!W24-1,"") | Y32: =IFERROR(subQ!Y24/subQ!X24-1,"") | AA32: =IFERROR(subQ!AA24/subQ!Y24-1,"") | AB32: =IFERROR(subQ!AB24/subQ!AA24-1,"") | AC32: -0.1251413 | AD32: -0.17765814 | AF32: -0.12602291 | AG32: -0.14794008 | AH32: -0.24835165 | AI32: -0.40643275 | AK32: -0.40394089 | AL32: -0.70247934 | AM32: -3.2777778 | AN32: 1.7439024
A33: drv:이자발생자산 | B33: qoq | C33: 이자발생자산 QoQ | G33: =IFERROR(subQ!G25/subQ!E25-1,"") | H33: =IFERROR(subQ!H25/subQ!G25-1,"") | I33: =IFERROR(subQ!I25/subQ!H25-1,"") | J33: =IFERROR(subQ!J25/subQ!I25-1,"") | L33: =IFERROR(subQ!L25/subQ!J25-1,"") | M33: =IFERROR(subQ!M25/subQ!L25-1,"") | N33: =IFERROR(subQ!N25/subQ!M25-1,"") | O33: =IFERROR(subQ!O25/subQ!N25-1,"") | Q33: =IFERROR(subQ!Q25/subQ!O25-1,"") | R33: =IFERROR(subQ!R25/subQ!Q25-1,"") | S33: =IFERROR(subQ!S25/subQ!R25-1,"") | T33: =IFERROR(subQ!T25/subQ!S25-1,"") | V33: =IFERROR(subQ!V25/subQ!T25-1,"") | W33: =IFERROR(subQ!W25/subQ!V25-1,"") | X33: =IFERROR(subQ!X25/subQ!W25-1,"") | Y33: =IFERROR(subQ!Y25/subQ!X25-1,"") | AA33: =IFERROR(subQ!AA25/subQ!Y25-1,"") | AB33: =IFERROR(subQ!AB25/subQ!AA25-1,"") | AC33: -0.004441072 | AD33: -0.00551655 | AF33: -0.003193814 | AG33: -0.003330523 | AH33: -0.004779832 | AI33: -0.005907854 | AK33: -0.003548677 | AL33: -0.003647129 | AM33: -0.005038543 | AN33: -0.006232687
A34: drv:현금및현금성자산 | B34: qoq | C34: 현금및현금성자산 QoQ | G34: =IFERROR(subQ!G26/subQ!E26-1,"") | H34: =IFERROR(subQ!H26/subQ!G26-1,"") | I34: =IFERROR(subQ!I26/subQ!H26-1,"") | J34: =IFERROR(subQ!J26/subQ!I26-1,"") | L34: =IFERROR(subQ!L26/subQ!J26-1,"") | M34: =IFERROR(subQ!M26/subQ!L26-1,"") | N34: =IFERROR(subQ!N26/subQ!M26-1,"") | O34: =IFERROR(subQ!O26/subQ!N26-1,"") | Q34: =IFERROR(subQ!Q26/subQ!O26-1,"") | R34: =IFERROR(subQ!R26/subQ!Q26-1,"") | S34: =IFERROR(subQ!S26/subQ!R26-1,"") | T34: =IFERROR(subQ!T26/subQ!S26-1,"") | V34: =IFERROR(subQ!V26/subQ!T26-1,"") | W34: =IFERROR(subQ!W26/subQ!V26-1,"") | X34: =IFERROR(subQ!X26/subQ!W26-1,"") | Y34: =IFERROR(subQ!Y26/subQ!X26-1,"") | AA34: =IFERROR(subQ!AA26/subQ!Y26-1,"") | AB34: =IFERROR(subQ!AB26/subQ!AA26-1,"")
A35: drv:CAPEX | B35: yoy | C35: CAPEX YoY | J35: =IFERROR(subQ!J27/subQ!E27-1,"") | L35: =IFERROR(subQ!L27/subQ!G27-1,"") | M35: =IFERROR(subQ!M27/subQ!H27-1,"") | N35: =IFERROR(subQ!N27/subQ!I27-1,"") | O35: =IFERROR(subQ!O27/subQ!J27-1,"") | Q35: =IFERROR(subQ!Q27/subQ!L27-1,"") | R35: =IFERROR(subQ!R27/subQ!M27-1,"") | S35: =IFERROR(subQ!S27/subQ!N27-1,"") | T35: =IFERROR(subQ!T27/subQ!O27-1,"") | V35: =IFERROR(subQ!V27/subQ!Q27-1,"") | W35: =IFERROR(subQ!W27/subQ!R27-1,"") | X35: =IFERROR(subQ!X27/subQ!S27-1,"") | Y35: =IFERROR(subQ!Y27/subQ!T27-1,"") | AA35: =IFERROR(subQ!AA27/subQ!V27-1,"") | AB35: =IFERROR(subQ!AB27/subQ!W27-1,"") | AC35: 18.620438 | AD35: 74.846501 | AF35: -0.48710121 | AG35: -0.51058577 | AH35: 0 | AI35: 0 | AK35: 0 | AL35: 0 | AM35: 0 | AN35: 0
A36: drv:영업활동현금흐름 | B36: yoy | C36: 영업활동현금흐름 YoY | J36: =IFERROR(subQ!J28/subQ!E28-1,"") | L36: =IFERROR(subQ!L28/subQ!G28-1,"") | M36: =IFERROR(subQ!M28/subQ!H28-1,"") | N36: =IFERROR(subQ!N28/subQ!I28-1,"") | O36: =IFERROR(subQ!O28/subQ!J28-1,"") | Q36: =IFERROR(subQ!Q28/subQ!L28-1,"") | R36: =IFERROR(subQ!R28/subQ!M28-1,"") | S36: =IFERROR(subQ!S28/subQ!N28-1,"") | T36: =IFERROR(subQ!T28/subQ!O28-1,"") | V36: =IFERROR(subQ!V28/subQ!Q28-1,"") | W36: =IFERROR(subQ!W28/subQ!R28-1,"") | X36: =IFERROR(subQ!X28/subQ!S28-1,"") | Y36: =IFERROR(subQ!Y28/subQ!T28-1,"") | AA36: =IFERROR(subQ!AA28/subQ!V28-1,"") | AB36: =IFERROR(subQ!AB28/subQ!W28-1,"")
A37: drv:주식수 | B37: qoq | C37: 주식수 QoQ | G37: =IFERROR(subQ!G29/subQ!E29-1,"") | H37: =IFERROR(subQ!H29/subQ!G29-1,"") | I37: =IFERROR(subQ!I29/subQ!H29-1,"") | J37: =IFERROR(subQ!J29/subQ!I29-1,"") | L37: =IFERROR(subQ!L29/subQ!J29-1,"") | M37: =IFERROR(subQ!M29/subQ!L29-1,"") | N37: =IFERROR(subQ!N29/subQ!M29-1,"") | O37: =IFERROR(subQ!O29/subQ!N29-1,"") | Q37: =IFERROR(subQ!Q29/subQ!O29-1,"") | R37: =IFERROR(subQ!R29/subQ!Q29-1,"") | S37: =IFERROR(subQ!S29/subQ!R29-1,"") | T37: =IFERROR(subQ!T29/subQ!S29-1,"") | V37: =IFERROR(subQ!V29/subQ!T29-1,"") | W37: =IFERROR(subQ!W29/subQ!V29-1,"") | X37: =IFERROR(subQ!X29/subQ!W29-1,"") | Y37: =IFERROR(subQ!Y29/subQ!X29-1,"") | AA37: =IFERROR(subQ!AA29/subQ!Y29-1,"") | AB37: =IFERROR(subQ!AB29/subQ!AA29-1,"") | AC37: 0 | AD37: 0 | AF37: 0 | AG37: 0 | AH37: 0 | AI37: 0 | AK37: 0 | AL37: 0 | AM37: 0 | AN37: 0
A38: drv:DPS | B38: abs | C38: DPS (가정, 원) | E38: =subQ!E33 | F38: =subQ!F33 | G38: =subQ!G33 | H38: =subQ!H33 | I38: =subQ!I33 | J38: =subQ!J33 | K38: =subQ!K33 | L38: =subQ!L33 | ... AB38: =subQ!AB33 | AD38: 0 | AE38: =subQ!AE33 | AI38: 0 | AJ38: =subQ!AJ33 | AN38: 0 | AO38: =subQ!AO33
B40: 3. 밸류에이션·스칼라 | C40: 노란 셀 = 가정. '연결' 표시는 추정 전 분기 수식이 이 셀을 참조한다는 뜻
A41: sc:종가 | C41: 종가 | D41: 4740 | E41: 원 — 네이버 정규장 종가(aik 확정종가 대조 · aik 4,840원)
A42: sc:기준일 | C42: 기준일 | D42: 20261014 | E42: 종가 기준일
A43: sc:COE | C43: COE | D43: 0.09 | E43: 자기자본비용(가정) — TP 적정 PBR = ROE/COE
A44: sc:PER_lo | C44: PER_lo | D44: 10 | E44: PER 밴드 하단(배) — sector_default(레퍼런스 TP_PE PB 예시 10/15/20배; 과거 PER 중위 639.1배가 3~40 밖(턴어라운드 왜곡))
A45: sc:PER_mid | C45: PER_mid | D45: 15 | E45: PER 밴드 중단(배)
A46: sc:PER_hi | C46: PER_hi | D46: 20 | E46: PER 밴드 상단(배)
A47: sc:EPS_Y1가중 | C47: EPS_Y1가중 | D47: 0.5 | E47: 12M fwd EPS = FY(last_actual연도)E × w + FY+1E × (1−w) — 기준 분기 2Q 이면 0.5(가정)
A48: sc:세율 | C48: 세율 | D48: 0.22 | E48: 참고(연결 안 됨: MAX(세전,0)×단일 세율로 재현 불가(지주 자회사 합산 등) → 분기별 역산) — 모델 assumptions 값 · 최근 12분기 세전 합 ≤ 0; 세전 > 0 분기 중위 0.0% 도 5~27% 밖 → 법정세율 근사 22% 가정
A49: sc:판관비율 | C49: 판관비율 | D49: 0.19017154 | E49: 연결 — 판관비 = 매출액 × 판관비율(역산, 재현 오차 ≤ 0.05억 · 모델 assumptions 0.1902)
A50: sc:지배주주비중 | C50: 지배주주비중 | D50: 1 | E50: 연결 — 지배주주순이익 = 당기순이익 × 비중(역산, 재현 오차 ≤ 0.05억)
A51: sc:이자율_자산 | C51: 이자율_자산 | D51: 0.021738295 | E51: 연결 — 이자손익 = (전분기 이자발생자산 × 자산이자율 − 전분기 총차입금 × 부채이자율)/4(역산, 재현 오차 ≤ 0.05억 · 모델 assumptions 0.0203)
A52: sc:이자율_부채 | C52: 이자율_부채 | D52: 0.0014673451 | E52: 연결 — 같은 수식의 부채 쪽(총차입금 행이 없으면 0)(역산, 재현 오차 ≤ 0.05억)
A53: sc:배당성향 | C53: 배당성향 | D53: 0 | E53: 배당성향(참고 — 모델은 직전 DPS 유지·Q2 지급 가정)
A54: sc:외화순노출_백만$ | C54: 외화순노출_백만$ | E54: 외화 순노출 × Δ기말환율 (외화 시트 방식) — 외화 순노출 미공시(face) → 0 + 표기
A55: sc:헤지비율 | C55: 헤지비율 | E55: sls 없음
A56: sc:헤지환율_약정 | C56: 헤지환율_약정 | E56: sls 없음

Sheet BS연결
B1: (백만원) | C1: 이름: BS연결H | E1: 4Q21 | F1: 2021 | G1: 1Q22 | H1: 2Q22 | I1: 3Q22 | J1: 4Q22 | K1: 2022 | L1: 1Q23 | M1: 2Q23 | N1: 3Q23 | O1: 4Q23 | P1: 2023 | Q1: 1Q24 | R1: 2Q24 | S1: 3Q24 | T1: 4Q24 | U1: 2024 | V1: 1Q25 | W1: 2Q25 | X1: 3Q25 | Y1: 4Q25 | Z1: 2025 | AA1: 1Q26 | AB1: 2Q26 | AC1: 3Q26 | AD1: 4Q26 | AE1: 2026 | AF1: 1Q27 | AG1: 2Q27 | AH1: 3Q27 | AI1: 4Q27 | AJ1: 2027 | AK1: 1Q28 | AL1: 2Q28 | AM1: 3Q28 | AN1: 4Q28 | AO1: 2028
B2: 연결 | D2: fin json(kship_fin.py)
B3: 해성에어로보틱스(연) | C3: UPDATE: 26-10-14 | E3: 1 | F3: 2 | G3: 3 | H3: 4 | I3: 5 | J3: 6 | K3: 7 | L3: 8 | M3: 9 | N3: 10 | O3: 11 | P3: 12 | Q3: 13 | R3: 14 | S3: 15 | T3: 16 | U3: 17 | V3: 18 | W3: 19 | X3: 20 | Y3: 21 | Z3: 22 | AA3: 23 | AB3: 24 | AC3: 25 | AD3: 26 | AE3: 27 | AF3: 28 | AG3: 29 | AH3: 30 | AI3: 31 | AJ3: 32 | AK3: 33 | AL3: 34 | AM3: 35 | AN3: 36 | AO3: 37
B4: Account Code | C4: AccountNAME | E4: 2021.12 | F4: 2021.12A | G4: 2022.03 | H4: 2022.06 | I4: 2022.09 | J4: 2022.12 | K4: 2022.12A | L4: 2023.03 | M4: 2023.06 | N4: 2023.09 | O4: 2023.12 | P4: 2023.12A | Q4: 2024.03 | R4: 2024.06 | S4: 2024.09 | T4: 2024.12 | U4: 2024.12A | V4: 2025.03 | W4: 2025.06 | X4: 2025.09 | Y4: 2025.12 | Z4: 2025.12A | AA4: 2026.03 | AB4: 2026.06 | AC4: 2026.09 | AD4: 2026.12 | AE4: 2026.12A | AF4: 2027.03 | AG4: 2027.06 | AH4: 2027.09 | AI4: 2027.12 | AJ4: 2027.12A | AK4: 2028.03 | AL4: 2028.06 | AM4: 2028.09 | AN4: 2028.12 | AO4: 2028.12A

Sheet BS별도
B1: (백만원) | C1: 이름: BS별도H | E1: 4Q21 | F1: 2021 | G1: 1Q22 | H1: 2Q22 | I1: 3Q22 | J1: 4Q22 | K1: 2022 | L1: 1Q23 | M1: 2Q23 | N1: 3Q23 | O1: 4Q23 | P1: 2023 | Q1: 1Q24 | R1: 2Q24 | S1: 3Q24 | T1: 4Q24 | U1: 2024 | V1: 1Q25 | W1: 2Q25 | X1: 3Q25 | Y1: 4Q25 | Z1: 2025 | AA1: 1Q26 | AB1: 2Q26 | AC1: 3Q26 | AD1: 4Q26 | AE1: 2026 | AF1: 1Q27 | AG1: 2Q27 | AH1: 3Q27 | AI1: 4Q27 | AJ1: 2027 | AK1: 1Q28 | AL1: 2Q28 | AM1: 3Q28 | AN1: 4Q28 | AO1: 2028
B2: 별도 | D2: fin json(kship_fin.py)
B3: 해성에어로보틱스(별) | C3: UPDATE: 26-10-14 | E3: 1 | F3: 2 | G3: 3 | H3: 4 | I3: 5 | J3: 6 | K3: 7 | L3: 8 | M3: 9 | N3: 10 | O3: 11 | P3: 12 | Q3: 13 | R3: 14 | S3: 15 | T3: 16 | U3: 17 | V3: 18 | W3: 19 | X3: 20 | Y3: 21 | Z3: 22 | AA3: 23 | AB3: 24 | AC3: 25 | AD3: 26 | AE3: 27 | AF3: 28 | AG3: 29 | AH3: 30 | AI3: 31 | AJ3: 32 | AK3: 33 | AL3: 34 | AM3: 35 | AN3: 36 | AO3: 37
B4: Account Code | C4: AccountNAME | E4: 2021.12 | F4: 2021.12A | G4: 2022.03 | H4: 2022.06 | I4: 2022.09 | J4: 2022.12 | K4: 2022.12A | L4: 2023.03 | M4: 2023.06 | N4: 2023.09 | O4: 2023.12 | P4: 2023.12A | Q4: 2024.03 | R4: 2024.06 | S4: 2024.09 | T4: 2024.12 | U4: 2024.12A | V4: 2025.03 | W4: 2025.06 | X4: 2025.09 | Y4: 2025.12 | Z4: 2025.12A | AA4: 2026.03 | AB4: 2026.06 | AC4: 2026.09 | AD4: 2026.12 | AE4: 2026.12A | AF4: 2027.03 | AG4: 2027.06 | AH4: 2027.09 | AI4: 2027.12 | AJ4: 2027.12A | AK4: 2028.03 | AL4: 2028.06 | AM4: 2028.09 | AN4: 2028.12 | AO4: 2028.12A
A5: 1 | C5: 유동자산 | E5: 23358.71 | F5: 23358.71 | G5: 21762.87 | H5: 21203.15 | I5: 19984.17 | J5: 19551.95 | K5: 19551.95 | L5: 20130.01 | M5: 19689.08 | N5: 19805.92 | O5: 19525.79 | P5: 19525.79 | Q5: 19976.58 | R5: 20093.42 | S5: 18387.79 | T5: 18463.75 | U5: 18463.75 | V5: 18784.92 | W5: 19875.51 | X5: 20048.65 | Y5: 20288.72 | Z5: 20288.72 | AA5: 18871.8 | AB5: 32428.96
A6: 1 | C6: 현금및현금성자산 | E6: 9286.11 | F6: 9286.11 | G6: 11448.72 | H6: 8747.7 | I6: 9207.46 | J6: 3986.02 | K6: 3986.02 | L6: 12735.22 | M6: 14066.69 | N6: 11557.83 | O6: 8913.9 | P6: 8913.9 | Q6: 10380.76 | R6: 8458 | S6: 6682.52 | T6: 8034.41 | U6: 8034.41 | V6: 9327.91 | W6: 6896.98 | X6: 11650.6 | Y6: 7981.82 | Z6: 7981.82 | AA6: 6475 | AB6: 23952.92
A7: 1 | C7: 단기금융상품 | E7: 9000 | F7: 9000 | G7: 5000 | H7: 2000 | J7: 4963.05 | K7: 4963.05 | L7: 2000 | N7: 1000 | O7: 2978.98 | P7: 2978.98 | Q7: 978.98 | R7: 2000 | S7: 3000 | T7: 2000 | U7: 2000 | V7: 2000 | W7: 2000 | Y7: 4000 | Z7: 4000 | AA7: 4000 | AB7: 0
A8: 1 | C8: 단기금융자산 | E8: 9000 | F8: 9000 | G8: 5000 | H8: 2000 | J8: 4963.05 | K8: 4963.05 | L8: 2000 | N8: 1000 | O8: 2978.98 | P8: 2978.98 | Q8: 978.98 | R8: 2000 | S8: 3000 | T8: 2000 | U8: 2000 | V8: 2000 | W8: 2000 | Y8: 4000 | Z8: 4000 | AA8: 4000 | AB8: 0
A9: 1 | C9: 매출채권및기타채권 | E9: 2660.28 | F9: 2660.28 | G9: 2550.09 | H9: 2816.14 | I9: 2199.34 | J9: 1957.9 | K9: 1957.9 | L9: 2127.5 | M9: 2237.19 | N9: 1760.2 | O9: 1725.06 | P9: 1725.06 | Q9: 1913.2 | R9: 3090.92 | S9: 2069.09 | T9: 2310.11 | U9: 2310.11 | V9: 1933.93 | W9: 2583 | X9: 1731.24 | Y9: 2429.74 | Z9: 2429.74 | AA9: 2324.16 | AB9: 2197.83
A10: 1 | C10: 기타유동금융자산 | E10: 102.83 | F10: 102.83 | G10: 227.43 | H10: 202.52 | I10: 69.31 | J10: 223.29 | K10: 223.29 | L10: 99.77 | M10: 77.18 | N10: 122.9 | O10: 60.68 | P10: 60.68 | Q10: 139.21 | R10: 20.4 | S10: 88.3 | T10: 23.21 | U10: 23.21 | V10: 92.03 | W10: 70.22 | X10: 36.91 | Y10: 35.35 | Z10: 35.35 | AA10: 100.98 | AB10: 170.5
A11: 1 | C11: 당기법인세자산(선급법인세) | E11: 8.06 | F11: 8.06 | G11: 19.49 | H11: 25.01 | I11: 35.55 | J11: 45.57 | K11: 45.57 | L11: 52.15 | M11: 21.58 | N11: 38.05 | O11: 56.98 | P11: 56.98 | Q11: 69.16 | R11: 28.54 | S11: 38.39 | T11: 52.19 | U11: 52.19 | V11: 64.25 | W11: 18.47 | X11: 33.19 | Y11: 45.76 | Z11: 45.76 | AA11: 51.9 | AB11: 25.9
A12: 1 | C12: 재고자산 | E12: 2291.51 | F12: 2291.51 | G12: 2510.24 | H12: 2722.58 | I12: 3082.17 | J12: 2800.09 | K12: 2800.09 | L12: 2790.66 | M12: 2358.47 | N12: 2557.6 | O12: 2699.73 | P12: 2699.73 | Q12: 3304.5 | R12: 3204.36 | S12: 3276.54 | T12: 2991.65 | U12: 2991.65 | V12: 3305.18 | W12: 3572.72 | X12: 3357.79 | Y12: 2642.49 | Z12: 2642.49 | AA12: 2943.44 | AB12: 2624.69
A13: 1 | C13: 기타유동자산 | E13: 9.93 | F13: 9.93 | G13: 6.89 | H13: 2.64 | I13: 7.74 | J13: 5.53 | K13: 5.53 | L13: 5.54 | M13: 9.52 | N13: 11.39 | O13: 71.92 | P13: 71.92 | Q13: 40.29 | R13: 8.11 | S13: 24.36 | T13: 5.72 | U13: 5.72 | V13: 5.54 | W13: 1.95 | X13: 18.71 | Y13: 28.08 | Z13: 28.08 | AA13: 36.05 | AB13: 1095.28
A14: 1 | C14: 비유동자산 | E14: 26611.38 | F14: 26611.38 | G14: 27882.98 | H14: 23551.82 | I14: 25005.63 | J14: 24807.71 | K14: 24807.71 | L14: 24553.29 | M14: 24304.1 | N14: 24214.22 | O14: 24128.15 | P14: 24128.15 | Q14: 23884 | R14: 23690 | S14: 24027.86 | T14: 23768.43 | U14: 23768.43 | V14: 23508.27 | W14: 23253.78 | X14: 23019.9 | Y14: 22773.69 | Z14: 22773.69 | AA14: 23840.49 | AB14: 28816.3
A15: 1 | C15: 투자부동산 | E15: 4742.85 | F15: 4742.85 | G15: 4714.71
A16: 1 | C16: 유형자산 | E16: 21808.03 | F16: 21808.03 | G16: 23115.83 | H16: 23493.99 | I16: 24949.87 | J16: 24754 | K16: 24754 | L16: 24501.64 | M16: 24262.43 | N16: 24174.71 | O16: 24083.02 | P16: 24083.02 | Q16: 23840.87 | R16: 23648.86 | S16: 23988.7 | T16: 23731.25 | U16: 23731.25 | V16: 23473.07 | W16: 23220.07 | X16: 22986.73 | Y16: 22726.69 | Z16: 22726.69 | AA16: 23793.64 | AB16: 24920.58
A17: 1 | C17: 무형자산 | E17: 32.46 | F17: 32.46 | G17: 24.32 | H17: 29.6 | I17: 27.45 | J17: 25.29 | K17: 25.29 | L17: 23.13 | M17: 20.97 | N17: 18.81 | O17: 16.65 | P17: 16.65 | Q17: 14.49 | R17: 12.33 | S17: 10.17 | T17: 8.02 | U17: 8.02 | V17: 5.86 | W17: 4.18 | X17: 3.46 | Y17: 2.99 | Z17: 2.99 | AA17: 2.65 | AB17: 2.33
A18: 1 | C18: 장기금융자산 | E18: 28.03 | F18: 28.03 | G18: 28.12 | H18: 28.22 | I18: 28.32 | J18: 28.42 | K18: 28.42 | L18: 28.52 | M18: 20.7 | N18: 20.7 | O18: 28.48 | P18: 28.48 | Q18: 28.64 | R18: 28.81 | S18: 28.98 | T18: 29.16 | U18: 29.16 | V18: 29.34 | W18: 29.52 | X18: 29.71 | Y18: 44 | Z18: 44 | AA18: 41.78 | AB18: 81.82
A19: 1 | C19: 투자자산 | E19: 28.03 | F19: 28.03 | G19: 28.12 | H19: 28.22 | I19: 28.32 | J19: 28.42 | K19: 28.42 | L19: 28.52 | M19: 20.7 | N19: 20.7 | O19: 28.48 | P19: 28.48 | Q19: 28.64 | R19: 28.81 | S19: 28.98 | T19: 29.16 | U19: 29.16 | V19: 29.34 | W19: 29.52 | X19: 29.71 | Y19: 44 | Z19: 44 | AA19: 41.78 | AB19: 3890.96
A20: 1 | C20: 자산총계 | E20: 49970.09 | F20: 49970.09 | G20: 49645.85 | H20: 44754.97 | I20: 44989.8 | J20: 44359.66 | K20: 44359.66 | L20: 44683.3 | M20: 43993.18 | N20: 44020.14 | O20: 43653.93 | P20: 43653.93 | Q20: 43860.58 | R20: 43783.42 | S20: 42415.64 | T20: 42232.17 | U20: 42232.17 | V20: 42293.19 | W20: 43129.29 | X20: 43068.55 | Y20: 43062.41 | Z20: 43062.41 | AA20: 42712.29 | AB20: 61245.26
A21: 1 | C21: 유동부채 | E21: 7617.98 | F21: 7617.98 | G21: 7364.76 | H21: 2714.78 | I21: 2728.75 | J21: 2393.91 | K21: 2393.91 | L21: 2264.43 | M21: 1763.79 | N21: 2363.64 | O21: 2262.3 | P21: 2262.3 | Q21: 2541.81 | R21: 2538.05 | S21: 1989.24 | T21: 2006.63 | U21: 2006.63 | V21: 2257.45 | W21: 2382.1 | X21: 2234.79 | Y21: 2405.65 | Z21: 2405.65 | AA21: 2325.11 | AB21: 19747.26
A22: 1 | C22: 매입채무및기타채무 | E22: 1813.45 | F22: 1813.45 | G22: 1580.78 | H22: 1854.74 | I22: 1444.31 | J22: 1255.62 | K22: 1255.62 | L22: 1462 | M22: 1111.66 | N22: 1636.88 | O22: 1523.62 | P22: 1523.62 | Q22: 1865.08 | R22: 1706.67 | S22: 1264.09 | T22: 1315.47 | U22: 1315.47 | V22: 1479.26 | W22: 1708.13 | X22: 1449.68 | Y22: 1539.6 | Z22: 1539.6 | AA22: 1469.57 | AB22: 1239.02
A23: 1 | C23: 기타유동금융부채 | E23: 709.77 | F23: 709.77 | G23: 687.7 | H23: 587.67 | I23: 500.3 | J23: 535.91 | K23: 535.91 | L23: 704.23 | M23: 539.5 | N23: 612.18 | O23: 543.9 | P23: 543.9 | Q23: 526.09 | R23: 700.21 | S23: 486.05 | T23: 579.99 | U23: 579.99 | V23: 516.94 | W23: 483.4 | X23: 554.72 | Y23: 561.43 | Z23: 561.43 | AA23: 597.96 | AB23: 755.97
A24: 1 | C24: 단기금융부채 | E24: 709.77 | F24: 709.77 | G24: 687.7 | H24: 587.67 | I24: 500.3 | J24: 535.91 | K24: 535.91 | L24: 704.23 | M24: 539.5 | N24: 612.18 | O24: 543.9 | P24: 543.9 | Q24: 526.09 | R24: 700.21 | S24: 486.05 | T24: 579.99 | U24: 579.99 | V24: 516.94 | W24: 483.4 | X24: 554.72 | Y24: 561.43 | Z24: 561.43 | AA24: 597.96 | AB24: 6546.19
A25: 1 | C25: 유동성장기부채 | E25: 5000 | F25: 5000 | G25: 5000 | AB25: 11551.82
A26: 1 | C26: 기타유동부채 | E26: 55.66 | F26: 55.66 | G26: 54.04 | H26: 81.02 | I26: 593.4 | J26: 562.47 | K26: 562.47 | L26: 55.6 | M26: 67.97 | N26: 77.26 | O26: 158.3 | P26: 158.3 | Q26: 114.56 | R26: 93.19 | S26: 207.2 | T26: 78.38 | U26: 78.38 | V26: 231.76 | W26: 160.83 | X26: 198.36 | Y26: 268.02 | Z26: 268.02 | AA26: 224.73 | AB26: 377.74
A27: 1 | C27: 단기충당부채 | E27: 39.11 | F27: 39.11 | G27: 42.24 | H27: 41.36 | I27: 40.74 | J27: 39.92 | K27: 39.92 | L27: 42.59 | M27: 44.66 | N27: 37.33 | O27: 36.49 | P27: 36.49 | Q27: 36.09 | R27: 37.99 | S27: 31.9 | T27: 32.8 | U27: 32.8 | V27: 29.49 | W27: 29.74 | X27: 32.02 | Y27: 36.61 | Z27: 36.61 | AA27: 32.85 | AB27: 32.5
A28: 1 | C28: 비유동부채 | E28: 1428.01 | F28: 1428.01 | G28: 1407.72 | H28: 1398.48 | I28: 1398.76 | J28: 1296.01 | K28: 1296.01 | L28: 1344.44 | M28: 1422.21 | N28: 1422.79 | O28: 1501.4 | P28: 1501.4 | Q28: 1607.18 | R28: 1545.9 | S28: 776.05 | T28: 757.24 | U28: 757.24 | V28: 785.98 | W28: 899.78 | X28: 941.72 | Y28: 1012 | Z28: 1012 | AA28: 1017.48 | AB28: 838.65
A29: 1 | C29: 확정급여부채 | E29: 760.15 | F29: 760.15 | G29: 742.35 | H29: 734.22 | I29: 735.33 | J29: 673.88 | K29: 673.88 | L29: 723.84 | M29: 720.75 | N29: 721.32 | O29: 778.78 | P29: 778.78 | Q29: 886.2 | R29: 826.6 | S29: 58.47 | T29: 41.4 | U29: 41.4 | V29: 71.93 | W29: 187.51 | X29: 231.35 | Y29: 266.62 | Z29: 266.62 | AA29: 274.04 | AB29: 72.2
A30: 1 | C30: 기타비유동금융부채 | E30: 2.42 | F30: 2.42 | G30: 0.79 | O30: 21.16 | P30: 21.16 | Q30: 19.52 | R30: 17.84 | S30: 16.12 | T30: 14.37 | U30: 14.37 | V30: 12.59 | W30: 10.8 | X30: 8.9 | Y30: 7 | Z30: 7 | AA30: 5.05 | AB30: 28.07
A31: 1 | C31: 장기금융부채 | E31: 2.42 | F31: 2.42 | G31: 0.79 | O31: 21.16 | P31: 21.16 | Q31: 19.52 | R31: 17.84 | S31: 16.12 | T31: 14.37 | U31: 14.37 | V31: 12.59 | W31: 10.8 | X31: 8.9 | Y31: 7 | Z31: 7 | AA31: 5.05 | AB31: 28.07
A32: 1 | C32: 이연법인세부채 | E32: 738.38 | F32: 738.38 | G32: 738.38 | H32: 738.38 | I32: 738.38 | J32: 704.82 | K32: 704.82 | L32: 704.82 | M32: 701.46 | N32: 701.46 | O32: 701.46 | P32: 701.46 | Q32: 701.46 | R32: 701.46 | S32: 701.46 | T32: 701.46 | U32: 701.46 | V32: 701.46 | W32: 701.46 | X32: 701.46 | Y32: 738.38 | Z32: 738.38 | AA32: 738.38 | AB32: 738.38
A33: 1 | C33: 부채총계 | E33: 9045.99 | F33: 9045.99 | G33: 8772.47 | H33: 4113.25 | I33: 4127.5 | J33: 3689.92 | K33: 3689.92 | L33: 3608.87 | M33: 3186 | N33: 3786.43 | O33: 3763.7 | P33: 3763.7 | Q33: 4148.99 | R33: 4083.95 | S33: 2765.29 | T33: 2763.87 | U33: 2763.87 | V33: 3043.43 | W33: 3281.88 | X33: 3176.51 | Y33: 3417.65 | Z33: 3417.65 | AA33: 3342.58 | AB33: 20585.92
A34: 1 | C34: 자본금 | E34: 5346.44 | F34: 5346.44 | G34: 5346.44 | H34: 5346.44 | I34: 5424.16 | J34: 5424.16 | K34: 5424.16 | L34: 5455.63 | M34: 5455.63 | N34: 5455.63 | O34: 5455.63 | P34: 5455.63 | Q34: 5539.41 | R34: 5570.4 | S34: 5570.4 | T34: 5570.4 | U34: 5570.4 | V34: 5570.4 | W34: 5570.4 | X34: 5582.65 | Y34: 5582.65 | Z34: 5582.65 | AA34: 5582.65 | AB34: 5582.65
A35: 1 | C35: 자본잉여금 | E35: 34265.18 | F35: 34265.18 | G35: 34265.18 | H35: 34265.18 | I35: 34805.94 | J35: 34805.94 | K35: 34805.94 | L35: 34947.4 | M35: 34947.4 | N35: 34947.4 | O35: 34947.4 | P35: 34947.4 | Q35: 34990.62 | R35: 34957.57 | S35: 34957.57 | T35: 34957.57 | U35: 34957.57 | V35: 34957.57 | W35: 34957.57 | X35: 35042.31 | Y35: 35042.31 | Z35: 35042.31 | AA35: 35042.31 | AB35: 35042.31
A36: 1 | C36: 기타자본 | E36: 2766 | F36: 2766 | G36: 2793.54 | H36: 2852.57 | I36: 2718.13 | J36: 2751.69 | K36: 2751.69 | L36: 2708.21 | M36: 2711.57 | N36: 2711.57 | O36: 2711.57 | P36: 2711.57 | Q36: 2679 | R36: 2679 | S36: 2679 | T36: 2679 | U36: 2679 | V36: 2679 | W36: 2679 | X36: 2654.82 | Y36: 2617.9 | Z36: 2617.9 | AA36: 2617.9 | AB36: 2617.9
A37: 1 | C37: 기타포괄이익누계액 | E37: -67.12 | F37: -67.12 | G37: -9.84 | H37: 37.04 | I37: 88.16 | J37: 101.27 | K37: 101.27 | L37: 86.13 | M37: 21.16 | N37: 38.56 | O37: -32.76 | P37: -32.76 | Q37: -89.48 | R37: -128.6 | S37: -88.62 | T37: -19.16 | U37: -19.16 | V37: -10.18 | W37: -88.05 | X37: -77.11 | Y37: -26.45 | Z37: -26.45 | AA37: -22.53 | AB37: -11.35
A38: 1 | C38: 이익잉여금 | E38: -1386.4 | F38: -1386.4 | G38: -1521.94 | H38: -1859.51 | I38: -2174.09 | J38: -2413.32 | K38: -2413.32 | L38: -2122.94 | M38: -2328.59 | N38: -2919.45 | O38: -3191.61 | P38: -3191.61 | Q38: -3407.95 | R38: -3378.9 | S38: -3468 | T38: -3719.51 | U38: -3719.51 | V38: -3947.04 | W38: -3271.51 | X38: -3310.63 | Y38: -3571.66 | Z38: -3571.66 | AA38: -3850.62 | AB38: -2572.16
A39: 1 | C39: 자본총계 | E39: 40924.1 | F39: 40924.1 | G39: 40873.38 | H39: 40641.71 | I39: 40862.3 | J39: 40669.74 | K39: 40669.74 | L39: 41074.43 | M39: 40807.17 | N39: 40233.71 | O39: 39890.24 | P39: 39890.24 | Q39: 39711.59 | R39: 39699.47 | S39: 39650.35 | T39: 39468.3 | U39: 39468.3 | V39: 39249.76 | W39: 39847.41 | X39: 39892.04 | Y39: 39644.76 | Z39: 39644.76 | AA39: 39369.71 | AB39: 40659.34
A40: 1 | C40: 부채와자본총계 | E40: 49970.09 | F40: 49970.09 | G40: 49645.85 | H40: 44754.97 | I40: 44989.8 | J40: 44359.66 | K40: 44359.66 | L40: 44683.3 | M40: 43993.18 | N40: 44020.14 | O40: 43653.93 | P40: 43653.93 | Q40: 43860.58 | R40: 43783.42 | S40: 42415.64 | T40: 42232.17 | U40: 42232.17 | V40: 42293.19 | W40: 43129.29 | X40: 43068.55 | Y40: 43062.41 | Z40: 43062.41 | AA40: 42712.29 | AB40: 61245.26
A41: 1 | C41: 지배주주지분 | E41: 40924.1 | F41: 40924.1 | G41: 40873.38 | H41: 40641.71 | I41: 40862.3 | J41: 40669.74 | K41: 40669.74 | L41: 41074.43 | M41: 40807.17 | N41: 40233.71 | O41: 39890.24 | P41: 39890.24 | Q41: 39711.59 | R41: 39699.47 | S41: 39650.35 | T41: 39468.3 | U41: 39468.3 | V41: 39249.76 | W41: 39847.41 | X41: 39892.04 | Y41: 39644.76 | Z41: 39644.76 | AA41: 39369.71 | AB41: 40659.34
A42: 1 | C42: 총차입금 | E42: 5000 | F42: 5000 | G42: 5000 | AB42: 23103.64
A43: 1 | C43: 순차입금 | E43: -13286.11 | F43: -13286.11 | G43: -11448.72 | AB43: -849.28
A44: 1 | C44: 이자발생자산 | E44: 18314.14 | F44: 18314.14 | G44: 16476.84 | H44: 10775.92 | I44: 9235.78 | J44: 8977.49 | K44: 8977.49 | L44: 14763.74 | M44: 14087.39 | N44: 12578.53 | O44: 11921.36 | P44: 11921.36 | Q44: 11388.38 | R44: 10486.81 | S44: 9711.5 | T44: 10063.57 | U44: 10063.57 | V44: 11357.25 | W44: 8926.5 | X44: 11680.31 | Y44: 12025.82 | Z44: 12025.82 | AA44: 10516.78 | AB44: 24034.74
A45: 1 | C45: 매각예정비유동자산및처분자산 | H45: 4686.56 | I45: 4686.56 | J45: 4686.56 | K45: 4686.56
A46: 1 | C46: 단기투자자산(공정가치) | I46: 696.05 | J46: 883.93 | K46: 883.93 | L46: 319.18 | M46: 918.45 | N46: 2757.95 | O46: 3018.54 | P46: 3018.54 | Q46: 3150.48 | R46: 3283.09 | S46: 3208.59 | T46: 3046.46 | U46: 3046.46 | V46: 2056.09 | W46: 4732.17 | X46: 3220.22 | Y46: 3125.48 | Z46: 3125.48 | AA46: 2940.28 | AB46: 2361.84
A47: 1 | C47: 종속기업및관계기업투자 | AB47: 3809.14
A48: 1 | C48: 단기파생상품부채 | AB48: 5790.22
A49: 1 | C49: 사채 | AB49: 11551.82
A50: 1 | C50: 매출액(수익) | E50: 4238.91 | G50: 3555.62 | H50: 3788.46 | I50: 3141.53 | J50: 3428.31 | K50: 13913.92 | L50: 3430.12 | M50: 3838.59 | N50: 3148.06 | O50: 3266.24 | P50: 13683.01 | Q50: 3418.53 | R50: 4521.41 | S50: 3400.74 | T50: 3597.44 | U50: 14938.12 | V50: 3065.14 | W50: 4000.59 | X50: 3801.58 | Y50: 4210.64 | Z50: 15077.95 | AA50: 3285.53 | AB50: 3315.34
A51: 1 | C51: 매출원가 | E51: 3515.69 | G51: 2999.21 | H51: 3240.13 | I51: 2656.67 | J51: 2740.27 | K51: 11636.28 | L51: 2946.06 | M51: 3268.82 | N51: 2869.55 | O51: 2899.98 | P51: 11984.41 | Q51: 2923.9 | R51: 3596.78 | S51: 2878.66 | T51: 3152.87 | U51: 12552.21 | V51: 2769.64 | W51: 3258.79 | X51: 3181.05 | Y51: 3738.96 | Z51: 12948.44 | AA51: 2899.27 | AB51: 2918.94
A52: 1 | C52: 매출총이익 | E52: 723.22 | G52: 556.41 | H52: 548.33 | I52: 484.86 | J52: 688.04 | K52: 2277.64 | L52: 484.06 | M52: 569.77 | N52: 278.52 | O52: 366.27 | P52: 1698.62 | Q52: 494.63 | R52: 924.63 | S52: 522.08 | T52: 444.56 | U52: 2385.9 | V52: 295.49 | W52: 741.8 | X52: 620.52 | Y52: 471.68 | Z52: 2129.49 | AA52: 386.26 | AB52: 396.4
A53: 1 | C53: 판관비 | E53: 878.61 | G53: 861.46 | H53: 969.41 | I53: 868.67 | J53: 848.06 | K53: 3547.6 | L53: 740.44 | M53: 764.55 | N53: 859.38 | O53: 829.5 | P53: 3193.87 | Q53: 802.51 | R53: 926.68 | S53: 707.06 | T53: 665.37 | U53: 3101.62 | V53: 672.94 | W53: 729.71 | X53: 647.44 | Y53: 700.57 | Z53: 2750.66 | AA53: 690.16 | AB53: 1132.34
A54: 1 | C54: 영업이익 | E54: -155.4 | G54: -305.05 | H54: -421.09 | I54: -383.81 | J54: -160.02 | K54: -1269.97 | L54: -256.38 | M54: -194.78 | N54: -580.86 | O54: -463.23 | P54: -1495.25 | Q54: -307.87 | R54: -2.05 | S54: -184.98 | T54: -220.82 | U54: -715.72 | V54: -377.45 | W54: 12.09 | X54: -26.91 | Y54: -228.9 | Z54: -621.17 | AA54: -303.89 | AB54: -735.94
A55: 1 | C55: 금융수익 | E55: 52.08 | G55: 186.52 | H55: 123.2 | I55: 189.46 | J55: 27.17 | K55: 526.35 | L55: 314.92 | M55: 179.81 | N55: 124.19 | O55: 189.49 | P55: 808.41 | Q55: 302.05 | R55: 252.93 | S55: 163.51 | T55: 158.57 | U55: 877.06 | V55: 302.27 | W55: 836.42 | X55: -19.22 | Y55: 144.57 | Z55: 1264.04 | AA55: 173.39 | AB55: 2386.67
A56: 1 | C56: 금융비용 | E56: 88.92 | G56: 56.82 | H56: 51.77 | I56: 125.58 | J56: 112.44 | K56: 346.61 | L56: 55.45 | M56: 247.61 | N56: 144.01 | O56: 15.23 | P56: 462.3 | Q56: 226.08 | R56: 204.93 | S56: 74.4 | T56: 195.15 | U56: 700.56 | V56: 157.71 | W56: 183.16 | X56: -2.85 | Y56: 183.23 | Z56: 521.25 | AA56: 186.16 | AB56: 379.04
A57: 1 | C57: 기타영업외수익 | E57: 13.23 | G57: 39.8 | H57: 12.08 | I57: 5.34 | J57: 6.06 | K57: 63.28 | L57: 287.29 | M57: 56.94 | N57: 9.81 | O57: 16.82 | P57: 370.86 | Q57: 15.57 | R57: 8.01 | S57: 6.77 | T57: 5.88 | U57: 36.23 | V57: 5.36 | W57: 10.18 | X57: 7.89 | Y57: 6.53 | Z57: 29.96 | AA57: 37.7 | AB57: 6.77
A58: 1 | C58: 기타영업외비용 | E58: 0.15 | G58: 0 | H58: 0 | I58: 0 | J58: 0 | K58: 0 | N58: 0 | O58: 0 | Q58: 0 | R58: 24.9 | S58: 0 | T58: 0 | U58: 24.9 | V58: 0 | W58: 0 | X58: 3.72 | Y58: 0 | Z58: 3.72 | AA58: 0 | AB58: 0
A59: 1 | C59: 법인세비용차감전계속사업이익 | E59: -179.15 | G59: -135.54 | H59: -337.57 | I59: -314.58 | J59: -239.23 | K59: -1026.92 | L59: 290.38 | M59: -205.64 | N59: -590.86 | O59: -272.16 | P59: -778.28 | Q59: -216.34 | R59: 29.06 | S59: -89.1 | T59: -251.51 | U59: -527.89 | V59: -227.53 | W59: 675.52 | X59: -39.11 | Y59: -261.03 | Z59: 147.85 | AA59: -278.97 | AB59: 1278.46
A60: 1 | C60: 법인세비용 | E60: -13.64 | AB60: 0
A61: 1 | C61: 당기순이익 | E61: -165.5 | G61: -135.54 | H61: -337.57 | I61: -314.58 | J61: -239.23 | K61: -1026.92 | L61: 290.38 | M61: -205.64 | N61: -590.86 | O61: -272.16 | P61: -778.28 | Q61: -216.34 | R61: 29.06 | S61: -89.1 | T61: -251.51 | U61: -527.89 | V61: -227.53 | W61: 675.52 | X61: -39.11 | Y61: -261.03 | Z61: 147.85 | AA61: -278.97 | AB61: 1278.46
A62: 1 | C62: 총포괄손익 | E62: -119.6 | G62: -78.26 | H62: -290.69 | I62: -263.46 | J62: -192.56 | K62: -824.97 | L62: 275.23 | M62: -267.25 | N62: -573.46 | O62: -343.47 | P62: -908.95 | Q62: -273.07 | R62: -10.07 | S62: -49.12 | T62: -182.05 | U62: -514.31 | V62: -218.55 | W62: 597.65 | X62: -28.17 | Y62: -210.36 | Z62: 140.57 | AA62: -275.05 | AB62: 1289.63
A63: 1 | C63: 금융손익 | E63: -36.84 | G63: 129.7 | H63: 71.43 | I63: 63.88 | J63: -85.27 | K63: 179.74 | L63: 259.47 | M63: -67.8 | N63: -19.82 | O63: 174.26 | P63: 346.11 | Q63: 75.97 | R63: 48 | S63: 89.11 | T63: -36.58 | U63: 176.5 | V63: 144.56 | W63: 653.26 | X63: -16.37 | Y63: -38.66 | Z63: 742.79 | AA63: -12.77 | AB63: 2007.63
A64: 1 | C64: 기타영업외손익 | E64: 13.08 | G64: 39.8 | H64: 12.08 | I64: 5.34 | J64: 6.06 | K64: 63.28 | L64: 287.29 | M64: 56.94 | N64: 9.81 | O64: 16.82 | P64: 370.86 | Q64: 15.57 | R64: -16.89 | S64: 6.77 | T64: 5.88 | U64: 11.33 | V64: 5.36 | W64: 10.18 | X64: 4.17 | Y64: 6.53 | Z64: 26.24 | AA64: 37.7 | AB64: 6.77
A65: 1 | C65: (지배주주지분)당기순이익 | E65: -165.5 | G65: -135.54 | H65: -337.57 | I65: -314.58 | J65: -239.23 | K65: -1026.92 | L65: 290.38 | M65: -205.64 | N65: -590.86 | O65: -272.16 | P65: -778.28 | Q65: -216.34 | R65: 29.06 | S65: -89.1 | T65: -251.51 | U65: -527.89 | V65: -227.53 | W65: 675.52 | X65: -39.11 | Y65: -261.03 | Z65: 147.85 | AA65: -278.97 | AB65: 1278.46
A66: 1 | C66: 계속사업이익 | E66: -165.5 | G66: -135.54 | H66: -337.57 | I66: -314.58 | J66: -239.23 | K66: -1026.92 | L66: 290.38 | M66: -205.64 | N66: -590.86 | O66: -272.16 | P66: -778.28 | Q66: -216.34 | R66: 29.06 | S66: -89.1 | T66: -251.51 | U66: -527.89 | V66: -227.53 | W66: 675.52 | X66: -39.11 | Y66: -261.03 | Z66: 147.85 | AA66: -278.97 | AB66: 1278.46
A67: 1 | C67: 이자수익 | G67: 79.3 | H67: 64.87 | I67: 65.21 | J67: 67.84 | K67: 277.22 | L67: 92.64 | M67: 102.92 | N67: 91.67 | O67: 92.76 | P67: 379.99 | Q67: 92.04 | R67: 83.8 | S67: 82.34 | T67: 83.75 | U67: 341.93 | V67: 81.38 | W67: 76.89 | X67: 70.7 | Y67: 80.35 | Z67: 309.32 | AA67: 86.16 | AB67: 58.62
A68: 1 | C68: 이자비용 | G68: 40.23 | H68: 23.5 | I68: 0.06 | J68: 0.05 | K68: 63.84 | L68: 0.02 | M68: 0.01 | N68: 0 | O68: 0.29 | P68: 0.32 | Q68: 0.57 | R68: 0.53 | S68: 0.51 | T68: 0.47 | U68: 2.08 | V68: 0.44 | W68: 0.4 | X68: 0.36 | Y68: 0.33 | Z68: 1.53 | AA68: 0.29 | AB68: 252.06
A69: 1 | C69: 외환차익 | G69: 27.57 | H69: 13.62 | I69: 51.73 | J69: 11.09 | K69: 104.01 | L69: 31.2 | M69: 59.96 | N69: 17.95 | O69: 13.95 | P69: 123.06 | Q69: 16.28 | R69: 2.72 | S69: 54.87 | T69: 15.62 | U69: 89.49 | V69: 30.84 | W69: 17.05 | X69: 1.08 | Y69: 4.6 | Z69: 53.57 | AA69: 45.36 | AB69: 58.93
A70: 1 | C70: 외환차손 | G70: 4.96 | H70: 28.03 | I70: 6.48 | J70: 20.49 | K70: 59.96 | L70: 0.7 | M70: 31.6 | N70: 31.26 | O70: 19.31 | P70: 82.87 | Q70: 5.82 | R70: 27.54 | S70: 1.19 | T70: 7.6 | U70: 42.15 | V70: 0.91 | W70: 13.64 | X70: 3.59 | Y70: 3.39 | Z70: 21.53 | AA70: 0.65 | AB70: 1.99
A71: 1 | C71: 외화환산이익 | G71: 4.56 | H71: 32.64 | I71: 64.69 | J71: -100.36 | K71: 1.53 | L71: 85.72 | M71: -81.11 | N71: 2.69 | O71: -6.73 | P71: 0.57 | Q71: 7.78 | R71: 11.01 | S71: -15.54 | T71: 25.46 | U71: 28.71 | V71: 6.27 | Y71: 4.63 | AA71: 41.87 | AB71: -37.96
A72: 1 | C72: 외화환산손실 | G72: 11.63 | H72: 0.24 | L72: 0.11 | M72: 145.74 | N72: -26.19 | O72: -35.58 | P72: 84.08 | Q72: 82.78 | R72: -23.67 | S72: -53.57 | T72: -5.41 | U72: 0.13 | V72: 0.07 | W72: 38.65 | X72: -21.27 | Y72: 29.78 | Z72: 47.23 | AA72: 0.01 | AB72: 0.15
A73: 1 | C73: 이자손익 | G73: 39.07 | H73: 41.37 | I73: 65.15 | J73: 67.79 | K73: 213.38 | L73: 92.62 | M73: 102.91 | N73: 91.67 | O73: 92.47 | P73: 379.67 | Q73: 91.47 | R73: 83.27 | S73: 81.83 | T73: 83.28 | U73: 339.85 | V73: 80.94 | W73: 76.49 | X73: 70.34 | Y73: 80.02 | Z73: 307.79 | AA73: 85.87 | AB73: -193.44
A74: 1 | C74: 배당금수익 | I74: 0 | J74: 0.31 | N74: 1.55 | O74: 0 | S74: 2.29 | T74: 0.36 | X74: 0 | Y74: 0
A75: 1 | C75: 영업활동으로인한현금흐름 | E75: 327.84 | G75: -422.93 | H75: -147.51 | I75: 467.96 | J75: -190.8 | K75: -293.28 | L75: 516.65 | M75: 157.62 | N75: 608.09 | O75: -277.08 | P75: 1005.28 | Q75: -432.33 | R75: -661.69 | S75: -178.14 | T75: 358.89 | U75: -913.27 | V75: 303.32 | W75: -309.35 | X75: 1293.05 | Y75: 358.16 | Z75: 1645.18 | AA75: -261.11 | AB75: -1097.28
A76: 1 | C76: 법인세납부(CF) | E76: -4.93 | G76: -11.43 | H76: -5.52 | I76: -10.54 | J76: -10.03 | K76: -37.52 | L76: -6.57 | M76: 30.56 | N76: -16.47 | O76: -18.93 | P76: -11.41 | Q76: -12.18 | R76: 40.62 | S76: -9.85 | T76: -13.8 | U76: 4.79 | V76: -12.06 | W76: 45.78 | X76: -14.72 | Y76: -12.57 | Z76: 6.43 | AA76: -6.14 | AB76: 25.99
A77: 1 | C77: 투자활동으로인한현금흐름 | E77: -9150.44 | G77: 2585.62 | H77: 2426.08 | I77: -537.05 | J77: -4869.25 | K77: -394.6 | L77: 8028.66 | M77: 1380.69 | N77: -3131.33 | O77: -2397.42 | P77: 3880.6 | Q77: 1883.94 | R77: -1293.13 | S77: -1636.86 | T77: 973.02 | U77: -73.03 | V77: 987.2 | W77: -2079.77 | X77: 3371.33 | Y77: -4008.86 | Z77: -1730.1 | AA77: -1280.2 | AB77: -767.33
A78: 1 | C78: 유형자산의증가 | E78: 150.44 | G78: 1541.47 | H78: 566.4 | I78: 1717.94 | J78: 104.77 | K78: 3930.58 | L78: 17.39 | M78: 47.37 | N78: 163.23 | O78: 205.42 | P78: 433.41 | Q78: 33.15 | R78: 87.95 | S78: 624.63 | T78: 30 | U78: 775.73 | V78: 30.65 | W78: 13.1 | X78: 34.25 | Y78: 8.86 | Z78: 86.86 | AA78: 1310.2 | AB78: 1373.07
A79: 1 | C79: CAPEX | E79: 150.44 | G79: 1541.47 | H79: 573.91 | I79: 1717.94 | J79: 104.77 | K79: 3938.09 | L79: 17.39 | M79: 47.37 | N79: 163.23 | O79: 205.42 | P79: 433.41 | Q79: 33.15 | R79: 87.95 | S79: 624.63 | T79: 30 | U79: 775.73 | V79: 30.65 | W79: 13.1 | X79: 34.25 | Y79: 8.86 | Z79: 86.86 | AA79: 1310.2 | AB79: 1373.07
A80: 1 | C80: 재무활동으로인한현금흐름 | E80: 10416.96 | G80: -2.77 | H80: -5001.65 | I80: 463.41 | J80: -1.65 | K80: -4542.66 | L80: 127.8 | M80: -0.79 | N80: 0 | O80: -1.04 | P80: 125.97 | Q80: 92.35 | R80: -4.14 | S80: -2.08 | T80: -2.08 | U80: 84.05 | V80: -2.08 | W80: -2.08 | X80: 70.73 | Y80: -2.08 | Z80: 64.49 | AA80: -2.08 | AB80: 19377.2
A81: 1 | C81: 유동성장기부채의감소 | E81: 0 | I81: 0 | J81: 0
A82: 1 | C82: 리스부채의상환 | E82: 5.03 | G82: 2.77 | H82: 1.65 | I82: 1.65 | J82: 1.65 | K82: 7.72 | L82: 1.65 | M82: 0.8 | N82: 0 | O82: 1.03 | P82: 3.48 | Q82: 2.08 | R82: 2.08 | S82: 2.07 | T82: 2.08 | U82: 8.31 | V82: 2.08 | W82: 2.08 | X82: 2.07 | Y82: 2.08 | Z82: 8.31 | AA82: 2.08 | AB82: 4.8
A83: 1 | C83: 현금및현금성자산의증감 | E83: 1585.98 | G83: 2162.61 | H83: -2701.02 | I83: 459.76 | J83: -5221.44 | K83: -5300.09 | L83: 8749.2 | M83: 1331.47 | N83: -2508.86 | O83: -2643.93 | P83: 4927.88 | Q83: 1466.86 | R83: -1922.76 | S83: -1775.48 | T83: 1351.89 | U83: -879.49 | V83: 1293.51 | W83: -2430.94 | X83: 4753.62 | Y83: -3668.78 | Z83: -52.59 | AA83: -1506.82 | AB83: 17477.92
A84: 1 | C84: 기말현금및현금성자산 | E84: 1587.27 | G84: 11448.72 | H84: -2701.02 | I84: 459.76 | J84: -5221.44 | K84: 3986.02 | L84: 12735.22 | M84: 1331.47 | N84: -2508.86 | O84: -2643.93 | P84: 8913.9 | Q84: 10380.76 | R84: -1922.76 | S84: -1775.48 | T84: 1351.89 | U84: 8034.41 | V84: 9327.91 | W84: -2430.93 | X84: 4753.62 | Y84: -3668.78 | Z84: 7981.82 | AA84: 6475 | AB84: 17477.92
A85: 1 | C85: 유형자산의감소 | G85: 52 | H85: 0 | I85: 0 | J85: 0 | K85: 52 | AA85: 30 | AB85: 0
A86: 1 | C86: 배당금수취(CF) | I86: 0 | J86: 0.31 | N86: 1.55 | O86: 0 | X86: 0 | Y86: 0
A87: 1 | C87: 무형자산의증가 | I87: 0 | J87: 0
A88: 1 | C88: 이자수취(CF) | O88: 134.73 | Q88: 78.49 | R88: 106.27 | S88: 63.94 | T88: 99.01 | U88: 347.71 | V88: 84.16 | W88: 35.19 | X88: 95.65 | Y88: 81.65 | Z88: 296.65 | AA88: 40.97 | AB88: 126.83

Sheet subQ
A1: YQ | C1: subQ 분기 서브모델(억원, U=100) | E1: 4Q21 | F1: 2021 | G1: 1Q22 | H1: 2Q22 | I1: 3Q22 | J1: 4Q22 | K1: 2022 | L1: 1Q23 | M1: 2Q23 | N1: 3Q23 | O1: 4Q23 | P1: 2023 | Q1: 1Q24 | R1: 2Q24 | S1: 3Q24 | T1: 4Q24 | U1: 2024 | V1: 1Q25 | W1: 2Q25 | X1: 3Q25 | Y1: 4Q25 | Z1: 2025 | AA1: 1Q26 | AB1: 2Q26 | AC1: 3Q26 | AD1: 4Q26 | AE1: 2026 | AF1: 1Q27 | AG1: 2Q27 | AH1: 3Q27 | AI1: 4Q27 | AJ1: 2027 | AK1: 1Q28 | AL1: 2Q28 | AM1: 3Q28 | AN1: 4Q28 | AO1: 2028
A2: A=이름(key) B=그룹 C=단위 D=FnGuide 계정명(VLOOKUP 키). 확정=VLOOKUP(BS), 추정=변수 가정 참조
E3: 1 | F3: 2 | G3: 3 | H3: 4 | I3: 5 | J3: 6 | K3: 7 | L3: 8 | M3: 9 | N3: 10 | O3: 11 | P3: 12 | Q3: 13 | R3: 14 | S3: 15 | T3: 16 | U3: 17 | V3: 18 | W3: 19 | X3: 20 | Y3: 21 | Z3: 22 | AA3: 23 | AB3: 24 | AC3: 25 | AD3: 26 | AE3: 27 | AF3: 28 | AG3: 29 | AH3: 30 | AI3: 31 | AJ3: 32 | AK3: 33 | AL3: 34 | AM3: 35 | AN3: 36 | AO3: 37
E4: 2021.12 | F4: 2021.12A | G4: 2022.03 | H4: 2022.06 | I4: 2022.09 | J4: 2022.12 | K4: 2022.12A | L4: 2023.03 | M4: 2023.06 | N4: 2023.09 | O4: 2023.12 | P4: 2023.12A | Q4: 2024.03 | R4: 2024.06 | S4: 2024.09 | T4: 2024.12 | U4: 2024.12A | V4: 2025.03 | W4: 2025.06 | X4: 2025.09 | Y4: 2025.12 | Z4: 2025.12A | AA4: 2026.03 | AB4: 2026.06 | AC4: 2026.09 | AD4: 2026.12 | AE4: 2026.12A | AF4: 2027.03 | AG4: 2027.06 | AH4: 2027.09 | AI4: 2027.12 | AJ4: 2027.12A | AK4: 2028.03 | AL4: 2028.06 | AM4: 2028.09 | AN4: 2028.12 | AO4: 2028.12A
A5: 매출액 | B5: 손익 | C5: 억원 | D5: 매출액(수익) | E5: =IFERROR(VLOOKUP($D5,BS별도,MATCH(E$1,BS별도H,0),0)/100,"") | G5: =IFERROR(VLOOKUP($D5,BS별도,MATCH(G$1,BS별도H,0),0)/100,"") | H5: =IFERROR(VLOOKUP($D5,BS별도,MATCH(H$1,BS별도H,0),0)/100,"") | I5: =IFERROR(VLOOKUP($D5,BS별도,MATCH(I$1,BS별도H,0),0)/100,"") | J5: =IFERROR(VLOOKUP($D5,BS별도,MATCH(J$1,BS별도H,0),0)/100,"") | K5: =SUM(G5:J5) | L5: =IFERROR(VLOOKUP($D5,BS별도,MATCH(L$1,BS별도H,0),0)/100,"") | M5: =IFERROR(VLOOKUP($D5,BS별도,MATCH(M$1,BS별도H,0),0)/100,"") | N5: =IFERROR(VLOOKUP($D5,BS별도,MATCH(N$1,BS별도H,0),0)/100,"") | O5: =IFERROR(VLOOKUP($D5,BS별도,MATCH(O$1,BS별도H,0),0)/100,"") | P5: =SUM(L5:O5) | Q5: =IFERROR(VLOOKUP($D5,BS별도,MATCH(Q$1,BS별도H,0),0)/100,"") | R5: =IFERROR(VLOOKUP($D5,BS별도,MATCH(R$1,BS별도H,0),0)/100,"") | S5: =IFERROR(VLOOKUP($D5,BS별도,MATCH(S$1,BS별도H,0),0)/100,"") | T5: =IFERROR(VLOOKUP($D5,BS별도,MATCH(T$1,BS별도H,0),0)/100,"") | U5: =SUM(Q5:T5) | V5: =IFERROR(VLOOKUP($D5,BS별도,MATCH(V$1,BS별도H,0),0)/100,"") | W5: =IFERROR(VLOOKUP($D5,BS별도,MATCH(W$1,BS별도H,0),0)/100,"") | X5: =IFERROR(VLOOKUP($D5,BS별도,MATCH(X$1,BS별도H,0),0)/100,"") | Y5: =IFERROR(VLOOKUP($D5,BS별도,MATCH(Y$1,BS별도H,0),0)/100,"") | Z5: =SUM(V5:Y5) | AA5: =IFERROR(VLOOKUP($D5,BS별도,MATCH(AA$1,BS별도H,0),0)/100,"") | AB5: =IFERROR(VLOOKUP($D5,BS별도,MATCH(AB$1,BS별도H,0),0)/100,"") | AC5: =IFERROR(X5*(1+변수!AC21),"") | AD5: =IFERROR(Y5*(1+변수!AD21),"") | AE5: =SUM(AA5:AD5) | AF5: =IFERROR(AA5*(1+변수!AF21),"") | AG5: =IFERROR(AB5*(1+변수!AG21),"") | AH5: =IFERROR(AC5*(1+변수!AH21),"") | AI5: =IFERROR(AD5*(1+변수!AI21),"") | AJ5: =SUM(AF5:AI5) | AK5: =IFERROR(AF5*(1+변수!AK21),"") | AL5: =IFERROR(AG5*(1+변수!AL21),"") | AM5: =IFERROR(AH5*(1+변수!AM21),"") | AN5: =IFERROR(AI5*(1+변수!AN21),"") | AO5: =SUM(AK5:AN5)
A6: 매출원가 | B6: 손익 | C6: 억원 | D6: 매출원가 | E6: =IFERROR(VLOOKUP($D6,BS별도,MATCH(E$1,BS별도H,0),0)/100,"") | G6: =IFERROR(VLOOKUP($D6,BS별도,MATCH(G$1,BS별도H,0),0)/100,"") | H6: =IFERROR(VLOOKUP($D6,BS별도,MATCH(H$1,BS별도H,0),0)/100,"") | I6: =IFERROR(VLOOKUP($D6,BS별도,MATCH(I$1,BS별도H,0),0)/100,"") | J6: =IFERROR(VLOOKUP($D6,BS별도,MATCH(J$1,BS별도H,0),0)/100,"") | K6: =SUM(G6:J6) | L6: =IFERROR(VLOOKUP($D6,BS별도,MATCH(L$1,BS별도H,0),0)/100,"") | M6: =IFERROR(VLOOKUP($D6,BS별도,MATCH(M$1,BS별도H,0),0)/100,"") | N6: =IFERROR(VLOOKUP($D6,BS별도,MATCH(N$1,BS별도H,0),0)/100,"") | O6: =IFERROR(VLOOKUP($D6,BS별도,MATCH(O$1,BS별도H,0),0)/100,"") | P6: =SUM(L6:O6) | Q6: =IFERROR(VLOOKUP($D6,BS별도,MATCH(Q$1,BS별도H,0),0)/100,"") | R6: =IFERROR(VLOOKUP($D6,BS별도,MATCH(R$1,BS별도H,0),0)/100,"") | S6: =IFERROR(VLOOKUP($D6,BS별도,MATCH(S$1,BS별도H,0),0)/100,"") | T6: =IFERROR(VLOOKUP($D6,BS별도,MATCH(T$1,BS별도H,0),0)/100,"") | U6: =SUM(Q6:T6) | V6: =IFERROR(VLOOKUP($D6,BS별도,MATCH(V$1,BS별도H,0),0)/100,"") | W6: =IFERROR(VLOOKUP($D6,BS별도,MATCH(W$1,BS별도H,0),0)/100,"") | X6: =IFERROR(VLOOKUP($D6,BS별도,MATCH(X$1,BS별도H,0),0)/100,"") | Y6: =IFERROR(VLOOKUP($D6,BS별도,MATCH(Y$1,BS별도H,0),0)/100,"") | Z6: =SUM(V6:Y6) | AA6: =IFERROR(VLOOKUP($D6,BS별도,MATCH(AA$1,BS별도H,0),0)/100,"") | AB6: =IFERROR(VLOOKUP($D6,BS별도,MATCH(AB$1,BS별도H,0),0)/100,"") | AC6: =IFERROR(AC5-AC7,"") | AD6: =IFERROR(AD5-AD7,"") | AE6: =SUM(AA6:AD6) | AF6: =IFERROR(AF5-AF7,"") | AG6: =IFERROR(AG5-AG7,"") | AH6: =IFERROR(AH5-AH7,"") | AI6: =IFERROR(AI5-AI7,"") | AJ6: =SUM(AF6:AI6) | AK6: =IFERROR(AK5-AK7,"") | AL6: =IFERROR(AL5-AL7,"") | AM6: =IFERROR(AM5-AM7,"") | AN6: =IFERROR(AN5-AN7,"") | AO6: =SUM(AK6:AN6)
A7: 매출총이익 | B7: 손익 | C7: 억원 | D7: 매출총이익 | E7: =IFERROR(VLOOKUP($D7,BS별도,MATCH(E$1,BS별도H,0),0)/100,"") | G7: =IFERROR(VLOOKUP($D7,BS별도,MATCH(G$1,BS별도H,0),0)/100,"") | H7: =IFERROR(VLOOKUP($D7,BS별도,MATCH(H$1,BS별도H,0),0)/100,"") | I7: =IFERROR(VLOOKUP($D7,BS별도,MATCH(I$1,BS별도H,0),0)/100,"") | J7: =IFERROR(VLOOKUP($D7,BS별도,MATCH(J$1,BS별도H,0),0)/100,"") | K7: =SUM(G7:J7) | L7: =IFERROR(VLOOKUP($D7,BS별도,MATCH(L$1,BS별도H,0),0)/100,"") | M7: =IFERROR(VLOOKUP($D7,BS별도,MATCH(M$1,BS별도H,0),0)/100,"") | N7: =IFERROR(VLOOKUP($D7,BS별도,MATCH(N$1,BS별도H,0),0)/100,"") | O7: =IFERROR(VLOOKUP($D7,BS별도,MATCH(O$1,BS별도H,0),0)/100,"") | P7: =SUM(L7:O7) | Q7: =IFERROR(VLOOKUP($D7,BS별도,MATCH(Q$1,BS별도H,0),0)/100,"") | R7: =IFERROR(VLOOKUP($D7,BS별도,MATCH(R$1,BS별도H,0),0)/100,"") | S7: =IFERROR(VLOOKUP($D7,BS별도,MATCH(S$1,BS별도H,0),0)/100,"") | T7: =IFERROR(VLOOKUP($D7,BS별도,MATCH(T$1,BS별도H,0),0)/100,"") | U7: =SUM(Q7:T7) | V7: =IFERROR(VLOOKUP($D7,BS별도,MATCH(V$1,BS별도H,0),0)/100,"") | W7: =IFERROR(VLOOKUP($D7,BS별도,MATCH(W$1,BS별도H,0),0)/100,"") | X7: =IFERROR(VLOOKUP($D7,BS별도,MATCH(X$1,BS별도H,0),0)/100,"") | Y7: =IFERROR(VLOOKUP($D7,BS별도,MATCH(Y$1,BS별도H,0),0)/100,"") | Z7: =SUM(V7:Y7) | AA7: =IFERROR(VLOOKUP($D7,BS별도,MATCH(AA$1,BS별도H,0),0)/100,"") | AB7: =IFERROR(VLOOKUP($D7,BS별도,MATCH(AB$1,BS별도H,0),0)/100,"") | AC7: =IFERROR(AC9+AC8,"") | AD7: =IFERROR(AD9+AD8,"") | AE7: =SUM(AA7:AD7) | AF7: =IFERROR(AF9+AF8,"") | AG7: =IFERROR(AG9+AG8,"") | AH7: =IFERROR(AH9+AH8,"") | AI7: =IFERROR(AI9+AI8,"") | AJ7: =SUM(AF7:AI7) | AK7: =IFERROR(AK9+AK8,"") | AL7: =IFERROR(AL9+AL8,"") | AM7: =IFERROR(AM9+AM8,"") | AN7: =IFERROR(AN9+AN8,"") | AO7: =SUM(AK7:AN7)
A8: 판관비 | B8: 손익 | C8: 억원 | D8: 판관비 | E8: =IFERROR(VLOOKUP($D8,BS별도,MATCH(E$1,BS별도H,0),0)/100,"") | G8: =IFERROR(VLOOKUP($D8,BS별도,MATCH(G$1,BS별도H,0),0)/100,"") | H8: =IFERROR(VLOOKUP($D8,BS별도,MATCH(H$1,BS별도H,0),0)/100,"") | I8: =IFERROR(VLOOKUP($D8,BS별도,MATCH(I$1,BS별도H,0),0)/100,"") | J8: =IFERROR(VLOOKUP($D8,BS별도,MATCH(J$1,BS별도H,0),0)/100,"") | K8: =SUM(G8:J8) | L8: =IFERROR(VLOOKUP($D8,BS별도,MATCH(L$1,BS별도H,0),0)/100,"") | M8: =IFERROR(VLOOKUP($D8,BS별도,MATCH(M$1,BS별도H,0),0)/100,"") | N8: =IFERROR(VLOOKUP($D8,BS별도,MATCH(N$1,BS별도H,0),0)/100,"") | O8: =IFERROR(VLOOKUP($D8,BS별도,MATCH(O$1,BS별도H,0),0)/100,"") | P8: =SUM(L8:O8) | Q8: =IFERROR(VLOOKUP($D8,BS별도,MATCH(Q$1,BS별도H,0),0)/100,"") | R8: =IFERROR(VLOOKUP($D8,BS별도,MATCH(R$1,BS별도H,0),0)/100,"") | S8: =IFERROR(VLOOKUP($D8,BS별도,MATCH(S$1,BS별도H,0),0)/100,"") | T8: =IFERROR(VLOOKUP($D8,BS별도,MATCH(T$1,BS별도H,0),0)/100,"") | U8: =SUM(Q8:T8) | V8: =IFERROR(VLOOKUP($D8,BS별도,MATCH(V$1,BS별도H,0),0)/100,"") | W8: =IFERROR(VLOOKUP($D8,BS별도,MATCH(W$1,BS별도H,0),0)/100,"") | X8: =IFERROR(VLOOKUP($D8,BS별도,MATCH(X$1,BS별도H,0),0)/100,"") | Y8: =IFERROR(VLOOKUP($D8,BS별도,MATCH(Y$1,BS별도H,0),0)/100,"") | Z8: =SUM(V8:Y8) | AA8: =IFERROR(VLOOKUP($D8,BS별도,MATCH(AA$1,BS별도H,0),0)/100,"") | AB8: =IFERROR(VLOOKUP($D8,BS별도,MATCH(AB$1,BS별도H,0),0)/100,"") | AC8: =IFERROR(AC5*변수!AC22,"") | AD8: =IFERROR(AD5*변수!AD22,"") | AE8: =SUM(AA8:AD8) | AF8: =IFERROR(AF5*변수!AF22,"") | AG8: =IFERROR(AG5*변수!AG22,"") | AH8: =IFERROR(AH5*변수!AH22,"") | AI8: =IFERROR(AI5*변수!AI22,"") | AJ8: =SUM(AF8:AI8) | AK8: =IFERROR(AK5*변수!AK22,"") | AL8: =IFERROR(AL5*변수!AL22,"") | AM8: =IFERROR(AM5*변수!AM22,"") | AN8: =IFERROR(AN5*변수!AN22,"") | AO8: =SUM(AK8:AN8)
A9: 영업이익 | B9: 손익 | C9: 억원 | D9: 영업이익 | E9: =IFERROR(VLOOKUP($D9,BS별도,MATCH(E$1,BS별도H,0),0)/100,"") | G9: =IFERROR(VLOOKUP($D9,BS별도,MATCH(G$1,BS별도H,0),0)/100,"") | H9: =IFERROR(VLOOKUP($D9,BS별도,MATCH(H$1,BS별도H,0),0)/100,"") | I9: =IFERROR(VLOOKUP($D9,BS별도,MATCH(I$1,BS별도H,0),0)/100,"") | J9: =IFERROR(VLOOKUP($D9,BS별도,MATCH(J$1,BS별도H,0),0)/100,"") | K9: =SUM(G9:J9) | L9: =IFERROR(VLOOKUP($D9,BS별도,MATCH(L$1,BS별도H,0),0)/100,"") | M9: =IFERROR(VLOOKUP($D9,BS별도,MATCH(M$1,BS별도H,0),0)/100,"") | N9: =IFERROR(VLOOKUP($D9,BS별도,MATCH(N$1,BS별도H,0),0)/100,"") | O9: =IFERROR(VLOOKUP($D9,BS별도,MATCH(O$1,BS별도H,0),0)/100,"") | P9: =SUM(L9:O9) | Q9: =IFERROR(VLOOKUP($D9,BS별도,MATCH(Q$1,BS별도H,0),0)/100,"") | R9: =IFERROR(VLOOKUP($D9,BS별도,MATCH(R$1,BS별도H,0),0)/100,"") | S9: =IFERROR(VLOOKUP($D9,BS별도,MATCH(S$1,BS별도H,0),0)/100,"") | T9: =IFERROR(VLOOKUP($D9,BS별도,MATCH(T$1,BS별도H,0),0)/100,"") | U9: =SUM(Q9:T9) | V9: =IFERROR(VLOOKUP($D9,BS별도,MATCH(V$1,BS별도H,0),0)/100,"") | W9: =IFERROR(VLOOKUP($D9,BS별도,MATCH(W$1,BS별도H,0),0)/100,"") | X9: =IFERROR(VLOOKUP($D9,BS별도,MATCH(X$1,BS별도H,0),0)/100,"") | Y9: =IFERROR(VLOOKUP($D9,BS별도,MATCH(Y$1,BS별도H,0),0)/100,"") | Z9: =SUM(V9:Y9) | AA9: =IFERROR(VLOOKUP($D9,BS별도,MATCH(AA$1,BS별도H,0),0)/100,"") | AB9: =IFERROR(VLOOKUP($D9,BS별도,MATCH(AB$1,BS별도H,0),0)/100,"") | AC9: =IFERROR(AC5*변수!AC23,"") | AD9: =IFERROR(AD5*변수!AD23,"") | AE9: =SUM(AA9:AD9) | AF9: =IFERROR(AF5*변수!AF23,"") | AG9: =IFERROR(AG5*변수!AG23,"") | AH9: =IFERROR(AH5*변수!AH23,"") | AI9: =IFERROR(AI5*변수!AI23,"") | AJ9: =SUM(AF9:AI9) | AK9: =IFERROR(AK5*변수!AK23,"") | AL9: =IFERROR(AL5*변수!AL23,"") | AM9: =IFERROR(AM5*변수!AM23,"") | AN9: =IFERROR(AN5*변수!AN23,"") | AO9: =SUM(AK9:AN9)
A10: OPM | B10: 손익 | C10: % | D10: 영업이익률 | E10: =IFERROR(E9/E5,"") | G10: =IFERROR(G9/G5,"") | H10: =IFERROR(H9/H5,"") | I10: =IFERROR(I9/I5,"") | J10: =IFERROR(J9/J5,"") | K10: =IFERROR(K9/K5,"") | L10: =IFERROR(L9/L5,"") | M10: =IFERROR(M9/M5,"") | N10: =IFERROR(N9/N5,"") | ... AO10: =IFERROR(AO9/AO5,"")
A11: 금융손익 | B11: 손익 | C11: 억원 | D11: 금융손익 | E11: =IFERROR(VLOOKUP($D11,BS별도,MATCH(E$1,BS별도H,0),0)/100,"") | G11: =IFERROR(VLOOKUP($D11,BS별도,MATCH(G$1,BS별도H,0),0)/100,"") | H11: =IFERROR(VLOOKUP($D11,BS별도,MATCH(H$1,BS별도H,0),0)/100,"") | I11: =IFERROR(VLOOKUP($D11,BS별도,MATCH(I$1,BS별도H,0),0)/100,"") | J11: =IFERROR(VLOOKUP($D11,BS별도,MATCH(J$1,BS별도H,0),0)/100,"") | K11: =SUM(G11:J11) | L11: =IFERROR(VLOOKUP($D11,BS별도,MATCH(L$1,BS별도H,0),0)/100,"") | M11: =IFERROR(VLOOKUP($D11,BS별도,MATCH(M$1,BS별도H,0),0)/100,"") | N11: =IFERROR(VLOOKUP($D11,BS별도,MATCH(N$1,BS별도H,0),0)/100,"") | O11: =IFERROR(VLOOKUP($D11,BS별도,MATCH(O$1,BS별도H,0),0)/100,"") | P11: =SUM(L11:O11) | Q11: =IFERROR(VLOOKUP($D11,BS별도,MATCH(Q$1,BS별도H,0),0)/100,"") | R11: =IFERROR(VLOOKUP($D11,BS별도,MATCH(R$1,BS별도H,0),0)/100,"") | S11: =IFERROR(VLOOKUP($D11,BS별도,MATCH(S$1,BS별도H,0),0)/100,"") | T11: =IFERROR(VLOOKUP($D11,BS별도,MATCH(T$1,BS별도H,0),0)/100,"") | U11: =SUM(Q11:T11) | V11: =IFERROR(VLOOKUP($D11,BS별도,MATCH(V$1,BS별도H,0),0)/100,"") | W11: =IFERROR(VLOOKUP($D11,BS별도,MATCH(W$1,BS별도H,0),0)/100,"") | X11: =IFERROR(VLOOKUP($D11,BS별도,MATCH(X$1,BS별도H,0),0)/100,"") | Y11: =IFERROR(VLOOKUP($D11,BS별도,MATCH(Y$1,BS별도H,0),0)/100,"") | Z11: =SUM(V11:Y11) | AA11: =IFERROR(VLOOKUP($D11,BS별도,MATCH(AA$1,BS별도H,0),0)/100,"") | AB11: =IFERROR(VLOOKUP($D11,BS별도,MATCH(AB$1,BS별도H,0),0)/100,"") | AC11: =IFERROR(AC12+AC13,"") | AD11: =IFERROR(AD12+AD13,"") | AE11: =SUM(AA11:AD11) | AF11: =IFERROR(AF12+AF13,"") | AG11: =IFERROR(AG12+AG13,"") | AH11: =IFERROR(AH12+AH13,"") | AI11: =IFERROR(AI12+AI13,"") | AJ11: =SUM(AF11:AI11) | AK11: =IFERROR(AK12+AK13,"") | AL11: =IFERROR(AL12+AL13,"") | AM11: =IFERROR(AM12+AM13,"") | AN11: =IFERROR(AN12+AN13,"") | AO11: =SUM(AK11:AN11)
A12: 이자손익 | B12: 손익 | C12: 억원 | D12: 이자손익 | G12: =IFERROR(VLOOKUP($D12,BS별도,MATCH(G$1,BS별도H,0),0)/100,"") | H12: =IFERROR(VLOOKUP($D12,BS별도,MATCH(H$1,BS별도H,0),0)/100,"") | I12: =IFERROR(VLOOKUP($D12,BS별도,MATCH(I$1,BS별도H,0),0)/100,"") | J12: =IFERROR(VLOOKUP($D12,BS별도,MATCH(J$1,BS별도H,0),0)/100,"") | K12: =SUM(G12:J12) | L12: =IFERROR(VLOOKUP($D12,BS별도,MATCH(L$1,BS별도H,0),0)/100,"") | M12: =IFERROR(VLOOKUP($D12,BS별도,MATCH(M$1,BS별도H,0),0)/100,"") | N12: =IFERROR(VLOOKUP($D12,BS별도,MATCH(N$1,BS별도H,0),0)/100,"") | O12: =IFERROR(VLOOKUP($D12,BS별도,MATCH(O$1,BS별도H,0),0)/100,"") | P12: =SUM(L12:O12) | Q12: =IFERROR(VLOOKUP($D12,BS별도,MATCH(Q$1,BS별도H,0),0)/100,"") | R12: =IFERROR(VLOOKUP($D12,BS별도,MATCH(R$1,BS별도H,0),0)/100,"") | S12: =IFERROR(VLOOKUP($D12,BS별도,MATCH(S$1,BS별도H,0),0)/100,"") | T12: =IFERROR(VLOOKUP($D12,BS별도,MATCH(T$1,BS별도H,0),0)/100,"") | U12: =SUM(Q12:T12) | V12: =IFERROR(VLOOKUP($D12,BS별도,MATCH(V$1,BS별도H,0),0)/100,"") | W12: =IFERROR(VLOOKUP($D12,BS별도,MATCH(W$1,BS별도H,0),0)/100,"") | X12: =IFERROR(VLOOKUP($D12,BS별도,MATCH(X$1,BS별도H,0),0)/100,"") | Y12: =IFERROR(VLOOKUP($D12,BS별도,MATCH(Y$1,BS별도H,0),0)/100,"") | Z12: =SUM(V12:Y12) | AA12: =IFERROR(VLOOKUP($D12,BS별도,MATCH(AA$1,BS별도H,0),0)/100,"") | AB12: =IFERROR(VLOOKUP($D12,BS별도,MATCH(AB$1,BS별도H,0),0)/100,"") | AC12: =IFERROR((AB25*변수!$D$51-AB23*변수!$D$52)/4,"") | AD12: =IFERROR((AC25*변수!$D$51-AC23*변수!$D$52)/4,"") | AE12: =SUM(AA12:AD12) | AF12: =IFERROR((AD25*변수!$D$51-AD23*변수!$D$52)/4,"") | AG12: =IFERROR((AF25*변수!$D$51-AF23*변수!$D$52)/4,"") | AH12: =IFERROR((AG25*변수!$D$51-AG23*변수!$D$52)/4,"") | AI12: =IFERROR((AH25*변수!$D$51-AH23*변수!$D$52)/4,"") | AJ12: =SUM(AF12:AI12) | AK12: =IFERROR((AI25*변수!$D$51-AI23*변수!$D$52)/4,"") | AL12: =IFERROR((AK25*변수!$D$51-AK23*변수!$D$52)/4,"") | AM12: =IFERROR((AL25*변수!$D$51-AL23*변수!$D$52)/4,"") | AN12: =IFERROR((AM25*변수!$D$51-AM23*변수!$D$52)/4,"") | AO12: =SUM(AK12:AN12)
A13: 외환손익 | B13: 손익 | C13: 억원 | D13: 외환손익(실적만; 추정 환효과는 환관련손익) | G13: =IFERROR((VLOOKUP("외환차익",BS별도,MATCH(G$1,BS별도H,0),0)-VLOOKUP("외환차손",BS별도,MATCH(G$1,BS별도H,0),0)+VLOOKUP("외화환산이익",BS별도,MATCH(G$1,BS별도H,0),0)-VLOOKUP("외화환산손실",BS별도,MATCH(G$1,BS별도H,0),0))/100,"") | H13: =IFERROR((VLOOKUP("외환차익",BS별도,MATCH(H$1,BS별도H,0),0)-VLOOKUP("외환차손",BS별도,MATCH(H$1,BS별도H,0),0)+VLOOKUP("외화환산이익",BS별도,MATCH(H$1,BS별도H,0),0)-VLOOKUP("외화환산손실",BS별도,MATCH(H$1,BS별도H,0),0))/100,"") | K13: =SUM(G13:J13) | L13: =IFERROR((VLOOKUP("외환차익",BS별도,MATCH(L$1,BS별도H,0),0)-VLOOKUP("외환차손",BS별도,MATCH(L$1,BS별도H,0),0)+VLOOKUP("외화환산이익",BS별도,MATCH(L$1,BS별도H,0),0)-VLOOKUP("외화환산손실",BS별도,MATCH(L$1,BS별도H,0),0))/100,"") | M13: =IFERROR((VLOOKUP("외환차익",BS별도,MATCH(M$1,BS별도H,0),0)-VLOOKUP("외환차손",BS별도,MATCH(M$1,BS별도H,0),0)+VLOOKUP("외화환산이익",BS별도,MATCH(M$1,BS별도H,0),0)-VLOOKUP("외화환산손실",BS별도,MATCH(M$1,BS별도H,0),0))/100,"") | N13: =IFERROR((VLOOKUP("외환차익",BS별도,MATCH(N$1,BS별도H,0),0)-VLOOKUP("외환차손",BS별도,MATCH(N$1,BS별도H,0),0)+VLOOKUP("외화환산이익",BS별도,MATCH(N$1,BS별도H,0),0)-VLOOKUP("외화환산손실",BS별도,MATCH(N$1,BS별도H,0),0))/100,"") | O13: =IFERROR((VLOOKUP("외환차익",BS별도,MATCH(O$1,BS별도H,0),0)-VLOOKUP("외환차손",BS별도,MATCH(O$1,BS별도H,0),0)+VLOOKUP("외화환산이익",BS별도,MATCH(O$1,BS별도H,0),0)-VLOOKUP("외화환산손실",BS별도,MATCH(O$1,BS별도H,0),0))/100,"") | P13: =SUM(L13:O13) | Q13: =IFERROR((VLOOKUP("외환차익",BS별도,MATCH(Q$1,BS별도H,0),0)-VLOOKUP("외환차손",BS별도,MATCH(Q$1,BS별도H,0),0)+VLOOKUP("외화환산이익",BS별도,MATCH(Q$1,BS별도H,0),0)-VLOOKUP("외화환산손실",BS별도,MATCH(Q$1,BS별도H,0),0))/100,"") | R13: =IFERROR((VLOOKUP("외환차익",BS별도,MATCH(R$1,BS별도H,0),0)-VLOOKUP("외환차손",BS별도,MATCH(R$1,BS별도H,0),0)+VLOOKUP("외화환산이익",BS별도,MATCH(R$1,BS별도H,0),0)-VLOOKUP("외화환산손실",BS별도,MATCH(R$1,BS별도H,0),0))/100,"") | S13: =IFERROR((VLOOKUP("외환차익",BS별도,MATCH(S$1,BS별도H,0),0)-VLOOKUP("외환차손",BS별도,MATCH(S$1,BS별도H,0),0)+VLOOKUP("외화환산이익",BS별도,MATCH(S$1,BS별도H,0),0)-VLOOKUP("외화환산손실",BS별도,MATCH(S$1,BS별도H,0),0))/100,"") | T13: =IFERROR((VLOOKUP("외환차익",BS별도,MATCH(T$1,BS별도H,0),0)-VLOOKUP("외환차손",BS별도,MATCH(T$1,BS별도H,0),0)+VLOOKUP("외화환산이익",BS별도,MATCH(T$1,BS별도H,0),0)-VLOOKUP("외화환산손실",BS별도,MATCH(T$1,BS별도H,0),0))/100,"") | U13: =SUM(Q13:T13) | V13: =IFERROR((VLOOKUP("외환차익",BS별도,MATCH(V$1,BS별도H,0),0)-VLOOKUP("외환차손",BS별도,MATCH(V$1,BS별도H,0),0)+VLOOKUP("외화환산이익",BS별도,MATCH(V$1,BS별도H,0),0)-VLOOKUP("외화환산손실",BS별도,MATCH(V$1,BS별도H,0),0))/100,"") | Y13: =IFERROR((VLOOKUP("외환차익",BS별도,MATCH(Y$1,BS별도H,0),0)-VLOOKUP("외환차손",BS별도,MATCH(Y$1,BS별도H,0),0)+VLOOKUP("외화환산이익",BS별도,MATCH(Y$1,BS별도H,0),0)-VLOOKUP("외화환산손실",BS별도,MATCH(Y$1,BS별도H,0),0))/100,"") | Z13: =SUM(V13:Y13) | AA13: =IFERROR((VLOOKUP("외환차익",BS별도,MATCH(AA$1,BS별도H,0),0)-VLOOKUP("외환차손",BS별도,MATCH(AA$1,BS별도H,0),0)+VLOOKUP("외화환산이익",BS별도,MATCH(AA$1,BS별도H,0),0)-VLOOKUP("외화환산손실",BS별도,MATCH(AA$1,BS별도H,0),0))/100,"") | AB13: =IFERROR((VLOOKUP("외환차익",BS별도,MATCH(AB$1,BS별도H,0),0)-VLOOKUP("외환차손",BS별도,MATCH(AB$1,BS별도H,0),0)+VLOOKUP("외화환산이익",BS별도,MATCH(AB$1,BS별도H,0),0)-VLOOKUP("외화환산손실",BS별도,MATCH(AB$1,BS별도H,0),0))/100,"") | AC13: =변수!AC24 | AD13: =변수!AD24 | AE13: =SUM(AA13:AD13) | AF13: =변수!AF24 | AG13: =변수!AG24 | AH13: =변수!AH24 | AI13: =변수!AI24 | AJ13: =SUM(AF13:AI13) | AK13: =변수!AK24 | AL13: =변수!AL24 | AM13: =변수!AM24 | AN13: =변수!AN24 | AO13: =SUM(AK13:AN13)
A14: 기타영업외손익 | B14: 손익 | C14: 억원 | D14: 기타영업외손익 | E14: =IFERROR(VLOOKUP($D14,BS별도,MATCH(E$1,BS별도H,0),0)/100,"") | G14: =IFERROR(VLOOKUP($D14,BS별도,MATCH(G$1,BS별도H,0),0)/100,"") | H14: =IFERROR(VLOOKUP($D14,BS별도,MATCH(H$1,BS별도H,0),0)/100,"") | I14: =IFERROR(VLOOKUP($D14,BS별도,MATCH(I$1,BS별도H,0),0)/100,"") | J14: =IFERROR(VLOOKUP($D14,BS별도,MATCH(J$1,BS별도H,0),0)/100,"") | K14: =SUM(G14:J14) | L14: =IFERROR(VLOOKUP($D14,BS별도,MATCH(L$1,BS별도H,0),0)/100,"") | M14: =IFERROR(VLOOKUP($D14,BS별도,MATCH(M$1,BS별도H,0),0)/100,"") | N14: =IFERROR(VLOOKUP($D14,BS별도,MATCH(N$1,BS별도H,0),0)/100,"") | O14: =IFERROR(VLOOKUP($D14,BS별도,MATCH(O$1,BS별도H,0),0)/100,"") | P14: =SUM(L14:O14) | Q14: =IFERROR(VLOOKUP($D14,BS별도,MATCH(Q$1,BS별도H,0),0)/100,"") | R14: =IFERROR(VLOOKUP($D14,BS별도,MATCH(R$1,BS별도H,0),0)/100,"") | S14: =IFERROR(VLOOKUP($D14,BS별도,MATCH(S$1,BS별도H,0),0)/100,"") | T14: =IFERROR(VLOOKUP($D14,BS별도,MATCH(T$1,BS별도H,0),0)/100,"") | U14: =SUM(Q14:T14) | V14: =IFERROR(VLOOKUP($D14,BS별도,MATCH(V$1,BS별도H,0),0)/100,"") | W14: =IFERROR(VLOOKUP($D14,BS별도,MATCH(W$1,BS별도H,0),0)/100,"") | X14: =IFERROR(VLOOKUP($D14,BS별도,MATCH(X$1,BS별도H,0),0)/100,"") | Y14: =IFERROR(VLOOKUP($D14,BS별도,MATCH(Y$1,BS별도H,0),0)/100,"") | Z14: =SUM(V14:Y14) | AA14: =IFERROR(VLOOKUP($D14,BS별도,MATCH(AA$1,BS별도H,0),0)/100,"") | AB14: =IFERROR(VLOOKUP($D14,BS별도,MATCH(AB$1,BS별도H,0),0)/100,"") | AC14: =변수!AC25 | AD14: =변수!AD25 | AE14: =SUM(AA14:AD14) | AF14: =변수!AF25 | AG14: =변수!AG25 | AH14: =변수!AH25 | AI14: =변수!AI25 | AJ14: =SUM(AF14:AI14) | AK14: =변수!AK25 | AL14: =변수!AL25 | AM14: =변수!AM25 | AN14: =변수!AN25 | AO14: =SUM(AK14:AN14)
A15: 세전이익 | B15: 손익 | C15: 억원 | D15: 법인세비용차감전계속사업이익 | E15: =IFERROR(VLOOKUP($D15,BS별도,MATCH(E$1,BS별도H,0),0)/100,"") | G15: =IFERROR(VLOOKUP($D15,BS별도,MATCH(G$1,BS별도H,0),0)/100,"") | H15: =IFERROR(VLOOKUP($D15,BS별도,MATCH(H$1,BS별도H,0),0)/100,"") | I15: =IFERROR(VLOOKUP($D15,BS별도,MATCH(I$1,BS별도H,0),0)/100,"") | J15: =IFERROR(VLOOKUP($D15,BS별도,MATCH(J$1,BS별도H,0),0)/100,"") | K15: =SUM(G15:J15) | L15: =IFERROR(VLOOKUP($D15,BS별도,MATCH(L$1,BS별도H,0),0)/100,"") | M15: =IFERROR(VLOOKUP($D15,BS별도,MATCH(M$1,BS별도H,0),0)/100,"") | N15: =IFERROR(VLOOKUP($D15,BS별도,MATCH(N$1,BS별도H,0),0)/100,"") | O15: =IFERROR(VLOOKUP($D15,BS별도,MATCH(O$1,BS별도H,0),0)/100,"") | P15: =SUM(L15:O15) | Q15: =IFERROR(VLOOKUP($D15,BS별도,MATCH(Q$1,BS별도H,0),0)/100,"") | R15: =IFERROR(VLOOKUP($D15,BS별도,MATCH(R$1,BS별도H,0),0)/100,"") | S15: =IFERROR(VLOOKUP($D15,BS별도,MATCH(S$1,BS별도H,0),0)/100,"") | T15: =IFERROR(VLOOKUP($D15,BS별도,MATCH(T$1,BS별도H,0),0)/100,"") | U15: =SUM(Q15:T15) | V15: =IFERROR(VLOOKUP($D15,BS별도,MATCH(V$1,BS별도H,0),0)/100,"") | W15: =IFERROR(VLOOKUP($D15,BS별도,MATCH(W$1,BS별도H,0),0)/100,"") | X15: =IFERROR(VLOOKUP($D15,BS별도,MATCH(X$1,BS별도H,0),0)/100,"") | Y15: =IFERROR(VLOOKUP($D15,BS별도,MATCH(Y$1,BS별도H,0),0)/100,"") | Z15: =SUM(V15:Y15) | AA15: =IFERROR(VLOOKUP($D15,BS별도,MATCH(AA$1,BS별도H,0),0)/100,"") | AB15: =IFERROR(VLOOKUP($D15,BS별도,MATCH(AB$1,BS별도H,0),0)/100,"") | AC15: =IFERROR(AC9+AC11+AC14,"") | AD15: =IFERROR(AD9+AD11+AD14,"") | AE15: =SUM(AA15:AD15) | AF15: =IFERROR(AF9+AF11+AF14,"") | AG15: =IFERROR(AG9+AG11+AG14,"") | AH15: =IFERROR(AH9+AH11+AH14,"") | AI15: =IFERROR(AI9+AI11+AI14,"") | AJ15: =SUM(AF15:AI15) | AK15: =IFERROR(AK9+AK11+AK14,"") | AL15: =IFERROR(AL9+AL11+AL14,"") | AM15: =IFERROR(AM9+AM11+AM14,"") | AN15: =IFERROR(AN9+AN11+AN14,"") | AO15: =SUM(AK15:AN15)
A16: 법인세비용 | B16: 손익 | C16: 억원 | D16: 법인세비용 | E16: =IFERROR(VLOOKUP($D16,BS별도,MATCH(E$1,BS별도H,0),0)/100,"") | K16: =SUM(G16:J16) | P16: =SUM(L16:O16) | U16: =SUM(Q16:T16) | Z16: =SUM(V16:Y16) | AB16: =IFERROR(VLOOKUP($D16,BS별도,MATCH(AB$1,BS별도H,0),0)/100,"") | AC16: =IFERROR(AC15*변수!AC26,"") | AD16: =IFERROR(AD15*변수!AD26,"") | AE16: =SUM(AA16:AD16) | AF16: =IFERROR(AF15*변수!AF26,"") | AG16: =IFERROR(AG15*변수!AG26,"") | AH16: =IFERROR(AH15*변수!AH26,"") | AI16: =IFERROR(AI15*변수!AI26,"") | AJ16: =SUM(AF16:AI16) | AK16: =IFERROR(AK15*변수!AK26,"") | AL16: =IFERROR(AL15*변수!AL26,"") | AM16: =IFERROR(AM15*변수!AM26,"") | AN16: =IFERROR(AN15*변수!AN26,"") | AO16: =SUM(AK16:AN16)
A17: 당기순이익 | B17: 손익 | C17: 억원 | D17: 당기순이익 | E17: =IFERROR(VLOOKUP($D17,BS별도,MATCH(E$1,BS별도H,0),0)/100,"") | G17: =IFERROR(VLOOKUP($D17,BS별도,MATCH(G$1,BS별도H,0),0)/100,"") | H17: =IFERROR(VLOOKUP($D17,BS별도,MATCH(H$1,BS별도H,0),0)/100,"") | I17: =IFERROR(VLOOKUP($D17,BS별도,MATCH(I$1,BS별도H,0),0)/100,"") | J17: =IFERROR(VLOOKUP($D17,BS별도,MATCH(J$1,BS별도H,0),0)/100,"") | K17: =SUM(G17:J17) | L17: =IFERROR(VLOOKUP($D17,BS별도,MATCH(L$1,BS별도H,0),0)/100,"") | M17: =IFERROR(VLOOKUP($D17,BS별도,MATCH(M$1,BS별도H,0),0)/100,"") | N17: =IFERROR(VLOOKUP($D17,BS별도,MATCH(N$1,BS별도H,0),0)/100,"") | O17: =IFERROR(VLOOKUP($D17,BS별도,MATCH(O$1,BS별도H,0),0)/100,"") | P17: =SUM(L17:O17) | Q17: =IFERROR(VLOOKUP($D17,BS별도,MATCH(Q$1,BS별도H,0),0)/100,"") | R17: =IFERROR(VLOOKUP($D17,BS별도,MATCH(R$1,BS별도H,0),0)/100,"") | S17: =IFERROR(VLOOKUP($D17,BS별도,MATCH(S$1,BS별도H,0),0)/100,"") | T17: =IFERROR(VLOOKUP($D17,BS별도,MATCH(T$1,BS별도H,0),0)/100,"") | U17: =SUM(Q17:T17) | V17: =IFERROR(VLOOKUP($D17,BS별도,MATCH(V$1,BS별도H,0),0)/100,"") | W17: =IFERROR(VLOOKUP($D17,BS별도,MATCH(W$1,BS별도H,0),0)/100,"") | X17: =IFERROR(VLOOKUP($D17,BS별도,MATCH(X$1,BS별도H,0),0)/100,"") | Y17: =IFERROR(VLOOKUP($D17,BS별도,MATCH(Y$1,BS별도H,0),0)/100,"") | Z17: =SUM(V17:Y17) | AA17: =IFERROR(VLOOKUP($D17,BS별도,MATCH(AA$1,BS별도H,0),0)/100,"") | AB17: =IFERROR(VLOOKUP($D17,BS별도,MATCH(AB$1,BS별도H,0),0)/100,"") | AC17: =IFERROR(AC15-AC16,"") | AD17: =IFERROR(AD15-AD16,"") | AE17: =SUM(AA17:AD17) | AF17: =IFERROR(AF15-AF16,"") | AG17: =IFERROR(AG15-AG16,"") | AH17: =IFERROR(AH15-AH16,"") | AI17: =IFERROR(AI15-AI16,"") | AJ17: =SUM(AF17:AI17) | AK17: =IFERROR(AK15-AK16,"") | AL17: =IFERROR(AL15-AL16,"") | AM17: =IFERROR(AM15-AM16,"") | AN17: =IFERROR(AN15-AN16,"") | AO17: =SUM(AK17:AN17)
A18: 지배주주순이익 | B18: 손익 | C18: 억원 | D18: (지배주주지분)당기순이익 | E18: =IFERROR(VLOOKUP($D18,BS별도,MATCH(E$1,BS별도H,0),0)/100,"") | G18: =IFERROR(VLOOKUP($D18,BS별도,MATCH(G$1,BS별도H,0),0)/100,"") | H18: =IFERROR(VLOOKUP($D18,BS별도,MATCH(H$1,BS별도H,0),0)/100,"") | I18: =IFERROR(VLOOKUP($D18,BS별도,MATCH(I$1,BS별도H,0),0)/100,"") | J18: =IFERROR(VLOOKUP($D18,BS별도,MATCH(J$1,BS별도H,0),0)/100,"") | K18: =SUM(G18:J18) | L18: =IFERROR(VLOOKUP($D18,BS별도,MATCH(L$1,BS별도H,0),0)/100,"") | M18: =IFERROR(VLOOKUP($D18,BS별도,MATCH(M$1,BS별도H,0),0)/100,"") | N18: =IFERROR(VLOOKUP($D18,BS별도,MATCH(N$1,BS별도H,0),0)/100,"") | O18: =IFERROR(VLOOKUP($D18,BS별도,MATCH(O$1,BS별도H,0),0)/100,"") | P18: =SUM(L18:O18) | Q18: =IFERROR(VLOOKUP($D18,BS별도,MATCH(Q$1,BS별도H,0),0)/100,"") | R18: =IFERROR(VLOOKUP($D18,BS별도,MATCH(R$1,BS별도H,0),0)/100,"") | S18: =IFERROR(VLOOKUP($D18,BS별도,MATCH(S$1,BS별도H,0),0)/100,"") | T18: =IFERROR(VLOOKUP($D18,BS별도,MATCH(T$1,BS별도H,0),0)/100,"") | U18: =SUM(Q18:T18) | V18: =IFERROR(VLOOKUP($D18,BS별도,MATCH(V$1,BS별도H,0),0)/100,"") | W18: =IFERROR(VLOOKUP($D18,BS별도,MATCH(W$1,BS별도H,0),0)/100,"") | X18: =IFERROR(VLOOKUP($D18,BS별도,MATCH(X$1,BS별도H,0),0)/100,"") | Y18: =IFERROR(VLOOKUP($D18,BS별도,MATCH(Y$1,BS별도H,0),0)/100,"") | Z18: =SUM(V18:Y18) | AA18: =IFERROR(VLOOKUP($D18,BS별도,MATCH(AA$1,BS별도H,0),0)/100,"") | AB18: =IFERROR(VLOOKUP($D18,BS별도,MATCH(AB$1,BS별도H,0),0)/100,"") | AC18: =IFERROR(AC17*변수!AC27,"") | AD18: =IFERROR(AD17*변수!AD27,"") | AE18: =SUM(AA18:AD18) | AF18: =IFERROR(AF17*변수!AF27,"") | AG18: =IFERROR(AG17*변수!AG27,"") | AH18: =IFERROR(AH17*변수!AH27,"") | AI18: =IFERROR(AI17*변수!AI27,"") | AJ18: =SUM(AF18:AI18) | AK18: =IFERROR(AK17*변수!AK27,"") | AL18: =IFERROR(AL17*변수!AL27,"") | AM18: =IFERROR(AM17*변수!AM27,"") | AN18: =IFERROR(AN17*변수!AN27,"") | AO18: =SUM(AK18:AN18)
A19: 자산총계 | B19: 재무상태 | C19: 억원 | D19: 자산총계 | E19: =IFERROR(VLOOKUP($D19,BS별도,MATCH(E$1,BS별도H,0),0)/100,"") | F19: 499.7 | G19: =IFERROR(VLOOKUP($D19,BS별도,MATCH(G$1,BS별도H,0),0)/100,"") | H19: =IFERROR(VLOOKUP($D19,BS별도,MATCH(H$1,BS별도H,0),0)/100,"") | I19: =IFERROR(VLOOKUP($D19,BS별도,MATCH(I$1,BS별도H,0),0)/100,"") | J19: =IFERROR(VLOOKUP($D19,BS별도,MATCH(J$1,BS별도H,0),0)/100,"") | K19: =J19 | L19: =IFERROR(VLOOKUP($D19,BS별도,MATCH(L$1,BS별도H,0),0)/100,"") | M19: =IFERROR(VLOOKUP($D19,BS별도,MATCH(M$1,BS별도H,0),0)/100,"") | N19: =IFERROR(VLOOKUP($D19,BS별도,MATCH(N$1,BS별도H,0),0)/100,"") | O19: =IFERROR(VLOOKUP($D19,BS별도,MATCH(O$1,BS별도H,0),0)/100,"") | P19: =O19 | Q19: =IFERROR(VLOOKUP($D19,BS별도,MATCH(Q$1,BS별도H,0),0)/100,"") | R19: =IFERROR(VLOOKUP($D19,BS별도,MATCH(R$1,BS별도H,0),0)/100,"") | S19: =IFERROR(VLOOKUP($D19,BS별도,MATCH(S$1,BS별도H,0),0)/100,"") | T19: =IFERROR(VLOOKUP($D19,BS별도,MATCH(T$1,BS별도H,0),0)/100,"") | U19: =T19 | V19: =IFERROR(VLOOKUP($D19,BS별도,MATCH(V$1,BS별도H,0),0)/100,"") | W19: =IFERROR(VLOOKUP($D19,BS별도,MATCH(W$1,BS별도H,0),0)/100,"") | X19: =IFERROR(VLOOKUP($D19,BS별도,MATCH(X$1,BS별도H,0),0)/100,"") | Y19: =IFERROR(VLOOKUP($D19,BS별도,MATCH(Y$1,BS별도H,0),0)/100,"") | Z19: =Y19 | AA19: =IFERROR(VLOOKUP($D19,BS별도,MATCH(AA$1,BS별도H,0),0)/100,"") | AB19: =IFERROR(VLOOKUP($D19,BS별도,MATCH(AB$1,BS별도H,0),0)/100,"") | AC19: =IFERROR(AC20+AC21,"") | AD19: =IFERROR(AD20+AD21,"") | AE19: =AD19 | AF19: =IFERROR(AF20+AF21,"") | AG19: =IFERROR(AG20+AG21,"") | AH19: =IFERROR(AH20+AH21,"") | AI19: =IFERROR(AI20+AI21,"") | AJ19: =AI19 | AK19: =IFERROR(AK20+AK21,"") | AL19: =IFERROR(AL20+AL21,"") | AM19: =IFERROR(AM20+AM21,"") | AN19: =IFERROR(AN20+AN21,"") | AO19: =AN19
A20: 부채총계 | B20: 재무상태 | C20: 억원 | D20: 부채총계 | E20: =IFERROR(VLOOKUP($D20,BS별도,MATCH(E$1,BS별도H,0),0)/100,"") | F20: 90.46 | G20: =IFERROR(VLOOKUP($D20,BS별도,MATCH(G$1,BS별도H,0),0)/100,"") | H20: =IFERROR(VLOOKUP($D20,BS별도,MATCH(H$1,BS별도H,0),0)/100,"") | I20: =IFERROR(VLOOKUP($D20,BS별도,MATCH(I$1,BS별도H,0),0)/100,"") | J20: =IFERROR(VLOOKUP($D20,BS별도,MATCH(J$1,BS별도H,0),0)/100,"") | K20: =J20 | L20: =IFERROR(VLOOKUP($D20,BS별도,MATCH(L$1,BS별도H,0),0)/100,"") | M20: =IFERROR(VLOOKUP($D20,BS별도,MATCH(M$1,BS별도H,0),0)/100,"") | N20: =IFERROR(VLOOKUP($D20,BS별도,MATCH(N$1,BS별도H,0),0)/100,"") | O20: =IFERROR(VLOOKUP($D20,BS별도,MATCH(O$1,BS별도H,0),0)/100,"") | P20: =O20 | Q20: =IFERROR(VLOOKUP($D20,BS별도,MATCH(Q$1,BS별도H,0),0)/100,"") | R20: =IFERROR(VLOOKUP($D20,BS별도,MATCH(R$1,BS별도H,0),0)/100,"") | S20: =IFERROR(VLOOKUP($D20,BS별도,MATCH(S$1,BS별도H,0),0)/100,"") | T20: =IFERROR(VLOOKUP($D20,BS별도,MATCH(T$1,BS별도H,0),0)/100,"") | U20: =T20 | V20: =IFERROR(VLOOKUP($D20,BS별도,MATCH(V$1,BS별도H,0),0)/100,"") | W20: =IFERROR(VLOOKUP($D20,BS별도,MATCH(W$1,BS별도H,0),0)/100,"") | X20: =IFERROR(VLOOKUP($D20,BS별도,MATCH(X$1,BS별도H,0),0)/100,"") | Y20: =IFERROR(VLOOKUP($D20,BS별도,MATCH(Y$1,BS별도H,0),0)/100,"") | Z20: =Y20 | AA20: =IFERROR(VLOOKUP($D20,BS별도,MATCH(AA$1,BS별도H,0),0)/100,"") | AB20: =IFERROR(VLOOKUP($D20,BS별도,MATCH(AB$1,BS별도H,0),0)/100,"") | AC20: =IFERROR(AB20*(1+변수!AC28),"") | AD20: =IFERROR(AC20*(1+변수!AD28),"") | AE20: =AD20 | AF20: =IFERROR(AD20*(1+변수!AF28),"") | AG20: =IFERROR(AF20*(1+변수!AG28),"") | AH20: =IFERROR(AG20*(1+변수!AH28),"") | AI20: =IFERROR(AH20*(1+변수!AI28),"") | AJ20: =AI20 | AK20: =IFERROR(AI20*(1+변수!AK28),"") | AL20: =IFERROR(AK20*(1+변수!AL28),"") | AM20: =IFERROR(AL20*(1+변수!AM28),"") | AN20: =IFERROR(AM20*(1+변수!AN28),"") | AO20: =AN20
A21: 자본총계 | B21: 재무상태 | C21: 억원 | D21: 자본총계 | E21: =IFERROR(VLOOKUP($D21,BS별도,MATCH(E$1,BS별도H,0),0)/100,"") | F21: 409.24 | G21: =IFERROR(VLOOKUP($D21,BS별도,MATCH(G$1,BS별도H,0),0)/100,"") | H21: =IFERROR(VLOOKUP($D21,BS별도,MATCH(H$1,BS별도H,0),0)/100,"") | I21: =IFERROR(VLOOKUP($D21,BS별도,MATCH(I$1,BS별도H,0),0)/100,"") | J21: =IFERROR(VLOOKUP($D21,BS별도,MATCH(J$1,BS별도H,0),0)/100,"") | K21: =J21 | L21: =IFERROR(VLOOKUP($D21,BS별도,MATCH(L$1,BS별도H,0),0)/100,"") | M21: =IFERROR(VLOOKUP($D21,BS별도,MATCH(M$1,BS별도H,0),0)/100,"") | N21: =IFERROR(VLOOKUP($D21,BS별도,MATCH(N$1,BS별도H,0),0)/100,"") | O21: =IFERROR(VLOOKUP($D21,BS별도,MATCH(O$1,BS별도H,0),0)/100,"") | P21: =O21 | Q21: =IFERROR(VLOOKUP($D21,BS별도,MATCH(Q$1,BS별도H,0),0)/100,"") | R21: =IFERROR(VLOOKUP($D21,BS별도,MATCH(R$1,BS별도H,0),0)/100,"") | S21: =IFERROR(VLOOKUP($D21,BS별도,MATCH(S$1,BS별도H,0),0)/100,"") | T21: =IFERROR(VLOOKUP($D21,BS별도,MATCH(T$1,BS별도H,0),0)/100,"") | U21: =T21 | V21: =IFERROR(VLOOKUP($D21,BS별도,MATCH(V$1,BS별도H,0),0)/100,"") | W21: =IFERROR(VLOOKUP($D21,BS별도,MATCH(W$1,BS별도H,0),0)/100,"") | X21: =IFERROR(VLOOKUP($D21,BS별도,MATCH(X$1,BS별도H,0),0)/100,"") | Y21: =IFERROR(VLOOKUP($D21,BS별도,MATCH(Y$1,BS별도H,0),0)/100,"") | Z21: =Y21 | AA21: =IFERROR(VLOOKUP($D21,BS별도,MATCH(AA$1,BS별도H,0),0)/100,"") | AB21: =IFERROR(VLOOKUP($D21,BS별도,MATCH(AB$1,BS별도H,0),0)/100,"") | AC21: =IFERROR(AB21+AC17-변수!AC29,"") | AD21: =IFERROR(AC21+AD17-변수!AD29,"") | AE21: =AD21 | AF21: =IFERROR(AD21+AF17-변수!AF29,"") | AG21: =IFERROR(AF21+AG17-변수!AG29,"") | AH21: =IFERROR(AG21+AH17-변수!AH29,"") | AI21: =IFERROR(AH21+AI17-변수!AI29,"") | AJ21: =AI21 | AK21: =IFERROR(AI21+AK17-변수!AK29,"") | AL21: =IFERROR(AK21+AL17-변수!AL29,"") | AM21: =IFERROR(AL21+AM17-변수!AM29,"") | AN21: =IFERROR(AM21+AN17-변수!AN29,"") | AO21: =AN21
A22: 지배주주지분 | B22: 재무상태 | C22: 억원 | D22: 지배주주지분 | E22: =IFERROR(VLOOKUP($D22,BS별도,MATCH(E$1,BS별도H,0),0)/100,"") | F22: 409.24 | G22: =IFERROR(VLOOKUP($D22,BS별도,MATCH(G$1,BS별도H,0),0)/100,"") | H22: =IFERROR(VLOOKUP($D22,BS별도,MATCH(H$1,BS별도H,0),0)/100,"") | I22: =IFERROR(VLOOKUP($D22,BS별도,MATCH(I$1,BS별도H,0),0)/100,"") | J22: =IFERROR(VLOOKUP($D22,BS별도,MATCH(J$1,BS별도H,0),0)/100,"") | K22: =J22 | L22: =IFERROR(VLOOKUP($D22,BS별도,MATCH(L$1,BS별도H,0),0)/100,"") | M22: =IFERROR(VLOOKUP($D22,BS별도,MATCH(M$1,BS별도H,0),0)/100,"") | N22: =IFERROR(VLOOKUP($D22,BS별도,MATCH(N$1,BS별도H,0),0)/100,"") | O22: =IFERROR(VLOOKUP($D22,BS별도,MATCH(O$1,BS별도H,0),0)/100,"") | P22: =O22 | Q22: =IFERROR(VLOOKUP($D22,BS별도,MATCH(Q$1,BS별도H,0),0)/100,"") | R22: =IFERROR(VLOOKUP($D22,BS별도,MATCH(R$1,BS별도H,0),0)/100,"") | S22: =IFERROR(VLOOKUP($D22,BS별도,MATCH(S$1,BS별도H,0),0)/100,"") | T22: =IFERROR(VLOOKUP($D22,BS별도,MATCH(T$1,BS별도H,0),0)/100,"") | U22: =T22 | V22: =IFERROR(VLOOKUP($D22,BS별도,MATCH(V$1,BS별도H,0),0)/100,"") | W22: =IFERROR(VLOOKUP($D22,BS별도,MATCH(W$1,BS별도H,0),0)/100,"") | X22: =IFERROR(VLOOKUP($D22,BS별도,MATCH(X$1,BS별도H,0),0)/100,"") | Y22: =IFERROR(VLOOKUP($D22,BS별도,MATCH(Y$1,BS별도H,0),0)/100,"") | Z22: =Y22 | AA22: =IFERROR(VLOOKUP($D22,BS별도,MATCH(AA$1,BS별도H,0),0)/100,"") | AB22: =IFERROR(VLOOKUP($D22,BS별도,MATCH(AB$1,BS별도H,0),0)/100,"") | AC22: =IFERROR(AB22+AC18-변수!AC30,"") | AD22: =IFERROR(AC22+AD18-변수!AD30,"") | AE22: =AD22 | AF22: =IFERROR(AD22+AF18-변수!AF30,"") | AG22: =IFERROR(AF22+AG18-변수!AG30,"") | AH22: =IFERROR(AG22+AH18-변수!AH30,"") | AI22: =IFERROR(AH22+AI18-변수!AI30,"") | AJ22: =AI22 | AK22: =IFERROR(AI22+AK18-변수!AK30,"") | AL22: =IFERROR(AK22+AL18-변수!AL30,"") | AM22: =IFERROR(AL22+AM18-변수!AM30,"") | AN22: =IFERROR(AM22+AN18-변수!AN30,"") | AO22: =AN22
A23: 총차입금 | B23: 재무상태 | C23: 억원 | D23: 총차입금 | E23: =IFERROR(VLOOKUP($D23,BS별도,MATCH(E$1,BS별도H,0),0)/100,"") | F23: 50 | G23: =IFERROR(VLOOKUP($D23,BS별도,MATCH(G$1,BS별도H,0),0)/100,"") | K23: =J23 | P23: =O23 | U23: =T23 | Z23: =Y23 | AB23: =IFERROR(VLOOKUP($D23,BS별도,MATCH(AB$1,BS별도H,0),0)/100,"") | AC23: =IFERROR(AB23*(1+변수!AC31),"") | AD23: =IFERROR(AC23*(1+변수!AD31),"") | AE23: =AD23 | AF23: =IFERROR(AD23*(1+변수!AF31),"") | AG23: =IFERROR(AF23*(1+변수!AG31),"") | AH23: =IFERROR(AG23*(1+변수!AH31),"") | AI23: =IFERROR(AH23*(1+변수!AI31),"") | AJ23: =AI23 | AK23: =IFERROR(AI23*(1+변수!AK31),"") | AL23: =IFERROR(AK23*(1+변수!AL31),"") | AM23: =IFERROR(AL23*(1+변수!AM31),"") | AN23: =IFERROR(AM23*(1+변수!AN31),"") | AO23: =AN23
A24: 순차입금 | B24: 재무상태 | C24: 억원 | D24: 순차입금 | E24: =IFERROR(VLOOKUP($D24,BS별도,MATCH(E$1,BS별도H,0),0)/100,"") | F24: -132.86 | G24: =IFERROR(VLOOKUP($D24,BS별도,MATCH(G$1,BS별도H,0),0)/100,"") | K24: =J24 | P24: =O24 | U24: =T24 | Z24: =Y24 | AB24: =IFERROR(VLOOKUP($D24,BS별도,MATCH(AB$1,BS별도H,0),0)/100,"") | AC24: =IFERROR(AB24*(1+변수!AC32),"") | AD24: =IFERROR(AC24*(1+변수!AD32),"") | AE24: =AD24 | AF24: =IFERROR(AD24*(1+변수!AF32),"") | AG24: =IFERROR(AF24*(1+변수!AG32),"") | AH24: =IFERROR(AG24*(1+변수!AH32),"") | AI24: =IFERROR(AH24*(1+변수!AI32),"") | AJ24: =AI24 | AK24: =IFERROR(AI24*(1+변수!AK32),"") | AL24: =IFERROR(AK24*(1+변수!AL32),"") | AM24: =IFERROR(AL24*(1+변수!AM32),"") | AN24: =IFERROR(AM24*(1+변수!AN32),"") | AO24: =AN24
A25: 이자발생자산 | B25: 재무상태 | C25: 억원 | D25: 이자발생자산 | E25: =IFERROR(VLOOKUP($D25,BS별도,MATCH(E$1,BS별도H,0),0)/100,"") | F25: 183.14 | G25: =IFERROR(VLOOKUP($D25,BS별도,MATCH(G$1,BS별도H,0),0)/100,"") | H25: =IFERROR(VLOOKUP($D25,BS별도,MATCH(H$1,BS별도H,0),0)/100,"") | I25: =IFERROR(VLOOKUP($D25,BS별도,MATCH(I$1,BS별도H,0),0)/100,"") | J25: =IFERROR(VLOOKUP($D25,BS별도,MATCH(J$1,BS별도H,0),0)/100,"") | K25: =J25 | L25: =IFERROR(VLOOKUP($D25,BS별도,MATCH(L$1,BS별도H,0),0)/100,"") | M25: =IFERROR(VLOOKUP($D25,BS별도,MATCH(M$1,BS별도H,0),0)/100,"") | N25: =IFERROR(VLOOKUP($D25,BS별도,MATCH(N$1,BS별도H,0),0)/100,"") | O25: =IFERROR(VLOOKUP($D25,BS별도,MATCH(O$1,BS별도H,0),0)/100,"") | P25: =O25 | Q25: =IFERROR(VLOOKUP($D25,BS별도,MATCH(Q$1,BS별도H,0),0)/100,"") | R25: =IFERROR(VLOOKUP($D25,BS별도,MATCH(R$1,BS별도H,0),0)/100,"") | S25: =IFERROR(VLOOKUP($D25,BS별도,MATCH(S$1,BS별도H,0),0)/100,"") | T25: =IFERROR(VLOOKUP($D25,BS별도,MATCH(T$1,BS별도H,0),0)/100,"") | U25: =T25 | V25: =IFERROR(VLOOKUP($D25,BS별도,MATCH(V$1,BS별도H,0),0)/100,"") | W25: =IFERROR(VLOOKUP($D25,BS별도,MATCH(W$1,BS별도H,0),0)/100,"") | X25: =IFERROR(VLOOKUP($D25,BS별도,MATCH(X$1,BS별도H,0),0)/100,"") | Y25: =IFERROR(VLOOKUP($D25,BS별도,MATCH(Y$1,BS별도H,0),0)/100,"") | Z25: =Y25 | AA25: =IFERROR(VLOOKUP($D25,BS별도,MATCH(AA$1,BS별도H,0),0)/100,"") | AB25: =IFERROR(VLOOKUP($D25,BS별도,MATCH(AB$1,BS별도H,0),0)/100,"") | AC25: =IFERROR(AB25*(1+변수!AC33),"") | AD25: =IFERROR(AC25*(1+변수!AD33),"") | AE25: =AD25 | AF25: =IFERROR(AD25*(1+변수!AF33),"") | AG25: =IFERROR(AF25*(1+변수!AG33),"") | AH25: =IFERROR(AG25*(1+변수!AH33),"") | AI25: =IFERROR(AH25*(1+변수!AI33),"") | AJ25: =AI25 | AK25: =IFERROR(AI25*(1+변수!AK33),"") | AL25: =IFERROR(AK25*(1+변수!AL33),"") | AM25: =IFERROR(AL25*(1+변수!AM33),"") | AN25: =IFERROR(AM25*(1+변수!AN33),"") | AO25: =AN25
A26: 현금및현금성자산 | B26: 재무상태 | C26: 억원 | D26: 현금및현금성자산 | E26: =IFERROR(VLOOKUP($D26,BS별도,MATCH(E$1,BS별도H,0),0)/100,"") | F26: 92.86 | G26: =IFERROR(VLOOKUP($D26,BS별도,MATCH(G$1,BS별도H,0),0)/100,"") | H26: =IFERROR(VLOOKUP($D26,BS별도,MATCH(H$1,BS별도H,0),0)/100,"") | I26: =IFERROR(VLOOKUP($D26,BS별도,MATCH(I$1,BS별도H,0),0)/100,"") | J26: =IFERROR(VLOOKUP($D26,BS별도,MATCH(J$1,BS별도H,0),0)/100,"") | K26: =J26 | L26: =IFERROR(VLOOKUP($D26,BS별도,MATCH(L$1,BS별도H,0),0)/100,"") | M26: =IFERROR(VLOOKUP($D26,BS별도,MATCH(M$1,BS별도H,0),0)/100,"") | N26: =IFERROR(VLOOKUP($D26,BS별도,MATCH(N$1,BS별도H,0),0)/100,"") | O26: =IFERROR(VLOOKUP($D26,BS별도,MATCH(O$1,BS별도H,0),0)/100,"") | P26: =O26 | Q26: =IFERROR(VLOOKUP($D26,BS별도,MATCH(Q$1,BS별도H,0),0)/100,"") | R26: =IFERROR(VLOOKUP($D26,BS별도,MATCH(R$1,BS별도H,0),0)/100,"") | S26: =IFERROR(VLOOKUP($D26,BS별도,MATCH(S$1,BS별도H,0),0)/100,"") | T26: =IFERROR(VLOOKUP($D26,BS별도,MATCH(T$1,BS별도H,0),0)/100,"") | U26: =T26 | V26: =IFERROR(VLOOKUP($D26,BS별도,MATCH(V$1,BS별도H,0),0)/100,"") | W26: =IFERROR(VLOOKUP($D26,BS별도,MATCH(W$1,BS별도H,0),0)/100,"") | X26: =IFERROR(VLOOKUP($D26,BS별도,MATCH(X$1,BS별도H,0),0)/100,"") | Y26: =IFERROR(VLOOKUP($D26,BS별도,MATCH(Y$1,BS별도H,0),0)/100,"") | Z26: =Y26 | AA26: =IFERROR(VLOOKUP($D26,BS별도,MATCH(AA$1,BS별도H,0),0)/100,"") | AB26: =IFERROR(VLOOKUP($D26,BS별도,MATCH(AB$1,BS별도H,0),0)/100,"") | AE26: =AD26 | AJ26: =AI26 | AO26: =AN26
A27: CAPEX | B27: 현금흐름 | C27: 억원 | D27: CAPEX | E27: =IFERROR(VLOOKUP($D27,BS별도,MATCH(E$1,BS별도H,0),0)/100,"") | G27: =IFERROR(VLOOKUP($D27,BS별도,MATCH(G$1,BS별도H,0),0)/100,"") | H27: =IFERROR(VLOOKUP($D27,BS별도,MATCH(H$1,BS별도H,0),0)/100,"") | I27: =IFERROR(VLOOKUP($D27,BS별도,MATCH(I$1,BS별도H,0),0)/100,"") | J27: =IFERROR(VLOOKUP($D27,BS별도,MATCH(J$1,BS별도H,0),0)/100,"") | K27: =SUM(G27:J27) | L27: =IFERROR(VLOOKUP($D27,BS별도,MATCH(L$1,BS별도H,0),0)/100,"") | M27: =IFERROR(VLOOKUP($D27,BS별도,MATCH(M$1,BS별도H,0),0)/100,"") | N27: =IFERROR(VLOOKUP($D27,BS별도,MATCH(N$1,BS별도H,0),0)/100,"") | O27: =IFERROR(VLOOKUP($D27,BS별도,MATCH(O$1,BS별도H,0),0)/100,"") | P27: =SUM(L27:O27) | Q27: =IFERROR(VLOOKUP($D27,BS별도,MATCH(Q$1,BS별도H,0),0)/100,"") | R27: =IFERROR(VLOOKUP($D27,BS별도,MATCH(R$1,BS별도H,0),0)/100,"") | S27: =IFERROR(VLOOKUP($D27,BS별도,MATCH(S$1,BS별도H,0),0)/100,"") | T27: =IFERROR(VLOOKUP($D27,BS별도,MATCH(T$1,BS별도H,0),0)/100,"") | U27: =SUM(Q27:T27) | V27: =IFERROR(VLOOKUP($D27,BS별도,MATCH(V$1,BS별도H,0),0)/100,"") | W27: =IFERROR(VLOOKUP($D27,BS별도,MATCH(W$1,BS별도H,0),0)/100,"") | X27: =IFERROR(VLOOKUP($D27,BS별도,MATCH(X$1,BS별도H,0),0)/100,"") | Y27: =IFERROR(VLOOKUP($D27,BS별도,MATCH(Y$1,BS별도H,0),0)/100,"") | Z27: =SUM(V27:Y27) | AA27: =IFERROR(VLOOKUP($D27,BS별도,MATCH(AA$1,BS별도H,0),0)/100,"") | AB27: =IFERROR(VLOOKUP($D27,BS별도,MATCH(AB$1,BS별도H,0),0)/100,"") | AC27: =IFERROR(X27*(1+변수!AC35),"") | AD27: =IFERROR(Y27*(1+변수!AD35),"") | AE27: =SUM(AA27:AD27) | AF27: =IFERROR(AA27*(1+변수!AF35),"") | AG27: =IFERROR(AB27*(1+변수!AG35),"") | AH27: =IFERROR(AC27*(1+변수!AH35),"") | AI27: =IFERROR(AD27*(1+변수!AI35),"") | AJ27: =SUM(AF27:AI27) | AK27: =IFERROR(AF27*(1+변수!AK35),"") | AL27: =IFERROR(AG27*(1+변수!AL35),"") | AM27: =IFERROR(AH27*(1+변수!AM35),"") | AN27: =IFERROR(AI27*(1+변수!AN35),"") | AO27: =SUM(AK27:AN27)
A28: 영업활동현금흐름 | B28: 현금흐름 | C28: 억원 | D28: 영업활동으로인한현금흐름 | E28: =IFERROR(VLOOKUP($D28,BS별도,MATCH(E$1,BS별도H,0),0)/100,"") | G28: =IFERROR(VLOOKUP($D28,BS별도,MATCH(G$1,BS별도H,0),0)/100,"") | H28: =IFERROR(VLOOKUP($D28,BS별도,MATCH(H$1,BS별도H,0),0)/100,"") | I28: =IFERROR(VLOOKUP($D28,BS별도,MATCH(I$1,BS별도H,0),0)/100,"") | J28: =IFERROR(VLOOKUP($D28,BS별도,MATCH(J$1,BS별도H,0),0)/100,"") | K28: =SUM(G28:J28) | L28: =IFERROR(VLOOKUP($D28,BS별도,MATCH(L$1,BS별도H,0),0)/100,"") | M28: =IFERROR(VLOOKUP($D28,BS별도,MATCH(M$1,BS별도H,0),0)/100,"") | N28: =IFERROR(VLOOKUP($D28,BS별도,MATCH(N$1,BS별도H,0),0)/100,"") | O28: =IFERROR(VLOOKUP($D28,BS별도,MATCH(O$1,BS별도H,0),0)/100,"") | P28: =SUM(L28:O28) | Q28: =IFERROR(VLOOKUP($D28,BS별도,MATCH(Q$1,BS별도H,0),0)/100,"") | R28: =IFERROR(VLOOKUP($D28,BS별도,MATCH(R$1,BS별도H,0),0)/100,"") | S28: =IFERROR(VLOOKUP($D28,BS별도,MATCH(S$1,BS별도H,0),0)/100,"") | T28: =IFERROR(VLOOKUP($D28,BS별도,MATCH(T$1,BS별도H,0),0)/100,"") | U28: =SUM(Q28:T28) | V28: =IFERROR(VLOOKUP($D28,BS별도,MATCH(V$1,BS별도H,0),0)/100,"") | W28: =IFERROR(VLOOKUP($D28,BS별도,MATCH(W$1,BS별도H,0),0)/100,"") | X28: =IFERROR(VLOOKUP($D28,BS별도,MATCH(X$1,BS별도H,0),0)/100,"") | Y28: =IFERROR(VLOOKUP($D28,BS별도,MATCH(Y$1,BS별도H,0),0)/100,"") | Z28: =SUM(V28:Y28) | AA28: =IFERROR(VLOOKUP($D28,BS별도,MATCH(AA$1,BS별도H,0),0)/100,"") | AB28: =IFERROR(VLOOKUP($D28,BS별도,MATCH(AB$1,BS별도H,0),0)/100,"") | AE28: =SUM(AA28:AD28) | AJ28: =SUM(AF28:AI28) | AO28: =SUM(AK28:AN28)
A29: 주식수 | B29: 주당 | C29: 백만주 | D29: 유통주식수 | E29: 9.46 | F29: =E29 | G29: 9.46 | H29: 9.46 | I29: 9.615 | J29: 9.615 | K29: =J29 | L29: 10.021 | M29: 10.021 | N29: 10.021 | O29: 10.021 | P29: =O29 | Q29: 10.798 | R29: 11.141 | S29: 11.141 | T29: 11.141 | U29: =T29 | V29: 11.141 | W29: 11.141 | X29: 11.165 | Y29: 11.165 | Z29: =Y29 | AA29: 11.165 | AB29: 11.165 | AC29: =IFERROR(AB29*(1+변수!AC37),"") | AD29: =IFERROR(AC29*(1+변수!AD37),"") | AE29: =AD29 | AF29: =IFERROR(AD29*(1+변수!AF37),"") | AG29: =IFERROR(AF29*(1+변수!AG37),"") | AH29: =IFERROR(AG29*(1+변수!AH37),"") | AI29: =IFERROR(AH29*(1+변수!AI37),"") | AJ29: =AI29 | AK29: =IFERROR(AI29*(1+변수!AK37),"") | AL29: =IFERROR(AK29*(1+변수!AL37),"") | AM29: =IFERROR(AL29*(1+변수!AM37),"") | AN29: =IFERROR(AM29*(1+변수!AN37),"") | AO29: =AN29
A30: EPS | B30: 주당 | C30: 원 | D30: EPS | E30: =IFERROR(E18*100/E29,"") | G30: =IFERROR(G18*100/G29,"") | H30: =IFERROR(H18*100/H29,"") | I30: =IFERROR(I18*100/I29,"") | J30: =IFERROR(J18*100/J29,"") | K30: =SUM(G30:J30) | L30: =IFERROR(L18*100/L29,"") | M30: =IFERROR(M18*100/M29,"") | N30: =IFERROR(N18*100/N29,"") | O30: =IFERROR(O18*100/O29,"") | P30: =SUM(L30:O30) | Q30: =IFERROR(Q18*100/Q29,"") | R30: =IFERROR(R18*100/R29,"") | S30: =IFERROR(S18*100/S29,"") | T30: =IFERROR(T18*100/T29,"") | U30: =SUM(Q30:T30) | V30: =IFERROR(V18*100/V29,"") | W30: =IFERROR(W18*100/W29,"") | X30: =IFERROR(X18*100/X29,"") | Y30: =IFERROR(Y18*100/Y29,"") | Z30: =SUM(V30:Y30) | AA30: =IFERROR(AA18*100/AA29,"") | AB30: =IFERROR(AB18*100/AB29,"") | AC30: =IFERROR(AC18*100/AC29,"") | AD30: =IFERROR(AD18*100/AD29,"") | AE30: =SUM(AA30:AD30) | AF30: =IFERROR(AF18*100/AF29,"") | AG30: =IFERROR(AG18*100/AG29,"") | AH30: =IFERROR(AH18*100/AH29,"") | AI30: =IFERROR(AI18*100/AI29,"") | AJ30: =SUM(AF30:AI30) | AK30: =IFERROR(AK18*100/AK29,"") | AL30: =IFERROR(AL18*100/AL29,"") | AM30: =IFERROR(AM18*100/AM29,"") | AN30: =IFERROR(AN18*100/AN29,"") | AO30: =SUM(AK30:AN30)
A31: 조정EPS | B31: 주당 | C31: 원 | D31: 조정 EPS(일회성 의심 분기의 초과 비영업손익 세후 차감 — 모델 추정) | E31: =IFERROR(E30,"") | G31: =IFERROR(G30,"") | H31: =IFERROR(H30,"") | I31: =IFERROR(I30,"") | J31: =IFERROR(J30,"") | K31: =SUM(G31:J31) | L31: =IFERROR(L30,"") | M31: =IFERROR(M30,"") | N31: =IFERROR(N30,"") | O31: =IFERROR(O30,"") | P31: =SUM(L31:O31) | Q31: =IFERROR(Q30,"") | R31: =IFERROR(R30,"") | S31: =IFERROR(S30,"") | T31: =IFERROR(T30,"") | U31: =SUM(Q31:T31) | V31: =IFERROR(V30,"") | W31: =IFERROR(W30,"") | X31: =IFERROR(X30,"") | Y31: =IFERROR(Y30,"") | Z31: =SUM(V31:Y31) | AA31: =IFERROR(AA30,"") | AB31: =IFERROR((AB18-(19.83)*(1.0))*100/AB29,"") | AC31: =IFERROR(AC30,"") | AD31: =IFERROR(AD30,"") | AE31: =SUM(AA31:AD31) | AF31: =IFERROR(AF30,"") | AG31: =IFERROR(AG30,"") | AH31: =IFERROR(AH30,"") | AI31: =IFERROR(AI30,"") | AJ31: =SUM(AF31:AI31) | AK31: =IFERROR(AK30,"") | AL31: =IFERROR(AL30,"") | AM31: =IFERROR(AM30,"") | AN31: =IFERROR(AN30,"") | AO31: =SUM(AK31:AN31)
A32: BPS | B32: 주당 | C32: 원 | D32: BPS | E32: =IFERROR(E22*100/E29,"") | F32: =E32 | G32: =IFERROR(G22*100/G29,"") | H32: =IFERROR(H22*100/H29,"") | I32: =IFERROR(I22*100/I29,"") | J32: =IFERROR(J22*100/J29,"") | K32: =J32 | L32: =IFERROR(L22*100/L29,"") | M32: =IFERROR(M22*100/M29,"") | N32: =IFERROR(N22*100/N29,"") | O32: =IFERROR(O22*100/O29,"") | P32: =O32 | Q32: =IFERROR(Q22*100/Q29,"") | R32: =IFERROR(R22*100/R29,"") | S32: =IFERROR(S22*100/S29,"") | T32: =IFERROR(T22*100/T29,"") | U32: =T32 | V32: =IFERROR(V22*100/V29,"") | W32: =IFERROR(W22*100/W29,"") | X32: =IFERROR(X22*100/X29,"") | Y32: =IFERROR(Y22*100/Y29,"") | Z32: =Y32 | AA32: =IFERROR(AA22*100/AA29,"") | AB32: =IFERROR(AB22*100/AB29,"") | AC32: =IFERROR(AC22*100/AC29,"") | AD32: =IFERROR(AD22*100/AD29,"") | AE32: =AD32 | AF32: =IFERROR(AF22*100/AF29,"") | AG32: =IFERROR(AG22*100/AG29,"") | AH32: =IFERROR(AH22*100/AH29,"") | AI32: =IFERROR(AI22*100/AI29,"") | AJ32: =AI32 | AK32: =IFERROR(AK22*100/AK29,"") | AL32: =IFERROR(AL22*100/AL29,"") | AM32: =IFERROR(AM22*100/AM29,"") | AN32: =IFERROR(AN22*100/AN29,"") | AO32: =AN32
A33: DPS | B33: 주당 | C33: 원 | D33: DPS(보통주) | E33: 0 | F33: 0 | J33: 0 | K33: =SUM(G33:J33) | O33: 0 | P33: =SUM(L33:O33) | T33: 0 | U33: =SUM(Q33:T33) | Y33: 0 | Z33: =SUM(V33:Y33) | AD33: =변수!AD38 | AE33: =SUM(AA33:AD33) | AI33: =변수!AI38 | AJ33: =SUM(AF33:AI33) | AN33: =변수!AN38 | AO33: =SUM(AK33:AN33)
A34: PER | B34: 주당 | C34: 배 | D34: PER | F34: =E34 | K34: =J34 | P34: =O34 | U34: =T34 | W34: =IFERROR(변수!W18/(S30+T30+V30+W30),"") | X34: =IFERROR(변수!X18/(T30+V30+W30+X30),"") | Y34: =IFERROR(변수!Y18/(V30+W30+X30+Y30),"") | Z34: =Y34 | AA34: =IFERROR(변수!AA18/(W30+X30+Y30+AA30),"") | AB34: =IFERROR(변수!AB18/(X30+Y30+AA30+AB30),"") | AC34: =IFERROR(변수!$D$41/(Y30+AA30+AB30+AC30),"") | AD34: =IFERROR(변수!$D$41/(AA30+AB30+AC30+AD30),"") | AE34: =AD34 | AF34: =IFERROR(변수!$D$41/(AB30+AC30+AD30+AF30),"") | AJ34: =AI34 | AO34: =AN34
A35: PBR | B35: 주당 | C35: 배 | D35: PBR | E35: =IFERROR(변수!E18/E32,"") | F35: =E35 | G35: =IFERROR(변수!G18/G32,"") | H35: =IFERROR(변수!H18/H32,"") | I35: =IFERROR(변수!I18/I32,"") | J35: =IFERROR(변수!J18/J32,"") | K35: =J35 | L35: =IFERROR(변수!L18/L32,"") | M35: =IFERROR(변수!M18/M32,"") | N35: =IFERROR(변수!N18/N32,"") | O35: =IFERROR(변수!O18/O32,"") | P35: =O35 | Q35: =IFERROR(변수!Q18/Q32,"") | R35: =IFERROR(변수!R18/R32,"") | S35: =IFERROR(변수!S18/S32,"") | T35: =IFERROR(변수!T18/T32,"") | U35: =T35 | V35: =IFERROR(변수!V18/V32,"") | W35: =IFERROR(변수!W18/W32,"") | X35: =IFERROR(변수!X18/X32,"") | Y35: =IFERROR(변수!Y18/Y32,"") | Z35: =Y35 | AA35: =IFERROR(변수!AA18/AA32,"") | AB35: =IFERROR(변수!AB18/AB32,"") | AC35: =IFERROR(변수!$D$41/AC32,"") | AD35: =IFERROR(변수!$D$41/AD32,"") | AE35: =AD35 | AF35: =IFERROR(변수!$D$41/AF32,"") | AG35: =IFERROR(변수!$D$41/AG32,"") | AH35: =IFERROR(변수!$D$41/AH32,"") | AI35: =IFERROR(변수!$D$41/AI32,"") | AJ35: =AI35 | AK35: =IFERROR(변수!$D$41/AK32,"") | AL35: =IFERROR(변수!$D$41/AL32,"") | AM35: =IFERROR(변수!$D$41/AM32,"") | AN35: =IFERROR(변수!$D$41/AN32,"") | AO35: =AN35
A36: 매출전사 | B36: 사업부 | C36: 억원 | D36: 매출 전사(부문 미분리) | E36: 42.39 | G36: 35.56 | H36: 37.88 | I36: 31.42 | J36: 34.28 | K36: =SUM(G36:J36) | L36: 34.3 | M36: 38.39 | N36: 31.48 | O36: 32.66 | P36: =SUM(L36:O36) | Q36: 34.19 | R36: 45.21 | S36: 34.01 | T36: 35.97 | U36: =SUM(Q36:T36) | V36: 30.65 | W36: 40.01 | X36: 38.02 | Y36: 42.11 | Z36: =SUM(V36:Y36) | AA36: 32.86 | AB36: 33.15 | AC36: =IFERROR(AC5,"") | AD36: =IFERROR(AD5,"") | AE36: =SUM(AA36:AD36) | AF36: =IFERROR(AF5,"") | AG36: =IFERROR(AG5,"") | AH36: =IFERROR(AH5,"") | AI36: =IFERROR(AI5,"") | AJ36: =SUM(AF36:AI36) | AK36: =IFERROR(AK5,"") | AL36: =IFERROR(AL5,"") | AM36: =IFERROR(AM5,"") | AN36: =IFERROR(AN5,"") | AO36: =SUM(AK36:AN36)
A37: OP전사 | B37: 사업부 | C37: 억원 | D37: OP 전사(부문 미분리) | E37: -1.55 | G37: -3.05 | H37: -4.21 | I37: -3.84 | J37: -1.6 | K37: =SUM(G37:J37) | L37: -2.56 | M37: -1.95 | N37: -5.81 | O37: -4.63 | P37: =SUM(L37:O37) | Q37: -3.08 | R37: -0.02 | S37: -1.85 | T37: -2.21 | U37: =SUM(Q37:T37) | V37: -3.77 | W37: 0.12 | X37: -0.27 | Y37: -2.29 | Z37: =SUM(V37:Y37) | AA37: -3.04 | AB37: -7.36 | AC37: =IFERROR(AC9,"") | AD37: =IFERROR(AD9,"") | AE37: =SUM(AA37:AD37) | AF37: =IFERROR(AF9,"") | AG37: =IFERROR(AG9,"") | AH37: =IFERROR(AH9,"") | AI37: =IFERROR(AI9,"") | AJ37: =SUM(AF37:AI37) | AK37: =IFERROR(AK9,"") | AL37: =IFERROR(AL9,"") | AM37: =IFERROR(AM9,"") | AN37: =IFERROR(AN9,"") | AO37: =SUM(AK37:AN37)
B38: 비율(참고)
A39: NPM | C39: % | D39: 지배주주순이익 / 매출액 | E39: =IFERROR(E18/E5,"") | F39: =IFERROR(F18/F5,"") | G39: =IFERROR(G18/G5,"") | H39: =IFERROR(H18/H5,"") | I39: =IFERROR(I18/I5,"") | J39: =IFERROR(J18/J5,"") | K39: =IFERROR(K18/K5,"") | L39: =IFERROR(L18/L5,"") | ... AO39: =IFERROR(AO18/AO5,"")
A40: 매출원가율 | C40: % | D40: 매출원가 / 매출액 | E40: =IFERROR(E6/E5,"") | F40: =IFERROR(F6/F5,"") | G40: =IFERROR(G6/G5,"") | H40: =IFERROR(H6/H5,"") | I40: =IFERROR(I6/I5,"") | J40: =IFERROR(J6/J5,"") | K40: =IFERROR(K6/K5,"") | L40: =IFERROR(L6/L5,"") | ... AO40: =IFERROR(AO6/AO5,"")
A41: 판관비율 | C41: % | D41: 판관비 / 매출액 | E41: =IFERROR(E8/E5,"") | F41: =IFERROR(F8/F5,"") | G41: =IFERROR(G8/G5,"") | H41: =IFERROR(H8/H5,"") | I41: =IFERROR(I8/I5,"") | J41: =IFERROR(J8/J5,"") | K41: =IFERROR(K8/K5,"") | L41: =IFERROR(L8/L5,"") | ... AO41: =IFERROR(AO8/AO5,"")

Sheet 분기
C1: 이름: 분기H — subQ 를 이름으로 VLOOKUP(억원) | E1: 4Q21 | F1: 1Q22 | G1: 2Q22 | H1: 3Q22 | I1: 4Q22 | J1: 1Q23 | K1: 2Q23 | L1: 3Q23 | M1: 4Q23 | N1: 1Q24 | O1: 2Q24 | P1: 3Q24 | Q1: 4Q24 | R1: 1Q25 | S1: 2Q25 | T1: 3Q25 | U1: 4Q25 | V1: 1Q26 | W1: 2Q26 | X1: 3Q26 | Y1: 4Q26 | Z1: 1Q27 | AA1: 2Q27 | AB1: 3Q27 | AC1: 4Q27 | AD1: 1Q28 | AE1: 2Q28 | AF1: 3Q28 | AG1: 4Q28
C2: 종가: | D2: =변수!D41
C3: 기준일: | D3: 20261014 | E3: 1 | F3: 2 | G3: 3 | H3: 4 | I3: 5 | J3: 6 | K3: 7 | L3: 8 | M3: 9 | N3: 10 | O3: 11 | P3: 12 | Q3: 13 | R3: 14 | S3: 15 | T3: 16 | U3: 17 | V3: 18 | W3: 19 | X3: 20 | Y3: 21 | Z3: 22 | AA3: 23 | AB3: 24 | AC3: 25 | AD3: 26 | AE3: 27 | AF3: 28 | AG3: 29
E4: 2021.12 | F4: 2022.03 | G4: 2022.06 | H4: 2022.09 | I4: 2022.12 | J4: 2023.03 | K4: 2023.06 | L4: 2023.09 | M4: 2023.12 | N4: 2024.03 | O4: 2024.06 | P4: 2024.09 | Q4: 2024.12 | R4: 2025.03 | S4: 2025.06 | T4: 2025.09 | U4: 2025.12 | V4: 2026.03 | W4: 2026.06 | X4: 2026.09 | Y4: 2026.12 | Z4: 2027.03 | AA4: 2027.06 | AB4: 2027.09 | AC4: 2027.12 | AD4: 2028.03 | AE4: 2028.06 | AF4: 2028.09 | AG4: 2028.12
A5: 매출액 | D5: 매출액 | E5: =IFERROR(VLOOKUP($A5,subQ,MATCH(E$1,SUBQH,0),0),"") | F5: =IFERROR(VLOOKUP($A5,subQ,MATCH(F$1,SUBQH,0),0),"") | G5: =IFERROR(VLOOKUP($A5,subQ,MATCH(G$1,SUBQH,0),0),"") | H5: =IFERROR(VLOOKUP($A5,subQ,MATCH(H$1,SUBQH,0),0),"") | I5: =IFERROR(VLOOKUP($A5,subQ,MATCH(I$1,SUBQH,0),0),"") | J5: =IFERROR(VLOOKUP($A5,subQ,MATCH(J$1,SUBQH,0),0),"") | K5: =IFERROR(VLOOKUP($A5,subQ,MATCH(K$1,SUBQH,0),0),"") | L5: =IFERROR(VLOOKUP($A5,subQ,MATCH(L$1,SUBQH,0),0),"") | ... AG5: =IFERROR(VLOOKUP($A5,subQ,MATCH(AG$1,SUBQH,0),0),"")
A6: 매출원가 | D6: 매출원가 | E6: =IFERROR(VLOOKUP($A6,subQ,MATCH(E$1,SUBQH,0),0),"") | F6: =IFERROR(VLOOKUP($A6,subQ,MATCH(F$1,SUBQH,0),0),"") | G6: =IFERROR(VLOOKUP($A6,subQ,MATCH(G$1,SUBQH,0),0),"") | H6: =IFERROR(VLOOKUP($A6,subQ,MATCH(H$1,SUBQH,0),0),"") | I6: =IFERROR(VLOOKUP($A6,subQ,MATCH(I$1,SUBQH,0),0),"") | J6: =IFERROR(VLOOKUP($A6,subQ,MATCH(J$1,SUBQH,0),0),"") | K6: =IFERROR(VLOOKUP($A6,subQ,MATCH(K$1,SUBQH,0),0),"") | L6: =IFERROR(VLOOKUP($A6,subQ,MATCH(L$1,SUBQH,0),0),"") | ... AG6: =IFERROR(VLOOKUP($A6,subQ,MATCH(AG$1,SUBQH,0),0),"")
A7: 매출총이익 | D7: 매출총이익 | E7: =IFERROR(VLOOKUP($A7,subQ,MATCH(E$1,SUBQH,0),0),"") | F7: =IFERROR(VLOOKUP($A7,subQ,MATCH(F$1,SUBQH,0),0),"") | G7: =IFERROR(VLOOKUP($A7,subQ,MATCH(G$1,SUBQH,0),0),"") | H7: =IFERROR(VLOOKUP($A7,subQ,MATCH(H$1,SUBQH,0),0),"") | I7: =IFERROR(VLOOKUP($A7,subQ,MATCH(I$1,SUBQH,0),0),"") | J7: =IFERROR(VLOOKUP($A7,subQ,MATCH(J$1,SUBQH,0),0),"") | K7: =IFERROR(VLOOKUP($A7,subQ,MATCH(K$1,SUBQH,0),0),"") | L7: =IFERROR(VLOOKUP($A7,subQ,MATCH(L$1,SUBQH,0),0),"") | ... AG7: =IFERROR(VLOOKUP($A7,subQ,MATCH(AG$1,SUBQH,0),0),"")
A8: 판관비 | D8: 판매비와관리비 | E8: =IFERROR(VLOOKUP($A8,subQ,MATCH(E$1,SUBQH,0),0),"") | F8: =IFERROR(VLOOKUP($A8,subQ,MATCH(F$1,SUBQH,0),0),"") | G8: =IFERROR(VLOOKUP($A8,subQ,MATCH(G$1,SUBQH,0),0),"") | H8: =IFERROR(VLOOKUP($A8,subQ,MATCH(H$1,SUBQH,0),0),"") | I8: =IFERROR(VLOOKUP($A8,subQ,MATCH(I$1,SUBQH,0),0),"") | J8: =IFERROR(VLOOKUP($A8,subQ,MATCH(J$1,SUBQH,0),0),"") | K8: =IFERROR(VLOOKUP($A8,subQ,MATCH(K$1,SUBQH,0),0),"") | L8: =IFERROR(VLOOKUP($A8,subQ,MATCH(L$1,SUBQH,0),0),"") | ... AG8: =IFERROR(VLOOKUP($A8,subQ,MATCH(AG$1,SUBQH,0),0),"")
A9: 영업이익 | D9: 영업이익 | E9: =IFERROR(VLOOKUP($A9,subQ,MATCH(E$1,SUBQH,0),0),"") | F9: =IFERROR(VLOOKUP($A9,subQ,MATCH(F$1,SUBQH,0),0),"") | G9: =IFERROR(VLOOKUP($A9,subQ,MATCH(G$1,SUBQH,0),0),"") | H9: =IFERROR(VLOOKUP($A9,subQ,MATCH(H$1,SUBQH,0),0),"") | I9: =IFERROR(VLOOKUP($A9,subQ,MATCH(I$1,SUBQH,0),0),"") | J9: =IFERROR(VLOOKUP($A9,subQ,MATCH(J$1,SUBQH,0),0),"") | K9: =IFERROR(VLOOKUP($A9,subQ,MATCH(K$1,SUBQH,0),0),"") | L9: =IFERROR(VLOOKUP($A9,subQ,MATCH(L$1,SUBQH,0),0),"") | ... AG9: =IFERROR(VLOOKUP($A9,subQ,MATCH(AG$1,SUBQH,0),0),"")
A10: OPM | D10: 영업이익률 | E10: =IFERROR(VLOOKUP($A10,subQ,MATCH(E$1,SUBQH,0),0),"") | F10: =IFERROR(VLOOKUP($A10,subQ,MATCH(F$1,SUBQH,0),0),"") | G10: =IFERROR(VLOOKUP($A10,subQ,MATCH(G$1,SUBQH,0),0),"") | H10: =IFERROR(VLOOKUP($A10,subQ,MATCH(H$1,SUBQH,0),0),"") | I10: =IFERROR(VLOOKUP($A10,subQ,MATCH(I$1,SUBQH,0),0),"") | J10: =IFERROR(VLOOKUP($A10,subQ,MATCH(J$1,SUBQH,0),0),"") | K10: =IFERROR(VLOOKUP($A10,subQ,MATCH(K$1,SUBQH,0),0),"") | L10: =IFERROR(VLOOKUP($A10,subQ,MATCH(L$1,SUBQH,0),0),"") | ... AG10: =IFERROR(VLOOKUP($A10,subQ,MATCH(AG$1,SUBQH,0),0),"")
A11: 금융손익 | D11: 금융손익(이자·환 포함) | E11: =IFERROR(VLOOKUP($A11,subQ,MATCH(E$1,SUBQH,0),0),"") | F11: =IFERROR(VLOOKUP($A11,subQ,MATCH(F$1,SUBQH,0),0),"") | G11: =IFERROR(VLOOKUP($A11,subQ,MATCH(G$1,SUBQH,0),0),"") | H11: =IFERROR(VLOOKUP($A11,subQ,MATCH(H$1,SUBQH,0),0),"") | I11: =IFERROR(VLOOKUP($A11,subQ,MATCH(I$1,SUBQH,0),0),"") | J11: =IFERROR(VLOOKUP($A11,subQ,MATCH(J$1,SUBQH,0),0),"") | K11: =IFERROR(VLOOKUP($A11,subQ,MATCH(K$1,SUBQH,0),0),"") | L11: =IFERROR(VLOOKUP($A11,subQ,MATCH(L$1,SUBQH,0),0),"") | ... AG11: =IFERROR(VLOOKUP($A11,subQ,MATCH(AG$1,SUBQH,0),0),"")
A12: 이자손익 | D12: 이자손익(이자수익 − 이자비용) | E12: =IFERROR(VLOOKUP($A12,subQ,MATCH(E$1,SUBQH,0),0),"") | F12: =IFERROR(VLOOKUP($A12,subQ,MATCH(F$1,SUBQH,0),0),"") | G12: =IFERROR(VLOOKUP($A12,subQ,MATCH(G$1,SUBQH,0),0),"") | H12: =IFERROR(VLOOKUP($A12,subQ,MATCH(H$1,SUBQH,0),0),"") | I12: =IFERROR(VLOOKUP($A12,subQ,MATCH(I$1,SUBQH,0),0),"") | J12: =IFERROR(VLOOKUP($A12,subQ,MATCH(J$1,SUBQH,0),0),"") | K12: =IFERROR(VLOOKUP($A12,subQ,MATCH(K$1,SUBQH,0),0),"") | L12: =IFERROR(VLOOKUP($A12,subQ,MATCH(L$1,SUBQH,0),0),"") | ... AG12: =IFERROR(VLOOKUP($A12,subQ,MATCH(AG$1,SUBQH,0),0),"")
A13: 외환손익 | D13: 외환손익(실적만; 추정 환효과는 환관련손익) | E13: =IFERROR(VLOOKUP($A13,subQ,MATCH(E$1,SUBQH,0),0),"") | F13: =IFERROR(VLOOKUP($A13,subQ,MATCH(F$1,SUBQH,0),0),"") | G13: =IFERROR(VLOOKUP($A13,subQ,MATCH(G$1,SUBQH,0),0),"") | H13: =IFERROR(VLOOKUP($A13,subQ,MATCH(H$1,SUBQH,0),0),"") | I13: =IFERROR(VLOOKUP($A13,subQ,MATCH(I$1,SUBQH,0),0),"") | J13: =IFERROR(VLOOKUP($A13,subQ,MATCH(J$1,SUBQH,0),0),"") | K13: =IFERROR(VLOOKUP($A13,subQ,MATCH(K$1,SUBQH,0),0),"") | L13: =IFERROR(VLOOKUP($A13,subQ,MATCH(L$1,SUBQH,0),0),"") | ... AG13: =IFERROR(VLOOKUP($A13,subQ,MATCH(AG$1,SUBQH,0),0),"")
A14: 기타영업외손익 | D14: 기타영업외손익 | E14: =IFERROR(VLOOKUP($A14,subQ,MATCH(E$1,SUBQH,0),0),"") | F14: =IFERROR(VLOOKUP($A14,subQ,MATCH(F$1,SUBQH,0),0),"") | G14: =IFERROR(VLOOKUP($A14,subQ,MATCH(G$1,SUBQH,0),0),"") | H14: =IFERROR(VLOOKUP($A14,subQ,MATCH(H$1,SUBQH,0),0),"") | I14: =IFERROR(VLOOKUP($A14,subQ,MATCH(I$1,SUBQH,0),0),"") | J14: =IFERROR(VLOOKUP($A14,subQ,MATCH(J$1,SUBQH,0),0),"") | K14: =IFERROR(VLOOKUP($A14,subQ,MATCH(K$1,SUBQH,0),0),"") | L14: =IFERROR(VLOOKUP($A14,subQ,MATCH(L$1,SUBQH,0),0),"") | ... AG14: =IFERROR(VLOOKUP($A14,subQ,MATCH(AG$1,SUBQH,0),0),"")
A15: 세전이익 | D15: 법인세비용차감전이익 | E15: =IFERROR(VLOOKUP($A15,subQ,MATCH(E$1,SUBQH,0),0),"") | F15: =IFERROR(VLOOKUP($A15,subQ,MATCH(F$1,SUBQH,0),0),"") | G15: =IFERROR(VLOOKUP($A15,subQ,MATCH(G$1,SUBQH,0),0),"") | H15: =IFERROR(VLOOKUP($A15,subQ,MATCH(H$1,SUBQH,0),0),"") | I15: =IFERROR(VLOOKUP($A15,subQ,MATCH(I$1,SUBQH,0),0),"") | J15: =IFERROR(VLOOKUP($A15,subQ,MATCH(J$1,SUBQH,0),0),"") | K15: =IFERROR(VLOOKUP($A15,subQ,MATCH(K$1,SUBQH,0),0),"") | L15: =IFERROR(VLOOKUP($A15,subQ,MATCH(L$1,SUBQH,0),0),"") | ... AG15: =IFERROR(VLOOKUP($A15,subQ,MATCH(AG$1,SUBQH,0),0),"")
A16: 법인세비용 | D16: 법인세비용 | E16: =IFERROR(VLOOKUP($A16,subQ,MATCH(E$1,SUBQH,0),0),"") | F16: =IFERROR(VLOOKUP($A16,subQ,MATCH(F$1,SUBQH,0),0),"") | G16: =IFERROR(VLOOKUP($A16,subQ,MATCH(G$1,SUBQH,0),0),"") | H16: =IFERROR(VLOOKUP($A16,subQ,MATCH(H$1,SUBQH,0),0),"") | I16: =IFERROR(VLOOKUP($A16,subQ,MATCH(I$1,SUBQH,0),0),"") | J16: =IFERROR(VLOOKUP($A16,subQ,MATCH(J$1,SUBQH,0),0),"") | K16: =IFERROR(VLOOKUP($A16,subQ,MATCH(K$1,SUBQH,0),0),"") | L16: =IFERROR(VLOOKUP($A16,subQ,MATCH(L$1,SUBQH,0),0),"") | ... AG16: =IFERROR(VLOOKUP($A16,subQ,MATCH(AG$1,SUBQH,0),0),"")
... A38: NPM | D38: NPM | E38: =IFERROR(VLOOKUP($A38,subQ,MATCH(E$1,SUBQH,0),0),"") | F38: =IFERROR(VLOOKUP($A38,subQ,MATCH(F$1,SUBQH,0),0),"") | G38: =IFERROR(VLOOKUP($A38,subQ,MATCH(G$1,SUBQH,0),0),"") | H38: =IFERROR(VLOOKUP($A38,subQ,MATCH(H$1,SUBQH,0),0),"") | I38: =IFERROR(VLOOKUP($A38,subQ,MATCH(I$1,SUBQH,0),0),"") | J38: =IFERROR(VLOOKUP($A38,subQ,MATCH(J$1,SUBQH,0),0),"") | K38: =IFERROR(VLOOKUP($A38,subQ,MATCH(K$1,SUBQH,0),0),"") | L38: =IFERROR(VLOOKUP($A38,subQ,MATCH(L$1,SUBQH,0),0),"") | ... AG38: =IFERROR(VLOOKUP($A38,subQ,MATCH(AG$1,SUBQH,0),0),"")
A39: 매출액 YoY | D39: 매출액 YoY | I39: =IFERROR(I5/E5-1,"") | J39: =IFERROR(J5/F5-1,"") | K39: =IFERROR(K5/G5-1,"") | L39: =IFERROR(L5/H5-1,"") | M39: =IFERROR(M5/I5-1,"") | N39: =IFERROR(N5/J5-1,"") | O39: =IFERROR(O5/K5-1,"") | P39: =IFERROR(P5/L5-1,"") | ... AG39: =IFERROR(AG5/AC5-1,"")
A40: 영업이익 YoY | D40: 영업이익 YoY | I40: =IFERROR(I9/E9-1,"") | J40: =IFERROR(J9/F9-1,"") | K40: =IFERROR(K9/G9-1,"") | L40: =IFERROR(L9/H9-1,"") | M40: =IFERROR(M9/I9-1,"") | N40: =IFERROR(N9/J9-1,"") | O40: =IFERROR(O9/K9-1,"") | P40: =IFERROR(P9/L9-1,"") | ... AG40: =IFERROR(AG9/AC9-1,"")
A41: 지배주주순이익 YoY | D41: 지배주주순이익 YoY | I41: =IFERROR(I18/E18-1,"") | J41: =IFERROR(J18/F18-1,"") | K41: =IFERROR(K18/G18-1,"") | L41: =IFERROR(L18/H18-1,"") | M41: =IFERROR(M18/I18-1,"") | N41: =IFERROR(N18/J18-1,"") | O41: =IFERROR(O18/K18-1,"") | P41: =IFERROR(P18/L18-1,"") | ... AG41: =IFERROR(AG18/AC18-1,"")

Sheet 연간예상
C1: 이름: 연간예상H — subQ 를 이름으로 VLOOKUP(억원) | E1: 2021 | F1: 2022 | G1: 2023 | H1: 2024 | I1: 2025 | J1: 2026 | K1: 2027 | L1: 2028
C2: 종가: | D2: =변수!D41
C3: 기준일: | D3: 20261014 | E3: 1 | F3: 2 | G3: 3 | H3: 4 | I3: 5 | J3: 6 | K3: 7 | L3: 8
E4: 2021.12A | F4: 2022.12A | G4: 2023.12A | H4: 2024.12A | I4: 2025.12A | J4: 2026.12A | K4: 2027.12A | L4: 2028.12A
A5: 매출액 | D5: 매출액 | E5: =IFERROR(VLOOKUP($A5,subQ,MATCH(E$1,SUBQH,0),0),"") | F5: =IFERROR(VLOOKUP($A5,subQ,MATCH(F$1,SUBQH,0),0),"") | G5: =IFERROR(VLOOKUP($A5,subQ,MATCH(G$1,SUBQH,0),0),"") | H5: =IFERROR(VLOOKUP($A5,subQ,MATCH(H$1,SUBQH,0),0),"") | I5: =IFERROR(VLOOKUP($A5,subQ,MATCH(I$1,SUBQH,0),0),"") | J5: =IFERROR(VLOOKUP($A5,subQ,MATCH(J$1,SUBQH,0),0),"") | K5: =IFERROR(VLOOKUP($A5,subQ,MATCH(K$1,SUBQH,0),0),"") | L5: =IFERROR(VLOOKUP($A5,subQ,MATCH(L$1,SUBQH,0),0),"")
A6: 매출원가 | D6: 매출원가 | E6: =IFERROR(VLOOKUP($A6,subQ,MATCH(E$1,SUBQH,0),0),"") | F6: =IFERROR(VLOOKUP($A6,subQ,MATCH(F$1,SUBQH,0),0),"") | G6: =IFERROR(VLOOKUP($A6,subQ,MATCH(G$1,SUBQH,0),0),"") | H6: =IFERROR(VLOOKUP($A6,subQ,MATCH(H$1,SUBQH,0),0),"") | I6: =IFERROR(VLOOKUP($A6,subQ,MATCH(I$1,SUBQH,0),0),"") | J6: =IFERROR(VLOOKUP($A6,subQ,MATCH(J$1,SUBQH,0),0),"") | K6: =IFERROR(VLOOKUP($A6,subQ,MATCH(K$1,SUBQH,0),0),"") | L6: =IFERROR(VLOOKUP($A6,subQ,MATCH(L$1,SUBQH,0),0),"")
A7: 매출총이익 | D7: 매출총이익 | E7: =IFERROR(VLOOKUP($A7,subQ,MATCH(E$1,SUBQH,0),0),"") | F7: =IFERROR(VLOOKUP($A7,subQ,MATCH(F$1,SUBQH,0),0),"") | G7: =IFERROR(VLOOKUP($A7,subQ,MATCH(G$1,SUBQH,0),0),"") | H7: =IFERROR(VLOOKUP($A7,subQ,MATCH(H$1,SUBQH,0),0),"") | I7: =IFERROR(VLOOKUP($A7,subQ,MATCH(I$1,SUBQH,0),0),"") | J7: =IFERROR(VLOOKUP($A7,subQ,MATCH(J$1,SUBQH,0),0),"") | K7: =IFERROR(VLOOKUP($A7,subQ,MATCH(K$1,SUBQH,0),0),"") | L7: =IFERROR(VLOOKUP($A7,subQ,MATCH(L$1,SUBQH,0),0),"")
A8: 판관비 | D8: 판매비와관리비 | E8: =IFERROR(VLOOKUP($A8,subQ,MATCH(E$1,SUBQH,0),0),"") | F8: =IFERROR(VLOOKUP($A8,subQ,MATCH(F$1,SUBQH,0),0),"") | G8: =IFERROR(VLOOKUP($A8,subQ,MATCH(G$1,SUBQH,0),0),"") | H8: =IFERROR(VLOOKUP($A8,subQ,MATCH(H$1,SUBQH,0),0),"") | I8: =IFERROR(VLOOKUP($A8,subQ,MATCH(I$1,SUBQH,0),0),"") | J8: =IFERROR(VLOOKUP($A8,subQ,MATCH(J$1,SUBQH,0),0),"") | K8: =IFERROR(VLOOKUP($A8,subQ,MATCH(K$1,SUBQH,0),0),"") | L8: =IFERROR(VLOOKUP($A8,subQ,MATCH(L$1,SUBQH,0),0),"")
A9: 영업이익 | D9: 영업이익 | E9: =IFERROR(VLOOKUP($A9,subQ,MATCH(E$1,SUBQH,0),0),"") | F9: =IFERROR(VLOOKUP($A9,subQ,MATCH(F$1,SUBQH,0),0),"") | G9: =IFERROR(VLOOKUP($A9,subQ,MATCH(G$1,SUBQH,0),0),"") | H9: =IFERROR(VLOOKUP($A9,subQ,MATCH(H$1,SUBQH,0),0),"") | I9: =IFERROR(VLOOKUP($A9,subQ,MATCH(I$1,SUBQH,0),0),"") | J9: =IFERROR(VLOOKUP($A9,subQ,MATCH(J$1,SUBQH,0),0),"") | K9: =IFERROR(VLOOKUP($A9,subQ,MATCH(K$1,SUBQH,0),0),"") | L9: =IFERROR(VLOOKUP($A9,subQ,MATCH(L$1,SUBQH,0),0),"")
A10: OPM | D10: 영업이익률 | E10: =IFERROR(VLOOKUP($A10,subQ,MATCH(E$1,SUBQH,0),0),"") | F10: =IFERROR(VLOOKUP($A10,subQ,MATCH(F$1,SUBQH,0),0),"") | G10: =IFERROR(VLOOKUP($A10,subQ,MATCH(G$1,SUBQH,0),0),"") | H10: =IFERROR(VLOOKUP($A10,subQ,MATCH(H$1,SUBQH,0),0),"") | I10: =IFERROR(VLOOKUP($A10,subQ,MATCH(I$1,SUBQH,0),0),"") | J10: =IFERROR(VLOOKUP($A10,subQ,MATCH(J$1,SUBQH,0),0),"") | K10: =IFERROR(VLOOKUP($A10,subQ,MATCH(K$1,SUBQH,0),0),"") | L10: =IFERROR(VLOOKUP($A10,subQ,MATCH(L$1,SUBQH,0),0),"")
A11: 금융손익 | D11: 금융손익(이자·환 포함) | E11: =IFERROR(VLOOKUP($A11,subQ,MATCH(E$1,SUBQH,0),0),"") | F11: =IFERROR(VLOOKUP($A11,subQ,MATCH(F$1,SUBQH,0),0),"") | G11: =IFERROR(VLOOKUP($A11,subQ,MATCH(G$1,SUBQH,0),0),"") | H11: =IFERROR(VLOOKUP($A11,subQ,MATCH(H$1,SUBQH,0),0),"") | I11: =IFERROR(VLOOKUP($A11,subQ,MATCH(I$1,SUBQH,0),0),"") | J11: =IFERROR(VLOOKUP($A11,subQ,MATCH(J$1,SUBQH,0),0),"") | K11: =IFERROR(VLOOKUP($A11,subQ,MATCH(K$1,SUBQH,0),0),"") | L11: =IFERROR(VLOOKUP($A11,subQ,MATCH(L$1,SUBQH,0),0),"")
A12: 이자손익 | D12: 이자손익(이자수익 − 이자비용) | E12: =IFERROR(VLOOKUP($A12,subQ,MATCH(E$1,SUBQH,0),0),"") | F12: =IFERROR(VLOOKUP($A12,subQ,MATCH(F$1,SUBQH,0),0),"") | G12: =IFERROR(VLOOKUP($A12,subQ,MATCH(G$1,SUBQH,0),0),"") | H12: =IFERROR(VLOOKUP($A12,subQ,MATCH(H$1,SUBQH,0),0),"") | I12: =IFERROR(VLOOKUP($A12,subQ,MATCH(I$1,SUBQH,0),0),"") | J12: =IFERROR(VLOOKUP($A12,subQ,MATCH(J$1,SUBQH,0),0),"") | K12: =IFERROR(VLOOKUP($A12,subQ,MATCH(K$1,SUBQH,0),0),"") | L12: =IFERROR(VLOOKUP($A12,subQ,MATCH(L$1,SUBQH,0),0),"")
A13: 외환손익 | D13: 외환손익(실적만; 추정 환효과는 환관련손익) | E13: =IFERROR(VLOOKUP($A13,subQ,MATCH(E$1,SUBQH,0),0),"") | F13: =IFERROR(VLOOKUP($A13,subQ,MATCH(F$1,SUBQH,0),0),"") | G13: =IFERROR(VLOOKUP($A13,subQ,MATCH(G$1,SUBQH,0),0),"") | H13: =IFERROR(VLOOKUP($A13,subQ,MATCH(H$1,SUBQH,0),0),"") | I13: =IFERROR(VLOOKUP($A13,subQ,MATCH(I$1,SUBQH,0),0),"") | J13: =IFERROR(VLOOKUP($A13,subQ,MATCH(J$1,SUBQH,0),0),"") | K13: =IFERROR(VLOOKUP($A13,subQ,MATCH(K$1,SUBQH,0),0),"") | L13: =IFERROR(VLOOKUP($A13,subQ,MATCH(L$1,SUBQH,0),0),"")
A14: 기타영업외손익 | D14: 기타영업외손익 | E14: =IFERROR(VLOOKUP($A14,subQ,MATCH(E$1,SUBQH,0),0),"") | F14: =IFERROR(VLOOKUP($A14,subQ,MATCH(F$1,SUBQH,0),0),"") | G14: =IFERROR(VLOOKUP($A14,subQ,MATCH(G$1,SUBQH,0),0),"") | H14: =IFERROR(VLOOKUP($A14,subQ,MATCH(H$1,SUBQH,0),0),"") | I14: =IFERROR(VLOOKUP($A14,subQ,MATCH(I$1,SUBQH,0),0),"") | J14: =IFERROR(VLOOKUP($A14,subQ,MATCH(J$1,SUBQH,0),0),"") | K14: =IFERROR(VLOOKUP($A14,subQ,MATCH(K$1,SUBQH,0),0),"") | L14: =IFERROR(VLOOKUP($A14,subQ,MATCH(L$1,SUBQH,0),0),"")
A15: 세전이익 | D15: 법인세비용차감전이익 | E15: =IFERROR(VLOOKUP($A15,subQ,MATCH(E$1,SUBQH,0),0),"") | F15: =IFERROR(VLOOKUP($A15,subQ,MATCH(F$1,SUBQH,0),0),"") | G15: =IFERROR(VLOOKUP($A15,subQ,MATCH(G$1,SUBQH,0),0),"") | H15: =IFERROR(VLOOKUP($A15,subQ,MATCH(H$1,SUBQH,0),0),"") | I15: =IFERROR(VLOOKUP($A15,subQ,MATCH(I$1,SUBQH,0),0),"") | J15: =IFERROR(VLOOKUP($A15,subQ,MATCH(J$1,SUBQH,0),0),"") | K15: =IFERROR(VLOOKUP($A15,subQ,MATCH(K$1,SUBQH,0),0),"") | L15: =IFERROR(VLOOKUP($A15,subQ,MATCH(L$1,SUBQH,0),0),"")
A16: 법인세비용 | D16: 법인세비용 | E16: =IFERROR(VLOOKUP($A16,subQ,MATCH(E$1,SUBQH,0),0),"") | F16: =IFERROR(VLOOKUP($A16,subQ,MATCH(F$1,SUBQH,0),0),"") | G16: =IFERROR(VLOOKUP($A16,subQ,MATCH(G$1,SUBQH,0),0),"") | H16: =IFERROR(VLOOKUP($A16,subQ,MATCH(H$1,SUBQH,0),0),"") | I16: =IFERROR(VLOOKUP($A16,subQ,MATCH(I$1,SUBQH,0),0),"") | J16: =IFERROR(VLOOKUP($A16,subQ,MATCH(J$1,SUBQH,0),0),"") | K16: =IFERROR(VLOOKUP($A16,subQ,MATCH(K$1,SUBQH,0),0),"") | L16: =IFERROR(VLOOKUP($A16,subQ,MATCH(L$1,SUBQH,0),0),"")
... A38: NPM | D38: NPM | E38: =IFERROR(VLOOKUP($A38,subQ,MATCH(E$1,SUBQH,0),0),"") | F38: =IFERROR(VLOOKUP($A38,subQ,MATCH(F$1,SUBQH,0),0),"") | G38: =IFERROR(VLOOKUP($A38,subQ,MATCH(G$1,SUBQH,0),0),"") | H38: =IFERROR(VLOOKUP($A38,subQ,MATCH(H$1,SUBQH,0),0),"") | I38: =IFERROR(VLOOKUP($A38,subQ,MATCH(I$1,SUBQH,0),0),"") | J38: =IFERROR(VLOOKUP($A38,subQ,MATCH(J$1,SUBQH,0),0),"") | K38: =IFERROR(VLOOKUP($A38,subQ,MATCH(K$1,SUBQH,0),0),"") | L38: =IFERROR(VLOOKUP($A38,subQ,MATCH(L$1,SUBQH,0),0),"")
A39: 매출액 YoY | D39: 매출액 YoY | F39: =IFERROR(F5/E5-1,"") | G39: =IFERROR(G5/F5-1,"") | H39: =IFERROR(H5/G5-1,"") | I39: =IFERROR(I5/H5-1,"") | J39: =IFERROR(J5/I5-1,"") | K39: =IFERROR(K5/J5-1,"") | L39: =IFERROR(L5/K5-1,"")
A40: 영업이익 YoY | D40: 영업이익 YoY | F40: =IFERROR(F9/E9-1,"") | G40: =IFERROR(G9/F9-1,"") | H40: =IFERROR(H9/G9-1,"") | I40: =IFERROR(I9/H9-1,"") | J40: =IFERROR(J9/I9-1,"") | K40: =IFERROR(K9/J9-1,"") | L40: =IFERROR(L9/K9-1,"")
A41: 지배주주순이익 YoY | D41: 지배주주순이익 YoY | F41: =IFERROR(F18/E18-1,"") | G41: =IFERROR(G18/F18-1,"") | H41: =IFERROR(H18/G18-1,"") | I41: =IFERROR(I18/H18-1,"") | J41: =IFERROR(J18/I18-1,"") | K41: =IFERROR(K18/J18-1,"") | L41: =IFERROR(L18/K18-1,"")

Sheet TP
B1: 종가 | C1: =변수!D41
B2: 기준일 | C2: =변수!D42
B3: 모델 산출값 — 목표주가·추천 아님. 밴드·COE 는 변수 시트 3절의 가정
C5: FY | D5: 2025 | E5: 2026 | F5: 2027 | G5: 2028
D6: A | E6: E | F6: E | G6: E
C7: EPS(원) | D7: =IFERROR(VLOOKUP("EPS",subQ,MATCH(D$5,SUBQH,0),0),"") | E7: =IFERROR(VLOOKUP("EPS",subQ,MATCH(E$5,SUBQH,0),0),"") | F7: =IFERROR(VLOOKUP("EPS",subQ,MATCH(F$5,SUBQH,0),0),"") | G7: =IFERROR(VLOOKUP("EPS",subQ,MATCH(G$5,SUBQH,0),0),"")
C8: BPS(원) | D8: =IFERROR(VLOOKUP("BPS",subQ,MATCH(D$5,SUBQH,0),0),"") | E8: =IFERROR(VLOOKUP("BPS",subQ,MATCH(E$5,SUBQH,0),0),"") | F8: =IFERROR(VLOOKUP("BPS",subQ,MATCH(F$5,SUBQH,0),0),"") | G8: =IFERROR(VLOOKUP("BPS",subQ,MATCH(G$5,SUBQH,0),0),"")
C9: 지배주주순이익(억원) | D9: =IFERROR(VLOOKUP("지배주주순이익",subQ,MATCH(D$5,SUBQH,0),0),"") | E9: =IFERROR(VLOOKUP("지배주주순이익",subQ,MATCH(E$5,SUBQH,0),0),"") | F9: =IFERROR(VLOOKUP("지배주주순이익",subQ,MATCH(F$5,SUBQH,0),0),"") | G9: =IFERROR(VLOOKUP("지배주주순이익",subQ,MATCH(G$5,SUBQH,0),0),"")
C10: 영업이익(억원) | D10: =IFERROR(VLOOKUP("영업이익",subQ,MATCH(D$5,SUBQH,0),0),"") | E10: =IFERROR(VLOOKUP("영업이익",subQ,MATCH(E$5,SUBQH,0),0),"") | F10: =IFERROR(VLOOKUP("영업이익",subQ,MATCH(F$5,SUBQH,0),0),"") | G10: =IFERROR(VLOOKUP("영업이익",subQ,MATCH(G$5,SUBQH,0),0),"")
C11: ROE(EPS/기초BPS) | E11: =IFERROR(E7/D8,"") | F11: =IFERROR(F7/E8,"") | G11: =IFERROR(G7/F8,"")
B13: PER
C14: 12M fwd EPS | D14: =IFERROR(E7*변수!D47+F7*(1-변수!D47),"")
C15: 적정가치 @PER_lo | D15: =변수!D44 | E15: =IFERROR(ROUND($D$14*D15,-2),"") | F15: =IFERROR(E15/$C$1-1,"") | G15: 배 · 원 · 종가 대비
C16: 적정가치 @PER_mid | D16: =변수!D45 | E16: =IFERROR(ROUND($D$14*D16,-2),"") | F16: =IFERROR(E16/$C$1-1,"") | G16: 배 · 원 · 종가 대비
C17: 적정가치 @PER_hi | D17: =변수!D46 | E17: =IFERROR(ROUND($D$14*D17,-2),"") | F17: =IFERROR(E17/$C$1-1,"") | G17: 배 · 원 · 종가 대비
C18: 현재 PER(종가/12M fwd EPS) | D18: =IFERROR($C$1/$D$14,"")
B20: PBR
C21: 최근 BPS(마지막 실적 분기) | D21: =IFERROR(VLOOKUP("BPS",subQ,MATCH("2Q26",SUBQH,0),0),"")
C22: ROE fwd(12M fwd EPS / BPS) | D22: =IFERROR($D$14/$D$21,"")
C23: COE | D23: =변수!D43
C24: 적정 PBR = ROE/COE | D24: =IFERROR(D22/D23,"")
C25: 적정가치(PBR) = BPS × 적정PBR | D25: =IFERROR(ROUND(D21*D24,-2),"") | E25: =IFERROR(D25/$C$1-1,"")
C26: 현재 PBR(종가/BPS) | D26: =IFERROR($C$1/D21,"")
B28: 모델 json valuation(참고)
C29: eps_fwd12m | D29: -35.3
C30: bps_latest | D30: 3641.6
C31: per_now
C32: pbr_now | D32: 1.3
C33: roe_fwd | D33: -0.0097
C34: fair_pbr
C35: fair_value_pbr
C36: ev_ebitda
C37: note | D37: 모델 산출값 — 목표주가·추천 아님

Sheet 외화
C1: 이름: 외화QH — 환율 QoQ · 외화 순노출 × Δ기말환율 | E1: 4Q21 | F1: 1Q22 | G1: 2Q22 | H1: 3Q22 | I1: 4Q22 | J1: 1Q23 | K1: 2Q23 | L1: 3Q23 | M1: 4Q23 | N1: 1Q24 | O1: 2Q24 | P1: 3Q24 | Q1: 4Q24 | R1: 1Q25 | S1: 2Q25 | T1: 3Q25 | U1: 4Q25 | V1: 1Q26 | W1: 2Q26 | X1: 3Q26 | Y1: 4Q26 | Z1: 1Q27 | AA1: 2Q27 | AB1: 3Q27 | AC1: 4Q27 | AD1: 1Q28 | AE1: 2Q28 | AF1: 3Q28 | AG1: 4Q28
E3: 1 | F3: 2 | G3: 3 | H3: 4 | I3: 5 | J3: 6 | K3: 7 | L3: 8 | M3: 9 | N3: 10 | O3: 11 | P3: 12 | Q3: 13 | R3: 14 | S3: 15 | T3: 16 | U3: 17 | V3: 18 | W3: 19 | X3: 20 | Y3: 21 | Z3: 22 | AA3: 23 | AB3: 24 | AC3: 25 | AD3: 26 | AE3: 27 | AF3: 28 | AG3: 29
E4: 2021.12 | F4: 2022.03 | G4: 2022.06 | H4: 2022.09 | I4: 2022.12 | J4: 2023.03 | K4: 2023.06 | L4: 2023.09 | M4: 2023.12 | N4: 2024.03 | O4: 2024.06 | P4: 2024.09 | Q4: 2024.12 | R4: 2025.03 | S4: 2025.06 | T4: 2025.09 | U4: 2025.12 | V4: 2026.03 | W4: 2026.06 | X4: 2026.09 | Y4: 2026.12 | Z4: 2027.03 | AA4: 2027.06 | AB4: 2027.09 | AC4: 2027.12 | AD4: 2028.03 | AE4: 2028.06 | AF4: 2028.09 | AG4: 2028.12
D5: 원/달러(평균) | E5: =IFERROR(VLOOKUP($D5,환율,MATCH(E$1,변수H,0),0),"") | F5: =IFERROR(VLOOKUP($D5,환율,MATCH(F$1,변수H,0),0),"") | G5: =IFERROR(VLOOKUP($D5,환율,MATCH(G$1,변수H,0),0),"") | H5: =IFERROR(VLOOKUP($D5,환율,MATCH(H$1,변수H,0),0),"") | I5: =IFERROR(VLOOKUP($D5,환율,MATCH(I$1,변수H,0),0),"") | J5: =IFERROR(VLOOKUP($D5,환율,MATCH(J$1,변수H,0),0),"") | K5: =IFERROR(VLOOKUP($D5,환율,MATCH(K$1,변수H,0),0),"") | L5: =IFERROR(VLOOKUP($D5,환율,MATCH(L$1,변수H,0),0),"") | ... AG5: =IFERROR(VLOOKUP($D5,환율,MATCH(AG$1,변수H,0),0),"")
A6: 원/달러(평균) QoQ | F6: =IFERROR(F5/E5-1,"") | G6: =IFERROR(G5/F5-1,"") | H6: =IFERROR(H5/G5-1,"") | I6: =IFERROR(I5/H5-1,"") | J6: =IFERROR(J5/I5-1,"") | K6: =IFERROR(K5/J5-1,"") | L6: =IFERROR(L5/K5-1,"") | M6: =IFERROR(M5/L5-1,"") | ... AG6: =IFERROR(AG5/AF5-1,"")
D7: 원/달러(기말) | E7: =IFERROR(VLOOKUP($D7,환율,MATCH(E$1,변수H,0),0),"") | F7: =IFERROR(VLOOKUP($D7,환율,MATCH(F$1,변수H,0),0),"") | G7: =IFERROR(VLOOKUP($D7,환율,MATCH(G$1,변수H,0),0),"") | H7: =IFERROR(VLOOKUP($D7,환율,MATCH(H$1,변수H,0),0),"") | I7: =IFERROR(VLOOKUP($D7,환율,MATCH(I$1,변수H,0),0),"") | J7: =IFERROR(VLOOKUP($D7,환율,MATCH(J$1,변수H,0),0),"") | K7: =IFERROR(VLOOKUP($D7,환율,MATCH(K$1,변수H,0),0),"") | L7: =IFERROR(VLOOKUP($D7,환율,MATCH(L$1,변수H,0),0),"") | ... AG7: =IFERROR(VLOOKUP($D7,환율,MATCH(AG$1,변수H,0),0),"")
A8: 원/달러(기말) QoQ | F8: =IFERROR(F7/E7-1,"") | G8: =IFERROR(G7/F7-1,"") | H8: =IFERROR(H7/G7-1,"") | I8: =IFERROR(I7/H7-1,"") | J8: =IFERROR(J7/I7-1,"") | K8: =IFERROR(K7/J7-1,"") | L8: =IFERROR(L7/K7-1,"") | M8: =IFERROR(M7/L7-1,"") | ... AG8: =IFERROR(AG7/AF7-1,"")
D9: W/Euro(평균) | E9: =IFERROR(VLOOKUP($D9,환율,MATCH(E$1,변수H,0),0),"") | F9: =IFERROR(VLOOKUP($D9,환율,MATCH(F$1,변수H,0),0),"") | G9: =IFERROR(VLOOKUP($D9,환율,MATCH(G$1,변수H,0),0),"") | H9: =IFERROR(VLOOKUP($D9,환율,MATCH(H$1,변수H,0),0),"") | I9: =IFERROR(VLOOKUP($D9,환율,MATCH(I$1,변수H,0),0),"") | J9: =IFERROR(VLOOKUP($D9,환율,MATCH(J$1,변수H,0),0),"") | K9: =IFERROR(VLOOKUP($D9,환율,MATCH(K$1,변수H,0),0),"") | L9: =IFERROR(VLOOKUP($D9,환율,MATCH(L$1,변수H,0),0),"") | ... AG9: =IFERROR(VLOOKUP($D9,환율,MATCH(AG$1,변수H,0),0),"")
A10: W/Euro(평균) QoQ | F10: =IFERROR(F9/E9-1,"") | G10: =IFERROR(G9/F9-1,"") | H10: =IFERROR(H9/G9-1,"") | I10: =IFERROR(I9/H9-1,"") | J10: =IFERROR(J9/I9-1,"") | K10: =IFERROR(K9/J9-1,"") | L10: =IFERROR(L9/K9-1,"") | M10: =IFERROR(M9/L9-1,"") | ... AG10: =IFERROR(AG9/AF9-1,"")
D11: W/Euro(기말) | E11: =IFERROR(VLOOKUP($D11,환율,MATCH(E$1,변수H,0),0),"") | F11: =IFERROR(VLOOKUP($D11,환율,MATCH(F$1,변수H,0),0),"") | G11: =IFERROR(VLOOKUP($D11,환율,MATCH(G$1,변수H,0),0),"") | H11: =IFERROR(VLOOKUP($D11,환율,MATCH(H$1,변수H,0),0),"") | I11: =IFERROR(VLOOKUP($D11,환율,MATCH(I$1,변수H,0),0),"") | J11: =IFERROR(VLOOKUP($D11,환율,MATCH(J$1,변수H,0),0),"") | K11: =IFERROR(VLOOKUP($D11,환율,MATCH(K$1,변수H,0),0),"") | L11: =IFERROR(VLOOKUP($D11,환율,MATCH(L$1,변수H,0),0),"") | ... AG11: =IFERROR(VLOOKUP($D11,환율,MATCH(AG$1,변수H,0),0),"")
A12: W/Euro(기말) QoQ | F12: =IFERROR(F11/E11-1,"") | G12: =IFERROR(G11/F11-1,"") | H12: =IFERROR(H11/G11-1,"") | I12: =IFERROR(I11/H11-1,"") | J12: =IFERROR(J11/I11-1,"") | K12: =IFERROR(K11/J11-1,"") | L12: =IFERROR(L11/K11-1,"") | M12: =IFERROR(M11/L11-1,"") | ... AG12: =IFERROR(AG11/AF11-1,"")
D13: 원/100Y(기말) | E13: =IFERROR(VLOOKUP($D13,환율,MATCH(E$1,변수H,0),0),"") | F13: =IFERROR(VLOOKUP($D13,환율,MATCH(F$1,변수H,0),0),"") | G13: =IFERROR(VLOOKUP($D13,환율,MATCH(G$1,변수H,0),0),"") | H13: =IFERROR(VLOOKUP($D13,환율,MATCH(H$1,변수H,0),0),"") | I13: =IFERROR(VLOOKUP($D13,환율,MATCH(I$1,변수H,0),0),"") | J13: =IFERROR(VLOOKUP($D13,환율,MATCH(J$1,변수H,0),0),"") | K13: =IFERROR(VLOOKUP($D13,환율,MATCH(K$1,변수H,0),0),"") | L13: =IFERROR(VLOOKUP($D13,환율,MATCH(L$1,변수H,0),0),"") | ... AG13: =IFERROR(VLOOKUP($D13,환율,MATCH(AG$1,변수H,0),0),"")
A14: 원/100Y(기말) QoQ | F14: =IFERROR(F13/E13-1,"") | G14: =IFERROR(G13/F13-1,"") | H14: =IFERROR(H13/G13-1,"") | I14: =IFERROR(I13/H13-1,"") | J14: =IFERROR(J13/I13-1,"") | K14: =IFERROR(K13/J13-1,"") | L14: =IFERROR(L13/K13-1,"") | M14: =IFERROR(M13/L13-1,"") | ... AG14: =IFERROR(AG13/AF13-1,"")
A16: 외화순노출 | C16: 외화 순노출(백만$) | D16: =변수!D54 | E16: 외화 순노출 × Δ기말환율 (외화 시트 방식)
A17: 환관련손익추정 | C17: 환관련손익 추정(억원) = 순노출 × Δ원/달러(기말) / 100 | F17: =IFERROR($D$16*(F7-E7)/100,"") | G17: =IFERROR($D$16*(G7-F7)/100,"") | H17: =IFERROR($D$16*(H7-G7)/100,"") | I17: =IFERROR($D$16*(I7-H7)/100,"") | J17: =IFERROR($D$16*(J7-I7)/100,"") | K17: =IFERROR($D$16*(K7-J7)/100,"") | L17: =IFERROR($D$16*(L7-K7)/100,"") | M17: =IFERROR($D$16*(M7-L7)/100,"") | ... AG17: =IFERROR($D$16*(AG7-AF7)/100,"")
A18: fx_pnl.by_q | C18: 모델 fx_pnl.by_q(억원, 참고)
C19: 외화 순노출 미공시(face) → 0 + 표기
