Workbook
Name 변수H: 변수!$C$1:$AO$1
Name 환율: 변수!$C$6:$AO$13
Name BS연결H: BS연결!$C$1:$AO$1
Name BS연결: BS연결!$C$5:$AO$5
Name BS별도H: BS별도!$C$1:$AO$1
Name BS별도: BS별도!$C$5:$AO$95
Name SUBQH: subQ!$A$1:$AO$1
Name subQ: subQ!$A$5:$AO$42

Sheet README
A1: 삼영이엔씨(065570) 실적 모델 — ARGUS 한국조선
A2: 기준 분기 2026Q2 · 마지막 실적 2026Q2 · 생성 2026-10-13
A3: 모든 수치는 모델 산출값(DART 공개 재무제표 + 우리 추정)이다 — 목표주가·투자 추천 아님. 참고용 · 투자조언 아님.
A5: 시트
A6: 변수 가정 시계열. 환율 8행(ECB via frankfurter — L2 fx.json; 추정 분기 = 노란 가정), 추정 드라이버(노란 셀 = 모델값에서 역산한 가정, 바꾸면 재계산; 연녹 셀 = 3절 스칼라 참조 수식), 3절 스칼라 가정(세율·판관비율·지배주주비중·이자율·종가·PER 밴드·COE·외화 순노출·헤지비율)
A7: BS연결/BS별도 FnGuide 계정명 × 기간 값 덤프(백만원). 행1 분기라벨, 행4 YYYY.MM / YYYY.12A. 이름정의 BS연결H·BS연결(계정명 C열부터)
A8: subQ 분기 서브모델(억원 = 백만원/100). 확정 행: =IFERROR(VLOOKUP($D행,BS연결,MATCH(E$1,BS연결H,0),0)/100,"") 추정 행: 변수 시트 가정 셀 참조 수식. 외환손익·파생상품손익은 BS 계정 합·차, 기타금융손익은 잔차, OPM·EPS·BPS·PER·PBR 은 파생 수식
A9: SLS 선표(조선사만, sls json 있을 때): 요약 행(sls 저장값) + 계약별 스케줄(백만$) × (헤지비율 × 헤지환율 + (1−헤지비율) × 건조시점 환율[변수 원/달러(평균)]) → 원화 수식 블록 → 합계 행이 subQ 매출조선에 연결
A10: 시나리오 신규수주 보수/기준/낙관(forecast_panel 패널, 모델에 scenarios 가 있을 때만): 매출액·영업이익 = subQ 기준값 ± (시나리오 신규 − base 신규) × OPM. base 만 subQ 행에 포함, 나머지는 합산 안 함
A11: 분기/연간예상 subQ 를 이름(A열 key)으로 VLOOKUP 한 보고서 표(억원)
A12: TP PER 밴드 × 12M fwd EPS, PBR = ROE/COE × BPS — 모델 산출값 구간, 목표주가·추천 아님
A13: 외화 환율 QoQ, 외화 순노출 × Δ기말환율 → 환관련손익 추정
... A34: 백테스트: {"freeze": "2025Q2", "horizon": 4, "revenue_wape_pct": 25.7, "op_wape_pct": 341.0, "n": 4, "note": "단일 회사 4분기 — 통계 아님", "driver_at_freeze": "trend_seasonal", "selection_oos_at_freeze": null, "frozen_inputs": "fin(연결/별도)·고객 조선사 모델·지주 자회사 모델은 2025Q2 까지의 분기만; 선표는 체결일 ≤ 2025Q2 말일 계약(원장 최신 금액·코호트 등급, 환산 없음); 잔고는 yards_cache 2025Q2; 시세·환율 forward·prices·forecast_panel 신규수주 미사용. 고객 가중치(suppliers.json 언급 비중)와 합병 체인링크는 현재 지식; 고객 연동 채택은 동결 모델 안에서도 자기 la−4분기 OOS 규칙(selection_oos_at_freeze)", "detail": [{"q": "2025Q3", "rev_pred": 68.7, "rev_act": 90.64, "op_pred": -11.96, "op_act": -4.86}, {"q": "2025Q4", "rev_pred": 147.65, "rev_act": 113.74, "op_pred": -25.71, "op_act": 1.88}, {"q": "2026Q1", "rev_pred": 49.49, "rev_act": 50.77, "op_pred": -8.62, "op_act": -3.23}, {"q": "2026Q2", "rev_pred": 85.36, "rev_act": 61.26, "op_pred": -14.86, "op_act": 8.69}]}

Sheet 변수
C1: 이름: 변수H | E1: 4Q21 | F1: 2021 | G1: 1Q22 | H1: 2Q22 | I1: 3Q22 | J1: 4Q22 | K1: 2022 | L1: 1Q23 | M1: 2Q23 | N1: 3Q23 | O1: 4Q23 | P1: 2023 | Q1: 1Q24 | R1: 2Q24 | S1: 3Q24 | T1: 4Q24 | U1: 2024 | V1: 1Q25 | W1: 2Q25 | X1: 3Q25 | Y1: 4Q25 | Z1: 2025 | AA1: 1Q26 | AB1: 2Q26 | AC1: 3Q26 | AD1: 4Q26 | AE1: 2026 | AF1: 1Q27 | AG1: 2Q27 | AH1: 3Q27 | AI1: 4Q27 | AJ1: 2027 | AK1: 1Q28 | AL1: 2Q28 | AM1: 3Q28 | AN1: 4Q28 | AO1: 2028
A2: 가정 시계열 — 노란 셀은 추정 가정(모델값에서 역산), 연녹 셀은 3절 스칼라 참조 수식. 바꾸면 subQ·분기·연간예상·TP·시나리오가 재계산됩니다.
E3: 1 | F3: 2 | G3: 3 | H3: 4 | I3: 5 | J3: 6 | K3: 7 | L3: 8 | M3: 9 | N3: 10 | O3: 11 | P3: 12 | Q3: 13 | R3: 14 | S3: 15 | T3: 16 | U3: 17 | V3: 18 | W3: 19 | X3: 20 | Y3: 21 | Z3: 22 | AA3: 23 | AB3: 24 | AC3: 25 | AD3: 26 | AE3: 27 | AF3: 28 | AG3: 29 | AH3: 30 | AI3: 31 | AJ3: 32 | AK3: 33 | AL3: 34 | AM3: 35 | AN3: 36 | AO3: 37
E4: 2021.12 | F4: 2021.12A | G4: 2022.03 | H4: 2022.06 | I4: 2022.09 | J4: 2022.12 | K4: 2022.12A | L4: 2023.03 | M4: 2023.06 | N4: 2023.09 | O4: 2023.12 | P4: 2023.12A | Q4: 2024.03 | R4: 2024.06 | S4: 2024.09 | T4: 2024.12 | U4: 2024.12A | V4: 2025.03 | W4: 2025.06 | X4: 2025.09 | Y4: 2025.12 | Z4: 2025.12A | AA4: 2026.03 | AB4: 2026.06 | AC4: 2026.09 | AD4: 2026.12 | AE4: 2026.12A | AF4: 2027.03 | AG4: 2027.06 | AH4: 2027.09 | AI4: 2027.12 | AJ4: 2027.12A | AK4: 2028.03 | AL4: 2028.06 | AM4: 2028.09 | AN4: 2028.12 | AO4: 2028.12A
B5: 1. FX | C5: 이름: 환율
A6: USDKRW_avg | C6: 원/달러(평균) | E6: 1183.5 | F6: 1145.51 | G6: 1205.78 | H6: 1262.09 | I6: 1341.93 | J6: 1360.12 | K6: 1292.98 | L6: 1276.95 | M6: 1315.69 | N6: 1313.62 | O6: 1322.01 | P6: 1306.85 | Q6: 1330.14 | R6: 1371.28 | S6: 1356.22 | T6: 1396.3 | U6: 1363.53 | V6: 1452.28 | W6: 1398.52 | X6: 1386.95 | Y6: 1449.19 | Z6: 1421.52 | AA6: 1466.12 | AB6: 1501.75 | AC6: 1418.75 | AD6: 1343.63 | AE6: 1456.58 | AF6: 1333.09 | AG6: 1333.09 | AH6: 1333.09 | AI6: 1333.09 | AK6: 1333.09 | AL6: 1333.09 | AM6: 1333.09 | AN6: 1333.09
A7: USDKRW_end | C7: 원/달러(기말) | E7: 1188.75 | F7: 1188.75 | G7: 1213.74 | H7: 1301.24 | I7: 1436.9 | J7: 1260.16 | K7: 1260.16 | L7: 1305.99 | M7: 1321.44 | N7: 1345.35 | O7: 1297.43 | P7: 1297.43 | Q7: 1349.25 | R7: 1377.73 | S7: 1312.17 | T7: 1474.78 | U7: 1474.78 | V7: 1474.54 | W7: 1355.13 | X7: 1403.67 | Y7: 1444.2 | Z7: 1444.2 | AA7: 1524.8 | AB7: 1550.89 | AC7: 1355.4 | AD7: 1333.09 | AE7: 1333.09 | AF7: 1333.09 | AG7: 1333.09 | AH7: 1333.09 | AI7: 1333.09 | AK7: 1333.09 | AL7: 1333.09 | AM7: 1333.09 | AN7: 1333.09
A8: JPY100KRW_avg | C8: 원/100Y(평균) | E8: 1041.02 | F8: 1042.74 | G8: 1036.79 | H8: 972.23 | I8: 970.61 | J8: 961.03 | K8: 985.1 | L8: 964.89 | M8: 957.36 | N8: 909 | O8: 893.22 | P8: 931.11 | Q8: 896.29 | R8: 880.14 | S8: 909.35 | T8: 917.25 | U8: 900.92 | V8: 952.59 | W8: 967.92 | X8: 940.32 | Y8: 940.77 | Z8: 950.17 | AA8: 934.39 | AB8: 942.16 | AC8: 890.41 | AD8: 849.51 | AE8: 918.81 | AF8: 840.54 | AG8: 840.54 | AH8: 840.54 | AI8: 840.54 | AK8: 840.54 | AL8: 840.54 | AM8: 840.54 | AN8: 840.54
A9: JPY100KRW_end | C9: 원/100Y(기말) | E9: 1032.62 | F9: 1032.62 | G9: 996.83 | H9: 954.9 | I9: 993.29 | J9: 955.54 | K9: 955.54 | L9: 980.62 | M9: 913.67 | N9: 901.47 | O9: 917.04 | P9: 917.04 | Q9: 892.42 | R9: 857.76 | S9: 919.21 | T9: 939.65 | U9: 939.65 | V9: 986.84 | W9: 938.85 | X9: 948.49 | Y9: 921.81 | Z9: 921.81 | AA9: 955.99 | AB9: 954.75 | AC9: 863.31 | AD9: 840.54 | AE9: 840.54 | AF9: 840.54 | AG9: 840.54 | AH9: 840.54 | AI9: 840.54 | AK9: 840.54 | AL9: 840.54 | AM9: 840.54 | AN9: 840.54
A10: EURKRW_avg | C10: W/Euro(평균) | E10: 1353.32 | F10: 1354.06 | G10: 1352.29 | H10: 1343.31 | I10: 1350.63 | J10: 1386.07 | K10: 1358.07 | L10: 1369.93 | M10: 1432.41 | N10: 1429.41 | O10: 1420.91 | P10: 1412.88 | Q10: 1444.21 | R10: 1476.42 | S10: 1489.3 | T10: 1490.78 | U10: 1475.4 | V10: 1528.33 | W10: 1585.13 | X10: 1620.04 | Y10: 1686.02 | Z10: 1605.45 | AA10: 1715.47 | AB10: 1746.09 | AC10: 1631.97 | AD10: 1507.34 | AE10: 1688.95 | AF10: 1490.54 | AG10: 1490.54 | AH10: 1490.54 | AI10: 1490.54 | AK10: 1490.54 | AL10: 1490.54 | AM10: 1490.54 | AN10: 1490.54
A11: EURKRW_end | C11: W/Euro(기말) | E11: 1346.38 | F11: 1346.38 | G11: 1347.37 | H11: 1351.6 | I11: 1400.62 | J11: 1344.08 | K11: 1344.08 | L11: 1420.26 | M11: 1435.88 | N11: 1425.26 | O11: 1433.66 | P11: 1433.66 | Q11: 1458.68 | R11: 1474.86 | S11: 1469.1 | T11: 1532.14 | U11: 1532.14 | V11: 1594.72 | W11: 1588.22 | X11: 1648.04 | Y11: 1696.94 | Z11: 1696.94 | AA11: 1753.21 | AB11: 1767.09 | AC11: 1539.06 | AD11: 1490.54 | AE11: 1490.54 | AF11: 1490.54 | AG11: 1490.54 | AH11: 1490.54 | AI11: 1490.54 | AK11: 1490.54 | AL11: 1490.54 | AM11: 1490.54 | AN11: 1490.54
A12: CNYKRW_avg | C12: 원/중국원(평균) | E12: 185.14 | F12: 177.65 | G12: 189.93 | H12: 190.76 | I12: 195.79 | J12: 191.09 | K12: 191.93 | L12: 186.59 | M12: 187.45 | N12: 181.28 | O12: 182.86 | P12: 184.52 | Q12: 185.04 | R12: 189.35 | S12: 189.24 | T12: 194.24 | U12: 189.49 | V12: 199.63 | W12: 193.41 | X12: 193.79 | Y12: 204.38 | Z12: 197.8 | AA12: 211.75 | AB12: 220.8 | AC12: 210.43 | AD12: 200.5 | AE12: 213.68 | AF12: 199.18 | AG12: 199.18 | AH12: 199.18 | AI12: 199.18 | AK12: 199.18 | AL12: 199.18 | AM12: 199.18 | AN12: 199.18
A13: CNYKRW_end | C13: 원/중국원(기말) | E13: 187.13 | F13: 187.13 | G13: 191.38 | H13: 194.13 | I13: 201.92 | J13: 182.67 | K13: 182.67 | L13: 189.97 | M13: 181.8 | N13: 184.26 | O13: 182.61 | P13: 182.61 | Q13: 186.66 | R13: 189.7 | S13: 187.12 | T13: 202.04 | U13: 202.04 | V13: 203.3 | W13: 189.14 | X13: 197.16 | Y13: 206.28 | Z13: 206.28 | AA13: 220.97 | AB13: 228.56 | AC13: 202.16 | AD13: 199.18 | AE13: 199.18 | AF13: 199.18 | AG13: 199.18 | AH13: 199.18 | AI13: 199.18 | AK13: 199.18 | AL13: 199.18 | AM13: 199.18 | AN13: 199.18
B14: 1b. 종가
A15: price_close_end | C15: 종가(기말) | E15: 7650 | G15: 7490 | H15: 4980 | I15: 7550 | J15: 4500 | L15: 4185 | M15: 5950 | N15: 4340 | O15: 2955 | Q15: 2890 | R15: 2365 | S15: 1841 | T15: 1740 | V15: 764
A16: price_high | C16: 종가(최고) | E16: 9300 | G16: 8150 | H16: 7800 | I16: 9050 | J16: 7800 | L16: 6680 | M16: 6100 | N16: 6780 | O16: 5500 | Q16: 4070 | R16: 3950 | S16: 2575 | T16: 2415 | V16: 1826
A17: price_low | C17: 종가(최저) | E17: 7050 | G17: 5990 | H17: 4510 | I17: 4605 | J17: 4340 | L17: 3970 | M17: 3585 | N17: 3700 | O17: 2680 | Q17: 2740 | R17: 2155 | S17: 1400 | T17: 1316 | V17: 745
A18: price_avg | C18: 종가(평균) | E18: 7971.7 | G18: 7363.9 | H18: 6173.5 | I18: 6987.2 | J18: 5679.6 | L18: 4868.4 | M18: 4383.9 | N18: 5382.5 | O18: 3625.1 | Q18: 3081.6 | R18: 3132.3 | S18: 1783.9 | T18: 1826.1 | V18: 1383.3
B20: 2. 추정 드라이버 | C20: 실적 열 = subQ 실현값(수식), 추정 열 = 가정(노란 = 모델값 역산, 연녹 = 3절 스칼라 참조)
A21: drv:매출액 | B21: yoy | C21: 매출액 YoY | J21: =IFERROR(subQ!J5/subQ!E5-1,"") | L21: =IFERROR(subQ!L5/subQ!G5-1,"") | M21: =IFERROR(subQ!M5/subQ!H5-1,"") | N21: =IFERROR(subQ!N5/subQ!I5-1,"") | O21: =IFERROR(subQ!O5/subQ!J5-1,"") | Q21: =IFERROR(subQ!Q5/subQ!L5-1,"") | R21: =IFERROR(subQ!R5/subQ!M5-1,"") | S21: =IFERROR(subQ!S5/subQ!N5-1,"") | T21: =IFERROR(subQ!T5/subQ!O5-1,"") | V21: =IFERROR(subQ!V5/subQ!Q5-1,"") | W21: =IFERROR(subQ!W5/subQ!R5-1,"") | X21: =IFERROR(subQ!X5/subQ!S5-1,"") | Y21: =IFERROR(subQ!Y5/subQ!T5-1,"") | AA21: =IFERROR(subQ!AA5/subQ!V5-1,"") | AB21: =IFERROR(subQ!AB5/subQ!W5-1,"") | AC21: -0.052626817 | AD21: -0.052555226 | AF21: -0.052672213 | AG21: -0.052627799 | AH21: -0.026202399 | AI21: -0.026354863 | AK21: -0.026195426 | AL21: -0.026188835 | AM21: -0.013154748 | AN21: -0.013152878
A22: drv:판관비 | B22: ratio | C22: 판관비율(/매출) | E22: =IFERROR(subQ!E8/subQ!E5,"") | F22: =IFERROR(subQ!F8/subQ!F5,"") | G22: =IFERROR(subQ!G8/subQ!G5,"") | H22: =IFERROR(subQ!H8/subQ!H5,"") | I22: =IFERROR(subQ!I8/subQ!I5,"") | J22: =IFERROR(subQ!J8/subQ!J5,"") | K22: =IFERROR(subQ!K8/subQ!K5,"") | L22: =IFERROR(subQ!L8/subQ!L5,"") | ... AB22: =IFERROR(subQ!AB8/subQ!AB5,"") | AC22: =$D$52 | AD22: =$D$52 | AE22: =IFERROR(subQ!AE8/subQ!AE5,"") | AF22: =$D$52 | AG22: =$D$52 | AH22: =$D$52 | AI22: =$D$52 | AJ22: =IFERROR(subQ!AJ8/subQ!AJ5,"") | AK22: =$D$52 | AL22: =$D$52 | AM22: =$D$52 | AN22: =$D$52 | AO22: =IFERROR(subQ!AO8/subQ!AO5,"")
A23: drv:영업이익 | B23: ratio | C23: 영업이익률(OPM) | E23: =IFERROR(subQ!E9/subQ!E5,"") | F23: =IFERROR(subQ!F9/subQ!F5,"") | G23: =IFERROR(subQ!G9/subQ!G5,"") | H23: =IFERROR(subQ!H9/subQ!H5,"") | I23: =IFERROR(subQ!I9/subQ!I5,"") | J23: =IFERROR(subQ!J9/subQ!J5,"") | K23: =IFERROR(subQ!K9/subQ!K5,"") | L23: =IFERROR(subQ!L9/subQ!L5,"") | ... AB23: =IFERROR(subQ!AB9/subQ!AB5,"") | AC23: -0.058576919 | AD23: -0.05855605 | AE23: =IFERROR(subQ!AE9/subQ!AE5,"") | AF23: -0.058627859 | AG23: -0.058580289 | AH23: -0.058598421 | AI23: -0.058616088 | AJ23: =IFERROR(subQ!AJ9/subQ!AJ5,"") | AK23: -0.058497011 | AL23: -0.05856334 | AM23: -0.058531265 | AN23: -0.058624686 | AO23: =IFERROR(subQ!AO9/subQ!AO5,"")
A24: drv:외환손익 | B24: abs | C24: 외환손익 (가정, 억원) | E24: =subQ!E13 | F24: =subQ!F13 | G24: =subQ!G13 | H24: =subQ!H13 | I24: =subQ!I13 | J24: =subQ!J13 | K24: =subQ!K13 | L24: =subQ!L13 | ... AB24: =subQ!AB13 | AC24: 0 | AD24: 0 | AE24: =subQ!AE13 | AF24: 0 | AG24: 0 | AH24: 0 | AI24: 0 | AJ24: =subQ!AJ13 | AK24: 0 | AL24: 0 | AM24: 0 | AN24: 0 | AO24: =subQ!AO13
A25: drv:파생상품손익 | B25: abs | C25: 파생상품손익 (가정, 억원) | E25: =subQ!E14 | F25: =subQ!F14 | G25: =subQ!G14 | H25: =subQ!H14 | I25: =subQ!I14 | J25: =subQ!J14 | K25: =subQ!K14 | L25: =subQ!L14 | ... AB25: =subQ!AB14 | AC25: 0 | AD25: 0 | AE25: =subQ!AE14 | AF25: 0 | AG25: 0 | AH25: 0 | AI25: 0 | AJ25: =subQ!AJ14 | AK25: 0 | AL25: 0 | AM25: 0 | AN25: 0 | AO25: =subQ!AO14
A26: drv:기타금융손익 | B26: abs | C26: 기타금융손익 (가정, 억원) | E26: =subQ!E15 | F26: =subQ!F15 | G26: =subQ!G15 | H26: =subQ!H15 | I26: =subQ!I15 | J26: =subQ!J15 | K26: =subQ!K15 | L26: =subQ!L15 | ... AB26: =subQ!AB15 | AC26: 0 | AD26: 0 | AE26: =subQ!AE15 | AF26: 0 | AG26: 0 | AH26: 0 | AI26: 0 | AJ26: =subQ!AJ15 | AK26: 0 | AL26: 0 | AM26: 0 | AN26: 0 | AO26: =subQ!AO15
A27: drv:기타영업외손익 | B27: abs | C27: 기타영업외손익 (가정, 억원) | E27: =subQ!E16 | F27: =subQ!F16 | G27: =subQ!G16 | H27: =subQ!H16 | I27: =subQ!I16 | J27: =subQ!J16 | K27: =subQ!K16 | L27: =subQ!L16 | ... AB27: =subQ!AB16 | AC27: 0 | AD27: 0 | AE27: =subQ!AE16 | AF27: 0 | AG27: 0 | AH27: 0 | AI27: 0 | AJ27: =subQ!AJ16 | AK27: 0 | AL27: 0 | AM27: 0 | AN27: 0 | AO27: =subQ!AO16
A28: drv:지분법손익 | B28: abs | C28: 지분법손익 (가정, 억원) | E28: =subQ!E17 | F28: =subQ!F17 | G28: =subQ!G17 | H28: =subQ!H17 | I28: =subQ!I17 | J28: =subQ!J17 | K28: =subQ!K17 | L28: =subQ!L17 | ... AB28: =subQ!AB17 | AC28: -1.56 | AD28: -1.56 | AE28: =subQ!AE17 | AF28: -1.56 | AG28: -1.56 | AH28: -1.56 | AI28: -1.56 | AJ28: =subQ!AJ17 | AK28: -1.56 | AL28: -1.56 | AM28: -1.56 | AN28: -1.56 | AO28: =subQ!AO17
A29: drv:법인세비용 | B29: ratio | C29: 법인세율(/세전) | E29: =IFERROR(subQ!E19/subQ!E18,"") | F29: =IFERROR(subQ!F19/subQ!F18,"") | G29: =IFERROR(subQ!G19/subQ!G18,"") | H29: =IFERROR(subQ!H19/subQ!H18,"") | I29: =IFERROR(subQ!I19/subQ!I18,"") | J29: =IFERROR(subQ!J19/subQ!J18,"") | K29: =IFERROR(subQ!K19/subQ!K18,"") | L29: =IFERROR(subQ!L19/subQ!L18,"") | ... AB29: =IFERROR(subQ!AB19/subQ!AB18,"") | AC29: 0 | AD29: 0 | AE29: =IFERROR(subQ!AE19/subQ!AE18,"") | AF29: 0 | AG29: 0 | AH29: 0 | AI29: 0 | AJ29: =IFERROR(subQ!AJ19/subQ!AJ18,"") | AK29: 0 | AL29: 0 | AM29: 0 | AN29: 0 | AO29: =IFERROR(subQ!AO19/subQ!AO18,"")
A30: drv:지배주주순이익 | B30: ratio | C30: 지배주주 비중(/당기순이익) | E30: =IFERROR(subQ!E21/subQ!E20,"") | F30: =IFERROR(subQ!F21/subQ!F20,"") | G30: =IFERROR(subQ!G21/subQ!G20,"") | H30: =IFERROR(subQ!H21/subQ!H20,"") | I30: =IFERROR(subQ!I21/subQ!I20,"") | J30: =IFERROR(subQ!J21/subQ!J20,"") | K30: =IFERROR(subQ!K21/subQ!K20,"") | L30: =IFERROR(subQ!L21/subQ!L20,"") | ... AB30: =IFERROR(subQ!AB21/subQ!AB20,"") | AC30: =$D$53 | AD30: =$D$53 | AE30: =IFERROR(subQ!AE21/subQ!AE20,"") | AF30: =$D$53 | AG30: =$D$53 | AH30: =$D$53 | AI30: =$D$53 | AJ30: =IFERROR(subQ!AJ21/subQ!AJ20,"") | AK30: =$D$53 | AL30: =$D$53 | AM30: =$D$53 | AN30: =$D$53 | AO30: =IFERROR(subQ!AO21/subQ!AO20,"")
A31: drv:부채총계 | B31: qoq | C31: 부채총계 QoQ | G31: =IFERROR(subQ!G23/subQ!E23-1,"") | H31: =IFERROR(subQ!H23/subQ!G23-1,"") | I31: =IFERROR(subQ!I23/subQ!H23-1,"") | J31: =IFERROR(subQ!J23/subQ!I23-1,"") | L31: =IFERROR(subQ!L23/subQ!J23-1,"") | M31: =IFERROR(subQ!M23/subQ!L23-1,"") | N31: =IFERROR(subQ!N23/subQ!M23-1,"") | O31: =IFERROR(subQ!O23/subQ!N23-1,"") | Q31: =IFERROR(subQ!Q23/subQ!O23-1,"") | R31: =IFERROR(subQ!R23/subQ!Q23-1,"") | S31: =IFERROR(subQ!S23/subQ!R23-1,"") | T31: =IFERROR(subQ!T23/subQ!S23-1,"") | V31: =IFERROR(subQ!V23/subQ!T23-1,"") | W31: =IFERROR(subQ!W23/subQ!V23-1,"") | X31: =IFERROR(subQ!X23/subQ!W23-1,"") | Y31: =IFERROR(subQ!Y23/subQ!X23-1,"") | AA31: =IFERROR(subQ!AA23/subQ!Y23-1,"") | AB31: =IFERROR(subQ!AB23/subQ!AA23-1,"") | AC31: 1.1897e-05 | AD31: 0 | AF31: 0 | AG31: 0 | AH31: 0 | AI31: 0 | AK31: 0 | AL31: 0 | AM31: 0 | AN31: 0
A32: drv:자본총계 | B32: roll | C32: 자본총계 기타변동(배당 등, 억원) | G32: =IFERROR(subQ!E24+subQ!G20-subQ!G24,"") | H32: =IFERROR(subQ!G24+subQ!H20-subQ!H24,"") | I32: =IFERROR(subQ!H24+subQ!I20-subQ!I24,"") | J32: =IFERROR(subQ!I24+subQ!J20-subQ!J24,"") | L32: =IFERROR(subQ!J24+subQ!L20-subQ!L24,"") | M32: =IFERROR(subQ!L24+subQ!M20-subQ!M24,"") | N32: =IFERROR(subQ!M24+subQ!N20-subQ!N24,"") | O32: =IFERROR(subQ!N24+subQ!O20-subQ!O24,"") | Q32: =IFERROR(subQ!O24+subQ!Q20-subQ!Q24,"") | R32: =IFERROR(subQ!Q24+subQ!R20-subQ!R24,"") | S32: =IFERROR(subQ!R24+subQ!S20-subQ!S24,"") | T32: =IFERROR(subQ!S24+subQ!T20-subQ!T24,"") | V32: =IFERROR(subQ!T24+subQ!V20-subQ!V24,"") | W32: =IFERROR(subQ!V24+subQ!W20-subQ!W24,"") | X32: =IFERROR(subQ!W24+subQ!X20-subQ!X24,"") | Y32: =IFERROR(subQ!X24+subQ!Y20-subQ!Y24,"") | AA32: =IFERROR(subQ!Y24+subQ!AA20-subQ!AA24,"") | AB32: =IFERROR(subQ!AA24+subQ!AB20-subQ!AB24,"") | AC32: -0.001733679 | AD32: 0.000915974 | AF32: -0.010663679 | AG32: -0.003838192 | AH32: 0.00152974 | AI32: -0.0167947 | AK32: 0.001771422 | AL32: -0.001475992 | AM32: 0.00386763 | AN32: -0.014578286
A33: drv:지배주주지분 | B33: roll | C33: 지배주주지분 기타변동(배당 등, 억원) | G33: =IFERROR(subQ!E25+subQ!G21-subQ!G25,"") | H33: =IFERROR(subQ!G25+subQ!H21-subQ!H25,"") | I33: =IFERROR(subQ!H25+subQ!I21-subQ!I25,"") | J33: =IFERROR(subQ!I25+subQ!J21-subQ!J25,"") | L33: =IFERROR(subQ!J25+subQ!L21-subQ!L25,"") | M33: =IFERROR(subQ!L25+subQ!M21-subQ!M25,"") | N33: =IFERROR(subQ!M25+subQ!N21-subQ!N25,"") | O33: =IFERROR(subQ!N25+subQ!O21-subQ!O25,"") | Q33: =IFERROR(subQ!O25+subQ!Q21-subQ!Q25,"") | R33: =IFERROR(subQ!Q25+subQ!R21-subQ!R25,"") | S33: =IFERROR(subQ!R25+subQ!S21-subQ!S25,"") | T33: =IFERROR(subQ!S25+subQ!T21-subQ!T25,"") | V33: =IFERROR(subQ!T25+subQ!V21-subQ!V25,"") | W33: =IFERROR(subQ!V25+subQ!W21-subQ!W25,"") | X33: =IFERROR(subQ!W25+subQ!X21-subQ!X25,"") | Y33: =IFERROR(subQ!X25+subQ!Y21-subQ!Y25,"") | AA33: =IFERROR(subQ!Y25+subQ!AA21-subQ!AA25,"") | AB33: =IFERROR(subQ!AA25+subQ!AB21-subQ!AB25,"") | AC33: -0.001733679 | AD33: 0.000915974 | AF33: -0.010663679 | AG33: -0.003838192 | AH33: 0.00152974 | AI33: -0.0167947 | AK33: 0.001771422 | AL33: -0.001475992 | AM33: 0.00386763 | AN33: -0.014578286
A34: drv:총차입금 | B34: qoq | C34: 총차입금 QoQ | G34: =IFERROR(subQ!G26/subQ!E26-1,"") | H34: =IFERROR(subQ!H26/subQ!G26-1,"") | I34: =IFERROR(subQ!I26/subQ!H26-1,"") | J34: =IFERROR(subQ!J26/subQ!I26-1,"") | L34: =IFERROR(subQ!L26/subQ!J26-1,"") | M34: =IFERROR(subQ!M26/subQ!L26-1,"") | N34: =IFERROR(subQ!N26/subQ!M26-1,"") | O34: =IFERROR(subQ!O26/subQ!N26-1,"") | Q34: =IFERROR(subQ!Q26/subQ!O26-1,"") | R34: =IFERROR(subQ!R26/subQ!Q26-1,"") | S34: =IFERROR(subQ!S26/subQ!R26-1,"") | T34: =IFERROR(subQ!T26/subQ!S26-1,"") | V34: =IFERROR(subQ!V26/subQ!T26-1,"") | W34: =IFERROR(subQ!W26/subQ!V26-1,"") | X34: =IFERROR(subQ!X26/subQ!W26-1,"") | Y34: =IFERROR(subQ!Y26/subQ!X26-1,"") | AA34: =IFERROR(subQ!AA26/subQ!Y26-1,"") | AB34: =IFERROR(subQ!AB26/subQ!AA26-1,"") | AC34: -6.823e-06 | AD34: 0 | AF34: 0 | AG34: 0 | AH34: 0 | AI34: 0 | AK34: 0 | AL34: 0 | AM34: 0 | AN34: 0
A35: drv:순차입금 | B35: qoq | C35: 순차입금 QoQ | G35: =IFERROR(subQ!G27/subQ!E27-1,"") | H35: =IFERROR(subQ!H27/subQ!G27-1,"") | I35: =IFERROR(subQ!I27/subQ!H27-1,"") | J35: =IFERROR(subQ!J27/subQ!I27-1,"") | L35: =IFERROR(subQ!L27/subQ!J27-1,"") | M35: =IFERROR(subQ!M27/subQ!L27-1,"") | N35: =IFERROR(subQ!N27/subQ!M27-1,"") | O35: =IFERROR(subQ!O27/subQ!N27-1,"") | Q35: =IFERROR(subQ!Q27/subQ!O27-1,"") | R35: =IFERROR(subQ!R27/subQ!Q27-1,"") | S35: =IFERROR(subQ!S27/subQ!R27-1,"") | T35: =IFERROR(subQ!T27/subQ!S27-1,"") | V35: =IFERROR(subQ!V27/subQ!T27-1,"") | W35: =IFERROR(subQ!W27/subQ!V27-1,"") | X35: =IFERROR(subQ!X27/subQ!W27-1,"") | Y35: =IFERROR(subQ!Y27/subQ!X27-1,"") | AA35: =IFERROR(subQ!AA27/subQ!Y27-1,"") | AB35: =IFERROR(subQ!AB27/subQ!AA27-1,"") | AC35: 0.12064616 | AD35: 0.11960225 | AF35: 0.078453947 | AG35: 0.077321946 | AH35: 0.082531144 | AI35: 0.084608343 | AK35: 0.057692308 | AL35: 0.057908236 | AM35: 0.063035397 | AN35: 0.065734124
A36: drv:이자발생자산 | B36: qoq | C36: 이자발생자산 QoQ | G36: =IFERROR(subQ!G28/subQ!E28-1,"") | H36: =IFERROR(subQ!H28/subQ!G28-1,"") | I36: =IFERROR(subQ!I28/subQ!H28-1,"") | J36: =IFERROR(subQ!J28/subQ!I28-1,"") | L36: =IFERROR(subQ!L28/subQ!J28-1,"") | M36: =IFERROR(subQ!M28/subQ!L28-1,"") | N36: =IFERROR(subQ!N28/subQ!M28-1,"") | O36: =IFERROR(subQ!O28/subQ!N28-1,"") | Q36: =IFERROR(subQ!Q28/subQ!O28-1,"") | R36: =IFERROR(subQ!R28/subQ!Q28-1,"") | S36: =IFERROR(subQ!S28/subQ!R28-1,"") | T36: =IFERROR(subQ!T28/subQ!S28-1,"") | V36: =IFERROR(subQ!V28/subQ!T28-1,"") | W36: =IFERROR(subQ!W28/subQ!V28-1,"") | X36: =IFERROR(subQ!X28/subQ!W28-1,"") | Y36: =IFERROR(subQ!Y28/subQ!X28-1,"") | AA36: =IFERROR(subQ!AA28/subQ!Y28-1,"") | AB36: =IFERROR(subQ!AB28/subQ!AA28-1,"") | AC36: -1.0077619 | AD36: 144.44444 | AF36: 0.72880061 | AG36: 0.44807777 | AH36: 0.35581324 | AI36: 0.29124466 | AK36: 0.16681192 | AL36: 0.15162832 | AM36: 0.15190038 | AN36: 0.14605856
A37: drv:현금및현금성자산 | B37: qoq | C37: 현금및현금성자산 QoQ | G37: =IFERROR(subQ!G29/subQ!E29-1,"") | H37: =IFERROR(subQ!H29/subQ!G29-1,"") | I37: =IFERROR(subQ!I29/subQ!H29-1,"") | J37: =IFERROR(subQ!J29/subQ!I29-1,"") | L37: =IFERROR(subQ!L29/subQ!J29-1,"") | M37: =IFERROR(subQ!M29/subQ!L29-1,"") | N37: =IFERROR(subQ!N29/subQ!M29-1,"") | O37: =IFERROR(subQ!O29/subQ!N29-1,"") | Q37: =IFERROR(subQ!Q29/subQ!O29-1,"") | R37: =IFERROR(subQ!R29/subQ!Q29-1,"") | S37: =IFERROR(subQ!S29/subQ!R29-1,"") | T37: =IFERROR(subQ!T29/subQ!S29-1,"") | V37: =IFERROR(subQ!V29/subQ!T29-1,"") | W37: =IFERROR(subQ!W29/subQ!V29-1,"") | X37: =IFERROR(subQ!X29/subQ!W29-1,"") | Y37: =IFERROR(subQ!Y29/subQ!X29-1,"") | AA37: =IFERROR(subQ!AA29/subQ!Y29-1,"") | AB37: =IFERROR(subQ!AB29/subQ!AA29-1,"")
A38: drv:CAPEX | B38: yoy | C38: CAPEX YoY | J38: =IFERROR(subQ!J30/subQ!E30-1,"") | L38: =IFERROR(subQ!L30/subQ!G30-1,"") | M38: =IFERROR(subQ!M30/subQ!H30-1,"") | N38: =IFERROR(subQ!N30/subQ!I30-1,"") | O38: =IFERROR(subQ!O30/subQ!J30-1,"") | Q38: =IFERROR(subQ!Q30/subQ!L30-1,"") | R38: =IFERROR(subQ!R30/subQ!M30-1,"") | S38: =IFERROR(subQ!S30/subQ!N30-1,"") | T38: =IFERROR(subQ!T30/subQ!O30-1,"") | V38: =IFERROR(subQ!V30/subQ!Q30-1,"") | W38: =IFERROR(subQ!W30/subQ!R30-1,"") | X38: =IFERROR(subQ!X30/subQ!S30-1,"") | Y38: =IFERROR(subQ!Y30/subQ!T30-1,"") | AA38: =IFERROR(subQ!AA30/subQ!V30-1,"") | AB38: =IFERROR(subQ!AB30/subQ!W30-1,"") | AC38: 1.3255814 | AD38: -0.4 | AF38: 0 | AG38: 0 | AH38: 0 | AI38: 0 | AK38: 0 | AL38: 0 | AM38: 0 | AN38: 0
A39: drv:영업활동현금흐름 | B39: yoy | C39: 영업활동현금흐름 YoY | J39: =IFERROR(subQ!J31/subQ!E31-1,"") | L39: =IFERROR(subQ!L31/subQ!G31-1,"") | M39: =IFERROR(subQ!M31/subQ!H31-1,"") | N39: =IFERROR(subQ!N31/subQ!I31-1,"") | O39: =IFERROR(subQ!O31/subQ!J31-1,"") | Q39: =IFERROR(subQ!Q31/subQ!L31-1,"") | R39: =IFERROR(subQ!R31/subQ!M31-1,"") | S39: =IFERROR(subQ!S31/subQ!N31-1,"") | T39: =IFERROR(subQ!T31/subQ!O31-1,"") | V39: =IFERROR(subQ!V31/subQ!Q31-1,"") | W39: =IFERROR(subQ!W31/subQ!R31-1,"") | X39: =IFERROR(subQ!X31/subQ!S31-1,"") | Y39: =IFERROR(subQ!Y31/subQ!T31-1,"") | AA39: =IFERROR(subQ!AA31/subQ!V31-1,"") | AB39: =IFERROR(subQ!AB31/subQ!W31-1,"")
A40: drv:주식수 | B40: qoq | C40: 주식수 QoQ | G40: =IFERROR(subQ!G32/subQ!E32-1,"") | H40: =IFERROR(subQ!H32/subQ!G32-1,"") | I40: =IFERROR(subQ!I32/subQ!H32-1,"") | J40: =IFERROR(subQ!J32/subQ!I32-1,"") | L40: =IFERROR(subQ!L32/subQ!J32-1,"") | M40: =IFERROR(subQ!M32/subQ!L32-1,"") | N40: =IFERROR(subQ!N32/subQ!M32-1,"") | O40: =IFERROR(subQ!O32/subQ!N32-1,"") | Q40: =IFERROR(subQ!Q32/subQ!O32-1,"") | R40: =IFERROR(subQ!R32/subQ!Q32-1,"") | S40: =IFERROR(subQ!S32/subQ!R32-1,"") | T40: =IFERROR(subQ!T32/subQ!S32-1,"") | V40: =IFERROR(subQ!V32/subQ!T32-1,"") | W40: =IFERROR(subQ!W32/subQ!V32-1,"") | X40: =IFERROR(subQ!X32/subQ!W32-1,"") | Y40: =IFERROR(subQ!Y32/subQ!X32-1,"") | AA40: =IFERROR(subQ!AA32/subQ!Y32-1,"") | AB40: =IFERROR(subQ!AB32/subQ!AA32-1,"") | AC40: 0 | AD40: 0 | AF40: 0 | AG40: 0 | AH40: 0 | AI40: 0 | AK40: 0 | AL40: 0 | AM40: 0 | AN40: 0
A41: drv:DPS | B41: abs | C41: DPS (가정, 원) | E41: =subQ!E35 | F41: =subQ!F35 | G41: =subQ!G35 | H41: =subQ!H35 | I41: =subQ!I35 | J41: =subQ!J35 | K41: =subQ!K35 | L41: =subQ!L35 | ... AB41: =subQ!AB35 | AD41: 0 | AE41: =subQ!AE35 | AI41: 0 | AJ41: =subQ!AJ35 | AN41: 0 | AO41: =subQ!AO35
B43: 3. 밸류에이션·스칼라 | C43: 노란 셀 = 가정. '연결' 표시는 추정 전 분기 수식이 이 셀을 참조한다는 뜻
A44: sc:종가 | C44: 종가 | D44: 764 | E44: 원 — 네이버 정규장 종가(aik 확정종가 대조 · aik 764원)
A45: sc:기준일 | C45: 기준일 | D45: 20261013 | E45: 종가 기준일
A46: sc:COE | C46: COE | D46: 0.09 | E46: 자기자본비용(가정) — TP 적정 PBR = ROE/COE
A47: sc:PER_lo | C47: PER_lo | D47: 10 | E47: PER 밴드 하단(배) — sector_default(레퍼런스 TP_PE PB 예시 10/15/20배; 과거 양(+)EPS 분기 0개 < 4)
A48: sc:PER_mid | C48: PER_mid | D48: 15 | E48: PER 밴드 중단(배)
A49: sc:PER_hi | C49: PER_hi | D49: 20 | E49: PER 밴드 상단(배)
A50: sc:EPS_Y1가중 | C50: EPS_Y1가중 | D50: 0.5 | E50: 12M fwd EPS = FY(last_actual연도)E × w + FY+1E × (1−w) — 기준 분기 2Q 이면 0.5(가정)
A51: sc:세율 | C51: 세율 | D51: 0.22 | E51: 참고(연결 안 됨: MAX(세전,0)×단일 세율로 재현 불가(지주 자회사 합산 등) → 분기별 역산) — 모델 assumptions 값 · 최근 12분기 세전 합 ≤ 0; 세전 > 0 분기 중위 -22.7% 도 5~27% 밖 → 법정세율 근사 22% 가정
A52: sc:판관비율 | C52: 판관비율 | D52: 0.28180731 | E52: 연결 — 판관비 = 매출액 × 판관비율(역산, 재현 오차 ≤ 0.05억 · 모델 assumptions 0.2818)
A53: sc:지배주주비중 | C53: 지배주주비중 | D53: 1 | E53: 연결 — 지배주주순이익 = 당기순이익 × 비중(역산, 재현 오차 ≤ 0.05억)
A54: sc:이자율_자산 | C54: 이자율_자산 | D54: 0.0097167955 | E54: 연결 — 이자손익 = (전분기 이자발생자산 × 자산이자율 − 전분기 총차입금 × 부채이자율)/4(역산, 재현 오차 ≤ 0.05억 · 모델 assumptions 0.0097)
A55: sc:이자율_부채 | C55: 이자율_부채 | D55: 0.19995577 | E55: 연결 — 같은 수식의 부채 쪽(총차입금 행이 없으면 0)(역산, 재현 오차 ≤ 0.05억 · 모델 assumptions 0.2)
A56: sc:배당성향 | C56: 배당성향 | D56: 0 | E56: 배당성향(참고 — 모델은 직전 DPS 유지·Q2 지급 가정)
A57: sc:외화순노출_백만$ | C57: 외화순노출_백만$ | E57: 외화 순노출 × Δ기말환율 (외화 시트 방식) — 외화 순노출 미공시(face) → 0 + 표기
A58: sc:헤지비율 | C58: 헤지비율 | E58: sls 없음
A59: sc:헤지환율_약정 | C59: 헤지환율_약정 | E59: sls 없음

Sheet BS연결
B1: (백만원) | C1: 이름: BS연결H | E1: 4Q21 | F1: 2021 | G1: 1Q22 | H1: 2Q22 | I1: 3Q22 | J1: 4Q22 | K1: 2022 | L1: 1Q23 | M1: 2Q23 | N1: 3Q23 | O1: 4Q23 | P1: 2023 | Q1: 1Q24 | R1: 2Q24 | S1: 3Q24 | T1: 4Q24 | U1: 2024 | V1: 1Q25 | W1: 2Q25 | X1: 3Q25 | Y1: 4Q25 | Z1: 2025 | AA1: 1Q26 | AB1: 2Q26 | AC1: 3Q26 | AD1: 4Q26 | AE1: 2026 | AF1: 1Q27 | AG1: 2Q27 | AH1: 3Q27 | AI1: 4Q27 | AJ1: 2027 | AK1: 1Q28 | AL1: 2Q28 | AM1: 3Q28 | AN1: 4Q28 | AO1: 2028
B2: 연결 | D2: fin json(kship_fin.py)
B3: 삼영이엔씨(연) | C3: UPDATE: 26-10-13 | E3: 1 | F3: 2 | G3: 3 | H3: 4 | I3: 5 | J3: 6 | K3: 7 | L3: 8 | M3: 9 | N3: 10 | O3: 11 | P3: 12 | Q3: 13 | R3: 14 | S3: 15 | T3: 16 | U3: 17 | V3: 18 | W3: 19 | X3: 20 | Y3: 21 | Z3: 22 | AA3: 23 | AB3: 24 | AC3: 25 | AD3: 26 | AE3: 27 | AF3: 28 | AG3: 29 | AH3: 30 | AI3: 31 | AJ3: 32 | AK3: 33 | AL3: 34 | AM3: 35 | AN3: 36 | AO3: 37
B4: Account Code | C4: AccountNAME | E4: 2021.12 | F4: 2021.12A | G4: 2022.03 | H4: 2022.06 | I4: 2022.09 | J4: 2022.12 | K4: 2022.12A | L4: 2023.03 | M4: 2023.06 | N4: 2023.09 | O4: 2023.12 | P4: 2023.12A | Q4: 2024.03 | R4: 2024.06 | S4: 2024.09 | T4: 2024.12 | U4: 2024.12A | V4: 2025.03 | W4: 2025.06 | X4: 2025.09 | Y4: 2025.12 | Z4: 2025.12A | AA4: 2026.03 | AB4: 2026.06 | AC4: 2026.09 | AD4: 2026.12 | AE4: 2026.12A | AF4: 2027.03 | AG4: 2027.06 | AH4: 2027.09 | AI4: 2027.12 | AJ4: 2027.12A | AK4: 2028.03 | AL4: 2028.06 | AM4: 2028.09 | AN4: 2028.12 | AO4: 2028.12A

Sheet BS별도
B1: (백만원) | C1: 이름: BS별도H | E1: 4Q21 | F1: 2021 | G1: 1Q22 | H1: 2Q22 | I1: 3Q22 | J1: 4Q22 | K1: 2022 | L1: 1Q23 | M1: 2Q23 | N1: 3Q23 | O1: 4Q23 | P1: 2023 | Q1: 1Q24 | R1: 2Q24 | S1: 3Q24 | T1: 4Q24 | U1: 2024 | V1: 1Q25 | W1: 2Q25 | X1: 3Q25 | Y1: 4Q25 | Z1: 2025 | AA1: 1Q26 | AB1: 2Q26 | AC1: 3Q26 | AD1: 4Q26 | AE1: 2026 | AF1: 1Q27 | AG1: 2Q27 | AH1: 3Q27 | AI1: 4Q27 | AJ1: 2027 | AK1: 1Q28 | AL1: 2Q28 | AM1: 3Q28 | AN1: 4Q28 | AO1: 2028
B2: 별도 | D2: fin json(kship_fin.py)
B3: 삼영이엔씨(별) | C3: UPDATE: 26-10-13 | E3: 1 | F3: 2 | G3: 3 | H3: 4 | I3: 5 | J3: 6 | K3: 7 | L3: 8 | M3: 9 | N3: 10 | O3: 11 | P3: 12 | Q3: 13 | R3: 14 | S3: 15 | T3: 16 | U3: 17 | V3: 18 | W3: 19 | X3: 20 | Y3: 21 | Z3: 22 | AA3: 23 | AB3: 24 | AC3: 25 | AD3: 26 | AE3: 27 | AF3: 28 | AG3: 29 | AH3: 30 | AI3: 31 | AJ3: 32 | AK3: 33 | AL3: 34 | AM3: 35 | AN3: 36 | AO3: 37
B4: Account Code | C4: AccountNAME | E4: 2021.12 | F4: 2021.12A | G4: 2022.03 | H4: 2022.06 | I4: 2022.09 | J4: 2022.12 | K4: 2022.12A | L4: 2023.03 | M4: 2023.06 | N4: 2023.09 | O4: 2023.12 | P4: 2023.12A | Q4: 2024.03 | R4: 2024.06 | S4: 2024.09 | T4: 2024.12 | U4: 2024.12A | V4: 2025.03 | W4: 2025.06 | X4: 2025.09 | Y4: 2025.12 | Z4: 2025.12A | AA4: 2026.03 | AB4: 2026.06 | AC4: 2026.09 | AD4: 2026.12 | AE4: 2026.12A | AF4: 2027.03 | AG4: 2027.06 | AH4: 2027.09 | AI4: 2027.12 | AJ4: 2027.12A | AK4: 2028.03 | AL4: 2028.06 | AM4: 2028.09 | AN4: 2028.12 | AO4: 2028.12A
A5: 1 | C5: 유동자산 | E5: 62281.39 | F5: 62281.39 | G5: 80901.24 | H5: 73778.74 | I5: 79577.61 | J5: 64720.89 | K5: 64720.89 | L5: 64700.66 | M5: 66807.26 | N5: 62879.58 | O5: 54484.83 | P5: 54484.83 | Q5: 54432.28 | R5: 52974.55 | S5: 54590.82 | T5: 44111.58 | U5: 44111.58 | V5: 41646.44 | W5: 43118.86 | X5: 40751.98 | Y5: 36959.58 | Z5: 36959.58 | AA5: 34858.23 | AB5: 37970.07
A6: 1 | C6: 현금및현금성자산 | E6: 3262.24 | F6: 3262.24 | G6: 22756.68 | H6: 9371.92 | I6: 7191.81 | J6: 6875.32 | K6: 6875.32 | L6: 3578.17 | M6: 2142.94 | N6: 2802.85 | O6: 3317.17 | P6: 3317.17 | Q6: 974.26 | R6: 658.26 | S6: 4273.54 | T6: 7482.47 | U6: 7482.47 | V6: 646.28 | W6: 572.84 | X6: 789.46 | Y6: 1117.46 | Z6: 1117.46 | AA6: 593.46 | AB6: 568.34
A7: 1 | C7: 기타유동금융자산 | E7: 1678.13 | F7: 1678.13 | G7: 625.8 | H7: 1314.69 | Y7: 1414 | Z7: 1414 | AB7: 1000
A8: 1 | C8: 단기투자자산(공정가치) | E8: 4043.11 | F8: 4043.11 | G8: 3942.61 | H8: 7623.44 | I8: 9867.83 | J8: 7711.72 | K8: 7711.72 | L8: 10177.65 | M8: 8400.69 | N8: 6955.84 | O8: 5176.28 | P8: 5176.28 | Q8: 3768.64 | R8: 3851.56 | S8: 3751.94 | T8: 734.7 | U8: 734.7 | V8: 150.7 | W8: 150.7 | X8: 150.7 | Y8: 150.32 | Z8: 150.32 | AA8: 150.32 | AB8: 101.75
A9: 1 | C9: 매출채권및기타채권 | E9: 17284.85 | F9: 17284.85 | G9: 15820.32 | H9: 22147.71 | I9: 25909.71 | J9: 17623.81 | K9: 17623.81 | L9: 14204.16 | M9: 18231.9 | N9: 17169.52 | O9: 12757.62 | P9: 12757.62 | Q9: 11659.76 | R9: 13396.12 | S9: 10710.71 | T9: 9579.15 | U9: 9579.15 | V9: 8997.93 | W9: 8933.91 | X9: 8729.34 | Y9: 5984.8 | Z9: 5984.8 | AA9: 5662.36 | AB9: 6839.73
A10: 1 | C10: 재고자산 | E10: 29727.39 | F10: 29727.39 | G10: 33857.91 | H10: 30458.57 | I10: 31524.5 | J10: 27194.5 | K10: 27194.5 | L10: 28736.17 | M10: 28891.6 | N10: 31750.8 | O10: 30623.78 | P10: 30623.78 | Q10: 32407.28 | R10: 28686.44 | S10: 29195.99 | T10: 20542.16 | U10: 20542.16 | V10: 25141.99 | W10: 25457.01 | X10: 23863.06 | Y10: 19833.54 | Z10: 19833.54 | AA10: 20189.19 | AB10: 22318.37
A11: 1 | C11: 기타유동자산 | E11: 6275.45 | F11: 6275.45 | G11: 3885.23 | H11: 2858.85 | I11: 5054.11 | J11: 5261 | K11: 5261 | L11: 7949.84 | M11: 9139.95 | N11: 4200.35 | O11: 2609.66 | P11: 2609.66 | Q11: 5621.97 | R11: 6382.06 | S11: 6658.51 | T11: 5772.89 | U11: 5772.89 | V11: 6709.31 | W11: 8004.28 | X11: 7219.29 | Y11: 8459.29 | Z11: 8459.29 | AA11: 8262.62 | AB11: 7141.87
A12: 1 | C12: 당기법인세자산(선급법인세) | E12: 10.21 | F12: 10.21 | G12: 12.69 | H12: 3.57 | I12: 29.66 | J12: 54.53 | K12: 54.53 | L12: 54.66 | M12: 0.17 | N12: 0.22 | O12: 0.31 | P12: 0.31 | Q12: 0.36 | R12: 0.11 | S12: 0.13 | T12: 0.21 | U12: 0.21 | V12: 0.22 | W12: 0.12 | X12: 0.13 | Y12: 0.16 | Z12: 0.16 | AA12: 0.28 | AB12: 0.01
A13: 1 | C13: 비유동자산 | E13: 32831.98 | F13: 32831.98 | G13: 32959.05 | H13: 32421 | I13: 35018.89 | J13: 15492.79 | K13: 15492.79 | L13: 15019.65 | M13: 18899.26 | N13: 22440.47 | O13: 19162 | P13: 19162 | Q13: 19109.87 | R13: 19147.07 | S13: 19547.04 | T13: 10789.38 | U13: 10789.38 | V13: 10678.01 | W13: 10662.56 | X13: 3284.63 | Y13: 3298.31 | Z13: 3298.31 | AA13: 3391.54 | AB13: 3385.51
A14: 1 | C14: 장기금융자산 | E14: 504.63 | F14: 504.63 | G14: 520.9 | H14: 1456.08 | I14: 1560.23 | J14: 626.53 | K14: 626.53 | L14: 602.97 | M14: 3230.87 | N14: 3940.73 | O14: 1997.16 | P14: 1997.16 | Q14: 1522.69 | R14: 1474.97 | S14: 1476.44 | T14: 591.17 | U14: 591.17 | V14: 591.17 | W14: 591.17 | X14: 591.17 | Y14: 591.17 | Z14: 591.17 | AA14: 591.17 | AB14: 591.17
A15: 1 | C15: 투자자산 | E15: 504.63 | F15: 504.63 | G15: 520.9 | H15: 1966.38 | I15: 1749.2 | J15: 626.53 | K15: 626.53 | L15: 602.97 | M15: 3230.87 | N15: 3940.73 | O15: 1997.16 | P15: 1997.16 | Q15: 1522.69 | R15: 1474.97 | S15: 1476.44 | T15: 591.17 | U15: 591.17 | V15: 591.17 | W15: 591.17 | X15: 591.17 | Y15: 591.17 | Z15: 591.17 | AA15: 591.17 | AB15: 591.17
A16: 1 | C16: 유형자산 | E16: 16514.54 | F16: 16514.54 | G16: 16227.62 | H16: 15906.54 | I16: 15691.47 | J16: 10018.69 | K16: 10018.69 | L16: 9959.88 | M16: 9924.72 | N16: 10082.13 | O16: 10038.64 | P16: 10038.64 | Q16: 9996.8 | R16: 9981.52 | S16: 9976.4 | T16: 9875.17 | U16: 9875.17 | V16: 9845.43 | W16: 9774.2 | X16: 2343.11 | Y16: 2328.25 | Z16: 2328.25 | AA16: 2303.86 | AB16: 2279.47
A17: 1 | C17: 사용권자산 | E17: 402.41 | F17: 402.41 | G17: 347.75 | H17: 326.68 | I17: 561.06 | L17: 92.2 | M17: 172.7 | N17: 152.52 | O17: 143.76 | P17: 143.76 | Q17: 121.56 | R17: 99.36 | S17: 77.16
A18: 1 | C18: 기타비유동자산 | E18: 402.41 | F18: 402.41 | G18: 347.75 | H18: 326.68 | I18: 561.06 | L18: 92.2 | M18: 172.7 | N18: 152.52 | O18: 143.76 | P18: 143.76 | Q18: 121.56 | R18: 99.36 | S18: 77.16
A19: 1 | C19: 무형자산 | E19: 8059.53 | F19: 8059.53 | G19: 8394.45 | H19: 7918.42 | I19: 7792.02 | J19: 2613.08 | K19: 2613.08 | L19: 2000.18 | M19: 3315.14 | N19: 3161.24 | O19: 2263.7 | P19: 2263.7 | Q19: 2272.03 | R19: 2236.65 | S19: 2056.01
A20: 1 | C20: 이연법인세자산 | E20: 7137.26 | F20: 7137.26 | G20: 7058.81 | H20: 5892.58 | I20: 8709.82 | J20: 917.64 | K20: 917.64 | L20: 1126.51 | M20: 1042.63 | N20: 939.04 | O20: 849.9 | P20: 849.9 | Q20: 1232.89 | R20: 1403.35 | S20: 1649.05
A21: 1 | C21: 자산총계 | E21: 95113.37 | F21: 95113.37 | G21: 113860.29 | H21: 106199.75 | I21: 114596.5 | J21: 80213.68 | K21: 80213.68 | L21: 79720.31 | M21: 85706.53 | N21: 85320.05 | O21: 73646.83 | P21: 73646.83 | Q21: 73542.14 | R21: 72121.63 | S21: 74137.86 | T21: 54900.96 | U21: 54900.96 | V21: 52324.45 | W21: 53781.41 | X21: 44036.61 | Y21: 40257.89 | Z21: 40257.89 | AA21: 38249.76 | AB21: 41355.58
A22: 1 | C22: 유동부채 | E22: 19682.11 | F22: 19682.11 | G22: 18289.38 | H22: 19078.56 | I22: 23094.29 | J22: 23167.82 | K22: 23167.82 | L22: 25164.12 | M22: 47037.64 | N22: 38812.15 | O22: 35777.82 | P22: 35777.82 | Q22: 41814.72 | R22: 37952.24 | S22: 36602.22 | T22: 37788.96 | U22: 37788.96 | V22: 34035.58 | W22: 34377.27 | X22: 25336.9 | Y22: 22066.83 | Z22: 22066.83 | AA22: 20385.83 | AB22: 26857.66
A23: 1 | C23: 매입채무및기타채무 | E23: 4745.36 | F23: 4745.36 | G23: 3738.68 | H23: 4572.09 | I23: 4529.55 | J23: 3753.37 | K23: 3753.37 | L23: 5017.99 | M23: 8510.28 | N23: 6088.78 | O23: 3882.43 | P23: 3882.43 | Q23: 4819.12 | R23: 6069.93 | S23: 5573.16 | T23: 3973.13 | U23: 3973.13 | V23: 3843.16 | W23: 5123.68 | X23: 4877.97 | Y23: 3238.07 | Z23: 3238.07 | AA23: 3868.77 | AB23: 5092.4
A24: 1 | C24: 단기차입금 | E24: 13000 | F24: 13000 | G24: 13000 | H24: 13000 | I24: 15000 | J24: 15000 | K24: 15000 | L24: 15000 | M24: 15480.01 | N24: 13480.01 | O24: 12000 | P24: 12000 | Q24: 12000 | R24: 12000 | S24: 12900 | T24: 6000 | U24: 6000 | V24: 6299.95 | W24: 6260.09 | X24: 6260.09 | Y24: 6260.07 | Z24: 6260.07 | AA24: 6260.07 | AB24: 6260.07
A25: 1 | C25: 기타유동부채 | E25: 1745.98 | F25: 1745.98 | G25: 1379.99 | H25: 1347.89 | I25: 3313.51 | J25: 3863.05 | K25: 3863.05 | L25: 4640.38 | M25: 5067.6 | N25: 5923.36 | O25: 7414.95 | P25: 7414.95 | Q25: 8794.58 | R25: 7689.65 | S25: 7649.64 | T25: 12266.91 | U25: 12266.91 | V25: 12371.26 | W25: 11514.16 | X25: 9649.21 | Y25: 8504.99 | Z25: 8504.99 | AA25: 6195.06 | AB25: 7418.73
A26: 1 | C26: 비유동부채 | E26: 211.05 | F26: 211.05 | G26: 19673.16 | H26: 19200.72 | I26: 20013.91 | J26: 19992.67 | K26: 19992.67 | L26: 19664.34 | M26: 474.22 | N26: 4095.37 | O26: 4124.83 | P26: 4124.83 | Q26: 305.61 | R26: 258.31 | S26: 216.26 | T26: 682.23 | U26: 682.23 | V26: 335.45 | W26: 312.84 | X26: 280.83 | Y26: 83.06 | Z26: 83.06 | AA26: 52.02 | AB26: 39.02
A27: 1 | C27: 비유동리스부채 | E27: 211.05 | F27: 211.05 | G27: 177.47 | H27: 169.32 | I27: 307.32 | J27: 596.86 | K27: 596.86 | L27: 467.47 | M27: 474.22 | N27: 349.67 | O27: 355.64 | P27: 355.64 | Q27: 305.61 | R27: 258.31 | S27: 216.26 | T27: 201.92 | U27: 201.92 | V27: 61.92 | W27: 64.87 | X27: 54.85 | Y27: 28.17 | Z27: 28.17
A28: 1 | C28: 리스부채 | E28: 211.05 | F28: 211.05 | G28: 177.47 | H28: 169.32 | I28: 307.32 | J28: 596.86 | K28: 596.86 | L28: 467.47 | M28: 474.22 | N28: 349.67 | O28: 355.64 | P28: 355.64 | Q28: 305.61 | R28: 258.31 | S28: 216.26 | T28: 201.92 | U28: 201.92 | V28: 61.92 | W28: 64.87 | X28: 54.85 | Y28: 28.17 | Z28: 28.17
A29: 1 | C29: 장기금융부채 | E29: 211.05 | F29: 211.05 | G29: 5220.24 | H29: 4511.8 | I29: 5082.05 | J29: 5119.74 | K29: 5119.74 | L29: 5587.87 | M29: 474.22 | N29: 1527.1 | O29: 1481.92 | P29: 1481.92 | Q29: 305.61 | R29: 258.31 | S29: 216.26 | T29: 201.92 | U29: 201.92 | V29: 61.92 | W29: 64.87 | X29: 54.85 | Y29: 28.17 | Z29: 28.17
A30: 1 | C30: 부채총계 | E30: 19893.17 | F30: 19893.17 | G30: 37962.53 | H30: 38279.28 | I30: 43108.2 | J30: 43160.49 | K30: 43160.49 | L30: 44828.46 | M30: 47511.87 | N30: 42907.52 | O30: 39902.65 | P30: 39902.65 | Q30: 42120.33 | R30: 38210.55 | S30: 36818.48 | T30: 38471.19 | U30: 38471.19 | V30: 34371.03 | W30: 34690.12 | X30: 25617.73 | Y30: 22149.89 | Z30: 22149.89 | AA30: 20437.85 | AB30: 26896.68
A31: 1 | C31: 자본금 | E31: 5397.01 | F31: 5397.01 | G31: 5397.01 | H31: 5397.01 | I31: 5397.01 | J31: 5397.01 | K31: 5397.01 | L31: 5532.77 | M31: 5710.57 | N31: 6161.5 | O31: 6161.5 | P31: 6161.5 | Q31: 6341.5 | R31: 6680.31 | S31: 6806.69 | T31: 7962.32 | U31: 7962.32 | V31: 8046.92 | W31: 8046.92 | X31: 8046.92 | Y31: 8046.92 | Z31: 8046.92 | AA31: 8046.92 | AB31: 8046.92
A32: 1 | C32: 자본잉여금 | E32: 13943.45 | F32: 13943.45 | G32: 13943.45 | H32: 13943.45 | I32: 13943.45 | J32: 13943.45 | K32: 13943.45 | L32: 15499.41 | M32: 17866.21 | N32: 21735.79 | O32: 21735.79 | P32: 21735.79 | Q32: 22552.99 | R32: 26946.93 | S32: 28560.13 | T32: 30205.5 | U32: 30205.5 | V32: 30959.02 | W32: 30959.02 | X32: 30959.02 | Y32: 31102.9 | Z32: 31102.9 | AA32: 31102.9 | AB32: 31102.9
A33: 1 | C33: 기타자본 | E33: -4952.92 | F33: -4952.92 | G33: -1256.79 | H33: -860.32 | I33: -858.58 | J33: -1350.99 | K33: -1350.99 | L33: -1598.89 | M33: -1959.54 | N33: 3070.61 | O33: 3006.43 | P33: 3006.43 | Q33: 2871.19 | R33: 2378 | S33: 5143.58 | T33: 2251.77 | U33: 2251.77 | V33: 2251.77 | W33: 2251.77 | X33: 2251.77 | Y33: 2107.9 | Z33: 2107.9 | AA33: 2107.9 | AB33: 2107.9
A34: 1 | C34: 이익잉여금 | E34: 60832.67 | F34: 60832.67 | G34: 57814.09 | H34: 49440.34 | I34: 53006.43 | J34: 19063.73 | K34: 19063.73 | L34: 15458.56 | M34: 16577.41 | N34: 11444.63 | O34: 2840.46 | P34: 2840.46 | Q34: -343.86 | R34: -2094.16 | S34: -3191.02 | T34: -23989.82 | U34: -23989.82 | V34: -23304.3 | W34: -22166.42 | X34: -22838.84 | Y34: -23149.72 | Z34: -23149.72 | AA34: -23445.8 | AB34: -26798.81
A35: 1 | C35: 자본총계 | E35: 75220.2 | F35: 75220.2 | G35: 75897.76 | H35: 67920.47 | I35: 71488.3 | J35: 37053.19 | K35: 37053.19 | L35: 34891.85 | M35: 38194.66 | N35: 42412.54 | O35: 33744.18 | P35: 33744.18 | Q35: 31421.82 | R35: 33911.08 | S35: 37319.38 | T35: 16429.77 | U35: 16429.77 | V35: 17953.41 | W35: 19091.3 | X35: 18418.88 | Y35: 18108 | Z35: 18108 | AA35: 17811.92 | AB35: 14458.9
A36: 1 | C36: 부채와자본총계 | E36: 95113.37 | F36: 95113.37 | G36: 113860.29 | H36: 106199.75 | I36: 114596.5 | J36: 80213.68 | K36: 80213.68 | L36: 79720.31 | M36: 85706.53 | N36: 85320.05 | O36: 73646.83 | P36: 73646.83 | Q36: 73542.14 | R36: 72121.63 | S36: 74137.86 | T36: 54900.96 | U36: 54900.96 | V36: 52324.45 | W36: 53781.41 | X36: 44036.61 | Y36: 40257.89 | Z36: 40257.89 | AA36: 38249.76 | AB36: 41355.58
A37: 1 | C37: 지배주주지분 | E37: 75220.2 | F37: 75220.2 | G37: 75897.76 | H37: 67920.47 | I37: 71488.3 | J37: 37053.19 | K37: 37053.19 | L37: 34891.85 | M37: 38194.66 | N37: 42412.54 | O37: 33744.18 | P37: 33744.18 | Q37: 31421.82 | R37: 33911.08 | S37: 37319.38 | T37: 16429.77 | U37: 16429.77 | V37: 17953.41 | W37: 19091.3 | X37: 18418.88 | Y37: 18108 | Z37: 18108 | AA37: 17811.92 | AB37: 14458.9
A38: 1 | C38: 총차입금 | E38: 13000 | F38: 13000 | G38: 27452.92 | H38: 27688.92 | I38: 29931.86 | J38: 29872.93 | K38: 29872.93 | L38: 29076.47 | M38: 28263.44 | N38: 25414.44 | O38: 23698.5 | P38: 23698.5 | Q38: 23329.64 | R38: 20682.5 | S38: 20510.24 | T38: 19215.17 | U38: 19215.17 | V38: 16120.15 | W38: 16080.29 | X38: 9180.29 | Y38: 10260.07 | Z38: 10260.07 | AA38: 10260.07 | AB38: 10260.07
A39: 1 | C39: 순차입금 | E39: 9737.76 | F39: 9737.76 | G39: 4696.24 | H39: 18317 | I39: 22740.05 | J39: 22997.61 | K39: 22997.61 | L39: 25498.3 | M39: 26120.5 | N39: 22611.59 | O39: 20381.33 | P39: 20381.33 | Q39: 22355.38 | R39: 20024.24 | S39: 16236.7 | T39: 11732.7 | U39: 11732.7 | V39: 15473.87 | W39: 15507.45 | X39: 8390.83 | Y39: 9142.61 | Z39: 9142.61 | AA39: 9666.61 | AB39: 9691.73
A40: 1 | C40: 이자발생자산 | E40: 3766.87 | F40: 3766.87 | G40: 23277.58 | H40: 10828 | I40: 8752.04 | J40: 7501.85 | K40: 7501.85 | L40: 4181.14 | M40: 5373.81 | N40: 6743.58 | O40: 5314.33 | P40: 5314.33 | Q40: 2496.95 | R40: 2133.23 | S40: 5749.98 | T40: 8073.64 | U40: 8073.64 | V40: 1237.45 | W40: 1164.01 | X40: 1380.63 | Y40: 1708.63 | Z40: 1708.63 | AA40: 1184.63 | AB40: 1159.51
A41: 1 | C41: 사채 | G41: 14452.92 | H41: 14688.92 | I41: 14931.86 | J41: 14872.93 | K41: 14872.93 | L41: 14076.47 | N41: 2568.26 | O41: 2642.91 | P41: 2642.91
A42: 1 | C42: 기타비유동금융부채 | G42: 5042.77 | H42: 4342.48 | I42: 4774.73 | J42: 4522.88 | K42: 4522.88 | L42: 5120.4 | N42: 1177.43 | O42: 1126.28 | P42: 1126.28
A43: 1 | C43: 종속기업및관계기업투자 | H43: 510.3 | I43: 188.97
A44: 1 | C44: 유동성장기부채 | M44: 12783.43 | N44: 9366.17 | O44: 9055.59 | P44: 9055.59 | Q44: 11329.64 | R44: 8682.5 | S44: 7610.24 | T44: 13215.17 | U44: 13215.17 | V44: 9820.2 | W44: 9820.2 | X44: 2920.2 | Y44: 4000 | Z44: 4000 | AA44: 4000 | AB44: 4000
A45: 1 | C45: 기타유동금융부채 | M45: 4735.96 | N45: 3502.03 | O45: 3158.89 | P45: 3158.89 | Q45: 4627.21 | R45: 3286.74 | S45: 2667.17 | T45: 2117.49 | U45: 2117.49 | V45: 1557.7 | W45: 1557.7 | X45: 1557.7
A46: 1 | C46: 단기금융부채 | M46: 4735.96 | N46: 3502.03 | O46: 3158.89 | P46: 3158.89 | Q46: 4627.21 | R46: 3286.74 | S46: 2667.17 | T46: 2117.49 | U46: 2117.49 | V46: 1557.7 | W46: 1557.7 | X46: 1557.7
A47: 1 | C47: 이연법인세부채 | T47: 480.31 | U47: 480.31 | V47: 273.53 | W47: 247.97 | X47: 225.98 | Y47: 54.88 | Z47: 54.88 | AA47: 52.02 | AB47: 39.02
A48: 1 | C48: 단기충당부채 | AB48: 4054.14
A49: 1 | C49: 매출액(수익) | E49: 15992.82 | G49: 4569.65 | H49: 8246.5 | I49: 7589.99 | J49: 11495.23 | K49: 31901.37 | L49: 7540.52 | M49: 9567.4 | N49: 7685.73 | O49: 8544.6 | P49: 33338.25 | Q49: 5822.19 | R49: 9706.65 | S49: 6533.29 | T49: 14040.92 | U49: 36103.05 | V49: 4706.32 | W49: 8117.38 | X49: 9064.01 | Y49: 11373.75 | Z49: 33261.46 | AA49: 5077.44 | AB49: 6126.42
A50: 1 | C50: 매출원가 | E50: 10554.05 | G50: 3574.72 | H50: 11168.49 | I50: 5015.79 | J50: 10808.07 | K50: 30567.07 | L50: 4889.14 | M50: 6703.75 | N50: 5176.88 | O50: 6821.12 | P50: 23590.89 | Q50: 3978.9 | R50: 7923.34 | S50: 3995.63 | T50: 13327.8 | U50: 29225.67 | V50: 3359.8 | W50: 4269.58 | X50: 6988.31 | Y50: 8318.7 | Z50: 22936.39 | AA50: 3565.04 | AB50: 3536.03
A51: 1 | C51: 매출총이익 | E51: 5438.78 | G51: 994.93 | H51: -2922 | I51: 2574.2 | J51: 687.16 | K51: 1334.29 | L51: 2651.37 | M51: 2863.65 | N51: 2508.86 | O51: 1723.49 | P51: 9747.37 | Q51: 1843.3 | R51: 1783.31 | S51: 2537.66 | T51: 713.12 | U51: 6877.39 | V51: 1346.52 | W51: 3847.79 | X51: 2075.7 | Y51: 3055.05 | Z51: 10325.06 | AA51: 1512.4 | AB51: 2590.4
A52: 1 | C52: 판관비 | E52: 1361.37 | G52: 4494.17 | H52: 3930.82 | I52: 4023.12 | J52: 9032.03 | K52: 21480.14 | L52: 5275.42 | M52: 3031.56 | N52: 3908.65 | O52: 3657.36 | P52: 15872.99 | Q52: 3107.13 | R52: 3395.24 | S52: 3330.07 | T52: 2978.16 | U52: 12810.6 | V52: 2671.92 | W52: 2418.58 | X52: 2561.98 | Y52: 2867.2 | Z52: 10519.68 | AA52: 1834.9 | AB52: 1720.99
A53: 1 | C53: 영업이익 | E53: 4077.41 | G53: -3499.24 | H53: -6852.81 | I53: -1448.93 | J53: -8344.87 | K53: -20145.85 | L53: -2624.05 | M53: -167.9 | N53: -1399.79 | O53: -1933.87 | P53: -6125.61 | Q53: -1263.84 | R53: -1611.93 | S53: -792.41 | T53: -2265.03 | U53: -5933.21 | V53: -1325.4 | W53: 1429.21 | X53: -486.28 | Y53: 187.86 | Z53: -194.61 | AA53: -322.5 | AB53: 869.4
A54: 1 | C54: 금융수익 | E54: 135.5 | G54: 451.19 | H54: 1030.91 | I54: 2235.09 | J54: -1997.64 | K54: 1719.55 | L54: 307.21 | M54: 1976.82 | N54: 47.96 | O54: 247.79 | P54: 2579.78 | Q54: 639.72 | R54: 123.26 | S54: -179.94 | T54: 1220.56 | U54: 1803.6 | V54: 3328.58 | W54: 408.16 | X54: 6.04 | Y54: 1393.91 | Z54: 5136.69 | AA54: 168.79 | AB54: 132.21
A55: 1 | C55: 금융비용 | E55: 143.09 | G55: 927.32 | H55: 1417.39 | I55: -151.1 | J55: 2738.69 | K55: 4932.3 | L55: 1752.91 | M55: 475.08 | N55: 644.91 | O55: 4435.63 | P55: 7308.53 | Q55: 2932.81 | R55: 346.58 | S55: 346.29 | T55: 4421.62 | U55: 8047.3 | V55: 1697.88 | W55: 727.8 | X55: 179.64 | Y55: 1868.94 | Z55: 4474.26 | AA55: 147.48 | AB55: 153.88
A56: 1 | C56: 기타영업외수익 | E56: 17.09 | G56: 17.54 | H56: 63.54 | I56: 20.87 | J56: 98.1 | K56: 200.05 | L56: 327.37 | M56: 1289.18 | N56: 201.84 | O56: 167.07 | P56: 1985.46 | Q56: 29.39 | R56: 45.02 | S56: 38.17 | T56: 21.23 | U56: 133.81 | V56: 195.6 | W56: 3.8 | X56: 911.43 | Y56: 33.72 | Z56: 1144.55 | AA56: 11.97 | AB56: 52.59
A57: 1 | C57: 기타영업외비용 | E57: 3056.13 | G57: 24.8 | H57: 42.08 | I57: 0.27 | J57: 13281.12 | K57: 13348.27 | L57: 0.4 | M57: 1324.99 | N57: 2815.75 | O57: 2543.43 | P57: 6684.57 | Q57: 4.05 | R57: 0.22 | S57: 0.13 | T57: 13253.2 | U57: 13257.6 | V57: 22.18 | W57: 1.04 | X57: 945.96 | Y57: 228.52 | Z57: 1197.7 | AA57: 9.72 | AB57: 4266.32
A58: 1 | C58: 법인세비용차감전계속사업이익 | E58: 1030.76 | G58: -3982.62 | H58: -7207.53 | I58: 636.53 | J58: -25953.17 | K58: -36506.79 | L58: -3742.78 | M58: 1298.02 | N58: -4610.66 | O58: -8498.07 | P58: -15553.49 | Q58: -3531.58 | R58: -1790.44 | S58: -1280.6 | T58: -18698.05 | U58: -25300.67 | V58: 478.73 | W58: 1112.33 | X58: -694.41 | Y58: -481.98 | Z58: 414.67 | AA58: -298.95 | AB58: -3366.01
A59: 1 | C59: 법인세비용 | E59: -293.39 | G59: -964.04 | H59: 1166.22 | I59: -2929.55 | J59: 7989.52 | K59: 5262.15 | L59: -137.61 | M59: 179.18 | N59: 522.12 | O59: 106.1 | P59: 669.79 | Q59: -347.26 | R59: -40.14 | S59: -183.74 | T59: 2100.75 | U59: 1529.61 | V59: -206.79 | W59: -25.55 | X59: -21.99 | Y59: -171.1 | Z59: -425.43 | AA59: -2.87 | AB59: -13
A60: 1 | C60: 당기순이익 | E60: 1324.15 | G60: -3018.58 | H60: -8373.76 | I60: 3566.09 | J60: -33942.7 | K60: -41768.95 | L60: -3605.17 | M60: 1118.85 | N60: -5132.78 | O60: -8604.17 | P60: -16223.27 | Q60: -3184.32 | R60: -1750.3 | S60: -1096.86 | T60: -20798.8 | U60: -26830.28 | V60: 685.52 | W60: 1137.88 | X60: -672.42 | Y60: -310.88 | Z60: 840.1 | AA60: -296.08 | AB60: -3353.01
... A65: 1 | C65: 계속사업이익 | E65: 1324.15 | G65: -3018.58 | H65: -8373.76 | I65: 3566.09 | J65: -33942.7 | K65: -41768.95 | L65: -3605.17 | M65: 1118.85 | N65: -5132.78 | O65: -8604.17 | P65: -16223.27 | Q65: -3184.32 | R65: -1750.3 | S65: -1096.86 | T65: -20798.8 | U65: -26830.28 | V65: 685.52 | W65: 1137.88 | X65: -672.42 | Y65: -310.88 | Z65: 840.1 | AA65: -296.08 | AB65: -3353.01
A66: 1 | C66: 종속기업,공동지배기업및관계기업관련손익 | H66: 10.3 | I66: -321.33
A67: 1 | C67: 지분법관련손익 | H67: 10.3 | I67: -321.33
A68: 1 | C68: 이자수익 | X68: 0.88 | Y68: 5.8 | AA68: 1.92 | AB68: 4.55
A69: 1 | C69: 이자비용 | X69: 288 | Y69: 1914.89 | AA69: 132.5 | AB69: 133.69
A70: 1 | C70: 외환차익 | X70: 19.19 | Y70: -153.11 | AA70: 104.58 | AB70: 106.13
A71: 1 | C71: 외환차손 | X71: 91.37 | Y71: 29.58 | AA71: 14.98 | AB71: 20
A72: 1 | C72: 외화환산이익 | X72: -14.03 | Y72: -16.49 | AA72: 62.28 | AB72: 21.53
A73: 1 | C73: 외화환산손실 | X73: -199.74 | Y73: -75.9
A74: 1 | C74: 파생상품이익 | X74: 0 | Y74: 1557.71
A75: 1 | C75: 파생상품손실 | X75: 0 | Y75: 0.38
A76: 1 | C76: 이자손익 | X76: -287.12 | Y76: -1909.09 | AA76: -130.58 | AB76: -129.14
A77: 1 | C77: 영업활동으로인한현금흐름 | E77: 4625.11 | G77: -1876.93 | H77: -2471.7 | I77: -532.79 | J77: -2334.32 | K77: -7215.74 | L77: -3330.42 | M77: -1598.54 | N77: -2786.54 | O77: 3183.91 | P77: -4531.59 | Q77: -1886.85 | R77: 2705.29 | S77: 217.11 | T77: 2685.66 | U77: 3721.21 | V77: -6821.69 | W77: 53.31 | X77: -289.94 | Y77: 456.12 | Z77: -6602.2 | AA77: -383.07 | AB77: -30.94
A78: 1 | C78: 이자수취(CF) | E78: 46.44 | G78: 28.85 | H78: 77.87 | I78: 116.82 | J78: 276.14 | K78: 499.68 | L78: 47.76 | M78: 24.75 | N78: 24.57 | O78: 20.23 | P78: 117.31 | Q78: 20.18 | R78: 19.49 | S78: 14.91 | T78: 15.57 | U78: 70.15 | V78: 15.14 | W78: 4 | X78: -16.93 | Y78: 22.62 | Z78: 24.83 | AA78: 0.77 | AB78: 0.78
A79: 1 | C79: 이자지급(CF) | E79: -78.47 | G79: -94.19 | H79: -109.72 | I79: -120.12 | J79: -161.65 | K79: -485.68 | L79: -182.17 | M79: -203.87 | Q79: -148.93 | V79: -190.83 | AA79: 99.49
A80: 1 | C80: 법인세납부(CF) | E80: -0.44 | G80: -2.48 | H80: 9.12 | I80: -26.09 | J80: -24.87 | K80: -44.32 | L80: -0.13 | M80: 54.49 | N80: -0.05 | O80: -0.09 | P80: 54.22 | Q80: -0.05 | R80: 0.25 | S80: -0.04 | T80: 28.53 | U80: 28.69 | V80: -0.02 | W80: 0.1 | X80: -0.01 | Y80: -0.03 | Z80: 0.04 | AA80: -0.12 | AB80: 0.27
A81: 1 | C81: 투자활동으로인한현금흐름 | E81: -5301.6 | G81: 1371.72 | H81: -11226.16 | I81: -3996.09 | J81: 3153.04 | K81: -10697.49 | L81: 177.93 | M81: -172.31 | N81: -1466.45 | O81: -564.15 | P81: -2024.98 | Q81: -626.96 | R81: -2950.89 | S81: -230.2 | T81: 2905 | U81: -903.05 | V81: 249.77 | W81: -44.3 | X81: 7442.68 | Y81: -1498.61 | Z81: 6149.54 | AA81: 1301.95 | AB81: -963.01
A82: 1 | C82: 유형자산의증가 | E82: 19.16 | G82: 27.25 | H82: 7.76 | I82: 93.9 | J82: 132.05 | K82: 260.96 | L82: 10.84 | M82: 35.62 | N82: 233.64 | O82: 116.45 | P82: 396.55 | Q82: 38.48 | R82: 68.63 | S82: 80 | T82: 3.5 | U82: 190.61 | V82: 41.5 | W82: 0 | X82: 2.58 | Y82: 10 | Z82: 54.08
A83: 1 | C83: CAPEX | E83: 1432.03 | G83: 708.43 | H83: 154.6 | I83: 637.5 | J83: 1113.31 | K83: 2613.84 | L83: 10.84 | M83: 1504.48 | N83: 233.64 | O83: 540.54 | P83: 2289.5 | Q83: 194.91 | R83: 181.35 | S83: 80 | T83: 3.5 | U83: 459.76 | V83: 41.5 | W83: 0 | X83: 2.58 | Y83: 10 | Z83: 54.08
A84: 1 | C84: 유형자산의감소 | E84: 0 | N84: 0 | O84: 0 | S84: 0 | V84: 32.36 | W84: 0 | X84: 7489.73 | Y84: 0 | Z84: 7522.09
A85: 1 | C85: 무형자산의증가 | E85: 1412.87 | G85: 681.18 | H85: 146.84 | I85: 543.6 | J85: 981.26 | K85: 2352.88 | N85: 0 | O85: 424.09 | Q85: 156.43 | R85: 112.72 | S85: 0 | T85: 0 | U85: 269.15
A86: 1 | C86: 재무활동으로인한현금흐름 | E86: -1623.97 | G86: 20004.16 | H86: 287.5 | I86: 2305.42 | J86: -1048.98 | K86: 21548.1 | L86: -144.39 | M86: 334.27 | N86: 4913.08 | O86: -2100.99 | P86: 3001.97 | Q86: 170.82 | R86: -72.07 | S86: 3633.04 | T86: -2386.55 | U86: 1345.24 | V86: -264.66 | W86: -80.5 | X86: -6938.14 | Y86: 1378.16 | Z86: -5905.14 | AA86: -1444.78 | AB86: 969.86
A87: 1 | C87: 단기차입금의증가 | E87: 0 | I87: 11000 | J87: 0 | N87: 0 | O87: 0 | V87: 400 | W87: 0 | X87: 0 | Y87: 0 | Z87: 400
A88: 1 | C88: 리스부채의상환 | E88: 55.49 | G88: 55.37 | H88: 53.58 | I88: 84.87 | J88: 258.08 | K88: 451.9 | L88: 144.39 | M88: 145.73 | N88: 139.67 | O88: 104.35 | P88: 534.14 | Q88: 76.38 | R88: 72.07 | S88: 66.97 | T88: 71.54 | U88: 286.96 | V88: 64.61 | W88: 40.64 | X88: 38.14 | Y88: 35.82 | Z88: 179.21 | AA88: 30.78 | AB88: 30.14
A89: 1 | C89: 자기주식의취득 | E89: 2029.9
A90: 1 | C90: 배당금지급 | E90: 0
A91: 1 | C91: 현금및현금성자산의증감 | E91: -2306.01 | G91: 19494.43 | H91: -13384.75 | I91: -2180.11 | J91: -316.49 | K91: 3613.08 | L91: -3297.15 | M91: -1435.23 | N91: 659.91 | O91: 514.32 | P91: -3558.15 | Q91: -2342.92 | R91: -316 | S91: 3615.28 | T91: 3208.94 | U91: 4165.3 | V91: -6836.19 | W91: -73.44 | X91: 216.61 | Y91: 328.01 | Z91: -6365.01 | AA91: -524.01 | AB91: -25.11
A92: 1 | C92: 기말현금및현금성자산 | E92: -2306.02 | G92: 22756.68 | H92: -13384.76 | I92: -2180.11 | J92: -316.49 | K92: 6875.32 | L92: 3578.17 | M92: -1435.23 | N92: 659.91 | O92: 514.32 | P92: 3317.17 | Q92: 974.26 | R92: -316 | S92: 3615.28 | T92: 3208.93 | U92: 7482.47 | V92: 646.28 | W92: -73.44 | X92: 216.62 | Y92: 328 | Z92: 1117.46 | AA92: 593.46 | AB92: -25.12
A93: 1 | C93: 단기차입금의감소 | I93: 9000 | J93: 0 | N93: 2000 | O93: 1480.01 | V93: 100.05 | W93: 39.86 | X93: 0 | Y93: 0.02 | Z93: 139.93
A94: 1 | C94: 무형자산의감소 | L94: 509.09 | M94: 0 | N94: 0 | O94: 0 | P94: 509.09
A95: 1 | C95: 유동성장기부채의감소 | Y95: 0

Sheet subQ
A1: YQ | C1: subQ 분기 서브모델(억원, U=100) | E1: 4Q21 | F1: 2021 | G1: 1Q22 | H1: 2Q22 | I1: 3Q22 | J1: 4Q22 | K1: 2022 | L1: 1Q23 | M1: 2Q23 | N1: 3Q23 | O1: 4Q23 | P1: 2023 | Q1: 1Q24 | R1: 2Q24 | S1: 3Q24 | T1: 4Q24 | U1: 2024 | V1: 1Q25 | W1: 2Q25 | X1: 3Q25 | Y1: 4Q25 | Z1: 2025 | AA1: 1Q26 | AB1: 2Q26 | AC1: 3Q26 | AD1: 4Q26 | AE1: 2026 | AF1: 1Q27 | AG1: 2Q27 | AH1: 3Q27 | AI1: 4Q27 | AJ1: 2027 | AK1: 1Q28 | AL1: 2Q28 | AM1: 3Q28 | AN1: 4Q28 | AO1: 2028
A2: A=이름(key) B=그룹 C=단위 D=FnGuide 계정명(VLOOKUP 키). 확정=VLOOKUP(BS), 추정=변수 가정 참조
E3: 1 | F3: 2 | G3: 3 | H3: 4 | I3: 5 | J3: 6 | K3: 7 | L3: 8 | M3: 9 | N3: 10 | O3: 11 | P3: 12 | Q3: 13 | R3: 14 | S3: 15 | T3: 16 | U3: 17 | V3: 18 | W3: 19 | X3: 20 | Y3: 21 | Z3: 22 | AA3: 23 | AB3: 24 | AC3: 25 | AD3: 26 | AE3: 27 | AF3: 28 | AG3: 29 | AH3: 30 | AI3: 31 | AJ3: 32 | AK3: 33 | AL3: 34 | AM3: 35 | AN3: 36 | AO3: 37
E4: 2021.12 | F4: 2021.12A | G4: 2022.03 | H4: 2022.06 | I4: 2022.09 | J4: 2022.12 | K4: 2022.12A | L4: 2023.03 | M4: 2023.06 | N4: 2023.09 | O4: 2023.12 | P4: 2023.12A | Q4: 2024.03 | R4: 2024.06 | S4: 2024.09 | T4: 2024.12 | U4: 2024.12A | V4: 2025.03 | W4: 2025.06 | X4: 2025.09 | Y4: 2025.12 | Z4: 2025.12A | AA4: 2026.03 | AB4: 2026.06 | AC4: 2026.09 | AD4: 2026.12 | AE4: 2026.12A | AF4: 2027.03 | AG4: 2027.06 | AH4: 2027.09 | AI4: 2027.12 | AJ4: 2027.12A | AK4: 2028.03 | AL4: 2028.06 | AM4: 2028.09 | AN4: 2028.12 | AO4: 2028.12A
A5: 매출액 | B5: 손익 | C5: 억원 | D5: 매출액(수익) | E5: =IFERROR(VLOOKUP($D5,BS별도,MATCH(E$1,BS별도H,0),0)/100,"") | G5: =IFERROR(VLOOKUP($D5,BS별도,MATCH(G$1,BS별도H,0),0)/100,"") | H5: =IFERROR(VLOOKUP($D5,BS별도,MATCH(H$1,BS별도H,0),0)/100,"") | I5: =IFERROR(VLOOKUP($D5,BS별도,MATCH(I$1,BS별도H,0),0)/100,"") | J5: =IFERROR(VLOOKUP($D5,BS별도,MATCH(J$1,BS별도H,0),0)/100,"") | K5: =SUM(G5:J5) | L5: =IFERROR(VLOOKUP($D5,BS별도,MATCH(L$1,BS별도H,0),0)/100,"") | M5: =IFERROR(VLOOKUP($D5,BS별도,MATCH(M$1,BS별도H,0),0)/100,"") | N5: =IFERROR(VLOOKUP($D5,BS별도,MATCH(N$1,BS별도H,0),0)/100,"") | O5: =IFERROR(VLOOKUP($D5,BS별도,MATCH(O$1,BS별도H,0),0)/100,"") | P5: =SUM(L5:O5) | Q5: =IFERROR(VLOOKUP($D5,BS별도,MATCH(Q$1,BS별도H,0),0)/100,"") | R5: =IFERROR(VLOOKUP($D5,BS별도,MATCH(R$1,BS별도H,0),0)/100,"") | S5: =IFERROR(VLOOKUP($D5,BS별도,MATCH(S$1,BS별도H,0),0)/100,"") | T5: =IFERROR(VLOOKUP($D5,BS별도,MATCH(T$1,BS별도H,0),0)/100,"") | U5: =SUM(Q5:T5) | V5: =IFERROR(VLOOKUP($D5,BS별도,MATCH(V$1,BS별도H,0),0)/100,"") | W5: =IFERROR(VLOOKUP($D5,BS별도,MATCH(W$1,BS별도H,0),0)/100,"") | X5: =IFERROR(VLOOKUP($D5,BS별도,MATCH(X$1,BS별도H,0),0)/100,"") | Y5: =IFERROR(VLOOKUP($D5,BS별도,MATCH(Y$1,BS별도H,0),0)/100,"") | Z5: =SUM(V5:Y5) | AA5: =IFERROR(VLOOKUP($D5,BS별도,MATCH(AA$1,BS별도H,0),0)/100,"") | AB5: =IFERROR(VLOOKUP($D5,BS별도,MATCH(AB$1,BS별도H,0),0)/100,"") | AC5: =IFERROR(X5*(1+변수!AC21),"") | AD5: =IFERROR(Y5*(1+변수!AD21),"") | AE5: =SUM(AA5:AD5) | AF5: =IFERROR(AA5*(1+변수!AF21),"") | AG5: =IFERROR(AB5*(1+변수!AG21),"") | AH5: =IFERROR(AC5*(1+변수!AH21),"") | AI5: =IFERROR(AD5*(1+변수!AI21),"") | AJ5: =SUM(AF5:AI5) | AK5: =IFERROR(AF5*(1+변수!AK21),"") | AL5: =IFERROR(AG5*(1+변수!AL21),"") | AM5: =IFERROR(AH5*(1+변수!AM21),"") | AN5: =IFERROR(AI5*(1+변수!AN21),"") | AO5: =SUM(AK5:AN5)
A6: 매출원가 | B6: 손익 | C6: 억원 | D6: 매출원가 | E6: =IFERROR(VLOOKUP($D6,BS별도,MATCH(E$1,BS별도H,0),0)/100,"") | G6: =IFERROR(VLOOKUP($D6,BS별도,MATCH(G$1,BS별도H,0),0)/100,"") | H6: =IFERROR(VLOOKUP($D6,BS별도,MATCH(H$1,BS별도H,0),0)/100,"") | I6: =IFERROR(VLOOKUP($D6,BS별도,MATCH(I$1,BS별도H,0),0)/100,"") | J6: =IFERROR(VLOOKUP($D6,BS별도,MATCH(J$1,BS별도H,0),0)/100,"") | K6: =SUM(G6:J6) | L6: =IFERROR(VLOOKUP($D6,BS별도,MATCH(L$1,BS별도H,0),0)/100,"") | M6: =IFERROR(VLOOKUP($D6,BS별도,MATCH(M$1,BS별도H,0),0)/100,"") | N6: =IFERROR(VLOOKUP($D6,BS별도,MATCH(N$1,BS별도H,0),0)/100,"") | O6: =IFERROR(VLOOKUP($D6,BS별도,MATCH(O$1,BS별도H,0),0)/100,"") | P6: =SUM(L6:O6) | Q6: =IFERROR(VLOOKUP($D6,BS별도,MATCH(Q$1,BS별도H,0),0)/100,"") | R6: =IFERROR(VLOOKUP($D6,BS별도,MATCH(R$1,BS별도H,0),0)/100,"") | S6: =IFERROR(VLOOKUP($D6,BS별도,MATCH(S$1,BS별도H,0),0)/100,"") | T6: =IFERROR(VLOOKUP($D6,BS별도,MATCH(T$1,BS별도H,0),0)/100,"") | U6: =SUM(Q6:T6) | V6: =IFERROR(VLOOKUP($D6,BS별도,MATCH(V$1,BS별도H,0),0)/100,"") | W6: =IFERROR(VLOOKUP($D6,BS별도,MATCH(W$1,BS별도H,0),0)/100,"") | X6: =IFERROR(VLOOKUP($D6,BS별도,MATCH(X$1,BS별도H,0),0)/100,"") | Y6: =IFERROR(VLOOKUP($D6,BS별도,MATCH(Y$1,BS별도H,0),0)/100,"") | Z6: =SUM(V6:Y6) | AA6: =IFERROR(VLOOKUP($D6,BS별도,MATCH(AA$1,BS별도H,0),0)/100,"") | AB6: =IFERROR(VLOOKUP($D6,BS별도,MATCH(AB$1,BS별도H,0),0)/100,"") | AC6: =IFERROR(AC5-AC7,"") | AD6: =IFERROR(AD5-AD7,"") | AE6: =SUM(AA6:AD6) | AF6: =IFERROR(AF5-AF7,"") | AG6: =IFERROR(AG5-AG7,"") | AH6: =IFERROR(AH5-AH7,"") | AI6: =IFERROR(AI5-AI7,"") | AJ6: =SUM(AF6:AI6) | AK6: =IFERROR(AK5-AK7,"") | AL6: =IFERROR(AL5-AL7,"") | AM6: =IFERROR(AM5-AM7,"") | AN6: =IFERROR(AN5-AN7,"") | AO6: =SUM(AK6:AN6)
A7: 매출총이익 | B7: 손익 | C7: 억원 | D7: 매출총이익 | E7: =IFERROR(VLOOKUP($D7,BS별도,MATCH(E$1,BS별도H,0),0)/100,"") | G7: =IFERROR(VLOOKUP($D7,BS별도,MATCH(G$1,BS별도H,0),0)/100,"") | H7: =IFERROR(VLOOKUP($D7,BS별도,MATCH(H$1,BS별도H,0),0)/100,"") | I7: =IFERROR(VLOOKUP($D7,BS별도,MATCH(I$1,BS별도H,0),0)/100,"") | J7: =IFERROR(VLOOKUP($D7,BS별도,MATCH(J$1,BS별도H,0),0)/100,"") | K7: =SUM(G7:J7) | L7: =IFERROR(VLOOKUP($D7,BS별도,MATCH(L$1,BS별도H,0),0)/100,"") | M7: =IFERROR(VLOOKUP($D7,BS별도,MATCH(M$1,BS별도H,0),0)/100,"") | N7: =IFERROR(VLOOKUP($D7,BS별도,MATCH(N$1,BS별도H,0),0)/100,"") | O7: =IFERROR(VLOOKUP($D7,BS별도,MATCH(O$1,BS별도H,0),0)/100,"") | P7: =SUM(L7:O7) | Q7: =IFERROR(VLOOKUP($D7,BS별도,MATCH(Q$1,BS별도H,0),0)/100,"") | R7: =IFERROR(VLOOKUP($D7,BS별도,MATCH(R$1,BS별도H,0),0)/100,"") | S7: =IFERROR(VLOOKUP($D7,BS별도,MATCH(S$1,BS별도H,0),0)/100,"") | T7: =IFERROR(VLOOKUP($D7,BS별도,MATCH(T$1,BS별도H,0),0)/100,"") | U7: =SUM(Q7:T7) | V7: =IFERROR(VLOOKUP($D7,BS별도,MATCH(V$1,BS별도H,0),0)/100,"") | W7: =IFERROR(VLOOKUP($D7,BS별도,MATCH(W$1,BS별도H,0),0)/100,"") | X7: =IFERROR(VLOOKUP($D7,BS별도,MATCH(X$1,BS별도H,0),0)/100,"") | Y7: =IFERROR(VLOOKUP($D7,BS별도,MATCH(Y$1,BS별도H,0),0)/100,"") | Z7: =SUM(V7:Y7) | AA7: =IFERROR(VLOOKUP($D7,BS별도,MATCH(AA$1,BS별도H,0),0)/100,"") | AB7: =IFERROR(VLOOKUP($D7,BS별도,MATCH(AB$1,BS별도H,0),0)/100,"") | AC7: =IFERROR(AC9+AC8,"") | AD7: =IFERROR(AD9+AD8,"") | AE7: =SUM(AA7:AD7) | AF7: =IFERROR(AF9+AF8,"") | AG7: =IFERROR(AG9+AG8,"") | AH7: =IFERROR(AH9+AH8,"") | AI7: =IFERROR(AI9+AI8,"") | AJ7: =SUM(AF7:AI7) | AK7: =IFERROR(AK9+AK8,"") | AL7: =IFERROR(AL9+AL8,"") | AM7: =IFERROR(AM9+AM8,"") | AN7: =IFERROR(AN9+AN8,"") | AO7: =SUM(AK7:AN7)
A8: 판관비 | B8: 손익 | C8: 억원 | D8: 판관비 | E8: =IFERROR(VLOOKUP($D8,BS별도,MATCH(E$1,BS별도H,0),0)/100,"") | G8: =IFERROR(VLOOKUP($D8,BS별도,MATCH(G$1,BS별도H,0),0)/100,"") | H8: =IFERROR(VLOOKUP($D8,BS별도,MATCH(H$1,BS별도H,0),0)/100,"") | I8: =IFERROR(VLOOKUP($D8,BS별도,MATCH(I$1,BS별도H,0),0)/100,"") | J8: =IFERROR(VLOOKUP($D8,BS별도,MATCH(J$1,BS별도H,0),0)/100,"") | K8: =SUM(G8:J8) | L8: =IFERROR(VLOOKUP($D8,BS별도,MATCH(L$1,BS별도H,0),0)/100,"") | M8: =IFERROR(VLOOKUP($D8,BS별도,MATCH(M$1,BS별도H,0),0)/100,"") | N8: =IFERROR(VLOOKUP($D8,BS별도,MATCH(N$1,BS별도H,0),0)/100,"") | O8: =IFERROR(VLOOKUP($D8,BS별도,MATCH(O$1,BS별도H,0),0)/100,"") | P8: =SUM(L8:O8) | Q8: =IFERROR(VLOOKUP($D8,BS별도,MATCH(Q$1,BS별도H,0),0)/100,"") | R8: =IFERROR(VLOOKUP($D8,BS별도,MATCH(R$1,BS별도H,0),0)/100,"") | S8: =IFERROR(VLOOKUP($D8,BS별도,MATCH(S$1,BS별도H,0),0)/100,"") | T8: =IFERROR(VLOOKUP($D8,BS별도,MATCH(T$1,BS별도H,0),0)/100,"") | U8: =SUM(Q8:T8) | V8: =IFERROR(VLOOKUP($D8,BS별도,MATCH(V$1,BS별도H,0),0)/100,"") | W8: =IFERROR(VLOOKUP($D8,BS별도,MATCH(W$1,BS별도H,0),0)/100,"") | X8: =IFERROR(VLOOKUP($D8,BS별도,MATCH(X$1,BS별도H,0),0)/100,"") | Y8: =IFERROR(VLOOKUP($D8,BS별도,MATCH(Y$1,BS별도H,0),0)/100,"") | Z8: =SUM(V8:Y8) | AA8: =IFERROR(VLOOKUP($D8,BS별도,MATCH(AA$1,BS별도H,0),0)/100,"") | AB8: =IFERROR(VLOOKUP($D8,BS별도,MATCH(AB$1,BS별도H,0),0)/100,"") | AC8: =IFERROR(AC5*변수!AC22,"") | AD8: =IFERROR(AD5*변수!AD22,"") | AE8: =SUM(AA8:AD8) | AF8: =IFERROR(AF5*변수!AF22,"") | AG8: =IFERROR(AG5*변수!AG22,"") | AH8: =IFERROR(AH5*변수!AH22,"") | AI8: =IFERROR(AI5*변수!AI22,"") | AJ8: =SUM(AF8:AI8) | AK8: =IFERROR(AK5*변수!AK22,"") | AL8: =IFERROR(AL5*변수!AL22,"") | AM8: =IFERROR(AM5*변수!AM22,"") | AN8: =IFERROR(AN5*변수!AN22,"") | AO8: =SUM(AK8:AN8)
A9: 영업이익 | B9: 손익 | C9: 억원 | D9: 영업이익 | E9: =IFERROR(VLOOKUP($D9,BS별도,MATCH(E$1,BS별도H,0),0)/100,"") | G9: =IFERROR(VLOOKUP($D9,BS별도,MATCH(G$1,BS별도H,0),0)/100,"") | H9: =IFERROR(VLOOKUP($D9,BS별도,MATCH(H$1,BS별도H,0),0)/100,"") | I9: =IFERROR(VLOOKUP($D9,BS별도,MATCH(I$1,BS별도H,0),0)/100,"") | J9: =IFERROR(VLOOKUP($D9,BS별도,MATCH(J$1,BS별도H,0),0)/100,"") | K9: =SUM(G9:J9) | L9: =IFERROR(VLOOKUP($D9,BS별도,MATCH(L$1,BS별도H,0),0)/100,"") | M9: =IFERROR(VLOOKUP($D9,BS별도,MATCH(M$1,BS별도H,0),0)/100,"") | N9: =IFERROR(VLOOKUP($D9,BS별도,MATCH(N$1,BS별도H,0),0)/100,"") | O9: =IFERROR(VLOOKUP($D9,BS별도,MATCH(O$1,BS별도H,0),0)/100,"") | P9: =SUM(L9:O9) | Q9: =IFERROR(VLOOKUP($D9,BS별도,MATCH(Q$1,BS별도H,0),0)/100,"") | R9: =IFERROR(VLOOKUP($D9,BS별도,MATCH(R$1,BS별도H,0),0)/100,"") | S9: =IFERROR(VLOOKUP($D9,BS별도,MATCH(S$1,BS별도H,0),0)/100,"") | T9: =IFERROR(VLOOKUP($D9,BS별도,MATCH(T$1,BS별도H,0),0)/100,"") | U9: =SUM(Q9:T9) | V9: =IFERROR(VLOOKUP($D9,BS별도,MATCH(V$1,BS별도H,0),0)/100,"") | W9: =IFERROR(VLOOKUP($D9,BS별도,MATCH(W$1,BS별도H,0),0)/100,"") | X9: =IFERROR(VLOOKUP($D9,BS별도,MATCH(X$1,BS별도H,0),0)/100,"") | Y9: =IFERROR(VLOOKUP($D9,BS별도,MATCH(Y$1,BS별도H,0),0)/100,"") | Z9: =SUM(V9:Y9) | AA9: =IFERROR(VLOOKUP($D9,BS별도,MATCH(AA$1,BS별도H,0),0)/100,"") | AB9: =IFERROR(VLOOKUP($D9,BS별도,MATCH(AB$1,BS별도H,0),0)/100,"") | AC9: =IFERROR(AC5*변수!AC23,"") | AD9: =IFERROR(AD5*변수!AD23,"") | AE9: =SUM(AA9:AD9) | AF9: =IFERROR(AF5*변수!AF23,"") | AG9: =IFERROR(AG5*변수!AG23,"") | AH9: =IFERROR(AH5*변수!AH23,"") | AI9: =IFERROR(AI5*변수!AI23,"") | AJ9: =SUM(AF9:AI9) | AK9: =IFERROR(AK5*변수!AK23,"") | AL9: =IFERROR(AL5*변수!AL23,"") | AM9: =IFERROR(AM5*변수!AM23,"") | AN9: =IFERROR(AN5*변수!AN23,"") | AO9: =SUM(AK9:AN9)
A10: OPM | B10: 손익 | C10: % | D10: 영업이익률 | E10: =IFERROR(E9/E5,"") | G10: =IFERROR(G9/G5,"") | H10: =IFERROR(H9/H5,"") | I10: =IFERROR(I9/I5,"") | J10: =IFERROR(J9/J5,"") | K10: =IFERROR(K9/K5,"") | L10: =IFERROR(L9/L5,"") | M10: =IFERROR(M9/M5,"") | N10: =IFERROR(N9/N5,"") | ... AO10: =IFERROR(AO9/AO5,"")
A11: 금융손익 | B11: 손익 | C11: 억원 | D11: 금융손익 | E11: =IFERROR(VLOOKUP($D11,BS별도,MATCH(E$1,BS별도H,0),0)/100,"") | G11: =IFERROR(VLOOKUP($D11,BS별도,MATCH(G$1,BS별도H,0),0)/100,"") | H11: =IFERROR(VLOOKUP($D11,BS별도,MATCH(H$1,BS별도H,0),0)/100,"") | I11: =IFERROR(VLOOKUP($D11,BS별도,MATCH(I$1,BS별도H,0),0)/100,"") | J11: =IFERROR(VLOOKUP($D11,BS별도,MATCH(J$1,BS별도H,0),0)/100,"") | K11: =SUM(G11:J11) | L11: =IFERROR(VLOOKUP($D11,BS별도,MATCH(L$1,BS별도H,0),0)/100,"") | M11: =IFERROR(VLOOKUP($D11,BS별도,MATCH(M$1,BS별도H,0),0)/100,"") | N11: =IFERROR(VLOOKUP($D11,BS별도,MATCH(N$1,BS별도H,0),0)/100,"") | O11: =IFERROR(VLOOKUP($D11,BS별도,MATCH(O$1,BS별도H,0),0)/100,"") | P11: =SUM(L11:O11) | Q11: =IFERROR(VLOOKUP($D11,BS별도,MATCH(Q$1,BS별도H,0),0)/100,"") | R11: =IFERROR(VLOOKUP($D11,BS별도,MATCH(R$1,BS별도H,0),0)/100,"") | S11: =IFERROR(VLOOKUP($D11,BS별도,MATCH(S$1,BS별도H,0),0)/100,"") | T11: =IFERROR(VLOOKUP($D11,BS별도,MATCH(T$1,BS별도H,0),0)/100,"") | U11: =SUM(Q11:T11) | V11: =IFERROR(VLOOKUP($D11,BS별도,MATCH(V$1,BS별도H,0),0)/100,"") | W11: =IFERROR(VLOOKUP($D11,BS별도,MATCH(W$1,BS별도H,0),0)/100,"") | X11: =IFERROR(VLOOKUP($D11,BS별도,MATCH(X$1,BS별도H,0),0)/100,"") | Y11: =IFERROR(VLOOKUP($D11,BS별도,MATCH(Y$1,BS별도H,0),0)/100,"") | Z11: =SUM(V11:Y11) | AA11: =IFERROR(VLOOKUP($D11,BS별도,MATCH(AA$1,BS별도H,0),0)/100,"") | AB11: =IFERROR(VLOOKUP($D11,BS별도,MATCH(AB$1,BS별도H,0),0)/100,"") | AC11: =IFERROR(AC12+AC13+AC14+AC15,"") | AD11: =IFERROR(AD12+AD13+AD14+AD15,"") | AE11: =SUM(AA11:AD11) | AF11: =IFERROR(AF12+AF13+AF14+AF15,"") | AG11: =IFERROR(AG12+AG13+AG14+AG15,"") | AH11: =IFERROR(AH12+AH13+AH14+AH15,"") | AI11: =IFERROR(AI12+AI13+AI14+AI15,"") | AJ11: =SUM(AF11:AI11) | AK11: =IFERROR(AK12+AK13+AK14+AK15,"") | AL11: =IFERROR(AL12+AL13+AL14+AL15,"") | AM11: =IFERROR(AM12+AM13+AM14+AM15,"") | AN11: =IFERROR(AN12+AN13+AN14+AN15,"") | AO11: =SUM(AK11:AN11)
A12: 이자손익 | B12: 손익 | C12: 억원 | D12: 이자손익 | K12: =SUM(G12:J12) | P12: =SUM(L12:O12) | U12: =SUM(Q12:T12) | X12: =IFERROR(VLOOKUP($D12,BS별도,MATCH(X$1,BS별도H,0),0)/100,"") | Y12: =IFERROR(VLOOKUP($D12,BS별도,MATCH(Y$1,BS별도H,0),0)/100,"") | Z12: =SUM(V12:Y12) | AA12: =IFERROR(VLOOKUP($D12,BS별도,MATCH(AA$1,BS별도H,0),0)/100,"") | AB12: =IFERROR(VLOOKUP($D12,BS별도,MATCH(AB$1,BS별도H,0),0)/100,"") | AC12: =IFERROR((AB28*변수!$D$54-AB26*변수!$D$55)/4,"") | AD12: =IFERROR((AC28*변수!$D$54-AC26*변수!$D$55)/4,"") | AE12: =SUM(AA12:AD12) | AF12: =IFERROR((AD28*변수!$D$54-AD26*변수!$D$55)/4,"") | AG12: =IFERROR((AF28*변수!$D$54-AF26*변수!$D$55)/4,"") | AH12: =IFERROR((AG28*변수!$D$54-AG26*변수!$D$55)/4,"") | AI12: =IFERROR((AH28*변수!$D$54-AH26*변수!$D$55)/4,"") | AJ12: =SUM(AF12:AI12) | AK12: =IFERROR((AI28*변수!$D$54-AI26*변수!$D$55)/4,"") | AL12: =IFERROR((AK28*변수!$D$54-AK26*변수!$D$55)/4,"") | AM12: =IFERROR((AL28*변수!$D$54-AL26*변수!$D$55)/4,"") | AN12: =IFERROR((AM28*변수!$D$54-AM26*변수!$D$55)/4,"") | AO12: =SUM(AK12:AN12)
A13: 외환손익 | B13: 손익 | C13: 억원 | D13: 외환손익(실적만; 추정 환효과는 환관련손익) | K13: =SUM(G13:J13) | P13: =SUM(L13:O13) | U13: =SUM(Q13:T13) | X13: =IFERROR((VLOOKUP("외환차익",BS별도,MATCH(X$1,BS별도H,0),0)-VLOOKUP("외환차손",BS별도,MATCH(X$1,BS별도H,0),0)+VLOOKUP("외화환산이익",BS별도,MATCH(X$1,BS별도H,0),0)-VLOOKUP("외화환산손실",BS별도,MATCH(X$1,BS별도H,0),0))/100,"") | Y13: =IFERROR((VLOOKUP("외환차익",BS별도,MATCH(Y$1,BS별도H,0),0)-VLOOKUP("외환차손",BS별도,MATCH(Y$1,BS별도H,0),0)+VLOOKUP("외화환산이익",BS별도,MATCH(Y$1,BS별도H,0),0)-VLOOKUP("외화환산손실",BS별도,MATCH(Y$1,BS별도H,0),0))/100,"") | Z13: =SUM(V13:Y13) | AC13: =변수!AC24 | AD13: =변수!AD24 | AE13: =SUM(AA13:AD13) | AF13: =변수!AF24 | AG13: =변수!AG24 | AH13: =변수!AH24 | AI13: =변수!AI24 | AJ13: =SUM(AF13:AI13) | AK13: =변수!AK24 | AL13: =변수!AL24 | AM13: =변수!AM24 | AN13: =변수!AN24 | AO13: =SUM(AK13:AN13)
A14: 파생상품손익 | B14: 손익 | C14: 억원 | D14: 파생상품손익 | K14: =SUM(G14:J14) | P14: =SUM(L14:O14) | U14: =SUM(Q14:T14) | X14: =IFERROR((VLOOKUP("파생상품이익",BS별도,MATCH(X$1,BS별도H,0),0)-VLOOKUP("파생상품손실",BS별도,MATCH(X$1,BS별도H,0),0))/100,"") | Y14: =IFERROR((VLOOKUP("파생상품이익",BS별도,MATCH(Y$1,BS별도H,0),0)-VLOOKUP("파생상품손실",BS별도,MATCH(Y$1,BS별도H,0),0))/100,"") | Z14: =SUM(V14:Y14) | AC14: =변수!AC25 | AD14: =변수!AD25 | AE14: =SUM(AA14:AD14) | AF14: =변수!AF25 | AG14: =변수!AG25 | AH14: =변수!AH25 | AI14: =변수!AI25 | AJ14: =SUM(AF14:AI14) | AK14: =변수!AK25 | AL14: =변수!AL25 | AM14: =변수!AM25 | AN14: =변수!AN25 | AO14: =SUM(AK14:AN14)
A15: 기타금융손익 | B15: 손익 | C15: 억원 | D15: 기타금융손익(금융손익 잔차) | K15: =SUM(G15:J15) | P15: =SUM(L15:O15) | U15: =SUM(Q15:T15) | X15: =IFERROR(X11-X12-X13-X14,"") | Y15: =IFERROR(Y11-Y12-Y13-Y14,"") | Z15: =SUM(V15:Y15) | AC15: =변수!AC26 | AD15: =변수!AD26 | AE15: =SUM(AA15:AD15) | AF15: =변수!AF26 | AG15: =변수!AG26 | AH15: =변수!AH26 | AI15: =변수!AI26 | AJ15: =SUM(AF15:AI15) | AK15: =변수!AK26 | AL15: =변수!AL26 | AM15: =변수!AM26 | AN15: =변수!AN26 | AO15: =SUM(AK15:AN15)
A16: 기타영업외손익 | B16: 손익 | C16: 억원 | D16: 기타영업외손익 | E16: =IFERROR(VLOOKUP($D16,BS별도,MATCH(E$1,BS별도H,0),0)/100,"") | G16: =IFERROR(VLOOKUP($D16,BS별도,MATCH(G$1,BS별도H,0),0)/100,"") | H16: =IFERROR(VLOOKUP($D16,BS별도,MATCH(H$1,BS별도H,0),0)/100,"") | I16: =IFERROR(VLOOKUP($D16,BS별도,MATCH(I$1,BS별도H,0),0)/100,"") | J16: =IFERROR(VLOOKUP($D16,BS별도,MATCH(J$1,BS별도H,0),0)/100,"") | K16: =SUM(G16:J16) | L16: =IFERROR(VLOOKUP($D16,BS별도,MATCH(L$1,BS별도H,0),0)/100,"") | M16: =IFERROR(VLOOKUP($D16,BS별도,MATCH(M$1,BS별도H,0),0)/100,"") | N16: =IFERROR(VLOOKUP($D16,BS별도,MATCH(N$1,BS별도H,0),0)/100,"") | O16: =IFERROR(VLOOKUP($D16,BS별도,MATCH(O$1,BS별도H,0),0)/100,"") | P16: =SUM(L16:O16) | Q16: =IFERROR(VLOOKUP($D16,BS별도,MATCH(Q$1,BS별도H,0),0)/100,"") | R16: =IFERROR(VLOOKUP($D16,BS별도,MATCH(R$1,BS별도H,0),0)/100,"") | S16: =IFERROR(VLOOKUP($D16,BS별도,MATCH(S$1,BS별도H,0),0)/100,"") | T16: =IFERROR(VLOOKUP($D16,BS별도,MATCH(T$1,BS별도H,0),0)/100,"") | U16: =SUM(Q16:T16) | V16: =IFERROR(VLOOKUP($D16,BS별도,MATCH(V$1,BS별도H,0),0)/100,"") | W16: =IFERROR(VLOOKUP($D16,BS별도,MATCH(W$1,BS별도H,0),0)/100,"") | X16: =IFERROR(VLOOKUP($D16,BS별도,MATCH(X$1,BS별도H,0),0)/100,"") | Y16: =IFERROR(VLOOKUP($D16,BS별도,MATCH(Y$1,BS별도H,0),0)/100,"") | Z16: =SUM(V16:Y16) | AA16: =IFERROR(VLOOKUP($D16,BS별도,MATCH(AA$1,BS별도H,0),0)/100,"") | AB16: =IFERROR(VLOOKUP($D16,BS별도,MATCH(AB$1,BS별도H,0),0)/100,"") | AC16: =변수!AC27 | AD16: =변수!AD27 | AE16: =SUM(AA16:AD16) | AF16: =변수!AF27 | AG16: =변수!AG27 | AH16: =변수!AH27 | AI16: =변수!AI27 | AJ16: =SUM(AF16:AI16) | AK16: =변수!AK27 | AL16: =변수!AL27 | AM16: =변수!AM27 | AN16: =변수!AN27 | AO16: =SUM(AK16:AN16)
A17: 지분법손익 | B17: 손익 | C17: 억원 | D17: 종속기업,공동지배기업및관계기업관련손익 | H17: =IFERROR(VLOOKUP($D17,BS별도,MATCH(H$1,BS별도H,0),0)/100,"") | I17: =IFERROR(VLOOKUP($D17,BS별도,MATCH(I$1,BS별도H,0),0)/100,"") | K17: =SUM(G17:J17) | P17: =SUM(L17:O17) | U17: =SUM(Q17:T17) | Z17: =SUM(V17:Y17) | AC17: =변수!AC28 | AD17: =변수!AD28 | AE17: =SUM(AA17:AD17) | AF17: =변수!AF28 | AG17: =변수!AG28 | AH17: =변수!AH28 | AI17: =변수!AI28 | AJ17: =SUM(AF17:AI17) | AK17: =변수!AK28 | AL17: =변수!AL28 | AM17: =변수!AM28 | AN17: =변수!AN28 | AO17: =SUM(AK17:AN17)
A18: 세전이익 | B18: 손익 | C18: 억원 | D18: 법인세비용차감전계속사업이익 | E18: =IFERROR(VLOOKUP($D18,BS별도,MATCH(E$1,BS별도H,0),0)/100,"") | G18: =IFERROR(VLOOKUP($D18,BS별도,MATCH(G$1,BS별도H,0),0)/100,"") | H18: =IFERROR(VLOOKUP($D18,BS별도,MATCH(H$1,BS별도H,0),0)/100,"") | I18: =IFERROR(VLOOKUP($D18,BS별도,MATCH(I$1,BS별도H,0),0)/100,"") | J18: =IFERROR(VLOOKUP($D18,BS별도,MATCH(J$1,BS별도H,0),0)/100,"") | K18: =SUM(G18:J18) | L18: =IFERROR(VLOOKUP($D18,BS별도,MATCH(L$1,BS별도H,0),0)/100,"") | M18: =IFERROR(VLOOKUP($D18,BS별도,MATCH(M$1,BS별도H,0),0)/100,"") | N18: =IFERROR(VLOOKUP($D18,BS별도,MATCH(N$1,BS별도H,0),0)/100,"") | O18: =IFERROR(VLOOKUP($D18,BS별도,MATCH(O$1,BS별도H,0),0)/100,"") | P18: =SUM(L18:O18) | Q18: =IFERROR(VLOOKUP($D18,BS별도,MATCH(Q$1,BS별도H,0),0)/100,"") | R18: =IFERROR(VLOOKUP($D18,BS별도,MATCH(R$1,BS별도H,0),0)/100,"") | S18: =IFERROR(VLOOKUP($D18,BS별도,MATCH(S$1,BS별도H,0),0)/100,"") | T18: =IFERROR(VLOOKUP($D18,BS별도,MATCH(T$1,BS별도H,0),0)/100,"") | U18: =SUM(Q18:T18) | V18: =IFERROR(VLOOKUP($D18,BS별도,MATCH(V$1,BS별도H,0),0)/100,"") | W18: =IFERROR(VLOOKUP($D18,BS별도,MATCH(W$1,BS별도H,0),0)/100,"") | X18: =IFERROR(VLOOKUP($D18,BS별도,MATCH(X$1,BS별도H,0),0)/100,"") | Y18: =IFERROR(VLOOKUP($D18,BS별도,MATCH(Y$1,BS별도H,0),0)/100,"") | Z18: =SUM(V18:Y18) | AA18: =IFERROR(VLOOKUP($D18,BS별도,MATCH(AA$1,BS별도H,0),0)/100,"") | AB18: =IFERROR(VLOOKUP($D18,BS별도,MATCH(AB$1,BS별도H,0),0)/100,"") | AC18: =IFERROR(AC9+AC11+AC16+AC17,"") | AD18: =IFERROR(AD9+AD11+AD16+AD17,"") | AE18: =SUM(AA18:AD18) | AF18: =IFERROR(AF9+AF11+AF16+AF17,"") | AG18: =IFERROR(AG9+AG11+AG16+AG17,"") | AH18: =IFERROR(AH9+AH11+AH16+AH17,"") | AI18: =IFERROR(AI9+AI11+AI16+AI17,"") | AJ18: =SUM(AF18:AI18) | AK18: =IFERROR(AK9+AK11+AK16+AK17,"") | AL18: =IFERROR(AL9+AL11+AL16+AL17,"") | AM18: =IFERROR(AM9+AM11+AM16+AM17,"") | AN18: =IFERROR(AN9+AN11+AN16+AN17,"") | AO18: =SUM(AK18:AN18)
A19: 법인세비용 | B19: 손익 | C19: 억원 | D19: 법인세비용 | E19: =IFERROR(VLOOKUP($D19,BS별도,MATCH(E$1,BS별도H,0),0)/100,"") | G19: =IFERROR(VLOOKUP($D19,BS별도,MATCH(G$1,BS별도H,0),0)/100,"") | H19: =IFERROR(VLOOKUP($D19,BS별도,MATCH(H$1,BS별도H,0),0)/100,"") | I19: =IFERROR(VLOOKUP($D19,BS별도,MATCH(I$1,BS별도H,0),0)/100,"") | J19: =IFERROR(VLOOKUP($D19,BS별도,MATCH(J$1,BS별도H,0),0)/100,"") | K19: =SUM(G19:J19) | L19: =IFERROR(VLOOKUP($D19,BS별도,MATCH(L$1,BS별도H,0),0)/100,"") | M19: =IFERROR(VLOOKUP($D19,BS별도,MATCH(M$1,BS별도H,0),0)/100,"") | N19: =IFERROR(VLOOKUP($D19,BS별도,MATCH(N$1,BS별도H,0),0)/100,"") | O19: =IFERROR(VLOOKUP($D19,BS별도,MATCH(O$1,BS별도H,0),0)/100,"") | P19: =SUM(L19:O19) | Q19: =IFERROR(VLOOKUP($D19,BS별도,MATCH(Q$1,BS별도H,0),0)/100,"") | R19: =IFERROR(VLOOKUP($D19,BS별도,MATCH(R$1,BS별도H,0),0)/100,"") | S19: =IFERROR(VLOOKUP($D19,BS별도,MATCH(S$1,BS별도H,0),0)/100,"") | T19: =IFERROR(VLOOKUP($D19,BS별도,MATCH(T$1,BS별도H,0),0)/100,"") | U19: =SUM(Q19:T19) | V19: =IFERROR(VLOOKUP($D19,BS별도,MATCH(V$1,BS별도H,0),0)/100,"") | W19: =IFERROR(VLOOKUP($D19,BS별도,MATCH(W$1,BS별도H,0),0)/100,"") | X19: =IFERROR(VLOOKUP($D19,BS별도,MATCH(X$1,BS별도H,0),0)/100,"") | Y19: =IFERROR(VLOOKUP($D19,BS별도,MATCH(Y$1,BS별도H,0),0)/100,"") | Z19: =SUM(V19:Y19) | AA19: =IFERROR(VLOOKUP($D19,BS별도,MATCH(AA$1,BS별도H,0),0)/100,"") | AB19: =IFERROR(VLOOKUP($D19,BS별도,MATCH(AB$1,BS별도H,0),0)/100,"") | AC19: =IFERROR(AC18*변수!AC29,"") | AD19: =IFERROR(AD18*변수!AD29,"") | AE19: =SUM(AA19:AD19) | AF19: =IFERROR(AF18*변수!AF29,"") | AG19: =IFERROR(AG18*변수!AG29,"") | AH19: =IFERROR(AH18*변수!AH29,"") | AI19: =IFERROR(AI18*변수!AI29,"") | AJ19: =SUM(AF19:AI19) | AK19: =IFERROR(AK18*변수!AK29,"") | AL19: =IFERROR(AL18*변수!AL29,"") | AM19: =IFERROR(AM18*변수!AM29,"") | AN19: =IFERROR(AN18*변수!AN29,"") | AO19: =SUM(AK19:AN19)
A20: 당기순이익 | B20: 손익 | C20: 억원 | D20: 당기순이익 | E20: =IFERROR(VLOOKUP($D20,BS별도,MATCH(E$1,BS별도H,0),0)/100,"") | G20: =IFERROR(VLOOKUP($D20,BS별도,MATCH(G$1,BS별도H,0),0)/100,"") | H20: =IFERROR(VLOOKUP($D20,BS별도,MATCH(H$1,BS별도H,0),0)/100,"") | I20: =IFERROR(VLOOKUP($D20,BS별도,MATCH(I$1,BS별도H,0),0)/100,"") | J20: =IFERROR(VLOOKUP($D20,BS별도,MATCH(J$1,BS별도H,0),0)/100,"") | K20: =SUM(G20:J20) | L20: =IFERROR(VLOOKUP($D20,BS별도,MATCH(L$1,BS별도H,0),0)/100,"") | M20: =IFERROR(VLOOKUP($D20,BS별도,MATCH(M$1,BS별도H,0),0)/100,"") | N20: =IFERROR(VLOOKUP($D20,BS별도,MATCH(N$1,BS별도H,0),0)/100,"") | O20: =IFERROR(VLOOKUP($D20,BS별도,MATCH(O$1,BS별도H,0),0)/100,"") | P20: =SUM(L20:O20) | Q20: =IFERROR(VLOOKUP($D20,BS별도,MATCH(Q$1,BS별도H,0),0)/100,"") | R20: =IFERROR(VLOOKUP($D20,BS별도,MATCH(R$1,BS별도H,0),0)/100,"") | S20: =IFERROR(VLOOKUP($D20,BS별도,MATCH(S$1,BS별도H,0),0)/100,"") | T20: =IFERROR(VLOOKUP($D20,BS별도,MATCH(T$1,BS별도H,0),0)/100,"") | U20: =SUM(Q20:T20) | V20: =IFERROR(VLOOKUP($D20,BS별도,MATCH(V$1,BS별도H,0),0)/100,"") | W20: =IFERROR(VLOOKUP($D20,BS별도,MATCH(W$1,BS별도H,0),0)/100,"") | X20: =IFERROR(VLOOKUP($D20,BS별도,MATCH(X$1,BS별도H,0),0)/100,"") | Y20: =IFERROR(VLOOKUP($D20,BS별도,MATCH(Y$1,BS별도H,0),0)/100,"") | Z20: =SUM(V20:Y20) | AA20: =IFERROR(VLOOKUP($D20,BS별도,MATCH(AA$1,BS별도H,0),0)/100,"") | AB20: =IFERROR(VLOOKUP($D20,BS별도,MATCH(AB$1,BS별도H,0),0)/100,"") | AC20: =IFERROR(AC18-AC19,"") | AD20: =IFERROR(AD18-AD19,"") | AE20: =SUM(AA20:AD20) | AF20: =IFERROR(AF18-AF19,"") | AG20: =IFERROR(AG18-AG19,"") | AH20: =IFERROR(AH18-AH19,"") | AI20: =IFERROR(AI18-AI19,"") | AJ20: =SUM(AF20:AI20) | AK20: =IFERROR(AK18-AK19,"") | AL20: =IFERROR(AL18-AL19,"") | AM20: =IFERROR(AM18-AM19,"") | AN20: =IFERROR(AN18-AN19,"") | AO20: =SUM(AK20:AN20)
A21: 지배주주순이익 | B21: 손익 | C21: 억원 | D21: (지배주주지분)당기순이익 | E21: =IFERROR(VLOOKUP($D21,BS별도,MATCH(E$1,BS별도H,0),0)/100,"") | G21: =IFERROR(VLOOKUP($D21,BS별도,MATCH(G$1,BS별도H,0),0)/100,"") | H21: =IFERROR(VLOOKUP($D21,BS별도,MATCH(H$1,BS별도H,0),0)/100,"") | I21: =IFERROR(VLOOKUP($D21,BS별도,MATCH(I$1,BS별도H,0),0)/100,"") | J21: =IFERROR(VLOOKUP($D21,BS별도,MATCH(J$1,BS별도H,0),0)/100,"") | K21: =SUM(G21:J21) | L21: =IFERROR(VLOOKUP($D21,BS별도,MATCH(L$1,BS별도H,0),0)/100,"") | M21: =IFERROR(VLOOKUP($D21,BS별도,MATCH(M$1,BS별도H,0),0)/100,"") | N21: =IFERROR(VLOOKUP($D21,BS별도,MATCH(N$1,BS별도H,0),0)/100,"") | O21: =IFERROR(VLOOKUP($D21,BS별도,MATCH(O$1,BS별도H,0),0)/100,"") | P21: =SUM(L21:O21) | Q21: =IFERROR(VLOOKUP($D21,BS별도,MATCH(Q$1,BS별도H,0),0)/100,"") | R21: =IFERROR(VLOOKUP($D21,BS별도,MATCH(R$1,BS별도H,0),0)/100,"") | S21: =IFERROR(VLOOKUP($D21,BS별도,MATCH(S$1,BS별도H,0),0)/100,"") | T21: =IFERROR(VLOOKUP($D21,BS별도,MATCH(T$1,BS별도H,0),0)/100,"") | U21: =SUM(Q21:T21) | V21: =IFERROR(VLOOKUP($D21,BS별도,MATCH(V$1,BS별도H,0),0)/100,"") | W21: =IFERROR(VLOOKUP($D21,BS별도,MATCH(W$1,BS별도H,0),0)/100,"") | X21: =IFERROR(VLOOKUP($D21,BS별도,MATCH(X$1,BS별도H,0),0)/100,"") | Y21: =IFERROR(VLOOKUP($D21,BS별도,MATCH(Y$1,BS별도H,0),0)/100,"") | Z21: =SUM(V21:Y21) | AA21: =IFERROR(VLOOKUP($D21,BS별도,MATCH(AA$1,BS별도H,0),0)/100,"") | AB21: =IFERROR(VLOOKUP($D21,BS별도,MATCH(AB$1,BS별도H,0),0)/100,"") | AC21: =IFERROR(AC20*변수!AC30,"") | AD21: =IFERROR(AD20*변수!AD30,"") | AE21: =SUM(AA21:AD21) | AF21: =IFERROR(AF20*변수!AF30,"") | AG21: =IFERROR(AG20*변수!AG30,"") | AH21: =IFERROR(AH20*변수!AH30,"") | AI21: =IFERROR(AI20*변수!AI30,"") | AJ21: =SUM(AF21:AI21) | AK21: =IFERROR(AK20*변수!AK30,"") | AL21: =IFERROR(AL20*변수!AL30,"") | AM21: =IFERROR(AM20*변수!AM30,"") | AN21: =IFERROR(AN20*변수!AN30,"") | AO21: =SUM(AK21:AN21)
A22: 자산총계 | B22: 재무상태 | C22: 억원 | D22: 자산총계 | E22: =IFERROR(VLOOKUP($D22,BS별도,MATCH(E$1,BS별도H,0),0)/100,"") | F22: 951.13 | G22: =IFERROR(VLOOKUP($D22,BS별도,MATCH(G$1,BS별도H,0),0)/100,"") | H22: =IFERROR(VLOOKUP($D22,BS별도,MATCH(H$1,BS별도H,0),0)/100,"") | I22: =IFERROR(VLOOKUP($D22,BS별도,MATCH(I$1,BS별도H,0),0)/100,"") | J22: =IFERROR(VLOOKUP($D22,BS별도,MATCH(J$1,BS별도H,0),0)/100,"") | K22: =J22 | L22: =IFERROR(VLOOKUP($D22,BS별도,MATCH(L$1,BS별도H,0),0)/100,"") | M22: =IFERROR(VLOOKUP($D22,BS별도,MATCH(M$1,BS별도H,0),0)/100,"") | N22: =IFERROR(VLOOKUP($D22,BS별도,MATCH(N$1,BS별도H,0),0)/100,"") | O22: =IFERROR(VLOOKUP($D22,BS별도,MATCH(O$1,BS별도H,0),0)/100,"") | P22: =O22 | Q22: =IFERROR(VLOOKUP($D22,BS별도,MATCH(Q$1,BS별도H,0),0)/100,"") | R22: =IFERROR(VLOOKUP($D22,BS별도,MATCH(R$1,BS별도H,0),0)/100,"") | S22: =IFERROR(VLOOKUP($D22,BS별도,MATCH(S$1,BS별도H,0),0)/100,"") | T22: =IFERROR(VLOOKUP($D22,BS별도,MATCH(T$1,BS별도H,0),0)/100,"") | U22: =T22 | V22: =IFERROR(VLOOKUP($D22,BS별도,MATCH(V$1,BS별도H,0),0)/100,"") | W22: =IFERROR(VLOOKUP($D22,BS별도,MATCH(W$1,BS별도H,0),0)/100,"") | X22: =IFERROR(VLOOKUP($D22,BS별도,MATCH(X$1,BS별도H,0),0)/100,"") | Y22: =IFERROR(VLOOKUP($D22,BS별도,MATCH(Y$1,BS별도H,0),0)/100,"") | Z22: =Y22 | AA22: =IFERROR(VLOOKUP($D22,BS별도,MATCH(AA$1,BS별도H,0),0)/100,"") | AB22: =IFERROR(VLOOKUP($D22,BS별도,MATCH(AB$1,BS별도H,0),0)/100,"") | AC22: =IFERROR(AC23+AC24,"") | AD22: =IFERROR(AD23+AD24,"") | AE22: =AD22 | AF22: =IFERROR(AF23+AF24,"") | AG22: =IFERROR(AG23+AG24,"") | AH22: =IFERROR(AH23+AH24,"") | AI22: =IFERROR(AI23+AI24,"") | AJ22: =AI22 | AK22: =IFERROR(AK23+AK24,"") | AL22: =IFERROR(AL23+AL24,"") | AM22: =IFERROR(AM23+AM24,"") | AN22: =IFERROR(AN23+AN24,"") | AO22: =AN22
A23: 부채총계 | B23: 재무상태 | C23: 억원 | D23: 부채총계 | E23: =IFERROR(VLOOKUP($D23,BS별도,MATCH(E$1,BS별도H,0),0)/100,"") | F23: 198.93 | G23: =IFERROR(VLOOKUP($D23,BS별도,MATCH(G$1,BS별도H,0),0)/100,"") | H23: =IFERROR(VLOOKUP($D23,BS별도,MATCH(H$1,BS별도H,0),0)/100,"") | I23: =IFERROR(VLOOKUP($D23,BS별도,MATCH(I$1,BS별도H,0),0)/100,"") | J23: =IFERROR(VLOOKUP($D23,BS별도,MATCH(J$1,BS별도H,0),0)/100,"") | K23: =J23 | L23: =IFERROR(VLOOKUP($D23,BS별도,MATCH(L$1,BS별도H,0),0)/100,"") | M23: =IFERROR(VLOOKUP($D23,BS별도,MATCH(M$1,BS별도H,0),0)/100,"") | N23: =IFERROR(VLOOKUP($D23,BS별도,MATCH(N$1,BS별도H,0),0)/100,"") | O23: =IFERROR(VLOOKUP($D23,BS별도,MATCH(O$1,BS별도H,0),0)/100,"") | P23: =O23 | Q23: =IFERROR(VLOOKUP($D23,BS별도,MATCH(Q$1,BS별도H,0),0)/100,"") | R23: =IFERROR(VLOOKUP($D23,BS별도,MATCH(R$1,BS별도H,0),0)/100,"") | S23: =IFERROR(VLOOKUP($D23,BS별도,MATCH(S$1,BS별도H,0),0)/100,"") | T23: =IFERROR(VLOOKUP($D23,BS별도,MATCH(T$1,BS별도H,0),0)/100,"") | U23: =T23 | V23: =IFERROR(VLOOKUP($D23,BS별도,MATCH(V$1,BS별도H,0),0)/100,"") | W23: =IFERROR(VLOOKUP($D23,BS별도,MATCH(W$1,BS별도H,0),0)/100,"") | X23: =IFERROR(VLOOKUP($D23,BS별도,MATCH(X$1,BS별도H,0),0)/100,"") | Y23: =IFERROR(VLOOKUP($D23,BS별도,MATCH(Y$1,BS별도H,0),0)/100,"") | Z23: =Y23 | AA23: =IFERROR(VLOOKUP($D23,BS별도,MATCH(AA$1,BS별도H,0),0)/100,"") | AB23: =IFERROR(VLOOKUP($D23,BS별도,MATCH(AB$1,BS별도H,0),0)/100,"") | AC23: =IFERROR(AB23*(1+변수!AC31),"") | AD23: =IFERROR(AC23*(1+변수!AD31),"") | AE23: =AD23 | AF23: =IFERROR(AD23*(1+변수!AF31),"") | AG23: =IFERROR(AF23*(1+변수!AG31),"") | AH23: =IFERROR(AG23*(1+변수!AH31),"") | AI23: =IFERROR(AH23*(1+변수!AI31),"") | AJ23: =AI23 | AK23: =IFERROR(AI23*(1+변수!AK31),"") | AL23: =IFERROR(AK23*(1+변수!AL31),"") | AM23: =IFERROR(AL23*(1+변수!AM31),"") | AN23: =IFERROR(AM23*(1+변수!AN31),"") | AO23: =AN23
A24: 자본총계 | B24: 재무상태 | C24: 억원 | D24: 자본총계 | E24: =IFERROR(VLOOKUP($D24,BS별도,MATCH(E$1,BS별도H,0),0)/100,"") | F24: 752.2 | G24: =IFERROR(VLOOKUP($D24,BS별도,MATCH(G$1,BS별도H,0),0)/100,"") | H24: =IFERROR(VLOOKUP($D24,BS별도,MATCH(H$1,BS별도H,0),0)/100,"") | I24: =IFERROR(VLOOKUP($D24,BS별도,MATCH(I$1,BS별도H,0),0)/100,"") | J24: =IFERROR(VLOOKUP($D24,BS별도,MATCH(J$1,BS별도H,0),0)/100,"") | K24: =J24 | L24: =IFERROR(VLOOKUP($D24,BS별도,MATCH(L$1,BS별도H,0),0)/100,"") | M24: =IFERROR(VLOOKUP($D24,BS별도,MATCH(M$1,BS별도H,0),0)/100,"") | N24: =IFERROR(VLOOKUP($D24,BS별도,MATCH(N$1,BS별도H,0),0)/100,"") | O24: =IFERROR(VLOOKUP($D24,BS별도,MATCH(O$1,BS별도H,0),0)/100,"") | P24: =O24 | Q24: =IFERROR(VLOOKUP($D24,BS별도,MATCH(Q$1,BS별도H,0),0)/100,"") | R24: =IFERROR(VLOOKUP($D24,BS별도,MATCH(R$1,BS별도H,0),0)/100,"") | S24: =IFERROR(VLOOKUP($D24,BS별도,MATCH(S$1,BS별도H,0),0)/100,"") | T24: =IFERROR(VLOOKUP($D24,BS별도,MATCH(T$1,BS별도H,0),0)/100,"") | U24: =T24 | V24: =IFERROR(VLOOKUP($D24,BS별도,MATCH(V$1,BS별도H,0),0)/100,"") | W24: =IFERROR(VLOOKUP($D24,BS별도,MATCH(W$1,BS별도H,0),0)/100,"") | X24: =IFERROR(VLOOKUP($D24,BS별도,MATCH(X$1,BS별도H,0),0)/100,"") | Y24: =IFERROR(VLOOKUP($D24,BS별도,MATCH(Y$1,BS별도H,0),0)/100,"") | Z24: =Y24 | AA24: =IFERROR(VLOOKUP($D24,BS별도,MATCH(AA$1,BS별도H,0),0)/100,"") | AB24: =IFERROR(VLOOKUP($D24,BS별도,MATCH(AB$1,BS별도H,0),0)/100,"") | AC24: =IFERROR(AB24+AC20-변수!AC32,"") | AD24: =IFERROR(AC24+AD20-변수!AD32,"") | AE24: =AD24 | AF24: =IFERROR(AD24+AF20-변수!AF32,"") | AG24: =IFERROR(AF24+AG20-변수!AG32,"") | AH24: =IFERROR(AG24+AH20-변수!AH32,"") | AI24: =IFERROR(AH24+AI20-변수!AI32,"") | AJ24: =AI24 | AK24: =IFERROR(AI24+AK20-변수!AK32,"") | AL24: =IFERROR(AK24+AL20-변수!AL32,"") | AM24: =IFERROR(AL24+AM20-변수!AM32,"") | AN24: =IFERROR(AM24+AN20-변수!AN32,"") | AO24: =AN24
A25: 지배주주지분 | B25: 재무상태 | C25: 억원 | D25: 지배주주지분 | E25: =IFERROR(VLOOKUP($D25,BS별도,MATCH(E$1,BS별도H,0),0)/100,"") | F25: 752.2 | G25: =IFERROR(VLOOKUP($D25,BS별도,MATCH(G$1,BS별도H,0),0)/100,"") | H25: =IFERROR(VLOOKUP($D25,BS별도,MATCH(H$1,BS별도H,0),0)/100,"") | I25: =IFERROR(VLOOKUP($D25,BS별도,MATCH(I$1,BS별도H,0),0)/100,"") | J25: =IFERROR(VLOOKUP($D25,BS별도,MATCH(J$1,BS별도H,0),0)/100,"") | K25: =J25 | L25: =IFERROR(VLOOKUP($D25,BS별도,MATCH(L$1,BS별도H,0),0)/100,"") | M25: =IFERROR(VLOOKUP($D25,BS별도,MATCH(M$1,BS별도H,0),0)/100,"") | N25: =IFERROR(VLOOKUP($D25,BS별도,MATCH(N$1,BS별도H,0),0)/100,"") | O25: =IFERROR(VLOOKUP($D25,BS별도,MATCH(O$1,BS별도H,0),0)/100,"") | P25: =O25 | Q25: =IFERROR(VLOOKUP($D25,BS별도,MATCH(Q$1,BS별도H,0),0)/100,"") | R25: =IFERROR(VLOOKUP($D25,BS별도,MATCH(R$1,BS별도H,0),0)/100,"") | S25: =IFERROR(VLOOKUP($D25,BS별도,MATCH(S$1,BS별도H,0),0)/100,"") | T25: =IFERROR(VLOOKUP($D25,BS별도,MATCH(T$1,BS별도H,0),0)/100,"") | U25: =T25 | V25: =IFERROR(VLOOKUP($D25,BS별도,MATCH(V$1,BS별도H,0),0)/100,"") | W25: =IFERROR(VLOOKUP($D25,BS별도,MATCH(W$1,BS별도H,0),0)/100,"") | X25: =IFERROR(VLOOKUP($D25,BS별도,MATCH(X$1,BS별도H,0),0)/100,"") | Y25: =IFERROR(VLOOKUP($D25,BS별도,MATCH(Y$1,BS별도H,0),0)/100,"") | Z25: =Y25 | AA25: =IFERROR(VLOOKUP($D25,BS별도,MATCH(AA$1,BS별도H,0),0)/100,"") | AB25: =IFERROR(VLOOKUP($D25,BS별도,MATCH(AB$1,BS별도H,0),0)/100,"") | AC25: =IFERROR(AB25+AC21-변수!AC33,"") | AD25: =IFERROR(AC25+AD21-변수!AD33,"") | AE25: =AD25 | AF25: =IFERROR(AD25+AF21-변수!AF33,"") | AG25: =IFERROR(AF25+AG21-변수!AG33,"") | AH25: =IFERROR(AG25+AH21-변수!AH33,"") | AI25: =IFERROR(AH25+AI21-변수!AI33,"") | AJ25: =AI25 | AK25: =IFERROR(AI25+AK21-변수!AK33,"") | AL25: =IFERROR(AK25+AL21-변수!AL33,"") | AM25: =IFERROR(AL25+AM21-변수!AM33,"") | AN25: =IFERROR(AM25+AN21-변수!AN33,"") | AO25: =AN25
A26: 총차입금 | B26: 재무상태 | C26: 억원 | D26: 총차입금 | E26: =IFERROR(VLOOKUP($D26,BS별도,MATCH(E$1,BS별도H,0),0)/100,"") | F26: 130 | G26: =IFERROR(VLOOKUP($D26,BS별도,MATCH(G$1,BS별도H,0),0)/100,"") | H26: =IFERROR(VLOOKUP($D26,BS별도,MATCH(H$1,BS별도H,0),0)/100,"") | I26: =IFERROR(VLOOKUP($D26,BS별도,MATCH(I$1,BS별도H,0),0)/100,"") | J26: =IFERROR(VLOOKUP($D26,BS별도,MATCH(J$1,BS별도H,0),0)/100,"") | K26: =J26 | L26: =IFERROR(VLOOKUP($D26,BS별도,MATCH(L$1,BS별도H,0),0)/100,"") | M26: =IFERROR(VLOOKUP($D26,BS별도,MATCH(M$1,BS별도H,0),0)/100,"") | N26: =IFERROR(VLOOKUP($D26,BS별도,MATCH(N$1,BS별도H,0),0)/100,"") | O26: =IFERROR(VLOOKUP($D26,BS별도,MATCH(O$1,BS별도H,0),0)/100,"") | P26: =O26 | Q26: =IFERROR(VLOOKUP($D26,BS별도,MATCH(Q$1,BS별도H,0),0)/100,"") | R26: =IFERROR(VLOOKUP($D26,BS별도,MATCH(R$1,BS별도H,0),0)/100,"") | S26: =IFERROR(VLOOKUP($D26,BS별도,MATCH(S$1,BS별도H,0),0)/100,"") | T26: =IFERROR(VLOOKUP($D26,BS별도,MATCH(T$1,BS별도H,0),0)/100,"") | U26: =T26 | V26: =IFERROR(VLOOKUP($D26,BS별도,MATCH(V$1,BS별도H,0),0)/100,"") | W26: =IFERROR(VLOOKUP($D26,BS별도,MATCH(W$1,BS별도H,0),0)/100,"") | X26: =IFERROR(VLOOKUP($D26,BS별도,MATCH(X$1,BS별도H,0),0)/100,"") | Y26: =IFERROR(VLOOKUP($D26,BS별도,MATCH(Y$1,BS별도H,0),0)/100,"") | Z26: =Y26 | AA26: =IFERROR(VLOOKUP($D26,BS별도,MATCH(AA$1,BS별도H,0),0)/100,"") | AB26: =IFERROR(VLOOKUP($D26,BS별도,MATCH(AB$1,BS별도H,0),0)/100,"") | AC26: =IFERROR(AB26*(1+변수!AC34),"") | AD26: =IFERROR(AC26*(1+변수!AD34),"") | AE26: =AD26 | AF26: =IFERROR(AD26*(1+변수!AF34),"") | AG26: =IFERROR(AF26*(1+변수!AG34),"") | AH26: =IFERROR(AG26*(1+변수!AH34),"") | AI26: =IFERROR(AH26*(1+변수!AI34),"") | AJ26: =AI26 | AK26: =IFERROR(AI26*(1+변수!AK34),"") | AL26: =IFERROR(AK26*(1+변수!AL34),"") | AM26: =IFERROR(AL26*(1+변수!AM34),"") | AN26: =IFERROR(AM26*(1+변수!AN34),"") | AO26: =AN26
A27: 순차입금 | B27: 재무상태 | C27: 억원 | D27: 순차입금 | E27: =IFERROR(VLOOKUP($D27,BS별도,MATCH(E$1,BS별도H,0),0)/100,"") | F27: 97.38 | G27: =IFERROR(VLOOKUP($D27,BS별도,MATCH(G$1,BS별도H,0),0)/100,"") | H27: =IFERROR(VLOOKUP($D27,BS별도,MATCH(H$1,BS별도H,0),0)/100,"") | I27: =IFERROR(VLOOKUP($D27,BS별도,MATCH(I$1,BS별도H,0),0)/100,"") | J27: =IFERROR(VLOOKUP($D27,BS별도,MATCH(J$1,BS별도H,0),0)/100,"") | K27: =J27 | L27: =IFERROR(VLOOKUP($D27,BS별도,MATCH(L$1,BS별도H,0),0)/100,"") | M27: =IFERROR(VLOOKUP($D27,BS별도,MATCH(M$1,BS별도H,0),0)/100,"") | N27: =IFERROR(VLOOKUP($D27,BS별도,MATCH(N$1,BS별도H,0),0)/100,"") | O27: =IFERROR(VLOOKUP($D27,BS별도,MATCH(O$1,BS별도H,0),0)/100,"") | P27: =O27 | Q27: =IFERROR(VLOOKUP($D27,BS별도,MATCH(Q$1,BS별도H,0),0)/100,"") | R27: =IFERROR(VLOOKUP($D27,BS별도,MATCH(R$1,BS별도H,0),0)/100,"") | S27: =IFERROR(VLOOKUP($D27,BS별도,MATCH(S$1,BS별도H,0),0)/100,"") | T27: =IFERROR(VLOOKUP($D27,BS별도,MATCH(T$1,BS별도H,0),0)/100,"") | U27: =T27 | V27: =IFERROR(VLOOKUP($D27,BS별도,MATCH(V$1,BS별도H,0),0)/100,"") | W27: =IFERROR(VLOOKUP($D27,BS별도,MATCH(W$1,BS별도H,0),0)/100,"") | X27: =IFERROR(VLOOKUP($D27,BS별도,MATCH(X$1,BS별도H,0),0)/100,"") | Y27: =IFERROR(VLOOKUP($D27,BS별도,MATCH(Y$1,BS별도H,0),0)/100,"") | Z27: =Y27 | AA27: =IFERROR(VLOOKUP($D27,BS별도,MATCH(AA$1,BS별도H,0),0)/100,"") | AB27: =IFERROR(VLOOKUP($D27,BS별도,MATCH(AB$1,BS별도H,0),0)/100,"") | AC27: =IFERROR(AB27*(1+변수!AC35),"") | AD27: =IFERROR(AC27*(1+변수!AD35),"") | AE27: =AD27 | AF27: =IFERROR(AD27*(1+변수!AF35),"") | AG27: =IFERROR(AF27*(1+변수!AG35),"") | AH27: =IFERROR(AG27*(1+변수!AH35),"") | AI27: =IFERROR(AH27*(1+변수!AI35),"") | AJ27: =AI27 | AK27: =IFERROR(AI27*(1+변수!AK35),"") | AL27: =IFERROR(AK27*(1+변수!AL35),"") | AM27: =IFERROR(AL27*(1+변수!AM35),"") | AN27: =IFERROR(AM27*(1+변수!AN35),"") | AO27: =AN27
A28: 이자발생자산 | B28: 재무상태 | C28: 억원 | D28: 이자발생자산 | E28: =IFERROR(VLOOKUP($D28,BS별도,MATCH(E$1,BS별도H,0),0)/100,"") | F28: 37.67 | G28: =IFERROR(VLOOKUP($D28,BS별도,MATCH(G$1,BS별도H,0),0)/100,"") | H28: =IFERROR(VLOOKUP($D28,BS별도,MATCH(H$1,BS별도H,0),0)/100,"") | I28: =IFERROR(VLOOKUP($D28,BS별도,MATCH(I$1,BS별도H,0),0)/100,"") | J28: =IFERROR(VLOOKUP($D28,BS별도,MATCH(J$1,BS별도H,0),0)/100,"") | K28: =J28 | L28: =IFERROR(VLOOKUP($D28,BS별도,MATCH(L$1,BS별도H,0),0)/100,"") | M28: =IFERROR(VLOOKUP($D28,BS별도,MATCH(M$1,BS별도H,0),0)/100,"") | N28: =IFERROR(VLOOKUP($D28,BS별도,MATCH(N$1,BS별도H,0),0)/100,"") | O28: =IFERROR(VLOOKUP($D28,BS별도,MATCH(O$1,BS별도H,0),0)/100,"") | P28: =O28 | Q28: =IFERROR(VLOOKUP($D28,BS별도,MATCH(Q$1,BS별도H,0),0)/100,"") | R28: =IFERROR(VLOOKUP($D28,BS별도,MATCH(R$1,BS별도H,0),0)/100,"") | S28: =IFERROR(VLOOKUP($D28,BS별도,MATCH(S$1,BS별도H,0),0)/100,"") | T28: =IFERROR(VLOOKUP($D28,BS별도,MATCH(T$1,BS별도H,0),0)/100,"") | U28: =T28 | V28: =IFERROR(VLOOKUP($D28,BS별도,MATCH(V$1,BS별도H,0),0)/100,"") | W28: =IFERROR(VLOOKUP($D28,BS별도,MATCH(W$1,BS별도H,0),0)/100,"") | X28: =IFERROR(VLOOKUP($D28,BS별도,MATCH(X$1,BS별도H,0),0)/100,"") | Y28: =IFERROR(VLOOKUP($D28,BS별도,MATCH(Y$1,BS별도H,0),0)/100,"") | Z28: =Y28 | AA28: =IFERROR(VLOOKUP($D28,BS별도,MATCH(AA$1,BS별도H,0),0)/100,"") | AB28: =IFERROR(VLOOKUP($D28,BS별도,MATCH(AB$1,BS별도H,0),0)/100,"") | AC28: =IFERROR(AB28*(1+변수!AC36),"") | AD28: =IFERROR(AC28*(1+변수!AD36),"") | AE28: =AD28 | AF28: =IFERROR(AD28*(1+변수!AF36),"") | AG28: =IFERROR(AF28*(1+변수!AG36),"") | AH28: =IFERROR(AG28*(1+변수!AH36),"") | AI28: =IFERROR(AH28*(1+변수!AI36),"") | AJ28: =AI28 | AK28: =IFERROR(AI28*(1+변수!AK36),"") | AL28: =IFERROR(AK28*(1+변수!AL36),"") | AM28: =IFERROR(AL28*(1+변수!AM36),"") | AN28: =IFERROR(AM28*(1+변수!AN36),"") | AO28: =AN28
A29: 현금및현금성자산 | B29: 재무상태 | C29: 억원 | D29: 현금및현금성자산 | E29: =IFERROR(VLOOKUP($D29,BS별도,MATCH(E$1,BS별도H,0),0)/100,"") | F29: 32.62 | G29: =IFERROR(VLOOKUP($D29,BS별도,MATCH(G$1,BS별도H,0),0)/100,"") | H29: =IFERROR(VLOOKUP($D29,BS별도,MATCH(H$1,BS별도H,0),0)/100,"") | I29: =IFERROR(VLOOKUP($D29,BS별도,MATCH(I$1,BS별도H,0),0)/100,"") | J29: =IFERROR(VLOOKUP($D29,BS별도,MATCH(J$1,BS별도H,0),0)/100,"") | K29: =J29 | L29: =IFERROR(VLOOKUP($D29,BS별도,MATCH(L$1,BS별도H,0),0)/100,"") | M29: =IFERROR(VLOOKUP($D29,BS별도,MATCH(M$1,BS별도H,0),0)/100,"") | N29: =IFERROR(VLOOKUP($D29,BS별도,MATCH(N$1,BS별도H,0),0)/100,"") | O29: =IFERROR(VLOOKUP($D29,BS별도,MATCH(O$1,BS별도H,0),0)/100,"") | P29: =O29 | Q29: =IFERROR(VLOOKUP($D29,BS별도,MATCH(Q$1,BS별도H,0),0)/100,"") | R29: =IFERROR(VLOOKUP($D29,BS별도,MATCH(R$1,BS별도H,0),0)/100,"") | S29: =IFERROR(VLOOKUP($D29,BS별도,MATCH(S$1,BS별도H,0),0)/100,"") | T29: =IFERROR(VLOOKUP($D29,BS별도,MATCH(T$1,BS별도H,0),0)/100,"") | U29: =T29 | V29: =IFERROR(VLOOKUP($D29,BS별도,MATCH(V$1,BS별도H,0),0)/100,"") | W29: =IFERROR(VLOOKUP($D29,BS별도,MATCH(W$1,BS별도H,0),0)/100,"") | X29: =IFERROR(VLOOKUP($D29,BS별도,MATCH(X$1,BS별도H,0),0)/100,"") | Y29: =IFERROR(VLOOKUP($D29,BS별도,MATCH(Y$1,BS별도H,0),0)/100,"") | Z29: =Y29 | AA29: =IFERROR(VLOOKUP($D29,BS별도,MATCH(AA$1,BS별도H,0),0)/100,"") | AB29: =IFERROR(VLOOKUP($D29,BS별도,MATCH(AB$1,BS별도H,0),0)/100,"") | AE29: =AD29 | AJ29: =AI29 | AO29: =AN29
A30: CAPEX | B30: 현금흐름 | C30: 억원 | D30: CAPEX | E30: =IFERROR(VLOOKUP($D30,BS별도,MATCH(E$1,BS별도H,0),0)/100,"") | G30: =IFERROR(VLOOKUP($D30,BS별도,MATCH(G$1,BS별도H,0),0)/100,"") | H30: =IFERROR(VLOOKUP($D30,BS별도,MATCH(H$1,BS별도H,0),0)/100,"") | I30: =IFERROR(VLOOKUP($D30,BS별도,MATCH(I$1,BS별도H,0),0)/100,"") | J30: =IFERROR(VLOOKUP($D30,BS별도,MATCH(J$1,BS별도H,0),0)/100,"") | K30: =SUM(G30:J30) | L30: =IFERROR(VLOOKUP($D30,BS별도,MATCH(L$1,BS별도H,0),0)/100,"") | M30: =IFERROR(VLOOKUP($D30,BS별도,MATCH(M$1,BS별도H,0),0)/100,"") | N30: =IFERROR(VLOOKUP($D30,BS별도,MATCH(N$1,BS별도H,0),0)/100,"") | O30: =IFERROR(VLOOKUP($D30,BS별도,MATCH(O$1,BS별도H,0),0)/100,"") | P30: =SUM(L30:O30) | Q30: =IFERROR(VLOOKUP($D30,BS별도,MATCH(Q$1,BS별도H,0),0)/100,"") | R30: =IFERROR(VLOOKUP($D30,BS별도,MATCH(R$1,BS별도H,0),0)/100,"") | S30: =IFERROR(VLOOKUP($D30,BS별도,MATCH(S$1,BS별도H,0),0)/100,"") | T30: =IFERROR(VLOOKUP($D30,BS별도,MATCH(T$1,BS별도H,0),0)/100,"") | U30: =SUM(Q30:T30) | V30: =IFERROR(VLOOKUP($D30,BS별도,MATCH(V$1,BS별도H,0),0)/100,"") | W30: =IFERROR(VLOOKUP($D30,BS별도,MATCH(W$1,BS별도H,0),0)/100,"") | X30: =IFERROR(VLOOKUP($D30,BS별도,MATCH(X$1,BS별도H,0),0)/100,"") | Y30: =IFERROR(VLOOKUP($D30,BS별도,MATCH(Y$1,BS별도H,0),0)/100,"") | Z30: =SUM(V30:Y30) | AC30: =IFERROR(X30*(1+변수!AC38),"") | AD30: =IFERROR(Y30*(1+변수!AD38),"") | AE30: =SUM(AA30:AD30) | AF30: =IFERROR(AD30*(1+변수!AF38),"") | AG30: =IFERROR(AF30*(1+변수!AG38),"") | AH30: =IFERROR(AC30*(1+변수!AH38),"") | AI30: =IFERROR(AD30*(1+변수!AI38),"") | AJ30: =SUM(AF30:AI30) | AK30: =IFERROR(AF30*(1+변수!AK38),"") | AL30: =IFERROR(AG30*(1+변수!AL38),"") | AM30: =IFERROR(AH30*(1+변수!AM38),"") | AN30: =IFERROR(AI30*(1+변수!AN38),"") | AO30: =SUM(AK30:AN30)
A31: 영업활동현금흐름 | B31: 현금흐름 | C31: 억원 | D31: 영업활동으로인한현금흐름 | E31: =IFERROR(VLOOKUP($D31,BS별도,MATCH(E$1,BS별도H,0),0)/100,"") | G31: =IFERROR(VLOOKUP($D31,BS별도,MATCH(G$1,BS별도H,0),0)/100,"") | H31: =IFERROR(VLOOKUP($D31,BS별도,MATCH(H$1,BS별도H,0),0)/100,"") | I31: =IFERROR(VLOOKUP($D31,BS별도,MATCH(I$1,BS별도H,0),0)/100,"") | J31: =IFERROR(VLOOKUP($D31,BS별도,MATCH(J$1,BS별도H,0),0)/100,"") | K31: =SUM(G31:J31) | L31: =IFERROR(VLOOKUP($D31,BS별도,MATCH(L$1,BS별도H,0),0)/100,"") | M31: =IFERROR(VLOOKUP($D31,BS별도,MATCH(M$1,BS별도H,0),0)/100,"") | N31: =IFERROR(VLOOKUP($D31,BS별도,MATCH(N$1,BS별도H,0),0)/100,"") | O31: =IFERROR(VLOOKUP($D31,BS별도,MATCH(O$1,BS별도H,0),0)/100,"") | P31: =SUM(L31:O31) | Q31: =IFERROR(VLOOKUP($D31,BS별도,MATCH(Q$1,BS별도H,0),0)/100,"") | R31: =IFERROR(VLOOKUP($D31,BS별도,MATCH(R$1,BS별도H,0),0)/100,"") | S31: =IFERROR(VLOOKUP($D31,BS별도,MATCH(S$1,BS별도H,0),0)/100,"") | T31: =IFERROR(VLOOKUP($D31,BS별도,MATCH(T$1,BS별도H,0),0)/100,"") | U31: =SUM(Q31:T31) | V31: =IFERROR(VLOOKUP($D31,BS별도,MATCH(V$1,BS별도H,0),0)/100,"") | W31: =IFERROR(VLOOKUP($D31,BS별도,MATCH(W$1,BS별도H,0),0)/100,"") | X31: =IFERROR(VLOOKUP($D31,BS별도,MATCH(X$1,BS별도H,0),0)/100,"") | Y31: =IFERROR(VLOOKUP($D31,BS별도,MATCH(Y$1,BS별도H,0),0)/100,"") | Z31: =SUM(V31:Y31) | AA31: =IFERROR(VLOOKUP($D31,BS별도,MATCH(AA$1,BS별도H,0),0)/100,"") | AB31: =IFERROR(VLOOKUP($D31,BS별도,MATCH(AB$1,BS별도H,0),0)/100,"") | AE31: =SUM(AA31:AD31) | AJ31: =SUM(AF31:AI31) | AO31: =SUM(AK31:AN31)
A32: 주식수 | B32: 주당 | C32: 백만주 | D32: 유통주식수 | E32: 10.206 | F32: =E32 | G32: 10.206 | H32: 10.206 | I32: 10.206 | J32: 10.206 | K32: =J32 | L32: 10.206 | M32: 10.833 | N32: 10.833 | O32: 12.323 | P32: =O32 | Q32: 12.323 | R32: 13.361 | S32: 13.361 | T32: 15.925 | U32: =T32 | V32: 15.925 | W32: 16.094 | X32: 16.094 | Y32: 16.094 | Z32: =Y32 | AA32: 16.094 | AB32: 16.094 | AC32: =IFERROR(AB32*(1+변수!AC40),"") | AD32: =IFERROR(AC32*(1+변수!AD40),"") | AE32: =AD32 | AF32: =IFERROR(AD32*(1+변수!AF40),"") | AG32: =IFERROR(AF32*(1+변수!AG40),"") | AH32: =IFERROR(AG32*(1+변수!AH40),"") | AI32: =IFERROR(AH32*(1+변수!AI40),"") | AJ32: =AI32 | AK32: =IFERROR(AI32*(1+변수!AK40),"") | AL32: =IFERROR(AK32*(1+변수!AL40),"") | AM32: =IFERROR(AL32*(1+변수!AM40),"") | AN32: =IFERROR(AM32*(1+변수!AN40),"") | AO32: =AN32
A33: EPS | B33: 주당 | C33: 원 | D33: EPS | E33: =IFERROR(E21*100/E32,"") | G33: =IFERROR(G21*100/G32,"") | H33: =IFERROR(H21*100/H32,"") | I33: =IFERROR(I21*100/I32,"") | J33: =IFERROR(J21*100/J32,"") | K33: =SUM(G33:J33) | L33: =IFERROR(L21*100/L32,"") | M33: =IFERROR(M21*100/M32,"") | N33: =IFERROR(N21*100/N32,"") | O33: =IFERROR(O21*100/O32,"") | P33: =SUM(L33:O33) | Q33: =IFERROR(Q21*100/Q32,"") | R33: =IFERROR(R21*100/R32,"") | S33: =IFERROR(S21*100/S32,"") | T33: =IFERROR(T21*100/T32,"") | U33: =SUM(Q33:T33) | V33: =IFERROR(V21*100/V32,"") | W33: =IFERROR(W21*100/W32,"") | X33: =IFERROR(X21*100/X32,"") | Y33: =IFERROR(Y21*100/Y32,"") | Z33: =SUM(V33:Y33) | AA33: =IFERROR(AA21*100/AA32,"") | AB33: =IFERROR(AB21*100/AB32,"") | AC33: =IFERROR(AC21*100/AC32,"") | AD33: =IFERROR(AD21*100/AD32,"") | AE33: =SUM(AA33:AD33) | AF33: =IFERROR(AF21*100/AF32,"") | AG33: =IFERROR(AG21*100/AG32,"") | AH33: =IFERROR(AH21*100/AH32,"") | AI33: =IFERROR(AI21*100/AI32,"") | AJ33: =SUM(AF33:AI33) | AK33: =IFERROR(AK21*100/AK32,"") | AL33: =IFERROR(AL21*100/AL32,"") | AM33: =IFERROR(AM21*100/AM32,"") | AN33: =IFERROR(AN21*100/AN32,"") | AO33: =SUM(AK33:AN33)
A34: BPS | B34: 주당 | C34: 원 | D34: BPS | E34: =IFERROR(E25*100/E32,"") | F34: =E34 | G34: =IFERROR(G25*100/G32,"") | H34: =IFERROR(H25*100/H32,"") | I34: =IFERROR(I25*100/I32,"") | J34: =IFERROR(J25*100/J32,"") | K34: =J34 | L34: =IFERROR(L25*100/L32,"") | M34: =IFERROR(M25*100/M32,"") | N34: =IFERROR(N25*100/N32,"") | O34: =IFERROR(O25*100/O32,"") | P34: =O34 | Q34: =IFERROR(Q25*100/Q32,"") | R34: =IFERROR(R25*100/R32,"") | S34: =IFERROR(S25*100/S32,"") | T34: =IFERROR(T25*100/T32,"") | U34: =T34 | V34: =IFERROR(V25*100/V32,"") | W34: =IFERROR(W25*100/W32,"") | X34: =IFERROR(X25*100/X32,"") | Y34: =IFERROR(Y25*100/Y32,"") | Z34: =Y34 | AA34: =IFERROR(AA25*100/AA32,"") | AB34: =IFERROR(AB25*100/AB32,"") | AC34: =IFERROR(AC25*100/AC32,"") | AD34: =IFERROR(AD25*100/AD32,"") | AE34: =AD34 | AF34: =IFERROR(AF25*100/AF32,"") | AG34: =IFERROR(AG25*100/AG32,"") | AH34: =IFERROR(AH25*100/AH32,"") | AI34: =IFERROR(AI25*100/AI32,"") | AJ34: =AI34 | AK34: =IFERROR(AK25*100/AK32,"") | AL34: =IFERROR(AL25*100/AL32,"") | AM34: =IFERROR(AM25*100/AM32,"") | AN34: =IFERROR(AN25*100/AN32,"") | AO34: =AN34
A35: DPS | B35: 주당 | C35: 원 | D35: DPS(보통주) | E35: 0 | F35: 0 | J35: 0 | K35: =SUM(G35:J35) | O35: 0 | P35: =SUM(L35:O35) | T35: 0 | U35: =SUM(Q35:T35) | Y35: 0 | Z35: =SUM(V35:Y35) | AD35: =변수!AD41 | AE35: =SUM(AA35:AD35) | AI35: =변수!AI41 | AJ35: =SUM(AF35:AI35) | AN35: =변수!AN41 | AO35: =SUM(AK35:AN35)
A36: PBR | B36: 주당 | C36: 배 | D36: PBR | E36: =IFERROR(변수!E18/E34,"") | F36: =E36 | G36: =IFERROR(변수!G18/G34,"") | H36: =IFERROR(변수!H18/H34,"") | I36: =IFERROR(변수!I18/I34,"") | J36: =IFERROR(변수!J18/J34,"") | K36: =J36 | L36: =IFERROR(변수!L18/L34,"") | M36: =IFERROR(변수!M18/M34,"") | N36: =IFERROR(변수!N18/N34,"") | O36: =IFERROR(변수!O18/O34,"") | P36: =O36 | Q36: =IFERROR(변수!Q18/Q34,"") | R36: =IFERROR(변수!R18/R34,"") | S36: =IFERROR(변수!S18/S34,"") | T36: =IFERROR(변수!T18/T34,"") | U36: =T36 | V36: =IFERROR(변수!V18/V34,"") | Z36: =Y36 | AC36: =IFERROR(변수!$D$44/AC34,"") | AD36: =IFERROR(변수!$D$44/AD34,"") | AE36: =AD36 | AF36: =IFERROR(변수!$D$44/AF34,"") | AG36: =IFERROR(변수!$D$44/AG34,"") | AH36: =IFERROR(변수!$D$44/AH34,"") | AI36: =IFERROR(변수!$D$44/AI34,"") | AJ36: =AI36 | AK36: =IFERROR(변수!$D$44/AK34,"") | AL36: =IFERROR(변수!$D$44/AL34,"") | AM36: =IFERROR(변수!$D$44/AM34,"") | AN36: =IFERROR(변수!$D$44/AN34,"") | AO36: =AN36
A37: 매출전사 | B37: 사업부 | C37: 억원 | D37: 매출 전사(부문 미분리) | E37: 159.93 | G37: 45.7 | H37: 82.47 | I37: 75.9 | J37: 114.95 | K37: =SUM(G37:J37) | L37: 75.41 | M37: 95.67 | N37: 76.86 | O37: 85.45 | P37: =SUM(L37:O37) | Q37: 58.22 | R37: 97.07 | S37: 65.33 | T37: 140.41 | U37: =SUM(Q37:T37) | V37: 47.06 | W37: 81.17 | X37: 90.64 | Y37: 113.74 | Z37: =SUM(V37:Y37) | AA37: 50.77 | AB37: 61.26 | AC37: =IFERROR(AC5,"") | AD37: =IFERROR(AD5,"") | AE37: =SUM(AA37:AD37) | AF37: =IFERROR(AF5,"") | AG37: =IFERROR(AG5,"") | AH37: =IFERROR(AH5,"") | AI37: =IFERROR(AI5,"") | AJ37: =SUM(AF37:AI37) | AK37: =IFERROR(AK5,"") | AL37: =IFERROR(AL5,"") | AM37: =IFERROR(AM5,"") | AN37: =IFERROR(AN5,"") | AO37: =SUM(AK37:AN37)
A38: OP전사 | B38: 사업부 | C38: 억원 | D38: OP 전사(부문 미분리) | E38: 40.77 | G38: -34.99 | H38: -68.53 | I38: -14.49 | J38: -83.45 | K38: =SUM(G38:J38) | L38: -26.24 | M38: -1.68 | N38: -14 | O38: -19.34 | P38: =SUM(L38:O38) | Q38: -12.64 | R38: -16.12 | S38: -7.92 | T38: -22.65 | U38: =SUM(Q38:T38) | V38: -13.25 | W38: 14.29 | X38: -4.86 | Y38: 1.88 | Z38: =SUM(V38:Y38) | AA38: -3.23 | AB38: 8.69 | AC38: =IFERROR(AC9,"") | AD38: =IFERROR(AD9,"") | AE38: =SUM(AA38:AD38) | AF38: =IFERROR(AF9,"") | AG38: =IFERROR(AG9,"") | AH38: =IFERROR(AH9,"") | AI38: =IFERROR(AI9,"") | AJ38: =SUM(AF38:AI38) | AK38: =IFERROR(AK9,"") | AL38: =IFERROR(AL9,"") | AM38: =IFERROR(AM9,"") | AN38: =IFERROR(AN9,"") | AO38: =SUM(AK38:AN38)
B39: 비율(참고)
A40: NPM | C40: % | D40: 지배주주순이익 / 매출액 | E40: =IFERROR(E21/E5,"") | F40: =IFERROR(F21/F5,"") | G40: =IFERROR(G21/G5,"") | H40: =IFERROR(H21/H5,"") | I40: =IFERROR(I21/I5,"") | J40: =IFERROR(J21/J5,"") | K40: =IFERROR(K21/K5,"") | L40: =IFERROR(L21/L5,"") | ... AO40: =IFERROR(AO21/AO5,"")
A41: 매출원가율 | C41: % | D41: 매출원가 / 매출액 | E41: =IFERROR(E6/E5,"") | F41: =IFERROR(F6/F5,"") | G41: =IFERROR(G6/G5,"") | H41: =IFERROR(H6/H5,"") | I41: =IFERROR(I6/I5,"") | J41: =IFERROR(J6/J5,"") | K41: =IFERROR(K6/K5,"") | L41: =IFERROR(L6/L5,"") | ... AO41: =IFERROR(AO6/AO5,"")
A42: 판관비율 | C42: % | D42: 판관비 / 매출액 | E42: =IFERROR(E8/E5,"") | F42: =IFERROR(F8/F5,"") | G42: =IFERROR(G8/G5,"") | H42: =IFERROR(H8/H5,"") | I42: =IFERROR(I8/I5,"") | J42: =IFERROR(J8/J5,"") | K42: =IFERROR(K8/K5,"") | L42: =IFERROR(L8/L5,"") | ... AO42: =IFERROR(AO8/AO5,"")

Sheet 분기
C1: 이름: 분기H — subQ 를 이름으로 VLOOKUP(억원) | E1: 4Q21 | F1: 1Q22 | G1: 2Q22 | H1: 3Q22 | I1: 4Q22 | J1: 1Q23 | K1: 2Q23 | L1: 3Q23 | M1: 4Q23 | N1: 1Q24 | O1: 2Q24 | P1: 3Q24 | Q1: 4Q24 | R1: 1Q25 | S1: 2Q25 | T1: 3Q25 | U1: 4Q25 | V1: 1Q26 | W1: 2Q26 | X1: 3Q26 | Y1: 4Q26 | Z1: 1Q27 | AA1: 2Q27 | AB1: 3Q27 | AC1: 4Q27 | AD1: 1Q28 | AE1: 2Q28 | AF1: 3Q28 | AG1: 4Q28
C2: 종가: | D2: =변수!D44
C3: 기준일: | D3: 20261013 | E3: 1 | F3: 2 | G3: 3 | H3: 4 | I3: 5 | J3: 6 | K3: 7 | L3: 8 | M3: 9 | N3: 10 | O3: 11 | P3: 12 | Q3: 13 | R3: 14 | S3: 15 | T3: 16 | U3: 17 | V3: 18 | W3: 19 | X3: 20 | Y3: 21 | Z3: 22 | AA3: 23 | AB3: 24 | AC3: 25 | AD3: 26 | AE3: 27 | AF3: 28 | AG3: 29
E4: 2021.12 | F4: 2022.03 | G4: 2022.06 | H4: 2022.09 | I4: 2022.12 | J4: 2023.03 | K4: 2023.06 | L4: 2023.09 | M4: 2023.12 | N4: 2024.03 | O4: 2024.06 | P4: 2024.09 | Q4: 2024.12 | R4: 2025.03 | S4: 2025.06 | T4: 2025.09 | U4: 2025.12 | V4: 2026.03 | W4: 2026.06 | X4: 2026.09 | Y4: 2026.12 | Z4: 2027.03 | AA4: 2027.06 | AB4: 2027.09 | AC4: 2027.12 | AD4: 2028.03 | AE4: 2028.06 | AF4: 2028.09 | AG4: 2028.12
A5: 매출액 | D5: 매출액 | E5: =IFERROR(VLOOKUP($A5,subQ,MATCH(E$1,SUBQH,0),0),"") | F5: =IFERROR(VLOOKUP($A5,subQ,MATCH(F$1,SUBQH,0),0),"") | G5: =IFERROR(VLOOKUP($A5,subQ,MATCH(G$1,SUBQH,0),0),"") | H5: =IFERROR(VLOOKUP($A5,subQ,MATCH(H$1,SUBQH,0),0),"") | I5: =IFERROR(VLOOKUP($A5,subQ,MATCH(I$1,SUBQH,0),0),"") | J5: =IFERROR(VLOOKUP($A5,subQ,MATCH(J$1,SUBQH,0),0),"") | K5: =IFERROR(VLOOKUP($A5,subQ,MATCH(K$1,SUBQH,0),0),"") | L5: =IFERROR(VLOOKUP($A5,subQ,MATCH(L$1,SUBQH,0),0),"") | ... AG5: =IFERROR(VLOOKUP($A5,subQ,MATCH(AG$1,SUBQH,0),0),"")
A6: 매출원가 | D6: 매출원가 | E6: =IFERROR(VLOOKUP($A6,subQ,MATCH(E$1,SUBQH,0),0),"") | F6: =IFERROR(VLOOKUP($A6,subQ,MATCH(F$1,SUBQH,0),0),"") | G6: =IFERROR(VLOOKUP($A6,subQ,MATCH(G$1,SUBQH,0),0),"") | H6: =IFERROR(VLOOKUP($A6,subQ,MATCH(H$1,SUBQH,0),0),"") | I6: =IFERROR(VLOOKUP($A6,subQ,MATCH(I$1,SUBQH,0),0),"") | J6: =IFERROR(VLOOKUP($A6,subQ,MATCH(J$1,SUBQH,0),0),"") | K6: =IFERROR(VLOOKUP($A6,subQ,MATCH(K$1,SUBQH,0),0),"") | L6: =IFERROR(VLOOKUP($A6,subQ,MATCH(L$1,SUBQH,0),0),"") | ... AG6: =IFERROR(VLOOKUP($A6,subQ,MATCH(AG$1,SUBQH,0),0),"")
A7: 매출총이익 | D7: 매출총이익 | E7: =IFERROR(VLOOKUP($A7,subQ,MATCH(E$1,SUBQH,0),0),"") | F7: =IFERROR(VLOOKUP($A7,subQ,MATCH(F$1,SUBQH,0),0),"") | G7: =IFERROR(VLOOKUP($A7,subQ,MATCH(G$1,SUBQH,0),0),"") | H7: =IFERROR(VLOOKUP($A7,subQ,MATCH(H$1,SUBQH,0),0),"") | I7: =IFERROR(VLOOKUP($A7,subQ,MATCH(I$1,SUBQH,0),0),"") | J7: =IFERROR(VLOOKUP($A7,subQ,MATCH(J$1,SUBQH,0),0),"") | K7: =IFERROR(VLOOKUP($A7,subQ,MATCH(K$1,SUBQH,0),0),"") | L7: =IFERROR(VLOOKUP($A7,subQ,MATCH(L$1,SUBQH,0),0),"") | ... AG7: =IFERROR(VLOOKUP($A7,subQ,MATCH(AG$1,SUBQH,0),0),"")
A8: 판관비 | D8: 판매비와관리비 | E8: =IFERROR(VLOOKUP($A8,subQ,MATCH(E$1,SUBQH,0),0),"") | F8: =IFERROR(VLOOKUP($A8,subQ,MATCH(F$1,SUBQH,0),0),"") | G8: =IFERROR(VLOOKUP($A8,subQ,MATCH(G$1,SUBQH,0),0),"") | H8: =IFERROR(VLOOKUP($A8,subQ,MATCH(H$1,SUBQH,0),0),"") | I8: =IFERROR(VLOOKUP($A8,subQ,MATCH(I$1,SUBQH,0),0),"") | J8: =IFERROR(VLOOKUP($A8,subQ,MATCH(J$1,SUBQH,0),0),"") | K8: =IFERROR(VLOOKUP($A8,subQ,MATCH(K$1,SUBQH,0),0),"") | L8: =IFERROR(VLOOKUP($A8,subQ,MATCH(L$1,SUBQH,0),0),"") | ... AG8: =IFERROR(VLOOKUP($A8,subQ,MATCH(AG$1,SUBQH,0),0),"")
A9: 영업이익 | D9: 영업이익 | E9: =IFERROR(VLOOKUP($A9,subQ,MATCH(E$1,SUBQH,0),0),"") | F9: =IFERROR(VLOOKUP($A9,subQ,MATCH(F$1,SUBQH,0),0),"") | G9: =IFERROR(VLOOKUP($A9,subQ,MATCH(G$1,SUBQH,0),0),"") | H9: =IFERROR(VLOOKUP($A9,subQ,MATCH(H$1,SUBQH,0),0),"") | I9: =IFERROR(VLOOKUP($A9,subQ,MATCH(I$1,SUBQH,0),0),"") | J9: =IFERROR(VLOOKUP($A9,subQ,MATCH(J$1,SUBQH,0),0),"") | K9: =IFERROR(VLOOKUP($A9,subQ,MATCH(K$1,SUBQH,0),0),"") | L9: =IFERROR(VLOOKUP($A9,subQ,MATCH(L$1,SUBQH,0),0),"") | ... AG9: =IFERROR(VLOOKUP($A9,subQ,MATCH(AG$1,SUBQH,0),0),"")
A10: OPM | D10: 영업이익률 | E10: =IFERROR(VLOOKUP($A10,subQ,MATCH(E$1,SUBQH,0),0),"") | F10: =IFERROR(VLOOKUP($A10,subQ,MATCH(F$1,SUBQH,0),0),"") | G10: =IFERROR(VLOOKUP($A10,subQ,MATCH(G$1,SUBQH,0),0),"") | H10: =IFERROR(VLOOKUP($A10,subQ,MATCH(H$1,SUBQH,0),0),"") | I10: =IFERROR(VLOOKUP($A10,subQ,MATCH(I$1,SUBQH,0),0),"") | J10: =IFERROR(VLOOKUP($A10,subQ,MATCH(J$1,SUBQH,0),0),"") | K10: =IFERROR(VLOOKUP($A10,subQ,MATCH(K$1,SUBQH,0),0),"") | L10: =IFERROR(VLOOKUP($A10,subQ,MATCH(L$1,SUBQH,0),0),"") | ... AG10: =IFERROR(VLOOKUP($A10,subQ,MATCH(AG$1,SUBQH,0),0),"")
A11: 금융손익 | D11: 금융손익(이자·환 포함) | E11: =IFERROR(VLOOKUP($A11,subQ,MATCH(E$1,SUBQH,0),0),"") | F11: =IFERROR(VLOOKUP($A11,subQ,MATCH(F$1,SUBQH,0),0),"") | G11: =IFERROR(VLOOKUP($A11,subQ,MATCH(G$1,SUBQH,0),0),"") | H11: =IFERROR(VLOOKUP($A11,subQ,MATCH(H$1,SUBQH,0),0),"") | I11: =IFERROR(VLOOKUP($A11,subQ,MATCH(I$1,SUBQH,0),0),"") | J11: =IFERROR(VLOOKUP($A11,subQ,MATCH(J$1,SUBQH,0),0),"") | K11: =IFERROR(VLOOKUP($A11,subQ,MATCH(K$1,SUBQH,0),0),"") | L11: =IFERROR(VLOOKUP($A11,subQ,MATCH(L$1,SUBQH,0),0),"") | ... AG11: =IFERROR(VLOOKUP($A11,subQ,MATCH(AG$1,SUBQH,0),0),"")
A12: 이자손익 | D12: 이자손익(이자수익 − 이자비용) | E12: =IFERROR(VLOOKUP($A12,subQ,MATCH(E$1,SUBQH,0),0),"") | F12: =IFERROR(VLOOKUP($A12,subQ,MATCH(F$1,SUBQH,0),0),"") | G12: =IFERROR(VLOOKUP($A12,subQ,MATCH(G$1,SUBQH,0),0),"") | H12: =IFERROR(VLOOKUP($A12,subQ,MATCH(H$1,SUBQH,0),0),"") | I12: =IFERROR(VLOOKUP($A12,subQ,MATCH(I$1,SUBQH,0),0),"") | J12: =IFERROR(VLOOKUP($A12,subQ,MATCH(J$1,SUBQH,0),0),"") | K12: =IFERROR(VLOOKUP($A12,subQ,MATCH(K$1,SUBQH,0),0),"") | L12: =IFERROR(VLOOKUP($A12,subQ,MATCH(L$1,SUBQH,0),0),"") | ... AG12: =IFERROR(VLOOKUP($A12,subQ,MATCH(AG$1,SUBQH,0),0),"")
A13: 외환손익 | D13: 외환손익(실적만; 추정 환효과는 환관련손익) | E13: =IFERROR(VLOOKUP($A13,subQ,MATCH(E$1,SUBQH,0),0),"") | F13: =IFERROR(VLOOKUP($A13,subQ,MATCH(F$1,SUBQH,0),0),"") | G13: =IFERROR(VLOOKUP($A13,subQ,MATCH(G$1,SUBQH,0),0),"") | H13: =IFERROR(VLOOKUP($A13,subQ,MATCH(H$1,SUBQH,0),0),"") | I13: =IFERROR(VLOOKUP($A13,subQ,MATCH(I$1,SUBQH,0),0),"") | J13: =IFERROR(VLOOKUP($A13,subQ,MATCH(J$1,SUBQH,0),0),"") | K13: =IFERROR(VLOOKUP($A13,subQ,MATCH(K$1,SUBQH,0),0),"") | L13: =IFERROR(VLOOKUP($A13,subQ,MATCH(L$1,SUBQH,0),0),"") | ... AG13: =IFERROR(VLOOKUP($A13,subQ,MATCH(AG$1,SUBQH,0),0),"")
A14: 파생상품손익 | D14: 파생상품손익 | E14: =IFERROR(VLOOKUP($A14,subQ,MATCH(E$1,SUBQH,0),0),"") | F14: =IFERROR(VLOOKUP($A14,subQ,MATCH(F$1,SUBQH,0),0),"") | G14: =IFERROR(VLOOKUP($A14,subQ,MATCH(G$1,SUBQH,0),0),"") | H14: =IFERROR(VLOOKUP($A14,subQ,MATCH(H$1,SUBQH,0),0),"") | I14: =IFERROR(VLOOKUP($A14,subQ,MATCH(I$1,SUBQH,0),0),"") | J14: =IFERROR(VLOOKUP($A14,subQ,MATCH(J$1,SUBQH,0),0),"") | K14: =IFERROR(VLOOKUP($A14,subQ,MATCH(K$1,SUBQH,0),0),"") | L14: =IFERROR(VLOOKUP($A14,subQ,MATCH(L$1,SUBQH,0),0),"") | ... AG14: =IFERROR(VLOOKUP($A14,subQ,MATCH(AG$1,SUBQH,0),0),"")
A15: 기타금융손익 | D15: 기타금융손익(금융손익 잔차) | E15: =IFERROR(VLOOKUP($A15,subQ,MATCH(E$1,SUBQH,0),0),"") | F15: =IFERROR(VLOOKUP($A15,subQ,MATCH(F$1,SUBQH,0),0),"") | G15: =IFERROR(VLOOKUP($A15,subQ,MATCH(G$1,SUBQH,0),0),"") | H15: =IFERROR(VLOOKUP($A15,subQ,MATCH(H$1,SUBQH,0),0),"") | I15: =IFERROR(VLOOKUP($A15,subQ,MATCH(I$1,SUBQH,0),0),"") | J15: =IFERROR(VLOOKUP($A15,subQ,MATCH(J$1,SUBQH,0),0),"") | K15: =IFERROR(VLOOKUP($A15,subQ,MATCH(K$1,SUBQH,0),0),"") | L15: =IFERROR(VLOOKUP($A15,subQ,MATCH(L$1,SUBQH,0),0),"") | ... AG15: =IFERROR(VLOOKUP($A15,subQ,MATCH(AG$1,SUBQH,0),0),"")
A16: 기타영업외손익 | D16: 기타영업외손익 | E16: =IFERROR(VLOOKUP($A16,subQ,MATCH(E$1,SUBQH,0),0),"") | F16: =IFERROR(VLOOKUP($A16,subQ,MATCH(F$1,SUBQH,0),0),"") | G16: =IFERROR(VLOOKUP($A16,subQ,MATCH(G$1,SUBQH,0),0),"") | H16: =IFERROR(VLOOKUP($A16,subQ,MATCH(H$1,SUBQH,0),0),"") | I16: =IFERROR(VLOOKUP($A16,subQ,MATCH(I$1,SUBQH,0),0),"") | J16: =IFERROR(VLOOKUP($A16,subQ,MATCH(J$1,SUBQH,0),0),"") | K16: =IFERROR(VLOOKUP($A16,subQ,MATCH(K$1,SUBQH,0),0),"") | L16: =IFERROR(VLOOKUP($A16,subQ,MATCH(L$1,SUBQH,0),0),"") | ... AG16: =IFERROR(VLOOKUP($A16,subQ,MATCH(AG$1,SUBQH,0),0),"")
... A39: NPM | D39: NPM | E39: =IFERROR(VLOOKUP($A39,subQ,MATCH(E$1,SUBQH,0),0),"") | F39: =IFERROR(VLOOKUP($A39,subQ,MATCH(F$1,SUBQH,0),0),"") | G39: =IFERROR(VLOOKUP($A39,subQ,MATCH(G$1,SUBQH,0),0),"") | H39: =IFERROR(VLOOKUP($A39,subQ,MATCH(H$1,SUBQH,0),0),"") | I39: =IFERROR(VLOOKUP($A39,subQ,MATCH(I$1,SUBQH,0),0),"") | J39: =IFERROR(VLOOKUP($A39,subQ,MATCH(J$1,SUBQH,0),0),"") | K39: =IFERROR(VLOOKUP($A39,subQ,MATCH(K$1,SUBQH,0),0),"") | L39: =IFERROR(VLOOKUP($A39,subQ,MATCH(L$1,SUBQH,0),0),"") | ... AG39: =IFERROR(VLOOKUP($A39,subQ,MATCH(AG$1,SUBQH,0),0),"")
A40: 매출액 YoY | D40: 매출액 YoY | I40: =IFERROR(I5/E5-1,"") | J40: =IFERROR(J5/F5-1,"") | K40: =IFERROR(K5/G5-1,"") | L40: =IFERROR(L5/H5-1,"") | M40: =IFERROR(M5/I5-1,"") | N40: =IFERROR(N5/J5-1,"") | O40: =IFERROR(O5/K5-1,"") | P40: =IFERROR(P5/L5-1,"") | ... AG40: =IFERROR(AG5/AC5-1,"")
A41: 영업이익 YoY | D41: 영업이익 YoY | I41: =IFERROR(I9/E9-1,"") | J41: =IFERROR(J9/F9-1,"") | K41: =IFERROR(K9/G9-1,"") | L41: =IFERROR(L9/H9-1,"") | M41: =IFERROR(M9/I9-1,"") | N41: =IFERROR(N9/J9-1,"") | O41: =IFERROR(O9/K9-1,"") | P41: =IFERROR(P9/L9-1,"") | ... AG41: =IFERROR(AG9/AC9-1,"")
A42: 지배주주순이익 YoY | D42: 지배주주순이익 YoY | I42: =IFERROR(I21/E21-1,"") | J42: =IFERROR(J21/F21-1,"") | K42: =IFERROR(K21/G21-1,"") | L42: =IFERROR(L21/H21-1,"") | M42: =IFERROR(M21/I21-1,"") | N42: =IFERROR(N21/J21-1,"") | O42: =IFERROR(O21/K21-1,"") | P42: =IFERROR(P21/L21-1,"") | ... AG42: =IFERROR(AG21/AC21-1,"")

Sheet 연간예상
C1: 이름: 연간예상H — subQ 를 이름으로 VLOOKUP(억원) | E1: 2021 | F1: 2022 | G1: 2023 | H1: 2024 | I1: 2025 | J1: 2026 | K1: 2027 | L1: 2028
C2: 종가: | D2: =변수!D44
C3: 기준일: | D3: 20261013 | E3: 1 | F3: 2 | G3: 3 | H3: 4 | I3: 5 | J3: 6 | K3: 7 | L3: 8
E4: 2021.12A | F4: 2022.12A | G4: 2023.12A | H4: 2024.12A | I4: 2025.12A | J4: 2026.12A | K4: 2027.12A | L4: 2028.12A
A5: 매출액 | D5: 매출액 | E5: =IFERROR(VLOOKUP($A5,subQ,MATCH(E$1,SUBQH,0),0),"") | F5: =IFERROR(VLOOKUP($A5,subQ,MATCH(F$1,SUBQH,0),0),"") | G5: =IFERROR(VLOOKUP($A5,subQ,MATCH(G$1,SUBQH,0),0),"") | H5: =IFERROR(VLOOKUP($A5,subQ,MATCH(H$1,SUBQH,0),0),"") | I5: =IFERROR(VLOOKUP($A5,subQ,MATCH(I$1,SUBQH,0),0),"") | J5: =IFERROR(VLOOKUP($A5,subQ,MATCH(J$1,SUBQH,0),0),"") | K5: =IFERROR(VLOOKUP($A5,subQ,MATCH(K$1,SUBQH,0),0),"") | L5: =IFERROR(VLOOKUP($A5,subQ,MATCH(L$1,SUBQH,0),0),"")
A6: 매출원가 | D6: 매출원가 | E6: =IFERROR(VLOOKUP($A6,subQ,MATCH(E$1,SUBQH,0),0),"") | F6: =IFERROR(VLOOKUP($A6,subQ,MATCH(F$1,SUBQH,0),0),"") | G6: =IFERROR(VLOOKUP($A6,subQ,MATCH(G$1,SUBQH,0),0),"") | H6: =IFERROR(VLOOKUP($A6,subQ,MATCH(H$1,SUBQH,0),0),"") | I6: =IFERROR(VLOOKUP($A6,subQ,MATCH(I$1,SUBQH,0),0),"") | J6: =IFERROR(VLOOKUP($A6,subQ,MATCH(J$1,SUBQH,0),0),"") | K6: =IFERROR(VLOOKUP($A6,subQ,MATCH(K$1,SUBQH,0),0),"") | L6: =IFERROR(VLOOKUP($A6,subQ,MATCH(L$1,SUBQH,0),0),"")
A7: 매출총이익 | D7: 매출총이익 | E7: =IFERROR(VLOOKUP($A7,subQ,MATCH(E$1,SUBQH,0),0),"") | F7: =IFERROR(VLOOKUP($A7,subQ,MATCH(F$1,SUBQH,0),0),"") | G7: =IFERROR(VLOOKUP($A7,subQ,MATCH(G$1,SUBQH,0),0),"") | H7: =IFERROR(VLOOKUP($A7,subQ,MATCH(H$1,SUBQH,0),0),"") | I7: =IFERROR(VLOOKUP($A7,subQ,MATCH(I$1,SUBQH,0),0),"") | J7: =IFERROR(VLOOKUP($A7,subQ,MATCH(J$1,SUBQH,0),0),"") | K7: =IFERROR(VLOOKUP($A7,subQ,MATCH(K$1,SUBQH,0),0),"") | L7: =IFERROR(VLOOKUP($A7,subQ,MATCH(L$1,SUBQH,0),0),"")
A8: 판관비 | D8: 판매비와관리비 | E8: =IFERROR(VLOOKUP($A8,subQ,MATCH(E$1,SUBQH,0),0),"") | F8: =IFERROR(VLOOKUP($A8,subQ,MATCH(F$1,SUBQH,0),0),"") | G8: =IFERROR(VLOOKUP($A8,subQ,MATCH(G$1,SUBQH,0),0),"") | H8: =IFERROR(VLOOKUP($A8,subQ,MATCH(H$1,SUBQH,0),0),"") | I8: =IFERROR(VLOOKUP($A8,subQ,MATCH(I$1,SUBQH,0),0),"") | J8: =IFERROR(VLOOKUP($A8,subQ,MATCH(J$1,SUBQH,0),0),"") | K8: =IFERROR(VLOOKUP($A8,subQ,MATCH(K$1,SUBQH,0),0),"") | L8: =IFERROR(VLOOKUP($A8,subQ,MATCH(L$1,SUBQH,0),0),"")
A9: 영업이익 | D9: 영업이익 | E9: =IFERROR(VLOOKUP($A9,subQ,MATCH(E$1,SUBQH,0),0),"") | F9: =IFERROR(VLOOKUP($A9,subQ,MATCH(F$1,SUBQH,0),0),"") | G9: =IFERROR(VLOOKUP($A9,subQ,MATCH(G$1,SUBQH,0),0),"") | H9: =IFERROR(VLOOKUP($A9,subQ,MATCH(H$1,SUBQH,0),0),"") | I9: =IFERROR(VLOOKUP($A9,subQ,MATCH(I$1,SUBQH,0),0),"") | J9: =IFERROR(VLOOKUP($A9,subQ,MATCH(J$1,SUBQH,0),0),"") | K9: =IFERROR(VLOOKUP($A9,subQ,MATCH(K$1,SUBQH,0),0),"") | L9: =IFERROR(VLOOKUP($A9,subQ,MATCH(L$1,SUBQH,0),0),"")
A10: OPM | D10: 영업이익률 | E10: =IFERROR(VLOOKUP($A10,subQ,MATCH(E$1,SUBQH,0),0),"") | F10: =IFERROR(VLOOKUP($A10,subQ,MATCH(F$1,SUBQH,0),0),"") | G10: =IFERROR(VLOOKUP($A10,subQ,MATCH(G$1,SUBQH,0),0),"") | H10: =IFERROR(VLOOKUP($A10,subQ,MATCH(H$1,SUBQH,0),0),"") | I10: =IFERROR(VLOOKUP($A10,subQ,MATCH(I$1,SUBQH,0),0),"") | J10: =IFERROR(VLOOKUP($A10,subQ,MATCH(J$1,SUBQH,0),0),"") | K10: =IFERROR(VLOOKUP($A10,subQ,MATCH(K$1,SUBQH,0),0),"") | L10: =IFERROR(VLOOKUP($A10,subQ,MATCH(L$1,SUBQH,0),0),"")
A11: 금융손익 | D11: 금융손익(이자·환 포함) | E11: =IFERROR(VLOOKUP($A11,subQ,MATCH(E$1,SUBQH,0),0),"") | F11: =IFERROR(VLOOKUP($A11,subQ,MATCH(F$1,SUBQH,0),0),"") | G11: =IFERROR(VLOOKUP($A11,subQ,MATCH(G$1,SUBQH,0),0),"") | H11: =IFERROR(VLOOKUP($A11,subQ,MATCH(H$1,SUBQH,0),0),"") | I11: =IFERROR(VLOOKUP($A11,subQ,MATCH(I$1,SUBQH,0),0),"") | J11: =IFERROR(VLOOKUP($A11,subQ,MATCH(J$1,SUBQH,0),0),"") | K11: =IFERROR(VLOOKUP($A11,subQ,MATCH(K$1,SUBQH,0),0),"") | L11: =IFERROR(VLOOKUP($A11,subQ,MATCH(L$1,SUBQH,0),0),"")
A12: 이자손익 | D12: 이자손익(이자수익 − 이자비용) | E12: =IFERROR(VLOOKUP($A12,subQ,MATCH(E$1,SUBQH,0),0),"") | F12: =IFERROR(VLOOKUP($A12,subQ,MATCH(F$1,SUBQH,0),0),"") | G12: =IFERROR(VLOOKUP($A12,subQ,MATCH(G$1,SUBQH,0),0),"") | H12: =IFERROR(VLOOKUP($A12,subQ,MATCH(H$1,SUBQH,0),0),"") | I12: =IFERROR(VLOOKUP($A12,subQ,MATCH(I$1,SUBQH,0),0),"") | J12: =IFERROR(VLOOKUP($A12,subQ,MATCH(J$1,SUBQH,0),0),"") | K12: =IFERROR(VLOOKUP($A12,subQ,MATCH(K$1,SUBQH,0),0),"") | L12: =IFERROR(VLOOKUP($A12,subQ,MATCH(L$1,SUBQH,0),0),"")
A13: 외환손익 | D13: 외환손익(실적만; 추정 환효과는 환관련손익) | E13: =IFERROR(VLOOKUP($A13,subQ,MATCH(E$1,SUBQH,0),0),"") | F13: =IFERROR(VLOOKUP($A13,subQ,MATCH(F$1,SUBQH,0),0),"") | G13: =IFERROR(VLOOKUP($A13,subQ,MATCH(G$1,SUBQH,0),0),"") | H13: =IFERROR(VLOOKUP($A13,subQ,MATCH(H$1,SUBQH,0),0),"") | I13: =IFERROR(VLOOKUP($A13,subQ,MATCH(I$1,SUBQH,0),0),"") | J13: =IFERROR(VLOOKUP($A13,subQ,MATCH(J$1,SUBQH,0),0),"") | K13: =IFERROR(VLOOKUP($A13,subQ,MATCH(K$1,SUBQH,0),0),"") | L13: =IFERROR(VLOOKUP($A13,subQ,MATCH(L$1,SUBQH,0),0),"")
A14: 파생상품손익 | D14: 파생상품손익 | E14: =IFERROR(VLOOKUP($A14,subQ,MATCH(E$1,SUBQH,0),0),"") | F14: =IFERROR(VLOOKUP($A14,subQ,MATCH(F$1,SUBQH,0),0),"") | G14: =IFERROR(VLOOKUP($A14,subQ,MATCH(G$1,SUBQH,0),0),"") | H14: =IFERROR(VLOOKUP($A14,subQ,MATCH(H$1,SUBQH,0),0),"") | I14: =IFERROR(VLOOKUP($A14,subQ,MATCH(I$1,SUBQH,0),0),"") | J14: =IFERROR(VLOOKUP($A14,subQ,MATCH(J$1,SUBQH,0),0),"") | K14: =IFERROR(VLOOKUP($A14,subQ,MATCH(K$1,SUBQH,0),0),"") | L14: =IFERROR(VLOOKUP($A14,subQ,MATCH(L$1,SUBQH,0),0),"")
A15: 기타금융손익 | D15: 기타금융손익(금융손익 잔차) | E15: =IFERROR(VLOOKUP($A15,subQ,MATCH(E$1,SUBQH,0),0),"") | F15: =IFERROR(VLOOKUP($A15,subQ,MATCH(F$1,SUBQH,0),0),"") | G15: =IFERROR(VLOOKUP($A15,subQ,MATCH(G$1,SUBQH,0),0),"") | H15: =IFERROR(VLOOKUP($A15,subQ,MATCH(H$1,SUBQH,0),0),"") | I15: =IFERROR(VLOOKUP($A15,subQ,MATCH(I$1,SUBQH,0),0),"") | J15: =IFERROR(VLOOKUP($A15,subQ,MATCH(J$1,SUBQH,0),0),"") | K15: =IFERROR(VLOOKUP($A15,subQ,MATCH(K$1,SUBQH,0),0),"") | L15: =IFERROR(VLOOKUP($A15,subQ,MATCH(L$1,SUBQH,0),0),"")
A16: 기타영업외손익 | D16: 기타영업외손익 | E16: =IFERROR(VLOOKUP($A16,subQ,MATCH(E$1,SUBQH,0),0),"") | F16: =IFERROR(VLOOKUP($A16,subQ,MATCH(F$1,SUBQH,0),0),"") | G16: =IFERROR(VLOOKUP($A16,subQ,MATCH(G$1,SUBQH,0),0),"") | H16: =IFERROR(VLOOKUP($A16,subQ,MATCH(H$1,SUBQH,0),0),"") | I16: =IFERROR(VLOOKUP($A16,subQ,MATCH(I$1,SUBQH,0),0),"") | J16: =IFERROR(VLOOKUP($A16,subQ,MATCH(J$1,SUBQH,0),0),"") | K16: =IFERROR(VLOOKUP($A16,subQ,MATCH(K$1,SUBQH,0),0),"") | L16: =IFERROR(VLOOKUP($A16,subQ,MATCH(L$1,SUBQH,0),0),"")
... A39: NPM | D39: NPM | E39: =IFERROR(VLOOKUP($A39,subQ,MATCH(E$1,SUBQH,0),0),"") | F39: =IFERROR(VLOOKUP($A39,subQ,MATCH(F$1,SUBQH,0),0),"") | G39: =IFERROR(VLOOKUP($A39,subQ,MATCH(G$1,SUBQH,0),0),"") | H39: =IFERROR(VLOOKUP($A39,subQ,MATCH(H$1,SUBQH,0),0),"") | I39: =IFERROR(VLOOKUP($A39,subQ,MATCH(I$1,SUBQH,0),0),"") | J39: =IFERROR(VLOOKUP($A39,subQ,MATCH(J$1,SUBQH,0),0),"") | K39: =IFERROR(VLOOKUP($A39,subQ,MATCH(K$1,SUBQH,0),0),"") | L39: =IFERROR(VLOOKUP($A39,subQ,MATCH(L$1,SUBQH,0),0),"")
A40: 매출액 YoY | D40: 매출액 YoY | F40: =IFERROR(F5/E5-1,"") | G40: =IFERROR(G5/F5-1,"") | H40: =IFERROR(H5/G5-1,"") | I40: =IFERROR(I5/H5-1,"") | J40: =IFERROR(J5/I5-1,"") | K40: =IFERROR(K5/J5-1,"") | L40: =IFERROR(L5/K5-1,"")
A41: 영업이익 YoY | D41: 영업이익 YoY | F41: =IFERROR(F9/E9-1,"") | G41: =IFERROR(G9/F9-1,"") | H41: =IFERROR(H9/G9-1,"") | I41: =IFERROR(I9/H9-1,"") | J41: =IFERROR(J9/I9-1,"") | K41: =IFERROR(K9/J9-1,"") | L41: =IFERROR(L9/K9-1,"")
A42: 지배주주순이익 YoY | D42: 지배주주순이익 YoY | F42: =IFERROR(F21/E21-1,"") | G42: =IFERROR(G21/F21-1,"") | H42: =IFERROR(H21/G21-1,"") | I42: =IFERROR(I21/H21-1,"") | J42: =IFERROR(J21/I21-1,"") | K42: =IFERROR(K21/J21-1,"") | L42: =IFERROR(L21/K21-1,"")

Sheet TP
B1: 종가 | C1: =변수!D44
B2: 기준일 | C2: =변수!D45
B3: 모델 산출값 — 목표주가·추천 아님. 밴드·COE 는 변수 시트 3절의 가정
C5: FY | D5: 2025 | E5: 2026 | F5: 2027 | G5: 2028
D6: A | E6: E | F6: E | G6: E
C7: EPS(원) | D7: =IFERROR(VLOOKUP("EPS",subQ,MATCH(D$5,SUBQH,0),0),"") | E7: =IFERROR(VLOOKUP("EPS",subQ,MATCH(E$5,SUBQH,0),0),"") | F7: =IFERROR(VLOOKUP("EPS",subQ,MATCH(F$5,SUBQH,0),0),"") | G7: =IFERROR(VLOOKUP("EPS",subQ,MATCH(G$5,SUBQH,0),0),"")
C8: BPS(원) | D8: =IFERROR(VLOOKUP("BPS",subQ,MATCH(D$5,SUBQH,0),0),"") | E8: =IFERROR(VLOOKUP("BPS",subQ,MATCH(E$5,SUBQH,0),0),"") | F8: =IFERROR(VLOOKUP("BPS",subQ,MATCH(F$5,SUBQH,0),0),"") | G8: =IFERROR(VLOOKUP("BPS",subQ,MATCH(G$5,SUBQH,0),0),"")
C9: 지배주주순이익(억원) | D9: =IFERROR(VLOOKUP("지배주주순이익",subQ,MATCH(D$5,SUBQH,0),0),"") | E9: =IFERROR(VLOOKUP("지배주주순이익",subQ,MATCH(E$5,SUBQH,0),0),"") | F9: =IFERROR(VLOOKUP("지배주주순이익",subQ,MATCH(F$5,SUBQH,0),0),"") | G9: =IFERROR(VLOOKUP("지배주주순이익",subQ,MATCH(G$5,SUBQH,0),0),"")
C10: 영업이익(억원) | D10: =IFERROR(VLOOKUP("영업이익",subQ,MATCH(D$5,SUBQH,0),0),"") | E10: =IFERROR(VLOOKUP("영업이익",subQ,MATCH(E$5,SUBQH,0),0),"") | F10: =IFERROR(VLOOKUP("영업이익",subQ,MATCH(F$5,SUBQH,0),0),"") | G10: =IFERROR(VLOOKUP("영업이익",subQ,MATCH(G$5,SUBQH,0),0),"")
C11: ROE(EPS/기초BPS) | E11: =IFERROR(E7/D8,"") | F11: =IFERROR(F7/E8,"") | G11: =IFERROR(G7/F8,"")
B13: PER
C14: 12M fwd EPS | D14: =IFERROR(E7*변수!D50+F7*(1-변수!D50),"")
C15: 적정가치 @PER_lo | D15: =변수!D47 | E15: =IFERROR(ROUND($D$14*D15,-2),"") | F15: =IFERROR(E15/$C$1-1,"") | G15: 배 · 원 · 종가 대비
C16: 적정가치 @PER_mid | D16: =변수!D48 | E16: =IFERROR(ROUND($D$14*D16,-2),"") | F16: =IFERROR(E16/$C$1-1,"") | G16: 배 · 원 · 종가 대비
C17: 적정가치 @PER_hi | D17: =변수!D49 | E17: =IFERROR(ROUND($D$14*D17,-2),"") | F17: =IFERROR(E17/$C$1-1,"") | G17: 배 · 원 · 종가 대비
C18: 현재 PER(종가/12M fwd EPS) | D18: =IFERROR($C$1/$D$14,"")
B20: PBR
C21: 최근 BPS(마지막 실적 분기) | D21: =IFERROR(VLOOKUP("BPS",subQ,MATCH("2Q26",SUBQH,0),0),"")
C22: ROE fwd(12M fwd EPS / BPS) | D22: =IFERROR($D$14/$D$21,"")
C23: COE | D23: =변수!D46
C24: 적정 PBR = ROE/COE | D24: =IFERROR(D22/D23,"")
C25: 적정가치(PBR) = BPS × 적정PBR | D25: =IFERROR(ROUND(D21*D24,-2),"") | E25: =IFERROR(D25/$C$1-1,"")
C26: 현재 PBR(종가/BPS) | D26: =IFERROR($C$1/D21,"")
B28: 모델 json valuation(참고)
C29: eps_fwd12m | D29: -275.6
C30: bps_latest | D30: 898.4
C31: per_now
C32: pbr_now | D32: 0.85
C33: roe_fwd | D33: -0.3068
C34: fair_pbr
C35: fair_value_pbr
C36: ev_ebitda
C37: note | D37: 모델 산출값 — 목표주가·추천 아님

Sheet 외화
C1: 이름: 외화QH — 환율 QoQ · 외화 순노출 × Δ기말환율 | E1: 4Q21 | F1: 1Q22 | G1: 2Q22 | H1: 3Q22 | I1: 4Q22 | J1: 1Q23 | K1: 2Q23 | L1: 3Q23 | M1: 4Q23 | N1: 1Q24 | O1: 2Q24 | P1: 3Q24 | Q1: 4Q24 | R1: 1Q25 | S1: 2Q25 | T1: 3Q25 | U1: 4Q25 | V1: 1Q26 | W1: 2Q26 | X1: 3Q26 | Y1: 4Q26 | Z1: 1Q27 | AA1: 2Q27 | AB1: 3Q27 | AC1: 4Q27 | AD1: 1Q28 | AE1: 2Q28 | AF1: 3Q28 | AG1: 4Q28
E3: 1 | F3: 2 | G3: 3 | H3: 4 | I3: 5 | J3: 6 | K3: 7 | L3: 8 | M3: 9 | N3: 10 | O3: 11 | P3: 12 | Q3: 13 | R3: 14 | S3: 15 | T3: 16 | U3: 17 | V3: 18 | W3: 19 | X3: 20 | Y3: 21 | Z3: 22 | AA3: 23 | AB3: 24 | AC3: 25 | AD3: 26 | AE3: 27 | AF3: 28 | AG3: 29
E4: 2021.12 | F4: 2022.03 | G4: 2022.06 | H4: 2022.09 | I4: 2022.12 | J4: 2023.03 | K4: 2023.06 | L4: 2023.09 | M4: 2023.12 | N4: 2024.03 | O4: 2024.06 | P4: 2024.09 | Q4: 2024.12 | R4: 2025.03 | S4: 2025.06 | T4: 2025.09 | U4: 2025.12 | V4: 2026.03 | W4: 2026.06 | X4: 2026.09 | Y4: 2026.12 | Z4: 2027.03 | AA4: 2027.06 | AB4: 2027.09 | AC4: 2027.12 | AD4: 2028.03 | AE4: 2028.06 | AF4: 2028.09 | AG4: 2028.12
D5: 원/달러(평균) | E5: =IFERROR(VLOOKUP($D5,환율,MATCH(E$1,변수H,0),0),"") | F5: =IFERROR(VLOOKUP($D5,환율,MATCH(F$1,변수H,0),0),"") | G5: =IFERROR(VLOOKUP($D5,환율,MATCH(G$1,변수H,0),0),"") | H5: =IFERROR(VLOOKUP($D5,환율,MATCH(H$1,변수H,0),0),"") | I5: =IFERROR(VLOOKUP($D5,환율,MATCH(I$1,변수H,0),0),"") | J5: =IFERROR(VLOOKUP($D5,환율,MATCH(J$1,변수H,0),0),"") | K5: =IFERROR(VLOOKUP($D5,환율,MATCH(K$1,변수H,0),0),"") | L5: =IFERROR(VLOOKUP($D5,환율,MATCH(L$1,변수H,0),0),"") | ... AG5: =IFERROR(VLOOKUP($D5,환율,MATCH(AG$1,변수H,0),0),"")
A6: 원/달러(평균) QoQ | F6: =IFERROR(F5/E5-1,"") | G6: =IFERROR(G5/F5-1,"") | H6: =IFERROR(H5/G5-1,"") | I6: =IFERROR(I5/H5-1,"") | J6: =IFERROR(J5/I5-1,"") | K6: =IFERROR(K5/J5-1,"") | L6: =IFERROR(L5/K5-1,"") | M6: =IFERROR(M5/L5-1,"") | ... AG6: =IFERROR(AG5/AF5-1,"")
D7: 원/달러(기말) | E7: =IFERROR(VLOOKUP($D7,환율,MATCH(E$1,변수H,0),0),"") | F7: =IFERROR(VLOOKUP($D7,환율,MATCH(F$1,변수H,0),0),"") | G7: =IFERROR(VLOOKUP($D7,환율,MATCH(G$1,변수H,0),0),"") | H7: =IFERROR(VLOOKUP($D7,환율,MATCH(H$1,변수H,0),0),"") | I7: =IFERROR(VLOOKUP($D7,환율,MATCH(I$1,변수H,0),0),"") | J7: =IFERROR(VLOOKUP($D7,환율,MATCH(J$1,변수H,0),0),"") | K7: =IFERROR(VLOOKUP($D7,환율,MATCH(K$1,변수H,0),0),"") | L7: =IFERROR(VLOOKUP($D7,환율,MATCH(L$1,변수H,0),0),"") | ... AG7: =IFERROR(VLOOKUP($D7,환율,MATCH(AG$1,변수H,0),0),"")
A8: 원/달러(기말) QoQ | F8: =IFERROR(F7/E7-1,"") | G8: =IFERROR(G7/F7-1,"") | H8: =IFERROR(H7/G7-1,"") | I8: =IFERROR(I7/H7-1,"") | J8: =IFERROR(J7/I7-1,"") | K8: =IFERROR(K7/J7-1,"") | L8: =IFERROR(L7/K7-1,"") | M8: =IFERROR(M7/L7-1,"") | ... AG8: =IFERROR(AG7/AF7-1,"")
D9: W/Euro(평균) | E9: =IFERROR(VLOOKUP($D9,환율,MATCH(E$1,변수H,0),0),"") | F9: =IFERROR(VLOOKUP($D9,환율,MATCH(F$1,변수H,0),0),"") | G9: =IFERROR(VLOOKUP($D9,환율,MATCH(G$1,변수H,0),0),"") | H9: =IFERROR(VLOOKUP($D9,환율,MATCH(H$1,변수H,0),0),"") | I9: =IFERROR(VLOOKUP($D9,환율,MATCH(I$1,변수H,0),0),"") | J9: =IFERROR(VLOOKUP($D9,환율,MATCH(J$1,변수H,0),0),"") | K9: =IFERROR(VLOOKUP($D9,환율,MATCH(K$1,변수H,0),0),"") | L9: =IFERROR(VLOOKUP($D9,환율,MATCH(L$1,변수H,0),0),"") | ... AG9: =IFERROR(VLOOKUP($D9,환율,MATCH(AG$1,변수H,0),0),"")
A10: W/Euro(평균) QoQ | F10: =IFERROR(F9/E9-1,"") | G10: =IFERROR(G9/F9-1,"") | H10: =IFERROR(H9/G9-1,"") | I10: =IFERROR(I9/H9-1,"") | J10: =IFERROR(J9/I9-1,"") | K10: =IFERROR(K9/J9-1,"") | L10: =IFERROR(L9/K9-1,"") | M10: =IFERROR(M9/L9-1,"") | ... AG10: =IFERROR(AG9/AF9-1,"")
D11: W/Euro(기말) | E11: =IFERROR(VLOOKUP($D11,환율,MATCH(E$1,변수H,0),0),"") | F11: =IFERROR(VLOOKUP($D11,환율,MATCH(F$1,변수H,0),0),"") | G11: =IFERROR(VLOOKUP($D11,환율,MATCH(G$1,변수H,0),0),"") | H11: =IFERROR(VLOOKUP($D11,환율,MATCH(H$1,변수H,0),0),"") | I11: =IFERROR(VLOOKUP($D11,환율,MATCH(I$1,변수H,0),0),"") | J11: =IFERROR(VLOOKUP($D11,환율,MATCH(J$1,변수H,0),0),"") | K11: =IFERROR(VLOOKUP($D11,환율,MATCH(K$1,변수H,0),0),"") | L11: =IFERROR(VLOOKUP($D11,환율,MATCH(L$1,변수H,0),0),"") | ... AG11: =IFERROR(VLOOKUP($D11,환율,MATCH(AG$1,변수H,0),0),"")
A12: W/Euro(기말) QoQ | F12: =IFERROR(F11/E11-1,"") | G12: =IFERROR(G11/F11-1,"") | H12: =IFERROR(H11/G11-1,"") | I12: =IFERROR(I11/H11-1,"") | J12: =IFERROR(J11/I11-1,"") | K12: =IFERROR(K11/J11-1,"") | L12: =IFERROR(L11/K11-1,"") | M12: =IFERROR(M11/L11-1,"") | ... AG12: =IFERROR(AG11/AF11-1,"")
D13: 원/100Y(기말) | E13: =IFERROR(VLOOKUP($D13,환율,MATCH(E$1,변수H,0),0),"") | F13: =IFERROR(VLOOKUP($D13,환율,MATCH(F$1,변수H,0),0),"") | G13: =IFERROR(VLOOKUP($D13,환율,MATCH(G$1,변수H,0),0),"") | H13: =IFERROR(VLOOKUP($D13,환율,MATCH(H$1,변수H,0),0),"") | I13: =IFERROR(VLOOKUP($D13,환율,MATCH(I$1,변수H,0),0),"") | J13: =IFERROR(VLOOKUP($D13,환율,MATCH(J$1,변수H,0),0),"") | K13: =IFERROR(VLOOKUP($D13,환율,MATCH(K$1,변수H,0),0),"") | L13: =IFERROR(VLOOKUP($D13,환율,MATCH(L$1,변수H,0),0),"") | ... AG13: =IFERROR(VLOOKUP($D13,환율,MATCH(AG$1,변수H,0),0),"")
A14: 원/100Y(기말) QoQ | F14: =IFERROR(F13/E13-1,"") | G14: =IFERROR(G13/F13-1,"") | H14: =IFERROR(H13/G13-1,"") | I14: =IFERROR(I13/H13-1,"") | J14: =IFERROR(J13/I13-1,"") | K14: =IFERROR(K13/J13-1,"") | L14: =IFERROR(L13/K13-1,"") | M14: =IFERROR(M13/L13-1,"") | ... AG14: =IFERROR(AG13/AF13-1,"")
A16: 외화순노출 | C16: 외화 순노출(백만$) | D16: =변수!D57 | E16: 외화 순노출 × Δ기말환율 (외화 시트 방식)
A17: 환관련손익추정 | C17: 환관련손익 추정(억원) = 순노출 × Δ원/달러(기말) / 100 | F17: =IFERROR($D$16*(F7-E7)/100,"") | G17: =IFERROR($D$16*(G7-F7)/100,"") | H17: =IFERROR($D$16*(H7-G7)/100,"") | I17: =IFERROR($D$16*(I7-H7)/100,"") | J17: =IFERROR($D$16*(J7-I7)/100,"") | K17: =IFERROR($D$16*(K7-J7)/100,"") | L17: =IFERROR($D$16*(L7-K7)/100,"") | M17: =IFERROR($D$16*(M7-L7)/100,"") | ... AG17: =IFERROR($D$16*(AG7-AF7)/100,"")
A18: fx_pnl.by_q | C18: 모델 fx_pnl.by_q(억원, 참고)
C19: 외화 순노출 미공시(face) → 0 + 표기
