Workbook
Name 변수H: 변수!$C$1:$AO$1
Name 환율: 변수!$C$6:$AO$13
Name BS연결H: BS연결!$C$1:$AO$1
Name BS연결: BS연결!$C$5:$AO$110
Name BS별도H: BS별도!$C$1:$AO$1
Name BS별도: BS별도!$C$5:$AO$95
Name SUBQH: subQ!$A$1:$AO$1
Name subQ: subQ!$A$5:$AO$46

Sheet README
A1: 세진중공업(075580) 실적 모델 — ARGUS 한국조선
A2: 기준 분기 2026Q2 · 마지막 실적 2026Q2 · 생성 2026-10-14
A3: 모든 수치는 모델 산출값(DART 공개 재무제표 + 우리 추정)이다 — 목표주가·투자 추천 아님. 참고용 · 투자조언 아님.
A5: 시트
A6: 변수 가정 시계열. 환율 8행(ECB via frankfurter — L2 fx.json; 추정 분기 = 노란 가정), 추정 드라이버(노란 셀 = 모델값에서 역산한 가정, 바꾸면 재계산; 연녹 셀 = 3절 스칼라 참조 수식), 3절 스칼라 가정(세율·판관비율·지배주주비중·이자율·종가·PER 밴드·COE·외화 순노출·헤지비율)
A7: BS연결/BS별도 FnGuide 계정명 × 기간 값 덤프(백만원). 행1 분기라벨, 행4 YYYY.MM / YYYY.12A. 이름정의 BS연결H·BS연결(계정명 C열부터)
A8: subQ 분기 서브모델(억원 = 백만원/100). 확정 행: =IFERROR(VLOOKUP($D행,BS연결,MATCH(E$1,BS연결H,0),0)/100,"") 추정 행: 변수 시트 가정 셀 참조 수식. 외환손익·파생상품손익은 BS 계정 합·차, 기타금융손익은 잔차, OPM·EPS·BPS·PER·PBR 은 파생 수식
A9: SLS 선표(조선사만, sls json 있을 때): 요약 행(sls 저장값) + 계약별 스케줄(백만$) × (헤지비율 × 헤지환율 + (1−헤지비율) × 건조시점 환율[변수 원/달러(평균)]) → 원화 수식 블록 → 합계 행이 subQ 매출조선에 연결
A10: 시나리오 신규수주 보수/기준/낙관(forecast_panel 패널, 모델에 scenarios 가 있을 때만): 매출액·영업이익 = subQ 기준값 ± (시나리오 신규 − base 신규) × OPM. base 만 subQ 행에 포함, 나머지는 합산 안 함
A11: 분기/연간예상 subQ 를 이름(A열 key)으로 VLOOKUP 한 보고서 표(억원)
A12: TP PER 밴드 × 12M fwd EPS, PBR = ROE/COE × BPS — 모델 산출값 구간, 목표주가·추천 아님
A13: 외화 환율 QoQ, 외화 순노출 × Δ기말환율 → 환관련손익 추정
... A34: 백테스트: {"freeze": "2025Q2", "horizon": 4, "revenue_wape_pct": 10.5, "op_wape_pct": 53.4, "n": 4, "note": "단일 회사 4분기 — 통계 아님", "driver_at_freeze": "trend_seasonal", "selection_oos_at_freeze": {"wape_link": null, "wape_trend": null, "adopted": false, "decision": "rejected", "note": "유의성 조건 미달 → OOS 비교 전 기각"}, "frozen_inputs": "fin(연결/별도)·고객 조선사 모델·지주 자회사 모델은 2025Q2 까지의 분기만; 선표는 체결일 ≤ 2025Q2 말일 계약(원장 최신 금액·코호트 등급, 환산 없음); 잔고는 yards_cache 2025Q2; 시세·환율 forward·prices·forecast_panel 신규수주 미사용. 고객 가중치(suppliers.json 언급 비중)와 합병 체인링크는 현재 지식; 고객 연동 채택은 동결 모델 안에서도 자기 la−4분기 OOS 규칙(selection_oos_at_freeze)", "detail": [{"q": "2025Q3", "rev_pred": 784.2, "rev_act": 903.68, "op_pred": 73.57, "op_act": 121.44}, {"q": "2025Q4", "rev_pred": 1146.12, "rev_act": 1156.51, "op_pred": 107.53, "op_act": 346.8}, {"q": "2026Q1", "rev_pred": 1045.89, "rev_act": 872.43, "op_pred": 98.13, "op_act": 136.39}, {"q": "2026Q2", "rev_pred": 1036.62, "rev_act": 934.98, "op_pred": 97.26, "op_act": 203.68}]}

Sheet 변수
C1: 이름: 변수H | E1: 4Q21 | F1: 2021 | G1: 1Q22 | H1: 2Q22 | I1: 3Q22 | J1: 4Q22 | K1: 2022 | L1: 1Q23 | M1: 2Q23 | N1: 3Q23 | O1: 4Q23 | P1: 2023 | Q1: 1Q24 | R1: 2Q24 | S1: 3Q24 | T1: 4Q24 | U1: 2024 | V1: 1Q25 | W1: 2Q25 | X1: 3Q25 | Y1: 4Q25 | Z1: 2025 | AA1: 1Q26 | AB1: 2Q26 | AC1: 3Q26 | AD1: 4Q26 | AE1: 2026 | AF1: 1Q27 | AG1: 2Q27 | AH1: 3Q27 | AI1: 4Q27 | AJ1: 2027 | AK1: 1Q28 | AL1: 2Q28 | AM1: 3Q28 | AN1: 4Q28 | AO1: 2028
A2: 가정 시계열 — 노란 셀은 추정 가정(모델값에서 역산), 연녹 셀은 3절 스칼라 참조 수식. 바꾸면 subQ·분기·연간예상·TP·시나리오가 재계산됩니다.
E3: 1 | F3: 2 | G3: 3 | H3: 4 | I3: 5 | J3: 6 | K3: 7 | L3: 8 | M3: 9 | N3: 10 | O3: 11 | P3: 12 | Q3: 13 | R3: 14 | S3: 15 | T3: 16 | U3: 17 | V3: 18 | W3: 19 | X3: 20 | Y3: 21 | Z3: 22 | AA3: 23 | AB3: 24 | AC3: 25 | AD3: 26 | AE3: 27 | AF3: 28 | AG3: 29 | AH3: 30 | AI3: 31 | AJ3: 32 | AK3: 33 | AL3: 34 | AM3: 35 | AN3: 36 | AO3: 37
E4: 2021.12 | F4: 2021.12A | G4: 2022.03 | H4: 2022.06 | I4: 2022.09 | J4: 2022.12 | K4: 2022.12A | L4: 2023.03 | M4: 2023.06 | N4: 2023.09 | O4: 2023.12 | P4: 2023.12A | Q4: 2024.03 | R4: 2024.06 | S4: 2024.09 | T4: 2024.12 | U4: 2024.12A | V4: 2025.03 | W4: 2025.06 | X4: 2025.09 | Y4: 2025.12 | Z4: 2025.12A | AA4: 2026.03 | AB4: 2026.06 | AC4: 2026.09 | AD4: 2026.12 | AE4: 2026.12A | AF4: 2027.03 | AG4: 2027.06 | AH4: 2027.09 | AI4: 2027.12 | AJ4: 2027.12A | AK4: 2028.03 | AL4: 2028.06 | AM4: 2028.09 | AN4: 2028.12 | AO4: 2028.12A
B5: 1. FX | C5: 이름: 환율
A6: USDKRW_avg | C6: 원/달러(평균) | E6: 1183.5 | F6: 1145.51 | G6: 1205.78 | H6: 1262.09 | I6: 1341.93 | J6: 1360.12 | K6: 1292.98 | L6: 1276.95 | M6: 1315.69 | N6: 1313.62 | O6: 1322.01 | P6: 1306.85 | Q6: 1330.14 | R6: 1371.28 | S6: 1356.22 | T6: 1396.3 | U6: 1363.53 | V6: 1452.28 | W6: 1398.52 | X6: 1386.95 | Y6: 1449.19 | Z6: 1421.52 | AA6: 1466.12 | AB6: 1501.75 | AC6: 1418.75 | AD6: 1343.39 | AE6: 1456.01 | AF6: 1341.45 | AG6: 1341.45 | AH6: 1341.45 | AI6: 1341.45 | AK6: 1341.45 | AL6: 1341.45 | AM6: 1341.45 | AN6: 1341.45
A7: USDKRW_end | C7: 원/달러(기말) | E7: 1188.75 | F7: 1188.75 | G7: 1213.74 | H7: 1301.24 | I7: 1436.9 | J7: 1260.16 | K7: 1260.16 | L7: 1305.99 | M7: 1321.44 | N7: 1345.35 | O7: 1297.43 | P7: 1297.43 | Q7: 1349.25 | R7: 1377.73 | S7: 1312.17 | T7: 1474.78 | U7: 1474.78 | V7: 1474.54 | W7: 1355.13 | X7: 1403.67 | Y7: 1444.2 | Z7: 1444.2 | AA7: 1524.8 | AB7: 1550.89 | AC7: 1355.4 | AD7: 1341.45 | AE7: 1341.45 | AF7: 1341.45 | AG7: 1341.45 | AH7: 1341.45 | AI7: 1341.45 | AK7: 1341.45 | AL7: 1341.45 | AM7: 1341.45 | AN7: 1341.45
A8: JPY100KRW_avg | C8: 원/100Y(평균) | E8: 1041.02 | F8: 1042.74 | G8: 1036.79 | H8: 972.23 | I8: 970.61 | J8: 961.03 | K8: 985.1 | L8: 964.89 | M8: 957.36 | N8: 909 | O8: 893.22 | P8: 931.11 | Q8: 896.29 | R8: 880.14 | S8: 909.35 | T8: 917.25 | U8: 900.92 | V8: 952.59 | W8: 967.92 | X8: 940.32 | Y8: 940.77 | Z8: 950.17 | AA8: 934.39 | AB8: 942.16 | AC8: 890.41 | AD8: 849.39 | AE8: 918.46 | AF8: 848.37 | AG8: 848.37 | AH8: 848.37 | AI8: 848.37 | AK8: 848.37 | AL8: 848.37 | AM8: 848.37 | AN8: 848.37
A9: JPY100KRW_end | C9: 원/100Y(기말) | E9: 1032.62 | F9: 1032.62 | G9: 996.83 | H9: 954.9 | I9: 993.29 | J9: 955.54 | K9: 955.54 | L9: 980.62 | M9: 913.67 | N9: 901.47 | O9: 917.04 | P9: 917.04 | Q9: 892.42 | R9: 857.76 | S9: 919.21 | T9: 939.65 | U9: 939.65 | V9: 986.84 | W9: 938.85 | X9: 948.49 | Y9: 921.81 | Z9: 921.81 | AA9: 955.99 | AB9: 954.75 | AC9: 863.31 | AD9: 848.37 | AE9: 848.37 | AF9: 848.37 | AG9: 848.37 | AH9: 848.37 | AI9: 848.37 | AK9: 848.37 | AL9: 848.37 | AM9: 848.37 | AN9: 848.37
A10: EURKRW_avg | C10: W/Euro(평균) | E10: 1353.32 | F10: 1354.06 | G10: 1352.29 | H10: 1343.31 | I10: 1350.63 | J10: 1386.07 | K10: 1358.07 | L10: 1369.93 | M10: 1432.41 | N10: 1429.41 | O10: 1420.91 | P10: 1412.88 | Q10: 1444.21 | R10: 1476.42 | S10: 1489.3 | T10: 1490.78 | U10: 1475.4 | V10: 1528.33 | W10: 1585.13 | X10: 1620.04 | Y10: 1686.02 | Z10: 1605.45 | AA10: 1715.47 | AB10: 1746.09 | AC10: 1631.97 | AD10: 1506.62 | AE10: 1688.01 | AF10: 1500.82 | AG10: 1500.82 | AH10: 1500.82 | AI10: 1500.82 | AK10: 1500.82 | AL10: 1500.82 | AM10: 1500.82 | AN10: 1500.82
A11: EURKRW_end | C11: W/Euro(기말) | E11: 1346.38 | F11: 1346.38 | G11: 1347.37 | H11: 1351.6 | I11: 1400.62 | J11: 1344.08 | K11: 1344.08 | L11: 1420.26 | M11: 1435.88 | N11: 1425.26 | O11: 1433.66 | P11: 1433.66 | Q11: 1458.68 | R11: 1474.86 | S11: 1469.1 | T11: 1532.14 | U11: 1532.14 | V11: 1594.72 | W11: 1588.22 | X11: 1648.04 | Y11: 1696.94 | Z11: 1696.94 | AA11: 1753.21 | AB11: 1767.09 | AC11: 1539.06 | AD11: 1500.82 | AE11: 1500.82 | AF11: 1500.82 | AG11: 1500.82 | AH11: 1500.82 | AI11: 1500.82 | AK11: 1500.82 | AL11: 1500.82 | AM11: 1500.82 | AN11: 1500.82
A12: CNYKRW_avg | C12: 원/중국원(평균) | E12: 185.14 | F12: 177.65 | G12: 189.93 | H12: 190.76 | I12: 195.79 | J12: 191.09 | K12: 191.93 | L12: 186.59 | M12: 187.45 | N12: 181.28 | O12: 182.86 | P12: 184.52 | Q12: 185.04 | R12: 189.35 | S12: 189.24 | T12: 194.24 | U12: 189.49 | V12: 199.63 | W12: 193.41 | X12: 193.79 | Y12: 204.38 | Z12: 197.8 | AA12: 211.75 | AB12: 220.8 | AC12: 210.43 | AD12: 200.49 | AE12: 213.61 | AF12: 200.4 | AG12: 200.4 | AH12: 200.4 | AI12: 200.4 | AK12: 200.4 | AL12: 200.4 | AM12: 200.4 | AN12: 200.4
A13: CNYKRW_end | C13: 원/중국원(기말) | E13: 187.13 | F13: 187.13 | G13: 191.38 | H13: 194.13 | I13: 201.92 | J13: 182.67 | K13: 182.67 | L13: 189.97 | M13: 181.8 | N13: 184.26 | O13: 182.61 | P13: 182.61 | Q13: 186.66 | R13: 189.7 | S13: 187.12 | T13: 202.04 | U13: 202.04 | V13: 203.3 | W13: 189.14 | X13: 197.16 | Y13: 206.28 | Z13: 206.28 | AA13: 220.97 | AB13: 228.56 | AC13: 202.16 | AD13: 200.4 | AE13: 200.4 | AF13: 200.4 | AG13: 200.4 | AH13: 200.4 | AI13: 200.4 | AK13: 200.4 | AL13: 200.4 | AM13: 200.4 | AN13: 200.4
B14: 1b. 종가
A15: price_close_end | C15: 종가(기말) | E15: 5900 | G15: 6840 | H15: 6500 | I15: 6210 | J15: 5150 | L15: 5810 | M15: 6510 | N15: 5160 | O15: 4755 | Q15: 6400 | R15: 10040 | S15: 7350 | T15: 8440 | V15: 6580 | W15: 11440 | X15: 21600 | Y15: 17400 | AA15: 15520 | AB15: 13210 | AC15: 9770 | AD15: 8710
A16: price_high | C16: 종가(최고) | E16: 6880 | G16: 7740 | H16: 7640 | I16: 8900 | J16: 6580 | L16: 6390 | M16: 7310 | N16: 7330 | O16: 5160 | Q16: 6700 | R16: 10680 | S16: 10920 | T16: 8880 | V16: 9600 | W16: 12950 | X16: 27400 | Y16: 25350 | AA16: 20900 | AB16: 22100 | AC16: 14570 | AD16: 10080
A17: price_low | C17: 종가(최저) | E17: 5230 | G17: 5850 | H17: 5560 | I17: 5030 | J17: 5030 | L17: 4945 | M17: 5810 | N17: 5010 | O17: 4195 | Q17: 4655 | R17: 6310 | S17: 6670 | T17: 6380 | V17: 6570 | W17: 6410 | X17: 10280 | Y17: 16750 | AA17: 14710 | AB17: 12600 | AC17: 8500 | AD17: 8120
A18: price_avg | C18: 종가(평균) | E18: 6025.2 | G18: 6785.4 | H18: 6666.8 | I18: 6841.6 | J18: 5779.7 | L18: 5762.3 | M18: 6450.5 | N18: 6145.2 | O18: 4592.2 | Q18: 5564.7 | R18: 7426.2 | S18: 8331.1 | T18: 7593 | V18: 8434 | W18: 9865.3 | X18: 15614.6 | Y18: 19573.9 | AA18: 18365.4 | AB18: 16779.2 | AC18: 10929 | AD18: 9386.2
B20: 2. 추정 드라이버 | C20: 실적 열 = subQ 실현값(수식), 추정 열 = 가정(노란 = 모델값 역산, 연녹 = 3절 스칼라 참조)
A21: drv:판관비 | B21: ratio | C21: 판관비율(/매출) | E21: =IFERROR(subQ!E8/subQ!E5,"") | F21: =IFERROR(subQ!F8/subQ!F5,"") | G21: =IFERROR(subQ!G8/subQ!G5,"") | H21: =IFERROR(subQ!H8/subQ!H5,"") | I21: =IFERROR(subQ!I8/subQ!I5,"") | J21: =IFERROR(subQ!J8/subQ!J5,"") | K21: =IFERROR(subQ!K8/subQ!K5,"") | L21: =IFERROR(subQ!L8/subQ!L5,"") | ... AB21: =IFERROR(subQ!AB8/subQ!AB5,"") | AC21: =$D$55 | AD21: =$D$55 | AE21: =IFERROR(subQ!AE8/subQ!AE5,"") | AF21: =$D$55 | AG21: =$D$55 | AH21: =$D$55 | AI21: =$D$55 | AJ21: =IFERROR(subQ!AJ8/subQ!AJ5,"") | AK21: =$D$55 | AL21: =$D$55 | AM21: =$D$55 | AN21: =$D$55 | AO21: =IFERROR(subQ!AO8/subQ!AO5,"")
A22: drv:외환손익 | B22: abs | C22: 외환손익 (가정, 억원) | E22: =subQ!E13 | F22: =subQ!F13 | G22: =subQ!G13 | H22: =subQ!H13 | I22: =subQ!I13 | J22: =subQ!J13 | K22: =subQ!K13 | L22: =subQ!L13 | ... AB22: =subQ!AB13 | AC22: 0 | AD22: 0 | AE22: =subQ!AE13 | AF22: 0 | AG22: 0 | AH22: 0 | AI22: 0 | AJ22: =subQ!AJ13 | AK22: 0 | AL22: 0 | AM22: 0 | AN22: 0 | AO22: =subQ!AO13
A23: drv:기타영업외손익 | B23: abs | C23: 기타영업외손익 (가정, 억원) | E23: =subQ!E14 | F23: =subQ!F14 | G23: =subQ!G14 | H23: =subQ!H14 | I23: =subQ!I14 | J23: =subQ!J14 | K23: =subQ!K14 | L23: =subQ!L14 | ... AB23: =subQ!AB14 | AC23: 0 | AD23: 0 | AE23: =subQ!AE14 | AF23: 0 | AG23: 0 | AH23: 0 | AI23: 0 | AJ23: =subQ!AJ14 | AK23: 0 | AL23: 0 | AM23: 0 | AN23: 0 | AO23: =subQ!AO14
A24: drv:지분법손익 | B24: abs | C24: 지분법손익 (가정, 억원) | E24: =subQ!E15 | F24: =subQ!F15 | G24: =subQ!G15 | H24: =subQ!H15 | I24: =subQ!I15 | J24: =subQ!J15 | K24: =subQ!K15 | L24: =subQ!L15 | ... AB24: =subQ!AB15 | AC24: -0.03 | AD24: -0.03 | AE24: =subQ!AE15 | AF24: -0.03 | AG24: -0.03 | AH24: -0.03 | AI24: -0.03 | AJ24: =subQ!AJ15 | AK24: -0.03 | AL24: -0.03 | AM24: -0.03 | AN24: -0.03 | AO24: =subQ!AO15
A25: drv:법인세비용 | B25: tax | C25: 법인세율(/세전) — 법인세 = MAX(세전,0) × 세율 | E25: =IFERROR(subQ!E17/subQ!E16,"") | F25: =IFERROR(subQ!F17/subQ!F16,"") | G25: =IFERROR(subQ!G17/subQ!G16,"") | H25: =IFERROR(subQ!H17/subQ!H16,"") | I25: =IFERROR(subQ!I17/subQ!I16,"") | J25: =IFERROR(subQ!J17/subQ!J16,"") | K25: =IFERROR(subQ!K17/subQ!K16,"") | L25: =IFERROR(subQ!L17/subQ!L16,"") | ... AB25: =IFERROR(subQ!AB17/subQ!AB16,"") | AC25: =$D$54 | AD25: =$D$54 | AE25: =IFERROR(subQ!AE17/subQ!AE16,"") | AF25: =$D$54 | AG25: =$D$54 | AH25: =$D$54 | AI25: =$D$54 | AJ25: =IFERROR(subQ!AJ17/subQ!AJ16,"") | AK25: =$D$54 | AL25: =$D$54 | AM25: =$D$54 | AN25: =$D$54 | AO25: =IFERROR(subQ!AO17/subQ!AO16,"")
A26: drv:지배주주순이익 | B26: ratio | C26: 지배주주 비중(/당기순이익) | E26: =IFERROR(subQ!E19/subQ!E18,"") | F26: =IFERROR(subQ!F19/subQ!F18,"") | G26: =IFERROR(subQ!G19/subQ!G18,"") | H26: =IFERROR(subQ!H19/subQ!H18,"") | I26: =IFERROR(subQ!I19/subQ!I18,"") | J26: =IFERROR(subQ!J19/subQ!J18,"") | K26: =IFERROR(subQ!K19/subQ!K18,"") | L26: =IFERROR(subQ!L19/subQ!L18,"") | ... AB26: =IFERROR(subQ!AB19/subQ!AB18,"") | AC26: =$D$56 | AD26: =$D$56 | AE26: =IFERROR(subQ!AE19/subQ!AE18,"") | AF26: =$D$56 | AG26: =$D$56 | AH26: =$D$56 | AI26: =$D$56 | AJ26: =IFERROR(subQ!AJ19/subQ!AJ18,"") | AK26: =$D$56 | AL26: =$D$56 | AM26: =$D$56 | AN26: =$D$56 | AO26: =IFERROR(subQ!AO19/subQ!AO18,"")
A27: drv:중단사업이익 | B27: abs | C27: 중단사업이익 (가정, 억원) | E27: =subQ!E20 | F27: =subQ!F20 | G27: =subQ!G20 | H27: =subQ!H20 | I27: =subQ!I20 | J27: =subQ!J20 | K27: =subQ!K20 | L27: =subQ!L20 | ... AB27: =subQ!AB20 | AE27: =subQ!AE20 | AJ27: =subQ!AJ20 | AO27: =subQ!AO20
A28: drv:부채총계 | B28: qoq | C28: 부채총계 QoQ | G28: =IFERROR(subQ!G22/subQ!E22-1,"") | H28: =IFERROR(subQ!H22/subQ!G22-1,"") | I28: =IFERROR(subQ!I22/subQ!H22-1,"") | J28: =IFERROR(subQ!J22/subQ!I22-1,"") | L28: =IFERROR(subQ!L22/subQ!J22-1,"") | M28: =IFERROR(subQ!M22/subQ!L22-1,"") | N28: =IFERROR(subQ!N22/subQ!M22-1,"") | O28: =IFERROR(subQ!O22/subQ!N22-1,"") | Q28: =IFERROR(subQ!Q22/subQ!O22-1,"") | R28: =IFERROR(subQ!R22/subQ!Q22-1,"") | S28: =IFERROR(subQ!S22/subQ!R22-1,"") | T28: =IFERROR(subQ!T22/subQ!S22-1,"") | V28: =IFERROR(subQ!V22/subQ!T22-1,"") | W28: =IFERROR(subQ!W22/subQ!V22-1,"") | X28: =IFERROR(subQ!X22/subQ!W22-1,"") | Y28: =IFERROR(subQ!Y22/subQ!X22-1,"") | AA28: =IFERROR(subQ!AA22/subQ!Y22-1,"") | AB28: =IFERROR(subQ!AB22/subQ!AA22-1,"") | AC28: 3.56e-07 | AD28: 0 | AF28: 0 | AG28: 0 | AH28: 0 | AI28: 0 | AK28: 0 | AL28: 0 | AM28: 0 | AN28: 0
A29: drv:자본총계 | B29: roll | C29: 자본총계 기타변동(배당 등, 억원) | G29: =IFERROR(subQ!E23+subQ!G18-subQ!G23,"") | H29: =IFERROR(subQ!G23+subQ!H18-subQ!H23,"") | I29: =IFERROR(subQ!H23+subQ!I18-subQ!I23,"") | J29: =IFERROR(subQ!I23+subQ!J18-subQ!J23,"") | L29: =IFERROR(subQ!J23+subQ!L18-subQ!L23,"") | M29: =IFERROR(subQ!L23+subQ!M18-subQ!M23,"") | N29: =IFERROR(subQ!M23+subQ!N18-subQ!N23,"") | O29: =IFERROR(subQ!N23+subQ!O18-subQ!O23,"") | Q29: =IFERROR(subQ!O23+subQ!Q18-subQ!Q23,"") | R29: =IFERROR(subQ!Q23+subQ!R18-subQ!R23,"") | S29: =IFERROR(subQ!R23+subQ!S18-subQ!S23,"") | T29: =IFERROR(subQ!S23+subQ!T18-subQ!T23,"") | V29: =IFERROR(subQ!T23+subQ!V18-subQ!V23,"") | W29: =IFERROR(subQ!V23+subQ!W18-subQ!W23,"") | X29: =IFERROR(subQ!W23+subQ!X18-subQ!X23,"") | Y29: =IFERROR(subQ!X23+subQ!Y18-subQ!Y23,"") | AA29: =IFERROR(subQ!Y23+subQ!AA18-subQ!AA23,"") | AB29: =IFERROR(subQ!AA23+subQ!AB18-subQ!AB23,"") | AC29: -0.004051246 | AD29: 0.004119066 | AF29: 0.001433243 | AG29: 127.91472 | AH29: 0.002618455 | AI29: 0.002143904 | AK29: -0.009662611 | AL29: 127.91791 | AM29: 0.007379189 | AN29: -0.008022117
A30: drv:지배주주지분 | B30: roll | C30: 지배주주지분 기타변동(배당 등, 억원) | G30: =IFERROR(subQ!E24+subQ!G19-subQ!G24,"") | H30: =IFERROR(subQ!G24+subQ!H19-subQ!H24,"") | I30: =IFERROR(subQ!H24+subQ!I19-subQ!I24,"") | J30: =IFERROR(subQ!I24+subQ!J19-subQ!J24,"") | L30: =IFERROR(subQ!J24+subQ!L19-subQ!L24,"") | M30: =IFERROR(subQ!L24+subQ!M19-subQ!M24,"") | N30: =IFERROR(subQ!M24+subQ!N19-subQ!N24,"") | O30: =IFERROR(subQ!N24+subQ!O19-subQ!O24,"") | Q30: =IFERROR(subQ!O24+subQ!Q19-subQ!Q24,"") | R30: =IFERROR(subQ!Q24+subQ!R19-subQ!R24,"") | S30: =IFERROR(subQ!R24+subQ!S19-subQ!S24,"") | T30: =IFERROR(subQ!S24+subQ!T19-subQ!T24,"") | V30: =IFERROR(subQ!T24+subQ!V19-subQ!V24,"") | W30: =IFERROR(subQ!V24+subQ!W19-subQ!W24,"") | X30: =IFERROR(subQ!W24+subQ!X19-subQ!X24,"") | Y30: =IFERROR(subQ!X24+subQ!Y19-subQ!Y24,"") | AA30: =IFERROR(subQ!Y24+subQ!AA19-subQ!AA24,"") | AB30: =IFERROR(subQ!AA24+subQ!AB19-subQ!AB24,"") | AC30: -0.004407822 | AD30: 0.010950517 | AF30: 0.000902872 | AG30: 127.91259 | AH30: 0.006426646 | AI30: -0.002653627 | AK30: -0.003054244 | AL30: 127.91709 | AM30: 0.007173953 | AN30: 0.002141468
A31: drv:총차입금 | B31: qoq | C31: 총차입금 QoQ | G31: =IFERROR(subQ!G25/subQ!E25-1,"") | H31: =IFERROR(subQ!H25/subQ!G25-1,"") | I31: =IFERROR(subQ!I25/subQ!H25-1,"") | J31: =IFERROR(subQ!J25/subQ!I25-1,"") | L31: =IFERROR(subQ!L25/subQ!J25-1,"") | M31: =IFERROR(subQ!M25/subQ!L25-1,"") | N31: =IFERROR(subQ!N25/subQ!M25-1,"") | O31: =IFERROR(subQ!O25/subQ!N25-1,"") | Q31: =IFERROR(subQ!Q25/subQ!O25-1,"") | R31: =IFERROR(subQ!R25/subQ!Q25-1,"") | S31: =IFERROR(subQ!S25/subQ!R25-1,"") | T31: =IFERROR(subQ!T25/subQ!S25-1,"") | V31: =IFERROR(subQ!V25/subQ!T25-1,"") | W31: =IFERROR(subQ!W25/subQ!V25-1,"") | X31: =IFERROR(subQ!X25/subQ!W25-1,"") | Y31: =IFERROR(subQ!Y25/subQ!X25-1,"") | AA31: =IFERROR(subQ!AA25/subQ!Y25-1,"") | AB31: =IFERROR(subQ!AB25/subQ!AA25-1,"") | AC31: 0 | AD31: 0 | AF31: 0 | AG31: 0 | AH31: 0 | AI31: 0 | AK31: 0 | AL31: 0 | AM31: 0 | AN31: 0
A32: drv:순차입금 | B32: qoq | C32: 순차입금 QoQ | G32: =IFERROR(subQ!G26/subQ!E26-1,"") | H32: =IFERROR(subQ!H26/subQ!G26-1,"") | I32: =IFERROR(subQ!I26/subQ!H26-1,"") | J32: =IFERROR(subQ!J26/subQ!I26-1,"") | L32: =IFERROR(subQ!L26/subQ!J26-1,"") | M32: =IFERROR(subQ!M26/subQ!L26-1,"") | N32: =IFERROR(subQ!N26/subQ!M26-1,"") | O32: =IFERROR(subQ!O26/subQ!N26-1,"") | Q32: =IFERROR(subQ!Q26/subQ!O26-1,"") | R32: =IFERROR(subQ!R26/subQ!Q26-1,"") | S32: =IFERROR(subQ!S26/subQ!R26-1,"") | T32: =IFERROR(subQ!T26/subQ!S26-1,"") | V32: =IFERROR(subQ!V26/subQ!T26-1,"") | W32: =IFERROR(subQ!W26/subQ!V26-1,"") | X32: =IFERROR(subQ!X26/subQ!W26-1,"") | Y32: =IFERROR(subQ!Y26/subQ!X26-1,"") | AA32: =IFERROR(subQ!AA26/subQ!Y26-1,"") | AB32: =IFERROR(subQ!AB26/subQ!AA26-1,"") | AC32: -0.078038257 | AD32: -0.11637173 | AF32: -0.094526295 | AG32: 0.003511428 | AH32: -0.11139993 | AI32: -0.17109543 | AK32: -0.14957676 | AL32: -0.00547011 | AM32: -0.18973491 | AN32: -0.31783644
A33: drv:이자발생자산 | B33: qoq | C33: 이자발생자산 QoQ | G33: =IFERROR(subQ!G27/subQ!E27-1,"") | H33: =IFERROR(subQ!H27/subQ!G27-1,"") | I33: =IFERROR(subQ!I27/subQ!H27-1,"") | J33: =IFERROR(subQ!J27/subQ!I27-1,"") | L33: =IFERROR(subQ!L27/subQ!J27-1,"") | M33: =IFERROR(subQ!M27/subQ!L27-1,"") | N33: =IFERROR(subQ!N27/subQ!M27-1,"") | O33: =IFERROR(subQ!O27/subQ!N27-1,"") | Q33: =IFERROR(subQ!Q27/subQ!O27-1,"") | R33: =IFERROR(subQ!R27/subQ!Q27-1,"") | S33: =IFERROR(subQ!S27/subQ!R27-1,"") | T33: =IFERROR(subQ!T27/subQ!S27-1,"") | V33: =IFERROR(subQ!V27/subQ!T27-1,"") | W33: =IFERROR(subQ!W27/subQ!V27-1,"") | X33: =IFERROR(subQ!X27/subQ!W27-1,"") | Y33: =IFERROR(subQ!Y27/subQ!X27-1,"") | AA33: =IFERROR(subQ!AA27/subQ!Y27-1,"") | AB33: =IFERROR(subQ!AB27/subQ!AA27-1,"") | AC33: 0.083679367 | AD33: 0.1061647 | AF33: 0.068886655 | AG33: -0.002167756 | AH33: 0.069163403 | AI33: 0.088291331 | AK33: 0.058781595 | AL33: 0.001731364 | AM33: 0.059464205 | AN33: 0.076177775
A34: drv:현금및현금성자산 | B34: qoq | C34: 현금및현금성자산 QoQ | G34: =IFERROR(subQ!G28/subQ!E28-1,"") | H34: =IFERROR(subQ!H28/subQ!G28-1,"") | I34: =IFERROR(subQ!I28/subQ!H28-1,"") | J34: =IFERROR(subQ!J28/subQ!I28-1,"") | L34: =IFERROR(subQ!L28/subQ!J28-1,"") | M34: =IFERROR(subQ!M28/subQ!L28-1,"") | N34: =IFERROR(subQ!N28/subQ!M28-1,"") | O34: =IFERROR(subQ!O28/subQ!N28-1,"") | Q34: =IFERROR(subQ!Q28/subQ!O28-1,"") | R34: =IFERROR(subQ!R28/subQ!Q28-1,"") | S34: =IFERROR(subQ!S28/subQ!R28-1,"") | T34: =IFERROR(subQ!T28/subQ!S28-1,"") | V34: =IFERROR(subQ!V28/subQ!T28-1,"") | W34: =IFERROR(subQ!W28/subQ!V28-1,"") | X34: =IFERROR(subQ!X28/subQ!W28-1,"") | Y34: =IFERROR(subQ!Y28/subQ!X28-1,"") | AA34: =IFERROR(subQ!AA28/subQ!Y28-1,"") | AB34: =IFERROR(subQ!AB28/subQ!AA28-1,"")
A35: drv:CAPEX | B35: yoy | C35: CAPEX YoY | J35: =IFERROR(subQ!J29/subQ!E29-1,"") | L35: =IFERROR(subQ!L29/subQ!G29-1,"") | M35: =IFERROR(subQ!M29/subQ!H29-1,"") | N35: =IFERROR(subQ!N29/subQ!I29-1,"") | O35: =IFERROR(subQ!O29/subQ!J29-1,"") | Q35: =IFERROR(subQ!Q29/subQ!L29-1,"") | R35: =IFERROR(subQ!R29/subQ!M29-1,"") | S35: =IFERROR(subQ!S29/subQ!N29-1,"") | T35: =IFERROR(subQ!T29/subQ!O29-1,"") | V35: =IFERROR(subQ!V29/subQ!Q29-1,"") | W35: =IFERROR(subQ!W29/subQ!R29-1,"") | X35: =IFERROR(subQ!X29/subQ!S29-1,"") | Y35: =IFERROR(subQ!Y29/subQ!T29-1,"") | AA35: =IFERROR(subQ!AA29/subQ!V29-1,"") | AB35: =IFERROR(subQ!AB29/subQ!W29-1,"") | AC35: 0.56216496 | AD35: -0.17731856 | AF35: 0.27488305 | AG35: -0.53450681 | AH35: 0 | AI35: 0 | AK35: 0 | AL35: 0 | AM35: 0 | AN35: 0
A36: drv:영업활동현금흐름 | B36: yoy | C36: 영업활동현금흐름 YoY | J36: =IFERROR(subQ!J30/subQ!E30-1,"") | L36: =IFERROR(subQ!L30/subQ!G30-1,"") | M36: =IFERROR(subQ!M30/subQ!H30-1,"") | N36: =IFERROR(subQ!N30/subQ!I30-1,"") | O36: =IFERROR(subQ!O30/subQ!J30-1,"") | Q36: =IFERROR(subQ!Q30/subQ!L30-1,"") | R36: =IFERROR(subQ!R30/subQ!M30-1,"") | S36: =IFERROR(subQ!S30/subQ!N30-1,"") | T36: =IFERROR(subQ!T30/subQ!O30-1,"") | V36: =IFERROR(subQ!V30/subQ!Q30-1,"") | W36: =IFERROR(subQ!W30/subQ!R30-1,"") | X36: =IFERROR(subQ!X30/subQ!S30-1,"") | Y36: =IFERROR(subQ!Y30/subQ!T30-1,"") | AA36: =IFERROR(subQ!AA30/subQ!V30-1,"") | AB36: =IFERROR(subQ!AB30/subQ!W30-1,"")
A37: drv:주식수 | B37: qoq | C37: 주식수 QoQ | G37: =IFERROR(subQ!G31/subQ!E31-1,"") | H37: =IFERROR(subQ!H31/subQ!G31-1,"") | I37: =IFERROR(subQ!I31/subQ!H31-1,"") | J37: =IFERROR(subQ!J31/subQ!I31-1,"") | L37: =IFERROR(subQ!L31/subQ!J31-1,"") | M37: =IFERROR(subQ!M31/subQ!L31-1,"") | N37: =IFERROR(subQ!N31/subQ!M31-1,"") | O37: =IFERROR(subQ!O31/subQ!N31-1,"") | Q37: =IFERROR(subQ!Q31/subQ!O31-1,"") | R37: =IFERROR(subQ!R31/subQ!Q31-1,"") | S37: =IFERROR(subQ!S31/subQ!R31-1,"") | T37: =IFERROR(subQ!T31/subQ!S31-1,"") | V37: =IFERROR(subQ!V31/subQ!T31-1,"") | W37: =IFERROR(subQ!W31/subQ!V31-1,"") | X37: =IFERROR(subQ!X31/subQ!W31-1,"") | Y37: =IFERROR(subQ!Y31/subQ!X31-1,"") | AA37: =IFERROR(subQ!AA31/subQ!Y31-1,"") | AB37: =IFERROR(subQ!AB31/subQ!AA31-1,"") | AC37: 0 | AD37: 0 | AF37: 0 | AG37: 0 | AH37: 0 | AI37: 0 | AK37: 0 | AL37: 0 | AM37: 0 | AN37: 0
A38: drv:DPS | B38: abs | C38: DPS (가정, 원) | E38: =subQ!E34 | F38: =subQ!F34 | G38: =subQ!G34 | H38: =subQ!H34 | I38: =subQ!I34 | J38: =subQ!J34 | K38: =subQ!K34 | L38: =subQ!L34 | ... AB38: =subQ!AB34 | AD38: 225 | AE38: =subQ!AE34 | AI38: 225 | AJ38: =subQ!AJ34 | AN38: 225 | AO38: =subQ!AO34
A39: drv:매출조선기자재 | B39: yoy | C39: 매출조선기자재 YoY | J39: =IFERROR(subQ!J37/subQ!E37-1,"") | L39: =IFERROR(subQ!L37/subQ!G37-1,"") | M39: =IFERROR(subQ!M37/subQ!H37-1,"") | N39: =IFERROR(subQ!N37/subQ!I37-1,"") | O39: =IFERROR(subQ!O37/subQ!J37-1,"") | Q39: =IFERROR(subQ!Q37/subQ!L37-1,"") | R39: =IFERROR(subQ!R37/subQ!M37-1,"") | S39: =IFERROR(subQ!S37/subQ!N37-1,"") | T39: =IFERROR(subQ!T37/subQ!O37-1,"") | V39: =IFERROR(subQ!V37/subQ!Q37-1,"") | W39: =IFERROR(subQ!W37/subQ!R37-1,"") | X39: =IFERROR(subQ!X37/subQ!S37-1,"") | Y39: =IFERROR(subQ!Y37/subQ!T37-1,"") | AA39: =IFERROR(subQ!AA37/subQ!V37-1,"") | AB39: =IFERROR(subQ!AB37/subQ!W37-1,"") | AC39: 0.026095373 | AD39: 0.026094896 | AF39: 0.026111765 | AG39: 0.026101455 | AH39: 0.013060514 | AI39: 0.01305611 | AK39: 0.013041581 | AL39: 0.01305776 | AM39: 0.006517691 | AN39: 0.006524584
A40: drv:OP조선기자재 | B40: ratio | C40: OP조선기자재 마진(/매출조선기자재) | E40: =IFERROR(subQ!E38/subQ!E37,"") | F40: =IFERROR(subQ!F38/subQ!F37,"") | G40: =IFERROR(subQ!G38/subQ!G37,"") | H40: =IFERROR(subQ!H38/subQ!H37,"") | I40: =IFERROR(subQ!I38/subQ!I37,"") | J40: =IFERROR(subQ!J38/subQ!J37,"") | K40: =IFERROR(subQ!K38/subQ!K37,"") | L40: =IFERROR(subQ!L38/subQ!L37,"") | ... AB40: =IFERROR(subQ!AB38/subQ!AB37,"") | AC40: 0.15727035 | AD40: 0.15727256 | AE40: =IFERROR(subQ!AE38/subQ!AE37,"") | AF40: 0.15727199 | AG40: 0.15726594 | AH40: 0.15727212 | AI40: 0.15727115 | AJ40: =IFERROR(subQ!AJ38/subQ!AJ37,"") | AK40: 0.15726576 | AL40: 0.15726979 | AM40: 0.15727365 | AN40: 0.15726675 | AO40: =IFERROR(subQ!AO38/subQ!AO37,"")
A41: drv:매출종속사 | B41: yoy | C41: 매출종속사 YoY | J41: =IFERROR(subQ!J39/subQ!E39-1,"") | L41: =IFERROR(subQ!L39/subQ!G39-1,"") | M41: =IFERROR(subQ!M39/subQ!H39-1,"") | N41: =IFERROR(subQ!N39/subQ!I39-1,"") | O41: =IFERROR(subQ!O39/subQ!J39-1,"") | Q41: =IFERROR(subQ!Q39/subQ!L39-1,"") | R41: =IFERROR(subQ!R39/subQ!M39-1,"") | S41: =IFERROR(subQ!S39/subQ!N39-1,"") | T41: =IFERROR(subQ!T39/subQ!O39-1,"") | V41: =IFERROR(subQ!V39/subQ!Q39-1,"") | W41: =IFERROR(subQ!W39/subQ!R39-1,"") | X41: =IFERROR(subQ!X39/subQ!S39-1,"") | Y41: =IFERROR(subQ!Y39/subQ!T39-1,"") | AA41: =IFERROR(subQ!AA39/subQ!V39-1,"") | AB41: =IFERROR(subQ!AB39/subQ!W39-1,"") | AC41: -0.010274649 | AD41: 0.24633327 | AF41: 0.16379959 | AG41: -0.00752985 | AH41: 0.1792773 | AI41: 0.16577343 | AK41: 0.18993579 | AL41: 0.22139528 | AM41: 0.24567462 | AN41: 0.24548175
A42: drv:OP종속사 | B42: ratio | C42: OP종속사 마진(/매출종속사) | E42: =IFERROR(subQ!E40/subQ!E39,"") | F42: =IFERROR(subQ!F40/subQ!F39,"") | G42: =IFERROR(subQ!G40/subQ!G39,"") | H42: =IFERROR(subQ!H40/subQ!H39,"") | I42: =IFERROR(subQ!I40/subQ!I39,"") | J42: =IFERROR(subQ!J40/subQ!J39,"") | K42: =IFERROR(subQ!K40/subQ!K39,"") | L42: =IFERROR(subQ!L40/subQ!L39,"") | ... AB42: =IFERROR(subQ!AB40/subQ!AB39,"") | AC42: 0.18814135 | AD42: 0.18823196 | AE42: =IFERROR(subQ!AE40/subQ!AE39,"") | AF42: 0.1887242 | AG42: 0.18859063 | AH42: 0.18814965 | AI42: 0.18819781 | AJ42: =IFERROR(subQ!AJ40/subQ!AJ39,"") | AK42: 0.1887388 | AL42: 0.18857041 | AM42: 0.18814384 | AN42: 0.18821163 | AO42: =IFERROR(subQ!AO40/subQ!AO39,"")
A43: drv:매출연결조정 | B43: ratio | C43: 매출연결조정 비율(/매출종속사 — 내부거래·잔차) | E43: =IFERROR(subQ!E41/subQ!E39,"") | F43: =IFERROR(subQ!F41/subQ!F39,"") | G43: =IFERROR(subQ!G41/subQ!G39,"") | H43: =IFERROR(subQ!H41/subQ!H39,"") | I43: =IFERROR(subQ!I41/subQ!I39,"") | J43: =IFERROR(subQ!J41/subQ!J39,"") | K43: =IFERROR(subQ!K41/subQ!K39,"") | L43: =IFERROR(subQ!L41/subQ!L39,"") | ... AB43: =IFERROR(subQ!AB41/subQ!AB39,"") | AC43: -0.62515472 | AD43: -0.62515242 | AE43: =IFERROR(subQ!AE41/subQ!AE39,"") | AF43: -0.6251363 | AG43: -0.62516709 | AH43: -0.62515659 | AI43: -0.62516115 | AJ43: =IFERROR(subQ!AJ41/subQ!AJ39,"") | AK43: -0.6251697 | AL43: -0.62516639 | AM43: -0.62515289 | AN43: -0.62515868 | AO43: =IFERROR(subQ!AO41/subQ!AO39,"")
A44: drv:OP연결조정 | B44: ratio | C44: OP연결조정 마진(/매출연결조정) | E44: =IFERROR(subQ!E42/subQ!E41,"") | F44: =IFERROR(subQ!F42/subQ!F41,"") | G44: =IFERROR(subQ!G42/subQ!G41,"") | H44: =IFERROR(subQ!H42/subQ!H41,"") | I44: =IFERROR(subQ!I42/subQ!I41,"") | J44: =IFERROR(subQ!J42/subQ!J41,"") | K44: =IFERROR(subQ!K42/subQ!K41,"") | L44: =IFERROR(subQ!L42/subQ!L41,"") | ... AB44: =IFERROR(subQ!AB42/subQ!AB41,"") | AC44: 0.14044836 | AD44: 0.14379026 | AE44: =IFERROR(subQ!AE42/subQ!AE41,"") | AF44: 0.14251567 | AG44: 0.14493759 | AH44: 0.14883016 | AI44: 0.15112252 | AJ44: =IFERROR(subQ!AJ42/subQ!AJ41,"") | AK44: 0.15119435 | AL44: 0.15443577 | AM44: 0.1586087 | AN44: 0.16051234 | AO44: =IFERROR(subQ!AO42/subQ!AO41,"")
B46: 3. 밸류에이션·스칼라 | C46: 노란 셀 = 가정. '연결' 표시는 추정 전 분기 수식이 이 셀을 참조한다는 뜻
A47: sc:종가 | C47: 종가 | D47: 8710 | E47: 원 — 네이버 정규장 종가(aik 확정종가 대조 · aik 8,640원)
A48: sc:기준일 | C48: 기준일 | D48: 20261014 | E48: 종가 기준일
A49: sc:COE | C49: COE | D49: 0.09 | E49: 자기자본비용(가정) — TP 적정 PBR = ROE/COE
A50: sc:PER_lo | C50: PER_lo | D50: 19 | E50: PER 밴드 하단(배) — hist_quarterly(분기 평균가 ÷ TTM EPS, 15분기, 25/50/75 백분위)
A51: sc:PER_mid | C51: PER_mid | D51: 22 | E51: PER 밴드 중단(배)
A52: sc:PER_hi | C52: PER_hi | D52: 27.4 | E52: PER 밴드 상단(배)
A53: sc:EPS_Y1가중 | C53: EPS_Y1가중 | D53: 0.5 | E53: 12M fwd EPS = FY(last_actual연도)E × w + FY+1E × (1−w) — 기준 분기 2Q 이면 0.5(가정)
A54: sc:세율 | C54: 세율 | D54: 0.19115989 | E54: 연결 — 법인세 = MAX(세전,0) × 세율(역산, 재현 오차 ≤ 0.05억 · 모델 assumptions 0.1912) · 최근 12분기 유효세율 19.1%(5~27% 안 — 그대로)
A55: sc:판관비율 | C55: 판관비율 | D55: 0.061317488 | E55: 연결 — 판관비 = 매출액 × 판관비율(역산, 재현 오차 ≤ 0.05억 · 모델 assumptions 0.0613)
A56: sc:지배주주비중 | C56: 지배주주비중 | D56: 0.8217694 | E56: 연결 — 지배주주순이익 = 당기순이익 × 비중(역산, 재현 오차 ≤ 0.05억)
A57: sc:이자율_자산 | C57: 이자율_자산 | D57: 0.036096874 | E57: 연결 — 이자손익 = (전분기 이자발생자산 × 자산이자율 − 전분기 총차입금 × 부채이자율)/4(역산, 재현 오차 ≤ 0.05억 · 모델 assumptions 0.0361)
A58: sc:이자율_부채 | C58: 이자율_부채 | D58: 0.038697218 | E58: 연결 — 같은 수식의 부채 쪽(총차입금 행이 없으면 0)(역산, 재현 오차 ≤ 0.05억 · 모델 assumptions 0.0387)
A59: sc:배당성향 | C59: 배당성향 | D59: 0.2524 | E59: 배당성향(참고 — 모델은 직전 DPS 유지·Q2 지급 가정)
A60: sc:외화순노출_백만$ | C60: 외화순노출_백만$ | E60: 외화 순노출 × Δ기말환율 (외화 시트 방식) — 외화 순노출 미공시(face) → 0 + 표기
A61: sc:헤지비율 | C61: 헤지비율 | E61: sls 없음
A62: sc:헤지환율_약정 | C62: 헤지환율_약정 | E62: sls 없음

Sheet BS연결
B1: (백만원) | C1: 이름: BS연결H | E1: 4Q21 | F1: 2021 | G1: 1Q22 | H1: 2Q22 | I1: 3Q22 | J1: 4Q22 | K1: 2022 | L1: 1Q23 | M1: 2Q23 | N1: 3Q23 | O1: 4Q23 | P1: 2023 | Q1: 1Q24 | R1: 2Q24 | S1: 3Q24 | T1: 4Q24 | U1: 2024 | V1: 1Q25 | W1: 2Q25 | X1: 3Q25 | Y1: 4Q25 | Z1: 2025 | AA1: 1Q26 | AB1: 2Q26 | AC1: 3Q26 | AD1: 4Q26 | AE1: 2026 | AF1: 1Q27 | AG1: 2Q27 | AH1: 3Q27 | AI1: 4Q27 | AJ1: 2027 | AK1: 1Q28 | AL1: 2Q28 | AM1: 3Q28 | AN1: 4Q28 | AO1: 2028
B2: 연결 | D2: fin json(kship_fin.py)
B3: 세진중공업(연) | C3: UPDATE: 26-10-14 | E3: 1 | F3: 2 | G3: 3 | H3: 4 | I3: 5 | J3: 6 | K3: 7 | L3: 8 | M3: 9 | N3: 10 | O3: 11 | P3: 12 | Q3: 13 | R3: 14 | S3: 15 | T3: 16 | U3: 17 | V3: 18 | W3: 19 | X3: 20 | Y3: 21 | Z3: 22 | AA3: 23 | AB3: 24 | AC3: 25 | AD3: 26 | AE3: 27 | AF3: 28 | AG3: 29 | AH3: 30 | AI3: 31 | AJ3: 32 | AK3: 33 | AL3: 34 | AM3: 35 | AN3: 36 | AO3: 37
B4: Account Code | C4: AccountNAME | E4: 2021.12 | F4: 2021.12A | G4: 2022.03 | H4: 2022.06 | I4: 2022.09 | J4: 2022.12 | K4: 2022.12A | L4: 2023.03 | M4: 2023.06 | N4: 2023.09 | O4: 2023.12 | P4: 2023.12A | Q4: 2024.03 | R4: 2024.06 | S4: 2024.09 | T4: 2024.12 | U4: 2024.12A | V4: 2025.03 | W4: 2025.06 | X4: 2025.09 | Y4: 2025.12 | Z4: 2025.12A | AA4: 2026.03 | AB4: 2026.06 | AC4: 2026.09 | AD4: 2026.12 | AE4: 2026.12A | AF4: 2027.03 | AG4: 2027.06 | AH4: 2027.09 | AI4: 2027.12 | AJ4: 2027.12A | AK4: 2028.03 | AL4: 2028.06 | AM4: 2028.09 | AN4: 2028.12 | AO4: 2028.12A
A5: 1 | C5: 유동자산 | E5: 199499.6 | F5: 199499.6 | G5: 178998.74 | H5: 145458.76 | I5: 159282.22 | J5: 154824.32 | K5: 154824.32 | L5: 150175.35 | M5: 131074.64 | N5: 126481.93 | O5: 125520.79 | P5: 125520.79 | Q5: 163955.01 | R5: 132666.8 | S5: 160199.03 | T5: 179641.93 | U5: 179641.93 | V5: 182158.07 | W5: 166651.69 | X5: 174398.44 | Y5: 164044.5 | Z5: 164044.5 | AA5: 177482.15 | AB5: 177209.19
A6: 1 | C6: 현금및현금성자산 | E6: 37668.74 | F6: 37668.74 | G6: 40389.7 | H6: 12766.44 | I6: 31143.77 | J6: 47137.19 | K6: 47137.19 | L6: 30087.12 | M6: 37120.17 | N6: 40568.36 | O6: 50751.66 | P6: 50751.66 | Q6: 69793.88 | R6: 46285.73 | S6: 79948.17 | T6: 79542.42 | U6: 79542.42 | V6: 74589.69 | W6: 89559.22 | X6: 97942.03 | Y6: 55053.8 | Z6: 55053.8 | AA6: 69548.18 | AB6: 43468.91
A7: 1 | C7: 단기투자자산(공정가치) | E7: 414.25 | F7: 414.25 | G7: 436.36 | H7: 386.91 | I7: 382.89 | J7: 394.77 | K7: 394.77 | L7: 406.03 | M7: 415.68 | N7: 450.65 | O7: 476.78 | P7: 476.78 | Q7: 0
A8: 1 | C8: 단기금융상품 | E8: 3975.43 | F8: 3975.43 | G8: 2010 | H8: 2010 | I8: 2015.2 | J8: 2013.54 | K8: 2013.54 | L8: 2019.17 | M8: 2011.56 | N8: 2010 | O8: 2011.53 | P8: 2011.53 | Q8: 2011.6 | R8: 2010 | S8: 2010 | T8: 11.75 | U8: 11.75 | V8: 10 | W8: 4996.7 | X8: 16217.23 | Y8: 26775.25 | Z8: 26775.25 | AA8: 35654.3 | AB8: 58677.94
A9: 1 | C9: 단기금융자산 | E9: 3975.43 | F9: 3975.43 | G9: 2010 | H9: 2010 | I9: 2015.2 | J9: 2013.54 | K9: 2013.54 | L9: 2019.17 | M9: 2011.56 | N9: 2010 | O9: 2011.53 | P9: 2011.53 | Q9: 2011.6 | R9: 2010 | S9: 2010 | T9: 11.75 | U9: 11.75 | V9: 10 | W9: 4996.7 | X9: 16217.23 | Y9: 26775.25 | Z9: 26775.25 | AA9: 35654.3 | AB9: 58677.94
A10: 1 | C10: 매출채권및기타채권 | E10: 32200.79 | F10: 32200.79 | G10: 56949.79 | H10: 43764.56 | I10: 30744.95 | J10: 29976.11 | K10: 29976.11 | L10: 39667.71 | M10: 39739.61 | N10: 28237.24 | O10: 29868.82 | P10: 29868.82 | Q10: 48163.6 | R10: 35810.35 | S10: 23892.82 | T10: 51576.69 | U10: 51576.69 | V10: 61521.1 | W10: 25806.6 | X10: 16031.6 | Y10: 38555.76 | Z10: 38555.76 | AA10: 24497.43 | AB10: 26230.92
A11: 1 | C11: 계약자산 | E11: 1962.36 | F11: 1962.36 | G11: 1165.39 | H11: 4726.92 | I11: 5004.79 | J11: 391.95 | K11: 391.95 | L11: 847.94 | M11: 406.02 | N11: 0 | O11: 190.13 | P11: 190.13 | Q11: 193.98 | R11: 192.44 | S11: 192.44 | T11: 5177.82 | U11: 5177.82 | V11: 192.44 | W11: 3878.74 | X11: 0
A12: 1 | C12: 기타유동자산 | E12: 10619.74 | F12: 10619.74 | G12: 7458.66 | H12: 5760.64 | I12: 6019.22 | J12: 5232.07 | K12: 5232.07 | L12: 5726.46 | M12: 3762.84 | N12: 6340.32 | O12: 6147.61 | P12: 6147.61 | Q12: 6158.9 | R12: 8248.57 | S12: 13467.6 | T12: 11970.72 | U12: 11970.72 | V12: 11509.09 | W12: 8875.87 | X12: 7883.43 | Y12: 12008.7 | Z12: 12008.7 | AA12: 11523.03 | AB12: 13635.84
A13: 1 | C13: 당기법인세자산(선급법인세) | E13: 20.99 | F13: 20.99 | G13: 8.31 | H13: 7.1 | I13: 8.26 | J13: 10.08 | K13: 10.08 | L13: 11.04 | M13: 1.95 | N13: 85.61 | O13: 3.98 | P13: 3.98 | Q13: 5.09 | R13: 2.2 | S13: 7.18 | T13: 68.65 | U13: 68.65 | V13: 69.58 | W13: 0.02 | X13: 0.03 | Y13: 0.05 | Z13: 0.05 | AA13: 0.06 | AB13: 0.02
A14: 1 | C14: 재고자산 | E14: 112637.3 | F14: 112637.3 | G14: 70580.53 | H14: 76036.19 | I14: 83963.14 | J14: 69668.6 | K14: 69668.6 | L14: 71409.88 | M14: 47616.81 | N14: 48789.74 | O14: 36070.27 | P14: 36070.27 | Q14: 37627.96 | R14: 40117.5 | S14: 40680.81 | T14: 31293.87 | U14: 31293.87 | V14: 34266.17 | W14: 33534.54 | X14: 36324.12 | Y14: 31650.95 | Z14: 31650.95 | AA14: 36259.16 | AB14: 34209.31
A15: 1 | C15: 매각예정비유동자산및처분자산 | E15: 0 | F15: 0 | J15: 0 | K15: 0 | AB15: 986.25
A16: 1 | C16: 비유동자산 | E16: 370904.7 | F16: 370904.7 | G16: 391461.51 | H16: 409624.06 | I16: 397881.39 | J16: 397024.86 | K16: 397024.86 | L16: 401360.12 | M16: 403480.08 | N16: 418077.89 | O16: 418498.12 | P16: 418498.12 | Q16: 419735.43 | R16: 427112.82 | S16: 430930.39 | T16: 441235.63 | U16: 441235.63 | V16: 447906.82 | W16: 460482.26 | X16: 467095.3 | Y16: 473719.16 | Z16: 473719.16 | AA16: 476315.05 | AB16: 482599.75
A17: 1 | C17: 장기매출채권및기타채권 | E17: 872.57 | F17: 872.57 | G17: 861.53 | H17: 542.56 | I17: 693.24 | J17: 838.04 | K17: 838.04 | L17: 1218.02 | M17: 775.8 | N17: 2377.67 | O17: 1700.85 | P17: 1700.85 | Q17: 1906.73 | R17: 1472.64 | S17: 1353.7 | T17: 1147.73 | U17: 1147.73 | V17: 1178.58 | W17: 14525.28 | X17: 15549.92 | Y17: 19687.52 | Z17: 19687.52 | AA17: 20801.3 | AB17: 21136.61
A18: 1 | C18: 장기금융자산 | E18: 8038.64 | F18: 8038.64 | G18: 8705.57 | H18: 27454.11 | I18: 10643.35 | J18: 9655.03 | K18: 9655.03 | L18: 14891.38 | M18: 16192.66 | N18: 15491 | O18: 15465.86 | P18: 15465.86 | Q18: 15318.81 | R18: 21576.81 | S18: 20500.33 | T18: 19887.19 | U18: 19887.19 | V18: 21519.9 | W18: 22558.18 | X18: 29794.03 | Y18: 30198.26 | Z18: 30198.26 | AA18: 31786.32 | AB18: 36464.26
A19: 1 | C19: 투자자산 | E19: 8038.64 | F19: 8038.64 | G19: 8705.57 | H19: 27454.11 | I19: 10643.35 | J19: 9655.03 | K19: 9655.03 | L19: 14891.38 | M19: 16192.66 | N19: 15491 | O19: 15465.86 | P19: 15465.86 | Q19: 15318.81 | R19: 21576.81 | S19: 20500.33 | T19: 19887.19 | U19: 19887.19 | V19: 21519.9 | W19: 22558.18 | X19: 29794.03 | Y19: 30198.26 | Z19: 30198.26 | AA19: 31786.32 | AB19: 36464.26
A20: 1 | C20: 종속기업및관계기업투자 | E20: 0 | F20: 0 | J20: 0 | K20: 0
A21: 1 | C21: 유형자산 | E21: 339118.58 | F21: 339118.58 | G21: 357299.42 | H21: 359959.38 | I21: 365692.01 | J21: 366038.15 | K21: 366038.15 | L21: 363344.23 | M21: 365127.41 | N21: 378722.38 | O21: 377377.93 | P21: 377377.93 | Q21: 378946.66 | R21: 379986.41 | S21: 383107.34 | T21: 393056.78 | U21: 393056.78 | V21: 392782.08 | W21: 391661.56 | X21: 391418.12 | Y21: 384127.19 | Z21: 384127.19 | AA21: 384477.73 | AB21: 387603.68
A22: 1 | C22: 사용권자산 | E22: 4220.09 | F22: 4220.09 | G22: 4041.95 | H22: 4569.46 | I22: 4239.45 | J22: 4060.19 | K22: 4060.19 | L22: 3904.97 | M22: 4054.65 | N22: 4197.24 | O22: 4046.92 | P22: 4046.92 | Q22: 3755.16 | R22: 3446.25 | S22: 3155.02 | T22: 2849.77 | U22: 2849.77 | V22: 9282.09 | W22: 8737.65 | X22: 8130.05 | Y22: 8009.74 | Z22: 8009.74 | AA22: 7357.28 | AB22: 6710.03
A23: 1 | C23: 기타비유동자산 | E23: 4220.09 | F23: 4220.09 | G23: 4041.95 | H23: 4569.46 | I23: 4239.45 | J23: 4060.19 | K23: 4060.19 | L23: 3904.97 | M23: 4054.65 | N23: 4197.24 | O23: 4046.92 | P23: 4046.92 | Q23: 3755.16 | R23: 3446.25 | S23: 3155.02 | T23: 2849.77 | U23: 2849.77 | V23: 9282.09 | W23: 8737.65 | X23: 8130.05 | Y23: 8009.74 | Z23: 8009.74 | AA23: 7357.28 | AB23: 6710.03
A24: 1 | C24: 무형자산 | E24: 12903.86 | F24: 12903.86 | G24: 12881.58 | H24: 12864.7 | I24: 13254.99 | J24: 13260.69 | K24: 13260.69 | L24: 13240.65 | M24: 13612.61 | N24: 13606.5 | O24: 13583.04 | P24: 13583.04 | Q24: 13565.09 | R24: 13647.45 | S24: 13636.69 | T24: 13619.33 | U24: 13619.33 | V24: 13606.87 | W24: 13594.64 | X24: 13582.88 | Y24: 13571.13 | Z24: 13571.13 | AA24: 13568.75 | AB24: 13565.79
A25: 1 | C25: 이연법인세자산 | E25: 5750.95 | F25: 5750.95 | G25: 7671.46 | H25: 4233.84 | I25: 3358.35 | J25: 3172.76 | K25: 3172.76 | L25: 4760.87 | M25: 3716.96 | N25: 3683.09 | O25: 6323.53 | P25: 6323.53 | Q25: 6242.98 | R25: 6983.25 | S25: 9177.31 | T25: 10674.83 | U25: 10674.83 | V25: 9537.3 | W25: 9404.96 | X25: 8620.29 | Y25: 9956.04 | Z25: 9956.04 | AA25: 10154.37 | AB25: 8950.08
A26: 1 | C26: 자산총계 | E26: 570404.3 | F26: 570404.3 | G26: 570460.24 | H26: 555082.82 | I26: 557163.61 | J26: 551849.17 | K26: 551849.17 | L26: 551535.47 | M26: 534554.72 | N26: 544559.82 | O26: 544018.92 | P26: 544018.92 | Q26: 583690.43 | R26: 559779.61 | S26: 591129.42 | T26: 620877.55 | U26: 620877.55 | V26: 630064.89 | W26: 627133.95 | X26: 641493.74 | Y26: 637763.65 | Z26: 637763.65 | AA26: 653797.2 | AB26: 659808.93
A27: 1 | C27: 유동부채 | E27: 241375.17 | F27: 241375.17 | G27: 218630.7 | H27: 227674.89 | I27: 266883.85 | J27: 245938.22 | K27: 245938.22 | L27: 304791.31 | M27: 283822.14 | N27: 265825.43 | O27: 247450.77 | P27: 247450.77 | Q27: 279334.83 | R27: 254465.61 | S27: 297598.92 | T27: 307570.48 | U27: 307570.48 | V27: 310609.46 | W27: 303540.87 | X27: 227355.89 | Y27: 200224.65 | Z27: 200224.65 | AA27: 220237.9 | AB27: 205546.29
A28: 1 | C28: 매입채무및기타채무 | E28: 56550.61 | F28: 56550.61 | G28: 59034.34 | H28: 44457.98 | I28: 37900.98 | J28: 29354.6 | K28: 29354.6 | L28: 48683.56 | M28: 43355.95 | N28: 51938.46 | O28: 41683.14 | P28: 41683.14 | Q28: 76014.84 | R28: 55300.82 | S28: 48495.62 | T28: 59526.84 | U28: 59526.84 | V28: 69662.71 | W28: 63036.54 | X28: 54729.31 | Y28: 52099.38 | Z28: 52099.38 | AA28: 71940.43 | AB28: 53203.34
A29: 1 | C29: 계약부채 | E29: 39485.15 | F29: 39485.15 | G29: 17379.57 | H29: 12905.83 | I29: 11004.26 | J29: 18123.98 | K29: 18123.98 | L29: 11773.52 | M29: 4814.15 | N29: 4759.15 | O29: 3172.67 | P29: 3172.67 | Q29: 12619.59 | R29: 13529.6 | S29: 15959.13 | T29: 13291.26 | U29: 13291.26 | V29: 5643.76 | W29: 5175 | X29: 17894.37 | Y29: 5175 | Z29: 5175 | AA29: 725.22 | AB29: 4286.67
A30: 1 | C30: 당기법인세부채(미지급법인세) | E30: 12208.71 | F30: 12208.71 | G30: 6629.09 | H30: 73.5 | I30: 602.61 | J30: 673.26 | K30: 673.26 | L30: 368.95 | M30: 3407.76 | N30: 3059.1 | O30: 9241.06 | P30: 9241.06 | Q30: 5777.9 | R30: 5913.41 | S30: 4043.35 | T30: 8325.35 | U30: 8325.35 | V30: 7653.73 | W30: 5743.46 | X30: 2642.92 | Y30: 8488.24 | Z30: 8488.24 | AA30: 9461.33 | AB30: 10603.22
A31: 1 | C31: 단기차입금 | E31: 36740.57 | F31: 36740.57 | G31: 54740.57 | H31: 53740.57 | I31: 57853.57 | J31: 54476.57 | K31: 54476.57 | L31: 56466.57 | M31: 77766.57 | N31: 83727.51 | O31: 88076 | P31: 88076 | Q31: 120076 | R31: 115076 | S31: 136476 | T31: 136476 | U31: 136476 | V31: 136476 | W31: 138461 | X31: 72261 | Y31: 47801 | Z31: 47801 | AA31: 132331 | AB31: 45801
A32: 1 | C32: 유동리스부채 | E32: 1419.51 | F32: 1419.51 | G32: 1212.16 | H32: 1044.11 | I32: 758.47 | J32: 751.68 | K32: 751.68 | L32: 765.63 | M32: 909.29 | N32: 1207.48 | O32: 1269.44 | P32: 1269.44 | Q32: 1561.82 | R32: 1306.15 | S32: 1039.39 | T32: 737.48 | U32: 737.48 | V32: 2861.5 | W32: 2770.68 | X32: 2613.53 | Y32: 2710.97 | Z32: 2710.97 | AA32: 2692.04 | AB32: 2674.43
... A56: 1 | C56: 이자발생자산 | E56: 49682.81 | F56: 49682.81 | G56: 51105.27 | H56: 42230.55 | I56: 43802.32 | J56: 58805.76 | K56: 58805.76 | L56: 46997.67 | M56: 55324.39 | N56: 58069.36 | O56: 68229.05 | P56: 68229.05 | Q56: 87124.29 | R56: 69872.54 | S56: 102458.5 | T56: 99441.36 | U56: 99441.36 | V56: 96119.59 | W56: 117114.1 | X56: 143953.29 | Y56: 112027.31 | Z56: 112027.31 | AA56: 136988.8 | AB56: 138611.11
A57: 1 | C57: 사채 | E57: 15000 | F57: 15000 | G57: 15000
A58: 1 | C58: 유동성장기부채 | E58: 91817.05 | F58: 91817.05 | G58: 76287.64 | H58: 110801.43 | I58: 151129.43 | J58: 138129.43 | K58: 138129.43 | L58: 181137.84 | M58: 147300.49 | N58: 114312.04 | O58: 100526.04 | P58: 100526.04 | Q58: 60880.12 | R58: 60879.96 | S58: 88046.64 | T58: 86330 | U58: 86330 | V58: 86030 | W58: 85730 | X58: 72630 | Y58: 79580 | Z58: 79580 | AB58: 85480
A59: 1 | C59: 투자부동산 | Y59: 8169.29 | Z59: 8169.29 | AA59: 8169.29 | AB59: 8169.29
A60: 1 | C60: 단기금융부채(face) | AA60: 132331
A61: 1 | C61: 장기금융부채(face) | AA61: 119500
A62: 1 | C62: 매출액(수익) | E62: 81901.42 | G62: 139922.87 | H62: 88872.43 | I62: 79905 | J62: 101190.53 | K62: 409890.83 | L62: 71702.28 | M62: 120491.49 | N62: 81986.97 | O62: 110615.72 | P62: 384796.46 | Q62: 86078.31 | R62: 80837.89 | S62: 74151.66 | T62: 111308.71 | U62: 352376.57 | V62: 98495.97 | W62: 98171.23 | X62: 90367.62 | Y62: 115651.44 | Z62: 402686.26 | AA62: 87243.09 | AB62: 93498.44
A63: 1 | C63: 매출원가 | E63: 86831.55 | G63: 141186.13 | H63: 70635.4 | I63: 69460.77 | J63: 81216.71 | K63: 362499.01 | L63: 72913.55 | M63: 93810.07 | N63: 82334.88 | O63: 79153.4 | P63: 328211.9 | Q63: 76060.99 | R63: 67462.41 | S63: 68006.93 | T63: 82318.69 | U63: 293849.02 | V63: 74721.46 | W63: 83099.11 | X63: 72766.24 | Y63: 74138.25 | Z63: 304725.06 | AA63: 67090.32 | AB63: 67311.53
A64: 1 | C64: 매출총이익 | E64: -4930.13 | G64: -1263.26 | H64: 18237.04 | I64: 10444.23 | J64: 19973.82 | K64: 47391.83 | L64: -1211.28 | M64: 26681.42 | N64: -347.92 | O64: 31462.31 | P64: 56584.53 | Q64: 10017.32 | R64: 13375.48 | S64: 6144.73 | T64: 28990.02 | U64: 58527.55 | V64: 23774.51 | W64: 15072.12 | X64: 17601.38 | Y64: 41513.19 | Z64: 97961.2 | AA64: 20152.77 | AB64: 26186.91
A65: 1 | C65: 판관비 | E65: 5562.81 | G65: 5929.56 | H65: 6069.34 | I65: 5843.83 | J65: 4596.74 | K65: 22439.47 | L65: 5208.53 | M65: 5487.14 | N65: 6299.83 | O65: 6034.31 | P65: 23029.81 | Q65: 5757.97 | R65: 5424 | S65: 5506.27 | T65: 5859.82 | U65: 22548.06 | V65: 5973.64 | W65: 6307.66 | X65: 5457.81 | Y65: 6833.45 | Z65: 24572.56 | AA65: 6513.94 | AB65: 5819.28
A66: 1 | C66: 영업이익 | E66: -10492.94 | G66: -7192.81 | H66: 12167.69 | I66: 4600.41 | J66: 15377.08 | K66: 24952.37 | L66: -6419.81 | M66: 21194.28 | N66: -6647.74 | O66: 25428 | P66: 33554.73 | Q66: 4259.35 | R66: 7951.48 | S66: 638.46 | T66: 23130.2 | U66: 35979.49 | V66: 17800.87 | W66: 8764.46 | X66: 12143.57 | Y66: 34679.73 | Z66: 73388.63 | AA66: 13638.83 | AB66: 20367.63
A67: 1 | C67: 기타영업외손익 | E67: -138.22 | G67: -13.94 | H67: 46.41 | I67: 877.05 | J67: -1893.11 | K67: -983.59 | L67: 603.25 | M67: -877.5 | N67: 455.5 | O67: 1758.04 | P67: 1939.29 | Q67: 110.15 | R67: 304.78 | S67: 430.77 | T67: 188.74 | U67: 1034.44 | V67: 305.6 | W67: 209.74 | X67: 166.32 | Y67: 319.8 | Z67: 1001.46 | AA67: 113.32 | AB67: 381.7
A68: 1 | C68: 기타영업외수익 | E68: 995.98 | G68: 111.15 | H68: 263.07 | I68: 1023.21 | J68: 37.09 | K68: 1434.52 | L68: 863.96 | M68: -268.84 | N68: 488.68 | O68: 1756.02 | P68: 2839.82 | Q68: 476.88 | R68: 333.75 | S68: 423.85 | T68: 273.1 | U68: 1507.58 | V68: 476.15 | W68: 320.43 | X68: 194.42 | Y68: 253.39 | Z68: 1244.39 | AA68: 261.62 | AB68: 487.29
A69: 1 | C69: 기타영업외비용 | E69: 1134.2 | G69: 125.09 | H69: 216.66 | I69: 146.17 | J69: 1930.21 | K69: 2418.13 | L69: 260.71 | M69: 608.66 | N69: 33.17 | O69: -2.03 | P69: 900.51 | Q69: 366.73 | R69: 28.97 | S69: -6.92 | T69: 84.37 | U69: 473.15 | V69: 170.55 | W69: 110.69 | X69: 28.1 | Y69: -66.41 | Z69: 242.93 | AA69: 148.3 | AB69: 105.59
A70: 1 | C70: 금융손익 | E70: -622.78 | G70: -2875.26 | H70: 2001.45 | I70: 455.01 | J70: -6405.57 | K70: -6824.37 | L70: -1767.94 | M70: -2749.08 | N70: -1724.77 | O70: -2707.67 | P70: -8949.46 | Q70: -1356.24 | R70: -2509.73 | S70: -2638.48 | T70: -826.9 | U70: -7331.35 | V70: -652.14 | W70: -2214.07 | X70: 472.9 | Y70: 1451.79 | Z70: -941.52 | AA70: 6732.92 | AB70: 6121.02
A71: 1 | C71: 금융수익 | E71: 881.61 | G71: 1261.8 | H71: 2260.37 | I71: 2673.51 | J71: 206.25 | K71: 6401.93 | L71: 1665.89 | M71: 626.16 | N71: 1079.94 | O71: 802.35 | P71: 4174.34 | Q71: 1718.62 | R71: 1129.72 | S71: 1101.25 | T71: 2738.68 | U71: 6688.27 | V71: 2225.28 | W71: 1479.28 | X71: 2886.02 | Y71: 4825.26 | Z71: 11415.84 | AA71: 10861.67 | AB71: 8207.5
A72: 1 | C72: 금융비용 | E72: 1504.4 | G72: 4137.05 | H72: 258.92 | I72: 2218.51 | J72: 6611.82 | K72: 13226.3 | L72: 3433.83 | M72: 3375.24 | N72: 2804.71 | O72: 3510.02 | P72: 13123.8 | Q72: 3074.86 | R72: 3639.45 | S72: 3739.73 | T72: 3565.58 | U72: 14019.62 | V72: 2877.42 | W72: 3693.35 | X72: 2413.12 | Y72: 3373.47 | Z72: 12357.36 | AA72: 4128.76 | AB72: 2086.48
A73: 1 | C73: 종속기업,공동지배기업및관계기업관련손익 | E73: 0 | G73: 0 | H73: 0 | I73: 0 | J73: -574.48 | K73: -574.48 | L73: -17.52 | M73: -240.58 | N73: -135.05 | O73: -325.37 | P73: -718.52 | Q73: -129.75 | R73: -124.23 | S73: -134.75 | T73: -246.38 | U73: -635.11 | V73: -100.49 | W73: 96.05 | X73: -7.91 | Y73: 0.11 | Z73: -12.24 | AA73: 13.82 | AB73: -6.39
... A80: 1 | C80: 계속사업이익 | E80: -9705.37 | G80: -8125.14 | H80: 10747.3 | I80: 4196.2 | J80: 6401.72 | K80: 13220.08 | L80: -6054.53 | M80: 13468.99 | N80: -8556.05 | O80: 24507.57 | P80: 23365.98 | Q80: 2603.33 | R80: 1735.43 | S80: -1120.41 | T80: 18803.1 | U80: 22021.45 | V80: 13181.26 | W80: 4830.15 | X80: 10041.29 | Y80: 31791.76 | Z80: 59844.46 | AA80: 15784.61 | AB80: 20623.42
A81: 1 | C81: 중단사업이익 | N81: 11800.77 | O81: -12436.42 | S81: 0 | T81: 0
A82: 1 | C82: 이자수익 | Q82: 641.92 | R82: 345.4 | S82: 1033.99 | T82: 845.59 | U82: 2866.9 | V82: 509.9 | W82: 1472.31 | X82: 515.16 | Y82: 1897.15 | Z82: 4394.52 | AB82: 731.79
A83: 1 | C83: 이자비용 | Q83: 3045.6 | R83: 2950.03 | S83: 2959.84 | T83: 2990.47 | U83: 11945.94 | V83: 2820.49 | W83: 2880.27 | X83: 2649.45 | Y83: 2486.17 | Z83: 10836.38 | AB83: 2239.9
A84: 1 | C84: 외환차익 | Q84: 697.64 | R84: 619.5 | S84: 62.69 | T84: 1391.84 | U84: 2771.67 | V84: 294.04 | W84: 176 | X84: 50.1 | Y84: 502.38 | Z84: 1022.52 | AB84: 507.94
A85: 1 | C85: 외환차손 | Q85: 10.47 | R85: 6.94 | S85: 103.68 | T85: 290.21 | U85: 411.3 | V85: 43.62 | W85: 162.47 | X85: 409.97 | Y85: 338.99 | Z85: 955.05 | AB85: 16.19
A86: 1 | C86: 외화환산이익 | Q86: 208.61 | R86: -173.75 | S86: 13.84 | T86: 178.28 | U86: 226.98 | V86: 1420.51 | W86: -550.57 | X86: 1503.87 | Y86: -15.1 | Z86: 2358.71 | AB86: 1238.84
A87: 1 | C87: 외화환산손실 | Q87: 18.8 | R87: 682.48 | S87: 676.2 | T87: 284.9 | U87: 1662.38 | V87: 13.31 | W87: 650.62 | X87: -646.31 | Y87: 10.82 | Z87: 28.44 | AB87: 14.61
A88: 1 | C88: 이자손익 | Q88: -2403.68 | R88: -2604.63 | S88: -1925.85 | T88: -2144.88 | U88: -9079.04 | V88: -2310.59 | W88: -1407.96 | X88: -2134.29 | Y88: -589.02 | Z88: -6441.86 | AB88: -1508.11
A89: 1 | C89: 배당금수익 | S89: 0 | T89: 0 | X89: 10.64 | Y89: 24.85 | AB89: 340.68
A90: 1 | C90: 영업활동으로인한현금흐름 | E90: -11105 | G90: -20116.62 | H90: 7511.35 | I90: 4975.25 | J90: 27161.72 | K90: 19531.7 | L90: -10890.66 | M90: 43778.46 | N90: 12798.55 | O90: 23379.42 | P90: 69065.77 | Q90: 13245.72 | R90: 6881.57 | S90: 2183.77 | T90: 9340.12 | U90: 31651.18 | V90: -711.8 | W90: 32230.31 | X90: 26686.46 | Y90: -647.34 | Z90: 57557.63 | AA90: 26339.65 | AB90: 15768.09
A91: 1 | C91: 법인세납부(CF) | E91: -109.44 | G91: -5594.55 | H91: -6715.09 | I91: -245.73 | J91: -30.65 | K91: -12586.02 | L91: -321.14 | M91: 295.05 | N91: -1009.87 | O91: -126.01 | P91: -1161.97 | Q91: -4239.15 | R91: -4477.44 | S91: -3440.63 | T91: -262.34 | U91: -12419.56 | V91: -3859.35 | W91: -3818.88 | X91: -1758.81 | Y91: -3544.68 | Z91: -12981.72 | AA91: -3576.28 | AB91: -4050.64
A92: 1 | C92: 투자활동으로인한현금흐름 | E92: -2757.98 | G92: -17566.38 | H92: -24412.36 | I92: 10213.53 | J92: -3443.48 | K92: -35208.69 | L92: -5697.75 | M92: -4816.71 | N92: -25873.48 | O92: -2913.21 | P92: -39301.15 | Q92: -4372 | R92: -15812.72 | S92: -5703.87 | T92: -14101.75 | U92: -39990.34 | V92: -2729.58 | W92: -6725.99 | X92: -19659.87 | Y92: -15083.38 | Z92: -44198.82 | AA92: -8734.1 | AB92: -26709.34
A93: 1 | C93: 유형자산의감소 | E93: 600 | G93: 689.24 | I93: 0 | J93: 6.64 | L93: 2343.53 | M93: 0 | N93: 0 | O93: 0 | P93: 2343.53 | Q93: 0 | R93: 0 | S93: 3.85 | T93: 4.78 | U93: 8.63 | X93: 0 | Y93: 0 | AA93: 71.92
A94: 1 | C94: 유형자산의증가 | E94: 3358.98 | G94: 20235.93 | H94: 4364.11 | I94: 7451.05 | J94: 3313.77 | K94: 35364.86 | L94: 1587.33 | M94: 3576.4 | N94: 37664.9 | O94: 309.29 | P94: 43137.92 | Q94: 3303.81 | R94: 2728.52 | S94: 4862.79 | T94: 9277.13 | U94: 20172.25 | V94: 2809.12 | W94: 1146.07 | X94: 1912.09 | Y94: 3630.81 | Z94: 9498.09 | AA94: 2342.4 | AB94: 6416.85
A95: 1 | C95: CAPEX | E95: 3408.48 | G95: 20235.93 | H95: 4369.61 | I95: 7863.9 | J95: 3342.52 | K95: 35811.96 | L95: 1587.33 | M95: 3970.4 | N95: 37681.98 | O95: 309.29 | P95: 43549 | Q95: 3303.81 | R95: 2828.52 | S95: 4869.39 | T95: 9277.13 | U95: 20278.85 | V95: 2809.12 | W95: 1146.07 | X95: 1912.09 | Y95: 3630.81 | Z95: 9498.09 | AA95: 2342.96 | AB95: 6416.85
A96: 1 | C96: 무형자산의증가 | E96: 49.5 | I96: 412.85 | J96: 28.75 | N96: 17.08 | O96: 0 | S96: 6.6 | T96: 0 | X96: 0 | AA96: 0.56 | AB96: 0
A97: 1 | C97: 재무활동으로인한현금흐름 | E97: 19600.66 | G97: 40002.33 | H97: -10465.85 | I97: 2314.28 | J97: -4511.02 | K97: 27339.74 | L97: -867.58 | M97: -31584.75 | N97: 16609.06 | O97: -10151.79 | P97: -25995.06 | Q97: 9557.9 | R97: -13923.18 | S97: 37748.96 | T97: 3914.34 | U97: 37298.02 | V97: -1631.27 | W97: -11272.32 | X97: 1271.83 | Y97: -25397.76 | Z97: -37029.52 | AA97: -1279.02 | AB97: -14879.09
A98: 1 | C98: 단기차입금의증가 | E98: 345 | G98: 53975.2 | H98: 16880 | I98: 26394.06 | J98: 24204 | K98: 121453.26 | L98: 450 | M98: 57120 | N98: 37120 | O98: 5660 | P98: 100350 | Q98: 50520 | R98: 43540 | S98: 66880 | T98: 330 | U98: 161270 | V98: 71577.01 | W98: 2072.99 | X98: 51230 | Y98: 1245 | Z98: 126125 | AA98: 45390 | AB98: 29610
A99: 1 | C99: 장기차입금의증가 | E99: 20639 | G99: 38500 | H99: 10000 | I99: 0 | J99: 28000 | K99: 76500 | L99: 0 | M99: 80 | N99: 39920 | O99: 100 | P99: 40100 | Q99: 8000 | R99: 0 | S99: 37455 | T99: 14145 | U99: 59600 | V99: 180 | W99: 105 | X99: 108180 | Y99: 20 | Z99: 108485 | AA99: 2010
A100: 1 | C100: 단기차입금의감소 | E100: 0 | G100: 35905.2 | H100: 17550 | I100: 21501.06 | J100: 27901 | K100: 102857.26 | L100: 0 | M100: 33700 | N100: 20390 | O100: 0 | P100: 54090 | Q100: 18000 | R100: 45000 | S100: 45200 | T100: 1100 | U100: 109300 | V100: 71700.33 | X100: 116200 | Y100: 24985 | AA100: 47000 | AB100: 30000
A101: 1 | C101: 유동성장기부채의감소 | E101: 828.14 | G101: 16129.05 | H101: 11086.22 | I101: 2100 | J101: 15600.35 | K101: 44915.62 | L101: 600 | M101: 32200 | N101: 26812 | O101: 15600 | P101: 75212 | Q101: 40600 | R101: 600 | S101: 15600 | T101: 2496.04 | U101: 59296.04 | V101: 1350 | W101: 1350 | X101: 41350 | Y101: 1050 | Z101: 45100 | AA101: 1050 | AB101: 1050
A102: 1 | C102: 리스부채의상환 | E102: 520.01 | G102: 538.26 | H102: 486.52 | I102: 478.72 | J102: 174.02 | K102: 1677.52 | L102: 177.58 | M102: 190.08 | N102: 228.95 | O102: 311.78 | P102: 908.39 | Q102: 313.27 | R102: 320.97 | S102: 317 | T102: 319.13 | U102: 1270.37 | V102: 337.95 | W102: 915.74 | X102: 588.18 | Y102: 627.76 | Z102: 2469.63 | AA102: 629.02 | AB102: 637.96
A103: 1 | C103: 장기차입금의감소 | E103: 0 | G103: 0.36 | H103: 0 | I103: 0 | J103: 12999.64 | K103: 13000 | L103: 0 | M103: 0 | N103: 13000 | O103: 0 | P103: 13000 | Q103: 208.41 | R103: 562.65 | S103: 5187.42 | T103: 6645.48 | U103: 12603.96 | V103: 0 | W103: 0 | X103: 0
A104: 1 | C104: 배당금지급 | E104: 0 | G104: 0 | H104: 8223.12 | I104: 0 | J104: 0 | K104: 8223.12 | N104: 0 | O104: 0 | S104: 0 | T104: 0 | X104: 0 | Y104: 0
A105: 1 | C105: 자기주식의취득 | E105: 0 | G105: 0 | J105: 0
A106: 1 | C106: 현금및현금성자산의증감 | E106: 5662.39 | G106: 2720.95 | H106: -27623.26 | I106: 18377.33 | J106: 15993.43 | K106: 9468.45 | L106: -17003.88 | M106: 7033.05 | N106: 3879.46 | O106: 9752.02 | P106: 3660.65 | Q106: 19094.45 | R106: -23560.38 | S106: 33662.45 | T106: -405.76 | U106: 28790.76 | V106: -4952.72 | W106: 14969.52 | X106: 8382.81 | Y106: -42888.22 | Z106: -24488.61 | AA106: 14494.38 | AB106: -26079.27
A107: 1 | C107: 기말현금및현금성자산 | E107: 5662.38 | G107: 40389.7 | H107: -27623.26 | I107: 18377.33 | J107: 15993.42 | K107: 47137.19 | L107: 30087.12 | M107: 7033.05 | N107: 3448.19 | O107: 10183.3 | P107: 50751.66 | Q107: 69793.88 | R107: -23508.15 | S107: 33662.44 | T107: -405.75 | U107: 79542.42 | V107: 74589.69 | W107: 14969.53 | X107: 8382.81 | Y107: -42888.23 | Z107: 55053.8 | AA107: 69548.18 | AB107: -26079.27
A108: 1 | C108: 배당금수취(CF) | I108: 31.36 | J108: 0 | L108: 0 | M108: 96.4 | N108: 0 | O108: 0 | P108: 96.4 | S108: 0 | T108: 0
A109: 1 | C109: 이자수취(CF) | O109: 188.75 | Q109: 493.48 | R109: 431.27 | S109: 866.21 | T109: 587.95 | U109: 2378.91 | V109: 621.75 | W109: 301.18 | X109: 561.72 | Y109: 1749.29 | Z109: 3233.94 | AA109: 1701.06 | AB109: 109.26
A110: 1 | C110: 이자지급(CF) | V110: -3362.94 | W110: -2665.68 | X110: -102.44 | Y110: -2674.74 | Z110: -8805.8 | AA110: -2347.47 | AB110: -2365.97

Sheet BS별도
B1: (백만원) | C1: 이름: BS별도H | E1: 4Q21 | F1: 2021 | G1: 1Q22 | H1: 2Q22 | I1: 3Q22 | J1: 4Q22 | K1: 2022 | L1: 1Q23 | M1: 2Q23 | N1: 3Q23 | O1: 4Q23 | P1: 2023 | Q1: 1Q24 | R1: 2Q24 | S1: 3Q24 | T1: 4Q24 | U1: 2024 | V1: 1Q25 | W1: 2Q25 | X1: 3Q25 | Y1: 4Q25 | Z1: 2025 | AA1: 1Q26 | AB1: 2Q26 | AC1: 3Q26 | AD1: 4Q26 | AE1: 2026 | AF1: 1Q27 | AG1: 2Q27 | AH1: 3Q27 | AI1: 4Q27 | AJ1: 2027 | AK1: 1Q28 | AL1: 2Q28 | AM1: 3Q28 | AN1: 4Q28 | AO1: 2028
B2: 별도 | D2: fin json(kship_fin.py)
B3: 세진중공업(별) | C3: UPDATE: 26-10-14 | E3: 1 | F3: 2 | G3: 3 | H3: 4 | I3: 5 | J3: 6 | K3: 7 | L3: 8 | M3: 9 | N3: 10 | O3: 11 | P3: 12 | Q3: 13 | R3: 14 | S3: 15 | T3: 16 | U3: 17 | V3: 18 | W3: 19 | X3: 20 | Y3: 21 | Z3: 22 | AA3: 23 | AB3: 24 | AC3: 25 | AD3: 26 | AE3: 27 | AF3: 28 | AG3: 29 | AH3: 30 | AI3: 31 | AJ3: 32 | AK3: 33 | AL3: 34 | AM3: 35 | AN3: 36 | AO3: 37
B4: Account Code | C4: AccountNAME | E4: 2021.12 | F4: 2021.12A | G4: 2022.03 | H4: 2022.06 | I4: 2022.09 | J4: 2022.12 | K4: 2022.12A | L4: 2023.03 | M4: 2023.06 | N4: 2023.09 | O4: 2023.12 | P4: 2023.12A | Q4: 2024.03 | R4: 2024.06 | S4: 2024.09 | T4: 2024.12 | U4: 2024.12A | V4: 2025.03 | W4: 2025.06 | X4: 2025.09 | Y4: 2025.12 | Z4: 2025.12A | AA4: 2026.03 | AB4: 2026.06 | AC4: 2026.09 | AD4: 2026.12 | AE4: 2026.12A | AF4: 2027.03 | AG4: 2027.06 | AH4: 2027.09 | AI4: 2027.12 | AJ4: 2027.12A | AK4: 2028.03 | AL4: 2028.06 | AM4: 2028.09 | AN4: 2028.12 | AO4: 2028.12A
A5: 1 | C5: 유동자산 | E5: 165200.01 | F5: 165200.01 | G5: 143519.33 | H5: 114213.28 | I5: 127566.01 | J5: 123243.37 | K5: 123243.37 | L5: 119879.41 | M5: 101631.4 | N5: 97334.66 | O5: 97441.87 | P5: 97441.87 | Q5: 130312.84 | R5: 97267.01 | S5: 125377.62 | T5: 142029.44 | U5: 142029.44 | V5: 144931.6 | W5: 119425.03 | X5: 123221.59 | Y5: 108478.1 | Z5: 108478.1 | AA5: 113722.91 | AB5: 109350.3
A6: 1 | C6: 현금및현금성자산 | E6: 26602.1 | F6: 26602.1 | G6: 29348.29 | H6: 8217.24 | I6: 24468.91 | J6: 40107.62 | K6: 40107.62 | L6: 18265.36 | M6: 22638.06 | N6: 22665.16 | O6: 32509.25 | P6: 32509.25 | Q6: 46702.99 | R6: 21139.37 | S6: 52544.38 | T6: 44858.86 | U6: 44858.86 | V6: 43021.8 | W6: 57089.02 | X6: 67680.92 | Y6: 23475.75 | Z6: 23475.75 | AA6: 39558.69 | AB6: 16154.31
A7: 1 | C7: 단기금융상품 | E7: 10 | F7: 10 | G7: 10 | H7: 10 | I7: 10 | J7: 10 | K7: 10 | L7: 10 | M7: 10 | N7: 10 | O7: 10 | P7: 10 | Q7: 10 | R7: 10 | S7: 10 | T7: 10 | U7: 10 | V7: 10 | W7: 4067.84 | X7: 8947.75 | Y7: 14454.86 | Z7: 14454.86 | AA7: 17670.96 | AB7: 31566.23
A8: 1 | C8: 단기금융자산 | E8: 10 | F8: 10 | G8: 10 | H8: 10 | I8: 10 | J8: 10 | K8: 10 | L8: 10 | M8: 10 | N8: 10 | O8: 10 | P8: 10 | Q8: 10 | R8: 10 | S8: 10 | T8: 10 | U8: 10 | V8: 10 | W8: 4067.84 | X8: 8947.75 | Y8: 14454.86 | Z8: 14454.86 | AA8: 17670.96 | AB8: 31566.23
A9: 1 | C9: 매출채권및기타채권 | E9: 24150.25 | F9: 24150.25 | G9: 47455.32 | H9: 35159.73 | I9: 24935.83 | J9: 17706.17 | K9: 17706.17 | L9: 31711.15 | M9: 32123.94 | N9: 23950.16 | O9: 26540.42 | P9: 26540.42 | Q9: 45175.78 | R9: 34965.76 | S9: 24869.66 | T9: 52505.62 | U9: 52505.62 | V9: 62720.19 | W9: 17846.37 | X9: 8145.31 | Y9: 32049.42 | Z9: 32049.42 | AA9: 18662.66 | AB9: 20989.68
A10: 1 | C10: 기타유동자산 | E10: 9742.53 | F10: 9742.53 | G10: 6138.62 | H10: 3880.19 | I10: 5178.13 | J10: 4672.22 | K10: 4672.22 | L10: 5129.36 | M10: 2434.47 | N10: 4756.07 | O10: 5047.11 | P10: 5047.11 | Q10: 4613.39 | R10: 6412.04 | S10: 11651.69 | T10: 10885.88 | U10: 10885.88 | V10: 10215.86 | W10: 7806.12 | X10: 6725.38 | Y10: 10790.66 | Z10: 10790.66 | AA10: 10429 | AB10: 12746.58
A11: 1 | C11: 재고자산 | E11: 104695.13 | F11: 104695.13 | G11: 60567.09 | H11: 63206.48 | I11: 69233.49 | J11: 60747.36 | K11: 60747.36 | L11: 64318.85 | M11: 44424.92 | N11: 45953.28 | O11: 33335.09 | P11: 33335.09 | Q11: 33810.68 | R11: 34739.84 | S11: 36301.89 | T11: 28783.7 | U11: 28783.7 | V11: 28963.75 | W11: 28736.95 | X11: 31722.23 | Y11: 27707.41 | Z11: 27707.41 | AA11: 27401.61 | AB11: 27893.49
A12: 1 | C12: 매각예정비유동자산및처분자산 | E12: 0 | F12: 0
A13: 1 | C13: 비유동자산 | E13: 279197.55 | F13: 279197.55 | G13: 283040.06 | H13: 298506.75 | I13: 285727.23 | J13: 288633.38 | K13: 288633.38 | L13: 293088.27 | M13: 294520.11 | N13: 325926.65 | O13: 326818.92 | P13: 326818.92 | Q13: 328653.83 | R13: 336861.54 | S13: 341425.68 | T13: 347650.38 | U13: 347650.38 | V13: 354074.84 | W13: 375608.53 | X13: 383424.16 | Y13: 383298.96 | Z13: 383298.96 | AA13: 386049.89 | AB13: 391199.53
A14: 1 | C14: 장기매출채권및기타채권 | E14: 7797.71 | F14: 7797.71 | G14: 7858.32 | H14: 7981.53 | I14: 8293.88 | J14: 11678.56 | K14: 11678.56 | L14: 12271.04 | M14: 12190.47 | N14: 12598.64 | O14: 12335.07 | P14: 12335.07 | Q14: 12677.42 | R14: 12536.59 | S14: 12638.61 | T14: 10871.28 | U14: 10871.28 | V14: 10981.25 | W14: 33468.62 | X14: 36358.4 | Y14: 41376.38 | Z14: 41376.38 | AA14: 43021.13 | AB14: 44167.59
A15: 1 | C15: 장기금융자산 | E15: 49317.93 | F15: 49317.93 | G15: 1192.27 | H15: 18784.44 | I15: 1282.27 | J15: 1107.71 | K15: 1107.71 | L15: 6152.71 | M15: 6197.71 | N15: 6242.71 | O15: 6287.71 | P15: 6287.71 | Q15: 6332.71 | R15: 12922.74 | S15: 12506.83 | T15: 12699.37 | U15: 12699.37 | V15: 13933.59 | W15: 14635.64 | X15: 21571.9 | Y15: 22279.97 | Z15: 22279.97 | AA15: 23325.74 | AB15: 26217.39
A16: 1 | C16: 투자자산 | E16: 50465.2 | F16: 50465.2 | G16: 50550.2 | H16: 68142.37 | I16: 50640.2 | J16: 50465.64 | K16: 50465.64 | L16: 55510.64 | M16: 55555.64 | N16: 51874.14 | O16: 51919.14 | P16: 51919.14 | Q16: 51964.14 | R16: 58554.17 | S16: 58138.26 | T16: 58330.8 | U16: 58330.8 | V16: 59565.02 | W16: 60267.07 | X16: 67203.33 | Y16: 61979.47 | Z16: 61979.47 | AA16: 63025.24 | AB16: 64660.74
A17: 1 | C17: 종속기업및관계기업투자 | E17: 1147.27 | F17: 1147.27 | G17: 49357.93 | H17: 49357.93 | I17: 49357.93 | J17: 49357.93 | K17: 49357.93 | L17: 49357.93 | M17: 49357.93 | N17: 45631.43 | O17: 45631.43 | P17: 45631.43 | Q17: 45631.43 | R17: 45631.43 | S17: 45631.43 | T17: 45631.43 | U17: 45631.43 | V17: 45631.43 | W17: 45631.43 | X17: 45631.43 | Y17: 39699.5 | Z17: 39699.5 | AA17: 39699.5 | AB17: 38443.35
A18: 1 | C18: 유형자산 | E18: 203035.14 | F18: 203035.14 | G18: 205002.55 | H18: 205894.73 | I18: 210957.89 | J18: 211082.54 | K18: 211082.54 | L18: 211900.86 | M18: 213976.47 | N18: 248520.66 | O18: 247342.19 | P18: 247342.19 | Q18: 249085.24 | R18: 250318.7 | S18: 253422.93 | T18: 261508.52 | U18: 261508.52 | V18: 261083.92 | W18: 260216.65 | X18: 259634.69 | Y18: 260543.87 | Z18: 260543.87 | AA18: 260879.02 | AB18: 265078.54
A19: 1 | C19: 사용권자산 | E19: 4144.21 | F19: 4144.21 | G19: 3978.54 | H19: 4300.74 | I19: 4135.61 | J19: 3970.48 | K19: 3970.48 | L19: 3813.35 | M19: 3972.75 | N19: 4125.06 | O19: 3984.47 | P19: 3984.47 | Q19: 3696.54 | R19: 3397.48 | S19: 3101.02 | T19: 2804.56 | U19: 2804.56 | V19: 9341.51 | W19: 8705.27 | X19: 8103.13 | Y19: 7987.87 | Z19: 7987.87 | AA19: 7340.47 | AB19: 6697.25
A20: 1 | C20: 기타비유동자산 | E20: 4144.21 | F20: 4144.21 | G20: 3978.54 | H20: 4300.74 | I20: 4135.61 | J20: 3970.48 | K20: 3970.48 | L20: 3813.35 | M20: 3972.75 | N20: 4125.06 | O20: 3984.47 | P20: 3984.47 | Q20: 3696.54 | R20: 3397.48 | S20: 3101.02 | T20: 2804.56 | U20: 2804.56 | V20: 9341.51 | W20: 8705.27 | X20: 8103.13 | Y20: 7987.87 | Z20: 7987.87 | AA20: 7340.47 | AB20: 6697.25
A21: 1 | C21: 무형자산 | E21: 4418.66 | F21: 4418.66 | G21: 4418.66 | H21: 4418.66 | I21: 4831.51 | J21: 4831.51 | K21: 4831.51 | L21: 4831.51 | M21: 5225.51 | N21: 5234.17 | O21: 5234.17 | P21: 5234.17 | Q21: 5234.17 | R21: 5334.17 | S21: 5334.17 | T21: 5334.17 | U21: 5334.17 | V21: 5334.17 | W21: 5334.17 | X21: 5334.17 | Y21: 5334.17 | Z21: 5334.17 | AA21: 5334.17 | AB21: 5334.17
A22: 1 | C22: 투자부동산 | E22: 3585.67 | F22: 3585.67 | G22: 3560.34 | H22: 3534.88 | I22: 3509.78 | J22: 3484.69 | K22: 3484.69 | L22: 0 | N22: 0 | O22: 0 | P22: 0 | T22: 0 | U22: 0
A23: 1 | C23: 이연법인세자산 | E23: 5750.95 | F23: 5750.95 | G23: 7671.46 | H23: 4233.84 | I23: 3358.35 | J23: 3119.97 | K23: 3119.97 | L23: 4760.87 | M23: 3599.28 | N23: 3573.97 | O23: 6003.87 | P23: 6003.87 | Q23: 5996.32 | R23: 6720.43 | S23: 8790.68 | T23: 8801.04 | U23: 8801.04 | V23: 7768.97 | W23: 7616.74 | X23: 6790.43 | Y23: 6077.2 | Z23: 6077.2 | AA23: 6449.86 | AB23: 5261.24
A24: 1 | C24: 자산총계 | E24: 444397.56 | F24: 444397.56 | G24: 426559.39 | H24: 412720.03 | I24: 413293.23 | J24: 411876.75 | K24: 411876.75 | L24: 412967.68 | M24: 396151.51 | N24: 423261.31 | O24: 424260.79 | P24: 424260.79 | Q24: 458966.67 | R24: 434128.55 | S24: 466803.3 | T24: 489679.81 | U24: 489679.81 | V24: 499006.44 | W24: 495033.56 | X24: 506645.75 | Y24: 491777.06 | Z24: 491777.06 | AA24: 499772.8 | AB24: 500549.83
A25: 1 | C25: 유동부채 | E25: 171104.83 | F25: 171104.83 | G25: 138660.43 | H25: 149224.55 | I25: 186457.53 | J25: 168279.92 | K25: 168279.92 | L25: 227336.4 | M25: 207674.24 | N25: 205888.89 | O25: 191700.36 | P25: 191700.36 | Q25: 226620.81 | R25: 197790.18 | S25: 249548.4 | T25: 256664.27 | U25: 256664.27 | V25: 259998.17 | W25: 252224.9 | X25: 178473.16 | Y25: 145261 | Z25: 145261 | AA25: 155225.17 | AB25: 142309.05
A26: 1 | C26: 매입채무및기타채무 | E26: 48565.05 | F26: 48565.05 | G26: 49610.72 | H26: 37393.52 | I26: 32826.86 | J26: 25301.53 | K26: 25301.53 | L26: 44407.8 | M26: 40264.41 | N26: 48672.64 | O26: 42860.32 | P26: 42860.32 | Q26: 71650.34 | R26: 49498.56 | S26: 48511.29 | T26: 54393.99 | U26: 54393.99 | V26: 63079.63 | W26: 56293.11 | X26: 51400.72 | Y26: 50711.29 | Z26: 50711.29 | AA26: 66329.76 | AB26: 51702.87
A27: 1 | C27: 계약부채 | E27: 37018.85 | F27: 37018.85 | G27: 14719.34 | H27: 10109.8 | I27: 10745.11 | J27: 16037.88 | K27: 16037.88 | L27: 11514.37 | M27: 4555 | N27: 4500 | O27: 2702.96 | P27: 2702.96 | Q27: 12149.88 | R27: 13059.89 | S27: 15489.42 | T27: 13291.26 | U27: 13291.26 | V27: 5643.76 | W27: 5175 | X27: 17894.37 | Y27: 5175 | Z27: 5175 | AA27: 725.22 | AB27: 4286.67
A28: 1 | C28: 당기법인세부채(미지급법인세) | E28: 11763.79 | F28: 11763.79 | G28: 6380.03 | H28: 0 | I28: 0 | J28: 447.34 | K28: 447.34 | L28: 225.74 | M28: 3333.31 | N28: 3059.1 | O28: 9137.34 | P28: 9137.34 | Q28: 5640.93 | R28: 3441.3 | S28: 1291.13 | T28: 5325.3 | U28: 5325.3 | V28: 5853.3 | W28: 5458.02 | X28: 2154.45 | Y28: 7833.21 | Z28: 7833.21 | AA28: 8319.27 | AB28: 7682.01
A29: 1 | C29: 단기차입금 | E29: 69700 | F29: 69700 | G29: 64300 | H29: 96900 | I29: 138013 | J29: 121600 | K29: 121600 | L29: 166000 | M29: 153600 | N29: 143600 | O29: 133600 | P29: 133600 | Q29: 133600 | R29: 128600 | S29: 181600 | T29: 181300 | U29: 181300 | V29: 181000 | W29: 180700 | X29: 101400 | Y29: 76170 | Z29: 76170 | AA29: 75120 | AB29: 74070
A30: 1 | C30: 단기금융부채(face) | E30: 69700 | F30: 69700 | G30: 64300 | H30: 96900 | I30: 138013 | J30: 121600 | K30: 121600 | L30: 166000 | M30: 153600 | N30: 143600 | O30: 133600 | P30: 133600 | Q30: 133600 | R30: 128600 | S30: 181600 | T30: 181300 | U30: 181300 | V30: 181000 | W30: 180700 | X30: 101400 | Y30: 76170 | Z30: 76170 | AA30: 75120 | AB30: 74070
A31: 1 | C31: 유동리스부채 | E31: 1362.34 | F31: 1362.34 | G31: 987.6 | H31: 826.17 | I31: 724.01 | J31: 726.65 | K31: 726.65 | L31: 725.99 | M31: 871.39 | N31: 1174.68 | O31: 1242.64 | P31: 1242.64 | Q31: 1534.48 | R31: 1284.08 | S31: 1009.46 | T31: 711.87 | U31: 711.87 | V31: 2934.66 | W31: 2751.07 | X31: 2593.56 | Y31: 2691.68 | Z31: 2691.68 | AA31: 2674.43 | AB31: 2659.6
A32: 1 | C32: 리스부채 | E32: 4028.67 | F32: 4028.67 | G32: 3543.78 | H32: 3537.8 | I32: 3256.92 | J32: 3079.68 | K32: 3079.68 | L32: 2914.71 | M32: 3020.66 | N32: 3191.44 | O32: 3043.05 | P32: 3043.05 | Q32: 2750.35 | R32: 2439.74 | S32: 2129.59 | T32: 1816.76 | U32: 1816.76 | V32: 8381.99 | W32: 7771.79 | X32: 7187.38 | Y32: 7024.33 | Z32: 7024.33 | AA32: 6396.24 | AB32: 5767.33
A33: 1 | C33: 단기금융부채 | E33: 2006.74 | F33: 2006.74 | G33: 987.6 | H33: 826.17 | I33: 724.01 | J33: 726.65 | K33: 726.65 | L33: 725.99 | M33: 871.39 | N33: 1174.68 | O33: 1242.64 | P33: 1242.64 | Q33: 1534.48 | R33: 1284.08 | S33: 1009.46 | T33: 711.87 | U33: 711.87 | V33: 2934.66 | W33: 2751.07 | X33: 2593.56 | Y33: 2691.68 | Z33: 2691.68 | AA33: 2674.43 | AB33: 2659.6
A34: 1 | C34: 기타유동금융부채 | E34: 644.4 | F34: 644.4
A35: 1 | C35: 단기충당부채 | E35: 2050.39 | F35: 2050.39 | G35: 2256.2 | H35: 3073.46 | I35: 3081.32 | J35: 3079.97 | K35: 3079.97 | L35: 3250.86 | M35: 4033.88 | N35: 4206.11 | O35: 1759.64 | P35: 1759.64 | Q35: 1686.62 | R35: 1722.25 | S35: 1605.85 | T35: 1487.93 | U35: 1487.93 | V35: 1378.65 | W35: 1774.4 | X35: 1746.35 | Y35: 1679.11 | Z35: 1679.11 | AA35: 1422.41 | AB35: 1523.62
A36: 1 | C36: 비유동부채 | E36: 113033.85 | F36: 113033.85 | G36: 142541.09 | H36: 106995.49 | I36: 67442.92 | J36: 78086.1 | K36: 78086.1 | L36: 33933.63 | M36: 22873.12 | N36: 49205.17 | O36: 50498.85 | P36: 50498.85 | Q36: 49434.08 | R36: 49425.45 | S36: 33628.48 | T36: 35953.35 | U36: 35953.35 | V36: 40109.34 | W36: 38908.18 | X36: 116496 | Y36: 116031.72 | Z36: 116031.72 | AA36: 116018.9 | AB36: 115760.62
A37: 1 | C37: 장기차입금 | E37: 107300 | F37: 107300 | G37: 136700 | H37: 101100 | J37: 73700 | K37: 73700 | L37: 28700 | M37: 17500 | N37: 43900 | O37: 43300 | P37: 43300 | Q37: 42700 | R37: 42100 | S37: 25900 | T37: 30650 | U37: 30650 | V37: 29600 | W37: 28550 | X37: 106500 | Y37: 106200 | Z37: 106200 | AA37: 106200 | AB37: 106200
A38: 1 | C38: 장기금융부채(face) | E38: 107300 | F38: 107300 | G38: 136700 | H38: 101100 | J38: 73700 | K38: 73700 | L38: 28700 | M38: 17500 | N38: 43900 | O38: 43300 | P38: 43300 | Q38: 42700 | R38: 42100 | S38: 25900 | T38: 30650 | U38: 30650 | V38: 29600 | W38: 28550 | X38: 106500 | Y38: 106200 | Z38: 106200 | AA38: 106200 | AB38: 106200
A39: 1 | C39: 비유동리스부채 | E39: 2666.33 | F39: 2666.33 | G39: 2556.18 | H39: 2711.63 | I39: 2532.91 | J39: 2353.03 | K39: 2353.03 | L39: 2188.72 | M39: 2149.27 | N39: 2016.76 | O39: 1800.41 | P39: 1800.41 | Q39: 1215.87 | R39: 1155.66 | S39: 1120.13 | T39: 1104.89 | U39: 1104.89 | V39: 5447.33 | W39: 5020.72 | X39: 4593.82 | Y39: 4332.65 | Z39: 4332.65 | AA39: 3721.81 | AB39: 3107.73
A40: 1 | C40: 장기금융부채 | E40: 2666.33 | F40: 2666.33 | G40: 2556.18 | H40: 2711.63 | I40: 2532.91 | J40: 2353.03 | K40: 2353.03 | L40: 2188.72 | M40: 2149.27 | N40: 2016.76 | O40: 1800.41 | P40: 1800.41 | Q40: 1215.87 | R40: 1155.66 | S40: 1120.13 | T40: 1104.89 | U40: 1104.89 | V40: 5447.33 | W40: 5020.72 | X40: 4593.82 | Y40: 4332.65 | Z40: 4332.65 | AA40: 3721.81 | AB40: 3107.73
A41: 1 | C41: 기타비유동부채 | E41: 576.55 | F41: 576.55 | G41: 541.68 | H41: 472.69 | I41: 423.04 | J41: 306.58 | K41: 306.58 | L41: 300.9 | M41: 295.36 | N41: 294.05 | O41: 253.15 | P41: 253.15 | Q41: 249.44 | R41: 336.21 | S41: 347.1 | T41: 470.38 | U41: 470.38 | V41: 489.33 | W41: 490.52 | X41: 499.5 | Y41: 393.95 | Z41: 393.95 | AA41: 381.05 | AB41: 378.11
A42: 1 | C42: 확정급여부채 | E42: 2490.97 | F42: 2490.97 | G42: 2743.24 | H42: 2711.17 | I42: 3186.96 | J42: 1726.49 | K42: 1726.49 | L42: 2744 | M42: 2928.49 | N42: 2994.37 | O42: 5145.29 | P42: 5145.29 | Q42: 5268.77 | R42: 5833.58 | S42: 6261.26 | T42: 3728.08 | U42: 3728.08 | V42: 4572.68 | W42: 4846.95 | X42: 4902.68 | Y42: 5105.12 | Z42: 5105.12 | AA42: 5716.04 | AB42: 6074.78
A43: 1 | C43: 부채총계 | E43: 284138.67 | F43: 284138.67 | G43: 281201.52 | H43: 256220.04 | I43: 253900.45 | J43: 246366.02 | K43: 246366.02 | L43: 261270.02 | M43: 230547.37 | N43: 255094.06 | O43: 242199.22 | P43: 242199.22 | Q43: 276054.89 | R43: 247215.63 | S43: 283176.88 | T43: 292617.62 | U43: 292617.62 | V43: 300107.52 | W43: 291133.08 | X43: 294969.17 | Y43: 261292.72 | Z43: 261292.72 | AA43: 271244.07 | AB43: 258069.67
A44: 1 | C44: 자본금 | E44: 31224.73 | F44: 31224.73 | G44: 31224.73 | H44: 31224.73 | I44: 31224.73 | J44: 31224.73 | K44: 31224.73 | L44: 31224.73 | M44: 31224.73 | N44: 31224.73 | O44: 31224.73 | P44: 31224.73 | Q44: 31224.73 | R44: 31224.73 | S44: 31224.73 | T44: 31224.73 | U44: 31224.73 | V44: 31224.73 | W44: 31224.73 | X44: 31224.73 | Y44: 31224.73 | Z44: 31224.73 | AA44: 31224.73 | AB44: 31224.73
A45: 1 | C45: 자본잉여금 | E45: 369.53 | F45: 369.53 | G45: 552.77 | H45: 143.83 | I45: 143.83 | J45: 143.83 | K45: 143.83 | L45: 143.83 | M45: 143.83 | N45: 143.83 | O45: 143.83 | P45: 143.83 | Q45: 143.83 | R45: 143.83 | S45: 143.83 | T45: 143.83 | U45: 143.83 | V45: 143.83 | W45: 143.83 | X45: 143.83 | Y45: 1769.68 | Z45: 1769.68 | AA45: 1769.68 | AB45: 1769.68
A46: 1 | C46: 기타자본 | E46: -8011.63 | F46: -8011.63 | G46: -7707.55 | H46: -7298.61 | I46: -7298.61 | J46: -7298.61 | K46: -7298.61 | L46: -7298.61 | M46: -7298.61 | N46: -7298.61 | O46: -7298.61 | P46: -7298.61 | Q46: 1625.85 | R46: 1625.85 | S46: 1625.85 | T46: 1625.85 | U46: 1625.85 | V46: 1625.85 | W46: 1625.85 | X46: 1625.85
A47: 1 | C47: 기타포괄이익누계액 | E47: -33.42 | F47: -33.42 | G47: -33.42 | H47: -67.27 | I47: -33.42 | J47: -202.27 | K47: -202.27 | L47: -202.27 | M47: -202.27 | N47: -202.27 | O47: -202.27 | P47: -202.27 | Q47: -202.27 | R47: -326.02 | S47: -482.17 | T47: -1850.85 | U47: -1850.85 | V47: -1374.51 | W47: -1280.27 | X47: -412.31 | Y47: -1001.23 | Z47: -1001.23 | AA47: -1864.07 | AB47: -1635.96
A48: 1 | C48: 이익잉여금 | E48: 136709.68 | F48: 136709.68 | G48: 121321.35 | H48: 132497.31 | I48: 135356.26 | J48: 141643.04 | K48: 141643.04 | L48: 127829.98 | M48: 141736.46 | N48: 144299.56 | O48: 158193.89 | P48: 158193.89 | Q48: 150119.64 | R48: 154244.53 | S48: 151114.17 | T48: 165918.64 | U48: 165918.64 | V48: 167279.02 | W48: 172186.35 | X48: 179094.49 | Y48: 198491.16 | Z48: 198491.16 | AA48: 197398.39 | AB48: 211121.71
A49: 1 | C49: 자본총계 | E49: 160258.89 | F49: 160258.89 | G49: 145357.87 | H49: 156499.99 | I49: 159392.79 | J49: 165510.73 | K49: 165510.73 | L49: 151697.66 | M49: 165604.14 | N49: 168167.24 | O49: 182061.57 | P49: 182061.57 | Q49: 182911.78 | R49: 186912.92 | S49: 183626.41 | T49: 197062.19 | U49: 197062.19 | V49: 198898.92 | W49: 203900.48 | X49: 211676.58 | Y49: 230484.34 | Z49: 230484.34 | AA49: 228528.73 | AB49: 242480.15
A50: 1 | C50: 부채와자본총계 | E50: 444397.56 | F50: 444397.56 | G50: 426559.39 | H50: 412720.03 | I50: 413293.23 | J50: 411876.75 | K50: 411876.75 | L50: 412967.68 | M50: 396151.51 | N50: 423261.31 | O50: 424260.79 | P50: 424260.79 | Q50: 458966.67 | R50: 434128.55 | S50: 466803.3 | T50: 489679.81 | U50: 489679.81 | V50: 499006.44 | W50: 495033.56 | X50: 506645.75 | Y50: 491777.06 | Z50: 491777.06 | AA50: 499772.8 | AB50: 500549.83
A51: 1 | C51: 지배주주지분 | E51: 160258.89 | F51: 160258.89 | G51: 145357.87 | H51: 156499.99 | I51: 159392.79 | J51: 165510.73 | K51: 165510.73 | L51: 151697.66 | M51: 165604.14 | N51: 168167.24 | O51: 182061.57 | P51: 182061.57 | Q51: 182911.78 | R51: 186912.92 | S51: 183626.41 | T51: 197062.19 | U51: 197062.19 | V51: 198898.92 | W51: 203900.48 | X51: 211676.58 | Y51: 230484.34 | Z51: 230484.34 | AA51: 228528.73 | AB51: 242480.15
A52: 1 | C52: 총차입금 | E52: 177000 | F52: 177000 | G52: 201000 | H52: 198000 | I52: 138013 | J52: 195300 | K52: 195300 | L52: 194700 | M52: 171100 | N52: 187500 | O52: 176900 | P52: 176900 | Q52: 176300 | R52: 170700 | S52: 207500 | T52: 211950 | U52: 211950 | V52: 210600 | W52: 209250 | X52: 207900 | Y52: 182370 | Z52: 182370 | AA52: 181320 | AB52: 180270
A53: 1 | C53: 순차입금 | E53: 150387.9 | F53: 150387.9 | G53: 171641.71 | H53: 189772.76 | I53: 113534.09 | J53: 155182.38 | K53: 155182.38 | L53: 176424.64 | M53: 148451.94 | N53: 164824.84 | O53: 144380.75 | P53: 144380.75 | Q53: 129587.01 | R53: 149550.63 | S53: 154945.62 | T53: 167081.14 | U53: 167081.14 | V53: 167568.2 | W53: 148093.14 | X53: 131271.33 | Y53: 144439.39 | Z53: 144439.39 | AA53: 124090.35 | AB53: 132549.46
A54: 1 | C54: 이자발생자산 | E54: 75930.03 | F54: 75930.03 | G54: 30550.56 | H54: 27011.68 | I54: 25761.18 | J54: 41225.33 | K54: 41225.33 | L54: 24428.07 | M54: 28845.77 | N54: 28917.87 | O54: 38806.96 | P54: 38806.96 | Q54: 53045.7 | R54: 34072.11 | S54: 65061.21 | T54: 57568.23 | U54: 57568.23 | V54: 56965.39 | W54: 75792.5 | X54: 98200.57 | Y54: 60210.58 | Z54: 60210.58 | AA54: 80555.39 | AB54: 73937.93
A55: 1 | C55: 기타유동부채 | G55: 406.55 | H55: 921.61 | I55: 1067.23 | J55: 1086.56 | K55: 1086.56 | L55: 1211.63 | M55: 1016.25 | N55: 676.36 | O55: 397.47 | P55: 397.47 | Q55: 358.56 | R55: 184.11 | S55: 41.25 | T55: 153.91 | U55: 153.91 | V55: 108.17 | W55: 73.3 | X55: 1283.71 | Y55: 1000.71 | Z55: 1000.71 | AA55: 634.09 | AB55: 384.28
A56: 1 | C56: 계약자산 | H56: 3739.63 | I56: 3739.63 | L56: 444.7 | T56: 4985.38 | U56: 4985.38 | V56: 0 | W56: 3878.74 | X56: 0
A57: 1 | C57: 장기매입채무및기타채무 | I57: 61300
A58: 1 | C58: 매출액(수익) | E58: 64557.81 | G58: 128719.92 | H58: 80273.87 | I58: 68805.26 | J58: 85266.79 | K58: 363065.84 | L58: 60148.33 | M58: 110127.93 | N58: 75583.02 | O58: 101980.32 | P58: 347839.6 | Q58: 78440.09 | R58: 70848.27 | S58: 65466.35 | T58: 96902.03 | U58: 311656.74 | V58: 90047.77 | W58: 88154.49 | X58: 80589.05 | Y58: 107338.84 | Z58: 366130.15 | AA58: 78164.43 | AB58: 83367.47
A59: 1 | C59: 매출원가 | E59: 73165.18 | G59: 131290.28 | H59: 64379.4 | I59: 63132.01 | J59: 68208.09 | K59: 327009.78 | L59: 62569.39 | M59: 87367.14 | N59: 77529.18 | O59: 77164.84 | P59: 304630.55 | Q59: 70833.09 | R59: 60445.65 | S59: 64259.24 | T59: 73053.14 | U59: 268591.12 | V59: 68889.18 | W59: 75779.87 | X59: 68334.02 | Y59: 72436.69 | Z59: 285439.76 | AA59: 62848.29 | AB59: 64286.28
A60: 1 | C60: 매출총이익 | E60: -8607.38 | G60: -2570.36 | H60: 15894.47 | I60: 5673.25 | J60: 17058.7 | K60: 36056.06 | L60: -2421.06 | M60: 22760.79 | N60: -1946.16 | O60: 24815.48 | P60: 43209.05 | Q60: 7607.01 | R60: 10402.63 | S60: 1207.11 | T60: 23848.89 | U60: 43065.64 | V60: 21158.59 | W60: 12374.62 | X60: 12255.03 | Y60: 34902.14 | Z60: 80690.38 | AA60: 15316.14 | AB60: 19081.19
A61: 1 | C61: 판관비 | E61: 3602.63 | G61: 3876.34 | H61: 4326.19 | I61: 3241.07 | J61: 2356.98 | K61: 13800.58 | L61: 3120.14 | M61: 3840.27 | N61: 3876.97 | O61: 3891.74 | P61: 14729.12 | Q61: 3613.4 | R61: 3416.56 | S61: 3389.26 | T61: 3423.88 | U61: 13843.1 | V61: 4064.28 | W61: 4495.99 | X61: 3560.52 | Y61: 4778.43 | Z61: 16899.22 | AA61: 4677.16 | AB61: 4206.11
A62: 1 | C62: 영업이익 | E62: -12210.01 | G62: -6446.7 | H62: 11568.28 | I62: 2432.18 | J62: 14701.71 | K62: 22255.47 | L62: -5541.2 | M62: 18920.52 | N62: -5823.13 | O62: 20923.74 | P62: 28479.93 | Q62: 3993.61 | R62: 6986.06 | S62: -2182.16 | T62: 20425.01 | U62: 29222.52 | V62: 17094.31 | W62: 7878.63 | X62: 8694.5 | Y62: 30123.71 | Z62: 63791.15 | AA62: 10638.98 | AB62: 14875.09
A63: 1 | C63: 기타영업외손익 | E63: -127.43 | G63: -68.64 | H63: 37.94 | I63: 910.62 | J63: -2610.46 | K63: -1730.54 | L63: -179.93 | M63: 254.75 | N63: 10304.35 | O63: 1574.53 | P63: 11953.7 | Q63: -47.75 | R63: 206.24 | S63: 90.59 | T63: 109.99 | U63: 359.07 | V63: 195.81 | W63: 61.92 | X63: 57.59 | Y63: -5813.95 | Z63: -5498.63 | AA63: -37.85 | AB63: -1216.33
A64: 1 | C64: 기타영업외수익 | E64: 945.77 | G64: 56.01 | H64: 153.92 | I64: 979.62 | J64: -685.39 | K64: 504.16 | L64: 76.53 | M64: 248.25 | N64: 10340.31 | O64: 1570.96 | P64: 12236.05 | Q64: 317.14 | R64: 207.98 | S64: 93.92 | T64: 113.62 | U64: 732.66 | V64: 349.18 | W64: 167.04 | X64: 74.13 | Y64: 42.58 | Z64: 632.93 | AA64: 65.35 | AB64: 71.5
A65: 1 | C65: 기타영업외비용 | E65: 1073.19 | G65: 124.65 | H65: 115.98 | I65: 69 | J65: 1925.07 | K65: 2234.7 | L65: 256.46 | M65: -6.5 | N65: 35.97 | O65: -3.57 | P65: 282.36 | Q65: 364.89 | R65: 1.74 | S65: 3.32 | T65: 3.63 | U65: 373.58 | V65: 153.37 | W65: 105.12 | X65: 16.54 | Y65: 5856.53 | Z65: 6131.56 | AA65: 103.2 | AB65: 1287.83
A66: 1 | C66: 금융손익 | E66: -738.75 | G66: -2664.54 | H66: 2520.92 | I66: 473.39 | J66: -4760.78 | K66: -4431.01 | L66: -1008.06 | M66: -1725.58 | N66: -1620.24 | O66: -2262.35 | P66: -6616.23 | Q66: -1214.64 | R66: -1526.59 | S66: -1855.91 | T66: -1098.5 | U66: -5695.64 | V66: -502.12 | W66: -1293.68 | X66: 168.66 | Y66: 1284.68 | Z66: -342.46 | AA66: 5269.61 | AB66: 3973.19
A67: 1 | C67: 금융수익 | E67: 285.24 | G67: 880.65 | H67: 2015.26 | I67: 1793.78 | J67: 550.49 | K67: 5240.18 | L67: 1235.1 | M67: 487.59 | N67: 642.37 | O67: 292.93 | P67: 2657.99 | Q67: 1007.93 | R67: 916.45 | S67: 800.92 | T67: 1501.25 | U67: 4226.55 | V67: 1681.11 | W67: 1374.9 | X67: 1994.24 | Y67: 3426.25 | Z67: 8476.5 | AA67: 7068.63 | AB67: 5446.73
A68: 1 | C68: 금융비용 | E68: 1023.99 | G68: 3545.19 | H68: -505.65 | I68: 1320.39 | J68: 5311.27 | K68: 9671.2 | L68: 2243.16 | M68: 2213.17 | N68: 2262.61 | O68: 2555.28 | P68: 9274.22 | Q68: 2222.57 | R68: 2443.05 | S68: 2656.82 | T68: 2599.75 | U68: 9922.19 | V68: 2183.23 | W68: 2668.58 | X68: 1825.58 | Y68: 2141.57 | Z68: 8818.96 | AA68: 1799.01 | AB68: 1473.54
A69: 1 | C69: 법인세비용차감전계속사업이익 | E69: -13076.18 | G69: -9179.87 | H69: 14127.13 | I69: 3816.19 | J69: 7330.48 | K69: 16093.93 | L69: -6729.18 | M69: 17449.69 | N69: 2860.98 | O69: 20235.91 | P69: 33817.4 | Q69: 2731.21 | R69: 5665.71 | S69: -3947.47 | T69: 19436.5 | U69: 23885.95 | V69: 16788 | W69: 6646.87 | X69: 8920.75 | Y69: 25594.45 | Z69: 57950.07 | AA69: 15870.74 | AB69: 17631.95
... A77: 1 | C77: 투자활동으로인한현금흐름 | E77: -1436.76 | G77: -3771.25 | H77: -20320.41 | I77: 10653.47 | J77: -3272.39 | K77: -16710.58 | L77: -6108.53 | M77: -4336.81 | N77: -25919.23 | O77: -2868.61 | P77: -39233.18 | Q77: -4835.19 | R77: -15773.64 | S77: -5749.24 | T77: -14569.83 | U77: -40927.9 | V77: -2392.26 | W77: -5760.72 | X77: -13190.34 | Y77: -11161.62 | Z77: -32504.94 | AA77: -4305.79 | AB77: -19083.89
A78: 1 | C78: 유형자산의감소 | E78: 0 | G78: 1 | H78: 11.09 | I78: 0 | J78: 2.6 | K78: 14.69 | L78: 2343.53 | M78: 0 | N78: 0 | O78: 0 | P78: 2343.53 | Q78: 0 | R78: 0 | S78: 1.8 | T78: 0 | U78: 1.8 | X78: 0 | Y78: 0
A79: 1 | C79: 유형자산의증가 | E79: 1692.22 | G79: 3841.43 | H79: 2405.5 | I79: 6644.12 | J79: 2624.27 | K79: 15515.32 | L79: 1483.08 | M79: 3568.18 | N79: 37637.11 | O79: 196.4 | P79: 42884.77 | Q79: 3230.19 | R79: 2692.3 | S79: 4586.04 | T79: 7221.73 | U79: 17730.26 | V79: 2469.29 | W79: 1004.01 | X79: 1405.23 | Y79: 3428.12 | Z79: 8306.65 | AA79: 2279.43 | AB79: 6139.5
A80: 1 | C80: CAPEX | E80: 1692.22 | G80: 3841.43 | H80: 2405.5 | I80: 7056.97 | J80: 2624.27 | K80: 15928.17 | L80: 1483.08 | M80: 3962.18 | N80: 37645.78 | O80: 196.4 | P80: 43287.44 | Q80: 3230.19 | R80: 2792.3 | S80: 4586.04 | T80: 7221.73 | U80: 17830.26 | V80: 2469.29 | W80: 1004.01 | X80: 1405.23 | Y80: 3428.12 | Z80: 8306.65 | AA80: 2279.43 | AB80: 6139.5
A81: 1 | C81: 무형자산의증가 | E81: 0 | J81: 0 | N81: 8.67 | O81: 0 | S81: 0 | T81: 0 | X81: 0
A82: 1 | C82: 재무활동으로인한현금흐름 | E82: 13643.42 | G82: 23476.97 | H82: -11702.81 | I82: 1032.37 | J82: -4189.6 | K82: 8616.93 | L82: -772.77 | M82: -32018.97 | N82: 16178.66 | O82: -10904.13 | P82: -27517.21 | Q82: 8382.43 | R82: -16894.3 | S82: 36489.85 | T82: 4137.18 | U82: 32115.16 | V82: -1992.35 | W82: -13324.52 | X82: -1934.4 | Y82: -26154.69 | Z82: -43405.96 | AA82: -1678.09 | AB82: -14470.03
A83: 1 | C83: 단기차입금의증가 | E83: 0 | G83: 45905.2 | H83: 15550 | I83: 24914.06 | J83: 20888 | K83: 107257.26 | L83: 0 | M83: 55000 | N83: 36200 | O83: 5000 | P83: 96200 | Q83: 50000 | R83: 40000 | S83: 66200 | T83: 0 | U83: 156200 | V83: 70000 | W83: 0 | X83: 50000 | Y83: 520 | Z83: 120520 | AA83: 45000 | AB83: 30000
A84: 1 | C84: 장기차입금의증가 | E84: 15000 | G84: 30000 | H84: 10000 | I84: 0 | J84: 28000 | K84: 68000 | L84: 0 | O84: 0 | T84: 5800 | Y84: 0
A85: 1 | C85: 리스부채의상환 | E85: 634.77 | G85: 523.03 | H85: 479.69 | I85: 280.64 | J85: 176.59 | K85: 1459.95 | L85: 172.77 | M85: 184.31 | N85: 221.34 | O85: 304.13 | P85: 882.55 | Q85: 307.58 | R85: 314.74 | S85: 310.15 | T85: 312.82 | U85: 1245.29 | V85: 642.35 | W85: 604.62 | X85: 584.41 | Y85: 624.69 | Z85: 2456.07 | AA85: 628.09 | AB85: 628.9
A86: 1 | C86: 자기주식의취득 | E86: 0 | G86: 0 | J86: 0
A87: 1 | C87: 배당금지급 | E87: 0 | I87: 0 | J87: 0 | N87: 0 | O87: 0 | S87: 0 | T87: 0 | X87: 0 | Y87: 0
A88: 1 | C88: 단기차입금의감소 | E88: 0 | G88: 35905.2 | H88: 17550 | I88: 21501.06 | J88: 24301 | K88: 99257.26 | L88: 0 | M88: 33000 | N88: 20000 | O88: 0 | P88: 53000 | Q88: 10000 | R88: 45000 | S88: 41200 | T88: 0 | U88: 96200 | V88: 70000 | W88: 0 | X88: 116200 | Y88: 25000 | Z88: 211200 | AA88: 45000 | AB88: 30000
A89: 1 | C89: 유동성장기부채의감소 | E89: 700 | G89: 16000 | H89: 11000 | I89: 2100 | J89: 15600 | K89: 44700 | L89: 600 | M89: 30600 | N89: 26800 | O89: 15600 | P89: 73600 | Q89: 40600 | R89: 600 | S89: 15600 | T89: 600 | U89: 57400 | V89: 1350 | W89: 1350 | X89: 41350 | Y89: 1050 | Z89: 45100 | AA89: 1050 | AB89: 1050
A90: 1 | C90: 현금및현금성자산의증감 | E90: -265.87 | G90: 2746.19 | H90: -21131.04 | I90: 16251.66 | J90: 15638.71 | K90: 13505.52 | L90: -21842.26 | M90: 4372.7 | N90: 27.1 | O90: 9844.09 | P90: -7598.37 | Q90: 14193.74 | R90: -25563.62 | S90: 31405.01 | T90: -7685.52 | U90: 12349.61 | V90: -1837.06 | W90: 14067.22 | X90: 10591.9 | Y90: -44205.18 | Z90: -21383.12 | AA90: 16082.94 | AB90: -23404.37
A91: 1 | C91: 기말현금및현금성자산 | E91: -265.87 | G91: 29348.29 | H91: -21131.05 | I91: 16251.67 | J91: 15638.71 | K91: 40107.62 | L91: 18265.36 | M91: 4372.7 | N91: 27.1 | O91: 9844.09 | P91: 32509.25 | Q91: 46702.99 | R91: -25563.62 | S91: 31405.01 | T91: -7685.52 | U91: 44858.86 | V91: 43021.8 | W91: 14067.22 | X91: 10591.9 | Y91: -44205.17 | Z91: 23475.75 | AA91: 39558.69 | AB91: -23404.38
A92: 1 | C92: 배당금수취(CF) | L92: 0
A93: 1 | C93: 이자수취(CF) | O93: 98.21 | Q93: 134.5 | R93: 415.6 | S93: 466.3 | T93: 408.43 | U93: 1424.83 | V93: 237.21 | W93: 223.72 | X93: 188.14 | Y93: 1704.35 | Z93: 2353.42 | AA93: 1303.54 | AB93: 86.56
A94: 1 | C94: 장기차입금의감소 | O94: 0 | T94: 750
A95: 1 | C95: 이자지급(CF) | V95: -2479.94 | W95: -1723.12 | X95: 712.19 | Y95: -1811.62 | Z95: -5302.49 | AA95: -1547.36 | AB95: -1549.62

Sheet subQ
A1: YQ | C1: subQ 분기 서브모델(억원, U=100) | E1: 4Q21 | F1: 2021 | G1: 1Q22 | H1: 2Q22 | I1: 3Q22 | J1: 4Q22 | K1: 2022 | L1: 1Q23 | M1: 2Q23 | N1: 3Q23 | O1: 4Q23 | P1: 2023 | Q1: 1Q24 | R1: 2Q24 | S1: 3Q24 | T1: 4Q24 | U1: 2024 | V1: 1Q25 | W1: 2Q25 | X1: 3Q25 | Y1: 4Q25 | Z1: 2025 | AA1: 1Q26 | AB1: 2Q26 | AC1: 3Q26 | AD1: 4Q26 | AE1: 2026 | AF1: 1Q27 | AG1: 2Q27 | AH1: 3Q27 | AI1: 4Q27 | AJ1: 2027 | AK1: 1Q28 | AL1: 2Q28 | AM1: 3Q28 | AN1: 4Q28 | AO1: 2028
A2: A=이름(key) B=그룹 C=단위 D=FnGuide 계정명(VLOOKUP 키). 확정=VLOOKUP(BS), 추정=변수 가정 참조
E3: 1 | F3: 2 | G3: 3 | H3: 4 | I3: 5 | J3: 6 | K3: 7 | L3: 8 | M3: 9 | N3: 10 | O3: 11 | P3: 12 | Q3: 13 | R3: 14 | S3: 15 | T3: 16 | U3: 17 | V3: 18 | W3: 19 | X3: 20 | Y3: 21 | Z3: 22 | AA3: 23 | AB3: 24 | AC3: 25 | AD3: 26 | AE3: 27 | AF3: 28 | AG3: 29 | AH3: 30 | AI3: 31 | AJ3: 32 | AK3: 33 | AL3: 34 | AM3: 35 | AN3: 36 | AO3: 37
E4: 2021.12 | F4: 2021.12A | G4: 2022.03 | H4: 2022.06 | I4: 2022.09 | J4: 2022.12 | K4: 2022.12A | L4: 2023.03 | M4: 2023.06 | N4: 2023.09 | O4: 2023.12 | P4: 2023.12A | Q4: 2024.03 | R4: 2024.06 | S4: 2024.09 | T4: 2024.12 | U4: 2024.12A | V4: 2025.03 | W4: 2025.06 | X4: 2025.09 | Y4: 2025.12 | Z4: 2025.12A | AA4: 2026.03 | AB4: 2026.06 | AC4: 2026.09 | AD4: 2026.12 | AE4: 2026.12A | AF4: 2027.03 | AG4: 2027.06 | AH4: 2027.09 | AI4: 2027.12 | AJ4: 2027.12A | AK4: 2028.03 | AL4: 2028.06 | AM4: 2028.09 | AN4: 2028.12 | AO4: 2028.12A
A5: 매출액 | B5: 손익 | C5: 억원 | D5: 매출액(수익) | E5: =IFERROR(VLOOKUP($D5,BS연결,MATCH(E$1,BS연결H,0),0)/100,"") | G5: =IFERROR(VLOOKUP($D5,BS연결,MATCH(G$1,BS연결H,0),0)/100,"") | H5: =IFERROR(VLOOKUP($D5,BS연결,MATCH(H$1,BS연결H,0),0)/100,"") | I5: =IFERROR(VLOOKUP($D5,BS연결,MATCH(I$1,BS연결H,0),0)/100,"") | J5: =IFERROR(VLOOKUP($D5,BS연결,MATCH(J$1,BS연결H,0),0)/100,"") | K5: =IFERROR(VLOOKUP($D5,BS연결,MATCH(K$1,BS연결H,0),0)/100,"") | L5: =IFERROR(VLOOKUP($D5,BS연결,MATCH(L$1,BS연결H,0),0)/100,"") | M5: =IFERROR(VLOOKUP($D5,BS연결,MATCH(M$1,BS연결H,0),0)/100,"") | N5: =IFERROR(VLOOKUP($D5,BS연결,MATCH(N$1,BS연결H,0),0)/100,"") | ... AB5: =IFERROR(VLOOKUP($D5,BS연결,MATCH(AB$1,BS연결H,0),0)/100,"") | AC5: =IFERROR(AC37+AC39+AC41,"") | AD5: =IFERROR(AD37+AD39+AD41,"") | AE5: =SUM(AA5:AD5) | AF5: =IFERROR(AF37+AF39+AF41,"") | AG5: =IFERROR(AG37+AG39+AG41,"") | AH5: =IFERROR(AH37+AH39+AH41,"") | AI5: =IFERROR(AI37+AI39+AI41,"") | AJ5: =SUM(AF5:AI5) | AK5: =IFERROR(AK37+AK39+AK41,"") | AL5: =IFERROR(AL37+AL39+AL41,"") | AM5: =IFERROR(AM37+AM39+AM41,"") | AN5: =IFERROR(AN37+AN39+AN41,"") | AO5: =SUM(AK5:AN5)
A6: 매출원가 | B6: 손익 | C6: 억원 | D6: 매출원가 | E6: =IFERROR(VLOOKUP($D6,BS연결,MATCH(E$1,BS연결H,0),0)/100,"") | G6: =IFERROR(VLOOKUP($D6,BS연결,MATCH(G$1,BS연결H,0),0)/100,"") | H6: =IFERROR(VLOOKUP($D6,BS연결,MATCH(H$1,BS연결H,0),0)/100,"") | I6: =IFERROR(VLOOKUP($D6,BS연결,MATCH(I$1,BS연결H,0),0)/100,"") | J6: =IFERROR(VLOOKUP($D6,BS연결,MATCH(J$1,BS연결H,0),0)/100,"") | K6: =IFERROR(VLOOKUP($D6,BS연결,MATCH(K$1,BS연결H,0),0)/100,"") | L6: =IFERROR(VLOOKUP($D6,BS연결,MATCH(L$1,BS연결H,0),0)/100,"") | M6: =IFERROR(VLOOKUP($D6,BS연결,MATCH(M$1,BS연결H,0),0)/100,"") | N6: =IFERROR(VLOOKUP($D6,BS연결,MATCH(N$1,BS연결H,0),0)/100,"") | ... AB6: =IFERROR(VLOOKUP($D6,BS연결,MATCH(AB$1,BS연결H,0),0)/100,"") | AC6: =IFERROR(AC5-AC7,"") | AD6: =IFERROR(AD5-AD7,"") | AE6: =SUM(AA6:AD6) | AF6: =IFERROR(AF5-AF7,"") | AG6: =IFERROR(AG5-AG7,"") | AH6: =IFERROR(AH5-AH7,"") | AI6: =IFERROR(AI5-AI7,"") | AJ6: =SUM(AF6:AI6) | AK6: =IFERROR(AK5-AK7,"") | AL6: =IFERROR(AL5-AL7,"") | AM6: =IFERROR(AM5-AM7,"") | AN6: =IFERROR(AN5-AN7,"") | AO6: =SUM(AK6:AN6)
A7: 매출총이익 | B7: 손익 | C7: 억원 | D7: 매출총이익 | E7: =IFERROR(VLOOKUP($D7,BS연결,MATCH(E$1,BS연결H,0),0)/100,"") | G7: =IFERROR(VLOOKUP($D7,BS연결,MATCH(G$1,BS연결H,0),0)/100,"") | H7: =IFERROR(VLOOKUP($D7,BS연결,MATCH(H$1,BS연결H,0),0)/100,"") | I7: =IFERROR(VLOOKUP($D7,BS연결,MATCH(I$1,BS연결H,0),0)/100,"") | J7: =IFERROR(VLOOKUP($D7,BS연결,MATCH(J$1,BS연결H,0),0)/100,"") | K7: =IFERROR(VLOOKUP($D7,BS연결,MATCH(K$1,BS연결H,0),0)/100,"") | L7: =IFERROR(VLOOKUP($D7,BS연결,MATCH(L$1,BS연결H,0),0)/100,"") | M7: =IFERROR(VLOOKUP($D7,BS연결,MATCH(M$1,BS연결H,0),0)/100,"") | N7: =IFERROR(VLOOKUP($D7,BS연결,MATCH(N$1,BS연결H,0),0)/100,"") | ... AB7: =IFERROR(VLOOKUP($D7,BS연결,MATCH(AB$1,BS연결H,0),0)/100,"") | AC7: =IFERROR(AC9+AC8,"") | AD7: =IFERROR(AD9+AD8,"") | AE7: =SUM(AA7:AD7) | AF7: =IFERROR(AF9+AF8,"") | AG7: =IFERROR(AG9+AG8,"") | AH7: =IFERROR(AH9+AH8,"") | AI7: =IFERROR(AI9+AI8,"") | AJ7: =SUM(AF7:AI7) | AK7: =IFERROR(AK9+AK8,"") | AL7: =IFERROR(AL9+AL8,"") | AM7: =IFERROR(AM9+AM8,"") | AN7: =IFERROR(AN9+AN8,"") | AO7: =SUM(AK7:AN7)
A8: 판관비 | B8: 손익 | C8: 억원 | D8: 판관비 | E8: =IFERROR(VLOOKUP($D8,BS연결,MATCH(E$1,BS연결H,0),0)/100,"") | G8: =IFERROR(VLOOKUP($D8,BS연결,MATCH(G$1,BS연결H,0),0)/100,"") | H8: =IFERROR(VLOOKUP($D8,BS연결,MATCH(H$1,BS연결H,0),0)/100,"") | I8: =IFERROR(VLOOKUP($D8,BS연결,MATCH(I$1,BS연결H,0),0)/100,"") | J8: =IFERROR(VLOOKUP($D8,BS연결,MATCH(J$1,BS연결H,0),0)/100,"") | K8: =IFERROR(VLOOKUP($D8,BS연결,MATCH(K$1,BS연결H,0),0)/100,"") | L8: =IFERROR(VLOOKUP($D8,BS연결,MATCH(L$1,BS연결H,0),0)/100,"") | M8: =IFERROR(VLOOKUP($D8,BS연결,MATCH(M$1,BS연결H,0),0)/100,"") | N8: =IFERROR(VLOOKUP($D8,BS연결,MATCH(N$1,BS연결H,0),0)/100,"") | ... AB8: =IFERROR(VLOOKUP($D8,BS연결,MATCH(AB$1,BS연결H,0),0)/100,"") | AC8: =IFERROR(AC5*변수!AC21,"") | AD8: =IFERROR(AD5*변수!AD21,"") | AE8: =SUM(AA8:AD8) | AF8: =IFERROR(AF5*변수!AF21,"") | AG8: =IFERROR(AG5*변수!AG21,"") | AH8: =IFERROR(AH5*변수!AH21,"") | AI8: =IFERROR(AI5*변수!AI21,"") | AJ8: =SUM(AF8:AI8) | AK8: =IFERROR(AK5*변수!AK21,"") | AL8: =IFERROR(AL5*변수!AL21,"") | AM8: =IFERROR(AM5*변수!AM21,"") | AN8: =IFERROR(AN5*변수!AN21,"") | AO8: =SUM(AK8:AN8)
A9: 영업이익 | B9: 손익 | C9: 억원 | D9: 영업이익 | E9: =IFERROR(VLOOKUP($D9,BS연결,MATCH(E$1,BS연결H,0),0)/100,"") | G9: =IFERROR(VLOOKUP($D9,BS연결,MATCH(G$1,BS연결H,0),0)/100,"") | H9: =IFERROR(VLOOKUP($D9,BS연결,MATCH(H$1,BS연결H,0),0)/100,"") | I9: =IFERROR(VLOOKUP($D9,BS연결,MATCH(I$1,BS연결H,0),0)/100,"") | J9: =IFERROR(VLOOKUP($D9,BS연결,MATCH(J$1,BS연결H,0),0)/100,"") | K9: =IFERROR(VLOOKUP($D9,BS연결,MATCH(K$1,BS연결H,0),0)/100,"") | L9: =IFERROR(VLOOKUP($D9,BS연결,MATCH(L$1,BS연결H,0),0)/100,"") | M9: =IFERROR(VLOOKUP($D9,BS연결,MATCH(M$1,BS연결H,0),0)/100,"") | N9: =IFERROR(VLOOKUP($D9,BS연결,MATCH(N$1,BS연결H,0),0)/100,"") | ... T9: =IFERROR(VLOOKUP($D9,BS연결,MATCH(T$1,BS연결H,0),0)/100,"") | U9: =SUM(Q9:T9) | V9: =IFERROR(VLOOKUP($D9,BS연결,MATCH(V$1,BS연결H,0),0)/100,"") | W9: =IFERROR(VLOOKUP($D9,BS연결,MATCH(W$1,BS연결H,0),0)/100,"") | X9: =IFERROR(VLOOKUP($D9,BS연결,MATCH(X$1,BS연결H,0),0)/100,"") | Y9: =IFERROR(VLOOKUP($D9,BS연결,MATCH(Y$1,BS연결H,0),0)/100,"") | Z9: =IFERROR(VLOOKUP($D9,BS연결,MATCH(Z$1,BS연결H,0),0)/100,"") | AA9: =IFERROR(VLOOKUP($D9,BS연결,MATCH(AA$1,BS연결H,0),0)/100,"") | AB9: =IFERROR(VLOOKUP($D9,BS연결,MATCH(AB$1,BS연결H,0),0)/100,"") | AC9: =IFERROR(AC38+AC40+AC42,"") | AD9: =IFERROR(AD38+AD40+AD42,"") | AE9: =SUM(AA9:AD9) | AF9: =IFERROR(AF38+AF40+AF42,"") | AG9: =IFERROR(AG38+AG40+AG42,"") | AH9: =IFERROR(AH38+AH40+AH42,"") | AI9: =IFERROR(AI38+AI40+AI42,"") | AJ9: =SUM(AF9:AI9) | AK9: =IFERROR(AK38+AK40+AK42,"") | AL9: =IFERROR(AL38+AL40+AL42,"") | AM9: =IFERROR(AM38+AM40+AM42,"") | AN9: =IFERROR(AN38+AN40+AN42,"") | AO9: =SUM(AK9:AN9)
A10: OPM | B10: 손익 | C10: % | D10: 영업이익률 | E10: =IFERROR(E9/E5,"") | G10: =IFERROR(G9/G5,"") | H10: =IFERROR(H9/H5,"") | I10: =IFERROR(I9/I5,"") | J10: =IFERROR(J9/J5,"") | K10: =IFERROR(K9/K5,"") | L10: =IFERROR(L9/L5,"") | M10: =IFERROR(M9/M5,"") | N10: =IFERROR(N9/N5,"") | ... AO10: =IFERROR(AO9/AO5,"")
A11: 금융손익 | B11: 손익 | C11: 억원 | D11: 금융손익 | E11: =IFERROR(VLOOKUP($D11,BS연결,MATCH(E$1,BS연결H,0),0)/100,"") | G11: =IFERROR(VLOOKUP($D11,BS연결,MATCH(G$1,BS연결H,0),0)/100,"") | H11: =IFERROR(VLOOKUP($D11,BS연결,MATCH(H$1,BS연결H,0),0)/100,"") | I11: =IFERROR(VLOOKUP($D11,BS연결,MATCH(I$1,BS연결H,0),0)/100,"") | J11: =IFERROR(VLOOKUP($D11,BS연결,MATCH(J$1,BS연결H,0),0)/100,"") | K11: =IFERROR(VLOOKUP($D11,BS연결,MATCH(K$1,BS연결H,0),0)/100,"") | L11: =IFERROR(VLOOKUP($D11,BS연결,MATCH(L$1,BS연결H,0),0)/100,"") | M11: =IFERROR(VLOOKUP($D11,BS연결,MATCH(M$1,BS연결H,0),0)/100,"") | N11: =IFERROR(VLOOKUP($D11,BS연결,MATCH(N$1,BS연결H,0),0)/100,"") | ... AB11: =IFERROR(VLOOKUP($D11,BS연결,MATCH(AB$1,BS연결H,0),0)/100,"") | AC11: =IFERROR(AC12+AC13,"") | AD11: =IFERROR(AD12+AD13,"") | AE11: =SUM(AA11:AD11) | AF11: =IFERROR(AF12+AF13,"") | AG11: =IFERROR(AG12+AG13,"") | AH11: =IFERROR(AH12+AH13,"") | AI11: =IFERROR(AI12+AI13,"") | AJ11: =SUM(AF11:AI11) | AK11: =IFERROR(AK12+AK13,"") | AL11: =IFERROR(AL12+AL13,"") | AM11: =IFERROR(AM12+AM13,"") | AN11: =IFERROR(AN12+AN13,"") | AO11: =SUM(AK11:AN11)
A12: 이자손익 | B12: 손익 | C12: 억원 | D12: 이자손익 | K12: =SUM(G12:J12) | P12: =SUM(L12:O12) | Q12: =IFERROR(VLOOKUP($D12,BS연결,MATCH(Q$1,BS연결H,0),0)/100,"") | R12: =IFERROR(VLOOKUP($D12,BS연결,MATCH(R$1,BS연결H,0),0)/100,"") | S12: =IFERROR(VLOOKUP($D12,BS연결,MATCH(S$1,BS연결H,0),0)/100,"") | T12: =IFERROR(VLOOKUP($D12,BS연결,MATCH(T$1,BS연결H,0),0)/100,"") | U12: =IFERROR(VLOOKUP($D12,BS연결,MATCH(U$1,BS연결H,0),0)/100,"") | V12: =IFERROR(VLOOKUP($D12,BS연결,MATCH(V$1,BS연결H,0),0)/100,"") | W12: =IFERROR(VLOOKUP($D12,BS연결,MATCH(W$1,BS연결H,0),0)/100,"") | X12: =IFERROR(VLOOKUP($D12,BS연결,MATCH(X$1,BS연결H,0),0)/100,"") | ... Z12: =IFERROR(VLOOKUP($D12,BS연결,MATCH(Z$1,BS연결H,0),0)/100,"") | AB12: =IFERROR(VLOOKUP($D12,BS연결,MATCH(AB$1,BS연결H,0),0)/100,"") | AC12: =IFERROR((AB27*변수!$D$57-AB25*변수!$D$58)/4,"") | AD12: =IFERROR((AC27*변수!$D$57-AC25*변수!$D$58)/4,"") | AE12: =SUM(AA12:AD12) | AF12: =IFERROR((AD27*변수!$D$57-AD25*변수!$D$58)/4,"") | AG12: =IFERROR((AF27*변수!$D$57-AF25*변수!$D$58)/4,"") | AH12: =IFERROR((AG27*변수!$D$57-AG25*변수!$D$58)/4,"") | AI12: =IFERROR((AH27*변수!$D$57-AH25*변수!$D$58)/4,"") | AJ12: =SUM(AF12:AI12) | AK12: =IFERROR((AI27*변수!$D$57-AI25*변수!$D$58)/4,"") | AL12: =IFERROR((AK27*변수!$D$57-AK25*변수!$D$58)/4,"") | AM12: =IFERROR((AL27*변수!$D$57-AL25*변수!$D$58)/4,"") | AN12: =IFERROR((AM27*변수!$D$57-AM25*변수!$D$58)/4,"") | AO12: =SUM(AK12:AN12)
A13: 외환손익 | B13: 손익 | C13: 억원 | D13: 외환손익(실적만; 추정 환효과는 환관련손익) | K13: =SUM(G13:J13) | P13: =SUM(L13:O13) | Q13: =IFERROR((VLOOKUP("외환차익",BS연결,MATCH(Q$1,BS연결H,0),0)-VLOOKUP("외환차손",BS연결,MATCH(Q$1,BS연결H,0),0)+VLOOKUP("외화환산이익",BS연결,MATCH(Q$1,BS연결H,0),0)-VLOOKUP("외화환산손실",BS연결,MATCH(Q$1,BS연결H,0),0))/100,"") | R13: =IFERROR((VLOOKUP("외환차익",BS연결,MATCH(R$1,BS연결H,0),0)-VLOOKUP("외환차손",BS연결,MATCH(R$1,BS연결H,0),0)+VLOOKUP("외화환산이익",BS연결,MATCH(R$1,BS연결H,0),0)-VLOOKUP("외화환산손실",BS연결,MATCH(R$1,BS연결H,0),0))/100,"") | S13: =IFERROR((VLOOKUP("외환차익",BS연결,MATCH(S$1,BS연결H,0),0)-VLOOKUP("외환차손",BS연결,MATCH(S$1,BS연결H,0),0)+VLOOKUP("외화환산이익",BS연결,MATCH(S$1,BS연결H,0),0)-VLOOKUP("외화환산손실",BS연결,MATCH(S$1,BS연결H,0),0))/100,"") | T13: =IFERROR((VLOOKUP("외환차익",BS연결,MATCH(T$1,BS연결H,0),0)-VLOOKUP("외환차손",BS연결,MATCH(T$1,BS연결H,0),0)+VLOOKUP("외화환산이익",BS연결,MATCH(T$1,BS연결H,0),0)-VLOOKUP("외화환산손실",BS연결,MATCH(T$1,BS연결H,0),0))/100,"") | U13: =SUM(Q13:T13) | V13: =IFERROR((VLOOKUP("외환차익",BS연결,MATCH(V$1,BS연결H,0),0)-VLOOKUP("외환차손",BS연결,MATCH(V$1,BS연결H,0),0)+VLOOKUP("외화환산이익",BS연결,MATCH(V$1,BS연결H,0),0)-VLOOKUP("외화환산손실",BS연결,MATCH(V$1,BS연결H,0),0))/100,"") | W13: =IFERROR((VLOOKUP("외환차익",BS연결,MATCH(W$1,BS연결H,0),0)-VLOOKUP("외환차손",BS연결,MATCH(W$1,BS연결H,0),0)+VLOOKUP("외화환산이익",BS연결,MATCH(W$1,BS연결H,0),0)-VLOOKUP("외화환산손실",BS연결,MATCH(W$1,BS연결H,0),0))/100,"") | X13: =IFERROR((VLOOKUP("외환차익",BS연결,MATCH(X$1,BS연결H,0),0)-VLOOKUP("외환차손",BS연결,MATCH(X$1,BS연결H,0),0)+VLOOKUP("외화환산이익",BS연결,MATCH(X$1,BS연결H,0),0)-VLOOKUP("외화환산손실",BS연결,MATCH(X$1,BS연결H,0),0))/100,"") | Y13: =IFERROR((VLOOKUP("외환차익",BS연결,MATCH(Y$1,BS연결H,0),0)-VLOOKUP("외환차손",BS연결,MATCH(Y$1,BS연결H,0),0)+VLOOKUP("외화환산이익",BS연결,MATCH(Y$1,BS연결H,0),0)-VLOOKUP("외화환산손실",BS연결,MATCH(Y$1,BS연결H,0),0))/100,"") | Z13: =SUM(V13:Y13) | AB13: =IFERROR((VLOOKUP("외환차익",BS연결,MATCH(AB$1,BS연결H,0),0)-VLOOKUP("외환차손",BS연결,MATCH(AB$1,BS연결H,0),0)+VLOOKUP("외화환산이익",BS연결,MATCH(AB$1,BS연결H,0),0)-VLOOKUP("외화환산손실",BS연결,MATCH(AB$1,BS연결H,0),0))/100,"") | AC13: =변수!AC22 | AD13: =변수!AD22 | AE13: =SUM(AA13:AD13) | AF13: =변수!AF22 | AG13: =변수!AG22 | AH13: =변수!AH22 | AI13: =변수!AI22 | AJ13: =SUM(AF13:AI13) | AK13: =변수!AK22 | AL13: =변수!AL22 | AM13: =변수!AM22 | AN13: =변수!AN22 | AO13: =SUM(AK13:AN13)
A14: 기타영업외손익 | B14: 손익 | C14: 억원 | D14: 기타영업외손익 | E14: =IFERROR(VLOOKUP($D14,BS연결,MATCH(E$1,BS연결H,0),0)/100,"") | G14: =IFERROR(VLOOKUP($D14,BS연결,MATCH(G$1,BS연결H,0),0)/100,"") | H14: =IFERROR(VLOOKUP($D14,BS연결,MATCH(H$1,BS연결H,0),0)/100,"") | I14: =IFERROR(VLOOKUP($D14,BS연결,MATCH(I$1,BS연결H,0),0)/100,"") | J14: =IFERROR(VLOOKUP($D14,BS연결,MATCH(J$1,BS연결H,0),0)/100,"") | K14: =IFERROR(VLOOKUP($D14,BS연결,MATCH(K$1,BS연결H,0),0)/100,"") | L14: =IFERROR(VLOOKUP($D14,BS연결,MATCH(L$1,BS연결H,0),0)/100,"") | M14: =IFERROR(VLOOKUP($D14,BS연결,MATCH(M$1,BS연결H,0),0)/100,"") | N14: =IFERROR(VLOOKUP($D14,BS연결,MATCH(N$1,BS연결H,0),0)/100,"") | O14: =IFERROR(VLOOKUP($D14,BS연결,MATCH(O$1,BS연결H,0),0)/100,"") | P14: =SUM(L14:O14) | Q14: =IFERROR(VLOOKUP($D14,BS연결,MATCH(Q$1,BS연결H,0),0)/100,"") | R14: =IFERROR(VLOOKUP($D14,BS연결,MATCH(R$1,BS연결H,0),0)/100,"") | S14: =IFERROR(VLOOKUP($D14,BS연결,MATCH(S$1,BS연결H,0),0)/100,"") | T14: =IFERROR(VLOOKUP($D14,BS연결,MATCH(T$1,BS연결H,0),0)/100,"") | U14: =IFERROR(VLOOKUP($D14,BS연결,MATCH(U$1,BS연결H,0),0)/100,"") | V14: =IFERROR(VLOOKUP($D14,BS연결,MATCH(V$1,BS연결H,0),0)/100,"") | W14: =IFERROR(VLOOKUP($D14,BS연결,MATCH(W$1,BS연결H,0),0)/100,"") | X14: =IFERROR(VLOOKUP($D14,BS연결,MATCH(X$1,BS연결H,0),0)/100,"") | ... AB14: =IFERROR(VLOOKUP($D14,BS연결,MATCH(AB$1,BS연결H,0),0)/100,"") | AC14: =변수!AC23 | AD14: =변수!AD23 | AE14: =SUM(AA14:AD14) | AF14: =변수!AF23 | AG14: =변수!AG23 | AH14: =변수!AH23 | AI14: =변수!AI23 | AJ14: =SUM(AF14:AI14) | AK14: =변수!AK23 | AL14: =변수!AL23 | AM14: =변수!AM23 | AN14: =변수!AN23 | AO14: =SUM(AK14:AN14)
A15: 지분법손익 | B15: 손익 | C15: 억원 | D15: 종속기업,공동지배기업및관계기업관련손익 | E15: =IFERROR(VLOOKUP($D15,BS연결,MATCH(E$1,BS연결H,0),0)/100,"") | G15: =IFERROR(VLOOKUP($D15,BS연결,MATCH(G$1,BS연결H,0),0)/100,"") | H15: =IFERROR(VLOOKUP($D15,BS연결,MATCH(H$1,BS연결H,0),0)/100,"") | I15: =IFERROR(VLOOKUP($D15,BS연결,MATCH(I$1,BS연결H,0),0)/100,"") | J15: =IFERROR(VLOOKUP($D15,BS연결,MATCH(J$1,BS연결H,0),0)/100,"") | K15: =IFERROR(VLOOKUP($D15,BS연결,MATCH(K$1,BS연결H,0),0)/100,"") | L15: =IFERROR(VLOOKUP($D15,BS연결,MATCH(L$1,BS연결H,0),0)/100,"") | M15: =IFERROR(VLOOKUP($D15,BS연결,MATCH(M$1,BS연결H,0),0)/100,"") | N15: =IFERROR(VLOOKUP($D15,BS연결,MATCH(N$1,BS연결H,0),0)/100,"") | ... AB15: =IFERROR(VLOOKUP($D15,BS연결,MATCH(AB$1,BS연결H,0),0)/100,"") | AC15: =변수!AC24 | AD15: =변수!AD24 | AE15: =SUM(AA15:AD15) | AF15: =변수!AF24 | AG15: =변수!AG24 | AH15: =변수!AH24 | AI15: =변수!AI24 | AJ15: =SUM(AF15:AI15) | AK15: =변수!AK24 | AL15: =변수!AL24 | AM15: =변수!AM24 | AN15: =변수!AN24 | AO15: =SUM(AK15:AN15)
A16: 세전이익 | B16: 손익 | C16: 억원 | D16: 법인세비용차감전계속사업이익 | E16: =IFERROR(VLOOKUP($D16,BS연결,MATCH(E$1,BS연결H,0),0)/100,"") | G16: =IFERROR(VLOOKUP($D16,BS연결,MATCH(G$1,BS연결H,0),0)/100,"") | H16: =IFERROR(VLOOKUP($D16,BS연결,MATCH(H$1,BS연결H,0),0)/100,"") | I16: =IFERROR(VLOOKUP($D16,BS연결,MATCH(I$1,BS연결H,0),0)/100,"") | J16: =IFERROR(VLOOKUP($D16,BS연결,MATCH(J$1,BS연결H,0),0)/100,"") | K16: =IFERROR(VLOOKUP($D16,BS연결,MATCH(K$1,BS연결H,0),0)/100,"") | L16: =IFERROR(VLOOKUP($D16,BS연결,MATCH(L$1,BS연결H,0),0)/100,"") | M16: =IFERROR(VLOOKUP($D16,BS연결,MATCH(M$1,BS연결H,0),0)/100,"") | N16: =IFERROR(VLOOKUP($D16,BS연결,MATCH(N$1,BS연결H,0),0)/100,"") | ... AB16: =IFERROR(VLOOKUP($D16,BS연결,MATCH(AB$1,BS연결H,0),0)/100,"") | AC16: =IFERROR(AC9+AC11+AC14+AC15,"") | AD16: =IFERROR(AD9+AD11+AD14+AD15,"") | AE16: =SUM(AA16:AD16) | AF16: =IFERROR(AF9+AF11+AF14+AF15,"") | AG16: =IFERROR(AG9+AG11+AG14+AG15,"") | AH16: =IFERROR(AH9+AH11+AH14+AH15,"") | AI16: =IFERROR(AI9+AI11+AI14+AI15,"") | AJ16: =SUM(AF16:AI16) | AK16: =IFERROR(AK9+AK11+AK14+AK15,"") | AL16: =IFERROR(AL9+AL11+AL14+AL15,"") | AM16: =IFERROR(AM9+AM11+AM14+AM15,"") | AN16: =IFERROR(AN9+AN11+AN14+AN15,"") | AO16: =SUM(AK16:AN16)
A17: 법인세비용 | B17: 손익 | C17: 억원 | D17: 법인세비용 | E17: =IFERROR(VLOOKUP($D17,BS연결,MATCH(E$1,BS연결H,0),0)/100,"") | G17: =IFERROR(VLOOKUP($D17,BS연결,MATCH(G$1,BS연결H,0),0)/100,"") | H17: =IFERROR(VLOOKUP($D17,BS연결,MATCH(H$1,BS연결H,0),0)/100,"") | I17: =IFERROR(VLOOKUP($D17,BS연결,MATCH(I$1,BS연결H,0),0)/100,"") | J17: =IFERROR(VLOOKUP($D17,BS연결,MATCH(J$1,BS연결H,0),0)/100,"") | K17: =IFERROR(VLOOKUP($D17,BS연결,MATCH(K$1,BS연결H,0),0)/100,"") | L17: =IFERROR(VLOOKUP($D17,BS연결,MATCH(L$1,BS연결H,0),0)/100,"") | M17: =IFERROR(VLOOKUP($D17,BS연결,MATCH(M$1,BS연결H,0),0)/100,"") | N17: =IFERROR(VLOOKUP($D17,BS연결,MATCH(N$1,BS연결H,0),0)/100,"") | ... Y17: =IFERROR(VLOOKUP($D17,BS연결,MATCH(Y$1,BS연결H,0),0)/100,"") | Z17: =SUM(V17:Y17) | AA17: =IFERROR(VLOOKUP($D17,BS연결,MATCH(AA$1,BS연결H,0),0)/100,"") | AB17: =IFERROR(VLOOKUP($D17,BS연결,MATCH(AB$1,BS연결H,0),0)/100,"") | AC17: =IFERROR(MAX(AC16,0)*변수!AC25,"") | AD17: =IFERROR(MAX(AD16,0)*변수!AD25,"") | AE17: =SUM(AA17:AD17) | AF17: =IFERROR(MAX(AF16,0)*변수!AF25,"") | AG17: =IFERROR(MAX(AG16,0)*변수!AG25,"") | AH17: =IFERROR(MAX(AH16,0)*변수!AH25,"") | AI17: =IFERROR(MAX(AI16,0)*변수!AI25,"") | AJ17: =SUM(AF17:AI17) | AK17: =IFERROR(MAX(AK16,0)*변수!AK25,"") | AL17: =IFERROR(MAX(AL16,0)*변수!AL25,"") | AM17: =IFERROR(MAX(AM16,0)*변수!AM25,"") | AN17: =IFERROR(MAX(AN16,0)*변수!AN25,"") | AO17: =SUM(AK17:AN17)
A18: 당기순이익 | B18: 손익 | C18: 억원 | D18: 당기순이익 | E18: =IFERROR(VLOOKUP($D18,BS연결,MATCH(E$1,BS연결H,0),0)/100,"") | G18: =IFERROR(VLOOKUP($D18,BS연결,MATCH(G$1,BS연결H,0),0)/100,"") | H18: =IFERROR(VLOOKUP($D18,BS연결,MATCH(H$1,BS연결H,0),0)/100,"") | I18: =IFERROR(VLOOKUP($D18,BS연결,MATCH(I$1,BS연결H,0),0)/100,"") | J18: =IFERROR(VLOOKUP($D18,BS연결,MATCH(J$1,BS연결H,0),0)/100,"") | K18: =IFERROR(VLOOKUP($D18,BS연결,MATCH(K$1,BS연결H,0),0)/100,"") | L18: =IFERROR(VLOOKUP($D18,BS연결,MATCH(L$1,BS연결H,0),0)/100,"") | M18: =IFERROR(VLOOKUP($D18,BS연결,MATCH(M$1,BS연결H,0),0)/100,"") | N18: =IFERROR(VLOOKUP($D18,BS연결,MATCH(N$1,BS연결H,0),0)/100,"") | ... AB18: =IFERROR(VLOOKUP($D18,BS연결,MATCH(AB$1,BS연결H,0),0)/100,"") | AC18: =IFERROR(AC16-AC17,"") | AD18: =IFERROR(AD16-AD17,"") | AE18: =SUM(AA18:AD18) | AF18: =IFERROR(AF16-AF17,"") | AG18: =IFERROR(AG16-AG17,"") | AH18: =IFERROR(AH16-AH17,"") | AI18: =IFERROR(AI16-AI17,"") | AJ18: =SUM(AF18:AI18) | AK18: =IFERROR(AK16-AK17,"") | AL18: =IFERROR(AL16-AL17,"") | AM18: =IFERROR(AM16-AM17,"") | AN18: =IFERROR(AN16-AN17,"") | AO18: =SUM(AK18:AN18)
A19: 지배주주순이익 | B19: 손익 | C19: 억원 | D19: (지배주주지분)당기순이익 | E19: =IFERROR(VLOOKUP($D19,BS연결,MATCH(E$1,BS연결H,0),0)/100,"") | G19: =IFERROR(VLOOKUP($D19,BS연결,MATCH(G$1,BS연결H,0),0)/100,"") | H19: =IFERROR(VLOOKUP($D19,BS연결,MATCH(H$1,BS연결H,0),0)/100,"") | I19: =IFERROR(VLOOKUP($D19,BS연결,MATCH(I$1,BS연결H,0),0)/100,"") | J19: =IFERROR(VLOOKUP($D19,BS연결,MATCH(J$1,BS연결H,0),0)/100,"") | K19: =IFERROR(VLOOKUP($D19,BS연결,MATCH(K$1,BS연결H,0),0)/100,"") | L19: =IFERROR(VLOOKUP($D19,BS연결,MATCH(L$1,BS연결H,0),0)/100,"") | M19: =IFERROR(VLOOKUP($D19,BS연결,MATCH(M$1,BS연결H,0),0)/100,"") | N19: =IFERROR(VLOOKUP($D19,BS연결,MATCH(N$1,BS연결H,0),0)/100,"") | ... AB19: =IFERROR(VLOOKUP($D19,BS연결,MATCH(AB$1,BS연결H,0),0)/100,"") | AC19: =IFERROR(AC18*변수!AC26,"") | AD19: =IFERROR(AD18*변수!AD26,"") | AE19: =SUM(AA19:AD19) | AF19: =IFERROR(AF18*변수!AF26,"") | AG19: =IFERROR(AG18*변수!AG26,"") | AH19: =IFERROR(AH18*변수!AH26,"") | AI19: =IFERROR(AI18*변수!AI26,"") | AJ19: =SUM(AF19:AI19) | AK19: =IFERROR(AK18*변수!AK26,"") | AL19: =IFERROR(AL18*변수!AL26,"") | AM19: =IFERROR(AM18*변수!AM26,"") | AN19: =IFERROR(AN18*변수!AN26,"") | AO19: =SUM(AK19:AN19)
A20: 중단사업이익 | B20: 손익 | C20: 억원 | D20: 중단사업이익 | K20: =SUM(G20:J20) | N20: =IFERROR(VLOOKUP($D20,BS연결,MATCH(N$1,BS연결H,0),0)/100,"") | O20: =IFERROR(VLOOKUP($D20,BS연결,MATCH(O$1,BS연결H,0),0)/100,"") | P20: =SUM(L20:O20) | S20: =IFERROR(VLOOKUP($D20,BS연결,MATCH(S$1,BS연결H,0),0)/100,"") | T20: =IFERROR(VLOOKUP($D20,BS연결,MATCH(T$1,BS연결H,0),0)/100,"") | U20: =SUM(Q20:T20) | Z20: =SUM(V20:Y20) | AE20: =SUM(AA20:AD20) | AJ20: =SUM(AF20:AI20) | AO20: =SUM(AK20:AN20)
A21: 자산총계 | B21: 재무상태 | C21: 억원 | D21: 자산총계 | E21: =IFERROR(VLOOKUP($D21,BS연결,MATCH(E$1,BS연결H,0),0)/100,"") | F21: =IFERROR(VLOOKUP($D21,BS연결,MATCH(F$1,BS연결H,0),0)/100,"") | G21: =IFERROR(VLOOKUP($D21,BS연결,MATCH(G$1,BS연결H,0),0)/100,"") | H21: =IFERROR(VLOOKUP($D21,BS연결,MATCH(H$1,BS연결H,0),0)/100,"") | I21: =IFERROR(VLOOKUP($D21,BS연결,MATCH(I$1,BS연결H,0),0)/100,"") | J21: =IFERROR(VLOOKUP($D21,BS연결,MATCH(J$1,BS연결H,0),0)/100,"") | K21: =IFERROR(VLOOKUP($D21,BS연결,MATCH(K$1,BS연결H,0),0)/100,"") | L21: =IFERROR(VLOOKUP($D21,BS연결,MATCH(L$1,BS연결H,0),0)/100,"") | ... AB21: =IFERROR(VLOOKUP($D21,BS연결,MATCH(AB$1,BS연결H,0),0)/100,"") | AC21: =IFERROR(AC22+AC23,"") | AD21: =IFERROR(AD22+AD23,"") | AE21: =AD21 | AF21: =IFERROR(AF22+AF23,"") | AG21: =IFERROR(AG22+AG23,"") | AH21: =IFERROR(AH22+AH23,"") | AI21: =IFERROR(AI22+AI23,"") | AJ21: =AI21 | AK21: =IFERROR(AK22+AK23,"") | AL21: =IFERROR(AL22+AL23,"") | AM21: =IFERROR(AM22+AM23,"") | AN21: =IFERROR(AN22+AN23,"") | AO21: =AN21
A22: 부채총계 | B22: 재무상태 | C22: 억원 | D22: 부채총계 | E22: =IFERROR(VLOOKUP($D22,BS연결,MATCH(E$1,BS연결H,0),0)/100,"") | F22: =IFERROR(VLOOKUP($D22,BS연결,MATCH(F$1,BS연결H,0),0)/100,"") | G22: =IFERROR(VLOOKUP($D22,BS연결,MATCH(G$1,BS연결H,0),0)/100,"") | H22: =IFERROR(VLOOKUP($D22,BS연결,MATCH(H$1,BS연결H,0),0)/100,"") | I22: =IFERROR(VLOOKUP($D22,BS연결,MATCH(I$1,BS연결H,0),0)/100,"") | J22: =IFERROR(VLOOKUP($D22,BS연결,MATCH(J$1,BS연결H,0),0)/100,"") | K22: =IFERROR(VLOOKUP($D22,BS연결,MATCH(K$1,BS연결H,0),0)/100,"") | L22: =IFERROR(VLOOKUP($D22,BS연결,MATCH(L$1,BS연결H,0),0)/100,"") | ... AB22: =IFERROR(VLOOKUP($D22,BS연결,MATCH(AB$1,BS연결H,0),0)/100,"") | AC22: =IFERROR(AB22*(1+변수!AC28),"") | AD22: =IFERROR(AC22*(1+변수!AD28),"") | AE22: =AD22 | AF22: =IFERROR(AD22*(1+변수!AF28),"") | AG22: =IFERROR(AF22*(1+변수!AG28),"") | AH22: =IFERROR(AG22*(1+변수!AH28),"") | AI22: =IFERROR(AH22*(1+변수!AI28),"") | AJ22: =AI22 | AK22: =IFERROR(AI22*(1+변수!AK28),"") | AL22: =IFERROR(AK22*(1+변수!AL28),"") | AM22: =IFERROR(AL22*(1+변수!AM28),"") | AN22: =IFERROR(AM22*(1+변수!AN28),"") | AO22: =AN22
A23: 자본총계 | B23: 재무상태 | C23: 억원 | D23: 자본총계 | E23: =IFERROR(VLOOKUP($D23,BS연결,MATCH(E$1,BS연결H,0),0)/100,"") | F23: =IFERROR(VLOOKUP($D23,BS연결,MATCH(F$1,BS연결H,0),0)/100,"") | G23: =IFERROR(VLOOKUP($D23,BS연결,MATCH(G$1,BS연결H,0),0)/100,"") | H23: =IFERROR(VLOOKUP($D23,BS연결,MATCH(H$1,BS연결H,0),0)/100,"") | I23: =IFERROR(VLOOKUP($D23,BS연결,MATCH(I$1,BS연결H,0),0)/100,"") | J23: =IFERROR(VLOOKUP($D23,BS연결,MATCH(J$1,BS연결H,0),0)/100,"") | K23: =IFERROR(VLOOKUP($D23,BS연결,MATCH(K$1,BS연결H,0),0)/100,"") | L23: =IFERROR(VLOOKUP($D23,BS연결,MATCH(L$1,BS연결H,0),0)/100,"") | ... AB23: =IFERROR(VLOOKUP($D23,BS연결,MATCH(AB$1,BS연결H,0),0)/100,"") | AC23: =IFERROR(AB23+AC18-변수!AC29,"") | AD23: =IFERROR(AC23+AD18-변수!AD29,"") | AE23: =AD23 | AF23: =IFERROR(AD23+AF18-변수!AF29,"") | AG23: =IFERROR(AF23+AG18-변수!AG29,"") | AH23: =IFERROR(AG23+AH18-변수!AH29,"") | AI23: =IFERROR(AH23+AI18-변수!AI29,"") | AJ23: =AI23 | AK23: =IFERROR(AI23+AK18-변수!AK29,"") | AL23: =IFERROR(AK23+AL18-변수!AL29,"") | AM23: =IFERROR(AL23+AM18-변수!AM29,"") | AN23: =IFERROR(AM23+AN18-변수!AN29,"") | AO23: =AN23
A24: 지배주주지분 | B24: 재무상태 | C24: 억원 | D24: 지배주주지분 | E24: =IFERROR(VLOOKUP($D24,BS연결,MATCH(E$1,BS연결H,0),0)/100,"") | F24: =IFERROR(VLOOKUP($D24,BS연결,MATCH(F$1,BS연결H,0),0)/100,"") | G24: =IFERROR(VLOOKUP($D24,BS연결,MATCH(G$1,BS연결H,0),0)/100,"") | H24: =IFERROR(VLOOKUP($D24,BS연결,MATCH(H$1,BS연결H,0),0)/100,"") | I24: =IFERROR(VLOOKUP($D24,BS연결,MATCH(I$1,BS연결H,0),0)/100,"") | J24: =IFERROR(VLOOKUP($D24,BS연결,MATCH(J$1,BS연결H,0),0)/100,"") | K24: =IFERROR(VLOOKUP($D24,BS연결,MATCH(K$1,BS연결H,0),0)/100,"") | L24: =IFERROR(VLOOKUP($D24,BS연결,MATCH(L$1,BS연결H,0),0)/100,"") | ... AB24: =IFERROR(VLOOKUP($D24,BS연결,MATCH(AB$1,BS연결H,0),0)/100,"") | AC24: =IFERROR(AB24+AC19-변수!AC30,"") | AD24: =IFERROR(AC24+AD19-변수!AD30,"") | AE24: =AD24 | AF24: =IFERROR(AD24+AF19-변수!AF30,"") | AG24: =IFERROR(AF24+AG19-변수!AG30,"") | AH24: =IFERROR(AG24+AH19-변수!AH30,"") | AI24: =IFERROR(AH24+AI19-변수!AI30,"") | AJ24: =AI24 | AK24: =IFERROR(AI24+AK19-변수!AK30,"") | AL24: =IFERROR(AK24+AL19-변수!AL30,"") | AM24: =IFERROR(AL24+AM19-변수!AM30,"") | AN24: =IFERROR(AM24+AN19-변수!AN30,"") | AO24: =AN24
A25: 총차입금 | B25: 재무상태 | C25: 억원 | D25: 총차입금 | E25: =IFERROR(VLOOKUP($D25,BS연결,MATCH(E$1,BS연결H,0),0)/100,"") | F25: =IFERROR(VLOOKUP($D25,BS연결,MATCH(F$1,BS연결H,0),0)/100,"") | G25: =IFERROR(VLOOKUP($D25,BS연결,MATCH(G$1,BS연결H,0),0)/100,"") | H25: =IFERROR(VLOOKUP($D25,BS연결,MATCH(H$1,BS연결H,0),0)/100,"") | I25: =IFERROR(VLOOKUP($D25,BS연결,MATCH(I$1,BS연결H,0),0)/100,"") | J25: =IFERROR(VLOOKUP($D25,BS연결,MATCH(J$1,BS연결H,0),0)/100,"") | K25: =IFERROR(VLOOKUP($D25,BS연결,MATCH(K$1,BS연결H,0),0)/100,"") | L25: =IFERROR(VLOOKUP($D25,BS연결,MATCH(L$1,BS연결H,0),0)/100,"") | ... AB25: =IFERROR(VLOOKUP($D25,BS연결,MATCH(AB$1,BS연결H,0),0)/100,"") | AC25: =IFERROR(AB25*(1+변수!AC31),"") | AD25: =IFERROR(AC25*(1+변수!AD31),"") | AE25: =AD25 | AF25: =IFERROR(AD25*(1+변수!AF31),"") | AG25: =IFERROR(AF25*(1+변수!AG31),"") | AH25: =IFERROR(AG25*(1+변수!AH31),"") | AI25: =IFERROR(AH25*(1+변수!AI31),"") | AJ25: =AI25 | AK25: =IFERROR(AI25*(1+변수!AK31),"") | AL25: =IFERROR(AK25*(1+변수!AL31),"") | AM25: =IFERROR(AL25*(1+변수!AM31),"") | AN25: =IFERROR(AM25*(1+변수!AN31),"") | AO25: =AN25
A26: 순차입금 | B26: 재무상태 | C26: 억원 | D26: 순차입금 | E26: =IFERROR(VLOOKUP($D26,BS연결,MATCH(E$1,BS연결H,0),0)/100,"") | F26: =IFERROR(VLOOKUP($D26,BS연결,MATCH(F$1,BS연결H,0),0)/100,"") | G26: =IFERROR(VLOOKUP($D26,BS연결,MATCH(G$1,BS연결H,0),0)/100,"") | H26: =IFERROR(VLOOKUP($D26,BS연결,MATCH(H$1,BS연결H,0),0)/100,"") | I26: =IFERROR(VLOOKUP($D26,BS연결,MATCH(I$1,BS연결H,0),0)/100,"") | J26: =IFERROR(VLOOKUP($D26,BS연결,MATCH(J$1,BS연결H,0),0)/100,"") | K26: =IFERROR(VLOOKUP($D26,BS연결,MATCH(K$1,BS연결H,0),0)/100,"") | L26: =IFERROR(VLOOKUP($D26,BS연결,MATCH(L$1,BS연결H,0),0)/100,"") | ... AB26: =IFERROR(VLOOKUP($D26,BS연결,MATCH(AB$1,BS연결H,0),0)/100,"") | AC26: =IFERROR(AB26*(1+변수!AC32),"") | AD26: =IFERROR(AC26*(1+변수!AD32),"") | AE26: =AD26 | AF26: =IFERROR(AD26*(1+변수!AF32),"") | AG26: =IFERROR(AF26*(1+변수!AG32),"") | AH26: =IFERROR(AG26*(1+변수!AH32),"") | AI26: =IFERROR(AH26*(1+변수!AI32),"") | AJ26: =AI26 | AK26: =IFERROR(AI26*(1+변수!AK32),"") | AL26: =IFERROR(AK26*(1+변수!AL32),"") | AM26: =IFERROR(AL26*(1+변수!AM32),"") | AN26: =IFERROR(AM26*(1+변수!AN32),"") | AO26: =AN26
A27: 이자발생자산 | B27: 재무상태 | C27: 억원 | D27: 이자발생자산 | E27: =IFERROR(VLOOKUP($D27,BS연결,MATCH(E$1,BS연결H,0),0)/100,"") | F27: =IFERROR(VLOOKUP($D27,BS연결,MATCH(F$1,BS연결H,0),0)/100,"") | G27: =IFERROR(VLOOKUP($D27,BS연결,MATCH(G$1,BS연결H,0),0)/100,"") | H27: =IFERROR(VLOOKUP($D27,BS연결,MATCH(H$1,BS연결H,0),0)/100,"") | I27: =IFERROR(VLOOKUP($D27,BS연결,MATCH(I$1,BS연결H,0),0)/100,"") | J27: =IFERROR(VLOOKUP($D27,BS연결,MATCH(J$1,BS연결H,0),0)/100,"") | K27: =IFERROR(VLOOKUP($D27,BS연결,MATCH(K$1,BS연결H,0),0)/100,"") | L27: =IFERROR(VLOOKUP($D27,BS연결,MATCH(L$1,BS연결H,0),0)/100,"") | ... AB27: =IFERROR(VLOOKUP($D27,BS연결,MATCH(AB$1,BS연결H,0),0)/100,"") | AC27: =IFERROR(AB27*(1+변수!AC33),"") | AD27: =IFERROR(AC27*(1+변수!AD33),"") | AE27: =AD27 | AF27: =IFERROR(AD27*(1+변수!AF33),"") | AG27: =IFERROR(AF27*(1+변수!AG33),"") | AH27: =IFERROR(AG27*(1+변수!AH33),"") | AI27: =IFERROR(AH27*(1+변수!AI33),"") | AJ27: =AI27 | AK27: =IFERROR(AI27*(1+변수!AK33),"") | AL27: =IFERROR(AK27*(1+변수!AL33),"") | AM27: =IFERROR(AL27*(1+변수!AM33),"") | AN27: =IFERROR(AM27*(1+변수!AN33),"") | AO27: =AN27
A28: 현금및현금성자산 | B28: 재무상태 | C28: 억원 | D28: 현금및현금성자산 | E28: =IFERROR(VLOOKUP($D28,BS연결,MATCH(E$1,BS연결H,0),0)/100,"") | F28: =IFERROR(VLOOKUP($D28,BS연결,MATCH(F$1,BS연결H,0),0)/100,"") | G28: =IFERROR(VLOOKUP($D28,BS연결,MATCH(G$1,BS연결H,0),0)/100,"") | H28: =IFERROR(VLOOKUP($D28,BS연결,MATCH(H$1,BS연결H,0),0)/100,"") | I28: =IFERROR(VLOOKUP($D28,BS연결,MATCH(I$1,BS연결H,0),0)/100,"") | J28: =IFERROR(VLOOKUP($D28,BS연결,MATCH(J$1,BS연결H,0),0)/100,"") | K28: =IFERROR(VLOOKUP($D28,BS연결,MATCH(K$1,BS연결H,0),0)/100,"") | L28: =IFERROR(VLOOKUP($D28,BS연결,MATCH(L$1,BS연결H,0),0)/100,"") | ... AB28: =IFERROR(VLOOKUP($D28,BS연결,MATCH(AB$1,BS연결H,0),0)/100,"") | AE28: =AD28 | AJ28: =AI28 | AO28: =AN28
A29: CAPEX | B29: 현금흐름 | C29: 억원 | D29: CAPEX | E29: =IFERROR(VLOOKUP($D29,BS연결,MATCH(E$1,BS연결H,0),0)/100,"") | G29: =IFERROR(VLOOKUP($D29,BS연결,MATCH(G$1,BS연결H,0),0)/100,"") | H29: =IFERROR(VLOOKUP($D29,BS연결,MATCH(H$1,BS연결H,0),0)/100,"") | I29: =IFERROR(VLOOKUP($D29,BS연결,MATCH(I$1,BS연결H,0),0)/100,"") | J29: =IFERROR(VLOOKUP($D29,BS연결,MATCH(J$1,BS연결H,0),0)/100,"") | K29: =IFERROR(VLOOKUP($D29,BS연결,MATCH(K$1,BS연결H,0),0)/100,"") | L29: =IFERROR(VLOOKUP($D29,BS연결,MATCH(L$1,BS연결H,0),0)/100,"") | M29: =IFERROR(VLOOKUP($D29,BS연결,MATCH(M$1,BS연결H,0),0)/100,"") | N29: =IFERROR(VLOOKUP($D29,BS연결,MATCH(N$1,BS연결H,0),0)/100,"") | ... AB29: =IFERROR(VLOOKUP($D29,BS연결,MATCH(AB$1,BS연결H,0),0)/100,"") | AC29: =IFERROR(X29*(1+변수!AC35),"") | AD29: =IFERROR(Y29*(1+변수!AD35),"") | AE29: =SUM(AA29:AD29) | AF29: =IFERROR(AA29*(1+변수!AF35),"") | AG29: =IFERROR(AB29*(1+변수!AG35),"") | AH29: =IFERROR(AC29*(1+변수!AH35),"") | AI29: =IFERROR(AD29*(1+변수!AI35),"") | AJ29: =SUM(AF29:AI29) | AK29: =IFERROR(AF29*(1+변수!AK35),"") | AL29: =IFERROR(AG29*(1+변수!AL35),"") | AM29: =IFERROR(AH29*(1+변수!AM35),"") | AN29: =IFERROR(AI29*(1+변수!AN35),"") | AO29: =SUM(AK29:AN29)
A30: 영업활동현금흐름 | B30: 현금흐름 | C30: 억원 | D30: 영업활동으로인한현금흐름 | E30: =IFERROR(VLOOKUP($D30,BS연결,MATCH(E$1,BS연결H,0),0)/100,"") | G30: =IFERROR(VLOOKUP($D30,BS연결,MATCH(G$1,BS연결H,0),0)/100,"") | H30: =IFERROR(VLOOKUP($D30,BS연결,MATCH(H$1,BS연결H,0),0)/100,"") | I30: =IFERROR(VLOOKUP($D30,BS연결,MATCH(I$1,BS연결H,0),0)/100,"") | J30: =IFERROR(VLOOKUP($D30,BS연결,MATCH(J$1,BS연결H,0),0)/100,"") | K30: =IFERROR(VLOOKUP($D30,BS연결,MATCH(K$1,BS연결H,0),0)/100,"") | L30: =IFERROR(VLOOKUP($D30,BS연결,MATCH(L$1,BS연결H,0),0)/100,"") | M30: =IFERROR(VLOOKUP($D30,BS연결,MATCH(M$1,BS연결H,0),0)/100,"") | N30: =IFERROR(VLOOKUP($D30,BS연결,MATCH(N$1,BS연결H,0),0)/100,"") | ... AB30: =IFERROR(VLOOKUP($D30,BS연결,MATCH(AB$1,BS연결H,0),0)/100,"") | AE30: =SUM(AA30:AD30) | AJ30: =SUM(AF30:AI30) | AO30: =SUM(AK30:AN30)
A31: 주식수 | B31: 주당 | C31: 백만주 | D31: 유통주식수 | E31: 54.821 | F31: =E31 | G31: 54.898 | H31: 54.898 | I31: 54.898 | J31: 54.898 | K31: =J31 | L31: 54.898 | M31: 54.898 | N31: 54.898 | O31: 54.898 | P31: =O31 | Q31: 56.849 | R31: 56.849 | S31: 56.849 | T31: 56.849 | U31: =T31 | V31: 56.849 | W31: 56.849 | X31: 56.849 | Y31: 56.849 | Z31: =Y31 | AA31: 56.849 | AB31: 56.849 | AC31: =IFERROR(AB31*(1+변수!AC37),"") | AD31: =IFERROR(AC31*(1+변수!AD37),"") | AE31: =AD31 | AF31: =IFERROR(AD31*(1+변수!AF37),"") | AG31: =IFERROR(AF31*(1+변수!AG37),"") | AH31: =IFERROR(AG31*(1+변수!AH37),"") | AI31: =IFERROR(AH31*(1+변수!AI37),"") | AJ31: =AI31 | AK31: =IFERROR(AI31*(1+변수!AK37),"") | AL31: =IFERROR(AK31*(1+변수!AL37),"") | AM31: =IFERROR(AL31*(1+변수!AM37),"") | AN31: =IFERROR(AM31*(1+변수!AN37),"") | AO31: =AN31
A32: EPS | B32: 주당 | C32: 원 | D32: EPS | E32: =IFERROR(E19*100/E31,"") | G32: =IFERROR(G19*100/G31,"") | H32: =IFERROR(H19*100/H31,"") | I32: =IFERROR(I19*100/I31,"") | J32: =IFERROR(J19*100/J31,"") | K32: =SUM(G32:J32) | L32: =IFERROR(L19*100/L31,"") | M32: =IFERROR(M19*100/M31,"") | N32: =IFERROR(N19*100/N31,"") | O32: =IFERROR(O19*100/O31,"") | P32: =SUM(L32:O32) | Q32: =IFERROR(Q19*100/Q31,"") | R32: =IFERROR(R19*100/R31,"") | S32: =IFERROR(S19*100/S31,"") | T32: =IFERROR(T19*100/T31,"") | U32: =SUM(Q32:T32) | V32: =IFERROR(V19*100/V31,"") | W32: =IFERROR(W19*100/W31,"") | X32: =IFERROR(X19*100/X31,"") | Y32: =IFERROR(Y19*100/Y31,"") | Z32: =SUM(V32:Y32) | AA32: =IFERROR(AA19*100/AA31,"") | AB32: =IFERROR(AB19*100/AB31,"") | AC32: =IFERROR(AC19*100/AC31,"") | AD32: =IFERROR(AD19*100/AD31,"") | AE32: =SUM(AA32:AD32) | AF32: =IFERROR(AF19*100/AF31,"") | AG32: =IFERROR(AG19*100/AG31,"") | AH32: =IFERROR(AH19*100/AH31,"") | AI32: =IFERROR(AI19*100/AI31,"") | AJ32: =SUM(AF32:AI32) | AK32: =IFERROR(AK19*100/AK31,"") | AL32: =IFERROR(AL19*100/AL31,"") | AM32: =IFERROR(AM19*100/AM31,"") | AN32: =IFERROR(AN19*100/AN31,"") | AO32: =SUM(AK32:AN32)
A33: BPS | B33: 주당 | C33: 원 | D33: BPS | E33: =IFERROR(E24*100/E31,"") | F33: =E33 | G33: =IFERROR(G24*100/G31,"") | H33: =IFERROR(H24*100/H31,"") | I33: =IFERROR(I24*100/I31,"") | J33: =IFERROR(J24*100/J31,"") | K33: =J33 | L33: =IFERROR(L24*100/L31,"") | M33: =IFERROR(M24*100/M31,"") | N33: =IFERROR(N24*100/N31,"") | O33: =IFERROR(O24*100/O31,"") | P33: =O33 | Q33: =IFERROR(Q24*100/Q31,"") | R33: =IFERROR(R24*100/R31,"") | S33: =IFERROR(S24*100/S31,"") | T33: =IFERROR(T24*100/T31,"") | U33: =T33 | V33: =IFERROR(V24*100/V31,"") | W33: =IFERROR(W24*100/W31,"") | X33: =IFERROR(X24*100/X31,"") | Y33: =IFERROR(Y24*100/Y31,"") | Z33: =Y33 | AA33: =IFERROR(AA24*100/AA31,"") | AB33: =IFERROR(AB24*100/AB31,"") | AC33: =IFERROR(AC24*100/AC31,"") | AD33: =IFERROR(AD24*100/AD31,"") | AE33: =AD33 | AF33: =IFERROR(AF24*100/AF31,"") | AG33: =IFERROR(AG24*100/AG31,"") | AH33: =IFERROR(AH24*100/AH31,"") | AI33: =IFERROR(AI24*100/AI31,"") | AJ33: =AI33 | AK33: =IFERROR(AK24*100/AK31,"") | AL33: =IFERROR(AL24*100/AL31,"") | AM33: =IFERROR(AM24*100/AM31,"") | AN33: =IFERROR(AN24*100/AN31,"") | AO33: =AN33
A34: DPS | B34: 주당 | C34: 원 | D34: DPS(보통주) | E34: 150 | F34: 150 | J34: 150 | K34: =SUM(G34:J34) | O34: 200 | P34: =SUM(L34:O34) | T34: 200 | U34: =SUM(Q34:T34) | Y34: 225 | Z34: =SUM(V34:Y34) | AD34: =변수!AD38 | AE34: =SUM(AA34:AD34) | AI34: =변수!AI38 | AJ34: =SUM(AF34:AI34) | AN34: =변수!AN38 | AO34: =SUM(AK34:AN34)
A35: PER | B35: 주당 | C35: 배 | D35: PER | F35: =E35 | J35: =IFERROR(변수!J18/(G32+H32+I32+J32),"") | K35: =J35 | L35: =IFERROR(변수!L18/(H32+I32+J32+L32),"") | M35: =IFERROR(변수!M18/(I32+J32+L32+M32),"") | N35: =IFERROR(변수!N18/(J32+L32+M32+N32),"") | O35: =IFERROR(변수!O18/(L32+M32+N32+O32),"") | P35: =O35 | Q35: =IFERROR(변수!Q18/(M32+N32+O32+Q32),"") | R35: =IFERROR(변수!R18/(N32+O32+Q32+R32),"") | S35: =IFERROR(변수!S18/(O32+Q32+R32+S32),"") | T35: =IFERROR(변수!T18/(Q32+R32+S32+T32),"") | U35: =T35 | V35: =IFERROR(변수!V18/(R32+S32+T32+V32),"") | W35: =IFERROR(변수!W18/(S32+T32+V32+W32),"") | X35: =IFERROR(변수!X18/(T32+V32+W32+X32),"") | Y35: =IFERROR(변수!Y18/(V32+W32+X32+Y32),"") | Z35: =Y35 | AA35: =IFERROR(변수!AA18/(W32+X32+Y32+AA32),"") | AB35: =IFERROR(변수!AB18/(X32+Y32+AA32+AB32),"") | AC35: =IFERROR(변수!$D$47/(Y32+AA32+AB32+AC32),"") | AD35: =IFERROR(변수!$D$47/(AA32+AB32+AC32+AD32),"") | AE35: =AD35 | AF35: =IFERROR(변수!$D$47/(AB32+AC32+AD32+AF32),"") | AG35: =IFERROR(변수!$D$47/(AC32+AD32+AF32+AG32),"") | AH35: =IFERROR(변수!$D$47/(AD32+AF32+AG32+AH32),"") | AI35: =IFERROR(변수!$D$47/(AF32+AG32+AH32+AI32),"") | AJ35: =AI35 | AK35: =IFERROR(변수!$D$47/(AG32+AH32+AI32+AK32),"") | AL35: =IFERROR(변수!$D$47/(AH32+AI32+AK32+AL32),"") | AM35: =IFERROR(변수!$D$47/(AI32+AK32+AL32+AM32),"") | AN35: =IFERROR(변수!$D$47/(AK32+AL32+AM32+AN32),"") | AO35: =AN35
A36: PBR | B36: 주당 | C36: 배 | D36: PBR | E36: =IFERROR(변수!E18/E33,"") | F36: =E36 | G36: =IFERROR(변수!G18/G33,"") | H36: =IFERROR(변수!H18/H33,"") | I36: =IFERROR(변수!I18/I33,"") | J36: =IFERROR(변수!J18/J33,"") | K36: =J36 | L36: =IFERROR(변수!L18/L33,"") | M36: =IFERROR(변수!M18/M33,"") | N36: =IFERROR(변수!N18/N33,"") | O36: =IFERROR(변수!O18/O33,"") | P36: =O36 | Q36: =IFERROR(변수!Q18/Q33,"") | R36: =IFERROR(변수!R18/R33,"") | S36: =IFERROR(변수!S18/S33,"") | T36: =IFERROR(변수!T18/T33,"") | U36: =T36 | V36: =IFERROR(변수!V18/V33,"") | W36: =IFERROR(변수!W18/W33,"") | X36: =IFERROR(변수!X18/X33,"") | Y36: =IFERROR(변수!Y18/Y33,"") | Z36: =Y36 | AA36: =IFERROR(변수!AA18/AA33,"") | AB36: =IFERROR(변수!AB18/AB33,"") | AC36: =IFERROR(변수!$D$47/AC33,"") | AD36: =IFERROR(변수!$D$47/AD33,"") | AE36: =AD36 | AF36: =IFERROR(변수!$D$47/AF33,"") | AG36: =IFERROR(변수!$D$47/AG33,"") | AH36: =IFERROR(변수!$D$47/AH33,"") | AI36: =IFERROR(변수!$D$47/AI33,"") | AJ36: =AI36 | AK36: =IFERROR(변수!$D$47/AK33,"") | AL36: =IFERROR(변수!$D$47/AL33,"") | AM36: =IFERROR(변수!$D$47/AM33,"") | AN36: =IFERROR(변수!$D$47/AN33,"") | AO36: =AN36
A37: 매출조선기자재 | B37: 사업부 | C37: 억원 | D37: 매출 조선기자재(별도 매출 — 풍력·플랜트 부문 미분리) | E37: 645.58 | G37: 1287.2 | H37: 802.74 | I37: 688.05 | J37: 852.67 | K37: =SUM(G37:J37) | L37: 601.48 | M37: 1101.28 | N37: 755.83 | O37: 1019.8 | P37: =SUM(L37:O37) | Q37: 784.4 | R37: 708.48 | S37: 654.66 | T37: 969.02 | U37: =SUM(Q37:T37) | V37: 900.48 | W37: 881.54 | X37: 805.89 | Y37: 1073.39 | Z37: =SUM(V37:Y37) | AA37: 781.64 | AB37: 833.67 | AC37: =IFERROR(X37*(1+변수!AC39),"") | AD37: =IFERROR(Y37*(1+변수!AD39),"") | AE37: =SUM(AA37:AD37) | AF37: =IFERROR(AA37*(1+변수!AF39),"") | AG37: =IFERROR(AB37*(1+변수!AG39),"") | AH37: =IFERROR(AC37*(1+변수!AH39),"") | AI37: =IFERROR(AD37*(1+변수!AI39),"") | AJ37: =SUM(AF37:AI37) | AK37: =IFERROR(AF37*(1+변수!AK39),"") | AL37: =IFERROR(AG37*(1+변수!AL39),"") | AM37: =IFERROR(AH37*(1+변수!AM39),"") | AN37: =IFERROR(AI37*(1+변수!AN39),"") | AO37: =SUM(AK37:AN37)
A38: OP조선기자재 | B38: 사업부 | C38: 억원 | D38: OP 조선기자재(별도 매출 — 풍력·플랜트 부문 미분리) | E38: -122.1 | G38: -64.47 | H38: 115.68 | I38: 24.32 | J38: 147.02 | K38: =SUM(G38:J38) | L38: -55.41 | M38: 189.21 | N38: -58.23 | O38: 209.24 | P38: =SUM(L38:O38) | Q38: 39.94 | R38: 69.86 | S38: -21.82 | T38: 204.25 | U38: =SUM(Q38:T38) | V38: 170.94 | W38: 78.79 | X38: 86.94 | Y38: 301.24 | Z38: =SUM(V38:Y38) | AA38: 106.39 | AB38: 148.75 | AC38: =IFERROR(AC37*변수!AC40,"") | AD38: =IFERROR(AD37*변수!AD40,"") | AE38: =SUM(AA38:AD38) | AF38: =IFERROR(AF37*변수!AF40,"") | AG38: =IFERROR(AG37*변수!AG40,"") | AH38: =IFERROR(AH37*변수!AH40,"") | AI38: =IFERROR(AI37*변수!AI40,"") | AJ38: =SUM(AF38:AI38) | AK38: =IFERROR(AK37*변수!AK40,"") | AL38: =IFERROR(AL37*변수!AL40,"") | AM38: =IFERROR(AM37*변수!AM40,"") | AN38: =IFERROR(AN37*변수!AN40,"") | AO38: =SUM(AK38:AN38)
A39: 매출종속사 | B39: 사업부 | C39: 억원 | D39: 매출 종속사 일승·동방선기 | E39: 306.45 | G39: 211.01 | H39: 207.75 | I39: 232.53 | J39: 247.67 | K39: =SUM(G39:J39) | L39: 214.07 | M39: 204.64 | N39: 153.64 | O39: 230.45 | P39: =SUM(L39:O39) | Q39: 155.7 | R39: 191.76 | S39: 217.32 | T39: 310.31 | U39: =SUM(Q39:T39) | V39: 184.98 | W39: 204.57 | X39: 253.05 | Y39: 282.95 | Z39: =SUM(V39:Y39) | AA39: 212.76 | AB39: 278.89 | AC39: =IFERROR(X39*(1+변수!AC41),"") | AD39: =IFERROR(Y39*(1+변수!AD41),"") | AE39: =SUM(AA39:AD39) | AF39: =IFERROR(AA39*(1+변수!AF41),"") | AG39: =IFERROR(AB39*(1+변수!AG41),"") | AH39: =IFERROR(AC39*(1+변수!AH41),"") | AI39: =IFERROR(AD39*(1+변수!AI41),"") | AJ39: =SUM(AF39:AI39) | AK39: =IFERROR(AF39*(1+변수!AK41),"") | AL39: =IFERROR(AG39*(1+변수!AL41),"") | AM39: =IFERROR(AH39*(1+변수!AM41),"") | AN39: =IFERROR(AI39*(1+변수!AN41),"") | AO39: =SUM(AK39:AN39)
A40: OP종속사 | B40: 사업부 | C40: 억원 | D40: OP 종속사 일승·동방선기 | E40: 29.26 | G40: -7.71 | H40: 10.59 | I40: 28.43 | J40: 14.97 | K40: =SUM(G40:J40) | L40: 11.48 | M40: 13.17 | N40: 0 | O40: 62.42 | P40: =SUM(L40:O40) | Q40: -1.09 | R40: 17.45 | S40: 34.81 | T40: 58.79 | U40: =SUM(Q40:T40) | V40: 11.24 | W40: 19.79 | X40: 63.72 | Y40: 106.78 | Z40: =SUM(V40:Y40) | AA40: 38.59 | AB40: 98.38 | AC40: =IFERROR(AC39*변수!AC42,"") | AD40: =IFERROR(AD39*변수!AD42,"") | AE40: =SUM(AA40:AD40) | AF40: =IFERROR(AF39*변수!AF42,"") | AG40: =IFERROR(AG39*변수!AG42,"") | AH40: =IFERROR(AH39*변수!AH42,"") | AI40: =IFERROR(AI39*변수!AI42,"") | AJ40: =SUM(AF40:AI40) | AK40: =IFERROR(AK39*변수!AK42,"") | AL40: =IFERROR(AL39*변수!AL42,"") | AM40: =IFERROR(AM39*변수!AM42,"") | AN40: =IFERROR(AN39*변수!AN42,"") | AO40: =SUM(AK40:AN40)
A41: 매출연결조정 | B41: 사업부 | C41: 억원 | D41: 매출 연결조정(세진베트남·내부거래 잔차) | E41: -133.01 | G41: -98.98 | H41: -121.76 | I41: -121.53 | J41: -88.43 | K41: =SUM(G41:J41) | L41: -98.53 | M41: -101 | N41: -89.6 | O41: -144.1 | P41: =SUM(L41:O41) | Q41: -79.32 | R41: -91.86 | S41: -130.47 | T41: -166.24 | U41: =SUM(Q41:T41) | V41: -100.5 | W41: -104.4 | X41: -155.26 | Y41: -199.82 | Z41: =SUM(V41:Y41) | AA41: -121.97 | AB41: -177.58 | AC41: =IFERROR(AC39*변수!AC43,"") | AD41: =IFERROR(AD39*변수!AD43,"") | AE41: =SUM(AA41:AD41) | AF41: =IFERROR(AF39*변수!AF43,"") | AG41: =IFERROR(AG39*변수!AG43,"") | AH41: =IFERROR(AH39*변수!AH43,"") | AI41: =IFERROR(AI39*변수!AI43,"") | AJ41: =SUM(AF41:AI41) | AK41: =IFERROR(AK39*변수!AK43,"") | AL41: =IFERROR(AL39*변수!AL43,"") | AM41: =IFERROR(AM39*변수!AM43,"") | AN41: =IFERROR(AN39*변수!AN43,"") | AO41: =SUM(AK41:AN41)
A42: OP연결조정 | B42: 사업부 | C42: 억원 | D42: OP 연결조정(세진베트남·내부거래 잔차) | E42: -12.09 | G42: 0.25 | H42: -4.6 | I42: -6.75 | J42: -8.22 | K42: =SUM(G42:J42) | L42: -20.27 | M42: 9.57 | N42: -8.25 | O42: -17.38 | P42: =SUM(L42:O42) | Q42: 3.75 | R42: -7.8 | S42: -6.6 | T42: -31.74 | U42: =SUM(Q42:T42) | V42: -4.17 | W42: -10.93 | X42: -29.23 | Y42: -61.22 | Z42: =SUM(V42:Y42) | AA42: -8.59 | AB42: -43.45 | AC42: =IFERROR(AC41*변수!AC44,"") | AD42: =IFERROR(AD41*변수!AD44,"") | AE42: =SUM(AA42:AD42) | AF42: =IFERROR(AF41*변수!AF44,"") | AG42: =IFERROR(AG41*변수!AG44,"") | AH42: =IFERROR(AH41*변수!AH44,"") | AI42: =IFERROR(AI41*변수!AI44,"") | AJ42: =SUM(AF42:AI42) | AK42: =IFERROR(AK41*변수!AK44,"") | AL42: =IFERROR(AL41*변수!AL44,"") | AM42: =IFERROR(AM41*변수!AM44,"") | AN42: =IFERROR(AN41*변수!AN44,"") | AO42: =SUM(AK42:AN42)
B43: 비율(참고)
A44: NPM | C44: % | D44: 지배주주순이익 / 매출액 | E44: =IFERROR(E19/E5,"") | F44: =IFERROR(F19/F5,"") | G44: =IFERROR(G19/G5,"") | H44: =IFERROR(H19/H5,"") | I44: =IFERROR(I19/I5,"") | J44: =IFERROR(J19/J5,"") | K44: =IFERROR(K19/K5,"") | L44: =IFERROR(L19/L5,"") | ... AO44: =IFERROR(AO19/AO5,"")
A45: 매출원가율 | C45: % | D45: 매출원가 / 매출액 | E45: =IFERROR(E6/E5,"") | F45: =IFERROR(F6/F5,"") | G45: =IFERROR(G6/G5,"") | H45: =IFERROR(H6/H5,"") | I45: =IFERROR(I6/I5,"") | J45: =IFERROR(J6/J5,"") | K45: =IFERROR(K6/K5,"") | L45: =IFERROR(L6/L5,"") | ... AO45: =IFERROR(AO6/AO5,"")
A46: 판관비율 | C46: % | D46: 판관비 / 매출액 | E46: =IFERROR(E8/E5,"") | F46: =IFERROR(F8/F5,"") | G46: =IFERROR(G8/G5,"") | H46: =IFERROR(H8/H5,"") | I46: =IFERROR(I8/I5,"") | J46: =IFERROR(J8/J5,"") | K46: =IFERROR(K8/K5,"") | L46: =IFERROR(L8/L5,"") | ... AO46: =IFERROR(AO8/AO5,"")

Sheet 분기
C1: 이름: 분기H — subQ 를 이름으로 VLOOKUP(억원) | E1: 4Q21 | F1: 1Q22 | G1: 2Q22 | H1: 3Q22 | I1: 4Q22 | J1: 1Q23 | K1: 2Q23 | L1: 3Q23 | M1: 4Q23 | N1: 1Q24 | O1: 2Q24 | P1: 3Q24 | Q1: 4Q24 | R1: 1Q25 | S1: 2Q25 | T1: 3Q25 | U1: 4Q25 | V1: 1Q26 | W1: 2Q26 | X1: 3Q26 | Y1: 4Q26 | Z1: 1Q27 | AA1: 2Q27 | AB1: 3Q27 | AC1: 4Q27 | AD1: 1Q28 | AE1: 2Q28 | AF1: 3Q28 | AG1: 4Q28
C2: 종가: | D2: =변수!D47
C3: 기준일: | D3: 20261014 | E3: 1 | F3: 2 | G3: 3 | H3: 4 | I3: 5 | J3: 6 | K3: 7 | L3: 8 | M3: 9 | N3: 10 | O3: 11 | P3: 12 | Q3: 13 | R3: 14 | S3: 15 | T3: 16 | U3: 17 | V3: 18 | W3: 19 | X3: 20 | Y3: 21 | Z3: 22 | AA3: 23 | AB3: 24 | AC3: 25 | AD3: 26 | AE3: 27 | AF3: 28 | AG3: 29
E4: 2021.12 | F4: 2022.03 | G4: 2022.06 | H4: 2022.09 | I4: 2022.12 | J4: 2023.03 | K4: 2023.06 | L4: 2023.09 | M4: 2023.12 | N4: 2024.03 | O4: 2024.06 | P4: 2024.09 | Q4: 2024.12 | R4: 2025.03 | S4: 2025.06 | T4: 2025.09 | U4: 2025.12 | V4: 2026.03 | W4: 2026.06 | X4: 2026.09 | Y4: 2026.12 | Z4: 2027.03 | AA4: 2027.06 | AB4: 2027.09 | AC4: 2027.12 | AD4: 2028.03 | AE4: 2028.06 | AF4: 2028.09 | AG4: 2028.12
A5: 매출액 | D5: 매출액 | E5: =IFERROR(VLOOKUP($A5,subQ,MATCH(E$1,SUBQH,0),0),"") | F5: =IFERROR(VLOOKUP($A5,subQ,MATCH(F$1,SUBQH,0),0),"") | G5: =IFERROR(VLOOKUP($A5,subQ,MATCH(G$1,SUBQH,0),0),"") | H5: =IFERROR(VLOOKUP($A5,subQ,MATCH(H$1,SUBQH,0),0),"") | I5: =IFERROR(VLOOKUP($A5,subQ,MATCH(I$1,SUBQH,0),0),"") | J5: =IFERROR(VLOOKUP($A5,subQ,MATCH(J$1,SUBQH,0),0),"") | K5: =IFERROR(VLOOKUP($A5,subQ,MATCH(K$1,SUBQH,0),0),"") | L5: =IFERROR(VLOOKUP($A5,subQ,MATCH(L$1,SUBQH,0),0),"") | ... AG5: =IFERROR(VLOOKUP($A5,subQ,MATCH(AG$1,SUBQH,0),0),"")
A6: 매출원가 | D6: 매출원가 | E6: =IFERROR(VLOOKUP($A6,subQ,MATCH(E$1,SUBQH,0),0),"") | F6: =IFERROR(VLOOKUP($A6,subQ,MATCH(F$1,SUBQH,0),0),"") | G6: =IFERROR(VLOOKUP($A6,subQ,MATCH(G$1,SUBQH,0),0),"") | H6: =IFERROR(VLOOKUP($A6,subQ,MATCH(H$1,SUBQH,0),0),"") | I6: =IFERROR(VLOOKUP($A6,subQ,MATCH(I$1,SUBQH,0),0),"") | J6: =IFERROR(VLOOKUP($A6,subQ,MATCH(J$1,SUBQH,0),0),"") | K6: =IFERROR(VLOOKUP($A6,subQ,MATCH(K$1,SUBQH,0),0),"") | L6: =IFERROR(VLOOKUP($A6,subQ,MATCH(L$1,SUBQH,0),0),"") | ... AG6: =IFERROR(VLOOKUP($A6,subQ,MATCH(AG$1,SUBQH,0),0),"")
A7: 매출총이익 | D7: 매출총이익 | E7: =IFERROR(VLOOKUP($A7,subQ,MATCH(E$1,SUBQH,0),0),"") | F7: =IFERROR(VLOOKUP($A7,subQ,MATCH(F$1,SUBQH,0),0),"") | G7: =IFERROR(VLOOKUP($A7,subQ,MATCH(G$1,SUBQH,0),0),"") | H7: =IFERROR(VLOOKUP($A7,subQ,MATCH(H$1,SUBQH,0),0),"") | I7: =IFERROR(VLOOKUP($A7,subQ,MATCH(I$1,SUBQH,0),0),"") | J7: =IFERROR(VLOOKUP($A7,subQ,MATCH(J$1,SUBQH,0),0),"") | K7: =IFERROR(VLOOKUP($A7,subQ,MATCH(K$1,SUBQH,0),0),"") | L7: =IFERROR(VLOOKUP($A7,subQ,MATCH(L$1,SUBQH,0),0),"") | ... AG7: =IFERROR(VLOOKUP($A7,subQ,MATCH(AG$1,SUBQH,0),0),"")
A8: 판관비 | D8: 판매비와관리비 | E8: =IFERROR(VLOOKUP($A8,subQ,MATCH(E$1,SUBQH,0),0),"") | F8: =IFERROR(VLOOKUP($A8,subQ,MATCH(F$1,SUBQH,0),0),"") | G8: =IFERROR(VLOOKUP($A8,subQ,MATCH(G$1,SUBQH,0),0),"") | H8: =IFERROR(VLOOKUP($A8,subQ,MATCH(H$1,SUBQH,0),0),"") | I8: =IFERROR(VLOOKUP($A8,subQ,MATCH(I$1,SUBQH,0),0),"") | J8: =IFERROR(VLOOKUP($A8,subQ,MATCH(J$1,SUBQH,0),0),"") | K8: =IFERROR(VLOOKUP($A8,subQ,MATCH(K$1,SUBQH,0),0),"") | L8: =IFERROR(VLOOKUP($A8,subQ,MATCH(L$1,SUBQH,0),0),"") | ... AG8: =IFERROR(VLOOKUP($A8,subQ,MATCH(AG$1,SUBQH,0),0),"")
A9: 영업이익 | D9: 영업이익 | E9: =IFERROR(VLOOKUP($A9,subQ,MATCH(E$1,SUBQH,0),0),"") | F9: =IFERROR(VLOOKUP($A9,subQ,MATCH(F$1,SUBQH,0),0),"") | G9: =IFERROR(VLOOKUP($A9,subQ,MATCH(G$1,SUBQH,0),0),"") | H9: =IFERROR(VLOOKUP($A9,subQ,MATCH(H$1,SUBQH,0),0),"") | I9: =IFERROR(VLOOKUP($A9,subQ,MATCH(I$1,SUBQH,0),0),"") | J9: =IFERROR(VLOOKUP($A9,subQ,MATCH(J$1,SUBQH,0),0),"") | K9: =IFERROR(VLOOKUP($A9,subQ,MATCH(K$1,SUBQH,0),0),"") | L9: =IFERROR(VLOOKUP($A9,subQ,MATCH(L$1,SUBQH,0),0),"") | ... AG9: =IFERROR(VLOOKUP($A9,subQ,MATCH(AG$1,SUBQH,0),0),"")
A10: OPM | D10: 영업이익률 | E10: =IFERROR(VLOOKUP($A10,subQ,MATCH(E$1,SUBQH,0),0),"") | F10: =IFERROR(VLOOKUP($A10,subQ,MATCH(F$1,SUBQH,0),0),"") | G10: =IFERROR(VLOOKUP($A10,subQ,MATCH(G$1,SUBQH,0),0),"") | H10: =IFERROR(VLOOKUP($A10,subQ,MATCH(H$1,SUBQH,0),0),"") | I10: =IFERROR(VLOOKUP($A10,subQ,MATCH(I$1,SUBQH,0),0),"") | J10: =IFERROR(VLOOKUP($A10,subQ,MATCH(J$1,SUBQH,0),0),"") | K10: =IFERROR(VLOOKUP($A10,subQ,MATCH(K$1,SUBQH,0),0),"") | L10: =IFERROR(VLOOKUP($A10,subQ,MATCH(L$1,SUBQH,0),0),"") | ... AG10: =IFERROR(VLOOKUP($A10,subQ,MATCH(AG$1,SUBQH,0),0),"")
A11: 금융손익 | D11: 금융손익(이자·환 포함) | E11: =IFERROR(VLOOKUP($A11,subQ,MATCH(E$1,SUBQH,0),0),"") | F11: =IFERROR(VLOOKUP($A11,subQ,MATCH(F$1,SUBQH,0),0),"") | G11: =IFERROR(VLOOKUP($A11,subQ,MATCH(G$1,SUBQH,0),0),"") | H11: =IFERROR(VLOOKUP($A11,subQ,MATCH(H$1,SUBQH,0),0),"") | I11: =IFERROR(VLOOKUP($A11,subQ,MATCH(I$1,SUBQH,0),0),"") | J11: =IFERROR(VLOOKUP($A11,subQ,MATCH(J$1,SUBQH,0),0),"") | K11: =IFERROR(VLOOKUP($A11,subQ,MATCH(K$1,SUBQH,0),0),"") | L11: =IFERROR(VLOOKUP($A11,subQ,MATCH(L$1,SUBQH,0),0),"") | ... AG11: =IFERROR(VLOOKUP($A11,subQ,MATCH(AG$1,SUBQH,0),0),"")
A12: 이자손익 | D12: 이자손익(이자수익 − 이자비용) | E12: =IFERROR(VLOOKUP($A12,subQ,MATCH(E$1,SUBQH,0),0),"") | F12: =IFERROR(VLOOKUP($A12,subQ,MATCH(F$1,SUBQH,0),0),"") | G12: =IFERROR(VLOOKUP($A12,subQ,MATCH(G$1,SUBQH,0),0),"") | H12: =IFERROR(VLOOKUP($A12,subQ,MATCH(H$1,SUBQH,0),0),"") | I12: =IFERROR(VLOOKUP($A12,subQ,MATCH(I$1,SUBQH,0),0),"") | J12: =IFERROR(VLOOKUP($A12,subQ,MATCH(J$1,SUBQH,0),0),"") | K12: =IFERROR(VLOOKUP($A12,subQ,MATCH(K$1,SUBQH,0),0),"") | L12: =IFERROR(VLOOKUP($A12,subQ,MATCH(L$1,SUBQH,0),0),"") | ... AG12: =IFERROR(VLOOKUP($A12,subQ,MATCH(AG$1,SUBQH,0),0),"")
A13: 외환손익 | D13: 외환손익(실적만; 추정 환효과는 환관련손익) | E13: =IFERROR(VLOOKUP($A13,subQ,MATCH(E$1,SUBQH,0),0),"") | F13: =IFERROR(VLOOKUP($A13,subQ,MATCH(F$1,SUBQH,0),0),"") | G13: =IFERROR(VLOOKUP($A13,subQ,MATCH(G$1,SUBQH,0),0),"") | H13: =IFERROR(VLOOKUP($A13,subQ,MATCH(H$1,SUBQH,0),0),"") | I13: =IFERROR(VLOOKUP($A13,subQ,MATCH(I$1,SUBQH,0),0),"") | J13: =IFERROR(VLOOKUP($A13,subQ,MATCH(J$1,SUBQH,0),0),"") | K13: =IFERROR(VLOOKUP($A13,subQ,MATCH(K$1,SUBQH,0),0),"") | L13: =IFERROR(VLOOKUP($A13,subQ,MATCH(L$1,SUBQH,0),0),"") | ... AG13: =IFERROR(VLOOKUP($A13,subQ,MATCH(AG$1,SUBQH,0),0),"")
A14: 기타영업외손익 | D14: 기타영업외손익 | E14: =IFERROR(VLOOKUP($A14,subQ,MATCH(E$1,SUBQH,0),0),"") | F14: =IFERROR(VLOOKUP($A14,subQ,MATCH(F$1,SUBQH,0),0),"") | G14: =IFERROR(VLOOKUP($A14,subQ,MATCH(G$1,SUBQH,0),0),"") | H14: =IFERROR(VLOOKUP($A14,subQ,MATCH(H$1,SUBQH,0),0),"") | I14: =IFERROR(VLOOKUP($A14,subQ,MATCH(I$1,SUBQH,0),0),"") | J14: =IFERROR(VLOOKUP($A14,subQ,MATCH(J$1,SUBQH,0),0),"") | K14: =IFERROR(VLOOKUP($A14,subQ,MATCH(K$1,SUBQH,0),0),"") | L14: =IFERROR(VLOOKUP($A14,subQ,MATCH(L$1,SUBQH,0),0),"") | ... AG14: =IFERROR(VLOOKUP($A14,subQ,MATCH(AG$1,SUBQH,0),0),"")
A15: 지분법손익 | D15: 지분법손익 | E15: =IFERROR(VLOOKUP($A15,subQ,MATCH(E$1,SUBQH,0),0),"") | F15: =IFERROR(VLOOKUP($A15,subQ,MATCH(F$1,SUBQH,0),0),"") | G15: =IFERROR(VLOOKUP($A15,subQ,MATCH(G$1,SUBQH,0),0),"") | H15: =IFERROR(VLOOKUP($A15,subQ,MATCH(H$1,SUBQH,0),0),"") | I15: =IFERROR(VLOOKUP($A15,subQ,MATCH(I$1,SUBQH,0),0),"") | J15: =IFERROR(VLOOKUP($A15,subQ,MATCH(J$1,SUBQH,0),0),"") | K15: =IFERROR(VLOOKUP($A15,subQ,MATCH(K$1,SUBQH,0),0),"") | L15: =IFERROR(VLOOKUP($A15,subQ,MATCH(L$1,SUBQH,0),0),"") | ... AG15: =IFERROR(VLOOKUP($A15,subQ,MATCH(AG$1,SUBQH,0),0),"")
A16: 세전이익 | D16: 법인세비용차감전이익 | E16: =IFERROR(VLOOKUP($A16,subQ,MATCH(E$1,SUBQH,0),0),"") | F16: =IFERROR(VLOOKUP($A16,subQ,MATCH(F$1,SUBQH,0),0),"") | G16: =IFERROR(VLOOKUP($A16,subQ,MATCH(G$1,SUBQH,0),0),"") | H16: =IFERROR(VLOOKUP($A16,subQ,MATCH(H$1,SUBQH,0),0),"") | I16: =IFERROR(VLOOKUP($A16,subQ,MATCH(I$1,SUBQH,0),0),"") | J16: =IFERROR(VLOOKUP($A16,subQ,MATCH(J$1,SUBQH,0),0),"") | K16: =IFERROR(VLOOKUP($A16,subQ,MATCH(K$1,SUBQH,0),0),"") | L16: =IFERROR(VLOOKUP($A16,subQ,MATCH(L$1,SUBQH,0),0),"") | ... AG16: =IFERROR(VLOOKUP($A16,subQ,MATCH(AG$1,SUBQH,0),0),"")
... A43: NPM | D43: NPM | E43: =IFERROR(VLOOKUP($A43,subQ,MATCH(E$1,SUBQH,0),0),"") | F43: =IFERROR(VLOOKUP($A43,subQ,MATCH(F$1,SUBQH,0),0),"") | G43: =IFERROR(VLOOKUP($A43,subQ,MATCH(G$1,SUBQH,0),0),"") | H43: =IFERROR(VLOOKUP($A43,subQ,MATCH(H$1,SUBQH,0),0),"") | I43: =IFERROR(VLOOKUP($A43,subQ,MATCH(I$1,SUBQH,0),0),"") | J43: =IFERROR(VLOOKUP($A43,subQ,MATCH(J$1,SUBQH,0),0),"") | K43: =IFERROR(VLOOKUP($A43,subQ,MATCH(K$1,SUBQH,0),0),"") | L43: =IFERROR(VLOOKUP($A43,subQ,MATCH(L$1,SUBQH,0),0),"") | ... AG43: =IFERROR(VLOOKUP($A43,subQ,MATCH(AG$1,SUBQH,0),0),"")
A44: 매출액 YoY | D44: 매출액 YoY | I44: =IFERROR(I5/E5-1,"") | J44: =IFERROR(J5/F5-1,"") | K44: =IFERROR(K5/G5-1,"") | L44: =IFERROR(L5/H5-1,"") | M44: =IFERROR(M5/I5-1,"") | N44: =IFERROR(N5/J5-1,"") | O44: =IFERROR(O5/K5-1,"") | P44: =IFERROR(P5/L5-1,"") | ... AG44: =IFERROR(AG5/AC5-1,"")
A45: 영업이익 YoY | D45: 영업이익 YoY | I45: =IFERROR(I9/E9-1,"") | J45: =IFERROR(J9/F9-1,"") | K45: =IFERROR(K9/G9-1,"") | L45: =IFERROR(L9/H9-1,"") | M45: =IFERROR(M9/I9-1,"") | N45: =IFERROR(N9/J9-1,"") | O45: =IFERROR(O9/K9-1,"") | P45: =IFERROR(P9/L9-1,"") | ... AG45: =IFERROR(AG9/AC9-1,"")
A46: 지배주주순이익 YoY | D46: 지배주주순이익 YoY | I46: =IFERROR(I19/E19-1,"") | J46: =IFERROR(J19/F19-1,"") | K46: =IFERROR(K19/G19-1,"") | L46: =IFERROR(L19/H19-1,"") | M46: =IFERROR(M19/I19-1,"") | N46: =IFERROR(N19/J19-1,"") | O46: =IFERROR(O19/K19-1,"") | P46: =IFERROR(P19/L19-1,"") | ... AG46: =IFERROR(AG19/AC19-1,"")

Sheet 연간예상
C1: 이름: 연간예상H — subQ 를 이름으로 VLOOKUP(억원) | E1: 2021 | F1: 2022 | G1: 2023 | H1: 2024 | I1: 2025 | J1: 2026 | K1: 2027 | L1: 2028
C2: 종가: | D2: =변수!D47
C3: 기준일: | D3: 20261014 | E3: 1 | F3: 2 | G3: 3 | H3: 4 | I3: 5 | J3: 6 | K3: 7 | L3: 8
E4: 2021.12A | F4: 2022.12A | G4: 2023.12A | H4: 2024.12A | I4: 2025.12A | J4: 2026.12A | K4: 2027.12A | L4: 2028.12A
A5: 매출액 | D5: 매출액 | E5: =IFERROR(VLOOKUP($A5,subQ,MATCH(E$1,SUBQH,0),0),"") | F5: =IFERROR(VLOOKUP($A5,subQ,MATCH(F$1,SUBQH,0),0),"") | G5: =IFERROR(VLOOKUP($A5,subQ,MATCH(G$1,SUBQH,0),0),"") | H5: =IFERROR(VLOOKUP($A5,subQ,MATCH(H$1,SUBQH,0),0),"") | I5: =IFERROR(VLOOKUP($A5,subQ,MATCH(I$1,SUBQH,0),0),"") | J5: =IFERROR(VLOOKUP($A5,subQ,MATCH(J$1,SUBQH,0),0),"") | K5: =IFERROR(VLOOKUP($A5,subQ,MATCH(K$1,SUBQH,0),0),"") | L5: =IFERROR(VLOOKUP($A5,subQ,MATCH(L$1,SUBQH,0),0),"")
A6: 매출원가 | D6: 매출원가 | E6: =IFERROR(VLOOKUP($A6,subQ,MATCH(E$1,SUBQH,0),0),"") | F6: =IFERROR(VLOOKUP($A6,subQ,MATCH(F$1,SUBQH,0),0),"") | G6: =IFERROR(VLOOKUP($A6,subQ,MATCH(G$1,SUBQH,0),0),"") | H6: =IFERROR(VLOOKUP($A6,subQ,MATCH(H$1,SUBQH,0),0),"") | I6: =IFERROR(VLOOKUP($A6,subQ,MATCH(I$1,SUBQH,0),0),"") | J6: =IFERROR(VLOOKUP($A6,subQ,MATCH(J$1,SUBQH,0),0),"") | K6: =IFERROR(VLOOKUP($A6,subQ,MATCH(K$1,SUBQH,0),0),"") | L6: =IFERROR(VLOOKUP($A6,subQ,MATCH(L$1,SUBQH,0),0),"")
A7: 매출총이익 | D7: 매출총이익 | E7: =IFERROR(VLOOKUP($A7,subQ,MATCH(E$1,SUBQH,0),0),"") | F7: =IFERROR(VLOOKUP($A7,subQ,MATCH(F$1,SUBQH,0),0),"") | G7: =IFERROR(VLOOKUP($A7,subQ,MATCH(G$1,SUBQH,0),0),"") | H7: =IFERROR(VLOOKUP($A7,subQ,MATCH(H$1,SUBQH,0),0),"") | I7: =IFERROR(VLOOKUP($A7,subQ,MATCH(I$1,SUBQH,0),0),"") | J7: =IFERROR(VLOOKUP($A7,subQ,MATCH(J$1,SUBQH,0),0),"") | K7: =IFERROR(VLOOKUP($A7,subQ,MATCH(K$1,SUBQH,0),0),"") | L7: =IFERROR(VLOOKUP($A7,subQ,MATCH(L$1,SUBQH,0),0),"")
A8: 판관비 | D8: 판매비와관리비 | E8: =IFERROR(VLOOKUP($A8,subQ,MATCH(E$1,SUBQH,0),0),"") | F8: =IFERROR(VLOOKUP($A8,subQ,MATCH(F$1,SUBQH,0),0),"") | G8: =IFERROR(VLOOKUP($A8,subQ,MATCH(G$1,SUBQH,0),0),"") | H8: =IFERROR(VLOOKUP($A8,subQ,MATCH(H$1,SUBQH,0),0),"") | I8: =IFERROR(VLOOKUP($A8,subQ,MATCH(I$1,SUBQH,0),0),"") | J8: =IFERROR(VLOOKUP($A8,subQ,MATCH(J$1,SUBQH,0),0),"") | K8: =IFERROR(VLOOKUP($A8,subQ,MATCH(K$1,SUBQH,0),0),"") | L8: =IFERROR(VLOOKUP($A8,subQ,MATCH(L$1,SUBQH,0),0),"")
A9: 영업이익 | D9: 영업이익 | E9: =IFERROR(VLOOKUP($A9,subQ,MATCH(E$1,SUBQH,0),0),"") | F9: =IFERROR(VLOOKUP($A9,subQ,MATCH(F$1,SUBQH,0),0),"") | G9: =IFERROR(VLOOKUP($A9,subQ,MATCH(G$1,SUBQH,0),0),"") | H9: =IFERROR(VLOOKUP($A9,subQ,MATCH(H$1,SUBQH,0),0),"") | I9: =IFERROR(VLOOKUP($A9,subQ,MATCH(I$1,SUBQH,0),0),"") | J9: =IFERROR(VLOOKUP($A9,subQ,MATCH(J$1,SUBQH,0),0),"") | K9: =IFERROR(VLOOKUP($A9,subQ,MATCH(K$1,SUBQH,0),0),"") | L9: =IFERROR(VLOOKUP($A9,subQ,MATCH(L$1,SUBQH,0),0),"")
A10: OPM | D10: 영업이익률 | E10: =IFERROR(VLOOKUP($A10,subQ,MATCH(E$1,SUBQH,0),0),"") | F10: =IFERROR(VLOOKUP($A10,subQ,MATCH(F$1,SUBQH,0),0),"") | G10: =IFERROR(VLOOKUP($A10,subQ,MATCH(G$1,SUBQH,0),0),"") | H10: =IFERROR(VLOOKUP($A10,subQ,MATCH(H$1,SUBQH,0),0),"") | I10: =IFERROR(VLOOKUP($A10,subQ,MATCH(I$1,SUBQH,0),0),"") | J10: =IFERROR(VLOOKUP($A10,subQ,MATCH(J$1,SUBQH,0),0),"") | K10: =IFERROR(VLOOKUP($A10,subQ,MATCH(K$1,SUBQH,0),0),"") | L10: =IFERROR(VLOOKUP($A10,subQ,MATCH(L$1,SUBQH,0),0),"")
A11: 금융손익 | D11: 금융손익(이자·환 포함) | E11: =IFERROR(VLOOKUP($A11,subQ,MATCH(E$1,SUBQH,0),0),"") | F11: =IFERROR(VLOOKUP($A11,subQ,MATCH(F$1,SUBQH,0),0),"") | G11: =IFERROR(VLOOKUP($A11,subQ,MATCH(G$1,SUBQH,0),0),"") | H11: =IFERROR(VLOOKUP($A11,subQ,MATCH(H$1,SUBQH,0),0),"") | I11: =IFERROR(VLOOKUP($A11,subQ,MATCH(I$1,SUBQH,0),0),"") | J11: =IFERROR(VLOOKUP($A11,subQ,MATCH(J$1,SUBQH,0),0),"") | K11: =IFERROR(VLOOKUP($A11,subQ,MATCH(K$1,SUBQH,0),0),"") | L11: =IFERROR(VLOOKUP($A11,subQ,MATCH(L$1,SUBQH,0),0),"")
A12: 이자손익 | D12: 이자손익(이자수익 − 이자비용) | E12: =IFERROR(VLOOKUP($A12,subQ,MATCH(E$1,SUBQH,0),0),"") | F12: =IFERROR(VLOOKUP($A12,subQ,MATCH(F$1,SUBQH,0),0),"") | G12: =IFERROR(VLOOKUP($A12,subQ,MATCH(G$1,SUBQH,0),0),"") | H12: =IFERROR(VLOOKUP($A12,subQ,MATCH(H$1,SUBQH,0),0),"") | I12: =IFERROR(VLOOKUP($A12,subQ,MATCH(I$1,SUBQH,0),0),"") | J12: =IFERROR(VLOOKUP($A12,subQ,MATCH(J$1,SUBQH,0),0),"") | K12: =IFERROR(VLOOKUP($A12,subQ,MATCH(K$1,SUBQH,0),0),"") | L12: =IFERROR(VLOOKUP($A12,subQ,MATCH(L$1,SUBQH,0),0),"")
A13: 외환손익 | D13: 외환손익(실적만; 추정 환효과는 환관련손익) | E13: =IFERROR(VLOOKUP($A13,subQ,MATCH(E$1,SUBQH,0),0),"") | F13: =IFERROR(VLOOKUP($A13,subQ,MATCH(F$1,SUBQH,0),0),"") | G13: =IFERROR(VLOOKUP($A13,subQ,MATCH(G$1,SUBQH,0),0),"") | H13: =IFERROR(VLOOKUP($A13,subQ,MATCH(H$1,SUBQH,0),0),"") | I13: =IFERROR(VLOOKUP($A13,subQ,MATCH(I$1,SUBQH,0),0),"") | J13: =IFERROR(VLOOKUP($A13,subQ,MATCH(J$1,SUBQH,0),0),"") | K13: =IFERROR(VLOOKUP($A13,subQ,MATCH(K$1,SUBQH,0),0),"") | L13: =IFERROR(VLOOKUP($A13,subQ,MATCH(L$1,SUBQH,0),0),"")
A14: 기타영업외손익 | D14: 기타영업외손익 | E14: =IFERROR(VLOOKUP($A14,subQ,MATCH(E$1,SUBQH,0),0),"") | F14: =IFERROR(VLOOKUP($A14,subQ,MATCH(F$1,SUBQH,0),0),"") | G14: =IFERROR(VLOOKUP($A14,subQ,MATCH(G$1,SUBQH,0),0),"") | H14: =IFERROR(VLOOKUP($A14,subQ,MATCH(H$1,SUBQH,0),0),"") | I14: =IFERROR(VLOOKUP($A14,subQ,MATCH(I$1,SUBQH,0),0),"") | J14: =IFERROR(VLOOKUP($A14,subQ,MATCH(J$1,SUBQH,0),0),"") | K14: =IFERROR(VLOOKUP($A14,subQ,MATCH(K$1,SUBQH,0),0),"") | L14: =IFERROR(VLOOKUP($A14,subQ,MATCH(L$1,SUBQH,0),0),"")
A15: 지분법손익 | D15: 지분법손익 | E15: =IFERROR(VLOOKUP($A15,subQ,MATCH(E$1,SUBQH,0),0),"") | F15: =IFERROR(VLOOKUP($A15,subQ,MATCH(F$1,SUBQH,0),0),"") | G15: =IFERROR(VLOOKUP($A15,subQ,MATCH(G$1,SUBQH,0),0),"") | H15: =IFERROR(VLOOKUP($A15,subQ,MATCH(H$1,SUBQH,0),0),"") | I15: =IFERROR(VLOOKUP($A15,subQ,MATCH(I$1,SUBQH,0),0),"") | J15: =IFERROR(VLOOKUP($A15,subQ,MATCH(J$1,SUBQH,0),0),"") | K15: =IFERROR(VLOOKUP($A15,subQ,MATCH(K$1,SUBQH,0),0),"") | L15: =IFERROR(VLOOKUP($A15,subQ,MATCH(L$1,SUBQH,0),0),"")
A16: 세전이익 | D16: 법인세비용차감전이익 | E16: =IFERROR(VLOOKUP($A16,subQ,MATCH(E$1,SUBQH,0),0),"") | F16: =IFERROR(VLOOKUP($A16,subQ,MATCH(F$1,SUBQH,0),0),"") | G16: =IFERROR(VLOOKUP($A16,subQ,MATCH(G$1,SUBQH,0),0),"") | H16: =IFERROR(VLOOKUP($A16,subQ,MATCH(H$1,SUBQH,0),0),"") | I16: =IFERROR(VLOOKUP($A16,subQ,MATCH(I$1,SUBQH,0),0),"") | J16: =IFERROR(VLOOKUP($A16,subQ,MATCH(J$1,SUBQH,0),0),"") | K16: =IFERROR(VLOOKUP($A16,subQ,MATCH(K$1,SUBQH,0),0),"") | L16: =IFERROR(VLOOKUP($A16,subQ,MATCH(L$1,SUBQH,0),0),"")
... A43: NPM | D43: NPM | E43: =IFERROR(VLOOKUP($A43,subQ,MATCH(E$1,SUBQH,0),0),"") | F43: =IFERROR(VLOOKUP($A43,subQ,MATCH(F$1,SUBQH,0),0),"") | G43: =IFERROR(VLOOKUP($A43,subQ,MATCH(G$1,SUBQH,0),0),"") | H43: =IFERROR(VLOOKUP($A43,subQ,MATCH(H$1,SUBQH,0),0),"") | I43: =IFERROR(VLOOKUP($A43,subQ,MATCH(I$1,SUBQH,0),0),"") | J43: =IFERROR(VLOOKUP($A43,subQ,MATCH(J$1,SUBQH,0),0),"") | K43: =IFERROR(VLOOKUP($A43,subQ,MATCH(K$1,SUBQH,0),0),"") | L43: =IFERROR(VLOOKUP($A43,subQ,MATCH(L$1,SUBQH,0),0),"")
A44: 매출액 YoY | D44: 매출액 YoY | F44: =IFERROR(F5/E5-1,"") | G44: =IFERROR(G5/F5-1,"") | H44: =IFERROR(H5/G5-1,"") | I44: =IFERROR(I5/H5-1,"") | J44: =IFERROR(J5/I5-1,"") | K44: =IFERROR(K5/J5-1,"") | L44: =IFERROR(L5/K5-1,"")
A45: 영업이익 YoY | D45: 영업이익 YoY | F45: =IFERROR(F9/E9-1,"") | G45: =IFERROR(G9/F9-1,"") | H45: =IFERROR(H9/G9-1,"") | I45: =IFERROR(I9/H9-1,"") | J45: =IFERROR(J9/I9-1,"") | K45: =IFERROR(K9/J9-1,"") | L45: =IFERROR(L9/K9-1,"")
A46: 지배주주순이익 YoY | D46: 지배주주순이익 YoY | F46: =IFERROR(F19/E19-1,"") | G46: =IFERROR(G19/F19-1,"") | H46: =IFERROR(H19/G19-1,"") | I46: =IFERROR(I19/H19-1,"") | J46: =IFERROR(J19/I19-1,"") | K46: =IFERROR(K19/J19-1,"") | L46: =IFERROR(L19/K19-1,"")

Sheet TP
B1: 종가 | C1: =변수!D47
B2: 기준일 | C2: =변수!D48
B3: 모델 산출값 — 목표주가·추천 아님. 밴드·COE 는 변수 시트 3절의 가정
C5: FY | D5: 2025 | E5: 2026 | F5: 2027 | G5: 2028
D6: A | E6: E | F6: E | G6: E
C7: EPS(원) | D7: =IFERROR(VLOOKUP("EPS",subQ,MATCH(D$5,SUBQH,0),0),"") | E7: =IFERROR(VLOOKUP("EPS",subQ,MATCH(E$5,SUBQH,0),0),"") | F7: =IFERROR(VLOOKUP("EPS",subQ,MATCH(F$5,SUBQH,0),0),"") | G7: =IFERROR(VLOOKUP("EPS",subQ,MATCH(G$5,SUBQH,0),0),"")
C8: BPS(원) | D8: =IFERROR(VLOOKUP("BPS",subQ,MATCH(D$5,SUBQH,0),0),"") | E8: =IFERROR(VLOOKUP("BPS",subQ,MATCH(E$5,SUBQH,0),0),"") | F8: =IFERROR(VLOOKUP("BPS",subQ,MATCH(F$5,SUBQH,0),0),"") | G8: =IFERROR(VLOOKUP("BPS",subQ,MATCH(G$5,SUBQH,0),0),"")
C9: 지배주주순이익(억원) | D9: =IFERROR(VLOOKUP("지배주주순이익",subQ,MATCH(D$5,SUBQH,0),0),"") | E9: =IFERROR(VLOOKUP("지배주주순이익",subQ,MATCH(E$5,SUBQH,0),0),"") | F9: =IFERROR(VLOOKUP("지배주주순이익",subQ,MATCH(F$5,SUBQH,0),0),"") | G9: =IFERROR(VLOOKUP("지배주주순이익",subQ,MATCH(G$5,SUBQH,0),0),"")
C10: 영업이익(억원) | D10: =IFERROR(VLOOKUP("영업이익",subQ,MATCH(D$5,SUBQH,0),0),"") | E10: =IFERROR(VLOOKUP("영업이익",subQ,MATCH(E$5,SUBQH,0),0),"") | F10: =IFERROR(VLOOKUP("영업이익",subQ,MATCH(F$5,SUBQH,0),0),"") | G10: =IFERROR(VLOOKUP("영업이익",subQ,MATCH(G$5,SUBQH,0),0),"")
C11: ROE(EPS/기초BPS) | E11: =IFERROR(E7/D8,"") | F11: =IFERROR(F7/E8,"") | G11: =IFERROR(G7/F8,"")
B13: PER
C14: 12M fwd EPS | D14: =IFERROR(E7*변수!D53+F7*(1-변수!D53),"")
C15: 적정가치 @PER_lo | D15: =변수!D50 | E15: =IFERROR(ROUND($D$14*D15,-2),"") | F15: =IFERROR(E15/$C$1-1,"") | G15: 배 · 원 · 종가 대비
C16: 적정가치 @PER_mid | D16: =변수!D51 | E16: =IFERROR(ROUND($D$14*D16,-2),"") | F16: =IFERROR(E16/$C$1-1,"") | G16: 배 · 원 · 종가 대비
C17: 적정가치 @PER_hi | D17: =변수!D52 | E17: =IFERROR(ROUND($D$14*D17,-2),"") | F17: =IFERROR(E17/$C$1-1,"") | G17: 배 · 원 · 종가 대비
C18: 현재 PER(종가/12M fwd EPS) | D18: =IFERROR($C$1/$D$14,"")
B20: PBR
C21: 최근 BPS(마지막 실적 분기) | D21: =IFERROR(VLOOKUP("BPS",subQ,MATCH("2Q26",SUBQH,0),0),"")
C22: ROE fwd(12M fwd EPS / BPS) | D22: =IFERROR($D$14/$D$21,"")
C23: COE | D23: =변수!D49
C24: 적정 PBR = ROE/COE | D24: =IFERROR(D22/D23,"")
C25: 적정가치(PBR) = BPS × 적정PBR | D25: =IFERROR(ROUND(D21*D24,-2),"") | E25: =IFERROR(D25/$C$1-1,"")
C26: 현재 PBR(종가/BPS) | D26: =IFERROR($C$1/D21,"")
B28: 모델 json valuation(참고)
C29: eps_fwd12m | D29: 743
C30: bps_latest | D30: 4321.6
C31: per_now | D31: 11.72
C32: pbr_now | D32: 2.02
C33: roe_fwd | D33: 0.1719
C34: fair_pbr | D34: 1.91
C35: fair_value_pbr | D35: 8300
C36: ev_ebitda
C37: note | D37: 모델 산출값 — 목표주가·추천 아님

Sheet 외화
C1: 이름: 외화QH — 환율 QoQ · 외화 순노출 × Δ기말환율 | E1: 4Q21 | F1: 1Q22 | G1: 2Q22 | H1: 3Q22 | I1: 4Q22 | J1: 1Q23 | K1: 2Q23 | L1: 3Q23 | M1: 4Q23 | N1: 1Q24 | O1: 2Q24 | P1: 3Q24 | Q1: 4Q24 | R1: 1Q25 | S1: 2Q25 | T1: 3Q25 | U1: 4Q25 | V1: 1Q26 | W1: 2Q26 | X1: 3Q26 | Y1: 4Q26 | Z1: 1Q27 | AA1: 2Q27 | AB1: 3Q27 | AC1: 4Q27 | AD1: 1Q28 | AE1: 2Q28 | AF1: 3Q28 | AG1: 4Q28
E3: 1 | F3: 2 | G3: 3 | H3: 4 | I3: 5 | J3: 6 | K3: 7 | L3: 8 | M3: 9 | N3: 10 | O3: 11 | P3: 12 | Q3: 13 | R3: 14 | S3: 15 | T3: 16 | U3: 17 | V3: 18 | W3: 19 | X3: 20 | Y3: 21 | Z3: 22 | AA3: 23 | AB3: 24 | AC3: 25 | AD3: 26 | AE3: 27 | AF3: 28 | AG3: 29
E4: 2021.12 | F4: 2022.03 | G4: 2022.06 | H4: 2022.09 | I4: 2022.12 | J4: 2023.03 | K4: 2023.06 | L4: 2023.09 | M4: 2023.12 | N4: 2024.03 | O4: 2024.06 | P4: 2024.09 | Q4: 2024.12 | R4: 2025.03 | S4: 2025.06 | T4: 2025.09 | U4: 2025.12 | V4: 2026.03 | W4: 2026.06 | X4: 2026.09 | Y4: 2026.12 | Z4: 2027.03 | AA4: 2027.06 | AB4: 2027.09 | AC4: 2027.12 | AD4: 2028.03 | AE4: 2028.06 | AF4: 2028.09 | AG4: 2028.12
D5: 원/달러(평균) | E5: =IFERROR(VLOOKUP($D5,환율,MATCH(E$1,변수H,0),0),"") | F5: =IFERROR(VLOOKUP($D5,환율,MATCH(F$1,변수H,0),0),"") | G5: =IFERROR(VLOOKUP($D5,환율,MATCH(G$1,변수H,0),0),"") | H5: =IFERROR(VLOOKUP($D5,환율,MATCH(H$1,변수H,0),0),"") | I5: =IFERROR(VLOOKUP($D5,환율,MATCH(I$1,변수H,0),0),"") | J5: =IFERROR(VLOOKUP($D5,환율,MATCH(J$1,변수H,0),0),"") | K5: =IFERROR(VLOOKUP($D5,환율,MATCH(K$1,변수H,0),0),"") | L5: =IFERROR(VLOOKUP($D5,환율,MATCH(L$1,변수H,0),0),"") | ... AG5: =IFERROR(VLOOKUP($D5,환율,MATCH(AG$1,변수H,0),0),"")
A6: 원/달러(평균) QoQ | F6: =IFERROR(F5/E5-1,"") | G6: =IFERROR(G5/F5-1,"") | H6: =IFERROR(H5/G5-1,"") | I6: =IFERROR(I5/H5-1,"") | J6: =IFERROR(J5/I5-1,"") | K6: =IFERROR(K5/J5-1,"") | L6: =IFERROR(L5/K5-1,"") | M6: =IFERROR(M5/L5-1,"") | ... AG6: =IFERROR(AG5/AF5-1,"")
D7: 원/달러(기말) | E7: =IFERROR(VLOOKUP($D7,환율,MATCH(E$1,변수H,0),0),"") | F7: =IFERROR(VLOOKUP($D7,환율,MATCH(F$1,변수H,0),0),"") | G7: =IFERROR(VLOOKUP($D7,환율,MATCH(G$1,변수H,0),0),"") | H7: =IFERROR(VLOOKUP($D7,환율,MATCH(H$1,변수H,0),0),"") | I7: =IFERROR(VLOOKUP($D7,환율,MATCH(I$1,변수H,0),0),"") | J7: =IFERROR(VLOOKUP($D7,환율,MATCH(J$1,변수H,0),0),"") | K7: =IFERROR(VLOOKUP($D7,환율,MATCH(K$1,변수H,0),0),"") | L7: =IFERROR(VLOOKUP($D7,환율,MATCH(L$1,변수H,0),0),"") | ... AG7: =IFERROR(VLOOKUP($D7,환율,MATCH(AG$1,변수H,0),0),"")
A8: 원/달러(기말) QoQ | F8: =IFERROR(F7/E7-1,"") | G8: =IFERROR(G7/F7-1,"") | H8: =IFERROR(H7/G7-1,"") | I8: =IFERROR(I7/H7-1,"") | J8: =IFERROR(J7/I7-1,"") | K8: =IFERROR(K7/J7-1,"") | L8: =IFERROR(L7/K7-1,"") | M8: =IFERROR(M7/L7-1,"") | ... AG8: =IFERROR(AG7/AF7-1,"")
D9: W/Euro(평균) | E9: =IFERROR(VLOOKUP($D9,환율,MATCH(E$1,변수H,0),0),"") | F9: =IFERROR(VLOOKUP($D9,환율,MATCH(F$1,변수H,0),0),"") | G9: =IFERROR(VLOOKUP($D9,환율,MATCH(G$1,변수H,0),0),"") | H9: =IFERROR(VLOOKUP($D9,환율,MATCH(H$1,변수H,0),0),"") | I9: =IFERROR(VLOOKUP($D9,환율,MATCH(I$1,변수H,0),0),"") | J9: =IFERROR(VLOOKUP($D9,환율,MATCH(J$1,변수H,0),0),"") | K9: =IFERROR(VLOOKUP($D9,환율,MATCH(K$1,변수H,0),0),"") | L9: =IFERROR(VLOOKUP($D9,환율,MATCH(L$1,변수H,0),0),"") | ... AG9: =IFERROR(VLOOKUP($D9,환율,MATCH(AG$1,변수H,0),0),"")
A10: W/Euro(평균) QoQ | F10: =IFERROR(F9/E9-1,"") | G10: =IFERROR(G9/F9-1,"") | H10: =IFERROR(H9/G9-1,"") | I10: =IFERROR(I9/H9-1,"") | J10: =IFERROR(J9/I9-1,"") | K10: =IFERROR(K9/J9-1,"") | L10: =IFERROR(L9/K9-1,"") | M10: =IFERROR(M9/L9-1,"") | ... AG10: =IFERROR(AG9/AF9-1,"")
D11: W/Euro(기말) | E11: =IFERROR(VLOOKUP($D11,환율,MATCH(E$1,변수H,0),0),"") | F11: =IFERROR(VLOOKUP($D11,환율,MATCH(F$1,변수H,0),0),"") | G11: =IFERROR(VLOOKUP($D11,환율,MATCH(G$1,변수H,0),0),"") | H11: =IFERROR(VLOOKUP($D11,환율,MATCH(H$1,변수H,0),0),"") | I11: =IFERROR(VLOOKUP($D11,환율,MATCH(I$1,변수H,0),0),"") | J11: =IFERROR(VLOOKUP($D11,환율,MATCH(J$1,변수H,0),0),"") | K11: =IFERROR(VLOOKUP($D11,환율,MATCH(K$1,변수H,0),0),"") | L11: =IFERROR(VLOOKUP($D11,환율,MATCH(L$1,변수H,0),0),"") | ... AG11: =IFERROR(VLOOKUP($D11,환율,MATCH(AG$1,변수H,0),0),"")
A12: W/Euro(기말) QoQ | F12: =IFERROR(F11/E11-1,"") | G12: =IFERROR(G11/F11-1,"") | H12: =IFERROR(H11/G11-1,"") | I12: =IFERROR(I11/H11-1,"") | J12: =IFERROR(J11/I11-1,"") | K12: =IFERROR(K11/J11-1,"") | L12: =IFERROR(L11/K11-1,"") | M12: =IFERROR(M11/L11-1,"") | ... AG12: =IFERROR(AG11/AF11-1,"")
D13: 원/100Y(기말) | E13: =IFERROR(VLOOKUP($D13,환율,MATCH(E$1,변수H,0),0),"") | F13: =IFERROR(VLOOKUP($D13,환율,MATCH(F$1,변수H,0),0),"") | G13: =IFERROR(VLOOKUP($D13,환율,MATCH(G$1,변수H,0),0),"") | H13: =IFERROR(VLOOKUP($D13,환율,MATCH(H$1,변수H,0),0),"") | I13: =IFERROR(VLOOKUP($D13,환율,MATCH(I$1,변수H,0),0),"") | J13: =IFERROR(VLOOKUP($D13,환율,MATCH(J$1,변수H,0),0),"") | K13: =IFERROR(VLOOKUP($D13,환율,MATCH(K$1,변수H,0),0),"") | L13: =IFERROR(VLOOKUP($D13,환율,MATCH(L$1,변수H,0),0),"") | ... AG13: =IFERROR(VLOOKUP($D13,환율,MATCH(AG$1,변수H,0),0),"")
A14: 원/100Y(기말) QoQ | F14: =IFERROR(F13/E13-1,"") | G14: =IFERROR(G13/F13-1,"") | H14: =IFERROR(H13/G13-1,"") | I14: =IFERROR(I13/H13-1,"") | J14: =IFERROR(J13/I13-1,"") | K14: =IFERROR(K13/J13-1,"") | L14: =IFERROR(L13/K13-1,"") | M14: =IFERROR(M13/L13-1,"") | ... AG14: =IFERROR(AG13/AF13-1,"")
A16: 외화순노출 | C16: 외화 순노출(백만$) | D16: =변수!D60 | E16: 외화 순노출 × Δ기말환율 (외화 시트 방식)
A17: 환관련손익추정 | C17: 환관련손익 추정(억원) = 순노출 × Δ원/달러(기말) / 100 | F17: =IFERROR($D$16*(F7-E7)/100,"") | G17: =IFERROR($D$16*(G7-F7)/100,"") | H17: =IFERROR($D$16*(H7-G7)/100,"") | I17: =IFERROR($D$16*(I7-H7)/100,"") | J17: =IFERROR($D$16*(J7-I7)/100,"") | K17: =IFERROR($D$16*(K7-J7)/100,"") | L17: =IFERROR($D$16*(L7-K7)/100,"") | M17: =IFERROR($D$16*(M7-L7)/100,"") | ... AG17: =IFERROR($D$16*(AG7-AF7)/100,"")
A18: fx_pnl.by_q | C18: 모델 fx_pnl.by_q(억원, 참고)
C19: 외화 순노출 미공시(face) → 0 + 표기
