Workbook
Name 변수H: 변수!$C$1:$AO$1
Name 환율: 변수!$C$6:$AO$13
Name BS연결H: BS연결!$C$1:$AO$1
Name BS연결: BS연결!$C$5:$AO$103
Name BS별도H: BS별도!$C$1:$AO$1
Name BS별도: BS별도!$C$5:$AO$92
Name SUBQH: subQ!$A$1:$AO$1
Name subQ: subQ!$A$5:$AO$42

Sheet README
A1: STX엔진(077970) 실적 모델 — ARGUS 한국조선
A2: 기준 분기 2026Q2 · 마지막 실적 2026Q2 · 생성 2026-10-26
A3: 모든 수치는 모델 산출값(DART 공개 재무제표 + 우리 추정)이다 — 목표주가·투자 추천 아님. 참고용 · 투자조언 아님.
A5: 시트
A6: 변수 가정 시계열. 환율 8행(ECB via frankfurter — L2 fx.json; 추정 분기 = 노란 가정), 추정 드라이버(노란 셀 = 모델값에서 역산한 가정, 바꾸면 재계산; 연녹 셀 = 3절 스칼라 참조 수식), 3절 스칼라 가정(세율·판관비율·지배주주비중·이자율·종가·PER 밴드·COE·외화 순노출·헤지비율)
A7: BS연결/BS별도 FnGuide 계정명 × 기간 값 덤프(백만원). 행1 분기라벨, 행4 YYYY.MM / YYYY.12A. 이름정의 BS연결H·BS연결(계정명 C열부터)
A8: subQ 분기 서브모델(억원 = 백만원/100). 확정 행: =IFERROR(VLOOKUP($D행,BS연결,MATCH(E$1,BS연결H,0),0)/100,"") 추정 행: 변수 시트 가정 셀 참조 수식. 외환손익·파생상품손익은 BS 계정 합·차, 기타금융손익은 잔차, OPM·EPS·BPS·PER·PBR 은 파생 수식
A9: SLS 선표(조선사만, sls json 있을 때): 요약 행(sls 저장값) + 계약별 스케줄(백만$) × (헤지비율 × 헤지환율 + (1−헤지비율) × 건조시점 환율[변수 원/달러(평균)]) → 원화 수식 블록 → 합계 행이 subQ 매출조선에 연결
A10: 시나리오 신규수주 보수/기준/낙관(forecast_panel 패널, 모델에 scenarios 가 있을 때만): 매출액·영업이익 = subQ 기준값 ± (시나리오 신규 − base 신규) × OPM. base 만 subQ 행에 포함, 나머지는 합산 안 함
A11: 분기/연간예상 subQ 를 이름(A열 key)으로 VLOOKUP 한 보고서 표(억원)
A12: TP PER 밴드 × 12M fwd EPS, PBR = ROE/COE × BPS — 모델 산출값 구간, 목표주가·추천 아님
A13: 외화 환율 QoQ, 외화 순노출 × Δ기말환율 → 환관련손익 추정
... A34: 백테스트: {"freeze": "2025Q2", "horizon": 4, "revenue_wape_pct": 20.9, "op_wape_pct": 48.8, "n": 4, "note": "단일 회사 4분기 — 통계 아님", "driver_at_freeze": "customer_yard_revenue_weighted", "selection_oos_at_freeze": {"freeze": "2024Q2", "n": 4, "wape_link": null, "wape_trend": 9.2, "adopted": "undetermined", "decision": "undetermined", "note": "현재 채택 조합(suppliers_mentions·시차 3·ma4·창 12)을 동결 데이터로 재적합할 수 없음(짝·고객 모델 부족) → 연동 WAPE 없음, undetermined(유의성 조건만으로 채택)"}, "frozen_inputs": "fin(연결/별도)·고객 조선사 모델·지주 자회사 모델은 2025Q2 까지의 분기만; 선표는 체결일 ≤ 2025Q2 말일 계약(원장 최신 금액·코호트 등급, 환산 없음); 잔고는 yards_cache 2025Q2; 시세·환율 forward·prices·forecast_panel 신규수주 미사용. 고객 가중치(suppliers.json 언급 비중)와 합병 체인링크는 현재 지식; 고객 연동 채택은 동결 모델 안에서도 자기 la−4분기 OOS 규칙(selection_oos_at_freeze)", "detail": [{"q": "2025Q3", "rev_pred": 2341.43, "rev_act": 1920.66, "op_pred": 140.4, "op_act": 154.26}, {"q": "2025Q4", "rev_pred": 3267.26, "rev_act": 2444.82, "op_pred": 195.91, "op_act": 53.68}, {"q": "2026Q1", "rev_pred": 1903.72, "rev_act": 1890.11, "op_pred": 114.15, "op_act": 175.04}, {"q": "2026Q2", "rev_pred": 2628.38, "rev_act": 2129.9, "op_pred": 157.6, "op_act": 249.61}]}

Sheet 변수
C1: 이름: 변수H | E1: 4Q21 | F1: 2021 | G1: 1Q22 | H1: 2Q22 | I1: 3Q22 | J1: 4Q22 | K1: 2022 | L1: 1Q23 | M1: 2Q23 | N1: 3Q23 | O1: 4Q23 | P1: 2023 | Q1: 1Q24 | R1: 2Q24 | S1: 3Q24 | T1: 4Q24 | U1: 2024 | V1: 1Q25 | W1: 2Q25 | X1: 3Q25 | Y1: 4Q25 | Z1: 2025 | AA1: 1Q26 | AB1: 2Q26 | AC1: 3Q26 | AD1: 4Q26 | AE1: 2026 | AF1: 1Q27 | AG1: 2Q27 | AH1: 3Q27 | AI1: 4Q27 | AJ1: 2027 | AK1: 1Q28 | AL1: 2Q28 | AM1: 3Q28 | AN1: 4Q28 | AO1: 2028
A2: 가정 시계열 — 노란 셀은 추정 가정(모델값에서 역산), 연녹 셀은 3절 스칼라 참조 수식. 바꾸면 subQ·분기·연간예상·TP·시나리오가 재계산됩니다.
E3: 1 | F3: 2 | G3: 3 | H3: 4 | I3: 5 | J3: 6 | K3: 7 | L3: 8 | M3: 9 | N3: 10 | O3: 11 | P3: 12 | Q3: 13 | R3: 14 | S3: 15 | T3: 16 | U3: 17 | V3: 18 | W3: 19 | X3: 20 | Y3: 21 | Z3: 22 | AA3: 23 | AB3: 24 | AC3: 25 | AD3: 26 | AE3: 27 | AF3: 28 | AG3: 29 | AH3: 30 | AI3: 31 | AJ3: 32 | AK3: 33 | AL3: 34 | AM3: 35 | AN3: 36 | AO3: 37
E4: 2021.12 | F4: 2021.12A | G4: 2022.03 | H4: 2022.06 | I4: 2022.09 | J4: 2022.12 | K4: 2022.12A | L4: 2023.03 | M4: 2023.06 | N4: 2023.09 | O4: 2023.12 | P4: 2023.12A | Q4: 2024.03 | R4: 2024.06 | S4: 2024.09 | T4: 2024.12 | U4: 2024.12A | V4: 2025.03 | W4: 2025.06 | X4: 2025.09 | Y4: 2025.12 | Z4: 2025.12A | AA4: 2026.03 | AB4: 2026.06 | AC4: 2026.09 | AD4: 2026.12 | AE4: 2026.12A | AF4: 2027.03 | AG4: 2027.06 | AH4: 2027.09 | AI4: 2027.12 | AJ4: 2027.12A | AK4: 2028.03 | AL4: 2028.06 | AM4: 2028.09 | AN4: 2028.12 | AO4: 2028.12A
B5: 1. FX | C5: 이름: 환율
A6: USDKRW_avg | C6: 원/달러(평균) | E6: 1183.5 | F6: 1145.51 | G6: 1205.78 | H6: 1262.09 | I6: 1341.93 | J6: 1360.12 | K6: 1292.98 | L6: 1276.95 | M6: 1315.69 | N6: 1313.62 | O6: 1322.01 | P6: 1306.85 | Q6: 1330.14 | R6: 1371.28 | S6: 1356.22 | T6: 1396.3 | U6: 1363.53 | V6: 1452.28 | W6: 1398.52 | X6: 1386.95 | Y6: 1449.19 | Z6: 1421.52 | AA6: 1466.12 | AB6: 1501.75 | AC6: 1418.75 | AD6: 1337.49 | AE6: 1451.19 | AF6: 1324.45 | AG6: 1324.45 | AH6: 1324.45 | AI6: 1324.45 | AK6: 1324.45 | AL6: 1324.45 | AM6: 1324.45 | AN6: 1324.45
A7: USDKRW_end | C7: 원/달러(기말) | E7: 1188.75 | F7: 1188.75 | G7: 1213.74 | H7: 1301.24 | I7: 1436.9 | J7: 1260.16 | K7: 1260.16 | L7: 1305.99 | M7: 1321.44 | N7: 1345.35 | O7: 1297.43 | P7: 1297.43 | Q7: 1349.25 | R7: 1377.73 | S7: 1312.17 | T7: 1474.78 | U7: 1474.78 | V7: 1474.54 | W7: 1355.13 | X7: 1403.67 | Y7: 1444.2 | Z7: 1444.2 | AA7: 1524.8 | AB7: 1550.89 | AC7: 1355.4 | AD7: 1324.45 | AE7: 1324.45 | AF7: 1324.45 | AG7: 1324.45 | AH7: 1324.45 | AI7: 1324.45 | AK7: 1324.45 | AL7: 1324.45 | AM7: 1324.45 | AN7: 1324.45
A8: JPY100KRW_avg | C8: 원/100Y(평균) | E8: 1041.02 | F8: 1042.74 | G8: 1036.79 | H8: 972.23 | I8: 970.61 | J8: 961.03 | K8: 985.1 | L8: 964.89 | M8: 957.36 | N8: 909 | O8: 893.22 | P8: 931.11 | Q8: 896.29 | R8: 880.14 | S8: 909.35 | T8: 917.25 | U8: 900.92 | V8: 952.59 | W8: 967.92 | X8: 940.32 | Y8: 940.77 | Z8: 950.17 | AA8: 934.39 | AB8: 942.16 | AC8: 890.41 | AD8: 846.51 | AE8: 915.57 | AF8: 844.67 | AG8: 844.67 | AH8: 844.67 | AI8: 844.67 | AK8: 844.67 | AL8: 844.67 | AM8: 844.67 | AN8: 844.67
A9: JPY100KRW_end | C9: 원/100Y(기말) | E9: 1032.62 | F9: 1032.62 | G9: 996.83 | H9: 954.9 | I9: 993.29 | J9: 955.54 | K9: 955.54 | L9: 980.62 | M9: 913.67 | N9: 901.47 | O9: 917.04 | P9: 917.04 | Q9: 892.42 | R9: 857.76 | S9: 919.21 | T9: 939.65 | U9: 939.65 | V9: 986.84 | W9: 938.85 | X9: 948.49 | Y9: 921.81 | Z9: 921.81 | AA9: 955.99 | AB9: 954.75 | AC9: 863.31 | AD9: 844.67 | AE9: 844.67 | AF9: 844.67 | AG9: 844.67 | AH9: 844.67 | AI9: 844.67 | AK9: 844.67 | AL9: 844.67 | AM9: 844.67 | AN9: 844.67
A10: EURKRW_avg | C10: W/Euro(평균) | E10: 1353.32 | F10: 1354.06 | G10: 1352.29 | H10: 1343.31 | I10: 1350.63 | J10: 1386.07 | K10: 1358.07 | L10: 1369.93 | M10: 1432.41 | N10: 1429.41 | O10: 1420.91 | P10: 1412.88 | Q10: 1444.21 | R10: 1476.42 | S10: 1489.3 | T10: 1490.78 | U10: 1475.4 | V10: 1528.33 | W10: 1585.13 | X10: 1620.04 | Y10: 1686.02 | Z10: 1605.45 | AA10: 1715.47 | AB10: 1746.09 | AC10: 1631.97 | AD10: 1500.06 | AE10: 1680.5 | AF10: 1482.45 | AG10: 1482.45 | AH10: 1482.45 | AI10: 1482.45 | AK10: 1482.45 | AL10: 1482.45 | AM10: 1482.45 | AN10: 1482.45
A11: EURKRW_end | C11: W/Euro(기말) | E11: 1346.38 | F11: 1346.38 | G11: 1347.37 | H11: 1351.6 | I11: 1400.62 | J11: 1344.08 | K11: 1344.08 | L11: 1420.26 | M11: 1435.88 | N11: 1425.26 | O11: 1433.66 | P11: 1433.66 | Q11: 1458.68 | R11: 1474.86 | S11: 1469.1 | T11: 1532.14 | U11: 1532.14 | V11: 1594.72 | W11: 1588.22 | X11: 1648.04 | Y11: 1696.94 | Z11: 1696.94 | AA11: 1753.21 | AB11: 1767.09 | AC11: 1539.06 | AD11: 1482.45 | AE11: 1482.45 | AF11: 1482.45 | AG11: 1482.45 | AH11: 1482.45 | AI11: 1482.45 | AK11: 1482.45 | AL11: 1482.45 | AM11: 1482.45 | AN11: 1482.45
A12: CNYKRW_avg | C12: 원/중국원(평균) | E12: 185.14 | F12: 177.65 | G12: 189.93 | H12: 190.76 | I12: 195.79 | J12: 191.09 | K12: 191.93 | L12: 186.59 | M12: 187.45 | N12: 181.28 | O12: 182.86 | P12: 184.52 | Q12: 185.04 | R12: 189.35 | S12: 189.24 | T12: 194.24 | U12: 189.49 | V12: 199.63 | W12: 193.41 | X12: 193.79 | Y12: 204.38 | Z12: 197.8 | AA12: 211.75 | AB12: 220.8 | AC12: 210.43 | AD12: 199.88 | AE12: 213.06 | AF12: 198.56 | AG12: 198.56 | AH12: 198.56 | AI12: 198.56 | AK12: 198.56 | AL12: 198.56 | AM12: 198.56 | AN12: 198.56
A13: CNYKRW_end | C13: 원/중국원(기말) | E13: 187.13 | F13: 187.13 | G13: 191.38 | H13: 194.13 | I13: 201.92 | J13: 182.67 | K13: 182.67 | L13: 189.97 | M13: 181.8 | N13: 184.26 | O13: 182.61 | P13: 182.61 | Q13: 186.66 | R13: 189.7 | S13: 187.12 | T13: 202.04 | U13: 202.04 | V13: 203.3 | W13: 189.14 | X13: 197.16 | Y13: 206.28 | Z13: 206.28 | AA13: 220.97 | AB13: 228.56 | AC13: 202.16 | AD13: 198.56 | AE13: 198.56 | AF13: 198.56 | AG13: 198.56 | AH13: 198.56 | AI13: 198.56 | AK13: 198.56 | AL13: 198.56 | AM13: 198.56 | AN13: 198.56
B14: 1b. 종가
A15: price_close_end | C15: 종가(기말) | E15: 9600 | G15: 12950 | H15: 14500 | I15: 12950 | J15: 13450 | L15: 12780 | M15: 14220 | N15: 13070 | O15: 11850 | Q15: 12970 | R15: 17100 | S15: 18120 | T15: 20100 | V15: 20800 | W15: 21500 | X15: 39550 | Y15: 34000 | AA15: 30650 | AB15: 29300 | AC15: 22200 | AD15: 15780
A16: price_high | C16: 종가(최고) | E16: 12900 | G16: 17500 | H16: 16550 | I16: 19500 | J16: 17350 | L16: 14840 | M16: 16080 | N16: 16180 | O16: 13510 | Q16: 13900 | R16: 18660 | S16: 24400 | T16: 22500 | V16: 31650 | W16: 27000 | X16: 49800 | Y16: 41850 | AA16: 40500 | AB16: 67700 | AC16: 31550 | AD16: 23800
A17: price_low | C17: 종가(최저) | E17: 8370 | G17: 8960 | H17: 11900 | I17: 12000 | J17: 11600 | L17: 12250 | M17: 12400 | N17: 12600 | O17: 11000 | Q17: 11450 | R17: 12310 | S17: 12880 | T17: 15150 | V17: 19150 | W17: 18310 | X17: 19910 | Y17: 28700 | AA17: 25100 | AB17: 26200 | AC17: 18830 | AD17: 15750
A18: price_avg | C18: 종가(평균) | E18: 10078.9 | G18: 11801.9 | H18: 13670.2 | I18: 14700 | J18: 13228.2 | L18: 13458.5 | M18: 13401.6 | N18: 14184.8 | O18: 11945.7 | Q18: 12403.1 | R18: 14312.3 | S18: 17817.6 | T18: 19656.2 | V18: 24307.6 | W18: 23137.2 | X18: 32170.8 | Y18: 35330.5 | AA18: 34270.3 | AB18: 41308.2 | AC18: 24844.4 | AD18: 19355.6
B20: 2. 추정 드라이버 | C20: 실적 열 = subQ 실현값(수식), 추정 열 = 가정(노란 = 모델값 역산, 연녹 = 3절 스칼라 참조)
A21: drv:매출액 | B21: yoy | C21: 매출액 YoY | J21: =IFERROR(subQ!J5/subQ!E5-1,"") | L21: =IFERROR(subQ!L5/subQ!G5-1,"") | M21: =IFERROR(subQ!M5/subQ!H5-1,"") | N21: =IFERROR(subQ!N5/subQ!I5-1,"") | O21: =IFERROR(subQ!O5/subQ!J5-1,"") | Q21: =IFERROR(subQ!Q5/subQ!L5-1,"") | R21: =IFERROR(subQ!R5/subQ!M5-1,"") | S21: =IFERROR(subQ!S5/subQ!N5-1,"") | T21: =IFERROR(subQ!T5/subQ!O5-1,"") | V21: =IFERROR(subQ!V5/subQ!Q5-1,"") | W21: =IFERROR(subQ!W5/subQ!R5-1,"") | X21: =IFERROR(subQ!X5/subQ!S5-1,"") | Y21: =IFERROR(subQ!Y5/subQ!T5-1,"") | AA21: =IFERROR(subQ!AA5/subQ!V5-1,"") | AB21: =IFERROR(subQ!AB5/subQ!W5-1,"") | AC21: 0.096806521 | AD21: 0.096802736 | AF21: 0.096806501 | AG21: 0.096803645 | AH21: 0.048400496 | AI21: 0.048402375 | AK21: 0.048401412 | AL21: 0.048401596 | AM21: 0.024201399 | AN21: 0.024202585
A22: drv:판관비 | B22: ratio | C22: 판관비율(/매출) | E22: =IFERROR(subQ!E8/subQ!E5,"") | F22: =IFERROR(subQ!F8/subQ!F5,"") | G22: =IFERROR(subQ!G8/subQ!G5,"") | H22: =IFERROR(subQ!H8/subQ!H5,"") | I22: =IFERROR(subQ!I8/subQ!I5,"") | J22: =IFERROR(subQ!J8/subQ!J5,"") | K22: =IFERROR(subQ!K8/subQ!K5,"") | L22: =IFERROR(subQ!L8/subQ!L5,"") | ... AB22: =IFERROR(subQ!AB8/subQ!AB5,"") | AC22: =$D$51 | AD22: =$D$51 | AE22: =IFERROR(subQ!AE8/subQ!AE5,"") | AF22: =$D$51 | AG22: =$D$51 | AH22: =$D$51 | AI22: =$D$51 | AJ22: =IFERROR(subQ!AJ8/subQ!AJ5,"") | AK22: =$D$51 | AL22: =$D$51 | AM22: =$D$51 | AN22: =$D$51 | AO22: =IFERROR(subQ!AO8/subQ!AO5,"")
A23: drv:영업이익 | B23: ratio | C23: 영업이익률(OPM) | E23: =IFERROR(subQ!E9/subQ!E5,"") | F23: =IFERROR(subQ!F9/subQ!F5,"") | G23: =IFERROR(subQ!G9/subQ!G5,"") | H23: =IFERROR(subQ!H9/subQ!H5,"") | I23: =IFERROR(subQ!I9/subQ!I5,"") | J23: =IFERROR(subQ!J9/subQ!J5,"") | K23: =IFERROR(subQ!K9/subQ!K5,"") | L23: =IFERROR(subQ!L9/subQ!L5,"") | ... AB23: =IFERROR(subQ!AB9/subQ!AB5,"") | AC23: 0.086462007 | AD23: 0.086459716 | AE23: =IFERROR(subQ!AE9/subQ!AE5,"") | AF23: 0.086460725 | AG23: 0.08646108 | AH23: 0.086459442 | AI23: 0.086462702 | AJ23: =IFERROR(subQ!AJ9/subQ!AJ5,"") | AK23: 0.08646281 | AL23: 0.08646265 | AM23: 0.086458886 | AN23: 0.086461687 | AO23: =IFERROR(subQ!AO9/subQ!AO5,"")
A24: drv:외환손익 | B24: abs | C24: 외환손익 (가정, 억원) | E24: =subQ!E13 | F24: =subQ!F13 | G24: =subQ!G13 | H24: =subQ!H13 | I24: =subQ!I13 | J24: =subQ!J13 | K24: =subQ!K13 | L24: =subQ!L13 | ... AB24: =subQ!AB13 | AC24: 0 | AD24: 0 | AE24: =subQ!AE13 | AF24: 0 | AG24: 0 | AH24: 0 | AI24: 0 | AJ24: =subQ!AJ13 | AK24: 0 | AL24: 0 | AM24: 0 | AN24: 0 | AO24: =subQ!AO13
A25: drv:파생상품손익 | B25: abs | C25: 파생상품손익 (가정, 억원) | E25: =subQ!E14 | F25: =subQ!F14 | G25: =subQ!G14 | H25: =subQ!H14 | I25: =subQ!I14 | J25: =subQ!J14 | K25: =subQ!K14 | L25: =subQ!L14 | ... AB25: =subQ!AB14 | AC25: 0 | AD25: 0 | AE25: =subQ!AE14 | AF25: 0 | AG25: 0 | AH25: 0 | AI25: 0 | AJ25: =subQ!AJ14 | AK25: 0 | AL25: 0 | AM25: 0 | AN25: 0 | AO25: =subQ!AO14
A26: drv:기타금융손익 | B26: abs | C26: 기타금융손익 (가정, 억원) | E26: =subQ!E15 | F26: =subQ!F15 | G26: =subQ!G15 | H26: =subQ!H15 | I26: =subQ!I15 | J26: =subQ!J15 | K26: =subQ!K15 | L26: =subQ!L15 | ... AB26: =subQ!AB15 | AC26: 0 | AD26: 0 | AE26: =subQ!AE15 | AF26: 0 | AG26: 0 | AH26: 0 | AI26: 0 | AJ26: =subQ!AJ15 | AK26: 0 | AL26: 0 | AM26: 0 | AN26: 0 | AO26: =subQ!AO15
A27: drv:기타영업외손익 | B27: abs | C27: 기타영업외손익 (가정, 억원) | E27: =subQ!E16 | F27: =subQ!F16 | G27: =subQ!G16 | H27: =subQ!H16 | I27: =subQ!I16 | J27: =subQ!J16 | K27: =subQ!K16 | L27: =subQ!L16 | ... AB27: =subQ!AB16 | AC27: 0 | AD27: 0 | AE27: =subQ!AE16 | AF27: 0 | AG27: 0 | AH27: 0 | AI27: 0 | AJ27: =subQ!AJ16 | AK27: 0 | AL27: 0 | AM27: 0 | AN27: 0 | AO27: =subQ!AO16
A28: drv:법인세비용 | B28: tax | C28: 법인세율(/세전) — 법인세 = MAX(세전,0) × 분기별 세율(이월결손 램프, assumptions.tax_schedule) | E28: =IFERROR(subQ!E18/subQ!E17,"") | F28: =IFERROR(subQ!F18/subQ!F17,"") | G28: =IFERROR(subQ!G18/subQ!G17,"") | H28: =IFERROR(subQ!H18/subQ!H17,"") | I28: =IFERROR(subQ!I18/subQ!I17,"") | J28: =IFERROR(subQ!J18/subQ!J17,"") | K28: =IFERROR(subQ!K18/subQ!K17,"") | L28: =IFERROR(subQ!L18/subQ!L17,"") | ... AB28: =IFERROR(subQ!AB18/subQ!AB17,"") | AC28: 0 | AD28: 0 | AE28: =IFERROR(subQ!AE18/subQ!AE17,"") | AF28: 0.027501426 | AG28: 0.055004409 | AH28: 0.08249227 | AI28: 0.11000713 | AJ28: =IFERROR(subQ!AJ18/subQ!AJ17,"") | AK28: 0.13751833 | AL28: 0.16500128 | AM28: 0.19247443 | AN28: 0.21999658 | AO28: =IFERROR(subQ!AO18/subQ!AO17,"")
A29: drv:지배주주순이익 | B29: ratio | C29: 지배주주 비중(/당기순이익) | E29: =IFERROR(subQ!E20/subQ!E19,"") | F29: =IFERROR(subQ!F20/subQ!F19,"") | G29: =IFERROR(subQ!G20/subQ!G19,"") | H29: =IFERROR(subQ!H20/subQ!H19,"") | I29: =IFERROR(subQ!I20/subQ!I19,"") | J29: =IFERROR(subQ!J20/subQ!J19,"") | K29: =IFERROR(subQ!K20/subQ!K19,"") | L29: =IFERROR(subQ!L20/subQ!L19,"") | ... AB29: =IFERROR(subQ!AB20/subQ!AB19,"") | AC29: =$D$52 | AD29: =$D$52 | AE29: =IFERROR(subQ!AE20/subQ!AE19,"") | AF29: =$D$52 | AG29: =$D$52 | AH29: =$D$52 | AI29: =$D$52 | AJ29: =IFERROR(subQ!AJ20/subQ!AJ19,"") | AK29: =$D$52 | AL29: =$D$52 | AM29: =$D$52 | AN29: =$D$52 | AO29: =IFERROR(subQ!AO20/subQ!AO19,"")
A30: drv:부채총계 | B30: qoq | C30: 부채총계 QoQ | G30: =IFERROR(subQ!G22/subQ!E22-1,"") | H30: =IFERROR(subQ!H22/subQ!G22-1,"") | I30: =IFERROR(subQ!I22/subQ!H22-1,"") | J30: =IFERROR(subQ!J22/subQ!I22-1,"") | L30: =IFERROR(subQ!L22/subQ!J22-1,"") | M30: =IFERROR(subQ!M22/subQ!L22-1,"") | N30: =IFERROR(subQ!N22/subQ!M22-1,"") | O30: =IFERROR(subQ!O22/subQ!N22-1,"") | Q30: =IFERROR(subQ!Q22/subQ!O22-1,"") | R30: =IFERROR(subQ!R22/subQ!Q22-1,"") | S30: =IFERROR(subQ!S22/subQ!R22-1,"") | T30: =IFERROR(subQ!T22/subQ!S22-1,"") | V30: =IFERROR(subQ!V22/subQ!T22-1,"") | W30: =IFERROR(subQ!W22/subQ!V22-1,"") | X30: =IFERROR(subQ!X22/subQ!W22-1,"") | Y30: =IFERROR(subQ!Y22/subQ!X22-1,"") | AA30: =IFERROR(subQ!AA22/subQ!Y22-1,"") | AB30: =IFERROR(subQ!AB22/subQ!AA22-1,"") | AC30: 5.41e-07 | AD30: 0 | AF30: 0 | AG30: 0 | AH30: 0 | AI30: 0 | AK30: 0 | AL30: 0 | AM30: 0 | AN30: 0
A31: drv:자본총계 | B31: roll | C31: 자본총계 기타변동(배당 등, 억원) | G31: =IFERROR(subQ!E23+subQ!G19-subQ!G23,"") | H31: =IFERROR(subQ!G23+subQ!H19-subQ!H23,"") | I31: =IFERROR(subQ!H23+subQ!I19-subQ!I23,"") | J31: =IFERROR(subQ!I23+subQ!J19-subQ!J23,"") | L31: =IFERROR(subQ!J23+subQ!L19-subQ!L23,"") | M31: =IFERROR(subQ!L23+subQ!M19-subQ!M23,"") | N31: =IFERROR(subQ!M23+subQ!N19-subQ!N23,"") | O31: =IFERROR(subQ!N23+subQ!O19-subQ!O23,"") | Q31: =IFERROR(subQ!O23+subQ!Q19-subQ!Q23,"") | R31: =IFERROR(subQ!Q23+subQ!R19-subQ!R23,"") | S31: =IFERROR(subQ!R23+subQ!S19-subQ!S23,"") | T31: =IFERROR(subQ!S23+subQ!T19-subQ!T23,"") | V31: =IFERROR(subQ!T23+subQ!V19-subQ!V23,"") | W31: =IFERROR(subQ!V23+subQ!W19-subQ!W23,"") | X31: =IFERROR(subQ!W23+subQ!X19-subQ!X23,"") | Y31: =IFERROR(subQ!X23+subQ!Y19-subQ!Y23,"") | AA31: =IFERROR(subQ!Y23+subQ!AA19-subQ!AA23,"") | AB31: =IFERROR(subQ!AA23+subQ!AB19-subQ!AB23,"") | AC31: 0.001220222 | AD31: 0.000867166 | AF31: -0.00160795 | AG31: 0.001357101 | AH31: -0.000606389 | AI31: 0.004095056 | AK31: -0.003889981 | AL31: 0.002249301 | AM31: 0.0027428 | AN31: -0.002731924
A32: drv:지배주주지분 | B32: roll | C32: 지배주주지분 기타변동(배당 등, 억원) | G32: =IFERROR(subQ!E24+subQ!G20-subQ!G24,"") | H32: =IFERROR(subQ!G24+subQ!H20-subQ!H24,"") | I32: =IFERROR(subQ!H24+subQ!I20-subQ!I24,"") | J32: =IFERROR(subQ!I24+subQ!J20-subQ!J24,"") | L32: =IFERROR(subQ!J24+subQ!L20-subQ!L24,"") | M32: =IFERROR(subQ!L24+subQ!M20-subQ!M24,"") | N32: =IFERROR(subQ!M24+subQ!N20-subQ!N24,"") | O32: =IFERROR(subQ!N24+subQ!O20-subQ!O24,"") | Q32: =IFERROR(subQ!O24+subQ!Q20-subQ!Q24,"") | R32: =IFERROR(subQ!Q24+subQ!R20-subQ!R24,"") | S32: =IFERROR(subQ!R24+subQ!S20-subQ!S24,"") | T32: =IFERROR(subQ!S24+subQ!T20-subQ!T24,"") | V32: =IFERROR(subQ!T24+subQ!V20-subQ!V24,"") | W32: =IFERROR(subQ!V24+subQ!W20-subQ!W24,"") | X32: =IFERROR(subQ!W24+subQ!X20-subQ!X24,"") | Y32: =IFERROR(subQ!X24+subQ!Y20-subQ!Y24,"") | AA32: =IFERROR(subQ!Y24+subQ!AA20-subQ!AA24,"") | AB32: =IFERROR(subQ!AA24+subQ!AB20-subQ!AB24,"") | AC32: 0.001220222 | AD32: 0.000867166 | AF32: -0.00160795 | AG32: 0.001357101 | AH32: -0.000606389 | AI32: 0.004095056 | AK32: -0.003889981 | AL32: 0.002249301 | AM32: 0.0027428 | AN32: -0.002731924
A33: drv:총차입금 | B33: qoq | C33: 총차입금 QoQ | G33: =IFERROR(subQ!G25/subQ!E25-1,"") | H33: =IFERROR(subQ!H25/subQ!G25-1,"") | I33: =IFERROR(subQ!I25/subQ!H25-1,"") | J33: =IFERROR(subQ!J25/subQ!I25-1,"") | L33: =IFERROR(subQ!L25/subQ!J25-1,"") | M33: =IFERROR(subQ!M25/subQ!L25-1,"") | N33: =IFERROR(subQ!N25/subQ!M25-1,"") | O33: =IFERROR(subQ!O25/subQ!N25-1,"") | Q33: =IFERROR(subQ!Q25/subQ!O25-1,"") | R33: =IFERROR(subQ!R25/subQ!Q25-1,"") | S33: =IFERROR(subQ!S25/subQ!R25-1,"") | T33: =IFERROR(subQ!T25/subQ!S25-1,"") | V33: =IFERROR(subQ!V25/subQ!T25-1,"") | W33: =IFERROR(subQ!W25/subQ!V25-1,"") | X33: =IFERROR(subQ!X25/subQ!W25-1,"") | Y33: =IFERROR(subQ!Y25/subQ!X25-1,"") | AA33: =IFERROR(subQ!AA25/subQ!Y25-1,"") | AB33: =IFERROR(subQ!AB25/subQ!AA25-1,"") | AC33: 7.58e-07 | AD33: 0 | AF33: 0 | AG33: 0 | AH33: 0 | AI33: 0 | AK33: 0 | AL33: 0 | AM33: 0 | AN33: 0
A34: drv:순차입금 | B34: qoq | C34: 순차입금 QoQ | G34: =IFERROR(subQ!G26/subQ!E26-1,"") | H34: =IFERROR(subQ!H26/subQ!G26-1,"") | I34: =IFERROR(subQ!I26/subQ!H26-1,"") | J34: =IFERROR(subQ!J26/subQ!I26-1,"") | L34: =IFERROR(subQ!L26/subQ!J26-1,"") | M34: =IFERROR(subQ!M26/subQ!L26-1,"") | N34: =IFERROR(subQ!N26/subQ!M26-1,"") | O34: =IFERROR(subQ!O26/subQ!N26-1,"") | Q34: =IFERROR(subQ!Q26/subQ!O26-1,"") | R34: =IFERROR(subQ!R26/subQ!Q26-1,"") | S34: =IFERROR(subQ!S26/subQ!R26-1,"") | T34: =IFERROR(subQ!T26/subQ!S26-1,"") | V34: =IFERROR(subQ!V26/subQ!T26-1,"") | W34: =IFERROR(subQ!W26/subQ!V26-1,"") | X34: =IFERROR(subQ!X26/subQ!W26-1,"") | Y34: =IFERROR(subQ!Y26/subQ!X26-1,"") | AA34: =IFERROR(subQ!AA26/subQ!Y26-1,"") | AB34: =IFERROR(subQ!AB26/subQ!AA26-1,"") | AC34: -0.07393204 | AD34: -0.10532172 | AF34: -0.086364174 | AG34: -0.10560873 | AH34: -0.10830671 | AI34: -0.15426974 | AK34: -0.13425748 | AL34: -0.17188093 | AM34: -0.18504885 | AN34: -0.28544412
A35: drv:이자발생자산 | B35: qoq | C35: 이자발생자산 QoQ | G35: =IFERROR(subQ!G27/subQ!E27-1,"") | H35: =IFERROR(subQ!H27/subQ!G27-1,"") | I35: =IFERROR(subQ!I27/subQ!H27-1,"") | J35: =IFERROR(subQ!J27/subQ!I27-1,"") | L35: =IFERROR(subQ!L27/subQ!J27-1,"") | M35: =IFERROR(subQ!M27/subQ!L27-1,"") | N35: =IFERROR(subQ!N27/subQ!M27-1,"") | O35: =IFERROR(subQ!O27/subQ!N27-1,"") | Q35: =IFERROR(subQ!Q27/subQ!O27-1,"") | R35: =IFERROR(subQ!R27/subQ!Q27-1,"") | S35: =IFERROR(subQ!S27/subQ!R27-1,"") | T35: =IFERROR(subQ!T27/subQ!S27-1,"") | V35: =IFERROR(subQ!V27/subQ!T27-1,"") | W35: =IFERROR(subQ!W27/subQ!V27-1,"") | X35: =IFERROR(subQ!X27/subQ!W27-1,"") | Y35: =IFERROR(subQ!Y27/subQ!X27-1,"") | AA35: =IFERROR(subQ!AA27/subQ!Y27-1,"") | AB35: =IFERROR(subQ!AB27/subQ!AA27-1,"") | AC35: 0.1118141 | AD35: 0.13268807 | AF35: 0.085932032 | AG35: 0.088418957 | AH35: 0.074508708 | AI35: 0.088072027 | AK35: 0.059575813 | AL35: 0.062318342 | AM35: 0.052301323 | AN35: 0.062476266
A36: drv:현금및현금성자산 | B36: qoq | C36: 현금및현금성자산 QoQ | G36: =IFERROR(subQ!G28/subQ!E28-1,"") | H36: =IFERROR(subQ!H28/subQ!G28-1,"") | I36: =IFERROR(subQ!I28/subQ!H28-1,"") | J36: =IFERROR(subQ!J28/subQ!I28-1,"") | L36: =IFERROR(subQ!L28/subQ!J28-1,"") | M36: =IFERROR(subQ!M28/subQ!L28-1,"") | N36: =IFERROR(subQ!N28/subQ!M28-1,"") | O36: =IFERROR(subQ!O28/subQ!N28-1,"") | Q36: =IFERROR(subQ!Q28/subQ!O28-1,"") | R36: =IFERROR(subQ!R28/subQ!Q28-1,"") | S36: =IFERROR(subQ!S28/subQ!R28-1,"") | T36: =IFERROR(subQ!T28/subQ!S28-1,"") | V36: =IFERROR(subQ!V28/subQ!T28-1,"") | W36: =IFERROR(subQ!W28/subQ!V28-1,"") | X36: =IFERROR(subQ!X28/subQ!W28-1,"") | Y36: =IFERROR(subQ!Y28/subQ!X28-1,"") | AA36: =IFERROR(subQ!AA28/subQ!Y28-1,"") | AB36: =IFERROR(subQ!AB28/subQ!AA28-1,"")
A37: drv:CAPEX | B37: yoy | C37: CAPEX YoY | J37: =IFERROR(subQ!J29/subQ!E29-1,"") | L37: =IFERROR(subQ!L29/subQ!G29-1,"") | M37: =IFERROR(subQ!M29/subQ!H29-1,"") | N37: =IFERROR(subQ!N29/subQ!I29-1,"") | O37: =IFERROR(subQ!O29/subQ!J29-1,"") | Q37: =IFERROR(subQ!Q29/subQ!L29-1,"") | R37: =IFERROR(subQ!R29/subQ!M29-1,"") | S37: =IFERROR(subQ!S29/subQ!N29-1,"") | T37: =IFERROR(subQ!T29/subQ!O29-1,"") | V37: =IFERROR(subQ!V29/subQ!Q29-1,"") | W37: =IFERROR(subQ!W29/subQ!R29-1,"") | X37: =IFERROR(subQ!X29/subQ!S29-1,"") | Y37: =IFERROR(subQ!Y29/subQ!T29-1,"") | AA37: =IFERROR(subQ!AA29/subQ!V29-1,"") | AB37: =IFERROR(subQ!AB29/subQ!W29-1,"") | AC37: -0.19513728 | AD37: -0.13989085 | AF37: 0.27028716 | AG37: 0.19434642 | AH37: 0 | AI37: 0 | AK37: 0 | AL37: 0 | AM37: 0 | AN37: 0
A38: drv:영업활동현금흐름 | B38: yoy | C38: 영업활동현금흐름 YoY | J38: =IFERROR(subQ!J30/subQ!E30-1,"") | L38: =IFERROR(subQ!L30/subQ!G30-1,"") | M38: =IFERROR(subQ!M30/subQ!H30-1,"") | N38: =IFERROR(subQ!N30/subQ!I30-1,"") | O38: =IFERROR(subQ!O30/subQ!J30-1,"") | Q38: =IFERROR(subQ!Q30/subQ!L30-1,"") | R38: =IFERROR(subQ!R30/subQ!M30-1,"") | S38: =IFERROR(subQ!S30/subQ!N30-1,"") | T38: =IFERROR(subQ!T30/subQ!O30-1,"") | V38: =IFERROR(subQ!V30/subQ!Q30-1,"") | W38: =IFERROR(subQ!W30/subQ!R30-1,"") | X38: =IFERROR(subQ!X30/subQ!S30-1,"") | Y38: =IFERROR(subQ!Y30/subQ!T30-1,"") | AA38: =IFERROR(subQ!AA30/subQ!V30-1,"") | AB38: =IFERROR(subQ!AB30/subQ!W30-1,"")
A39: drv:주식수 | B39: qoq | C39: 주식수 QoQ | G39: =IFERROR(subQ!G31/subQ!E31-1,"") | H39: =IFERROR(subQ!H31/subQ!G31-1,"") | I39: =IFERROR(subQ!I31/subQ!H31-1,"") | J39: =IFERROR(subQ!J31/subQ!I31-1,"") | L39: =IFERROR(subQ!L31/subQ!J31-1,"") | M39: =IFERROR(subQ!M31/subQ!L31-1,"") | N39: =IFERROR(subQ!N31/subQ!M31-1,"") | O39: =IFERROR(subQ!O31/subQ!N31-1,"") | Q39: =IFERROR(subQ!Q31/subQ!O31-1,"") | R39: =IFERROR(subQ!R31/subQ!Q31-1,"") | S39: =IFERROR(subQ!S31/subQ!R31-1,"") | T39: =IFERROR(subQ!T31/subQ!S31-1,"") | V39: =IFERROR(subQ!V31/subQ!T31-1,"") | W39: =IFERROR(subQ!W31/subQ!V31-1,"") | X39: =IFERROR(subQ!X31/subQ!W31-1,"") | Y39: =IFERROR(subQ!Y31/subQ!X31-1,"") | AA39: =IFERROR(subQ!AA31/subQ!Y31-1,"") | AB39: =IFERROR(subQ!AB31/subQ!AA31-1,"") | AC39: 0 | AD39: 0 | AF39: 0 | AG39: 0 | AH39: 0 | AI39: 0 | AK39: 0 | AL39: 0 | AM39: 0 | AN39: 0
A40: drv:DPS | B40: abs | C40: DPS (가정, 원) | E40: =subQ!E34 | F40: =subQ!F34 | G40: =subQ!G34 | H40: =subQ!H34 | I40: =subQ!I34 | J40: =subQ!J34 | K40: =subQ!K34 | L40: =subQ!L34 | ... AB40: =subQ!AB34 | AD40: 0 | AE40: =subQ!AE34 | AI40: 0 | AJ40: =subQ!AJ34 | AN40: 0 | AO40: =subQ!AO34
B42: 3. 밸류에이션·스칼라 | C42: 노란 셀 = 가정. '연결' 표시는 추정 전 분기 수식이 이 셀을 참조한다는 뜻
A43: sc:종가 | C43: 종가 | D43: 15780 | E43: 원 — 네이버 정규장 종가(aik 확정종가 대조 · aik 17,000원)
A44: sc:기준일 | C44: 기준일 | D44: 20261026 | E44: 종가 기준일
A45: sc:COE | C45: COE | D45: 0.09 | E45: 자기자본비용(가정) — TP 적정 PBR = ROE/COE
A46: sc:PER_lo | C46: PER_lo | D46: 14.9 | E46: PER 밴드 하단(배) — hist_quarterly(분기 평균가 ÷ TTM EPS, 11분기, 25/50/75 백분위)
A47: sc:PER_mid | C47: PER_mid | D47: 17.5 | E47: PER 밴드 중단(배)
A48: sc:PER_hi | C48: PER_hi | D48: 24.6 | E48: PER 밴드 상단(배)
A49: sc:EPS_Y1가중 | C49: EPS_Y1가중 | D49: 0.5 | E49: 12M fwd EPS = FY(last_actual연도)E × w + FY+1E × (1−w) — 기준 분기 2Q 이면 0.5(가정)
A50: sc:세율 | C50: 세율 | D50: 0 | E50: 참고(연결 안 됨: 이월결손 램프(assumptions.tax_schedule, 0%→22%) — 분기별 세율 드라이버 행 사용) — 모델 assumptions 값(시작 0% → terminal 22%, 2026Q4 까지 유지 → 2027Q1~2028Q4 선형 램프 — 분기별 값은 2절 drv:법인세비용 행) · 최근 8분기 중 세전 > 0 인 8분기(2024Q3~2026Q2) 법인세/세전 중위 -3.3%·최근 4분기 중위 -1.8% 가 모두 5% 미만 → 이월결손 공제 중으로 보고 0.0% 를 2026Q4 까지 유지, 2027Q1~2028Q4 선형 램프로 법정세율 근사 22% 수렴
A51: sc:판관비율 | C51: 판관비율 | D51: 0.078783016 | E51: 연결 — 판관비 = 매출액 × 판관비율(역산, 재현 오차 ≤ 0.05억 · 모델 assumptions 0.0788)
A52: sc:지배주주비중 | C52: 지배주주비중 | D52: 1 | E52: 연결 — 지배주주순이익 = 당기순이익 × 비중(역산, 재현 오차 ≤ 0.05억)
A53: sc:이자율_자산 | C53: 이자율_자산 | D53: 0.023278756 | E53: 연결 — 이자손익 = (전분기 이자발생자산 × 자산이자율 − 전분기 총차입금 × 부채이자율)/4(역산, 재현 오차 ≤ 0.05억 · 모델 assumptions 0.0233)
A54: sc:이자율_부채 | C54: 이자율_부채 | D54: 0.037088832 | E54: 연결 — 같은 수식의 부채 쪽(총차입금 행이 없으면 0)(역산, 재현 오차 ≤ 0.05억 · 모델 assumptions 0.0371)
A55: sc:배당성향 | C55: 배당성향 | D55: 0 | E55: 배당성향(참고 — 모델은 직전 DPS 유지·Q2 지급 가정)
A56: sc:외화순노출_백만$ | C56: 외화순노출_백만$ | E56: 외화 순노출 × Δ기말환율 (외화 시트 방식) — 외화 순노출 미공시(face) → 0 + 표기
A57: sc:헤지비율 | C57: 헤지비율 | E57: sls 없음
A58: sc:헤지환율_약정 | C58: 헤지환율_약정 | E58: sls 없음

Sheet BS연결
B1: (백만원) | C1: 이름: BS연결H | E1: 4Q21 | F1: 2021 | G1: 1Q22 | H1: 2Q22 | I1: 3Q22 | J1: 4Q22 | K1: 2022 | L1: 1Q23 | M1: 2Q23 | N1: 3Q23 | O1: 4Q23 | P1: 2023 | Q1: 1Q24 | R1: 2Q24 | S1: 3Q24 | T1: 4Q24 | U1: 2024 | V1: 1Q25 | W1: 2Q25 | X1: 3Q25 | Y1: 4Q25 | Z1: 2025 | AA1: 1Q26 | AB1: 2Q26 | AC1: 3Q26 | AD1: 4Q26 | AE1: 2026 | AF1: 1Q27 | AG1: 2Q27 | AH1: 3Q27 | AI1: 4Q27 | AJ1: 2027 | AK1: 1Q28 | AL1: 2Q28 | AM1: 3Q28 | AN1: 4Q28 | AO1: 2028
B2: 연결 | D2: fin json(kship_fin.py)
B3: STX엔진(연) | C3: UPDATE: 26-10-26 | E3: 1 | F3: 2 | G3: 3 | H3: 4 | I3: 5 | J3: 6 | K3: 7 | L3: 8 | M3: 9 | N3: 10 | O3: 11 | P3: 12 | Q3: 13 | R3: 14 | S3: 15 | T3: 16 | U3: 17 | V3: 18 | W3: 19 | X3: 20 | Y3: 21 | Z3: 22 | AA3: 23 | AB3: 24 | AC3: 25 | AD3: 26 | AE3: 27 | AF3: 28 | AG3: 29 | AH3: 30 | AI3: 31 | AJ3: 32 | AK3: 33 | AL3: 34 | AM3: 35 | AN3: 36 | AO3: 37
B4: Account Code | C4: AccountNAME | E4: 2021.12 | F4: 2021.12A | G4: 2022.03 | H4: 2022.06 | I4: 2022.09 | J4: 2022.12 | K4: 2022.12A | L4: 2023.03 | M4: 2023.06 | N4: 2023.09 | O4: 2023.12 | P4: 2023.12A | Q4: 2024.03 | R4: 2024.06 | S4: 2024.09 | T4: 2024.12 | U4: 2024.12A | V4: 2025.03 | W4: 2025.06 | X4: 2025.09 | Y4: 2025.12 | Z4: 2025.12A | AA4: 2026.03 | AB4: 2026.06 | AC4: 2026.09 | AD4: 2026.12 | AE4: 2026.12A | AF4: 2027.03 | AG4: 2027.06 | AH4: 2027.09 | AI4: 2027.12 | AJ4: 2027.12A | AK4: 2028.03 | AL4: 2028.06 | AM4: 2028.09 | AN4: 2028.12 | AO4: 2028.12A
A5: 1 | C5: 유동자산 | E5: 427101 | F5: 427101 | G5: 419659 | H5: 418966 | I5: 429083 | J5: 468460 | K5: 468460 | L5: 483477 | M5: 448281 | N5: 446925 | O5: 490899 | P5: 490899 | Q5: 573665 | R5: 596885 | S5: 572986 | T5: 555213.66 | U5: 555213.66 | V5: 525196.82 | W5: 635843.1 | X5: 671710.7 | Y5: 727075.77 | Z5: 727075.77 | AA5: 774506.29 | AB5: 780031.12
A6: 1 | C6: 현금및현금성자산 | E6: 104687 | F6: 104687 | G6: 109517 | H6: 76889 | I6: 56648 | J6: 88277 | K6: 88277 | L6: 63412 | M6: 71516 | N6: 57911 | O6: 86616 | P6: 86616 | Q6: 105211 | R6: 101695 | S6: 98619 | T6: 131440.92 | U6: 131440.92 | V6: 44331.39 | W6: 109016.06 | X6: 167149.21 | Y6: 164134.33 | Z6: 164134.33 | AA6: 110270.44 | AB6: 114235.36
A7: 1 | C7: 기타유동금융자산 | E7: 1869 | F7: 1869 | G7: 1347 | H7: 1937 | I7: 1970 | L7: 9311 | M7: 369 | N7: 246
A8: 1 | C8: 매출채권및기타채권 | E8: 93506 | F8: 93506 | G8: 71354 | H8: 73359 | I8: 96141 | J8: 110235 | K8: 110235 | L8: 112722 | M8: 104788 | N8: 105637 | O8: 136635 | P8: 136635 | Q8: 101290 | R8: 124273 | S8: 124231 | T8: 91585.37 | U8: 91585.37 | V8: 101167.75 | W8: 141419.58 | X8: 99833.51 | Y8: 141748.29 | Z8: 141748.29 | AA8: 184178.49 | AB8: 137930.07
A9: 1 | C9: 계약자산 | E9: 16551 | F9: 16551 | G9: 16412 | H9: 17722 | I9: 17708 | J9: 12431 | K9: 12431 | L9: 18008 | M9: 15161 | N9: 14888 | O9: 6051 | P9: 6051 | Q9: 8170 | R9: 8362 | S9: 12439 | T9: 10372.02 | U9: 10372.02 | V9: 14089.45 | W9: 14583.59 | X9: 19223.46 | Y9: 24268.64 | Z9: 24268.64 | AA9: 32917.99 | AB9: 40432.66
A10: 1 | C10: 선급금 | E10: 22378 | F10: 22378 | G10: 37854 | H10: 39056 | I10: 35255 | J10: 47238 | K10: 47238 | L10: 55457 | M10: 59281 | N10: 54777 | O10: 53735 | P10: 53735 | Q10: 61152 | R10: 59737 | S10: 43214 | T10: 37270.7 | U10: 37270.7 | V10: 43594.87 | W10: 59011.95 | X10: 82649.35 | Y10: 45267.19 | Z10: 45267.19 | AA10: 67291.79 | AB10: 69367.13
A11: 1 | C11: 선급금등 | E11: 22378 | F11: 22378 | G11: 37854 | H11: 39056 | I11: 35255 | J11: 47238 | K11: 47238 | L11: 55457 | M11: 59281 | N11: 54777 | O11: 53735 | P11: 53735 | Q11: 61152 | R11: 59737 | S11: 43214 | T11: 37270.7 | U11: 37270.7 | V11: 43594.87 | W11: 59011.95 | X11: 82649.35 | Y11: 45267.19 | Z11: 45267.19 | AA11: 67291.79 | AB11: 69367.13
A12: 1 | C12: 기타유동자산 | E12: 28491 | F12: 28491 | G12: 43066 | H12: 45573 | I12: 40730 | J12: 47238 | K12: 47238 | L12: 60042 | M12: 63155 | N12: 59037 | O12: 53735 | P12: 53735 | Q12: 61152 | R12: 59737 | S12: 43214 | T12: 37270.7 | U12: 37270.7 | V12: 43594.87 | W12: 59011.95 | X12: 82649.35 | Y12: 45267.19 | Z12: 45267.19 | AA12: 67291.79 | AB12: 69367.13
A13: 1 | C13: 재고자산 | E13: 181566 | F13: 181566 | G13: 176620 | H13: 197952 | I13: 204463 | J13: 188620 | K13: 188620 | L13: 216215 | M13: 191044 | N13: 208383 | O13: 205831 | P13: 205831 | Q13: 292688 | R13: 299546 | S13: 289626 | T13: 276995.24 | U13: 276995.24 | V13: 316005.61 | W13: 303625.35 | X13: 295599.49 | Y13: 337393.7 | Z13: 337393.7 | AA13: 360422.92 | AB13: 396142.96
A14: 1 | C14: 당기법인세자산(선급법인세) | E14: 81 | F14: 81 | G14: 35 | H14: 58 | I14: 30 | J14: 161 | K14: 161 | L14: 576 | M14: 592 | N14: 662 | O14: 338 | P14: 338 | Q14: 449 | R14: 235 | S14: 113 | T14: 89.04 | U14: 89.04 | V14: 202.74 | Y14: 0 | Z14: 0
A15: 1 | C15: 유동확정계약자산 | E15: 350 | F15: 350 | G15: 1308 | H15: 5476 | I15: 11393 | J15: 3636 | K15: 3636 | L15: 3034 | M15: 1652 | N15: 161 | T15: 0 | U15: 0
A16: 1 | C16: 단기금융자산 | E16: 350 | F16: 350 | G16: 1308 | H16: 5476 | I16: 11393 | J16: 13435 | K16: 13435 | L16: 3191 | M16: 1656 | N16: 161 | O16: 246 | P16: 246 | Q16: 265 | R16: 631 | S16: 304 | T16: 2099.22 | U16: 2099.22 | V16: 2970.12 | W16: 2591.2 | X16: 2267.23 | Y16: 7272.27 | Z16: 7272.27 | AA16: 14347.17 | AB16: 14513.68
A17: 1 | C17: 비유동자산 | E17: 410379 | F17: 410379 | G17: 410733 | H17: 424700 | I17: 414494 | J17: 384928 | K17: 384928 | L17: 383836 | M17: 397592 | N17: 394369 | O17: 408235 | P17: 408235 | Q17: 400160 | R17: 397844 | S17: 407675 | T17: 413596.78 | U17: 413596.78 | V17: 421271 | W17: 418959.12 | X17: 426031.29 | Y17: 430459.27 | Z17: 430459.27 | AA17: 435031.3 | AB17: 435088.73
A18: 1 | C18: 유형자산 | E18: 294844 | F18: 294844 | G18: 295003 | H18: 294595 | I18: 293592 | J18: 277601 | K18: 277601 | L18: 276311 | M18: 276022 | N18: 276121 | O18: 276836 | P18: 276836 | Q18: 275194 | R18: 275524 | S18: 275750 | T18: 276213.39 | U18: 276213.39 | V18: 274955.99 | W18: 274865.01 | X18: 274481.36 | Y18: 279161.3 | Z18: 279161.3 | AA18: 278468.27 | AB18: 277656.07
A19: 1 | C19: 무형자산 | E19: 10813 | F19: 10813 | G19: 10622 | H19: 10628 | I19: 4927 | J19: 8804 | K19: 8804 | L19: 8740 | M19: 13881 | N19: 14115 | O19: 15207 | P19: 15207 | Q19: 15260 | R19: 16402 | S19: 19723 | T19: 22836.62 | U19: 22836.62 | V19: 24197.62 | W19: 24870.96 | X19: 27837.23 | Y19: 28831.72 | Z19: 28831.72 | AA19: 28307.74 | AB19: 28571.1
A20: 1 | C20: 투자부동산 | E20: 58779 | F20: 58779 | G20: 58343 | H20: 57907 | I20: 57471 | J20: 57035 | K20: 57035 | L20: 56599 | M20: 56164 | N20: 55728 | O20: 55292 | P20: 55292 | Q20: 54856 | R20: 54420 | S20: 53985 | T20: 53548.82 | U20: 53548.82 | V20: 53113.02 | W20: 52677.22 | X20: 52241.42 | Y20: 51805.62 | Z20: 51805.62 | AA20: 51369.82 | AB20: 50934.02
A21: 1 | C21: 장기매출채권및기타채권 | E21: 6806 | F21: 6806 | G21: 6977 | H21: 5599 | I21: 5417 | J21: 3884 | K21: 3884 | L21: 2004 | M21: 3480 | N21: 2243 | O21: 3617 | P21: 3617 | Q21: 1050 | R21: 3586 | S21: 2431 | T21: 582.2 | U21: 582.2 | V21: 484.9 | W21: 484.9 | X21: 484.9 | Y21: 222.04 | Z21: 222.04 | AA21: 222.04 | AB21: 222.04
A22: 1 | C22: 비유동확정계약자산 | E22: 116 | F22: 116 | G22: 137 | H22: 309
A23: 1 | C23: 투자자산 | E23: 116 | F23: 116 | G23: 137 | H23: 309 | J23: 7908 | K23: 7908 | O23: 8544 | P23: 8544 | Q23: 8493 | R23: 8865 | S23: 8865 | T23: 9170.53 | U23: 9170.53 | V23: 9194 | W23: 10943.74 | X23: 12875.88 | Y23: 12966.37 | Z23: 12966.37 | AA23: 13432.55 | AB23: 13057.94
A24: 1 | C24: 기타비유동자산 | E24: 27855 | F24: 27855 | G24: 28532 | H24: 45285 | I24: 45058 | J24: 27933 | K24: 27933 | L24: 30592 | M24: 37897 | N24: 36049 | O24: 46788 | P24: 46788 | Q24: 43327 | R24: 37118 | S24: 44856 | T24: 47670.29 | U24: 47670.29 | V24: 55623.46 | W24: 51532.58 | X24: 54032.38 | Y24: 54407.5 | Z24: 54407.5 | AA24: 60106.78 | AB24: 61512.53
A25: 1 | C25: 자산총계 | E25: 837480 | F25: 837480 | G25: 830392 | H25: 843666 | I25: 843577 | J25: 853388 | K25: 853388 | L25: 867313 | M25: 845873 | N25: 841294 | O25: 899134 | P25: 899134 | Q25: 973825 | R25: 994729 | S25: 980661 | T25: 968810.44 | U25: 968810.44 | V25: 946467.82 | W25: 1054802.2 | X25: 1097742 | Y25: 1157535 | Z25: 1157535 | AA25: 1209537.6 | AB25: 1215119.9
A26: 1 | C26: 유동부채 | E26: 490794 | F26: 490794 | G26: 485500 | H26: 499331 | I26: 508648 | J26: 539906 | K26: 539906 | L26: 555109 | M26: 531035 | N26: 525406 | O26: 577722 | P26: 577722 | Q26: 650598 | R26: 655142 | S26: 638608 | T26: 628413.77 | U26: 628413.77 | V26: 592952.6 | W26: 670122.46 | X26: 696259.97 | Y26: 744923.47 | Z26: 744923.47 | AA26: 779610.83 | AB26: 762086.76
A27: 1 | C27: 매입채무및기타채무 | E27: 73675 | F27: 73675 | G27: 74364 | H27: 75215 | I27: 69718 | J27: 117660 | K27: 117660 | L27: 103041 | M27: 98226 | N27: 104555 | O27: 132747 | P27: 132747 | Q27: 126425 | R27: 117556 | S27: 110425 | T27: 134985.47 | U27: 134985.47 | V27: 122331.51 | W27: 111544.62 | X27: 107069.3 | Y27: 162339.59 | Z27: 162339.59 | AA27: 121590.24 | AB27: 117415.48
A28: 1 | C28: 단기차입금 | E28: 258774 | F28: 258774 | G28: 245826 | H28: 234164 | I28: 239521 | J28: 237830 | K28: 237830 | L28: 251122 | M28: 244348 | N28: 245130 | O28: 259304 | P28: 259304 | Q28: 299177 | R28: 324065 | S28: 328481 | T28: 312315.66 | U28: 312315.66 | V28: 282732.55 | W28: 294527.04 | X28: 306662.23 | Y28: 311529.62 | Z28: 311529.62 | AA28: 351081.7 | AB28: 343225.74
A29: 1 | C29: 선수금 | E29: 115626 | F29: 115626 | G29: 127445 | H29: 143159 | I29: 149799 | J29: 148760 | K29: 148760 | L29: 172442 | M29: 154229 | N29: 145822 | O29: 165492 | P29: 165492 | Q29: 201790 | R29: 185409 | S29: 174218 | T29: 153797.27 | U29: 153797.27 | V29: 157194.14 | W29: 228975.9 | X29: 254095.51 | Y29: 246853.68 | Z29: 246853.68 | AA29: 284936.28 | AB29: 274435.18
A30: 1 | C30: 기타유동부채 | E30: 134856 | F30: 134856 | G30: 144778 | H30: 157926 | I30: 165101 | J30: 148760 | K30: 148760 | L30: 172442 | M30: 154346 | N30: 145922 | O30: 165492 | P30: 165492 | Q30: 201790 | R30: 185409 | S30: 174218 | T30: 153797.27 | U30: 153797.27 | V30: 157194.14 | W30: 228975.9 | X30: 254095.51 | Y30: 246853.68 | Z30: 246853.68 | AA30: 284936.28 | AB30: 274435.18
A31: 1 | C31: 계약부채 | E31: 19819 | F31: 19819 | G31: 15981 | H31: 23164 | I31: 21926 | J31: 22131 | K31: 22131 | L31: 17119 | M31: 25586 | N31: 22713 | O31: 13439 | P31: 13439 | Q31: 19077 | R31: 23427 | S31: 20654 | T31: 21720.44 | U31: 21720.44 | V31: 26179.81 | W31: 29457.74 | X31: 22200.95 | Y31: 16414.21 | Z31: 16414.21 | AA31: 14563.47 | AB31: 18282.17
A32: 1 | C32: 단기충당부채 | E32: 3350 | F32: 3350 | G32: 3248 | H32: 3556 | I32: 3582 | J32: 7638 | K32: 7638 | L32: 6994 | M32: 7057 | N32: 6817 | O32: 5455 | P32: 5455 | Q32: 3799 | R32: 3913 | S32: 4067 | T32: 4096.2 | U32: 4096.2 | V32: 3702.52 | W32: 4768.62 | X32: 5357.8 | Y32: 6030.41 | Z32: 6030.41 | AA32: 6053.63 | AB32: 6813.49
A33: 1 | C33: 단기파생상품부채 | E33: 320 | F33: 320 | G33: 1303 | H33: 5086 | I33: 8800 | J33: 5099 | K33: 5099 | L33: 3750 | M33: 1472 | N33: 269 | S33: 67 | T33: 0 | U33: 0 | W33: 136.47 | Y33: 365.37 | Z33: 365.37 | AA33: 340.01 | AB33: 113.4
A34: 1 | C34: 단기금융부채 | E34: 320 | F34: 320 | G34: 1303 | H34: 5086 | I34: 8800 | J34: 5099 | K34: 5099 | L34: 3750 | M34: 1472 | N34: 269 | S34: 67 | T34: 0 | U34: 0 | W34: 136.47 | Y34: 365.37 | Z34: 365.37 | AA34: 340.01 | AB34: 113.4
A35: 1 | C35: 비유동부채 | E35: 62711 | F35: 62711 | G35: 63980 | H35: 65384 | I35: 64134 | J35: 53237 | K35: 53237 | L35: 54695 | M35: 55653 | N35: 56884 | O35: 61778 | P35: 61778 | Q35: 63017 | R35: 64959 | S35: 68478 | T35: 63826.9 | U35: 63826.9 | V35: 68180.18 | W35: 69631.87 | X35: 70886.72 | Y35: 69640.48 | Z35: 69640.48 | AA35: 69514.3 | AB35: 70097.79
A36: 1 | C36: 확정급여부채 | E36: 37822 | F36: 37822 | G36: 38382 | H36: 39270 | I36: 39628 | J36: 31428 | K36: 31428 | L36: 32304 | M36: 33129 | N36: 33653 | O36: 35753 | P36: 35753 | Q36: 36629 | R36: 37141 | S36: 38123 | T36: 38703.49 | U36: 38703.49 | V36: 39698.49 | W36: 40688.94 | X36: 41679.69 | Y36: 41792.43 | Z36: 41792.43 | AA36: 42881.13 | AB36: 43871.59
A37: 1 | C37: 이연법인세부채 | E37: 19326 | F37: 19326 | G37: 19581 | H37: 19234 | I37: 17225 | J37: 15323 | K37: 15323 | L37: 15651 | M37: 15811 | N37: 16079 | O37: 18509 | P37: 18509 | Q37: 18509 | R37: 18360 | S37: 18444 | T37: 12296.12 | U37: 12296.12 | V37: 12078.9 | W37: 12011.73 | X37: 11986.17 | Y37: 3948.84 | Z37: 3948.84 | AA37: 2842 | AB37: 2711.72
A38: 1 | C38: 장기충당부채 | E38: 365 | F38: 365 | G38: 400
A39: 1 | C39: 장기파생상품부채 | E39: 152 | F39: 152 | G39: 133 | H39: 308
A40: 1 | C40: 장기금융부채 | E40: 152 | F40: 152 | G40: 133 | H40: 308
A41: 1 | C41: 기타비유동부채 | E41: 5046 | F41: 5046 | G41: 5484 | H41: 6572 | I41: 7281
A42: 1 | C42: 부채총계 | E42: 553505 | F42: 553505 | G42: 549480 | H42: 564715 | I42: 572782 | J42: 593143 | K42: 593143 | L42: 609804 | M42: 586688 | N42: 582290 | O42: 639500 | P42: 639500 | Q42: 713615 | R42: 720101 | S42: 707086 | T42: 692240.66 | U42: 692240.66 | V42: 661132.78 | W42: 739754.33 | X42: 767146.69 | Y42: 814563.95 | Z42: 814563.95 | AA42: 849125.13 | AB42: 832184.55
A43: 1 | C43: 자본금 | E43: 69141 | F43: 69141 | G43: 69141 | H43: 69141 | I43: 69141 | J43: 69141 | K43: 69141 | L43: 69141 | M43: 69141 | N43: 69141 | O43: 69141 | P43: 69141 | Q43: 69141 | R43: 69141 | S43: 69141 | T43: 69140.75 | U43: 69140.75 | V43: 100370.28 | W43: 100370.28 | X43: 100370.28 | Y43: 100370.28 | Z43: 100370.28 | AA43: 100370.28 | AB43: 100370.28
A44: 1 | C44: 자본잉여금 | E44: 471577 | F44: 471577 | G44: 471577 | H44: 471577 | I44: 471577 | J44: 471577 | K44: 471577 | L44: 471577 | M44: 471577 | N44: 471577 | O44: 471577 | P44: 471577 | Q44: 471577 | R44: 471577 | S44: 471577 | T44: 471577.41 | U44: 471577.41 | V44: 129217.93 | W44: 129217.93 | X44: 129217.93 | Y44: 129217.93 | Z44: 129217.93 | AA44: 129217.93 | AB44: 129217.93
A45: 1 | C45: 기타자본 | E45: 89149 | F45: 89149 | G45: 89149 | H45: 89149 | I45: 89149 | J45: 89149 | K45: 89149 | L45: 89149 | M45: 89149 | N45: 89149 | O45: 89149 | P45: 89149 | Q45: 89149 | R45: 89149 | S45: 89149 | T45: 89149.06 | U45: 89149.06 | V45: -5201.6 | W45: -5201.6 | X45: -5201.6 | Y45: -5201.6 | Z45: -5201.6 | AA45: -5201.6 | AB45: -5201.6
A46: 1 | C46: 기타포괄이익누계액 | E46: 50061 | F46: 50061 | G46: 50202 | H46: 49708 | I46: 48154 | J46: 50330 | K46: 50330 | L46: 51013 | M46: 50909 | N46: 51166 | O46: 49573 | P46: 49573 | Q46: 49939 | R46: 50659 | S46: 50508 | T46: 52039 | U46: 52039 | V46: 52618.12 | W46: 52616.82 | X46: 54114.38 | Y46: 54259.1 | Z46: 54259.1 | AA46: 55032.86 | AB46: 55399.4
A47: 1 | C47: 이익잉여금 | E47: -395953 | F47: -395953 | G47: -399157 | H47: -400624 | I47: -407226 | J47: -419952 | K47: -419952 | L47: -423371 | M47: -421591 | N47: -422029 | O47: -419806 | P47: -419806 | Q47: -419596 | R47: -405898 | S47: -406800 | T47: -405336.46 | U47: -405336.46 | V47: 8330.31 | W47: 38044.46 | X47: 52094.31 | Y47: 64325.38 | Z47: 64325.38 | AA47: 80992.98 | AB47: 103149.29
A48: 1 | C48: 자본총계 | E48: 283975 | F48: 283975 | G48: 280912 | H48: 278951 | I48: 270795 | J48: 260245 | K48: 260245 | L48: 257509 | M48: 259185 | N48: 259004 | O48: 259634 | P48: 259634 | Q48: 260210 | R48: 274628 | S48: 273575 | T48: 276569.77 | U48: 276569.77 | V48: 285335.04 | W48: 315047.89 | X48: 330595.29 | Y48: 342971.09 | Z48: 342971.09 | AA48: 360412.45 | AB48: 382935.31
A49: 1 | C49: 부채와자본총계 | E49: 837480 | F49: 837480 | G49: 830392 | H49: 843666 | I49: 843577 | J49: 853388 | K49: 853388 | L49: 867313 | M49: 845873 | N49: 841294 | O49: 899134 | P49: 899134 | Q49: 973825 | R49: 994729 | S49: 980661 | T49: 968810.44 | U49: 968810.44 | V49: 946467.82 | W49: 1054802.2 | X49: 1097742 | Y49: 1157535 | Z49: 1157535 | AA49: 1209537.6 | AB49: 1215119.9
A50: 1 | C50: 지배주주지분 | E50: 283975 | F50: 283975 | G50: 280912 | H50: 278951 | I50: 270795 | J50: 260245 | K50: 260245 | L50: 257509 | M50: 259185 | N50: 259004 | O50: 259634 | P50: 259634 | Q50: 260210 | R50: 274628 | S50: 273575 | T50: 276569.77 | U50: 276569.77 | V50: 285335.04 | W50: 315047.89 | X50: 330595.29 | Y50: 342971.09 | Z50: 342971.09 | AA50: 360412.45 | AB50: 382935.31
A51: 1 | C51: 총차입금 | E51: 258774 | F51: 258774 | G51: 245826 | H51: 234164 | I51: 239521 | J51: 237830 | K51: 237830 | L51: 251122 | M51: 244348 | N51: 245130 | O51: 259304 | P51: 259304 | Q51: 299177 | R51: 324065 | S51: 328481 | T51: 312315.66 | U51: 312315.66 | V51: 286065.88 | W51: 297443.71 | X51: 309162.23 | Y51: 313612.95 | Z51: 313612.95 | AA51: 352748.37 | AB51: 343225.74
A52: 1 | C52: 순차입금 | E52: 153737 | F52: 153737 | G52: 135001 | H52: 151799 | I52: 171480 | J52: 136118 | K52: 136118 | L52: 184519 | M52: 171176 | N52: 187058 | O52: 172442 | P52: 172442 | Q52: 193701 | R52: 221739 | S52: 229558 | T52: 178775.52 | U52: 178775.52 | V52: 238764.37 | W52: 185836.45 | X52: 139745.79 | Y52: 142206.35 | Z52: 142206.35 | AA52: 228130.76 | AB52: 214476.7
A53: 1 | C53: 이자발생자산 | E53: 105037 | F53: 105037 | G53: 110825 | H53: 82365 | I53: 68041 | J53: 109620 | K53: 109620 | L53: 66603 | M53: 73172 | N53: 58072 | O53: 95406 | P53: 95406 | Q53: 113969 | R53: 111191 | S53: 107788 | T53: 142710.67 | U53: 142710.67 | V53: 56495.51 | W53: 122551 | X53: 182292.32 | Y53: 184372.97 | Z53: 184372.97 | AA53: 138050.16 | AB53: 141806.98
A54: 1 | C54: 당기법인세부채(미지급법인세) | H54: 220 | J54: 517 | K54: 517 | L54: 538 | O54: 678 | P54: 678 | Q54: 217 | R54: 268 | S54: 263 | T54: 904.99 | U54: 904.99 | V54: 518.28 | W54: 573.14 | X54: 741.82 | Y54: 1190.8 | Z54: 1190.8 | AA54: 858.39 | AB54: 1667.6
A55: 1 | C55: 단기금융상품 | J55: 8945 | K55: 8945 | O55: 246 | P55: 246 | Q55: 250 | R55: 175 | S55: 177 | T55: 186.4 | U55: 186.4 | V55: 192.05 | W55: 335.26 | X55: 308.59 | Y55: 6009.5 | Z55: 6009.5 | AA55: 12950.3 | AB55: 13183.48
A56: 1 | C56: 유동파생상품자산 | J56: 854 | K56: 854 | L56: 157 | M56: 4 | Q56: 15 | R56: 456 | S56: 127 | T56: 1912.82 | U56: 1912.82 | V56: 2778.07 | W56: 2255.94 | X56: 1958.64 | Y56: 1262.77 | Z56: 1262.77 | AA56: 1396.87 | AB56: 1330.2
A57: 1 | C57: 장기금융자산 | J57: 7908 | K57: 7908 | O57: 8544 | P57: 8544 | Q57: 8493 | R57: 8865 | S57: 8865 | T57: 9170.53 | U57: 9170.53 | V57: 9194 | W57: 10943.74 | X57: 12875.88 | Y57: 12966.37 | Z57: 12966.37 | AA57: 13432.55 | AB57: 13057.94
A58: 1 | C58: 이연법인세자산 | J58: 1034 | K58: 1034 | L58: 1093 | M58: 1175 | N58: 1222 | O58: 1167 | P58: 1167 | Q58: 1141 | R58: 1338 | S58: 1193 | T58: 1216.28 | U58: 1216.28 | V58: 1306.08 | W58: 1150.03 | X58: 1177.09 | Y58: 1184.13 | Z58: 1184.13 | AA58: 1226.72 | AB58: 1329.81
A59: 1 | C59: 비지배주주지분 | T59: 0 | U59: 0 | V59: 0 | Y59: 0 | Z59: 0 | AA59: 0 | AB59: 0
A60: 1 | C60: 장기차입금 | V60: 3333.33 | W60: 2916.67 | X60: 2500 | Y60: 2083.33 | Z60: 2083.33 | AA60: 1666.67 | AB60: 0
A61: 1 | C61: 매출액(수익) | E61: 166298 | G61: 111918 | H61: 104916 | I61: 137416 | J61: 189771 | K61: 544021 | L61: 116981 | M61: 163437 | N61: 138535 | O61: 211424 | P61: 630377 | Q61: 115506 | R61: 197361 | S61: 193968 | T61: 217774.81 | U61: 724609.81 | V61: 139139.48 | W61: 213655.14 | X61: 192065.78 | Y61: 244481.52 | Z61: 789341.92 | AA61: 189010.55 | AB61: 212989.81
A62: 1 | C62: 매출원가 | E62: 153568 | G62: 102002 | H62: 94134 | I62: 123454 | J62: 187549 | K62: 507139 | L62: 106684 | M62: 147883 | N62: 124055 | O62: 183854 | P62: 562476 | Q62: 96814 | R62: 163746 | S62: 174757 | T62: 190738.86 | U62: 626055.86 | V62: 110316.18 | W62: 167284.32 | X62: 160267.71 | Y62: 219538.39 | Z62: 657406.6 | AA62: 156859.27 | AB62: 171641.61
A63: 1 | C63: 매출총이익 | E63: 12730 | G63: 9916 | H63: 10782 | I63: 13962 | J63: 2222 | K63: 36882 | L63: 10297 | M63: 15554 | N63: 14480 | O63: 27570 | P63: 67901 | Q63: 18692 | R63: 33615 | S63: 19211 | T63: 27035.94 | U63: 98553.94 | V63: 28823.29 | W63: 46370.82 | X63: 31798.07 | Y63: 24943.14 | Z63: 131935.32 | AA63: 32151.29 | AB63: 41348.2
A64: 1 | C64: 판관비 | E64: 9233 | G64: 11043 | H64: 10148 | I64: 12696 | J64: 11811 | K64: 45698 | L64: 10647 | M64: 11104 | N64: 12596 | O64: 14686 | P64: 49033 | Q64: 11879 | R64: 11849 | S64: 13785 | T64: 18804.11 | U64: 56317.11 | V64: 13371.5 | W64: 13023.2 | X64: 16372.1 | Y64: 19575.57 | Z64: 62342.37 | AA64: 14647.77 | AB64: 16387.54
A65: 1 | C65: 영업이익 | E65: 3497 | G65: -1127 | H65: 634 | I65: 1266 | J65: -9589 | K65: -8816 | L65: -350 | M65: 4450 | N65: 1884 | O65: 12884 | P65: 18868 | Q65: 6813 | R65: 21766 | S65: 5426 | T65: 8231.84 | U65: 42236.84 | V65: 15451.79 | W65: 33347.62 | X65: 15425.96 | Y65: 5367.57 | Z65: 69592.94 | AA65: 17503.52 | AB65: 24960.66
A66: 1 | C66: 기타영업외수익 | E66: 1510 | G66: 166 | H66: 610 | I66: 7482 | J66: 4832 | K66: 13090 | L66: 2784 | M66: 1172 | N66: 521 | O66: 323 | P66: 4800 | Q66: 369 | R66: 86 | S66: 110 | T66: 733.37 | U66: 1298.37 | V66: 144.29 | W66: 316.01 | X66: 319.07 | Y66: 3239.91 | Z66: 4019.28 | AA66: 292.11 | AB66: 1206.58
A67: 1 | C67: 기타영업외비용 | E67: 653 | G67: 510 | H67: 1266 | I67: 5762 | J67: 17578 | K67: 25116 | L67: 527 | M67: 123 | N67: 248 | O67: 134 | P67: 1032 | Q67: 260 | R67: 42 | S67: 286 | T67: 397.6 | U67: 985.6 | V67: 55.62 | W67: 48.25 | X67: 212.2 | Y67: 29.17 | Z67: 345.24 | AA67: 40.41 | AB67: 37.46
A68: 1 | C68: 금융수익 | E68: 5813 | G68: 3668 | H68: 8257 | I68: 6495 | J68: 3691 | K68: 22111 | L68: 7183 | M68: 2564 | N68: 3842 | O68: 845 | P68: 14434 | Q68: 4427 | R68: 3387 | S68: 1859 | T68: 5647.04 | U68: 15320.04 | V68: 8907.68 | W68: 5220.41 | X68: 5460.16 | Y68: 6209.93 | Z68: 25798.18 | AA68: 7249.34 | AB68: 5004.28
A69: 1 | C69: 금융비용 | E69: 6246 | G69: 4817 | H69: 9803 | I69: 16494 | J69: -1435 | K69: 29679 | L69: 11995 | M69: 5957 | N69: 6003 | O69: 5459 | P69: 29414 | Q69: 8516 | R69: 9304 | S69: 5000 | T69: 12790.71 | U69: 35610.71 | V69: 14147.18 | W69: 8704.56 | X69: 6847.06 | Y69: 7527.65 | Z69: 37226.45 | AA69: 9006.18 | AB69: 7917.91
A70: 1 | C70: 법인세비용차감전계속사업이익 | E70: 3921 | G70: -2620 | H70: -1568 | I70: -7013 | J70: -17209 | K70: -28410 | L70: -2905 | M70: 2106 | N70: -4 | O70: 8459 | P70: 7656 | Q70: 2833 | R70: 15893 | S70: 2109 | T70: 1423.93 | U70: 22258.93 | V70: 10300.95 | W70: 30131.23 | X70: 14145.93 | Y70: 7260.59 | Z70: 61838.7 | AA70: 15998.38 | AB70: 23216.15
A71: 1 | C71: 법인세비용 | E71: -365 | G71: 348 | H71: -335 | I71: -648 | J71: -1093 | K71: -1728 | L71: 278 | M71: 93 | N71: 198 | O71: 1402 | P71: 1971 | Q71: 431 | R71: 26 | S71: -124 | T71: -5289.85 | U71: -4956.85 | V71: -245.71 | W71: 417.08 | X71: 96.09 | Y71: -7376.97 | Z71: -7109.51 | AA71: -669.22 | AB71: 1059.84
A72: 1 | C72: 당기순이익 | E72: 4286 | G72: -2968 | H72: -1233 | I72: -6365 | J72: -16116 | K72: -26682 | L72: -3183 | M72: 2013 | Q72: 2402 | R72: 15868 | S72: 2234 | T72: 6713.79 | U72: 27217.79 | V72: 10546.67 | W72: 29714.15 | X72: 14049.84 | Y72: 14637.56 | Z72: 68948.22 | AA72: 16667.61 | AB72: 22156.31
A73: 1 | C73: 총포괄손익 | E73: 21420 | G73: -2827 | H73: -1726 | I73: -7920 | J73: -10311 | K73: -22784 | L73: -2500 | M73: 1908 | N73: 55 | O73: 988 | P73: 451 | Q73: 2768 | R73: 16588 | S73: 2083 | T73: 5529.9 | U73: 26968.9 | V73: 11125.79 | W73: 29712.85 | X73: 15547.4 | Y73: 12375.79 | Z73: 68761.83 | AA73: 17441.36 | AB73: 22522.85
A74: 1 | C74: (지배주주지분)당기순이익 | E74: 4286 | G74: -2968 | H74: -1233 | I74: -6365 | J74: -16116 | K74: -26682 | L74: -3183 | M74: 2013 | N74: -202 | O74: 7057 | P74: 5685 | Q74: 2402 | R74: 15868 | S74: 2234 | T74: 6713.79 | U74: 27217.79 | V74: 10546.67 | W74: 29714.15 | X74: 14049.84 | Y74: 14637.56 | Z74: 68948.22 | AA74: 16667.61 | AB74: 22156.31
A75: 1 | C75: 금융손익 | E75: -433 | G75: -1149 | H75: -1546 | I75: -9999 | J75: 5126 | K75: -7568 | L75: -4812 | M75: -3393 | N75: -2161 | O75: -4614 | P75: -14980 | Q75: -4089 | R75: -5917 | S75: -3141 | T75: -7143.67 | U75: -20290.67 | V75: -5239.5 | W75: -3484.15 | X75: -1386.9 | Y75: -1317.72 | Z75: -11428.27 | AA75: -1756.84 | AB75: -2913.63
A76: 1 | C76: 기타영업외손익 | E76: 857 | G76: -344 | H76: -656 | I76: 1720 | J76: -12746 | K76: -12026 | L76: 2257 | M76: 1049 | N76: 273 | O76: 189 | P76: 3768 | Q76: 109 | R76: 44 | S76: -176 | T76: 335.77 | U76: 312.77 | V76: 88.67 | W76: 267.76 | X76: 106.87 | Y76: 3210.74 | Z76: 3674.04 | AA76: 251.7 | AB76: 1169.12
A77: 1 | C77: 계속사업이익 | E77: 4286 | G77: -2968 | H77: -1233 | I77: -6365 | J77: -16116 | K77: -26682 | L77: -3183 | M77: 2013 | Q77: 2402 | R77: 15868 | S77: 2234 | T77: 6713.79 | U77: 27217.79 | V77: 10546.67 | W77: 29714.15 | X77: 14049.84 | Y77: 14637.56 | Z77: 68948.22 | AA77: 16667.61 | AB77: 22156.31
A78: 1 | C78: (비지배주주지분)당기순이익 | V78: 0 | W78: 0 | AA78: 0 | AB78: 0
A79: 1 | C79: 이자수익 | V79: 576.68 | W79: 400.92 | X79: 922.1 | Y79: 987.34 | Z79: 2887.04 | AA79: 1064.78 | AB79: 789.85
A80: 1 | C80: 이자비용 | V80: 3462.5 | W80: 3010.97 | X80: 3040.12 | Y80: 3046.07 | Z80: 12559.66 | AA80: 2998.65 | AB80: 3144.86
A81: 1 | C81: 외환차익 | V81: 5809.42 | W81: 3862.33 | X81: 3295.81 | Y81: 3510.15 | Z81: 16477.71 | AA81: 3089.73 | AB81: 3226.71
A82: 1 | C82: 외환차손 | V82: 6418.45 | W82: 6115.47 | X82: 3773.07 | Y82: 5374.45 | Z82: 21681.44 | AA82: 2962.93 | AB82: 4245.05
A83: 1 | C83: 외화환산이익 | V83: 437.15 | W83: 517.77 | X83: -32.47 | Y83: 506.15 | Z83: 1428.6 | AA83: 1833.46 | AB83: -339.54
A84: 1 | C84: 외화환산손실 | V84: 4165.37 | W84: -558.36 | X84: 170.33 | Y84: -1258.24 | Z84: 2519.1 | AA84: 3044.6 | AB84: 528.01
A85: 1 | C85: 파생상품이익 | V85: 2084.44 | W85: 439.39 | X85: 1274.73 | Y85: 1191.65 | Z85: 4990.21 | AA85: 1261.37 | AB85: 1327.25
A86: 1 | C86: 파생상품손실 | V86: 100.87 | W86: 136.47 | X86: -136.47 | Y86: 365.37 | Z86: 466.24 | AA86: 0 | AB86: 0
A87: 1 | C87: 이자손익 | V87: -2885.82 | W87: -2610.05 | X87: -2118.02 | Y87: -2058.73 | Z87: -9672.62 | AA87: -1933.87 | AB87: -2355.01
A88: 1 | C88: 영업활동으로인한현금흐름 | E88: 10623 | G88: 22413 | H88: -15740 | I88: -17870 | J88: 37775 | K88: 26578 | L88: -29292 | M88: 14728 | N88: -20107 | O88: 21394 | P88: -13277 | Q88: -12374 | R88: -17487 | S88: -1349 | T88: 67922.2 | U88: 36712.2 | V88: -46156.78 | W88: 59531.99 | X88: 58318.39 | Y88: 1177.45 | Z88: 72871.05 | AA88: -76331.59 | AB88: 19318.66
A89: 1 | C89: 이자수취(CF) | E89: 123 | G89: 179 | H89: 199 | I89: 263 | J89: 406 | K89: 1047 | L89: 562 | M89: 681 | N89: 490 | O89: 540 | P89: 2273 | Q89: 755 | R89: 850 | S89: 821 | T89: 766.36 | U89: 3192.36 | V89: 708.77 | W89: 519.1 | X89: 796.51 | Y89: 934.38 | Z89: 2958.76 | AA89: 790.1 | AB89: 814.35
A90: 1 | C90: 법인세납부(CF) | E90: -19 | G90: -49 | H90: -233 | I90: -235 | J90: -167 | K90: -684 | L90: -403 | M90: -578 | N90: -74 | O90: 485 | P90: -570 | Q90: -987 | R90: -151 | S90: 458 | T90: -126.56 | U90: -806.56 | V90: -579.24 | W90: -199.74 | X90: -181.13 | Y90: -404.22 | Z90: -1364.33 | AA90: -718.13 | AB90: -437.46
A91: 1 | C91: 투자활동으로인한현금흐름 | E91: -4004 | G91: -1864 | H91: -1747 | I91: -1328 | J91: -10286 | K91: -15225 | L91: -2713 | M91: 2675 | N91: 7226 | O91: -3524 | P91: 3664 | Q91: -1304 | R91: -2574 | S91: -4842 | T91: -6178.13 | U91: -14898.13 | V91: -3405.46 | W91: -3982.16 | X91: -8356.72 | Y91: -10864.63 | Z91: -26608.97 | AA91: -12043.6 | AB91: -3810.84
A92: 1 | C92: 유형자산의감소 | E92: 2 | G92: 16 | H92: 1 | I92: 0 | J92: 0 | K92: 17 | L92: 8 | M92: 49 | N92: 41 | O92: 36 | P92: 134 | X92: 0 | Y92: 0
A93: 1 | C93: 무형자산의감소 | E93: 0 | O93: 0
A94: 1 | C94: 유형자산의증가 | E94: 4056 | G94: 2839 | H94: 1627 | I94: 1350 | J94: 6375 | K94: 12191 | L94: 2140 | M94: 1654 | N94: 2441 | O94: 2452 | P94: 8687 | Q94: 1497 | R94: 1154 | S94: 2444 | T94: 4076.71 | U94: 9171.71 | V94: 1803.95 | W94: 2075.63 | X94: 2292.47 | Y94: 3740.95 | Z94: 9913 | AA94: 4123.91 | AB94: 3655.7
A95: 1 | C95: CAPEX | E95: 4352 | G95: 2845 | H95: 1872 | I95: 1351 | J95: 6613 | K95: 12681 | L95: 2346 | M95: 5924 | N95: 2814 | O95: 4855 | P95: 15939 | Q95: 1691 | R95: 2529 | S95: 4840 | T95: 9289.53 | U95: 18349.53 | V95: 3348.64 | W95: 2805.15 | X95: 6618.52 | Y95: 6193.4 | Z95: 18965.71 | AA95: 4193.54 | AB95: 4460.18
A96: 1 | C96: 무형자산의증가 | E96: 296 | G96: 6 | H96: 245 | I96: 1 | J96: 238 | K96: 490 | L96: 206 | M96: 4270 | N96: 373 | O96: 2403 | P96: 7252 | Q96: 194 | R96: 1375 | S96: 2396 | T96: 5212.82 | U96: 9177.82 | V96: 1544.69 | W96: 729.52 | X96: 4326.05 | Y96: 2452.45 | Z96: 9052.71 | AA96: 69.63 | AB96: 804.48
A97: 1 | C97: 재무활동으로인한현금흐름 | E97: -4942 | G97: -15747 | H97: -15216 | I97: -1336 | J97: 4482 | K97: -27817 | L97: 6953 | M97: -9276 | N97: -819 | O97: 10922 | P97: 7780 | Q97: 31980 | R97: 16235 | S97: 3587 | T97: -29864 | U97: 21938 | V97: -37647.71 | W97: 9555.04 | X97: 7400.18 | Y97: 6846.89 | Z97: -13845.6 | AA97: 33688.69 | AB97: -11849.37
A98: 1 | C98: 차입금의증가 | E98: 20587 | G98: 16172 | H98: 16355 | I98: 27368 | J98: 42367 | K98: 102262 | L98: 31430 | M98: 17223 | N98: 27781 | O98: 39836 | P98: 116270 | Q98: 57603 | R98: 45824 | S98: 54976 | T98: 39763.36 | U98: 198166.36 | V98: 31485.56 | W98: 66430.27 | X98: 48797.62 | Y98: 53985.05 | Z98: 200698.5 | AA98: 55996.23 | AB98: 70864.23
A99: 1 | C99: 차입금의감소 | E99: 23472 | G99: 29714 | H99: 29251 | I99: 26233 | J99: 36891 | K99: 122089 | L99: 21774 | M99: 23278 | N99: 26088 | O99: 23959 | P99: 95099 | Q99: 20037 | R99: 23849 | S99: 46830 | T99: 62068.43 | U99: 152784.43 | V99: 61680.16 | W99: 53031.07 | X99: 38603.34 | Y99: 47787.13 | Z99: 201101.7 | AA99: 19778.46 | AB99: 80909.11
A100: 1 | C100: 리스부채의상환 | E100: 350 | G100: 354 | H100: 330 | I100: 788 | L100: 409 | M100: 411 | N100: 434 | O100: 438 | P100: 1692 | Q100: 425 | R100: 404 | S100: 463 | T100: 468.43 | U100: 1760.43 | V100: 482.26 | W100: 472.72 | X100: 494.78 | Y100: 499.92 | Z100: 1949.68 | AA100: 505.42 | AB100: 514.65
...

Sheet BS별도
B1: (백만원) | C1: 이름: BS별도H | E1: 4Q21 | F1: 2021 | G1: 1Q22 | H1: 2Q22 | I1: 3Q22 | J1: 4Q22 | K1: 2022 | L1: 1Q23 | M1: 2Q23 | N1: 3Q23 | O1: 4Q23 | P1: 2023 | Q1: 1Q24 | R1: 2Q24 | S1: 3Q24 | T1: 4Q24 | U1: 2024 | V1: 1Q25 | W1: 2Q25 | X1: 3Q25 | Y1: 4Q25 | Z1: 2025 | AA1: 1Q26 | AB1: 2Q26 | AC1: 3Q26 | AD1: 4Q26 | AE1: 2026 | AF1: 1Q27 | AG1: 2Q27 | AH1: 3Q27 | AI1: 4Q27 | AJ1: 2027 | AK1: 1Q28 | AL1: 2Q28 | AM1: 3Q28 | AN1: 4Q28 | AO1: 2028
B2: 별도 | D2: fin json(kship_fin.py)
B3: STX엔진(별) | C3: UPDATE: 26-10-26 | E3: 1 | F3: 2 | G3: 3 | H3: 4 | I3: 5 | J3: 6 | K3: 7 | L3: 8 | M3: 9 | N3: 10 | O3: 11 | P3: 12 | Q3: 13 | R3: 14 | S3: 15 | T3: 16 | U3: 17 | V3: 18 | W3: 19 | X3: 20 | Y3: 21 | Z3: 22 | AA3: 23 | AB3: 24 | AC3: 25 | AD3: 26 | AE3: 27 | AF3: 28 | AG3: 29 | AH3: 30 | AI3: 31 | AJ3: 32 | AK3: 33 | AL3: 34 | AM3: 35 | AN3: 36 | AO3: 37
B4: Account Code | C4: AccountNAME | E4: 2021.12 | F4: 2021.12A | G4: 2022.03 | H4: 2022.06 | I4: 2022.09 | J4: 2022.12 | K4: 2022.12A | L4: 2023.03 | M4: 2023.06 | N4: 2023.09 | O4: 2023.12 | P4: 2023.12A | Q4: 2024.03 | R4: 2024.06 | S4: 2024.09 | T4: 2024.12 | U4: 2024.12A | V4: 2025.03 | W4: 2025.06 | X4: 2025.09 | Y4: 2025.12 | Z4: 2025.12A | AA4: 2026.03 | AB4: 2026.06 | AC4: 2026.09 | AD4: 2026.12 | AE4: 2026.12A | AF4: 2027.03 | AG4: 2027.06 | AH4: 2027.09 | AI4: 2027.12 | AJ4: 2027.12A | AK4: 2028.03 | AL4: 2028.06 | AM4: 2028.09 | AN4: 2028.12 | AO4: 2028.12A
A5: 1 | C5: 유동자산 | E5: 405872 | F5: 405872 | G5: 400593 | H5: 400955 | I5: 411164 | J5: 452931 | K5: 452931 | L5: 467142 | M5: 430434 | N5: 426456 | O5: 473638 | P5: 473638 | Q5: 552266 | R5: 570673 | S5: 545197 | T5: 527154.66 | U5: 527154.66 | V5: 497251.45 | W5: 606147.76 | X5: 638990.13 | Y5: 698966.09 | Z5: 698966.09 | AA5: 743955.36 | AB5: 748842.33
A6: 1 | C6: 현금및현금성자산 | E6: 102715 | F6: 102715 | G6: 106855 | H6: 74388 | I6: 52061 | J6: 84255 | K6: 84255 | L6: 58442 | M6: 65990 | N6: 49445 | O6: 77545 | P6: 77545 | Q6: 98884 | R6: 96304 | S6: 88464 | T6: 122652.27 | U6: 122652.27 | V6: 36540.03 | W6: 101134.73 | X6: 156209.85 | Y6: 152795.42 | Z6: 152795.42 | AA6: 98302.8 | AB6: 100829.96
A7: 1 | C7: 기타유동금융자산 | E7: 1869 | F7: 1869 | G7: 1347 | H7: 1937 | I7: 1970 | L7: 9311 | M7: 369 | N7: 246
A8: 1 | C8: 매출채권및기타채권 | E8: 96356 | F8: 96356 | G8: 75272 | H8: 76904 | I8: 99940 | J8: 115691 | K8: 115691 | L8: 119120 | M8: 109020 | N8: 109440 | O8: 143338 | P8: 143338 | Q8: 101730 | R8: 121927 | S8: 124069 | T8: 91329.36 | U8: 91329.36 | V8: 99087.97 | W8: 137384.39 | X8: 97040.08 | Y8: 138447.21 | Z8: 138447.21 | AA8: 179257.1 | AB8: 134803.19
A9: 1 | C9: 계약자산 | E9: 3792 | F9: 3792 | G9: 5379 | H9: 8663 | I9: 10439 | J9: 7445 | K9: 7445 | L9: 14293 | M9: 13542 | N9: 13328 | O9: 6051 | P9: 6051 | Q9: 8170 | R9: 8362 | S9: 12439 | T9: 10372.02 | U9: 10372.02 | V9: 14089.45 | W9: 14583.59 | X9: 19223.46 | Y9: 24268.64 | Z9: 24268.64 | AA9: 32917.99 | AB9: 40291.51
A10: 1 | C10: 선급금 | E10: 21732 | F10: 21732 | G10: 36915 | H10: 38068 | I10: 34339 | J10: 45188 | K10: 45188 | L10: 53090 | M10: 55911 | N10: 52386 | O10: 50349 | P10: 50349 | Q10: 56958 | R10: 54450 | S10: 37909 | T10: 31880.82 | U10: 31880.82 | V10: 37975.62 | W10: 53600.66 | X10: 76966.04 | Y10: 45155.2 | Z10: 45155.2 | AA10: 66916.51 | AB10: 69202.67
A11: 1 | C11: 선급금등 | E11: 21732 | F11: 21732 | G11: 36915 | H11: 38068 | I11: 34339 | J11: 45188 | K11: 45188 | L11: 53090 | M11: 55911 | N11: 52386 | O11: 50349 | P11: 50349 | Q11: 56958 | R11: 54450 | S11: 37909 | T11: 31880.82 | U11: 31880.82 | V11: 37975.62 | W11: 53600.66 | X11: 76966.04 | Y11: 45155.2 | Z11: 45155.2 | AA11: 66916.51 | AB11: 69202.67
A12: 1 | C12: 기타유동자산 | E12: 27350 | F12: 27350 | G12: 41681 | H12: 44126 | I12: 39377 | J12: 45188 | K12: 45188 | L12: 57300 | M12: 59292 | N12: 56221 | O12: 50349 | P12: 50349 | Q12: 56958 | R12: 54450 | S12: 37909 | T12: 31880.82 | U12: 31880.82 | V12: 37975.62 | W12: 53600.66 | X12: 76966.04 | Y12: 45155.2 | Z12: 45155.2 | AA12: 66916.51 | AB12: 69202.67
A13: 1 | C13: 재고자산 | E13: 173359 | F13: 173359 | G13: 168716 | H13: 189403 | I13: 195954 | J13: 179148 | K13: 179148 | L13: 205238 | M13: 180378 | N13: 197356 | O13: 195192 | P13: 195192 | Q13: 282247 | R13: 287218 | S13: 278451 | T13: 265187.12 | U13: 265187.12 | V13: 304338.01 | W13: 292182.57 | X13: 283099.6 | Y13: 325059.44 | Z13: 325059.44 | AA13: 348560.66 | AB13: 383422.98
A14: 1 | C14: 당기법인세자산(선급법인세) | E14: 81 | F14: 81 | G14: 35 | H14: 58 | I14: 30 | J14: 161 | K14: 161 | L14: 247 | M14: 188 | N14: 259 | O14: 338 | P14: 338 | Q14: 449 | R14: 235 | S14: 113 | T14: 89.04 | U14: 89.04 | V14: 202.74 | W14: 0 | Y14: 0 | Z14: 0
A15: 1 | C15: 유동확정계약자산 | E15: 350 | F15: 350 | G15: 1308 | H15: 5476 | I15: 11393 | J15: 3636 | K15: 3636 | L15: 3034 | M15: 1652 | N15: 161 | T15: 0 | U15: 0
A16: 1 | C16: 단기금융자산 | E16: 350 | F16: 350 | G16: 1308 | H16: 5476 | I16: 11393 | J16: 13435 | K16: 13435 | L16: 3191 | M16: 1655 | N16: 161 | O16: 245 | P16: 245 | Q16: 265 | R16: 631 | S16: 304 | T16: 2099.22 | U16: 2099.22 | V16: 2970.12 | W16: 2591.2 | X16: 2267.23 | Y16: 7272.27 | Z16: 7272.27 | AA16: 14347.17 | AB16: 14513.68
A17: 1 | C17: 비유동자산 | E17: 417202 | F17: 417202 | G17: 415697 | H17: 428603 | I17: 416936 | J17: 384615 | K17: 384615 | L17: 382554 | M17: 395160 | N17: 392066 | O17: 406236 | P17: 406236 | Q17: 398393 | R17: 394807 | S17: 404991 | T17: 410535.95 | U17: 410535.95 | V17: 418370.24 | W17: 415470.15 | X17: 422774.1 | Y17: 426768.34 | Z17: 426768.34 | AA17: 431552.29 | AB17: 431810.94
A18: 1 | C18: 종속기업및관계기업투자 | E18: 480 | F18: 480 | G18: 480 | H18: 480 | I18: 480 | J18: 480 | K18: 480 | L18: 480 | M18: 480 | N18: 480 | O18: 480 | P18: 480 | Q18: 480 | R18: 480 | S18: 480 | T18: 480.39 | U18: 480.39 | V18: 480.39 | W18: 480.39 | X18: 480.39 | Y18: 480.39 | Z18: 480.39 | AA18: 480.39 | AB18: 480.39
A19: 1 | C19: 투자자산 | E19: 596 | F19: 596 | G19: 617 | H19: 790 | I19: 480 | J19: 8388 | K19: 8388 | L19: 480 | M19: 480 | N19: 480 | O19: 9024 | P19: 9024 | Q19: 8974 | R19: 9345 | S19: 9345 | T19: 9650.92 | U19: 9650.92 | V19: 9674.39 | W19: 11424.13 | X19: 13356.27 | Y19: 13446.76 | Z19: 13446.76 | AA19: 13912.94 | AB19: 13538.33
A20: 1 | C20: 유형자산 | E20: 293349 | F20: 293349 | G20: 292930 | H20: 292794 | I20: 291807 | J20: 275550 | K20: 275550 | L20: 274460 | M20: 274399 | N20: 274676 | O20: 275636 | P20: 275636 | Q20: 274203 | R20: 273470 | S20: 273899 | T20: 274013.18 | U20: 274013.18 | V20: 273009.95 | W20: 272162.08 | X20: 272041.99 | Y20: 276298.06 | Z20: 276298.06 | AA20: 275865.77 | AB20: 275361.54
A21: 1 | C21: 무형자산 | E21: 10813 | F21: 10813 | G21: 10622 | H21: 10628 | I21: 4927 | J21: 8804 | K21: 8804 | L21: 8741 | M21: 13881 | N21: 14115 | O21: 15207 | P21: 15207 | Q21: 15260 | R21: 16402 | S21: 19723 | T21: 22836.62 | U21: 22836.62 | V21: 24197.62 | W21: 24870.96 | X21: 27837.23 | Y21: 28831.72 | Z21: 28831.72 | AA21: 28307.74 | AB21: 28571.1
A22: 1 | C22: 투자부동산 | E22: 58778 | F22: 58778 | G22: 58343 | H22: 57907 | I22: 57471 | J22: 57035 | K22: 57035 | L22: 56599 | M22: 56164 | N22: 55728 | O22: 55292 | P22: 55292 | Q22: 54856 | R22: 54420 | S22: 53985 | T22: 53548.82 | U22: 53548.82 | V22: 53113.02 | W22: 52677.22 | X22: 52241.42 | Y22: 51805.62 | Z22: 51805.62 | AA22: 51369.82 | AB22: 50934.02
A23: 1 | C23: 장기매출채권및기타채권 | E23: 6806 | F23: 6806 | G23: 6976 | H23: 5599 | I23: 5417 | J23: 3884 | K23: 3884 | L23: 2004 | M23: 3480 | N23: 2243 | O23: 3618 | P23: 3618 | Q23: 1050 | R23: 3586 | S23: 2431 | T23: 582.2 | U23: 582.2 | V23: 484.9 | W23: 484.9 | X23: 484.9 | Y23: 222.04 | Z23: 222.04 | AA23: 222.04 | AB23: 222.04
A24: 1 | C24: 비유동확정계약자산 | E24: 116 | F24: 116 | G24: 137 | H24: 310
A25: 1 | C25: 기타비유동자산 | E25: 27720 | F25: 27720 | G25: 28401 | H25: 45162 | I25: 44950 | J25: 27933 | K25: 27933 | L25: 30583 | M25: 37889 | N25: 36041 | O25: 46788 | P25: 46788 | Q25: 43327 | R25: 37118 | S25: 44856 | T25: 47670.29 | U25: 47670.29 | V25: 55623.46 | W25: 51532.58 | X25: 54032.38 | Y25: 54407.5 | Z25: 54407.5 | AA25: 60106.78 | AB25: 61512.53
A26: 1 | C26: 자산총계 | E26: 823074 | F26: 823074 | G26: 816290 | H26: 829558 | I26: 828100 | J26: 837546 | K26: 837546 | L26: 849696 | M26: 825594 | N26: 818522 | O26: 879874 | P26: 879874 | Q26: 950659 | R26: 965480 | S26: 950188 | T26: 937690.62 | U26: 937690.62 | V26: 915621.69 | W26: 1021617.9 | X26: 1061764.2 | Y26: 1125734.4 | Z26: 1125734.4 | AA26: 1175507.6 | AB26: 1180653.3
A27: 1 | C27: 유동부채 | E27: 485167 | F27: 485167 | G27: 481597 | H27: 496193 | I27: 505630 | J27: 535074 | K27: 535074 | L27: 550972 | M27: 526597 | N27: 521090 | O27: 571394 | P27: 571394 | Q27: 642802 | R27: 645408 | S27: 628054 | T27: 617217.75 | U27: 617217.75 | V27: 582997.72 | W27: 660191.77 | X27: 685454.11 | Y27: 739416.83 | Z27: 739416.83 | AA27: 773946.48 | AB27: 757572.63
A28: 1 | C28: 매입채무및기타채무 | E28: 69062 | F28: 69062 | G28: 71709 | H28: 73414 | I28: 67827 | J28: 113827 | K28: 113827 | L28: 99870 | M28: 94831 | N28: 101280 | O28: 129153 | P28: 129153 | Q28: 122860 | R28: 113745 | S28: 106033 | T28: 130891.92 | U28: 130891.92 | V28: 119099.54 | W28: 108069.23 | X28: 103305.28 | Y28: 158154.38 | Z28: 158154.38 | AA28: 117403.29 | AB28: 114135.87
A29: 1 | C29: 단기차입금 | E29: 258774 | F29: 258774 | G29: 245826 | H29: 234164 | I29: 239521 | J29: 237830 | K29: 237830 | L29: 251122 | M29: 244348 | N29: 245130 | O29: 259304 | P29: 259304 | Q29: 299178 | R29: 324066 | S29: 328482 | T29: 312315.66 | U29: 312315.66 | V29: 282732.55 | W29: 294527.04 | X29: 306662.23 | Y29: 311529.62 | Z29: 311529.62 | AA29: 351081.7 | AB29: 343225.74
A30: 1 | C30: 선수금 | E30: 115116 | F30: 115116 | G30: 126961 | H30: 142740 | I30: 149380 | J30: 148334 | K30: 148334 | L30: 172073 | M30: 153302 | N30: 144849 | O30: 164569 | P30: 164569 | Q30: 201073 | R30: 184940 | S30: 173409 | T30: 152879.4 | U30: 152879.4 | V30: 156566.2 | W30: 228529.26 | X30: 253231.74 | Y30: 246226.99 | Z30: 246226.99 | AA30: 284238.47 | AB30: 273941.24
A31: 1 | C31: 기타유동부채 | E31: 133842 | F31: 133842 | G31: 143530 | H31: 156809 | I31: 163974 | J31: 148334 | K31: 148334 | L31: 172073 | M31: 153303 | N31: 144881 | O31: 164569 | P31: 164569 | Q31: 201073 | R31: 184940 | S31: 173409 | T31: 152879.4 | U31: 152879.4 | V31: 156566.2 | W31: 228529.26 | X31: 253231.74 | Y31: 246226.99 | Z31: 246226.99 | AA31: 284238.47 | AB31: 273941.24
A32: 1 | C32: 계약부채 | E32: 19819 | F32: 19819 | G32: 15981 | H32: 23164 | I32: 21926 | J32: 22131 | K32: 22131 | L32: 17119 | M32: 25586 | N32: 22713 | O32: 12408 | P32: 12408 | Q32: 15933 | R32: 18411 | S32: 15683 | T32: 16564.66 | U32: 16564.66 | V32: 20824.64 | W32: 24089.25 | X32: 16654.72 | Y32: 16414.21 | Z32: 16414.21 | AA32: 14540.06 | AB32: 18282.17
A33: 1 | C33: 단기충당부채 | E33: 3350 | F33: 3350 | G33: 3248 | H33: 3556 | I33: 3582 | J33: 7637 | K33: 7637 | L33: 6994 | M33: 7057 | N33: 6817 | O33: 5419 | P33: 5419 | Q33: 3758 | R33: 3868 | S33: 4025 | T33: 4057.78 | U33: 4057.78 | V33: 3652.06 | W33: 4718.02 | X33: 5313.64 | Y33: 5965.25 | Z33: 5965.25 | AA33: 5988.67 | AB33: 6742.73
A34: 1 | C34: 단기파생상품부채 | E34: 320 | F34: 320 | G34: 1303 | H34: 5086 | I34: 8800 | J34: 5099 | K34: 5099 | L34: 3750 | M34: 1472 | N34: 269 | S34: 67 | T34: 0 | U34: 0 | W34: 136.47 | Y34: 365.37 | Z34: 365.37 | AA34: 340.01 | AB34: 113.4
A35: 1 | C35: 단기금융부채 | E35: 320 | F35: 320 | G35: 1303 | H35: 5086 | I35: 8800 | J35: 5099 | K35: 5099 | L35: 3750 | M35: 1472 | N35: 269 | S35: 67 | T35: 0 | U35: 0 | W35: 136.47 | Y35: 365.37 | Z35: 365.37 | AA35: 340.01 | AB35: 113.4
A36: 1 | C36: 비유동부채 | E36: 62829 | F36: 62829 | G36: 63778 | H36: 65447 | I36: 64260 | J36: 52289 | K36: 52289 | L36: 53933 | M36: 55061 | N36: 56398 | O36: 61441 | P36: 61441 | Q36: 62779 | R36: 64063 | S36: 67717 | T36: 62949.37 | U36: 62949.37 | V36: 67459.88 | W36: 68297.7 | X36: 69769.71 | Y36: 68295.34 | Z36: 68295.34 | AA36: 68360.64 | AB36: 69118.28
A37: 1 | C37: 확정급여부채 | E37: 37822 | F37: 37822 | G37: 38382 | H37: 39270 | I37: 39628 | J37: 31428 | K37: 31428 | L37: 32304 | M37: 33129 | N37: 33653 | O37: 35753 | P37: 35753 | Q37: 36629 | R37: 37141 | S37: 38123 | T37: 38703.49 | U37: 38703.49 | V37: 39698.49 | W37: 40688.94 | X37: 41679.69 | Y37: 41792.43 | Z37: 41792.43 | AA37: 42881.13 | AB37: 43871.59
A38: 1 | C38: 이연법인세부채 | E38: 20151 | F38: 20151 | G38: 20439 | H38: 20124 | I38: 18129 | J38: 15323 | K38: 15323 | L38: 15650 | M38: 15811 | N38: 16080 | O38: 18509 | P38: 18509 | Q38: 18509 | R38: 18360 | S38: 18444 | T38: 12296.12 | U38: 12296.12 | V38: 12078.9 | W38: 12011.73 | X38: 11986.17 | Y38: 3948.84 | Z38: 3948.84 | AA38: 2842 | AB38: 2711.72
A39: 1 | C39: 장기충당부채 | E39: 364 | F39: 364 | G39: 400
A40: 1 | C40: 장기파생상품부채 | E40: 152 | F40: 152 | G40: 133 | H40: 308
A41: 1 | C41: 장기금융부채 | E41: 152 | F41: 152 | G41: 133 | H41: 308
A42: 1 | C42: 기타비유동부채 | E42: 4340 | F42: 4340 | G42: 4424 | H42: 5745 | I42: 6503
A43: 1 | C43: 부채총계 | E43: 547996 | F43: 547996 | G43: 545375 | H43: 561640 | I43: 569890 | J43: 587363 | K43: 587363 | L43: 604905 | M43: 581658 | N43: 577488 | O43: 632835 | P43: 632835 | Q43: 705581 | R43: 709471 | S43: 695771 | T43: 680167.12 | U43: 680167.12 | V43: 650457.59 | W43: 728489.47 | X43: 755223.82 | Y43: 807712.16 | Z43: 807712.16 | AA43: 842307.12 | AB43: 826690.91
A44: 1 | C44: 자본금 | E44: 69141 | F44: 69141 | G44: 69141 | H44: 69141 | I44: 69141 | J44: 69141 | K44: 69141 | L44: 69141 | M44: 69141 | N44: 69141 | O44: 69141 | P44: 69141 | Q44: 69141 | R44: 69141 | S44: 69141 | T44: 69140.75 | U44: 69140.75 | V44: 100370.28 | W44: 100370.28 | X44: 100370.28 | Y44: 100370.28 | Z44: 100370.28 | AA44: 100370.28 | AB44: 100370.28
A45: 1 | C45: 자본잉여금 | E45: 460456 | F45: 460456 | G45: 460456 | H45: 460456 | I45: 460456 | J45: 460456 | K45: 460456 | L45: 460456 | M45: 460456 | N45: 460456 | O45: 460456 | P45: 460456 | Q45: 460456 | R45: 460456 | S45: 460456 | T45: 460455.49 | U45: 460455.49 | V45: 118096.01 | W45: 118096.01 | X45: 118096.01 | Y45: 118096.01 | Z45: 118096.01 | AA45: 118096.01 | AB45: 118096.01
A46: 1 | C46: 기타자본 | E46: 94221 | F46: 94221 | G46: 94221 | H46: 94221 | I46: 94221 | J46: 94221 | K46: 94221 | L46: 94221 | M46: 94221 | N46: 94221 | O46: 94221 | P46: 94221 | Q46: 94221 | R46: 94221 | S46: 94221 | T46: 94220.47 | U46: 94220.47 | V46: -130.19 | W46: -130.19 | X46: -130.19 | Y46: -130.19 | Z46: -130.19 | AA46: -130.19 | AB46: -130.19
A47: 1 | C47: 기타포괄이익누계액 | E47: 46124 | F47: 46124 | G47: 46132 | H47: 46115 | I47: 43793 | J47: 46634 | K47: 46634 | L47: 46596 | M47: 46643 | N47: 46725 | O47: 45248 | P47: 45248 | Q47: 45245 | R47: 45405 | S47: 45414 | T47: 45843.32 | U47: 45843.32 | V47: 45895.24 | W47: 46431.85 | X47: 47157.4 | Y47: 46542.89 | Z47: 46542.89 | AA47: 46078.18 | AB47: 45851.63
A48: 1 | C48: 이익잉여금 | E48: -394864 | F48: -394864 | G48: -399035 | H48: -402015 | I48: -409401 | J48: -420269 | K48: -420269 | L48: -425623 | M48: -426525 | N48: -429509 | O48: -422027 | P48: -422027 | Q48: -423985 | R48: -413214 | S48: -414815 | T48: -412136.54 | U48: -412136.54 | V48: 932.75 | W48: 28360.48 | X48: 41046.92 | Y48: 53143.27 | Z48: 53143.27 | AA48: 68786.24 | AB48: 89774.63
A49: 1 | C49: 자본총계 | E49: 275078 | F49: 275078 | G49: 270915 | H49: 267918 | I49: 258210 | J49: 250183 | K49: 250183 | L49: 244791 | M49: 243936 | N49: 241034 | O49: 247039 | P49: 247039 | Q49: 245078 | R49: 256009 | S49: 254417 | T49: 257523.49 | U49: 257523.49 | V49: 265164.1 | W49: 293128.43 | X49: 306540.42 | Y49: 318022.26 | Z49: 318022.26 | AA49: 333200.53 | AB49: 353962.36
A50: 1 | C50: 부채와자본총계 | E50: 823074 | F50: 823074 | G50: 816290 | H50: 829558 | I50: 828100 | J50: 837546 | K50: 837546 | L50: 849696 | M50: 825594 | N50: 818522 | O50: 879874 | P50: 879874 | Q50: 950659 | R50: 965480 | S50: 950188 | T50: 937690.62 | U50: 937690.62 | V50: 915621.69 | W50: 1021617.9 | X50: 1061764.2 | Y50: 1125734.4 | Z50: 1125734.4 | AA50: 1175507.6 | AB50: 1180653.3
A51: 1 | C51: 지배주주지분 | E51: 275078 | F51: 275078 | G51: 270915 | H51: 267918 | I51: 258210 | J51: 250183 | K51: 250183 | L51: 244791 | M51: 243936 | N51: 241034 | O51: 247039 | P51: 247039 | Q51: 245078 | R51: 256009 | S51: 254417 | T51: 257523.49 | U51: 257523.49 | V51: 265164.1 | W51: 293128.43 | X51: 306540.42 | Y51: 318022.26 | Z51: 318022.26 | AA51: 333200.53 | AB51: 353962.36
A52: 1 | C52: 총차입금 | E52: 258774 | F52: 258774 | G52: 245826 | H52: 234164 | I52: 239521 | J52: 237830 | K52: 237830 | L52: 251122 | M52: 244348 | N52: 245130 | O52: 259304 | P52: 259304 | Q52: 299178 | R52: 324066 | S52: 328482 | T52: 312315.66 | U52: 312315.66 | V52: 286065.88 | W52: 297443.71 | X52: 309162.23 | Y52: 313612.95 | Z52: 313612.95 | AA52: 352748.37 | AB52: 343225.74
A53: 1 | C53: 순차입금 | E53: 155709 | F53: 155709 | G53: 137663 | H53: 154300 | I53: 176067 | J53: 140140 | K53: 140140 | L53: 189489 | M53: 176703 | N53: 195524 | O53: 181514 | P53: 181514 | Q53: 200029 | R53: 227131 | S53: 239714 | T53: 187564.17 | U53: 187564.17 | V53: 246555.73 | W53: 193717.78 | X53: 150685.15 | Y53: 153545.26 | Z53: 153545.26 | AA53: 240098.4 | AB53: 227882.1
A54: 1 | C54: 이자발생자산 | E54: 103065 | F54: 103065 | G54: 108163 | H54: 79864 | I54: 63454 | J54: 105598 | K54: 105598 | L54: 61633 | M54: 67645 | N54: 49606 | O54: 86334 | P54: 86334 | Q54: 107643 | R54: 105800 | S54: 97633 | T54: 133922.02 | U54: 133922.02 | V54: 48704.15 | W54: 114669.67 | X54: 171352.96 | Y54: 173034.06 | Z54: 173034.06 | AA54: 126082.52 | AB54: 128401.58
A55: 1 | C55: 단기금융상품 | J55: 8945 | K55: 8945 | O55: 245 | P55: 245 | Q55: 250 | R55: 175 | S55: 177 | T55: 186.4 | U55: 186.4 | V55: 192.05 | W55: 335.26 | X55: 308.59 | Y55: 6009.5 | Z55: 6009.5 | AA55: 12950.3 | AB55: 13183.48
A56: 1 | C56: 유동파생상품자산 | J56: 854 | K56: 854 | L56: 157 | M56: 3 | Q56: 15 | R56: 456 | S56: 127 | T56: 1912.82 | U56: 1912.82 | V56: 2778.07 | W56: 2255.94 | X56: 1958.64 | Y56: 1262.77 | Z56: 1262.77 | AA56: 1396.87 | AB56: 1330.2
A57: 1 | C57: 장기금융자산 | J57: 7908 | K57: 7908 | O57: 8544 | P57: 8544 | Q57: 8494 | R57: 8865 | S57: 8865 | T57: 9170.53 | U57: 9170.53 | V57: 9194 | W57: 10943.74 | X57: 12875.88 | Y57: 12966.37 | Z57: 12966.37 | AA57: 13432.55 | AB57: 13057.94
A58: 1 | C58: 당기법인세부채(미지급법인세) | R58: 18 | W58: 122.51 | X58: 226.28 | Y58: 628.52 | Z58: 628.52 | AA58: 254.13 | AB58: 1131.48
A59: 1 | C59: 장기차입금 | V59: 3333.33 | W59: 2916.67 | X59: 2500 | Y59: 2083.33 | Z59: 2083.33 | AA59: 1666.67 | AB59: 0
A60: 1 | C60: 매출액(수익) | E60: 151774 | G60: 105667 | H60: 97882 | I60: 127452 | J60: 183734 | K60: 514735 | L60: 107440 | M60: 152706 | N60: 128856 | O60: 207937 | P60: 596939 | Q60: 104766 | R60: 188265 | S60: 184391 | T60: 210535.76 | U60: 687957.76 | V60: 128358.99 | W60: 203266.1 | X60: 182355.89 | Y60: 230837.49 | Z60: 744818.47 | AA60: 177968.18 | AB60: 203304.81
A61: 1 | C61: 매출원가 | E61: 143366 | G61: 98006 | H61: 90104 | I61: 117455 | J61: 185083 | K61: 490648 | L61: 101507 | M61: 141996 | N61: 118151 | O61: 178994 | P61: 540648 | Q61: 90336 | R61: 160310 | S61: 168527 | T61: 185741.93 | U61: 604914.93 | V61: 103364.44 | W61: 162453.25 | X61: 154679.16 | Y61: 209087.33 | Z61: 629584.18 | AA61: 150128.93 | AB61: 166101.53
A62: 1 | C62: 매출총이익 | E62: 8408 | G62: 7661 | H62: 7778 | I62: 9997 | J62: -1349 | K62: 24087 | L62: 5933 | M62: 10710 | N62: 10705 | O62: 28943 | P62: 56291 | Q62: 14430 | R62: 27955 | S62: 15864 | T62: 24793.83 | U62: 83042.83 | V62: 24994.55 | W62: 40812.85 | X62: 27676.73 | Y62: 21750.15 | Z62: 115234.28 | AA62: 27839.26 | AB62: 37203.28
A63: 1 | C63: 판관비 | E63: 3938 | G63: 9519 | H63: 8396 | I63: 9998 | J63: 8060 | K63: 35973 | L63: 8220 | M63: 8720 | N63: 10561 | O63: 12228 | P63: 39729 | Q63: 9558 | R63: 9138 | S63: 11380 | T63: 15594.89 | U63: 45670.89 | V63: 10288.5 | W63: 10221.68 | X63: 13448.64 | Y63: 16522.16 | Z63: 50480.98 | AA63: 11357.24 | AB63: 13203.91
A64: 1 | C64: 영업이익 | E64: 4470 | G64: -1858 | H64: -618 | I64: -1 | J64: -9409 | K64: -11886 | L64: -2287 | M64: 1990 | N64: 144 | O64: 16715 | P64: 16562 | Q64: 4872 | R64: 18817 | S64: 4484 | T64: 9198.94 | U64: 37371.94 | V64: 14706.05 | W64: 30591.17 | X64: 14228.09 | Y64: 5227.99 | Z64: 64753.3 | AA64: 16482.02 | AB64: 23999.37
A65: 1 | C65: 기타영업외수익 | E65: 2021 | G65: 106 | H65: 598 | I65: 7464 | J65: 4821 | K65: 12989 | L65: 2770 | M65: 1233 | N65: 291 | O65: 221 | P65: 4515 | Q65: 324 | R65: 71 | S65: 63 | T65: 688.04 | U65: 1146.04 | V65: 75.46 | W65: 225.8 | X65: 296.37 | Y65: 3070.28 | Z65: 3667.91 | AA65: 243.34 | AB65: 1104.45
A66: 1 | C66: 기타영업외비용 | E66: 653 | G66: 510 | H66: 1173 | I66: 6098 | J66: 17412 | K66: 25193 | L66: 364 | M66: 123 | N66: 248 | O66: 112 | P66: 847 | Q66: 261 | R66: 36 | S66: 286 | T66: 392.46 | U66: 975.46 | V66: 54.76 | W66: 48.25 | X66: 209.14 | Y66: 24.38 | Z66: 336.53 | AA66: 39.21 | AB66: 37.44
A67: 1 | C67: 금융수익 | E67: 5707 | G67: 3485 | H67: 7944 | I67: 6052 | J67: 4384 | K67: 21865 | L67: 7007 | M67: 2296 | N67: 3232 | O67: 1572 | P67: 14107 | Q67: 4043 | R67: 3469 | S67: 1687 | T67: 5234.29 | U67: 14433.29 | V67: 8761.54 | W67: 5127.74 | X67: 5374.05 | Y67: 6145.05 | Z67: 25408.38 | AA67: 7142.89 | AB67: 4894.05
A68: 1 | C68: 금융비용 | E68: 6216 | G68: 4804 | H68: 9801 | I68: 16487 | J68: -1459 | K68: 29633 | L68: 11907 | M68: 5916 | N68: 5922 | O68: 5239 | P68: 28984 | Q68: 8429 | R68: 9234 | S68: 4742 | T68: 12690.42 | U68: 35095.42 | V68: 13771.76 | W68: 8281.3 | X68: 6989.43 | Y68: 7573.23 | Z68: 36615.72 | AA68: 8860.89 | AB68: 7882.02
A69: 1 | C69: 법인세비용차감전계속사업이익 | E69: 5329 | G69: -3581 | H69: -3050 | I69: -9070 | J69: -16157 | K69: -31858 | L69: -4781 | M69: -520 | N69: -2503 | O69: 13157 | P69: 5353 | Q69: 549 | R69: 13087 | S69: 1206 | T69: 2038.4 | U69: 16880.4 | V69: 9716.53 | W69: 27615.15 | X69: 12699.95 | Y69: 6845.71 | Z69: 56877.34 | AA69: 14968.14 | AB69: 22078.42
A70: 1 | C70: 법인세비용 | E70: -627 | G70: 354 | H70: -303 | I70: -1921 | J70: -1899 | K70: -3769 | L70: 337 | M70: 148 | N70: 246 | O70: 841 | P70: 1572 | Q70: 315 | R70: 147 | S70: -328 | T70: -5889.48 | U70: -5755.48 | V70: -232.67 | W70: 187.43 | X70: 13.51 | Y70: -7657.11 | Z70: -7688.84 | AA70: -674.84 | AB70: 1090.03
A71: 1 | C71: 당기순이익 | E71: 5956 | G71: -3935 | H71: -2747 | I71: -7149 | J71: -14258 | K71: -28089 | L71: -5118 | M71: -668 | Q71: 234 | R71: 12940 | S71: 1534 | T71: 7927.87 | U71: 22635.87 | V71: 9949.2 | W71: 27427.73 | X71: 12686.44 | Y71: 14502.83 | Z71: 64566.2 | AA71: 15642.98 | AB71: 20988.39
A72: 1 | C72: 총포괄손익 | E72: 23149 | G72: -3927 | H72: -2764 | I72: -9459 | J72: -7788 | K72: -23938 | L72: -5156 | M72: -621 | N72: -2667 | O72: 6364 | P72: -2080 | Q72: 230 | R72: 13100 | S72: 1544 | T72: 5641.2 | U72: 20515.2 | V72: 10001.12 | W72: 27964.33 | X72: 13411.98 | Y72: 11481.84 | Z72: 62859.27 | AA72: 15178.27 | AB72: 20761.83
A73: 1 | C73: 금융손익 | E73: -509 | G73: -1319 | H73: -1857 | I73: -10435 | J73: 5843 | K73: -7768 | L73: -4900 | M73: -3620 | N73: -2690 | O73: -3667 | P73: -14877 | Q73: -4386 | R73: -5765 | S73: -3055 | T73: -7456.13 | U73: -20662.13 | V73: -5010.22 | W73: -3153.56 | X73: -1615.38 | Y73: -1428.18 | Z73: -11207.34 | AA73: -1718 | AB73: -2987.97
A74: 1 | C74: 기타영업외손익 | E74: 1368 | G74: -404 | H74: -575 | I74: 1366 | J74: -12591 | K74: -12204 | L74: 2406 | M74: 1110 | N74: 43 | O74: 109 | P74: 3668 | Q74: 63 | R74: 35 | S74: -223 | T74: 295.58 | U74: 170.58 | V74: 20.7 | W74: 177.55 | X74: 87.23 | Y74: 3045.9 | Z74: 3331.38 | AA74: 204.13 | AB74: 1067.01
A75: 1 | C75: (지배주주지분)당기순이익 | E75: 5956 | G75: -3935 | H75: -2747 | I75: -7149 | J75: -14258 | K75: -28089 | L75: -5118 | M75: -668 | Q75: 234 | R75: 12940 | S75: 1534 | T75: 7927.87 | U75: 22635.87 | V75: 9949.2 | W75: 27427.73 | X75: 12686.44 | Y75: 14502.83 | Z75: 64566.2 | AA75: 15642.98 | AB75: 20988.39
A76: 1 | C76: 계속사업이익 | E76: 5956 | G76: -3935 | H76: -2747 | I76: -7149 | J76: -14258 | K76: -28089 | L76: -5118 | M76: -668 | Q76: 234 | R76: 12940 | S76: 1534 | T76: 7927.87 | U76: 22635.87 | V76: 9949.2 | W76: 27427.73 | X76: 12686.44 | Y76: 14502.83 | Z76: 64566.2 | AA76: 15642.98 | AB76: 20988.39
A77: 1 | C77: 영업활동으로인한현금흐름 | E77: 10932 | G77: 21572 | H77: -15753 | I77: -20263 | J77: 38307 | K77: 23863 | L77: -30265 | M77: 13953 | N77: -23171 | O77: 20519 | P77: -18964 | Q77: -9647 | R77: -16675 | S77: -6467 | T77: 69391.01 | U77: 36602.01 | V77: -45360.66 | W77: 58870.67 | X77: 55201.46 | Y77: 772.44 | Z77: 69483.91 | AA77: -76767.65 | AB77: 17789.56
A78: 1 | C78: 이자수취(CF) | E78: 123 | G78: 179 | H78: 199 | I78: 248 | J78: 420 | K78: 1046 | L78: 557 | M78: 666 | N78: 468 | O78: 519 | P78: 2210 | Q78: 726 | R78: 813 | S78: 771 | T78: 728.82 | U78: 3038.82 | V78: 676.13 | W78: 491.47 | X78: 763.13 | Y78: 906.33 | Z78: 2837.06 | AA78: 759.38 | AB78: 782.11
A79: 1 | C79: 법인세납부(CF) | E79: -19 | G79: -23 | H79: -30 | I79: -38 | J79: -64 | K79: -155 | L79: -86 | M79: 59 | N79: -71 | O79: -79 | P79: -177 | Q79: -426 | R79: 529 | S79: -117 | T79: -111.69 | U79: -125.69 | V79: -103.36 | W79: -54.96 | X79: -116.81 | Y79: -138.82 | Z79: -413.95 | AA79: -692.36 | AB79: -288.49
A80: 1 | C80: 투자활동으로인한현금흐름 | E80: -3908 | G80: -1867 | H80: -1658 | I80: -1349 | J80: -10287 | K80: -15161 | L80: -2725 | M80: 2646 | N80: 7221 | O80: -3566 | P80: 3576 | Q80: -1302 | R80: -2479 | S80: -4817 | T80: -6023.35 | U80: -14621.35 | V80: -3384.58 | W80: -3938 | X80: -8326.13 | Y80: -10840.86 | Z80: -26489.57 | AA80: -12042.32 | AB80: -3810.41
A81: 1 | C81: 유형자산의감소 | E81: 2 | G81: 16 | H81: 1 | I81: 0 | J81: 0 | K81: 17 | L81: 2 | M81: 0 | N81: 40 | O81: 0 | P81: 42 | X81: 0 | Y81: 0
A82: 1 | C82: 무형자산의감소 | E82: 0 | O82: 0
A83: 1 | C83: 유형자산의증가 | E83: 3955 | G83: 2833 | H83: 1545 | I83: 1333 | J83: 6370 | K83: 12081 | L83: 2139 | M83: 1628 | N83: 2440 | O83: 2450 | P83: 8657 | Q83: 1489 | R83: 1061 | S83: 2419 | T83: 3921.59 | U83: 8890.59 | V83: 1784.27 | W83: 2032.07 | X83: 2261.89 | Y83: 3717.21 | Z83: 9795.44 | AA83: 4122.64 | AB83: 3655.69
A84: 1 | C84: CAPEX | E84: 4251 | G84: 2839 | H84: 1790 | I84: 1334 | J84: 6608 | K84: 12571 | L84: 2345 | M84: 5898 | N84: 2813 | O84: 4854 | P84: 15910 | Q84: 1683 | R84: 2436 | S84: 4815 | T84: 9134.41 | U84: 18068.41 | V84: 3328.96 | W84: 2761.59 | X84: 6587.94 | Y84: 6169.66 | Z84: 18848.15 | AA84: 4192.27 | AB84: 4460.17
A85: 1 | C85: 무형자산의증가 | E85: 296 | G85: 6 | H85: 245 | I85: 1 | J85: 238 | K85: 490 | L85: 206 | M85: 4270 | N85: 373 | O85: 2404 | P85: 7253 | Q85: 194 | R85: 1375 | S85: 2396 | T85: 5212.82 | U85: 9177.82 | V85: 1544.69 | W85: 729.52 | X85: 4326.05 | Y85: 2452.45 | Z85: 9052.71 | AA85: 69.63 | AB85: 804.48
A86: 1 | C86: 재무활동으로인한현금흐름 | E86: -4764 | G86: -15565 | H86: -15056 | I86: -715 | J86: 4174 | K86: -27162 | L86: 7177 | M86: -9051 | N86: -595 | O86: 11147 | P86: 8678 | Q86: 32205 | R86: 16442 | S86: 3853 | T86: -29591.91 | U86: 22908.09 | V86: -37367.01 | W86: 9831.59 | X86: 7699.62 | Y86: 7147.42 | Z86: -12688.38 | AA86: 33992.33 | AB86: -11543.99
A87: 1 | C87: 차입금의증가 | E87: 20587 | G87: 16172 | H87: 16355 | I87: 27368 | J87: 42367 | K87: 102262 | L87: 31430 | M87: 17223 | N87: 27781 | O87: 39836 | P87: 116270 | Q87: 57603 | R87: 45824 | S87: 54975 | T87: 39764.36 | U87: 198166.36 | V87: 31485.56 | W87: 66430.27 | X87: 48797.62 | Y87: 53985.05 | Z87: 200698.5 | AA87: 55996.23 | AB87: 70864.23
A88: 1 | C88: 차입금의감소 | E88: 23472 | G88: 29714 | H88: 29251 | I88: 26233 | J88: 36891 | K88: 122089 | L88: 21774 | M88: 23278 | N88: 26088 | O88: 23959 | P88: 95099 | Q88: 20037 | R88: 23849 | S88: 46830 | T88: 62068.43 | U88: 152784.43 | V88: 61680.16 | W88: 53031.07 | X88: 38603.34 | Y88: 47787.13 | Z88: 201101.7 | AA88: 19778.46 | AB88: 80909.11
A89: 1 | C89: 리스부채의상환 | E89: 173 | G89: 172 | H89: 170 | I89: 167 | J89: 180 | K89: 689 | L89: 185 | M89: 185 | N89: 211 | O89: 213 | P89: 794 | Q89: 200 | R89: 188 | S89: 195 | T89: 197.79 | U89: 780.79 | V89: 201.56 | W89: 196.18 | X89: 195.33 | Y89: 199.38 | Z89: 792.45 | AA89: 201.77 | AB89: 209.28
A90: 1 | C90: 이자지급(CF) | E90: -1506 | G90: -1616 | H90: -1787 | I90: -1911 | J90: -2401 | K90: -7715 | L90: -2632 | M90: -2708 | N90: -2576 | O90: -4377 | P90: -12293 | Q90: -3486 | R90: -3471 | S90: -3891 | T90: -4378.41 | U90: -15226.41 | V90: -4699.27 | W90: -3804.76 | X90: -3280.91 | Y90: -3637.66 | Z90: -15422.6 | AA90: -2387.88 | AB90: -3035.56
A91: 1 | C91: 현금및현금성자산의증감 | E91: 2260 | G91: 4140 | H91: -32467 | I91: -22327 | J91: 32194 | K91: -18460 | L91: -25813 | M91: 7548 | N91: -16545 | O91: 28100 | P91: -6710 | Q91: 21256 | R91: -2712 | S91: -7431 | T91: 33775.75 | U91: 44888.75 | V91: -86112.24 | W91: 64764.26 | X91: 54574.94 | Y91: -2921 | Z91: 30305.96 | AA91: -54817.65 | AB91: 2435.17
A92: 1 | C92: 기말현금및현금성자산 | E92: 2260 | G92: 106855 | H92: -32467 | I92: -22327 | J92: 32194 | K92: 84255 | L92: 58442 | M92: 7548 | N92: -16545 | O92: 28100 | P92: 77545 | Q92: 98884 | R92: -2580 | S92: -7840 | T92: 34188.27 | U92: 122652.27 | V92: 36540.03 | W92: 64594.7 | X92: 55075.12 | Y92: -3414.43 | Z92: 152795.42 | AA92: 98302.8 | AB92: 2527.16

Sheet subQ
A1: YQ | C1: subQ 분기 서브모델(억원, U=100) | E1: 4Q21 | F1: 2021 | G1: 1Q22 | H1: 2Q22 | I1: 3Q22 | J1: 4Q22 | K1: 2022 | L1: 1Q23 | M1: 2Q23 | N1: 3Q23 | O1: 4Q23 | P1: 2023 | Q1: 1Q24 | R1: 2Q24 | S1: 3Q24 | T1: 4Q24 | U1: 2024 | V1: 1Q25 | W1: 2Q25 | X1: 3Q25 | Y1: 4Q25 | Z1: 2025 | AA1: 1Q26 | AB1: 2Q26 | AC1: 3Q26 | AD1: 4Q26 | AE1: 2026 | AF1: 1Q27 | AG1: 2Q27 | AH1: 3Q27 | AI1: 4Q27 | AJ1: 2027 | AK1: 1Q28 | AL1: 2Q28 | AM1: 3Q28 | AN1: 4Q28 | AO1: 2028
A2: A=이름(key) B=그룹 C=단위 D=FnGuide 계정명(VLOOKUP 키). 확정=VLOOKUP(BS), 추정=변수 가정 참조
E3: 1 | F3: 2 | G3: 3 | H3: 4 | I3: 5 | J3: 6 | K3: 7 | L3: 8 | M3: 9 | N3: 10 | O3: 11 | P3: 12 | Q3: 13 | R3: 14 | S3: 15 | T3: 16 | U3: 17 | V3: 18 | W3: 19 | X3: 20 | Y3: 21 | Z3: 22 | AA3: 23 | AB3: 24 | AC3: 25 | AD3: 26 | AE3: 27 | AF3: 28 | AG3: 29 | AH3: 30 | AI3: 31 | AJ3: 32 | AK3: 33 | AL3: 34 | AM3: 35 | AN3: 36 | AO3: 37
E4: 2021.12 | F4: 2021.12A | G4: 2022.03 | H4: 2022.06 | I4: 2022.09 | J4: 2022.12 | K4: 2022.12A | L4: 2023.03 | M4: 2023.06 | N4: 2023.09 | O4: 2023.12 | P4: 2023.12A | Q4: 2024.03 | R4: 2024.06 | S4: 2024.09 | T4: 2024.12 | U4: 2024.12A | V4: 2025.03 | W4: 2025.06 | X4: 2025.09 | Y4: 2025.12 | Z4: 2025.12A | AA4: 2026.03 | AB4: 2026.06 | AC4: 2026.09 | AD4: 2026.12 | AE4: 2026.12A | AF4: 2027.03 | AG4: 2027.06 | AH4: 2027.09 | AI4: 2027.12 | AJ4: 2027.12A | AK4: 2028.03 | AL4: 2028.06 | AM4: 2028.09 | AN4: 2028.12 | AO4: 2028.12A
A5: 매출액 | B5: 손익 | C5: 억원 | D5: 매출액(수익) | E5: =IFERROR(VLOOKUP($D5,BS연결,MATCH(E$1,BS연결H,0),0)/100,"") | G5: =IFERROR(VLOOKUP($D5,BS연결,MATCH(G$1,BS연결H,0),0)/100,"") | H5: =IFERROR(VLOOKUP($D5,BS연결,MATCH(H$1,BS연결H,0),0)/100,"") | I5: =IFERROR(VLOOKUP($D5,BS연결,MATCH(I$1,BS연결H,0),0)/100,"") | J5: =IFERROR(VLOOKUP($D5,BS연결,MATCH(J$1,BS연결H,0),0)/100,"") | K5: =IFERROR(VLOOKUP($D5,BS연결,MATCH(K$1,BS연결H,0),0)/100,"") | L5: =IFERROR(VLOOKUP($D5,BS연결,MATCH(L$1,BS연결H,0),0)/100,"") | M5: =IFERROR(VLOOKUP($D5,BS연결,MATCH(M$1,BS연결H,0),0)/100,"") | N5: =IFERROR(VLOOKUP($D5,BS연결,MATCH(N$1,BS연결H,0),0)/100,"") | ... AB5: =IFERROR(VLOOKUP($D5,BS연결,MATCH(AB$1,BS연결H,0),0)/100,"") | AC5: =IFERROR(X5*(1+변수!AC21),"") | AD5: =IFERROR(Y5*(1+변수!AD21),"") | AE5: =SUM(AA5:AD5) | AF5: =IFERROR(AA5*(1+변수!AF21),"") | AG5: =IFERROR(AB5*(1+변수!AG21),"") | AH5: =IFERROR(AC5*(1+변수!AH21),"") | AI5: =IFERROR(AD5*(1+변수!AI21),"") | AJ5: =SUM(AF5:AI5) | AK5: =IFERROR(AF5*(1+변수!AK21),"") | AL5: =IFERROR(AG5*(1+변수!AL21),"") | AM5: =IFERROR(AH5*(1+변수!AM21),"") | AN5: =IFERROR(AI5*(1+변수!AN21),"") | AO5: =SUM(AK5:AN5)
A6: 매출원가 | B6: 손익 | C6: 억원 | D6: 매출원가 | E6: =IFERROR(VLOOKUP($D6,BS연결,MATCH(E$1,BS연결H,0),0)/100,"") | G6: =IFERROR(VLOOKUP($D6,BS연결,MATCH(G$1,BS연결H,0),0)/100,"") | H6: =IFERROR(VLOOKUP($D6,BS연결,MATCH(H$1,BS연결H,0),0)/100,"") | I6: =IFERROR(VLOOKUP($D6,BS연결,MATCH(I$1,BS연결H,0),0)/100,"") | J6: =IFERROR(VLOOKUP($D6,BS연결,MATCH(J$1,BS연결H,0),0)/100,"") | K6: =IFERROR(VLOOKUP($D6,BS연결,MATCH(K$1,BS연결H,0),0)/100,"") | L6: =IFERROR(VLOOKUP($D6,BS연결,MATCH(L$1,BS연결H,0),0)/100,"") | M6: =IFERROR(VLOOKUP($D6,BS연결,MATCH(M$1,BS연결H,0),0)/100,"") | N6: =IFERROR(VLOOKUP($D6,BS연결,MATCH(N$1,BS연결H,0),0)/100,"") | ... AB6: =IFERROR(VLOOKUP($D6,BS연결,MATCH(AB$1,BS연결H,0),0)/100,"") | AC6: =IFERROR(AC5-AC7,"") | AD6: =IFERROR(AD5-AD7,"") | AE6: =SUM(AA6:AD6) | AF6: =IFERROR(AF5-AF7,"") | AG6: =IFERROR(AG5-AG7,"") | AH6: =IFERROR(AH5-AH7,"") | AI6: =IFERROR(AI5-AI7,"") | AJ6: =SUM(AF6:AI6) | AK6: =IFERROR(AK5-AK7,"") | AL6: =IFERROR(AL5-AL7,"") | AM6: =IFERROR(AM5-AM7,"") | AN6: =IFERROR(AN5-AN7,"") | AO6: =SUM(AK6:AN6)
A7: 매출총이익 | B7: 손익 | C7: 억원 | D7: 매출총이익 | E7: =IFERROR(VLOOKUP($D7,BS연결,MATCH(E$1,BS연결H,0),0)/100,"") | G7: =IFERROR(VLOOKUP($D7,BS연결,MATCH(G$1,BS연결H,0),0)/100,"") | H7: =IFERROR(VLOOKUP($D7,BS연결,MATCH(H$1,BS연결H,0),0)/100,"") | I7: =IFERROR(VLOOKUP($D7,BS연결,MATCH(I$1,BS연결H,0),0)/100,"") | J7: =IFERROR(VLOOKUP($D7,BS연결,MATCH(J$1,BS연결H,0),0)/100,"") | K7: =IFERROR(VLOOKUP($D7,BS연결,MATCH(K$1,BS연결H,0),0)/100,"") | L7: =IFERROR(VLOOKUP($D7,BS연결,MATCH(L$1,BS연결H,0),0)/100,"") | M7: =IFERROR(VLOOKUP($D7,BS연결,MATCH(M$1,BS연결H,0),0)/100,"") | N7: =IFERROR(VLOOKUP($D7,BS연결,MATCH(N$1,BS연결H,0),0)/100,"") | ... AB7: =IFERROR(VLOOKUP($D7,BS연결,MATCH(AB$1,BS연결H,0),0)/100,"") | AC7: =IFERROR(AC9+AC8,"") | AD7: =IFERROR(AD9+AD8,"") | AE7: =SUM(AA7:AD7) | AF7: =IFERROR(AF9+AF8,"") | AG7: =IFERROR(AG9+AG8,"") | AH7: =IFERROR(AH9+AH8,"") | AI7: =IFERROR(AI9+AI8,"") | AJ7: =SUM(AF7:AI7) | AK7: =IFERROR(AK9+AK8,"") | AL7: =IFERROR(AL9+AL8,"") | AM7: =IFERROR(AM9+AM8,"") | AN7: =IFERROR(AN9+AN8,"") | AO7: =SUM(AK7:AN7)
A8: 판관비 | B8: 손익 | C8: 억원 | D8: 판관비 | E8: =IFERROR(VLOOKUP($D8,BS연결,MATCH(E$1,BS연결H,0),0)/100,"") | G8: =IFERROR(VLOOKUP($D8,BS연결,MATCH(G$1,BS연결H,0),0)/100,"") | H8: =IFERROR(VLOOKUP($D8,BS연결,MATCH(H$1,BS연결H,0),0)/100,"") | I8: =IFERROR(VLOOKUP($D8,BS연결,MATCH(I$1,BS연결H,0),0)/100,"") | J8: =IFERROR(VLOOKUP($D8,BS연결,MATCH(J$1,BS연결H,0),0)/100,"") | K8: =IFERROR(VLOOKUP($D8,BS연결,MATCH(K$1,BS연결H,0),0)/100,"") | L8: =IFERROR(VLOOKUP($D8,BS연결,MATCH(L$1,BS연결H,0),0)/100,"") | M8: =IFERROR(VLOOKUP($D8,BS연결,MATCH(M$1,BS연결H,0),0)/100,"") | N8: =IFERROR(VLOOKUP($D8,BS연결,MATCH(N$1,BS연결H,0),0)/100,"") | ... AB8: =IFERROR(VLOOKUP($D8,BS연결,MATCH(AB$1,BS연결H,0),0)/100,"") | AC8: =IFERROR(AC5*변수!AC22,"") | AD8: =IFERROR(AD5*변수!AD22,"") | AE8: =SUM(AA8:AD8) | AF8: =IFERROR(AF5*변수!AF22,"") | AG8: =IFERROR(AG5*변수!AG22,"") | AH8: =IFERROR(AH5*변수!AH22,"") | AI8: =IFERROR(AI5*변수!AI22,"") | AJ8: =SUM(AF8:AI8) | AK8: =IFERROR(AK5*변수!AK22,"") | AL8: =IFERROR(AL5*변수!AL22,"") | AM8: =IFERROR(AM5*변수!AM22,"") | AN8: =IFERROR(AN5*변수!AN22,"") | AO8: =SUM(AK8:AN8)
A9: 영업이익 | B9: 손익 | C9: 억원 | D9: 영업이익 | E9: =IFERROR(VLOOKUP($D9,BS연결,MATCH(E$1,BS연결H,0),0)/100,"") | G9: =IFERROR(VLOOKUP($D9,BS연결,MATCH(G$1,BS연결H,0),0)/100,"") | H9: =IFERROR(VLOOKUP($D9,BS연결,MATCH(H$1,BS연결H,0),0)/100,"") | I9: =IFERROR(VLOOKUP($D9,BS연결,MATCH(I$1,BS연결H,0),0)/100,"") | J9: =IFERROR(VLOOKUP($D9,BS연결,MATCH(J$1,BS연결H,0),0)/100,"") | K9: =IFERROR(VLOOKUP($D9,BS연결,MATCH(K$1,BS연결H,0),0)/100,"") | L9: =IFERROR(VLOOKUP($D9,BS연결,MATCH(L$1,BS연결H,0),0)/100,"") | M9: =IFERROR(VLOOKUP($D9,BS연결,MATCH(M$1,BS연결H,0),0)/100,"") | N9: =IFERROR(VLOOKUP($D9,BS연결,MATCH(N$1,BS연결H,0),0)/100,"") | ... AB9: =IFERROR(VLOOKUP($D9,BS연결,MATCH(AB$1,BS연결H,0),0)/100,"") | AC9: =IFERROR(AC5*변수!AC23,"") | AD9: =IFERROR(AD5*변수!AD23,"") | AE9: =SUM(AA9:AD9) | AF9: =IFERROR(AF5*변수!AF23,"") | AG9: =IFERROR(AG5*변수!AG23,"") | AH9: =IFERROR(AH5*변수!AH23,"") | AI9: =IFERROR(AI5*변수!AI23,"") | AJ9: =SUM(AF9:AI9) | AK9: =IFERROR(AK5*변수!AK23,"") | AL9: =IFERROR(AL5*변수!AL23,"") | AM9: =IFERROR(AM5*변수!AM23,"") | AN9: =IFERROR(AN5*변수!AN23,"") | AO9: =SUM(AK9:AN9)
A10: OPM | B10: 손익 | C10: % | D10: 영업이익률 | E10: =IFERROR(E9/E5,"") | G10: =IFERROR(G9/G5,"") | H10: =IFERROR(H9/H5,"") | I10: =IFERROR(I9/I5,"") | J10: =IFERROR(J9/J5,"") | K10: =IFERROR(K9/K5,"") | L10: =IFERROR(L9/L5,"") | M10: =IFERROR(M9/M5,"") | N10: =IFERROR(N9/N5,"") | ... AO10: =IFERROR(AO9/AO5,"")
A11: 금융손익 | B11: 손익 | C11: 억원 | D11: 금융손익 | E11: =IFERROR(VLOOKUP($D11,BS연결,MATCH(E$1,BS연결H,0),0)/100,"") | G11: =IFERROR(VLOOKUP($D11,BS연결,MATCH(G$1,BS연결H,0),0)/100,"") | H11: =IFERROR(VLOOKUP($D11,BS연결,MATCH(H$1,BS연결H,0),0)/100,"") | I11: =IFERROR(VLOOKUP($D11,BS연결,MATCH(I$1,BS연결H,0),0)/100,"") | J11: =IFERROR(VLOOKUP($D11,BS연결,MATCH(J$1,BS연결H,0),0)/100,"") | K11: =IFERROR(VLOOKUP($D11,BS연결,MATCH(K$1,BS연결H,0),0)/100,"") | L11: =IFERROR(VLOOKUP($D11,BS연결,MATCH(L$1,BS연결H,0),0)/100,"") | M11: =IFERROR(VLOOKUP($D11,BS연결,MATCH(M$1,BS연결H,0),0)/100,"") | N11: =IFERROR(VLOOKUP($D11,BS연결,MATCH(N$1,BS연결H,0),0)/100,"") | ... AB11: =IFERROR(VLOOKUP($D11,BS연결,MATCH(AB$1,BS연결H,0),0)/100,"") | AC11: =IFERROR(AC12+AC13+AC14+AC15,"") | AD11: =IFERROR(AD12+AD13+AD14+AD15,"") | AE11: =SUM(AA11:AD11) | AF11: =IFERROR(AF12+AF13+AF14+AF15,"") | AG11: =IFERROR(AG12+AG13+AG14+AG15,"") | AH11: =IFERROR(AH12+AH13+AH14+AH15,"") | AI11: =IFERROR(AI12+AI13+AI14+AI15,"") | AJ11: =SUM(AF11:AI11) | AK11: =IFERROR(AK12+AK13+AK14+AK15,"") | AL11: =IFERROR(AL12+AL13+AL14+AL15,"") | AM11: =IFERROR(AM12+AM13+AM14+AM15,"") | AN11: =IFERROR(AN12+AN13+AN14+AN15,"") | AO11: =SUM(AK11:AN11)
A12: 이자손익 | B12: 손익 | C12: 억원 | D12: 이자손익 | K12: =SUM(G12:J12) | P12: =SUM(L12:O12) | U12: =SUM(Q12:T12) | V12: =IFERROR(VLOOKUP($D12,BS연결,MATCH(V$1,BS연결H,0),0)/100,"") | W12: =IFERROR(VLOOKUP($D12,BS연결,MATCH(W$1,BS연결H,0),0)/100,"") | X12: =IFERROR(VLOOKUP($D12,BS연결,MATCH(X$1,BS연결H,0),0)/100,"") | Y12: =IFERROR(VLOOKUP($D12,BS연결,MATCH(Y$1,BS연결H,0),0)/100,"") | Z12: =IFERROR(VLOOKUP($D12,BS연결,MATCH(Z$1,BS연결H,0),0)/100,"") | AA12: =IFERROR(VLOOKUP($D12,BS연결,MATCH(AA$1,BS연결H,0),0)/100,"") | AB12: =IFERROR(VLOOKUP($D12,BS연결,MATCH(AB$1,BS연결H,0),0)/100,"") | AC12: =IFERROR((AB27*변수!$D$53-AB25*변수!$D$54)/4,"") | AD12: =IFERROR((AC27*변수!$D$53-AC25*변수!$D$54)/4,"") | AE12: =SUM(AA12:AD12) | AF12: =IFERROR((AD27*변수!$D$53-AD25*변수!$D$54)/4,"") | AG12: =IFERROR((AF27*변수!$D$53-AF25*변수!$D$54)/4,"") | AH12: =IFERROR((AG27*변수!$D$53-AG25*변수!$D$54)/4,"") | AI12: =IFERROR((AH27*변수!$D$53-AH25*변수!$D$54)/4,"") | AJ12: =SUM(AF12:AI12) | AK12: =IFERROR((AI27*변수!$D$53-AI25*변수!$D$54)/4,"") | AL12: =IFERROR((AK27*변수!$D$53-AK25*변수!$D$54)/4,"") | AM12: =IFERROR((AL27*변수!$D$53-AL25*변수!$D$54)/4,"") | AN12: =IFERROR((AM27*변수!$D$53-AM25*변수!$D$54)/4,"") | AO12: =SUM(AK12:AN12)
A13: 외환손익 | B13: 손익 | C13: 억원 | D13: 외환손익(실적만; 추정 환효과는 환관련손익) | K13: =SUM(G13:J13) | P13: =SUM(L13:O13) | U13: =SUM(Q13:T13) | V13: =IFERROR((VLOOKUP("외환차익",BS연결,MATCH(V$1,BS연결H,0),0)-VLOOKUP("외환차손",BS연결,MATCH(V$1,BS연결H,0),0)+VLOOKUP("외화환산이익",BS연결,MATCH(V$1,BS연결H,0),0)-VLOOKUP("외화환산손실",BS연결,MATCH(V$1,BS연결H,0),0))/100,"") | W13: =IFERROR((VLOOKUP("외환차익",BS연결,MATCH(W$1,BS연결H,0),0)-VLOOKUP("외환차손",BS연결,MATCH(W$1,BS연결H,0),0)+VLOOKUP("외화환산이익",BS연결,MATCH(W$1,BS연결H,0),0)-VLOOKUP("외화환산손실",BS연결,MATCH(W$1,BS연결H,0),0))/100,"") | X13: =IFERROR((VLOOKUP("외환차익",BS연결,MATCH(X$1,BS연결H,0),0)-VLOOKUP("외환차손",BS연결,MATCH(X$1,BS연결H,0),0)+VLOOKUP("외화환산이익",BS연결,MATCH(X$1,BS연결H,0),0)-VLOOKUP("외화환산손실",BS연결,MATCH(X$1,BS연결H,0),0))/100,"") | Y13: =IFERROR((VLOOKUP("외환차익",BS연결,MATCH(Y$1,BS연결H,0),0)-VLOOKUP("외환차손",BS연결,MATCH(Y$1,BS연결H,0),0)+VLOOKUP("외화환산이익",BS연결,MATCH(Y$1,BS연결H,0),0)-VLOOKUP("외화환산손실",BS연결,MATCH(Y$1,BS연결H,0),0))/100,"") | Z13: =SUM(V13:Y13) | AA13: =IFERROR((VLOOKUP("외환차익",BS연결,MATCH(AA$1,BS연결H,0),0)-VLOOKUP("외환차손",BS연결,MATCH(AA$1,BS연결H,0),0)+VLOOKUP("외화환산이익",BS연결,MATCH(AA$1,BS연결H,0),0)-VLOOKUP("외화환산손실",BS연결,MATCH(AA$1,BS연결H,0),0))/100,"") | AB13: =IFERROR((VLOOKUP("외환차익",BS연결,MATCH(AB$1,BS연결H,0),0)-VLOOKUP("외환차손",BS연결,MATCH(AB$1,BS연결H,0),0)+VLOOKUP("외화환산이익",BS연결,MATCH(AB$1,BS연결H,0),0)-VLOOKUP("외화환산손실",BS연결,MATCH(AB$1,BS연결H,0),0))/100,"") | AC13: =변수!AC24 | AD13: =변수!AD24 | AE13: =SUM(AA13:AD13) | AF13: =변수!AF24 | AG13: =변수!AG24 | AH13: =변수!AH24 | AI13: =변수!AI24 | AJ13: =SUM(AF13:AI13) | AK13: =변수!AK24 | AL13: =변수!AL24 | AM13: =변수!AM24 | AN13: =변수!AN24 | AO13: =SUM(AK13:AN13)
A14: 파생상품손익 | B14: 손익 | C14: 억원 | D14: 파생상품손익 | K14: =SUM(G14:J14) | P14: =SUM(L14:O14) | U14: =SUM(Q14:T14) | V14: =IFERROR((VLOOKUP("파생상품이익",BS연결,MATCH(V$1,BS연결H,0),0)-VLOOKUP("파생상품손실",BS연결,MATCH(V$1,BS연결H,0),0))/100,"") | W14: =IFERROR((VLOOKUP("파생상품이익",BS연결,MATCH(W$1,BS연결H,0),0)-VLOOKUP("파생상품손실",BS연결,MATCH(W$1,BS연결H,0),0))/100,"") | X14: =IFERROR((VLOOKUP("파생상품이익",BS연결,MATCH(X$1,BS연결H,0),0)-VLOOKUP("파생상품손실",BS연결,MATCH(X$1,BS연결H,0),0))/100,"") | Y14: =IFERROR((VLOOKUP("파생상품이익",BS연결,MATCH(Y$1,BS연결H,0),0)-VLOOKUP("파생상품손실",BS연결,MATCH(Y$1,BS연결H,0),0))/100,"") | Z14: =SUM(V14:Y14) | AA14: =IFERROR((VLOOKUP("파생상품이익",BS연결,MATCH(AA$1,BS연결H,0),0)-VLOOKUP("파생상품손실",BS연결,MATCH(AA$1,BS연결H,0),0))/100,"") | AB14: =IFERROR((VLOOKUP("파생상품이익",BS연결,MATCH(AB$1,BS연결H,0),0)-VLOOKUP("파생상품손실",BS연결,MATCH(AB$1,BS연결H,0),0))/100,"") | AC14: =변수!AC25 | AD14: =변수!AD25 | AE14: =SUM(AA14:AD14) | AF14: =변수!AF25 | AG14: =변수!AG25 | AH14: =변수!AH25 | AI14: =변수!AI25 | AJ14: =SUM(AF14:AI14) | AK14: =변수!AK25 | AL14: =변수!AL25 | AM14: =변수!AM25 | AN14: =변수!AN25 | AO14: =SUM(AK14:AN14)
A15: 기타금융손익 | B15: 손익 | C15: 억원 | D15: 기타금융손익(금융손익 잔차) | K15: =SUM(G15:J15) | P15: =SUM(L15:O15) | U15: =SUM(Q15:T15) | V15: =IFERROR(V11-V12-V13-V14,"") | W15: =IFERROR(W11-W12-W13-W14,"") | X15: =IFERROR(X11-X12-X13-X14,"") | Y15: =IFERROR(Y11-Y12-Y13-Y14,"") | Z15: =SUM(V15:Y15) | AA15: =IFERROR(AA11-AA12-AA13-AA14,"") | AB15: =IFERROR(AB11-AB12-AB13-AB14,"") | AC15: =변수!AC26 | AD15: =변수!AD26 | AE15: =SUM(AA15:AD15) | AF15: =변수!AF26 | AG15: =변수!AG26 | AH15: =변수!AH26 | AI15: =변수!AI26 | AJ15: =SUM(AF15:AI15) | AK15: =변수!AK26 | AL15: =변수!AL26 | AM15: =변수!AM26 | AN15: =변수!AN26 | AO15: =SUM(AK15:AN15)
A16: 기타영업외손익 | B16: 손익 | C16: 억원 | D16: 기타영업외손익 | E16: =IFERROR(VLOOKUP($D16,BS연결,MATCH(E$1,BS연결H,0),0)/100,"") | G16: =IFERROR(VLOOKUP($D16,BS연결,MATCH(G$1,BS연결H,0),0)/100,"") | H16: =IFERROR(VLOOKUP($D16,BS연결,MATCH(H$1,BS연결H,0),0)/100,"") | I16: =IFERROR(VLOOKUP($D16,BS연결,MATCH(I$1,BS연결H,0),0)/100,"") | J16: =IFERROR(VLOOKUP($D16,BS연결,MATCH(J$1,BS연결H,0),0)/100,"") | K16: =IFERROR(VLOOKUP($D16,BS연결,MATCH(K$1,BS연결H,0),0)/100,"") | L16: =IFERROR(VLOOKUP($D16,BS연결,MATCH(L$1,BS연결H,0),0)/100,"") | M16: =IFERROR(VLOOKUP($D16,BS연결,MATCH(M$1,BS연결H,0),0)/100,"") | N16: =IFERROR(VLOOKUP($D16,BS연결,MATCH(N$1,BS연결H,0),0)/100,"") | ... AB16: =IFERROR(VLOOKUP($D16,BS연결,MATCH(AB$1,BS연결H,0),0)/100,"") | AC16: =변수!AC27 | AD16: =변수!AD27 | AE16: =SUM(AA16:AD16) | AF16: =변수!AF27 | AG16: =변수!AG27 | AH16: =변수!AH27 | AI16: =변수!AI27 | AJ16: =SUM(AF16:AI16) | AK16: =변수!AK27 | AL16: =변수!AL27 | AM16: =변수!AM27 | AN16: =변수!AN27 | AO16: =SUM(AK16:AN16)
A17: 세전이익 | B17: 손익 | C17: 억원 | D17: 법인세비용차감전계속사업이익 | E17: =IFERROR(VLOOKUP($D17,BS연결,MATCH(E$1,BS연결H,0),0)/100,"") | G17: =IFERROR(VLOOKUP($D17,BS연결,MATCH(G$1,BS연결H,0),0)/100,"") | H17: =IFERROR(VLOOKUP($D17,BS연결,MATCH(H$1,BS연결H,0),0)/100,"") | I17: =IFERROR(VLOOKUP($D17,BS연결,MATCH(I$1,BS연결H,0),0)/100,"") | J17: =IFERROR(VLOOKUP($D17,BS연결,MATCH(J$1,BS연결H,0),0)/100,"") | K17: =IFERROR(VLOOKUP($D17,BS연결,MATCH(K$1,BS연결H,0),0)/100,"") | L17: =IFERROR(VLOOKUP($D17,BS연결,MATCH(L$1,BS연결H,0),0)/100,"") | M17: =IFERROR(VLOOKUP($D17,BS연결,MATCH(M$1,BS연결H,0),0)/100,"") | N17: =IFERROR(VLOOKUP($D17,BS연결,MATCH(N$1,BS연결H,0),0)/100,"") | ... AB17: =IFERROR(VLOOKUP($D17,BS연결,MATCH(AB$1,BS연결H,0),0)/100,"") | AC17: =IFERROR(AC9+AC11+AC16,"") | AD17: =IFERROR(AD9+AD11+AD16,"") | AE17: =SUM(AA17:AD17) | AF17: =IFERROR(AF9+AF11+AF16,"") | AG17: =IFERROR(AG9+AG11+AG16,"") | AH17: =IFERROR(AH9+AH11+AH16,"") | AI17: =IFERROR(AI9+AI11+AI16,"") | AJ17: =SUM(AF17:AI17) | AK17: =IFERROR(AK9+AK11+AK16,"") | AL17: =IFERROR(AL9+AL11+AL16,"") | AM17: =IFERROR(AM9+AM11+AM16,"") | AN17: =IFERROR(AN9+AN11+AN16,"") | AO17: =SUM(AK17:AN17)
A18: 법인세비용 | B18: 손익 | C18: 억원 | D18: 법인세비용 | E18: =IFERROR(VLOOKUP($D18,BS연결,MATCH(E$1,BS연결H,0),0)/100,"") | G18: =IFERROR(VLOOKUP($D18,BS연결,MATCH(G$1,BS연결H,0),0)/100,"") | H18: =IFERROR(VLOOKUP($D18,BS연결,MATCH(H$1,BS연결H,0),0)/100,"") | I18: =IFERROR(VLOOKUP($D18,BS연결,MATCH(I$1,BS연결H,0),0)/100,"") | J18: =IFERROR(VLOOKUP($D18,BS연결,MATCH(J$1,BS연결H,0),0)/100,"") | K18: =IFERROR(VLOOKUP($D18,BS연결,MATCH(K$1,BS연결H,0),0)/100,"") | L18: =IFERROR(VLOOKUP($D18,BS연결,MATCH(L$1,BS연결H,0),0)/100,"") | M18: =IFERROR(VLOOKUP($D18,BS연결,MATCH(M$1,BS연결H,0),0)/100,"") | N18: =IFERROR(VLOOKUP($D18,BS연결,MATCH(N$1,BS연결H,0),0)/100,"") | ... AB18: =IFERROR(VLOOKUP($D18,BS연결,MATCH(AB$1,BS연결H,0),0)/100,"") | AC18: =IFERROR(MAX(AC17,0)*변수!AC28,"") | AD18: =IFERROR(MAX(AD17,0)*변수!AD28,"") | AE18: =SUM(AA18:AD18) | AF18: =IFERROR(MAX(AF17,0)*변수!AF28,"") | AG18: =IFERROR(MAX(AG17,0)*변수!AG28,"") | AH18: =IFERROR(MAX(AH17,0)*변수!AH28,"") | AI18: =IFERROR(MAX(AI17,0)*변수!AI28,"") | AJ18: =SUM(AF18:AI18) | AK18: =IFERROR(MAX(AK17,0)*변수!AK28,"") | AL18: =IFERROR(MAX(AL17,0)*변수!AL28,"") | AM18: =IFERROR(MAX(AM17,0)*변수!AM28,"") | AN18: =IFERROR(MAX(AN17,0)*변수!AN28,"") | AO18: =SUM(AK18:AN18)
A19: 당기순이익 | B19: 손익 | C19: 억원 | D19: 당기순이익 | E19: =IFERROR(VLOOKUP($D19,BS연결,MATCH(E$1,BS연결H,0),0)/100,"") | G19: =IFERROR(VLOOKUP($D19,BS연결,MATCH(G$1,BS연결H,0),0)/100,"") | H19: =IFERROR(VLOOKUP($D19,BS연결,MATCH(H$1,BS연결H,0),0)/100,"") | I19: =IFERROR(VLOOKUP($D19,BS연결,MATCH(I$1,BS연결H,0),0)/100,"") | J19: =IFERROR(VLOOKUP($D19,BS연결,MATCH(J$1,BS연결H,0),0)/100,"") | K19: =IFERROR(VLOOKUP($D19,BS연결,MATCH(K$1,BS연결H,0),0)/100,"") | L19: =IFERROR(VLOOKUP($D19,BS연결,MATCH(L$1,BS연결H,0),0)/100,"") | M19: =IFERROR(VLOOKUP($D19,BS연결,MATCH(M$1,BS연결H,0),0)/100,"") | P19: =SUM(L19:O19) | Q19: =IFERROR(VLOOKUP($D19,BS연결,MATCH(Q$1,BS연결H,0),0)/100,"") | R19: =IFERROR(VLOOKUP($D19,BS연결,MATCH(R$1,BS연결H,0),0)/100,"") | S19: =IFERROR(VLOOKUP($D19,BS연결,MATCH(S$1,BS연결H,0),0)/100,"") | T19: =IFERROR(VLOOKUP($D19,BS연결,MATCH(T$1,BS연결H,0),0)/100,"") | U19: =IFERROR(VLOOKUP($D19,BS연결,MATCH(U$1,BS연결H,0),0)/100,"") | V19: =IFERROR(VLOOKUP($D19,BS연결,MATCH(V$1,BS연결H,0),0)/100,"") | W19: =IFERROR(VLOOKUP($D19,BS연결,MATCH(W$1,BS연결H,0),0)/100,"") | X19: =IFERROR(VLOOKUP($D19,BS연결,MATCH(X$1,BS연결H,0),0)/100,"") | ... AB19: =IFERROR(VLOOKUP($D19,BS연결,MATCH(AB$1,BS연결H,0),0)/100,"") | AC19: =IFERROR(AC17-AC18,"") | AD19: =IFERROR(AD17-AD18,"") | AE19: =SUM(AA19:AD19) | AF19: =IFERROR(AF17-AF18,"") | AG19: =IFERROR(AG17-AG18,"") | AH19: =IFERROR(AH17-AH18,"") | AI19: =IFERROR(AI17-AI18,"") | AJ19: =SUM(AF19:AI19) | AK19: =IFERROR(AK17-AK18,"") | AL19: =IFERROR(AL17-AL18,"") | AM19: =IFERROR(AM17-AM18,"") | AN19: =IFERROR(AN17-AN18,"") | AO19: =SUM(AK19:AN19)
A20: 지배주주순이익 | B20: 손익 | C20: 억원 | D20: (지배주주지분)당기순이익 | E20: =IFERROR(VLOOKUP($D20,BS연결,MATCH(E$1,BS연결H,0),0)/100,"") | G20: =IFERROR(VLOOKUP($D20,BS연결,MATCH(G$1,BS연결H,0),0)/100,"") | H20: =IFERROR(VLOOKUP($D20,BS연결,MATCH(H$1,BS연결H,0),0)/100,"") | I20: =IFERROR(VLOOKUP($D20,BS연결,MATCH(I$1,BS연결H,0),0)/100,"") | J20: =IFERROR(VLOOKUP($D20,BS연결,MATCH(J$1,BS연결H,0),0)/100,"") | K20: =IFERROR(VLOOKUP($D20,BS연결,MATCH(K$1,BS연결H,0),0)/100,"") | L20: =IFERROR(VLOOKUP($D20,BS연결,MATCH(L$1,BS연결H,0),0)/100,"") | M20: =IFERROR(VLOOKUP($D20,BS연결,MATCH(M$1,BS연결H,0),0)/100,"") | N20: =IFERROR(VLOOKUP($D20,BS연결,MATCH(N$1,BS연결H,0),0)/100,"") | ... AB20: =IFERROR(VLOOKUP($D20,BS연결,MATCH(AB$1,BS연결H,0),0)/100,"") | AC20: =IFERROR(AC19*변수!AC29,"") | AD20: =IFERROR(AD19*변수!AD29,"") | AE20: =SUM(AA20:AD20) | AF20: =IFERROR(AF19*변수!AF29,"") | AG20: =IFERROR(AG19*변수!AG29,"") | AH20: =IFERROR(AH19*변수!AH29,"") | AI20: =IFERROR(AI19*변수!AI29,"") | AJ20: =SUM(AF20:AI20) | AK20: =IFERROR(AK19*변수!AK29,"") | AL20: =IFERROR(AL19*변수!AL29,"") | AM20: =IFERROR(AM19*변수!AM29,"") | AN20: =IFERROR(AN19*변수!AN29,"") | AO20: =SUM(AK20:AN20)
A21: 자산총계 | B21: 재무상태 | C21: 억원 | D21: 자산총계 | E21: =IFERROR(VLOOKUP($D21,BS연결,MATCH(E$1,BS연결H,0),0)/100,"") | F21: =IFERROR(VLOOKUP($D21,BS연결,MATCH(F$1,BS연결H,0),0)/100,"") | G21: =IFERROR(VLOOKUP($D21,BS연결,MATCH(G$1,BS연결H,0),0)/100,"") | H21: =IFERROR(VLOOKUP($D21,BS연결,MATCH(H$1,BS연결H,0),0)/100,"") | I21: =IFERROR(VLOOKUP($D21,BS연결,MATCH(I$1,BS연결H,0),0)/100,"") | J21: =IFERROR(VLOOKUP($D21,BS연결,MATCH(J$1,BS연결H,0),0)/100,"") | K21: =IFERROR(VLOOKUP($D21,BS연결,MATCH(K$1,BS연결H,0),0)/100,"") | L21: =IFERROR(VLOOKUP($D21,BS연결,MATCH(L$1,BS연결H,0),0)/100,"") | ... AB21: =IFERROR(VLOOKUP($D21,BS연결,MATCH(AB$1,BS연결H,0),0)/100,"") | AC21: =IFERROR(AC22+AC23,"") | AD21: =IFERROR(AD22+AD23,"") | AE21: =AD21 | AF21: =IFERROR(AF22+AF23,"") | AG21: =IFERROR(AG22+AG23,"") | AH21: =IFERROR(AH22+AH23,"") | AI21: =IFERROR(AI22+AI23,"") | AJ21: =AI21 | AK21: =IFERROR(AK22+AK23,"") | AL21: =IFERROR(AL22+AL23,"") | AM21: =IFERROR(AM22+AM23,"") | AN21: =IFERROR(AN22+AN23,"") | AO21: =AN21
A22: 부채총계 | B22: 재무상태 | C22: 억원 | D22: 부채총계 | E22: =IFERROR(VLOOKUP($D22,BS연결,MATCH(E$1,BS연결H,0),0)/100,"") | F22: =IFERROR(VLOOKUP($D22,BS연결,MATCH(F$1,BS연결H,0),0)/100,"") | G22: =IFERROR(VLOOKUP($D22,BS연결,MATCH(G$1,BS연결H,0),0)/100,"") | H22: =IFERROR(VLOOKUP($D22,BS연결,MATCH(H$1,BS연결H,0),0)/100,"") | I22: =IFERROR(VLOOKUP($D22,BS연결,MATCH(I$1,BS연결H,0),0)/100,"") | J22: =IFERROR(VLOOKUP($D22,BS연결,MATCH(J$1,BS연결H,0),0)/100,"") | K22: =IFERROR(VLOOKUP($D22,BS연결,MATCH(K$1,BS연결H,0),0)/100,"") | L22: =IFERROR(VLOOKUP($D22,BS연결,MATCH(L$1,BS연결H,0),0)/100,"") | ... AB22: =IFERROR(VLOOKUP($D22,BS연결,MATCH(AB$1,BS연결H,0),0)/100,"") | AC22: =IFERROR(AB22*(1+변수!AC30),"") | AD22: =IFERROR(AC22*(1+변수!AD30),"") | AE22: =AD22 | AF22: =IFERROR(AD22*(1+변수!AF30),"") | AG22: =IFERROR(AF22*(1+변수!AG30),"") | AH22: =IFERROR(AG22*(1+변수!AH30),"") | AI22: =IFERROR(AH22*(1+변수!AI30),"") | AJ22: =AI22 | AK22: =IFERROR(AI22*(1+변수!AK30),"") | AL22: =IFERROR(AK22*(1+변수!AL30),"") | AM22: =IFERROR(AL22*(1+변수!AM30),"") | AN22: =IFERROR(AM22*(1+변수!AN30),"") | AO22: =AN22
A23: 자본총계 | B23: 재무상태 | C23: 억원 | D23: 자본총계 | E23: =IFERROR(VLOOKUP($D23,BS연결,MATCH(E$1,BS연결H,0),0)/100,"") | F23: =IFERROR(VLOOKUP($D23,BS연결,MATCH(F$1,BS연결H,0),0)/100,"") | G23: =IFERROR(VLOOKUP($D23,BS연결,MATCH(G$1,BS연결H,0),0)/100,"") | H23: =IFERROR(VLOOKUP($D23,BS연결,MATCH(H$1,BS연결H,0),0)/100,"") | I23: =IFERROR(VLOOKUP($D23,BS연결,MATCH(I$1,BS연결H,0),0)/100,"") | J23: =IFERROR(VLOOKUP($D23,BS연결,MATCH(J$1,BS연결H,0),0)/100,"") | K23: =IFERROR(VLOOKUP($D23,BS연결,MATCH(K$1,BS연결H,0),0)/100,"") | L23: =IFERROR(VLOOKUP($D23,BS연결,MATCH(L$1,BS연결H,0),0)/100,"") | ... AB23: =IFERROR(VLOOKUP($D23,BS연결,MATCH(AB$1,BS연결H,0),0)/100,"") | AC23: =IFERROR(AB23+AC19-변수!AC31,"") | AD23: =IFERROR(AC23+AD19-변수!AD31,"") | AE23: =AD23 | AF23: =IFERROR(AD23+AF19-변수!AF31,"") | AG23: =IFERROR(AF23+AG19-변수!AG31,"") | AH23: =IFERROR(AG23+AH19-변수!AH31,"") | AI23: =IFERROR(AH23+AI19-변수!AI31,"") | AJ23: =AI23 | AK23: =IFERROR(AI23+AK19-변수!AK31,"") | AL23: =IFERROR(AK23+AL19-변수!AL31,"") | AM23: =IFERROR(AL23+AM19-변수!AM31,"") | AN23: =IFERROR(AM23+AN19-변수!AN31,"") | AO23: =AN23
A24: 지배주주지분 | B24: 재무상태 | C24: 억원 | D24: 지배주주지분 | E24: =IFERROR(VLOOKUP($D24,BS연결,MATCH(E$1,BS연결H,0),0)/100,"") | F24: =IFERROR(VLOOKUP($D24,BS연결,MATCH(F$1,BS연결H,0),0)/100,"") | G24: =IFERROR(VLOOKUP($D24,BS연결,MATCH(G$1,BS연결H,0),0)/100,"") | H24: =IFERROR(VLOOKUP($D24,BS연결,MATCH(H$1,BS연결H,0),0)/100,"") | I24: =IFERROR(VLOOKUP($D24,BS연결,MATCH(I$1,BS연결H,0),0)/100,"") | J24: =IFERROR(VLOOKUP($D24,BS연결,MATCH(J$1,BS연결H,0),0)/100,"") | K24: =IFERROR(VLOOKUP($D24,BS연결,MATCH(K$1,BS연결H,0),0)/100,"") | L24: =IFERROR(VLOOKUP($D24,BS연결,MATCH(L$1,BS연결H,0),0)/100,"") | ... AB24: =IFERROR(VLOOKUP($D24,BS연결,MATCH(AB$1,BS연결H,0),0)/100,"") | AC24: =IFERROR(AB24+AC20-변수!AC32,"") | AD24: =IFERROR(AC24+AD20-변수!AD32,"") | AE24: =AD24 | AF24: =IFERROR(AD24+AF20-변수!AF32,"") | AG24: =IFERROR(AF24+AG20-변수!AG32,"") | AH24: =IFERROR(AG24+AH20-변수!AH32,"") | AI24: =IFERROR(AH24+AI20-변수!AI32,"") | AJ24: =AI24 | AK24: =IFERROR(AI24+AK20-변수!AK32,"") | AL24: =IFERROR(AK24+AL20-변수!AL32,"") | AM24: =IFERROR(AL24+AM20-변수!AM32,"") | AN24: =IFERROR(AM24+AN20-변수!AN32,"") | AO24: =AN24
A25: 총차입금 | B25: 재무상태 | C25: 억원 | D25: 총차입금 | E25: =IFERROR(VLOOKUP($D25,BS연결,MATCH(E$1,BS연결H,0),0)/100,"") | F25: =IFERROR(VLOOKUP($D25,BS연결,MATCH(F$1,BS연결H,0),0)/100,"") | G25: =IFERROR(VLOOKUP($D25,BS연결,MATCH(G$1,BS연결H,0),0)/100,"") | H25: =IFERROR(VLOOKUP($D25,BS연결,MATCH(H$1,BS연결H,0),0)/100,"") | I25: =IFERROR(VLOOKUP($D25,BS연결,MATCH(I$1,BS연결H,0),0)/100,"") | J25: =IFERROR(VLOOKUP($D25,BS연결,MATCH(J$1,BS연결H,0),0)/100,"") | K25: =IFERROR(VLOOKUP($D25,BS연결,MATCH(K$1,BS연결H,0),0)/100,"") | L25: =IFERROR(VLOOKUP($D25,BS연결,MATCH(L$1,BS연결H,0),0)/100,"") | ... AB25: =IFERROR(VLOOKUP($D25,BS연결,MATCH(AB$1,BS연결H,0),0)/100,"") | AC25: =IFERROR(AB25*(1+변수!AC33),"") | AD25: =IFERROR(AC25*(1+변수!AD33),"") | AE25: =AD25 | AF25: =IFERROR(AD25*(1+변수!AF33),"") | AG25: =IFERROR(AF25*(1+변수!AG33),"") | AH25: =IFERROR(AG25*(1+변수!AH33),"") | AI25: =IFERROR(AH25*(1+변수!AI33),"") | AJ25: =AI25 | AK25: =IFERROR(AI25*(1+변수!AK33),"") | AL25: =IFERROR(AK25*(1+변수!AL33),"") | AM25: =IFERROR(AL25*(1+변수!AM33),"") | AN25: =IFERROR(AM25*(1+변수!AN33),"") | AO25: =AN25
A26: 순차입금 | B26: 재무상태 | C26: 억원 | D26: 순차입금 | E26: =IFERROR(VLOOKUP($D26,BS연결,MATCH(E$1,BS연결H,0),0)/100,"") | F26: =IFERROR(VLOOKUP($D26,BS연결,MATCH(F$1,BS연결H,0),0)/100,"") | G26: =IFERROR(VLOOKUP($D26,BS연결,MATCH(G$1,BS연결H,0),0)/100,"") | H26: =IFERROR(VLOOKUP($D26,BS연결,MATCH(H$1,BS연결H,0),0)/100,"") | I26: =IFERROR(VLOOKUP($D26,BS연결,MATCH(I$1,BS연결H,0),0)/100,"") | J26: =IFERROR(VLOOKUP($D26,BS연결,MATCH(J$1,BS연결H,0),0)/100,"") | K26: =IFERROR(VLOOKUP($D26,BS연결,MATCH(K$1,BS연결H,0),0)/100,"") | L26: =IFERROR(VLOOKUP($D26,BS연결,MATCH(L$1,BS연결H,0),0)/100,"") | ... AB26: =IFERROR(VLOOKUP($D26,BS연결,MATCH(AB$1,BS연결H,0),0)/100,"") | AC26: =IFERROR(AB26*(1+변수!AC34),"") | AD26: =IFERROR(AC26*(1+변수!AD34),"") | AE26: =AD26 | AF26: =IFERROR(AD26*(1+변수!AF34),"") | AG26: =IFERROR(AF26*(1+변수!AG34),"") | AH26: =IFERROR(AG26*(1+변수!AH34),"") | AI26: =IFERROR(AH26*(1+변수!AI34),"") | AJ26: =AI26 | AK26: =IFERROR(AI26*(1+변수!AK34),"") | AL26: =IFERROR(AK26*(1+변수!AL34),"") | AM26: =IFERROR(AL26*(1+변수!AM34),"") | AN26: =IFERROR(AM26*(1+변수!AN34),"") | AO26: =AN26
A27: 이자발생자산 | B27: 재무상태 | C27: 억원 | D27: 이자발생자산 | E27: =IFERROR(VLOOKUP($D27,BS연결,MATCH(E$1,BS연결H,0),0)/100,"") | F27: =IFERROR(VLOOKUP($D27,BS연결,MATCH(F$1,BS연결H,0),0)/100,"") | G27: =IFERROR(VLOOKUP($D27,BS연결,MATCH(G$1,BS연결H,0),0)/100,"") | H27: =IFERROR(VLOOKUP($D27,BS연결,MATCH(H$1,BS연결H,0),0)/100,"") | I27: =IFERROR(VLOOKUP($D27,BS연결,MATCH(I$1,BS연결H,0),0)/100,"") | J27: =IFERROR(VLOOKUP($D27,BS연결,MATCH(J$1,BS연결H,0),0)/100,"") | K27: =IFERROR(VLOOKUP($D27,BS연결,MATCH(K$1,BS연결H,0),0)/100,"") | L27: =IFERROR(VLOOKUP($D27,BS연결,MATCH(L$1,BS연결H,0),0)/100,"") | ... AB27: =IFERROR(VLOOKUP($D27,BS연결,MATCH(AB$1,BS연결H,0),0)/100,"") | AC27: =IFERROR(AB27*(1+변수!AC35),"") | AD27: =IFERROR(AC27*(1+변수!AD35),"") | AE27: =AD27 | AF27: =IFERROR(AD27*(1+변수!AF35),"") | AG27: =IFERROR(AF27*(1+변수!AG35),"") | AH27: =IFERROR(AG27*(1+변수!AH35),"") | AI27: =IFERROR(AH27*(1+변수!AI35),"") | AJ27: =AI27 | AK27: =IFERROR(AI27*(1+변수!AK35),"") | AL27: =IFERROR(AK27*(1+변수!AL35),"") | AM27: =IFERROR(AL27*(1+변수!AM35),"") | AN27: =IFERROR(AM27*(1+변수!AN35),"") | AO27: =AN27
A28: 현금및현금성자산 | B28: 재무상태 | C28: 억원 | D28: 현금및현금성자산 | E28: =IFERROR(VLOOKUP($D28,BS연결,MATCH(E$1,BS연결H,0),0)/100,"") | F28: =IFERROR(VLOOKUP($D28,BS연결,MATCH(F$1,BS연결H,0),0)/100,"") | G28: =IFERROR(VLOOKUP($D28,BS연결,MATCH(G$1,BS연결H,0),0)/100,"") | H28: =IFERROR(VLOOKUP($D28,BS연결,MATCH(H$1,BS연결H,0),0)/100,"") | I28: =IFERROR(VLOOKUP($D28,BS연결,MATCH(I$1,BS연결H,0),0)/100,"") | J28: =IFERROR(VLOOKUP($D28,BS연결,MATCH(J$1,BS연결H,0),0)/100,"") | K28: =IFERROR(VLOOKUP($D28,BS연결,MATCH(K$1,BS연결H,0),0)/100,"") | L28: =IFERROR(VLOOKUP($D28,BS연결,MATCH(L$1,BS연결H,0),0)/100,"") | ... AB28: =IFERROR(VLOOKUP($D28,BS연결,MATCH(AB$1,BS연결H,0),0)/100,"") | AE28: =AD28 | AJ28: =AI28 | AO28: =AN28
A29: CAPEX | B29: 현금흐름 | C29: 억원 | D29: CAPEX | E29: =IFERROR(VLOOKUP($D29,BS연결,MATCH(E$1,BS연결H,0),0)/100,"") | G29: =IFERROR(VLOOKUP($D29,BS연결,MATCH(G$1,BS연결H,0),0)/100,"") | H29: =IFERROR(VLOOKUP($D29,BS연결,MATCH(H$1,BS연결H,0),0)/100,"") | I29: =IFERROR(VLOOKUP($D29,BS연결,MATCH(I$1,BS연결H,0),0)/100,"") | J29: =IFERROR(VLOOKUP($D29,BS연결,MATCH(J$1,BS연결H,0),0)/100,"") | K29: =IFERROR(VLOOKUP($D29,BS연결,MATCH(K$1,BS연결H,0),0)/100,"") | L29: =IFERROR(VLOOKUP($D29,BS연결,MATCH(L$1,BS연결H,0),0)/100,"") | M29: =IFERROR(VLOOKUP($D29,BS연결,MATCH(M$1,BS연결H,0),0)/100,"") | N29: =IFERROR(VLOOKUP($D29,BS연결,MATCH(N$1,BS연결H,0),0)/100,"") | ... AB29: =IFERROR(VLOOKUP($D29,BS연결,MATCH(AB$1,BS연결H,0),0)/100,"") | AC29: =IFERROR(X29*(1+변수!AC37),"") | AD29: =IFERROR(Y29*(1+변수!AD37),"") | AE29: =SUM(AA29:AD29) | AF29: =IFERROR(AA29*(1+변수!AF37),"") | AG29: =IFERROR(AB29*(1+변수!AG37),"") | AH29: =IFERROR(AC29*(1+변수!AH37),"") | AI29: =IFERROR(AD29*(1+변수!AI37),"") | AJ29: =SUM(AF29:AI29) | AK29: =IFERROR(AF29*(1+변수!AK37),"") | AL29: =IFERROR(AG29*(1+변수!AL37),"") | AM29: =IFERROR(AH29*(1+변수!AM37),"") | AN29: =IFERROR(AI29*(1+변수!AN37),"") | AO29: =SUM(AK29:AN29)
A30: 영업활동현금흐름 | B30: 현금흐름 | C30: 억원 | D30: 영업활동으로인한현금흐름 | E30: =IFERROR(VLOOKUP($D30,BS연결,MATCH(E$1,BS연결H,0),0)/100,"") | G30: =IFERROR(VLOOKUP($D30,BS연결,MATCH(G$1,BS연결H,0),0)/100,"") | H30: =IFERROR(VLOOKUP($D30,BS연결,MATCH(H$1,BS연결H,0),0)/100,"") | I30: =IFERROR(VLOOKUP($D30,BS연결,MATCH(I$1,BS연결H,0),0)/100,"") | J30: =IFERROR(VLOOKUP($D30,BS연결,MATCH(J$1,BS연결H,0),0)/100,"") | K30: =IFERROR(VLOOKUP($D30,BS연결,MATCH(K$1,BS연결H,0),0)/100,"") | L30: =IFERROR(VLOOKUP($D30,BS연결,MATCH(L$1,BS연결H,0),0)/100,"") | M30: =IFERROR(VLOOKUP($D30,BS연결,MATCH(M$1,BS연결H,0),0)/100,"") | N30: =IFERROR(VLOOKUP($D30,BS연결,MATCH(N$1,BS연결H,0),0)/100,"") | ... AB30: =IFERROR(VLOOKUP($D30,BS연결,MATCH(AB$1,BS연결H,0),0)/100,"") | AE30: =SUM(AA30:AD30) | AJ30: =SUM(AF30:AI30) | AO30: =SUM(AK30:AN30)
A31: 주식수 | B31: 주당 | C31: 백만주 | D31: 유통주식수 | E31: 23 | F31: =E31 | G31: 23 | H31: 23 | I31: 23 | J31: 23 | K31: =J31 | L31: 23 | M31: 23 | N31: 23 | O31: 23 | P31: =O31 | Q31: 23 | R31: 23 | S31: 23 | T31: 23 | U31: =T31 | V31: 23 | W31: 40.139 | X31: 40.139 | Y31: 40.139 | Z31: =Y31 | AA31: 40.139 | AB31: 40.139 | AC31: =IFERROR(AB31*(1+변수!AC39),"") | AD31: =IFERROR(AC31*(1+변수!AD39),"") | AE31: =AD31 | AF31: =IFERROR(AD31*(1+변수!AF39),"") | AG31: =IFERROR(AF31*(1+변수!AG39),"") | AH31: =IFERROR(AG31*(1+변수!AH39),"") | AI31: =IFERROR(AH31*(1+변수!AI39),"") | AJ31: =AI31 | AK31: =IFERROR(AI31*(1+변수!AK39),"") | AL31: =IFERROR(AK31*(1+변수!AL39),"") | AM31: =IFERROR(AL31*(1+변수!AM39),"") | AN31: =IFERROR(AM31*(1+변수!AN39),"") | AO31: =AN31
A32: EPS | B32: 주당 | C32: 원 | D32: EPS | E32: =IFERROR(E20*100/E31,"") | G32: =IFERROR(G20*100/G31,"") | H32: =IFERROR(H20*100/H31,"") | I32: =IFERROR(I20*100/I31,"") | J32: =IFERROR(J20*100/J31,"") | K32: =SUM(G32:J32) | L32: =IFERROR(L20*100/L31,"") | M32: =IFERROR(M20*100/M31,"") | N32: =IFERROR(N20*100/N31,"") | O32: =IFERROR(O20*100/O31,"") | P32: =SUM(L32:O32) | Q32: =IFERROR(Q20*100/Q31,"") | R32: =IFERROR(R20*100/R31,"") | S32: =IFERROR(S20*100/S31,"") | T32: =IFERROR(T20*100/T31,"") | U32: =SUM(Q32:T32) | V32: =IFERROR(V20*100/V31,"") | W32: =IFERROR(W20*100/W31,"") | X32: =IFERROR(X20*100/X31,"") | Y32: =IFERROR(Y20*100/Y31,"") | Z32: =SUM(V32:Y32) | AA32: =IFERROR(AA20*100/AA31,"") | AB32: =IFERROR(AB20*100/AB31,"") | AC32: =IFERROR(AC20*100/AC31,"") | AD32: =IFERROR(AD20*100/AD31,"") | AE32: =SUM(AA32:AD32) | AF32: =IFERROR(AF20*100/AF31,"") | AG32: =IFERROR(AG20*100/AG31,"") | AH32: =IFERROR(AH20*100/AH31,"") | AI32: =IFERROR(AI20*100/AI31,"") | AJ32: =SUM(AF32:AI32) | AK32: =IFERROR(AK20*100/AK31,"") | AL32: =IFERROR(AL20*100/AL31,"") | AM32: =IFERROR(AM20*100/AM31,"") | AN32: =IFERROR(AN20*100/AN31,"") | AO32: =SUM(AK32:AN32)
A33: BPS | B33: 주당 | C33: 원 | D33: BPS | E33: =IFERROR(E24*100/E31,"") | F33: =E33 | G33: =IFERROR(G24*100/G31,"") | H33: =IFERROR(H24*100/H31,"") | I33: =IFERROR(I24*100/I31,"") | J33: =IFERROR(J24*100/J31,"") | K33: =J33 | L33: =IFERROR(L24*100/L31,"") | M33: =IFERROR(M24*100/M31,"") | N33: =IFERROR(N24*100/N31,"") | O33: =IFERROR(O24*100/O31,"") | P33: =O33 | Q33: =IFERROR(Q24*100/Q31,"") | R33: =IFERROR(R24*100/R31,"") | S33: =IFERROR(S24*100/S31,"") | T33: =IFERROR(T24*100/T31,"") | U33: =T33 | V33: =IFERROR(V24*100/V31,"") | W33: =IFERROR(W24*100/W31,"") | X33: =IFERROR(X24*100/X31,"") | Y33: =IFERROR(Y24*100/Y31,"") | Z33: =Y33 | AA33: =IFERROR(AA24*100/AA31,"") | AB33: =IFERROR(AB24*100/AB31,"") | AC33: =IFERROR(AC24*100/AC31,"") | AD33: =IFERROR(AD24*100/AD31,"") | AE33: =AD33 | AF33: =IFERROR(AF24*100/AF31,"") | AG33: =IFERROR(AG24*100/AG31,"") | AH33: =IFERROR(AH24*100/AH31,"") | AI33: =IFERROR(AI24*100/AI31,"") | AJ33: =AI33 | AK33: =IFERROR(AK24*100/AK31,"") | AL33: =IFERROR(AL24*100/AL31,"") | AM33: =IFERROR(AM24*100/AM31,"") | AN33: =IFERROR(AN24*100/AN31,"") | AO33: =AN33
A34: DPS | B34: 주당 | C34: 원 | D34: DPS(보통주) | E34: 0 | F34: 0 | J34: 0 | K34: =SUM(G34:J34) | O34: 0 | P34: =SUM(L34:O34) | T34: 0 | U34: =SUM(Q34:T34) | Y34: 0 | Z34: =SUM(V34:Y34) | AD34: =변수!AD40 | AE34: =SUM(AA34:AD34) | AI34: =변수!AI40 | AJ34: =SUM(AF34:AI34) | AN34: =변수!AN40 | AO34: =SUM(AK34:AN34)
A35: PER | B35: 주당 | C35: 배 | D35: PER | F35: =E35 | K35: =J35 | O35: =IFERROR(변수!O18/(L32+M32+N32+O32),"") | P35: =O35 | Q35: =IFERROR(변수!Q18/(M32+N32+O32+Q32),"") | R35: =IFERROR(변수!R18/(N32+O32+Q32+R32),"") | S35: =IFERROR(변수!S18/(O32+Q32+R32+S32),"") | T35: =IFERROR(변수!T18/(Q32+R32+S32+T32),"") | U35: =T35 | V35: =IFERROR(변수!V18/(R32+S32+T32+V32),"") | W35: =IFERROR(변수!W18/(S32+T32+V32+W32),"") | X35: =IFERROR(변수!X18/(T32+V32+W32+X32),"") | Y35: =IFERROR(변수!Y18/(V32+W32+X32+Y32),"") | Z35: =Y35 | AA35: =IFERROR(변수!AA18/(W32+X32+Y32+AA32),"") | AB35: =IFERROR(변수!AB18/(X32+Y32+AA32+AB32),"") | AC35: =IFERROR(변수!$D$43/(Y32+AA32+AB32+AC32),"") | AD35: =IFERROR(변수!$D$43/(AA32+AB32+AC32+AD32),"") | AE35: =AD35 | AF35: =IFERROR(변수!$D$43/(AB32+AC32+AD32+AF32),"") | AG35: =IFERROR(변수!$D$43/(AC32+AD32+AF32+AG32),"") | AH35: =IFERROR(변수!$D$43/(AD32+AF32+AG32+AH32),"") | AI35: =IFERROR(변수!$D$43/(AF32+AG32+AH32+AI32),"") | AJ35: =AI35 | AK35: =IFERROR(변수!$D$43/(AG32+AH32+AI32+AK32),"") | AL35: =IFERROR(변수!$D$43/(AH32+AI32+AK32+AL32),"") | AM35: =IFERROR(변수!$D$43/(AI32+AK32+AL32+AM32),"") | AN35: =IFERROR(변수!$D$43/(AK32+AL32+AM32+AN32),"") | AO35: =AN35
A36: PBR | B36: 주당 | C36: 배 | D36: PBR | E36: =IFERROR(변수!E18/E33,"") | F36: =E36 | G36: =IFERROR(변수!G18/G33,"") | H36: =IFERROR(변수!H18/H33,"") | I36: =IFERROR(변수!I18/I33,"") | J36: =IFERROR(변수!J18/J33,"") | K36: =J36 | L36: =IFERROR(변수!L18/L33,"") | M36: =IFERROR(변수!M18/M33,"") | N36: =IFERROR(변수!N18/N33,"") | O36: =IFERROR(변수!O18/O33,"") | P36: =O36 | Q36: =IFERROR(변수!Q18/Q33,"") | R36: =IFERROR(변수!R18/R33,"") | S36: =IFERROR(변수!S18/S33,"") | T36: =IFERROR(변수!T18/T33,"") | U36: =T36 | V36: =IFERROR(변수!V18/V33,"") | W36: =IFERROR(변수!W18/W33,"") | X36: =IFERROR(변수!X18/X33,"") | Y36: =IFERROR(변수!Y18/Y33,"") | Z36: =Y36 | AA36: =IFERROR(변수!AA18/AA33,"") | AB36: =IFERROR(변수!AB18/AB33,"") | AC36: =IFERROR(변수!$D$43/AC33,"") | AD36: =IFERROR(변수!$D$43/AD33,"") | AE36: =AD36 | AF36: =IFERROR(변수!$D$43/AF33,"") | AG36: =IFERROR(변수!$D$43/AG33,"") | AH36: =IFERROR(변수!$D$43/AH33,"") | AI36: =IFERROR(변수!$D$43/AI33,"") | AJ36: =AI36 | AK36: =IFERROR(변수!$D$43/AK33,"") | AL36: =IFERROR(변수!$D$43/AL33,"") | AM36: =IFERROR(변수!$D$43/AM33,"") | AN36: =IFERROR(변수!$D$43/AN33,"") | AO36: =AN36
A37: 매출전사 | B37: 사업부 | C37: 억원 | D37: 매출 전사(부문 미분리) | E37: 1662.98 | G37: 1119.18 | H37: 1049.16 | I37: 1374.16 | J37: 1897.71 | K37: =SUM(G37:J37) | L37: 1169.81 | M37: 1634.37 | N37: 1385.35 | O37: 2114.24 | P37: =SUM(L37:O37) | Q37: 1155.06 | R37: 1973.61 | S37: 1939.68 | T37: 2177.75 | U37: =SUM(Q37:T37) | V37: 1391.39 | W37: 2136.55 | X37: 1920.66 | Y37: 2444.82 | Z37: =SUM(V37:Y37) | AA37: 1890.11 | AB37: 2129.9 | AC37: =IFERROR(AC5,"") | AD37: =IFERROR(AD5,"") | AE37: =SUM(AA37:AD37) | AF37: =IFERROR(AF5,"") | AG37: =IFERROR(AG5,"") | AH37: =IFERROR(AH5,"") | AI37: =IFERROR(AI5,"") | AJ37: =SUM(AF37:AI37) | AK37: =IFERROR(AK5,"") | AL37: =IFERROR(AL5,"") | AM37: =IFERROR(AM5,"") | AN37: =IFERROR(AN5,"") | AO37: =SUM(AK37:AN37)
A38: OP전사 | B38: 사업부 | C38: 억원 | D38: OP 전사(부문 미분리) | E38: 34.97 | G38: -11.27 | H38: 6.34 | I38: 12.66 | J38: -95.89 | K38: =SUM(G38:J38) | L38: -3.5 | M38: 44.5 | N38: 18.84 | O38: 128.84 | P38: =SUM(L38:O38) | Q38: 68.13 | R38: 217.66 | S38: 54.26 | T38: 82.32 | U38: =SUM(Q38:T38) | V38: 154.52 | W38: 333.48 | X38: 154.26 | Y38: 53.68 | Z38: =SUM(V38:Y38) | AA38: 175.04 | AB38: 249.61 | AC38: =IFERROR(AC9,"") | AD38: =IFERROR(AD9,"") | AE38: =SUM(AA38:AD38) | AF38: =IFERROR(AF9,"") | AG38: =IFERROR(AG9,"") | AH38: =IFERROR(AH9,"") | AI38: =IFERROR(AI9,"") | AJ38: =SUM(AF38:AI38) | AK38: =IFERROR(AK9,"") | AL38: =IFERROR(AL9,"") | AM38: =IFERROR(AM9,"") | AN38: =IFERROR(AN9,"") | AO38: =SUM(AK38:AN38)
B39: 비율(참고)
A40: NPM | C40: % | D40: 지배주주순이익 / 매출액 | E40: =IFERROR(E20/E5,"") | F40: =IFERROR(F20/F5,"") | G40: =IFERROR(G20/G5,"") | H40: =IFERROR(H20/H5,"") | I40: =IFERROR(I20/I5,"") | J40: =IFERROR(J20/J5,"") | K40: =IFERROR(K20/K5,"") | L40: =IFERROR(L20/L5,"") | ... AO40: =IFERROR(AO20/AO5,"")
A41: 매출원가율 | C41: % | D41: 매출원가 / 매출액 | E41: =IFERROR(E6/E5,"") | F41: =IFERROR(F6/F5,"") | G41: =IFERROR(G6/G5,"") | H41: =IFERROR(H6/H5,"") | I41: =IFERROR(I6/I5,"") | J41: =IFERROR(J6/J5,"") | K41: =IFERROR(K6/K5,"") | L41: =IFERROR(L6/L5,"") | ... AO41: =IFERROR(AO6/AO5,"")
A42: 판관비율 | C42: % | D42: 판관비 / 매출액 | E42: =IFERROR(E8/E5,"") | F42: =IFERROR(F8/F5,"") | G42: =IFERROR(G8/G5,"") | H42: =IFERROR(H8/H5,"") | I42: =IFERROR(I8/I5,"") | J42: =IFERROR(J8/J5,"") | K42: =IFERROR(K8/K5,"") | L42: =IFERROR(L8/L5,"") | ... AO42: =IFERROR(AO8/AO5,"")

Sheet 분기
C1: 이름: 분기H — subQ 를 이름으로 VLOOKUP(억원) | E1: 4Q21 | F1: 1Q22 | G1: 2Q22 | H1: 3Q22 | I1: 4Q22 | J1: 1Q23 | K1: 2Q23 | L1: 3Q23 | M1: 4Q23 | N1: 1Q24 | O1: 2Q24 | P1: 3Q24 | Q1: 4Q24 | R1: 1Q25 | S1: 2Q25 | T1: 3Q25 | U1: 4Q25 | V1: 1Q26 | W1: 2Q26 | X1: 3Q26 | Y1: 4Q26 | Z1: 1Q27 | AA1: 2Q27 | AB1: 3Q27 | AC1: 4Q27 | AD1: 1Q28 | AE1: 2Q28 | AF1: 3Q28 | AG1: 4Q28
C2: 종가: | D2: =변수!D43
C3: 기준일: | D3: 20261026 | E3: 1 | F3: 2 | G3: 3 | H3: 4 | I3: 5 | J3: 6 | K3: 7 | L3: 8 | M3: 9 | N3: 10 | O3: 11 | P3: 12 | Q3: 13 | R3: 14 | S3: 15 | T3: 16 | U3: 17 | V3: 18 | W3: 19 | X3: 20 | Y3: 21 | Z3: 22 | AA3: 23 | AB3: 24 | AC3: 25 | AD3: 26 | AE3: 27 | AF3: 28 | AG3: 29
E4: 2021.12 | F4: 2022.03 | G4: 2022.06 | H4: 2022.09 | I4: 2022.12 | J4: 2023.03 | K4: 2023.06 | L4: 2023.09 | M4: 2023.12 | N4: 2024.03 | O4: 2024.06 | P4: 2024.09 | Q4: 2024.12 | R4: 2025.03 | S4: 2025.06 | T4: 2025.09 | U4: 2025.12 | V4: 2026.03 | W4: 2026.06 | X4: 2026.09 | Y4: 2026.12 | Z4: 2027.03 | AA4: 2027.06 | AB4: 2027.09 | AC4: 2027.12 | AD4: 2028.03 | AE4: 2028.06 | AF4: 2028.09 | AG4: 2028.12
A5: 매출액 | D5: 매출액 | E5: =IFERROR(VLOOKUP($A5,subQ,MATCH(E$1,SUBQH,0),0),"") | F5: =IFERROR(VLOOKUP($A5,subQ,MATCH(F$1,SUBQH,0),0),"") | G5: =IFERROR(VLOOKUP($A5,subQ,MATCH(G$1,SUBQH,0),0),"") | H5: =IFERROR(VLOOKUP($A5,subQ,MATCH(H$1,SUBQH,0),0),"") | I5: =IFERROR(VLOOKUP($A5,subQ,MATCH(I$1,SUBQH,0),0),"") | J5: =IFERROR(VLOOKUP($A5,subQ,MATCH(J$1,SUBQH,0),0),"") | K5: =IFERROR(VLOOKUP($A5,subQ,MATCH(K$1,SUBQH,0),0),"") | L5: =IFERROR(VLOOKUP($A5,subQ,MATCH(L$1,SUBQH,0),0),"") | ... AG5: =IFERROR(VLOOKUP($A5,subQ,MATCH(AG$1,SUBQH,0),0),"")
A6: 매출원가 | D6: 매출원가 | E6: =IFERROR(VLOOKUP($A6,subQ,MATCH(E$1,SUBQH,0),0),"") | F6: =IFERROR(VLOOKUP($A6,subQ,MATCH(F$1,SUBQH,0),0),"") | G6: =IFERROR(VLOOKUP($A6,subQ,MATCH(G$1,SUBQH,0),0),"") | H6: =IFERROR(VLOOKUP($A6,subQ,MATCH(H$1,SUBQH,0),0),"") | I6: =IFERROR(VLOOKUP($A6,subQ,MATCH(I$1,SUBQH,0),0),"") | J6: =IFERROR(VLOOKUP($A6,subQ,MATCH(J$1,SUBQH,0),0),"") | K6: =IFERROR(VLOOKUP($A6,subQ,MATCH(K$1,SUBQH,0),0),"") | L6: =IFERROR(VLOOKUP($A6,subQ,MATCH(L$1,SUBQH,0),0),"") | ... AG6: =IFERROR(VLOOKUP($A6,subQ,MATCH(AG$1,SUBQH,0),0),"")
A7: 매출총이익 | D7: 매출총이익 | E7: =IFERROR(VLOOKUP($A7,subQ,MATCH(E$1,SUBQH,0),0),"") | F7: =IFERROR(VLOOKUP($A7,subQ,MATCH(F$1,SUBQH,0),0),"") | G7: =IFERROR(VLOOKUP($A7,subQ,MATCH(G$1,SUBQH,0),0),"") | H7: =IFERROR(VLOOKUP($A7,subQ,MATCH(H$1,SUBQH,0),0),"") | I7: =IFERROR(VLOOKUP($A7,subQ,MATCH(I$1,SUBQH,0),0),"") | J7: =IFERROR(VLOOKUP($A7,subQ,MATCH(J$1,SUBQH,0),0),"") | K7: =IFERROR(VLOOKUP($A7,subQ,MATCH(K$1,SUBQH,0),0),"") | L7: =IFERROR(VLOOKUP($A7,subQ,MATCH(L$1,SUBQH,0),0),"") | ... AG7: =IFERROR(VLOOKUP($A7,subQ,MATCH(AG$1,SUBQH,0),0),"")
A8: 판관비 | D8: 판매비와관리비 | E8: =IFERROR(VLOOKUP($A8,subQ,MATCH(E$1,SUBQH,0),0),"") | F8: =IFERROR(VLOOKUP($A8,subQ,MATCH(F$1,SUBQH,0),0),"") | G8: =IFERROR(VLOOKUP($A8,subQ,MATCH(G$1,SUBQH,0),0),"") | H8: =IFERROR(VLOOKUP($A8,subQ,MATCH(H$1,SUBQH,0),0),"") | I8: =IFERROR(VLOOKUP($A8,subQ,MATCH(I$1,SUBQH,0),0),"") | J8: =IFERROR(VLOOKUP($A8,subQ,MATCH(J$1,SUBQH,0),0),"") | K8: =IFERROR(VLOOKUP($A8,subQ,MATCH(K$1,SUBQH,0),0),"") | L8: =IFERROR(VLOOKUP($A8,subQ,MATCH(L$1,SUBQH,0),0),"") | ... AG8: =IFERROR(VLOOKUP($A8,subQ,MATCH(AG$1,SUBQH,0),0),"")
A9: 영업이익 | D9: 영업이익 | E9: =IFERROR(VLOOKUP($A9,subQ,MATCH(E$1,SUBQH,0),0),"") | F9: =IFERROR(VLOOKUP($A9,subQ,MATCH(F$1,SUBQH,0),0),"") | G9: =IFERROR(VLOOKUP($A9,subQ,MATCH(G$1,SUBQH,0),0),"") | H9: =IFERROR(VLOOKUP($A9,subQ,MATCH(H$1,SUBQH,0),0),"") | I9: =IFERROR(VLOOKUP($A9,subQ,MATCH(I$1,SUBQH,0),0),"") | J9: =IFERROR(VLOOKUP($A9,subQ,MATCH(J$1,SUBQH,0),0),"") | K9: =IFERROR(VLOOKUP($A9,subQ,MATCH(K$1,SUBQH,0),0),"") | L9: =IFERROR(VLOOKUP($A9,subQ,MATCH(L$1,SUBQH,0),0),"") | ... AG9: =IFERROR(VLOOKUP($A9,subQ,MATCH(AG$1,SUBQH,0),0),"")
A10: OPM | D10: 영업이익률 | E10: =IFERROR(VLOOKUP($A10,subQ,MATCH(E$1,SUBQH,0),0),"") | F10: =IFERROR(VLOOKUP($A10,subQ,MATCH(F$1,SUBQH,0),0),"") | G10: =IFERROR(VLOOKUP($A10,subQ,MATCH(G$1,SUBQH,0),0),"") | H10: =IFERROR(VLOOKUP($A10,subQ,MATCH(H$1,SUBQH,0),0),"") | I10: =IFERROR(VLOOKUP($A10,subQ,MATCH(I$1,SUBQH,0),0),"") | J10: =IFERROR(VLOOKUP($A10,subQ,MATCH(J$1,SUBQH,0),0),"") | K10: =IFERROR(VLOOKUP($A10,subQ,MATCH(K$1,SUBQH,0),0),"") | L10: =IFERROR(VLOOKUP($A10,subQ,MATCH(L$1,SUBQH,0),0),"") | ... AG10: =IFERROR(VLOOKUP($A10,subQ,MATCH(AG$1,SUBQH,0),0),"")
A11: 금융손익 | D11: 금융손익(이자·환 포함) | E11: =IFERROR(VLOOKUP($A11,subQ,MATCH(E$1,SUBQH,0),0),"") | F11: =IFERROR(VLOOKUP($A11,subQ,MATCH(F$1,SUBQH,0),0),"") | G11: =IFERROR(VLOOKUP($A11,subQ,MATCH(G$1,SUBQH,0),0),"") | H11: =IFERROR(VLOOKUP($A11,subQ,MATCH(H$1,SUBQH,0),0),"") | I11: =IFERROR(VLOOKUP($A11,subQ,MATCH(I$1,SUBQH,0),0),"") | J11: =IFERROR(VLOOKUP($A11,subQ,MATCH(J$1,SUBQH,0),0),"") | K11: =IFERROR(VLOOKUP($A11,subQ,MATCH(K$1,SUBQH,0),0),"") | L11: =IFERROR(VLOOKUP($A11,subQ,MATCH(L$1,SUBQH,0),0),"") | ... AG11: =IFERROR(VLOOKUP($A11,subQ,MATCH(AG$1,SUBQH,0),0),"")
A12: 이자손익 | D12: 이자손익(이자수익 − 이자비용) | E12: =IFERROR(VLOOKUP($A12,subQ,MATCH(E$1,SUBQH,0),0),"") | F12: =IFERROR(VLOOKUP($A12,subQ,MATCH(F$1,SUBQH,0),0),"") | G12: =IFERROR(VLOOKUP($A12,subQ,MATCH(G$1,SUBQH,0),0),"") | H12: =IFERROR(VLOOKUP($A12,subQ,MATCH(H$1,SUBQH,0),0),"") | I12: =IFERROR(VLOOKUP($A12,subQ,MATCH(I$1,SUBQH,0),0),"") | J12: =IFERROR(VLOOKUP($A12,subQ,MATCH(J$1,SUBQH,0),0),"") | K12: =IFERROR(VLOOKUP($A12,subQ,MATCH(K$1,SUBQH,0),0),"") | L12: =IFERROR(VLOOKUP($A12,subQ,MATCH(L$1,SUBQH,0),0),"") | ... AG12: =IFERROR(VLOOKUP($A12,subQ,MATCH(AG$1,SUBQH,0),0),"")
A13: 외환손익 | D13: 외환손익(실적만; 추정 환효과는 환관련손익) | E13: =IFERROR(VLOOKUP($A13,subQ,MATCH(E$1,SUBQH,0),0),"") | F13: =IFERROR(VLOOKUP($A13,subQ,MATCH(F$1,SUBQH,0),0),"") | G13: =IFERROR(VLOOKUP($A13,subQ,MATCH(G$1,SUBQH,0),0),"") | H13: =IFERROR(VLOOKUP($A13,subQ,MATCH(H$1,SUBQH,0),0),"") | I13: =IFERROR(VLOOKUP($A13,subQ,MATCH(I$1,SUBQH,0),0),"") | J13: =IFERROR(VLOOKUP($A13,subQ,MATCH(J$1,SUBQH,0),0),"") | K13: =IFERROR(VLOOKUP($A13,subQ,MATCH(K$1,SUBQH,0),0),"") | L13: =IFERROR(VLOOKUP($A13,subQ,MATCH(L$1,SUBQH,0),0),"") | ... AG13: =IFERROR(VLOOKUP($A13,subQ,MATCH(AG$1,SUBQH,0),0),"")
A14: 파생상품손익 | D14: 파생상품손익 | E14: =IFERROR(VLOOKUP($A14,subQ,MATCH(E$1,SUBQH,0),0),"") | F14: =IFERROR(VLOOKUP($A14,subQ,MATCH(F$1,SUBQH,0),0),"") | G14: =IFERROR(VLOOKUP($A14,subQ,MATCH(G$1,SUBQH,0),0),"") | H14: =IFERROR(VLOOKUP($A14,subQ,MATCH(H$1,SUBQH,0),0),"") | I14: =IFERROR(VLOOKUP($A14,subQ,MATCH(I$1,SUBQH,0),0),"") | J14: =IFERROR(VLOOKUP($A14,subQ,MATCH(J$1,SUBQH,0),0),"") | K14: =IFERROR(VLOOKUP($A14,subQ,MATCH(K$1,SUBQH,0),0),"") | L14: =IFERROR(VLOOKUP($A14,subQ,MATCH(L$1,SUBQH,0),0),"") | ... AG14: =IFERROR(VLOOKUP($A14,subQ,MATCH(AG$1,SUBQH,0),0),"")
A15: 기타금융손익 | D15: 기타금융손익(금융손익 잔차) | E15: =IFERROR(VLOOKUP($A15,subQ,MATCH(E$1,SUBQH,0),0),"") | F15: =IFERROR(VLOOKUP($A15,subQ,MATCH(F$1,SUBQH,0),0),"") | G15: =IFERROR(VLOOKUP($A15,subQ,MATCH(G$1,SUBQH,0),0),"") | H15: =IFERROR(VLOOKUP($A15,subQ,MATCH(H$1,SUBQH,0),0),"") | I15: =IFERROR(VLOOKUP($A15,subQ,MATCH(I$1,SUBQH,0),0),"") | J15: =IFERROR(VLOOKUP($A15,subQ,MATCH(J$1,SUBQH,0),0),"") | K15: =IFERROR(VLOOKUP($A15,subQ,MATCH(K$1,SUBQH,0),0),"") | L15: =IFERROR(VLOOKUP($A15,subQ,MATCH(L$1,SUBQH,0),0),"") | ... AG15: =IFERROR(VLOOKUP($A15,subQ,MATCH(AG$1,SUBQH,0),0),"")
A16: 기타영업외손익 | D16: 기타영업외손익 | E16: =IFERROR(VLOOKUP($A16,subQ,MATCH(E$1,SUBQH,0),0),"") | F16: =IFERROR(VLOOKUP($A16,subQ,MATCH(F$1,SUBQH,0),0),"") | G16: =IFERROR(VLOOKUP($A16,subQ,MATCH(G$1,SUBQH,0),0),"") | H16: =IFERROR(VLOOKUP($A16,subQ,MATCH(H$1,SUBQH,0),0),"") | I16: =IFERROR(VLOOKUP($A16,subQ,MATCH(I$1,SUBQH,0),0),"") | J16: =IFERROR(VLOOKUP($A16,subQ,MATCH(J$1,SUBQH,0),0),"") | K16: =IFERROR(VLOOKUP($A16,subQ,MATCH(K$1,SUBQH,0),0),"") | L16: =IFERROR(VLOOKUP($A16,subQ,MATCH(L$1,SUBQH,0),0),"") | ... AG16: =IFERROR(VLOOKUP($A16,subQ,MATCH(AG$1,SUBQH,0),0),"")
... A39: NPM | D39: NPM | E39: =IFERROR(VLOOKUP($A39,subQ,MATCH(E$1,SUBQH,0),0),"") | F39: =IFERROR(VLOOKUP($A39,subQ,MATCH(F$1,SUBQH,0),0),"") | G39: =IFERROR(VLOOKUP($A39,subQ,MATCH(G$1,SUBQH,0),0),"") | H39: =IFERROR(VLOOKUP($A39,subQ,MATCH(H$1,SUBQH,0),0),"") | I39: =IFERROR(VLOOKUP($A39,subQ,MATCH(I$1,SUBQH,0),0),"") | J39: =IFERROR(VLOOKUP($A39,subQ,MATCH(J$1,SUBQH,0),0),"") | K39: =IFERROR(VLOOKUP($A39,subQ,MATCH(K$1,SUBQH,0),0),"") | L39: =IFERROR(VLOOKUP($A39,subQ,MATCH(L$1,SUBQH,0),0),"") | ... AG39: =IFERROR(VLOOKUP($A39,subQ,MATCH(AG$1,SUBQH,0),0),"")
A40: 매출액 YoY | D40: 매출액 YoY | I40: =IFERROR(I5/E5-1,"") | J40: =IFERROR(J5/F5-1,"") | K40: =IFERROR(K5/G5-1,"") | L40: =IFERROR(L5/H5-1,"") | M40: =IFERROR(M5/I5-1,"") | N40: =IFERROR(N5/J5-1,"") | O40: =IFERROR(O5/K5-1,"") | P40: =IFERROR(P5/L5-1,"") | ... AG40: =IFERROR(AG5/AC5-1,"")
A41: 영업이익 YoY | D41: 영업이익 YoY | I41: =IFERROR(I9/E9-1,"") | J41: =IFERROR(J9/F9-1,"") | K41: =IFERROR(K9/G9-1,"") | L41: =IFERROR(L9/H9-1,"") | M41: =IFERROR(M9/I9-1,"") | N41: =IFERROR(N9/J9-1,"") | O41: =IFERROR(O9/K9-1,"") | P41: =IFERROR(P9/L9-1,"") | ... AG41: =IFERROR(AG9/AC9-1,"")
A42: 지배주주순이익 YoY | D42: 지배주주순이익 YoY | I42: =IFERROR(I20/E20-1,"") | J42: =IFERROR(J20/F20-1,"") | K42: =IFERROR(K20/G20-1,"") | L42: =IFERROR(L20/H20-1,"") | M42: =IFERROR(M20/I20-1,"") | N42: =IFERROR(N20/J20-1,"") | O42: =IFERROR(O20/K20-1,"") | P42: =IFERROR(P20/L20-1,"") | ... AG42: =IFERROR(AG20/AC20-1,"")

Sheet 연간예상
C1: 이름: 연간예상H — subQ 를 이름으로 VLOOKUP(억원) | E1: 2021 | F1: 2022 | G1: 2023 | H1: 2024 | I1: 2025 | J1: 2026 | K1: 2027 | L1: 2028
C2: 종가: | D2: =변수!D43
C3: 기준일: | D3: 20261026 | E3: 1 | F3: 2 | G3: 3 | H3: 4 | I3: 5 | J3: 6 | K3: 7 | L3: 8
E4: 2021.12A | F4: 2022.12A | G4: 2023.12A | H4: 2024.12A | I4: 2025.12A | J4: 2026.12A | K4: 2027.12A | L4: 2028.12A
A5: 매출액 | D5: 매출액 | E5: =IFERROR(VLOOKUP($A5,subQ,MATCH(E$1,SUBQH,0),0),"") | F5: =IFERROR(VLOOKUP($A5,subQ,MATCH(F$1,SUBQH,0),0),"") | G5: =IFERROR(VLOOKUP($A5,subQ,MATCH(G$1,SUBQH,0),0),"") | H5: =IFERROR(VLOOKUP($A5,subQ,MATCH(H$1,SUBQH,0),0),"") | I5: =IFERROR(VLOOKUP($A5,subQ,MATCH(I$1,SUBQH,0),0),"") | J5: =IFERROR(VLOOKUP($A5,subQ,MATCH(J$1,SUBQH,0),0),"") | K5: =IFERROR(VLOOKUP($A5,subQ,MATCH(K$1,SUBQH,0),0),"") | L5: =IFERROR(VLOOKUP($A5,subQ,MATCH(L$1,SUBQH,0),0),"")
A6: 매출원가 | D6: 매출원가 | E6: =IFERROR(VLOOKUP($A6,subQ,MATCH(E$1,SUBQH,0),0),"") | F6: =IFERROR(VLOOKUP($A6,subQ,MATCH(F$1,SUBQH,0),0),"") | G6: =IFERROR(VLOOKUP($A6,subQ,MATCH(G$1,SUBQH,0),0),"") | H6: =IFERROR(VLOOKUP($A6,subQ,MATCH(H$1,SUBQH,0),0),"") | I6: =IFERROR(VLOOKUP($A6,subQ,MATCH(I$1,SUBQH,0),0),"") | J6: =IFERROR(VLOOKUP($A6,subQ,MATCH(J$1,SUBQH,0),0),"") | K6: =IFERROR(VLOOKUP($A6,subQ,MATCH(K$1,SUBQH,0),0),"") | L6: =IFERROR(VLOOKUP($A6,subQ,MATCH(L$1,SUBQH,0),0),"")
A7: 매출총이익 | D7: 매출총이익 | E7: =IFERROR(VLOOKUP($A7,subQ,MATCH(E$1,SUBQH,0),0),"") | F7: =IFERROR(VLOOKUP($A7,subQ,MATCH(F$1,SUBQH,0),0),"") | G7: =IFERROR(VLOOKUP($A7,subQ,MATCH(G$1,SUBQH,0),0),"") | H7: =IFERROR(VLOOKUP($A7,subQ,MATCH(H$1,SUBQH,0),0),"") | I7: =IFERROR(VLOOKUP($A7,subQ,MATCH(I$1,SUBQH,0),0),"") | J7: =IFERROR(VLOOKUP($A7,subQ,MATCH(J$1,SUBQH,0),0),"") | K7: =IFERROR(VLOOKUP($A7,subQ,MATCH(K$1,SUBQH,0),0),"") | L7: =IFERROR(VLOOKUP($A7,subQ,MATCH(L$1,SUBQH,0),0),"")
A8: 판관비 | D8: 판매비와관리비 | E8: =IFERROR(VLOOKUP($A8,subQ,MATCH(E$1,SUBQH,0),0),"") | F8: =IFERROR(VLOOKUP($A8,subQ,MATCH(F$1,SUBQH,0),0),"") | G8: =IFERROR(VLOOKUP($A8,subQ,MATCH(G$1,SUBQH,0),0),"") | H8: =IFERROR(VLOOKUP($A8,subQ,MATCH(H$1,SUBQH,0),0),"") | I8: =IFERROR(VLOOKUP($A8,subQ,MATCH(I$1,SUBQH,0),0),"") | J8: =IFERROR(VLOOKUP($A8,subQ,MATCH(J$1,SUBQH,0),0),"") | K8: =IFERROR(VLOOKUP($A8,subQ,MATCH(K$1,SUBQH,0),0),"") | L8: =IFERROR(VLOOKUP($A8,subQ,MATCH(L$1,SUBQH,0),0),"")
A9: 영업이익 | D9: 영업이익 | E9: =IFERROR(VLOOKUP($A9,subQ,MATCH(E$1,SUBQH,0),0),"") | F9: =IFERROR(VLOOKUP($A9,subQ,MATCH(F$1,SUBQH,0),0),"") | G9: =IFERROR(VLOOKUP($A9,subQ,MATCH(G$1,SUBQH,0),0),"") | H9: =IFERROR(VLOOKUP($A9,subQ,MATCH(H$1,SUBQH,0),0),"") | I9: =IFERROR(VLOOKUP($A9,subQ,MATCH(I$1,SUBQH,0),0),"") | J9: =IFERROR(VLOOKUP($A9,subQ,MATCH(J$1,SUBQH,0),0),"") | K9: =IFERROR(VLOOKUP($A9,subQ,MATCH(K$1,SUBQH,0),0),"") | L9: =IFERROR(VLOOKUP($A9,subQ,MATCH(L$1,SUBQH,0),0),"")
A10: OPM | D10: 영업이익률 | E10: =IFERROR(VLOOKUP($A10,subQ,MATCH(E$1,SUBQH,0),0),"") | F10: =IFERROR(VLOOKUP($A10,subQ,MATCH(F$1,SUBQH,0),0),"") | G10: =IFERROR(VLOOKUP($A10,subQ,MATCH(G$1,SUBQH,0),0),"") | H10: =IFERROR(VLOOKUP($A10,subQ,MATCH(H$1,SUBQH,0),0),"") | I10: =IFERROR(VLOOKUP($A10,subQ,MATCH(I$1,SUBQH,0),0),"") | J10: =IFERROR(VLOOKUP($A10,subQ,MATCH(J$1,SUBQH,0),0),"") | K10: =IFERROR(VLOOKUP($A10,subQ,MATCH(K$1,SUBQH,0),0),"") | L10: =IFERROR(VLOOKUP($A10,subQ,MATCH(L$1,SUBQH,0),0),"")
A11: 금융손익 | D11: 금융손익(이자·환 포함) | E11: =IFERROR(VLOOKUP($A11,subQ,MATCH(E$1,SUBQH,0),0),"") | F11: =IFERROR(VLOOKUP($A11,subQ,MATCH(F$1,SUBQH,0),0),"") | G11: =IFERROR(VLOOKUP($A11,subQ,MATCH(G$1,SUBQH,0),0),"") | H11: =IFERROR(VLOOKUP($A11,subQ,MATCH(H$1,SUBQH,0),0),"") | I11: =IFERROR(VLOOKUP($A11,subQ,MATCH(I$1,SUBQH,0),0),"") | J11: =IFERROR(VLOOKUP($A11,subQ,MATCH(J$1,SUBQH,0),0),"") | K11: =IFERROR(VLOOKUP($A11,subQ,MATCH(K$1,SUBQH,0),0),"") | L11: =IFERROR(VLOOKUP($A11,subQ,MATCH(L$1,SUBQH,0),0),"")
A12: 이자손익 | D12: 이자손익(이자수익 − 이자비용) | E12: =IFERROR(VLOOKUP($A12,subQ,MATCH(E$1,SUBQH,0),0),"") | F12: =IFERROR(VLOOKUP($A12,subQ,MATCH(F$1,SUBQH,0),0),"") | G12: =IFERROR(VLOOKUP($A12,subQ,MATCH(G$1,SUBQH,0),0),"") | H12: =IFERROR(VLOOKUP($A12,subQ,MATCH(H$1,SUBQH,0),0),"") | I12: =IFERROR(VLOOKUP($A12,subQ,MATCH(I$1,SUBQH,0),0),"") | J12: =IFERROR(VLOOKUP($A12,subQ,MATCH(J$1,SUBQH,0),0),"") | K12: =IFERROR(VLOOKUP($A12,subQ,MATCH(K$1,SUBQH,0),0),"") | L12: =IFERROR(VLOOKUP($A12,subQ,MATCH(L$1,SUBQH,0),0),"")
A13: 외환손익 | D13: 외환손익(실적만; 추정 환효과는 환관련손익) | E13: =IFERROR(VLOOKUP($A13,subQ,MATCH(E$1,SUBQH,0),0),"") | F13: =IFERROR(VLOOKUP($A13,subQ,MATCH(F$1,SUBQH,0),0),"") | G13: =IFERROR(VLOOKUP($A13,subQ,MATCH(G$1,SUBQH,0),0),"") | H13: =IFERROR(VLOOKUP($A13,subQ,MATCH(H$1,SUBQH,0),0),"") | I13: =IFERROR(VLOOKUP($A13,subQ,MATCH(I$1,SUBQH,0),0),"") | J13: =IFERROR(VLOOKUP($A13,subQ,MATCH(J$1,SUBQH,0),0),"") | K13: =IFERROR(VLOOKUP($A13,subQ,MATCH(K$1,SUBQH,0),0),"") | L13: =IFERROR(VLOOKUP($A13,subQ,MATCH(L$1,SUBQH,0),0),"")
A14: 파생상품손익 | D14: 파생상품손익 | E14: =IFERROR(VLOOKUP($A14,subQ,MATCH(E$1,SUBQH,0),0),"") | F14: =IFERROR(VLOOKUP($A14,subQ,MATCH(F$1,SUBQH,0),0),"") | G14: =IFERROR(VLOOKUP($A14,subQ,MATCH(G$1,SUBQH,0),0),"") | H14: =IFERROR(VLOOKUP($A14,subQ,MATCH(H$1,SUBQH,0),0),"") | I14: =IFERROR(VLOOKUP($A14,subQ,MATCH(I$1,SUBQH,0),0),"") | J14: =IFERROR(VLOOKUP($A14,subQ,MATCH(J$1,SUBQH,0),0),"") | K14: =IFERROR(VLOOKUP($A14,subQ,MATCH(K$1,SUBQH,0),0),"") | L14: =IFERROR(VLOOKUP($A14,subQ,MATCH(L$1,SUBQH,0),0),"")
A15: 기타금융손익 | D15: 기타금융손익(금융손익 잔차) | E15: =IFERROR(VLOOKUP($A15,subQ,MATCH(E$1,SUBQH,0),0),"") | F15: =IFERROR(VLOOKUP($A15,subQ,MATCH(F$1,SUBQH,0),0),"") | G15: =IFERROR(VLOOKUP($A15,subQ,MATCH(G$1,SUBQH,0),0),"") | H15: =IFERROR(VLOOKUP($A15,subQ,MATCH(H$1,SUBQH,0),0),"") | I15: =IFERROR(VLOOKUP($A15,subQ,MATCH(I$1,SUBQH,0),0),"") | J15: =IFERROR(VLOOKUP($A15,subQ,MATCH(J$1,SUBQH,0),0),"") | K15: =IFERROR(VLOOKUP($A15,subQ,MATCH(K$1,SUBQH,0),0),"") | L15: =IFERROR(VLOOKUP($A15,subQ,MATCH(L$1,SUBQH,0),0),"")
A16: 기타영업외손익 | D16: 기타영업외손익 | E16: =IFERROR(VLOOKUP($A16,subQ,MATCH(E$1,SUBQH,0),0),"") | F16: =IFERROR(VLOOKUP($A16,subQ,MATCH(F$1,SUBQH,0),0),"") | G16: =IFERROR(VLOOKUP($A16,subQ,MATCH(G$1,SUBQH,0),0),"") | H16: =IFERROR(VLOOKUP($A16,subQ,MATCH(H$1,SUBQH,0),0),"") | I16: =IFERROR(VLOOKUP($A16,subQ,MATCH(I$1,SUBQH,0),0),"") | J16: =IFERROR(VLOOKUP($A16,subQ,MATCH(J$1,SUBQH,0),0),"") | K16: =IFERROR(VLOOKUP($A16,subQ,MATCH(K$1,SUBQH,0),0),"") | L16: =IFERROR(VLOOKUP($A16,subQ,MATCH(L$1,SUBQH,0),0),"")
... A39: NPM | D39: NPM | E39: =IFERROR(VLOOKUP($A39,subQ,MATCH(E$1,SUBQH,0),0),"") | F39: =IFERROR(VLOOKUP($A39,subQ,MATCH(F$1,SUBQH,0),0),"") | G39: =IFERROR(VLOOKUP($A39,subQ,MATCH(G$1,SUBQH,0),0),"") | H39: =IFERROR(VLOOKUP($A39,subQ,MATCH(H$1,SUBQH,0),0),"") | I39: =IFERROR(VLOOKUP($A39,subQ,MATCH(I$1,SUBQH,0),0),"") | J39: =IFERROR(VLOOKUP($A39,subQ,MATCH(J$1,SUBQH,0),0),"") | K39: =IFERROR(VLOOKUP($A39,subQ,MATCH(K$1,SUBQH,0),0),"") | L39: =IFERROR(VLOOKUP($A39,subQ,MATCH(L$1,SUBQH,0),0),"")
A40: 매출액 YoY | D40: 매출액 YoY | F40: =IFERROR(F5/E5-1,"") | G40: =IFERROR(G5/F5-1,"") | H40: =IFERROR(H5/G5-1,"") | I40: =IFERROR(I5/H5-1,"") | J40: =IFERROR(J5/I5-1,"") | K40: =IFERROR(K5/J5-1,"") | L40: =IFERROR(L5/K5-1,"")
A41: 영업이익 YoY | D41: 영업이익 YoY | F41: =IFERROR(F9/E9-1,"") | G41: =IFERROR(G9/F9-1,"") | H41: =IFERROR(H9/G9-1,"") | I41: =IFERROR(I9/H9-1,"") | J41: =IFERROR(J9/I9-1,"") | K41: =IFERROR(K9/J9-1,"") | L41: =IFERROR(L9/K9-1,"")
A42: 지배주주순이익 YoY | D42: 지배주주순이익 YoY | F42: =IFERROR(F20/E20-1,"") | G42: =IFERROR(G20/F20-1,"") | H42: =IFERROR(H20/G20-1,"") | I42: =IFERROR(I20/H20-1,"") | J42: =IFERROR(J20/I20-1,"") | K42: =IFERROR(K20/J20-1,"") | L42: =IFERROR(L20/K20-1,"")

Sheet TP
B1: 종가 | C1: =변수!D43
B2: 기준일 | C2: =변수!D44
B3: 모델 산출값 — 목표주가·추천 아님. 밴드·COE 는 변수 시트 3절의 가정
C5: FY | D5: 2025 | E5: 2026 | F5: 2027 | G5: 2028
D6: A | E6: E | F6: E | G6: E
C7: EPS(원) | D7: =IFERROR(VLOOKUP("EPS",subQ,MATCH(D$5,SUBQH,0),0),"") | E7: =IFERROR(VLOOKUP("EPS",subQ,MATCH(E$5,SUBQH,0),0),"") | F7: =IFERROR(VLOOKUP("EPS",subQ,MATCH(F$5,SUBQH,0),0),"") | G7: =IFERROR(VLOOKUP("EPS",subQ,MATCH(G$5,SUBQH,0),0),"")
C8: BPS(원) | D8: =IFERROR(VLOOKUP("BPS",subQ,MATCH(D$5,SUBQH,0),0),"") | E8: =IFERROR(VLOOKUP("BPS",subQ,MATCH(E$5,SUBQH,0),0),"") | F8: =IFERROR(VLOOKUP("BPS",subQ,MATCH(F$5,SUBQH,0),0),"") | G8: =IFERROR(VLOOKUP("BPS",subQ,MATCH(G$5,SUBQH,0),0),"")
C9: 지배주주순이익(억원) | D9: =IFERROR(VLOOKUP("지배주주순이익",subQ,MATCH(D$5,SUBQH,0),0),"") | E9: =IFERROR(VLOOKUP("지배주주순이익",subQ,MATCH(E$5,SUBQH,0),0),"") | F9: =IFERROR(VLOOKUP("지배주주순이익",subQ,MATCH(F$5,SUBQH,0),0),"") | G9: =IFERROR(VLOOKUP("지배주주순이익",subQ,MATCH(G$5,SUBQH,0),0),"")
C10: 영업이익(억원) | D10: =IFERROR(VLOOKUP("영업이익",subQ,MATCH(D$5,SUBQH,0),0),"") | E10: =IFERROR(VLOOKUP("영업이익",subQ,MATCH(E$5,SUBQH,0),0),"") | F10: =IFERROR(VLOOKUP("영업이익",subQ,MATCH(F$5,SUBQH,0),0),"") | G10: =IFERROR(VLOOKUP("영업이익",subQ,MATCH(G$5,SUBQH,0),0),"")
C11: ROE(EPS/기초BPS) | E11: =IFERROR(E7/D8,"") | F11: =IFERROR(F7/E8,"") | G11: =IFERROR(G7/F8,"")
B13: PER
C14: 12M fwd EPS | D14: =IFERROR(E7*변수!D49+F7*(1-변수!D49),"")
C15: 적정가치 @PER_lo | D15: =변수!D46 | E15: =IFERROR(ROUND($D$14*D15,-2),"") | F15: =IFERROR(E15/$C$1-1,"") | G15: 배 · 원 · 종가 대비
C16: 적정가치 @PER_mid | D16: =변수!D47 | E16: =IFERROR(ROUND($D$14*D16,-2),"") | F16: =IFERROR(E16/$C$1-1,"") | G16: 배 · 원 · 종가 대비
C17: 적정가치 @PER_hi | D17: =변수!D48 | E17: =IFERROR(ROUND($D$14*D17,-2),"") | F17: =IFERROR(E17/$C$1-1,"") | G17: 배 · 원 · 종가 대비
C18: 현재 PER(종가/12M fwd EPS) | D18: =IFERROR($C$1/$D$14,"")
B20: PBR
C21: 최근 BPS(마지막 실적 분기) | D21: =IFERROR(VLOOKUP("BPS",subQ,MATCH("2Q26",SUBQH,0),0),"")
C22: ROE fwd(12M fwd EPS / BPS) | D22: =IFERROR($D$14/$D$21,"")
C23: COE | D23: =변수!D45
C24: 적정 PBR = ROE/COE | D24: =IFERROR(D22/D23,"")
C25: 적정가치(PBR) = BPS × 적정PBR | D25: =IFERROR(ROUND(D21*D24,-2),"") | E25: =IFERROR(D25/$C$1-1,"")
C26: 현재 PBR(종가/BPS) | D26: =IFERROR($C$1/D21,"")
B28: 모델 json valuation(참고)
C29: eps_fwd12m | D29: 1725.7
C30: bps_latest | D30: 9540.3
C31: per_now | D31: 9.14
C32: pbr_now | D32: 1.65
C33: roe_fwd | D33: 0.1809
C34: fair_pbr | D34: 2.01
C35: fair_value_pbr | D35: 19200
C36: ev_ebitda
C37: note | D37: 모델 산출값 — 목표주가·추천 아님

Sheet 외화
C1: 이름: 외화QH — 환율 QoQ · 외화 순노출 × Δ기말환율 | E1: 4Q21 | F1: 1Q22 | G1: 2Q22 | H1: 3Q22 | I1: 4Q22 | J1: 1Q23 | K1: 2Q23 | L1: 3Q23 | M1: 4Q23 | N1: 1Q24 | O1: 2Q24 | P1: 3Q24 | Q1: 4Q24 | R1: 1Q25 | S1: 2Q25 | T1: 3Q25 | U1: 4Q25 | V1: 1Q26 | W1: 2Q26 | X1: 3Q26 | Y1: 4Q26 | Z1: 1Q27 | AA1: 2Q27 | AB1: 3Q27 | AC1: 4Q27 | AD1: 1Q28 | AE1: 2Q28 | AF1: 3Q28 | AG1: 4Q28
E3: 1 | F3: 2 | G3: 3 | H3: 4 | I3: 5 | J3: 6 | K3: 7 | L3: 8 | M3: 9 | N3: 10 | O3: 11 | P3: 12 | Q3: 13 | R3: 14 | S3: 15 | T3: 16 | U3: 17 | V3: 18 | W3: 19 | X3: 20 | Y3: 21 | Z3: 22 | AA3: 23 | AB3: 24 | AC3: 25 | AD3: 26 | AE3: 27 | AF3: 28 | AG3: 29
E4: 2021.12 | F4: 2022.03 | G4: 2022.06 | H4: 2022.09 | I4: 2022.12 | J4: 2023.03 | K4: 2023.06 | L4: 2023.09 | M4: 2023.12 | N4: 2024.03 | O4: 2024.06 | P4: 2024.09 | Q4: 2024.12 | R4: 2025.03 | S4: 2025.06 | T4: 2025.09 | U4: 2025.12 | V4: 2026.03 | W4: 2026.06 | X4: 2026.09 | Y4: 2026.12 | Z4: 2027.03 | AA4: 2027.06 | AB4: 2027.09 | AC4: 2027.12 | AD4: 2028.03 | AE4: 2028.06 | AF4: 2028.09 | AG4: 2028.12
D5: 원/달러(평균) | E5: =IFERROR(VLOOKUP($D5,환율,MATCH(E$1,변수H,0),0),"") | F5: =IFERROR(VLOOKUP($D5,환율,MATCH(F$1,변수H,0),0),"") | G5: =IFERROR(VLOOKUP($D5,환율,MATCH(G$1,변수H,0),0),"") | H5: =IFERROR(VLOOKUP($D5,환율,MATCH(H$1,변수H,0),0),"") | I5: =IFERROR(VLOOKUP($D5,환율,MATCH(I$1,변수H,0),0),"") | J5: =IFERROR(VLOOKUP($D5,환율,MATCH(J$1,변수H,0),0),"") | K5: =IFERROR(VLOOKUP($D5,환율,MATCH(K$1,변수H,0),0),"") | L5: =IFERROR(VLOOKUP($D5,환율,MATCH(L$1,변수H,0),0),"") | ... AG5: =IFERROR(VLOOKUP($D5,환율,MATCH(AG$1,변수H,0),0),"")
A6: 원/달러(평균) QoQ | F6: =IFERROR(F5/E5-1,"") | G6: =IFERROR(G5/F5-1,"") | H6: =IFERROR(H5/G5-1,"") | I6: =IFERROR(I5/H5-1,"") | J6: =IFERROR(J5/I5-1,"") | K6: =IFERROR(K5/J5-1,"") | L6: =IFERROR(L5/K5-1,"") | M6: =IFERROR(M5/L5-1,"") | ... AG6: =IFERROR(AG5/AF5-1,"")
D7: 원/달러(기말) | E7: =IFERROR(VLOOKUP($D7,환율,MATCH(E$1,변수H,0),0),"") | F7: =IFERROR(VLOOKUP($D7,환율,MATCH(F$1,변수H,0),0),"") | G7: =IFERROR(VLOOKUP($D7,환율,MATCH(G$1,변수H,0),0),"") | H7: =IFERROR(VLOOKUP($D7,환율,MATCH(H$1,변수H,0),0),"") | I7: =IFERROR(VLOOKUP($D7,환율,MATCH(I$1,변수H,0),0),"") | J7: =IFERROR(VLOOKUP($D7,환율,MATCH(J$1,변수H,0),0),"") | K7: =IFERROR(VLOOKUP($D7,환율,MATCH(K$1,변수H,0),0),"") | L7: =IFERROR(VLOOKUP($D7,환율,MATCH(L$1,변수H,0),0),"") | ... AG7: =IFERROR(VLOOKUP($D7,환율,MATCH(AG$1,변수H,0),0),"")
A8: 원/달러(기말) QoQ | F8: =IFERROR(F7/E7-1,"") | G8: =IFERROR(G7/F7-1,"") | H8: =IFERROR(H7/G7-1,"") | I8: =IFERROR(I7/H7-1,"") | J8: =IFERROR(J7/I7-1,"") | K8: =IFERROR(K7/J7-1,"") | L8: =IFERROR(L7/K7-1,"") | M8: =IFERROR(M7/L7-1,"") | ... AG8: =IFERROR(AG7/AF7-1,"")
D9: W/Euro(평균) | E9: =IFERROR(VLOOKUP($D9,환율,MATCH(E$1,변수H,0),0),"") | F9: =IFERROR(VLOOKUP($D9,환율,MATCH(F$1,변수H,0),0),"") | G9: =IFERROR(VLOOKUP($D9,환율,MATCH(G$1,변수H,0),0),"") | H9: =IFERROR(VLOOKUP($D9,환율,MATCH(H$1,변수H,0),0),"") | I9: =IFERROR(VLOOKUP($D9,환율,MATCH(I$1,변수H,0),0),"") | J9: =IFERROR(VLOOKUP($D9,환율,MATCH(J$1,변수H,0),0),"") | K9: =IFERROR(VLOOKUP($D9,환율,MATCH(K$1,변수H,0),0),"") | L9: =IFERROR(VLOOKUP($D9,환율,MATCH(L$1,변수H,0),0),"") | ... AG9: =IFERROR(VLOOKUP($D9,환율,MATCH(AG$1,변수H,0),0),"")
A10: W/Euro(평균) QoQ | F10: =IFERROR(F9/E9-1,"") | G10: =IFERROR(G9/F9-1,"") | H10: =IFERROR(H9/G9-1,"") | I10: =IFERROR(I9/H9-1,"") | J10: =IFERROR(J9/I9-1,"") | K10: =IFERROR(K9/J9-1,"") | L10: =IFERROR(L9/K9-1,"") | M10: =IFERROR(M9/L9-1,"") | ... AG10: =IFERROR(AG9/AF9-1,"")
D11: W/Euro(기말) | E11: =IFERROR(VLOOKUP($D11,환율,MATCH(E$1,변수H,0),0),"") | F11: =IFERROR(VLOOKUP($D11,환율,MATCH(F$1,변수H,0),0),"") | G11: =IFERROR(VLOOKUP($D11,환율,MATCH(G$1,변수H,0),0),"") | H11: =IFERROR(VLOOKUP($D11,환율,MATCH(H$1,변수H,0),0),"") | I11: =IFERROR(VLOOKUP($D11,환율,MATCH(I$1,변수H,0),0),"") | J11: =IFERROR(VLOOKUP($D11,환율,MATCH(J$1,변수H,0),0),"") | K11: =IFERROR(VLOOKUP($D11,환율,MATCH(K$1,변수H,0),0),"") | L11: =IFERROR(VLOOKUP($D11,환율,MATCH(L$1,변수H,0),0),"") | ... AG11: =IFERROR(VLOOKUP($D11,환율,MATCH(AG$1,변수H,0),0),"")
A12: W/Euro(기말) QoQ | F12: =IFERROR(F11/E11-1,"") | G12: =IFERROR(G11/F11-1,"") | H12: =IFERROR(H11/G11-1,"") | I12: =IFERROR(I11/H11-1,"") | J12: =IFERROR(J11/I11-1,"") | K12: =IFERROR(K11/J11-1,"") | L12: =IFERROR(L11/K11-1,"") | M12: =IFERROR(M11/L11-1,"") | ... AG12: =IFERROR(AG11/AF11-1,"")
D13: 원/100Y(기말) | E13: =IFERROR(VLOOKUP($D13,환율,MATCH(E$1,변수H,0),0),"") | F13: =IFERROR(VLOOKUP($D13,환율,MATCH(F$1,변수H,0),0),"") | G13: =IFERROR(VLOOKUP($D13,환율,MATCH(G$1,변수H,0),0),"") | H13: =IFERROR(VLOOKUP($D13,환율,MATCH(H$1,변수H,0),0),"") | I13: =IFERROR(VLOOKUP($D13,환율,MATCH(I$1,변수H,0),0),"") | J13: =IFERROR(VLOOKUP($D13,환율,MATCH(J$1,변수H,0),0),"") | K13: =IFERROR(VLOOKUP($D13,환율,MATCH(K$1,변수H,0),0),"") | L13: =IFERROR(VLOOKUP($D13,환율,MATCH(L$1,변수H,0),0),"") | ... AG13: =IFERROR(VLOOKUP($D13,환율,MATCH(AG$1,변수H,0),0),"")
A14: 원/100Y(기말) QoQ | F14: =IFERROR(F13/E13-1,"") | G14: =IFERROR(G13/F13-1,"") | H14: =IFERROR(H13/G13-1,"") | I14: =IFERROR(I13/H13-1,"") | J14: =IFERROR(J13/I13-1,"") | K14: =IFERROR(K13/J13-1,"") | L14: =IFERROR(L13/K13-1,"") | M14: =IFERROR(M13/L13-1,"") | ... AG14: =IFERROR(AG13/AF13-1,"")
A16: 외화순노출 | C16: 외화 순노출(백만$) | D16: =변수!D56 | E16: 외화 순노출 × Δ기말환율 (외화 시트 방식)
A17: 환관련손익추정 | C17: 환관련손익 추정(억원) = 순노출 × Δ원/달러(기말) / 100 | F17: =IFERROR($D$16*(F7-E7)/100,"") | G17: =IFERROR($D$16*(G7-F7)/100,"") | H17: =IFERROR($D$16*(H7-G7)/100,"") | I17: =IFERROR($D$16*(I7-H7)/100,"") | J17: =IFERROR($D$16*(J7-I7)/100,"") | K17: =IFERROR($D$16*(K7-J7)/100,"") | L17: =IFERROR($D$16*(L7-K7)/100,"") | M17: =IFERROR($D$16*(M7-L7)/100,"") | ... AG17: =IFERROR($D$16*(AG7-AF7)/100,"")
A18: fx_pnl.by_q | C18: 모델 fx_pnl.by_q(억원, 참고)
C19: 외화 순노출 미공시(face) → 0 + 표기
