Workbook
Name 변수H: 변수!$C$1:$AO$1
Name 환율: 변수!$C$6:$AO$13
Name BS연결H: BS연결!$C$1:$AO$1
Name BS연결: BS연결!$C$5:$AO$107
Name BS별도H: BS별도!$C$1:$AO$1
Name BS별도: BS별도!$C$5:$AO$94
Name SUBQH: subQ!$A$1:$AO$1
Name subQ: subQ!$A$5:$AO$42

Sheet README
A1: 현대리바트(079430) 실적 모델 — ARGUS 한국조선
A2: 기준 분기 2026Q2 · 마지막 실적 2026Q2 · 생성 2026-10-11
A3: 모든 수치는 모델 산출값(DART 공개 재무제표 + 우리 추정)이다 — 목표주가·투자 추천 아님. 참고용 · 투자조언 아님.
A5: 시트
A6: 변수 가정 시계열. 환율 8행(ECB via frankfurter — L2 fx.json; 추정 분기 = 노란 가정), 추정 드라이버(노란 셀 = 모델값에서 역산한 가정, 바꾸면 재계산; 연녹 셀 = 3절 스칼라 참조 수식), 3절 스칼라 가정(세율·판관비율·지배주주비중·이자율·종가·PER 밴드·COE·외화 순노출·헤지비율)
A7: BS연결/BS별도 FnGuide 계정명 × 기간 값 덤프(백만원). 행1 분기라벨, 행4 YYYY.MM / YYYY.12A. 이름정의 BS연결H·BS연결(계정명 C열부터)
A8: subQ 분기 서브모델(억원 = 백만원/100). 확정 행: =IFERROR(VLOOKUP($D행,BS연결,MATCH(E$1,BS연결H,0),0)/100,"") 추정 행: 변수 시트 가정 셀 참조 수식. 외환손익·파생상품손익은 BS 계정 합·차, 기타금융손익은 잔차, OPM·EPS·BPS·PER·PBR 은 파생 수식
A9: SLS 선표(조선사만, sls json 있을 때): 요약 행(sls 저장값) + 계약별 스케줄(백만$) × (헤지비율 × 헤지환율 + (1−헤지비율) × 건조시점 환율[변수 원/달러(평균)]) → 원화 수식 블록 → 합계 행이 subQ 매출조선에 연결
A10: 시나리오 신규수주 보수/기준/낙관(forecast_panel 패널, 모델에 scenarios 가 있을 때만): 매출액·영업이익 = subQ 기준값 ± (시나리오 신규 − base 신규) × OPM. base 만 subQ 행에 포함, 나머지는 합산 안 함
A11: 분기/연간예상 subQ 를 이름(A열 key)으로 VLOOKUP 한 보고서 표(억원)
A12: TP PER 밴드 × 12M fwd EPS, PBR = ROE/COE × BPS — 모델 산출값 구간, 목표주가·추천 아님
A13: 외화 환율 QoQ, 외화 순노출 × Δ기말환율 → 환관련손익 추정
... A34: 백테스트: {"freeze": "2025Q2", "horizon": 4, "revenue_wape_pct": 53.5, "op_wape_pct": 159.0, "n": 4, "note": "단일 회사 4분기 — 통계 아님", "driver_at_freeze": "customer_yard_revenue_weighted", "selection_oos_at_freeze": {"freeze": "2024Q2", "n": 4, "wape_link": 9.8, "wape_trend": 25.5, "adopted": true, "decision": "adopted"}, "frozen_inputs": "fin(연결/별도)·고객 조선사 모델·지주 자회사 모델은 2025Q2 까지의 분기만; 선표는 체결일 ≤ 2025Q2 말일 계약(원장 최신 금액·코호트 등급, 환산 없음); 잔고는 yards_cache 2025Q2; 시세·환율 forward·prices·forecast_panel 신규수주 미사용. 고객 가중치(suppliers.json 언급 비중)와 합병 체인링크는 현재 지식; 고객 연동 채택은 동결 모델 안에서도 자기 la−4분기 OOS 규칙(selection_oos_at_freeze)", "detail": [{"q": "2025Q3", "rev_pred": 5265.44, "rev_act": 3406.55, "op_pred": 68.09, "op_act": 37.37}, {"q": "2025Q4", "rev_pred": 5473.11, "rev_act": 3579.2, "op_pred": 70.77, "op_act": -26.11}, {"q": "2026Q1", "rev_pred": 5550.01, "rev_act": 3559.35, "op_pred": 71.77, "op_act": 10.53}, {"q": "2026Q2", "rev_pred": 5627.6, "rev_act": 3731.33, "op_pred": 72.77, "op_act": 55.59}]}

Sheet 변수
C1: 이름: 변수H | E1: 4Q21 | F1: 2021 | G1: 1Q22 | H1: 2Q22 | I1: 3Q22 | J1: 4Q22 | K1: 2022 | L1: 1Q23 | M1: 2Q23 | N1: 3Q23 | O1: 4Q23 | P1: 2023 | Q1: 1Q24 | R1: 2Q24 | S1: 3Q24 | T1: 4Q24 | U1: 2024 | V1: 1Q25 | W1: 2Q25 | X1: 3Q25 | Y1: 4Q25 | Z1: 2025 | AA1: 1Q26 | AB1: 2Q26 | AC1: 3Q26 | AD1: 4Q26 | AE1: 2026 | AF1: 1Q27 | AG1: 2Q27 | AH1: 3Q27 | AI1: 4Q27 | AJ1: 2027 | AK1: 1Q28 | AL1: 2Q28 | AM1: 3Q28 | AN1: 4Q28 | AO1: 2028
A2: 가정 시계열 — 노란 셀은 추정 가정(모델값에서 역산), 연녹 셀은 3절 스칼라 참조 수식. 바꾸면 subQ·분기·연간예상·TP·시나리오가 재계산됩니다.
E3: 1 | F3: 2 | G3: 3 | H3: 4 | I3: 5 | J3: 6 | K3: 7 | L3: 8 | M3: 9 | N3: 10 | O3: 11 | P3: 12 | Q3: 13 | R3: 14 | S3: 15 | T3: 16 | U3: 17 | V3: 18 | W3: 19 | X3: 20 | Y3: 21 | Z3: 22 | AA3: 23 | AB3: 24 | AC3: 25 | AD3: 26 | AE3: 27 | AF3: 28 | AG3: 29 | AH3: 30 | AI3: 31 | AJ3: 32 | AK3: 33 | AL3: 34 | AM3: 35 | AN3: 36 | AO3: 37
E4: 2021.12 | F4: 2021.12A | G4: 2022.03 | H4: 2022.06 | I4: 2022.09 | J4: 2022.12 | K4: 2022.12A | L4: 2023.03 | M4: 2023.06 | N4: 2023.09 | O4: 2023.12 | P4: 2023.12A | Q4: 2024.03 | R4: 2024.06 | S4: 2024.09 | T4: 2024.12 | U4: 2024.12A | V4: 2025.03 | W4: 2025.06 | X4: 2025.09 | Y4: 2025.12 | Z4: 2025.12A | AA4: 2026.03 | AB4: 2026.06 | AC4: 2026.09 | AD4: 2026.12 | AE4: 2026.12A | AF4: 2027.03 | AG4: 2027.06 | AH4: 2027.09 | AI4: 2027.12 | AJ4: 2027.12A | AK4: 2028.03 | AL4: 2028.06 | AM4: 2028.09 | AN4: 2028.12 | AO4: 2028.12A
B5: 1. FX | C5: 이름: 환율
A6: USDKRW_avg | C6: 원/달러(평균) | E6: 1183.5 | F6: 1145.51 | G6: 1205.78 | H6: 1262.09 | I6: 1341.93 | J6: 1360.12 | K6: 1292.98 | L6: 1276.95 | M6: 1315.69 | N6: 1313.62 | O6: 1322.01 | P6: 1306.85 | Q6: 1330.14 | R6: 1371.28 | S6: 1356.22 | T6: 1396.3 | U6: 1363.53 | V6: 1452.28 | W6: 1398.52 | X6: 1386.95 | Y6: 1449.19 | Z6: 1421.52 | AA6: 1466.12 | AB6: 1501.75 | AC6: 1418.75 | AD6: 1345.14 | AE6: 1457.21 | AF6: 1341.49 | AG6: 1341.49 | AH6: 1341.49 | AI6: 1341.49 | AK6: 1341.49 | AL6: 1341.49 | AM6: 1341.49 | AN6: 1341.49
A7: USDKRW_end | C7: 원/달러(기말) | E7: 1188.75 | F7: 1188.75 | G7: 1213.74 | H7: 1301.24 | I7: 1436.9 | J7: 1260.16 | K7: 1260.16 | L7: 1305.99 | M7: 1321.44 | N7: 1345.35 | O7: 1297.43 | P7: 1297.43 | Q7: 1349.25 | R7: 1377.73 | S7: 1312.17 | T7: 1474.78 | U7: 1474.78 | V7: 1474.54 | W7: 1355.13 | X7: 1403.67 | Y7: 1444.2 | Z7: 1444.2 | AA7: 1524.8 | AB7: 1550.89 | AC7: 1355.4 | AD7: 1341.49 | AE7: 1341.49 | AF7: 1341.49 | AG7: 1341.49 | AH7: 1341.49 | AI7: 1341.49 | AK7: 1341.49 | AL7: 1341.49 | AM7: 1341.49 | AN7: 1341.49
A8: JPY100KRW_avg | C8: 원/100Y(평균) | E8: 1041.02 | F8: 1042.74 | G8: 1036.79 | H8: 972.23 | I8: 970.61 | J8: 961.03 | K8: 985.1 | L8: 964.89 | M8: 957.36 | N8: 909 | O8: 893.22 | P8: 931.11 | Q8: 896.29 | R8: 880.14 | S8: 909.35 | T8: 917.25 | U8: 900.92 | V8: 952.59 | W8: 967.92 | X8: 940.32 | Y8: 940.77 | Z8: 950.17 | AA8: 934.39 | AB8: 942.16 | AC8: 890.41 | AD8: 850.79 | AE8: 919.21 | AF8: 847.7 | AG8: 847.7 | AH8: 847.7 | AI8: 847.7 | AK8: 847.7 | AL8: 847.7 | AM8: 847.7 | AN8: 847.7
A9: JPY100KRW_end | C9: 원/100Y(기말) | E9: 1032.62 | F9: 1032.62 | G9: 996.83 | H9: 954.9 | I9: 993.29 | J9: 955.54 | K9: 955.54 | L9: 980.62 | M9: 913.67 | N9: 901.47 | O9: 917.04 | P9: 917.04 | Q9: 892.42 | R9: 857.76 | S9: 919.21 | T9: 939.65 | U9: 939.65 | V9: 986.84 | W9: 938.85 | X9: 948.49 | Y9: 921.81 | Z9: 921.81 | AA9: 955.99 | AB9: 954.75 | AC9: 863.31 | AD9: 847.7 | AE9: 847.7 | AF9: 847.7 | AG9: 847.7 | AH9: 847.7 | AI9: 847.7 | AK9: 847.7 | AL9: 847.7 | AM9: 847.7 | AN9: 847.7
A10: EURKRW_avg | C10: W/Euro(평균) | E10: 1353.32 | F10: 1354.06 | G10: 1352.29 | H10: 1343.31 | I10: 1350.63 | J10: 1386.07 | K10: 1358.07 | L10: 1369.93 | M10: 1432.41 | N10: 1429.41 | O10: 1420.91 | P10: 1412.88 | Q10: 1444.21 | R10: 1476.42 | S10: 1489.3 | T10: 1490.78 | U10: 1475.4 | V10: 1528.33 | W10: 1585.13 | X10: 1620.04 | Y10: 1686.02 | Z10: 1605.45 | AA10: 1715.47 | AB10: 1746.09 | AC10: 1631.97 | AD10: 1509.74 | AE10: 1689.95 | AF10: 1503.27 | AG10: 1503.27 | AH10: 1503.27 | AI10: 1503.27 | AK10: 1503.27 | AL10: 1503.27 | AM10: 1503.27 | AN10: 1503.27
A11: EURKRW_end | C11: W/Euro(기말) | E11: 1346.38 | F11: 1346.38 | G11: 1347.37 | H11: 1351.6 | I11: 1400.62 | J11: 1344.08 | K11: 1344.08 | L11: 1420.26 | M11: 1435.88 | N11: 1425.26 | O11: 1433.66 | P11: 1433.66 | Q11: 1458.68 | R11: 1474.86 | S11: 1469.1 | T11: 1532.14 | U11: 1532.14 | V11: 1594.72 | W11: 1588.22 | X11: 1648.04 | Y11: 1696.94 | Z11: 1696.94 | AA11: 1753.21 | AB11: 1767.09 | AC11: 1539.06 | AD11: 1503.27 | AE11: 1503.27 | AF11: 1503.27 | AG11: 1503.27 | AH11: 1503.27 | AI11: 1503.27 | AK11: 1503.27 | AL11: 1503.27 | AM11: 1503.27 | AN11: 1503.27
A12: CNYKRW_avg | C12: 원/중국원(평균) | E12: 185.14 | F12: 177.65 | G12: 189.93 | H12: 190.76 | I12: 195.79 | J12: 191.09 | K12: 191.93 | L12: 186.59 | M12: 187.45 | N12: 181.28 | O12: 182.86 | P12: 184.52 | Q12: 185.04 | R12: 189.35 | S12: 189.24 | T12: 194.24 | U12: 189.49 | V12: 199.63 | W12: 193.41 | X12: 193.79 | Y12: 204.38 | Z12: 197.8 | AA12: 211.75 | AB12: 220.8 | AC12: 210.43 | AD12: 200.69 | AE12: 213.75 | AF12: 200.46 | AG12: 200.46 | AH12: 200.46 | AI12: 200.46 | AK12: 200.46 | AL12: 200.46 | AM12: 200.46 | AN12: 200.46
A13: CNYKRW_end | C13: 원/중국원(기말) | E13: 187.13 | F13: 187.13 | G13: 191.38 | H13: 194.13 | I13: 201.92 | J13: 182.67 | K13: 182.67 | L13: 189.97 | M13: 181.8 | N13: 184.26 | O13: 182.61 | P13: 182.61 | Q13: 186.66 | R13: 189.7 | S13: 187.12 | T13: 202.04 | U13: 202.04 | V13: 203.3 | W13: 189.14 | X13: 197.16 | Y13: 206.28 | Z13: 206.28 | AA13: 220.97 | AB13: 228.56 | AC13: 202.16 | AD13: 200.46 | AE13: 200.46 | AF13: 200.46 | AG13: 200.46 | AH13: 200.46 | AI13: 200.46 | AK13: 200.46 | AL13: 200.46 | AM13: 200.46 | AN13: 200.46
B14: 1b. 종가
A15: price_close_end | C15: 종가(기말) | E15: 15150 | G15: 15950 | H15: 10950 | I15: 9210 | J15: 8590 | L15: 7910 | M15: 8650 | N15: 8990 | O15: 7760 | Q15: 7670 | R15: 9220 | S15: 7990 | T15: 7630 | V15: 6910 | W15: 7880 | X15: 7070 | Y15: 6890 | AA15: 6810 | AB15: 5780 | AC15: 5730 | AD15: 5560
A16: price_high | C16: 종가(최고) | E16: 17500 | G16: 17800 | H16: 17000 | I16: 11950 | J16: 11750 | L16: 9730 | M16: 10010 | N16: 9200 | O16: 9650 | Q16: 9080 | R16: 11800 | S16: 10810 | T16: 9360 | V16: 7990 | W16: 8420 | X16: 8610 | Y16: 7170 | AA16: 8900 | AB16: 9300 | AC16: 6290 | AD16: 5800
A17: price_low | C17: 종가(최저) | E17: 13300 | G17: 12500 | H17: 10150 | I17: 9020 | J17: 8210 | L17: 7630 | M17: 7700 | N17: 6600 | O17: 7600 | Q17: 6840 | R17: 7160 | S17: 7690 | T17: 7060 | V17: 6900 | W17: 6590 | X17: 7040 | Y17: 5980 | AA17: 6330 | AB17: 5420 | AC17: 5100 | AD17: 5520
A18: price_avg | C18: 종가(평균) | E18: 15515.9 | G18: 14335.6 | H18: 13646.8 | I18: 10967.5 | J18: 9196.5 | L18: 8797.6 | M18: 8121.8 | N18: 8094.2 | O18: 8076.2 | Q18: 7589.3 | R18: 8743.8 | S18: 8906.6 | T18: 7951.6 | V18: 7493.1 | W18: 7575.8 | X18: 7612.3 | Y18: 6535.6 | AA18: 6910.8 | AB18: 6866.4 | AC18: 5830.8 | AD18: 5640
B20: 2. 추정 드라이버 | C20: 실적 열 = subQ 실현값(수식), 추정 열 = 가정(노란 = 모델값 역산, 연녹 = 3절 스칼라 참조)
A21: drv:매출액 | B21: yoy | C21: 매출액 YoY | J21: =IFERROR(subQ!J5/subQ!E5-1,"") | L21: =IFERROR(subQ!L5/subQ!G5-1,"") | M21: =IFERROR(subQ!M5/subQ!H5-1,"") | N21: =IFERROR(subQ!N5/subQ!I5-1,"") | O21: =IFERROR(subQ!O5/subQ!J5-1,"") | Q21: =IFERROR(subQ!Q5/subQ!L5-1,"") | R21: =IFERROR(subQ!R5/subQ!M5-1,"") | S21: =IFERROR(subQ!S5/subQ!N5-1,"") | T21: =IFERROR(subQ!T5/subQ!O5-1,"") | V21: =IFERROR(subQ!V5/subQ!Q5-1,"") | W21: =IFERROR(subQ!W5/subQ!R5-1,"") | X21: =IFERROR(subQ!X5/subQ!S5-1,"") | Y21: =IFERROR(subQ!Y5/subQ!T5-1,"") | AA21: =IFERROR(subQ!AA5/subQ!V5-1,"") | AB21: =IFERROR(subQ!AB5/subQ!W5-1,"") | AC21: -0.16830273 | AD21: -0.16830269 | AF21: -0.16830404 | AG21: -0.16830281 | AH21: -0.084151601 | AI21: -0.084150483 | AK21: -0.084150255 | AL21: -0.084151269 | AM21: -0.042076461 | AN21: -0.042078854
A22: drv:판관비 | B22: ratio | C22: 판관비율(/매출) | E22: =IFERROR(subQ!E8/subQ!E5,"") | F22: =IFERROR(subQ!F8/subQ!F5,"") | G22: =IFERROR(subQ!G8/subQ!G5,"") | H22: =IFERROR(subQ!H8/subQ!H5,"") | I22: =IFERROR(subQ!I8/subQ!I5,"") | J22: =IFERROR(subQ!J8/subQ!J5,"") | K22: =IFERROR(subQ!K8/subQ!K5,"") | L22: =IFERROR(subQ!L8/subQ!L5,"") | ... AB22: =IFERROR(subQ!AB8/subQ!AB5,"") | AC22: =$D$51 | AD22: =$D$51 | AE22: =IFERROR(subQ!AE8/subQ!AE5,"") | AF22: =$D$51 | AG22: =$D$51 | AH22: =$D$51 | AI22: =$D$51 | AJ22: =IFERROR(subQ!AJ8/subQ!AJ5,"") | AK22: =$D$51 | AL22: =$D$51 | AM22: =$D$51 | AN22: =$D$51 | AO22: =IFERROR(subQ!AO8/subQ!AO5,"")
A23: drv:영업이익 | B23: ratio | C23: 영업이익률(OPM) | E23: =IFERROR(subQ!E9/subQ!E5,"") | F23: =IFERROR(subQ!F9/subQ!F5,"") | G23: =IFERROR(subQ!G9/subQ!G5,"") | H23: =IFERROR(subQ!H9/subQ!H5,"") | I23: =IFERROR(subQ!I9/subQ!I5,"") | J23: =IFERROR(subQ!J9/subQ!J5,"") | K23: =IFERROR(subQ!K9/subQ!K5,"") | L23: =IFERROR(subQ!L9/subQ!L5,"") | ... AB23: =IFERROR(subQ!AB9/subQ!AB5,"") | AC23: 0.01168282 | AD23: 0.011683648 | AE23: =IFERROR(subQ!AE9/subQ!AE5,"") | AF23: 0.011681249 | AG23: 0.011680963 | AH23: 0.011681054 | AI23: 0.011682457 | AJ23: =IFERROR(subQ!AJ9/subQ!AJ5,"") | AK23: 0.011681217 | AL23: 0.011681133 | AM23: 0.011683202 | AN23: 0.011682538 | AO23: =IFERROR(subQ!AO9/subQ!AO5,"")
A24: drv:외환손익 | B24: abs | C24: 외환손익 (가정, 억원) | E24: =subQ!E13 | F24: =subQ!F13 | G24: =subQ!G13 | H24: =subQ!H13 | I24: =subQ!I13 | J24: =subQ!J13 | K24: =subQ!K13 | L24: =subQ!L13 | ... AB24: =subQ!AB13 | AC24: 0 | AD24: 0 | AE24: =subQ!AE13 | AF24: 0 | AG24: 0 | AH24: 0 | AI24: 0 | AJ24: =subQ!AJ13 | AK24: 0 | AL24: 0 | AM24: 0 | AN24: 0 | AO24: =subQ!AO13
A25: drv:파생상품손익 | B25: abs | C25: 파생상품손익 (가정, 억원) | E25: =subQ!E14 | F25: =subQ!F14 | G25: =subQ!G14 | H25: =subQ!H14 | I25: =subQ!I14 | J25: =subQ!J14 | K25: =subQ!K14 | L25: =subQ!L14 | ... AB25: =subQ!AB14 | AC25: 0 | AD25: 0 | AE25: =subQ!AE14 | AF25: 0 | AG25: 0 | AH25: 0 | AI25: 0 | AJ25: =subQ!AJ14 | AK25: 0 | AL25: 0 | AM25: 0 | AN25: 0 | AO25: =subQ!AO14
A26: drv:기타금융손익 | B26: abs | C26: 기타금융손익 (가정, 억원) | E26: =subQ!E15 | F26: =subQ!F15 | G26: =subQ!G15 | H26: =subQ!H15 | I26: =subQ!I15 | J26: =subQ!J15 | K26: =subQ!K15 | L26: =subQ!L15 | ... AB26: =subQ!AB15 | AC26: 0 | AD26: 0 | AE26: =subQ!AE15 | AF26: 0 | AG26: 0 | AH26: 0 | AI26: 0 | AJ26: =subQ!AJ15 | AK26: 0 | AL26: 0 | AM26: 0 | AN26: 0 | AO26: =subQ!AO15
A27: drv:기타영업외손익 | B27: abs | C27: 기타영업외손익 (가정, 억원) | E27: =subQ!E16 | F27: =subQ!F16 | G27: =subQ!G16 | H27: =subQ!H16 | I27: =subQ!I16 | J27: =subQ!J16 | K27: =subQ!K16 | L27: =subQ!L16 | ... AB27: =subQ!AB16 | AC27: 0 | AD27: 0 | AE27: =subQ!AE16 | AF27: 0 | AG27: 0 | AH27: 0 | AI27: 0 | AJ27: =subQ!AJ16 | AK27: 0 | AL27: 0 | AM27: 0 | AN27: 0 | AO27: =subQ!AO16
A28: drv:법인세비용 | B28: tax | C28: 법인세율(/세전) — 법인세 = MAX(세전,0) × 세율 | E28: =IFERROR(subQ!E18/subQ!E17,"") | F28: =IFERROR(subQ!F18/subQ!F17,"") | G28: =IFERROR(subQ!G18/subQ!G17,"") | H28: =IFERROR(subQ!H18/subQ!H17,"") | I28: =IFERROR(subQ!I18/subQ!I17,"") | J28: =IFERROR(subQ!J18/subQ!J17,"") | K28: =IFERROR(subQ!K18/subQ!K17,"") | L28: =IFERROR(subQ!L18/subQ!L17,"") | ... AB28: =IFERROR(subQ!AB18/subQ!AB17,"") | AC28: =$D$50 | AD28: =$D$50 | AE28: =IFERROR(subQ!AE18/subQ!AE17,"") | AF28: =$D$50 | AG28: =$D$50 | AH28: =$D$50 | AI28: =$D$50 | AJ28: =IFERROR(subQ!AJ18/subQ!AJ17,"") | AK28: =$D$50 | AL28: =$D$50 | AM28: =$D$50 | AN28: =$D$50 | AO28: =IFERROR(subQ!AO18/subQ!AO17,"")
A29: drv:지배주주순이익 | B29: ratio | C29: 지배주주 비중(/당기순이익) | E29: =IFERROR(subQ!E20/subQ!E19,"") | F29: =IFERROR(subQ!F20/subQ!F19,"") | G29: =IFERROR(subQ!G20/subQ!G19,"") | H29: =IFERROR(subQ!H20/subQ!H19,"") | I29: =IFERROR(subQ!I20/subQ!I19,"") | J29: =IFERROR(subQ!J20/subQ!J19,"") | K29: =IFERROR(subQ!K20/subQ!K19,"") | L29: =IFERROR(subQ!L20/subQ!L19,"") | ... AB29: =IFERROR(subQ!AB20/subQ!AB19,"") | AC29: =$D$52 | AD29: =$D$52 | AE29: =IFERROR(subQ!AE20/subQ!AE19,"") | AF29: =$D$52 | AG29: =$D$52 | AH29: =$D$52 | AI29: =$D$52 | AJ29: =IFERROR(subQ!AJ20/subQ!AJ19,"") | AK29: =$D$52 | AL29: =$D$52 | AM29: =$D$52 | AN29: =$D$52 | AO29: =IFERROR(subQ!AO20/subQ!AO19,"")
A30: drv:부채총계 | B30: qoq | C30: 부채총계 QoQ | G30: =IFERROR(subQ!G22/subQ!E22-1,"") | H30: =IFERROR(subQ!H22/subQ!G22-1,"") | I30: =IFERROR(subQ!I22/subQ!H22-1,"") | J30: =IFERROR(subQ!J22/subQ!I22-1,"") | L30: =IFERROR(subQ!L22/subQ!J22-1,"") | M30: =IFERROR(subQ!M22/subQ!L22-1,"") | N30: =IFERROR(subQ!N22/subQ!M22-1,"") | O30: =IFERROR(subQ!O22/subQ!N22-1,"") | Q30: =IFERROR(subQ!Q22/subQ!O22-1,"") | R30: =IFERROR(subQ!R22/subQ!Q22-1,"") | S30: =IFERROR(subQ!S22/subQ!R22-1,"") | T30: =IFERROR(subQ!T22/subQ!S22-1,"") | V30: =IFERROR(subQ!V22/subQ!T22-1,"") | W30: =IFERROR(subQ!W22/subQ!V22-1,"") | X30: =IFERROR(subQ!X22/subQ!W22-1,"") | Y30: =IFERROR(subQ!Y22/subQ!X22-1,"") | AA30: =IFERROR(subQ!AA22/subQ!Y22-1,"") | AB30: =IFERROR(subQ!AB22/subQ!AA22-1,"")
A31: drv:자본총계 | B31: roll | C31: 자본총계 기타변동(배당 등, 억원) | G31: =IFERROR(subQ!E23+subQ!G19-subQ!G23,"") | H31: =IFERROR(subQ!G23+subQ!H19-subQ!H23,"") | I31: =IFERROR(subQ!H23+subQ!I19-subQ!I23,"") | J31: =IFERROR(subQ!I23+subQ!J19-subQ!J23,"") | L31: =IFERROR(subQ!J23+subQ!L19-subQ!L23,"") | M31: =IFERROR(subQ!L23+subQ!M19-subQ!M23,"") | N31: =IFERROR(subQ!M23+subQ!N19-subQ!N23,"") | O31: =IFERROR(subQ!N23+subQ!O19-subQ!O23,"") | Q31: =IFERROR(subQ!O23+subQ!Q19-subQ!Q23,"") | R31: =IFERROR(subQ!Q23+subQ!R19-subQ!R23,"") | S31: =IFERROR(subQ!R23+subQ!S19-subQ!S23,"") | T31: =IFERROR(subQ!S23+subQ!T19-subQ!T23,"") | V31: =IFERROR(subQ!T23+subQ!V19-subQ!V23,"") | W31: =IFERROR(subQ!V23+subQ!W19-subQ!W23,"") | X31: =IFERROR(subQ!W23+subQ!X19-subQ!X23,"") | Y31: =IFERROR(subQ!X23+subQ!Y19-subQ!Y23,"") | AA31: =IFERROR(subQ!Y23+subQ!AA19-subQ!AA23,"") | AB31: =IFERROR(subQ!AA23+subQ!AB19-subQ!AB23,"") | AC31: 0.005754465 | AD31: -0.002606911 | AF31: -0.00403701 | AG31: 26.150263 | AH31: -0.003289889 | AI31: -0.000619259 | AK31: -0.004711348 | AL31: 26.145833 | AM31: 0.00172711 | AN31: -0.00113153
A32: drv:지배주주지분 | B32: roll | C32: 지배주주지분 기타변동(배당 등, 억원) | G32: =IFERROR(subQ!E24+subQ!G20-subQ!G24,"") | H32: =IFERROR(subQ!G24+subQ!H20-subQ!H24,"") | I32: =IFERROR(subQ!H24+subQ!I20-subQ!I24,"") | J32: =IFERROR(subQ!I24+subQ!J20-subQ!J24,"") | L32: =IFERROR(subQ!J24+subQ!L20-subQ!L24,"") | M32: =IFERROR(subQ!L24+subQ!M20-subQ!M24,"") | N32: =IFERROR(subQ!M24+subQ!N20-subQ!N24,"") | O32: =IFERROR(subQ!N24+subQ!O20-subQ!O24,"") | Q32: =IFERROR(subQ!O24+subQ!Q20-subQ!Q24,"") | R32: =IFERROR(subQ!Q24+subQ!R20-subQ!R24,"") | S32: =IFERROR(subQ!R24+subQ!S20-subQ!S24,"") | T32: =IFERROR(subQ!S24+subQ!T20-subQ!T24,"") | V32: =IFERROR(subQ!T24+subQ!V20-subQ!V24,"") | W32: =IFERROR(subQ!V24+subQ!W20-subQ!W24,"") | X32: =IFERROR(subQ!W24+subQ!X20-subQ!X24,"") | Y32: =IFERROR(subQ!X24+subQ!Y20-subQ!Y24,"") | AA32: =IFERROR(subQ!Y24+subQ!AA20-subQ!AA24,"") | AB32: =IFERROR(subQ!AA24+subQ!AB20-subQ!AB24,"") | AC32: 0.005754465 | AD32: -0.002606911 | AF32: -0.00403701 | AG32: 26.150263 | AH32: -0.003289889 | AI32: -0.000619259 | AK32: -0.004711348 | AL32: 26.145833 | AM32: 0.00172711 | AN32: -0.00113153
A33: drv:총차입금 | B33: qoq | C33: 총차입금 QoQ | G33: =IFERROR(subQ!G25/subQ!E25-1,"") | H33: =IFERROR(subQ!H25/subQ!G25-1,"") | I33: =IFERROR(subQ!I25/subQ!H25-1,"") | J33: =IFERROR(subQ!J25/subQ!I25-1,"") | L33: =IFERROR(subQ!L25/subQ!J25-1,"") | M33: =IFERROR(subQ!M25/subQ!L25-1,"") | N33: =IFERROR(subQ!N25/subQ!M25-1,"") | O33: =IFERROR(subQ!O25/subQ!N25-1,"") | Q33: =IFERROR(subQ!Q25/subQ!O25-1,"") | R33: =IFERROR(subQ!R25/subQ!Q25-1,"") | S33: =IFERROR(subQ!S25/subQ!R25-1,"") | T33: =IFERROR(subQ!T25/subQ!S25-1,"") | V33: =IFERROR(subQ!V25/subQ!T25-1,"") | W33: =IFERROR(subQ!W25/subQ!V25-1,"") | X33: =IFERROR(subQ!X25/subQ!W25-1,"") | Y33: =IFERROR(subQ!Y25/subQ!X25-1,"") | AA33: =IFERROR(subQ!AA25/subQ!Y25-1,"") | AB33: =IFERROR(subQ!AB25/subQ!AA25-1,"")
A34: drv:순차입금 | B34: qoq | C34: 순차입금 QoQ | G34: =IFERROR(subQ!G26/subQ!E26-1,"") | H34: =IFERROR(subQ!H26/subQ!G26-1,"") | I34: =IFERROR(subQ!I26/subQ!H26-1,"") | J34: =IFERROR(subQ!J26/subQ!I26-1,"") | L34: =IFERROR(subQ!L26/subQ!J26-1,"") | M34: =IFERROR(subQ!M26/subQ!L26-1,"") | N34: =IFERROR(subQ!N26/subQ!M26-1,"") | O34: =IFERROR(subQ!O26/subQ!N26-1,"") | Q34: =IFERROR(subQ!Q26/subQ!O26-1,"") | R34: =IFERROR(subQ!R26/subQ!Q26-1,"") | S34: =IFERROR(subQ!S26/subQ!R26-1,"") | T34: =IFERROR(subQ!T26/subQ!S26-1,"") | V34: =IFERROR(subQ!V26/subQ!T26-1,"") | W34: =IFERROR(subQ!W26/subQ!V26-1,"") | X34: =IFERROR(subQ!X26/subQ!W26-1,"") | Y34: =IFERROR(subQ!Y26/subQ!X26-1,"") | AA34: =IFERROR(subQ!AA26/subQ!Y26-1,"") | AB34: =IFERROR(subQ!AB26/subQ!AA26-1,"")
A35: drv:이자발생자산 | B35: qoq | C35: 이자발생자산 QoQ | G35: =IFERROR(subQ!G27/subQ!E27-1,"") | H35: =IFERROR(subQ!H27/subQ!G27-1,"") | I35: =IFERROR(subQ!I27/subQ!H27-1,"") | J35: =IFERROR(subQ!J27/subQ!I27-1,"") | L35: =IFERROR(subQ!L27/subQ!J27-1,"") | M35: =IFERROR(subQ!M27/subQ!L27-1,"") | N35: =IFERROR(subQ!N27/subQ!M27-1,"") | O35: =IFERROR(subQ!O27/subQ!N27-1,"") | Q35: =IFERROR(subQ!Q27/subQ!O27-1,"") | R35: =IFERROR(subQ!R27/subQ!Q27-1,"") | S35: =IFERROR(subQ!S27/subQ!R27-1,"") | T35: =IFERROR(subQ!T27/subQ!S27-1,"") | V35: =IFERROR(subQ!V27/subQ!T27-1,"") | W35: =IFERROR(subQ!W27/subQ!V27-1,"") | X35: =IFERROR(subQ!X27/subQ!W27-1,"") | Y35: =IFERROR(subQ!Y27/subQ!X27-1,"") | AA35: =IFERROR(subQ!AA27/subQ!Y27-1,"") | AB35: =IFERROR(subQ!AB27/subQ!AA27-1,"") | AC35: 0.032111391 | AD35: 0.032623198 | AF35: 0.031571708 | AG35: 0.005595847 | AH35: 0.027341396 | AI35: 0.02786523 | AK35: 0.027100297 | AL35: 0.003352566 | AM35: 0.024580253 | AN35: 0.025098647
A36: drv:현금및현금성자산 | B36: qoq | C36: 현금및현금성자산 QoQ | G36: =IFERROR(subQ!G28/subQ!E28-1,"") | H36: =IFERROR(subQ!H28/subQ!G28-1,"") | I36: =IFERROR(subQ!I28/subQ!H28-1,"") | J36: =IFERROR(subQ!J28/subQ!I28-1,"") | L36: =IFERROR(subQ!L28/subQ!J28-1,"") | M36: =IFERROR(subQ!M28/subQ!L28-1,"") | N36: =IFERROR(subQ!N28/subQ!M28-1,"") | O36: =IFERROR(subQ!O28/subQ!N28-1,"") | Q36: =IFERROR(subQ!Q28/subQ!O28-1,"") | R36: =IFERROR(subQ!R28/subQ!Q28-1,"") | S36: =IFERROR(subQ!S28/subQ!R28-1,"") | T36: =IFERROR(subQ!T28/subQ!S28-1,"") | V36: =IFERROR(subQ!V28/subQ!T28-1,"") | W36: =IFERROR(subQ!W28/subQ!V28-1,"") | X36: =IFERROR(subQ!X28/subQ!W28-1,"") | Y36: =IFERROR(subQ!Y28/subQ!X28-1,"") | AA36: =IFERROR(subQ!AA28/subQ!Y28-1,"") | AB36: =IFERROR(subQ!AB28/subQ!AA28-1,"")
A37: drv:CAPEX | B37: yoy | C37: CAPEX YoY | J37: =IFERROR(subQ!J29/subQ!E29-1,"") | L37: =IFERROR(subQ!L29/subQ!G29-1,"") | M37: =IFERROR(subQ!M29/subQ!H29-1,"") | N37: =IFERROR(subQ!N29/subQ!I29-1,"") | O37: =IFERROR(subQ!O29/subQ!J29-1,"") | Q37: =IFERROR(subQ!Q29/subQ!L29-1,"") | R37: =IFERROR(subQ!R29/subQ!M29-1,"") | S37: =IFERROR(subQ!S29/subQ!N29-1,"") | T37: =IFERROR(subQ!T29/subQ!O29-1,"") | V37: =IFERROR(subQ!V29/subQ!Q29-1,"") | W37: =IFERROR(subQ!W29/subQ!R29-1,"") | X37: =IFERROR(subQ!X29/subQ!S29-1,"") | Y37: =IFERROR(subQ!Y29/subQ!T29-1,"") | AA37: =IFERROR(subQ!AA29/subQ!V29-1,"") | AB37: =IFERROR(subQ!AB29/subQ!W29-1,"") | AC37: -0.47370001 | AD37: -0.21987213 | AF37: 0.39263125 | AG37: 0.81381603 | AH37: 0 | AI37: 0 | AK37: 0 | AL37: 0 | AM37: 0 | AN37: 0
A38: drv:영업활동현금흐름 | B38: yoy | C38: 영업활동현금흐름 YoY | J38: =IFERROR(subQ!J30/subQ!E30-1,"") | L38: =IFERROR(subQ!L30/subQ!G30-1,"") | M38: =IFERROR(subQ!M30/subQ!H30-1,"") | N38: =IFERROR(subQ!N30/subQ!I30-1,"") | O38: =IFERROR(subQ!O30/subQ!J30-1,"") | Q38: =IFERROR(subQ!Q30/subQ!L30-1,"") | R38: =IFERROR(subQ!R30/subQ!M30-1,"") | S38: =IFERROR(subQ!S30/subQ!N30-1,"") | T38: =IFERROR(subQ!T30/subQ!O30-1,"") | V38: =IFERROR(subQ!V30/subQ!Q30-1,"") | W38: =IFERROR(subQ!W30/subQ!R30-1,"") | X38: =IFERROR(subQ!X30/subQ!S30-1,"") | Y38: =IFERROR(subQ!Y30/subQ!T30-1,"") | AA38: =IFERROR(subQ!AA30/subQ!V30-1,"") | AB38: =IFERROR(subQ!AB30/subQ!W30-1,"")
A39: drv:주식수 | B39: qoq | C39: 주식수 QoQ | G39: =IFERROR(subQ!G31/subQ!E31-1,"") | H39: =IFERROR(subQ!H31/subQ!G31-1,"") | I39: =IFERROR(subQ!I31/subQ!H31-1,"") | J39: =IFERROR(subQ!J31/subQ!I31-1,"") | L39: =IFERROR(subQ!L31/subQ!J31-1,"") | M39: =IFERROR(subQ!M31/subQ!L31-1,"") | N39: =IFERROR(subQ!N31/subQ!M31-1,"") | O39: =IFERROR(subQ!O31/subQ!N31-1,"") | Q39: =IFERROR(subQ!Q31/subQ!O31-1,"") | R39: =IFERROR(subQ!R31/subQ!Q31-1,"") | S39: =IFERROR(subQ!S31/subQ!R31-1,"") | T39: =IFERROR(subQ!T31/subQ!S31-1,"") | V39: =IFERROR(subQ!V31/subQ!T31-1,"") | W39: =IFERROR(subQ!W31/subQ!V31-1,"") | X39: =IFERROR(subQ!X31/subQ!W31-1,"") | Y39: =IFERROR(subQ!Y31/subQ!X31-1,"") | AA39: =IFERROR(subQ!AA31/subQ!Y31-1,"") | AB39: =IFERROR(subQ!AB31/subQ!AA31-1,"") | AC39: 0 | AD39: 0 | AF39: 0 | AG39: 0 | AH39: 0 | AI39: 0 | AK39: 0 | AL39: 0 | AM39: 0 | AN39: 0
A40: drv:DPS | B40: abs | C40: DPS (가정, 원) | E40: =subQ!E34 | F40: =subQ!F34 | G40: =subQ!G34 | H40: =subQ!H34 | I40: =subQ!I34 | J40: =subQ!J34 | K40: =subQ!K34 | L40: =subQ!L34 | ... AB40: =subQ!AB34 | AD40: 130 | AE40: =subQ!AE34 | AI40: 130 | AJ40: =subQ!AJ34 | AN40: 130 | AO40: =subQ!AO34
B42: 3. 밸류에이션·스칼라 | C42: 노란 셀 = 가정. '연결' 표시는 추정 전 분기 수식이 이 셀을 참조한다는 뜻
A43: sc:종가 | C43: 종가 | D43: 5560 | E43: 원 — 네이버 정규장 종가(aik 확정종가 대조 · aik 5,570원)
A44: sc:기준일 | C44: 기준일 | D44: 20261008 | E44: 종가 기준일
A45: sc:COE | C45: COE | D45: 0.09 | E45: 자기자본비용(가정) — TP 적정 PBR = ROE/COE
A46: sc:PER_lo | C46: PER_lo | D46: 12.8 | E46: PER 밴드 하단(배) — hist_quarterly(분기 평균가 ÷ TTM EPS, 8분기, 25/50/75 백분위) · 캡 5~30배 적용(원값 12.8/16.0/56.4)
A47: sc:PER_mid | C47: PER_mid | D47: 16 | E47: PER 밴드 중단(배)
A48: sc:PER_hi | C48: PER_hi | D48: 30 | E48: PER 밴드 상단(배)
A49: sc:EPS_Y1가중 | C49: EPS_Y1가중 | D49: 0.5 | E49: 12M fwd EPS = FY(last_actual연도)E × w + FY+1E × (1−w) — 기준 분기 2Q 이면 0.5(가정)
A50: sc:세율 | C50: 세율 | D50: 0.24287805 | E50: 연결 — 법인세 = MAX(세전,0) × 세율(역산, 재현 오차 ≤ 0.05억 · 모델 assumptions 0.2429) · 최근 12분기 유효세율 177.6% 가 5~27% 밖 → 클립 대신 최근 8분기 중 세전 > 0 인 7분기(2024Q3~2026Q2)의 법인세/세전 중위 24.3%
A51: sc:판관비율 | C51: 판관비율 | D51: 0.1636509 | E51: 연결 — 판관비 = 매출액 × 판관비율(역산, 재현 오차 ≤ 0.05억 · 모델 assumptions 0.1637)
A52: sc:지배주주비중 | C52: 지배주주비중 | D52: 1 | E52: 연결 — 지배주주순이익 = 당기순이익 × 비중(역산, 재현 오차 ≤ 0.05억)
A53: sc:이자율_자산 | C53: 이자율_자산 | D53: 0.022650938 | E53: 연결 — 이자손익 = (전분기 이자발생자산 × 자산이자율 − 전분기 총차입금 × 부채이자율)/4(역산, 재현 오차 ≤ 0.05억 · 모델 assumptions 0.0227)
A54: sc:이자율_부채 | C54: 이자율_부채 | D54: 0 | E54: 연결 — 같은 수식의 부채 쪽(총차입금 행이 없으면 0)(역산, 재현 오차 ≤ 0.05억 · 모델 assumptions 0.047)
A55: sc:배당성향 | C55: 배당성향 | D55: 0.353 | E55: 배당성향(참고 — 모델은 직전 DPS 유지·Q2 지급 가정)
A56: sc:외화순노출_백만$ | C56: 외화순노출_백만$ | E56: 외화 순노출 × Δ기말환율 (외화 시트 방식) — 외화 순노출 미공시(face) → 0 + 표기
A57: sc:헤지비율 | C57: 헤지비율 | E57: sls 없음
A58: sc:헤지환율_약정 | C58: 헤지환율_약정 | E58: sls 없음

Sheet BS연결
B1: (백만원) | C1: 이름: BS연결H | E1: 4Q21 | F1: 2021 | G1: 1Q22 | H1: 2Q22 | I1: 3Q22 | J1: 4Q22 | K1: 2022 | L1: 1Q23 | M1: 2Q23 | N1: 3Q23 | O1: 4Q23 | P1: 2023 | Q1: 1Q24 | R1: 2Q24 | S1: 3Q24 | T1: 4Q24 | U1: 2024 | V1: 1Q25 | W1: 2Q25 | X1: 3Q25 | Y1: 4Q25 | Z1: 2025 | AA1: 1Q26 | AB1: 2Q26 | AC1: 3Q26 | AD1: 4Q26 | AE1: 2026 | AF1: 1Q27 | AG1: 2Q27 | AH1: 3Q27 | AI1: 4Q27 | AJ1: 2027 | AK1: 1Q28 | AL1: 2Q28 | AM1: 3Q28 | AN1: 4Q28 | AO1: 2028
B2: 연결 | D2: fin json(kship_fin.py)
B3: 현대리바트(연) | C3: UPDATE: 26-10-11 | E3: 1 | F3: 2 | G3: 3 | H3: 4 | I3: 5 | J3: 6 | K3: 7 | L3: 8 | M3: 9 | N3: 10 | O3: 11 | P3: 12 | Q3: 13 | R3: 14 | S3: 15 | T3: 16 | U3: 17 | V3: 18 | W3: 19 | X3: 20 | Y3: 21 | Z3: 22 | AA3: 23 | AB3: 24 | AC3: 25 | AD3: 26 | AE3: 27 | AF3: 28 | AG3: 29 | AH3: 30 | AI3: 31 | AJ3: 32 | AK3: 33 | AL3: 34 | AM3: 35 | AN3: 36 | AO3: 37
B4: Account Code | C4: AccountNAME | E4: 2021.12 | F4: 2021.12A | G4: 2022.03 | H4: 2022.06 | I4: 2022.09 | J4: 2022.12 | K4: 2022.12A | L4: 2023.03 | M4: 2023.06 | N4: 2023.09 | O4: 2023.12 | P4: 2023.12A | Q4: 2024.03 | R4: 2024.06 | S4: 2024.09 | T4: 2024.12 | U4: 2024.12A | V4: 2025.03 | W4: 2025.06 | X4: 2025.09 | Y4: 2025.12 | Z4: 2025.12A | AA4: 2026.03 | AB4: 2026.06 | AC4: 2026.09 | AD4: 2026.12 | AE4: 2026.12A | AF4: 2027.03 | AG4: 2027.06 | AH4: 2027.09 | AI4: 2027.12 | AJ4: 2027.12A | AK4: 2028.03 | AL4: 2028.06 | AM4: 2028.09 | AN4: 2028.12 | AO4: 2028.12A
A5: 1 | C5: 유동자산 | E5: 430586.11 | F5: 430586.11 | G5: 385413.14 | H5: 407344.29 | I5: 440514.04 | J5: 452085.67 | K5: 452085.67 | L5: 436815.13 | M5: 469370.3 | N5: 530911.66 | O5: 511898.83 | P5: 511898.83 | Q5: 563551.18 | R5: 541852.46 | S5: 529131.27 | T5: 478301.94 | U5: 478301.94 | V5: 474362.69 | W5: 461003.21 | X5: 414269.07 | Y5: 405941.23 | Z5: 405941.23 | AA5: 455561.55 | AB5: 479386.76
A6: 1 | C6: 현금및현금성자산 | E6: 14279.25 | F6: 14279.25 | G6: 10698.94 | H6: 10653.03 | I6: 12545.3 | J6: 14896.6 | K6: 14896.6 | L6: 18605.43 | M6: 14313.62 | N6: 15942.53 | O6: 21158.75 | P6: 21158.75 | Q6: 9048.06 | R6: 10907 | S6: 58103.82 | T6: 19122.66 | U6: 19122.66 | V6: 20019.41 | W6: 32250.37 | X6: 17318.76 | Y6: 18308.94 | Z6: 18308.94 | AA6: 32198.25 | AB6: 62336.58
A7: 1 | C7: 매출채권및기타채권 | E7: 237036.37 | F7: 237036.37 | G7: 209882 | H7: 203970.25 | I7: 211829.17 | J7: 246854.8 | K7: 246854.8 | L7: 232002.24 | M7: 245614.88 | N7: 293236.36 | O7: 258609.36 | P7: 258609.36 | Q7: 332543.86 | R7: 315666.75 | S7: 253078.1 | T7: 223102.42 | U7: 223102.42 | V7: 241887.88 | W7: 236415.49 | X7: 213746.8 | Y7: 201881.38 | Z7: 201881.38 | AA7: 222690.27 | AB7: 222573.88
A8: 1 | C8: 단기금융상품 | E8: 8951.38 | F8: 8951.38 | G8: 8030.93 | H8: 7744.57 | I8: 7767.15 | J8: 7814.4 | K8: 7814.4 | L8: 5942.95 | M8: 5600.21 | N8: 5786.41 | O8: 5611.67 | P8: 5611.67 | Q8: 5536.68 | R8: 9005.57 | S8: 9295.65
A9: 1 | C9: 단기금융자산 | E9: 8951.38 | F9: 8951.38 | G9: 8030.93 | H9: 7744.57 | I9: 7767.15 | J9: 7814.4 | K9: 7814.4 | L9: 5942.95 | M9: 5600.21 | N9: 5786.41 | O9: 5611.67 | P9: 5611.67 | Q9: 5536.68 | R9: 9005.57 | S9: 9295.65
A10: 1 | C10: 재고자산 | E10: 142534.05 | F10: 142534.05 | G10: 132502.7 | H10: 153985.32 | I10: 164842.44 | J10: 162300.13 | K10: 162300.13 | L10: 166069.26 | M10: 189425.39 | N10: 203940.53 | O10: 213456.76 | P10: 213456.76 | Q10: 204099.94 | R10: 193026.95 | S10: 199808.92 | T10: 219376.94 | U10: 219376.94 | V10: 193972.96 | W10: 174032.45 | X10: 166883.51 | Y10: 165047.7 | Z10: 165047.7 | AA10: 153733.69 | AB10: 154965.33
A11: 1 | C11: 당기법인세자산(선급법인세) | E11: 62.9 | F11: 62.9 | G11: 33.31 | H11: 0.09 | I11: 45.29 | J11: 1844.5 | K11: 1844.5 | L11: 1854.79 | M11: 75.97 | N11: 61.12 | O11: 75.13 | P11: 75.13 | Q11: 203.19 | R11: 177.59 | S11: 47.63 | T11: 174.2 | U11: 174.2 | V11: 169.1 | W11: 37.52 | X11: 36.48 | Y11: 197.21 | Z11: 197.21 | AA11: 40.84 | AB11: 40.84
A12: 1 | C12: 계약자산 | E12: 60.09 | F12: 60.09 | G12: 61.37 | H12: 139.5 | I12: 19992.29 | J12: 6794.99 | K12: 6794.99 | L12: 5784.06 | M12: 5839.42 | N12: 6533.31 | O12: 6260.07 | P12: 6260.07 | Q12: 4268.77 | R12: 4369.59 | S12: 2145.51
A13: 1 | C13: 기타유동자산 | E13: 27662.06 | F13: 27662.06 | G13: 24203.9 | H13: 30851.52 | I13: 23492.4 | J13: 11580.25 | K13: 11580.25 | L13: 6556.4 | M13: 8500.8 | N13: 5411.4 | O13: 6727.08 | P13: 6727.08 | Q13: 7850.68 | R13: 8699.01 | S13: 6651.64 | T13: 6201.62 | U13: 6201.62 | V13: 7492.2 | W13: 6306.17 | X13: 5606.12 | Y13: 5956.56 | Z13: 5956.56 | AA13: 10597.22 | AB13: 10886.75
A14: 1 | C14: 비유동자산 | E14: 433062.39 | F14: 433062.39 | G14: 432150.86 | H14: 432157.5 | I14: 426520.87 | J14: 402073.66 | K14: 402073.66 | L14: 401198.54 | M14: 396144.87 | N14: 392192.79 | O14: 387562.5 | P14: 387562.5 | Q14: 374788.61 | R14: 367200.51 | S14: 361682.64 | T14: 380084.48 | U14: 380084.48 | V14: 369347.4 | W14: 364279.11 | X14: 362951.51 | Y14: 367314.96 | Z14: 367314.96 | AA14: 341816.4 | AB14: 343547.33
A15: 1 | C15: 장기금융자산 | E15: 35192.68 | F15: 35192.68 | G15: 35435.37 | H15: 35549.11 | I15: 34977.93 | J15: 33986.41 | K15: 33986.41 | L15: 37722.94 | M15: 38048.65 | N15: 36781.44 | O15: 36992.7 | P15: 36992.7 | Q15: 34034.56 | R15: 30238.61 | S15: 30007.66 | T15: 29972.42 | U15: 29972.42 | V15: 29803.19 | W15: 28198.72 | X15: 28653.21 | Y15: 23857.62 | Z15: 23857.62 | AA15: 21910.97 | AB15: 27711.84
A16: 1 | C16: 투자자산 | E16: 35192.68 | F16: 35192.68 | G16: 35435.37 | H16: 35549.11 | I16: 34977.93 | J16: 33986.41 | K16: 33986.41 | L16: 37722.94 | M16: 38048.65 | N16: 36781.44 | O16: 36992.7 | P16: 36992.7 | Q16: 34034.56 | R16: 30238.61 | S16: 30007.66 | T16: 29972.42 | U16: 29972.42 | V16: 29803.19 | W16: 28198.72 | X16: 28653.21 | Y16: 23857.62 | Z16: 23857.62 | AA16: 21910.97 | AB16: 27711.84
A17: 1 | C17: 유형자산 | E17: 365549.02 | F17: 365549.02 | G17: 366408.14 | H17: 366399.19 | I17: 361565.09 | J17: 322241.77 | K17: 322241.77 | L17: 319797.9 | M17: 315197.55 | N17: 313694.09 | O17: 302201.42 | P17: 302201.42 | Q17: 297181.71 | R17: 296479.32 | S17: 293717.9 | T17: 289575.46 | U17: 289575.46 | V17: 286014.41 | W17: 284320.95 | X17: 285179.85 | Y17: 279921.36 | Z17: 279921.36 | AA17: 276407.37 | AB17: 274244.31
A18: 1 | C18: 투자부동산 | E18: 1301.84 | F18: 1301.84 | G18: 1293.31 | H18: 910.47 | I18: 904.72 | J18: 898.97 | K18: 898.97 | L18: 893.21 | M18: 2008.17 | N18: 1994.65 | O18: 1981.13 | P18: 1981.13 | Q18: 1967.62 | R18: 1954.1 | S18: 1940.58 | T18: 1927.06 | U18: 1927.06 | V18: 1913.55 | W18: 1900.03 | X18: 1886.51 | Y18: 1873 | Z18: 1873 | AA18: 1859.48 | AB18: 1845.96
A19: 1 | C19: 무형자산 | E19: 27998.83 | F19: 27998.83 | G19: 27756.45 | H19: 27514.06 | I19: 27271.68 | J19: 27029.29 | K19: 27029.29 | L19: 26786.91 | M19: 26544.53 | N19: 26302.14 | O19: 27081.76 | P19: 27081.76 | Q19: 26839.38 | R19: 26596.99 | S19: 26354.61
A20: 1 | C20: 이연법인세자산 | E20: 119.66 | F20: 119.66 | G20: 139.56 | H20: 167.8 | I20: 202.69 | J20: 6873.3 | K20: 6873.3 | L20: 8439.76 | M20: 7889.3 | N20: 7729.01 | O20: 13866.9 | P20: 13866.9 | Q20: 12612.71 | R20: 10885.33 | S20: 9404.42 | T20: 11037.56 | U20: 11037.56 | V20: 9838.98 | W20: 9710.3 | X20: 8837.62 | Y20: 8997.84 | Z20: 8997.84 | AA20: 8831.94 | AB20: 8209.84
A21: 1 | C21: 기타비유동자산 | E21: 1808.5 | F21: 1808.5 | G21: 18.86 | H21: 18.1 | I21: 18.56 | J21: 9505.72 | K21: 9505.72 | L21: 7557.82 | M21: 6456.67 | N21: 5691.47 | O21: 5438.59 | P21: 5438.59 | Q21: 2152.63 | R21: 1046.17 | S21: 257.46 | T21: 2.09 | U21: 2.09
A22: 1 | C22: 자산총계 | E22: 863648.5 | F22: 863648.5 | G22: 817564 | H22: 839501.79 | I22: 867034.91 | J22: 854159.33 | K22: 854159.33 | L22: 838013.67 | M22: 865515.17 | N22: 923104.45 | O22: 899461.32 | P22: 899461.32 | Q22: 938339.78 | R22: 909052.97 | S22: 890813.9
A23: 1 | C23: 유동부채 | E23: 320525.54 | F23: 320525.54 | G23: 272846.15 | H23: 294374.53 | I23: 322671.77 | J23: 374995.67 | K23: 374995.67 | L23: 367884.75 | M23: 395847.62 | N23: 453378.85 | O23: 454030.88 | P23: 454030.88 | Q23: 498240.96 | R23: 443428.67 | S23: 417432.52 | T23: 386392.17 | U23: 386392.17 | V23: 369742.09 | W23: 372215.97 | X23: 330022.48 | Y23: 329975.03 | Z23: 329975.03 | AA23: 316255.87 | AB23: 319157.98
A24: 1 | C24: 매입채무및기타채무 | E24: 212254.17 | F24: 212254.17 | G24: 192043.44 | H24: 205094.65 | I24: 188587.42 | J24: 201387.12 | K24: 201387.12 | L24: 211795.1 | M24: 235150.9 | N24: 238064.63 | O24: 270930.14 | P24: 270930.14 | Q24: 278019.12 | R24: 265178.01 | S24: 257210.89 | T24: 244666.17 | U24: 244666.17 | V24: 219497.1 | W24: 228269.98 | X24: 184971.26 | Y24: 188794.21 | Z24: 188794.21 | AA24: 176848.17 | AB24: 204927.73
A25: 1 | C25: 단기차입금 | E25: 34471.7 | F25: 34471.7 | G25: 24161.19 | H25: 31728.61 | I25: 54195.75 | J25: 110019.58 | K25: 110019.58 | L25: 107559.93 | M25: 111575.32 | N25: 170590.04 | O25: 138808.86 | P25: 138808.86 | Q25: 153989.08 | R25: 112119.71 | S25: 111842.2
A26: 1 | C26: 단기금융부채(face) | E26: 34471.7 | F26: 34471.7 | G26: 24161.19 | H26: 31728.61 | I26: 54195.75 | J26: 110019.58 | K26: 110019.58 | L26: 107559.93 | M26: 111575.32 | N26: 170590.04 | O26: 138808.86 | P26: 138808.86 | Q26: 153989.08 | R26: 112119.71 | S26: 111842.2
A27: 1 | C27: 기타유동부채 | E27: 2818.96 | F27: 2818.96 | G27: 2104.93 | H27: 1114.5 | I27: 1167.92 | J27: 1809.07 | K27: 1809.07 | L27: 854.56 | M27: 872.52 | N27: 1258.77 | O27: 2288.57 | P27: 2288.57 | Q27: 2172.26 | R27: 4155.89 | S27: 1672.32 | T27: 2189.16 | U27: 2189.16 | V27: 4379.82 | W27: 3280.87 | X27: 3053.23 | Y27: 3352.75 | Z27: 3352.75 | AA27: 2922.05 | AB27: 1700.28
A28: 1 | C28: 계약부채 | E28: 53733.13 | F28: 53733.13 | G28: 35663.58 | H28: 37324.4 | I28: 60740.46 | J28: 39202.65 | K28: 39202.65 | L28: 28157.45 | M28: 30136.41 | N28: 26094.72 | O28: 24946.51 | P28: 24946.51 | Q28: 39856.15 | R28: 40819.64 | S28: 28235.66 | T28: 35628.21 | U28: 35628.21 | V28: 25298.9 | W28: 19976.68 | X28: 18582.45 | Y28: 21159.5 | Z28: 21159.5 | AA28: 26899.75 | AB28: 38711.05
A29: 1 | C29: 당기법인세부채(미지급법인세) | E29: 707.79 | F29: 707.79 | G29: 1445.75 | H29: 1377.23 | I29: 194.8 | J29: 0 | K29: 0 | L29: 3.18 | M29: 13.26 | N29: 2.53 | O29: 83.4 | P29: 83.4 | Q29: 358.64 | R29: 359.91 | S29: 297.11 | T29: 42.49 | U29: 42.49 | V29: 394.92 | W29: 446.03 | X29: 244.23 | Y29: 78.35 | Z29: 78.35 | AA29: 252.5 | AB29: 522.27
A30: 1 | C30: 단기충당부채 | E30: 2740.18 | F30: 2740.18 | G30: 3172.77 | H30: 3192.44 | I30: 3558.4 | J30: 9051.05 | K30: 9051.05 | L30: 6452.14 | M30: 5059.29 | N30: 4560.31 | O30: 4823.74 | P30: 4823.74 | Q30: 12132.79 | R30: 8355.23 | S30: 5157.5 | T30: 5921.23 | U30: 5921.23 | V30: 4937.72 | W30: 4856.03 | X30: 4679.6 | Y30: 3733.71 | Z30: 3733.71 | AA30: 3279.59 | AB30: 3127.38
A31: 1 | C31: 비유동부채 | E31: 54065.48 | F31: 54065.48 | G31: 55641.18 | H31: 56665.08 | I31: 55049.42 | J31: 40630.56 | K31: 40630.56 | L31: 38393.4 | M31: 36097.74 | N31: 36318.52 | O31: 43073.63 | P31: 43073.63 | Q31: 32988.15 | R31: 52856.45 | S31: 56331.03 | T31: 60250.5 | U31: 60250.5 | V31: 58386.12 | W31: 37522.79 | X31: 28517.56 | Y31: 25209.48 | Z31: 25209.48 | AA31: 64089.26 | AB31: 83113.67
A32: 1 | C32: 장기차입금 | E32: 628.01 | F32: 628.01 | G32: 276.18 | H32: 377.77 | I32: 323.23 | J32: 229.69 | K32: 229.69 | L32: 546.2 | M32: 528.01 | N32: 583.71 | O32: 591.98 | P32: 591.98 | Q32: 177.04 | R32: 20272.17 | S32: 24227.3
A33: 1 | C33: 장기금융부채(face) | E33: 628.01 | F33: 628.01 | G33: 276.18 | H33: 377.77 | I33: 323.23 | J33: 229.69 | K33: 229.69 | L33: 546.2 | M33: 528.01 | N33: 583.71 | O33: 591.98 | P33: 591.98 | Q33: 177.04 | R33: 20272.17 | S33: 24227.3
A34: 1 | C34: 장기충당부채 | E34: 2782.97 | F34: 2782.97 | G34: 2687.59 | H34: 2938.46 | I34: 2917.45 | J34: 2853.05 | K34: 2853.05 | L34: 2767.81 | M34: 2855.78 | N34: 2750.14 | O34: 10851.49 | P34: 10851.49 | Q34: 3014.42 | R34: 3074.15 | S34: 3071.4 | T34: 3155.88 | U34: 3155.88 | V34: 3109.87 | W34: 3321.85 | X34: 3396.67 | Y34: 3013.64 | Z34: 3013.64 | AA34: 2950.24 | AB34: 2735.44
A35: 1 | C35: 이연법인세부채 | E35: 7795.07 | F35: 7795.07 | G35: 7408.92 | H35: 6914.44 | I35: 6562.99 | J35: 0 | K35: 0 | L35: 0 | M35: 0 | N35: 0 | O35: 0 | P35: 0 | Q35: 0 | R35: 0 | S35: 0
A36: 1 | C36: 기타비유동부채 | E36: 1107.41 | F36: 1107.41 | G36: 1081.45 | H36: 1037.66 | I36: 1110.65 | J36: 1175.81 | K36: 1175.81 | L36: 1249.6 | M36: 1260.48 | N36: 1279.18 | O36: 1410.78 | P36: 1410.78 | Q36: 1413.37 | R36: 1423.17 | S36: 1432.7 | T36: 1750.34 | U36: 1750.34 | V36: 1811.24 | W36: 1746.52 | X36: 1871.23 | Y36: 2330.66 | Z36: 2330.66 | AA36: 2370.62 | AB36: 2395.89
A37: 1 | C37: 부채총계 | E37: 374591.02 | F37: 374591.02 | G37: 328487.33 | H37: 351039.6 | I37: 377721.19 | J37: 415626.22 | K37: 415626.22 | L37: 406278.15 | M37: 431945.35 | N37: 489697.37 | O37: 497104.51 | P37: 497104.51 | Q37: 531229.11 | R37: 496285.12 | S37: 473763.55
A38: 1 | C38: 지배주주지분 | E38: 489057.48 | F38: 489057.48 | G38: 489076.67 | H38: 488462.18 | I38: 489313.72 | J38: 438533.11 | K38: 438533.11 | L38: 431735.52 | M38: 433569.82 | N38: 433407.08 | O38: 402356.81 | P38: 402356.81 | Q38: 407110.67 | R38: 412767.85 | S38: 417050.36 | T38: 411743.74 | U38: 411743.74 | V38: 415581.89 | W38: 415543.55 | X38: 418680.54 | Y38: 418071.67 | Z38: 418071.67 | AA38: 417032.82 | AB38: 420662.43
A39: 1 | C39: 자본금 | E39: 20535.28 | F39: 20535.28 | G39: 20535.28 | H39: 20535.28 | I39: 20535.28 | J39: 20535.28 | K39: 20535.28 | L39: 20535.28 | M39: 20535.28 | N39: 20535.28 | O39: 20535.28 | P39: 20535.28 | Q39: 20535.28 | R39: 20535.28 | S39: 20535.28 | T39: 20535.28 | U39: 20535.28 | V39: 20535.28 | W39: 20535.28 | X39: 20535.28 | Y39: 20535.28 | Z39: 20535.28 | AA39: 20535.28 | AB39: 20535.28
A40: 1 | C40: 자본잉여금 | E40: 101695.16 | F40: 101695.16 | G40: 101695.16 | H40: 101695.16 | I40: 101695.16 | J40: 101695.16 | K40: 101695.16 | L40: 101695.16 | M40: 101695.16 | N40: 101695.16 | O40: 101695.16 | P40: 101695.16 | Q40: 101695.16 | R40: 101695.16 | S40: 101695.16 | T40: 101695.16 | U40: 101695.16 | V40: 101695.16 | W40: 101695.16 | X40: 101695.16 | Y40: 101695.16 | Z40: 101695.16 | AA40: 101695.16 | AB40: 101695.16
A41: 1 | C41: 기타자본 | E41: -3428.12 | F41: -3428.12 | G41: -3428.12 | H41: -3428.12 | I41: -3428.12 | J41: -3428.12 | K41: -3428.12 | L41: -3428.12 | M41: -3428.12 | N41: -3428.12 | O41: -3428.12 | P41: -3428.12 | Q41: -3428.12 | R41: -3428.12 | S41: -3428.12 | T41: -3428.12 | U41: -3428.12 | V41: -3428.12 | W41: -3428.12 | X41: -3428.12 | Y41: -3428.12 | Z41: -3428.12 | AA41: -3428.12 | AB41: 0
A42: 1 | C42: 기타포괄이익누계액 | E42: 406.65 | F42: 406.65 | G42: 430.45 | H42: 532.98 | I42: 839.48 | J42: 418.07 | K42: 418.07 | L42: 572.28 | M42: 490.81 | N42: 505.45 | O42: 382.17 | P42: 382.17 | Q42: 404.86 | R42: 446.62 | S42: 519.65 | T42: 865.73 | U42: 865.73 | V42: 804.71 | W42: 167.49 | X42: 320.95 | Y42: 630.94 | Z42: 630.94 | AA42: 1017.21 | AB42: 1145.84
A43: 1 | C43: 이익잉여금 | E43: 369848.5 | F43: 369848.5 | G43: 369843.9 | H43: 369126.88 | I43: 369671.92 | J43: 319312.71 | K43: 319312.71 | L43: 312360.92 | M43: 314276.68 | N43: 314099.31 | O43: 283172.31 | P43: 283172.31 | Q43: 287903.48 | R43: 293518.91 | S43: 297728.38 | T43: 292075.69 | U43: 292075.69 | V43: 295974.85 | W43: 296573.74 | X43: 299557.26 | Y43: 298638.41 | Z43: 298638.41 | AA43: 297213.28 | AB43: 297286.15
A44: 1 | C44: 자본총계 | E44: 489057.48 | F44: 489057.48 | G44: 489076.67 | H44: 488462.18 | I44: 489313.72 | J44: 438533.11 | K44: 438533.11 | L44: 431735.52 | M44: 433569.82 | N44: 433407.08 | O44: 402356.81 | P44: 402356.81 | Q44: 407110.67 | R44: 412767.85 | S44: 417050.36 | T44: 411743.74 | U44: 411743.74 | V44: 415581.89 | W44: 415543.55 | X44: 418680.54 | Y44: 418071.67 | Z44: 418071.67 | AA44: 417032.82 | AB44: 420662.43
A45: 1 | C45: 부채와자본총계 | E45: 863648.5 | F45: 863648.5 | G45: 817564 | H45: 839501.79 | I45: 867034.91 | J45: 854159.33 | K45: 854159.33 | L45: 838013.67 | M45: 865515.17 | N45: 923104.45 | O45: 899461.32 | P45: 899461.32 | Q45: 938339.78 | R45: 909052.97 | S45: 890813.9
A46: 1 | C46: 총차입금 | E46: 35099.71 | F46: 35099.71 | G46: 24437.37 | H46: 32106.38 | I46: 54518.98 | J46: 110249.27 | K46: 110249.27 | L46: 108106.13 | M46: 112103.33 | N46: 171173.75 | O46: 139400.84 | P46: 139400.84 | Q46: 154166.12 | R46: 132391.88 | S46: 136069.5
A47: 1 | C47: 순차입금 | E47: 11869.08 | F47: 11869.08 | G47: 5707.5 | H47: 13708.78 | I47: 34206.53 | J47: 87538.27 | K47: 87538.27 | L47: 83557.75 | M47: 92189.5 | N47: 149444.81 | O47: 112630.42 | P47: 112630.42 | Q47: 139581.38 | R47: 112479.31 | S47: 68670.03
A48: 1 | C48: 이자발생자산 | E48: 58423.31 | F48: 58423.31 | G48: 54165.24 | H48: 53946.71 | I48: 55290.38 | J48: 56697.41 | K48: 56697.41 | L48: 62271.32 | M48: 57962.48 | N48: 58510.38 | O48: 63763.12 | P48: 63763.12 | Q48: 48619.3 | R48: 50151.18 | S48: 97407.13 | T48: 49095.08 | U48: 49095.08 | V48: 49822.6 | W48: 60449.09 | X48: 45971.97 | Y48: 42166.56 | Z48: 42166.56 | AA48: 54109.22 | AB48: 90048.42
A49: 1 | C49: 확정급여부채 | G49: 2125.59 | H49: 3506.51 | I49: 4753.9 | J49: 0 | K49: 0 | L49: 0 | M49: 0 | N49: 0 | S49: 143.49 | T49: 32.18 | U49: 32.18 | V49: 236.31 | W49: 395.33 | X49: 1135.56 | AB49: 28.61
A50: 1 | C50: 유동리스부채 | O50: 12149.65 | P50: 12149.65 | Q50: 11712.93 | R50: 12440.27 | S50: 13016.84 | T50: 12863.34 | U50: 12863.34 | V50: 12380.73 | W50: 12014.42 | X50: 12150.44 | Y50: 11227.59 | Z50: 11227.59 | AA50: 11184.55 | AB50: 11480.96
A51: 1 | C51: 리스부채 | O51: 41244.88 | P51: 41244.88 | Q51: 38815.65 | R51: 39412.88 | S51: 39442.78 | T51: 37063.78 | U51: 37063.78 | V51: 34590.38 | W51: 33097.99 | X51: 33344.73 | Y51: 30145.75 | Z51: 30145.75 | AA51: 29119.28 | AB51: 28510.62
A52: 1 | C52: 단기금융부채 | O52: 12149.65 | P52: 12149.65 | Q52: 11712.93 | R52: 12440.27 | S52: 13016.84 | T52: 94600.99 | U52: 94600.99 | V52: 112294.86 | W52: 114122.67 | X52: 117805.88 | Y52: 112856.51 | Z52: 112856.51 | AA52: 99188.62 | AB52: 63305.55
A53: 1 | C53: 비유동리스부채 | O53: 29095.23 | P53: 29095.23 | Q53: 27102.72 | R53: 26972.61 | S53: 26425.94 | T53: 24200.44 | U53: 24200.44 | V53: 22209.65 | W53: 21083.57 | X53: 21194.29 | Y53: 18918.16 | Z53: 18918.16 | AA53: 17934.73 | AB53: 17029.66
A54: 1 | C54: 장기금융부채 | O54: 29095.23 | P54: 29095.23 | Q54: 27102.72 | R54: 26972.61 | S54: 26425.94 | T54: 54320.69 | U54: 54320.69 | V54: 52308.07 | W54: 31235.67 | X54: 21377.76 | Y54: 19161.04 | Z54: 19161.04 | AA54: 58053.8 | AB54: 77247.42
A55: 1 | C55: 기타유동금융자산 | T55: 10324.1 | U55: 10324.1 | V55: 10514.81 | W55: 11961.21 | X55: 10677.39 | Y55: 14549.44 | Z55: 14549.44 | AA55: 36301.28 | AB55: 28583.37
A56: 1 | C56: 장기매출채권및기타채권 | T56: 16338.41 | U56: 16338.41 | V56: 13951.11 | W56: 12584.33 | X56: 13009.25 | Y56: 14129.7 | Z56: 14129.7 | AA56: 1884.18 | AB56: 2414.84
A57: 1 | C57: 기타유동금융부채 | T57: 81737.65 | U57: 81737.65 | V57: 99914.13 | W57: 102108.25 | X57: 105655.44 | Y57: 101628.92 | Z57: 101628.92 | AA57: 88004.07 | AB57: 51824.59
A58: 1 | C58: 기타비유동금융부채 | T58: 30120.25 | U58: 30120.25 | V58: 30098.42 | W58: 10152.1 | X58: 183.47 | Y58: 242.88 | Z58: 242.88 | AA58: 40119.07 | AB58: 60217.76
A59: 1 | C59: 비지배주주지분 | T59: 0 | U59: 0
A60: 1 | C60: 매출액(수익) | E60: 371878.68 | G60: 368754.95 | H60: 360072.1 | I60: 364281.71 | J60: 402592.35 | K60: 1495701.1 | L60: 370218.98 | M60: 398671.34 | N60: 396614.25 | O60: 420200.37 | P60: 1585704.9 | Q60: 504787.43 | R60: 496957.05 | S60: 454114.68 | T60: 414797.84 | U60: 1870657 | V60: 437760.42 | W60: 409870.55 | X60: 340655.2 | Y60: 357919.88 | Z60: 1546206.1 | AA60: 355935.36 | AB60: 373133.4
A61: 1 | C61: 매출원가 | E61: 308261.66 | G61: 305509.61 | H61: 300475.38 | I61: 303416.33 | J61: 372721.91 | K61: 1282123.2 | L61: 320220.84 | M61: 337334.19 | N61: 332290.86 | O61: 371958.05 | P61: 1361803.9 | Q61: 433314.47 | R61: 424748.49 | S61: 381817.74 | T61: 345557.7 | U61: 1585438.4 | V61: 361613.8 | W61: 336420.78 | X61: 270841.4 | Y61: 309239.3 | Z61: 1278115.3 | AA61: 293723.68 | AB61: 309561.68
A62: 1 | C62: 매출총이익 | E62: 63617.02 | G62: 63245.34 | H62: 59596.71 | I62: 60865.38 | J62: 29870.44 | K62: 213577.87 | L62: 49998.14 | M62: 61337.15 | N62: 64323.39 | O62: 48242.32 | P62: 223901 | Q62: 71472.96 | R62: 72208.56 | S62: 72296.94 | T62: 69240.14 | U62: 285218.6 | V62: 76146.62 | W62: 73449.76 | X62: 69813.8 | Y62: 48680.58 | Z62: 268090.76 | AA62: 62211.67 | AB62: 63571.72
A63: 1 | C63: 판관비 | E63: 62289.75 | G63: 60329.67 | H63: 59882.58 | I63: 60355.25 | J63: 60905.7 | K63: 241473.2 | L63: 57603.07 | M63: 57861.25 | N63: 63074.58 | O63: 65214.23 | P63: 243753.13 | Q63: 64674.16 | R63: 64038.49 | S63: 62533.12 | T63: 69936.28 | U63: 261182.05 | V63: 66634.87 | W63: 68369.93 | X63: 66076.66 | Y63: 51291.95 | Z63: 252373.41 | AA63: 61159.14 | AB63: 58013.19
A64: 1 | C64: 영업이익 | E64: 1327.27 | G64: 2915.68 | H64: -285.87 | I64: 510.13 | J64: -31035.26 | K64: -27895.32 | L64: -7604.93 | M64: 3475.9 | N64: 1248.81 | O64: -16971.91 | P64: -19852.13 | Q64: 6798.8 | R64: 8170.07 | S64: 9763.82 | T64: -696.14 | U64: 24036.55 | V64: 9511.74 | W64: 5079.83 | X64: 3737.14 | Y64: -2611.37 | Z64: 15717.34 | AA64: 1052.53 | AB64: 5558.53
A65: 1 | C65: 기타영업외수익 | E65: 178.86 | G65: 199.15 | H65: 144.43 | I65: 129.56 | J65: 40.09 | K65: 513.23 | L65: 149.73 | M65: 133.12 | N65: 198.96 | O65: 349.13 | P65: 830.94 | Q65: 255.29 | R65: 314.35 | S65: 148.27 | T65: 225.29 | U65: 943.2 | V65: 272.48 | W65: 303.74 | X65: 162.38 | Y65: 304.76 | Z65: 1043.36 | AA65: 408.7 | AB65: 430.75
A66: 1 | C66: 기타영업외비용 | E66: 466.84 | G66: 428.6 | H66: 169.21 | I66: 132.46 | J66: 30964.76 | K66: 31695.03 | L66: 497.31 | M66: 82.59 | N66: -9.13 | O66: 14556.91 | P66: 15127.68 | Q66: 46.97 | R66: 63.57 | S66: 70.61 | T66: 186.13 | U66: 367.28 | V66: 36.59 | W66: 464.92 | X66: 65.35 | Y66: 1514.03 | Z66: 2080.89 | AA66: 66.08 | AB66: 842.14
A67: 1 | C67: 금융수익 | E67: 378.38 | G67: 1424.07 | H67: 2590.55 | I67: 5450.18 | J67: -1554.6 | K67: 7910.2 | L67: 2041.24 | M67: 1766.21 | N67: 1530.33 | O67: -749.66 | P67: 4588.12 | Q67: 2325.18 | R67: 2061.65 | S67: -1443.16 | T67: 4152.18 | U67: 7095.85 | V67: 844.91 | W67: 1174.92 | X67: 527.56 | Y67: 1426.27 | Z67: 3973.66 | AA67: 2573.56 | AB67: 2001.61
A68: 1 | C68: 금융비용 | E68: 644.05 | G68: 1341.34 | H68: 3014.36 | I68: 5077.67 | J68: 5368.15 | K68: 14801.52 | L68: 2398.07 | M68: 2868.4 | N68: 2917.42 | O68: 2848.17 | P68: 11032.06 | Q68: 2951.06 | R68: 2996.86 | S68: 2511.45 | T68: 3023.89 | U68: 11483.26 | V68: 2403.46 | W68: 5239.1 | X68: 396.2 | Y68: 1452.59 | Z68: 9491.35 | AA68: 1746.51 | AB68: 2312.31
A69: 1 | C69: 법인세비용차감전계속사업이익 | E69: 773.62 | G69: 2768.95 | H69: -734.47 | I69: 879.74 | J69: -68882.68 | K69: -65968.46 | L69: -8309.35 | M69: 2424.24 | N69: 69.81 | O69: -34777.51 | P69: -40592.81 | Q69: 6381.23 | R69: 7485.63 | S69: 5886.86 | T69: 471.3 | U69: 20225.02 | V69: 8189.08 | W69: 854.48 | X69: 3965.53 | Y69: -3846.95 | Z69: 9162.14 | AA69: 2222.19 | AB69: 4836.44
A70: 1 | C70: 법인세비용 | E70: -729.61 | G70: 646.58 | H70: -124.59 | I70: 249.21 | J70: -15968.61 | K70: -15197.41 | L70: -1468.5 | M70: 415.97 | N70: 185.89 | O70: -5590.63 | P70: -6457.27 | Q70: 1697.04 | R70: 1736.4 | S70: 1663.95 | T70: -51.32 | U70: 5046.07 | V70: 1632.67 | W70: 236.4 | X70: 963.12 | Y70: -1077.13 | Z70: 1755.06 | AA70: 607.67 | AB70: 1082
A71: 1 | C71: 당기순이익 | E71: 1503.23 | G71: 2122.37 | H71: -609.88 | I71: 630.53 | J71: -52914.06 | K71: -50771.04 | L71: -6840.85 | M71: 2008.28 | N71: -116.08 | O71: -29186.88 | P71: -34135.53 | Q71: 4684.19 | R71: 5749.23 | S71: 4222.91 | T71: 522.62 | U71: 15178.95 | V71: 6556.42 | W71: 618.09 | X71: 3002.4 | Y71: -2769.82 | Z71: 7407.09 | AA71: 1614.52 | AB71: 3754.44
... A76: 1 | C76: 계속사업이익 | E76: 1503.23 | G76: 2122.37 | H76: -609.88 | I76: 630.53 | J76: -52914.06 | K76: -50771.04 | L76: -6840.85 | M76: 2008.28 | N76: -116.08 | O76: -29186.88 | P76: -34135.53 | Q76: 4684.19 | R76: 5749.23 | S76: 4222.91 | T76: 522.62 | U76: 15178.95 | V76: 6556.42 | W76: 618.09 | X76: 3002.4 | Y76: -2769.82 | Z76: 7407.09 | AA76: 1614.52 | AB76: 3754.44
A77: 1 | C77: 이자수익 | G77: 208.38 | H77: 250.03 | I77: 221.66 | J77: 251.91 | K77: 931.98 | L77: 221.29 | M77: 242.3 | N77: 249.02 | O77: 132.37 | P77: 844.98 | Q77: 240.06 | R77: 269.78 | S77: 266.3 | T77: 335 | U77: 1111.14 | V77: 270.81 | W77: 294.41 | X77: 255.58 | Y77: 246.9 | Z77: 1067.7 | AA77: 260.7 | AB77: 552.33
A78: 1 | C78: 이자비용 | G78: 346.42 | H78: 375.25 | I78: 728.05 | J78: 1098.63 | K78: 2548.35 | L78: 1430.43 | M78: 1645.8 | N78: 1977.19 | O78: 2473.18 | P78: 7526.6 | Q78: 2127.18 | R78: 2173.95 | S78: 2265.13 | T78: 1833.19 | U78: 8399.45 | V78: 1762.94 | W78: 1641.54 | X78: 1156.97 | Y78: 1150.98 | Z78: 5712.43 | AA78: 1144.78 | AB78: 1301.1
A79: 1 | C79: 외환차익 | G79: 401.18 | H79: 870.77 | I79: 1592.18 | J79: 2136.56 | K79: 5000.69 | L79: 746.04 | N79: 387.74 | O79: 550.26 | Q79: 506.06 | S79: 266.5 | T79: 319.9 | V79: 353.48 | W79: 340.21 | X79: 484.91 | Y79: 762.31 | Z79: 1940.91 | AA79: 955.3 | AB79: 493.61
A80: 1 | C80: 외환차손 | G80: 675.48 | H80: 1355.95 | I80: 2090.13 | J80: 2530.12 | K80: 6651.68 | L80: 747.36 | M80: 597.1 | N80: 520.95 | O80: 466.28 | P80: 2331.69 | Q80: 347.13 | R80: 403.47 | S80: 337.91 | T80: 692.91 | U80: 1781.42 | V80: 438.45 | W80: 563.31 | X80: 1365.47 | Y80: 659.89 | Z80: 3027.12 | AA80: 439.34 | AB80: 643.11
A81: 1 | C81: 외화환산이익 | G81: 802.04 | H81: 1464.79 | I81: 3634.8 | J81: -3943.07 | K81: 1958.56 | L81: 1073.91 | M81: 891.65 | N81: 893.56 | O81: -1437.59 | P81: 1421.53 | Q81: 1579.07 | R81: 1346.39 | S81: -1975.96 | T81: 3497.28 | U81: 4446.78 | V81: 180.7 | W81: 538.65 | X81: -262.97 | Y81: 270.51 | Z81: 726.89 | AA81: 1180.87 | AB81: 866.6
A82: 1 | C82: 외화환산손실 | G82: 319.44 | H82: 1044.86 | I82: 2046.47 | J82: 1739.4 | K82: 5150.17 | L82: 220.28 | M82: 625.49 | N82: 419.29 | O82: -101.14 | P82: 1163.92 | Q82: 458.68 | R82: 410.46 | S82: -91.59 | T82: 497.79 | U82: 1275.34 | V82: 193.49 | W82: 2921.98 | X82: -2117.5 | Y82: -455.43 | Z82: 542.54 | AA82: 150.62 | AB82: 223.98
A83: 1 | C83: 이자손익 | G83: -138.04 | H83: -125.22 | I83: -506.39 | J83: -846.72 | K83: -1616.37 | L83: -1209.14 | M83: -1403.5 | N83: -1728.17 | O83: -2340.81 | P83: -6681.62 | Q83: -1887.12 | R83: -1904.17 | S83: -1998.83 | T83: -1498.19 | U83: -7288.31 | V83: -1492.13 | W83: -1347.13 | X83: -901.39 | Y83: -904.08 | Z83: -4644.73 | AA83: -884.08 | AB83: -748.77
A84: 1 | C84: 파생상품손실 | H84: 237.5 | I84: 213.02 | J84: 0 | Q84: 18.07 | R84: 8.97 | S84: 0 | T84: 0 | U84: 27.04 | V84: 8.57 | W84: 112.27 | X84: -8.74 | Y84: 97.14 | Z84: 209.24 | AA84: 11.77 | AB84: 26.66
A85: 1 | C85: (비지배주주지분)당기순이익 | L85: 0 | M85: 0
A86: 1 | C86: 배당금수익 | M86: 15.13 | N86: 0 | O86: 0 | R86: 22.4 | S86: 0 | T86: 0 | V86: 0 | W86: 25.82 | X86: 0 | Y86: 0 | Z86: 25.82 | AA86: 3.83 | AB86: 51.8
A87: 1 | C87: 파생상품이익 | M87: 6.75 | N87: 0 | O87: 5.31 | V87: 39.91 | W87: -24.16 | X87: 50.03 | Y87: 146.56 | Z87: 212.34 | AA87: 153.39 | AB87: 86.73
A88: 1 | C88: 영업활동으로인한현금흐름 | E88: -2577.4 | G88: 16441.59 | H88: 2262.41 | I88: -14492.06 | J88: -46878.96 | K88: -42667.02 | L88: 13932.01 | M88: -2616.03 | N88: -51713.01 | O88: 43150.59 | P88: 2753.56 | Q88: -25950.23 | R88: 28484.94 | S88: 47711.35 | T88: -9662.97 | U88: 40583.09 | V88: -8473.1 | W88: 38044.93 | X88: -1743.32 | Y88: 10126.43 | Z88: 37954.94 | AA88: 14629.84 | AB88: 48186.66
A89: 1 | C89: 이자수취(CF) | E89: 32.28 | G89: 32.36 | H89: 59.05 | I89: 30.39 | J89: 57.84 | K89: 179.64 | L89: 38.97 | M89: 77.16 | N89: 44.23 | O89: 44.89 | P89: 205.25 | Q89: 64.25 | R89: 149.1 | S89: 67.36 | V89: 71.53 | W89: 151.72 | X89: 70.05 | Y89: 65.65 | Z89: 358.95 | AA89: 87.93 | AB89: 359.44
A90: 1 | C90: 이자지급(CF) | E90: -365.16 | G90: -424.32 | H90: -578.8 | I90: -590.15 | J90: -931.92 | K90: -2525.19 | L90: -1408.9 | M90: -1588.87
A91: 1 | C91: 법인세납부(CF) | E91: 9.37 | G91: -251.31 | H91: -387.37 | I91: -1831.93 | J91: -0.79 | K91: -2471.4 | L91: -73.22 | M91: 1946.85 | N91: -13.1 | O91: -41.43 | P91: 1819.1 | Q91: -136.41 | R91: -87.41 | S91: -62.83 | V91: -54.87 | W91: 71.12 | X91: -268.28 | Y91: 23.18 | Z91: -228.85 | AA91: 47.06 | AB91: -105.09
A92: 1 | C92: 투자활동으로인한현금흐름 | E92: -3569.55 | G92: -3725.1 | H92: -6078.95 | I92: -2654.62 | J92: -2843.22 | K92: -15301.89 | L92: -4838.45 | M92: -2116.5 | N92: -2076.94 | O92: -2786.99 | P92: -11818.88 | Q92: 2475.9 | R92: -1622.19 | S92: -976.47 | T92: -2017.33 | U92: -2140.09 | V92: -2807.31 | W92: -4371.89 | X92: -3681.16 | Y92: -2002.61 | Z92: -12862.97 | AA92: -21668.37 | AB92: 125.68
A93: 1 | C93: 유형자산의감소 | E93: 39.71 | G93: 859.58 | I93: 6.18 | J93: 48.68 | L93: 35.85 | M93: 11.21 | N93: 2.36 | O93: 38.13 | P93: 87.55 | S93: 54.18 | T93: 112.69 | V93: 15.29 | W93: 585.7 | X93: 37.7 | Y93: 43.35 | Z93: 682.04 | AA93: 1.27 | AB93: 1.64
A94: 1 | C94: 유형자산의증가 | E94: 5488.89 | G94: 5364.98 | H94: 5376.94 | I94: 3297.9 | J94: 4010.47 | K94: 18050.29 | L94: 4705.3 | M94: 1746.6 | N94: 3375.87 | O94: 1764.25 | P94: 11592.02 | Q94: 621.15 | R94: 1363.81 | S94: 1075.21 | V94: 2857.41 | W94: 5186.91 | X94: 4664.64 | Y94: 3146.92 | Z94: 15855.88 | AA94: 1762.85 | AB94: 1353.5
A95: 1 | C95: CAPEX | E95: 5488.89 | G95: 5364.98 | H95: 5376.94 | I95: 3297.9 | J95: 4010.47 | K95: 18050.29 | L95: 4705.3 | M95: 1746.6 | N95: 3375.87 | O95: 2786.25 | P95: 12614.02 | Q95: 621.15 | R95: 1363.81 | S95: 1075.21 | V95: 2857.41 | W95: 5186.91 | X95: 4664.64 | Y95: 3146.92 | Z95: 15855.88 | AA95: 1762.85 | AB95: 1353.5
A96: 1 | C96: 재무활동으로인한현금흐름 | E96: 9400.95 | G96: -16267.93 | H96: 3699.99 | I96: 18973.28 | J96: 52215.73 | K96: 58621.07 | L96: -5475.32 | M96: 608.64 | N96: 55401.75 | O96: -35205.63 | P96: 15329.44 | Q96: 11315.08 | R96: -25049.62 | S96: 462.88 | T96: -27498.13 | U96: -40769.79 | V96: 12152.9 | W96: -21045.43 | X96: -9728.71 | Y96: -7227.42 | Z96: -25848.66 | AA96: 20590.9 | AB96: -19145.47
A97: 1 | C97: 단기차입금의증가 | E97: 62561.58 | G97: 17667.22 | H97: 63492.54 | I97: 147268.35 | J97: 218270.02 | K97: 446698.13 | L97: 206880.38 | M97: 189389.38 | N97: 379244.75 | O97: 277533.57 | P97: 1053048.1 | Q97: 371083.14 | R97: 209022.73 | S97: 372295 | T97: 172687.99 | U97: 1125088.9 | V97: 225527 | W97: 206144.61 | X97: 185039.98 | Y97: 156129.55 | Z97: 772841.14 | AA97: 105334 | AB97: 44127.75
A98: 1 | C98: 단기차입금의감소 | E98: 49532.2 | G98: 30314 | H98: 54166 | I98: 124625.48 | J98: 162472.68 | K98: 371578.16 | L98: 209043.44 | M98: 185400.94 | N98: 320174.84 | O98: 309306.22 | P98: 1023925.4 | Q98: 356360.71 | R98: 250759.23 | S98: 372610 | T98: 202913.64 | U98: 1182643.6 | V98: 209997 | W98: 220923.51 | X98: 191449.01 | Y98: 160210.3 | Z98: 782579.82 | AA98: 121566.9 | AB98: 57643.01
A99: 1 | C99: 장기차입금의감소 | E99: 0 | L99: 0 | M99: 0 | Q99: 0 | R99: 0 | S99: 0
A100: 1 | C100: 배당금지급 | E100: 0 | I100: 0 | J100: 0 | L100: 0 | M100: 0 | N100: 0 | Q100: 0 | R100: 0 | S100: 0 | X100: 0 | Y100: 0
A101: 1 | C101: 리스부채의상환 | E101: 3628.43 | G101: 3621.15 | H101: 3651.13 | I101: 3648.59 | J101: 3531.61 | K101: 14452.48 | L101: 3368.66 | M101: 3369.8 | N101: 3668.16 | O101: 3433.22 | P101: 13839.84 | Q101: 3387.36 | R101: 3283.11 | S101: 3207.11 | V101: 3390.1 | W101: 3321.23 | X101: 3276.64 | Y101: 3146.66 | Z101: 13134.63 | AA101: 3106.03 | AB101: 3045.63
A102: 1 | C102: 현금및현금성자산의증감 | E102: 3209.43 | G102: -3580.31 | H102: -45.9 | I102: 1892.26 | J102: 2351.3 | K102: 617.35 | L102: 3708.83 | M102: -4291.8 | N102: 1628.91 | O102: 5216.22 | P102: 6262.16 | Q102: -12110.69 | R102: 1858.93 | S102: 47196.83 | T102: -38981.17 | U102: -2036.1 | V102: 896.75 | W102: 12230.97 | X102: -14931.62 | Y102: 990.19 | Z102: -813.71 | AA102: 13889.31 | AB102: 30138.33
A103: 1 | C103: 기말현금및현금성자산 | E103: 3209.44 | G103: 10698.94 | H103: -45.91 | I103: 1892.27 | J103: 2351.3 | K103: 14896.6 | L103: 18605.43 | M103: -4291.81 | N103: 1628.91 | O103: 5216.22 | P103: 21158.75 | Q103: 9048.06 | R103: 1858.94 | S103: 47196.82 | T103: -38981.16 | U103: 19122.66 | V103: 20019.41 | W103: 12230.96 | X103: -14931.61 | Y103: 990.18 | Z103: 18308.94 | AA103: 32198.25 | AB103: 30138.33
A104: 1 | C104: 무형자산의감소 | L104: 0 | M104: 0 | N104: 0 | Q104: 0 | R104: 0 | S104: 0
...

Sheet BS별도
B1: (백만원) | C1: 이름: BS별도H | E1: 4Q21 | F1: 2021 | G1: 1Q22 | H1: 2Q22 | I1: 3Q22 | J1: 4Q22 | K1: 2022 | L1: 1Q23 | M1: 2Q23 | N1: 3Q23 | O1: 4Q23 | P1: 2023 | Q1: 1Q24 | R1: 2Q24 | S1: 3Q24 | T1: 4Q24 | U1: 2024 | V1: 1Q25 | W1: 2Q25 | X1: 3Q25 | Y1: 4Q25 | Z1: 2025 | AA1: 1Q26 | AB1: 2Q26 | AC1: 3Q26 | AD1: 4Q26 | AE1: 2026 | AF1: 1Q27 | AG1: 2Q27 | AH1: 3Q27 | AI1: 4Q27 | AJ1: 2027 | AK1: 1Q28 | AL1: 2Q28 | AM1: 3Q28 | AN1: 4Q28 | AO1: 2028
B2: 별도 | D2: fin json(kship_fin.py)
B3: 현대리바트(별) | C3: UPDATE: 26-10-11 | E3: 1 | F3: 2 | G3: 3 | H3: 4 | I3: 5 | J3: 6 | K3: 7 | L3: 8 | M3: 9 | N3: 10 | O3: 11 | P3: 12 | Q3: 13 | R3: 14 | S3: 15 | T3: 16 | U3: 17 | V3: 18 | W3: 19 | X3: 20 | Y3: 21 | Z3: 22 | AA3: 23 | AB3: 24 | AC3: 25 | AD3: 26 | AE3: 27 | AF3: 28 | AG3: 29 | AH3: 30 | AI3: 31 | AJ3: 32 | AK3: 33 | AL3: 34 | AM3: 35 | AN3: 36 | AO3: 37
B4: Account Code | C4: AccountNAME | E4: 2021.12 | F4: 2021.12A | G4: 2022.03 | H4: 2022.06 | I4: 2022.09 | J4: 2022.12 | K4: 2022.12A | L4: 2023.03 | M4: 2023.06 | N4: 2023.09 | O4: 2023.12 | P4: 2023.12A | Q4: 2024.03 | R4: 2024.06 | S4: 2024.09 | T4: 2024.12 | U4: 2024.12A | V4: 2025.03 | W4: 2025.06 | X4: 2025.09 | Y4: 2025.12 | Z4: 2025.12A | AA4: 2026.03 | AB4: 2026.06 | AC4: 2026.09 | AD4: 2026.12 | AE4: 2026.12A | AF4: 2027.03 | AG4: 2027.06 | AH4: 2027.09 | AI4: 2027.12 | AJ4: 2027.12A | AK4: 2028.03 | AL4: 2028.06 | AM4: 2028.09 | AN4: 2028.12 | AO4: 2028.12A
A5: 1 | C5: 유동자산 | E5: 422929.92 | F5: 422929.92 | G5: 378492.77 | H5: 398793.92 | I5: 432112.23 | J5: 447441.04 | K5: 447441.04 | L5: 429806.46 | M5: 463656.89 | N5: 524621.11 | O5: 503826.87 | P5: 503826.87 | Q5: 554212.11 | R5: 533385.99 | S5: 520419.39 | T5: 469657 | U5: 469657 | V5: 463387.66 | W5: 449884.57 | X5: 403310.62 | Y5: 398061.05 | Z5: 398061.05 | AA5: 444422.27 | AB5: 469415.94
A6: 1 | C6: 현금및현금성자산 | E6: 8495.23 | F6: 8495.23 | G6: 6265.28 | H6: 5593.66 | I6: 7340.08 | J6: 11240.16 | K6: 11240.16 | L6: 15404.67 | M6: 10282.32 | N6: 12635.2 | O6: 18108.25 | P6: 18108.25 | Q6: 5709.74 | R6: 6891.07 | S6: 53508.92 | T6: 13963.04 | U6: 13963.04 | V6: 13764.41 | W6: 24215.67 | X6: 9389.26 | Y6: 12866.58 | Z6: 12866.58 | AA6: 23969.17 | AB6: 55729.05
A7: 1 | C7: 매출채권및기타채권 | E7: 240198.07 | F7: 240198.07 | G7: 213872.22 | H7: 206457.97 | I7: 215921.82 | J7: 251113.39 | K7: 251113.39 | L7: 234194.05 | M7: 248760.92 | N7: 295960.33 | O7: 265226.19 | P7: 265226.19 | Q7: 338580.41 | R7: 322116.44 | S7: 257619.45 | T7: 229730.44 | U7: 229730.44 | V7: 247789.02 | W7: 240997.15 | X7: 217793.85 | Y7: 206230.1 | Z7: 206230.1 | AA7: 226287.46 | AB7: 226498.83
A8: 1 | C8: 단기금융상품 | E8: 8801.38 | F8: 8801.38 | G8: 7880.93 | H8: 7594.57 | I8: 7617.15 | J8: 7664.4 | K8: 7664.4 | L8: 5792.95 | M8: 5450.21 | N8: 5636.41 | O8: 5461.67 | P8: 5461.67 | Q8: 5386.68 | R8: 8855.57 | S8: 9145.65
A9: 1 | C9: 단기금융자산 | E9: 8801.38 | F9: 8801.38 | G9: 7880.93 | H9: 7594.57 | I9: 7617.15 | J9: 7664.4 | K9: 7664.4 | L9: 5792.95 | M9: 5450.21 | N9: 5636.41 | O9: 5461.67 | P9: 5461.67 | Q9: 5386.68 | R9: 8855.57 | S9: 9145.65
A10: 1 | C10: 재고자산 | E10: 138877.55 | F10: 138877.55 | G10: 128542.95 | H10: 150214.53 | I10: 161652.06 | J10: 158197.77 | K10: 158197.77 | L10: 162465.09 | M10: 185658.37 | N10: 199273.29 | O10: 203274.54 | P10: 203274.54 | Q10: 193199.62 | R10: 184105.91 | S10: 192262 | T10: 210718.83 | U10: 210718.83 | V10: 185593.71 | W10: 168687.95 | X10: 161682.84 | Y10: 160221.43 | Z10: 160221.43 | AA10: 149420.19 | AB10: 149990.98
A11: 1 | C11: 당기법인세자산(선급법인세) | E11: 62.9 | F11: 62.9 | G11: 33.31 | I11: 27.11 | J11: 1821.24 | K11: 1821.24 | L11: 1838.78 | M11: 59.83 | N11: 45.22 | O11: 46.59 | P11: 46.59 | Q11: 178.8 | R11: 166.33 | S11: 36.58 | T11: 173.16 | U11: 173.16 | V11: 168.07 | W11: 36.48 | X11: 36.48 | Y11: 197.21 | Z11: 197.21 | AA11: 40.84 | AB11: 40.84
A12: 1 | C12: 계약자산 | E12: 60.09 | F12: 60.09 | G12: 61.37 | H12: 139.5 | I12: 19992.29 | J12: 6794.99 | K12: 6794.99 | L12: 5784.06 | M12: 5839.42 | N12: 6533.31 | O12: 6260.07 | P12: 6260.07 | Q12: 4268.77 | R12: 4369.59 | S12: 2145.51
A13: 1 | C13: 기타유동자산 | E13: 26434.7 | F13: 26434.7 | G13: 21836.71 | H13: 28793.69 | I13: 19561.72 | J13: 10609.1 | K13: 10609.1 | L13: 4326.86 | M13: 7605.81 | N13: 4537.35 | O13: 5449.56 | P13: 5449.56 | Q13: 6888.09 | R13: 6881.07 | S13: 5701.29 | T13: 4897.43 | U13: 4897.43 | V13: 5401.3 | W13: 4136.11 | X13: 3880.8 | Y13: 4146.29 | Z13: 4146.29 | AA13: 8553.34 | AB13: 8722.87
A14: 1 | C14: 비유동자산 | E14: 430902.98 | F14: 430902.98 | G14: 430036.6 | H14: 430768.18 | I14: 425066.13 | J14: 401153.05 | K14: 401153.05 | L14: 400518.99 | M14: 395867.17 | N14: 392099.58 | O14: 387788.51 | P14: 387788.51 | Q14: 375334.32 | R14: 368025.73 | S14: 361181.5 | T14: 379095 | U14: 379095 | V14: 368893.11 | W14: 362860.32 | X14: 361464.16 | Y14: 364951.71 | Z14: 364951.71 | AA14: 340611.06 | AB14: 342773.26
A15: 1 | C15: 장기금융자산 | E15: 34885.4 | F15: 34885.4 | G15: 35118.26 | H15: 35221.23 | I15: 34634.54 | J15: 33676.13 | K15: 33676.13 | L15: 37355.92 | M15: 37673.33 | N15: 36408.7 | O15: 36922.77 | P15: 36922.77 | Q15: 33964.3 | R15: 30170.22 | S15: 29938.84 | T15: 29803.18 | U15: 29803.18 | V15: 29637.43 | W15: 28033.74 | X15: 28488.09 | Y15: 23692.13 | Z15: 23692.13 | AA15: 21744.8 | AB15: 27508.51
A16: 1 | C16: 투자자산 | E16: 37686.26 | F16: 37686.26 | G16: 37919.12 | H16: 38669.34 | I16: 38082.65 | J16: 37124.24 | K16: 37124.24 | L16: 40804.03 | M16: 41121.44 | N16: 39856.81 | O16: 40370.88 | P16: 40370.88 | Q16: 37412.41 | R16: 33618.33 | S16: 33386.95 | T16: 33751.29 | U16: 33751.29 | V16: 33585.54 | W16: 31981.85 | X16: 32436.2 | Y16: 27640.24 | Z16: 27640.24 | AA16: 25692.91 | AB16: 27508.51
A17: 1 | C17: 종속기업및관계기업투자 | E17: 2800.86 | F17: 2800.86 | G17: 2800.86 | H17: 3448.11 | I17: 3448.11 | J17: 3448.11 | K17: 3448.11 | L17: 3448.11 | M17: 3448.11 | N17: 3448.11 | O17: 3448.11 | P17: 3448.11 | Q17: 3448.11 | R17: 3448.11 | S17: 3448.11 | T17: 3948.11 | U17: 3948.11 | V17: 3948.11 | W17: 3948.11 | X17: 3948.11 | Y17: 3948.11 | Z17: 3948.11 | AA17: 3948.11
A18: 1 | C18: 유형자산 | E18: 360983.13 | F18: 360983.13 | G18: 362000.39 | H18: 362108.14 | I18: 357259.01 | J18: 318632.28 | K18: 318632.28 | L18: 316355.39 | M18: 311983.37 | N18: 310615.92 | O18: 299438.69 | P18: 299438.69 | Q18: 294581.03 | R18: 294051.19 | S18: 289947.7 | T18: 285837.08 | U18: 285837.08 | V18: 282581.27 | W18: 279897.2 | X18: 280538.79 | Y18: 275525.93 | Z18: 275525.93 | AA18: 272163.14 | AB18: 270364.63
A19: 1 | C19: 투자부동산 | E19: 1301.84 | F19: 1301.84 | G19: 1293.31 | H19: 910.47 | I19: 904.72 | J19: 898.97 | K19: 898.97 | L19: 893.21 | M19: 2008.17 | N19: 1994.65 | O19: 1981.13 | P19: 1981.13 | Q19: 1967.62 | R19: 1954.1 | S19: 1940.58 | T19: 1927.06 | U19: 1927.06 | V19: 1913.55 | W19: 1900.03 | X19: 1886.51 | Y19: 1873 | Z19: 1873 | AA19: 1859.48 | AB19: 1845.96
A20: 1 | C20: 무형자산 | E20: 27998.83 | F20: 27998.83 | G20: 27756.45 | H20: 27514.06 | I20: 27271.68 | J20: 27029.29 | K20: 27029.29 | L20: 26786.91 | M20: 26544.53 | N20: 26302.14 | O20: 27081.76 | P20: 27081.76 | Q20: 26839.38 | R20: 26596.99 | S20: 26354.61
A21: 1 | C21: 기타비유동자산 | E21: 1891.75 | F21: 1891.75 | G21: 18.86 | H21: 18.1 | I21: 18.56 | J21: 9169.31 | K21: 9169.31 | L21: 7293.08 | M21: 6385.55 | N21: 5673.89 | O21: 5160.72 | P21: 5160.72 | Q21: 2020.29 | R21: 1022.32 | S21: 257.46 | T21: 2.09 | U21: 2.09
A22: 1 | C22: 자산총계 | E22: 853832.89 | F22: 853832.89 | G22: 808529.37 | H22: 829562.1 | I22: 857178.35 | J22: 848594.09 | K22: 848594.09 | L22: 830325.45 | M22: 859524.06 | N22: 916720.69 | O22: 891615.38 | P22: 891615.38 | Q22: 929546.43 | R22: 901411.72 | S22: 881600.89
A23: 1 | C23: 유동부채 | E23: 315248.63 | F23: 315248.63 | G23: 268209.52 | H23: 288971.68 | I23: 317200.39 | J23: 372180.01 | K23: 372180.01 | L23: 362201.15 | M23: 391665.83 | N23: 448200.86 | O23: 448544.76 | P23: 448544.76 | Q23: 491706.64 | R23: 438934.9 | S23: 412570.14 | T23: 381760.23 | U23: 381760.23 | V23: 363727.15 | W23: 364840.43 | X23: 322941.25 | Y23: 324690.44 | Z23: 324690.44 | AA23: 309340.79 | AB23: 314008.2
A24: 1 | C24: 매입채무및기타채무 | E24: 209858.21 | F24: 209858.21 | G24: 190842.08 | H24: 203165.26 | I24: 186523.1 | J24: 200149.63 | K24: 200149.63 | L24: 207551.01 | M24: 233164.81 | N24: 234580.31 | O24: 267920.97 | P24: 267920.97 | Q24: 273547.7 | R24: 261871.23 | S24: 254684.09 | T24: 241952.33 | U24: 241952.33 | V24: 216273.56 | W24: 224132.84 | X24: 181371.84 | Y24: 186857.19 | Z24: 186857.19 | AA24: 173358.49 | AB24: 202796.01
A25: 1 | C25: 단기차입금 | E25: 34191.16 | F25: 34191.16 | G25: 23419.58 | H25: 30916.47 | I25: 53610.96 | J25: 109452.45 | K25: 109452.45 | L25: 107081.85 | M25: 110805.05 | N25: 170308.05 | O25: 137722.8 | P25: 137722.8 | Q25: 153081.87 | R25: 111741.04 | S25: 111469.8
A26: 1 | C26: 단기금융부채(face) | E26: 34191.16 | F26: 34191.16 | G26: 23419.58 | H26: 30916.47 | I26: 53610.96 | J26: 109452.45 | K26: 109452.45 | L26: 107081.85 | M26: 110805.05 | N26: 170308.05 | O26: 137722.8 | P26: 137722.8 | Q26: 153081.87 | R26: 111741.04 | S26: 111469.8
A27: 1 | C27: 계약부채 | E27: 52427.35 | F27: 52427.35 | G27: 34340.17 | H27: 35974.35 | I27: 59315.2 | J27: 39199.05 | K27: 39199.05 | L27: 28169.83 | M27: 29704.59 | N27: 25726.51 | O27: 24530.36 | P27: 24530.36 | Q27: 39538.11 | R27: 40573.07 | S27: 27547.03 | T27: 35183.22 | U27: 35183.22 | V27: 24171.53 | W27: 19217.34 | X27: 17716.47 | Y27: 20488.6 | Z27: 20488.6 | AA27: 25906.56 | AB27: 37955.69
A28: 1 | C28: 기타유동부채 | E28: 2414.57 | F28: 2414.57 | G28: 1683.77 | H28: 750.64 | I28: 782.14 | J28: 1664.66 | K28: 1664.66 | L28: 741.51 | M28: 756.68 | N28: 874.76 | O28: 1894.85 | P28: 1894.85 | Q28: 1712.07 | R28: 3717.82 | S28: 1189.44 | T28: 1703.35 | U28: 1703.35 | V28: 3788.95 | W28: 2873.39 | X28: 2460.58 | Y28: 2833.11 | Z28: 2833.11 | AA28: 2529.18 | AB28: 1233.11
A29: 1 | C29: 당기법인세부채(미지급법인세) | E29: 667.32 | F29: 667.32 | G29: 1380.95 | H29: 1300.68 | I29: 98.82 | J29: 0 | K29: 0 | L29: 0 | M29: 0 | N29: 0 | O29: 0 | P29: 0 | Q29: 265.01 | R29: 322.15 | S29: 244.21 | V29: 267.85 | W29: 345.49 | X29: 199.94 | AA29: 11.02 | AB29: 181.93
A30: 1 | C30: 단기충당부채 | E30: 2740.18 | F30: 2740.18 | G30: 3172.77 | H30: 3192.44 | I30: 3558.4 | J30: 9051.05 | K30: 9051.05 | L30: 6452.14 | M30: 5059.29 | N30: 4560.31 | O30: 4823.74 | P30: 4823.74 | Q30: 12132.79 | R30: 8355.23 | S30: 5157.5 | T30: 5921.23 | U30: 5921.23 | V30: 4937.72 | W30: 4856.03 | X30: 4679.6 | Y30: 3733.71 | Z30: 3733.71 | AA30: 3279.59 | AB30: 3127.38
A31: 1 | C31: 비유동부채 | E31: 52814.92 | F31: 52814.92 | G31: 54351.65 | H31: 55341.61 | I31: 53744.42 | J31: 40173.51 | K31: 40173.51 | L31: 38103.19 | M31: 36045.97 | N31: 36287.24 | O31: 43053.05 | P31: 43053.05 | Q31: 32948.53 | R31: 52810.77 | S31: 55285.14 | T31: 59445.91 | U31: 59445.91 | V31: 57525.49 | W31: 36488.42 | X31: 27504.64 | Y31: 24887.3 | Z31: 24887.3 | AA31: 63748.47 | AB31: 82760.93
A32: 1 | C32: 장기차입금 | E32: 590.79 | F32: 590.79 | G32: 237.38 | H32: 337.65 | I32: 281.28 | J32: 192.27 | K32: 192.27 | L32: 507.63 | M32: 528.01 | N32: 583.71 | O32: 591.98 | P32: 591.98 | Q32: 177.04 | R32: 20272.17 | S32: 24227.3
A33: 1 | C33: 장기금융부채(face) | E33: 590.79 | F33: 590.79 | G33: 237.38 | H33: 337.65 | I33: 281.28 | J33: 192.27 | K33: 192.27 | L33: 507.63 | M33: 528.01 | N33: 583.71 | O33: 591.98 | P33: 591.98 | Q33: 177.04 | R33: 20272.17 | S33: 24227.3
A34: 1 | C34: 장기충당부채 | E34: 2782.97 | F34: 2782.97 | G34: 2687.59 | H34: 2938.46 | I34: 2917.45 | J34: 2853.05 | K34: 2853.05 | L34: 2767.81 | M34: 2855.78 | N34: 2750.14 | O34: 10851.49 | P34: 10851.49 | Q34: 3014.42 | R34: 3074.15 | S34: 3071.4 | T34: 3155.88 | U34: 3155.88 | V34: 3109.87 | W34: 3321.85 | X34: 3396.67 | Y34: 3013.64 | Z34: 3013.64 | AA34: 2950.24 | AB34: 2735.44
A35: 1 | C35: 확정급여부채 | E35: 0 | F35: 0 | G35: 1940.64 | H35: 3140.53 | I35: 4231.98 | J35: 0 | K35: 0 | L35: 0 | M35: 0 | N35: 0 | X35: 625.2
A36: 1 | C36: 이연법인세부채 | E36: 7795.07 | F36: 7795.07 | G36: 7408.92 | H36: 6914.44 | I36: 6562.99 | J36: 0 | K36: 0 | L36: 0 | M36: 0 | N36: 0 | O36: 0 | P36: 0 | Q36: 0 | R36: 0 | S36: 0
A37: 1 | C37: 기타비유동부채 | E37: 1107.41 | F37: 1107.41 | G37: 1081.45 | H37: 1037.66 | I37: 1110.65 | J37: 1175.81 | K37: 1175.81 | L37: 1249.6 | M37: 1260.48 | N37: 1279.18 | O37: 1410.78 | P37: 1410.78 | Q37: 1413.37 | R37: 1423.17 | S37: 1432.7 | T37: 1750.34 | U37: 1750.34 | V37: 1771.39 | W37: 1666.08 | X37: 1678.82 | Y37: 2068.32 | Z37: 2068.32 | AA37: 2109.19 | AB37: 2132.03
A38: 1 | C38: 부채총계 | E38: 368063.55 | F38: 368063.55 | G38: 322561.17 | H38: 344313.28 | I38: 370944.81 | J38: 412353.52 | K38: 412353.52 | L38: 400304.34 | M38: 427711.8 | N38: 484488.1 | O38: 491597.8 | P38: 491597.8 | Q38: 524655.17 | R38: 491745.67 | S38: 467855.27
A39: 1 | C39: 자본금 | E39: 20535.28 | F39: 20535.28 | G39: 20535.28 | H39: 20535.28 | I39: 20535.28 | J39: 20535.28 | K39: 20535.28 | L39: 20535.28 | M39: 20535.28 | N39: 20535.28 | O39: 20535.28 | P39: 20535.28 | Q39: 20535.28 | R39: 20535.28 | S39: 20535.28 | T39: 20535.28 | U39: 20535.28 | V39: 20535.28 | W39: 20535.28 | X39: 20535.28 | Y39: 20535.28 | Z39: 20535.28 | AA39: 20535.28 | AB39: 20535.28
A40: 1 | C40: 자본잉여금 | E40: 102586.87 | F40: 102586.87 | G40: 102586.87 | H40: 102586.87 | I40: 102586.87 | J40: 102586.87 | K40: 102586.87 | L40: 102586.87 | M40: 102586.87 | N40: 102586.87 | O40: 102586.87 | P40: 102586.87 | Q40: 102586.87 | R40: 102586.87 | S40: 102586.87 | T40: 102586.87 | U40: 102586.87 | V40: 102586.87 | W40: 102586.87 | X40: 102586.87 | Y40: 102586.87 | Z40: 102586.87 | AA40: 102586.87 | AB40: 102586.87
A41: 1 | C41: 기타자본 | E41: -3428.12 | F41: -3428.12 | G41: -3428.12 | H41: -3428.12 | I41: -3428.12 | J41: -3428.12 | K41: -3428.12 | L41: -3428.12 | M41: -3428.12 | N41: -3428.12 | O41: -3428.12 | P41: -3428.12 | Q41: -3428.12 | R41: -3428.12 | S41: -3428.12 | T41: -3428.12 | U41: -3428.12 | V41: -3428.12 | W41: -3428.12 | X41: -3428.12 | Y41: -3428.12 | Z41: -3428.12 | AA41: -3428.12 | AB41: 0
A42: 1 | C42: 기타포괄이익누계액 | E42: 98.05 | F42: 98.05 | G42: 103.6 | H42: 65.08 | I42: 51.01 | J42: 59.32 | K42: 59.32 | L42: 61.51 | M42: 74.95 | N42: 107.88 | O42: 120.01 | P42: 120.01 | Q42: 81.83 | R42: 95.35 | S42: 96.87 | T42: 97.99 | U42: 97.99 | V42: 90.35 | W42: 80.87 | X42: 81.11 | Y42: 76.62 | Z42: 76.62 | AA42: 64.13 | AB42: 59.87
A43: 1 | C43: 이익잉여금 | E43: 365977.26 | F43: 365977.26 | G43: 366170.57 | H43: 365489.71 | I43: 366488.5 | J43: 316487.22 | K43: 316487.22 | L43: 310265.57 | M43: 312043.28 | N43: 312430.68 | O43: 280203.53 | P43: 280203.53 | Q43: 285115.4 | R43: 289876.67 | S43: 293954.72 | T43: 287753.85 | U43: 287753.85 | V43: 291243.76 | W43: 291641.14 | X43: 294553.76 | Y43: 293664.38 | Z43: 293664.38 | AA43: 292185.91 | AB43: 292238.04
A44: 1 | C44: 자본총계 | E44: 485769.35 | F44: 485769.35 | G44: 485968.2 | H44: 485248.82 | I44: 486233.55 | J44: 436240.57 | K44: 436240.57 | L44: 430021.11 | M44: 431812.26 | N44: 432232.59 | O44: 400017.58 | P44: 400017.58 | Q44: 404891.26 | R44: 409666.05 | S44: 413745.62 | T44: 407545.86 | U44: 407545.86 | V44: 411028.14 | W44: 411416.04 | X44: 414328.9 | Y44: 413435.03 | Z44: 413435.03 | AA44: 411944.08 | AB44: 415420.06
A45: 1 | C45: 부채와자본총계 | E45: 853832.89 | F45: 853832.89 | G45: 808529.37 | H45: 829562.1 | I45: 857178.35 | J45: 848594.09 | K45: 848594.09 | L45: 830325.45 | M45: 859524.06 | N45: 916720.69 | O45: 891615.38 | P45: 891615.38 | Q45: 929546.43 | R45: 901411.72 | S45: 881600.89
A46: 1 | C46: 지배주주지분 | E46: 485769.35 | F46: 485769.35 | G46: 485968.2 | H46: 485248.82 | I46: 486233.55 | J46: 436240.57 | K46: 436240.57 | L46: 430021.11 | M46: 431812.26 | N46: 432232.59 | O46: 400017.58 | P46: 400017.58 | Q46: 404891.26 | R46: 409666.05 | S46: 413745.62 | T46: 407545.86 | U46: 407545.86 | V46: 411028.14 | W46: 411416.04 | X46: 414328.9 | Y46: 413435.03 | Z46: 413435.03 | AA46: 411944.08 | AB46: 415420.06
A47: 1 | C47: 총차입금 | E47: 34781.95 | F47: 34781.95 | G47: 23656.96 | H47: 31254.12 | I47: 53892.24 | J47: 109644.72 | K47: 109644.72 | L47: 107589.48 | M47: 111333.06 | N47: 170891.76 | O47: 138314.78 | P47: 138314.78 | Q47: 153258.91 | R47: 132013.21 | S47: 135697.1
A48: 1 | C48: 순차입금 | E48: 17485.34 | F48: 17485.34 | G48: 9510.75 | H48: 18065.89 | I48: 38935.01 | J48: 90740.16 | K48: 90740.16 | L48: 86391.86 | M48: 95600.53 | N48: 152620.15 | O48: 114744.86 | P48: 114744.86 | Q48: 142162.49 | R48: 116266.57 | S48: 73042.53
A49: 1 | C49: 이자발생자산 | E49: 52182.01 | F49: 52182.01 | G49: 49264.47 | H49: 48409.46 | I49: 49591.77 | J49: 52580.69 | K49: 52580.69 | L49: 58553.54 | M49: 53405.86 | N49: 54680.31 | O49: 60492.69 | P49: 60492.69 | Q49: 45060.72 | R49: 45916.86 | S49: 92593.41 | T49: 43766.22 | U49: 43766.22 | V49: 43401.84 | W49: 52249.41 | X49: 37877.35 | Y49: 36558.71 | Z49: 36558.71 | AA49: 45713.97 | AB49: 83237.56
A50: 1 | C50: 이연법인세자산 | J50: 6811.47 | K50: 6811.47 | L50: 8386.36 | M50: 7824.1 | N50: 7656.16 | O50: 13755.32 | P50: 13755.32 | Q50: 12513.58 | R50: 10782.8 | S50: 9294.19 | T50: 10200.37 | U50: 10200.37 | V50: 9035.47 | W50: 8932.12 | X50: 8208.34 | Y50: 8424.83 | Z50: 8424.83 | AA50: 8209.71 | AB50: 7570.66
A51: 1 | C51: 유동리스부채 | O51: 11652.03 | P51: 11652.03 | Q51: 11429.08 | R51: 12354.36 | S51: 12278.07 | T51: 12083.63 | U51: 12083.63 | V51: 11602.4 | W51: 10897.74 | X51: 10970.33 | Y51: 9974.73 | Z51: 9974.73 | AA51: 10170.02 | AB51: 10777.54
A52: 1 | C52: 리스부채 | O52: 40726.67 | P52: 40726.67 | Q52: 38492.19 | R52: 39281.29 | S52: 37801.61 | T52: 35511.66 | U52: 35511.66 | V52: 33227.57 | W52: 31422.72 | X52: 31854.46 | Y52: 28833.04 | Z52: 28833.04 | AA52: 28025.38 | AB52: 27746.94
A53: 1 | C53: 단기금융부채 | O53: 11652.03 | P53: 11652.03 | Q53: 11429.08 | R53: 12354.36 | S53: 12278.07 | T53: 93656.19 | U53: 93656.19 | V53: 111348.77 | W53: 112151.62 | X53: 115827.01 | Y53: 110777.82 | Z53: 110777.82 | AA53: 97390.78 | AB53: 61850.37
A54: 1 | C54: 비유동리스부채 | O54: 29074.64 | P54: 29074.64 | Q54: 27063.11 | R54: 26926.93 | S54: 25523.54 | T54: 23428.03 | U54: 23428.03 | V54: 21625.17 | W54: 20524.98 | X54: 20884.13 | Y54: 18858.31 | Z54: 18858.31 | AA54: 17855.36 | AB54: 16969.4
A55: 1 | C55: 장기금융부채 | O55: 29074.64 | P55: 29074.64 | Q55: 27063.11 | R55: 26926.93 | S55: 25523.54 | T55: 53548.28 | U55: 53548.28 | V55: 51723.59 | W55: 30677.08 | X55: 21067.6 | Y55: 19101.19 | Z55: 19101.19 | AA55: 57974.43 | AB55: 77187.16
A56: 1 | C56: 기타유동금융자산 | T56: 10174.1 | U56: 10174.1 | V56: 10364.81 | W56: 11811.21 | X56: 10527.39 | Y56: 14399.44 | Z56: 14399.44 | AA56: 36151.28 | AB56: 28433.37
A57: 1 | C57: 장기매출채권및기타채권 | T57: 16145.62 | U57: 16145.62 | V57: 13951.11 | W57: 12584.33 | X57: 13009.25 | Y57: 13312.63 | Z57: 13312.63 | AA57: 1884.18 | AB57: 2414.84
A58: 1 | C58: 기타유동금융부채 | T58: 81572.56 | U58: 81572.56 | V58: 99746.37 | W58: 101253.88 | X58: 104856.68 | Y58: 100803.09 | Z58: 100803.09 | AA58: 87220.76 | AB58: 51072.83
A59: 1 | C59: 기타비유동금융부채 | T59: 30120.25 | U59: 30120.25 | V59: 30098.42 | W59: 10152.1 | X59: 183.47 | Y59: 242.88 | Z59: 242.88 | AA59: 40119.07 | AB59: 60217.76
A60: 1 | C60: 매출액(수익) | E60: 366092.92 | G60: 361297.53 | H60: 353179.53 | I60: 355688.1 | J60: 393068.09 | K60: 1463233.2 | L60: 364246.58 | M60: 385867.52 | N60: 386560.17 | O60: 415453.94 | P60: 1552128.2 | Q60: 494993.7 | R60: 483945.38 | S60: 440922.19 | T60: 401597.66 | U60: 1821458.9 | V60: 424011.52 | W60: 390622.11 | X60: 322500.91 | Y60: 340157.67 | Z60: 1477292.2 | AA60: 340409.22 | AB60: 357173.07
A61: 1 | C61: 매출원가 | E61: 304141.47 | G61: 299900.01 | H61: 296026.27 | I61: 297170.1 | J61: 365011.95 | K61: 1258108.3 | L61: 315657.61 | M61: 327383.06 | N61: 324582.89 | O61: 371788.4 | P61: 1339412 | Q61: 426109.17 | R61: 417240.89 | S61: 372360.58 | T61: 336642.68 | U61: 1552353.3 | V61: 351717.87 | W61: 323551.26 | X61: 259834.94 | Y61: 283846.74 | Z61: 1218950.8 | AA61: 281530.19 | AB61: 295844.21
A62: 1 | C62: 매출총이익 | E62: 61951.45 | G62: 61397.53 | H62: 57153.25 | I62: 58518 | J62: 28056.13 | K62: 205124.91 | L62: 48588.97 | M62: 58484.46 | N62: 61977.28 | O62: 43665.54 | P62: 212716.25 | Q62: 68884.52 | R62: 66704.49 | S62: 68561.61 | T62: 64954.98 | U62: 269105.6 | V62: 72293.65 | W62: 67070.84 | X62: 62665.97 | Y62: 56310.94 | Z62: 258341.4 | AA62: 58879.03 | AB62: 61328.86
A63: 1 | C63: 판관비 | E63: 60361.4 | G63: 58323.41 | H63: 57453.35 | I63: 58138.69 | J63: 58516.6 | K63: 232432.05 | L63: 55533.8 | M63: 55167.76 | N63: 60158.76 | O63: 62467.14 | P63: 233327.46 | Q63: 61963.54 | R63: 59393.68 | S63: 58989.39 | T63: 65880.78 | U63: 246227.39 | V63: 63266.78 | W63: 62226.27 | X63: 59234.58 | Y63: 59046.8 | Z63: 243774.43 | AA63: 58175.62 | AB63: 55919.64
A64: 1 | C64: 영업이익 | E64: 1590.06 | G64: 3074.11 | H64: -300.1 | I64: 379.31 | J64: -30460.45 | K64: -27307.13 | L64: -6944.82 | M64: 3316.7 | N64: 1818.52 | O64: -18801.59 | P64: -20611.19 | Q64: 6920.98 | R64: 7310.81 | S64: 9572.22 | T64: -925.8 | U64: 22878.21 | V64: 9026.87 | W64: 4844.57 | X64: 3431.39 | Y64: -2735.86 | Z64: 14566.97 | AA64: 703.41 | AB64: 5409.22
A65: 1 | C65: 기타영업외수익 | E65: 163.76 | G65: 190.96 | H65: 142.31 | I65: 125.85 | J65: 40.66 | K65: 499.78 | L65: 144.09 | M65: 132.57 | N65: 198.91 | O65: 348.71 | P65: 824.28 | Q65: 234.05 | R65: 307.49 | S65: 148.11 | T65: 218.72 | U65: 908.37 | V65: 169.75 | W65: 357.8 | X65: 146.57 | Y65: 301.33 | Z65: 975.45 | AA65: 407.95 | AB65: 430.74
A66: 1 | C66: 기타영업외비용 | E66: 1006.78 | G66: 427.88 | H66: 169.41 | I66: 131.81 | J66: 30963.2 | K66: 31692.3 | L66: 495.51 | M66: 82.68 | N66: -10.19 | O66: 14644.83 | P66: 15212.83 | Q66: 65.35 | R66: 38.52 | S66: 70.34 | T66: 185.95 | U66: 360.16 | V66: 36.02 | W66: 461.49 | X66: 56.82 | Y66: 1511.4 | Z66: 2065.73 | AA66: 65.14 | AB66: 842.15
A67: 1 | C67: 금융수익 | E67: 372.94 | G67: 1417.74 | H67: 2586.78 | I67: 5985.09 | J67: -1606.13 | K67: 8383.48 | L67: 2028.79 | M67: 1748.54 | N67: 1507.7 | O67: -715.46 | P67: 4569.57 | Q67: 2334.76 | R67: 2026.5 | S67: -1452.22 | T67: 4082.62 | U67: 6991.66 | V67: 811.51 | W67: 1068.07 | X67: 515.34 | Y67: 1485.08 | Z67: 3880 | AA67: 2554.74 | AB67: 1961.07
A68: 1 | C68: 금융비용 | E68: 673.95 | G68: 1320.74 | H68: 2958.15 | I68: 5014.13 | J68: 5346.75 | K68: 14639.77 | L68: 2341.2 | M68: 2827.72 | N68: 2895.33 | O68: 2812.48 | P68: 10876.73 | Q68: 2929.42 | R68: 3001.86 | S68: 2486.87 | T68: 2999.97 | U68: 11418.12 | V68: 2376.14 | W68: 5198.4 | X68: 352.36 | Y68: 1411.49 | Z68: 9338.39 | AA68: 1692.75 | AB68: 2283.44
A69: 1 | C69: 법인세비용차감전계속사업이익 | E69: 446.03 | G69: 2934.19 | H69: -698.58 | I69: 1344.31 | J69: -68335.89 | K69: -64755.97 | L69: -7608.65 | M69: 2287.4 | N69: 640 | O69: -36625.66 | P69: -41306.91 | Q69: 6495.02 | R69: 6604.43 | S69: 5710.9 | T69: 189.63 | U69: 18999.98 | V69: 7595.97 | W69: 610.55 | X69: 3684.11 | Y69: -3872.34 | Z69: 8018.29 | AA69: 1908.22 | AB69: 4675.44
A70: 1 | C70: 법인세비용 | E70: -674.36 | G70: 623.15 | H70: -121.84 | I70: 263.66 | J70: -15984.39 | K70: -15219.42 | L70: -1492.67 | M70: 417.72 | N70: 192.12 | O70: -5709.11 | P70: -6591.94 | Q70: 1635.95 | R70: 1708.78 | S70: 1619.15 | T70: 503.35 | U70: 5467.23 | V70: 1456.61 | W70: 196.47 | X70: 755.37 | Y70: -1153.48 | Z70: 1254.97 | AA70: 359.01 | AB70: 946.63
A71: 1 | C71: 당기순이익 | E71: 1120.38 | G71: 2311.04 | H71: -576.74 | I71: 1080.65 | J71: -52351.5 | K71: -49536.55 | L71: -6115.98 | M71: 1869.68 | N71: 447.88 | O71: -30916.53 | P71: -34714.95 | Q71: 4859.07 | R71: 4895.64 | S71: 4091.75 | T71: -313.72 | U71: 13532.74 | V71: 6139.36 | W71: 414.08 | X71: 2928.75 | Y71: -2718.86 | Z71: 6763.33 | AA71: 1549.2 | AB71: 3728.81
... A77: 1 | C77: 영업활동으로인한현금흐름 | E77: -3372.65 | G77: 18843.9 | H77: 1301.7 | I77: -15033.63 | J77: -45702.08 | K77: -40590.11 | L77: 14156.51 | M77: -3602.16 | N77: -51872.59 | O77: 44337.91 | P77: 3019.67 | Q77: -26680.23 | R77: 27088.84 | S77: 46973.31 | T77: -10056.78 | U77: 37325.14 | V77: -9748.32 | W77: 35293.64 | X77: -2328.87 | Y77: 12472.11 | Z77: 35688.56 | AA77: 11648.79 | AB77: 49428.74
A78: 1 | C78: 이자수취(CF) | E78: 29.01 | G78: 30.51 | H78: 55.88 | I78: 23.72 | J78: 48.39 | K78: 158.5 | L78: 28.3 | M78: 71.37 | N78: 26.32 | O78: 30.74 | P78: 156.73 | Q78: 51.3 | R78: 140.86 | S78: 59.81 | V78: 66.65 | W78: 149.79 | X78: 65.7 | Y78: 57.4 | Z78: 339.54 | AA78: 86.22 | AB78: 356.62
A79: 1 | C79: 이자지급(CF) | E79: -352.76 | G79: -456.95 | H79: -523.91 | I79: -578.76 | J79: -998.48 | K79: -2558.1 | L79: -1394.13 | M79: -1575.43
A80: 1 | C80: 법인세납부(CF) | E80: -1.35 | G80: -233.91 | H80: -374.06 | I80: -1813.45 | J80: -1.32 | K80: -2422.74 | L80: -68.5 | M80: 1946.9 | N80: -1.29 | O80: -1.38 | P80: 1875.73 | Q80: -136.41 | R80: -5.32 | S80: -75.5 | V80: -6.08 | W80: 123.97 | X80: -172.37 | Y80: -4.73 | Z80: -59.21 | AA80: 159.29 | AB80: -55.95
A81: 1 | C81: 투자활동으로인한현금흐름 | E81: -4191.29 | G81: -4559.24 | H81: -5892.2 | I81: -2641.5 | J81: -2795.74 | K81: -15888.68 | L81: -4838.45 | M81: -2093.55 | N81: -1889.31 | O81: -3094.89 | P81: -11916.2 | Q81: 2533.14 | R81: -1550.43 | S81: -973.82 | T81: -2393.78 | U81: -2384.89 | V81: -2810.39 | W81: -3262.96 | X81: -3245.35 | Y81: -1999.78 | Z81: -11318.48 | AA81: -21660.54 | AB81: 163.26
A82: 1 | C82: 유형자산의감소 | E82: 39.71 | G82: 27.51 | H82: 22.7 | I82: 6.18 | J82: 58.1 | K82: 114.49 | L82: 35.85 | M82: 11.21 | N82: 2.36 | O82: 38.13 | P82: 87.55 | S82: 54.18 | V82: 15.29 | W82: 585.7 | X82: 12.38 | Y82: 43.31 | Z82: 656.68 | AA82: 1.27 | AB82: 1.64
A83: 1 | C83: 유형자산의증가 | E83: 5473.63 | G83: 5364.32 | H83: 5374.86 | I83: 3284.53 | J83: 3976.98 | K83: 18000.69 | L83: 4705.3 | M83: 1720.04 | N83: 3188.85 | O83: 1771.62 | P83: 11385.81 | Q83: 563.91 | R83: 1290.12 | S83: 1072.57 | V83: 2857.41 | W83: 4078.13 | X83: 4203.55 | Y83: 3144.04 | Z83: 14283.13 | AA83: 1755.02 | AB83: 1353.42
A84: 1 | C84: CAPEX | E84: 5473.63 | G84: 5364.32 | H84: 5374.86 | I84: 3284.53 | J84: 3976.98 | K84: 18000.69 | L84: 4705.3 | M84: 1720.04 | N84: 3188.85 | O84: 2793.62 | P84: 12407.81 | Q84: 563.91 | R84: 1290.12 | S84: 1072.57 | V84: 2857.41 | W84: 4078.13 | X84: 4203.55 | Y84: 3144.04 | Z84: 14283.13 | AA84: 1755.02 | AB84: 1353.42
A85: 1 | C85: 재무활동으로인한현금흐름 | E85: 9898.73 | G85: -16513.2 | H85: 3866.85 | I85: 19460.89 | J85: 52431.3 | K85: 59245.84 | L85: -5156.86 | M85: 574.76 | N85: 56111.73 | O85: -35758.91 | P85: 15770.72 | Q85: 11743.05 | R85: -24356.12 | S85: 625.73 | T85: -27107.27 | U85: -39094.61 | V85: 12340.34 | W85: -21440.39 | X85: -9366.84 | Y85: -6943.26 | Z85: -25410.15 | AA85: 21015.24 | AB85: -18766.42
A86: 1 | C86: 단기차입금의증가 | E86: 62851 | G86: 17211 | H86: 63436 | I86: 147520.48 | J86: 218252.68 | K86: 446420.16 | L86: 206880.38 | M86: 189247 | N86: 379387.13 | O86: 277533.57 | P86: 1053048.1 | Q86: 371083.14 | R86: 207925.72 | S86: 372295 | T86: 172592 | U86: 1123895.9 | V86: 225527 | W86: 205294 | X86: 185041 | Y86: 156128 | Z86: 771990 | AA86: 105334 | AB86: 43402
A87: 1 | C87: 단기차입금의감소 | E87: 49532.2 | G87: 30314 | H87: 54166 | I87: 124625.48 | J87: 162472.68 | K87: 371578.16 | L87: 208935.38 | M87: 185509 | N87: 319835.13 | O87: 310082.57 | P87: 1024362.1 | Q87: 356160.14 | R87: 249164.72 | S87: 372610 | T87: 202592 | U87: 1180526.9 | V87: 209997 | W87: 220824 | X87: 191361 | Y87: 160208 | Z87: 782390 | AA87: 121466 | AB87: 56870
A88: 1 | C88: 배당금지급 | E88: 0 | I88: 0 | J88: 0 | L88: 0 | M88: 0 | N88: 0 | X88: 0 | Y88: 0
A89: 1 | C89: 리스부채의상환 | E89: 3420.07 | G89: 3410.2 | H89: 3427.73 | I89: 3413.11 | J89: 3298.7 | K89: 13549.74 | L89: 3158.26 | M89: 3153.24 | N89: 3440.27 | O89: 3210.15 | P89: 12961.92 | Q89: 3159.95 | R89: 3087.12 | S89: 3044.27 | V89: 3202.66 | W89: 2965.09 | X89: 3003.79 | Y89: 2863.27 | Z89: 12034.81 | AA89: 2782.6 | AB89: 2713.84
A90: 1 | C90: 현금및현금성자산의증감 | E90: 2316.36 | G90: -2229.94 | H90: -671.62 | I90: 1746.41 | J90: 3900.09 | K90: 2744.94 | L90: 4164.5 | M90: -5122.34 | N90: 2352.88 | O90: 5473.05 | P90: 6868.09 | Q90: -12398.51 | R90: 1181.33 | S90: 46617.85 | T90: -39545.88 | U90: -4145.21 | V90: -198.63 | W90: 10451.26 | X90: -14826.41 | Y90: 3477.32 | Z90: -1096.46 | AA90: 11102.59 | AB90: 31759.88
A91: 1 | C91: 기말현금및현금성자산 | E91: 2316.36 | G91: 6265.28 | H91: -671.62 | I91: 1746.42 | J91: 3900.08 | K91: 11240.16 | L91: 15404.67 | M91: -5122.35 | N91: 2352.88 | O91: 5473.05 | P91: 18108.25 | Q91: 5709.74 | R91: 1181.33 | S91: 46617.85 | T91: -39545.88 | U91: 13963.04 | V91: 13764.41 | W91: 10451.26 | X91: -14826.41 | Y91: 3477.32 | Z91: 12866.58 | AA91: 23969.17 | AB91: 31759.88
A92: 1 | C92: 무형자산의감소 | G92: 0 | L92: 0 | M92: 0 | N92: 0 | Q92: 0 | R92: 0 | S92: 0
A93: 1 | C93: 배당금수취(CF) | O93: 0 | Q93: 0 | R93: 21.51 | S93: 0 | X93: 0 | Y93: 0 | AA93: 3.82 | AB93: 49.42
A94: 1 | C94: 장기차입금의증가 | S94: 4000 | T94: 6000 | AA94: 40000 | AB94: 0

Sheet subQ
A1: YQ | C1: subQ 분기 서브모델(억원, U=100) | E1: 4Q21 | F1: 2021 | G1: 1Q22 | H1: 2Q22 | I1: 3Q22 | J1: 4Q22 | K1: 2022 | L1: 1Q23 | M1: 2Q23 | N1: 3Q23 | O1: 4Q23 | P1: 2023 | Q1: 1Q24 | R1: 2Q24 | S1: 3Q24 | T1: 4Q24 | U1: 2024 | V1: 1Q25 | W1: 2Q25 | X1: 3Q25 | Y1: 4Q25 | Z1: 2025 | AA1: 1Q26 | AB1: 2Q26 | AC1: 3Q26 | AD1: 4Q26 | AE1: 2026 | AF1: 1Q27 | AG1: 2Q27 | AH1: 3Q27 | AI1: 4Q27 | AJ1: 2027 | AK1: 1Q28 | AL1: 2Q28 | AM1: 3Q28 | AN1: 4Q28 | AO1: 2028
A2: A=이름(key) B=그룹 C=단위 D=FnGuide 계정명(VLOOKUP 키). 확정=VLOOKUP(BS), 추정=변수 가정 참조
E3: 1 | F3: 2 | G3: 3 | H3: 4 | I3: 5 | J3: 6 | K3: 7 | L3: 8 | M3: 9 | N3: 10 | O3: 11 | P3: 12 | Q3: 13 | R3: 14 | S3: 15 | T3: 16 | U3: 17 | V3: 18 | W3: 19 | X3: 20 | Y3: 21 | Z3: 22 | AA3: 23 | AB3: 24 | AC3: 25 | AD3: 26 | AE3: 27 | AF3: 28 | AG3: 29 | AH3: 30 | AI3: 31 | AJ3: 32 | AK3: 33 | AL3: 34 | AM3: 35 | AN3: 36 | AO3: 37
E4: 2021.12 | F4: 2021.12A | G4: 2022.03 | H4: 2022.06 | I4: 2022.09 | J4: 2022.12 | K4: 2022.12A | L4: 2023.03 | M4: 2023.06 | N4: 2023.09 | O4: 2023.12 | P4: 2023.12A | Q4: 2024.03 | R4: 2024.06 | S4: 2024.09 | T4: 2024.12 | U4: 2024.12A | V4: 2025.03 | W4: 2025.06 | X4: 2025.09 | Y4: 2025.12 | Z4: 2025.12A | AA4: 2026.03 | AB4: 2026.06 | AC4: 2026.09 | AD4: 2026.12 | AE4: 2026.12A | AF4: 2027.03 | AG4: 2027.06 | AH4: 2027.09 | AI4: 2027.12 | AJ4: 2027.12A | AK4: 2028.03 | AL4: 2028.06 | AM4: 2028.09 | AN4: 2028.12 | AO4: 2028.12A
A5: 매출액 | B5: 손익 | C5: 억원 | D5: 매출액(수익) | E5: =IFERROR(VLOOKUP($D5,BS연결,MATCH(E$1,BS연결H,0),0)/100,"") | G5: =IFERROR(VLOOKUP($D5,BS연결,MATCH(G$1,BS연결H,0),0)/100,"") | H5: =IFERROR(VLOOKUP($D5,BS연결,MATCH(H$1,BS연결H,0),0)/100,"") | I5: =IFERROR(VLOOKUP($D5,BS연결,MATCH(I$1,BS연결H,0),0)/100,"") | J5: =IFERROR(VLOOKUP($D5,BS연결,MATCH(J$1,BS연결H,0),0)/100,"") | K5: =IFERROR(VLOOKUP($D5,BS연결,MATCH(K$1,BS연결H,0),0)/100,"") | L5: =IFERROR(VLOOKUP($D5,BS연결,MATCH(L$1,BS연결H,0),0)/100,"") | M5: =IFERROR(VLOOKUP($D5,BS연결,MATCH(M$1,BS연결H,0),0)/100,"") | N5: =IFERROR(VLOOKUP($D5,BS연결,MATCH(N$1,BS연결H,0),0)/100,"") | ... AB5: =IFERROR(VLOOKUP($D5,BS연결,MATCH(AB$1,BS연결H,0),0)/100,"") | AC5: =IFERROR(X5*(1+변수!AC21),"") | AD5: =IFERROR(Y5*(1+변수!AD21),"") | AE5: =SUM(AA5:AD5) | AF5: =IFERROR(AA5*(1+변수!AF21),"") | AG5: =IFERROR(AB5*(1+변수!AG21),"") | AH5: =IFERROR(AC5*(1+변수!AH21),"") | AI5: =IFERROR(AD5*(1+변수!AI21),"") | AJ5: =SUM(AF5:AI5) | AK5: =IFERROR(AF5*(1+변수!AK21),"") | AL5: =IFERROR(AG5*(1+변수!AL21),"") | AM5: =IFERROR(AH5*(1+변수!AM21),"") | AN5: =IFERROR(AI5*(1+변수!AN21),"") | AO5: =SUM(AK5:AN5)
A6: 매출원가 | B6: 손익 | C6: 억원 | D6: 매출원가 | E6: =IFERROR(VLOOKUP($D6,BS연결,MATCH(E$1,BS연결H,0),0)/100,"") | G6: =IFERROR(VLOOKUP($D6,BS연결,MATCH(G$1,BS연결H,0),0)/100,"") | H6: =IFERROR(VLOOKUP($D6,BS연결,MATCH(H$1,BS연결H,0),0)/100,"") | I6: =IFERROR(VLOOKUP($D6,BS연결,MATCH(I$1,BS연결H,0),0)/100,"") | J6: =IFERROR(VLOOKUP($D6,BS연결,MATCH(J$1,BS연결H,0),0)/100,"") | K6: =IFERROR(VLOOKUP($D6,BS연결,MATCH(K$1,BS연결H,0),0)/100,"") | L6: =IFERROR(VLOOKUP($D6,BS연결,MATCH(L$1,BS연결H,0),0)/100,"") | M6: =IFERROR(VLOOKUP($D6,BS연결,MATCH(M$1,BS연결H,0),0)/100,"") | N6: =IFERROR(VLOOKUP($D6,BS연결,MATCH(N$1,BS연결H,0),0)/100,"") | ... AB6: =IFERROR(VLOOKUP($D6,BS연결,MATCH(AB$1,BS연결H,0),0)/100,"") | AC6: =IFERROR(AC5-AC7,"") | AD6: =IFERROR(AD5-AD7,"") | AE6: =SUM(AA6:AD6) | AF6: =IFERROR(AF5-AF7,"") | AG6: =IFERROR(AG5-AG7,"") | AH6: =IFERROR(AH5-AH7,"") | AI6: =IFERROR(AI5-AI7,"") | AJ6: =SUM(AF6:AI6) | AK6: =IFERROR(AK5-AK7,"") | AL6: =IFERROR(AL5-AL7,"") | AM6: =IFERROR(AM5-AM7,"") | AN6: =IFERROR(AN5-AN7,"") | AO6: =SUM(AK6:AN6)
A7: 매출총이익 | B7: 손익 | C7: 억원 | D7: 매출총이익 | E7: =IFERROR(VLOOKUP($D7,BS연결,MATCH(E$1,BS연결H,0),0)/100,"") | G7: =IFERROR(VLOOKUP($D7,BS연결,MATCH(G$1,BS연결H,0),0)/100,"") | H7: =IFERROR(VLOOKUP($D7,BS연결,MATCH(H$1,BS연결H,0),0)/100,"") | I7: =IFERROR(VLOOKUP($D7,BS연결,MATCH(I$1,BS연결H,0),0)/100,"") | J7: =IFERROR(VLOOKUP($D7,BS연결,MATCH(J$1,BS연결H,0),0)/100,"") | K7: =IFERROR(VLOOKUP($D7,BS연결,MATCH(K$1,BS연결H,0),0)/100,"") | L7: =IFERROR(VLOOKUP($D7,BS연결,MATCH(L$1,BS연결H,0),0)/100,"") | M7: =IFERROR(VLOOKUP($D7,BS연결,MATCH(M$1,BS연결H,0),0)/100,"") | N7: =IFERROR(VLOOKUP($D7,BS연결,MATCH(N$1,BS연결H,0),0)/100,"") | ... AB7: =IFERROR(VLOOKUP($D7,BS연결,MATCH(AB$1,BS연결H,0),0)/100,"") | AC7: =IFERROR(AC9+AC8,"") | AD7: =IFERROR(AD9+AD8,"") | AE7: =SUM(AA7:AD7) | AF7: =IFERROR(AF9+AF8,"") | AG7: =IFERROR(AG9+AG8,"") | AH7: =IFERROR(AH9+AH8,"") | AI7: =IFERROR(AI9+AI8,"") | AJ7: =SUM(AF7:AI7) | AK7: =IFERROR(AK9+AK8,"") | AL7: =IFERROR(AL9+AL8,"") | AM7: =IFERROR(AM9+AM8,"") | AN7: =IFERROR(AN9+AN8,"") | AO7: =SUM(AK7:AN7)
A8: 판관비 | B8: 손익 | C8: 억원 | D8: 판관비 | E8: =IFERROR(VLOOKUP($D8,BS연결,MATCH(E$1,BS연결H,0),0)/100,"") | G8: =IFERROR(VLOOKUP($D8,BS연결,MATCH(G$1,BS연결H,0),0)/100,"") | H8: =IFERROR(VLOOKUP($D8,BS연결,MATCH(H$1,BS연결H,0),0)/100,"") | I8: =IFERROR(VLOOKUP($D8,BS연결,MATCH(I$1,BS연결H,0),0)/100,"") | J8: =IFERROR(VLOOKUP($D8,BS연결,MATCH(J$1,BS연결H,0),0)/100,"") | K8: =IFERROR(VLOOKUP($D8,BS연결,MATCH(K$1,BS연결H,0),0)/100,"") | L8: =IFERROR(VLOOKUP($D8,BS연결,MATCH(L$1,BS연결H,0),0)/100,"") | M8: =IFERROR(VLOOKUP($D8,BS연결,MATCH(M$1,BS연결H,0),0)/100,"") | N8: =IFERROR(VLOOKUP($D8,BS연결,MATCH(N$1,BS연결H,0),0)/100,"") | ... AB8: =IFERROR(VLOOKUP($D8,BS연결,MATCH(AB$1,BS연결H,0),0)/100,"") | AC8: =IFERROR(AC5*변수!AC22,"") | AD8: =IFERROR(AD5*변수!AD22,"") | AE8: =SUM(AA8:AD8) | AF8: =IFERROR(AF5*변수!AF22,"") | AG8: =IFERROR(AG5*변수!AG22,"") | AH8: =IFERROR(AH5*변수!AH22,"") | AI8: =IFERROR(AI5*변수!AI22,"") | AJ8: =SUM(AF8:AI8) | AK8: =IFERROR(AK5*변수!AK22,"") | AL8: =IFERROR(AL5*변수!AL22,"") | AM8: =IFERROR(AM5*변수!AM22,"") | AN8: =IFERROR(AN5*변수!AN22,"") | AO8: =SUM(AK8:AN8)
A9: 영업이익 | B9: 손익 | C9: 억원 | D9: 영업이익 | E9: =IFERROR(VLOOKUP($D9,BS연결,MATCH(E$1,BS연결H,0),0)/100,"") | G9: =IFERROR(VLOOKUP($D9,BS연결,MATCH(G$1,BS연결H,0),0)/100,"") | H9: =IFERROR(VLOOKUP($D9,BS연결,MATCH(H$1,BS연결H,0),0)/100,"") | I9: =IFERROR(VLOOKUP($D9,BS연결,MATCH(I$1,BS연결H,0),0)/100,"") | J9: =IFERROR(VLOOKUP($D9,BS연결,MATCH(J$1,BS연결H,0),0)/100,"") | K9: =IFERROR(VLOOKUP($D9,BS연결,MATCH(K$1,BS연결H,0),0)/100,"") | L9: =IFERROR(VLOOKUP($D9,BS연결,MATCH(L$1,BS연결H,0),0)/100,"") | M9: =IFERROR(VLOOKUP($D9,BS연결,MATCH(M$1,BS연결H,0),0)/100,"") | N9: =IFERROR(VLOOKUP($D9,BS연결,MATCH(N$1,BS연결H,0),0)/100,"") | ... AB9: =IFERROR(VLOOKUP($D9,BS연결,MATCH(AB$1,BS연결H,0),0)/100,"") | AC9: =IFERROR(AC5*변수!AC23,"") | AD9: =IFERROR(AD5*변수!AD23,"") | AE9: =SUM(AA9:AD9) | AF9: =IFERROR(AF5*변수!AF23,"") | AG9: =IFERROR(AG5*변수!AG23,"") | AH9: =IFERROR(AH5*변수!AH23,"") | AI9: =IFERROR(AI5*변수!AI23,"") | AJ9: =SUM(AF9:AI9) | AK9: =IFERROR(AK5*변수!AK23,"") | AL9: =IFERROR(AL5*변수!AL23,"") | AM9: =IFERROR(AM5*변수!AM23,"") | AN9: =IFERROR(AN5*변수!AN23,"") | AO9: =SUM(AK9:AN9)
A10: OPM | B10: 손익 | C10: % | D10: 영업이익률 | E10: =IFERROR(E9/E5,"") | G10: =IFERROR(G9/G5,"") | H10: =IFERROR(H9/H5,"") | I10: =IFERROR(I9/I5,"") | J10: =IFERROR(J9/J5,"") | K10: =IFERROR(K9/K5,"") | L10: =IFERROR(L9/L5,"") | M10: =IFERROR(M9/M5,"") | N10: =IFERROR(N9/N5,"") | ... AO10: =IFERROR(AO9/AO5,"")
A11: 금융손익 | B11: 손익 | C11: 억원 | D11: 금융손익 | E11: =IFERROR(VLOOKUP($D11,BS연결,MATCH(E$1,BS연결H,0),0)/100,"") | G11: =IFERROR(VLOOKUP($D11,BS연결,MATCH(G$1,BS연결H,0),0)/100,"") | H11: =IFERROR(VLOOKUP($D11,BS연결,MATCH(H$1,BS연결H,0),0)/100,"") | I11: =IFERROR(VLOOKUP($D11,BS연결,MATCH(I$1,BS연결H,0),0)/100,"") | J11: =IFERROR(VLOOKUP($D11,BS연결,MATCH(J$1,BS연결H,0),0)/100,"") | K11: =IFERROR(VLOOKUP($D11,BS연결,MATCH(K$1,BS연결H,0),0)/100,"") | L11: =IFERROR(VLOOKUP($D11,BS연결,MATCH(L$1,BS연결H,0),0)/100,"") | M11: =IFERROR(VLOOKUP($D11,BS연결,MATCH(M$1,BS연결H,0),0)/100,"") | N11: =IFERROR(VLOOKUP($D11,BS연결,MATCH(N$1,BS연결H,0),0)/100,"") | ... AB11: =IFERROR(VLOOKUP($D11,BS연결,MATCH(AB$1,BS연결H,0),0)/100,"") | AC11: =IFERROR(AC12+AC13+AC14+AC15,"") | AD11: =IFERROR(AD12+AD13+AD14+AD15,"") | AE11: =SUM(AA11:AD11) | AF11: =IFERROR(AF12+AF13+AF14+AF15,"") | AG11: =IFERROR(AG12+AG13+AG14+AG15,"") | AH11: =IFERROR(AH12+AH13+AH14+AH15,"") | AI11: =IFERROR(AI12+AI13+AI14+AI15,"") | AJ11: =SUM(AF11:AI11) | AK11: =IFERROR(AK12+AK13+AK14+AK15,"") | AL11: =IFERROR(AL12+AL13+AL14+AL15,"") | AM11: =IFERROR(AM12+AM13+AM14+AM15,"") | AN11: =IFERROR(AN12+AN13+AN14+AN15,"") | AO11: =SUM(AK11:AN11)
A12: 이자손익 | B12: 손익 | C12: 억원 | D12: 이자손익 | G12: =IFERROR(VLOOKUP($D12,BS연결,MATCH(G$1,BS연결H,0),0)/100,"") | H12: =IFERROR(VLOOKUP($D12,BS연결,MATCH(H$1,BS연결H,0),0)/100,"") | I12: =IFERROR(VLOOKUP($D12,BS연결,MATCH(I$1,BS연결H,0),0)/100,"") | J12: =IFERROR(VLOOKUP($D12,BS연결,MATCH(J$1,BS연결H,0),0)/100,"") | K12: =IFERROR(VLOOKUP($D12,BS연결,MATCH(K$1,BS연결H,0),0)/100,"") | L12: =IFERROR(VLOOKUP($D12,BS연결,MATCH(L$1,BS연결H,0),0)/100,"") | M12: =IFERROR(VLOOKUP($D12,BS연결,MATCH(M$1,BS연결H,0),0)/100,"") | N12: =IFERROR(VLOOKUP($D12,BS연결,MATCH(N$1,BS연결H,0),0)/100,"") | ... AB12: =IFERROR(VLOOKUP($D12,BS연결,MATCH(AB$1,BS연결H,0),0)/100,"") | AC12: =IFERROR((AB27*변수!$D$53-AB25*변수!$D$54)/4,"") | AD12: =IFERROR((AC27*변수!$D$53-AC25*변수!$D$54)/4,"") | AE12: =SUM(AA12:AD12) | AF12: =IFERROR((AD27*변수!$D$53-AD25*변수!$D$54)/4,"") | AG12: =IFERROR((AF27*변수!$D$53-AF25*변수!$D$54)/4,"") | AH12: =IFERROR((AG27*변수!$D$53-AG25*변수!$D$54)/4,"") | AI12: =IFERROR((AH27*변수!$D$53-AH25*변수!$D$54)/4,"") | AJ12: =SUM(AF12:AI12) | AK12: =IFERROR((AI27*변수!$D$53-AI25*변수!$D$54)/4,"") | AL12: =IFERROR((AK27*변수!$D$53-AK25*변수!$D$54)/4,"") | AM12: =IFERROR((AL27*변수!$D$53-AL25*변수!$D$54)/4,"") | AN12: =IFERROR((AM27*변수!$D$53-AM25*변수!$D$54)/4,"") | AO12: =SUM(AK12:AN12)
A13: 외환손익 | B13: 손익 | C13: 억원 | D13: 외환손익(실적만; 추정 환효과는 환관련손익) | G13: =IFERROR((VLOOKUP("외환차익",BS연결,MATCH(G$1,BS연결H,0),0)-VLOOKUP("외환차손",BS연결,MATCH(G$1,BS연결H,0),0)+VLOOKUP("외화환산이익",BS연결,MATCH(G$1,BS연결H,0),0)-VLOOKUP("외화환산손실",BS연결,MATCH(G$1,BS연결H,0),0))/100,"") | H13: =IFERROR((VLOOKUP("외환차익",BS연결,MATCH(H$1,BS연결H,0),0)-VLOOKUP("외환차손",BS연결,MATCH(H$1,BS연결H,0),0)+VLOOKUP("외화환산이익",BS연결,MATCH(H$1,BS연결H,0),0)-VLOOKUP("외화환산손실",BS연결,MATCH(H$1,BS연결H,0),0))/100,"") | I13: =IFERROR((VLOOKUP("외환차익",BS연결,MATCH(I$1,BS연결H,0),0)-VLOOKUP("외환차손",BS연결,MATCH(I$1,BS연결H,0),0)+VLOOKUP("외화환산이익",BS연결,MATCH(I$1,BS연결H,0),0)-VLOOKUP("외화환산손실",BS연결,MATCH(I$1,BS연결H,0),0))/100,"") | J13: =IFERROR((VLOOKUP("외환차익",BS연결,MATCH(J$1,BS연결H,0),0)-VLOOKUP("외환차손",BS연결,MATCH(J$1,BS연결H,0),0)+VLOOKUP("외화환산이익",BS연결,MATCH(J$1,BS연결H,0),0)-VLOOKUP("외화환산손실",BS연결,MATCH(J$1,BS연결H,0),0))/100,"") | K13: =SUM(G13:J13) | L13: =IFERROR((VLOOKUP("외환차익",BS연결,MATCH(L$1,BS연결H,0),0)-VLOOKUP("외환차손",BS연결,MATCH(L$1,BS연결H,0),0)+VLOOKUP("외화환산이익",BS연결,MATCH(L$1,BS연결H,0),0)-VLOOKUP("외화환산손실",BS연결,MATCH(L$1,BS연결H,0),0))/100,"") | N13: =IFERROR((VLOOKUP("외환차익",BS연결,MATCH(N$1,BS연결H,0),0)-VLOOKUP("외환차손",BS연결,MATCH(N$1,BS연결H,0),0)+VLOOKUP("외화환산이익",BS연결,MATCH(N$1,BS연결H,0),0)-VLOOKUP("외화환산손실",BS연결,MATCH(N$1,BS연결H,0),0))/100,"") | O13: =IFERROR((VLOOKUP("외환차익",BS연결,MATCH(O$1,BS연결H,0),0)-VLOOKUP("외환차손",BS연결,MATCH(O$1,BS연결H,0),0)+VLOOKUP("외화환산이익",BS연결,MATCH(O$1,BS연결H,0),0)-VLOOKUP("외화환산손실",BS연결,MATCH(O$1,BS연결H,0),0))/100,"") | P13: =SUM(L13:O13) | Q13: =IFERROR((VLOOKUP("외환차익",BS연결,MATCH(Q$1,BS연결H,0),0)-VLOOKUP("외환차손",BS연결,MATCH(Q$1,BS연결H,0),0)+VLOOKUP("외화환산이익",BS연결,MATCH(Q$1,BS연결H,0),0)-VLOOKUP("외화환산손실",BS연결,MATCH(Q$1,BS연결H,0),0))/100,"") | S13: =IFERROR((VLOOKUP("외환차익",BS연결,MATCH(S$1,BS연결H,0),0)-VLOOKUP("외환차손",BS연결,MATCH(S$1,BS연결H,0),0)+VLOOKUP("외화환산이익",BS연결,MATCH(S$1,BS연결H,0),0)-VLOOKUP("외화환산손실",BS연결,MATCH(S$1,BS연결H,0),0))/100,"") | T13: =IFERROR((VLOOKUP("외환차익",BS연결,MATCH(T$1,BS연결H,0),0)-VLOOKUP("외환차손",BS연결,MATCH(T$1,BS연결H,0),0)+VLOOKUP("외화환산이익",BS연결,MATCH(T$1,BS연결H,0),0)-VLOOKUP("외화환산손실",BS연결,MATCH(T$1,BS연결H,0),0))/100,"") | U13: =SUM(Q13:T13) | V13: =IFERROR((VLOOKUP("외환차익",BS연결,MATCH(V$1,BS연결H,0),0)-VLOOKUP("외환차손",BS연결,MATCH(V$1,BS연결H,0),0)+VLOOKUP("외화환산이익",BS연결,MATCH(V$1,BS연결H,0),0)-VLOOKUP("외화환산손실",BS연결,MATCH(V$1,BS연결H,0),0))/100,"") | W13: =IFERROR((VLOOKUP("외환차익",BS연결,MATCH(W$1,BS연결H,0),0)-VLOOKUP("외환차손",BS연결,MATCH(W$1,BS연결H,0),0)+VLOOKUP("외화환산이익",BS연결,MATCH(W$1,BS연결H,0),0)-VLOOKUP("외화환산손실",BS연결,MATCH(W$1,BS연결H,0),0))/100,"") | X13: =IFERROR((VLOOKUP("외환차익",BS연결,MATCH(X$1,BS연결H,0),0)-VLOOKUP("외환차손",BS연결,MATCH(X$1,BS연결H,0),0)+VLOOKUP("외화환산이익",BS연결,MATCH(X$1,BS연결H,0),0)-VLOOKUP("외화환산손실",BS연결,MATCH(X$1,BS연결H,0),0))/100,"") | Y13: =IFERROR((VLOOKUP("외환차익",BS연결,MATCH(Y$1,BS연결H,0),0)-VLOOKUP("외환차손",BS연결,MATCH(Y$1,BS연결H,0),0)+VLOOKUP("외화환산이익",BS연결,MATCH(Y$1,BS연결H,0),0)-VLOOKUP("외화환산손실",BS연결,MATCH(Y$1,BS연결H,0),0))/100,"") | Z13: =SUM(V13:Y13) | AA13: =IFERROR((VLOOKUP("외환차익",BS연결,MATCH(AA$1,BS연결H,0),0)-VLOOKUP("외환차손",BS연결,MATCH(AA$1,BS연결H,0),0)+VLOOKUP("외화환산이익",BS연결,MATCH(AA$1,BS연결H,0),0)-VLOOKUP("외화환산손실",BS연결,MATCH(AA$1,BS연결H,0),0))/100,"") | AB13: =IFERROR((VLOOKUP("외환차익",BS연결,MATCH(AB$1,BS연결H,0),0)-VLOOKUP("외환차손",BS연결,MATCH(AB$1,BS연결H,0),0)+VLOOKUP("외화환산이익",BS연결,MATCH(AB$1,BS연결H,0),0)-VLOOKUP("외화환산손실",BS연결,MATCH(AB$1,BS연결H,0),0))/100,"") | AC13: =변수!AC24 | AD13: =변수!AD24 | AE13: =SUM(AA13:AD13) | AF13: =변수!AF24 | AG13: =변수!AG24 | AH13: =변수!AH24 | AI13: =변수!AI24 | AJ13: =SUM(AF13:AI13) | AK13: =변수!AK24 | AL13: =변수!AL24 | AM13: =변수!AM24 | AN13: =변수!AN24 | AO13: =SUM(AK13:AN13)
A14: 파생상품손익 | B14: 손익 | C14: 억원 | D14: 파생상품손익 | K14: =SUM(G14:J14) | P14: =SUM(L14:O14) | U14: =SUM(Q14:T14) | V14: =IFERROR((VLOOKUP("파생상품이익",BS연결,MATCH(V$1,BS연결H,0),0)-VLOOKUP("파생상품손실",BS연결,MATCH(V$1,BS연결H,0),0))/100,"") | W14: =IFERROR((VLOOKUP("파생상품이익",BS연결,MATCH(W$1,BS연결H,0),0)-VLOOKUP("파생상품손실",BS연결,MATCH(W$1,BS연결H,0),0))/100,"") | X14: =IFERROR((VLOOKUP("파생상품이익",BS연결,MATCH(X$1,BS연결H,0),0)-VLOOKUP("파생상품손실",BS연결,MATCH(X$1,BS연결H,0),0))/100,"") | Y14: =IFERROR((VLOOKUP("파생상품이익",BS연결,MATCH(Y$1,BS연결H,0),0)-VLOOKUP("파생상품손실",BS연결,MATCH(Y$1,BS연결H,0),0))/100,"") | Z14: =SUM(V14:Y14) | AA14: =IFERROR((VLOOKUP("파생상품이익",BS연결,MATCH(AA$1,BS연결H,0),0)-VLOOKUP("파생상품손실",BS연결,MATCH(AA$1,BS연결H,0),0))/100,"") | AB14: =IFERROR((VLOOKUP("파생상품이익",BS연결,MATCH(AB$1,BS연결H,0),0)-VLOOKUP("파생상품손실",BS연결,MATCH(AB$1,BS연결H,0),0))/100,"") | AC14: =변수!AC25 | AD14: =변수!AD25 | AE14: =SUM(AA14:AD14) | AF14: =변수!AF25 | AG14: =변수!AG25 | AH14: =변수!AH25 | AI14: =변수!AI25 | AJ14: =SUM(AF14:AI14) | AK14: =변수!AK25 | AL14: =변수!AL25 | AM14: =변수!AM25 | AN14: =변수!AN25 | AO14: =SUM(AK14:AN14)
A15: 기타금융손익 | B15: 손익 | C15: 억원 | D15: 기타금융손익(금융손익 잔차) | K15: =SUM(G15:J15) | P15: =SUM(L15:O15) | U15: =SUM(Q15:T15) | V15: =IFERROR(V11-V12-V13-V14,"") | W15: =IFERROR(W11-W12-W13-W14,"") | X15: =IFERROR(X11-X12-X13-X14,"") | Y15: =IFERROR(Y11-Y12-Y13-Y14,"") | Z15: =SUM(V15:Y15) | AA15: =IFERROR(AA11-AA12-AA13-AA14,"") | AB15: =IFERROR(AB11-AB12-AB13-AB14,"") | AC15: =변수!AC26 | AD15: =변수!AD26 | AE15: =SUM(AA15:AD15) | AF15: =변수!AF26 | AG15: =변수!AG26 | AH15: =변수!AH26 | AI15: =변수!AI26 | AJ15: =SUM(AF15:AI15) | AK15: =변수!AK26 | AL15: =변수!AL26 | AM15: =변수!AM26 | AN15: =변수!AN26 | AO15: =SUM(AK15:AN15)
A16: 기타영업외손익 | B16: 손익 | C16: 억원 | D16: 기타영업외손익 | E16: =IFERROR(VLOOKUP($D16,BS연결,MATCH(E$1,BS연결H,0),0)/100,"") | G16: =IFERROR(VLOOKUP($D16,BS연결,MATCH(G$1,BS연결H,0),0)/100,"") | H16: =IFERROR(VLOOKUP($D16,BS연결,MATCH(H$1,BS연결H,0),0)/100,"") | I16: =IFERROR(VLOOKUP($D16,BS연결,MATCH(I$1,BS연결H,0),0)/100,"") | J16: =IFERROR(VLOOKUP($D16,BS연결,MATCH(J$1,BS연결H,0),0)/100,"") | K16: =IFERROR(VLOOKUP($D16,BS연결,MATCH(K$1,BS연결H,0),0)/100,"") | L16: =IFERROR(VLOOKUP($D16,BS연결,MATCH(L$1,BS연결H,0),0)/100,"") | M16: =IFERROR(VLOOKUP($D16,BS연결,MATCH(M$1,BS연결H,0),0)/100,"") | N16: =IFERROR(VLOOKUP($D16,BS연결,MATCH(N$1,BS연결H,0),0)/100,"") | ... AB16: =IFERROR(VLOOKUP($D16,BS연결,MATCH(AB$1,BS연결H,0),0)/100,"") | AC16: =변수!AC27 | AD16: =변수!AD27 | AE16: =SUM(AA16:AD16) | AF16: =변수!AF27 | AG16: =변수!AG27 | AH16: =변수!AH27 | AI16: =변수!AI27 | AJ16: =SUM(AF16:AI16) | AK16: =변수!AK27 | AL16: =변수!AL27 | AM16: =변수!AM27 | AN16: =변수!AN27 | AO16: =SUM(AK16:AN16)
A17: 세전이익 | B17: 손익 | C17: 억원 | D17: 법인세비용차감전계속사업이익 | E17: =IFERROR(VLOOKUP($D17,BS연결,MATCH(E$1,BS연결H,0),0)/100,"") | G17: =IFERROR(VLOOKUP($D17,BS연결,MATCH(G$1,BS연결H,0),0)/100,"") | H17: =IFERROR(VLOOKUP($D17,BS연결,MATCH(H$1,BS연결H,0),0)/100,"") | I17: =IFERROR(VLOOKUP($D17,BS연결,MATCH(I$1,BS연결H,0),0)/100,"") | J17: =IFERROR(VLOOKUP($D17,BS연결,MATCH(J$1,BS연결H,0),0)/100,"") | K17: =IFERROR(VLOOKUP($D17,BS연결,MATCH(K$1,BS연결H,0),0)/100,"") | L17: =IFERROR(VLOOKUP($D17,BS연결,MATCH(L$1,BS연결H,0),0)/100,"") | M17: =IFERROR(VLOOKUP($D17,BS연결,MATCH(M$1,BS연결H,0),0)/100,"") | N17: =IFERROR(VLOOKUP($D17,BS연결,MATCH(N$1,BS연결H,0),0)/100,"") | ... AB17: =IFERROR(VLOOKUP($D17,BS연결,MATCH(AB$1,BS연결H,0),0)/100,"") | AC17: =IFERROR(AC9+AC11+AC16,"") | AD17: =IFERROR(AD9+AD11+AD16,"") | AE17: =SUM(AA17:AD17) | AF17: =IFERROR(AF9+AF11+AF16,"") | AG17: =IFERROR(AG9+AG11+AG16,"") | AH17: =IFERROR(AH9+AH11+AH16,"") | AI17: =IFERROR(AI9+AI11+AI16,"") | AJ17: =SUM(AF17:AI17) | AK17: =IFERROR(AK9+AK11+AK16,"") | AL17: =IFERROR(AL9+AL11+AL16,"") | AM17: =IFERROR(AM9+AM11+AM16,"") | AN17: =IFERROR(AN9+AN11+AN16,"") | AO17: =SUM(AK17:AN17)
A18: 법인세비용 | B18: 손익 | C18: 억원 | D18: 법인세비용 | E18: =IFERROR(VLOOKUP($D18,BS연결,MATCH(E$1,BS연결H,0),0)/100,"") | G18: =IFERROR(VLOOKUP($D18,BS연결,MATCH(G$1,BS연결H,0),0)/100,"") | H18: =IFERROR(VLOOKUP($D18,BS연결,MATCH(H$1,BS연결H,0),0)/100,"") | I18: =IFERROR(VLOOKUP($D18,BS연결,MATCH(I$1,BS연결H,0),0)/100,"") | J18: =IFERROR(VLOOKUP($D18,BS연결,MATCH(J$1,BS연결H,0),0)/100,"") | K18: =IFERROR(VLOOKUP($D18,BS연결,MATCH(K$1,BS연결H,0),0)/100,"") | L18: =IFERROR(VLOOKUP($D18,BS연결,MATCH(L$1,BS연결H,0),0)/100,"") | M18: =IFERROR(VLOOKUP($D18,BS연결,MATCH(M$1,BS연결H,0),0)/100,"") | N18: =IFERROR(VLOOKUP($D18,BS연결,MATCH(N$1,BS연결H,0),0)/100,"") | ... AB18: =IFERROR(VLOOKUP($D18,BS연결,MATCH(AB$1,BS연결H,0),0)/100,"") | AC18: =IFERROR(MAX(AC17,0)*변수!AC28,"") | AD18: =IFERROR(MAX(AD17,0)*변수!AD28,"") | AE18: =SUM(AA18:AD18) | AF18: =IFERROR(MAX(AF17,0)*변수!AF28,"") | AG18: =IFERROR(MAX(AG17,0)*변수!AG28,"") | AH18: =IFERROR(MAX(AH17,0)*변수!AH28,"") | AI18: =IFERROR(MAX(AI17,0)*변수!AI28,"") | AJ18: =SUM(AF18:AI18) | AK18: =IFERROR(MAX(AK17,0)*변수!AK28,"") | AL18: =IFERROR(MAX(AL17,0)*변수!AL28,"") | AM18: =IFERROR(MAX(AM17,0)*변수!AM28,"") | AN18: =IFERROR(MAX(AN17,0)*변수!AN28,"") | AO18: =SUM(AK18:AN18)
A19: 당기순이익 | B19: 손익 | C19: 억원 | D19: 당기순이익 | E19: =IFERROR(VLOOKUP($D19,BS연결,MATCH(E$1,BS연결H,0),0)/100,"") | G19: =IFERROR(VLOOKUP($D19,BS연결,MATCH(G$1,BS연결H,0),0)/100,"") | H19: =IFERROR(VLOOKUP($D19,BS연결,MATCH(H$1,BS연결H,0),0)/100,"") | I19: =IFERROR(VLOOKUP($D19,BS연결,MATCH(I$1,BS연결H,0),0)/100,"") | J19: =IFERROR(VLOOKUP($D19,BS연결,MATCH(J$1,BS연결H,0),0)/100,"") | K19: =IFERROR(VLOOKUP($D19,BS연결,MATCH(K$1,BS연결H,0),0)/100,"") | L19: =IFERROR(VLOOKUP($D19,BS연결,MATCH(L$1,BS연결H,0),0)/100,"") | M19: =IFERROR(VLOOKUP($D19,BS연결,MATCH(M$1,BS연결H,0),0)/100,"") | N19: =IFERROR(VLOOKUP($D19,BS연결,MATCH(N$1,BS연결H,0),0)/100,"") | ... AB19: =IFERROR(VLOOKUP($D19,BS연결,MATCH(AB$1,BS연결H,0),0)/100,"") | AC19: =IFERROR(AC17-AC18,"") | AD19: =IFERROR(AD17-AD18,"") | AE19: =SUM(AA19:AD19) | AF19: =IFERROR(AF17-AF18,"") | AG19: =IFERROR(AG17-AG18,"") | AH19: =IFERROR(AH17-AH18,"") | AI19: =IFERROR(AI17-AI18,"") | AJ19: =SUM(AF19:AI19) | AK19: =IFERROR(AK17-AK18,"") | AL19: =IFERROR(AL17-AL18,"") | AM19: =IFERROR(AM17-AM18,"") | AN19: =IFERROR(AN17-AN18,"") | AO19: =SUM(AK19:AN19)
A20: 지배주주순이익 | B20: 손익 | C20: 억원 | D20: (지배주주지분)당기순이익 | E20: =IFERROR(VLOOKUP($D20,BS연결,MATCH(E$1,BS연결H,0),0)/100,"") | G20: =IFERROR(VLOOKUP($D20,BS연결,MATCH(G$1,BS연결H,0),0)/100,"") | H20: =IFERROR(VLOOKUP($D20,BS연결,MATCH(H$1,BS연결H,0),0)/100,"") | I20: =IFERROR(VLOOKUP($D20,BS연결,MATCH(I$1,BS연결H,0),0)/100,"") | J20: =IFERROR(VLOOKUP($D20,BS연결,MATCH(J$1,BS연결H,0),0)/100,"") | K20: =IFERROR(VLOOKUP($D20,BS연결,MATCH(K$1,BS연결H,0),0)/100,"") | L20: =IFERROR(VLOOKUP($D20,BS연결,MATCH(L$1,BS연결H,0),0)/100,"") | M20: =IFERROR(VLOOKUP($D20,BS연결,MATCH(M$1,BS연결H,0),0)/100,"") | N20: =IFERROR(VLOOKUP($D20,BS연결,MATCH(N$1,BS연결H,0),0)/100,"") | ... AB20: =IFERROR(VLOOKUP($D20,BS연결,MATCH(AB$1,BS연결H,0),0)/100,"") | AC20: =IFERROR(AC19*변수!AC29,"") | AD20: =IFERROR(AD19*변수!AD29,"") | AE20: =SUM(AA20:AD20) | AF20: =IFERROR(AF19*변수!AF29,"") | AG20: =IFERROR(AG19*변수!AG29,"") | AH20: =IFERROR(AH19*변수!AH29,"") | AI20: =IFERROR(AI19*변수!AI29,"") | AJ20: =SUM(AF20:AI20) | AK20: =IFERROR(AK19*변수!AK29,"") | AL20: =IFERROR(AL19*변수!AL29,"") | AM20: =IFERROR(AM19*변수!AM29,"") | AN20: =IFERROR(AN19*변수!AN29,"") | AO20: =SUM(AK20:AN20)
A21: 자산총계 | B21: 재무상태 | C21: 억원 | D21: 자산총계 | E21: =IFERROR(VLOOKUP($D21,BS연결,MATCH(E$1,BS연결H,0),0)/100,"") | F21: =IFERROR(VLOOKUP($D21,BS연결,MATCH(F$1,BS연결H,0),0)/100,"") | G21: =IFERROR(VLOOKUP($D21,BS연결,MATCH(G$1,BS연결H,0),0)/100,"") | H21: =IFERROR(VLOOKUP($D21,BS연결,MATCH(H$1,BS연결H,0),0)/100,"") | I21: =IFERROR(VLOOKUP($D21,BS연결,MATCH(I$1,BS연결H,0),0)/100,"") | J21: =IFERROR(VLOOKUP($D21,BS연결,MATCH(J$1,BS연결H,0),0)/100,"") | K21: =IFERROR(VLOOKUP($D21,BS연결,MATCH(K$1,BS연결H,0),0)/100,"") | L21: =IFERROR(VLOOKUP($D21,BS연결,MATCH(L$1,BS연결H,0),0)/100,"") | ... S21: =IFERROR(VLOOKUP($D21,BS연결,MATCH(S$1,BS연결H,0),0)/100,"") | U21: =T21 | Z21: =Y21 | AC21: =IFERROR(AC22+AC23,"") | AD21: =IFERROR(AD22+AD23,"") | AE21: =AD21 | AF21: =IFERROR(AF22+AF23,"") | AG21: =IFERROR(AG22+AG23,"") | AH21: =IFERROR(AH22+AH23,"") | AI21: =IFERROR(AI22+AI23,"") | AJ21: =AI21 | AK21: =IFERROR(AK22+AK23,"") | AL21: =IFERROR(AL22+AL23,"") | AM21: =IFERROR(AM22+AM23,"") | AN21: =IFERROR(AN22+AN23,"") | AO21: =AN21
A22: 부채총계 | B22: 재무상태 | C22: 억원 | D22: 부채총계 | E22: =IFERROR(VLOOKUP($D22,BS연결,MATCH(E$1,BS연결H,0),0)/100,"") | F22: =IFERROR(VLOOKUP($D22,BS연결,MATCH(F$1,BS연결H,0),0)/100,"") | G22: =IFERROR(VLOOKUP($D22,BS연결,MATCH(G$1,BS연결H,0),0)/100,"") | H22: =IFERROR(VLOOKUP($D22,BS연결,MATCH(H$1,BS연결H,0),0)/100,"") | I22: =IFERROR(VLOOKUP($D22,BS연결,MATCH(I$1,BS연결H,0),0)/100,"") | J22: =IFERROR(VLOOKUP($D22,BS연결,MATCH(J$1,BS연결H,0),0)/100,"") | K22: =IFERROR(VLOOKUP($D22,BS연결,MATCH(K$1,BS연결H,0),0)/100,"") | L22: =IFERROR(VLOOKUP($D22,BS연결,MATCH(L$1,BS연결H,0),0)/100,"") | ... S22: =IFERROR(VLOOKUP($D22,BS연결,MATCH(S$1,BS연결H,0),0)/100,"") | U22: =T22 | Z22: =Y22 | AE22: =AD22 | AJ22: =AI22 | AO22: =AN22
A23: 자본총계 | B23: 재무상태 | C23: 억원 | D23: 자본총계 | E23: =IFERROR(VLOOKUP($D23,BS연결,MATCH(E$1,BS연결H,0),0)/100,"") | F23: =IFERROR(VLOOKUP($D23,BS연결,MATCH(F$1,BS연결H,0),0)/100,"") | G23: =IFERROR(VLOOKUP($D23,BS연결,MATCH(G$1,BS연결H,0),0)/100,"") | H23: =IFERROR(VLOOKUP($D23,BS연결,MATCH(H$1,BS연결H,0),0)/100,"") | I23: =IFERROR(VLOOKUP($D23,BS연결,MATCH(I$1,BS연결H,0),0)/100,"") | J23: =IFERROR(VLOOKUP($D23,BS연결,MATCH(J$1,BS연결H,0),0)/100,"") | K23: =IFERROR(VLOOKUP($D23,BS연결,MATCH(K$1,BS연결H,0),0)/100,"") | L23: =IFERROR(VLOOKUP($D23,BS연결,MATCH(L$1,BS연결H,0),0)/100,"") | ... AB23: =IFERROR(VLOOKUP($D23,BS연결,MATCH(AB$1,BS연결H,0),0)/100,"") | AC23: =IFERROR(AB23+AC19-변수!AC31,"") | AD23: =IFERROR(AC23+AD19-변수!AD31,"") | AE23: =AD23 | AF23: =IFERROR(AD23+AF19-변수!AF31,"") | AG23: =IFERROR(AF23+AG19-변수!AG31,"") | AH23: =IFERROR(AG23+AH19-변수!AH31,"") | AI23: =IFERROR(AH23+AI19-변수!AI31,"") | AJ23: =AI23 | AK23: =IFERROR(AI23+AK19-변수!AK31,"") | AL23: =IFERROR(AK23+AL19-변수!AL31,"") | AM23: =IFERROR(AL23+AM19-변수!AM31,"") | AN23: =IFERROR(AM23+AN19-변수!AN31,"") | AO23: =AN23
A24: 지배주주지분 | B24: 재무상태 | C24: 억원 | D24: 지배주주지분 | E24: =IFERROR(VLOOKUP($D24,BS연결,MATCH(E$1,BS연결H,0),0)/100,"") | F24: =IFERROR(VLOOKUP($D24,BS연결,MATCH(F$1,BS연결H,0),0)/100,"") | G24: =IFERROR(VLOOKUP($D24,BS연결,MATCH(G$1,BS연결H,0),0)/100,"") | H24: =IFERROR(VLOOKUP($D24,BS연결,MATCH(H$1,BS연결H,0),0)/100,"") | I24: =IFERROR(VLOOKUP($D24,BS연결,MATCH(I$1,BS연결H,0),0)/100,"") | J24: =IFERROR(VLOOKUP($D24,BS연결,MATCH(J$1,BS연결H,0),0)/100,"") | K24: =IFERROR(VLOOKUP($D24,BS연결,MATCH(K$1,BS연결H,0),0)/100,"") | L24: =IFERROR(VLOOKUP($D24,BS연결,MATCH(L$1,BS연결H,0),0)/100,"") | ... AB24: =IFERROR(VLOOKUP($D24,BS연결,MATCH(AB$1,BS연결H,0),0)/100,"") | AC24: =IFERROR(AB24+AC20-변수!AC32,"") | AD24: =IFERROR(AC24+AD20-변수!AD32,"") | AE24: =AD24 | AF24: =IFERROR(AD24+AF20-변수!AF32,"") | AG24: =IFERROR(AF24+AG20-변수!AG32,"") | AH24: =IFERROR(AG24+AH20-변수!AH32,"") | AI24: =IFERROR(AH24+AI20-변수!AI32,"") | AJ24: =AI24 | AK24: =IFERROR(AI24+AK20-변수!AK32,"") | AL24: =IFERROR(AK24+AL20-변수!AL32,"") | AM24: =IFERROR(AL24+AM20-변수!AM32,"") | AN24: =IFERROR(AM24+AN20-변수!AN32,"") | AO24: =AN24
A25: 총차입금 | B25: 재무상태 | C25: 억원 | D25: 총차입금 | E25: =IFERROR(VLOOKUP($D25,BS연결,MATCH(E$1,BS연결H,0),0)/100,"") | F25: =IFERROR(VLOOKUP($D25,BS연결,MATCH(F$1,BS연결H,0),0)/100,"") | G25: =IFERROR(VLOOKUP($D25,BS연결,MATCH(G$1,BS연결H,0),0)/100,"") | H25: =IFERROR(VLOOKUP($D25,BS연결,MATCH(H$1,BS연결H,0),0)/100,"") | I25: =IFERROR(VLOOKUP($D25,BS연결,MATCH(I$1,BS연결H,0),0)/100,"") | J25: =IFERROR(VLOOKUP($D25,BS연결,MATCH(J$1,BS연결H,0),0)/100,"") | K25: =IFERROR(VLOOKUP($D25,BS연결,MATCH(K$1,BS연결H,0),0)/100,"") | L25: =IFERROR(VLOOKUP($D25,BS연결,MATCH(L$1,BS연결H,0),0)/100,"") | ... S25: =IFERROR(VLOOKUP($D25,BS연결,MATCH(S$1,BS연결H,0),0)/100,"") | U25: =T25 | Z25: =Y25 | AE25: =AD25 | AJ25: =AI25 | AO25: =AN25
A26: 순차입금 | B26: 재무상태 | C26: 억원 | D26: 순차입금 | E26: =IFERROR(VLOOKUP($D26,BS연결,MATCH(E$1,BS연결H,0),0)/100,"") | F26: =IFERROR(VLOOKUP($D26,BS연결,MATCH(F$1,BS연결H,0),0)/100,"") | G26: =IFERROR(VLOOKUP($D26,BS연결,MATCH(G$1,BS연결H,0),0)/100,"") | H26: =IFERROR(VLOOKUP($D26,BS연결,MATCH(H$1,BS연결H,0),0)/100,"") | I26: =IFERROR(VLOOKUP($D26,BS연결,MATCH(I$1,BS연결H,0),0)/100,"") | J26: =IFERROR(VLOOKUP($D26,BS연결,MATCH(J$1,BS연결H,0),0)/100,"") | K26: =IFERROR(VLOOKUP($D26,BS연결,MATCH(K$1,BS연결H,0),0)/100,"") | L26: =IFERROR(VLOOKUP($D26,BS연결,MATCH(L$1,BS연결H,0),0)/100,"") | ... S26: =IFERROR(VLOOKUP($D26,BS연결,MATCH(S$1,BS연결H,0),0)/100,"") | U26: =T26 | Z26: =Y26 | AE26: =AD26 | AJ26: =AI26 | AO26: =AN26
A27: 이자발생자산 | B27: 재무상태 | C27: 억원 | D27: 이자발생자산 | E27: =IFERROR(VLOOKUP($D27,BS연결,MATCH(E$1,BS연결H,0),0)/100,"") | F27: =IFERROR(VLOOKUP($D27,BS연결,MATCH(F$1,BS연결H,0),0)/100,"") | G27: =IFERROR(VLOOKUP($D27,BS연결,MATCH(G$1,BS연결H,0),0)/100,"") | H27: =IFERROR(VLOOKUP($D27,BS연결,MATCH(H$1,BS연결H,0),0)/100,"") | I27: =IFERROR(VLOOKUP($D27,BS연결,MATCH(I$1,BS연결H,0),0)/100,"") | J27: =IFERROR(VLOOKUP($D27,BS연결,MATCH(J$1,BS연결H,0),0)/100,"") | K27: =IFERROR(VLOOKUP($D27,BS연결,MATCH(K$1,BS연결H,0),0)/100,"") | L27: =IFERROR(VLOOKUP($D27,BS연결,MATCH(L$1,BS연결H,0),0)/100,"") | ... AB27: =IFERROR(VLOOKUP($D27,BS연결,MATCH(AB$1,BS연결H,0),0)/100,"") | AC27: =IFERROR(AB27*(1+변수!AC35),"") | AD27: =IFERROR(AC27*(1+변수!AD35),"") | AE27: =AD27 | AF27: =IFERROR(AD27*(1+변수!AF35),"") | AG27: =IFERROR(AF27*(1+변수!AG35),"") | AH27: =IFERROR(AG27*(1+변수!AH35),"") | AI27: =IFERROR(AH27*(1+변수!AI35),"") | AJ27: =AI27 | AK27: =IFERROR(AI27*(1+변수!AK35),"") | AL27: =IFERROR(AK27*(1+변수!AL35),"") | AM27: =IFERROR(AL27*(1+변수!AM35),"") | AN27: =IFERROR(AM27*(1+변수!AN35),"") | AO27: =AN27
A28: 현금및현금성자산 | B28: 재무상태 | C28: 억원 | D28: 현금및현금성자산 | E28: =IFERROR(VLOOKUP($D28,BS연결,MATCH(E$1,BS연결H,0),0)/100,"") | F28: =IFERROR(VLOOKUP($D28,BS연결,MATCH(F$1,BS연결H,0),0)/100,"") | G28: =IFERROR(VLOOKUP($D28,BS연결,MATCH(G$1,BS연결H,0),0)/100,"") | H28: =IFERROR(VLOOKUP($D28,BS연결,MATCH(H$1,BS연결H,0),0)/100,"") | I28: =IFERROR(VLOOKUP($D28,BS연결,MATCH(I$1,BS연결H,0),0)/100,"") | J28: =IFERROR(VLOOKUP($D28,BS연결,MATCH(J$1,BS연결H,0),0)/100,"") | K28: =IFERROR(VLOOKUP($D28,BS연결,MATCH(K$1,BS연결H,0),0)/100,"") | L28: =IFERROR(VLOOKUP($D28,BS연결,MATCH(L$1,BS연결H,0),0)/100,"") | ... AB28: =IFERROR(VLOOKUP($D28,BS연결,MATCH(AB$1,BS연결H,0),0)/100,"") | AE28: =AD28 | AJ28: =AI28 | AO28: =AN28
A29: CAPEX | B29: 현금흐름 | C29: 억원 | D29: CAPEX | E29: =IFERROR(VLOOKUP($D29,BS연결,MATCH(E$1,BS연결H,0),0)/100,"") | G29: =IFERROR(VLOOKUP($D29,BS연결,MATCH(G$1,BS연결H,0),0)/100,"") | H29: =IFERROR(VLOOKUP($D29,BS연결,MATCH(H$1,BS연결H,0),0)/100,"") | I29: =IFERROR(VLOOKUP($D29,BS연결,MATCH(I$1,BS연결H,0),0)/100,"") | J29: =IFERROR(VLOOKUP($D29,BS연결,MATCH(J$1,BS연결H,0),0)/100,"") | K29: =IFERROR(VLOOKUP($D29,BS연결,MATCH(K$1,BS연결H,0),0)/100,"") | L29: =IFERROR(VLOOKUP($D29,BS연결,MATCH(L$1,BS연결H,0),0)/100,"") | M29: =IFERROR(VLOOKUP($D29,BS연결,MATCH(M$1,BS연결H,0),0)/100,"") | N29: =IFERROR(VLOOKUP($D29,BS연결,MATCH(N$1,BS연결H,0),0)/100,"") | ... S29: =IFERROR(VLOOKUP($D29,BS연결,MATCH(S$1,BS연결H,0),0)/100,"") | U29: =SUM(Q29:T29) | V29: =IFERROR(VLOOKUP($D29,BS연결,MATCH(V$1,BS연결H,0),0)/100,"") | W29: =IFERROR(VLOOKUP($D29,BS연결,MATCH(W$1,BS연결H,0),0)/100,"") | X29: =IFERROR(VLOOKUP($D29,BS연결,MATCH(X$1,BS연결H,0),0)/100,"") | Y29: =IFERROR(VLOOKUP($D29,BS연결,MATCH(Y$1,BS연결H,0),0)/100,"") | Z29: =IFERROR(VLOOKUP($D29,BS연결,MATCH(Z$1,BS연결H,0),0)/100,"") | AA29: =IFERROR(VLOOKUP($D29,BS연결,MATCH(AA$1,BS연결H,0),0)/100,"") | AB29: =IFERROR(VLOOKUP($D29,BS연결,MATCH(AB$1,BS연결H,0),0)/100,"") | AC29: =IFERROR(X29*(1+변수!AC37),"") | AD29: =IFERROR(Y29*(1+변수!AD37),"") | AE29: =SUM(AA29:AD29) | AF29: =IFERROR(AA29*(1+변수!AF37),"") | AG29: =IFERROR(AB29*(1+변수!AG37),"") | AH29: =IFERROR(AC29*(1+변수!AH37),"") | AI29: =IFERROR(AD29*(1+변수!AI37),"") | AJ29: =SUM(AF29:AI29) | AK29: =IFERROR(AF29*(1+변수!AK37),"") | AL29: =IFERROR(AG29*(1+변수!AL37),"") | AM29: =IFERROR(AH29*(1+변수!AM37),"") | AN29: =IFERROR(AI29*(1+변수!AN37),"") | AO29: =SUM(AK29:AN29)
A30: 영업활동현금흐름 | B30: 현금흐름 | C30: 억원 | D30: 영업활동으로인한현금흐름 | E30: =IFERROR(VLOOKUP($D30,BS연결,MATCH(E$1,BS연결H,0),0)/100,"") | G30: =IFERROR(VLOOKUP($D30,BS연결,MATCH(G$1,BS연결H,0),0)/100,"") | H30: =IFERROR(VLOOKUP($D30,BS연결,MATCH(H$1,BS연결H,0),0)/100,"") | I30: =IFERROR(VLOOKUP($D30,BS연결,MATCH(I$1,BS연결H,0),0)/100,"") | J30: =IFERROR(VLOOKUP($D30,BS연결,MATCH(J$1,BS연결H,0),0)/100,"") | K30: =IFERROR(VLOOKUP($D30,BS연결,MATCH(K$1,BS연결H,0),0)/100,"") | L30: =IFERROR(VLOOKUP($D30,BS연결,MATCH(L$1,BS연결H,0),0)/100,"") | M30: =IFERROR(VLOOKUP($D30,BS연결,MATCH(M$1,BS연결H,0),0)/100,"") | N30: =IFERROR(VLOOKUP($D30,BS연결,MATCH(N$1,BS연결H,0),0)/100,"") | ... AB30: =IFERROR(VLOOKUP($D30,BS연결,MATCH(AB$1,BS연결H,0),0)/100,"") | AE30: =SUM(AA30:AD30) | AJ30: =SUM(AF30:AI30) | AO30: =SUM(AK30:AN30)
A31: 주식수 | B31: 주당 | C31: 백만주 | D31: 유통주식수 | E31: 20.114 | F31: =E31 | G31: 20.114 | H31: 20.114 | I31: 20.114 | J31: 20.114 | K31: =J31 | L31: 20.114 | M31: 20.114 | N31: 20.114 | O31: 20.114 | P31: =O31 | Q31: 20.114 | R31: 20.114 | S31: 20.114 | T31: 20.114 | U31: =T31 | V31: 20.114 | W31: 20.114 | X31: 20.114 | Y31: 20.114 | Z31: =Y31 | AA31: 20.114 | AB31: 20.114 | AC31: =IFERROR(AB31*(1+변수!AC39),"") | AD31: =IFERROR(AC31*(1+변수!AD39),"") | AE31: =AD31 | AF31: =IFERROR(AD31*(1+변수!AF39),"") | AG31: =IFERROR(AF31*(1+변수!AG39),"") | AH31: =IFERROR(AG31*(1+변수!AH39),"") | AI31: =IFERROR(AH31*(1+변수!AI39),"") | AJ31: =AI31 | AK31: =IFERROR(AI31*(1+변수!AK39),"") | AL31: =IFERROR(AK31*(1+변수!AL39),"") | AM31: =IFERROR(AL31*(1+변수!AM39),"") | AN31: =IFERROR(AM31*(1+변수!AN39),"") | AO31: =AN31
A32: EPS | B32: 주당 | C32: 원 | D32: EPS | E32: =IFERROR(E20*100/E31,"") | G32: =IFERROR(G20*100/G31,"") | H32: =IFERROR(H20*100/H31,"") | I32: =IFERROR(I20*100/I31,"") | J32: =IFERROR(J20*100/J31,"") | K32: =SUM(G32:J32) | L32: =IFERROR(L20*100/L31,"") | M32: =IFERROR(M20*100/M31,"") | N32: =IFERROR(N20*100/N31,"") | O32: =IFERROR(O20*100/O31,"") | P32: =SUM(L32:O32) | Q32: =IFERROR(Q20*100/Q31,"") | R32: =IFERROR(R20*100/R31,"") | S32: =IFERROR(S20*100/S31,"") | T32: =IFERROR(T20*100/T31,"") | U32: =SUM(Q32:T32) | V32: =IFERROR(V20*100/V31,"") | W32: =IFERROR(W20*100/W31,"") | X32: =IFERROR(X20*100/X31,"") | Y32: =IFERROR(Y20*100/Y31,"") | Z32: =SUM(V32:Y32) | AA32: =IFERROR(AA20*100/AA31,"") | AB32: =IFERROR(AB20*100/AB31,"") | AC32: =IFERROR(AC20*100/AC31,"") | AD32: =IFERROR(AD20*100/AD31,"") | AE32: =SUM(AA32:AD32) | AF32: =IFERROR(AF20*100/AF31,"") | AG32: =IFERROR(AG20*100/AG31,"") | AH32: =IFERROR(AH20*100/AH31,"") | AI32: =IFERROR(AI20*100/AI31,"") | AJ32: =SUM(AF32:AI32) | AK32: =IFERROR(AK20*100/AK31,"") | AL32: =IFERROR(AL20*100/AL31,"") | AM32: =IFERROR(AM20*100/AM31,"") | AN32: =IFERROR(AN20*100/AN31,"") | AO32: =SUM(AK32:AN32)
A33: BPS | B33: 주당 | C33: 원 | D33: BPS | E33: =IFERROR(E24*100/E31,"") | F33: =E33 | G33: =IFERROR(G24*100/G31,"") | H33: =IFERROR(H24*100/H31,"") | I33: =IFERROR(I24*100/I31,"") | J33: =IFERROR(J24*100/J31,"") | K33: =J33 | L33: =IFERROR(L24*100/L31,"") | M33: =IFERROR(M24*100/M31,"") | N33: =IFERROR(N24*100/N31,"") | O33: =IFERROR(O24*100/O31,"") | P33: =O33 | Q33: =IFERROR(Q24*100/Q31,"") | R33: =IFERROR(R24*100/R31,"") | S33: =IFERROR(S24*100/S31,"") | T33: =IFERROR(T24*100/T31,"") | U33: =T33 | V33: =IFERROR(V24*100/V31,"") | W33: =IFERROR(W24*100/W31,"") | X33: =IFERROR(X24*100/X31,"") | Y33: =IFERROR(Y24*100/Y31,"") | Z33: =Y33 | AA33: =IFERROR(AA24*100/AA31,"") | AB33: =IFERROR(AB24*100/AB31,"") | AC33: =IFERROR(AC24*100/AC31,"") | AD33: =IFERROR(AD24*100/AD31,"") | AE33: =AD33 | AF33: =IFERROR(AF24*100/AF31,"") | AG33: =IFERROR(AG24*100/AG31,"") | AH33: =IFERROR(AH24*100/AH31,"") | AI33: =IFERROR(AI24*100/AI31,"") | AJ33: =AI33 | AK33: =IFERROR(AK24*100/AK31,"") | AL33: =IFERROR(AL24*100/AL31,"") | AM33: =IFERROR(AM24*100/AM31,"") | AN33: =IFERROR(AN24*100/AN31,"") | AO33: =AN33
A34: DPS | B34: 주당 | C34: 원 | D34: DPS(보통주) | E34: 100 | F34: 100 | J34: 0 | K34: =SUM(G34:J34) | O34: 0 | P34: =SUM(L34:O34) | T34: 130 | U34: =SUM(Q34:T34) | Y34: 130 | Z34: =SUM(V34:Y34) | AD34: =변수!AD40 | AE34: =SUM(AA34:AD34) | AI34: =변수!AI40 | AJ34: =SUM(AF34:AI34) | AN34: =변수!AN40 | AO34: =SUM(AK34:AN34)
A35: PER | B35: 주당 | C35: 배 | D35: PER | F35: =E35 | I35: =IFERROR(변수!I18/(E32+G32+H32+I32),"") | K35: =J35 | P35: =O35 | T35: =IFERROR(변수!T18/(Q32+R32+S32+T32),"") | U35: =T35 | V35: =IFERROR(변수!V18/(R32+S32+T32+V32),"") | W35: =IFERROR(변수!W18/(S32+T32+V32+W32),"") | X35: =IFERROR(변수!X18/(T32+V32+W32+X32),"") | Y35: =IFERROR(변수!Y18/(V32+W32+X32+Y32),"") | Z35: =Y35 | AA35: =IFERROR(변수!AA18/(W32+X32+Y32+AA32),"") | AB35: =IFERROR(변수!AB18/(X32+Y32+AA32+AB32),"") | AC35: =IFERROR(변수!$D$43/(Y32+AA32+AB32+AC32),"") | AD35: =IFERROR(변수!$D$43/(AA32+AB32+AC32+AD32),"") | AE35: =AD35 | AF35: =IFERROR(변수!$D$43/(AB32+AC32+AD32+AF32),"") | AG35: =IFERROR(변수!$D$43/(AC32+AD32+AF32+AG32),"") | AH35: =IFERROR(변수!$D$43/(AD32+AF32+AG32+AH32),"") | AI35: =IFERROR(변수!$D$43/(AF32+AG32+AH32+AI32),"") | AJ35: =AI35 | AK35: =IFERROR(변수!$D$43/(AG32+AH32+AI32+AK32),"") | AL35: =IFERROR(변수!$D$43/(AH32+AI32+AK32+AL32),"") | AM35: =IFERROR(변수!$D$43/(AI32+AK32+AL32+AM32),"") | AN35: =IFERROR(변수!$D$43/(AK32+AL32+AM32+AN32),"") | AO35: =AN35
A36: PBR | B36: 주당 | C36: 배 | D36: PBR | E36: =IFERROR(변수!E18/E33,"") | F36: =E36 | G36: =IFERROR(변수!G18/G33,"") | H36: =IFERROR(변수!H18/H33,"") | I36: =IFERROR(변수!I18/I33,"") | J36: =IFERROR(변수!J18/J33,"") | K36: =J36 | L36: =IFERROR(변수!L18/L33,"") | M36: =IFERROR(변수!M18/M33,"") | N36: =IFERROR(변수!N18/N33,"") | O36: =IFERROR(변수!O18/O33,"") | P36: =O36 | Q36: =IFERROR(변수!Q18/Q33,"") | R36: =IFERROR(변수!R18/R33,"") | S36: =IFERROR(변수!S18/S33,"") | T36: =IFERROR(변수!T18/T33,"") | U36: =T36 | V36: =IFERROR(변수!V18/V33,"") | W36: =IFERROR(변수!W18/W33,"") | X36: =IFERROR(변수!X18/X33,"") | Y36: =IFERROR(변수!Y18/Y33,"") | Z36: =Y36 | AA36: =IFERROR(변수!AA18/AA33,"") | AB36: =IFERROR(변수!AB18/AB33,"") | AC36: =IFERROR(변수!$D$43/AC33,"") | AD36: =IFERROR(변수!$D$43/AD33,"") | AE36: =AD36 | AF36: =IFERROR(변수!$D$43/AF33,"") | AG36: =IFERROR(변수!$D$43/AG33,"") | AH36: =IFERROR(변수!$D$43/AH33,"") | AI36: =IFERROR(변수!$D$43/AI33,"") | AJ36: =AI36 | AK36: =IFERROR(변수!$D$43/AK33,"") | AL36: =IFERROR(변수!$D$43/AL33,"") | AM36: =IFERROR(변수!$D$43/AM33,"") | AN36: =IFERROR(변수!$D$43/AN33,"") | AO36: =AN36
A37: 매출전사 | B37: 사업부 | C37: 억원 | D37: 매출 전사(부문 미분리) | E37: 3718.79 | G37: 3687.55 | H37: 3600.72 | I37: 3642.82 | J37: 4025.92 | K37: =SUM(G37:J37) | L37: 3702.19 | M37: 3986.71 | N37: 3966.14 | O37: 4202 | P37: =SUM(L37:O37) | Q37: 5047.87 | R37: 4969.57 | S37: 4541.15 | T37: 4147.98 | U37: =SUM(Q37:T37) | V37: 4377.6 | W37: 4098.71 | X37: 3406.55 | Y37: 3579.2 | Z37: =SUM(V37:Y37) | AA37: 3559.35 | AB37: 3731.33 | AC37: =IFERROR(AC5,"") | AD37: =IFERROR(AD5,"") | AE37: =SUM(AA37:AD37) | AF37: =IFERROR(AF5,"") | AG37: =IFERROR(AG5,"") | AH37: =IFERROR(AH5,"") | AI37: =IFERROR(AI5,"") | AJ37: =SUM(AF37:AI37) | AK37: =IFERROR(AK5,"") | AL37: =IFERROR(AL5,"") | AM37: =IFERROR(AM5,"") | AN37: =IFERROR(AN5,"") | AO37: =SUM(AK37:AN37)
A38: OP전사 | B38: 사업부 | C38: 억원 | D38: OP 전사(부문 미분리) | E38: 13.27 | G38: 29.16 | H38: -2.86 | I38: 5.1 | J38: -310.35 | K38: =SUM(G38:J38) | L38: -76.05 | M38: 34.76 | N38: 12.49 | O38: -169.72 | P38: =SUM(L38:O38) | Q38: 67.99 | R38: 81.7 | S38: 97.64 | T38: -6.96 | U38: =SUM(Q38:T38) | V38: 95.12 | W38: 50.8 | X38: 37.37 | Y38: -26.11 | Z38: =SUM(V38:Y38) | AA38: 10.53 | AB38: 55.59 | AC38: =IFERROR(AC9,"") | AD38: =IFERROR(AD9,"") | AE38: =SUM(AA38:AD38) | AF38: =IFERROR(AF9,"") | AG38: =IFERROR(AG9,"") | AH38: =IFERROR(AH9,"") | AI38: =IFERROR(AI9,"") | AJ38: =SUM(AF38:AI38) | AK38: =IFERROR(AK9,"") | AL38: =IFERROR(AL9,"") | AM38: =IFERROR(AM9,"") | AN38: =IFERROR(AN9,"") | AO38: =SUM(AK38:AN38)
B39: 비율(참고)
A40: NPM | C40: % | D40: 지배주주순이익 / 매출액 | E40: =IFERROR(E20/E5,"") | F40: =IFERROR(F20/F5,"") | G40: =IFERROR(G20/G5,"") | H40: =IFERROR(H20/H5,"") | I40: =IFERROR(I20/I5,"") | J40: =IFERROR(J20/J5,"") | K40: =IFERROR(K20/K5,"") | L40: =IFERROR(L20/L5,"") | ... AO40: =IFERROR(AO20/AO5,"")
A41: 매출원가율 | C41: % | D41: 매출원가 / 매출액 | E41: =IFERROR(E6/E5,"") | F41: =IFERROR(F6/F5,"") | G41: =IFERROR(G6/G5,"") | H41: =IFERROR(H6/H5,"") | I41: =IFERROR(I6/I5,"") | J41: =IFERROR(J6/J5,"") | K41: =IFERROR(K6/K5,"") | L41: =IFERROR(L6/L5,"") | ... AO41: =IFERROR(AO6/AO5,"")
A42: 판관비율 | C42: % | D42: 판관비 / 매출액 | E42: =IFERROR(E8/E5,"") | F42: =IFERROR(F8/F5,"") | G42: =IFERROR(G8/G5,"") | H42: =IFERROR(H8/H5,"") | I42: =IFERROR(I8/I5,"") | J42: =IFERROR(J8/J5,"") | K42: =IFERROR(K8/K5,"") | L42: =IFERROR(L8/L5,"") | ... AO42: =IFERROR(AO8/AO5,"")

Sheet 분기
C1: 이름: 분기H — subQ 를 이름으로 VLOOKUP(억원) | E1: 4Q21 | F1: 1Q22 | G1: 2Q22 | H1: 3Q22 | I1: 4Q22 | J1: 1Q23 | K1: 2Q23 | L1: 3Q23 | M1: 4Q23 | N1: 1Q24 | O1: 2Q24 | P1: 3Q24 | Q1: 4Q24 | R1: 1Q25 | S1: 2Q25 | T1: 3Q25 | U1: 4Q25 | V1: 1Q26 | W1: 2Q26 | X1: 3Q26 | Y1: 4Q26 | Z1: 1Q27 | AA1: 2Q27 | AB1: 3Q27 | AC1: 4Q27 | AD1: 1Q28 | AE1: 2Q28 | AF1: 3Q28 | AG1: 4Q28
C2: 종가: | D2: =변수!D43
C3: 기준일: | D3: 20261008 | E3: 1 | F3: 2 | G3: 3 | H3: 4 | I3: 5 | J3: 6 | K3: 7 | L3: 8 | M3: 9 | N3: 10 | O3: 11 | P3: 12 | Q3: 13 | R3: 14 | S3: 15 | T3: 16 | U3: 17 | V3: 18 | W3: 19 | X3: 20 | Y3: 21 | Z3: 22 | AA3: 23 | AB3: 24 | AC3: 25 | AD3: 26 | AE3: 27 | AF3: 28 | AG3: 29
E4: 2021.12 | F4: 2022.03 | G4: 2022.06 | H4: 2022.09 | I4: 2022.12 | J4: 2023.03 | K4: 2023.06 | L4: 2023.09 | M4: 2023.12 | N4: 2024.03 | O4: 2024.06 | P4: 2024.09 | Q4: 2024.12 | R4: 2025.03 | S4: 2025.06 | T4: 2025.09 | U4: 2025.12 | V4: 2026.03 | W4: 2026.06 | X4: 2026.09 | Y4: 2026.12 | Z4: 2027.03 | AA4: 2027.06 | AB4: 2027.09 | AC4: 2027.12 | AD4: 2028.03 | AE4: 2028.06 | AF4: 2028.09 | AG4: 2028.12
A5: 매출액 | D5: 매출액 | E5: =IFERROR(VLOOKUP($A5,subQ,MATCH(E$1,SUBQH,0),0),"") | F5: =IFERROR(VLOOKUP($A5,subQ,MATCH(F$1,SUBQH,0),0),"") | G5: =IFERROR(VLOOKUP($A5,subQ,MATCH(G$1,SUBQH,0),0),"") | H5: =IFERROR(VLOOKUP($A5,subQ,MATCH(H$1,SUBQH,0),0),"") | I5: =IFERROR(VLOOKUP($A5,subQ,MATCH(I$1,SUBQH,0),0),"") | J5: =IFERROR(VLOOKUP($A5,subQ,MATCH(J$1,SUBQH,0),0),"") | K5: =IFERROR(VLOOKUP($A5,subQ,MATCH(K$1,SUBQH,0),0),"") | L5: =IFERROR(VLOOKUP($A5,subQ,MATCH(L$1,SUBQH,0),0),"") | ... AG5: =IFERROR(VLOOKUP($A5,subQ,MATCH(AG$1,SUBQH,0),0),"")
A6: 매출원가 | D6: 매출원가 | E6: =IFERROR(VLOOKUP($A6,subQ,MATCH(E$1,SUBQH,0),0),"") | F6: =IFERROR(VLOOKUP($A6,subQ,MATCH(F$1,SUBQH,0),0),"") | G6: =IFERROR(VLOOKUP($A6,subQ,MATCH(G$1,SUBQH,0),0),"") | H6: =IFERROR(VLOOKUP($A6,subQ,MATCH(H$1,SUBQH,0),0),"") | I6: =IFERROR(VLOOKUP($A6,subQ,MATCH(I$1,SUBQH,0),0),"") | J6: =IFERROR(VLOOKUP($A6,subQ,MATCH(J$1,SUBQH,0),0),"") | K6: =IFERROR(VLOOKUP($A6,subQ,MATCH(K$1,SUBQH,0),0),"") | L6: =IFERROR(VLOOKUP($A6,subQ,MATCH(L$1,SUBQH,0),0),"") | ... AG6: =IFERROR(VLOOKUP($A6,subQ,MATCH(AG$1,SUBQH,0),0),"")
A7: 매출총이익 | D7: 매출총이익 | E7: =IFERROR(VLOOKUP($A7,subQ,MATCH(E$1,SUBQH,0),0),"") | F7: =IFERROR(VLOOKUP($A7,subQ,MATCH(F$1,SUBQH,0),0),"") | G7: =IFERROR(VLOOKUP($A7,subQ,MATCH(G$1,SUBQH,0),0),"") | H7: =IFERROR(VLOOKUP($A7,subQ,MATCH(H$1,SUBQH,0),0),"") | I7: =IFERROR(VLOOKUP($A7,subQ,MATCH(I$1,SUBQH,0),0),"") | J7: =IFERROR(VLOOKUP($A7,subQ,MATCH(J$1,SUBQH,0),0),"") | K7: =IFERROR(VLOOKUP($A7,subQ,MATCH(K$1,SUBQH,0),0),"") | L7: =IFERROR(VLOOKUP($A7,subQ,MATCH(L$1,SUBQH,0),0),"") | ... AG7: =IFERROR(VLOOKUP($A7,subQ,MATCH(AG$1,SUBQH,0),0),"")
A8: 판관비 | D8: 판매비와관리비 | E8: =IFERROR(VLOOKUP($A8,subQ,MATCH(E$1,SUBQH,0),0),"") | F8: =IFERROR(VLOOKUP($A8,subQ,MATCH(F$1,SUBQH,0),0),"") | G8: =IFERROR(VLOOKUP($A8,subQ,MATCH(G$1,SUBQH,0),0),"") | H8: =IFERROR(VLOOKUP($A8,subQ,MATCH(H$1,SUBQH,0),0),"") | I8: =IFERROR(VLOOKUP($A8,subQ,MATCH(I$1,SUBQH,0),0),"") | J8: =IFERROR(VLOOKUP($A8,subQ,MATCH(J$1,SUBQH,0),0),"") | K8: =IFERROR(VLOOKUP($A8,subQ,MATCH(K$1,SUBQH,0),0),"") | L8: =IFERROR(VLOOKUP($A8,subQ,MATCH(L$1,SUBQH,0),0),"") | ... AG8: =IFERROR(VLOOKUP($A8,subQ,MATCH(AG$1,SUBQH,0),0),"")
A9: 영업이익 | D9: 영업이익 | E9: =IFERROR(VLOOKUP($A9,subQ,MATCH(E$1,SUBQH,0),0),"") | F9: =IFERROR(VLOOKUP($A9,subQ,MATCH(F$1,SUBQH,0),0),"") | G9: =IFERROR(VLOOKUP($A9,subQ,MATCH(G$1,SUBQH,0),0),"") | H9: =IFERROR(VLOOKUP($A9,subQ,MATCH(H$1,SUBQH,0),0),"") | I9: =IFERROR(VLOOKUP($A9,subQ,MATCH(I$1,SUBQH,0),0),"") | J9: =IFERROR(VLOOKUP($A9,subQ,MATCH(J$1,SUBQH,0),0),"") | K9: =IFERROR(VLOOKUP($A9,subQ,MATCH(K$1,SUBQH,0),0),"") | L9: =IFERROR(VLOOKUP($A9,subQ,MATCH(L$1,SUBQH,0),0),"") | ... AG9: =IFERROR(VLOOKUP($A9,subQ,MATCH(AG$1,SUBQH,0),0),"")
A10: OPM | D10: 영업이익률 | E10: =IFERROR(VLOOKUP($A10,subQ,MATCH(E$1,SUBQH,0),0),"") | F10: =IFERROR(VLOOKUP($A10,subQ,MATCH(F$1,SUBQH,0),0),"") | G10: =IFERROR(VLOOKUP($A10,subQ,MATCH(G$1,SUBQH,0),0),"") | H10: =IFERROR(VLOOKUP($A10,subQ,MATCH(H$1,SUBQH,0),0),"") | I10: =IFERROR(VLOOKUP($A10,subQ,MATCH(I$1,SUBQH,0),0),"") | J10: =IFERROR(VLOOKUP($A10,subQ,MATCH(J$1,SUBQH,0),0),"") | K10: =IFERROR(VLOOKUP($A10,subQ,MATCH(K$1,SUBQH,0),0),"") | L10: =IFERROR(VLOOKUP($A10,subQ,MATCH(L$1,SUBQH,0),0),"") | ... AG10: =IFERROR(VLOOKUP($A10,subQ,MATCH(AG$1,SUBQH,0),0),"")
A11: 금융손익 | D11: 금융손익(이자·환 포함) | E11: =IFERROR(VLOOKUP($A11,subQ,MATCH(E$1,SUBQH,0),0),"") | F11: =IFERROR(VLOOKUP($A11,subQ,MATCH(F$1,SUBQH,0),0),"") | G11: =IFERROR(VLOOKUP($A11,subQ,MATCH(G$1,SUBQH,0),0),"") | H11: =IFERROR(VLOOKUP($A11,subQ,MATCH(H$1,SUBQH,0),0),"") | I11: =IFERROR(VLOOKUP($A11,subQ,MATCH(I$1,SUBQH,0),0),"") | J11: =IFERROR(VLOOKUP($A11,subQ,MATCH(J$1,SUBQH,0),0),"") | K11: =IFERROR(VLOOKUP($A11,subQ,MATCH(K$1,SUBQH,0),0),"") | L11: =IFERROR(VLOOKUP($A11,subQ,MATCH(L$1,SUBQH,0),0),"") | ... AG11: =IFERROR(VLOOKUP($A11,subQ,MATCH(AG$1,SUBQH,0),0),"")
A12: 이자손익 | D12: 이자손익(이자수익 − 이자비용) | E12: =IFERROR(VLOOKUP($A12,subQ,MATCH(E$1,SUBQH,0),0),"") | F12: =IFERROR(VLOOKUP($A12,subQ,MATCH(F$1,SUBQH,0),0),"") | G12: =IFERROR(VLOOKUP($A12,subQ,MATCH(G$1,SUBQH,0),0),"") | H12: =IFERROR(VLOOKUP($A12,subQ,MATCH(H$1,SUBQH,0),0),"") | I12: =IFERROR(VLOOKUP($A12,subQ,MATCH(I$1,SUBQH,0),0),"") | J12: =IFERROR(VLOOKUP($A12,subQ,MATCH(J$1,SUBQH,0),0),"") | K12: =IFERROR(VLOOKUP($A12,subQ,MATCH(K$1,SUBQH,0),0),"") | L12: =IFERROR(VLOOKUP($A12,subQ,MATCH(L$1,SUBQH,0),0),"") | ... AG12: =IFERROR(VLOOKUP($A12,subQ,MATCH(AG$1,SUBQH,0),0),"")
A13: 외환손익 | D13: 외환손익(실적만; 추정 환효과는 환관련손익) | E13: =IFERROR(VLOOKUP($A13,subQ,MATCH(E$1,SUBQH,0),0),"") | F13: =IFERROR(VLOOKUP($A13,subQ,MATCH(F$1,SUBQH,0),0),"") | G13: =IFERROR(VLOOKUP($A13,subQ,MATCH(G$1,SUBQH,0),0),"") | H13: =IFERROR(VLOOKUP($A13,subQ,MATCH(H$1,SUBQH,0),0),"") | I13: =IFERROR(VLOOKUP($A13,subQ,MATCH(I$1,SUBQH,0),0),"") | J13: =IFERROR(VLOOKUP($A13,subQ,MATCH(J$1,SUBQH,0),0),"") | K13: =IFERROR(VLOOKUP($A13,subQ,MATCH(K$1,SUBQH,0),0),"") | L13: =IFERROR(VLOOKUP($A13,subQ,MATCH(L$1,SUBQH,0),0),"") | ... AG13: =IFERROR(VLOOKUP($A13,subQ,MATCH(AG$1,SUBQH,0),0),"")
A14: 파생상품손익 | D14: 파생상품손익 | E14: =IFERROR(VLOOKUP($A14,subQ,MATCH(E$1,SUBQH,0),0),"") | F14: =IFERROR(VLOOKUP($A14,subQ,MATCH(F$1,SUBQH,0),0),"") | G14: =IFERROR(VLOOKUP($A14,subQ,MATCH(G$1,SUBQH,0),0),"") | H14: =IFERROR(VLOOKUP($A14,subQ,MATCH(H$1,SUBQH,0),0),"") | I14: =IFERROR(VLOOKUP($A14,subQ,MATCH(I$1,SUBQH,0),0),"") | J14: =IFERROR(VLOOKUP($A14,subQ,MATCH(J$1,SUBQH,0),0),"") | K14: =IFERROR(VLOOKUP($A14,subQ,MATCH(K$1,SUBQH,0),0),"") | L14: =IFERROR(VLOOKUP($A14,subQ,MATCH(L$1,SUBQH,0),0),"") | ... AG14: =IFERROR(VLOOKUP($A14,subQ,MATCH(AG$1,SUBQH,0),0),"")
A15: 기타금융손익 | D15: 기타금융손익(금융손익 잔차) | E15: =IFERROR(VLOOKUP($A15,subQ,MATCH(E$1,SUBQH,0),0),"") | F15: =IFERROR(VLOOKUP($A15,subQ,MATCH(F$1,SUBQH,0),0),"") | G15: =IFERROR(VLOOKUP($A15,subQ,MATCH(G$1,SUBQH,0),0),"") | H15: =IFERROR(VLOOKUP($A15,subQ,MATCH(H$1,SUBQH,0),0),"") | I15: =IFERROR(VLOOKUP($A15,subQ,MATCH(I$1,SUBQH,0),0),"") | J15: =IFERROR(VLOOKUP($A15,subQ,MATCH(J$1,SUBQH,0),0),"") | K15: =IFERROR(VLOOKUP($A15,subQ,MATCH(K$1,SUBQH,0),0),"") | L15: =IFERROR(VLOOKUP($A15,subQ,MATCH(L$1,SUBQH,0),0),"") | ... AG15: =IFERROR(VLOOKUP($A15,subQ,MATCH(AG$1,SUBQH,0),0),"")
A16: 기타영업외손익 | D16: 기타영업외손익 | E16: =IFERROR(VLOOKUP($A16,subQ,MATCH(E$1,SUBQH,0),0),"") | F16: =IFERROR(VLOOKUP($A16,subQ,MATCH(F$1,SUBQH,0),0),"") | G16: =IFERROR(VLOOKUP($A16,subQ,MATCH(G$1,SUBQH,0),0),"") | H16: =IFERROR(VLOOKUP($A16,subQ,MATCH(H$1,SUBQH,0),0),"") | I16: =IFERROR(VLOOKUP($A16,subQ,MATCH(I$1,SUBQH,0),0),"") | J16: =IFERROR(VLOOKUP($A16,subQ,MATCH(J$1,SUBQH,0),0),"") | K16: =IFERROR(VLOOKUP($A16,subQ,MATCH(K$1,SUBQH,0),0),"") | L16: =IFERROR(VLOOKUP($A16,subQ,MATCH(L$1,SUBQH,0),0),"") | ... AG16: =IFERROR(VLOOKUP($A16,subQ,MATCH(AG$1,SUBQH,0),0),"")
... A39: NPM | D39: NPM | E39: =IFERROR(VLOOKUP($A39,subQ,MATCH(E$1,SUBQH,0),0),"") | F39: =IFERROR(VLOOKUP($A39,subQ,MATCH(F$1,SUBQH,0),0),"") | G39: =IFERROR(VLOOKUP($A39,subQ,MATCH(G$1,SUBQH,0),0),"") | H39: =IFERROR(VLOOKUP($A39,subQ,MATCH(H$1,SUBQH,0),0),"") | I39: =IFERROR(VLOOKUP($A39,subQ,MATCH(I$1,SUBQH,0),0),"") | J39: =IFERROR(VLOOKUP($A39,subQ,MATCH(J$1,SUBQH,0),0),"") | K39: =IFERROR(VLOOKUP($A39,subQ,MATCH(K$1,SUBQH,0),0),"") | L39: =IFERROR(VLOOKUP($A39,subQ,MATCH(L$1,SUBQH,0),0),"") | ... AG39: =IFERROR(VLOOKUP($A39,subQ,MATCH(AG$1,SUBQH,0),0),"")
A40: 매출액 YoY | D40: 매출액 YoY | I40: =IFERROR(I5/E5-1,"") | J40: =IFERROR(J5/F5-1,"") | K40: =IFERROR(K5/G5-1,"") | L40: =IFERROR(L5/H5-1,"") | M40: =IFERROR(M5/I5-1,"") | N40: =IFERROR(N5/J5-1,"") | O40: =IFERROR(O5/K5-1,"") | P40: =IFERROR(P5/L5-1,"") | ... AG40: =IFERROR(AG5/AC5-1,"")
A41: 영업이익 YoY | D41: 영업이익 YoY | I41: =IFERROR(I9/E9-1,"") | J41: =IFERROR(J9/F9-1,"") | K41: =IFERROR(K9/G9-1,"") | L41: =IFERROR(L9/H9-1,"") | M41: =IFERROR(M9/I9-1,"") | N41: =IFERROR(N9/J9-1,"") | O41: =IFERROR(O9/K9-1,"") | P41: =IFERROR(P9/L9-1,"") | ... AG41: =IFERROR(AG9/AC9-1,"")
A42: 지배주주순이익 YoY | D42: 지배주주순이익 YoY | I42: =IFERROR(I20/E20-1,"") | J42: =IFERROR(J20/F20-1,"") | K42: =IFERROR(K20/G20-1,"") | L42: =IFERROR(L20/H20-1,"") | M42: =IFERROR(M20/I20-1,"") | N42: =IFERROR(N20/J20-1,"") | O42: =IFERROR(O20/K20-1,"") | P42: =IFERROR(P20/L20-1,"") | ... AG42: =IFERROR(AG20/AC20-1,"")

Sheet 연간예상
C1: 이름: 연간예상H — subQ 를 이름으로 VLOOKUP(억원) | E1: 2021 | F1: 2022 | G1: 2023 | H1: 2024 | I1: 2025 | J1: 2026 | K1: 2027 | L1: 2028
C2: 종가: | D2: =변수!D43
C3: 기준일: | D3: 20261008 | E3: 1 | F3: 2 | G3: 3 | H3: 4 | I3: 5 | J3: 6 | K3: 7 | L3: 8
E4: 2021.12A | F4: 2022.12A | G4: 2023.12A | H4: 2024.12A | I4: 2025.12A | J4: 2026.12A | K4: 2027.12A | L4: 2028.12A
A5: 매출액 | D5: 매출액 | E5: =IFERROR(VLOOKUP($A5,subQ,MATCH(E$1,SUBQH,0),0),"") | F5: =IFERROR(VLOOKUP($A5,subQ,MATCH(F$1,SUBQH,0),0),"") | G5: =IFERROR(VLOOKUP($A5,subQ,MATCH(G$1,SUBQH,0),0),"") | H5: =IFERROR(VLOOKUP($A5,subQ,MATCH(H$1,SUBQH,0),0),"") | I5: =IFERROR(VLOOKUP($A5,subQ,MATCH(I$1,SUBQH,0),0),"") | J5: =IFERROR(VLOOKUP($A5,subQ,MATCH(J$1,SUBQH,0),0),"") | K5: =IFERROR(VLOOKUP($A5,subQ,MATCH(K$1,SUBQH,0),0),"") | L5: =IFERROR(VLOOKUP($A5,subQ,MATCH(L$1,SUBQH,0),0),"")
A6: 매출원가 | D6: 매출원가 | E6: =IFERROR(VLOOKUP($A6,subQ,MATCH(E$1,SUBQH,0),0),"") | F6: =IFERROR(VLOOKUP($A6,subQ,MATCH(F$1,SUBQH,0),0),"") | G6: =IFERROR(VLOOKUP($A6,subQ,MATCH(G$1,SUBQH,0),0),"") | H6: =IFERROR(VLOOKUP($A6,subQ,MATCH(H$1,SUBQH,0),0),"") | I6: =IFERROR(VLOOKUP($A6,subQ,MATCH(I$1,SUBQH,0),0),"") | J6: =IFERROR(VLOOKUP($A6,subQ,MATCH(J$1,SUBQH,0),0),"") | K6: =IFERROR(VLOOKUP($A6,subQ,MATCH(K$1,SUBQH,0),0),"") | L6: =IFERROR(VLOOKUP($A6,subQ,MATCH(L$1,SUBQH,0),0),"")
A7: 매출총이익 | D7: 매출총이익 | E7: =IFERROR(VLOOKUP($A7,subQ,MATCH(E$1,SUBQH,0),0),"") | F7: =IFERROR(VLOOKUP($A7,subQ,MATCH(F$1,SUBQH,0),0),"") | G7: =IFERROR(VLOOKUP($A7,subQ,MATCH(G$1,SUBQH,0),0),"") | H7: =IFERROR(VLOOKUP($A7,subQ,MATCH(H$1,SUBQH,0),0),"") | I7: =IFERROR(VLOOKUP($A7,subQ,MATCH(I$1,SUBQH,0),0),"") | J7: =IFERROR(VLOOKUP($A7,subQ,MATCH(J$1,SUBQH,0),0),"") | K7: =IFERROR(VLOOKUP($A7,subQ,MATCH(K$1,SUBQH,0),0),"") | L7: =IFERROR(VLOOKUP($A7,subQ,MATCH(L$1,SUBQH,0),0),"")
A8: 판관비 | D8: 판매비와관리비 | E8: =IFERROR(VLOOKUP($A8,subQ,MATCH(E$1,SUBQH,0),0),"") | F8: =IFERROR(VLOOKUP($A8,subQ,MATCH(F$1,SUBQH,0),0),"") | G8: =IFERROR(VLOOKUP($A8,subQ,MATCH(G$1,SUBQH,0),0),"") | H8: =IFERROR(VLOOKUP($A8,subQ,MATCH(H$1,SUBQH,0),0),"") | I8: =IFERROR(VLOOKUP($A8,subQ,MATCH(I$1,SUBQH,0),0),"") | J8: =IFERROR(VLOOKUP($A8,subQ,MATCH(J$1,SUBQH,0),0),"") | K8: =IFERROR(VLOOKUP($A8,subQ,MATCH(K$1,SUBQH,0),0),"") | L8: =IFERROR(VLOOKUP($A8,subQ,MATCH(L$1,SUBQH,0),0),"")
A9: 영업이익 | D9: 영업이익 | E9: =IFERROR(VLOOKUP($A9,subQ,MATCH(E$1,SUBQH,0),0),"") | F9: =IFERROR(VLOOKUP($A9,subQ,MATCH(F$1,SUBQH,0),0),"") | G9: =IFERROR(VLOOKUP($A9,subQ,MATCH(G$1,SUBQH,0),0),"") | H9: =IFERROR(VLOOKUP($A9,subQ,MATCH(H$1,SUBQH,0),0),"") | I9: =IFERROR(VLOOKUP($A9,subQ,MATCH(I$1,SUBQH,0),0),"") | J9: =IFERROR(VLOOKUP($A9,subQ,MATCH(J$1,SUBQH,0),0),"") | K9: =IFERROR(VLOOKUP($A9,subQ,MATCH(K$1,SUBQH,0),0),"") | L9: =IFERROR(VLOOKUP($A9,subQ,MATCH(L$1,SUBQH,0),0),"")
A10: OPM | D10: 영업이익률 | E10: =IFERROR(VLOOKUP($A10,subQ,MATCH(E$1,SUBQH,0),0),"") | F10: =IFERROR(VLOOKUP($A10,subQ,MATCH(F$1,SUBQH,0),0),"") | G10: =IFERROR(VLOOKUP($A10,subQ,MATCH(G$1,SUBQH,0),0),"") | H10: =IFERROR(VLOOKUP($A10,subQ,MATCH(H$1,SUBQH,0),0),"") | I10: =IFERROR(VLOOKUP($A10,subQ,MATCH(I$1,SUBQH,0),0),"") | J10: =IFERROR(VLOOKUP($A10,subQ,MATCH(J$1,SUBQH,0),0),"") | K10: =IFERROR(VLOOKUP($A10,subQ,MATCH(K$1,SUBQH,0),0),"") | L10: =IFERROR(VLOOKUP($A10,subQ,MATCH(L$1,SUBQH,0),0),"")
A11: 금융손익 | D11: 금융손익(이자·환 포함) | E11: =IFERROR(VLOOKUP($A11,subQ,MATCH(E$1,SUBQH,0),0),"") | F11: =IFERROR(VLOOKUP($A11,subQ,MATCH(F$1,SUBQH,0),0),"") | G11: =IFERROR(VLOOKUP($A11,subQ,MATCH(G$1,SUBQH,0),0),"") | H11: =IFERROR(VLOOKUP($A11,subQ,MATCH(H$1,SUBQH,0),0),"") | I11: =IFERROR(VLOOKUP($A11,subQ,MATCH(I$1,SUBQH,0),0),"") | J11: =IFERROR(VLOOKUP($A11,subQ,MATCH(J$1,SUBQH,0),0),"") | K11: =IFERROR(VLOOKUP($A11,subQ,MATCH(K$1,SUBQH,0),0),"") | L11: =IFERROR(VLOOKUP($A11,subQ,MATCH(L$1,SUBQH,0),0),"")
A12: 이자손익 | D12: 이자손익(이자수익 − 이자비용) | E12: =IFERROR(VLOOKUP($A12,subQ,MATCH(E$1,SUBQH,0),0),"") | F12: =IFERROR(VLOOKUP($A12,subQ,MATCH(F$1,SUBQH,0),0),"") | G12: =IFERROR(VLOOKUP($A12,subQ,MATCH(G$1,SUBQH,0),0),"") | H12: =IFERROR(VLOOKUP($A12,subQ,MATCH(H$1,SUBQH,0),0),"") | I12: =IFERROR(VLOOKUP($A12,subQ,MATCH(I$1,SUBQH,0),0),"") | J12: =IFERROR(VLOOKUP($A12,subQ,MATCH(J$1,SUBQH,0),0),"") | K12: =IFERROR(VLOOKUP($A12,subQ,MATCH(K$1,SUBQH,0),0),"") | L12: =IFERROR(VLOOKUP($A12,subQ,MATCH(L$1,SUBQH,0),0),"")
A13: 외환손익 | D13: 외환손익(실적만; 추정 환효과는 환관련손익) | E13: =IFERROR(VLOOKUP($A13,subQ,MATCH(E$1,SUBQH,0),0),"") | F13: =IFERROR(VLOOKUP($A13,subQ,MATCH(F$1,SUBQH,0),0),"") | G13: =IFERROR(VLOOKUP($A13,subQ,MATCH(G$1,SUBQH,0),0),"") | H13: =IFERROR(VLOOKUP($A13,subQ,MATCH(H$1,SUBQH,0),0),"") | I13: =IFERROR(VLOOKUP($A13,subQ,MATCH(I$1,SUBQH,0),0),"") | J13: =IFERROR(VLOOKUP($A13,subQ,MATCH(J$1,SUBQH,0),0),"") | K13: =IFERROR(VLOOKUP($A13,subQ,MATCH(K$1,SUBQH,0),0),"") | L13: =IFERROR(VLOOKUP($A13,subQ,MATCH(L$1,SUBQH,0),0),"")
A14: 파생상품손익 | D14: 파생상품손익 | E14: =IFERROR(VLOOKUP($A14,subQ,MATCH(E$1,SUBQH,0),0),"") | F14: =IFERROR(VLOOKUP($A14,subQ,MATCH(F$1,SUBQH,0),0),"") | G14: =IFERROR(VLOOKUP($A14,subQ,MATCH(G$1,SUBQH,0),0),"") | H14: =IFERROR(VLOOKUP($A14,subQ,MATCH(H$1,SUBQH,0),0),"") | I14: =IFERROR(VLOOKUP($A14,subQ,MATCH(I$1,SUBQH,0),0),"") | J14: =IFERROR(VLOOKUP($A14,subQ,MATCH(J$1,SUBQH,0),0),"") | K14: =IFERROR(VLOOKUP($A14,subQ,MATCH(K$1,SUBQH,0),0),"") | L14: =IFERROR(VLOOKUP($A14,subQ,MATCH(L$1,SUBQH,0),0),"")
A15: 기타금융손익 | D15: 기타금융손익(금융손익 잔차) | E15: =IFERROR(VLOOKUP($A15,subQ,MATCH(E$1,SUBQH,0),0),"") | F15: =IFERROR(VLOOKUP($A15,subQ,MATCH(F$1,SUBQH,0),0),"") | G15: =IFERROR(VLOOKUP($A15,subQ,MATCH(G$1,SUBQH,0),0),"") | H15: =IFERROR(VLOOKUP($A15,subQ,MATCH(H$1,SUBQH,0),0),"") | I15: =IFERROR(VLOOKUP($A15,subQ,MATCH(I$1,SUBQH,0),0),"") | J15: =IFERROR(VLOOKUP($A15,subQ,MATCH(J$1,SUBQH,0),0),"") | K15: =IFERROR(VLOOKUP($A15,subQ,MATCH(K$1,SUBQH,0),0),"") | L15: =IFERROR(VLOOKUP($A15,subQ,MATCH(L$1,SUBQH,0),0),"")
A16: 기타영업외손익 | D16: 기타영업외손익 | E16: =IFERROR(VLOOKUP($A16,subQ,MATCH(E$1,SUBQH,0),0),"") | F16: =IFERROR(VLOOKUP($A16,subQ,MATCH(F$1,SUBQH,0),0),"") | G16: =IFERROR(VLOOKUP($A16,subQ,MATCH(G$1,SUBQH,0),0),"") | H16: =IFERROR(VLOOKUP($A16,subQ,MATCH(H$1,SUBQH,0),0),"") | I16: =IFERROR(VLOOKUP($A16,subQ,MATCH(I$1,SUBQH,0),0),"") | J16: =IFERROR(VLOOKUP($A16,subQ,MATCH(J$1,SUBQH,0),0),"") | K16: =IFERROR(VLOOKUP($A16,subQ,MATCH(K$1,SUBQH,0),0),"") | L16: =IFERROR(VLOOKUP($A16,subQ,MATCH(L$1,SUBQH,0),0),"")
... A39: NPM | D39: NPM | E39: =IFERROR(VLOOKUP($A39,subQ,MATCH(E$1,SUBQH,0),0),"") | F39: =IFERROR(VLOOKUP($A39,subQ,MATCH(F$1,SUBQH,0),0),"") | G39: =IFERROR(VLOOKUP($A39,subQ,MATCH(G$1,SUBQH,0),0),"") | H39: =IFERROR(VLOOKUP($A39,subQ,MATCH(H$1,SUBQH,0),0),"") | I39: =IFERROR(VLOOKUP($A39,subQ,MATCH(I$1,SUBQH,0),0),"") | J39: =IFERROR(VLOOKUP($A39,subQ,MATCH(J$1,SUBQH,0),0),"") | K39: =IFERROR(VLOOKUP($A39,subQ,MATCH(K$1,SUBQH,0),0),"") | L39: =IFERROR(VLOOKUP($A39,subQ,MATCH(L$1,SUBQH,0),0),"")
A40: 매출액 YoY | D40: 매출액 YoY | F40: =IFERROR(F5/E5-1,"") | G40: =IFERROR(G5/F5-1,"") | H40: =IFERROR(H5/G5-1,"") | I40: =IFERROR(I5/H5-1,"") | J40: =IFERROR(J5/I5-1,"") | K40: =IFERROR(K5/J5-1,"") | L40: =IFERROR(L5/K5-1,"")
A41: 영업이익 YoY | D41: 영업이익 YoY | F41: =IFERROR(F9/E9-1,"") | G41: =IFERROR(G9/F9-1,"") | H41: =IFERROR(H9/G9-1,"") | I41: =IFERROR(I9/H9-1,"") | J41: =IFERROR(J9/I9-1,"") | K41: =IFERROR(K9/J9-1,"") | L41: =IFERROR(L9/K9-1,"")
A42: 지배주주순이익 YoY | D42: 지배주주순이익 YoY | F42: =IFERROR(F20/E20-1,"") | G42: =IFERROR(G20/F20-1,"") | H42: =IFERROR(H20/G20-1,"") | I42: =IFERROR(I20/H20-1,"") | J42: =IFERROR(J20/I20-1,"") | K42: =IFERROR(K20/J20-1,"") | L42: =IFERROR(L20/K20-1,"")

Sheet TP
B1: 종가 | C1: =변수!D43
B2: 기준일 | C2: =변수!D44
B3: 모델 산출값 — 목표주가·추천 아님. 밴드·COE 는 변수 시트 3절의 가정
C5: FY | D5: 2025 | E5: 2026 | F5: 2027 | G5: 2028
D6: A | E6: E | F6: E | G6: E
C7: EPS(원) | D7: =IFERROR(VLOOKUP("EPS",subQ,MATCH(D$5,SUBQH,0),0),"") | E7: =IFERROR(VLOOKUP("EPS",subQ,MATCH(E$5,SUBQH,0),0),"") | F7: =IFERROR(VLOOKUP("EPS",subQ,MATCH(F$5,SUBQH,0),0),"") | G7: =IFERROR(VLOOKUP("EPS",subQ,MATCH(G$5,SUBQH,0),0),"")
C8: BPS(원) | D8: =IFERROR(VLOOKUP("BPS",subQ,MATCH(D$5,SUBQH,0),0),"") | E8: =IFERROR(VLOOKUP("BPS",subQ,MATCH(E$5,SUBQH,0),0),"") | F8: =IFERROR(VLOOKUP("BPS",subQ,MATCH(F$5,SUBQH,0),0),"") | G8: =IFERROR(VLOOKUP("BPS",subQ,MATCH(G$5,SUBQH,0),0),"")
C9: 지배주주순이익(억원) | D9: =IFERROR(VLOOKUP("지배주주순이익",subQ,MATCH(D$5,SUBQH,0),0),"") | E9: =IFERROR(VLOOKUP("지배주주순이익",subQ,MATCH(E$5,SUBQH,0),0),"") | F9: =IFERROR(VLOOKUP("지배주주순이익",subQ,MATCH(F$5,SUBQH,0),0),"") | G9: =IFERROR(VLOOKUP("지배주주순이익",subQ,MATCH(G$5,SUBQH,0),0),"")
C10: 영업이익(억원) | D10: =IFERROR(VLOOKUP("영업이익",subQ,MATCH(D$5,SUBQH,0),0),"") | E10: =IFERROR(VLOOKUP("영업이익",subQ,MATCH(E$5,SUBQH,0),0),"") | F10: =IFERROR(VLOOKUP("영업이익",subQ,MATCH(F$5,SUBQH,0),0),"") | G10: =IFERROR(VLOOKUP("영업이익",subQ,MATCH(G$5,SUBQH,0),0),"")
C11: ROE(EPS/기초BPS) | E11: =IFERROR(E7/D8,"") | F11: =IFERROR(F7/E8,"") | G11: =IFERROR(G7/F8,"")
B13: PER
C14: 12M fwd EPS | D14: =IFERROR(E7*변수!D49+F7*(1-변수!D49),"")
C15: 적정가치 @PER_lo | D15: =변수!D46 | E15: =IFERROR(ROUND($D$14*D15,-2),"") | F15: =IFERROR(E15/$C$1-1,"") | G15: 배 · 원 · 종가 대비
C16: 적정가치 @PER_mid | D16: =변수!D47 | E16: =IFERROR(ROUND($D$14*D16,-2),"") | F16: =IFERROR(E16/$C$1-1,"") | G16: 배 · 원 · 종가 대비
C17: 적정가치 @PER_hi | D17: =변수!D48 | E17: =IFERROR(ROUND($D$14*D17,-2),"") | F17: =IFERROR(E17/$C$1-1,"") | G17: 배 · 원 · 종가 대비
C18: 현재 PER(종가/12M fwd EPS) | D18: =IFERROR($C$1/$D$14,"")
B20: PBR
C21: 최근 BPS(마지막 실적 분기) | D21: =IFERROR(VLOOKUP("BPS",subQ,MATCH("2Q26",SUBQH,0),0),"")
C22: ROE fwd(12M fwd EPS / BPS) | D22: =IFERROR($D$14/$D$21,"")
C23: COE | D23: =변수!D45
C24: 적정 PBR = ROE/COE | D24: =IFERROR(D22/D23,"")
C25: 적정가치(PBR) = BPS × 적정PBR | D25: =IFERROR(ROUND(D21*D24,-2),"") | E25: =IFERROR(D25/$C$1-1,"")
C26: 현재 PBR(종가/BPS) | D26: =IFERROR($C$1/D21,"")
B28: 모델 json valuation(참고)
C29: eps_fwd12m | D29: 602.7
C30: bps_latest | D30: 20913.7
C31: per_now | D31: 9.23
C32: pbr_now | D32: 0.27
C33: roe_fwd | D33: 0.0288
C34: fair_pbr | D34: 0.32
C35: fair_value_pbr | D35: 6700
C36: ev_ebitda
C37: note | D37: 모델 산출값 — 목표주가·추천 아님

Sheet 외화
C1: 이름: 외화QH — 환율 QoQ · 외화 순노출 × Δ기말환율 | E1: 4Q21 | F1: 1Q22 | G1: 2Q22 | H1: 3Q22 | I1: 4Q22 | J1: 1Q23 | K1: 2Q23 | L1: 3Q23 | M1: 4Q23 | N1: 1Q24 | O1: 2Q24 | P1: 3Q24 | Q1: 4Q24 | R1: 1Q25 | S1: 2Q25 | T1: 3Q25 | U1: 4Q25 | V1: 1Q26 | W1: 2Q26 | X1: 3Q26 | Y1: 4Q26 | Z1: 1Q27 | AA1: 2Q27 | AB1: 3Q27 | AC1: 4Q27 | AD1: 1Q28 | AE1: 2Q28 | AF1: 3Q28 | AG1: 4Q28
E3: 1 | F3: 2 | G3: 3 | H3: 4 | I3: 5 | J3: 6 | K3: 7 | L3: 8 | M3: 9 | N3: 10 | O3: 11 | P3: 12 | Q3: 13 | R3: 14 | S3: 15 | T3: 16 | U3: 17 | V3: 18 | W3: 19 | X3: 20 | Y3: 21 | Z3: 22 | AA3: 23 | AB3: 24 | AC3: 25 | AD3: 26 | AE3: 27 | AF3: 28 | AG3: 29
E4: 2021.12 | F4: 2022.03 | G4: 2022.06 | H4: 2022.09 | I4: 2022.12 | J4: 2023.03 | K4: 2023.06 | L4: 2023.09 | M4: 2023.12 | N4: 2024.03 | O4: 2024.06 | P4: 2024.09 | Q4: 2024.12 | R4: 2025.03 | S4: 2025.06 | T4: 2025.09 | U4: 2025.12 | V4: 2026.03 | W4: 2026.06 | X4: 2026.09 | Y4: 2026.12 | Z4: 2027.03 | AA4: 2027.06 | AB4: 2027.09 | AC4: 2027.12 | AD4: 2028.03 | AE4: 2028.06 | AF4: 2028.09 | AG4: 2028.12
D5: 원/달러(평균) | E5: =IFERROR(VLOOKUP($D5,환율,MATCH(E$1,변수H,0),0),"") | F5: =IFERROR(VLOOKUP($D5,환율,MATCH(F$1,변수H,0),0),"") | G5: =IFERROR(VLOOKUP($D5,환율,MATCH(G$1,변수H,0),0),"") | H5: =IFERROR(VLOOKUP($D5,환율,MATCH(H$1,변수H,0),0),"") | I5: =IFERROR(VLOOKUP($D5,환율,MATCH(I$1,변수H,0),0),"") | J5: =IFERROR(VLOOKUP($D5,환율,MATCH(J$1,변수H,0),0),"") | K5: =IFERROR(VLOOKUP($D5,환율,MATCH(K$1,변수H,0),0),"") | L5: =IFERROR(VLOOKUP($D5,환율,MATCH(L$1,변수H,0),0),"") | ... AG5: =IFERROR(VLOOKUP($D5,환율,MATCH(AG$1,변수H,0),0),"")
A6: 원/달러(평균) QoQ | F6: =IFERROR(F5/E5-1,"") | G6: =IFERROR(G5/F5-1,"") | H6: =IFERROR(H5/G5-1,"") | I6: =IFERROR(I5/H5-1,"") | J6: =IFERROR(J5/I5-1,"") | K6: =IFERROR(K5/J5-1,"") | L6: =IFERROR(L5/K5-1,"") | M6: =IFERROR(M5/L5-1,"") | ... AG6: =IFERROR(AG5/AF5-1,"")
D7: 원/달러(기말) | E7: =IFERROR(VLOOKUP($D7,환율,MATCH(E$1,변수H,0),0),"") | F7: =IFERROR(VLOOKUP($D7,환율,MATCH(F$1,변수H,0),0),"") | G7: =IFERROR(VLOOKUP($D7,환율,MATCH(G$1,변수H,0),0),"") | H7: =IFERROR(VLOOKUP($D7,환율,MATCH(H$1,변수H,0),0),"") | I7: =IFERROR(VLOOKUP($D7,환율,MATCH(I$1,변수H,0),0),"") | J7: =IFERROR(VLOOKUP($D7,환율,MATCH(J$1,변수H,0),0),"") | K7: =IFERROR(VLOOKUP($D7,환율,MATCH(K$1,변수H,0),0),"") | L7: =IFERROR(VLOOKUP($D7,환율,MATCH(L$1,변수H,0),0),"") | ... AG7: =IFERROR(VLOOKUP($D7,환율,MATCH(AG$1,변수H,0),0),"")
A8: 원/달러(기말) QoQ | F8: =IFERROR(F7/E7-1,"") | G8: =IFERROR(G7/F7-1,"") | H8: =IFERROR(H7/G7-1,"") | I8: =IFERROR(I7/H7-1,"") | J8: =IFERROR(J7/I7-1,"") | K8: =IFERROR(K7/J7-1,"") | L8: =IFERROR(L7/K7-1,"") | M8: =IFERROR(M7/L7-1,"") | ... AG8: =IFERROR(AG7/AF7-1,"")
D9: W/Euro(평균) | E9: =IFERROR(VLOOKUP($D9,환율,MATCH(E$1,변수H,0),0),"") | F9: =IFERROR(VLOOKUP($D9,환율,MATCH(F$1,변수H,0),0),"") | G9: =IFERROR(VLOOKUP($D9,환율,MATCH(G$1,변수H,0),0),"") | H9: =IFERROR(VLOOKUP($D9,환율,MATCH(H$1,변수H,0),0),"") | I9: =IFERROR(VLOOKUP($D9,환율,MATCH(I$1,변수H,0),0),"") | J9: =IFERROR(VLOOKUP($D9,환율,MATCH(J$1,변수H,0),0),"") | K9: =IFERROR(VLOOKUP($D9,환율,MATCH(K$1,변수H,0),0),"") | L9: =IFERROR(VLOOKUP($D9,환율,MATCH(L$1,변수H,0),0),"") | ... AG9: =IFERROR(VLOOKUP($D9,환율,MATCH(AG$1,변수H,0),0),"")
A10: W/Euro(평균) QoQ | F10: =IFERROR(F9/E9-1,"") | G10: =IFERROR(G9/F9-1,"") | H10: =IFERROR(H9/G9-1,"") | I10: =IFERROR(I9/H9-1,"") | J10: =IFERROR(J9/I9-1,"") | K10: =IFERROR(K9/J9-1,"") | L10: =IFERROR(L9/K9-1,"") | M10: =IFERROR(M9/L9-1,"") | ... AG10: =IFERROR(AG9/AF9-1,"")
D11: W/Euro(기말) | E11: =IFERROR(VLOOKUP($D11,환율,MATCH(E$1,변수H,0),0),"") | F11: =IFERROR(VLOOKUP($D11,환율,MATCH(F$1,변수H,0),0),"") | G11: =IFERROR(VLOOKUP($D11,환율,MATCH(G$1,변수H,0),0),"") | H11: =IFERROR(VLOOKUP($D11,환율,MATCH(H$1,변수H,0),0),"") | I11: =IFERROR(VLOOKUP($D11,환율,MATCH(I$1,변수H,0),0),"") | J11: =IFERROR(VLOOKUP($D11,환율,MATCH(J$1,변수H,0),0),"") | K11: =IFERROR(VLOOKUP($D11,환율,MATCH(K$1,변수H,0),0),"") | L11: =IFERROR(VLOOKUP($D11,환율,MATCH(L$1,변수H,0),0),"") | ... AG11: =IFERROR(VLOOKUP($D11,환율,MATCH(AG$1,변수H,0),0),"")
A12: W/Euro(기말) QoQ | F12: =IFERROR(F11/E11-1,"") | G12: =IFERROR(G11/F11-1,"") | H12: =IFERROR(H11/G11-1,"") | I12: =IFERROR(I11/H11-1,"") | J12: =IFERROR(J11/I11-1,"") | K12: =IFERROR(K11/J11-1,"") | L12: =IFERROR(L11/K11-1,"") | M12: =IFERROR(M11/L11-1,"") | ... AG12: =IFERROR(AG11/AF11-1,"")
D13: 원/100Y(기말) | E13: =IFERROR(VLOOKUP($D13,환율,MATCH(E$1,변수H,0),0),"") | F13: =IFERROR(VLOOKUP($D13,환율,MATCH(F$1,변수H,0),0),"") | G13: =IFERROR(VLOOKUP($D13,환율,MATCH(G$1,변수H,0),0),"") | H13: =IFERROR(VLOOKUP($D13,환율,MATCH(H$1,변수H,0),0),"") | I13: =IFERROR(VLOOKUP($D13,환율,MATCH(I$1,변수H,0),0),"") | J13: =IFERROR(VLOOKUP($D13,환율,MATCH(J$1,변수H,0),0),"") | K13: =IFERROR(VLOOKUP($D13,환율,MATCH(K$1,변수H,0),0),"") | L13: =IFERROR(VLOOKUP($D13,환율,MATCH(L$1,변수H,0),0),"") | ... AG13: =IFERROR(VLOOKUP($D13,환율,MATCH(AG$1,변수H,0),0),"")
A14: 원/100Y(기말) QoQ | F14: =IFERROR(F13/E13-1,"") | G14: =IFERROR(G13/F13-1,"") | H14: =IFERROR(H13/G13-1,"") | I14: =IFERROR(I13/H13-1,"") | J14: =IFERROR(J13/I13-1,"") | K14: =IFERROR(K13/J13-1,"") | L14: =IFERROR(L13/K13-1,"") | M14: =IFERROR(M13/L13-1,"") | ... AG14: =IFERROR(AG13/AF13-1,"")
A16: 외화순노출 | C16: 외화 순노출(백만$) | D16: =변수!D56 | E16: 외화 순노출 × Δ기말환율 (외화 시트 방식)
A17: 환관련손익추정 | C17: 환관련손익 추정(억원) = 순노출 × Δ원/달러(기말) / 100 | F17: =IFERROR($D$16*(F7-E7)/100,"") | G17: =IFERROR($D$16*(G7-F7)/100,"") | H17: =IFERROR($D$16*(H7-G7)/100,"") | I17: =IFERROR($D$16*(I7-H7)/100,"") | J17: =IFERROR($D$16*(J7-I7)/100,"") | K17: =IFERROR($D$16*(K7-J7)/100,"") | L17: =IFERROR($D$16*(L7-K7)/100,"") | M17: =IFERROR($D$16*(M7-L7)/100,"") | ... AG17: =IFERROR($D$16*(AG7-AF7)/100,"")
A18: fx_pnl.by_q | C18: 모델 fx_pnl.by_q(억원, 참고)
C19: 외화 순노출 미공시(face) → 0 + 표기
