Workbook
Name 변수H: 변수!$C$1:$AO$1
Name 환율: 변수!$C$6:$AO$13
Name BS연결H: BS연결!$C$1:$AO$1
Name BS연결: BS연결!$C$5:$AO$122
Name BS별도H: BS별도!$C$1:$AO$1
Name BS별도: BS별도!$C$5:$AO$120
Name SUBQH: subQ!$A$1:$AO$1
Name subQ: subQ!$A$5:$AO$43

Sheet README
A1: 한화엔진(082740) 실적 모델 — ARGUS 한국조선
A2: 기준 분기 2026Q2 · 마지막 실적 2026Q2 · 생성 2026-10-13
A3: 모든 수치는 모델 산출값(DART 공개 재무제표 + 우리 추정)이다 — 목표주가·투자 추천 아님. 참고용 · 투자조언 아님.
A5: 시트
A6: 변수 가정 시계열. 환율 8행(ECB via frankfurter — L2 fx.json; 추정 분기 = 노란 가정), 추정 드라이버(노란 셀 = 모델값에서 역산한 가정, 바꾸면 재계산; 연녹 셀 = 3절 스칼라 참조 수식), 3절 스칼라 가정(세율·판관비율·지배주주비중·이자율·종가·PER 밴드·COE·외화 순노출·헤지비율)
A7: BS연결/BS별도 FnGuide 계정명 × 기간 값 덤프(백만원). 행1 분기라벨, 행4 YYYY.MM / YYYY.12A. 이름정의 BS연결H·BS연결(계정명 C열부터)
A8: subQ 분기 서브모델(억원 = 백만원/100). 확정 행: =IFERROR(VLOOKUP($D행,BS연결,MATCH(E$1,BS연결H,0),0)/100,"") 추정 행: 변수 시트 가정 셀 참조 수식. 외환손익·파생상품손익은 BS 계정 합·차, 기타금융손익은 잔차, OPM·EPS·BPS·PER·PBR 은 파생 수식
A9: SLS 선표(조선사만, sls json 있을 때): 요약 행(sls 저장값) + 계약별 스케줄(백만$) × (헤지비율 × 헤지환율 + (1−헤지비율) × 건조시점 환율[변수 원/달러(평균)]) → 원화 수식 블록 → 합계 행이 subQ 매출조선에 연결
A10: 시나리오 신규수주 보수/기준/낙관(forecast_panel 패널, 모델에 scenarios 가 있을 때만): 매출액·영업이익 = subQ 기준값 ± (시나리오 신규 − base 신규) × OPM. base 만 subQ 행에 포함, 나머지는 합산 안 함
A11: 분기/연간예상 subQ 를 이름(A열 key)으로 VLOOKUP 한 보고서 표(억원)
A12: TP PER 밴드 × 12M fwd EPS, PBR = ROE/COE × BPS — 모델 산출값 구간, 목표주가·추천 아님
A13: 외화 환율 QoQ, 외화 순노출 × Δ기말환율 → 환관련손익 추정
... A34: 백테스트: {"freeze": "2025Q2", "horizon": 4, "revenue_wape_pct": 9.7, "op_wape_pct": 44.3, "n": 4, "note": "단일 회사 4분기 — 통계 아님", "driver_at_freeze": "customer_yard_revenue_weighted", "selection_oos_at_freeze": {"freeze": "2024Q2", "n": 4, "wape_link": null, "wape_trend": 12.7, "adopted": "undetermined", "decision": "undetermined", "note": "현재 채택 조합(suppliers_mentions·시차 2·ma4·창 12)을 동결 데이터로 재적합할 수 없음(짝·고객 모델 부족) → 연동 WAPE 없음, undetermined(유의성 조건만으로 채택)"}, "frozen_inputs": "fin(연결/별도)·고객 조선사 모델·지주 자회사 모델은 2025Q2 까지의 분기만; 선표는 체결일 ≤ 2025Q2 말일 계약(원장 최신 금액·코호트 등급, 환산 없음); 잔고는 yards_cache 2025Q2; 시세·환율 forward·prices·forecast_panel 신규수주 미사용. 고객 가중치(suppliers.json 언급 비중)와 합병 체인링크는 현재 지식; 고객 연동 채택은 동결 모델 안에서도 자기 la−4분기 OOS 규칙(selection_oos_at_freeze)", "detail": [{"q": "2025Q3", "rev_pred": 3305.76, "rev_act": 2973.45, "op_pred": 199.62, "op_act": 266.31}, {"q": "2025Q4", "rev_pred": 4386.85, "rev_act": 3678.3, "op_pred": 264.9, "op_act": 473.48}, {"q": "2026Q1", "rev_pred": 3679.41, "rev_act": 3452.39, "op_pred": 222.19, "op_act": 513.79}, {"q": "2026Q2", "rev_pred": 3680.92, "rev_act": 3622.2, "op_pred": 222.28, "op_act": 379.11}]}

Sheet 변수
C1: 이름: 변수H | E1: 4Q21 | F1: 2021 | G1: 1Q22 | H1: 2Q22 | I1: 3Q22 | J1: 4Q22 | K1: 2022 | L1: 1Q23 | M1: 2Q23 | N1: 3Q23 | O1: 4Q23 | P1: 2023 | Q1: 1Q24 | R1: 2Q24 | S1: 3Q24 | T1: 4Q24 | U1: 2024 | V1: 1Q25 | W1: 2Q25 | X1: 3Q25 | Y1: 4Q25 | Z1: 2025 | AA1: 1Q26 | AB1: 2Q26 | AC1: 3Q26 | AD1: 4Q26 | AE1: 2026 | AF1: 1Q27 | AG1: 2Q27 | AH1: 3Q27 | AI1: 4Q27 | AJ1: 2027 | AK1: 1Q28 | AL1: 2Q28 | AM1: 3Q28 | AN1: 4Q28 | AO1: 2028
A2: 가정 시계열 — 노란 셀은 추정 가정(모델값에서 역산), 연녹 셀은 3절 스칼라 참조 수식. 바꾸면 subQ·분기·연간예상·TP·시나리오가 재계산됩니다.
E3: 1 | F3: 2 | G3: 3 | H3: 4 | I3: 5 | J3: 6 | K3: 7 | L3: 8 | M3: 9 | N3: 10 | O3: 11 | P3: 12 | Q3: 13 | R3: 14 | S3: 15 | T3: 16 | U3: 17 | V3: 18 | W3: 19 | X3: 20 | Y3: 21 | Z3: 22 | AA3: 23 | AB3: 24 | AC3: 25 | AD3: 26 | AE3: 27 | AF3: 28 | AG3: 29 | AH3: 30 | AI3: 31 | AJ3: 32 | AK3: 33 | AL3: 34 | AM3: 35 | AN3: 36 | AO3: 37
E4: 2021.12 | F4: 2021.12A | G4: 2022.03 | H4: 2022.06 | I4: 2022.09 | J4: 2022.12 | K4: 2022.12A | L4: 2023.03 | M4: 2023.06 | N4: 2023.09 | O4: 2023.12 | P4: 2023.12A | Q4: 2024.03 | R4: 2024.06 | S4: 2024.09 | T4: 2024.12 | U4: 2024.12A | V4: 2025.03 | W4: 2025.06 | X4: 2025.09 | Y4: 2025.12 | Z4: 2025.12A | AA4: 2026.03 | AB4: 2026.06 | AC4: 2026.09 | AD4: 2026.12 | AE4: 2026.12A | AF4: 2027.03 | AG4: 2027.06 | AH4: 2027.09 | AI4: 2027.12 | AJ4: 2027.12A | AK4: 2028.03 | AL4: 2028.06 | AM4: 2028.09 | AN4: 2028.12 | AO4: 2028.12A
B5: 1. FX | C5: 이름: 환율
A6: USDKRW_avg | C6: 원/달러(평균) | E6: 1183.5 | F6: 1145.51 | G6: 1205.78 | H6: 1262.09 | I6: 1341.93 | J6: 1360.12 | K6: 1292.98 | L6: 1276.95 | M6: 1315.69 | N6: 1313.62 | O6: 1322.01 | P6: 1306.85 | Q6: 1330.14 | R6: 1371.28 | S6: 1356.22 | T6: 1396.3 | U6: 1363.53 | V6: 1452.28 | W6: 1398.52 | X6: 1386.95 | Y6: 1449.19 | Z6: 1421.52 | AA6: 1466.12 | AB6: 1501.75 | AC6: 1418.75 | AD6: 1343.63 | AE6: 1456.58 | AF6: 1333.09 | AG6: 1333.09 | AH6: 1333.09 | AI6: 1333.09 | AK6: 1333.09 | AL6: 1333.09 | AM6: 1333.09 | AN6: 1333.09
A7: USDKRW_end | C7: 원/달러(기말) | E7: 1188.75 | F7: 1188.75 | G7: 1213.74 | H7: 1301.24 | I7: 1436.9 | J7: 1260.16 | K7: 1260.16 | L7: 1305.99 | M7: 1321.44 | N7: 1345.35 | O7: 1297.43 | P7: 1297.43 | Q7: 1349.25 | R7: 1377.73 | S7: 1312.17 | T7: 1474.78 | U7: 1474.78 | V7: 1474.54 | W7: 1355.13 | X7: 1403.67 | Y7: 1444.2 | Z7: 1444.2 | AA7: 1524.8 | AB7: 1550.89 | AC7: 1355.4 | AD7: 1333.09 | AE7: 1333.09 | AF7: 1333.09 | AG7: 1333.09 | AH7: 1333.09 | AI7: 1333.09 | AK7: 1333.09 | AL7: 1333.09 | AM7: 1333.09 | AN7: 1333.09
A8: JPY100KRW_avg | C8: 원/100Y(평균) | E8: 1041.02 | F8: 1042.74 | G8: 1036.79 | H8: 972.23 | I8: 970.61 | J8: 961.03 | K8: 985.1 | L8: 964.89 | M8: 957.36 | N8: 909 | O8: 893.22 | P8: 931.11 | Q8: 896.29 | R8: 880.14 | S8: 909.35 | T8: 917.25 | U8: 900.92 | V8: 952.59 | W8: 967.92 | X8: 940.32 | Y8: 940.77 | Z8: 950.17 | AA8: 934.39 | AB8: 942.16 | AC8: 890.41 | AD8: 849.51 | AE8: 918.81 | AF8: 840.54 | AG8: 840.54 | AH8: 840.54 | AI8: 840.54 | AK8: 840.54 | AL8: 840.54 | AM8: 840.54 | AN8: 840.54
A9: JPY100KRW_end | C9: 원/100Y(기말) | E9: 1032.62 | F9: 1032.62 | G9: 996.83 | H9: 954.9 | I9: 993.29 | J9: 955.54 | K9: 955.54 | L9: 980.62 | M9: 913.67 | N9: 901.47 | O9: 917.04 | P9: 917.04 | Q9: 892.42 | R9: 857.76 | S9: 919.21 | T9: 939.65 | U9: 939.65 | V9: 986.84 | W9: 938.85 | X9: 948.49 | Y9: 921.81 | Z9: 921.81 | AA9: 955.99 | AB9: 954.75 | AC9: 863.31 | AD9: 840.54 | AE9: 840.54 | AF9: 840.54 | AG9: 840.54 | AH9: 840.54 | AI9: 840.54 | AK9: 840.54 | AL9: 840.54 | AM9: 840.54 | AN9: 840.54
A10: EURKRW_avg | C10: W/Euro(평균) | E10: 1353.32 | F10: 1354.06 | G10: 1352.29 | H10: 1343.31 | I10: 1350.63 | J10: 1386.07 | K10: 1358.07 | L10: 1369.93 | M10: 1432.41 | N10: 1429.41 | O10: 1420.91 | P10: 1412.88 | Q10: 1444.21 | R10: 1476.42 | S10: 1489.3 | T10: 1490.78 | U10: 1475.4 | V10: 1528.33 | W10: 1585.13 | X10: 1620.04 | Y10: 1686.02 | Z10: 1605.45 | AA10: 1715.47 | AB10: 1746.09 | AC10: 1631.97 | AD10: 1507.34 | AE10: 1688.95 | AF10: 1490.54 | AG10: 1490.54 | AH10: 1490.54 | AI10: 1490.54 | AK10: 1490.54 | AL10: 1490.54 | AM10: 1490.54 | AN10: 1490.54
A11: EURKRW_end | C11: W/Euro(기말) | E11: 1346.38 | F11: 1346.38 | G11: 1347.37 | H11: 1351.6 | I11: 1400.62 | J11: 1344.08 | K11: 1344.08 | L11: 1420.26 | M11: 1435.88 | N11: 1425.26 | O11: 1433.66 | P11: 1433.66 | Q11: 1458.68 | R11: 1474.86 | S11: 1469.1 | T11: 1532.14 | U11: 1532.14 | V11: 1594.72 | W11: 1588.22 | X11: 1648.04 | Y11: 1696.94 | Z11: 1696.94 | AA11: 1753.21 | AB11: 1767.09 | AC11: 1539.06 | AD11: 1490.54 | AE11: 1490.54 | AF11: 1490.54 | AG11: 1490.54 | AH11: 1490.54 | AI11: 1490.54 | AK11: 1490.54 | AL11: 1490.54 | AM11: 1490.54 | AN11: 1490.54
A12: CNYKRW_avg | C12: 원/중국원(평균) | E12: 185.14 | F12: 177.65 | G12: 189.93 | H12: 190.76 | I12: 195.79 | J12: 191.09 | K12: 191.93 | L12: 186.59 | M12: 187.45 | N12: 181.28 | O12: 182.86 | P12: 184.52 | Q12: 185.04 | R12: 189.35 | S12: 189.24 | T12: 194.24 | U12: 189.49 | V12: 199.63 | W12: 193.41 | X12: 193.79 | Y12: 204.38 | Z12: 197.8 | AA12: 211.75 | AB12: 220.8 | AC12: 210.43 | AD12: 200.5 | AE12: 213.68 | AF12: 199.18 | AG12: 199.18 | AH12: 199.18 | AI12: 199.18 | AK12: 199.18 | AL12: 199.18 | AM12: 199.18 | AN12: 199.18
A13: CNYKRW_end | C13: 원/중국원(기말) | E13: 187.13 | F13: 187.13 | G13: 191.38 | H13: 194.13 | I13: 201.92 | J13: 182.67 | K13: 182.67 | L13: 189.97 | M13: 181.8 | N13: 184.26 | O13: 182.61 | P13: 182.61 | Q13: 186.66 | R13: 189.7 | S13: 187.12 | T13: 202.04 | U13: 202.04 | V13: 203.3 | W13: 189.14 | X13: 197.16 | Y13: 206.28 | Z13: 206.28 | AA13: 220.97 | AB13: 228.56 | AC13: 202.16 | AD13: 199.18 | AE13: 199.18 | AF13: 199.18 | AG13: 199.18 | AH13: 199.18 | AI13: 199.18 | AK13: 199.18 | AL13: 199.18 | AM13: 199.18 | AN13: 199.18
B14: 1b. 종가
A15: price_close_end | C15: 종가(기말) | E15: 6542 | G15: 7201 | H15: 8098 | I15: 7140 | J15: 7420 | L15: 7450 | M15: 10120 | N15: 8840 | O15: 9790 | Q15: 9820 | R15: 15630 | S15: 13460 | T15: 18440 | V15: 21250 | W15: 28450 | X15: 44900 | Y15: 42950 | AA15: 43550 | AB15: 51000 | AC15: 49350 | AD15: 37400
A16: price_high | C16: 종가(최고) | E16: 7428 | G16: 8196 | H16: 8785 | I16: 9470 | J16: 7970 | L16: 9100 | M16: 10850 | N16: 12750 | O16: 10220 | Q16: 10450 | R16: 16990 | S16: 17160 | T16: 19100 | V16: 28750 | W16: 32350 | X16: 48600 | Y16: 53900 | AA16: 59900 | AB16: 94400 | AC16: 58000 | AD16: 49500
A17: price_low | C17: 종가(최저) | E17: 5569 | G17: 6306 | H17: 6180 | I17: 6572 | J17: 6110 | L17: 6650 | M17: 7190 | N17: 8650 | O17: 7560 | Q17: 7990 | R17: 9270 | S17: 11000 | T17: 13110 | V17: 17820 | W17: 20000 | X17: 24650 | Y17: 39400 | AA17: 41300 | AB17: 42850 | AC17: 35800 | AD17: 34500
A18: price_avg | C18: 종가(평균) | E18: 6396.5 | G18: 7130.2 | H18: 7539.9 | I18: 7942.9 | J18: 7167.7 | L18: 7374 | M18: 8558.4 | N18: 10654.2 | O18: 8818.3 | Q18: 9172.8 | R18: 12623.3 | S18: 13837.9 | T18: 15717.2 | V18: 23237.1 | W18: 27122.5 | X18: 37497.7 | Y18: 44940.7 | AA18: 51281.4 | AB18: 62239.3 | AC18: 46760.5 | AD18: 43971.4
B20: 2. 추정 드라이버 | C20: 실적 열 = subQ 실현값(수식), 추정 열 = 가정(노란 = 모델값 역산, 연녹 = 3절 스칼라 참조)
A21: drv:매출액 | B21: yoy | C21: 매출액 YoY | J21: =IFERROR(subQ!J5/subQ!E5-1,"") | L21: =IFERROR(subQ!L5/subQ!G5-1,"") | M21: =IFERROR(subQ!M5/subQ!H5-1,"") | N21: =IFERROR(subQ!N5/subQ!I5-1,"") | O21: =IFERROR(subQ!O5/subQ!J5-1,"") | Q21: =IFERROR(subQ!Q5/subQ!L5-1,"") | R21: =IFERROR(subQ!R5/subQ!M5-1,"") | S21: =IFERROR(subQ!S5/subQ!N5-1,"") | T21: =IFERROR(subQ!T5/subQ!O5-1,"") | V21: =IFERROR(subQ!V5/subQ!Q5-1,"") | W21: =IFERROR(subQ!W5/subQ!R5-1,"") | X21: =IFERROR(subQ!X5/subQ!S5-1,"") | Y21: =IFERROR(subQ!Y5/subQ!T5-1,"") | AA21: =IFERROR(subQ!AA5/subQ!V5-1,"") | AB21: =IFERROR(subQ!AB5/subQ!W5-1,"") | AC21: 0.15722693 | AD21: 0.30545216 | AF21: 0.2183516 | AG21: 0.28408185 | AH21: 0.30867839 | AI21: 0.17476842 | AK21: 0.13292188 | AL21: 0.11538743 | AM21: 0.11270877 | AN21: 0.1512963
A22: drv:판관비 | B22: ratio | C22: 판관비율(/매출) | E22: =IFERROR(subQ!E8/subQ!E5,"") | F22: =IFERROR(subQ!F8/subQ!F5,"") | G22: =IFERROR(subQ!G8/subQ!G5,"") | H22: =IFERROR(subQ!H8/subQ!H5,"") | I22: =IFERROR(subQ!I8/subQ!I5,"") | J22: =IFERROR(subQ!J8/subQ!J5,"") | K22: =IFERROR(subQ!K8/subQ!K5,"") | L22: =IFERROR(subQ!L8/subQ!L5,"") | ... AB22: =IFERROR(subQ!AB8/subQ!AB5,"") | AC22: =$D$52 | AD22: =$D$52 | AE22: =IFERROR(subQ!AE8/subQ!AE5,"") | AF22: =$D$52 | AG22: =$D$52 | AH22: =$D$52 | AI22: =$D$52 | AJ22: =IFERROR(subQ!AJ8/subQ!AJ5,"") | AK22: =$D$52 | AL22: =$D$52 | AM22: =$D$52 | AN22: =$D$52 | AO22: =IFERROR(subQ!AO8/subQ!AO5,"")
A23: drv:영업이익 | B23: ratio | C23: 영업이익률(OPM) | E23: =IFERROR(subQ!E9/subQ!E5,"") | F23: =IFERROR(subQ!F9/subQ!F5,"") | G23: =IFERROR(subQ!G9/subQ!G5,"") | H23: =IFERROR(subQ!H9/subQ!H5,"") | I23: =IFERROR(subQ!I9/subQ!I5,"") | J23: =IFERROR(subQ!J9/subQ!J5,"") | K23: =IFERROR(subQ!K9/subQ!K5,"") | L23: =IFERROR(subQ!L9/subQ!L5,"") | ... AB23: =IFERROR(subQ!AB9/subQ!AB5,"") | AC23: 0.088341626 | AD23: 0.088339053 | AE23: =IFERROR(subQ!AE9/subQ!AE5,"") | AF23: 0.08834039 | AG23: 0.088340643 | AH23: 0.088338948 | AI23: 0.088339937 | AJ23: =IFERROR(subQ!AJ9/subQ!AJ5,"") | AK23: 0.088340157 | AL23: 0.088340346 | AM23: 0.088339836 | AN23: 0.088340632 | AO23: =IFERROR(subQ!AO9/subQ!AO5,"")
A24: drv:외환손익 | B24: abs | C24: 외환손익 (가정, 억원) | E24: =subQ!E13 | F24: =subQ!F13 | G24: =subQ!G13 | H24: =subQ!H13 | I24: =subQ!I13 | J24: =subQ!J13 | K24: =subQ!K13 | L24: =subQ!L13 | ... AB24: =subQ!AB13 | AC24: 0 | AD24: 0 | AE24: =subQ!AE13 | AF24: 0 | AG24: 0 | AH24: 0 | AI24: 0 | AJ24: =subQ!AJ13 | AK24: 0 | AL24: 0 | AM24: 0 | AN24: 0 | AO24: =subQ!AO13
A25: drv:파생상품손익 | B25: abs | C25: 파생상품손익 (가정, 억원) | E25: =subQ!E14 | F25: =subQ!F14 | G25: =subQ!G14 | H25: =subQ!H14 | I25: =subQ!I14 | J25: =subQ!J14 | K25: =subQ!K14 | L25: =subQ!L14 | ... AB25: =subQ!AB14 | AC25: 0 | AD25: 0 | AE25: =subQ!AE14 | AF25: 0 | AG25: 0 | AH25: 0 | AI25: 0 | AJ25: =subQ!AJ14 | AK25: 0 | AL25: 0 | AM25: 0 | AN25: 0 | AO25: =subQ!AO14
A26: drv:기타금융손익 | B26: abs | C26: 기타금융손익 (가정, 억원) | E26: =subQ!E15 | F26: =subQ!F15 | G26: =subQ!G15 | H26: =subQ!H15 | I26: =subQ!I15 | J26: =subQ!J15 | K26: =subQ!K15 | L26: =subQ!L15 | ... AB26: =subQ!AB15 | AC26: 0 | AD26: 0 | AE26: =subQ!AE15 | AF26: 0 | AG26: 0 | AH26: 0 | AI26: 0 | AJ26: =subQ!AJ15 | AK26: 0 | AL26: 0 | AM26: 0 | AN26: 0 | AO26: =subQ!AO15
A27: drv:기타영업외손익 | B27: abs | C27: 기타영업외손익 (가정, 억원) | E27: =subQ!E16 | F27: =subQ!F16 | G27: =subQ!G16 | H27: =subQ!H16 | I27: =subQ!I16 | J27: =subQ!J16 | K27: =subQ!K16 | L27: =subQ!L16 | ... AB27: =subQ!AB16 | AC27: 0 | AD27: 0 | AE27: =subQ!AE16 | AF27: 0 | AG27: 0 | AH27: 0 | AI27: 0 | AJ27: =subQ!AJ16 | AK27: 0 | AL27: 0 | AM27: 0 | AN27: 0 | AO27: =subQ!AO16
A28: drv:지분법손익 | B28: abs | C28: 지분법손익 (가정, 억원) | E28: =subQ!E17 | F28: =subQ!F17 | G28: =subQ!G17 | H28: =subQ!H17 | I28: =subQ!I17 | J28: =subQ!J17 | K28: =subQ!K17 | L28: =subQ!L17 | ... AB28: =subQ!AB17 | AC28: -0.04 | AD28: -0.04 | AE28: =subQ!AE17 | AF28: -0.04 | AG28: -0.04 | AH28: -0.04 | AI28: -0.04 | AJ28: =subQ!AJ17 | AK28: -0.04 | AL28: -0.04 | AM28: -0.04 | AN28: -0.04 | AO28: =subQ!AO17
A29: drv:법인세비용 | B29: tax | C29: 법인세율(/세전) — 법인세 = MAX(세전,0) × 세율 | E29: =IFERROR(subQ!E19/subQ!E18,"") | F29: =IFERROR(subQ!F19/subQ!F18,"") | G29: =IFERROR(subQ!G19/subQ!G18,"") | H29: =IFERROR(subQ!H19/subQ!H18,"") | I29: =IFERROR(subQ!I19/subQ!I18,"") | J29: =IFERROR(subQ!J19/subQ!J18,"") | K29: =IFERROR(subQ!K19/subQ!K18,"") | L29: =IFERROR(subQ!L19/subQ!L18,"") | ... AB29: =IFERROR(subQ!AB19/subQ!AB18,"") | AC29: =$D$51 | AD29: =$D$51 | AE29: =IFERROR(subQ!AE19/subQ!AE18,"") | AF29: =$D$51 | AG29: =$D$51 | AH29: =$D$51 | AI29: =$D$51 | AJ29: =IFERROR(subQ!AJ19/subQ!AJ18,"") | AK29: =$D$51 | AL29: =$D$51 | AM29: =$D$51 | AN29: =$D$51 | AO29: =IFERROR(subQ!AO19/subQ!AO18,"")
A30: drv:지배주주순이익 | B30: ratio | C30: 지배주주 비중(/당기순이익) | E30: =IFERROR(subQ!E21/subQ!E20,"") | F30: =IFERROR(subQ!F21/subQ!F20,"") | G30: =IFERROR(subQ!G21/subQ!G20,"") | H30: =IFERROR(subQ!H21/subQ!H20,"") | I30: =IFERROR(subQ!I21/subQ!I20,"") | J30: =IFERROR(subQ!J21/subQ!J20,"") | K30: =IFERROR(subQ!K21/subQ!K20,"") | L30: =IFERROR(subQ!L21/subQ!L20,"") | ... AB30: =IFERROR(subQ!AB21/subQ!AB20,"") | AC30: =$D$53 | AD30: =$D$53 | AE30: =IFERROR(subQ!AE21/subQ!AE20,"") | AF30: =$D$53 | AG30: =$D$53 | AH30: =$D$53 | AI30: =$D$53 | AJ30: =IFERROR(subQ!AJ21/subQ!AJ20,"") | AK30: =$D$53 | AL30: =$D$53 | AM30: =$D$53 | AN30: =$D$53 | AO30: =IFERROR(subQ!AO21/subQ!AO20,"")
A31: drv:부채총계 | B31: qoq | C31: 부채총계 QoQ | G31: =IFERROR(subQ!G23/subQ!E23-1,"") | H31: =IFERROR(subQ!H23/subQ!G23-1,"") | I31: =IFERROR(subQ!I23/subQ!H23-1,"") | J31: =IFERROR(subQ!J23/subQ!I23-1,"") | L31: =IFERROR(subQ!L23/subQ!J23-1,"") | M31: =IFERROR(subQ!M23/subQ!L23-1,"") | N31: =IFERROR(subQ!N23/subQ!M23-1,"") | O31: =IFERROR(subQ!O23/subQ!N23-1,"") | Q31: =IFERROR(subQ!Q23/subQ!O23-1,"") | R31: =IFERROR(subQ!R23/subQ!Q23-1,"") | S31: =IFERROR(subQ!S23/subQ!R23-1,"") | T31: =IFERROR(subQ!T23/subQ!S23-1,"") | V31: =IFERROR(subQ!V23/subQ!T23-1,"") | W31: =IFERROR(subQ!W23/subQ!V23-1,"") | X31: =IFERROR(subQ!X23/subQ!W23-1,"") | Y31: =IFERROR(subQ!Y23/subQ!X23-1,"") | AA31: =IFERROR(subQ!AA23/subQ!Y23-1,"") | AB31: =IFERROR(subQ!AB23/subQ!AA23-1,"") | AC31: 1.31e-07 | AD31: 0 | AF31: 0 | AG31: 0 | AH31: 0 | AI31: 0 | AK31: 0 | AL31: 0 | AM31: 0 | AN31: 0
A32: drv:자본총계 | B32: roll | C32: 자본총계 기타변동(배당 등, 억원) | G32: =IFERROR(subQ!E24+subQ!G20-subQ!G24,"") | H32: =IFERROR(subQ!G24+subQ!H20-subQ!H24,"") | I32: =IFERROR(subQ!H24+subQ!I20-subQ!I24,"") | J32: =IFERROR(subQ!I24+subQ!J20-subQ!J24,"") | L32: =IFERROR(subQ!J24+subQ!L20-subQ!L24,"") | M32: =IFERROR(subQ!L24+subQ!M20-subQ!M24,"") | N32: =IFERROR(subQ!M24+subQ!N20-subQ!N24,"") | O32: =IFERROR(subQ!N24+subQ!O20-subQ!O24,"") | Q32: =IFERROR(subQ!O24+subQ!Q20-subQ!Q24,"") | R32: =IFERROR(subQ!Q24+subQ!R20-subQ!R24,"") | S32: =IFERROR(subQ!R24+subQ!S20-subQ!S24,"") | T32: =IFERROR(subQ!S24+subQ!T20-subQ!T24,"") | V32: =IFERROR(subQ!T24+subQ!V20-subQ!V24,"") | W32: =IFERROR(subQ!V24+subQ!W20-subQ!W24,"") | X32: =IFERROR(subQ!W24+subQ!X20-subQ!X24,"") | Y32: =IFERROR(subQ!X24+subQ!Y20-subQ!Y24,"") | AA32: =IFERROR(subQ!Y24+subQ!AA20-subQ!AA24,"") | AB32: =IFERROR(subQ!AA24+subQ!AB20-subQ!AB24,"") | AC32: 0.00530175 | AD32: -0.013456659 | AF32: -9.101e-05 | AG32: -0.001622087 | AH32: -0.002867333 | AI32: -0.006608591 | AK32: -6.7464e-05 | AL32: 0.003934382 | AM32: -0.00065193 | AN32: 0.001525968
A33: drv:지배주주지분 | B33: roll | C33: 지배주주지분 기타변동(배당 등, 억원) | G33: =IFERROR(subQ!E25+subQ!G21-subQ!G25,"") | H33: =IFERROR(subQ!G25+subQ!H21-subQ!H25,"") | I33: =IFERROR(subQ!H25+subQ!I21-subQ!I25,"") | J33: =IFERROR(subQ!I25+subQ!J21-subQ!J25,"") | L33: =IFERROR(subQ!J25+subQ!L21-subQ!L25,"") | M33: =IFERROR(subQ!L25+subQ!M21-subQ!M25,"") | N33: =IFERROR(subQ!M25+subQ!N21-subQ!N25,"") | O33: =IFERROR(subQ!N25+subQ!O21-subQ!O25,"") | Q33: =IFERROR(subQ!O25+subQ!Q21-subQ!Q25,"") | R33: =IFERROR(subQ!Q25+subQ!R21-subQ!R25,"") | S33: =IFERROR(subQ!R25+subQ!S21-subQ!S25,"") | T33: =IFERROR(subQ!S25+subQ!T21-subQ!T25,"") | V33: =IFERROR(subQ!T25+subQ!V21-subQ!V25,"") | W33: =IFERROR(subQ!V25+subQ!W21-subQ!W25,"") | X33: =IFERROR(subQ!W25+subQ!X21-subQ!X25,"") | Y33: =IFERROR(subQ!X25+subQ!Y21-subQ!Y25,"") | AA33: =IFERROR(subQ!Y25+subQ!AA21-subQ!AA25,"") | AB33: =IFERROR(subQ!AA25+subQ!AB21-subQ!AB25,"") | AC33: 0.00530175 | AD33: -0.013456659 | AF33: -9.101e-05 | AG33: -0.001622087 | AH33: -0.002867333 | AI33: -0.006608591 | AK33: -6.7464e-05 | AL33: 0.003934382 | AM33: -0.00065193 | AN33: 0.001525968
A34: drv:총차입금 | B34: qoq | C34: 총차입금 QoQ | G34: =IFERROR(subQ!G26/subQ!E26-1,"") | H34: =IFERROR(subQ!H26/subQ!G26-1,"") | I34: =IFERROR(subQ!I26/subQ!H26-1,"") | J34: =IFERROR(subQ!J26/subQ!I26-1,"") | L34: =IFERROR(subQ!L26/subQ!J26-1,"") | M34: =IFERROR(subQ!M26/subQ!L26-1,"") | N34: =IFERROR(subQ!N26/subQ!M26-1,"") | O34: =IFERROR(subQ!O26/subQ!N26-1,"") | Q34: =IFERROR(subQ!Q26/subQ!O26-1,"") | R34: =IFERROR(subQ!R26/subQ!Q26-1,"") | S34: =IFERROR(subQ!S26/subQ!R26-1,"") | T34: =IFERROR(subQ!T26/subQ!S26-1,"") | V34: =IFERROR(subQ!V26/subQ!T26-1,"") | W34: =IFERROR(subQ!W26/subQ!V26-1,"") | X34: =IFERROR(subQ!X26/subQ!W26-1,"") | Y34: =IFERROR(subQ!Y26/subQ!X26-1,"") | AA34: =IFERROR(subQ!AA26/subQ!Y26-1,"") | AB34: =IFERROR(subQ!AB26/subQ!AA26-1,"") | AC34: 1.2984e-05 | AD34: 0 | AF34: 0 | AG34: 0 | AH34: 0 | AI34: 0 | AK34: 0 | AL34: 0 | AM34: 0 | AN34: 0
A35: drv:순차입금 | B35: qoq | C35: 순차입금 QoQ | G35: =IFERROR(subQ!G27/subQ!E27-1,"") | H35: =IFERROR(subQ!H27/subQ!G27-1,"") | I35: =IFERROR(subQ!I27/subQ!H27-1,"") | J35: =IFERROR(subQ!J27/subQ!I27-1,"") | L35: =IFERROR(subQ!L27/subQ!J27-1,"") | M35: =IFERROR(subQ!M27/subQ!L27-1,"") | N35: =IFERROR(subQ!N27/subQ!M27-1,"") | O35: =IFERROR(subQ!O27/subQ!N27-1,"") | Q35: =IFERROR(subQ!Q27/subQ!O27-1,"") | R35: =IFERROR(subQ!R27/subQ!Q27-1,"") | S35: =IFERROR(subQ!S27/subQ!R27-1,"") | T35: =IFERROR(subQ!T27/subQ!S27-1,"") | V35: =IFERROR(subQ!V27/subQ!T27-1,"") | W35: =IFERROR(subQ!W27/subQ!V27-1,"") | X35: =IFERROR(subQ!X27/subQ!W27-1,"") | Y35: =IFERROR(subQ!Y27/subQ!X27-1,"") | AA35: =IFERROR(subQ!AA27/subQ!Y27-1,"") | AB35: =IFERROR(subQ!AB27/subQ!AA27-1,"") | AC35: 0.093593109 | AD35: 0.11749772 | AF35: 0.093662308 | AG35: 0.094640444 | AH35: 0.084547923 | AI35: 0.096557401 | AK35: 0.076051152 | AL35: 0.076870616 | AM35: 0.069696915 | AN35: 0.082930741
A36: drv:이자발생자산 | B36: qoq | C36: 이자발생자산 QoQ | G36: =IFERROR(subQ!G28/subQ!E28-1,"") | H36: =IFERROR(subQ!H28/subQ!G28-1,"") | I36: =IFERROR(subQ!I28/subQ!H28-1,"") | J36: =IFERROR(subQ!J28/subQ!I28-1,"") | L36: =IFERROR(subQ!L28/subQ!J28-1,"") | M36: =IFERROR(subQ!M28/subQ!L28-1,"") | N36: =IFERROR(subQ!N28/subQ!M28-1,"") | O36: =IFERROR(subQ!O28/subQ!N28-1,"") | Q36: =IFERROR(subQ!Q28/subQ!O28-1,"") | R36: =IFERROR(subQ!R28/subQ!Q28-1,"") | S36: =IFERROR(subQ!S28/subQ!R28-1,"") | T36: =IFERROR(subQ!T28/subQ!S28-1,"") | V36: =IFERROR(subQ!V28/subQ!T28-1,"") | W36: =IFERROR(subQ!W28/subQ!V28-1,"") | X36: =IFERROR(subQ!X28/subQ!W28-1,"") | Y36: =IFERROR(subQ!Y28/subQ!X28-1,"") | AA36: =IFERROR(subQ!AA28/subQ!Y28-1,"") | AB36: =IFERROR(subQ!AB28/subQ!AA28-1,"") | AC36: 0.083527318 | AD36: 0.1058306 | AF36: 0.085254445 | AG36: 0.086812172 | AH36: 0.078113085 | AI36: 0.089743124 | AK36: 0.071124349 | AL36: 0.072221398 | AM36: 0.065765503 | AN36: 0.078541505
A37: drv:현금및현금성자산 | B37: qoq | C37: 현금및현금성자산 QoQ | G37: =IFERROR(subQ!G29/subQ!E29-1,"") | H37: =IFERROR(subQ!H29/subQ!G29-1,"") | I37: =IFERROR(subQ!I29/subQ!H29-1,"") | J37: =IFERROR(subQ!J29/subQ!I29-1,"") | L37: =IFERROR(subQ!L29/subQ!J29-1,"") | M37: =IFERROR(subQ!M29/subQ!L29-1,"") | N37: =IFERROR(subQ!N29/subQ!M29-1,"") | O37: =IFERROR(subQ!O29/subQ!N29-1,"") | Q37: =IFERROR(subQ!Q29/subQ!O29-1,"") | R37: =IFERROR(subQ!R29/subQ!Q29-1,"") | S37: =IFERROR(subQ!S29/subQ!R29-1,"") | T37: =IFERROR(subQ!T29/subQ!S29-1,"") | V37: =IFERROR(subQ!V29/subQ!T29-1,"") | W37: =IFERROR(subQ!W29/subQ!V29-1,"") | X37: =IFERROR(subQ!X29/subQ!W29-1,"") | Y37: =IFERROR(subQ!Y29/subQ!X29-1,"") | AA37: =IFERROR(subQ!AA29/subQ!Y29-1,"") | AB37: =IFERROR(subQ!AB29/subQ!AA29-1,"")
A38: drv:CAPEX | B38: yoy | C38: CAPEX YoY | J38: =IFERROR(subQ!J30/subQ!E30-1,"") | L38: =IFERROR(subQ!L30/subQ!G30-1,"") | M38: =IFERROR(subQ!M30/subQ!H30-1,"") | N38: =IFERROR(subQ!N30/subQ!I30-1,"") | O38: =IFERROR(subQ!O30/subQ!J30-1,"") | Q38: =IFERROR(subQ!Q30/subQ!L30-1,"") | R38: =IFERROR(subQ!R30/subQ!M30-1,"") | S38: =IFERROR(subQ!S30/subQ!N30-1,"") | T38: =IFERROR(subQ!T30/subQ!O30-1,"") | V38: =IFERROR(subQ!V30/subQ!Q30-1,"") | W38: =IFERROR(subQ!W30/subQ!R30-1,"") | X38: =IFERROR(subQ!X30/subQ!S30-1,"") | Y38: =IFERROR(subQ!Y30/subQ!T30-1,"") | AA38: =IFERROR(subQ!AA30/subQ!V30-1,"") | AB38: =IFERROR(subQ!AB30/subQ!W30-1,"") | AC38: 0.39933808 | AD38: -0.22199439 | AF38: -0.43968291 | AG38: 0 | AH38: 0 | AI38: 0 | AK38: 0 | AL38: 0 | AM38: 0 | AN38: 0
A39: drv:영업활동현금흐름 | B39: yoy | C39: 영업활동현금흐름 YoY | J39: =IFERROR(subQ!J31/subQ!E31-1,"") | L39: =IFERROR(subQ!L31/subQ!G31-1,"") | M39: =IFERROR(subQ!M31/subQ!H31-1,"") | N39: =IFERROR(subQ!N31/subQ!I31-1,"") | O39: =IFERROR(subQ!O31/subQ!J31-1,"") | Q39: =IFERROR(subQ!Q31/subQ!L31-1,"") | R39: =IFERROR(subQ!R31/subQ!M31-1,"") | S39: =IFERROR(subQ!S31/subQ!N31-1,"") | T39: =IFERROR(subQ!T31/subQ!O31-1,"") | V39: =IFERROR(subQ!V31/subQ!Q31-1,"") | W39: =IFERROR(subQ!W31/subQ!R31-1,"") | X39: =IFERROR(subQ!X31/subQ!S31-1,"") | Y39: =IFERROR(subQ!Y31/subQ!T31-1,"") | AA39: =IFERROR(subQ!AA31/subQ!V31-1,"") | AB39: =IFERROR(subQ!AB31/subQ!W31-1,"")
A40: drv:주식수 | B40: qoq | C40: 주식수 QoQ | G40: =IFERROR(subQ!G32/subQ!E32-1,"") | H40: =IFERROR(subQ!H32/subQ!G32-1,"") | I40: =IFERROR(subQ!I32/subQ!H32-1,"") | J40: =IFERROR(subQ!J32/subQ!I32-1,"") | L40: =IFERROR(subQ!L32/subQ!J32-1,"") | M40: =IFERROR(subQ!M32/subQ!L32-1,"") | N40: =IFERROR(subQ!N32/subQ!M32-1,"") | O40: =IFERROR(subQ!O32/subQ!N32-1,"") | Q40: =IFERROR(subQ!Q32/subQ!O32-1,"") | R40: =IFERROR(subQ!R32/subQ!Q32-1,"") | S40: =IFERROR(subQ!S32/subQ!R32-1,"") | T40: =IFERROR(subQ!T32/subQ!S32-1,"") | V40: =IFERROR(subQ!V32/subQ!T32-1,"") | W40: =IFERROR(subQ!W32/subQ!V32-1,"") | X40: =IFERROR(subQ!X32/subQ!W32-1,"") | Y40: =IFERROR(subQ!Y32/subQ!X32-1,"") | AA40: =IFERROR(subQ!AA32/subQ!Y32-1,"") | AB40: =IFERROR(subQ!AB32/subQ!AA32-1,"") | AC40: 0 | AD40: 0 | AF40: 0 | AG40: 0 | AH40: 0 | AI40: 0 | AK40: 0 | AL40: 0 | AM40: 0 | AN40: 0
A41: drv:DPS | B41: abs | C41: DPS (가정, 원) | E41: =subQ!E35 | F41: =subQ!F35 | G41: =subQ!G35 | H41: =subQ!H35 | I41: =subQ!I35 | J41: =subQ!J35 | K41: =subQ!K35 | L41: =subQ!L35 | ... AB41: =subQ!AB35 | AD41: 0 | AE41: =subQ!AE35 | AI41: 0 | AJ41: =subQ!AJ35 | AN41: 0 | AO41: =subQ!AO35
B43: 3. 밸류에이션·스칼라 | C43: 노란 셀 = 가정. '연결' 표시는 추정 전 분기 수식이 이 셀을 참조한다는 뜻
A44: sc:종가 | C44: 종가 | D44: 37400 | E44: 원 — 네이버 정규장 종가(aik 확정종가 대조 · aik 41,050원)
A45: sc:기준일 | C45: 기준일 | D45: 20261013 | E45: 종가 기준일
A46: sc:COE | C46: COE | D46: 0.09 | E46: 자기자본비용(가정) — TP 적정 PBR = ROE/COE
A47: sc:PER_lo | C47: PER_lo | D47: 21.6 | E47: PER 밴드 하단(배) — hist_quarterly(분기 평균가 ÷ TTM EPS, 11분기, 25/50/75 백분위) · 캡 5~30배 적용(원값 21.6/24.9/48.7)
A48: sc:PER_mid | C48: PER_mid | D48: 24.9 | E48: PER 밴드 중단(배)
A49: sc:PER_hi | C49: PER_hi | D49: 30 | E49: PER 밴드 상단(배)
A50: sc:EPS_Y1가중 | C50: EPS_Y1가중 | D50: 0.5 | E50: 12M fwd EPS = FY(last_actual연도)E × w + FY+1E × (1−w) — 기준 분기 2Q 이면 0.5(가정)
A51: sc:세율 | C51: 세율 | D51: 0.21999808 | E51: 연결 — 법인세 = MAX(세전,0) × 세율(역산, 재현 오차 ≤ 0.05억 · 모델 assumptions 0.22) · 최근 12분기 유효세율 -12.9% 가 5~27% 밖; 세전 > 0 분기 중위 2.9% 도 5~27% 밖 → 법정세율 근사 22% 가정
A52: sc:판관비율 | C52: 판관비율 | D52: 0.045777058 | E52: 연결 — 판관비 = 매출액 × 판관비율(역산, 재현 오차 ≤ 0.05억 · 모델 assumptions 0.0458)
A53: sc:지배주주비중 | C53: 지배주주비중 | D53: 1 | E53: 연결 — 지배주주순이익 = 당기순이익 × 비중(역산, 재현 오차 ≤ 0.05억)
A54: sc:이자율_자산 | C54: 이자율_자산 | D54: 0.037700895 | E54: 연결 — 이자손익 = (전분기 이자발생자산 × 자산이자율 − 전분기 총차입금 × 부채이자율)/4(역산, 재현 오차 ≤ 0.05억 · 모델 assumptions 0.0377)
A55: sc:이자율_부채 | C55: 이자율_부채 | D55: 0.050465156 | E55: 연결 — 같은 수식의 부채 쪽(총차입금 행이 없으면 0)(역산, 재현 오차 ≤ 0.05억 · 모델 assumptions 0.0504)
A56: sc:배당성향 | C56: 배당성향 | D56: 0 | E56: 배당성향(참고 — 모델은 직전 DPS 유지·Q2 지급 가정)
A57: sc:외화순노출_백만$ | C57: 외화순노출_백만$ | E57: 외화 순노출 × Δ기말환율 (외화 시트 방식) — 외화 순노출 미공시(face) → 0 + 표기
A58: sc:헤지비율 | C58: 헤지비율 | E58: sls 없음
A59: sc:헤지환율_약정 | C59: 헤지환율_약정 | E59: sls 없음

Sheet BS연결
B1: (백만원) | C1: 이름: BS연결H | E1: 4Q21 | F1: 2021 | G1: 1Q22 | H1: 2Q22 | I1: 3Q22 | J1: 4Q22 | K1: 2022 | L1: 1Q23 | M1: 2Q23 | N1: 3Q23 | O1: 4Q23 | P1: 2023 | Q1: 1Q24 | R1: 2Q24 | S1: 3Q24 | T1: 4Q24 | U1: 2024 | V1: 1Q25 | W1: 2Q25 | X1: 3Q25 | Y1: 4Q25 | Z1: 2025 | AA1: 1Q26 | AB1: 2Q26 | AC1: 3Q26 | AD1: 4Q26 | AE1: 2026 | AF1: 1Q27 | AG1: 2Q27 | AH1: 3Q27 | AI1: 4Q27 | AJ1: 2027 | AK1: 1Q28 | AL1: 2Q28 | AM1: 3Q28 | AN1: 4Q28 | AO1: 2028
B2: 연결 | D2: fin json(kship_fin.py)
B3: 한화엔진(연) | C3: UPDATE: 26-10-13 | E3: 1 | F3: 2 | G3: 3 | H3: 4 | I3: 5 | J3: 6 | K3: 7 | L3: 8 | M3: 9 | N3: 10 | O3: 11 | P3: 12 | Q3: 13 | R3: 14 | S3: 15 | T3: 16 | U3: 17 | V3: 18 | W3: 19 | X3: 20 | Y3: 21 | Z3: 22 | AA3: 23 | AB3: 24 | AC3: 25 | AD3: 26 | AE3: 27 | AF3: 28 | AG3: 29 | AH3: 30 | AI3: 31 | AJ3: 32 | AK3: 33 | AL3: 34 | AM3: 35 | AN3: 36 | AO3: 37
B4: Account Code | C4: AccountNAME | E4: 2021.12 | F4: 2021.12A | G4: 2022.03 | H4: 2022.06 | I4: 2022.09 | J4: 2022.12 | K4: 2022.12A | L4: 2023.03 | M4: 2023.06 | N4: 2023.09 | O4: 2023.12 | P4: 2023.12A | Q4: 2024.03 | R4: 2024.06 | S4: 2024.09 | T4: 2024.12 | U4: 2024.12A | V4: 2025.03 | W4: 2025.06 | X4: 2025.09 | Y4: 2025.12 | Z4: 2025.12A | AA4: 2026.03 | AB4: 2026.06 | AC4: 2026.09 | AD4: 2026.12 | AE4: 2026.12A | AF4: 2027.03 | AG4: 2027.06 | AH4: 2027.09 | AI4: 2027.12 | AJ4: 2027.12A | AK4: 2028.03 | AL4: 2028.06 | AM4: 2028.09 | AN4: 2028.12 | AO4: 2028.12A
A5: 1 | C5: 유동자산 | E5: 344869.46 | F5: 344869.46 | G5: 353848.61 | H5: 389318.95 | I5: 539497.07 | J5: 471073.55 | K5: 471073.55 | L5: 492546.99 | M5: 552402.07 | Y5: 1031851.2 | Z5: 1031851.2 | AA5: 856528.61 | AB5: 1040092.9
A6: 1 | C6: 현금및현금성자산 | E6: 54072.27 | F6: 54072.27 | G6: 63867.89 | H6: 54601.56 | I6: 91486.71 | J6: 54559.25 | K6: 54559.25 | L6: 66371.55 | M6: 33083.66 | Y6: 276708.03 | Z6: 276708.03 | AA6: 49997.56 | AB6: 163635.95
A7: 1 | C7: 단기금융상품 | E7: 12702.29 | F7: 12702.29 | G7: 8568 | H7: 8497.16 | I7: 42291.27 | J7: 15156.82 | K7: 15156.82 | L7: 13870.42 | M7: 13910.76 | Y7: 133988.65 | Z7: 133988.65 | AA7: 65265.9
A8: 1 | C8: 단기금융자산 | E8: 12825.24 | F8: 12825.24 | G8: 8689.65 | H8: 8610.46 | I8: 42395.52 | J8: 15257.32 | K8: 15257.32 | L8: 13974.42 | M8: 14015.66 | Y8: 134106 | Z8: 134106 | AA8: 70823.4 | AB8: 142045.33
A9: 1 | C9: 단기대여금 | E9: 122.95 | F9: 122.95 | G9: 121.65 | H9: 113.3 | I9: 104.25 | J9: 100.5 | K9: 100.5 | L9: 104 | M9: 104.9 | Y9: 117.35 | Z9: 117.35 | AA9: 176.2
A10: 1 | C10: 매출채권및기타채권 | E10: 59573.79 | F10: 59573.79 | G10: 56633.51 | H10: 50838.22 | I10: 49956.88 | J10: 71262.89 | K10: 71262.89 | L10: 69235.43 | M10: 72694.88 | Y10: 165742.58 | Z10: 165742.58 | AA10: 193202.37 | AB10: 152728.52
A11: 1 | C11: 계약자산 | E11: 12664.66 | F11: 12664.66 | AB11: 17130.13
A12: 1 | C12: 당기법인세자산(선급법인세) | E12: 146.29 | F12: 146.29 | G12: 152.66 | H12: 117.23 | I12: 139.42 | J12: 211.85 | K12: 211.85 | L12: 257.65 | M12: 312.85 | Y12: 18.3 | Z12: 18.3 | AB12: 334.38
A13: 1 | C13: 재고자산 | E13: 179427.93 | F13: 179427.93 | G13: 190338.02 | H13: 219008.4 | I13: 241946.35 | J13: 252292.72 | K13: 252292.72 | L13: 269549.22 | M13: 322351.85 | Y13: 356165.91 | Z13: 356165.91 | AA13: 391082.44 | AB13: 474237.38
A14: 1 | C14: 기타유동자산 | E14: 9051.3 | F14: 9051.3 | G14: 12040.68 | H14: 14130.14 | I14: 15952.97 | J14: 14647.14 | K14: 14647.14 | L14: 14546.24 | M14: 16315.88 | Y14: 15258.84 | Z14: 15258.84 | AA14: 29390.95 | AB14: 33442.32
A15: 1 | C15: 비유동자산 | E15: 450755.27 | F15: 450755.27 | G15: 449351.04 | H15: 482798.51 | I15: 541209.93 | J15: 485156.75 | K15: 485156.75 | L15: 502326.36 | M15: 477828.77 | Y15: 663839.01 | Z15: 663839.01 | AA15: 1054041 | AB15: 1130671.8
A16: 1 | C16: 장기금융자산 | E16: 518.77 | F16: 518.77 | G16: 1472 | H16: 3639.48 | I16: 5621.98 | J16: 8008.43 | K16: 8008.43 | L16: 7778.89 | M16: 8472.58 | Y16: 1158.77 | Z16: 1158.77 | AA16: 1158.77 | AB16: 1460.03
A17: 1 | C17: 투자자산 | E17: 3668.07 | F17: 3668.07 | G17: 3276.48 | H17: 5479.86 | I17: 7421.14 | J17: 44759.74 | K17: 44759.74 | L17: 44784.07 | M17: 9887.23 | Y17: 1517.76 | Z17: 1517.76 | AA17: 1866.96 | AB17: 128253.11
A18: 1 | C18: 종속기업및관계기업투자 | E18: 2839.41 | F18: 2839.41 | G18: 1514.03 | H18: 1532.32 | I18: 1532.32 | J18: 36484.57 | K18: 36484.57 | L18: 36624.78 | M18: 1076.27
A19: 1 | C19: 장기대여금 | E19: 309.89 | F19: 309.89 | G19: 290.45 | H19: 308.06 | I19: 266.84 | J19: 266.74 | K19: 266.74 | L19: 380.4 | M19: 338.38 | Y19: 358.99 | Z19: 358.99 | AA19: 463.3
A20: 1 | C20: 장기매출채권및기타채권 | E20: 579.58 | F20: 579.58 | G20: 591.47 | H20: 593.29 | I20: 596.43 | J20: 591.97 | K20: 591.97 | L20: 608.81 | M20: 596.33 | Y20: 2734.92 | Z20: 2734.92 | AA20: 2278.51 | AB20: 3173.69
A21: 1 | C21: 유형자산 | E21: 361262.63 | F21: 361262.63 | G21: 359286.02 | H21: 359531.92 | I21: 357967.24 | J21: 354241.66 | K21: 354241.66 | L21: 356421.66 | M21: 366070.83 | Y21: 433599.71 | Z21: 433599.71 | AA21: 460320.15 | AB21: 493553.84
A22: 1 | C22: 사용권자산 | E22: 11937.8 | F22: 11937.8 | G22: 11592.36 | H22: 11237.53 | I22: 10805 | J22: 10742.3 | K22: 10742.3 | L22: 10533.81 | M22: 11288.93 | Y22: 9028.79 | Z22: 9028.79 | AA22: 8890.83 | AB22: 19496.9
A23: 1 | C23: 기타비유동자산 | E23: 13689.75 | F23: 13689.75 | G23: 13217.1 | H23: 13172.23 | I23: 13028.98 | J23: 11779.6 | K23: 11779.6 | L23: 12044.73 | M23: 12723.46 | Y23: 16298.55 | Z23: 16298.55 | AA23: 323080.24 | AB23: 26664.74
A24: 1 | C24: 투자부동산 | E24: 47673.85 | F24: 47673.85 | G24: 47673.85 | H24: 47169.78 | I24: 47169.78 | J24: 47192.31 | K24: 47192.31 | L24: 47192.31 | M24: 47192.31 | Y24: 48965.82 | Z24: 48965.82 | AA24: 48965.82 | AB24: 48965.82
A25: 1 | C25: 무형자산 | E25: 3755.14 | F25: 3755.14 | G25: 3534.4 | H25: 3429.61 | I25: 3488.19 | J25: 3448.29 | K25: 3448.29 | L25: 3209.51 | M25: 2967.92 | Y25: 9617.77 | Z25: 9617.77 | AA25: 20383.14
A26: 1 | C26: 이연법인세자산 | E26: 13995.03 | F26: 13995.03 | G26: 14685.46 | H26: 14877.67 | I26: 13452.88 | J26: 13110.98 | K26: 13110.98 | L26: 11554.47 | M26: 11454.18 | Y26: 77750.89 | Z26: 77750.89 | AA26: 64689.18 | AB26: 65305.78
A27: 1 | C27: 자산총계 | E27: 795624.73 | F27: 795624.73 | G27: 803199.65 | H27: 872117.46 | I27: 1080707 | J27: 956230.29 | K27: 956230.29 | L27: 994873.36 | M27: 1030230.8 | Y27: 1695690.3 | Z27: 1695690.3 | AA27: 1910569.6 | AB27: 2170764.7
A28: 1 | C28: 유동부채 | E28: 431103.69 | F28: 431103.69 | G28: 475517.02 | H28: 549023.56 | I28: 606568.37 | J28: 498756.38 | K28: 498756.38 | L28: 533646.28 | M28: 518471.56 | Y28: 611221.29 | Z28: 611221.29 | AA28: 722234.12 | AB28: 818702.3
A29: 1 | C29: 매입채무및기타채무 | E29: 124028.52 | F29: 124028.52 | G29: 132551.37 | H29: 132319.06 | I29: 118165.31 | J29: 133169.77 | K29: 133169.77 | L29: 140100.22 | M29: 144542.5 | Y29: 179006.96 | Z29: 179006.96 | AA29: 229328.81 | AB29: 220566.4
A30: 1 | C30: 계약부채 | E30: 2381.61 | F30: 2381.61 | G30: 2232.58 | H30: 2337.48 | I30: 2295.76 | J30: 125312.31 | K30: 125312.31 | L30: 136489.79 | M30: 153159.35 | Y30: 250874.74 | Z30: 250874.74 | AA30: 269004.85 | AB30: 382815.21
A31: 1 | C31: 단기차입금 | E31: 127850.09 | F31: 127850.09 | G31: 137895.08 | H31: 148104.69 | I31: 128402.11 | J31: 125000 | K31: 125000 | L31: 125000 | M31: 143900 | AB31: 21576.59
A32: 1 | C32: 유동성장기부채 | E32: 8412 | F32: 8412 | G32: 12470.9 | H32: 62555.8 | I32: 60055.75 | J32: 57055.75 | K32: 57055.75 | L32: 54055.75 | M32: 4055.75 | Y32: 43008.75 | Z32: 43008.75 | AA32: 45391.85 | AB32: 0
A33: 1 | C33: 선수금 | E33: 128935.23 | F33: 128935.23 | G33: 130096.7 | H33: 119213.08 | I33: 125753.52
A34: 1 | C34: 기타유동부채 | E34: 143004.11 | F34: 143004.11 | G34: 147007.37 | H34: 138395.35 | I34: 144496.54 | J34: 16453.15 | K34: 16453.15 | L34: 19222.68 | M34: 20402.79 | Y34: 51443.19 | Z34: 51443.19 | AA34: 39711.02 | AB34: 49744.45
A35: 1 | C35: 단기충당부채 | E35: 7490.2 | F35: 7490.2 | G35: 20519.14 | H35: 16271.12 | I35: 12649.07 | J35: 9805.65 | K35: 9805.65 | L35: 10302.54 | M35: 7322.26 | Y35: 5951.68 | Z35: 5951.68 | AA35: 5357.49 | AB35: 6150.66
A36: 1 | C36: 비유동부채 | E36: 155419.72 | F36: 155419.72 | G36: 163610.83 | H36: 190146.91 | I36: 249697.55 | J36: 235848.09 | K36: 235848.09 | L36: 233601.97 | M36: 284381.98 | Y36: 528366.07 | Z36: 528366.07 | AA36: 578302.71 | AB36: 702314.5
A37: 1 | C37: 장기차입금 | E37: 75708 | F37: 75708 | G37: 72335.1 | H37: 21723.2 | I37: 20709.06 | J37: 19695.12 | K37: 19695.12 | L37: 18681.18 | M37: 17667.24 | Y37: 10000 | Z37: 10000 | AA37: 10000 | AB37: 10000
A38: 1 | C38: 장기매입채무및기타채무 | E38: 9704.52 | F38: 9704.52 | G38: 9530.38 | H38: 9235.66 | I38: 8963.7 | J38: 8747.39 | K38: 8747.39 | L38: 8670.86 | M38: 9188.19 | Y38: 20095.14 | Z38: 20095.14 | AA38: 11718.59
A39: 1 | C39: 확정급여부채 | E39: 9270.24 | F39: 9270.24 | G39: 11571.13 | H39: 12349.59 | I39: 13244.12 | J39: 4818.18 | K39: 4818.18 | L39: 7560.97 | M39: 8345.16 | Y39: 8347.75 | Z39: 8347.75 | AA39: 10306.64 | AB39: 9637.45
A40: 1 | C40: 장기충당부채 | E40: 5706.54 | F40: 5706.54 | G40: 19062.5 | H40: 37332.88 | I40: 21780.78 | J40: 15612.39 | K40: 15612.39 | L40: 7332.01 | M40: 5306.71 | Y40: 8035.87 | Z40: 8035.87 | AA40: 7031.03 | AB40: 8080.48
A41: 1 | C41: 기타비유동부채 | E41: 3465.35 | F41: 3465.35 | G41: 3400.47 | H41: 3503.95 | I41: 3607.43 | J41: 3241.2 | K41: 3241.2 | L41: 3654.77 | M41: 3560.23 | Y41: 10723.87 | Z41: 10723.87 | AA41: 11450.32 | AB41: 11975.4
A42: 1 | C42: 부채총계 | E42: 586523.41 | F42: 586523.41 | G42: 639127.85 | H42: 739170.46 | I42: 856265.92 | J42: 734604.47 | K42: 734604.47 | L42: 767248.25 | M42: 802853.54 | Y42: 1139587.4 | Z42: 1139587.4 | AA42: 1300536.8 | AB42: 1521016.8
A43: 1 | C43: 자본금 | E43: 46721.25 | F43: 46721.25 | G43: 46721.25 | H43: 46721.25 | I43: 71543.99 | J43: 71543.99 | K43: 71543.99 | L43: 71543.99 | M43: 71543.99 | Y43: 83447.14 | Z43: 83447.14 | AA43: 83447.14 | AB43: 83447.14
A44: 1 | C44: 자본잉여금 | E44: 208952.94 | F44: 208952.94 | G44: 208952.94 | H44: 208952.94 | I44: 273469.85 | J44: 273460.96 | K44: 273460.96 | L44: 273460.96 | M44: 273460.96 | Y44: 352820.98 | Z44: 352820.98 | AA44: 353327.81 | AB44: 355519.07
A45: 1 | C45: 기타자본 | E45: -54788.96 | F45: -54788.96 | G45: -54788.96 | H45: -54788.96 | I45: -54909.84 | J45: -54909.84 | K45: -54909.84 | L45: -54909.84 | M45: -54909.84 | Y45: -54909.84 | Z45: -54909.84 | AA45: -54909.84 | AB45: -50772.36
A46: 1 | C46: 기타포괄이익누계액 | E46: 79022.73 | F46: 79022.73 | G46: 78415.03 | H46: 78246 | I46: 78243.22 | J46: 79075.99 | K46: 79075.99 | L46: 79414.06 | M46: 78783.25 | Y46: 84457.58 | Z46: 84457.58 | AA46: 85027.33 | AB46: 85076.17
A47: 1 | C47: 이익잉여금 | E47: -70806.64 | F47: -70806.64 | G47: -115228.47 | H47: -146184.23 | I47: -143906.15 | J47: -147545.28 | K47: -147545.28 | L47: -141884.06 | M47: -141501.07 | Y47: 90287.04 | Z47: 90287.04 | AA47: 143140.38 | AB47: 176477.86
A48: 1 | C48: 자본총계 | E48: 209101.32 | F48: 209101.32 | G48: 164071.79 | H48: 132947 | I48: 224441.08 | J48: 221625.83 | K48: 221625.83 | L48: 227625.11 | M48: 227377.29 | Y48: 556102.9 | Z48: 556102.9 | AA48: 610032.82 | AB48: 649747.88
A49: 1 | C49: 부채와자본총계 | E49: 795624.73 | F49: 795624.73 | G49: 803199.65 | H49: 872117.46 | I49: 1080707 | J49: 956230.29 | K49: 956230.29 | L49: 994873.36 | M49: 1030230.8 | Y49: 1695690.3 | Z49: 1695690.3 | AA49: 1910569.6 | AB49: 2170764.7
A50: 1 | C50: 지배주주지분 | E50: 209101.32 | F50: 209101.32 | G50: 164071.79 | H50: 132947 | I50: 224441.08 | J50: 221625.83 | K50: 221625.83 | L50: 227625.11 | M50: 227377.29 | Y50: 556102.9 | Z50: 556102.9 | AA50: 610032.82 | AB50: 649747.88
... A53: 1 | C53: 이자발생자산 | E53: 67416.28 | F53: 67416.28 | G53: 74029.54 | H53: 66851.5 | I53: 139504.21 | J53: 77825 | K53: 77825 | L53: 88124.86 | M53: 55571.9 | Y53: 411972.8 | Z53: 411972.8 | AA53: 121979.73 | AB53: 307141.31
A54: 1 | C54: 매각예정비유동자산및처분자산 | J54: 6927.38 | K54: 6927.38 | L54: 7220.98 | M54: 42412.49
A55: 1 | C55: 비유동계약부채 | J55: 150627.17 | K55: 150627.17 | L55: 159766.33 | M55: 176226.57 | Y55: 397590.94 | Z55: 397590.94 | AA55: 396812.13 | AB55: 482270.11
A56: 1 | C56: 사채 | M56: 39103.92
A57: 1 | C57: 당기법인세부채(미지급법인세) | Y57: 2440.38 | Z57: 2440.38 | AA57: 4064.64 | AB57: 1940.49
A58: 1 | C58: 유동파생상품자산 | AA58: 5381.3
A59: 1 | C59: 비유동파생상품자산 | AA59: 244.89
A60: 1 | C60: 단기파생상품부채 | AA60: 46.99 | AB60: 0
A61: 1 | C61: 단기금융부채 | AA61: 46.99 | AB61: 135908.49
A62: 1 | C62: 기타유동금융자산 | AB62: 56538.88
A63: 1 | C63: 유동확정계약자산 | AB63: 142045.33
A64: 1 | C64: 비유동확정계약자산 | AB64: 126793.08
A65: 1 | C65: 단기금융부채(face) | AB65: 21576.59
A66: 1 | C66: 기타유동금융부채 | AB66: 135908.49
A67: 1 | C67: 기타비유동금융부채 | AB67: 134212.82
A68: 1 | C68: 장기금융부채 | AB68: 134279.17
A69: 1 | C69: 장기파생상품부채 | AB69: 66.35
A70: 1 | C70: 이연법인세부채 | AB70: 25380.74
A71: 1 | C71: 비지배주주지분 | AB71: 0
A72: 1 | C72: 매출액(수익) | E72: 195696.52 | G72: 177843.36 | H72: 186463.86 | I72: 175722.69 | J72: 224212.93 | K72: 764242.84 | L72: 199346.87 | M72: 189045.67 | AA72: 345239.42 | AB72: 362219.9
A73: 1 | C73: 매출원가 | E73: 195835.77 | G73: 172877.78 | H73: 208911.14 | I73: 167705.44 | J73: 212486.99 | K73: 761981.35 | L73: 186268.23 | M73: 177428.85 | AA73: 279847.04 | AB73: 287115.93
A74: 1 | C74: 매출총이익 | E74: -139.25 | G74: 4965.59 | H74: -22447.28 | I74: 8017.25 | J74: 11725.95 | K74: 2261.51 | L74: 13078.64 | M74: 11616.82 | AA74: 65392.38 | AB74: 75103.97
A75: 1 | C75: 판관비 | E75: 7419.42 | G75: 7522.54 | H75: 8083.85 | I75: 7499.68 | J75: 8689.66 | K75: 31795.73 | L75: 9004.54 | M75: 8143.45 | AA75: 14013.44 | AB75: 37193.26
A76: 1 | C76: 영업이익 | E76: -7558.67 | G76: -2556.95 | H76: -30531.13 | I76: 517.58 | J76: 3036.28 | K76: -29534.22 | L76: 4074.1 | M76: 3473.37 | AA76: 51378.94 | AB76: 37910.72
A77: 1 | C77: 금융수익 | E77: 3453.06 | G77: 15427.54 | H77: 70781.75 | I77: 144323.12 | J77: -93430.63 | K77: 137101.78 | L77: 58707.19 | M77: 26858.49 | AA77: 211830.29 | AB77: 87195.22
A78: 1 | C78: 금융비용 | E78: 5617.08 | G78: 16710.29 | H78: 71471.27 | I78: 141504.97 | J78: -82449.81 | K78: 147236.72 | L78: 61685.47 | M78: 29729.58 | AA78: 192402.43 | AB78: 83533.44
A79: 1 | C79: 기타영업외수익 | E79: 3759.85 | G79: 33.08 | H79: 131.94 | I79: 394.18 | J79: 3318.81 | K79: 3878.01 | L79: 6078.63 | M79: 323.18 | AA79: 79.09 | AB79: 146.41
A80: 1 | C80: 기타영업외비용 | E80: 10781.43 | G80: 50.17 | H80: 190.99 | I80: 27.03 | J80: 1260.33 | K80: 1528.52 | L80: 53.68 | M80: 359.17 | AA80: 1767.01 | AB80: 5855.47
A81: 1 | C81: 종속기업,공동지배기업및관계기업관련손익 | E81: 32.95 | G81: -862.13 | H81: -3.41 | J81: -483.42 | L81: 96.95 | M81: -0.15
A82: 1 | C82: 지분법관련손익 | E82: 32.95 | G82: -862.13 | H82: -3.41 | J82: -483.42 | L82: 96.95 | M82: -0.15
A83: 1 | C83: 법인세비용차감전계속사업이익 | E83: -16711.33 | G83: -4718.91 | H83: -31283.11 | I83: 3702.87 | J83: -6369.48 | K83: -38668.63 | L83: 7217.73 | M83: 566.14 | AA83: 69118.88 | AB83: 35863.43
A84: 1 | C84: 법인세비용 | E84: -3075.28 | G84: 8.44 | H84: -192.21 | I84: 1424.79 | J84: 362.75 | K84: 1603.77 | L84: 1556.51 | M84: 183.14 | AA84: 16265.55 | AB84: 2663.59
A85: 1 | C85: 계속사업이익 | E85: -13636.05 | G85: -4727.35 | H85: -31090.9 | I85: 2278.08 | J85: -6732.22 | K85: -40272.39 | L85: 5661.21 | M85: 383 | AA85: 52853.34 | AB85: 33199.84
A86: 1 | C86: 당기순이익 | E86: -13636.05 | G86: -4727.35 | H86: -31090.9 | I86: 2278.08 | J86: -6732.22 | K86: -40272.39 | L86: 5661.21 | M86: 383 | AA86: 52853.34 | AB86: 33199.84
A87: 1 | C87: (지배주주지분)당기순이익 | E87: -13636.05 | G87: -4727.35 | H87: -31090.9 | I87: 2278.08 | J87: -6732.22 | K87: -40272.39 | L87: 5661.21 | M87: 383 | AA87: 52853.34 | AB87: 33199.84
A88: 1 | C88: 금융손익 | E88: -2164.02 | G88: -1282.75 | H88: -689.52 | I88: 2818.15 | J88: -10980.82 | K88: -10134.94 | L88: -2978.28 | M88: -2871.09 | AA88: 19427.86 | AB88: 3661.78
A89: 1 | C89: 기타영업외손익 | E89: -7021.58 | G89: -17.09 | H89: -59.05 | I89: 367.15 | J89: 2058.48 | K89: 2349.49 | L89: 6024.95 | M89: -35.99 | AA89: -1687.92 | AB89: -5709.06
A90: 1 | C90: 총포괄손익 | E90: -15472.35 | G90: -5335.05 | H90: -31124.79 | I90: 2275.3 | J90: -2806.36 | K90: -36990.9 | L90: 5999.28 | M90: -247.81 | AA90: 53423.09 | AB90: 33386.32
A91: 1 | C91: 이자수익 | G91: 73.03 | H91: 85.59 | I91: 377.56 | J91: 541.54 | K91: 1077.72 | L91: 332.92 | M91: 381.4 | AA91: 3273.17 | AB91: 1784.17
A92: 1 | C92: 이자비용 | G92: 2054.84 | H92: 2475.73 | I92: 2532.11 | J92: 2539.39 | K92: 9602.07 | L92: 2607.75 | M92: 2969.32 | AA92: 552.43 | AB92: 726.1
A93: 1 | C93: 외환차익 | G93: 3518.18 | H93: 6007.98 | I93: 9105.88 | J93: 6881.07 | K93: 25513.11 | L93: 6949.4 | M93: 6494.07 | AA93: 66794.41 | AB93: 40928.65
A94: 1 | C94: 외환차손 | G94: 1601.86 | H94: 2871.11 | I94: 2407.15 | J94: 15101.93 | K94: 21982.05 | L94: 6565.81 | M94: 6017.84 | AA94: 49388.18 | AB94: 32548.55
A95: 1 | C95: 외화환산이익 | G95: 437.59 | H95: 713.79 | I95: 2108.99 | J95: -2535.05 | K95: 725.32 | L95: 546.35 | M95: 1064.89 | AA95: 7836.39 | AB95: -4059.95
A96: 1 | C96: 외화환산손실 | G96: 245.16 | H96: 61.58 | I96: 475.02 | J96: 1774 | K96: 2555.76 | L96: 447.04 | M96: -273.25 | AA96: 2517.68 | AB96: -2358.13
A97: 1 | C97: 파생상품이익 | G97: 1297.39 | H97: -584.27 | I97: 16.41 | J97: 35573.24 | K97: 36302.77 | L97: 2487.59 | M97: 1490.48 | AA97: 3123.64 | AB97: 838.03
A98: 1 | C98: 파생상품손실 | G98: 11163.04 | H98: 66701.98 | I98: 135648.36 | J98: -132623.79 | K98: 80889.59 | L98: 50193.14 | M98: 19305.85 | AA98: 138535 | AB98: 51104.13
A99: 1 | C99: 이자손익 | G99: -1981.81 | H99: -2390.14 | I99: -2154.55 | J99: -1997.85 | K99: -8524.35 | L99: -2274.83 | M99: -2587.92 | AA99: 2720.74 | AB99: 1058.07
A100: 1 | C100: 배당금수익 | H100: 0.46 | I100: 20.96 | J100: 0 | AA100: 0 | AB100: 0
A101: 1 | C101: 영업외손익 | AB101: -2047.28
A102: 1 | C102: (비지배주주지분)당기순이익 | AB102: 0
...

Sheet BS별도
B1: (백만원) | C1: 이름: BS별도H | E1: 4Q21 | F1: 2021 | G1: 1Q22 | H1: 2Q22 | I1: 3Q22 | J1: 4Q22 | K1: 2022 | L1: 1Q23 | M1: 2Q23 | N1: 3Q23 | O1: 4Q23 | P1: 2023 | Q1: 1Q24 | R1: 2Q24 | S1: 3Q24 | T1: 4Q24 | U1: 2024 | V1: 1Q25 | W1: 2Q25 | X1: 3Q25 | Y1: 4Q25 | Z1: 2025 | AA1: 1Q26 | AB1: 2Q26 | AC1: 3Q26 | AD1: 4Q26 | AE1: 2026 | AF1: 1Q27 | AG1: 2Q27 | AH1: 3Q27 | AI1: 4Q27 | AJ1: 2027 | AK1: 1Q28 | AL1: 2Q28 | AM1: 3Q28 | AN1: 4Q28 | AO1: 2028
B2: 별도 | D2: fin json(kship_fin.py)
B3: 한화엔진(별) | C3: UPDATE: 26-10-13 | E3: 1 | F3: 2 | G3: 3 | H3: 4 | I3: 5 | J3: 6 | K3: 7 | L3: 8 | M3: 9 | N3: 10 | O3: 11 | P3: 12 | Q3: 13 | R3: 14 | S3: 15 | T3: 16 | U3: 17 | V3: 18 | W3: 19 | X3: 20 | Y3: 21 | Z3: 22 | AA3: 23 | AB3: 24 | AC3: 25 | AD3: 26 | AE3: 27 | AF3: 28 | AG3: 29 | AH3: 30 | AI3: 31 | AJ3: 32 | AK3: 33 | AL3: 34 | AM3: 35 | AN3: 36 | AO3: 37
B4: Account Code | C4: AccountNAME | E4: 2021.12 | F4: 2021.12A | G4: 2022.03 | H4: 2022.06 | I4: 2022.09 | J4: 2022.12 | K4: 2022.12A | L4: 2023.03 | M4: 2023.06 | N4: 2023.09 | O4: 2023.12 | P4: 2023.12A | Q4: 2024.03 | R4: 2024.06 | S4: 2024.09 | T4: 2024.12 | U4: 2024.12A | V4: 2025.03 | W4: 2025.06 | X4: 2025.09 | Y4: 2025.12 | Z4: 2025.12A | AA4: 2026.03 | AB4: 2026.06 | AC4: 2026.09 | AD4: 2026.12 | AE4: 2026.12A | AF4: 2027.03 | AG4: 2027.06 | AH4: 2027.09 | AI4: 2027.12 | AJ4: 2027.12A | AK4: 2028.03 | AL4: 2028.06 | AM4: 2028.09 | AN4: 2028.12 | AO4: 2028.12A
A5: 1 | C5: 유동자산 | E5: 346614.99 | F5: 346614.99 | G5: 356365.88 | H5: 390253.03 | I5: 540764.2 | J5: 471073.55 | K5: 471073.55 | L5: 492253.39 | M5: 552402.07 | N5: 611065.18 | O5: 655667.27 | P5: 655667.27 | Q5: 750413.99 | R5: 699944.85 | S5: 612864.18 | T5: 785001.24 | U5: 785001.24 | V5: 851970.85 | W5: 853459.44 | X5: 917610.92 | Y5: 1031851.2 | Z5: 1031851.2 | AA5: 852962.37 | AB5: 976282.4
A6: 1 | C6: 현금및현금성자산 | E6: 53585.63 | F6: 53585.63 | G6: 63630.95 | H6: 54135.08 | I6: 91288.83 | J6: 54559.25 | K6: 54559.25 | L6: 66371.55 | M6: 33083.66 | N6: 47857.15 | O6: 102831.94 | P6: 102831.94 | Q6: 206784.17 | R6: 98484.97 | S6: 80109 | T6: 133001.19 | U6: 133001.19 | V6: 123194.8 | W6: 203510.89 | X6: 218647.84 | Y6: 276708.03 | Z6: 276708.03 | AA6: 46502.75 | AB6: 156711.61
A7: 1 | C7: 단기금융상품 | E7: 12702.29 | F7: 12702.29 | G7: 8568 | H7: 8497.16 | I7: 42291.27 | J7: 15156.82 | K7: 15156.82 | L7: 13870.42 | M7: 13910.76 | N7: 16846.02 | O7: 18612.47 | P7: 18612.47 | Q7: 16917.66 | R7: 24899.77 | S7: 12539.26 | T7: 6649.16 | U7: 6649.16 | V7: 65458.64 | W7: 133814.27 | X7: 150479.7 | Y7: 133988.65 | Z7: 133988.65 | AA7: 65265.9
A8: 1 | C8: 단기금융자산 | E8: 14059.78 | F8: 14059.78 | G8: 10082.11 | H8: 8610.46 | I8: 42395.52 | J8: 15257.32 | K8: 15257.32 | L8: 13974.42 | M8: 14015.66 | N8: 16953.42 | O8: 18726.37 | P8: 18726.37 | Q8: 17033.76 | R8: 25014.52 | S8: 12656.06 | T8: 6766.66 | U8: 6766.66 | V8: 65568.84 | W8: 133922.52 | X8: 150593.6 | Y8: 134106 | Z8: 134106 | AA8: 70823.4 | AB8: 142045.33
A9: 1 | C9: 단기대여금 | E9: 1357.49 | F9: 1357.49 | G9: 1514.11 | H9: 113.3 | I9: 104.25 | J9: 100.5 | K9: 100.5 | L9: 104 | M9: 104.9 | N9: 107.4 | O9: 113.9 | P9: 113.9 | Q9: 116.1 | R9: 114.75 | S9: 116.8 | T9: 117.5 | U9: 117.5 | V9: 110.2 | W9: 108.25 | X9: 113.9 | Y9: 117.35 | Z9: 117.35 | AA9: 176.2
A10: 1 | C10: 매출채권및기타채권 | E10: 61460.63 | F10: 61460.63 | G10: 58679.42 | H10: 52273.4 | I10: 51497.35 | J10: 71262.89 | K10: 71262.89 | L10: 69235.43 | M10: 72694.88 | N10: 68484.46 | O10: 86308.2 | P10: 86308.2 | Q10: 101001.9 | R10: 117001.28 | S10: 103633.04 | T10: 135080.97 | U10: 135080.97 | V10: 159251.38 | W10: 131598.76 | X10: 117452.15 | Y10: 165742.58 | Z10: 165742.58 | AA10: 193202 | AB10: 123760.64
A11: 1 | C11: 계약자산 | E11: 12664.66 | F11: 12664.66 | N11: 877.05 | O11: 700.7 | P11: 700.7 | R11: 530.23 | S11: 598.73 | T11: 4492.99 | U11: 4492.99 | V11: 0 | W11: 0 | X11: 0
A12: 1 | C12: 당기법인세자산(선급법인세) | E12: 146.29 | F12: 146.29 | G12: 152.66 | H12: 117.23 | I12: 139.42 | J12: 211.85 | K12: 211.85 | L12: 257.65 | M12: 312.85 | N12: 389.14 | O12: 385.46 | P12: 385.46 | Q12: 83.7 | R12: 44.69 | T12: 0 | U12: 0 | V12: 193.35 | W12: 127.35 | X12: 4.3 | Y12: 18.3 | Z12: 18.3 | AB12: 26.79
A13: 1 | C13: 재고자산 | E13: 179045.98 | F13: 179045.98 | G13: 190016.21 | H13: 218947.82 | I13: 241888.53 | J13: 252292.72 | K13: 252292.72 | L13: 269549.22 | M13: 322351.85 | N13: 374061.81 | O13: 366491.88 | P13: 366491.88 | Q13: 359722.18 | R13: 369663.85 | S13: 358367.95 | T13: 370325.63 | U13: 370325.63 | V13: 374170.9 | W13: 328435.94 | X13: 348771.35 | Y13: 356165.91 | Z13: 356165.91 | AA13: 391082.44 | AB13: 466105.59
A14: 1 | C14: 기타유동자산 | E14: 8544.04 | F14: 8544.04 | G14: 11678.34 | H14: 14156.09 | I14: 15935.33 | J14: 14647.14 | K14: 14647.14 | L14: 14546.24 | M14: 16315.88 | N14: 14592.13 | O14: 16741.12 | P14: 16741.12 | Q14: 14172.59 | R14: 14461.98 | S14: 15426.89 | T14: 16454.51 | U14: 16454.51 | V14: 16837.3 | W14: 15336.42 | X14: 17561.28 | Y14: 15258.84 | Z14: 15258.84 | AA14: 29319.9 | AB14: 31956.04
A15: 1 | C15: 비유동자산 | E15: 445773.77 | F15: 445773.77 | G15: 444183.58 | H15: 478591.64 | I15: 536908.77 | J15: 485156.75 | K15: 485156.75 | L15: 502186.15 | M15: 477828.77 | N15: 502787.6 | O15: 481190.9 | P15: 481190.9 | Q15: 499761.5 | R15: 520351.33 | S15: 508758.52 | T15: 628100.71 | U15: 628100.71 | V15: 633346.55 | W15: 576292.46 | X15: 576697.09 | Y15: 663843.29 | Z15: 663843.29 | AA15: 1057216.7 | AB15: 1085203.6
A16: 1 | C16: 장기금융자산 | E16: 518.77 | F16: 518.77 | G16: 1472 | H16: 3639.48 | I16: 5621.98 | J16: 8008.43 | K16: 8008.43 | L16: 7778.89 | M16: 8472.58 | N16: 5572.35 | O16: 3072.46 | P16: 3072.46 | Q16: 2702.18 | R16: 1158.77 | S16: 1158.77 | T16: 1158.77 | U16: 1158.77 | V16: 1158.77 | W16: 1158.77 | X16: 1158.77 | Y16: 1158.77 | Z16: 1158.77 | AA16: 1158.77 | AB16: 1220.54
A17: 1 | C17: 투자자산 | E17: 3668.07 | F17: 3668.07 | G17: 3276.48 | H17: 5461.57 | I17: 7402.85 | J17: 44759.74 | K17: 44759.74 | L17: 44643.86 | M17: 9887.23 | N17: 7064.51 | O17: 4611.29 | P17: 4611.29 | Q17: 4236.08 | R17: 2735.22 | S17: 2738.39 | T17: 2794.28 | U17: 2794.28 | V17: 2840.82 | W17: 2979.34 | X17: 1543.45 | Y17: 1522.04 | Z17: 1522.04 | AA17: 311931.24 | AB17: 128013.62
A18: 1 | C18: 종속기업및관계기업투자 | E18: 2839.41 | F18: 2839.41 | G18: 1514.03 | H18: 1514.03 | I18: 1514.03 | J18: 36484.57 | K18: 36484.57 | L18: 36484.57 | M18: 1076.27 | N18: 1153.64 | O18: 1154.81 | P18: 1154.81 | Q18: 1154.81 | R18: 1236.01 | S18: 1239.42 | T18: 1286.54 | U18: 1286.54 | V18: 1352.22 | W18: 1493.73 | X18: 0 | Y18: 4.28 | Z18: 4.28 | AA18: 310064.28
A19: 1 | C19: 장기대여금 | E19: 309.89 | F19: 309.89 | G19: 290.45 | H19: 308.06 | I19: 266.84 | J19: 266.74 | K19: 266.74 | L19: 380.4 | M19: 338.38 | N19: 338.52 | O19: 384.02 | P19: 384.02 | Q19: 379.09 | R19: 340.44 | S19: 340.2 | T19: 348.97 | U19: 348.97 | V19: 329.83 | W19: 326.84 | X19: 384.68 | Y19: 358.99 | Z19: 358.99 | AA19: 463.3
A20: 1 | C20: 장기매출채권및기타채권 | E20: 579.58 | F20: 579.58 | G20: 591.47 | H20: 593.29 | I20: 596.43 | J20: 591.97 | K20: 591.97 | L20: 608.81 | M20: 596.33 | N20: 603.52 | O20: 589.92 | P20: 589.92 | Q20: 1452.58 | R20: 1407.18 | S20: 1406.88 | T20: 1493.53 | U20: 1493.53 | V20: 1801.61 | W20: 1819.5 | X20: 2685.11 | Y20: 2734.92 | Z20: 2734.92 | AA20: 2278.51 | AB20: 3083.55
A21: 1 | C21: 유형자산 | E21: 358378.92 | F21: 358378.92 | G21: 356224.49 | H21: 356637.32 | I21: 355015.27 | J21: 354241.66 | K21: 354241.66 | L21: 356421.66 | M21: 366070.83 | N21: 370471.9 | O21: 379948.53 | P21: 379948.53 | Q21: 384268.82 | R21: 392748.36 | S21: 410808.32 | T21: 415497.11 | U21: 415497.11 | V21: 417018.14 | W21: 415696.73 | X21: 425828.43 | Y21: 433599.71 | Z21: 433599.71 | AA21: 460320.15 | AB21: 490282.47
A22: 1 | C22: 사용권자산 | E22: 11937.8 | F22: 11937.8 | G22: 11592.36 | H22: 11237.53 | I22: 10805 | J22: 10742.3 | K22: 10742.3 | L22: 10533.81 | M22: 11288.93 | N22: 10936.94 | O22: 10791.77 | P22: 10791.77 | Q22: 10790.39 | R22: 10609.86 | S22: 10459.36 | T22: 10091 | U22: 10091 | V22: 9976.15 | W22: 9545.87 | X22: 9098.02 | Y22: 9028.79 | Z22: 9028.79 | AA22: 8890.83 | AB22: 9319.68
A23: 1 | C23: 기타비유동자산 | E23: 12421.68 | F23: 12421.68 | G23: 11932.44 | H23: 11878.24 | I23: 11698.07 | J23: 11779.6 | K23: 11779.6 | L23: 12044.73 | M23: 12723.46 | N23: 12682.66 | O23: 12176.2 | P23: 12176.2 | Q23: 12036.46 | R23: 11812.68 | S23: 12792.21 | T23: 12714.65 | U23: 12714.65 | V23: 17327.25 | W23: 14331.01 | X23: 13403.04 | Y23: 16298.55 | Z23: 16298.55 | AA23: 16191.63 | AB23: 16078.69
A24: 1 | C24: 투자부동산 | E24: 47673.85 | F24: 47673.85 | G24: 47673.85 | H24: 47169.78 | I24: 47169.78 | J24: 47192.31 | K24: 47192.31 | L24: 47192.31 | M24: 47192.31 | N24: 47192.31 | O24: 48965.82 | P24: 48965.82 | Q24: 48965.82 | R24: 48965.82 | S24: 48965.82 | T24: 48965.82 | U24: 48965.82 | V24: 48965.82 | W24: 48965.82 | X24: 48965.82 | Y24: 48965.82 | Z24: 48965.82 | AA24: 48965.82 | AB24: 48965.82
A25: 1 | C25: 무형자산 | E25: 3755.14 | F25: 3755.14 | G25: 3534.4 | H25: 3429.61 | I25: 3488.19 | J25: 3448.29 | K25: 3448.29 | L25: 3209.51 | M25: 2967.92 | N25: 2730.67 | O25: 2861.61 | P25: 2861.61 | Q25: 2717.67 | R25: 2714.87 | S25: 3302.65 | T25: 5712.95 | U25: 5712.95 | V25: 7078.43 | W25: 6866.4 | X25: 7420.32 | Y25: 9617.77 | Z25: 9617.77 | AA25: 20383.14
A26: 1 | C26: 이연법인세자산 | E26: 13165.33 | F26: 13165.33 | G26: 13864.2 | H26: 14877.67 | I26: 13452.88 | J26: 13110.98 | K26: 13110.98 | L26: 11554.47 | M26: 11454.18 | N26: 12124.08 | O26: 13062.19 | P26: 13062.19 | Q26: 10030.96 | R26: 5909.52 | S26: 3353.98 | T26: 16906.84 | U26: 16906.84 | V26: 16373.32 | W26: 25717.08 | X26: 25545.1 | Y26: 77750.89 | Z26: 77750.89 | AA26: 64689.18 | AB26: 65260.11
A27: 1 | C27: 자산총계 | E27: 792388.77 | F27: 792388.77 | G27: 800549.46 | H27: 868844.67 | I27: 1077673 | J27: 956230.29 | K27: 956230.29 | L27: 994439.54 | M27: 1030230.8 | N27: 1113852.8 | O27: 1136858.2 | P27: 1136858.2 | Q27: 1250175.5 | R27: 1220296.2 | S27: 1121622.7 | T27: 1413101.9 | U27: 1413101.9 | V27: 1485317.4 | W27: 1429751.9 | X27: 1494308 | Y27: 1695694.5 | Z27: 1695694.5 | AA27: 1910179.1 | AB27: 2061486
A28: 1 | C28: 유동부채 | E28: 428139.57 | F28: 428139.57 | G28: 472573.32 | H28: 545879.3 | I28: 603253.72 | J28: 498797.88 | K28: 498797.88 | L28: 533688.97 | M28: 518514.55 | N28: 596934.07 | O28: 603567.82 | P28: 603567.82 | Q28: 613162.88 | R28: 535412.69 | S28: 443990.06 | T28: 586563.18 | U28: 586563.18 | V28: 606765.29 | W28: 528929.2 | X28: 561720.42 | Y28: 611225.57 | Z28: 611225.57 | AA28: 722238.4 | AB28: 740378.58
A29: 1 | C29: 매입채무및기타채무 | E29: 123914.49 | F29: 123914.49 | G29: 132502.75 | H29: 132279.49 | I29: 118306.45 | J29: 133211.27 | K29: 133211.27 | L29: 140142.91 | M29: 144585.49 | N29: 148992.39 | O29: 199823.97 | P29: 199823.97 | Q29: 176885.8 | R29: 174927.17 | S29: 136815.45 | T29: 160663.68 | U29: 160663.68 | V29: 178995.03 | W29: 149408.71 | X29: 150287.02 | Y29: 179011.24 | Z29: 179011.24 | AA29: 229333.1 | AB29: 196418.51
A30: 1 | C30: 계약부채 | E30: 2381.61 | F30: 2381.61 | G30: 2232.58 | H30: 2337.48 | I30: 2295.76 | J30: 125312.31 | K30: 125312.31 | L30: 136489.79 | M30: 153159.35 | N30: 173445.3 | O30: 180982.12 | P30: 180982.12 | Q30: 190770.4 | R30: 208366.09 | S30: 203483.4 | T30: 226940.11 | U30: 226940.11 | V30: 246984.13 | W30: 235275.65 | X30: 245235.76 | Y30: 250874.74 | Z30: 250874.74 | AA30: 269004.85 | AB30: 352317.06
A31: 1 | C31: 단기차입금 | E31: 125000 | F31: 125000 | G31: 135000 | H31: 145000 | I31: 125000 | J31: 125000 | K31: 125000 | L31: 125000 | M31: 143900 | N31: 169600 | O31: 153000 | P31: 153000 | Q31: 151800 | R31: 50000 | S31: 36000 | T31: 30000 | U31: 30000 | V31: 30000 | W31: 20000 | X31: 20000
A32: 1 | C32: 유동성장기부채 | E32: 8412 | F32: 8412 | G32: 12470.9 | H32: 62555.8 | I32: 60055.75 | J32: 57055.75 | K32: 57055.75 | L32: 54055.75 | M32: 4055.75 | N32: 17805.75 | O32: 17055.75 | P32: 17055.75 | Q32: 16305.75 | T32: 0 | U32: 0 | V32: 0 | W32: 40602.7 | X32: 42000.98 | Y32: 43008.75 | Z32: 43008.75 | AA32: 45391.85 | AB32: 0
A33: 1 | C33: 선수금 | E33: 128935.23 | F33: 128935.23 | G33: 130096.7 | H33: 119213.08 | I33: 125753.52
A34: 1 | C34: 기타유동부채 | E34: 143004.11 | F34: 143004.11 | G34: 147007.37 | H34: 138395.35 | I34: 144442.86 | J34: 16453.15 | K34: 16453.15 | L34: 19222.68 | M34: 20402.79 | N34: 21652.81 | O34: 19618.75 | P34: 19618.75 | Q34: 20576.7 | R34: 27229.97 | S34: 29142.58 | T34: 37789.59 | U34: 37789.59 | V34: 30157.53 | W34: 37085.04 | X34: 42740.59 | Y34: 51443.19 | Z34: 51443.19 | AA34: 39711.02 | AB34: 47480.87
A35: 1 | C35: 단기충당부채 | E35: 7490.2 | F35: 7490.2 | G35: 20519.14 | H35: 16271.12 | I35: 12649.07 | J35: 9805.65 | K35: 9805.65 | L35: 10302.54 | M35: 7322.26 | N35: 6003.42 | O35: 5418.09 | P35: 5418.09 | Q35: 5691.98 | R35: 4891.72 | S35: 4377.74 | T35: 4565.94 | U35: 4565.94 | V35: 4889.84 | W35: 5136.11 | X35: 6979.16 | Y35: 5951.68 | Z35: 5951.68 | AA35: 5357.49 | AB35: 5588.93
A36: 1 | C36: 비유동부채 | E36: 155419.72 | F36: 155419.72 | G36: 163610.83 | H36: 190146.91 | I36: 249697.55 | J36: 235848.09 | K36: 235848.09 | L36: 233601.97 | M36: 284381.98 | N36: 291310.33 | O36: 309142.06 | P36: 309142.06 | Q36: 308196.85 | R36: 343200.79 | S36: 325077.87 | T36: 433242.98 | U36: 433242.98 | V36: 465322.02 | W36: 470769.71 | X36: 471031 | Y36: 528366.07 | Z36: 528366.07 | AA36: 578302.71 | AB36: 668541.61
A37: 1 | C37: 장기차입금 | E37: 75708 | F37: 75708 | G37: 72335.1 | H37: 21723.2 | I37: 20709.06 | J37: 19695.12 | K37: 19695.12 | L37: 18681.18 | M37: 17667.24 | N37: 2903.31 | O37: 2639.37 | P37: 2639.37 | Q37: 2375.43 | S37: 10000 | T37: 0 | U37: 0 | V37: 10000 | W37: 10000 | X37: 10000 | Y37: 10000 | Z37: 10000 | AA37: 10000 | AB37: 10000
A38: 1 | C38: 장기매입채무및기타채무 | E38: 9704.52 | F38: 9704.52 | G38: 9530.38 | H38: 9235.66 | I38: 8963.7 | J38: 8747.39 | K38: 8747.39 | L38: 8670.86 | M38: 9188.19 | N38: 8949.29 | O38: 8708.96 | P38: 8708.96 | Q38: 8723.85 | R38: 8988.13 | S38: 9593.13 | T38: 10549.09 | U38: 10549.09 | V38: 11746.72 | W38: 14009.95 | X38: 19180.03 | Y38: 20095.14 | Z38: 20095.14 | AA38: 11718.59
A39: 1 | C39: 확정급여부채 | E39: 9270.24 | F39: 9270.24 | G39: 11571.13 | H39: 12349.59 | I39: 13244.12 | J39: 4818.18 | K39: 4818.18 | L39: 7560.97 | M39: 8345.16 | N39: 9237.29 | O39: 7110.7 | P39: 7110.7 | Q39: 9561.63 | R39: 10721.55 | S39: 11737.22 | T39: 5049.89 | U39: 5049.89 | V39: 0 | W39: 4151.62 | X39: 3526.66 | Y39: 8347.75 | Z39: 8347.75 | AA39: 10306.64 | AB39: 9637.45
A40: 1 | C40: 장기충당부채 | E40: 5706.54 | F40: 5706.54 | G40: 19062.5 | H40: 37332.88 | I40: 21780.78 | J40: 15612.39 | K40: 15612.39 | L40: 7332.01 | M40: 5306.71 | N40: 5048.55 | O40: 5957.99 | P40: 5957.99 | Q40: 5491.21 | R40: 5564.97 | S40: 5566.76 | T40: 5582.28 | U40: 5582.28 | V40: 5916.9 | W40: 6367.33 | X40: 9962.44 | Y40: 8035.87 | Z40: 8035.87 | AA40: 7031.03 | AB40: 8080.48
A41: 1 | C41: 기타비유동부채 | E41: 3465.35 | F41: 3465.35 | G41: 3400.47 | H41: 3503.95 | I41: 3607.43 | J41: 3241.2 | K41: 3241.2 | L41: 3654.77 | M41: 3560.23 | N41: 3356.32 | O41: 3626.46 | P41: 3626.46 | Q41: 3648.44 | R41: 3763.86 | S41: 3879.28 | T41: 6359.6 | U41: 6359.6 | V41: 6568.92 | W41: 6778.24 | X41: 6987.55 | Y41: 10723.87 | Z41: 10723.87 | AA41: 11450.32 | AB41: 11797.38
A42: 1 | C42: 부채총계 | E42: 583559.29 | F42: 583559.29 | G42: 636184.16 | H42: 736026.2 | I42: 852951.27 | J42: 734645.96 | K42: 734645.96 | L42: 767290.94 | M42: 802896.53 | N42: 888244.41 | O42: 912709.87 | P42: 912709.87 | Q42: 921359.74 | R42: 878613.48 | S42: 769067.93 | T42: 1019806.2 | U42: 1019806.2 | V42: 1072087.3 | W42: 999698.91 | X42: 1032751.4 | Y42: 1139591.6 | Z42: 1139591.6 | AA42: 1300541.1 | AB42: 1408920.2
A43: 1 | C43: 자본금 | E43: 46721.25 | F43: 46721.25 | G43: 46721.25 | H43: 46721.25 | I43: 71543.99 | J43: 71543.99 | K43: 71543.99 | L43: 71543.99 | M43: 71543.99 | N43: 71543.99 | O43: 71543.99 | P43: 71543.99 | Q43: 83447.14 | R43: 83447.14 | S43: 83447.14 | T43: 83447.14 | U43: 83447.14 | V43: 83447.14 | W43: 83447.14 | X43: 83447.14 | Y43: 83447.14 | Z43: 83447.14 | AA43: 83447.14 | AB43: 83447.14
A44: 1 | C44: 자본잉여금 | E44: 208952.94 | F44: 208952.94 | G44: 208952.94 | H44: 208952.94 | I44: 273469.85 | J44: 273460.96 | K44: 273460.96 | L44: 273460.96 | M44: 273460.96 | N44: 273460.96 | O44: 273460.96 | P44: 273460.96 | Q44: 351036.02 | R44: 349583.69 | S44: 350027.26 | T44: 350248.55 | U44: 350248.55 | V44: 350675.84 | W44: 351519.66 | X44: 352227.27 | Y44: 352820.98 | Z44: 352820.98 | AA44: 353327.81 | AB44: 355519.07
A45: 1 | C45: 기타자본 | E45: -54788.96 | F45: -54788.96 | G45: -54788.96 | H45: -54788.96 | I45: -54909.84 | J45: -54909.84 | K45: -54909.84 | L45: -54909.84 | M45: -54909.84 | N45: -54909.84 | O45: -54909.84 | P45: -54909.84 | Q45: -54909.84 | R45: -54909.84 | S45: -54909.84 | T45: -54909.84 | U45: -54909.84 | V45: -54909.84 | W45: -54909.84 | X45: -54909.84 | Y45: -54909.84 | Z45: -54909.84 | AA45: -54909.84 | AB45: -50772.36
A46: 1 | C46: 기타포괄이익누계액 | E46: 77643.78 | F46: 77643.78 | G46: 77643.78 | H46: 77508.64 | I46: 77508.64 | J46: 78531.18 | K46: 78531.18 | L46: 78531.18 | M46: 78256.93 | N46: 79361.71 | O46: 85311.49 | P46: 85311.49 | Q46: 85630.26 | R46: 85641.79 | S46: 85484.67 | T46: 85556.14 | U46: 85556.14 | V46: 85654.44 | W46: 85698.51 | X46: 85751.31 | Y46: 84457.58 | Z46: 84457.58 | AA46: 84607.75 | AB46: 83765.5
A47: 1 | C47: 이익잉여금 | E47: -69699.53 | F47: -69699.53 | G47: -114163.71 | H47: -145575.41 | I47: -142890.96 | J47: -147041.97 | K47: -147041.97 | L47: -141477.7 | M47: -141017.74 | N47: -143848.45 | O47: -151258.32 | P47: -151258.32 | Q47: -136387.83 | R47: -122080.09 | S47: -111494.46 | T47: -71046.2 | U47: -71046.2 | V47: -51637.49 | W47: -35702.48 | X47: -4959.28 | Y47: 90287.04 | Z47: 90287.04 | AA47: 143165.11 | AB47: 180606.49
A48: 1 | C48: 자본총계 | E48: 208829.48 | F48: 208829.48 | G48: 164365.3 | H48: 132818.46 | I48: 224721.69 | J48: 221584.33 | K48: 221584.33 | L48: 227148.6 | M48: 227334.31 | N48: 225608.38 | O48: 224148.29 | P48: 224148.29 | Q48: 328815.75 | R48: 341682.7 | S48: 352554.77 | T48: 393295.79 | U48: 393295.79 | V48: 413230.09 | W48: 430052.99 | X48: 461556.6 | Y48: 556102.9 | Z48: 556102.9 | AA48: 609637.97 | AB48: 652565.84
A49: 1 | C49: 부채와자본총계 | E49: 792388.77 | F49: 792388.77 | G49: 800549.46 | H49: 868844.67 | I49: 1077673 | J49: 956230.29 | K49: 956230.29 | L49: 994439.54 | M49: 1030230.8 | N49: 1113852.8 | O49: 1136858.2 | P49: 1136858.2 | Q49: 1250175.5 | R49: 1220296.2 | S49: 1121622.7 | T49: 1413101.9 | U49: 1413101.9 | V49: 1485317.4 | W49: 1429751.9 | X49: 1494308 | Y49: 1695694.5 | Z49: 1695694.5 | AA49: 1910179.1 | AB49: 2061486
A50: 1 | C50: 지배주주지분 | E50: 208829.48 | F50: 208829.48 | G50: 164365.3 | H50: 132818.46 | I50: 224721.69 | J50: 221584.33 | K50: 221584.33 | L50: 227148.6 | M50: 227334.31 | N50: 225608.38 | O50: 224148.29 | P50: 224148.29 | Q50: 328815.75 | R50: 341682.7 | S50: 352554.77 | T50: 393295.79 | U50: 393295.79 | V50: 413230.09 | W50: 430052.99 | X50: 461556.6 | Y50: 556102.9 | Z50: 556102.9 | AA50: 609637.97 | AB50: 652565.84
... A53: 1 | C53: 이자발생자산 | E53: 68164.18 | F53: 68164.18 | G53: 75185.06 | H53: 66385.02 | I53: 139306.33 | J53: 77825 | K53: 77825 | L53: 88124.86 | M53: 55571.9 | N53: 70382.92 | O53: 124630.77 | P53: 124630.77 | Q53: 226520.11 | R53: 124658.26 | S53: 93923.83 | T53: 140926.62 | U53: 140926.62 | V53: 189922.41 | W53: 338592.18 | X53: 370400.21 | Y53: 411972.8 | Z53: 411972.8 | AA53: 118484.92 | AB53: 299977.48
A54: 1 | C54: 매각예정비유동자산및처분자산 | J54: 6927.38 | K54: 6927.38 | L54: 6927.38 | M54: 42412.49 | N54: 35500 | O54: 35500 | P54: 35500 | T54: 0 | U54: 0 | X54: 1395.62
A55: 1 | C55: 비유동계약부채 | J55: 150627.17 | K55: 150627.17 | L55: 159766.33 | M55: 176226.57 | N55: 182654.83 | O55: 227220.41 | P55: 227220.41 | Q55: 204861.01 | R55: 221092.61 | S55: 221208.98 | T55: 253183.14 | U55: 253183.14 | V55: 276878.67 | W55: 373782.48 | X55: 374682.94 | Y55: 397590.94 | Z55: 397590.94 | AA55: 396812.13 | AB55: 482270.11
A56: 1 | C56: 사채 | M56: 39103.92 | N56: 40080.84 | O56: 38452.73 | P56: 38452.73 | Q56: 40188.9 | R56: 41479.58 | S56: 39425.89 | T56: 43947.01 | U56: 43947.01 | V56: 43870.24 | W56: 0 | X56: 0
A57: 1 | C57: 당기법인세부채(미지급법인세) | Q57: 378.31 | R57: 467.73 | S57: 220.79 | T57: 869.53 | U57: 869.53 | V57: 585.81 | W57: 765.59 | X57: 591.53 | Y57: 2440.38 | Z57: 2440.38 | AA57: 4064.64 | AB57: 2664.73
A58: 1 | C58: 유동파생상품자산 | AA58: 5381.3
A59: 1 | C59: 비유동파생상품자산 | AA59: 244.89
A60: 1 | C60: 단기파생상품부채 | AA60: 46.99 | AB60: 0
A61: 1 | C61: 단기금융부채 | AA61: 46.99 | AB61: 135908.49
A62: 1 | C62: 장기파생상품부채 | AA62: 130714.21 | AB62: 66.35
A63: 1 | C63: 장기금융부채 | AA63: 130714.21 | AB63: 134279.17
A64: 1 | C64: 기타유동금융자산 | AB64: 55676.39
A65: 1 | C65: 유동확정계약자산 | AB65: 142045.33
A66: 1 | C66: 비유동확정계약자산 | AB66: 126793.08
A67: 1 | C67: 기타유동금융부채 | AB67: 135908.49
A68: 1 | C68: 기타비유동금융부채 | AB68: 134212.82
A69: 1 | C69: 매출액(수익) | E69: 195576.55 | G69: 177595.41 | H69: 186318.7 | I69: 175602.57 | J69: 224114.81 | K69: 763631.49 | L69: 199346.87 | M69: 189045.67 | N69: 187637.17 | O69: 278354.7 | P69: 854384.41 | Q69: 293365.12 | R69: 286485.26 | S69: 296086.23 | T69: 326268.1 | U69: 1202204.7 | V69: 318182 | W69: 387700.4 | X69: 297345.31 | Y69: 367829.64 | Z69: 1371057.4 | AA69: 345239.42 | AB69: 331514.92
A70: 1 | C70: 매출원가 | E70: 195534.84 | G70: 172687.81 | H70: 208626.18 | I70: 167616.6 | J70: 212389.46 | K70: 761320.05 | L70: 186268.23 | M70: 177428.85 | N70: 177908.13 | O70: 269314.97 | P70: 810920.18 | Q70: 264197.18 | R70: 259381.71 | S70: 269527.35 | T70: 292758.12 | U70: 1085864.4 | V70: 283200.58 | W70: 341759.23 | X70: 257585.07 | Y70: 303047.2 | Z70: 1185592.1 | AA70: 279847.04 | AB70: 270443.55
A71: 1 | C71: 매출총이익 | E71: 41.72 | G71: 4907.6 | H71: -22307.48 | I71: 7985.97 | J71: 11725.34 | K71: 2311.43 | L71: 13078.64 | M71: 11616.82 | N71: 9729.04 | O71: 9039.74 | P71: 43464.24 | Q71: 29167.94 | R71: 27103.55 | S71: 26558.88 | T71: 33509.99 | U71: 116340.36 | V71: 34981.42 | W71: 45941.17 | X71: 39760.24 | Y71: 64782.43 | Z71: 185465.26 | AA71: 65392.38 | AB71: 61071.37
A72: 1 | C72: 판관비 | E72: 7237.22 | G72: 7191.89 | H72: 7343.56 | I72: 7244.46 | J72: 8528.61 | K72: 30308.52 | L72: 9004.54 | M72: 8143.45 | N72: 8644.69 | O72: 8943 | P72: 34735.68 | Q72: 9740.75 | R72: 8480.57 | S72: 11272.32 | T72: 15314.98 | U72: 44808.62 | V72: 12669.24 | W72: 12165.78 | X72: 13129.12 | Y72: 17434.82 | Z72: 55398.96 | AA72: 13988.71 | AB72: 19314.14
A73: 1 | C73: 영업이익 | E73: -7195.51 | G73: -2284.29 | H73: -29651.04 | I73: 741.5 | J73: 3196.74 | K73: -27997.09 | L73: 4074.1 | M73: 3473.37 | N73: 1084.35 | O73: 96.75 | P73: 8728.57 | Q73: 19427.18 | R73: 18622.98 | S73: 15286.55 | T73: 18195.01 | U73: 71531.72 | V73: 22312.18 | W73: 33775.39 | X73: 26631.12 | Y73: 47347.61 | Z73: 130066.3 | AA73: 51403.67 | AB73: 41757.23
A74: 1 | C74: 금융수익 | E74: 3482.09 | G74: 15529.77 | H74: 70787.69 | I74: 144323.46 | J74: -93568.59 | K74: 137072.33 | L74: 58707.19 | M74: 26858.49 | N74: 61435.99 | O74: -19237.39 | P74: 127764.28 | Q74: 88953.48 | R74: 74986.23 | S74: -37327.3 | T74: 228734.43 | U74: 355346.84 | V74: 47586.24 | W74: 150937.94 | X74: -61311.63 | Y74: 33407.62 | Z74: 170620.17 | AA74: 211830.29 | AB74: 86126.55
A75: 1 | C75: 금융비용 | E75: 5537.24 | G75: 16670.62 | H75: 71209.23 | I75: 141234.09 | J75: -82532.84 | K75: 146581.1 | L75: 61685.47 | M75: 29729.58 | N75: 64165.87 | O75: -13665.77 | P75: 141915.15 | Q75: 89770.1 | R75: 74776.42 | S75: -32731.31 | T75: 220592.69 | U75: 352407.9 | V75: 48789.27 | W75: 168066.32 | X75: -70764.09 | Y75: 26641.65 | Z75: 172733.15 | AA75: 192402.43 | AB75: 81643.8
A76: 1 | C76: 기타영업외수익 | E76: 3759.77 | G76: 30.99 | H76: 77.49 | I76: 303.8 | J76: 7301.12 | K76: 7713.4 | L76: 6078.63 | M76: 414.88 | N76: 171.54 | O76: 1815.7 | P76: 8480.75 | Q76: 53.19 | R76: 92.31 | S76: 3241.22 | T76: 77.94 | U76: 3464.66 | V76: 201.82 | W76: 195.41 | X76: 162.16 | Y76: 2894.02 | Z76: 3453.41 | AA76: 79.09 | AB76: 146.39
A77: 1 | C77: 기타영업외비용 | E77: 9506.82 | G77: 1375.55 | H77: 2565.22 | I77: 25.44 | J77: 6343.47 | K77: 10309.68 | L77: 53.68 | M77: 374.06 | N77: 1658.69 | O77: 2008.92 | P77: 4095.35 | Q77: 21.65 | R77: 435.95 | S77: 193.03 | T77: 11.34 | U77: 661.97 | V77: 1313.51 | W77: 1928.19 | X77: 4991.35 | Y77: 2519.36 | Z77: 10752.41 | AA77: 1767.01 | AB77: 5855.35
A78: 1 | C78: 법인세비용차감전계속사업이익 | E78: -14997.7 | G78: -4769.7 | H78: -32560.31 | I78: 4109.24 | J78: -6881.36 | K78: -40102.13 | L78: 7120.78 | M78: 643.1 | N78: -3075.32 | O78: -5645.52 | P78: -956.96 | Q78: 18642.11 | R78: 18538.67 | S78: 13712.13 | T78: 26461.19 | U78: 77354.1 | V78: 19979.61 | W78: 15051.37 | X78: 31246.92 | Y78: 54488.24 | Z78: 120766.14 | AA78: 69143.61 | AB78: 40531.01
A79: 1 | C79: 법인세비용 | E79: -2262.89 | H79: -1013.47 | I79: 1424.79 | J79: 362.74 | L79: 1556.51 | M79: 183.14 | N79: -727.94 | O79: -1522.26 | P79: -510.55 | Q79: 3771.62 | R79: 4230.93 | S79: 3126.51 | T79: -12934.51 | U79: -1805.45 | V79: 570.9 | W79: -6505.09 | X79: 946.57 | Y79: -47999.66 | Z79: -52987.28 | AA79: 16265.55 | AB79: 3227.27
A80: 1 | C80: 계속사업이익 | E80: -12734.82 | G80: -4769.7 | H80: -31546.84 | I80: 2684.45 | J80: -7244.1 | K80: -40876.19 | L80: 5564.27 | M80: 459.96 | N80: -2347.38 | O80: -4123.26 | P80: -446.41 | Q80: 14870.49 | R80: 14307.74 | S80: 10585.62 | T80: 39395.7 | U80: 79159.55 | V80: 19408.71 | W80: 21556.46 | X80: 30300.35 | Y80: 102487.91 | Z80: 173753.43 | AA80: 52878.07 | AB80: 37303.74
A81: 1 | C81: 당기순이익 | E81: -12734.82 | G81: -4769.7 | H81: -31546.84 | I81: 2684.45 | J81: -7244.1 | K81: -40876.19 | L81: 5564.27 | M81: 459.96 | N81: -2347.38 | O81: -4123.26 | P81: -446.41 | Q81: 14870.49 | R81: 14307.74 | S81: 10585.62 | T81: 39395.7 | U81: 79159.55 | V81: 19408.71 | W81: 21556.46 | X81: 30300.35 | Y81: 102487.91 | Z81: 173753.43 | AA81: 52878.07 | AB81: 37303.74
A82: 1 | C82: 금융손익 | E82: -2055.15 | G82: -1140.85 | H82: -421.54 | I82: 3089.37 | J82: -11035.75 | K82: -9508.77 | L82: -2978.28 | M82: -2871.09 | N82: -2729.88 | O82: -5571.62 | P82: -14150.87 | Q82: -816.62 | R82: 209.81 | S82: -4595.99 | T82: 8141.74 | U82: 2938.94 | V82: -1203.03 | W82: -17128.38 | X82: 9452.46 | Y82: 6765.97 | Z82: -2112.98 | AA82: 19427.86 | AB82: 4482.75
A83: 1 | C83: 기타영업외손익 | E83: -5747.05 | G83: -1344.56 | H83: -2487.73 | I83: 278.36 | J83: 957.65 | K83: -2596.28 | L83: 6024.95 | M83: 40.82 | N83: -1487.15 | O83: -193.22 | P83: 4385.4 | Q83: 31.54 | R83: -343.64 | S83: 3048.19 | T83: 66.6 | U83: 2802.69 | V83: -1111.69 | W83: -1732.78 | X83: -4829.19 | Y83: 374.66 | Z83: -7299 | AA83: -1687.92 | AB83: -5708.96
A84: 1 | C84: (지배주주지분)당기순이익 | E84: -12734.82 | G84: -4769.7 | H84: -31546.84 | I84: 2684.45 | J84: -7244.1 | K84: -40876.19 | L84: 5564.27 | M84: 459.96 | N84: -2347.38 | O84: -4123.26 | P84: -446.41 | Q84: 14870.49 | R84: 14307.74 | S84: 10585.62 | T84: 39395.7 | U84: 79159.55 | V84: 19408.71 | W84: 21556.46 | X84: 30300.35 | Y84: 102487.91 | Z84: 173753.43 | AA84: 52878.07 | AB84: 37303.74
A85: 1 | C85: 총포괄손익 | E85: -14205.08 | G85: -4769.7 | H85: -31546.84 | I85: 2684.45 | J85: -3128.47 | K85: -36760.56 | L85: 5564.27 | M85: 185.71 | N85: -1768.92 | O85: -1460.09 | P85: 2520.97 | Q85: 15189.25 | R85: 14319.27 | S85: 10428.5 | T85: 40519.73 | U85: 80456.75 | V85: 19507.01 | W85: 15979.08 | X85: 30796 | Y85: 93952.6 | Z85: 160234.69 | AA85: 53028.24 | AB85: 36599.13
A86: 1 | C86: 종속기업,공동지배기업및관계기업관련손익 | N86: 57.36 | O86: 22.59 | R86: 49.53 | S86: -26.61 | T86: 57.86 | V86: -17.84 | W86: 137.14 | X86: -7.47 | Y86: 0 | Z86: 111.83
A87: 1 | C87: 지분법관련손익 | N87: 57.36 | O87: 22.59 | R87: 49.53 | S87: -26.61 | T87: 57.86 | V87: -17.84 | W87: 137.14 | X87: -7.47 | Y87: 0 | Z87: 111.83
A88: 1 | C88: 이자수익 | V88: 1098.71 | W88: 2221.01 | X88: 3447.36
A89: 1 | C89: 이자비용 | V89: 930.34 | W89: 852.07 | X89: 761.66
A90: 1 | C90: 외환차익 | V90: 8268.01 | W90: 9411.64 | X90: 15093.09
A91: 1 | C91: 외환차손 | V91: 9280.44 | W91: 26079.92 | X91: 13161.58
A92: 1 | C92: 외화환산이익 | V92: 1394.36 | W92: 2068.02 | X92: 1393.4
A93: 1 | C93: 외화환산손실 | V93: 110.46 | W93: 8006.3 | X93: -6376.12
A94: 1 | C94: 파생상품이익 | V94: 6734.65 | W94: 164986.15 | X94: -90049.82
A95: 1 | C95: 파생상품손실 | V95: 32705.85 | W95: -24525.74 | X95: 9919.02
A96: 1 | C96: 이자손익 | V96: 168.37 | W96: 1368.94 | X96: 2685.7
A97: 1 | C97: 배당금수익 | W97: 8.96 | X97: 0
A98: 1 | C98: 영업외손익 | AB98: -1226.22
A99: 1 | C99: 영업활동으로인한현금흐름 | E99: -9770.23 | G99: -1721.07 | H99: -14610.2 | I99: 9535.18 | J99: -13644.79 | K99: -20440.88 | L99: 19613.07 | M99: -29204.48 | N99: -384.07 | O99: 80127.59 | P99: 70152.11 | Q99: -14455.7 | R99: 37443.6 | S99: -4336.27 | T99: 71724.07 | U99: 90375.7 | V99: 46058.61 | W99: 169896.82 | X99: 34713.08 | Y99: 79650.17 | Z99: 330318.68 | AA99: 48835.01 | AB99: 182471.81
A100: 1 | C100: 법인세납부(CF) | E100: -9.16 | G100: -6.37 | H100: 35.44 | I100: -22.2 | J100: -72.43 | K100: -65.56 | L100: -45.8 | M100: -55.2 | N100: -76.29 | O100: 3.68 | P100: -173.61 | Q100: -156.07 | R100: 24.98 | S100: -716.99 | T100: -310.5 | U100: -1158.58 | V100: -325.24 | W100: -585.81 | X100: -0.84 | Y100: -0.27 | Z100: -912.16 | AA100: -1606.38
A101: 1 | C101: 투자활동으로인한현금흐름 | E101: -2787.46 | G101: 1640.88 | H101: -4083.5 | I101: -38917.21 | J101: -16511.7 | K101: -57871.53 | L101: -3086.88 | M101: -11699.19 | N101: -9012.13 | O101: -6481.14 | P101: -30279.34 | Q101: 31045.05 | R101: -22379.04 | S101: -8850.68 | T101: -4129.06 | U101: -4313.73 | V101: -65613.69 | W101: -78391.57 | X101: -20306.37 | Y101: 3191.67 | Z101: -161119.96 | AA101: -278449.16 | AB101: -31131.53
A102: 1 | C102: 유형자산의감소 | E102: 0 | I102: 0 | J102: 0 | L102: 49.22 | M102: 15.92 | N102: 101.1 | O102: 46.15 | P102: 212.39 | T102: 1.89 | Y102: 141.01 | AA102: 1.82
...

Sheet subQ
A1: YQ | C1: subQ 분기 서브모델(억원, U=100) | E1: 4Q21 | F1: 2021 | G1: 1Q22 | H1: 2Q22 | I1: 3Q22 | J1: 4Q22 | K1: 2022 | L1: 1Q23 | M1: 2Q23 | N1: 3Q23 | O1: 4Q23 | P1: 2023 | Q1: 1Q24 | R1: 2Q24 | S1: 3Q24 | T1: 4Q24 | U1: 2024 | V1: 1Q25 | W1: 2Q25 | X1: 3Q25 | Y1: 4Q25 | Z1: 2025 | AA1: 1Q26 | AB1: 2Q26 | AC1: 3Q26 | AD1: 4Q26 | AE1: 2026 | AF1: 1Q27 | AG1: 2Q27 | AH1: 3Q27 | AI1: 4Q27 | AJ1: 2027 | AK1: 1Q28 | AL1: 2Q28 | AM1: 3Q28 | AN1: 4Q28 | AO1: 2028
A2: A=이름(key) B=그룹 C=단위 D=FnGuide 계정명(VLOOKUP 키). 확정=VLOOKUP(BS), 추정=변수 가정 참조
E3: 1 | F3: 2 | G3: 3 | H3: 4 | I3: 5 | J3: 6 | K3: 7 | L3: 8 | M3: 9 | N3: 10 | O3: 11 | P3: 12 | Q3: 13 | R3: 14 | S3: 15 | T3: 16 | U3: 17 | V3: 18 | W3: 19 | X3: 20 | Y3: 21 | Z3: 22 | AA3: 23 | AB3: 24 | AC3: 25 | AD3: 26 | AE3: 27 | AF3: 28 | AG3: 29 | AH3: 30 | AI3: 31 | AJ3: 32 | AK3: 33 | AL3: 34 | AM3: 35 | AN3: 36 | AO3: 37
E4: 2021.12 | F4: 2021.12A | G4: 2022.03 | H4: 2022.06 | I4: 2022.09 | J4: 2022.12 | K4: 2022.12A | L4: 2023.03 | M4: 2023.06 | N4: 2023.09 | O4: 2023.12 | P4: 2023.12A | Q4: 2024.03 | R4: 2024.06 | S4: 2024.09 | T4: 2024.12 | U4: 2024.12A | V4: 2025.03 | W4: 2025.06 | X4: 2025.09 | Y4: 2025.12 | Z4: 2025.12A | AA4: 2026.03 | AB4: 2026.06 | AC4: 2026.09 | AD4: 2026.12 | AE4: 2026.12A | AF4: 2027.03 | AG4: 2027.06 | AH4: 2027.09 | AI4: 2027.12 | AJ4: 2027.12A | AK4: 2028.03 | AL4: 2028.06 | AM4: 2028.09 | AN4: 2028.12 | AO4: 2028.12A
A5: 매출액 | B5: 손익 | C5: 억원 | D5: 매출액(수익) | E5: =IFERROR(VLOOKUP($D5,BS연결,MATCH(E$1,BS연결H,0),0)/100,"") | G5: =IFERROR(VLOOKUP($D5,BS연결,MATCH(G$1,BS연결H,0),0)/100,"") | H5: =IFERROR(VLOOKUP($D5,BS연결,MATCH(H$1,BS연결H,0),0)/100,"") | I5: =IFERROR(VLOOKUP($D5,BS연결,MATCH(I$1,BS연결H,0),0)/100,"") | J5: =IFERROR(VLOOKUP($D5,BS연결,MATCH(J$1,BS연결H,0),0)/100,"") | K5: =IFERROR(VLOOKUP($D5,BS연결,MATCH(K$1,BS연결H,0),0)/100,"") | L5: =IFERROR(VLOOKUP($D5,BS연결,MATCH(L$1,BS연결H,0),0)/100,"") | M5: =IFERROR(VLOOKUP($D5,BS연결,MATCH(M$1,BS연결H,0),0)/100,"") | N5: =IFERROR(VLOOKUP($D5,BS별도,MATCH(N$1,BS별도H,0),0)/100,"") | O5: =IFERROR(VLOOKUP($D5,BS별도,MATCH(O$1,BS별도H,0),0)/100,"") | P5: =SUM(L5:O5) | Q5: =IFERROR(VLOOKUP($D5,BS별도,MATCH(Q$1,BS별도H,0),0)/100,"") | R5: =IFERROR(VLOOKUP($D5,BS별도,MATCH(R$1,BS별도H,0),0)/100,"") | S5: =IFERROR(VLOOKUP($D5,BS별도,MATCH(S$1,BS별도H,0),0)/100,"") | T5: =IFERROR(VLOOKUP($D5,BS별도,MATCH(T$1,BS별도H,0),0)/100,"") | U5: =SUM(Q5:T5) | V5: =IFERROR(VLOOKUP($D5,BS별도,MATCH(V$1,BS별도H,0),0)/100,"") | W5: =IFERROR(VLOOKUP($D5,BS별도,MATCH(W$1,BS별도H,0),0)/100,"") | X5: =IFERROR(VLOOKUP($D5,BS별도,MATCH(X$1,BS별도H,0),0)/100,"") | Y5: =IFERROR(VLOOKUP($D5,BS별도,MATCH(Y$1,BS별도H,0),0)/100,"") | Z5: =SUM(V5:Y5) | AA5: =IFERROR(VLOOKUP($D5,BS연결,MATCH(AA$1,BS연결H,0),0)/100,"") | AB5: =IFERROR(VLOOKUP($D5,BS연결,MATCH(AB$1,BS연결H,0),0)/100,"") | AC5: =IFERROR(X5*(1+변수!AC21),"") | AD5: =IFERROR(Y5*(1+변수!AD21),"") | AE5: =SUM(AA5:AD5) | AF5: =IFERROR(AA5*(1+변수!AF21),"") | AG5: =IFERROR(AB5*(1+변수!AG21),"") | AH5: =IFERROR(AC5*(1+변수!AH21),"") | AI5: =IFERROR(AD5*(1+변수!AI21),"") | AJ5: =SUM(AF5:AI5) | AK5: =IFERROR(AF5*(1+변수!AK21),"") | AL5: =IFERROR(AG5*(1+변수!AL21),"") | AM5: =IFERROR(AH5*(1+변수!AM21),"") | AN5: =IFERROR(AI5*(1+변수!AN21),"") | AO5: =SUM(AK5:AN5)
A6: 매출원가 | B6: 손익 | C6: 억원 | D6: 매출원가 | E6: =IFERROR(VLOOKUP($D6,BS연결,MATCH(E$1,BS연결H,0),0)/100,"") | G6: =IFERROR(VLOOKUP($D6,BS연결,MATCH(G$1,BS연결H,0),0)/100,"") | H6: =IFERROR(VLOOKUP($D6,BS연결,MATCH(H$1,BS연결H,0),0)/100,"") | I6: =IFERROR(VLOOKUP($D6,BS연결,MATCH(I$1,BS연결H,0),0)/100,"") | J6: =IFERROR(VLOOKUP($D6,BS연결,MATCH(J$1,BS연결H,0),0)/100,"") | K6: =IFERROR(VLOOKUP($D6,BS연결,MATCH(K$1,BS연결H,0),0)/100,"") | L6: =IFERROR(VLOOKUP($D6,BS연결,MATCH(L$1,BS연결H,0),0)/100,"") | M6: =IFERROR(VLOOKUP($D6,BS연결,MATCH(M$1,BS연결H,0),0)/100,"") | N6: =IFERROR(VLOOKUP($D6,BS별도,MATCH(N$1,BS별도H,0),0)/100,"") | O6: =IFERROR(VLOOKUP($D6,BS별도,MATCH(O$1,BS별도H,0),0)/100,"") | P6: =SUM(L6:O6) | Q6: =IFERROR(VLOOKUP($D6,BS별도,MATCH(Q$1,BS별도H,0),0)/100,"") | R6: =IFERROR(VLOOKUP($D6,BS별도,MATCH(R$1,BS별도H,0),0)/100,"") | S6: =IFERROR(VLOOKUP($D6,BS별도,MATCH(S$1,BS별도H,0),0)/100,"") | T6: =IFERROR(VLOOKUP($D6,BS별도,MATCH(T$1,BS별도H,0),0)/100,"") | U6: =SUM(Q6:T6) | V6: =IFERROR(VLOOKUP($D6,BS별도,MATCH(V$1,BS별도H,0),0)/100,"") | W6: =IFERROR(VLOOKUP($D6,BS별도,MATCH(W$1,BS별도H,0),0)/100,"") | X6: =IFERROR(VLOOKUP($D6,BS별도,MATCH(X$1,BS별도H,0),0)/100,"") | Y6: =IFERROR(VLOOKUP($D6,BS별도,MATCH(Y$1,BS별도H,0),0)/100,"") | Z6: =SUM(V6:Y6) | AA6: =IFERROR(VLOOKUP($D6,BS연결,MATCH(AA$1,BS연결H,0),0)/100,"") | AB6: =IFERROR(VLOOKUP($D6,BS연결,MATCH(AB$1,BS연결H,0),0)/100,"") | AC6: =IFERROR(AC5-AC7,"") | AD6: =IFERROR(AD5-AD7,"") | AE6: =SUM(AA6:AD6) | AF6: =IFERROR(AF5-AF7,"") | AG6: =IFERROR(AG5-AG7,"") | AH6: =IFERROR(AH5-AH7,"") | AI6: =IFERROR(AI5-AI7,"") | AJ6: =SUM(AF6:AI6) | AK6: =IFERROR(AK5-AK7,"") | AL6: =IFERROR(AL5-AL7,"") | AM6: =IFERROR(AM5-AM7,"") | AN6: =IFERROR(AN5-AN7,"") | AO6: =SUM(AK6:AN6)
A7: 매출총이익 | B7: 손익 | C7: 억원 | D7: 매출총이익 | E7: =IFERROR(VLOOKUP($D7,BS연결,MATCH(E$1,BS연결H,0),0)/100,"") | G7: =IFERROR(VLOOKUP($D7,BS연결,MATCH(G$1,BS연결H,0),0)/100,"") | H7: =IFERROR(VLOOKUP($D7,BS연결,MATCH(H$1,BS연결H,0),0)/100,"") | I7: =IFERROR(VLOOKUP($D7,BS연결,MATCH(I$1,BS연결H,0),0)/100,"") | J7: =IFERROR(VLOOKUP($D7,BS연결,MATCH(J$1,BS연결H,0),0)/100,"") | K7: =IFERROR(VLOOKUP($D7,BS연결,MATCH(K$1,BS연결H,0),0)/100,"") | L7: =IFERROR(VLOOKUP($D7,BS연결,MATCH(L$1,BS연결H,0),0)/100,"") | M7: =IFERROR(VLOOKUP($D7,BS연결,MATCH(M$1,BS연결H,0),0)/100,"") | N7: =IFERROR(VLOOKUP($D7,BS별도,MATCH(N$1,BS별도H,0),0)/100,"") | O7: =IFERROR(VLOOKUP($D7,BS별도,MATCH(O$1,BS별도H,0),0)/100,"") | P7: =SUM(L7:O7) | Q7: =IFERROR(VLOOKUP($D7,BS별도,MATCH(Q$1,BS별도H,0),0)/100,"") | R7: =IFERROR(VLOOKUP($D7,BS별도,MATCH(R$1,BS별도H,0),0)/100,"") | S7: =IFERROR(VLOOKUP($D7,BS별도,MATCH(S$1,BS별도H,0),0)/100,"") | T7: =IFERROR(VLOOKUP($D7,BS별도,MATCH(T$1,BS별도H,0),0)/100,"") | U7: =SUM(Q7:T7) | V7: =IFERROR(VLOOKUP($D7,BS별도,MATCH(V$1,BS별도H,0),0)/100,"") | W7: =IFERROR(VLOOKUP($D7,BS별도,MATCH(W$1,BS별도H,0),0)/100,"") | X7: =IFERROR(VLOOKUP($D7,BS별도,MATCH(X$1,BS별도H,0),0)/100,"") | Y7: =IFERROR(VLOOKUP($D7,BS별도,MATCH(Y$1,BS별도H,0),0)/100,"") | Z7: =SUM(V7:Y7) | AA7: =IFERROR(VLOOKUP($D7,BS연결,MATCH(AA$1,BS연결H,0),0)/100,"") | AB7: =IFERROR(VLOOKUP($D7,BS연결,MATCH(AB$1,BS연결H,0),0)/100,"") | AC7: =IFERROR(AC9+AC8,"") | AD7: =IFERROR(AD9+AD8,"") | AE7: =SUM(AA7:AD7) | AF7: =IFERROR(AF9+AF8,"") | AG7: =IFERROR(AG9+AG8,"") | AH7: =IFERROR(AH9+AH8,"") | AI7: =IFERROR(AI9+AI8,"") | AJ7: =SUM(AF7:AI7) | AK7: =IFERROR(AK9+AK8,"") | AL7: =IFERROR(AL9+AL8,"") | AM7: =IFERROR(AM9+AM8,"") | AN7: =IFERROR(AN9+AN8,"") | AO7: =SUM(AK7:AN7)
A8: 판관비 | B8: 손익 | C8: 억원 | D8: 판관비 | E8: =IFERROR(VLOOKUP($D8,BS연결,MATCH(E$1,BS연결H,0),0)/100,"") | G8: =IFERROR(VLOOKUP($D8,BS연결,MATCH(G$1,BS연결H,0),0)/100,"") | H8: =IFERROR(VLOOKUP($D8,BS연결,MATCH(H$1,BS연결H,0),0)/100,"") | I8: =IFERROR(VLOOKUP($D8,BS연결,MATCH(I$1,BS연결H,0),0)/100,"") | J8: =IFERROR(VLOOKUP($D8,BS연결,MATCH(J$1,BS연결H,0),0)/100,"") | K8: =SUM(G8:J8) | L8: =IFERROR(VLOOKUP($D8,BS연결,MATCH(L$1,BS연결H,0),0)/100,"") | M8: =IFERROR(VLOOKUP($D8,BS연결,MATCH(M$1,BS연결H,0),0)/100,"") | N8: =IFERROR(VLOOKUP($D8,BS별도,MATCH(N$1,BS별도H,0),0)/100,"") | O8: =IFERROR(VLOOKUP($D8,BS별도,MATCH(O$1,BS별도H,0),0)/100,"") | P8: =SUM(L8:O8) | Q8: =IFERROR(VLOOKUP($D8,BS별도,MATCH(Q$1,BS별도H,0),0)/100,"") | R8: =IFERROR(VLOOKUP($D8,BS별도,MATCH(R$1,BS별도H,0),0)/100,"") | S8: =IFERROR(VLOOKUP($D8,BS별도,MATCH(S$1,BS별도H,0),0)/100,"") | T8: =IFERROR(VLOOKUP($D8,BS별도,MATCH(T$1,BS별도H,0),0)/100,"") | U8: =SUM(Q8:T8) | V8: =IFERROR(VLOOKUP($D8,BS별도,MATCH(V$1,BS별도H,0),0)/100,"") | W8: =IFERROR(VLOOKUP($D8,BS별도,MATCH(W$1,BS별도H,0),0)/100,"") | X8: =IFERROR(VLOOKUP($D8,BS별도,MATCH(X$1,BS별도H,0),0)/100,"") | Y8: =IFERROR(VLOOKUP($D8,BS별도,MATCH(Y$1,BS별도H,0),0)/100,"") | Z8: =SUM(V8:Y8) | AA8: =IFERROR(VLOOKUP($D8,BS연결,MATCH(AA$1,BS연결H,0),0)/100,"") | AB8: =IFERROR(VLOOKUP($D8,BS연결,MATCH(AB$1,BS연결H,0),0)/100,"") | AC8: =IFERROR(AC5*변수!AC22,"") | AD8: =IFERROR(AD5*변수!AD22,"") | AE8: =SUM(AA8:AD8) | AF8: =IFERROR(AF5*변수!AF22,"") | AG8: =IFERROR(AG5*변수!AG22,"") | AH8: =IFERROR(AH5*변수!AH22,"") | AI8: =IFERROR(AI5*변수!AI22,"") | AJ8: =SUM(AF8:AI8) | AK8: =IFERROR(AK5*변수!AK22,"") | AL8: =IFERROR(AL5*변수!AL22,"") | AM8: =IFERROR(AM5*변수!AM22,"") | AN8: =IFERROR(AN5*변수!AN22,"") | AO8: =SUM(AK8:AN8)
A9: 영업이익 | B9: 손익 | C9: 억원 | D9: 영업이익 | E9: =IFERROR(VLOOKUP($D9,BS연결,MATCH(E$1,BS연결H,0),0)/100,"") | G9: =IFERROR(VLOOKUP($D9,BS연결,MATCH(G$1,BS연결H,0),0)/100,"") | H9: =IFERROR(VLOOKUP($D9,BS연결,MATCH(H$1,BS연결H,0),0)/100,"") | I9: =IFERROR(VLOOKUP($D9,BS연결,MATCH(I$1,BS연결H,0),0)/100,"") | J9: =IFERROR(VLOOKUP($D9,BS연결,MATCH(J$1,BS연결H,0),0)/100,"") | K9: =IFERROR(VLOOKUP($D9,BS연결,MATCH(K$1,BS연결H,0),0)/100,"") | L9: =IFERROR(VLOOKUP($D9,BS연결,MATCH(L$1,BS연결H,0),0)/100,"") | M9: =IFERROR(VLOOKUP($D9,BS연결,MATCH(M$1,BS연결H,0),0)/100,"") | N9: =IFERROR(VLOOKUP($D9,BS별도,MATCH(N$1,BS별도H,0),0)/100,"") | O9: =IFERROR(VLOOKUP($D9,BS별도,MATCH(O$1,BS별도H,0),0)/100,"") | P9: =SUM(L9:O9) | Q9: =IFERROR(VLOOKUP($D9,BS별도,MATCH(Q$1,BS별도H,0),0)/100,"") | R9: =IFERROR(VLOOKUP($D9,BS별도,MATCH(R$1,BS별도H,0),0)/100,"") | S9: =IFERROR(VLOOKUP($D9,BS별도,MATCH(S$1,BS별도H,0),0)/100,"") | T9: =IFERROR(VLOOKUP($D9,BS별도,MATCH(T$1,BS별도H,0),0)/100,"") | U9: =SUM(Q9:T9) | V9: =IFERROR(VLOOKUP($D9,BS별도,MATCH(V$1,BS별도H,0),0)/100,"") | W9: =IFERROR(VLOOKUP($D9,BS별도,MATCH(W$1,BS별도H,0),0)/100,"") | X9: =IFERROR(VLOOKUP($D9,BS별도,MATCH(X$1,BS별도H,0),0)/100,"") | Y9: =IFERROR(VLOOKUP($D9,BS별도,MATCH(Y$1,BS별도H,0),0)/100,"") | Z9: =SUM(V9:Y9) | AA9: =IFERROR(VLOOKUP($D9,BS연결,MATCH(AA$1,BS연결H,0),0)/100,"") | AB9: =IFERROR(VLOOKUP($D9,BS연결,MATCH(AB$1,BS연결H,0),0)/100,"") | AC9: =IFERROR(AC5*변수!AC23,"") | AD9: =IFERROR(AD5*변수!AD23,"") | AE9: =SUM(AA9:AD9) | AF9: =IFERROR(AF5*변수!AF23,"") | AG9: =IFERROR(AG5*변수!AG23,"") | AH9: =IFERROR(AH5*변수!AH23,"") | AI9: =IFERROR(AI5*변수!AI23,"") | AJ9: =SUM(AF9:AI9) | AK9: =IFERROR(AK5*변수!AK23,"") | AL9: =IFERROR(AL5*변수!AL23,"") | AM9: =IFERROR(AM5*변수!AM23,"") | AN9: =IFERROR(AN5*변수!AN23,"") | AO9: =SUM(AK9:AN9)
A10: OPM | B10: 손익 | C10: % | D10: 영업이익률 | E10: =IFERROR(E9/E5,"") | G10: =IFERROR(G9/G5,"") | H10: =IFERROR(H9/H5,"") | I10: =IFERROR(I9/I5,"") | J10: =IFERROR(J9/J5,"") | K10: =IFERROR(K9/K5,"") | L10: =IFERROR(L9/L5,"") | M10: =IFERROR(M9/M5,"") | N10: =IFERROR(N9/N5,"") | ... AO10: =IFERROR(AO9/AO5,"")
A11: 금융손익 | B11: 손익 | C11: 억원 | D11: 금융손익 | E11: =IFERROR(VLOOKUP($D11,BS연결,MATCH(E$1,BS연결H,0),0)/100,"") | G11: =IFERROR(VLOOKUP($D11,BS연결,MATCH(G$1,BS연결H,0),0)/100,"") | H11: =IFERROR(VLOOKUP($D11,BS연결,MATCH(H$1,BS연결H,0),0)/100,"") | I11: =IFERROR(VLOOKUP($D11,BS연결,MATCH(I$1,BS연결H,0),0)/100,"") | J11: =IFERROR(VLOOKUP($D11,BS연결,MATCH(J$1,BS연결H,0),0)/100,"") | K11: =IFERROR(VLOOKUP($D11,BS연결,MATCH(K$1,BS연결H,0),0)/100,"") | L11: =IFERROR(VLOOKUP($D11,BS연결,MATCH(L$1,BS연결H,0),0)/100,"") | M11: =IFERROR(VLOOKUP($D11,BS연결,MATCH(M$1,BS연결H,0),0)/100,"") | N11: =IFERROR(VLOOKUP($D11,BS별도,MATCH(N$1,BS별도H,0),0)/100,"") | O11: =IFERROR(VLOOKUP($D11,BS별도,MATCH(O$1,BS별도H,0),0)/100,"") | P11: =SUM(L11:O11) | Q11: =IFERROR(VLOOKUP($D11,BS별도,MATCH(Q$1,BS별도H,0),0)/100,"") | R11: =IFERROR(VLOOKUP($D11,BS별도,MATCH(R$1,BS별도H,0),0)/100,"") | S11: =IFERROR(VLOOKUP($D11,BS별도,MATCH(S$1,BS별도H,0),0)/100,"") | T11: =IFERROR(VLOOKUP($D11,BS별도,MATCH(T$1,BS별도H,0),0)/100,"") | U11: =SUM(Q11:T11) | V11: =IFERROR(VLOOKUP($D11,BS별도,MATCH(V$1,BS별도H,0),0)/100,"") | W11: =IFERROR(VLOOKUP($D11,BS별도,MATCH(W$1,BS별도H,0),0)/100,"") | X11: =IFERROR(VLOOKUP($D11,BS별도,MATCH(X$1,BS별도H,0),0)/100,"") | Y11: =IFERROR(VLOOKUP($D11,BS별도,MATCH(Y$1,BS별도H,0),0)/100,"") | Z11: =SUM(V11:Y11) | AA11: =IFERROR(VLOOKUP($D11,BS연결,MATCH(AA$1,BS연결H,0),0)/100,"") | AB11: =IFERROR(VLOOKUP($D11,BS연결,MATCH(AB$1,BS연결H,0),0)/100,"") | AC11: =IFERROR(AC12+AC13+AC14+AC15,"") | AD11: =IFERROR(AD12+AD13+AD14+AD15,"") | AE11: =SUM(AA11:AD11) | AF11: =IFERROR(AF12+AF13+AF14+AF15,"") | AG11: =IFERROR(AG12+AG13+AG14+AG15,"") | AH11: =IFERROR(AH12+AH13+AH14+AH15,"") | AI11: =IFERROR(AI12+AI13+AI14+AI15,"") | AJ11: =SUM(AF11:AI11) | AK11: =IFERROR(AK12+AK13+AK14+AK15,"") | AL11: =IFERROR(AL12+AL13+AL14+AL15,"") | AM11: =IFERROR(AM12+AM13+AM14+AM15,"") | AN11: =IFERROR(AN12+AN13+AN14+AN15,"") | AO11: =SUM(AK11:AN11)
A12: 이자손익 | B12: 손익 | C12: 억원 | D12: 이자손익 | G12: =IFERROR(VLOOKUP($D12,BS연결,MATCH(G$1,BS연결H,0),0)/100,"") | H12: =IFERROR(VLOOKUP($D12,BS연결,MATCH(H$1,BS연결H,0),0)/100,"") | I12: =IFERROR(VLOOKUP($D12,BS연결,MATCH(I$1,BS연결H,0),0)/100,"") | J12: =IFERROR(VLOOKUP($D12,BS연결,MATCH(J$1,BS연결H,0),0)/100,"") | K12: =IFERROR(VLOOKUP($D12,BS연결,MATCH(K$1,BS연결H,0),0)/100,"") | L12: =IFERROR(VLOOKUP($D12,BS연결,MATCH(L$1,BS연결H,0),0)/100,"") | M12: =IFERROR(VLOOKUP($D12,BS연결,MATCH(M$1,BS연결H,0),0)/100,"") | P12: =SUM(L12:O12) | U12: =SUM(Q12:T12) | V12: =IFERROR(VLOOKUP($D12,BS별도,MATCH(V$1,BS별도H,0),0)/100,"") | W12: =IFERROR(VLOOKUP($D12,BS별도,MATCH(W$1,BS별도H,0),0)/100,"") | X12: =IFERROR(VLOOKUP($D12,BS별도,MATCH(X$1,BS별도H,0),0)/100,"") | Z12: =SUM(V12:Y12) | AA12: =IFERROR(VLOOKUP($D12,BS연결,MATCH(AA$1,BS연결H,0),0)/100,"") | AB12: =IFERROR(VLOOKUP($D12,BS연결,MATCH(AB$1,BS연결H,0),0)/100,"") | AC12: =IFERROR((AB28*변수!$D$54-AB26*변수!$D$55)/4,"") | AD12: =IFERROR((AC28*변수!$D$54-AC26*변수!$D$55)/4,"") | AE12: =SUM(AA12:AD12) | AF12: =IFERROR((AD28*변수!$D$54-AD26*변수!$D$55)/4,"") | AG12: =IFERROR((AF28*변수!$D$54-AF26*변수!$D$55)/4,"") | AH12: =IFERROR((AG28*변수!$D$54-AG26*변수!$D$55)/4,"") | AI12: =IFERROR((AH28*변수!$D$54-AH26*변수!$D$55)/4,"") | AJ12: =SUM(AF12:AI12) | AK12: =IFERROR((AI28*변수!$D$54-AI26*변수!$D$55)/4,"") | AL12: =IFERROR((AK28*변수!$D$54-AK26*변수!$D$55)/4,"") | AM12: =IFERROR((AL28*변수!$D$54-AL26*변수!$D$55)/4,"") | AN12: =IFERROR((AM28*변수!$D$54-AM26*변수!$D$55)/4,"") | AO12: =SUM(AK12:AN12)
A13: 외환손익 | B13: 손익 | C13: 억원 | D13: 외환손익(실적만; 추정 환효과는 환관련손익) | G13: =IFERROR((VLOOKUP("외환차익",BS연결,MATCH(G$1,BS연결H,0),0)-VLOOKUP("외환차손",BS연결,MATCH(G$1,BS연결H,0),0)+VLOOKUP("외화환산이익",BS연결,MATCH(G$1,BS연결H,0),0)-VLOOKUP("외화환산손실",BS연결,MATCH(G$1,BS연결H,0),0))/100,"") | H13: =IFERROR((VLOOKUP("외환차익",BS연결,MATCH(H$1,BS연결H,0),0)-VLOOKUP("외환차손",BS연결,MATCH(H$1,BS연결H,0),0)+VLOOKUP("외화환산이익",BS연결,MATCH(H$1,BS연결H,0),0)-VLOOKUP("외화환산손실",BS연결,MATCH(H$1,BS연결H,0),0))/100,"") | I13: =IFERROR((VLOOKUP("외환차익",BS연결,MATCH(I$1,BS연결H,0),0)-VLOOKUP("외환차손",BS연결,MATCH(I$1,BS연결H,0),0)+VLOOKUP("외화환산이익",BS연결,MATCH(I$1,BS연결H,0),0)-VLOOKUP("외화환산손실",BS연결,MATCH(I$1,BS연결H,0),0))/100,"") | J13: =IFERROR((VLOOKUP("외환차익",BS연결,MATCH(J$1,BS연결H,0),0)-VLOOKUP("외환차손",BS연결,MATCH(J$1,BS연결H,0),0)+VLOOKUP("외화환산이익",BS연결,MATCH(J$1,BS연결H,0),0)-VLOOKUP("외화환산손실",BS연결,MATCH(J$1,BS연결H,0),0))/100,"") | K13: =SUM(G13:J13) | L13: =IFERROR((VLOOKUP("외환차익",BS연결,MATCH(L$1,BS연결H,0),0)-VLOOKUP("외환차손",BS연결,MATCH(L$1,BS연결H,0),0)+VLOOKUP("외화환산이익",BS연결,MATCH(L$1,BS연결H,0),0)-VLOOKUP("외화환산손실",BS연결,MATCH(L$1,BS연결H,0),0))/100,"") | M13: =IFERROR((VLOOKUP("외환차익",BS연결,MATCH(M$1,BS연결H,0),0)-VLOOKUP("외환차손",BS연결,MATCH(M$1,BS연결H,0),0)+VLOOKUP("외화환산이익",BS연결,MATCH(M$1,BS연결H,0),0)-VLOOKUP("외화환산손실",BS연결,MATCH(M$1,BS연결H,0),0))/100,"") | P13: =SUM(L13:O13) | U13: =SUM(Q13:T13) | V13: =IFERROR((VLOOKUP("외환차익",BS별도,MATCH(V$1,BS별도H,0),0)-VLOOKUP("외환차손",BS별도,MATCH(V$1,BS별도H,0),0)+VLOOKUP("외화환산이익",BS별도,MATCH(V$1,BS별도H,0),0)-VLOOKUP("외화환산손실",BS별도,MATCH(V$1,BS별도H,0),0))/100,"") | W13: =IFERROR((VLOOKUP("외환차익",BS별도,MATCH(W$1,BS별도H,0),0)-VLOOKUP("외환차손",BS별도,MATCH(W$1,BS별도H,0),0)+VLOOKUP("외화환산이익",BS별도,MATCH(W$1,BS별도H,0),0)-VLOOKUP("외화환산손실",BS별도,MATCH(W$1,BS별도H,0),0))/100,"") | X13: =IFERROR((VLOOKUP("외환차익",BS별도,MATCH(X$1,BS별도H,0),0)-VLOOKUP("외환차손",BS별도,MATCH(X$1,BS별도H,0),0)+VLOOKUP("외화환산이익",BS별도,MATCH(X$1,BS별도H,0),0)-VLOOKUP("외화환산손실",BS별도,MATCH(X$1,BS별도H,0),0))/100,"") | Z13: =SUM(V13:Y13) | AA13: =IFERROR((VLOOKUP("외환차익",BS연결,MATCH(AA$1,BS연결H,0),0)-VLOOKUP("외환차손",BS연결,MATCH(AA$1,BS연결H,0),0)+VLOOKUP("외화환산이익",BS연결,MATCH(AA$1,BS연결H,0),0)-VLOOKUP("외화환산손실",BS연결,MATCH(AA$1,BS연결H,0),0))/100,"") | AB13: =IFERROR((VLOOKUP("외환차익",BS연결,MATCH(AB$1,BS연결H,0),0)-VLOOKUP("외환차손",BS연결,MATCH(AB$1,BS연결H,0),0)+VLOOKUP("외화환산이익",BS연결,MATCH(AB$1,BS연결H,0),0)-VLOOKUP("외화환산손실",BS연결,MATCH(AB$1,BS연결H,0),0))/100,"") | AC13: =변수!AC24 | AD13: =변수!AD24 | AE13: =SUM(AA13:AD13) | AF13: =변수!AF24 | AG13: =변수!AG24 | AH13: =변수!AH24 | AI13: =변수!AI24 | AJ13: =SUM(AF13:AI13) | AK13: =변수!AK24 | AL13: =변수!AL24 | AM13: =변수!AM24 | AN13: =변수!AN24 | AO13: =SUM(AK13:AN13)
A14: 파생상품손익 | B14: 손익 | C14: 억원 | D14: 파생상품손익 | G14: =IFERROR((VLOOKUP("파생상품이익",BS연결,MATCH(G$1,BS연결H,0),0)-VLOOKUP("파생상품손실",BS연결,MATCH(G$1,BS연결H,0),0))/100,"") | H14: =IFERROR((VLOOKUP("파생상품이익",BS연결,MATCH(H$1,BS연결H,0),0)-VLOOKUP("파생상품손실",BS연결,MATCH(H$1,BS연결H,0),0))/100,"") | I14: =IFERROR((VLOOKUP("파생상품이익",BS연결,MATCH(I$1,BS연결H,0),0)-VLOOKUP("파생상품손실",BS연결,MATCH(I$1,BS연결H,0),0))/100,"") | J14: =IFERROR((VLOOKUP("파생상품이익",BS연결,MATCH(J$1,BS연결H,0),0)-VLOOKUP("파생상품손실",BS연결,MATCH(J$1,BS연결H,0),0))/100,"") | K14: =SUM(G14:J14) | L14: =IFERROR((VLOOKUP("파생상품이익",BS연결,MATCH(L$1,BS연결H,0),0)-VLOOKUP("파생상품손실",BS연결,MATCH(L$1,BS연결H,0),0))/100,"") | M14: =IFERROR((VLOOKUP("파생상품이익",BS연결,MATCH(M$1,BS연결H,0),0)-VLOOKUP("파생상품손실",BS연결,MATCH(M$1,BS연결H,0),0))/100,"") | P14: =SUM(L14:O14) | U14: =SUM(Q14:T14) | V14: =IFERROR((VLOOKUP("파생상품이익",BS별도,MATCH(V$1,BS별도H,0),0)-VLOOKUP("파생상품손실",BS별도,MATCH(V$1,BS별도H,0),0))/100,"") | W14: =IFERROR((VLOOKUP("파생상품이익",BS별도,MATCH(W$1,BS별도H,0),0)-VLOOKUP("파생상품손실",BS별도,MATCH(W$1,BS별도H,0),0))/100,"") | X14: =IFERROR((VLOOKUP("파생상품이익",BS별도,MATCH(X$1,BS별도H,0),0)-VLOOKUP("파생상품손실",BS별도,MATCH(X$1,BS별도H,0),0))/100,"") | Z14: =SUM(V14:Y14) | AA14: =IFERROR((VLOOKUP("파생상품이익",BS연결,MATCH(AA$1,BS연결H,0),0)-VLOOKUP("파생상품손실",BS연결,MATCH(AA$1,BS연결H,0),0))/100,"") | AB14: =IFERROR((VLOOKUP("파생상품이익",BS연결,MATCH(AB$1,BS연결H,0),0)-VLOOKUP("파생상품손실",BS연결,MATCH(AB$1,BS연결H,0),0))/100,"") | AC14: =변수!AC25 | AD14: =변수!AD25 | AE14: =SUM(AA14:AD14) | AF14: =변수!AF25 | AG14: =변수!AG25 | AH14: =변수!AH25 | AI14: =변수!AI25 | AJ14: =SUM(AF14:AI14) | AK14: =변수!AK25 | AL14: =변수!AL25 | AM14: =변수!AM25 | AN14: =변수!AN25 | AO14: =SUM(AK14:AN14)
A15: 기타금융손익 | B15: 손익 | C15: 억원 | D15: 기타금융손익(금융손익 잔차) | G15: =IFERROR(G11-G12-G13-G14,"") | H15: =IFERROR(H11-H12-H13-H14,"") | I15: =IFERROR(I11-I12-I13-I14,"") | J15: =IFERROR(J11-J12-J13-J14,"") | K15: =SUM(G15:J15) | L15: =IFERROR(L11-L12-L13-L14,"") | M15: =IFERROR(M11-M12-M13-M14,"") | P15: =SUM(L15:O15) | U15: =SUM(Q15:T15) | V15: =IFERROR(V11-V12-V13-V14,"") | W15: =IFERROR(W11-W12-W13-W14,"") | X15: =IFERROR(X11-X12-X13-X14,"") | Z15: =SUM(V15:Y15) | AA15: =IFERROR(AA11-AA12-AA13-AA14,"") | AB15: =IFERROR(AB11-AB12-AB13-AB14,"") | AC15: =변수!AC26 | AD15: =변수!AD26 | AE15: =SUM(AA15:AD15) | AF15: =변수!AF26 | AG15: =변수!AG26 | AH15: =변수!AH26 | AI15: =변수!AI26 | AJ15: =SUM(AF15:AI15) | AK15: =변수!AK26 | AL15: =변수!AL26 | AM15: =변수!AM26 | AN15: =변수!AN26 | AO15: =SUM(AK15:AN15)
A16: 기타영업외손익 | B16: 손익 | C16: 억원 | D16: 기타영업외손익 | E16: =IFERROR(VLOOKUP($D16,BS연결,MATCH(E$1,BS연결H,0),0)/100,"") | G16: =IFERROR(VLOOKUP($D16,BS연결,MATCH(G$1,BS연결H,0),0)/100,"") | H16: =IFERROR(VLOOKUP($D16,BS연결,MATCH(H$1,BS연결H,0),0)/100,"") | I16: =IFERROR(VLOOKUP($D16,BS연결,MATCH(I$1,BS연결H,0),0)/100,"") | J16: =IFERROR(VLOOKUP($D16,BS연결,MATCH(J$1,BS연결H,0),0)/100,"") | K16: =IFERROR(VLOOKUP($D16,BS연결,MATCH(K$1,BS연결H,0),0)/100,"") | L16: =IFERROR(VLOOKUP($D16,BS연결,MATCH(L$1,BS연결H,0),0)/100,"") | M16: =IFERROR(VLOOKUP($D16,BS연결,MATCH(M$1,BS연결H,0),0)/100,"") | N16: =IFERROR(VLOOKUP($D16,BS별도,MATCH(N$1,BS별도H,0),0)/100,"") | O16: =IFERROR(VLOOKUP($D16,BS별도,MATCH(O$1,BS별도H,0),0)/100,"") | P16: =SUM(L16:O16) | Q16: =IFERROR(VLOOKUP($D16,BS별도,MATCH(Q$1,BS별도H,0),0)/100,"") | R16: =IFERROR(VLOOKUP($D16,BS별도,MATCH(R$1,BS별도H,0),0)/100,"") | S16: =IFERROR(VLOOKUP($D16,BS별도,MATCH(S$1,BS별도H,0),0)/100,"") | T16: =IFERROR(VLOOKUP($D16,BS별도,MATCH(T$1,BS별도H,0),0)/100,"") | U16: =SUM(Q16:T16) | V16: =IFERROR(VLOOKUP($D16,BS별도,MATCH(V$1,BS별도H,0),0)/100,"") | W16: =IFERROR(VLOOKUP($D16,BS별도,MATCH(W$1,BS별도H,0),0)/100,"") | X16: =IFERROR(VLOOKUP($D16,BS별도,MATCH(X$1,BS별도H,0),0)/100,"") | Y16: =IFERROR(VLOOKUP($D16,BS별도,MATCH(Y$1,BS별도H,0),0)/100,"") | Z16: =SUM(V16:Y16) | AA16: =IFERROR(VLOOKUP($D16,BS연결,MATCH(AA$1,BS연결H,0),0)/100,"") | AB16: =IFERROR(VLOOKUP($D16,BS연결,MATCH(AB$1,BS연결H,0),0)/100,"") | AC16: =변수!AC27 | AD16: =변수!AD27 | AE16: =SUM(AA16:AD16) | AF16: =변수!AF27 | AG16: =변수!AG27 | AH16: =변수!AH27 | AI16: =변수!AI27 | AJ16: =SUM(AF16:AI16) | AK16: =변수!AK27 | AL16: =변수!AL27 | AM16: =변수!AM27 | AN16: =변수!AN27 | AO16: =SUM(AK16:AN16)
A17: 지분법손익 | B17: 손익 | C17: 억원 | D17: 종속기업,공동지배기업및관계기업관련손익 | E17: =IFERROR(VLOOKUP($D17,BS연결,MATCH(E$1,BS연결H,0),0)/100,"") | G17: =IFERROR(VLOOKUP($D17,BS연결,MATCH(G$1,BS연결H,0),0)/100,"") | H17: =IFERROR(VLOOKUP($D17,BS연결,MATCH(H$1,BS연결H,0),0)/100,"") | J17: =IFERROR(VLOOKUP($D17,BS연결,MATCH(J$1,BS연결H,0),0)/100,"") | K17: =SUM(G17:J17) | L17: =IFERROR(VLOOKUP($D17,BS연결,MATCH(L$1,BS연결H,0),0)/100,"") | M17: =IFERROR(VLOOKUP($D17,BS연결,MATCH(M$1,BS연결H,0),0)/100,"") | N17: =IFERROR(VLOOKUP($D17,BS별도,MATCH(N$1,BS별도H,0),0)/100,"") | O17: =IFERROR(VLOOKUP($D17,BS별도,MATCH(O$1,BS별도H,0),0)/100,"") | P17: =SUM(L17:O17) | R17: =IFERROR(VLOOKUP($D17,BS별도,MATCH(R$1,BS별도H,0),0)/100,"") | S17: =IFERROR(VLOOKUP($D17,BS별도,MATCH(S$1,BS별도H,0),0)/100,"") | T17: =IFERROR(VLOOKUP($D17,BS별도,MATCH(T$1,BS별도H,0),0)/100,"") | U17: =SUM(Q17:T17) | V17: =IFERROR(VLOOKUP($D17,BS별도,MATCH(V$1,BS별도H,0),0)/100,"") | W17: =IFERROR(VLOOKUP($D17,BS별도,MATCH(W$1,BS별도H,0),0)/100,"") | X17: =IFERROR(VLOOKUP($D17,BS별도,MATCH(X$1,BS별도H,0),0)/100,"") | Y17: =IFERROR(VLOOKUP($D17,BS별도,MATCH(Y$1,BS별도H,0),0)/100,"") | Z17: =SUM(V17:Y17) | AC17: =변수!AC28 | AD17: =변수!AD28 | AE17: =SUM(AA17:AD17) | AF17: =변수!AF28 | AG17: =변수!AG28 | AH17: =변수!AH28 | AI17: =변수!AI28 | AJ17: =SUM(AF17:AI17) | AK17: =변수!AK28 | AL17: =변수!AL28 | AM17: =변수!AM28 | AN17: =변수!AN28 | AO17: =SUM(AK17:AN17)
A18: 세전이익 | B18: 손익 | C18: 억원 | D18: 법인세비용차감전계속사업이익 | E18: =IFERROR(VLOOKUP($D18,BS연결,MATCH(E$1,BS연결H,0),0)/100,"") | G18: =IFERROR(VLOOKUP($D18,BS연결,MATCH(G$1,BS연결H,0),0)/100,"") | H18: =IFERROR(VLOOKUP($D18,BS연결,MATCH(H$1,BS연결H,0),0)/100,"") | I18: =IFERROR(VLOOKUP($D18,BS연결,MATCH(I$1,BS연결H,0),0)/100,"") | J18: =IFERROR(VLOOKUP($D18,BS연결,MATCH(J$1,BS연결H,0),0)/100,"") | K18: =IFERROR(VLOOKUP($D18,BS연결,MATCH(K$1,BS연결H,0),0)/100,"") | L18: =IFERROR(VLOOKUP($D18,BS연결,MATCH(L$1,BS연결H,0),0)/100,"") | M18: =IFERROR(VLOOKUP($D18,BS연결,MATCH(M$1,BS연결H,0),0)/100,"") | N18: =IFERROR(VLOOKUP($D18,BS별도,MATCH(N$1,BS별도H,0),0)/100,"") | O18: =IFERROR(VLOOKUP($D18,BS별도,MATCH(O$1,BS별도H,0),0)/100,"") | P18: =SUM(L18:O18) | Q18: =IFERROR(VLOOKUP($D18,BS별도,MATCH(Q$1,BS별도H,0),0)/100,"") | R18: =IFERROR(VLOOKUP($D18,BS별도,MATCH(R$1,BS별도H,0),0)/100,"") | S18: =IFERROR(VLOOKUP($D18,BS별도,MATCH(S$1,BS별도H,0),0)/100,"") | T18: =IFERROR(VLOOKUP($D18,BS별도,MATCH(T$1,BS별도H,0),0)/100,"") | U18: =SUM(Q18:T18) | V18: =IFERROR(VLOOKUP($D18,BS별도,MATCH(V$1,BS별도H,0),0)/100,"") | W18: =IFERROR(VLOOKUP($D18,BS별도,MATCH(W$1,BS별도H,0),0)/100,"") | X18: =IFERROR(VLOOKUP($D18,BS별도,MATCH(X$1,BS별도H,0),0)/100,"") | Y18: =IFERROR(VLOOKUP($D18,BS별도,MATCH(Y$1,BS별도H,0),0)/100,"") | Z18: =SUM(V18:Y18) | AA18: =IFERROR(VLOOKUP($D18,BS연결,MATCH(AA$1,BS연결H,0),0)/100,"") | AB18: =IFERROR(VLOOKUP($D18,BS연결,MATCH(AB$1,BS연결H,0),0)/100,"") | AC18: =IFERROR(AC9+AC11+AC16+AC17,"") | AD18: =IFERROR(AD9+AD11+AD16+AD17,"") | AE18: =SUM(AA18:AD18) | AF18: =IFERROR(AF9+AF11+AF16+AF17,"") | AG18: =IFERROR(AG9+AG11+AG16+AG17,"") | AH18: =IFERROR(AH9+AH11+AH16+AH17,"") | AI18: =IFERROR(AI9+AI11+AI16+AI17,"") | AJ18: =SUM(AF18:AI18) | AK18: =IFERROR(AK9+AK11+AK16+AK17,"") | AL18: =IFERROR(AL9+AL11+AL16+AL17,"") | AM18: =IFERROR(AM9+AM11+AM16+AM17,"") | AN18: =IFERROR(AN9+AN11+AN16+AN17,"") | AO18: =SUM(AK18:AN18)
A19: 법인세비용 | B19: 손익 | C19: 억원 | D19: 법인세비용 | E19: =IFERROR(VLOOKUP($D19,BS연결,MATCH(E$1,BS연결H,0),0)/100,"") | G19: =IFERROR(VLOOKUP($D19,BS연결,MATCH(G$1,BS연결H,0),0)/100,"") | H19: =IFERROR(VLOOKUP($D19,BS연결,MATCH(H$1,BS연결H,0),0)/100,"") | I19: =IFERROR(VLOOKUP($D19,BS연결,MATCH(I$1,BS연결H,0),0)/100,"") | J19: =IFERROR(VLOOKUP($D19,BS연결,MATCH(J$1,BS연결H,0),0)/100,"") | K19: =IFERROR(VLOOKUP($D19,BS연결,MATCH(K$1,BS연결H,0),0)/100,"") | L19: =IFERROR(VLOOKUP($D19,BS연결,MATCH(L$1,BS연결H,0),0)/100,"") | M19: =IFERROR(VLOOKUP($D19,BS연결,MATCH(M$1,BS연결H,0),0)/100,"") | N19: =IFERROR(VLOOKUP($D19,BS별도,MATCH(N$1,BS별도H,0),0)/100,"") | O19: =IFERROR(VLOOKUP($D19,BS별도,MATCH(O$1,BS별도H,0),0)/100,"") | P19: =SUM(L19:O19) | Q19: =IFERROR(VLOOKUP($D19,BS별도,MATCH(Q$1,BS별도H,0),0)/100,"") | R19: =IFERROR(VLOOKUP($D19,BS별도,MATCH(R$1,BS별도H,0),0)/100,"") | S19: =IFERROR(VLOOKUP($D19,BS별도,MATCH(S$1,BS별도H,0),0)/100,"") | T19: =IFERROR(VLOOKUP($D19,BS별도,MATCH(T$1,BS별도H,0),0)/100,"") | U19: =SUM(Q19:T19) | V19: =IFERROR(VLOOKUP($D19,BS별도,MATCH(V$1,BS별도H,0),0)/100,"") | W19: =IFERROR(VLOOKUP($D19,BS별도,MATCH(W$1,BS별도H,0),0)/100,"") | X19: =IFERROR(VLOOKUP($D19,BS별도,MATCH(X$1,BS별도H,0),0)/100,"") | Y19: =IFERROR(VLOOKUP($D19,BS별도,MATCH(Y$1,BS별도H,0),0)/100,"") | Z19: =SUM(V19:Y19) | AA19: =IFERROR(VLOOKUP($D19,BS연결,MATCH(AA$1,BS연결H,0),0)/100,"") | AB19: =IFERROR(VLOOKUP($D19,BS연결,MATCH(AB$1,BS연결H,0),0)/100,"") | AC19: =IFERROR(MAX(AC18,0)*변수!AC29,"") | AD19: =IFERROR(MAX(AD18,0)*변수!AD29,"") | AE19: =SUM(AA19:AD19) | AF19: =IFERROR(MAX(AF18,0)*변수!AF29,"") | AG19: =IFERROR(MAX(AG18,0)*변수!AG29,"") | AH19: =IFERROR(MAX(AH18,0)*변수!AH29,"") | AI19: =IFERROR(MAX(AI18,0)*변수!AI29,"") | AJ19: =SUM(AF19:AI19) | AK19: =IFERROR(MAX(AK18,0)*변수!AK29,"") | AL19: =IFERROR(MAX(AL18,0)*변수!AL29,"") | AM19: =IFERROR(MAX(AM18,0)*변수!AM29,"") | AN19: =IFERROR(MAX(AN18,0)*변수!AN29,"") | AO19: =SUM(AK19:AN19)
A20: 당기순이익 | B20: 손익 | C20: 억원 | D20: 당기순이익 | E20: =IFERROR(VLOOKUP($D20,BS연결,MATCH(E$1,BS연결H,0),0)/100,"") | G20: =IFERROR(VLOOKUP($D20,BS연결,MATCH(G$1,BS연결H,0),0)/100,"") | H20: =IFERROR(VLOOKUP($D20,BS연결,MATCH(H$1,BS연결H,0),0)/100,"") | I20: =IFERROR(VLOOKUP($D20,BS연결,MATCH(I$1,BS연결H,0),0)/100,"") | J20: =IFERROR(VLOOKUP($D20,BS연결,MATCH(J$1,BS연결H,0),0)/100,"") | K20: =IFERROR(VLOOKUP($D20,BS연결,MATCH(K$1,BS연결H,0),0)/100,"") | L20: =IFERROR(VLOOKUP($D20,BS연결,MATCH(L$1,BS연결H,0),0)/100,"") | M20: =IFERROR(VLOOKUP($D20,BS연결,MATCH(M$1,BS연결H,0),0)/100,"") | N20: =IFERROR(VLOOKUP($D20,BS별도,MATCH(N$1,BS별도H,0),0)/100,"") | O20: =IFERROR(VLOOKUP($D20,BS별도,MATCH(O$1,BS별도H,0),0)/100,"") | P20: =SUM(L20:O20) | Q20: =IFERROR(VLOOKUP($D20,BS별도,MATCH(Q$1,BS별도H,0),0)/100,"") | R20: =IFERROR(VLOOKUP($D20,BS별도,MATCH(R$1,BS별도H,0),0)/100,"") | S20: =IFERROR(VLOOKUP($D20,BS별도,MATCH(S$1,BS별도H,0),0)/100,"") | T20: =IFERROR(VLOOKUP($D20,BS별도,MATCH(T$1,BS별도H,0),0)/100,"") | U20: =SUM(Q20:T20) | V20: =IFERROR(VLOOKUP($D20,BS별도,MATCH(V$1,BS별도H,0),0)/100,"") | W20: =IFERROR(VLOOKUP($D20,BS별도,MATCH(W$1,BS별도H,0),0)/100,"") | X20: =IFERROR(VLOOKUP($D20,BS별도,MATCH(X$1,BS별도H,0),0)/100,"") | Y20: =IFERROR(VLOOKUP($D20,BS별도,MATCH(Y$1,BS별도H,0),0)/100,"") | Z20: =SUM(V20:Y20) | AA20: =IFERROR(VLOOKUP($D20,BS연결,MATCH(AA$1,BS연결H,0),0)/100,"") | AB20: =IFERROR(VLOOKUP($D20,BS연결,MATCH(AB$1,BS연결H,0),0)/100,"") | AC20: =IFERROR(AC18-AC19,"") | AD20: =IFERROR(AD18-AD19,"") | AE20: =SUM(AA20:AD20) | AF20: =IFERROR(AF18-AF19,"") | AG20: =IFERROR(AG18-AG19,"") | AH20: =IFERROR(AH18-AH19,"") | AI20: =IFERROR(AI18-AI19,"") | AJ20: =SUM(AF20:AI20) | AK20: =IFERROR(AK18-AK19,"") | AL20: =IFERROR(AL18-AL19,"") | AM20: =IFERROR(AM18-AM19,"") | AN20: =IFERROR(AN18-AN19,"") | AO20: =SUM(AK20:AN20)
A21: 지배주주순이익 | B21: 손익 | C21: 억원 | D21: (지배주주지분)당기순이익 | E21: =IFERROR(VLOOKUP($D21,BS연결,MATCH(E$1,BS연결H,0),0)/100,"") | G21: =IFERROR(VLOOKUP($D21,BS연결,MATCH(G$1,BS연결H,0),0)/100,"") | H21: =IFERROR(VLOOKUP($D21,BS연결,MATCH(H$1,BS연결H,0),0)/100,"") | I21: =IFERROR(VLOOKUP($D21,BS연결,MATCH(I$1,BS연결H,0),0)/100,"") | J21: =IFERROR(VLOOKUP($D21,BS연결,MATCH(J$1,BS연결H,0),0)/100,"") | K21: =IFERROR(VLOOKUP($D21,BS연결,MATCH(K$1,BS연결H,0),0)/100,"") | L21: =IFERROR(VLOOKUP($D21,BS연결,MATCH(L$1,BS연결H,0),0)/100,"") | M21: =IFERROR(VLOOKUP($D21,BS연결,MATCH(M$1,BS연결H,0),0)/100,"") | N21: =IFERROR(VLOOKUP($D21,BS별도,MATCH(N$1,BS별도H,0),0)/100,"") | O21: =IFERROR(VLOOKUP($D21,BS별도,MATCH(O$1,BS별도H,0),0)/100,"") | P21: =SUM(L21:O21) | Q21: =IFERROR(VLOOKUP($D21,BS별도,MATCH(Q$1,BS별도H,0),0)/100,"") | R21: =IFERROR(VLOOKUP($D21,BS별도,MATCH(R$1,BS별도H,0),0)/100,"") | S21: =IFERROR(VLOOKUP($D21,BS별도,MATCH(S$1,BS별도H,0),0)/100,"") | T21: =IFERROR(VLOOKUP($D21,BS별도,MATCH(T$1,BS별도H,0),0)/100,"") | U21: =SUM(Q21:T21) | V21: =IFERROR(VLOOKUP($D21,BS별도,MATCH(V$1,BS별도H,0),0)/100,"") | W21: =IFERROR(VLOOKUP($D21,BS별도,MATCH(W$1,BS별도H,0),0)/100,"") | X21: =IFERROR(VLOOKUP($D21,BS별도,MATCH(X$1,BS별도H,0),0)/100,"") | Y21: =IFERROR(VLOOKUP($D21,BS별도,MATCH(Y$1,BS별도H,0),0)/100,"") | Z21: =SUM(V21:Y21) | AA21: =IFERROR(VLOOKUP($D21,BS연결,MATCH(AA$1,BS연결H,0),0)/100,"") | AB21: =IFERROR(VLOOKUP($D21,BS연결,MATCH(AB$1,BS연결H,0),0)/100,"") | AC21: =IFERROR(AC20*변수!AC30,"") | AD21: =IFERROR(AD20*변수!AD30,"") | AE21: =SUM(AA21:AD21) | AF21: =IFERROR(AF20*변수!AF30,"") | AG21: =IFERROR(AG20*변수!AG30,"") | AH21: =IFERROR(AH20*변수!AH30,"") | AI21: =IFERROR(AI20*변수!AI30,"") | AJ21: =SUM(AF21:AI21) | AK21: =IFERROR(AK20*변수!AK30,"") | AL21: =IFERROR(AL20*변수!AL30,"") | AM21: =IFERROR(AM20*변수!AM30,"") | AN21: =IFERROR(AN20*변수!AN30,"") | AO21: =SUM(AK21:AN21)
A22: 자산총계 | B22: 재무상태 | C22: 억원 | D22: 자산총계 | E22: =IFERROR(VLOOKUP($D22,BS연결,MATCH(E$1,BS연결H,0),0)/100,"") | F22: =IFERROR(VLOOKUP($D22,BS연결,MATCH(F$1,BS연결H,0),0)/100,"") | G22: =IFERROR(VLOOKUP($D22,BS연결,MATCH(G$1,BS연결H,0),0)/100,"") | H22: =IFERROR(VLOOKUP($D22,BS연결,MATCH(H$1,BS연결H,0),0)/100,"") | I22: =IFERROR(VLOOKUP($D22,BS연결,MATCH(I$1,BS연결H,0),0)/100,"") | J22: =IFERROR(VLOOKUP($D22,BS연결,MATCH(J$1,BS연결H,0),0)/100,"") | K22: =IFERROR(VLOOKUP($D22,BS연결,MATCH(K$1,BS연결H,0),0)/100,"") | L22: =IFERROR(VLOOKUP($D22,BS연결,MATCH(L$1,BS연결H,0),0)/100,"") | M22: =IFERROR(VLOOKUP($D22,BS연결,MATCH(M$1,BS연결H,0),0)/100,"") | N22: =IFERROR(VLOOKUP($D22,BS별도,MATCH(N$1,BS별도H,0),0)/100,"") | O22: =IFERROR(VLOOKUP($D22,BS별도,MATCH(O$1,BS별도H,0),0)/100,"") | P22: =O22 | Q22: =IFERROR(VLOOKUP($D22,BS별도,MATCH(Q$1,BS별도H,0),0)/100,"") | R22: =IFERROR(VLOOKUP($D22,BS별도,MATCH(R$1,BS별도H,0),0)/100,"") | S22: =IFERROR(VLOOKUP($D22,BS별도,MATCH(S$1,BS별도H,0),0)/100,"") | T22: =IFERROR(VLOOKUP($D22,BS별도,MATCH(T$1,BS별도H,0),0)/100,"") | U22: =T22 | V22: =IFERROR(VLOOKUP($D22,BS별도,MATCH(V$1,BS별도H,0),0)/100,"") | W22: =IFERROR(VLOOKUP($D22,BS별도,MATCH(W$1,BS별도H,0),0)/100,"") | X22: =IFERROR(VLOOKUP($D22,BS별도,MATCH(X$1,BS별도H,0),0)/100,"") | Y22: =IFERROR(VLOOKUP($D22,BS별도,MATCH(Y$1,BS별도H,0),0)/100,"") | Z22: =Y22 | AA22: =IFERROR(VLOOKUP($D22,BS연결,MATCH(AA$1,BS연결H,0),0)/100,"") | AB22: =IFERROR(VLOOKUP($D22,BS연결,MATCH(AB$1,BS연결H,0),0)/100,"") | AC22: =IFERROR(AC23+AC24,"") | AD22: =IFERROR(AD23+AD24,"") | AE22: =AD22 | AF22: =IFERROR(AF23+AF24,"") | AG22: =IFERROR(AG23+AG24,"") | AH22: =IFERROR(AH23+AH24,"") | AI22: =IFERROR(AI23+AI24,"") | AJ22: =AI22 | AK22: =IFERROR(AK23+AK24,"") | AL22: =IFERROR(AL23+AL24,"") | AM22: =IFERROR(AM23+AM24,"") | AN22: =IFERROR(AN23+AN24,"") | AO22: =AN22
A23: 부채총계 | B23: 재무상태 | C23: 억원 | D23: 부채총계 | E23: =IFERROR(VLOOKUP($D23,BS연결,MATCH(E$1,BS연결H,0),0)/100,"") | F23: =IFERROR(VLOOKUP($D23,BS연결,MATCH(F$1,BS연결H,0),0)/100,"") | G23: =IFERROR(VLOOKUP($D23,BS연결,MATCH(G$1,BS연결H,0),0)/100,"") | H23: =IFERROR(VLOOKUP($D23,BS연결,MATCH(H$1,BS연결H,0),0)/100,"") | I23: =IFERROR(VLOOKUP($D23,BS연결,MATCH(I$1,BS연결H,0),0)/100,"") | J23: =IFERROR(VLOOKUP($D23,BS연결,MATCH(J$1,BS연결H,0),0)/100,"") | K23: =IFERROR(VLOOKUP($D23,BS연결,MATCH(K$1,BS연결H,0),0)/100,"") | L23: =IFERROR(VLOOKUP($D23,BS연결,MATCH(L$1,BS연결H,0),0)/100,"") | M23: =IFERROR(VLOOKUP($D23,BS연결,MATCH(M$1,BS연결H,0),0)/100,"") | N23: =IFERROR(VLOOKUP($D23,BS별도,MATCH(N$1,BS별도H,0),0)/100,"") | O23: =IFERROR(VLOOKUP($D23,BS별도,MATCH(O$1,BS별도H,0),0)/100,"") | P23: =O23 | Q23: =IFERROR(VLOOKUP($D23,BS별도,MATCH(Q$1,BS별도H,0),0)/100,"") | R23: =IFERROR(VLOOKUP($D23,BS별도,MATCH(R$1,BS별도H,0),0)/100,"") | S23: =IFERROR(VLOOKUP($D23,BS별도,MATCH(S$1,BS별도H,0),0)/100,"") | T23: =IFERROR(VLOOKUP($D23,BS별도,MATCH(T$1,BS별도H,0),0)/100,"") | U23: =T23 | V23: =IFERROR(VLOOKUP($D23,BS별도,MATCH(V$1,BS별도H,0),0)/100,"") | W23: =IFERROR(VLOOKUP($D23,BS별도,MATCH(W$1,BS별도H,0),0)/100,"") | X23: =IFERROR(VLOOKUP($D23,BS별도,MATCH(X$1,BS별도H,0),0)/100,"") | Y23: =IFERROR(VLOOKUP($D23,BS별도,MATCH(Y$1,BS별도H,0),0)/100,"") | Z23: =Y23 | AA23: =IFERROR(VLOOKUP($D23,BS연결,MATCH(AA$1,BS연결H,0),0)/100,"") | AB23: =IFERROR(VLOOKUP($D23,BS연결,MATCH(AB$1,BS연결H,0),0)/100,"") | AC23: =IFERROR(AB23*(1+변수!AC31),"") | AD23: =IFERROR(AC23*(1+변수!AD31),"") | AE23: =AD23 | AF23: =IFERROR(AD23*(1+변수!AF31),"") | AG23: =IFERROR(AF23*(1+변수!AG31),"") | AH23: =IFERROR(AG23*(1+변수!AH31),"") | AI23: =IFERROR(AH23*(1+변수!AI31),"") | AJ23: =AI23 | AK23: =IFERROR(AI23*(1+변수!AK31),"") | AL23: =IFERROR(AK23*(1+변수!AL31),"") | AM23: =IFERROR(AL23*(1+변수!AM31),"") | AN23: =IFERROR(AM23*(1+변수!AN31),"") | AO23: =AN23
A24: 자본총계 | B24: 재무상태 | C24: 억원 | D24: 자본총계 | E24: =IFERROR(VLOOKUP($D24,BS연결,MATCH(E$1,BS연결H,0),0)/100,"") | F24: =IFERROR(VLOOKUP($D24,BS연결,MATCH(F$1,BS연결H,0),0)/100,"") | G24: =IFERROR(VLOOKUP($D24,BS연결,MATCH(G$1,BS연결H,0),0)/100,"") | H24: =IFERROR(VLOOKUP($D24,BS연결,MATCH(H$1,BS연결H,0),0)/100,"") | I24: =IFERROR(VLOOKUP($D24,BS연결,MATCH(I$1,BS연결H,0),0)/100,"") | J24: =IFERROR(VLOOKUP($D24,BS연결,MATCH(J$1,BS연결H,0),0)/100,"") | K24: =IFERROR(VLOOKUP($D24,BS연결,MATCH(K$1,BS연결H,0),0)/100,"") | L24: =IFERROR(VLOOKUP($D24,BS연결,MATCH(L$1,BS연결H,0),0)/100,"") | M24: =IFERROR(VLOOKUP($D24,BS연결,MATCH(M$1,BS연결H,0),0)/100,"") | N24: =IFERROR(VLOOKUP($D24,BS별도,MATCH(N$1,BS별도H,0),0)/100,"") | O24: =IFERROR(VLOOKUP($D24,BS별도,MATCH(O$1,BS별도H,0),0)/100,"") | P24: =O24 | Q24: =IFERROR(VLOOKUP($D24,BS별도,MATCH(Q$1,BS별도H,0),0)/100,"") | R24: =IFERROR(VLOOKUP($D24,BS별도,MATCH(R$1,BS별도H,0),0)/100,"") | S24: =IFERROR(VLOOKUP($D24,BS별도,MATCH(S$1,BS별도H,0),0)/100,"") | T24: =IFERROR(VLOOKUP($D24,BS별도,MATCH(T$1,BS별도H,0),0)/100,"") | U24: =T24 | V24: =IFERROR(VLOOKUP($D24,BS별도,MATCH(V$1,BS별도H,0),0)/100,"") | W24: =IFERROR(VLOOKUP($D24,BS별도,MATCH(W$1,BS별도H,0),0)/100,"") | X24: =IFERROR(VLOOKUP($D24,BS별도,MATCH(X$1,BS별도H,0),0)/100,"") | Y24: =IFERROR(VLOOKUP($D24,BS별도,MATCH(Y$1,BS별도H,0),0)/100,"") | Z24: =IFERROR(VLOOKUP($D24,BS연결,MATCH(Z$1,BS연결H,0),0)/100,"") | AA24: =IFERROR(VLOOKUP($D24,BS연결,MATCH(AA$1,BS연결H,0),0)/100,"") | AB24: =IFERROR(VLOOKUP($D24,BS연결,MATCH(AB$1,BS연결H,0),0)/100,"") | AC24: =IFERROR(AB24+AC20-변수!AC32,"") | AD24: =IFERROR(AC24+AD20-변수!AD32,"") | AE24: =AD24 | AF24: =IFERROR(AD24+AF20-변수!AF32,"") | AG24: =IFERROR(AF24+AG20-변수!AG32,"") | AH24: =IFERROR(AG24+AH20-변수!AH32,"") | AI24: =IFERROR(AH24+AI20-변수!AI32,"") | AJ24: =AI24 | AK24: =IFERROR(AI24+AK20-변수!AK32,"") | AL24: =IFERROR(AK24+AL20-변수!AL32,"") | AM24: =IFERROR(AL24+AM20-변수!AM32,"") | AN24: =IFERROR(AM24+AN20-변수!AN32,"") | AO24: =AN24
A25: 지배주주지분 | B25: 재무상태 | C25: 억원 | D25: 지배주주지분 | E25: =IFERROR(VLOOKUP($D25,BS연결,MATCH(E$1,BS연결H,0),0)/100,"") | F25: =IFERROR(VLOOKUP($D25,BS연결,MATCH(F$1,BS연결H,0),0)/100,"") | G25: =IFERROR(VLOOKUP($D25,BS연결,MATCH(G$1,BS연결H,0),0)/100,"") | H25: =IFERROR(VLOOKUP($D25,BS연결,MATCH(H$1,BS연결H,0),0)/100,"") | I25: =IFERROR(VLOOKUP($D25,BS연결,MATCH(I$1,BS연결H,0),0)/100,"") | J25: =IFERROR(VLOOKUP($D25,BS연결,MATCH(J$1,BS연결H,0),0)/100,"") | K25: =IFERROR(VLOOKUP($D25,BS연결,MATCH(K$1,BS연결H,0),0)/100,"") | L25: =IFERROR(VLOOKUP($D25,BS연결,MATCH(L$1,BS연결H,0),0)/100,"") | M25: =IFERROR(VLOOKUP($D25,BS연결,MATCH(M$1,BS연결H,0),0)/100,"") | N25: =IFERROR(VLOOKUP($D25,BS별도,MATCH(N$1,BS별도H,0),0)/100,"") | O25: =IFERROR(VLOOKUP($D25,BS별도,MATCH(O$1,BS별도H,0),0)/100,"") | P25: =O25 | Q25: =IFERROR(VLOOKUP($D25,BS별도,MATCH(Q$1,BS별도H,0),0)/100,"") | R25: =IFERROR(VLOOKUP($D25,BS별도,MATCH(R$1,BS별도H,0),0)/100,"") | S25: =IFERROR(VLOOKUP($D25,BS별도,MATCH(S$1,BS별도H,0),0)/100,"") | T25: =IFERROR(VLOOKUP($D25,BS별도,MATCH(T$1,BS별도H,0),0)/100,"") | U25: =T25 | V25: =IFERROR(VLOOKUP($D25,BS별도,MATCH(V$1,BS별도H,0),0)/100,"") | W25: =IFERROR(VLOOKUP($D25,BS별도,MATCH(W$1,BS별도H,0),0)/100,"") | X25: =IFERROR(VLOOKUP($D25,BS별도,MATCH(X$1,BS별도H,0),0)/100,"") | Y25: =IFERROR(VLOOKUP($D25,BS별도,MATCH(Y$1,BS별도H,0),0)/100,"") | Z25: =IFERROR(VLOOKUP($D25,BS연결,MATCH(Z$1,BS연결H,0),0)/100,"") | AA25: =IFERROR(VLOOKUP($D25,BS연결,MATCH(AA$1,BS연결H,0),0)/100,"") | AB25: =IFERROR(VLOOKUP($D25,BS연결,MATCH(AB$1,BS연결H,0),0)/100,"") | AC25: =IFERROR(AB25+AC21-변수!AC33,"") | AD25: =IFERROR(AC25+AD21-변수!AD33,"") | AE25: =AD25 | AF25: =IFERROR(AD25+AF21-변수!AF33,"") | AG25: =IFERROR(AF25+AG21-변수!AG33,"") | AH25: =IFERROR(AG25+AH21-변수!AH33,"") | AI25: =IFERROR(AH25+AI21-변수!AI33,"") | AJ25: =AI25 | AK25: =IFERROR(AI25+AK21-변수!AK33,"") | AL25: =IFERROR(AK25+AL21-변수!AL33,"") | AM25: =IFERROR(AL25+AM21-변수!AM33,"") | AN25: =IFERROR(AM25+AN21-변수!AN33,"") | AO25: =AN25
A26: 총차입금 | B26: 재무상태 | C26: 억원 | D26: 총차입금 | E26: =IFERROR(VLOOKUP($D26,BS연결,MATCH(E$1,BS연결H,0),0)/100,"") | F26: =IFERROR(VLOOKUP($D26,BS연결,MATCH(F$1,BS연결H,0),0)/100,"") | G26: =IFERROR(VLOOKUP($D26,BS연결,MATCH(G$1,BS연결H,0),0)/100,"") | H26: =IFERROR(VLOOKUP($D26,BS연결,MATCH(H$1,BS연결H,0),0)/100,"") | I26: =IFERROR(VLOOKUP($D26,BS연결,MATCH(I$1,BS연결H,0),0)/100,"") | J26: =IFERROR(VLOOKUP($D26,BS연결,MATCH(J$1,BS연결H,0),0)/100,"") | K26: =IFERROR(VLOOKUP($D26,BS연결,MATCH(K$1,BS연결H,0),0)/100,"") | L26: =IFERROR(VLOOKUP($D26,BS연결,MATCH(L$1,BS연결H,0),0)/100,"") | M26: =IFERROR(VLOOKUP($D26,BS연결,MATCH(M$1,BS연결H,0),0)/100,"") | N26: =IFERROR(VLOOKUP($D26,BS별도,MATCH(N$1,BS별도H,0),0)/100,"") | O26: =IFERROR(VLOOKUP($D26,BS별도,MATCH(O$1,BS별도H,0),0)/100,"") | P26: =O26 | Q26: =IFERROR(VLOOKUP($D26,BS별도,MATCH(Q$1,BS별도H,0),0)/100,"") | R26: =IFERROR(VLOOKUP($D26,BS별도,MATCH(R$1,BS별도H,0),0)/100,"") | S26: =IFERROR(VLOOKUP($D26,BS별도,MATCH(S$1,BS별도H,0),0)/100,"") | T26: =IFERROR(VLOOKUP($D26,BS별도,MATCH(T$1,BS별도H,0),0)/100,"") | U26: =T26 | V26: =IFERROR(VLOOKUP($D26,BS별도,MATCH(V$1,BS별도H,0),0)/100,"") | W26: =IFERROR(VLOOKUP($D26,BS별도,MATCH(W$1,BS별도H,0),0)/100,"") | X26: =IFERROR(VLOOKUP($D26,BS별도,MATCH(X$1,BS별도H,0),0)/100,"") | Y26: =IFERROR(VLOOKUP($D26,BS별도,MATCH(Y$1,BS별도H,0),0)/100,"") | Z26: =IFERROR(VLOOKUP($D26,BS연결,MATCH(Z$1,BS연결H,0),0)/100,"") | AA26: =IFERROR(VLOOKUP($D26,BS연결,MATCH(AA$1,BS연결H,0),0)/100,"") | AB26: =IFERROR(VLOOKUP($D26,BS연결,MATCH(AB$1,BS연결H,0),0)/100,"") | AC26: =IFERROR(AB26*(1+변수!AC34),"") | AD26: =IFERROR(AC26*(1+변수!AD34),"") | AE26: =AD26 | AF26: =IFERROR(AD26*(1+변수!AF34),"") | AG26: =IFERROR(AF26*(1+변수!AG34),"") | AH26: =IFERROR(AG26*(1+변수!AH34),"") | AI26: =IFERROR(AH26*(1+변수!AI34),"") | AJ26: =AI26 | AK26: =IFERROR(AI26*(1+변수!AK34),"") | AL26: =IFERROR(AK26*(1+변수!AL34),"") | AM26: =IFERROR(AL26*(1+변수!AM34),"") | AN26: =IFERROR(AM26*(1+변수!AN34),"") | AO26: =AN26
A27: 순차입금 | B27: 재무상태 | C27: 억원 | D27: 순차입금 | E27: =IFERROR(VLOOKUP($D27,BS연결,MATCH(E$1,BS연결H,0),0)/100,"") | F27: =IFERROR(VLOOKUP($D27,BS연결,MATCH(F$1,BS연결H,0),0)/100,"") | G27: =IFERROR(VLOOKUP($D27,BS연결,MATCH(G$1,BS연결H,0),0)/100,"") | H27: =IFERROR(VLOOKUP($D27,BS연결,MATCH(H$1,BS연결H,0),0)/100,"") | I27: =IFERROR(VLOOKUP($D27,BS연결,MATCH(I$1,BS연결H,0),0)/100,"") | J27: =IFERROR(VLOOKUP($D27,BS연결,MATCH(J$1,BS연결H,0),0)/100,"") | K27: =IFERROR(VLOOKUP($D27,BS연결,MATCH(K$1,BS연결H,0),0)/100,"") | L27: =IFERROR(VLOOKUP($D27,BS연결,MATCH(L$1,BS연결H,0),0)/100,"") | M27: =IFERROR(VLOOKUP($D27,BS연결,MATCH(M$1,BS연결H,0),0)/100,"") | N27: =IFERROR(VLOOKUP($D27,BS별도,MATCH(N$1,BS별도H,0),0)/100,"") | O27: =IFERROR(VLOOKUP($D27,BS별도,MATCH(O$1,BS별도H,0),0)/100,"") | P27: =O27 | Q27: =IFERROR(VLOOKUP($D27,BS별도,MATCH(Q$1,BS별도H,0),0)/100,"") | R27: =IFERROR(VLOOKUP($D27,BS별도,MATCH(R$1,BS별도H,0),0)/100,"") | S27: =IFERROR(VLOOKUP($D27,BS별도,MATCH(S$1,BS별도H,0),0)/100,"") | T27: =IFERROR(VLOOKUP($D27,BS별도,MATCH(T$1,BS별도H,0),0)/100,"") | U27: =T27 | V27: =IFERROR(VLOOKUP($D27,BS별도,MATCH(V$1,BS별도H,0),0)/100,"") | W27: =IFERROR(VLOOKUP($D27,BS별도,MATCH(W$1,BS별도H,0),0)/100,"") | X27: =IFERROR(VLOOKUP($D27,BS별도,MATCH(X$1,BS별도H,0),0)/100,"") | Y27: =IFERROR(VLOOKUP($D27,BS별도,MATCH(Y$1,BS별도H,0),0)/100,"") | Z27: =IFERROR(VLOOKUP($D27,BS연결,MATCH(Z$1,BS연결H,0),0)/100,"") | AA27: =IFERROR(VLOOKUP($D27,BS연결,MATCH(AA$1,BS연결H,0),0)/100,"") | AB27: =IFERROR(VLOOKUP($D27,BS연결,MATCH(AB$1,BS연결H,0),0)/100,"") | AC27: =IFERROR(AB27*(1+변수!AC35),"") | AD27: =IFERROR(AC27*(1+변수!AD35),"") | AE27: =AD27 | AF27: =IFERROR(AD27*(1+변수!AF35),"") | AG27: =IFERROR(AF27*(1+변수!AG35),"") | AH27: =IFERROR(AG27*(1+변수!AH35),"") | AI27: =IFERROR(AH27*(1+변수!AI35),"") | AJ27: =AI27 | AK27: =IFERROR(AI27*(1+변수!AK35),"") | AL27: =IFERROR(AK27*(1+변수!AL35),"") | AM27: =IFERROR(AL27*(1+변수!AM35),"") | AN27: =IFERROR(AM27*(1+변수!AN35),"") | AO27: =AN27
A28: 이자발생자산 | B28: 재무상태 | C28: 억원 | D28: 이자발생자산 | E28: =IFERROR(VLOOKUP($D28,BS연결,MATCH(E$1,BS연결H,0),0)/100,"") | F28: =IFERROR(VLOOKUP($D28,BS연결,MATCH(F$1,BS연결H,0),0)/100,"") | G28: =IFERROR(VLOOKUP($D28,BS연결,MATCH(G$1,BS연결H,0),0)/100,"") | H28: =IFERROR(VLOOKUP($D28,BS연결,MATCH(H$1,BS연결H,0),0)/100,"") | I28: =IFERROR(VLOOKUP($D28,BS연결,MATCH(I$1,BS연결H,0),0)/100,"") | J28: =IFERROR(VLOOKUP($D28,BS연결,MATCH(J$1,BS연결H,0),0)/100,"") | K28: =IFERROR(VLOOKUP($D28,BS연결,MATCH(K$1,BS연결H,0),0)/100,"") | L28: =IFERROR(VLOOKUP($D28,BS연결,MATCH(L$1,BS연결H,0),0)/100,"") | M28: =IFERROR(VLOOKUP($D28,BS연결,MATCH(M$1,BS연결H,0),0)/100,"") | N28: =IFERROR(VLOOKUP($D28,BS별도,MATCH(N$1,BS별도H,0),0)/100,"") | O28: =IFERROR(VLOOKUP($D28,BS별도,MATCH(O$1,BS별도H,0),0)/100,"") | P28: =O28 | Q28: =IFERROR(VLOOKUP($D28,BS별도,MATCH(Q$1,BS별도H,0),0)/100,"") | R28: =IFERROR(VLOOKUP($D28,BS별도,MATCH(R$1,BS별도H,0),0)/100,"") | S28: =IFERROR(VLOOKUP($D28,BS별도,MATCH(S$1,BS별도H,0),0)/100,"") | T28: =IFERROR(VLOOKUP($D28,BS별도,MATCH(T$1,BS별도H,0),0)/100,"") | U28: =T28 | V28: =IFERROR(VLOOKUP($D28,BS별도,MATCH(V$1,BS별도H,0),0)/100,"") | W28: =IFERROR(VLOOKUP($D28,BS별도,MATCH(W$1,BS별도H,0),0)/100,"") | X28: =IFERROR(VLOOKUP($D28,BS별도,MATCH(X$1,BS별도H,0),0)/100,"") | Y28: =IFERROR(VLOOKUP($D28,BS별도,MATCH(Y$1,BS별도H,0),0)/100,"") | Z28: =IFERROR(VLOOKUP($D28,BS연결,MATCH(Z$1,BS연결H,0),0)/100,"") | AA28: =IFERROR(VLOOKUP($D28,BS연결,MATCH(AA$1,BS연결H,0),0)/100,"") | AB28: =IFERROR(VLOOKUP($D28,BS연결,MATCH(AB$1,BS연결H,0),0)/100,"") | AC28: =IFERROR(AB28*(1+변수!AC36),"") | AD28: =IFERROR(AC28*(1+변수!AD36),"") | AE28: =AD28 | AF28: =IFERROR(AD28*(1+변수!AF36),"") | AG28: =IFERROR(AF28*(1+변수!AG36),"") | AH28: =IFERROR(AG28*(1+변수!AH36),"") | AI28: =IFERROR(AH28*(1+변수!AI36),"") | AJ28: =AI28 | AK28: =IFERROR(AI28*(1+변수!AK36),"") | AL28: =IFERROR(AK28*(1+변수!AL36),"") | AM28: =IFERROR(AL28*(1+변수!AM36),"") | AN28: =IFERROR(AM28*(1+변수!AN36),"") | AO28: =AN28
A29: 현금및현금성자산 | B29: 재무상태 | C29: 억원 | D29: 현금및현금성자산 | E29: =IFERROR(VLOOKUP($D29,BS연결,MATCH(E$1,BS연결H,0),0)/100,"") | F29: =IFERROR(VLOOKUP($D29,BS연결,MATCH(F$1,BS연결H,0),0)/100,"") | G29: =IFERROR(VLOOKUP($D29,BS연결,MATCH(G$1,BS연결H,0),0)/100,"") | H29: =IFERROR(VLOOKUP($D29,BS연결,MATCH(H$1,BS연결H,0),0)/100,"") | I29: =IFERROR(VLOOKUP($D29,BS연결,MATCH(I$1,BS연결H,0),0)/100,"") | J29: =IFERROR(VLOOKUP($D29,BS연결,MATCH(J$1,BS연결H,0),0)/100,"") | K29: =IFERROR(VLOOKUP($D29,BS연결,MATCH(K$1,BS연결H,0),0)/100,"") | L29: =IFERROR(VLOOKUP($D29,BS연결,MATCH(L$1,BS연결H,0),0)/100,"") | M29: =IFERROR(VLOOKUP($D29,BS연결,MATCH(M$1,BS연결H,0),0)/100,"") | N29: =IFERROR(VLOOKUP($D29,BS별도,MATCH(N$1,BS별도H,0),0)/100,"") | O29: =IFERROR(VLOOKUP($D29,BS별도,MATCH(O$1,BS별도H,0),0)/100,"") | P29: =O29 | Q29: =IFERROR(VLOOKUP($D29,BS별도,MATCH(Q$1,BS별도H,0),0)/100,"") | R29: =IFERROR(VLOOKUP($D29,BS별도,MATCH(R$1,BS별도H,0),0)/100,"") | S29: =IFERROR(VLOOKUP($D29,BS별도,MATCH(S$1,BS별도H,0),0)/100,"") | T29: =IFERROR(VLOOKUP($D29,BS별도,MATCH(T$1,BS별도H,0),0)/100,"") | U29: =T29 | V29: =IFERROR(VLOOKUP($D29,BS별도,MATCH(V$1,BS별도H,0),0)/100,"") | W29: =IFERROR(VLOOKUP($D29,BS별도,MATCH(W$1,BS별도H,0),0)/100,"") | X29: =IFERROR(VLOOKUP($D29,BS별도,MATCH(X$1,BS별도H,0),0)/100,"") | Y29: =IFERROR(VLOOKUP($D29,BS별도,MATCH(Y$1,BS별도H,0),0)/100,"") | Z29: =IFERROR(VLOOKUP($D29,BS연결,MATCH(Z$1,BS연결H,0),0)/100,"") | AA29: =IFERROR(VLOOKUP($D29,BS연결,MATCH(AA$1,BS연결H,0),0)/100,"") | AB29: =IFERROR(VLOOKUP($D29,BS연결,MATCH(AB$1,BS연결H,0),0)/100,"") | AE29: =AD29 | AJ29: =AI29 | AO29: =AN29
A30: CAPEX | B30: 현금흐름 | C30: 억원 | D30: CAPEX | E30: =IFERROR(VLOOKUP($D30,BS연결,MATCH(E$1,BS연결H,0),0)/100,"") | G30: =IFERROR(VLOOKUP($D30,BS연결,MATCH(G$1,BS연결H,0),0)/100,"") | H30: =IFERROR(VLOOKUP($D30,BS연결,MATCH(H$1,BS연결H,0),0)/100,"") | I30: =IFERROR(VLOOKUP($D30,BS연결,MATCH(I$1,BS연결H,0),0)/100,"") | J30: =IFERROR(VLOOKUP($D30,BS연결,MATCH(J$1,BS연결H,0),0)/100,"") | K30: =IFERROR(VLOOKUP($D30,BS연결,MATCH(K$1,BS연결H,0),0)/100,"") | L30: =IFERROR(VLOOKUP($D30,BS연결,MATCH(L$1,BS연결H,0),0)/100,"") | M30: =IFERROR(VLOOKUP($D30,BS연결,MATCH(M$1,BS연결H,0),0)/100,"") | N30: =IFERROR(VLOOKUP($D30,BS별도,MATCH(N$1,BS별도H,0),0)/100,"") | O30: =IFERROR(VLOOKUP($D30,BS별도,MATCH(O$1,BS별도H,0),0)/100,"") | P30: =SUM(L30:O30) | Q30: =IFERROR(VLOOKUP($D30,BS별도,MATCH(Q$1,BS별도H,0),0)/100,"") | R30: =IFERROR(VLOOKUP($D30,BS별도,MATCH(R$1,BS별도H,0),0)/100,"") | S30: =IFERROR(VLOOKUP($D30,BS별도,MATCH(S$1,BS별도H,0),0)/100,"") | T30: =IFERROR(VLOOKUP($D30,BS별도,MATCH(T$1,BS별도H,0),0)/100,"") | U30: =SUM(Q30:T30) | V30: =IFERROR(VLOOKUP($D30,BS별도,MATCH(V$1,BS별도H,0),0)/100,"") | W30: =IFERROR(VLOOKUP($D30,BS별도,MATCH(W$1,BS별도H,0),0)/100,"") | X30: =IFERROR(VLOOKUP($D30,BS별도,MATCH(X$1,BS별도H,0),0)/100,"") | Y30: =IFERROR(VLOOKUP($D30,BS별도,MATCH(Y$1,BS별도H,0),0)/100,"") | Z30: =SUM(V30:Y30) | AA30: =IFERROR(VLOOKUP($D30,BS연결,MATCH(AA$1,BS연결H,0),0)/100,"") | AC30: =IFERROR(X30*(1+변수!AC38),"") | AD30: =IFERROR(Y30*(1+변수!AD38),"") | AE30: =SUM(AA30:AD30) | AF30: =IFERROR(AA30*(1+변수!AF38),"") | AG30: =IFERROR(AF30*(1+변수!AG38),"") | AH30: =IFERROR(AC30*(1+변수!AH38),"") | AI30: =IFERROR(AD30*(1+변수!AI38),"") | AJ30: =SUM(AF30:AI30) | AK30: =IFERROR(AF30*(1+변수!AK38),"") | AL30: =IFERROR(AG30*(1+변수!AL38),"") | AM30: =IFERROR(AH30*(1+변수!AM38),"") | AN30: =IFERROR(AI30*(1+변수!AN38),"") | AO30: =SUM(AK30:AN30)
A31: 영업활동현금흐름 | B31: 현금흐름 | C31: 억원 | D31: 영업활동으로인한현금흐름 | E31: =IFERROR(VLOOKUP($D31,BS연결,MATCH(E$1,BS연결H,0),0)/100,"") | G31: =IFERROR(VLOOKUP($D31,BS연결,MATCH(G$1,BS연결H,0),0)/100,"") | H31: =IFERROR(VLOOKUP($D31,BS연결,MATCH(H$1,BS연결H,0),0)/100,"") | I31: =IFERROR(VLOOKUP($D31,BS연결,MATCH(I$1,BS연결H,0),0)/100,"") | J31: =IFERROR(VLOOKUP($D31,BS연결,MATCH(J$1,BS연결H,0),0)/100,"") | K31: =SUM(G31:J31) | L31: =IFERROR(VLOOKUP($D31,BS연결,MATCH(L$1,BS연결H,0),0)/100,"") | M31: =IFERROR(VLOOKUP($D31,BS연결,MATCH(M$1,BS연결H,0),0)/100,"") | N31: =IFERROR(VLOOKUP($D31,BS별도,MATCH(N$1,BS별도H,0),0)/100,"") | O31: =IFERROR(VLOOKUP($D31,BS별도,MATCH(O$1,BS별도H,0),0)/100,"") | P31: =SUM(L31:O31) | Q31: =IFERROR(VLOOKUP($D31,BS별도,MATCH(Q$1,BS별도H,0),0)/100,"") | R31: =IFERROR(VLOOKUP($D31,BS별도,MATCH(R$1,BS별도H,0),0)/100,"") | S31: =IFERROR(VLOOKUP($D31,BS별도,MATCH(S$1,BS별도H,0),0)/100,"") | T31: =IFERROR(VLOOKUP($D31,BS별도,MATCH(T$1,BS별도H,0),0)/100,"") | U31: =SUM(Q31:T31) | V31: =IFERROR(VLOOKUP($D31,BS별도,MATCH(V$1,BS별도H,0),0)/100,"") | W31: =IFERROR(VLOOKUP($D31,BS별도,MATCH(W$1,BS별도H,0),0)/100,"") | X31: =IFERROR(VLOOKUP($D31,BS별도,MATCH(X$1,BS별도H,0),0)/100,"") | Y31: =IFERROR(VLOOKUP($D31,BS별도,MATCH(Y$1,BS별도H,0),0)/100,"") | Z31: =SUM(V31:Y31) | AA31: =IFERROR(VLOOKUP($D31,BS연결,MATCH(AA$1,BS연결H,0),0)/100,"") | AB31: =IFERROR(VLOOKUP($D31,BS연결,MATCH(AB$1,BS연결H,0),0)/100,"") | AE31: =SUM(AA31:AD31) | AJ31: =SUM(AF31:AI31) | AO31: =SUM(AK31:AN31)
A32: 주식수 | B32: 주당 | C32: 백만주 | D32: 유통주식수 | E32: 46.714 | F32: =E32 | G32: 46.714 | H32: 46.714 | I32: 71.522 | J32: 71.522 | K32: =J32 | L32: 71.522 | M32: 71.522 | N32: 71.522 | O32: 71.522 | P32: =O32 | Q32: 83.426 | R32: 83.426 | S32: 83.426 | T32: 83.426 | U32: =T32 | V32: 83.426 | W32: 83.426 | X32: 83.426 | Y32: 83.426 | Z32: =Y32 | AA32: 83.426 | AB32: 83.426 | AC32: =IFERROR(AB32*(1+변수!AC40),"") | AD32: =IFERROR(AC32*(1+변수!AD40),"") | AE32: =AD32 | AF32: =IFERROR(AD32*(1+변수!AF40),"") | AG32: =IFERROR(AF32*(1+변수!AG40),"") | AH32: =IFERROR(AG32*(1+변수!AH40),"") | AI32: =IFERROR(AH32*(1+변수!AI40),"") | AJ32: =AI32 | AK32: =IFERROR(AI32*(1+변수!AK40),"") | AL32: =IFERROR(AK32*(1+변수!AL40),"") | AM32: =IFERROR(AL32*(1+변수!AM40),"") | AN32: =IFERROR(AM32*(1+변수!AN40),"") | AO32: =AN32
A33: EPS | B33: 주당 | C33: 원 | D33: EPS | E33: =IFERROR(E21*100/E32,"") | G33: =IFERROR(G21*100/G32,"") | H33: =IFERROR(H21*100/H32,"") | I33: =IFERROR(I21*100/I32,"") | J33: =IFERROR(J21*100/J32,"") | K33: =SUM(G33:J33) | L33: =IFERROR(L21*100/L32,"") | M33: =IFERROR(M21*100/M32,"") | N33: =IFERROR(N21*100/N32,"") | O33: =IFERROR(O21*100/O32,"") | P33: =SUM(L33:O33) | Q33: =IFERROR(Q21*100/Q32,"") | R33: =IFERROR(R21*100/R32,"") | S33: =IFERROR(S21*100/S32,"") | T33: =IFERROR(T21*100/T32,"") | U33: =SUM(Q33:T33) | V33: =IFERROR(V21*100/V32,"") | W33: =IFERROR(W21*100/W32,"") | X33: =IFERROR(X21*100/X32,"") | Y33: =IFERROR(Y21*100/Y32,"") | Z33: =SUM(V33:Y33) | AA33: =IFERROR(AA21*100/AA32,"") | AB33: =IFERROR(AB21*100/AB32,"") | AC33: =IFERROR(AC21*100/AC32,"") | AD33: =IFERROR(AD21*100/AD32,"") | AE33: =SUM(AA33:AD33) | AF33: =IFERROR(AF21*100/AF32,"") | AG33: =IFERROR(AG21*100/AG32,"") | AH33: =IFERROR(AH21*100/AH32,"") | AI33: =IFERROR(AI21*100/AI32,"") | AJ33: =SUM(AF33:AI33) | AK33: =IFERROR(AK21*100/AK32,"") | AL33: =IFERROR(AL21*100/AL32,"") | AM33: =IFERROR(AM21*100/AM32,"") | AN33: =IFERROR(AN21*100/AN32,"") | AO33: =SUM(AK33:AN33)
A34: BPS | B34: 주당 | C34: 원 | D34: BPS | E34: =IFERROR(E25*100/E32,"") | F34: =E34 | G34: =IFERROR(G25*100/G32,"") | H34: =IFERROR(H25*100/H32,"") | I34: =IFERROR(I25*100/I32,"") | J34: =IFERROR(J25*100/J32,"") | K34: =J34 | L34: =IFERROR(L25*100/L32,"") | M34: =IFERROR(M25*100/M32,"") | N34: =IFERROR(N25*100/N32,"") | O34: =IFERROR(O25*100/O32,"") | P34: =O34 | Q34: =IFERROR(Q25*100/Q32,"") | R34: =IFERROR(R25*100/R32,"") | S34: =IFERROR(S25*100/S32,"") | T34: =IFERROR(T25*100/T32,"") | U34: =T34 | V34: =IFERROR(V25*100/V32,"") | W34: =IFERROR(W25*100/W32,"") | X34: =IFERROR(X25*100/X32,"") | Y34: =IFERROR(Y25*100/Y32,"") | Z34: =Y34 | AA34: =IFERROR(AA25*100/AA32,"") | AB34: =IFERROR(AB25*100/AB32,"") | AC34: =IFERROR(AC25*100/AC32,"") | AD34: =IFERROR(AD25*100/AD32,"") | AE34: =AD34 | AF34: =IFERROR(AF25*100/AF32,"") | AG34: =IFERROR(AG25*100/AG32,"") | AH34: =IFERROR(AH25*100/AH32,"") | AI34: =IFERROR(AI25*100/AI32,"") | AJ34: =AI34 | AK34: =IFERROR(AK25*100/AK32,"") | AL34: =IFERROR(AL25*100/AL32,"") | AM34: =IFERROR(AM25*100/AM32,"") | AN34: =IFERROR(AN25*100/AN32,"") | AO34: =AN34
A35: DPS | B35: 주당 | C35: 원 | D35: DPS(보통주) | E35: 0 | F35: 0 | J35: 0 | K35: =SUM(G35:J35) | O35: 0 | P35: =SUM(L35:O35) | T35: 0 | U35: =SUM(Q35:T35) | Y35: 0 | Z35: =SUM(V35:Y35) | AD35: =변수!AD41 | AE35: =SUM(AA35:AD35) | AI35: =변수!AI41 | AJ35: =SUM(AF35:AI35) | AN35: =변수!AN41 | AO35: =SUM(AK35:AN35)
A36: PER | B36: 주당 | C36: 배 | D36: PER | F36: =E36 | K36: =J36 | M36: =IFERROR(변수!M18/(I33+J33+L33+M33),"") | P36: =O36 | Q36: =IFERROR(변수!Q18/(M33+N33+O33+Q33),"") | R36: =IFERROR(변수!R18/(N33+O33+Q33+R33),"") | S36: =IFERROR(변수!S18/(O33+Q33+R33+S33),"") | T36: =IFERROR(변수!T18/(Q33+R33+S33+T33),"") | U36: =T36 | V36: =IFERROR(변수!V18/(R33+S33+T33+V33),"") | W36: =IFERROR(변수!W18/(S33+T33+V33+W33),"") | X36: =IFERROR(변수!X18/(T33+V33+W33+X33),"") | Y36: =IFERROR(변수!Y18/(V33+W33+X33+Y33),"") | Z36: =Y36 | AA36: =IFERROR(변수!AA18/(W33+X33+Y33+AA33),"") | AB36: =IFERROR(변수!AB18/(X33+Y33+AA33+AB33),"") | AC36: =IFERROR(변수!$D$44/(Y33+AA33+AB33+AC33),"") | AD36: =IFERROR(변수!$D$44/(AA33+AB33+AC33+AD33),"") | AE36: =AD36 | AF36: =IFERROR(변수!$D$44/(AB33+AC33+AD33+AF33),"") | AG36: =IFERROR(변수!$D$44/(AC33+AD33+AF33+AG33),"") | AH36: =IFERROR(변수!$D$44/(AD33+AF33+AG33+AH33),"") | AI36: =IFERROR(변수!$D$44/(AF33+AG33+AH33+AI33),"") | AJ36: =AI36 | AK36: =IFERROR(변수!$D$44/(AG33+AH33+AI33+AK33),"") | AL36: =IFERROR(변수!$D$44/(AH33+AI33+AK33+AL33),"") | AM36: =IFERROR(변수!$D$44/(AI33+AK33+AL33+AM33),"") | AN36: =IFERROR(변수!$D$44/(AK33+AL33+AM33+AN33),"") | AO36: =AN36
A37: PBR | B37: 주당 | C37: 배 | D37: PBR | E37: =IFERROR(변수!E18/E34,"") | F37: =E37 | G37: =IFERROR(변수!G18/G34,"") | H37: =IFERROR(변수!H18/H34,"") | I37: =IFERROR(변수!I18/I34,"") | J37: =IFERROR(변수!J18/J34,"") | K37: =J37 | L37: =IFERROR(변수!L18/L34,"") | M37: =IFERROR(변수!M18/M34,"") | N37: =IFERROR(변수!N18/N34,"") | O37: =IFERROR(변수!O18/O34,"") | P37: =O37 | Q37: =IFERROR(변수!Q18/Q34,"") | R37: =IFERROR(변수!R18/R34,"") | S37: =IFERROR(변수!S18/S34,"") | T37: =IFERROR(변수!T18/T34,"") | U37: =T37 | V37: =IFERROR(변수!V18/V34,"") | W37: =IFERROR(변수!W18/W34,"") | X37: =IFERROR(변수!X18/X34,"") | Y37: =IFERROR(변수!Y18/Y34,"") | Z37: =Y37 | AA37: =IFERROR(변수!AA18/AA34,"") | AB37: =IFERROR(변수!AB18/AB34,"") | AC37: =IFERROR(변수!$D$44/AC34,"") | AD37: =IFERROR(변수!$D$44/AD34,"") | AE37: =AD37 | AF37: =IFERROR(변수!$D$44/AF34,"") | AG37: =IFERROR(변수!$D$44/AG34,"") | AH37: =IFERROR(변수!$D$44/AH34,"") | AI37: =IFERROR(변수!$D$44/AI34,"") | AJ37: =AI37 | AK37: =IFERROR(변수!$D$44/AK34,"") | AL37: =IFERROR(변수!$D$44/AL34,"") | AM37: =IFERROR(변수!$D$44/AM34,"") | AN37: =IFERROR(변수!$D$44/AN34,"") | AO37: =AN37
A38: 매출전사 | B38: 사업부 | C38: 억원 | D38: 매출 전사(부문 미분리) | E38: 1956.97 | G38: 1778.43 | H38: 1864.64 | I38: 1757.23 | J38: 2242.13 | K38: =SUM(G38:J38) | L38: 1993.47 | M38: 1890.46 | N38: 1876.37 | O38: 2783.55 | P38: =SUM(L38:O38) | Q38: 2933.65 | R38: 2864.85 | S38: 2960.86 | T38: 3262.68 | U38: =SUM(Q38:T38) | V38: 3181.82 | W38: 3877 | X38: 2973.45 | Y38: 3678.3 | Z38: =SUM(V38:Y38) | AA38: 3452.39 | AB38: 3622.2 | AC38: =IFERROR(AC5,"") | AD38: =IFERROR(AD5,"") | AE38: =SUM(AA38:AD38) | AF38: =IFERROR(AF5,"") | AG38: =IFERROR(AG5,"") | AH38: =IFERROR(AH5,"") | AI38: =IFERROR(AI5,"") | AJ38: =SUM(AF38:AI38) | AK38: =IFERROR(AK5,"") | AL38: =IFERROR(AL5,"") | AM38: =IFERROR(AM5,"") | AN38: =IFERROR(AN5,"") | AO38: =SUM(AK38:AN38)
A39: OP전사 | B39: 사업부 | C39: 억원 | D39: OP 전사(부문 미분리) | E39: -75.59 | G39: -25.57 | H39: -305.31 | I39: 5.18 | J39: 30.36 | K39: =SUM(G39:J39) | L39: 40.74 | M39: 34.73 | N39: 10.84 | O39: 0.97 | P39: =SUM(L39:O39) | Q39: 194.27 | R39: 186.23 | S39: 152.87 | T39: 181.95 | U39: =SUM(Q39:T39) | V39: 223.12 | W39: 337.75 | X39: 266.31 | Y39: 473.48 | Z39: =SUM(V39:Y39) | AA39: 513.79 | AB39: 379.11 | AC39: =IFERROR(AC9,"") | AD39: =IFERROR(AD9,"") | AE39: =SUM(AA39:AD39) | AF39: =IFERROR(AF9,"") | AG39: =IFERROR(AG9,"") | AH39: =IFERROR(AH9,"") | AI39: =IFERROR(AI9,"") | AJ39: =SUM(AF39:AI39) | AK39: =IFERROR(AK9,"") | AL39: =IFERROR(AL9,"") | AM39: =IFERROR(AM9,"") | AN39: =IFERROR(AN9,"") | AO39: =SUM(AK39:AN39)
B40: 비율(참고)
A41: NPM | C41: % | D41: 지배주주순이익 / 매출액 | E41: =IFERROR(E21/E5,"") | F41: =IFERROR(F21/F5,"") | G41: =IFERROR(G21/G5,"") | H41: =IFERROR(H21/H5,"") | I41: =IFERROR(I21/I5,"") | J41: =IFERROR(J21/J5,"") | K41: =IFERROR(K21/K5,"") | L41: =IFERROR(L21/L5,"") | ... AO41: =IFERROR(AO21/AO5,"")
A42: 매출원가율 | C42: % | D42: 매출원가 / 매출액 | E42: =IFERROR(E6/E5,"") | F42: =IFERROR(F6/F5,"") | G42: =IFERROR(G6/G5,"") | H42: =IFERROR(H6/H5,"") | I42: =IFERROR(I6/I5,"") | J42: =IFERROR(J6/J5,"") | K42: =IFERROR(K6/K5,"") | L42: =IFERROR(L6/L5,"") | ... AO42: =IFERROR(AO6/AO5,"")
A43: 판관비율 | C43: % | D43: 판관비 / 매출액 | E43: =IFERROR(E8/E5,"") | F43: =IFERROR(F8/F5,"") | G43: =IFERROR(G8/G5,"") | H43: =IFERROR(H8/H5,"") | I43: =IFERROR(I8/I5,"") | J43: =IFERROR(J8/J5,"") | K43: =IFERROR(K8/K5,"") | L43: =IFERROR(L8/L5,"") | ... AO43: =IFERROR(AO8/AO5,"")

Sheet 분기
C1: 이름: 분기H — subQ 를 이름으로 VLOOKUP(억원) | E1: 4Q21 | F1: 1Q22 | G1: 2Q22 | H1: 3Q22 | I1: 4Q22 | J1: 1Q23 | K1: 2Q23 | L1: 3Q23 | M1: 4Q23 | N1: 1Q24 | O1: 2Q24 | P1: 3Q24 | Q1: 4Q24 | R1: 1Q25 | S1: 2Q25 | T1: 3Q25 | U1: 4Q25 | V1: 1Q26 | W1: 2Q26 | X1: 3Q26 | Y1: 4Q26 | Z1: 1Q27 | AA1: 2Q27 | AB1: 3Q27 | AC1: 4Q27 | AD1: 1Q28 | AE1: 2Q28 | AF1: 3Q28 | AG1: 4Q28
C2: 종가: | D2: =변수!D44
C3: 기준일: | D3: 20261013 | E3: 1 | F3: 2 | G3: 3 | H3: 4 | I3: 5 | J3: 6 | K3: 7 | L3: 8 | M3: 9 | N3: 10 | O3: 11 | P3: 12 | Q3: 13 | R3: 14 | S3: 15 | T3: 16 | U3: 17 | V3: 18 | W3: 19 | X3: 20 | Y3: 21 | Z3: 22 | AA3: 23 | AB3: 24 | AC3: 25 | AD3: 26 | AE3: 27 | AF3: 28 | AG3: 29
E4: 2021.12 | F4: 2022.03 | G4: 2022.06 | H4: 2022.09 | I4: 2022.12 | J4: 2023.03 | K4: 2023.06 | L4: 2023.09 | M4: 2023.12 | N4: 2024.03 | O4: 2024.06 | P4: 2024.09 | Q4: 2024.12 | R4: 2025.03 | S4: 2025.06 | T4: 2025.09 | U4: 2025.12 | V4: 2026.03 | W4: 2026.06 | X4: 2026.09 | Y4: 2026.12 | Z4: 2027.03 | AA4: 2027.06 | AB4: 2027.09 | AC4: 2027.12 | AD4: 2028.03 | AE4: 2028.06 | AF4: 2028.09 | AG4: 2028.12
A5: 매출액 | D5: 매출액 | E5: =IFERROR(VLOOKUP($A5,subQ,MATCH(E$1,SUBQH,0),0),"") | F5: =IFERROR(VLOOKUP($A5,subQ,MATCH(F$1,SUBQH,0),0),"") | G5: =IFERROR(VLOOKUP($A5,subQ,MATCH(G$1,SUBQH,0),0),"") | H5: =IFERROR(VLOOKUP($A5,subQ,MATCH(H$1,SUBQH,0),0),"") | I5: =IFERROR(VLOOKUP($A5,subQ,MATCH(I$1,SUBQH,0),0),"") | J5: =IFERROR(VLOOKUP($A5,subQ,MATCH(J$1,SUBQH,0),0),"") | K5: =IFERROR(VLOOKUP($A5,subQ,MATCH(K$1,SUBQH,0),0),"") | L5: =IFERROR(VLOOKUP($A5,subQ,MATCH(L$1,SUBQH,0),0),"") | ... AG5: =IFERROR(VLOOKUP($A5,subQ,MATCH(AG$1,SUBQH,0),0),"")
A6: 매출원가 | D6: 매출원가 | E6: =IFERROR(VLOOKUP($A6,subQ,MATCH(E$1,SUBQH,0),0),"") | F6: =IFERROR(VLOOKUP($A6,subQ,MATCH(F$1,SUBQH,0),0),"") | G6: =IFERROR(VLOOKUP($A6,subQ,MATCH(G$1,SUBQH,0),0),"") | H6: =IFERROR(VLOOKUP($A6,subQ,MATCH(H$1,SUBQH,0),0),"") | I6: =IFERROR(VLOOKUP($A6,subQ,MATCH(I$1,SUBQH,0),0),"") | J6: =IFERROR(VLOOKUP($A6,subQ,MATCH(J$1,SUBQH,0),0),"") | K6: =IFERROR(VLOOKUP($A6,subQ,MATCH(K$1,SUBQH,0),0),"") | L6: =IFERROR(VLOOKUP($A6,subQ,MATCH(L$1,SUBQH,0),0),"") | ... AG6: =IFERROR(VLOOKUP($A6,subQ,MATCH(AG$1,SUBQH,0),0),"")
A7: 매출총이익 | D7: 매출총이익 | E7: =IFERROR(VLOOKUP($A7,subQ,MATCH(E$1,SUBQH,0),0),"") | F7: =IFERROR(VLOOKUP($A7,subQ,MATCH(F$1,SUBQH,0),0),"") | G7: =IFERROR(VLOOKUP($A7,subQ,MATCH(G$1,SUBQH,0),0),"") | H7: =IFERROR(VLOOKUP($A7,subQ,MATCH(H$1,SUBQH,0),0),"") | I7: =IFERROR(VLOOKUP($A7,subQ,MATCH(I$1,SUBQH,0),0),"") | J7: =IFERROR(VLOOKUP($A7,subQ,MATCH(J$1,SUBQH,0),0),"") | K7: =IFERROR(VLOOKUP($A7,subQ,MATCH(K$1,SUBQH,0),0),"") | L7: =IFERROR(VLOOKUP($A7,subQ,MATCH(L$1,SUBQH,0),0),"") | ... AG7: =IFERROR(VLOOKUP($A7,subQ,MATCH(AG$1,SUBQH,0),0),"")
A8: 판관비 | D8: 판매비와관리비 | E8: =IFERROR(VLOOKUP($A8,subQ,MATCH(E$1,SUBQH,0),0),"") | F8: =IFERROR(VLOOKUP($A8,subQ,MATCH(F$1,SUBQH,0),0),"") | G8: =IFERROR(VLOOKUP($A8,subQ,MATCH(G$1,SUBQH,0),0),"") | H8: =IFERROR(VLOOKUP($A8,subQ,MATCH(H$1,SUBQH,0),0),"") | I8: =IFERROR(VLOOKUP($A8,subQ,MATCH(I$1,SUBQH,0),0),"") | J8: =IFERROR(VLOOKUP($A8,subQ,MATCH(J$1,SUBQH,0),0),"") | K8: =IFERROR(VLOOKUP($A8,subQ,MATCH(K$1,SUBQH,0),0),"") | L8: =IFERROR(VLOOKUP($A8,subQ,MATCH(L$1,SUBQH,0),0),"") | ... AG8: =IFERROR(VLOOKUP($A8,subQ,MATCH(AG$1,SUBQH,0),0),"")
A9: 영업이익 | D9: 영업이익 | E9: =IFERROR(VLOOKUP($A9,subQ,MATCH(E$1,SUBQH,0),0),"") | F9: =IFERROR(VLOOKUP($A9,subQ,MATCH(F$1,SUBQH,0),0),"") | G9: =IFERROR(VLOOKUP($A9,subQ,MATCH(G$1,SUBQH,0),0),"") | H9: =IFERROR(VLOOKUP($A9,subQ,MATCH(H$1,SUBQH,0),0),"") | I9: =IFERROR(VLOOKUP($A9,subQ,MATCH(I$1,SUBQH,0),0),"") | J9: =IFERROR(VLOOKUP($A9,subQ,MATCH(J$1,SUBQH,0),0),"") | K9: =IFERROR(VLOOKUP($A9,subQ,MATCH(K$1,SUBQH,0),0),"") | L9: =IFERROR(VLOOKUP($A9,subQ,MATCH(L$1,SUBQH,0),0),"") | ... AG9: =IFERROR(VLOOKUP($A9,subQ,MATCH(AG$1,SUBQH,0),0),"")
A10: OPM | D10: 영업이익률 | E10: =IFERROR(VLOOKUP($A10,subQ,MATCH(E$1,SUBQH,0),0),"") | F10: =IFERROR(VLOOKUP($A10,subQ,MATCH(F$1,SUBQH,0),0),"") | G10: =IFERROR(VLOOKUP($A10,subQ,MATCH(G$1,SUBQH,0),0),"") | H10: =IFERROR(VLOOKUP($A10,subQ,MATCH(H$1,SUBQH,0),0),"") | I10: =IFERROR(VLOOKUP($A10,subQ,MATCH(I$1,SUBQH,0),0),"") | J10: =IFERROR(VLOOKUP($A10,subQ,MATCH(J$1,SUBQH,0),0),"") | K10: =IFERROR(VLOOKUP($A10,subQ,MATCH(K$1,SUBQH,0),0),"") | L10: =IFERROR(VLOOKUP($A10,subQ,MATCH(L$1,SUBQH,0),0),"") | ... AG10: =IFERROR(VLOOKUP($A10,subQ,MATCH(AG$1,SUBQH,0),0),"")
A11: 금융손익 | D11: 금융손익(이자·환 포함) | E11: =IFERROR(VLOOKUP($A11,subQ,MATCH(E$1,SUBQH,0),0),"") | F11: =IFERROR(VLOOKUP($A11,subQ,MATCH(F$1,SUBQH,0),0),"") | G11: =IFERROR(VLOOKUP($A11,subQ,MATCH(G$1,SUBQH,0),0),"") | H11: =IFERROR(VLOOKUP($A11,subQ,MATCH(H$1,SUBQH,0),0),"") | I11: =IFERROR(VLOOKUP($A11,subQ,MATCH(I$1,SUBQH,0),0),"") | J11: =IFERROR(VLOOKUP($A11,subQ,MATCH(J$1,SUBQH,0),0),"") | K11: =IFERROR(VLOOKUP($A11,subQ,MATCH(K$1,SUBQH,0),0),"") | L11: =IFERROR(VLOOKUP($A11,subQ,MATCH(L$1,SUBQH,0),0),"") | ... AG11: =IFERROR(VLOOKUP($A11,subQ,MATCH(AG$1,SUBQH,0),0),"")
A12: 이자손익 | D12: 이자손익(이자수익 − 이자비용) | E12: =IFERROR(VLOOKUP($A12,subQ,MATCH(E$1,SUBQH,0),0),"") | F12: =IFERROR(VLOOKUP($A12,subQ,MATCH(F$1,SUBQH,0),0),"") | G12: =IFERROR(VLOOKUP($A12,subQ,MATCH(G$1,SUBQH,0),0),"") | H12: =IFERROR(VLOOKUP($A12,subQ,MATCH(H$1,SUBQH,0),0),"") | I12: =IFERROR(VLOOKUP($A12,subQ,MATCH(I$1,SUBQH,0),0),"") | J12: =IFERROR(VLOOKUP($A12,subQ,MATCH(J$1,SUBQH,0),0),"") | K12: =IFERROR(VLOOKUP($A12,subQ,MATCH(K$1,SUBQH,0),0),"") | L12: =IFERROR(VLOOKUP($A12,subQ,MATCH(L$1,SUBQH,0),0),"") | ... AG12: =IFERROR(VLOOKUP($A12,subQ,MATCH(AG$1,SUBQH,0),0),"")
A13: 외환손익 | D13: 외환손익(실적만; 추정 환효과는 환관련손익) | E13: =IFERROR(VLOOKUP($A13,subQ,MATCH(E$1,SUBQH,0),0),"") | F13: =IFERROR(VLOOKUP($A13,subQ,MATCH(F$1,SUBQH,0),0),"") | G13: =IFERROR(VLOOKUP($A13,subQ,MATCH(G$1,SUBQH,0),0),"") | H13: =IFERROR(VLOOKUP($A13,subQ,MATCH(H$1,SUBQH,0),0),"") | I13: =IFERROR(VLOOKUP($A13,subQ,MATCH(I$1,SUBQH,0),0),"") | J13: =IFERROR(VLOOKUP($A13,subQ,MATCH(J$1,SUBQH,0),0),"") | K13: =IFERROR(VLOOKUP($A13,subQ,MATCH(K$1,SUBQH,0),0),"") | L13: =IFERROR(VLOOKUP($A13,subQ,MATCH(L$1,SUBQH,0),0),"") | ... AG13: =IFERROR(VLOOKUP($A13,subQ,MATCH(AG$1,SUBQH,0),0),"")
A14: 파생상품손익 | D14: 파생상품손익 | E14: =IFERROR(VLOOKUP($A14,subQ,MATCH(E$1,SUBQH,0),0),"") | F14: =IFERROR(VLOOKUP($A14,subQ,MATCH(F$1,SUBQH,0),0),"") | G14: =IFERROR(VLOOKUP($A14,subQ,MATCH(G$1,SUBQH,0),0),"") | H14: =IFERROR(VLOOKUP($A14,subQ,MATCH(H$1,SUBQH,0),0),"") | I14: =IFERROR(VLOOKUP($A14,subQ,MATCH(I$1,SUBQH,0),0),"") | J14: =IFERROR(VLOOKUP($A14,subQ,MATCH(J$1,SUBQH,0),0),"") | K14: =IFERROR(VLOOKUP($A14,subQ,MATCH(K$1,SUBQH,0),0),"") | L14: =IFERROR(VLOOKUP($A14,subQ,MATCH(L$1,SUBQH,0),0),"") | ... AG14: =IFERROR(VLOOKUP($A14,subQ,MATCH(AG$1,SUBQH,0),0),"")
A15: 기타금융손익 | D15: 기타금융손익(금융손익 잔차) | E15: =IFERROR(VLOOKUP($A15,subQ,MATCH(E$1,SUBQH,0),0),"") | F15: =IFERROR(VLOOKUP($A15,subQ,MATCH(F$1,SUBQH,0),0),"") | G15: =IFERROR(VLOOKUP($A15,subQ,MATCH(G$1,SUBQH,0),0),"") | H15: =IFERROR(VLOOKUP($A15,subQ,MATCH(H$1,SUBQH,0),0),"") | I15: =IFERROR(VLOOKUP($A15,subQ,MATCH(I$1,SUBQH,0),0),"") | J15: =IFERROR(VLOOKUP($A15,subQ,MATCH(J$1,SUBQH,0),0),"") | K15: =IFERROR(VLOOKUP($A15,subQ,MATCH(K$1,SUBQH,0),0),"") | L15: =IFERROR(VLOOKUP($A15,subQ,MATCH(L$1,SUBQH,0),0),"") | ... AG15: =IFERROR(VLOOKUP($A15,subQ,MATCH(AG$1,SUBQH,0),0),"")
A16: 기타영업외손익 | D16: 기타영업외손익 | E16: =IFERROR(VLOOKUP($A16,subQ,MATCH(E$1,SUBQH,0),0),"") | F16: =IFERROR(VLOOKUP($A16,subQ,MATCH(F$1,SUBQH,0),0),"") | G16: =IFERROR(VLOOKUP($A16,subQ,MATCH(G$1,SUBQH,0),0),"") | H16: =IFERROR(VLOOKUP($A16,subQ,MATCH(H$1,SUBQH,0),0),"") | I16: =IFERROR(VLOOKUP($A16,subQ,MATCH(I$1,SUBQH,0),0),"") | J16: =IFERROR(VLOOKUP($A16,subQ,MATCH(J$1,SUBQH,0),0),"") | K16: =IFERROR(VLOOKUP($A16,subQ,MATCH(K$1,SUBQH,0),0),"") | L16: =IFERROR(VLOOKUP($A16,subQ,MATCH(L$1,SUBQH,0),0),"") | ... AG16: =IFERROR(VLOOKUP($A16,subQ,MATCH(AG$1,SUBQH,0),0),"")
... A40: NPM | D40: NPM | E40: =IFERROR(VLOOKUP($A40,subQ,MATCH(E$1,SUBQH,0),0),"") | F40: =IFERROR(VLOOKUP($A40,subQ,MATCH(F$1,SUBQH,0),0),"") | G40: =IFERROR(VLOOKUP($A40,subQ,MATCH(G$1,SUBQH,0),0),"") | H40: =IFERROR(VLOOKUP($A40,subQ,MATCH(H$1,SUBQH,0),0),"") | I40: =IFERROR(VLOOKUP($A40,subQ,MATCH(I$1,SUBQH,0),0),"") | J40: =IFERROR(VLOOKUP($A40,subQ,MATCH(J$1,SUBQH,0),0),"") | K40: =IFERROR(VLOOKUP($A40,subQ,MATCH(K$1,SUBQH,0),0),"") | L40: =IFERROR(VLOOKUP($A40,subQ,MATCH(L$1,SUBQH,0),0),"") | ... AG40: =IFERROR(VLOOKUP($A40,subQ,MATCH(AG$1,SUBQH,0),0),"")
A41: 매출액 YoY | D41: 매출액 YoY | I41: =IFERROR(I5/E5-1,"") | J41: =IFERROR(J5/F5-1,"") | K41: =IFERROR(K5/G5-1,"") | L41: =IFERROR(L5/H5-1,"") | M41: =IFERROR(M5/I5-1,"") | N41: =IFERROR(N5/J5-1,"") | O41: =IFERROR(O5/K5-1,"") | P41: =IFERROR(P5/L5-1,"") | ... AG41: =IFERROR(AG5/AC5-1,"")
A42: 영업이익 YoY | D42: 영업이익 YoY | I42: =IFERROR(I9/E9-1,"") | J42: =IFERROR(J9/F9-1,"") | K42: =IFERROR(K9/G9-1,"") | L42: =IFERROR(L9/H9-1,"") | M42: =IFERROR(M9/I9-1,"") | N42: =IFERROR(N9/J9-1,"") | O42: =IFERROR(O9/K9-1,"") | P42: =IFERROR(P9/L9-1,"") | ... AG42: =IFERROR(AG9/AC9-1,"")
A43: 지배주주순이익 YoY | D43: 지배주주순이익 YoY | I43: =IFERROR(I21/E21-1,"") | J43: =IFERROR(J21/F21-1,"") | K43: =IFERROR(K21/G21-1,"") | L43: =IFERROR(L21/H21-1,"") | M43: =IFERROR(M21/I21-1,"") | N43: =IFERROR(N21/J21-1,"") | O43: =IFERROR(O21/K21-1,"") | P43: =IFERROR(P21/L21-1,"") | ... AG43: =IFERROR(AG21/AC21-1,"")

Sheet 연간예상
C1: 이름: 연간예상H — subQ 를 이름으로 VLOOKUP(억원) | E1: 2021 | F1: 2022 | G1: 2023 | H1: 2024 | I1: 2025 | J1: 2026 | K1: 2027 | L1: 2028
C2: 종가: | D2: =변수!D44
C3: 기준일: | D3: 20261013 | E3: 1 | F3: 2 | G3: 3 | H3: 4 | I3: 5 | J3: 6 | K3: 7 | L3: 8
E4: 2021.12A | F4: 2022.12A | G4: 2023.12A | H4: 2024.12A | I4: 2025.12A | J4: 2026.12A | K4: 2027.12A | L4: 2028.12A
A5: 매출액 | D5: 매출액 | E5: =IFERROR(VLOOKUP($A5,subQ,MATCH(E$1,SUBQH,0),0),"") | F5: =IFERROR(VLOOKUP($A5,subQ,MATCH(F$1,SUBQH,0),0),"") | G5: =IFERROR(VLOOKUP($A5,subQ,MATCH(G$1,SUBQH,0),0),"") | H5: =IFERROR(VLOOKUP($A5,subQ,MATCH(H$1,SUBQH,0),0),"") | I5: =IFERROR(VLOOKUP($A5,subQ,MATCH(I$1,SUBQH,0),0),"") | J5: =IFERROR(VLOOKUP($A5,subQ,MATCH(J$1,SUBQH,0),0),"") | K5: =IFERROR(VLOOKUP($A5,subQ,MATCH(K$1,SUBQH,0),0),"") | L5: =IFERROR(VLOOKUP($A5,subQ,MATCH(L$1,SUBQH,0),0),"")
A6: 매출원가 | D6: 매출원가 | E6: =IFERROR(VLOOKUP($A6,subQ,MATCH(E$1,SUBQH,0),0),"") | F6: =IFERROR(VLOOKUP($A6,subQ,MATCH(F$1,SUBQH,0),0),"") | G6: =IFERROR(VLOOKUP($A6,subQ,MATCH(G$1,SUBQH,0),0),"") | H6: =IFERROR(VLOOKUP($A6,subQ,MATCH(H$1,SUBQH,0),0),"") | I6: =IFERROR(VLOOKUP($A6,subQ,MATCH(I$1,SUBQH,0),0),"") | J6: =IFERROR(VLOOKUP($A6,subQ,MATCH(J$1,SUBQH,0),0),"") | K6: =IFERROR(VLOOKUP($A6,subQ,MATCH(K$1,SUBQH,0),0),"") | L6: =IFERROR(VLOOKUP($A6,subQ,MATCH(L$1,SUBQH,0),0),"")
A7: 매출총이익 | D7: 매출총이익 | E7: =IFERROR(VLOOKUP($A7,subQ,MATCH(E$1,SUBQH,0),0),"") | F7: =IFERROR(VLOOKUP($A7,subQ,MATCH(F$1,SUBQH,0),0),"") | G7: =IFERROR(VLOOKUP($A7,subQ,MATCH(G$1,SUBQH,0),0),"") | H7: =IFERROR(VLOOKUP($A7,subQ,MATCH(H$1,SUBQH,0),0),"") | I7: =IFERROR(VLOOKUP($A7,subQ,MATCH(I$1,SUBQH,0),0),"") | J7: =IFERROR(VLOOKUP($A7,subQ,MATCH(J$1,SUBQH,0),0),"") | K7: =IFERROR(VLOOKUP($A7,subQ,MATCH(K$1,SUBQH,0),0),"") | L7: =IFERROR(VLOOKUP($A7,subQ,MATCH(L$1,SUBQH,0),0),"")
A8: 판관비 | D8: 판매비와관리비 | E8: =IFERROR(VLOOKUP($A8,subQ,MATCH(E$1,SUBQH,0),0),"") | F8: =IFERROR(VLOOKUP($A8,subQ,MATCH(F$1,SUBQH,0),0),"") | G8: =IFERROR(VLOOKUP($A8,subQ,MATCH(G$1,SUBQH,0),0),"") | H8: =IFERROR(VLOOKUP($A8,subQ,MATCH(H$1,SUBQH,0),0),"") | I8: =IFERROR(VLOOKUP($A8,subQ,MATCH(I$1,SUBQH,0),0),"") | J8: =IFERROR(VLOOKUP($A8,subQ,MATCH(J$1,SUBQH,0),0),"") | K8: =IFERROR(VLOOKUP($A8,subQ,MATCH(K$1,SUBQH,0),0),"") | L8: =IFERROR(VLOOKUP($A8,subQ,MATCH(L$1,SUBQH,0),0),"")
A9: 영업이익 | D9: 영업이익 | E9: =IFERROR(VLOOKUP($A9,subQ,MATCH(E$1,SUBQH,0),0),"") | F9: =IFERROR(VLOOKUP($A9,subQ,MATCH(F$1,SUBQH,0),0),"") | G9: =IFERROR(VLOOKUP($A9,subQ,MATCH(G$1,SUBQH,0),0),"") | H9: =IFERROR(VLOOKUP($A9,subQ,MATCH(H$1,SUBQH,0),0),"") | I9: =IFERROR(VLOOKUP($A9,subQ,MATCH(I$1,SUBQH,0),0),"") | J9: =IFERROR(VLOOKUP($A9,subQ,MATCH(J$1,SUBQH,0),0),"") | K9: =IFERROR(VLOOKUP($A9,subQ,MATCH(K$1,SUBQH,0),0),"") | L9: =IFERROR(VLOOKUP($A9,subQ,MATCH(L$1,SUBQH,0),0),"")
A10: OPM | D10: 영업이익률 | E10: =IFERROR(VLOOKUP($A10,subQ,MATCH(E$1,SUBQH,0),0),"") | F10: =IFERROR(VLOOKUP($A10,subQ,MATCH(F$1,SUBQH,0),0),"") | G10: =IFERROR(VLOOKUP($A10,subQ,MATCH(G$1,SUBQH,0),0),"") | H10: =IFERROR(VLOOKUP($A10,subQ,MATCH(H$1,SUBQH,0),0),"") | I10: =IFERROR(VLOOKUP($A10,subQ,MATCH(I$1,SUBQH,0),0),"") | J10: =IFERROR(VLOOKUP($A10,subQ,MATCH(J$1,SUBQH,0),0),"") | K10: =IFERROR(VLOOKUP($A10,subQ,MATCH(K$1,SUBQH,0),0),"") | L10: =IFERROR(VLOOKUP($A10,subQ,MATCH(L$1,SUBQH,0),0),"")
A11: 금융손익 | D11: 금융손익(이자·환 포함) | E11: =IFERROR(VLOOKUP($A11,subQ,MATCH(E$1,SUBQH,0),0),"") | F11: =IFERROR(VLOOKUP($A11,subQ,MATCH(F$1,SUBQH,0),0),"") | G11: =IFERROR(VLOOKUP($A11,subQ,MATCH(G$1,SUBQH,0),0),"") | H11: =IFERROR(VLOOKUP($A11,subQ,MATCH(H$1,SUBQH,0),0),"") | I11: =IFERROR(VLOOKUP($A11,subQ,MATCH(I$1,SUBQH,0),0),"") | J11: =IFERROR(VLOOKUP($A11,subQ,MATCH(J$1,SUBQH,0),0),"") | K11: =IFERROR(VLOOKUP($A11,subQ,MATCH(K$1,SUBQH,0),0),"") | L11: =IFERROR(VLOOKUP($A11,subQ,MATCH(L$1,SUBQH,0),0),"")
A12: 이자손익 | D12: 이자손익(이자수익 − 이자비용) | E12: =IFERROR(VLOOKUP($A12,subQ,MATCH(E$1,SUBQH,0),0),"") | F12: =IFERROR(VLOOKUP($A12,subQ,MATCH(F$1,SUBQH,0),0),"") | G12: =IFERROR(VLOOKUP($A12,subQ,MATCH(G$1,SUBQH,0),0),"") | H12: =IFERROR(VLOOKUP($A12,subQ,MATCH(H$1,SUBQH,0),0),"") | I12: =IFERROR(VLOOKUP($A12,subQ,MATCH(I$1,SUBQH,0),0),"") | J12: =IFERROR(VLOOKUP($A12,subQ,MATCH(J$1,SUBQH,0),0),"") | K12: =IFERROR(VLOOKUP($A12,subQ,MATCH(K$1,SUBQH,0),0),"") | L12: =IFERROR(VLOOKUP($A12,subQ,MATCH(L$1,SUBQH,0),0),"")
A13: 외환손익 | D13: 외환손익(실적만; 추정 환효과는 환관련손익) | E13: =IFERROR(VLOOKUP($A13,subQ,MATCH(E$1,SUBQH,0),0),"") | F13: =IFERROR(VLOOKUP($A13,subQ,MATCH(F$1,SUBQH,0),0),"") | G13: =IFERROR(VLOOKUP($A13,subQ,MATCH(G$1,SUBQH,0),0),"") | H13: =IFERROR(VLOOKUP($A13,subQ,MATCH(H$1,SUBQH,0),0),"") | I13: =IFERROR(VLOOKUP($A13,subQ,MATCH(I$1,SUBQH,0),0),"") | J13: =IFERROR(VLOOKUP($A13,subQ,MATCH(J$1,SUBQH,0),0),"") | K13: =IFERROR(VLOOKUP($A13,subQ,MATCH(K$1,SUBQH,0),0),"") | L13: =IFERROR(VLOOKUP($A13,subQ,MATCH(L$1,SUBQH,0),0),"")
A14: 파생상품손익 | D14: 파생상품손익 | E14: =IFERROR(VLOOKUP($A14,subQ,MATCH(E$1,SUBQH,0),0),"") | F14: =IFERROR(VLOOKUP($A14,subQ,MATCH(F$1,SUBQH,0),0),"") | G14: =IFERROR(VLOOKUP($A14,subQ,MATCH(G$1,SUBQH,0),0),"") | H14: =IFERROR(VLOOKUP($A14,subQ,MATCH(H$1,SUBQH,0),0),"") | I14: =IFERROR(VLOOKUP($A14,subQ,MATCH(I$1,SUBQH,0),0),"") | J14: =IFERROR(VLOOKUP($A14,subQ,MATCH(J$1,SUBQH,0),0),"") | K14: =IFERROR(VLOOKUP($A14,subQ,MATCH(K$1,SUBQH,0),0),"") | L14: =IFERROR(VLOOKUP($A14,subQ,MATCH(L$1,SUBQH,0),0),"")
A15: 기타금융손익 | D15: 기타금융손익(금융손익 잔차) | E15: =IFERROR(VLOOKUP($A15,subQ,MATCH(E$1,SUBQH,0),0),"") | F15: =IFERROR(VLOOKUP($A15,subQ,MATCH(F$1,SUBQH,0),0),"") | G15: =IFERROR(VLOOKUP($A15,subQ,MATCH(G$1,SUBQH,0),0),"") | H15: =IFERROR(VLOOKUP($A15,subQ,MATCH(H$1,SUBQH,0),0),"") | I15: =IFERROR(VLOOKUP($A15,subQ,MATCH(I$1,SUBQH,0),0),"") | J15: =IFERROR(VLOOKUP($A15,subQ,MATCH(J$1,SUBQH,0),0),"") | K15: =IFERROR(VLOOKUP($A15,subQ,MATCH(K$1,SUBQH,0),0),"") | L15: =IFERROR(VLOOKUP($A15,subQ,MATCH(L$1,SUBQH,0),0),"")
A16: 기타영업외손익 | D16: 기타영업외손익 | E16: =IFERROR(VLOOKUP($A16,subQ,MATCH(E$1,SUBQH,0),0),"") | F16: =IFERROR(VLOOKUP($A16,subQ,MATCH(F$1,SUBQH,0),0),"") | G16: =IFERROR(VLOOKUP($A16,subQ,MATCH(G$1,SUBQH,0),0),"") | H16: =IFERROR(VLOOKUP($A16,subQ,MATCH(H$1,SUBQH,0),0),"") | I16: =IFERROR(VLOOKUP($A16,subQ,MATCH(I$1,SUBQH,0),0),"") | J16: =IFERROR(VLOOKUP($A16,subQ,MATCH(J$1,SUBQH,0),0),"") | K16: =IFERROR(VLOOKUP($A16,subQ,MATCH(K$1,SUBQH,0),0),"") | L16: =IFERROR(VLOOKUP($A16,subQ,MATCH(L$1,SUBQH,0),0),"")
... A40: NPM | D40: NPM | E40: =IFERROR(VLOOKUP($A40,subQ,MATCH(E$1,SUBQH,0),0),"") | F40: =IFERROR(VLOOKUP($A40,subQ,MATCH(F$1,SUBQH,0),0),"") | G40: =IFERROR(VLOOKUP($A40,subQ,MATCH(G$1,SUBQH,0),0),"") | H40: =IFERROR(VLOOKUP($A40,subQ,MATCH(H$1,SUBQH,0),0),"") | I40: =IFERROR(VLOOKUP($A40,subQ,MATCH(I$1,SUBQH,0),0),"") | J40: =IFERROR(VLOOKUP($A40,subQ,MATCH(J$1,SUBQH,0),0),"") | K40: =IFERROR(VLOOKUP($A40,subQ,MATCH(K$1,SUBQH,0),0),"") | L40: =IFERROR(VLOOKUP($A40,subQ,MATCH(L$1,SUBQH,0),0),"")
A41: 매출액 YoY | D41: 매출액 YoY | F41: =IFERROR(F5/E5-1,"") | G41: =IFERROR(G5/F5-1,"") | H41: =IFERROR(H5/G5-1,"") | I41: =IFERROR(I5/H5-1,"") | J41: =IFERROR(J5/I5-1,"") | K41: =IFERROR(K5/J5-1,"") | L41: =IFERROR(L5/K5-1,"")
A42: 영업이익 YoY | D42: 영업이익 YoY | F42: =IFERROR(F9/E9-1,"") | G42: =IFERROR(G9/F9-1,"") | H42: =IFERROR(H9/G9-1,"") | I42: =IFERROR(I9/H9-1,"") | J42: =IFERROR(J9/I9-1,"") | K42: =IFERROR(K9/J9-1,"") | L42: =IFERROR(L9/K9-1,"")
A43: 지배주주순이익 YoY | D43: 지배주주순이익 YoY | F43: =IFERROR(F21/E21-1,"") | G43: =IFERROR(G21/F21-1,"") | H43: =IFERROR(H21/G21-1,"") | I43: =IFERROR(I21/H21-1,"") | J43: =IFERROR(J21/I21-1,"") | K43: =IFERROR(K21/J21-1,"") | L43: =IFERROR(L21/K21-1,"")

Sheet TP
B1: 종가 | C1: =변수!D44
B2: 기준일 | C2: =변수!D45
B3: 모델 산출값 — 목표주가·추천 아님. 밴드·COE 는 변수 시트 3절의 가정
C5: FY | D5: 2025 | E5: 2026 | F5: 2027 | G5: 2028
D6: A | E6: E | F6: E | G6: E
C7: EPS(원) | D7: =IFERROR(VLOOKUP("EPS",subQ,MATCH(D$5,SUBQH,0),0),"") | E7: =IFERROR(VLOOKUP("EPS",subQ,MATCH(E$5,SUBQH,0),0),"") | F7: =IFERROR(VLOOKUP("EPS",subQ,MATCH(F$5,SUBQH,0),0),"") | G7: =IFERROR(VLOOKUP("EPS",subQ,MATCH(G$5,SUBQH,0),0),"")
C8: BPS(원) | D8: =IFERROR(VLOOKUP("BPS",subQ,MATCH(D$5,SUBQH,0),0),"") | E8: =IFERROR(VLOOKUP("BPS",subQ,MATCH(E$5,SUBQH,0),0),"") | F8: =IFERROR(VLOOKUP("BPS",subQ,MATCH(F$5,SUBQH,0),0),"") | G8: =IFERROR(VLOOKUP("BPS",subQ,MATCH(G$5,SUBQH,0),0),"")
C9: 지배주주순이익(억원) | D9: =IFERROR(VLOOKUP("지배주주순이익",subQ,MATCH(D$5,SUBQH,0),0),"") | E9: =IFERROR(VLOOKUP("지배주주순이익",subQ,MATCH(E$5,SUBQH,0),0),"") | F9: =IFERROR(VLOOKUP("지배주주순이익",subQ,MATCH(F$5,SUBQH,0),0),"") | G9: =IFERROR(VLOOKUP("지배주주순이익",subQ,MATCH(G$5,SUBQH,0),0),"")
C10: 영업이익(억원) | D10: =IFERROR(VLOOKUP("영업이익",subQ,MATCH(D$5,SUBQH,0),0),"") | E10: =IFERROR(VLOOKUP("영업이익",subQ,MATCH(E$5,SUBQH,0),0),"") | F10: =IFERROR(VLOOKUP("영업이익",subQ,MATCH(F$5,SUBQH,0),0),"") | G10: =IFERROR(VLOOKUP("영업이익",subQ,MATCH(G$5,SUBQH,0),0),"")
C11: ROE(EPS/기초BPS) | E11: =IFERROR(E7/D8,"") | F11: =IFERROR(F7/E8,"") | G11: =IFERROR(G7/F8,"")
B13: PER
C14: 12M fwd EPS | D14: =IFERROR(E7*변수!D50+F7*(1-변수!D50),"")
C15: 적정가치 @PER_lo | D15: =변수!D47 | E15: =IFERROR(ROUND($D$14*D15,-2),"") | F15: =IFERROR(E15/$C$1-1,"") | G15: 배 · 원 · 종가 대비
C16: 적정가치 @PER_mid | D16: =변수!D48 | E16: =IFERROR(ROUND($D$14*D16,-2),"") | F16: =IFERROR(E16/$C$1-1,"") | G16: 배 · 원 · 종가 대비
C17: 적정가치 @PER_hi | D17: =변수!D49 | E17: =IFERROR(ROUND($D$14*D17,-2),"") | F17: =IFERROR(E17/$C$1-1,"") | G17: 배 · 원 · 종가 대비
C18: 현재 PER(종가/12M fwd EPS) | D18: =IFERROR($C$1/$D$14,"")
B20: PBR
C21: 최근 BPS(마지막 실적 분기) | D21: =IFERROR(VLOOKUP("BPS",subQ,MATCH("2Q26",SUBQH,0),0),"")
C22: ROE fwd(12M fwd EPS / BPS) | D22: =IFERROR($D$14/$D$21,"")
C23: COE | D23: =변수!D46
C24: 적정 PBR = ROE/COE | D24: =IFERROR(D22/D23,"")
C25: 적정가치(PBR) = BPS × 적정PBR | D25: =IFERROR(ROUND(D21*D24,-2),"") | E25: =IFERROR(D25/$C$1-1,"")
C26: 현재 PBR(종가/BPS) | D26: =IFERROR($C$1/D21,"")
B28: 모델 json valuation(참고)
C29: eps_fwd12m | D29: 1521.4
C30: bps_latest | D30: 7788.4
C31: per_now | D31: 24.58
C32: pbr_now | D32: 4.8
C33: roe_fwd | D33: 0.1953
C34: fair_pbr | D34: 2.17
C35: fair_value_pbr | D35: 16900
C36: ev_ebitda
C37: note | D37: 모델 산출값 — 목표주가·추천 아님

Sheet 외화
C1: 이름: 외화QH — 환율 QoQ · 외화 순노출 × Δ기말환율 | E1: 4Q21 | F1: 1Q22 | G1: 2Q22 | H1: 3Q22 | I1: 4Q22 | J1: 1Q23 | K1: 2Q23 | L1: 3Q23 | M1: 4Q23 | N1: 1Q24 | O1: 2Q24 | P1: 3Q24 | Q1: 4Q24 | R1: 1Q25 | S1: 2Q25 | T1: 3Q25 | U1: 4Q25 | V1: 1Q26 | W1: 2Q26 | X1: 3Q26 | Y1: 4Q26 | Z1: 1Q27 | AA1: 2Q27 | AB1: 3Q27 | AC1: 4Q27 | AD1: 1Q28 | AE1: 2Q28 | AF1: 3Q28 | AG1: 4Q28
E3: 1 | F3: 2 | G3: 3 | H3: 4 | I3: 5 | J3: 6 | K3: 7 | L3: 8 | M3: 9 | N3: 10 | O3: 11 | P3: 12 | Q3: 13 | R3: 14 | S3: 15 | T3: 16 | U3: 17 | V3: 18 | W3: 19 | X3: 20 | Y3: 21 | Z3: 22 | AA3: 23 | AB3: 24 | AC3: 25 | AD3: 26 | AE3: 27 | AF3: 28 | AG3: 29
E4: 2021.12 | F4: 2022.03 | G4: 2022.06 | H4: 2022.09 | I4: 2022.12 | J4: 2023.03 | K4: 2023.06 | L4: 2023.09 | M4: 2023.12 | N4: 2024.03 | O4: 2024.06 | P4: 2024.09 | Q4: 2024.12 | R4: 2025.03 | S4: 2025.06 | T4: 2025.09 | U4: 2025.12 | V4: 2026.03 | W4: 2026.06 | X4: 2026.09 | Y4: 2026.12 | Z4: 2027.03 | AA4: 2027.06 | AB4: 2027.09 | AC4: 2027.12 | AD4: 2028.03 | AE4: 2028.06 | AF4: 2028.09 | AG4: 2028.12
D5: 원/달러(평균) | E5: =IFERROR(VLOOKUP($D5,환율,MATCH(E$1,변수H,0),0),"") | F5: =IFERROR(VLOOKUP($D5,환율,MATCH(F$1,변수H,0),0),"") | G5: =IFERROR(VLOOKUP($D5,환율,MATCH(G$1,변수H,0),0),"") | H5: =IFERROR(VLOOKUP($D5,환율,MATCH(H$1,변수H,0),0),"") | I5: =IFERROR(VLOOKUP($D5,환율,MATCH(I$1,변수H,0),0),"") | J5: =IFERROR(VLOOKUP($D5,환율,MATCH(J$1,변수H,0),0),"") | K5: =IFERROR(VLOOKUP($D5,환율,MATCH(K$1,변수H,0),0),"") | L5: =IFERROR(VLOOKUP($D5,환율,MATCH(L$1,변수H,0),0),"") | ... AG5: =IFERROR(VLOOKUP($D5,환율,MATCH(AG$1,변수H,0),0),"")
A6: 원/달러(평균) QoQ | F6: =IFERROR(F5/E5-1,"") | G6: =IFERROR(G5/F5-1,"") | H6: =IFERROR(H5/G5-1,"") | I6: =IFERROR(I5/H5-1,"") | J6: =IFERROR(J5/I5-1,"") | K6: =IFERROR(K5/J5-1,"") | L6: =IFERROR(L5/K5-1,"") | M6: =IFERROR(M5/L5-1,"") | ... AG6: =IFERROR(AG5/AF5-1,"")
D7: 원/달러(기말) | E7: =IFERROR(VLOOKUP($D7,환율,MATCH(E$1,변수H,0),0),"") | F7: =IFERROR(VLOOKUP($D7,환율,MATCH(F$1,변수H,0),0),"") | G7: =IFERROR(VLOOKUP($D7,환율,MATCH(G$1,변수H,0),0),"") | H7: =IFERROR(VLOOKUP($D7,환율,MATCH(H$1,변수H,0),0),"") | I7: =IFERROR(VLOOKUP($D7,환율,MATCH(I$1,변수H,0),0),"") | J7: =IFERROR(VLOOKUP($D7,환율,MATCH(J$1,변수H,0),0),"") | K7: =IFERROR(VLOOKUP($D7,환율,MATCH(K$1,변수H,0),0),"") | L7: =IFERROR(VLOOKUP($D7,환율,MATCH(L$1,변수H,0),0),"") | ... AG7: =IFERROR(VLOOKUP($D7,환율,MATCH(AG$1,변수H,0),0),"")
A8: 원/달러(기말) QoQ | F8: =IFERROR(F7/E7-1,"") | G8: =IFERROR(G7/F7-1,"") | H8: =IFERROR(H7/G7-1,"") | I8: =IFERROR(I7/H7-1,"") | J8: =IFERROR(J7/I7-1,"") | K8: =IFERROR(K7/J7-1,"") | L8: =IFERROR(L7/K7-1,"") | M8: =IFERROR(M7/L7-1,"") | ... AG8: =IFERROR(AG7/AF7-1,"")
D9: W/Euro(평균) | E9: =IFERROR(VLOOKUP($D9,환율,MATCH(E$1,변수H,0),0),"") | F9: =IFERROR(VLOOKUP($D9,환율,MATCH(F$1,변수H,0),0),"") | G9: =IFERROR(VLOOKUP($D9,환율,MATCH(G$1,변수H,0),0),"") | H9: =IFERROR(VLOOKUP($D9,환율,MATCH(H$1,변수H,0),0),"") | I9: =IFERROR(VLOOKUP($D9,환율,MATCH(I$1,변수H,0),0),"") | J9: =IFERROR(VLOOKUP($D9,환율,MATCH(J$1,변수H,0),0),"") | K9: =IFERROR(VLOOKUP($D9,환율,MATCH(K$1,변수H,0),0),"") | L9: =IFERROR(VLOOKUP($D9,환율,MATCH(L$1,변수H,0),0),"") | ... AG9: =IFERROR(VLOOKUP($D9,환율,MATCH(AG$1,변수H,0),0),"")
A10: W/Euro(평균) QoQ | F10: =IFERROR(F9/E9-1,"") | G10: =IFERROR(G9/F9-1,"") | H10: =IFERROR(H9/G9-1,"") | I10: =IFERROR(I9/H9-1,"") | J10: =IFERROR(J9/I9-1,"") | K10: =IFERROR(K9/J9-1,"") | L10: =IFERROR(L9/K9-1,"") | M10: =IFERROR(M9/L9-1,"") | ... AG10: =IFERROR(AG9/AF9-1,"")
D11: W/Euro(기말) | E11: =IFERROR(VLOOKUP($D11,환율,MATCH(E$1,변수H,0),0),"") | F11: =IFERROR(VLOOKUP($D11,환율,MATCH(F$1,변수H,0),0),"") | G11: =IFERROR(VLOOKUP($D11,환율,MATCH(G$1,변수H,0),0),"") | H11: =IFERROR(VLOOKUP($D11,환율,MATCH(H$1,변수H,0),0),"") | I11: =IFERROR(VLOOKUP($D11,환율,MATCH(I$1,변수H,0),0),"") | J11: =IFERROR(VLOOKUP($D11,환율,MATCH(J$1,변수H,0),0),"") | K11: =IFERROR(VLOOKUP($D11,환율,MATCH(K$1,변수H,0),0),"") | L11: =IFERROR(VLOOKUP($D11,환율,MATCH(L$1,변수H,0),0),"") | ... AG11: =IFERROR(VLOOKUP($D11,환율,MATCH(AG$1,변수H,0),0),"")
A12: W/Euro(기말) QoQ | F12: =IFERROR(F11/E11-1,"") | G12: =IFERROR(G11/F11-1,"") | H12: =IFERROR(H11/G11-1,"") | I12: =IFERROR(I11/H11-1,"") | J12: =IFERROR(J11/I11-1,"") | K12: =IFERROR(K11/J11-1,"") | L12: =IFERROR(L11/K11-1,"") | M12: =IFERROR(M11/L11-1,"") | ... AG12: =IFERROR(AG11/AF11-1,"")
D13: 원/100Y(기말) | E13: =IFERROR(VLOOKUP($D13,환율,MATCH(E$1,변수H,0),0),"") | F13: =IFERROR(VLOOKUP($D13,환율,MATCH(F$1,변수H,0),0),"") | G13: =IFERROR(VLOOKUP($D13,환율,MATCH(G$1,변수H,0),0),"") | H13: =IFERROR(VLOOKUP($D13,환율,MATCH(H$1,변수H,0),0),"") | I13: =IFERROR(VLOOKUP($D13,환율,MATCH(I$1,변수H,0),0),"") | J13: =IFERROR(VLOOKUP($D13,환율,MATCH(J$1,변수H,0),0),"") | K13: =IFERROR(VLOOKUP($D13,환율,MATCH(K$1,변수H,0),0),"") | L13: =IFERROR(VLOOKUP($D13,환율,MATCH(L$1,변수H,0),0),"") | ... AG13: =IFERROR(VLOOKUP($D13,환율,MATCH(AG$1,변수H,0),0),"")
A14: 원/100Y(기말) QoQ | F14: =IFERROR(F13/E13-1,"") | G14: =IFERROR(G13/F13-1,"") | H14: =IFERROR(H13/G13-1,"") | I14: =IFERROR(I13/H13-1,"") | J14: =IFERROR(J13/I13-1,"") | K14: =IFERROR(K13/J13-1,"") | L14: =IFERROR(L13/K13-1,"") | M14: =IFERROR(M13/L13-1,"") | ... AG14: =IFERROR(AG13/AF13-1,"")
A16: 외화순노출 | C16: 외화 순노출(백만$) | D16: =변수!D57 | E16: 외화 순노출 × Δ기말환율 (외화 시트 방식)
A17: 환관련손익추정 | C17: 환관련손익 추정(억원) = 순노출 × Δ원/달러(기말) / 100 | F17: =IFERROR($D$16*(F7-E7)/100,"") | G17: =IFERROR($D$16*(G7-F7)/100,"") | H17: =IFERROR($D$16*(H7-G7)/100,"") | I17: =IFERROR($D$16*(I7-H7)/100,"") | J17: =IFERROR($D$16*(J7-I7)/100,"") | K17: =IFERROR($D$16*(K7-J7)/100,"") | L17: =IFERROR($D$16*(L7-K7)/100,"") | M17: =IFERROR($D$16*(M7-L7)/100,"") | ... AG17: =IFERROR($D$16*(AG7-AF7)/100,"")
A18: fx_pnl.by_q | C18: 모델 fx_pnl.by_q(억원, 참고)
C19: 외화 순노출 미공시(face) → 0 + 표기
