Workbook
Name 변수H: 변수!$C$1:$AO$1
Name 환율: 변수!$C$6:$AO$13
Name BS연결H: BS연결!$C$1:$AO$1
Name BS연결: BS연결!$C$5:$AO$99
Name BS별도H: BS별도!$C$1:$AO$1
Name BS별도: BS별도!$C$5:$AO$95
Name SUBQH: subQ!$A$1:$AO$1
Name subQ: subQ!$A$5:$AO$41

Sheet README
A1: 엔케이(085310) 실적 모델 — ARGUS 한국조선
A2: 기준 분기 2026Q2 · 마지막 실적 2026Q2 · 생성 2026-10-11
A3: 모든 수치는 모델 산출값(DART 공개 재무제표 + 우리 추정)이다 — 목표주가·투자 추천 아님. 참고용 · 투자조언 아님.
A5: 시트
A6: 변수 가정 시계열. 환율 8행(ECB via frankfurter — L2 fx.json; 추정 분기 = 노란 가정), 추정 드라이버(노란 셀 = 모델값에서 역산한 가정, 바꾸면 재계산; 연녹 셀 = 3절 스칼라 참조 수식), 3절 스칼라 가정(세율·판관비율·지배주주비중·이자율·종가·PER 밴드·COE·외화 순노출·헤지비율)
A7: BS연결/BS별도 FnGuide 계정명 × 기간 값 덤프(백만원). 행1 분기라벨, 행4 YYYY.MM / YYYY.12A. 이름정의 BS연결H·BS연결(계정명 C열부터)
A8: subQ 분기 서브모델(억원 = 백만원/100). 확정 행: =IFERROR(VLOOKUP($D행,BS연결,MATCH(E$1,BS연결H,0),0)/100,"") 추정 행: 변수 시트 가정 셀 참조 수식. 외환손익·파생상품손익은 BS 계정 합·차, 기타금융손익은 잔차, OPM·EPS·BPS·PER·PBR 은 파생 수식
A9: SLS 선표(조선사만, sls json 있을 때): 요약 행(sls 저장값) + 계약별 스케줄(백만$) × (헤지비율 × 헤지환율 + (1−헤지비율) × 건조시점 환율[변수 원/달러(평균)]) → 원화 수식 블록 → 합계 행이 subQ 매출조선에 연결
A10: 시나리오 신규수주 보수/기준/낙관(forecast_panel 패널, 모델에 scenarios 가 있을 때만): 매출액·영업이익 = subQ 기준값 ± (시나리오 신규 − base 신규) × OPM. base 만 subQ 행에 포함, 나머지는 합산 안 함
A11: 분기/연간예상 subQ 를 이름(A열 key)으로 VLOOKUP 한 보고서 표(억원)
A12: TP PER 밴드 × 12M fwd EPS, PBR = ROE/COE × BPS — 모델 산출값 구간, 목표주가·추천 아님
A13: 외화 환율 QoQ, 외화 순노출 × Δ기말환율 → 환관련손익 추정
... A34: 백테스트: {"freeze": "2025Q2", "horizon": 4, "revenue_wape_pct": 8.3, "op_wape_pct": 129.2, "n": 4, "note": "단일 회사 4분기 — 통계 아님", "driver_at_freeze": "customer_yard_revenue_weighted", "selection_oos_at_freeze": {"freeze": "2024Q2", "n": 4, "wape_link": null, "wape_trend": 23.0, "adopted": "undetermined", "decision": "undetermined", "note": "현재 채택 조합(suppliers_mentions·시차 4·ma4·창 8)을 동결 데이터로 재적합할 수 없음(짝·고객 모델 부족) → 연동 WAPE 없음, undetermined(유의성 조건만으로 채택)"}, "frozen_inputs": "fin(연결/별도)·고객 조선사 모델·지주 자회사 모델은 2025Q2 까지의 분기만; 선표는 체결일 ≤ 2025Q2 말일 계약(원장 최신 금액·코호트 등급, 환산 없음); 잔고는 yards_cache 2025Q2; 시세·환율 forward·prices·forecast_panel 신규수주 미사용. 고객 가중치(suppliers.json 언급 비중)와 합병 체인링크는 현재 지식; 고객 연동 채택은 동결 모델 안에서도 자기 la−4분기 OOS 규칙(selection_oos_at_freeze)", "detail": [{"q": "2025Q3", "rev_pred": 277.78, "rev_act": 285.56, "op_pred": -13.37, "op_act": -50.22}, {"q": "2025Q4", "rev_pred": 411.63, "rev_act": 490.43, "op_pred": -19.81, "op_act": 49.97}, {"q": "2026Q1", "rev_pred": 341.66, "rev_act": 319.14, "op_pred": -16.44, "op_act": 5.34}, {"q": "2026Q2", "rev_pred": 355.91, "rev_act": 367.92, "op_pred": -17.13, "op_act": 31.44}]}

Sheet 변수
C1: 이름: 변수H | E1: 4Q21 | F1: 2021 | G1: 1Q22 | H1: 2Q22 | I1: 3Q22 | J1: 4Q22 | K1: 2022 | L1: 1Q23 | M1: 2Q23 | N1: 3Q23 | O1: 4Q23 | P1: 2023 | Q1: 1Q24 | R1: 2Q24 | S1: 3Q24 | T1: 4Q24 | U1: 2024 | V1: 1Q25 | W1: 2Q25 | X1: 3Q25 | Y1: 4Q25 | Z1: 2025 | AA1: 1Q26 | AB1: 2Q26 | AC1: 3Q26 | AD1: 4Q26 | AE1: 2026 | AF1: 1Q27 | AG1: 2Q27 | AH1: 3Q27 | AI1: 4Q27 | AJ1: 2027 | AK1: 1Q28 | AL1: 2Q28 | AM1: 3Q28 | AN1: 4Q28 | AO1: 2028
A2: 가정 시계열 — 노란 셀은 추정 가정(모델값에서 역산), 연녹 셀은 3절 스칼라 참조 수식. 바꾸면 subQ·분기·연간예상·TP·시나리오가 재계산됩니다.
E3: 1 | F3: 2 | G3: 3 | H3: 4 | I3: 5 | J3: 6 | K3: 7 | L3: 8 | M3: 9 | N3: 10 | O3: 11 | P3: 12 | Q3: 13 | R3: 14 | S3: 15 | T3: 16 | U3: 17 | V3: 18 | W3: 19 | X3: 20 | Y3: 21 | Z3: 22 | AA3: 23 | AB3: 24 | AC3: 25 | AD3: 26 | AE3: 27 | AF3: 28 | AG3: 29 | AH3: 30 | AI3: 31 | AJ3: 32 | AK3: 33 | AL3: 34 | AM3: 35 | AN3: 36 | AO3: 37
E4: 2021.12 | F4: 2021.12A | G4: 2022.03 | H4: 2022.06 | I4: 2022.09 | J4: 2022.12 | K4: 2022.12A | L4: 2023.03 | M4: 2023.06 | N4: 2023.09 | O4: 2023.12 | P4: 2023.12A | Q4: 2024.03 | R4: 2024.06 | S4: 2024.09 | T4: 2024.12 | U4: 2024.12A | V4: 2025.03 | W4: 2025.06 | X4: 2025.09 | Y4: 2025.12 | Z4: 2025.12A | AA4: 2026.03 | AB4: 2026.06 | AC4: 2026.09 | AD4: 2026.12 | AE4: 2026.12A | AF4: 2027.03 | AG4: 2027.06 | AH4: 2027.09 | AI4: 2027.12 | AJ4: 2027.12A | AK4: 2028.03 | AL4: 2028.06 | AM4: 2028.09 | AN4: 2028.12 | AO4: 2028.12A
B5: 1. FX | C5: 이름: 환율
A6: USDKRW_avg | C6: 원/달러(평균) | E6: 1183.5 | F6: 1145.51 | G6: 1205.78 | H6: 1262.09 | I6: 1341.93 | J6: 1360.12 | K6: 1292.98 | L6: 1276.95 | M6: 1315.69 | N6: 1313.62 | O6: 1322.01 | P6: 1306.85 | Q6: 1330.14 | R6: 1371.28 | S6: 1356.22 | T6: 1396.3 | U6: 1363.53 | V6: 1452.28 | W6: 1398.52 | X6: 1386.95 | Y6: 1449.19 | Z6: 1421.52 | AA6: 1466.12 | AB6: 1501.75 | AC6: 1418.75 | AD6: 1345.14 | AE6: 1457.21 | AF6: 1341.49 | AG6: 1341.49 | AH6: 1341.49 | AI6: 1341.49 | AK6: 1341.49 | AL6: 1341.49 | AM6: 1341.49 | AN6: 1341.49
A7: USDKRW_end | C7: 원/달러(기말) | E7: 1188.75 | F7: 1188.75 | G7: 1213.74 | H7: 1301.24 | I7: 1436.9 | J7: 1260.16 | K7: 1260.16 | L7: 1305.99 | M7: 1321.44 | N7: 1345.35 | O7: 1297.43 | P7: 1297.43 | Q7: 1349.25 | R7: 1377.73 | S7: 1312.17 | T7: 1474.78 | U7: 1474.78 | V7: 1474.54 | W7: 1355.13 | X7: 1403.67 | Y7: 1444.2 | Z7: 1444.2 | AA7: 1524.8 | AB7: 1550.89 | AC7: 1355.4 | AD7: 1341.49 | AE7: 1341.49 | AF7: 1341.49 | AG7: 1341.49 | AH7: 1341.49 | AI7: 1341.49 | AK7: 1341.49 | AL7: 1341.49 | AM7: 1341.49 | AN7: 1341.49
A8: JPY100KRW_avg | C8: 원/100Y(평균) | E8: 1041.02 | F8: 1042.74 | G8: 1036.79 | H8: 972.23 | I8: 970.61 | J8: 961.03 | K8: 985.1 | L8: 964.89 | M8: 957.36 | N8: 909 | O8: 893.22 | P8: 931.11 | Q8: 896.29 | R8: 880.14 | S8: 909.35 | T8: 917.25 | U8: 900.92 | V8: 952.59 | W8: 967.92 | X8: 940.32 | Y8: 940.77 | Z8: 950.17 | AA8: 934.39 | AB8: 942.16 | AC8: 890.41 | AD8: 850.79 | AE8: 919.21 | AF8: 847.7 | AG8: 847.7 | AH8: 847.7 | AI8: 847.7 | AK8: 847.7 | AL8: 847.7 | AM8: 847.7 | AN8: 847.7
A9: JPY100KRW_end | C9: 원/100Y(기말) | E9: 1032.62 | F9: 1032.62 | G9: 996.83 | H9: 954.9 | I9: 993.29 | J9: 955.54 | K9: 955.54 | L9: 980.62 | M9: 913.67 | N9: 901.47 | O9: 917.04 | P9: 917.04 | Q9: 892.42 | R9: 857.76 | S9: 919.21 | T9: 939.65 | U9: 939.65 | V9: 986.84 | W9: 938.85 | X9: 948.49 | Y9: 921.81 | Z9: 921.81 | AA9: 955.99 | AB9: 954.75 | AC9: 863.31 | AD9: 847.7 | AE9: 847.7 | AF9: 847.7 | AG9: 847.7 | AH9: 847.7 | AI9: 847.7 | AK9: 847.7 | AL9: 847.7 | AM9: 847.7 | AN9: 847.7
A10: EURKRW_avg | C10: W/Euro(평균) | E10: 1353.32 | F10: 1354.06 | G10: 1352.29 | H10: 1343.31 | I10: 1350.63 | J10: 1386.07 | K10: 1358.07 | L10: 1369.93 | M10: 1432.41 | N10: 1429.41 | O10: 1420.91 | P10: 1412.88 | Q10: 1444.21 | R10: 1476.42 | S10: 1489.3 | T10: 1490.78 | U10: 1475.4 | V10: 1528.33 | W10: 1585.13 | X10: 1620.04 | Y10: 1686.02 | Z10: 1605.45 | AA10: 1715.47 | AB10: 1746.09 | AC10: 1631.97 | AD10: 1509.74 | AE10: 1689.95 | AF10: 1503.27 | AG10: 1503.27 | AH10: 1503.27 | AI10: 1503.27 | AK10: 1503.27 | AL10: 1503.27 | AM10: 1503.27 | AN10: 1503.27
A11: EURKRW_end | C11: W/Euro(기말) | E11: 1346.38 | F11: 1346.38 | G11: 1347.37 | H11: 1351.6 | I11: 1400.62 | J11: 1344.08 | K11: 1344.08 | L11: 1420.26 | M11: 1435.88 | N11: 1425.26 | O11: 1433.66 | P11: 1433.66 | Q11: 1458.68 | R11: 1474.86 | S11: 1469.1 | T11: 1532.14 | U11: 1532.14 | V11: 1594.72 | W11: 1588.22 | X11: 1648.04 | Y11: 1696.94 | Z11: 1696.94 | AA11: 1753.21 | AB11: 1767.09 | AC11: 1539.06 | AD11: 1503.27 | AE11: 1503.27 | AF11: 1503.27 | AG11: 1503.27 | AH11: 1503.27 | AI11: 1503.27 | AK11: 1503.27 | AL11: 1503.27 | AM11: 1503.27 | AN11: 1503.27
A12: CNYKRW_avg | C12: 원/중국원(평균) | E12: 185.14 | F12: 177.65 | G12: 189.93 | H12: 190.76 | I12: 195.79 | J12: 191.09 | K12: 191.93 | L12: 186.59 | M12: 187.45 | N12: 181.28 | O12: 182.86 | P12: 184.52 | Q12: 185.04 | R12: 189.35 | S12: 189.24 | T12: 194.24 | U12: 189.49 | V12: 199.63 | W12: 193.41 | X12: 193.79 | Y12: 204.38 | Z12: 197.8 | AA12: 211.75 | AB12: 220.8 | AC12: 210.43 | AD12: 200.69 | AE12: 213.75 | AF12: 200.46 | AG12: 200.46 | AH12: 200.46 | AI12: 200.46 | AK12: 200.46 | AL12: 200.46 | AM12: 200.46 | AN12: 200.46
A13: CNYKRW_end | C13: 원/중국원(기말) | E13: 187.13 | F13: 187.13 | G13: 191.38 | H13: 194.13 | I13: 201.92 | J13: 182.67 | K13: 182.67 | L13: 189.97 | M13: 181.8 | N13: 184.26 | O13: 182.61 | P13: 182.61 | Q13: 186.66 | R13: 189.7 | S13: 187.12 | T13: 202.04 | U13: 202.04 | V13: 203.3 | W13: 189.14 | X13: 197.16 | Y13: 206.28 | Z13: 206.28 | AA13: 220.97 | AB13: 228.56 | AC13: 202.16 | AD13: 200.46 | AE13: 200.46 | AF13: 200.46 | AG13: 200.46 | AH13: 200.46 | AI13: 200.46 | AK13: 200.46 | AL13: 200.46 | AM13: 200.46 | AN13: 200.46
B14: 1b. 종가
A15: price_close_end | C15: 종가(기말) | E15: 10450 | G15: 10500 | H15: 9150 | I15: 8810 | J15: 8700 | L15: 9470 | M15: 10070 | N15: 9870 | O15: 10050 | Q15: 8920 | R15: 9480 | S15: 8000 | T15: 8620 | V15: 7990 | W15: 8440 | X15: 13070 | Y15: 11670 | AA15: 10780 | AB15: 9010 | AC15: 8930 | AD15: 8950
A16: price_high | C16: 종가(최고) | E16: 12500 | G16: 11000 | H16: 12000 | I16: 12400 | J16: 11300 | L16: 9810 | M16: 10500 | N16: 11480 | O16: 10990 | Q16: 10250 | R16: 11140 | S16: 9560 | T16: 8690 | V16: 10500 | W16: 9960 | X16: 17300 | Y16: 17610 | AA16: 13200 | AB16: 12630 | AC16: 11270 | AD16: 9990
A17: price_low | C17: 종가(최저) | E17: 9030 | G17: 9010 | H17: 8100 | I17: 8310 | J17: 8540 | L17: 8310 | M17: 9000 | N17: 9600 | O17: 9440 | Q17: 8850 | R17: 8450 | S17: 7640 | T17: 6100 | V17: 7900 | W17: 7420 | X17: 8020 | Y17: 11630 | AA17: 8750 | AB17: 8350 | AC17: 6950 | AD17: 8540
A18: price_avg | C18: 종가(평균) | E18: 10581.7 | G18: 9897.8 | H18: 10746.3 | I18: 9623.8 | J18: 9205.8 | L18: 9173.1 | M18: 9553.9 | N18: 10441.6 | O18: 9909.7 | Q18: 9451.5 | R18: 9359.7 | S18: 8521.1 | T18: 7566.9 | V18: 9200.7 | W18: 8436.2 | X18: 11064.2 | Y18: 13384.6 | AA18: 11161.2 | AB18: 10448.8 | AC18: 8774.7 | AD18: 8928
B20: 2. 추정 드라이버 | C20: 실적 열 = subQ 실현값(수식), 추정 열 = 가정(노란 = 모델값 역산, 연녹 = 3절 스칼라 참조)
A21: drv:매출액 | B21: yoy | C21: 매출액 YoY | J21: =IFERROR(subQ!J5/subQ!E5-1,"") | L21: =IFERROR(subQ!L5/subQ!G5-1,"") | M21: =IFERROR(subQ!M5/subQ!H5-1,"") | N21: =IFERROR(subQ!N5/subQ!I5-1,"") | O21: =IFERROR(subQ!O5/subQ!J5-1,"") | Q21: =IFERROR(subQ!Q5/subQ!L5-1,"") | R21: =IFERROR(subQ!R5/subQ!M5-1,"") | S21: =IFERROR(subQ!S5/subQ!N5-1,"") | T21: =IFERROR(subQ!T5/subQ!O5-1,"") | V21: =IFERROR(subQ!V5/subQ!Q5-1,"") | W21: =IFERROR(subQ!W5/subQ!R5-1,"") | X21: =IFERROR(subQ!X5/subQ!S5-1,"") | Y21: =IFERROR(subQ!Y5/subQ!T5-1,"") | AA21: =IFERROR(subQ!AA5/subQ!V5-1,"") | AB21: =IFERROR(subQ!AB5/subQ!W5-1,"") | AC21: 0.30229965 | AD21: 0.30229292 | AF21: 0.302299 | AG21: 0.30229008 | AH21: 0.15115091 | AI21: 0.15115551 | AK21: 0.15114768 | AL21: 0.1511458 | AM21: 0.075568222 | AN21: 0.075569217
A22: drv:판관비 | B22: ratio | C22: 판관비율(/매출) | E22: =IFERROR(subQ!E8/subQ!E5,"") | F22: =IFERROR(subQ!F8/subQ!F5,"") | G22: =IFERROR(subQ!G8/subQ!G5,"") | H22: =IFERROR(subQ!H8/subQ!H5,"") | I22: =IFERROR(subQ!I8/subQ!I5,"") | J22: =IFERROR(subQ!J8/subQ!J5,"") | K22: =IFERROR(subQ!K8/subQ!K5,"") | L22: =IFERROR(subQ!L8/subQ!L5,"") | ... AB22: =IFERROR(subQ!AB8/subQ!AB5,"") | AC22: =$D$50 | AD22: =$D$50 | AE22: =IFERROR(subQ!AE8/subQ!AE5,"") | AF22: =$D$50 | AG22: =$D$50 | AH22: =$D$50 | AI22: =$D$50 | AJ22: =IFERROR(subQ!AJ8/subQ!AJ5,"") | AK22: =$D$50 | AL22: =$D$50 | AM22: =$D$50 | AN22: =$D$50 | AO22: =IFERROR(subQ!AO8/subQ!AO5,"")
A23: drv:영업이익 | B23: ratio | C23: 영업이익률(OPM) | E23: =IFERROR(subQ!E9/subQ!E5,"") | F23: =IFERROR(subQ!F9/subQ!F5,"") | G23: =IFERROR(subQ!G9/subQ!G5,"") | H23: =IFERROR(subQ!H9/subQ!H5,"") | I23: =IFERROR(subQ!I9/subQ!I5,"") | J23: =IFERROR(subQ!J9/subQ!J5,"") | K23: =IFERROR(subQ!K9/subQ!K5,"") | L23: =IFERROR(subQ!L9/subQ!L5,"") | ... AB23: =IFERROR(subQ!AB9/subQ!AB5,"") | AC23: -0.014063676 | AD23: -0.014060249 | AE23: =IFERROR(subQ!AE9/subQ!AE5,"") | AF23: -0.014051297 | AG23: -0.01406687 | AH23: -0.014062464 | AI23: -0.014063818 | AJ23: =IFERROR(subQ!AJ9/subQ!AJ5,"") | AK23: -0.01406655 | AL23: -0.014069186 | AM23: -0.014051777 | AN23: -0.014062065 | AO23: =IFERROR(subQ!AO9/subQ!AO5,"")
A24: drv:기타영업외손익 | B24: abs | C24: 기타영업외손익 (가정, 억원) | E24: =subQ!E13 | F24: =subQ!F13 | G24: =subQ!G13 | H24: =subQ!H13 | I24: =subQ!I13 | J24: =subQ!J13 | K24: =subQ!K13 | L24: =subQ!L13 | ... AB24: =subQ!AB13 | AC24: 0 | AD24: 0 | AE24: =subQ!AE13 | AF24: 0 | AG24: 0 | AH24: 0 | AI24: 0 | AJ24: =subQ!AJ13 | AK24: 0 | AL24: 0 | AM24: 0 | AN24: 0 | AO24: =subQ!AO13
A25: drv:지분법손익 | B25: abs | C25: 지분법손익 (가정, 억원) | E25: =subQ!E14 | F25: =subQ!F14 | G25: =subQ!G14 | H25: =subQ!H14 | I25: =subQ!I14 | J25: =subQ!J14 | K25: =subQ!K14 | L25: =subQ!L14 | ... AB25: =subQ!AB14 | AC25: 0 | AD25: 0 | AE25: =subQ!AE14 | AF25: 0 | AG25: 0 | AH25: 0 | AI25: 0 | AJ25: =subQ!AJ14 | AK25: 0 | AL25: 0 | AM25: 0 | AN25: 0 | AO25: =subQ!AO14
A26: drv:법인세비용 | B26: tax | C26: 법인세율(/세전) — 법인세 = MAX(세전,0) × 세율 | E26: =IFERROR(subQ!E16/subQ!E15,"") | F26: =IFERROR(subQ!F16/subQ!F15,"") | G26: =IFERROR(subQ!G16/subQ!G15,"") | H26: =IFERROR(subQ!H16/subQ!H15,"") | I26: =IFERROR(subQ!I16/subQ!I15,"") | J26: =IFERROR(subQ!J16/subQ!J15,"") | K26: =IFERROR(subQ!K16/subQ!K15,"") | L26: =IFERROR(subQ!L16/subQ!L15,"") | ... AB26: =IFERROR(subQ!AB16/subQ!AB15,"") | AC26: =$D$49 | AD26: =$D$49 | AE26: =IFERROR(subQ!AE16/subQ!AE15,"") | AF26: =$D$49 | AG26: =$D$49 | AH26: =$D$49 | AI26: =$D$49 | AJ26: =IFERROR(subQ!AJ16/subQ!AJ15,"") | AK26: =$D$49 | AL26: =$D$49 | AM26: =$D$49 | AN26: =$D$49 | AO26: =IFERROR(subQ!AO16/subQ!AO15,"")
A27: drv:지배주주순이익 | B27: ratio | C27: 지배주주 비중(/당기순이익) | E27: =IFERROR(subQ!E18/subQ!E17,"") | F27: =IFERROR(subQ!F18/subQ!F17,"") | G27: =IFERROR(subQ!G18/subQ!G17,"") | H27: =IFERROR(subQ!H18/subQ!H17,"") | I27: =IFERROR(subQ!I18/subQ!I17,"") | J27: =IFERROR(subQ!J18/subQ!J17,"") | K27: =IFERROR(subQ!K18/subQ!K17,"") | L27: =IFERROR(subQ!L18/subQ!L17,"") | ... AB27: =IFERROR(subQ!AB18/subQ!AB17,"") | AC27: =$D$51 | AD27: =$D$51 | AE27: =IFERROR(subQ!AE18/subQ!AE17,"") | AF27: =$D$51 | AG27: =$D$51 | AH27: =$D$51 | AI27: =$D$51 | AJ27: =IFERROR(subQ!AJ18/subQ!AJ17,"") | AK27: =$D$51 | AL27: =$D$51 | AM27: =$D$51 | AN27: =$D$51 | AO27: =IFERROR(subQ!AO18/subQ!AO17,"")
A28: drv:중단사업이익 | B28: abs | C28: 중단사업이익 (가정, 억원) | E28: =subQ!E19 | F28: =subQ!F19 | G28: =subQ!G19 | H28: =subQ!H19 | I28: =subQ!I19 | J28: =subQ!J19 | K28: =subQ!K19 | L28: =subQ!L19 | ... AB28: =subQ!AB19 | AE28: =subQ!AE19 | AJ28: =subQ!AJ19 | AO28: =subQ!AO19
A29: drv:부채총계 | B29: qoq | C29: 부채총계 QoQ | G29: =IFERROR(subQ!G21/subQ!E21-1,"") | H29: =IFERROR(subQ!H21/subQ!G21-1,"") | I29: =IFERROR(subQ!I21/subQ!H21-1,"") | J29: =IFERROR(subQ!J21/subQ!I21-1,"") | L29: =IFERROR(subQ!L21/subQ!J21-1,"") | M29: =IFERROR(subQ!M21/subQ!L21-1,"") | N29: =IFERROR(subQ!N21/subQ!M21-1,"") | O29: =IFERROR(subQ!O21/subQ!N21-1,"") | Q29: =IFERROR(subQ!Q21/subQ!O21-1,"") | R29: =IFERROR(subQ!R21/subQ!Q21-1,"") | S29: =IFERROR(subQ!S21/subQ!R21-1,"") | T29: =IFERROR(subQ!T21/subQ!S21-1,"") | V29: =IFERROR(subQ!V21/subQ!T21-1,"") | W29: =IFERROR(subQ!W21/subQ!V21-1,"") | X29: =IFERROR(subQ!X21/subQ!W21-1,"") | Y29: =IFERROR(subQ!Y21/subQ!X21-1,"") | AA29: =IFERROR(subQ!AA21/subQ!Y21-1,"") | AB29: =IFERROR(subQ!AB21/subQ!AA21-1,"") | AC29: -5.849e-06 | AD29: 0 | AF29: 0 | AG29: 0 | AH29: 0 | AI29: 0 | AK29: 0 | AL29: 0 | AM29: 0 | AN29: 0
A30: drv:자본총계 | B30: roll | C30: 자본총계 기타변동(배당 등, 억원) | G30: =IFERROR(subQ!E22+subQ!G17-subQ!G22,"") | H30: =IFERROR(subQ!G22+subQ!H17-subQ!H22,"") | I30: =IFERROR(subQ!H22+subQ!I17-subQ!I22,"") | J30: =IFERROR(subQ!I22+subQ!J17-subQ!J22,"") | L30: =IFERROR(subQ!J22+subQ!L17-subQ!L22,"") | M30: =IFERROR(subQ!L22+subQ!M17-subQ!M22,"") | N30: =IFERROR(subQ!M22+subQ!N17-subQ!N22,"") | O30: =IFERROR(subQ!N22+subQ!O17-subQ!O22,"") | Q30: =IFERROR(subQ!O22+subQ!Q17-subQ!Q22,"") | R30: =IFERROR(subQ!Q22+subQ!R17-subQ!R22,"") | S30: =IFERROR(subQ!R22+subQ!S17-subQ!S22,"") | T30: =IFERROR(subQ!S22+subQ!T17-subQ!T22,"") | V30: =IFERROR(subQ!T22+subQ!V17-subQ!V22,"") | W30: =IFERROR(subQ!V22+subQ!W17-subQ!W22,"") | X30: =IFERROR(subQ!W22+subQ!X17-subQ!X22,"") | Y30: =IFERROR(subQ!X22+subQ!Y17-subQ!Y22,"") | AA30: =IFERROR(subQ!Y22+subQ!AA17-subQ!AA22,"") | AB30: =IFERROR(subQ!AA22+subQ!AB17-subQ!AB22,"") | AC30: 0.008637673 | AD30: -0.004379011 | AF30: 0.000791705 | AG30: 6.9424195 | AH30: 0.003009043 | AI30: -0.008588473 | AK30: -0.003047909 | AL30: 6.9397254 | AM30: 0.011795324 | AN30: -0.004061584
A31: drv:지배주주지분 | B31: roll | C31: 지배주주지분 기타변동(배당 등, 억원) | G31: =IFERROR(subQ!E23+subQ!G18-subQ!G23,"") | H31: =IFERROR(subQ!G23+subQ!H18-subQ!H23,"") | I31: =IFERROR(subQ!H23+subQ!I18-subQ!I23,"") | J31: =IFERROR(subQ!I23+subQ!J18-subQ!J23,"") | L31: =IFERROR(subQ!J23+subQ!L18-subQ!L23,"") | M31: =IFERROR(subQ!L23+subQ!M18-subQ!M23,"") | N31: =IFERROR(subQ!M23+subQ!N18-subQ!N23,"") | O31: =IFERROR(subQ!N23+subQ!O18-subQ!O23,"") | Q31: =IFERROR(subQ!O23+subQ!Q18-subQ!Q23,"") | R31: =IFERROR(subQ!Q23+subQ!R18-subQ!R23,"") | S31: =IFERROR(subQ!R23+subQ!S18-subQ!S23,"") | T31: =IFERROR(subQ!S23+subQ!T18-subQ!T23,"") | V31: =IFERROR(subQ!T23+subQ!V18-subQ!V23,"") | W31: =IFERROR(subQ!V23+subQ!W18-subQ!W23,"") | X31: =IFERROR(subQ!W23+subQ!X18-subQ!X23,"") | Y31: =IFERROR(subQ!X23+subQ!Y18-subQ!Y23,"") | AA31: =IFERROR(subQ!Y23+subQ!AA18-subQ!AA23,"") | AB31: =IFERROR(subQ!AA23+subQ!AB18-subQ!AB23,"") | AC31: 0.003137673 | AD31: 0.005620989 | AF31: 0.000791705 | AG31: 6.9424195 | AH31: -0.006990957 | AI31: 0.001411527 | AK31: -0.003047909 | AL31: 6.9397254 | AM31: 0.001795324 | AN31: 0.005938416
A32: drv:총차입금 | B32: qoq | C32: 총차입금 QoQ | G32: =IFERROR(subQ!G24/subQ!E24-1,"") | H32: =IFERROR(subQ!H24/subQ!G24-1,"") | I32: =IFERROR(subQ!I24/subQ!H24-1,"") | J32: =IFERROR(subQ!J24/subQ!I24-1,"") | L32: =IFERROR(subQ!L24/subQ!J24-1,"") | M32: =IFERROR(subQ!M24/subQ!L24-1,"") | N32: =IFERROR(subQ!N24/subQ!M24-1,"") | O32: =IFERROR(subQ!O24/subQ!N24-1,"") | Q32: =IFERROR(subQ!Q24/subQ!O24-1,"") | R32: =IFERROR(subQ!R24/subQ!Q24-1,"") | S32: =IFERROR(subQ!S24/subQ!R24-1,"") | T32: =IFERROR(subQ!T24/subQ!S24-1,"") | V32: =IFERROR(subQ!V24/subQ!T24-1,"") | W32: =IFERROR(subQ!W24/subQ!V24-1,"") | X32: =IFERROR(subQ!X24/subQ!W24-1,"") | Y32: =IFERROR(subQ!Y24/subQ!X24-1,"") | AA32: =IFERROR(subQ!AA24/subQ!Y24-1,"") | AB32: =IFERROR(subQ!AB24/subQ!AA24-1,"") | AC32: -7.576e-06 | AD32: 0 | AF32: 0 | AG32: 0 | AH32: 0 | AI32: 0 | AK32: 0 | AL32: 0 | AM32: 0 | AN32: 0
A33: drv:순차입금 | B33: qoq | C33: 순차입금 QoQ | G33: =IFERROR(subQ!G25/subQ!E25-1,"") | H33: =IFERROR(subQ!H25/subQ!G25-1,"") | I33: =IFERROR(subQ!I25/subQ!H25-1,"") | J33: =IFERROR(subQ!J25/subQ!I25-1,"") | L33: =IFERROR(subQ!L25/subQ!J25-1,"") | M33: =IFERROR(subQ!M25/subQ!L25-1,"") | N33: =IFERROR(subQ!N25/subQ!M25-1,"") | O33: =IFERROR(subQ!O25/subQ!N25-1,"") | Q33: =IFERROR(subQ!Q25/subQ!O25-1,"") | R33: =IFERROR(subQ!R25/subQ!Q25-1,"") | S33: =IFERROR(subQ!S25/subQ!R25-1,"") | T33: =IFERROR(subQ!T25/subQ!S25-1,"") | V33: =IFERROR(subQ!V25/subQ!T25-1,"") | W33: =IFERROR(subQ!W25/subQ!V25-1,"") | X33: =IFERROR(subQ!X25/subQ!W25-1,"") | Y33: =IFERROR(subQ!Y25/subQ!X25-1,"") | AA33: =IFERROR(subQ!AA25/subQ!Y25-1,"") | AB33: =IFERROR(subQ!AB25/subQ!AA25-1,"") | AC33: 0.001045741 | AD33: -0.005144738 | AF33: 3.358e-05 | AG33: -0.013095818 | AH33: -0.000357258 | AI33: -0.007709326 | AK33: -0.001629307 | AL33: -0.01534048 | AM33: -0.001343359 | AN33: -0.009468572
A34: drv:이자발생자산 | B34: qoq | C34: 이자발생자산 QoQ | G34: =IFERROR(subQ!G26/subQ!E26-1,"") | H34: =IFERROR(subQ!H26/subQ!G26-1,"") | I34: =IFERROR(subQ!I26/subQ!H26-1,"") | J34: =IFERROR(subQ!J26/subQ!I26-1,"") | L34: =IFERROR(subQ!L26/subQ!J26-1,"") | M34: =IFERROR(subQ!M26/subQ!L26-1,"") | N34: =IFERROR(subQ!N26/subQ!M26-1,"") | O34: =IFERROR(subQ!O26/subQ!N26-1,"") | Q34: =IFERROR(subQ!Q26/subQ!O26-1,"") | R34: =IFERROR(subQ!R26/subQ!Q26-1,"") | S34: =IFERROR(subQ!S26/subQ!R26-1,"") | T34: =IFERROR(subQ!T26/subQ!S26-1,"") | V34: =IFERROR(subQ!V26/subQ!T26-1,"") | W34: =IFERROR(subQ!W26/subQ!V26-1,"") | X34: =IFERROR(subQ!X26/subQ!W26-1,"") | Y34: =IFERROR(subQ!Y26/subQ!X26-1,"") | AA34: =IFERROR(subQ!AA26/subQ!Y26-1,"") | AB34: =IFERROR(subQ!AB26/subQ!AA26-1,"") | AC34: 0.000806296 | AD34: -0.00397404 | AF34: 3.8863e-05 | AG34: -0.010116842 | AH34: -0.000274808 | AI34: -0.00592963 | AK34: -0.001250938 | AL34: -0.011773547 | AM34: -0.001027283 | AN34: -0.007238441
A35: drv:현금및현금성자산 | B35: qoq | C35: 현금및현금성자산 QoQ | G35: =IFERROR(subQ!G27/subQ!E27-1,"") | H35: =IFERROR(subQ!H27/subQ!G27-1,"") | I35: =IFERROR(subQ!I27/subQ!H27-1,"") | J35: =IFERROR(subQ!J27/subQ!I27-1,"") | L35: =IFERROR(subQ!L27/subQ!J27-1,"") | M35: =IFERROR(subQ!M27/subQ!L27-1,"") | N35: =IFERROR(subQ!N27/subQ!M27-1,"") | O35: =IFERROR(subQ!O27/subQ!N27-1,"") | Q35: =IFERROR(subQ!Q27/subQ!O27-1,"") | R35: =IFERROR(subQ!R27/subQ!Q27-1,"") | S35: =IFERROR(subQ!S27/subQ!R27-1,"") | T35: =IFERROR(subQ!T27/subQ!S27-1,"") | V35: =IFERROR(subQ!V27/subQ!T27-1,"") | W35: =IFERROR(subQ!W27/subQ!V27-1,"") | X35: =IFERROR(subQ!X27/subQ!W27-1,"") | Y35: =IFERROR(subQ!Y27/subQ!X27-1,"") | AA35: =IFERROR(subQ!AA27/subQ!Y27-1,"") | AB35: =IFERROR(subQ!AB27/subQ!AA27-1,"")
A36: drv:CAPEX | B36: yoy | C36: CAPEX YoY | J36: =IFERROR(subQ!J28/subQ!E28-1,"") | L36: =IFERROR(subQ!L28/subQ!G28-1,"") | M36: =IFERROR(subQ!M28/subQ!H28-1,"") | N36: =IFERROR(subQ!N28/subQ!I28-1,"") | O36: =IFERROR(subQ!O28/subQ!J28-1,"") | Q36: =IFERROR(subQ!Q28/subQ!L28-1,"") | R36: =IFERROR(subQ!R28/subQ!M28-1,"") | S36: =IFERROR(subQ!S28/subQ!N28-1,"") | T36: =IFERROR(subQ!T28/subQ!O28-1,"") | V36: =IFERROR(subQ!V28/subQ!Q28-1,"") | W36: =IFERROR(subQ!W28/subQ!R28-1,"") | X36: =IFERROR(subQ!X28/subQ!S28-1,"") | Y36: =IFERROR(subQ!Y28/subQ!T28-1,"") | AA36: =IFERROR(subQ!AA28/subQ!V28-1,"") | AB36: =IFERROR(subQ!AB28/subQ!W28-1,"") | AC36: -0.39704984 | AD36: -0.44136601 | AF36: 1.9294432 | AG36: 2.4668816 | AH36: 0 | AI36: 0 | AK36: 0 | AL36: 0 | AM36: 0 | AN36: 0
A37: drv:영업활동현금흐름 | B37: yoy | C37: 영업활동현금흐름 YoY | J37: =IFERROR(subQ!J29/subQ!E29-1,"") | L37: =IFERROR(subQ!L29/subQ!G29-1,"") | M37: =IFERROR(subQ!M29/subQ!H29-1,"") | N37: =IFERROR(subQ!N29/subQ!I29-1,"") | O37: =IFERROR(subQ!O29/subQ!J29-1,"") | Q37: =IFERROR(subQ!Q29/subQ!L29-1,"") | R37: =IFERROR(subQ!R29/subQ!M29-1,"") | S37: =IFERROR(subQ!S29/subQ!N29-1,"") | T37: =IFERROR(subQ!T29/subQ!O29-1,"") | V37: =IFERROR(subQ!V29/subQ!Q29-1,"") | W37: =IFERROR(subQ!W29/subQ!R29-1,"") | X37: =IFERROR(subQ!X29/subQ!S29-1,"") | Y37: =IFERROR(subQ!Y29/subQ!T29-1,"") | AA37: =IFERROR(subQ!AA29/subQ!V29-1,"") | AB37: =IFERROR(subQ!AB29/subQ!W29-1,"")
A38: drv:주식수 | B38: qoq | C38: 주식수 QoQ | G38: =IFERROR(subQ!G30/subQ!E30-1,"") | H38: =IFERROR(subQ!H30/subQ!G30-1,"") | I38: =IFERROR(subQ!I30/subQ!H30-1,"") | J38: =IFERROR(subQ!J30/subQ!I30-1,"") | L38: =IFERROR(subQ!L30/subQ!J30-1,"") | M38: =IFERROR(subQ!M30/subQ!L30-1,"") | N38: =IFERROR(subQ!N30/subQ!M30-1,"") | O38: =IFERROR(subQ!O30/subQ!N30-1,"") | Q38: =IFERROR(subQ!Q30/subQ!O30-1,"") | R38: =IFERROR(subQ!R30/subQ!Q30-1,"") | S38: =IFERROR(subQ!S30/subQ!R30-1,"") | T38: =IFERROR(subQ!T30/subQ!S30-1,"") | V38: =IFERROR(subQ!V30/subQ!T30-1,"") | W38: =IFERROR(subQ!W30/subQ!V30-1,"") | X38: =IFERROR(subQ!X30/subQ!W30-1,"") | Y38: =IFERROR(subQ!Y30/subQ!X30-1,"") | AA38: =IFERROR(subQ!AA30/subQ!Y30-1,"") | AB38: =IFERROR(subQ!AB30/subQ!AA30-1,"") | AC38: 0 | AD38: 0 | AF38: 0 | AG38: 0 | AH38: 0 | AI38: 0 | AK38: 0 | AL38: 0 | AM38: 0 | AN38: 0
A39: drv:DPS | B39: abs | C39: DPS (가정, 원) | E39: =subQ!E33 | F39: =subQ!F33 | G39: =subQ!G33 | H39: =subQ!H33 | I39: =subQ!I33 | J39: =subQ!J33 | K39: =subQ!K33 | L39: =subQ!L33 | ... AB39: =subQ!AB33 | AD39: 100 | AE39: =subQ!AE33 | AI39: 100 | AJ39: =subQ!AJ33 | AN39: 100 | AO39: =subQ!AO33
B41: 3. 밸류에이션·스칼라 | C41: 노란 셀 = 가정. '연결' 표시는 추정 전 분기 수식이 이 셀을 참조한다는 뜻
A42: sc:종가 | C42: 종가 | D42: 8950 | E42: 원 — 네이버 정규장 종가(aik 확정종가 대조 · aik 8,810원)
A43: sc:기준일 | C43: 기준일 | D43: 20261008 | E43: 종가 기준일
A44: sc:COE | C44: COE | D44: 0.09 | E44: 자기자본비용(가정) — TP 적정 PBR = ROE/COE
A45: sc:PER_lo | C45: PER_lo | D45: 5 | E45: PER 밴드 하단(배) — hist_quarterly(분기 평균가 ÷ TTM EPS, 10분기, 25/50/75 백분위) · 캡 5~30배 적용(원값 1.3/5.4/6.8)
A46: sc:PER_mid | C46: PER_mid | D46: 5.4 | E46: PER 밴드 중단(배)
A47: sc:PER_hi | C47: PER_hi | D47: 6.8 | E47: PER 밴드 상단(배)
A48: sc:EPS_Y1가중 | C48: EPS_Y1가중 | D48: 0.5 | E48: 12M fwd EPS = FY(last_actual연도)E × w + FY+1E × (1−w) — 기준 분기 2Q 이면 0.5(가정)
A49: sc:세율 | C49: 세율 | D49: 0.043478261 | E49: 연결 — 법인세 = MAX(세전,0) × 세율(역산, 재현 오차 ≤ 0.05억 · 모델 assumptions 0.0522) · 최근 12분기 유효세율 5.2%(5~27% 안 — 그대로)
A50: sc:판관비율 | C50: 판관비율 | D50: 0.1619279 | E50: 연결 — 판관비 = 매출액 × 판관비율(역산, 재현 오차 ≤ 0.05억 · 모델 assumptions 0.1619)
A51: sc:지배주주비중 | C51: 지배주주비중 | D51: 1 | E51: 연결 — 지배주주순이익 = 당기순이익 × 비중(역산, 재현 오차 ≤ 0.05억)
A52: sc:이자율_자산 | C52: 이자율_자산 | D52: 0.030427833 | E52: 연결 — 이자손익 = (전분기 이자발생자산 × 자산이자율 − 전분기 총차입금 × 부채이자율)/4(역산, 재현 오차 ≤ 0.05억 · 모델 assumptions 0.0304)
A53: sc:이자율_부채 | C53: 이자율_부채 | D53: 0 | E53: 연결 — 같은 수식의 부채 쪽(총차입금 행이 없으면 0)(역산, 재현 오차 ≤ 0.05억)
A54: sc:배당성향 | C54: 배당성향 | E54: 배당성향(참고 — 모델은 직전 DPS 유지·Q2 지급 가정)
A55: sc:외화순노출_백만$ | C55: 외화순노출_백만$ | E55: 외화 순노출 × Δ기말환율 (외화 시트 방식) — 외화 순노출 미공시(face) → 0 + 표기
A56: sc:헤지비율 | C56: 헤지비율 | E56: sls 없음
A57: sc:헤지환율_약정 | C57: 헤지환율_약정 | E57: sls 없음

Sheet BS연결
B1: (백만원) | C1: 이름: BS연결H | E1: 4Q21 | F1: 2021 | G1: 1Q22 | H1: 2Q22 | I1: 3Q22 | J1: 4Q22 | K1: 2022 | L1: 1Q23 | M1: 2Q23 | N1: 3Q23 | O1: 4Q23 | P1: 2023 | Q1: 1Q24 | R1: 2Q24 | S1: 3Q24 | T1: 4Q24 | U1: 2024 | V1: 1Q25 | W1: 2Q25 | X1: 3Q25 | Y1: 4Q25 | Z1: 2025 | AA1: 1Q26 | AB1: 2Q26 | AC1: 3Q26 | AD1: 4Q26 | AE1: 2026 | AF1: 1Q27 | AG1: 2Q27 | AH1: 3Q27 | AI1: 4Q27 | AJ1: 2027 | AK1: 1Q28 | AL1: 2Q28 | AM1: 3Q28 | AN1: 4Q28 | AO1: 2028
B2: 연결 | D2: fin json(kship_fin.py)
B3: 엔케이(연) | C3: UPDATE: 26-10-11 | E3: 1 | F3: 2 | G3: 3 | H3: 4 | I3: 5 | J3: 6 | K3: 7 | L3: 8 | M3: 9 | N3: 10 | O3: 11 | P3: 12 | Q3: 13 | R3: 14 | S3: 15 | T3: 16 | U3: 17 | V3: 18 | W3: 19 | X3: 20 | Y3: 21 | Z3: 22 | AA3: 23 | AB3: 24 | AC3: 25 | AD3: 26 | AE3: 27 | AF3: 28 | AG3: 29 | AH3: 30 | AI3: 31 | AJ3: 32 | AK3: 33 | AL3: 34 | AM3: 35 | AN3: 36 | AO3: 37
B4: Account Code | C4: AccountNAME | E4: 2021.12 | F4: 2021.12A | G4: 2022.03 | H4: 2022.06 | I4: 2022.09 | J4: 2022.12 | K4: 2022.12A | L4: 2023.03 | M4: 2023.06 | N4: 2023.09 | O4: 2023.12 | P4: 2023.12A | Q4: 2024.03 | R4: 2024.06 | S4: 2024.09 | T4: 2024.12 | U4: 2024.12A | V4: 2025.03 | W4: 2025.06 | X4: 2025.09 | Y4: 2025.12 | Z4: 2025.12A | AA4: 2026.03 | AB4: 2026.06 | AC4: 2026.09 | AD4: 2026.12 | AE4: 2026.12A | AF4: 2027.03 | AG4: 2027.06 | AH4: 2027.09 | AI4: 2027.12 | AJ4: 2027.12A | AK4: 2028.03 | AL4: 2028.06 | AM4: 2028.09 | AN4: 2028.12 | AO4: 2028.12A
A5: 1 | C5: 유동자산 | E5: 71679.87 | F5: 71679.87 | G5: 64304.02 | H5: 62744.95 | I5: 69036.31 | J5: 85643.41 | K5: 85643.41 | L5: 84154.74 | M5: 78641.35 | N5: 75977.76 | O5: 169799.53 | P5: 169799.53 | Q5: 173152.02 | R5: 170030.54 | S5: 162508 | T5: 166228.28 | U5: 166228.28 | V5: 157874.01 | W5: 135473.65 | X5: 131010.66 | Y5: 125704.72 | Z5: 125704.72 | AA5: 128279.78 | AB5: 126600.56
A6: 1 | C6: 현금및현금성자산 | E6: 51477.69 | F6: 51477.69 | G6: 30806.24 | H6: 30022.25 | I6: 21710.66 | J6: 29701.15 | K6: 29701.15 | L6: 28795.96 | M6: 27058.65 | N6: 27348.1 | O6: 24768.6 | P6: 24768.6 | Q6: 24771.32 | R6: 22065.86 | S6: 24250.94 | T6: 28765.02 | U6: 28765.02 | V6: 32241.33 | W6: 29451.54 | X6: 50369.61 | Y6: 48368.97 | Z6: 48368.97 | AA6: 54587.23 | AB6: 76964.59
A7: 1 | C7: 기타유동금융자산 | E7: 7887.37 | F7: 7887.37 | G7: 22709.38 | H7: 19709.38 | I7: 27659.39 | J7: 24847.25 | K7: 24847.25 | L7: 26241.16 | M7: 23277.21 | N7: 21392.85 | O7: 109172.01 | P7: 109172.01 | Q7: 108401.61 | R7: 108571.21 | S7: 103292.81 | T7: 98895.44 | U7: 98895.44 | V7: 79748.63 | W7: 60867.28 | X7: 20016.61 | Y7: 20000 | Z7: 20000 | AA7: 20000 | AB7: 0
A8: 1 | C8: 매출채권및기타채권 | E8: 10328.7 | F8: 10328.7 | G8: 8803.49 | H8: 11297.35 | I8: 16530.03 | J8: 20794.39 | K8: 20794.39 | L8: 19788.58 | M8: 18081.67 | N8: 13807.79 | O8: 17989.6 | P8: 17989.6 | Q8: 22131.19 | R8: 21567.47 | S8: 15528.65 | T8: 18230 | U8: 18230 | V8: 14915.44 | W8: 23182.68 | X8: 29530.14 | Y8: 28443.13 | Z8: 28443.13 | AA8: 22942.14 | AB8: 20643.78
A9: 1 | C9: 기타유동자산 | E9: 116.57 | F9: 116.57 | G9: 395.35 | H9: 261.86 | I9: 1240.54 | J9: 767.94 | K9: 767.94 | L9: 612.6 | M9: 1183.96 | N9: 2764.26 | O9: 3131.23 | P9: 3131.23 | Q9: 3652.91 | R9: 5233.87 | S9: 4679.88 | T9: 4581.33 | U9: 4581.33 | V9: 12618.49 | W9: 3791.02 | X9: 5209.86 | Y9: 8197.3 | Z9: 8197.3 | AA9: 10108.48 | AB9: 9363.95
A10: 1 | C10: 당기법인세자산(선급법인세) | E10: 36.46 | F10: 36.46 | G10: 55.6 | H10: 46.89 | I10: 85.12 | J10: 173.41 | K10: 173.41 | L10: 294.83 | M10: 219.81 | N10: 261.02 | O10: 46.79 | P10: 46.79 | Q10: 145.67 | R10: 153.65 | S10: 450.95 | T10: 488.86 | U10: 488.86 | V10: 789.21 | W10: 342.01 | X10: 527.11 | Y10: 554.94 | Z10: 554.94 | AA10: 619.99 | AB10: 18.01
A11: 1 | C11: 재고자산 | E11: 1833.08 | F11: 1833.08 | G11: 1533.96 | H11: 1407.23 | I11: 1810.57 | J11: 9359.28 | K11: 9359.28 | L11: 8421.62 | M11: 8820.05 | N11: 10403.75 | O11: 14691.29 | P11: 14691.29 | Q11: 14049.33 | R11: 12438.48 | S11: 14304.76 | T11: 13409.86 | U11: 13409.86 | V11: 15647.15 | W11: 16705.87 | X11: 23820.46 | Y11: 16999.58 | Z11: 16999.58 | AA11: 15686.4 | AB11: 14867.22
A12: 1 | C12: 유동파생상품자산 | E12: 0 | F12: 0 | G12: 0 | H12: 0 | I12: 0 | J12: 0 | K12: 0 | L12: 0 | M12: 0 | N12: 0 | O12: 0 | P12: 0 | Q12: 0 | R12: 0 | S12: 0 | T12: 0 | U12: 0 | V12: 0
A13: 1 | C13: 단기금융자산 | E13: 0 | F13: 0 | G13: 0 | H13: 0 | I13: 0 | J13: 0 | K13: 0 | L13: 0 | M13: 0 | N13: 0 | O13: 0 | P13: 0 | Q13: 0 | R13: 0 | S13: 0 | T13: 0 | U13: 0 | V13: 0
A14: 1 | C14: 매각예정비유동자산및처분자산 | E14: 0 | F14: 0 | G14: 0 | H14: 0 | I14: 0 | J14: 0 | K14: 0 | L14: 0 | M14: 0 | N14: 0 | O14: 10407.89 | P14: 10407.89 | Q14: 10407.89 | R14: 0 | S14: 0 | T14: 0 | U14: 0 | V14: 0
A15: 1 | C15: 비유동자산 | E15: 59046.65 | F15: 59046.65 | G15: 66383.16 | H15: 68472.8 | I15: 65383.72 | J15: 100102.52 | K15: 100102.52 | L15: 99547.66 | M15: 98262.42 | N15: 103965.19 | O15: 67458.66 | P15: 67458.66 | Q15: 61542.69 | R15: 61805.43 | S15: 63903 | T15: 60915.41 | U15: 60915.41 | V15: 60094.82 | W15: 70310.39 | X15: 100310.74 | Y15: 104842.51 | Z15: 104842.51 | AA15: 100513.06 | AB15: 100605.42
A16: 1 | C16: 장기금융자산 | E16: 12220.19 | F16: 12220.19 | G16: 15231.79 | H16: 14481.42 | I16: 14481.42 | J16: 2244.84 | K16: 2244.84 | L16: 1244.84 | M16: 645.84 | N16: 645.84 | O16: 644.93 | P16: 644.93 | Q16: 644.93 | R16: 644.93 | S16: 675.66 | T16: 644.93 | U16: 644.93 | V16: 644.93 | W16: 644.93 | X16: 729.43 | Y16: 475.47 | Z16: 475.47 | AA16: 475.47 | AB16: 475.97
A17: 1 | C17: 투자자산 | E17: 27935.17 | F17: 27935.17 | G17: 32097.53 | H17: 32210.21 | I17: 33203.19 | J17: 21317.01 | K17: 21317.01 | L17: 21103.88 | M17: 20049.73 | N17: 26055.25 | O17: 1891.78 | P17: 1891.78 | Q17: 1792.64 | R17: 1789.42 | S17: 1817.34 | T17: 1791.1 | U17: 1791.1 | V17: 1813.18 | W17: 1810.68 | X17: 1892.17 | Y17: 475.47 | Z17: 475.47 | AA17: 475.47 | AB17: 475.97
A18: 1 | C18: 종속기업및관계기업투자 | E18: 15714.98 | F18: 15714.98 | G18: 16865.74 | H18: 17728.79 | I18: 18721.77 | J18: 19072.17 | K18: 19072.17 | L18: 19859.04 | M18: 19403.89 | N18: 25409.41 | O18: 1246.85 | P18: 1246.85 | Q18: 1147.71 | R18: 1144.49 | S18: 1141.68 | T18: 1146.17 | U18: 1146.17 | V18: 1168.25 | W18: 1165.75 | X18: 1162.74 | Y18: 0 | Z18: 0 | AA18: 0
A19: 1 | C19: 장기매출채권및기타채권 | E19: 0 | F19: 0 | G19: 0 | H19: 0 | I19: 0 | J19: 0 | K19: 0 | L19: 0 | M19: 0 | N19: 0 | O19: 0 | P19: 0 | Q19: 0 | R19: 0 | Y19: 0 | Z19: 0 | AA19: 0 | AB19: 0
A20: 1 | C20: 유형자산 | E20: 21213.33 | F20: 21213.33 | G20: 23828.59 | H20: 25408.94 | I20: 21295.34 | J20: 51379.8 | K20: 51379.8 | L20: 50948.62 | M20: 50815.97 | N20: 50094.22 | O20: 40053.57 | P20: 40053.57 | Q20: 41454.66 | R20: 41495.46 | S20: 40136.05 | T20: 40617.62 | U20: 40617.62 | V20: 40104.11 | W20: 40974.14 | X20: 75752.46 | Y20: 80767.64 | Z20: 80767.64 | AA20: 80985.54 | AB20: 81301.79
A21: 1 | C21: 사용권자산 | E21: 96.25 | F21: 96.25 | G21: 92.5 | H21: 88.75 | I21: 85 | J21: 13341.87 | K21: 13341.87 | L21: 13256.6 | M21: 13171.33 | N21: 13086.06 | O21: 13367.43 | P21: 13367.43 | Q21: 6282.43 | R21: 6369.11 | S21: 6581.42 | T21: 6441.65 | U21: 6441.65 | V21: 6143.97 | W21: 6086.28 | X21: 6071.84 | Y21: 7643.6 | Z21: 7643.6 | AA21: 3051.47 | AB21: 2843.52
A22: 1 | C22: 기타비유동자산 | E22: 96.25 | F22: 96.25 | G22: 92.5 | H22: 88.75 | I22: 85 | J22: 13341.87 | K22: 13341.87 | L22: 13256.6 | M22: 13171.33 | N22: 13086.06 | O22: 13367.43 | P22: 13367.43 | Q22: 6282.43 | R22: 6369.11 | S22: 6581.42 | T22: 6441.65 | U22: 6441.65 | V22: 6143.97 | W22: 14886.28 | X22: 6071.84 | Y22: 7643.6 | Z22: 7643.6 | AA22: 3051.47 | AB22: 2843.52
A23: 1 | C23: 무형자산 | E23: 47.03 | F23: 47.03 | G23: 47.03 | H23: 47.03 | I23: 47.03 | J23: 103.87 | K23: 103.87 | L23: 96.76 | M23: 109.32 | N23: 175.78 | O23: 181.53 | P23: 181.53 | Q23: 175.21 | R23: 336.35 | S23: 271.54 | T23: 282.61 | U23: 282.61 | V23: 266.31 | W23: 250.34 | X23: 255.35 | Y23: 234.76 | Z23: 234.76 | AA23: 215.04 | AB23: 209.14
A24: 1 | C24: 투자부동산 | E24: 8962.2 | F24: 8962.2 | G24: 8949.12 | H24: 8936.04 | I24: 9977.22 | J24: 11476.04 | K24: 11476.04 | L24: 11527 | M24: 11501.27 | N24: 11889.08 | O24: 11388.38 | P24: 11388.38 | Q24: 11362.21 | R24: 11336.04 | S24: 11309.87 | T24: 11283.71 | U24: 11283.71 | V24: 11257.54 | W24: 11857.84 | X24: 14917.8 | Y24: 14254.69 | Z24: 14254.69 | AA24: 14228.52 | AB24: 14202.35
A25: 1 | C25: 이연법인세자산 | E25: 0 | F25: 0 | G25: 0 | H25: 0 | I25: 0 | J25: 0 | K25: 0 | L25: 0 | M25: 0 | N25: 0 | O25: 0 | P25: 0 | Q25: 0 | R25: 0 | S25: 0 | T25: 0 | U25: 0 | V25: 0 | Y25: 21.2 | Z25: 21.2 | AA25: 21.2 | AB25: 21.2
A26: 1 | C26: 자산총계 | E26: 130726.53 | F26: 130726.53 | G26: 130687.18 | H26: 131217.75 | I26: 134420.03 | J26: 185745.93 | K26: 185745.93 | L26: 183702.4 | M26: 176903.77 | N26: 179942.96 | O26: 247666.09 | P26: 247666.09 | Q26: 245102.6 | R26: 231835.97 | S26: 226411 | T26: 227143.69 | U26: 227143.69 | V26: 217968.84 | W26: 205784.04 | X26: 231321.4 | Y26: 230547.23 | Z26: 230547.23 | AA26: 228792.84 | AB26: 227205.97
A27: 1 | C27: 유동부채 | E27: 26677.28 | F27: 26677.28 | G27: 26786.67 | H27: 25952.57 | I27: 25624.92 | J27: 40936.88 | K27: 40936.88 | L27: 36507.5 | M27: 29216.18 | N27: 24954.35 | O27: 41882.69 | P27: 41882.69 | Q27: 43653.21 | R27: 35143.14 | S27: 32794.57 | T27: 37203.71 | U27: 37203.71 | V27: 31981.87 | W27: 27685.47 | X27: 57662.57 | Y27: 55256.86 | Z27: 55256.86 | AA27: 55697.7 | AB27: 50684.51
A28: 1 | C28: 기타유동부채 | E28: 0 | F28: 0 | G28: 0 | H28: 0 | I28: 0 | J28: 0 | K28: 0 | L28: 0 | M28: 0 | N28: 0 | O28: 0 | P28: 0 | Q28: 0 | R28: 0 | S28: 0 | T28: 0 | U28: 0 | V28: 0
A29: 1 | C29: 단기차입금 | E29: 0 | F29: 0 | G29: 0 | H29: 0 | I29: 0 | J29: 8248.15 | K29: 8248.15 | L29: 7271.23 | M29: 7498.54 | N29: 2265.85 | O29: 2525.93 | P29: 2525.93 | Q29: 2634.55 | R29: 3255.08 | S29: 3034.91 | T29: 5005.95 | U29: 5005.95 | V29: 3893.72 | W29: 122.04 | X29: 7070.13 | Y29: 6380 | Z29: 6380 | AA29: 15440 | AB29: 17160.13
A30: 1 | C30: 당기법인세부채(미지급법인세) | E30: 0 | F30: 0 | G30: 0 | H30: 0 | I30: 0 | J30: 0.21 | K30: 0.21 | L30: 0 | M30: 0 | N30: 0 | O30: 4159.27 | P30: 4159.27 | Q30: 4159.27 | R30: 0 | S30: 0 | T30: 0 | U30: 0 | V30: 0 | Y30: 201.83 | Z30: 201.83 | AA30: 25.63 | AB30: 684.38
A31: 1 | C31: 유동성장기부채 | E31: 10066.44 | F31: 10066.44 | G31: 10385.18 | H31: 10721.69 | I31: 10563.45 | J31: 10903.99 | K31: 10903.99 | L31: 7073.16 | M31: 0 | N31: 0 | O31: 0 | P31: 0 | Q31: 0 | R31: 0 | S31: 0 | T31: 0 | U31: 0 | V31: 0 | X31: 8760.5 | Y31: 9345.5 | Z31: 9345.5
A32: 1 | C32: 유동리스부채 | E32: 0 | F32: 0 | G32: 0 | H32: 0 | I32: 0 | J32: 27.09 | K32: 27.09 | L32: 27.34 | M32: 29.42 | N32: 23.24 | O32: 264.46 | P32: 264.46 | Q32: 162.32 | R32: 87.31 | S32: 358.4 | T32: 269.8 | U32: 269.8 | V32: 29.8 | W32: 29.8 | X32: 39.91 | Y32: 691.79 | Z32: 691.79 | AA32: 662.18 | AB32: 677.3
A33: 1 | C33: 리스부채 | E33: 0 | F33: 0 | G33: 0 | H33: 0 | I33: 0 | J33: 12951.62 | K33: 12951.62 | L33: 12945.21 | M33: 12936.92 | N33: 12930.74 | O33: 13171.96 | P33: 13171.96 | Q33: 6127.38 | R33: 6267.75 | S33: 6531.32 | T33: 6434.63 | U33: 6434.63 | V33: 6187.61 | W33: 6180.31 | X33: 6182.83 | Y33: 7785.57 | Z33: 7785.57 | AA33: 2964.76 | AB33: 2799.45
A34: 1 | C34: 단기금융부채 | E34: 3091.39 | F34: 3091.39 | G34: 3091.39 | H34: 1092.38 | I34: 1042.72 | J34: 511.36 | K34: 511.36 | L34: 331.74 | M34: 29.42 | N34: 23.24 | O34: 264.46 | P34: 264.46 | Q34: 162.32 | R34: 87.31 | S34: 358.4 | T34: 269.8 | U34: 269.8 | V34: 29.8 | W34: 29.8 | X34: 39.91 | Y34: 691.79 | Z34: 691.79 | AA34: 662.18 | AB34: 677.3
A35: 1 | C35: 단기충당부채 | E35: 1480.71 | F35: 1480.71 | G35: 1480.71 | H35: 2345 | I35: 2345 | J35: 2818.04 | K35: 2818.04 | L35: 2435.61 | M35: 2678.4 | N35: 2586.18 | O35: 1566.35 | P35: 1566.35 | Q35: 1305.06 | R35: 1349.31 | S35: 1389.2 | T35: 1769.37 | U35: 1769.37 | V35: 1336.98 | W35: 1334.68 | X35: 1338.94 | Y35: 1384.34 | Z35: 1384.34 | AA35: 1095.25 | AB35: 1121.27
A36: 1 | C36: 단기파생상품부채 | E36: 3091.39 | F36: 3091.39 | G36: 3091.39 | H36: 1092.38 | I36: 1042.72 | J36: 484.27 | K36: 484.27 | L36: 304.4 | M36: 0 | N36: 0 | O36: 0 | P36: 0 | Q36: 0 | R36: 0 | S36: 0 | T36: 0 | U36: 0 | V36: 0
A37: 1 | C37: 비유동부채 | E37: 1334.65 | F37: 1334.65 | G37: 1368 | H37: 1254.14 | I37: 1255.21 | J37: 16577.52 | K37: 16577.52 | L37: 16573.9 | M37: 16308.52 | N37: 21398.21 | O37: 21073.49 | P37: 21073.49 | Q37: 14365.46 | R37: 13531.49 | S37: 13494.35 | T37: 6883.4 | U37: 6883.4 | V37: 6866.88 | W37: 6869.43 | X37: 8751.85 | Y37: 9041.12 | Z37: 9041.12 | AA37: 4249.93 | AB37: 4027.81
A38: 1 | C38: 장기차입금 | E38: 0 | F38: 0 | G38: 0 | H38: 0 | I38: 0 | J38: 0 | K38: 0 | L38: 0 | M38: 0 | N38: 5000 | O38: 5000 | P38: 5000 | Q38: 5000 | R38: 5000 | S38: 5000 | T38: 0 | U38: 0 | V38: 0 | X38: 662 | Y38: 6 | Z38: 6 | AA38: 6 | AB38: 0
A39: 1 | C39: 비유동리스부채 | E39: 0 | F39: 0 | G39: 0 | H39: 0 | I39: 0 | J39: 12924.53 | K39: 12924.53 | L39: 12917.87 | M39: 12907.5 | N39: 12907.5 | O39: 12907.5 | P39: 12907.5 | Q39: 5965.06 | R39: 6180.44 | S39: 6172.92 | T39: 6164.83 | U39: 6164.83 | V39: 6157.81 | W39: 6150.51 | X39: 6142.92 | Y39: 7093.78 | Z39: 7093.78 | AA39: 2302.58 | AB39: 2122.15
A40: 1 | C40: 장기금융부채 | E40: 0 | F40: 0 | G40: 0 | H40: 0 | I40: 0 | J40: 12924.53 | K40: 12924.53 | L40: 12917.87 | M40: 12907.5 | N40: 12907.5 | O40: 12907.5 | P40: 12907.5 | Q40: 5965.06 | R40: 6180.44 | S40: 6172.92 | T40: 6164.83 | U40: 6164.83 | V40: 6157.81 | W40: 6150.51 | X40: 6142.92 | Y40: 7093.78 | Z40: 7093.78 | AA40: 2302.58 | AB40: 2122.15
A41: 1 | C41: 사채 | E41: 0 | F41: 0 | G41: 0 | H41: 0 | I41: 0 | J41: 0 | K41: 0 | L41: 0 | M41: 0 | N41: 0 | O41: 0 | P41: 0 | Q41: 0 | R41: 0 | S41: 0 | T41: 0 | U41: 0 | V41: 0
A42: 1 | C42: 이연법인세부채 | E42: 0 | F42: 0 | G42: 0 | H42: 0 | I42: 0 | J42: 2754.53 | K42: 2754.53 | L42: 2754.53 | M42: 2681.84 | N42: 2645.99 | O42: 2466.93 | P42: 2466.93 | Q42: 2446.34 | R42: 1693.34 | S42: 1672.75 | T42: 99.55 | U42: 99.55 | V42: 89.8 | W42: 99.55 | X42: 1265.64 | Y42: 1276.7 | Z42: 1276.7 | AA42: 1276.7 | AB42: 1276.7
A43: 1 | C43: 부채총계 | E43: 28011.92 | F43: 28011.92 | G43: 28154.67 | H43: 27206.71 | I43: 26880.13 | J43: 57514.39 | K43: 57514.39 | L43: 53081.4 | M43: 45524.7 | N43: 46352.56 | O43: 62956.18 | P43: 62956.18 | Q43: 58018.67 | R43: 48674.63 | S43: 46288.92 | T43: 44087.12 | U43: 44087.12 | V43: 38848.74 | W43: 34554.91 | X43: 66414.42 | Y43: 64297.98 | Z43: 64297.98 | AA43: 59947.63 | AB43: 54712.32
A44: 1 | C44: 지배주주지분 | E44: 102681 | F44: 102681 | G44: 102498.21 | H44: 103974.41 | I44: 107499.26 | J44: 114895.13 | K44: 114895.13 | L44: 116648.12 | M44: 117346.89 | N44: 121972.64 | O44: 173702.37 | P44: 173702.37 | Q44: 175765.51 | R44: 172266.95 | S44: 169912.93 | T44: 173414.28 | U44: 173414.28 | V44: 169978.44 | W44: 161111.1 | X44: 161101.48 | Y44: 162396.44 | Z44: 162396.44 | AA44: 161350.33 | AB44: 168560.1
A45: 1 | C45: 자본금 | E45: 123528.57 | F45: 123528.57 | G45: 123528.57 | H45: 123528.57 | I45: 123528.57 | J45: 123528.57 | K45: 123528.57 | L45: 123528.57 | M45: 123528.57 | N45: 123528.57 | O45: 123528.57 | P45: 123528.57 | Q45: 123528.57 | R45: 123528.57 | S45: 123528.57 | T45: 123528.57 | U45: 123528.57 | V45: 123528.57 | W45: 123528.57 | X45: 123528.57 | Y45: 123528.57 | Z45: 123528.57 | AA45: 123528.57 | AB45: 123528.56
A46: 1 | C46: 이익잉여금 | E46: -37093.12 | F46: -37093.12 | G46: -38106.85 | H46: -37103.7 | I46: -34451.68 | J46: -29935.3 | K46: -29935.3 | L46: -28386.09 | M46: -33038.79 | N46: -27852.41 | O46: 23982.93 | P46: 23982.93 | Q46: 25853.12 | R46: 22151.05 | S46: 20129.91 | T46: 23108.3 | U46: 23108.3 | V46: 15889.2 | W46: 13232.67 | X46: 10454.11 | Y46: 11608.47 | Z46: 11608.47 | AA46: 13712.12 | AB46: 12956.67
A47: 1 | C47: 기타자본 | E47: 16245.56 | F47: 16245.56 | G47: 17076.5 | H47: 17549.54 | I47: 18422.38 | J47: 21301.86 | K47: 21301.86 | L47: 21505.65 | M47: 26857.11 | N47: 26296.49 | O47: 26190.87 | P47: 26190.87 | Q47: 26383.83 | R47: 26587.34 | S47: 26254.45 | T47: 26777.41 | U47: 26777.41 | V47: 30560.67 | W47: 24349.87 | X47: 27118.8 | Y47: 27259.41 | Z47: 27259.41 | AA47: 24109.64 | AB47: 32074.87
A48: 1 | C48: 비지배주주지분 | E48: 33.6 | F48: 33.6 | G48: 34.3 | H48: 36.62 | I48: 40.64 | J48: 13336.42 | K48: 13336.42 | L48: 13972.88 | M48: 14032.18 | N48: 11617.76 | O48: 11007.54 | P48: 11007.54 | Q48: 11318.43 | R48: 10894.39 | S48: 10209.15 | T48: 9642.3 | U48: 9642.3 | V48: 9141.65 | W48: 10118.03 | X48: 3805.5 | Y48: 3852.81 | Z48: 3852.81 | AA48: 7494.88 | AB48: 3933.55
A49: 1 | C49: 자본총계 | E49: 102714.61 | F49: 102714.61 | G49: 102532.51 | H49: 104011.03 | I49: 107539.91 | J49: 128231.54 | K49: 128231.54 | L49: 130621.01 | M49: 131379.07 | N49: 133590.4 | O49: 184709.91 | P49: 184709.91 | Q49: 187083.94 | R49: 183161.34 | S49: 180122.08 | T49: 183056.58 | U49: 183056.58 | V49: 179120.09 | W49: 171229.13 | X49: 164906.98 | Y49: 166249.25 | Z49: 166249.25 | AA49: 168845.21 | AB49: 172493.65
A50: 1 | C50: 부채와자본총계 | E50: 130726.53 | F50: 130726.53 | G50: 130687.18 | H50: 131217.75 | I50: 134420.03 | J50: 185745.93 | K50: 185745.93 | L50: 183702.4 | M50: 176903.77 | N50: 179942.96 | O50: 247666.09 | P50: 247666.09 | Q50: 245102.6 | R50: 231835.97 | S50: 226411 | T50: 227143.69 | U50: 227143.69 | V50: 217968.84 | W50: 205784.04 | X50: 231321.4 | Y50: 230547.23 | Z50: 230547.23 | AA50: 228792.84 | AB50: 227205.97
A51: 1 | C51: 총차입금 | E51: 10066.44 | F51: 10066.44 | G51: 10385.18 | H51: 10721.69 | I51: 10563.45 | J51: 19152.14 | K51: 19152.14 | L51: 14344.39 | M51: 7498.54 | N51: 7265.85 | O51: 7525.93 | P51: 7525.93 | Q51: 7634.55 | R51: 8255.08 | S51: 8034.91 | T51: 5005.95 | U51: 5005.95 | V51: 3893.72 | W51: 122.04 | X51: 16492.63 | Y51: 15731.5 | Z51: 15731.5 | AA51: 15446 | AB51: 17160.13
A52: 1 | C52: 순차입금 | E52: -41411.25 | F52: -41411.25 | G52: -20421.06 | H52: -19300.56 | I52: -11147.21 | J52: -10549.01 | K52: -10549.01 | L52: -14451.57 | M52: -19560.11 | N52: -20082.25 | O52: -17242.67 | P52: -17242.67 | Q52: -17136.77 | R52: -13810.78 | S52: -16216.03 | T52: -23759.07 | U52: -23759.07 | V52: -28347.61 | W52: -29329.5 | X52: -33876.98 | Y52: -32637.47 | Z52: -32637.47 | AA52: -39141.23 | AB52: -59804.46
A53: 1 | C53: 이자발생자산 | E53: 63697.88 | F53: 63697.88 | G53: 46038.03 | H53: 44503.67 | I53: 36192.08 | J53: 31945.99 | K53: 31945.99 | L53: 30040.8 | M53: 27704.49 | N53: 27993.94 | O53: 25413.53 | P53: 25413.53 | Q53: 25416.25 | R53: 22710.79 | S53: 24926.6 | T53: 29409.95 | U53: 29409.95 | V53: 32886.26 | W53: 30096.47 | X53: 51099.04 | Y53: 48844.44 | Z53: 48844.44 | AA53: 55062.7 | AB53: 77440.56
A54: 1 | C54: 기타비유동부채 | O54: 0 | P54: 0 | Q54: 0 | R54: 0 | S54: 0 | T54: 0 | U54: 0 | V54: 0
A55: 1 | C55: 계약자산 | T55: 1857.79 | U55: 1857.79 | V55: 1913.75 | W55: 1133.26 | X55: 1536.88 | Y55: 3140.8 | Z55: 3140.8 | AA55: 4335.54 | AB55: 4743.01
A56: 1 | C56: 계약부채 | T56: 2639.77 | U56: 2639.77 | V56: 1069.23 | W56: 519.91 | X56: 2981.73 | Y56: 4793.79 | Z56: 4793.79 | AA56: 5464.72 | AB56: 886.46
A57: 1 | C57: 장기금융부채(face) | T57: 0 | U57: 0 | V57: 0 | AB57: 0
A58: 1 | C58: 단기금융부채(face) | AA58: 15440 | AB58: 17160.13
A59: 1 | C59: 매출액(수익) | E59: 19224.71 | G59: 15491.23 | H59: 17163.19 | I59: 18451.56 | J59: 25581.91 | K59: 76687.89 | L59: 26304.85 | M59: 24975.49 | N59: 17348.67 | O59: 22906.23 | P59: 91535.24 | Q59: 25528.82 | R59: 25567.91 | S59: 23853.75 | T59: 35986.08 | U59: 110936.56 | V59: 23944.61 | W59: 28559.28 | X59: 28555.64 | Y59: 49042.73 | Z59: 130102.26 | AA59: 31914.33 | AB59: 36792.11
A60: 1 | C60: 매출원가 | E60: 15254.53 | G60: 15211.06 | H60: 16437.47 | I60: 16038.69 | J60: 20418.31 | K60: 68105.53 | L60: 21032.47 | M60: 19934.73 | N60: 15672.11 | O60: 21567.92 | P60: 78207.23 | Q60: 21796.99 | R60: 24017.89 | S60: 21720.64 | T60: 32519.44 | U60: 100054.96 | V60: 21630.58 | W60: 24662.64 | X60: 28374.83 | Y60: 38518.99 | Z60: 113187.04 | AA60: 26192.33 | AB60: 27713.55
A61: 1 | C61: 매출총이익 | E61: 3970.18 | G61: 280.17 | H61: 725.72 | I61: 2412.87 | J61: 5163.6 | K61: 8582.36 | L61: 5272.38 | M61: 5040.76 | N61: 1676.56 | O61: 1338.32 | P61: 13328.02 | Q61: 3731.83 | R61: 1550.02 | S61: 2133.12 | T61: 3466.64 | U61: 10881.61 | V61: 2314.04 | W61: 3896.64 | X61: 180.81 | Y61: 10523.74 | Z61: 16915.23 | AA61: 5722 | AB61: 9078.55
A62: 1 | C62: 판관비 | E62: 1595 | G62: 2002.01 | H62: 2279.99 | I62: 2243.35 | J62: 1186.66 | K62: 7712.01 | L62: 3200.66 | M62: 3244.46 | N62: 3693.7 | O62: 4293.31 | P62: 14432.13 | Q62: 3747.57 | R62: 3580.73 | S62: 3470.77 | T62: 4907.4 | U62: 15706.47 | V62: 3276.31 | W62: 3556.4 | X62: 5203.2 | Y62: 5527.11 | Z62: 17563.02 | AA62: 5187.96 | AB62: 5934.33
A63: 1 | C63: 영업이익 | E63: 2375.18 | G63: -1721.84 | H63: -1554.27 | I63: 169.52 | J63: 3976.93 | K63: 870.34 | L63: 2071.72 | M63: 1796.3 | N63: -2017.14 | O63: -2954.98 | P63: -1104.1 | Q63: -15.74 | R63: -2030.7 | S63: -1337.65 | T63: -1440.77 | U63: -4824.86 | V63: -962.28 | W63: 340.24 | X63: -5022.39 | Y63: 4996.63 | Z63: -647.8 | AA63: 534.04 | AB63: 3144.23
A64: 1 | C64: 기타영업외수익 | E64: 5045.86 | G64: 385.92 | H64: 837.95 | I64: 1915.2 | J64: 7434.34 | K64: 10573.41 | L64: 568.29 | M64: 237.87 | N64: 579.79 | O64: 61744.35 | P64: 63130.3 | Q64: 950.39 | R64: 646.54 | S64: -336.67 | T64: 1648.74 | U64: 2909 | V64: 969.56 | W64: 94.39 | X64: 1775.5 | Y64: -311.2 | Z64: 2528.25 | AA64: 1390.92 | AB64: 1018.51
A65: 1 | C65: 기타영업외비용 | E65: 172.55 | G65: 157.34 | H65: 1293.49 | I65: 541.18 | J65: 4508.34 | K65: 6500.35 | L65: 504.71 | M65: 867.09 | N65: -240.93 | O65: 2079.85 | P65: 3210.72 | Q65: 212.4 | R65: 3640.46 | S65: 1317.38 | T65: 334.03 | U65: 5504.27 | V65: 924.73 | W65: 876.66 | X65: 540.18 | Y65: 3166.07 | Z65: 5507.64 | AA65: 362.32 | AB65: 326.36
A66: 1 | C66: 금융수익 | E66: -1083.74 | G66: 401.4 | H66: 2572.2 | I66: 663.65 | J66: 1044.22 | K66: 4681.47 | L66: 1035.17 | M66: 912.55 | N66: 439.35 | O66: 271.8 | P66: 2658.87 | Q66: 1850.23 | R66: 965.89 | S66: 1023.12 | T66: 1544.15 | U66: 5383.39 | V66: 947.93 | W66: 612.56 | X66: 399.19 | Y66: 598.17 | Z66: 2557.85 | AA66: 1597 | AB66: 854.61
A67: 1 | C67: 금융비용 | E67: -1779.84 | G67: 365.3 | H67: 349.19 | I67: 364.69 | J67: 1021.69 | K67: 2100.87 | L67: 1690.15 | M67: 773.95 | N67: 403.82 | O67: 874.71 | P67: 3742.63 | Q67: 398.57 | R67: 520.67 | S67: 753.59 | T67: 588.52 | U67: 2261.35 | V67: 394.9 | W67: 1834.6 | X67: -529.36 | Y67: 721.44 | Z67: 2421.58 | AA67: 237.95 | AB67: 365.4
A68: 1 | C68: 종속기업,공동지배기업및관계기업관련손익 | E68: 269.86 | G68: 443.4 | H68: 790.56 | I68: 809.52 | J68: 941.18 | K68: 2984.66 | L68: 760.14 | M68: 0 | N68: 5949.15 | O68: -1075.67 | P68: 5633.62 | Q68: 0 | R68: 0 | S68: 0 | T68: 0 | U68: 0 | V68: 0 | W68: 2.5 | X68: 3.01 | Y68: -7.24 | Z68: -1.73 | AA68: 0 | AB68: 0
A69: 1 | C69: 지분법관련손익 | E69: 269.86 | G69: 443.4 | H69: 790.56 | I69: 809.52 | J69: 941.18 | K69: 2984.66 | L69: 760.14 | M69: 0 | N69: 5949.15 | O69: -1075.67 | P69: 5633.62 | Q69: 0 | R69: 0 | S69: 0 | T69: 0 | U69: 0 | V69: 0 | W69: 2.5 | X69: 3.01 | Y69: -7.24 | Z69: -1.73 | AA69: 0 | AB69: 0
A70: 1 | C70: 법인세비용차감전계속사업이익 | E70: 8210.5 | G70: -1013.75 | H70: 1003.77 | I70: 2652.03 | J70: 7866.66 | K70: 10508.71 | L70: 2240.44 | M70: 865.18 | N70: 4784.8 | O70: 55474.89 | P70: 63365.31 | Q70: 2158.86 | R70: -4582.63 | S70: -2724.99 | T70: 834.07 | U70: -4314.69 | V70: -366.15 | W70: -1666.57 | X70: -2861.52 | Y70: 1392.5 | Z70: -3501.74 | AA70: 2921.69 | AB70: 4325.6
... A72: 1 | C72: 계속사업이익 | E72: 8210.49 | G72: -1013.75 | H72: 1003.15 | I72: 2652.02 | J72: 8040.04 | K72: 10681.46 | L72: 2184.63 | M72: 926.03 | N72: 4820.64 | O72: 51224.96 | P72: 59156.26 | Q72: 2179.45 | R72: -4127.31 | S72: -2704.41 | T72: 2407.27 | U72: -2245 | V72: -356.4 | W72: -1677.04 | X72: -2861.51 | Y72: 1200.75 | Z72: -3694.2 | AA72: 2917.59 | AB72: 3552.45
A73: 1 | C73: 중단사업이익 | E73: 0 | G73: 0 | H73: 0 | I73: 0 | J73: 0 | K73: 0 | L73: 0 | M73: 0 | N73: 0 | O73: 0 | P73: 0 | Q73: 0 | R73: 0 | S73: 0 | T73: 0 | U73: 0 | V73: 0 | W73: 0 | X73: 0
A74: 1 | C74: 당기순이익 | E74: 8210.49 | G74: -1013.75 | H74: 1003.15 | I74: 2652.02 | J74: 8040.04 | K74: 10681.46 | L74: 2184.63 | M74: 926.03 | N74: 4820.64 | O74: 51224.96 | P74: 59156.26 | Q74: 2179.45 | R74: -4127.31 | S74: -2704.41 | T74: 2407.27 | U74: -2245 | V74: -356.4 | W74: -1677.04 | X74: -2861.51 | Y74: 1200.75 | Z74: -3694.2 | AA74: 2917.59 | AB74: 3552.45
A75: 1 | C75: (지배주주지분)당기순이익 | E75: 8210.5 | G75: -1013.73 | H75: 1003.15 | I75: 2652.02 | J75: 8070.63 | K75: 10712.07 | L75: 1549.2 | M75: 866.98 | N75: 5186.37 | O75: 51835.34 | P75: 59437.89 | Q75: 1870.19 | R75: -3702.07 | S75: -2021.14 | T75: 2978.4 | U75: -874.62 | V75: 144.15 | W75: -2656.54 | X75: -2778.56 | Y75: 1154.36 | Z75: -4136.59 | AA75: 2798.47 | AB75: 3593.82
A76: 1 | C76: (비지배주주지분)당기순이익 | E76: 0 | G76: -0.02 | H76: 0 | I76: 0 | J76: -30.6 | K76: -30.62 | L76: 635.43 | M76: 59.04 | N76: -365.73 | O76: -610.37 | P76: -281.63 | Q76: 309.25 | R76: -425.24 | S76: -683.27 | T76: -571.12 | U76: -1370.38 | V76: -500.55 | W76: 979.5 | X76: -82.95 | Y76: 46.39 | Z76: 442.39 | AA76: 119.12 | AB76: -41.37
A77: 1 | C77: 총포괄손익 | E77: 9546.47 | G77: -182.1 | H77: 1478.52 | I77: 3528.87 | J77: 7360.52 | K77: 12185.81 | L77: 2389.46 | M77: 758.06 | N77: 5034.99 | O77: 51119.51 | P77: 59302.02 | Q77: 2374.03 | R77: -3922.59 | S77: -3039.26 | T77: 3130.89 | U77: -1456.93 | V77: -349.57 | W77: -2204.08 | X77: -2643.16 | Y77: 1356.95 | Z77: -3839.86 | AA77: 3290.77 | AB77: 3684.33
A78: 1 | C78: 금융손익 | E78: 696.1 | G78: 36.1 | H78: 2223.01 | I78: 298.96 | J78: 22.53 | K78: 2580.6 | L78: -654.98 | M78: 138.6 | N78: 35.53 | O78: -602.91 | P78: -1083.76 | Q78: 1451.66 | R78: 445.22 | S78: 269.53 | T78: 955.63 | U78: 3122.04 | V78: 553.03 | W78: -1222.04 | X78: 928.55 | Y78: -123.27 | Z78: 136.27 | AA78: 1359.05 | AB78: 489.21
A79: 1 | C79: 기타영업외손익 | E79: 4873.31 | G79: 228.58 | H79: -455.54 | I79: 1374.02 | J79: 2926 | K79: 4073.06 | L79: 63.58 | M79: -629.22 | N79: 820.72 | O79: 59664.5 | P79: 59919.58 | Q79: 737.99 | R79: -2993.92 | S79: -1654.05 | T79: 1314.71 | U79: -2595.27 | V79: 44.83 | W79: -782.27 | X79: 1235.32 | Y79: -3477.27 | Z79: -2979.39 | AA79: 1028.6 | AB79: 692.15
A80: 1 | C80: 영업활동으로인한현금흐름 | E80: -1873.83 | G80: 144.41 | H80: -2745.59 | I80: 1145.72 | J80: -1573.83 | K80: -3029.29 | L80: 5092.62 | M80: 3005.68 | N80: 995.21 | O80: 2911.17 | P80: 12004.68 | Q80: 271.18 | R80: -6547.03 | S80: -2058.29 | T80: -343.65 | U80: -8677.79 | V80: -11926.44 | W80: 1160.69 | X80: 771.46 | Y80: 4114.85 | Z80: -5879.44 | AA80: 6687.76 | AB80: 2504.78
A81: 1 | C81: 법인세납부(CF) | E81: -9.46 | G81: -19.14 | H81: 8.09 | I81: -38.25 | J81: -87.15 | K81: -136.45 | L81: -177.44 | M81: 63.18 | N81: -41.21 | O81: -53.75 | P81: -209.22 | Q81: -98.88 | R81: -4464.94 | S81: -297.3 | T81: -37.92 | U81: -4899.04 | V81: -300.35 | W81: 446.48 | X81: -161.11 | Y81: -13.01 | Z81: -27.99 | AA81: -230.78 | AB81: 449.1
A82: 1 | C82: 투자활동으로인한현금흐름 | E82: 22715.38 | G82: -20925.56 | H82: 1495.66 | I82: -9705.52 | J82: 12048.26 | K82: -17087.16 | L82: -829.19 | M82: 3383.22 | N82: 1221.23 | O82: -4318.93 | P82: -543.67 | Q82: -551.09 | R82: 3195.59 | S82: 4947.66 | T82: 7690.25 | U82: 15282.41 | V82: 19352.48 | W82: 7112.81 | X82: 19336.64 | Y82: -6847.75 | Z82: 38954.18 | AA82: -1260.61 | AB82: 18944.91
A83: 1 | C83: 유형자산의감소 | E83: 17596.91 | G83: 0 | H83: 0.45 | I83: 43.91 | J83: 5382.72 | K83: 5427.08 | L83: 0 | M83: 0 | N83: 13.22 | O83: 38.25 | P83: 51.47 | Q83: 1.82 | R83: 1.35 | S83: 0 | T83: 0 | U83: 3.17 | V83: 6.2 | W83: 0 | X83: 20.71 | Y83: 113 | Z83: 139.91 | AA83: 0 | AB83: 0
A84: 1 | C84: 무형자산의감소 | E84: 0 | G84: 0 | H84: 0 | I84: 0 | J84: 0 | K84: 0 | L84: 0 | M84: 0 | N84: 0 | O84: 0 | P84: 0 | Q84: 0 | R84: 0 | S84: 0 | T84: 0 | U84: 0 | V84: 0
A85: 1 | C85: 유형자산의증가 | E85: 1945.15 | G85: 2915.89 | H85: 1933.64 | I85: 1048.48 | L85: 249.24 | M85: 479.22 | N85: 197.28 | O85: 679.53 | P85: 1605.27 | Q85: 1950.74 | R85: 872.52 | S85: 173.1 | T85: 833.91 | U85: 3830.27 | V85: 49.58 | W85: 1122.13 | X85: 6563.51 | Y85: 7086.02 | Z85: 14821.24 | AA85: 1351.11 | AB85: 1127.28
A86: 1 | C86: CAPEX | E86: 1945.15 | G86: 2915.89 | H86: 1933.64 | I86: 1048.48 | J86: 0 | K86: 5898.01 | L86: 249.24 | M86: 499.22 | N86: 274.08 | O86: 680.26 | P86: 1702.8 | Q86: 1950.74 | R86: 902.52 | S86: 173.14 | T86: 870.14 | U86: 3896.54 | V86: 49.58 | W86: 1122.13 | X86: 6564.39 | Y86: 7085.14 | Z86: 14821.24 | AA86: 1351.11 | AB86: 1141.66
A87: 1 | C87: 무형자산의증가 | E87: 0 | G87: 0 | H87: 0 | I87: 0 | J87: 0 | K87: 0 | L87: 0 | M87: 20 | N87: 76.8 | O87: 0.73 | P87: 97.53 | Q87: 0 | R87: 30 | S87: 0.04 | T87: 36.23 | U87: 66.27 | V87: 0 | W87: 0 | X87: 0.88 | AA87: 0 | AB87: 14.38
A88: 1 | C88: 재무활동으로인한현금흐름 | E88: -10.21 | G88: 0 | H88: 0 | I88: -504.5 | J88: -849.11 | K88: -1353.61 | L88: -5345.24 | M88: -8173.93 | N88: -2115.25 | O88: -847.27 | P88: -16481.69 | Q88: -76.37 | R88: 486.26 | S88: -287.27 | T88: -3718.38 | U88: -3595.76 | V88: -4040.89 | W88: -10343.2 | X88: 352.23 | Y88: -918.55 | Z88: -14950.41 | AA88: -522.11 | AB88: 410.04
A89: 1 | C89: 단기차입금의증가 | E89: 0 | G89: 0 | H89: 0 | I89: 0 | J89: 0 | K89: 0 | L89: 4421.76 | M89: 8383 | N89: 2266.6 | Q89: 2876.09 | R89: 4242.55 | S89: 3842.13 | T89: 4144.42 | U89: 15105.19 | V89: 3230.66 | W89: 3711.25 | X89: 2388.06 | Y89: 0 | Z89: 9329.97 | AA89: 0 | AB89: 1540
A90: 1 | C90: 장기차입금의증가 | E90: 0 | G90: 0 | H90: 0 | I90: 0 | J90: 0 | K90: 0 | L90: 0 | M90: 0 | N90: 0 | O90: 0 | P90: 0 | Q90: 0 | R90: 0 | S90: 0 | T90: 0 | U90: 0 | V90: 0
A91: 1 | C91: 단기차입금의감소 | E91: 0 | G91: 0 | H91: 0 | I91: 0 | J91: 817.18 | K91: 817.18 | L91: 5398.68 | M91: 9226.41 | N91: 1428.57 | Q91: 2767.47 | R91: 3660.73 | S91: 3964.82 | T91: 2521.71 | U91: 12914.73 | V91: 4372.35 | W91: 7453.48 | X91: 1953.98 | Y91: 748.12 | Z91: 14527.93 | AA91: 285.5 | AB91: 123
A92: 1 | C92: 유동성장기부채의감소 | E92: 0 | G92: 0 | H92: 0 | I92: 0 | J92: 0 | K92: 0 | L92: 0 | M92: 0 | N92: 0 | O92: 0 | P92: 0 | Q92: 0 | R92: 0 | S92: 0 | T92: 0 | U92: 0 | V92: 0
A93: 1 | C93: 리스부채의상환 | E93: 10.21 | G93: 0 | H93: 0 | I93: 0 | J93: 0 | K93: 0 | L93: 134.72 | M93: 101.88 | N93: 129.61 | O93: 953.7 | P93: 1319.91 | Q93: 192.99 | R93: 117.55 | S93: 154.6 | T93: 154.69 | U93: 619.83 | V93: 98.59 | W93: 127.79 | X93: 81.84 | Y93: 205.76 | Z93: 513.98 | AA93: 236.61 | AB93: 236.26
A94: 1 | C94: 장기차입금의감소 | E94: 0 | G94: 0 | H94: 0 | I94: 0 | J94: 0 | K94: 0 | L94: 0 | M94: 0 | N94: 0 | O94: 0 | P94: 0 | Q94: 0 | R94: 0 | S94: 0 | T94: 5000 | U94: 5000 | V94: 0 | AA94: 0 | AB94: 0
A95: 1 | C95: 현금및현금성자산의증감 | E95: 41462.56 | G95: -41452.6 | H95: -2033.92 | I95: -17375.89 | J95: 17615.8 | K95: -43246.61 | L95: -1987 | M95: -3522.34 | N95: 390.62 | O95: -4834.51 | P95: -9953.23 | Q95: -353.57 | R95: -5570.62 | S95: 4787.17 | T95: 8142.29 | U95: 7005.27 | V95: 6861.46 | W95: -4859.49 | X95: 41378.41 | Y95: -5652.1 | Z95: 37728.28 | AA95: 11123.3 | AB95: 44237.09
A96: 1 | C96: 기말현금및현금성자산 | E96: 20631.21 | G96: 30806.24 | H96: -783.99 | I96: -8311.59 | J96: 7990.49 | K96: 29701.15 | L96: 28795.96 | M96: -1737.31 | N96: 289.45 | O96: -2579.5 | P96: 24768.6 | Q96: 24771.32 | R96: -2705.46 | S96: 2185.08 | T96: 4514.08 | U96: 28765.02 | V96: 32241.33 | W96: -2789.79 | X96: 20918.07 | Y96: -2000.64 | Z96: 48368.97 | AA96: 54587.23 | AB96: 22377.36
A97: 1 | C97: 이자수취(CF) | O97: 406.72 | Q97: 336.85 | R97: 587.32 | S97: 1932.03 | T97: 242.14 | U97: 3098.34 | V97: 1815.32 | W97: 274.31 | X97: 1044.55 | Y97: 149.83 | Z97: 3284.01 | AA97: 348.45 | AB97: 225.59
A98: 1 | C98: 자기주식의취득 | V98: 2800.61 | W98: 5686.88 | X98: 0 | Y98: 14.67 | Z98: 8502.16 | AA98: 0 | AB98: 35.89
A99: 1 | C99: 배당금지급 | X99: 0 | Y99: 0 | AA99: 0 | AB99: 694.81

Sheet BS별도
B1: (백만원) | C1: 이름: BS별도H | E1: 4Q21 | F1: 2021 | G1: 1Q22 | H1: 2Q22 | I1: 3Q22 | J1: 4Q22 | K1: 2022 | L1: 1Q23 | M1: 2Q23 | N1: 3Q23 | O1: 4Q23 | P1: 2023 | Q1: 1Q24 | R1: 2Q24 | S1: 3Q24 | T1: 4Q24 | U1: 2024 | V1: 1Q25 | W1: 2Q25 | X1: 3Q25 | Y1: 4Q25 | Z1: 2025 | AA1: 1Q26 | AB1: 2Q26 | AC1: 3Q26 | AD1: 4Q26 | AE1: 2026 | AF1: 1Q27 | AG1: 2Q27 | AH1: 3Q27 | AI1: 4Q27 | AJ1: 2027 | AK1: 1Q28 | AL1: 2Q28 | AM1: 3Q28 | AN1: 4Q28 | AO1: 2028
B2: 별도 | D2: fin json(kship_fin.py)
B3: 엔케이(별) | C3: UPDATE: 26-10-11 | E3: 1 | F3: 2 | G3: 3 | H3: 4 | I3: 5 | J3: 6 | K3: 7 | L3: 8 | M3: 9 | N3: 10 | O3: 11 | P3: 12 | Q3: 13 | R3: 14 | S3: 15 | T3: 16 | U3: 17 | V3: 18 | W3: 19 | X3: 20 | Y3: 21 | Z3: 22 | AA3: 23 | AB3: 24 | AC3: 25 | AD3: 26 | AE3: 27 | AF3: 28 | AG3: 29 | AH3: 30 | AI3: 31 | AJ3: 32 | AK3: 33 | AL3: 34 | AM3: 35 | AN3: 36 | AO3: 37
B4: Account Code | C4: AccountNAME | E4: 2021.12 | F4: 2021.12A | G4: 2022.03 | H4: 2022.06 | I4: 2022.09 | J4: 2022.12 | K4: 2022.12A | L4: 2023.03 | M4: 2023.06 | N4: 2023.09 | O4: 2023.12 | P4: 2023.12A | Q4: 2024.03 | R4: 2024.06 | S4: 2024.09 | T4: 2024.12 | U4: 2024.12A | V4: 2025.03 | W4: 2025.06 | X4: 2025.09 | Y4: 2025.12 | Z4: 2025.12A | AA4: 2026.03 | AB4: 2026.06 | AC4: 2026.09 | AD4: 2026.12 | AE4: 2026.12A | AF4: 2027.03 | AG4: 2027.06 | AH4: 2027.09 | AI4: 2027.12 | AJ4: 2027.12A | AK4: 2028.03 | AL4: 2028.06 | AM4: 2028.09 | AN4: 2028.12 | AO4: 2028.12A
A5: 1 | C5: 유동자산 | E5: 65566.7 | F5: 65566.7 | G5: 58061.8 | H5: 56092.85 | I5: 61653.85 | J5: 64525.92 | K5: 64525.92 | L5: 60619.77 | M5: 54225.72 | N5: 50780.97 | O5: 143601.76 | P5: 143601.76 | Q5: 140981.67 | R5: 139146.41 | S5: 136032.54 | T5: 136865.88 | U5: 136865.88 | V5: 130801.12 | W5: 100569.74 | X5: 79177.08 | Y5: 72833.22 | Z5: 72833.22 | AA5: 71039.31 | AB5: 75630.07
A6: 1 | C6: 현금및현금성자산 | E6: 45391.44 | F6: 45391.44 | G6: 24587.41 | H6: 23393.87 | I6: 14350.98 | J6: 19363.79 | K6: 19363.79 | L6: 17881.11 | M6: 14744.16 | N6: 11982.17 | O6: 10792.67 | P6: 10792.67 | Q6: 6039.45 | R6: 4140.99 | S6: 5998.83 | T6: 10292.83 | U6: 10292.83 | V6: 14756.4 | W6: 6412.75 | X6: 25044.62 | Y6: 25060.54 | Z6: 25060.54 | AA6: 26799.93 | AB6: 54894.2
A7: 1 | C7: 기타유동금융자산 | E7: 7887.37 | F7: 7887.37 | G7: 22709.38 | H7: 19709.38 | I7: 27659.39 | J7: 24833.6 | K7: 24833.6 | L7: 26226.8 | M7: 23262.8 | N7: 21379.2 | O7: 109157.6 | P7: 109157.6 | Q7: 108387.2 | R7: 108556.8 | S7: 103278.4 | T7: 98880 | U7: 98880 | V7: 79732 | W7: 60851.2 | X7: 20000 | Y7: 20000 | Z7: 20000 | AA7: 20000 | AB7: 0
A8: 1 | C8: 매출채권및기타채권 | E8: 10301.78 | F8: 10301.78 | G8: 8780.11 | H8: 11273.63 | I8: 16507.26 | J8: 14007.41 | K8: 14007.41 | L8: 14275.54 | M8: 13706.06 | N8: 13512.04 | O8: 12083.1 | P8: 12083.1 | Q8: 14827.28 | R8: 14369.05 | S8: 12758.09 | T8: 14752.08 | U8: 14752.08 | V8: 12942.06 | W8: 20081.87 | X8: 18544.05 | Y8: 19473.09 | Z8: 19473.09 | AA8: 14875.38 | AB8: 12513.45
A9: 1 | C9: 기타유동자산 | E9: 116.57 | F9: 116.57 | G9: 395.35 | H9: 261.86 | I9: 1240.54 | J9: 561.63 | K9: 561.63 | L9: 372.09 | M9: 819.55 | N9: 2251.58 | O9: 3045.64 | P9: 3045.64 | Q9: 3582.36 | R9: 5544.74 | S9: 5060.28 | T9: 4758.32 | U9: 4758.32 | V9: 13085.14 | W9: 3847.35 | X9: 4873.19 | Y9: 3192.83 | Z9: 3192.83 | AA9: 3777.35 | AB9: 3712.77
A10: 1 | C10: 당기법인세자산(선급법인세) | E10: 36.45 | F10: 36.45 | G10: 55.59 | H10: 46.89 | I10: 85.12 | J10: 129.57 | K10: 129.57 | L10: 250.44 | M10: 170.36 | N10: 210.73 | O10: 0 | P10: 0 | Q10: 49.4 | R10: 106.18 | S10: 401.01 | T10: 437.55 | U10: 437.55 | V10: 689.93 | W10: 291.49 | X10: 451.4 | Y10: 464.06 | Z10: 464.06 | AA10: 513.92 | AB10: 0
A11: 1 | C11: 재고자산 | E11: 1833.08 | F11: 1833.08 | G11: 1533.96 | H11: 1407.23 | I11: 1810.57 | J11: 2052.43 | K11: 2052.43 | L11: 1613.79 | M11: 1522.78 | N11: 1445.26 | O11: 8522.76 | P11: 8522.76 | Q11: 8095.98 | R11: 6428.65 | S11: 8535.92 | T11: 5887.29 | U11: 5887.29 | V11: 7681.84 | W11: 7951.82 | X11: 9130.56 | Y11: 3249.86 | Z11: 3249.86 | AA11: 3679.91 | AB11: 3116.82
A12: 1 | C12: 유동파생상품자산 | E12: 0 | F12: 0 | G12: 0 | H12: 0 | I12: 0 | J12: 0 | K12: 0 | L12: 0 | M12: 0 | N12: 0 | O12: 0 | P12: 0 | Q12: 0 | R12: 0 | S12: 0 | T12: 0 | U12: 0 | V12: 0
A13: 1 | C13: 단기금융자산 | E13: 0 | F13: 0 | G13: 0 | H13: 0 | I13: 0 | J13: 0 | K13: 0 | L13: 0 | M13: 0 | N13: 0 | O13: 0 | P13: 0 | Q13: 0 | R13: 0 | S13: 0 | T13: 0 | U13: 0 | V13: 0
A14: 1 | C14: 매각예정비유동자산및처분자산 | E14: 0 | F14: 0 | G14: 0 | H14: 0 | I14: 0 | J14: 3577.49 | K14: 3577.49 | L14: 0 | M14: 0 | N14: 0 | O14: 0 | P14: 0 | Q14: 0 | R14: 0 | S14: 0 | T14: 0 | U14: 0 | V14: 0
A15: 1 | C15: 비유동자산 | E15: 61435.85 | F15: 61435.85 | G15: 67617.44 | H15: 68826.76 | I15: 64698.62 | J15: 65851.86 | K15: 65851.86 | L15: 65182.82 | M15: 64756.09 | N15: 67818.82 | O15: 57484.07 | P15: 57484.07 | Q15: 57898.94 | R15: 58621.16 | S15: 58802.69 | T15: 60884.75 | U15: 60884.75 | V15: 60475.12 | W15: 81147.23 | X15: 103407.05 | Y15: 106726.67 | Z15: 106726.67 | AA15: 106931.04 | AB15: 101975.88
A16: 1 | C16: 장기금융자산 | E16: 12220.19 | F16: 12220.19 | G16: 15231.79 | H16: 14481.42 | I16: 14481.42 | J16: 12537.04 | K16: 12537.04 | L16: 11537.04 | M16: 10938.04 | N16: 10938.04 | O16: 12186.72 | P16: 12186.72 | Q16: 12186.72 | R16: 12186.72 | S16: 12186.72 | T16: 13991.7 | U16: 13991.7 | V16: 13991.7 | W16: 13991.7 | X16: 13991.7 | Y16: 13837.67 | Z16: 13837.67 | AA16: 13837.67 | AB16: 8697.39
A17: 1 | C17: 투자자산 | E17: 30330.09 | F17: 30330.09 | G17: 33337.17 | H17: 32569.16 | I17: 32522.71 | J17: 36534 | K17: 36534 | L17: 35722.67 | M17: 34924.47 | N17: 37699.74 | O17: 28127.07 | P17: 28127.07 | Q17: 28127.07 | R17: 28090.97 | S17: 28091.04 | T17: 29895.02 | U17: 29895.02 | V17: 29894.06 | W17: 42689.93 | X17: 69198.94 | Y17: 67997.48 | Z17: 67997.48 | AA17: 67997.48 | AB17: 8697.39
A18: 1 | C18: 종속기업및관계기업투자 | E18: 18109.9 | F18: 18109.9 | G18: 18105.38 | H18: 18087.74 | I18: 18041.29 | J18: 23996.96 | K18: 23996.96 | L18: 24185.63 | M18: 23986.43 | N18: 26761.7 | O18: 15940.35 | P18: 15940.35 | Q18: 15940.35 | R18: 15904.25 | S18: 15904.32 | T18: 15903.32 | U18: 15903.32 | V18: 15902.36 | W18: 28698.23 | X18: 55207.24 | Y18: 54159.81 | Z18: 54159.81 | AA18: 54159.81
A19: 1 | C19: 장기매출채권및기타채권 | E19: 0 | F19: 0 | G19: 0 | H19: 0 | I19: 0 | J19: 0 | K19: 0 | L19: 0 | M19: 0 | N19: 0 | O19: 0 | P19: 0 | Q19: 0 | R19: 0
A20: 1 | C20: 유형자산 | E20: 21207.61 | F20: 21207.61 | G20: 23823.24 | H20: 25403.95 | I20: 21290.72 | J20: 16195.17 | K20: 16195.17 | L20: 16159.38 | M20: 16560.33 | N20: 16413.72 | O20: 16925.15 | P20: 16925.15 | Q20: 17548.83 | R20: 18434.13 | S20: 18375.37 | T20: 18772.98 | U20: 18772.98 | V20: 18633.81 | W20: 17112.69 | X20: 21680.86 | Y20: 26386.49 | Z20: 26386.49 | AA20: 26709.65 | AB20: 27022.1
A21: 1 | C21: 사용권자산 | E21: 96.25 | F21: 96.25 | G21: 92.5 | H21: 88.75 | I21: 85 | J21: 81.25 | K21: 81.25 | L21: 77.5 | M21: 73.75 | N21: 70 | O21: 425.47 | P21: 425.47 | Q21: 340.26 | R21: 235.93 | S21: 491.61 | T21: 387.29 | U21: 387.29 | V21: 132.97 | W21: 118.64 | X21: 104.32 | Y21: 707.32 | Z21: 707.32 | AA21: 604.8 | AB21: 502.29
A22: 1 | C22: 기타비유동자산 | E22: 96.25 | F22: 96.25 | G22: 92.5 | H22: 88.75 | I22: 85 | J22: 81.25 | K22: 81.25 | L22: 77.5 | M22: 73.75 | N22: 70 | O22: 425.47 | P22: 425.47 | Q22: 340.26 | R22: 235.93 | S22: 491.61 | T22: 387.29 | U22: 387.29 | V22: 132.97 | W22: 8918.64 | X22: 104.32 | Y22: 707.32 | Z22: 707.32 | AA22: 604.8 | AB22: 502.29
A23: 1 | C23: 무형자산 | E23: 47.03 | F23: 47.03 | G23: 47.03 | H23: 47.03 | I23: 47.03 | J23: 47.03 | K23: 47.03 | L23: 47.03 | M23: 47.03 | N23: 47.03 | O23: 47.03 | P23: 47.03 | Q23: 47.03 | R23: 47.03 | S23: 47.03 | T23: 47.03 | U23: 47.03 | V23: 47.03 | W23: 47.03 | X23: 47.91 | Y23: 47.03 | Z23: 47.03 | AA23: 47.03 | AB23: 47.03
A24: 1 | C24: 투자부동산 | E24: 8962.2 | F24: 8962.2 | G24: 8949.12 | H24: 8936.04 | I24: 9977.22 | J24: 11476.04 | K24: 11476.04 | L24: 11527 | M24: 11501.27 | N24: 11889.08 | O24: 11388.38 | P24: 11388.38 | Q24: 11362.21 | R24: 11336.04 | S24: 11309.87 | T24: 11283.71 | U24: 11283.71 | V24: 11257.54 | W24: 11857.84 | X24: 11842.15 | Y24: 11179.03 | Z24: 11179.03 | AA24: 11152.86 | AB24: 11126.7
A25: 1 | C25: 이연법인세자산 | E25: 0 | F25: 0 | G25: 0 | H25: 0 | I25: 0 | J25: 0 | K25: 0 | L25: 0 | M25: 0 | N25: 0 | O25: 0 | P25: 0 | Q25: 0 | R25: 0 | S25: 0 | T25: 0 | U25: 0 | V25: 0
A26: 1 | C26: 자산총계 | E26: 127002.55 | F26: 127002.55 | G26: 125679.24 | H26: 124919.61 | I26: 126352.47 | J26: 130377.79 | K26: 130377.79 | L26: 125802.59 | M26: 118981.81 | N26: 118599.79 | O26: 201085.83 | P26: 201085.83 | Q26: 198880.61 | R26: 197767.58 | S26: 194835.24 | T26: 197750.63 | U26: 197750.63 | V26: 191276.24 | W26: 181716.97 | X26: 182584.13 | Y26: 179559.89 | Z26: 179559.89 | AA26: 177970.35 | AB26: 177605.94
A27: 1 | C27: 유동부채 | E27: 26434.17 | F27: 26434.17 | G27: 26527.84 | H27: 25684.43 | I27: 25301.97 | J27: 25675.45 | K27: 25675.45 | L27: 20779.9 | M27: 13418.56 | N27: 12704.99 | O27: 28139.98 | P27: 28139.98 | Q27: 24684.31 | R27: 23467.55 | S27: 21861.54 | T27: 23177.72 | U27: 23177.72 | V27: 19721.68 | W27: 19639.27 | X27: 21535.74 | Y27: 21263.41 | Z27: 21263.41 | AA27: 16180.38 | AB27: 13423.8
A28: 1 | C28: 기타유동부채 | E28: 0 | F28: 0 | G28: 0 | H28: 0 | I28: 0 | J28: 0 | K28: 0 | L28: 0 | M28: 0 | N28: 0 | O28: 0 | P28: 0 | Q28: 0 | R28: 0 | S28: 0 | T28: 0 | U28: 0 | V28: 0
A29: 1 | C29: 단기차입금 | E29: 0 | F29: 0 | G29: 0 | H29: 0 | I29: 0 | J29: 0 | K29: 0 | L29: 0 | M29: 0 | N29: 0 | O29: 0 | P29: 0 | Q29: 0 | R29: 0 | S29: 0 | T29: 0 | U29: 0 | V29: 0
A30: 1 | C30: 당기법인세부채(미지급법인세) | E30: 0 | F30: 0 | G30: 0 | H30: 0 | I30: 0 | J30: 0 | K30: 0 | L30: 0 | M30: 0 | N30: 0 | O30: 4159.27 | P30: 4159.27 | Q30: 4159.27 | R30: 0 | S30: 0 | T30: 0 | U30: 0 | V30: 0 | Y30: 0 | Z30: 0 | AA30: 0 | AB30: 684.38
A31: 1 | C31: 유동성장기부채 | E31: 10066.44 | F31: 10066.44 | G31: 10385.18 | H31: 10721.69 | I31: 10563.45 | J31: 10903.99 | K31: 10903.99 | L31: 7073.16 | M31: 0 | N31: 0 | O31: 0 | P31: 0 | Q31: 0 | R31: 0 | S31: 0 | T31: 0 | U31: 0 | V31: 0
A32: 1 | C32: 유동리스부채 | E32: 0 | F32: 0 | G32: 0 | H32: 0 | I32: 0 | J32: 0 | K32: 0 | L32: 0 | M32: 0 | N32: 0 | O32: 240 | P32: 240 | Q32: 150 | R32: 60 | S32: 330 | T32: 240 | U32: 240 | V32: 0 | W32: 0 | X32: 0 | Y32: 319.69 | Z32: 319.69 | AA32: 319.69 | AB32: 334.77
A33: 1 | C33: 리스부채 | E33: 0 | F33: 0 | G33: 0 | H33: 0 | I33: 0 | J33: 0 | K33: 0 | L33: 0 | M33: 0 | N33: 0 | O33: 240 | P33: 240 | Q33: 150 | R33: 60 | S33: 330 | T33: 240 | U33: 240 | V33: 0 | W33: 0 | X33: 0 | Y33: 579.56 | Z33: 579.56 | AA33: 502.38 | AB33: 423.4
A34: 1 | C34: 단기금융부채 | E34: 3091.39 | F34: 3091.39 | G34: 3091.39 | H34: 1092.38 | I34: 1042.72 | J34: 484.27 | K34: 484.27 | L34: 304.4 | M34: 0 | N34: 0 | O34: 240 | P34: 240 | Q34: 150 | R34: 60 | S34: 330 | T34: 240 | U34: 240 | V34: 0 | W34: 0 | X34: 0 | Y34: 319.69 | Z34: 319.69 | AA34: 319.69 | AB34: 334.77
A35: 1 | C35: 단기충당부채 | E35: 1480.71 | F35: 1480.71 | G35: 1480.71 | H35: 2345 | I35: 2345 | J35: 2818.04 | K35: 2818.04 | L35: 2435.61 | M35: 2678.4 | N35: 2586.18 | O35: 1566.35 | P35: 1566.35 | Q35: 1305.06 | R35: 1349.31 | S35: 1389.2 | T35: 1769.37 | U35: 1769.37 | V35: 1336.98 | W35: 1334.68 | X35: 1338.94 | Y35: 1384.34 | Z35: 1384.34 | AA35: 1095.25 | AB35: 1121.27
A36: 1 | C36: 기타유동금융부채 | E36: 0 | F36: 0 | G36: 0 | H36: 0 | I36: 0 | J36: 0 | K36: 0 | L36: 0 | M36: 0 | N36: 0 | O36: 0 | P36: 0 | Q36: 0 | R36: 0 | S36: 0 | T36: 0 | U36: 0 | V36: 0
A37: 1 | C37: 단기파생상품부채 | E37: 3091.39 | F37: 3091.39 | G37: 3091.39 | H37: 1092.38 | I37: 1042.72 | J37: 484.27 | K37: 484.27 | L37: 304.4 | M37: 0 | N37: 0 | O37: 0 | P37: 0 | Q37: 0 | R37: 0 | S37: 0 | T37: 0 | U37: 0 | V37: 0
A38: 1 | C38: 비유동부채 | E38: 1334.65 | F38: 1334.65 | G38: 1368 | H38: 1254.14 | I38: 1255.21 | J38: 898.46 | K38: 898.46 | L38: 901.5 | M38: 719.18 | N38: 651.38 | O38: 689 | P38: 689 | Q38: 689.03 | R38: 617.66 | S38: 618.63 | T38: 619.02 | U38: 619.02 | V38: 619.27 | W38: 619.37 | X38: 627.06 | Y38: 888.84 | Z38: 888.84 | AA38: 811.66 | AB38: 717.6
A39: 1 | C39: 장기차입금 | E39: 0 | F39: 0 | G39: 0 | H39: 0 | I39: 0 | J39: 0 | K39: 0 | L39: 0 | M39: 0 | N39: 0 | O39: 0 | P39: 0 | Q39: 0 | R39: 0 | S39: 0 | T39: 0 | U39: 0 | V39: 0
A40: 1 | C40: 비유동리스부채 | E40: 0 | F40: 0 | G40: 0 | H40: 0 | I40: 0 | J40: 0 | K40: 0 | L40: 0 | M40: 0 | N40: 0 | O40: 0 | P40: 0 | Q40: 0 | R40: 0 | S40: 0 | T40: 0 | U40: 0 | V40: 0 | Y40: 259.87 | Z40: 259.87 | AA40: 182.69 | AB40: 88.63
A41: 1 | C41: 장기금융부채 | E41: 0 | F41: 0 | G41: 0 | H41: 0 | I41: 0 | J41: 0 | K41: 0 | L41: 0 | M41: 0 | N41: 0 | O41: 0 | P41: 0 | Q41: 0 | R41: 0 | S41: 0 | T41: 0 | U41: 0 | V41: 0 | Y41: 259.87 | Z41: 259.87 | AA41: 182.69 | AB41: 88.63
A42: 1 | C42: 사채 | E42: 0 | F42: 0 | G42: 0 | H42: 0 | I42: 0 | J42: 0 | K42: 0 | L42: 0 | M42: 0 | N42: 0 | O42: 0 | P42: 0 | Q42: 0 | R42: 0 | S42: 0 | T42: 0 | U42: 0 | V42: 0
A43: 1 | C43: 이연법인세부채 | E43: 0 | F43: 0 | G43: 0 | H43: 0 | I43: 0 | J43: 0 | K43: 0 | L43: 0 | M43: 0 | N43: 0 | O43: 0 | P43: 0 | Q43: 0 | R43: 0 | S43: 0 | T43: 0 | U43: 0 | V43: 0
A44: 1 | C44: 부채총계 | E44: 27768.82 | F44: 27768.82 | G44: 27895.84 | H44: 26938.57 | I44: 26557.18 | J44: 26573.91 | K44: 26573.91 | L44: 21681.4 | M44: 14137.74 | N44: 13356.37 | O44: 28828.98 | P44: 28828.98 | Q44: 25373.34 | R44: 24085.21 | S44: 22480.16 | T44: 23796.74 | U44: 23796.74 | V44: 20340.95 | W44: 20258.64 | X44: 22162.81 | Y44: 22152.25 | Z44: 22152.25 | AA44: 16992.04 | AB44: 14141.4
A45: 1 | C45: 자본금 | E45: 123528.57 | F45: 123528.57 | G45: 123528.57 | H45: 123528.57 | I45: 123528.57 | J45: 123528.57 | K45: 123528.57 | L45: 123528.57 | M45: 123528.57 | N45: 123528.57 | O45: 123528.57 | P45: 123528.57 | Q45: 123528.57 | R45: 123528.57 | S45: 123528.57 | T45: 123528.57 | U45: 123528.57 | V45: 123528.57 | W45: 123528.57 | X45: 123528.57 | Y45: 123528.57 | Z45: 123528.57 | AA45: 123528.57 | AB45: 123528.56
A46: 1 | C46: 이익잉여금 | E46: -20082.13 | F46: -20082.13 | G46: -21532.47 | H46: -21334.82 | I46: -19520.57 | J46: -19688.19 | K46: -19688.19 | L46: -19370.88 | M46: -23970.51 | N46: -23571.16 | O46: 43442.27 | P46: 43442.27 | Q46: 44692.7 | R46: 44867.79 | S46: 43540.5 | T46: 45335.71 | U46: 45335.71 | V46: 38540.78 | W46: 34750.7 | X46: 33713.69 | Y46: 30714.69 | Z46: 30714.69 | AA46: 34285.36 | AB46: 32458.2
A47: 1 | C47: 기타자본 | E47: -4212.7 | F47: -4212.7 | G47: -4212.7 | H47: -4212.7 | I47: -4212.7 | J47: -36.49 | K47: -36.49 | L47: -36.49 | M47: 5286.01 | N47: 5286.01 | O47: 5286.01 | P47: 5286.01 | Q47: 5286.01 | R47: 5286.01 | S47: 5286.01 | T47: 5089.62 | U47: 5089.62 | V47: 8865.94 | W47: 3179.06 | X47: 3179.06 | Y47: 3164.39 | Z47: 3164.39 | AA47: 3164.39 | AB47: 7477.78
A48: 1 | C48: 자본총계 | E48: 99233.73 | F48: 99233.73 | G48: 97783.4 | H48: 97981.05 | I48: 99795.29 | J48: 103803.88 | K48: 103803.88 | L48: 104121.19 | M48: 104844.06 | N48: 105243.41 | O48: 172256.84 | P48: 172256.84 | Q48: 173507.27 | R48: 173682.36 | S48: 172355.08 | T48: 173953.89 | U48: 173953.89 | V48: 170935.29 | W48: 161458.33 | X48: 160421.32 | Y48: 157407.64 | Z48: 157407.64 | AA48: 160978.31 | AB48: 163464.54
A49: 1 | C49: 부채와자본총계 | E49: 127002.55 | F49: 127002.55 | G49: 125679.24 | H49: 124919.61 | I49: 126352.47 | J49: 130377.79 | K49: 130377.79 | L49: 125802.59 | M49: 118981.81 | N49: 118599.79 | O49: 201085.83 | P49: 201085.83 | Q49: 198880.61 | R49: 197767.58 | S49: 194835.24 | T49: 197750.63 | U49: 197750.63 | V49: 191276.24 | W49: 181716.97 | X49: 182584.13 | Y49: 179559.89 | Z49: 179559.89 | AA49: 177970.35 | AB49: 177605.94
A50: 1 | C50: 지배주주지분 | E50: 99233.73 | F50: 99233.73 | G50: 97783.4 | H50: 97981.05 | I50: 99795.29 | J50: 103803.88 | K50: 103803.88 | L50: 104121.19 | M50: 104844.06 | N50: 105243.41 | O50: 172256.84 | P50: 172256.84 | Q50: 173507.27 | R50: 173682.36 | S50: 172355.08 | T50: 173953.89 | U50: 173953.89 | V50: 170935.29 | W50: 161458.33 | X50: 160421.32 | Y50: 157407.64 | Z50: 157407.64 | AA50: 160978.31 | AB50: 163464.54
A51: 1 | C51: 총차입금 | E51: 10066.44 | F51: 10066.44 | G51: 10385.18 | H51: 10721.69 | I51: 10563.45 | J51: 10903.99 | K51: 10903.99 | L51: 7073.16 | M51: 0 | N51: 0 | O51: 0 | P51: 0 | Q51: 0 | R51: 0 | S51: 0 | T51: 0 | U51: 0 | V51: 0
A52: 1 | C52: 순차입금 | E52: -35325 | F52: -35325 | G52: -14202.23 | H52: -12672.18 | I52: -3787.53 | J52: -8459.8 | K52: -8459.8 | L52: -10807.95 | M52: -14744.16 | N52: -11982.17 | O52: -10792.67 | P52: -10792.67 | Q52: -6039.45 | R52: -4140.99 | S52: -5998.83 | T52: -10292.83 | U52: -10292.83 | V52: -14756.4
A53: 1 | C53: 이자발생자산 | E53: 57611.63 | F53: 57611.63 | G53: 39819.2 | H53: 37875.29 | I53: 28832.4 | J53: 31900.83 | K53: 31900.83 | L53: 29418.15 | M53: 25682.2 | N53: 22920.21 | O53: 22979.39 | P53: 22979.39 | Q53: 18226.17 | R53: 16327.71 | S53: 18185.55 | T53: 24284.53 | U53: 24284.53 | V53: 28748.1 | W53: 20404.45 | X53: 39036.32 | Y53: 38898.21 | Z53: 38898.21 | AA53: 40637.6 | AB53: 63591.59
A54: 1 | C54: 단기금융부채(face) | N54: 0 | O54: 0 | P54: 0 | Q54: 0 | R54: 0 | S54: 0 | T54: 0 | U54: 0 | V54: 0
A55: 1 | C55: 기타비유동부채 | N55: 0 | O55: 0 | P55: 0 | Q55: 0 | R55: 0 | S55: 0 | T55: 0 | U55: 0 | V55: 0
A56: 1 | C56: 장기금융부채(face) | S56: 0 | T56: 0 | U56: 0 | V56: 0
A57: 1 | C57: 계약자산 | T57: 1857.79 | U57: 1857.79 | V57: 1913.75 | W57: 1133.26 | X57: 1133.26 | Y57: 1392.83 | Z57: 1392.83 | AA57: 1392.83 | AB57: 1392.83
A58: 1 | C58: 계약부채 | T58: 2639.77 | U58: 2639.77 | V58: 1069.23 | W58: 519.91 | X58: 519.91 | Y58: 0 | Z58: 0 | AA58: 0 | AB58: 0
A59: 1 | C59: 매출액(수익) | E59: 19189.6 | G59: 15460.29 | H59: 17129.94 | I59: 18420.39 | J59: 20174.69 | K59: 71185.31 | L59: 13811.68 | M59: 16227.93 | N59: 12058.9 | O59: 15169.37 | P59: 57267.88 | Q59: 18296.41 | R59: 19065.15 | S59: 17139.93 | T59: 30150.32 | U59: 84651.81 | V59: 20166.42 | W59: 22849.01 | X59: 19200.5 | Y59: 31134.14 | Z59: 93350.07 | AA59: 19599.25 | AB59: 21215
A60: 1 | C60: 매출원가 | E60: 15278.53 | G60: 15235.06 | H60: 16461.47 | I60: 16062.69 | J60: 15482.73 | K60: 63241.95 | L60: 12094.67 | M60: 13421.2 | N60: 10801.54 | O60: 14681.94 | P60: 50999.35 | Q60: 16141.89 | R60: 17649.31 | S60: 17013.2 | T60: 28310.7 | U60: 79115.1 | V60: 18154.57 | W60: 22462.72 | X60: 18508.87 | Y60: 28812.98 | Z60: 87939.14 | AA60: 14279.02 | AB60: 14038.72
A61: 1 | C61: 매출총이익 | E61: 3911.07 | G61: 225.23 | H61: 668.47 | I61: 2357.71 | J61: 4691.96 | K61: 7943.37 | L61: 1717.01 | M61: 2806.73 | N61: 1257.36 | O61: 487.43 | P61: 6268.53 | Q61: 2154.52 | R61: 1415.84 | S61: 126.73 | T61: 1839.62 | U61: 5536.71 | V61: 2011.85 | W61: 386.28 | X61: 691.64 | Y61: 2321.16 | Z61: 5410.93 | AA61: 5320.23 | AB61: 7176.28
A62: 1 | C62: 판관비 | E62: 1521.66 | G62: 1938.98 | H62: 2220.71 | I62: 2170.1 | J62: 570.87 | K62: 6900.66 | L62: 2079.41 | M62: 2219.57 | N62: 2482.32 | O62: 2862.14 | P62: 9643.44 | Q62: 2724.58 | R62: 2478.13 | S62: 1639.26 | T62: 4694.66 | U62: 11536.63 | V62: 2417.47 | W62: 2422.11 | X62: 3026.92 | Y62: 3382.12 | Z62: 11248.62 | AA62: 2913.92 | AB62: 4109.23
A63: 1 | C63: 영업이익 | E63: 2389.41 | G63: -1713.75 | H63: -1552.24 | I63: 187.6 | J63: 4121.09 | K63: 1042.7 | L63: -362.4 | M63: 587.16 | N63: -1224.96 | O63: -2374.72 | P63: -3374.92 | Q63: -570.06 | R63: -1062.29 | S63: -1512.53 | T63: -2855.03 | U63: -5999.91 | V63: -405.62 | W63: -2035.82 | X63: -2335.28 | Y63: -1060.97 | Z63: -5837.69 | AA63: 2406.31 | AB63: 3067.05
A64: 1 | C64: 기타영업외수익 | E64: 5045.85 | G64: 385.92 | H64: 837.94 | I64: 1915.2 | J64: 1044.14 | K64: 4183.2 | L64: 652.44 | M64: 22.76 | N64: 1320.17 | O64: 76727.95 | P64: 78723.32 | Q64: 529.24 | R64: 448.66 | S64: -83.53 | T64: 2997.63 | U64: 3892 | V64: 959.7 | W64: 183.87 | X64: 774.36 | Y64: 538.73 | Z64: 2456.66 | AA64: 626.85 | AB64: 1195.08
A65: 1 | C65: 기타영업외비용 | E65: 328.49 | G65: 158.6 | H65: 1311.03 | I65: 587.53 | J65: 1702.01 | K65: 3759.17 | L65: 429.02 | M65: 292.11 | N65: 238.6 | O65: 2951.66 | P65: 3911.39 | Q65: 196.14 | R65: 172.84 | S65: 272.67 | T65: 161.78 | U65: 803.43 | V65: 904.48 | W65: 798.23 | X65: 870.95 | Y65: 2931.62 | Z65: 5505.28 | AA65: 268.63 | AB65: 1752.46
A66: 1 | C66: 금융수익 | E66: -1083.77 | G66: 401.39 | H66: 2572.16 | I66: 663.64 | J66: 889.69 | K66: 4526.88 | L66: 905.01 | M66: 731.07 | N66: 534.55 | O66: 301.01 | P66: 2471.64 | Q66: 1488.37 | R66: 1260.73 | S66: 916.39 | T66: 1533.31 | U66: 5198.8 | V66: 967.15 | W66: 415.89 | X66: 445.47 | Y66: 610.11 | Z66: 2438.62 | AA66: 1513.78 | AB66: 794.99
A67: 1 | C67: 금융비용 | E67: -1779.84 | G67: 365.3 | H67: 349.19 | I67: 364.67 | J67: 1090.45 | K67: 2169.61 | L67: 392.91 | M67: 117.64 | N67: -8.19 | O67: 209.65 | P67: 712.01 | Q67: 0.98 | R67: 2.16 | S67: 374.94 | T67: -281.07 | U67: 97.01 | V67: 48.43 | W67: 1555.78 | X67: -949.39 | Y67: 155.27 | Z67: 810.09 | AA67: 12.82 | AB67: 11.02
A68: 1 | C68: 법인세비용차감전계속사업이익 | E68: 7802.84 | G68: -1450.33 | H68: 197.65 | I68: 1814.25 | J68: 3262.47 | K68: 3824.04 | L68: 373.12 | M68: 931.24 | N68: 399.35 | O68: 71492.94 | P68: 73196.65 | Q68: 1250.43 | R68: 472.11 | S68: -1327.29 | T68: 1795.21 | U68: 2190.46 | V68: 568.32 | W68: -3790.08 | X68: -1037.01 | Y68: -2999.01 | Z68: -7257.78 | AA68: 4265.48 | AB68: 3293.64
A69: 1 | C69: 법인세비용 | E69: 0 | G69: 0 | H69: 0 | I69: 0 | J69: 0 | K69: 0 | L69: 55.81 | M69: 11.19 | N69: 0 | O69: 4427.26 | P69: 4494.26 | Q69: 0 | R69: 297.01 | S69: 0 | T69: 0 | U69: 297.01 | V69: 0 | W69: 0 | X69: 0 | Y69: 0 | Z69: 0 | AA69: 0 | AB69: 771.52
A70: 1 | C70: 계속사업이익 | E70: 7802.84 | G70: -1450.33 | H70: 197.65 | I70: 1814.25 | J70: 3262.47 | K70: 3824.04 | L70: 317.31 | M70: 920.05 | N70: 399.35 | O70: 67065.68 | P70: 68702.39 | Q70: 1250.43 | R70: 175.09 | S70: -1327.29 | T70: 1795.21 | U70: 1893.44 | V70: 568.32 | W70: -3790.08 | X70: -1037.01 | Y70: -2999.01 | Z70: -7257.78 | AA70: 4265.48 | AB70: 2522.12
... A75: 1 | C75: (지배주주지분)당기순이익 | E75: 7802.84 | G75: -1450.33 | H75: 197.65 | I75: 1814.25 | J75: 3262.47 | K75: 3824.04 | L75: 317.31 | M75: 920.05 | N75: 399.35 | O75: 67013.43 | P75: 68650.14 | Q75: 1250.43 | R75: 175.09 | S75: -1327.29 | T75: 1795.21 | U75: 1893.44 | V75: 568.32 | W75: -3790.08 | X75: -1037.01 | Y75: -2999.01 | Z75: -7257.78 | AA75: 4265.48 | AB75: 2522.12
A76: 1 | C76: 중단사업이익 | G76: 0 | H76: 0 | I76: 0 | J76: 0 | K76: 0 | L76: 0 | M76: 0 | N76: 0 | O76: -52.25 | P76: -52.25 | Q76: 0 | R76: 0 | S76: 0 | T76: 0 | U76: 0 | V76: 0 | W76: 0 | X76: 0 | Y76: 0 | Z76: 0
A77: 1 | C77: 영업활동으로인한현금흐름 | E77: -1884.77 | G77: 140.86 | H77: -2736.54 | I77: 1137.83 | J77: 1615.85 | K77: 158 | L77: 3370.61 | M77: 653.08 | N77: -1315.66 | O77: -547.77 | P77: 2160.26 | Q77: -4976.02 | R77: -484.71 | S77: -2832 | T77: -731.01 | U77: -9023.74 | V77: -12062.15 | W77: 1106.54 | X77: -412.18 | Y77: 5845.75 | Z77: -5522.04 | AA77: 1611.53 | AB77: 4893.31
A78: 1 | C78: 법인세납부(CF) | E78: -10.6 | G78: -19.14 | H78: 8.7 | I78: -38.22 | J78: -44.46 | K78: -93.12 | L78: -176.67 | M78: 68.88 | N78: -40.36 | O78: -57.26 | P78: -205.41 | Q78: -49.4 | R78: -4513.07 | S78: -294.82 | T78: -36.55 | U78: -4893.84 | V78: -252.38 | W78: 398.44 | X78: -159.91 | Y78: -12.66 | Z78: -26.51 | AA78: -49.86 | AB78: 426.78
A79: 1 | C79: 투자활동으로인한현금흐름 | E79: 22715.38 | G79: -20925.56 | H79: 1495.66 | I79: -9705.52 | J79: 4177.93 | K79: -24957.49 | L79: -609.99 | M79: 3436.77 | N79: -1471.45 | O79: -282.03 | P79: 1073.3 | Q79: 247.7 | R79: -1267.37 | S79: 4842.45 | T79: 5194.08 | U79: 9016.86 | V79: 19251.22 | W79: -2818.15 | X79: 18900.57 | Y79: -5822.12 | Z79: 29511.52 | AA79: -724.09 | AB79: 23654.95
A80: 1 | C80: 유형자산의감소 | E80: 17596.91 | G80: 0 | H80: 0.45 | I80: 43.91 | J80: 5382.71 | K80: 5427.07 | L80: 0 | M80: 0 | N80: 0 | O80: 38.25 | P80: 38.25 | Q80: 1.82 | R80: 317.85 | S80: 0 | T80: 0 | U80: 319.67 | V80: 6.2 | W80: 0 | X80: 0 | Y80: 0 | Z80: 6.2 | AA80: 0 | AB80: 0
A81: 1 | C81: 유형자산의증가 | E81: 1945.15 | G81: 2915.89 | H81: 1933.64 | I81: 1048.48 | L81: 30.04 | M81: 445.67 | N81: 129.88 | O81: 326.13 | P81: 931.72 | Q81: 748.81 | R81: 1395.31 | S81: 216.26 | T81: 198.28 | U81: 2558.66 | V81: 3.85 | W81: 1063.08 | X81: 5068.22 | Y81: 6473.21 | Z81: 12608.36 | AA81: 826.95 | AB81: 414.76
A82: 1 | C82: CAPEX | E82: 1945.15 | G82: 2915.89 | H82: 1933.64 | I82: 1048.48 | J82: 0 | K82: 5898.01 | L82: 30.04 | M82: 445.67 | N82: 129.88 | O82: 326.13 | P82: 931.72 | Q82: 748.81 | R82: 1395.31 | S82: 216.26 | T82: 198.28 | U82: 2558.66 | V82: 3.85 | W82: 1063.08 | X82: 5069.1 | Y82: 6472.33 | Z82: 12608.36 | AA82: 826.95 | AB82: 414.76
A83: 1 | C83: 무형자산의증가 | E83: 0 | G83: 0 | H83: 0 | I83: 0 | J83: 0 | K83: 0 | L83: 0 | M83: 0 | N83: 0 | O83: 0 | P83: 0 | Q83: 0 | R83: 0 | S83: 0 | T83: 0 | U83: 0 | V83: 0 | AA83: 0 | AB83: 0
A84: 1 | C84: 재무활동으로인한현금흐름 | E84: -10.21 | G84: 0 | H84: 0 | I84: -504.5 | J84: 0 | K84: -504.5 | L84: -4233.59 | M84: -7228.64 | N84: 0 | O84: -317.93 | P84: -11780.16 | Q84: -90 | R84: -90 | S84: -90 | T84: -286.39 | U84: -556.39 | V84: -2834.61 | W84: -6473.19 | X84: 0 | Y84: -50.09 | Z84: -9357.89 | AA84: -77.18 | AB84: -809.68
A85: 1 | C85: 단기차입금의증가 | E85: 0 | G85: 0 | H85: 0 | I85: 0 | J85: 0 | K85: 0 | L85: 0 | M85: 5000 | N85: 0 | Q85: 0 | R85: 0 | S85: 0 | T85: 0 | U85: 0 | V85: 0
A86: 1 | C86: 장기차입금의증가 | E86: 0 | G86: 0 | H86: 0 | I86: 0 | J86: 0 | K86: 0 | L86: 0 | M86: 0 | N86: 0 | O86: 0 | P86: 0 | Q86: 0 | R86: 0 | S86: 0 | T86: 0 | U86: 0 | V86: 0
A87: 1 | C87: 단기차입금의감소 | E87: 0 | G87: 0 | H87: 0 | I87: 0 | J87: 0 | K87: 0 | L87: 0 | M87: 5000 | N87: 0 | Q87: 0 | R87: 0 | S87: 0 | T87: 0 | U87: 0 | V87: 0
A88: 1 | C88: 유동성장기부채의감소 | E88: 0 | G88: 0 | H88: 0 | I88: 0 | J88: 0 | K88: 0 | L88: 0 | M88: 0 | N88: 0 | O88: 0 | P88: 0 | Q88: 0 | R88: 0 | S88: 0 | T88: 0 | U88: 0 | V88: 0
A89: 1 | C89: 리스부채의상환 | E89: 10.21 | G89: 0 | H89: 0 | I89: 0 | J89: 0 | K89: 0 | L89: 0 | M89: 0 | N89: 0 | O89: 120 | P89: 120 | Q89: 90 | R89: 90 | S89: 90 | T89: 90 | U89: 360 | V89: 34 | W89: 0 | X89: 0 | Y89: 75.42 | Z89: 109.42 | AA89: 77.18 | AB89: 78.98
A90: 1 | C90: 장기차입금의감소 | E90: 0 | G90: 0 | H90: 0 | I90: 0 | J90: 0 | K90: 0 | L90: 0 | M90: 0 | N90: 0 | O90: 0 | P90: 0 | Q90: 0 | R90: 0 | S90: 0 | T90: 0 | U90: 0 | V90: 0
A91: 1 | C91: 현금및현금성자산의증감 | E91: 41437.61 | G91: -41588.73 | H91: -2434.42 | I91: -18115.08 | J91: 10806.59 | K91: -51331.64 | L91: -2955.65 | M91: -6275.75 | N91: -5549.1 | O91: -2337.22 | P91: -17117.72 | Q91: -9571.55 | R91: -3740.53 | S91: 3778.28 | T91: 8470.69 | U91: -1063.11 | V91: 8818.03 | W91: -16528.45 | X91: 37120.26 | Y91: -10.56 | Z91: 29399.28 | AA91: 2549.65 | AB91: 55832.85
A92: 1 | C92: 기말현금및현금성자산 | E92: 20617.2 | G92: 24587.41 | H92: -1193.54 | I92: -9042.89 | J92: 5012.81 | K92: 19363.79 | L92: 17881.11 | M92: -3136.95 | N92: -2761.99 | O92: -1189.5 | P92: 10792.67 | Q92: 6039.45 | R92: -1898.46 | S92: 1857.84 | T92: 4294 | U92: 10292.83 | V92: 14756.4 | W92: -8343.65 | X92: 18631.87 | Y92: 15.92 | Z92: 25060.54 | AA92: 26799.93 | AB92: 28094.27
A93: 1 | C93: 이자수취(CF) | O93: 371.17 | Q93: 332 | R93: 379.09 | S93: 1925.15 | T93: 205.04 | U93: 2841.28 | V93: 1638.86 | W93: 255.52 | X93: 1038.38 | Y93: 82.22 | Z93: 3014.98 | AA93: 331.93 | AB93: 233.92
A94: 1 | C94: 자기주식의취득 | V94: 2800.61 | W94: 5686.88 | X94: 0 | Y94: 14.67 | Z94: 8502.16 | AA94: 0 | AB94: 35.89
A95: 1 | C95: 배당금지급 | X95: 0 | Y95: 0 | AA95: 0 | AB95: 694.81

Sheet subQ
A1: YQ | C1: subQ 분기 서브모델(억원, U=100) | E1: 4Q21 | F1: 2021 | G1: 1Q22 | H1: 2Q22 | I1: 3Q22 | J1: 4Q22 | K1: 2022 | L1: 1Q23 | M1: 2Q23 | N1: 3Q23 | O1: 4Q23 | P1: 2023 | Q1: 1Q24 | R1: 2Q24 | S1: 3Q24 | T1: 4Q24 | U1: 2024 | V1: 1Q25 | W1: 2Q25 | X1: 3Q25 | Y1: 4Q25 | Z1: 2025 | AA1: 1Q26 | AB1: 2Q26 | AC1: 3Q26 | AD1: 4Q26 | AE1: 2026 | AF1: 1Q27 | AG1: 2Q27 | AH1: 3Q27 | AI1: 4Q27 | AJ1: 2027 | AK1: 1Q28 | AL1: 2Q28 | AM1: 3Q28 | AN1: 4Q28 | AO1: 2028
A2: A=이름(key) B=그룹 C=단위 D=FnGuide 계정명(VLOOKUP 키). 확정=VLOOKUP(BS), 추정=변수 가정 참조
E3: 1 | F3: 2 | G3: 3 | H3: 4 | I3: 5 | J3: 6 | K3: 7 | L3: 8 | M3: 9 | N3: 10 | O3: 11 | P3: 12 | Q3: 13 | R3: 14 | S3: 15 | T3: 16 | U3: 17 | V3: 18 | W3: 19 | X3: 20 | Y3: 21 | Z3: 22 | AA3: 23 | AB3: 24 | AC3: 25 | AD3: 26 | AE3: 27 | AF3: 28 | AG3: 29 | AH3: 30 | AI3: 31 | AJ3: 32 | AK3: 33 | AL3: 34 | AM3: 35 | AN3: 36 | AO3: 37
E4: 2021.12 | F4: 2021.12A | G4: 2022.03 | H4: 2022.06 | I4: 2022.09 | J4: 2022.12 | K4: 2022.12A | L4: 2023.03 | M4: 2023.06 | N4: 2023.09 | O4: 2023.12 | P4: 2023.12A | Q4: 2024.03 | R4: 2024.06 | S4: 2024.09 | T4: 2024.12 | U4: 2024.12A | V4: 2025.03 | W4: 2025.06 | X4: 2025.09 | Y4: 2025.12 | Z4: 2025.12A | AA4: 2026.03 | AB4: 2026.06 | AC4: 2026.09 | AD4: 2026.12 | AE4: 2026.12A | AF4: 2027.03 | AG4: 2027.06 | AH4: 2027.09 | AI4: 2027.12 | AJ4: 2027.12A | AK4: 2028.03 | AL4: 2028.06 | AM4: 2028.09 | AN4: 2028.12 | AO4: 2028.12A
A5: 매출액 | B5: 손익 | C5: 억원 | D5: 매출액(수익) | E5: =IFERROR(VLOOKUP($D5,BS연결,MATCH(E$1,BS연결H,0),0)/100,"") | G5: =IFERROR(VLOOKUP($D5,BS연결,MATCH(G$1,BS연결H,0),0)/100,"") | H5: =IFERROR(VLOOKUP($D5,BS연결,MATCH(H$1,BS연결H,0),0)/100,"") | I5: =IFERROR(VLOOKUP($D5,BS연결,MATCH(I$1,BS연결H,0),0)/100,"") | J5: =IFERROR(VLOOKUP($D5,BS연결,MATCH(J$1,BS연결H,0),0)/100,"") | K5: =IFERROR(VLOOKUP($D5,BS연결,MATCH(K$1,BS연결H,0),0)/100,"") | L5: =IFERROR(VLOOKUP($D5,BS연결,MATCH(L$1,BS연결H,0),0)/100,"") | M5: =IFERROR(VLOOKUP($D5,BS연결,MATCH(M$1,BS연결H,0),0)/100,"") | N5: =IFERROR(VLOOKUP($D5,BS연결,MATCH(N$1,BS연결H,0),0)/100,"") | ... AB5: =IFERROR(VLOOKUP($D5,BS연결,MATCH(AB$1,BS연결H,0),0)/100,"") | AC5: =IFERROR(X5*(1+변수!AC21),"") | AD5: =IFERROR(Y5*(1+변수!AD21),"") | AE5: =SUM(AA5:AD5) | AF5: =IFERROR(AA5*(1+변수!AF21),"") | AG5: =IFERROR(AB5*(1+변수!AG21),"") | AH5: =IFERROR(AC5*(1+변수!AH21),"") | AI5: =IFERROR(AD5*(1+변수!AI21),"") | AJ5: =SUM(AF5:AI5) | AK5: =IFERROR(AF5*(1+변수!AK21),"") | AL5: =IFERROR(AG5*(1+변수!AL21),"") | AM5: =IFERROR(AH5*(1+변수!AM21),"") | AN5: =IFERROR(AI5*(1+변수!AN21),"") | AO5: =SUM(AK5:AN5)
A6: 매출원가 | B6: 손익 | C6: 억원 | D6: 매출원가 | E6: =IFERROR(VLOOKUP($D6,BS연결,MATCH(E$1,BS연결H,0),0)/100,"") | G6: =IFERROR(VLOOKUP($D6,BS연결,MATCH(G$1,BS연결H,0),0)/100,"") | H6: =IFERROR(VLOOKUP($D6,BS연결,MATCH(H$1,BS연결H,0),0)/100,"") | I6: =IFERROR(VLOOKUP($D6,BS연결,MATCH(I$1,BS연결H,0),0)/100,"") | J6: =IFERROR(VLOOKUP($D6,BS연결,MATCH(J$1,BS연결H,0),0)/100,"") | K6: =IFERROR(VLOOKUP($D6,BS연결,MATCH(K$1,BS연결H,0),0)/100,"") | L6: =IFERROR(VLOOKUP($D6,BS연결,MATCH(L$1,BS연결H,0),0)/100,"") | M6: =IFERROR(VLOOKUP($D6,BS연결,MATCH(M$1,BS연결H,0),0)/100,"") | N6: =IFERROR(VLOOKUP($D6,BS연결,MATCH(N$1,BS연결H,0),0)/100,"") | ... AB6: =IFERROR(VLOOKUP($D6,BS연결,MATCH(AB$1,BS연결H,0),0)/100,"") | AC6: =IFERROR(AC5-AC7,"") | AD6: =IFERROR(AD5-AD7,"") | AE6: =SUM(AA6:AD6) | AF6: =IFERROR(AF5-AF7,"") | AG6: =IFERROR(AG5-AG7,"") | AH6: =IFERROR(AH5-AH7,"") | AI6: =IFERROR(AI5-AI7,"") | AJ6: =SUM(AF6:AI6) | AK6: =IFERROR(AK5-AK7,"") | AL6: =IFERROR(AL5-AL7,"") | AM6: =IFERROR(AM5-AM7,"") | AN6: =IFERROR(AN5-AN7,"") | AO6: =SUM(AK6:AN6)
A7: 매출총이익 | B7: 손익 | C7: 억원 | D7: 매출총이익 | E7: =IFERROR(VLOOKUP($D7,BS연결,MATCH(E$1,BS연결H,0),0)/100,"") | G7: =IFERROR(VLOOKUP($D7,BS연결,MATCH(G$1,BS연결H,0),0)/100,"") | H7: =IFERROR(VLOOKUP($D7,BS연결,MATCH(H$1,BS연결H,0),0)/100,"") | I7: =IFERROR(VLOOKUP($D7,BS연결,MATCH(I$1,BS연결H,0),0)/100,"") | J7: =IFERROR(VLOOKUP($D7,BS연결,MATCH(J$1,BS연결H,0),0)/100,"") | K7: =IFERROR(VLOOKUP($D7,BS연결,MATCH(K$1,BS연결H,0),0)/100,"") | L7: =IFERROR(VLOOKUP($D7,BS연결,MATCH(L$1,BS연결H,0),0)/100,"") | M7: =IFERROR(VLOOKUP($D7,BS연결,MATCH(M$1,BS연결H,0),0)/100,"") | N7: =IFERROR(VLOOKUP($D7,BS연결,MATCH(N$1,BS연결H,0),0)/100,"") | ... AB7: =IFERROR(VLOOKUP($D7,BS연결,MATCH(AB$1,BS연결H,0),0)/100,"") | AC7: =IFERROR(AC9+AC8,"") | AD7: =IFERROR(AD9+AD8,"") | AE7: =SUM(AA7:AD7) | AF7: =IFERROR(AF9+AF8,"") | AG7: =IFERROR(AG9+AG8,"") | AH7: =IFERROR(AH9+AH8,"") | AI7: =IFERROR(AI9+AI8,"") | AJ7: =SUM(AF7:AI7) | AK7: =IFERROR(AK9+AK8,"") | AL7: =IFERROR(AL9+AL8,"") | AM7: =IFERROR(AM9+AM8,"") | AN7: =IFERROR(AN9+AN8,"") | AO7: =SUM(AK7:AN7)
A8: 판관비 | B8: 손익 | C8: 억원 | D8: 판관비 | E8: =IFERROR(VLOOKUP($D8,BS연결,MATCH(E$1,BS연결H,0),0)/100,"") | G8: =IFERROR(VLOOKUP($D8,BS연결,MATCH(G$1,BS연결H,0),0)/100,"") | H8: =IFERROR(VLOOKUP($D8,BS연결,MATCH(H$1,BS연결H,0),0)/100,"") | I8: =IFERROR(VLOOKUP($D8,BS연결,MATCH(I$1,BS연결H,0),0)/100,"") | J8: =IFERROR(VLOOKUP($D8,BS연결,MATCH(J$1,BS연결H,0),0)/100,"") | K8: =IFERROR(VLOOKUP($D8,BS연결,MATCH(K$1,BS연결H,0),0)/100,"") | L8: =IFERROR(VLOOKUP($D8,BS연결,MATCH(L$1,BS연결H,0),0)/100,"") | M8: =IFERROR(VLOOKUP($D8,BS연결,MATCH(M$1,BS연결H,0),0)/100,"") | N8: =IFERROR(VLOOKUP($D8,BS연결,MATCH(N$1,BS연결H,0),0)/100,"") | ... AB8: =IFERROR(VLOOKUP($D8,BS연결,MATCH(AB$1,BS연결H,0),0)/100,"") | AC8: =IFERROR(AC5*변수!AC22,"") | AD8: =IFERROR(AD5*변수!AD22,"") | AE8: =SUM(AA8:AD8) | AF8: =IFERROR(AF5*변수!AF22,"") | AG8: =IFERROR(AG5*변수!AG22,"") | AH8: =IFERROR(AH5*변수!AH22,"") | AI8: =IFERROR(AI5*변수!AI22,"") | AJ8: =SUM(AF8:AI8) | AK8: =IFERROR(AK5*변수!AK22,"") | AL8: =IFERROR(AL5*변수!AL22,"") | AM8: =IFERROR(AM5*변수!AM22,"") | AN8: =IFERROR(AN5*변수!AN22,"") | AO8: =SUM(AK8:AN8)
A9: 영업이익 | B9: 손익 | C9: 억원 | D9: 영업이익 | E9: =IFERROR(VLOOKUP($D9,BS연결,MATCH(E$1,BS연결H,0),0)/100,"") | G9: =IFERROR(VLOOKUP($D9,BS연결,MATCH(G$1,BS연결H,0),0)/100,"") | H9: =IFERROR(VLOOKUP($D9,BS연결,MATCH(H$1,BS연결H,0),0)/100,"") | I9: =IFERROR(VLOOKUP($D9,BS연결,MATCH(I$1,BS연결H,0),0)/100,"") | J9: =IFERROR(VLOOKUP($D9,BS연결,MATCH(J$1,BS연결H,0),0)/100,"") | K9: =IFERROR(VLOOKUP($D9,BS연결,MATCH(K$1,BS연결H,0),0)/100,"") | L9: =IFERROR(VLOOKUP($D9,BS연결,MATCH(L$1,BS연결H,0),0)/100,"") | M9: =IFERROR(VLOOKUP($D9,BS연결,MATCH(M$1,BS연결H,0),0)/100,"") | N9: =IFERROR(VLOOKUP($D9,BS연결,MATCH(N$1,BS연결H,0),0)/100,"") | ... T9: =IFERROR(VLOOKUP($D9,BS연결,MATCH(T$1,BS연결H,0),0)/100,"") | U9: =SUM(Q9:T9) | V9: =IFERROR(VLOOKUP($D9,BS연결,MATCH(V$1,BS연결H,0),0)/100,"") | W9: =IFERROR(VLOOKUP($D9,BS연결,MATCH(W$1,BS연결H,0),0)/100,"") | X9: =IFERROR(VLOOKUP($D9,BS연결,MATCH(X$1,BS연결H,0),0)/100,"") | Y9: =IFERROR(VLOOKUP($D9,BS연결,MATCH(Y$1,BS연결H,0),0)/100,"") | Z9: =IFERROR(VLOOKUP($D9,BS연결,MATCH(Z$1,BS연결H,0),0)/100,"") | AA9: =IFERROR(VLOOKUP($D9,BS연결,MATCH(AA$1,BS연결H,0),0)/100,"") | AB9: =IFERROR(VLOOKUP($D9,BS연결,MATCH(AB$1,BS연결H,0),0)/100,"") | AC9: =IFERROR(AC5*변수!AC23,"") | AD9: =IFERROR(AD5*변수!AD23,"") | AE9: =SUM(AA9:AD9) | AF9: =IFERROR(AF5*변수!AF23,"") | AG9: =IFERROR(AG5*변수!AG23,"") | AH9: =IFERROR(AH5*변수!AH23,"") | AI9: =IFERROR(AI5*변수!AI23,"") | AJ9: =SUM(AF9:AI9) | AK9: =IFERROR(AK5*변수!AK23,"") | AL9: =IFERROR(AL5*변수!AL23,"") | AM9: =IFERROR(AM5*변수!AM23,"") | AN9: =IFERROR(AN5*변수!AN23,"") | AO9: =SUM(AK9:AN9)
A10: OPM | B10: 손익 | C10: % | D10: 영업이익률 | E10: =IFERROR(E9/E5,"") | G10: =IFERROR(G9/G5,"") | H10: =IFERROR(H9/H5,"") | I10: =IFERROR(I9/I5,"") | J10: =IFERROR(J9/J5,"") | K10: =IFERROR(K9/K5,"") | L10: =IFERROR(L9/L5,"") | M10: =IFERROR(M9/M5,"") | N10: =IFERROR(N9/N5,"") | ... AO10: =IFERROR(AO9/AO5,"")
A11: 금융손익 | B11: 손익 | C11: 억원 | D11: 금융손익 | E11: =IFERROR(VLOOKUP($D11,BS연결,MATCH(E$1,BS연결H,0),0)/100,"") | G11: =IFERROR(VLOOKUP($D11,BS연결,MATCH(G$1,BS연결H,0),0)/100,"") | H11: =IFERROR(VLOOKUP($D11,BS연결,MATCH(H$1,BS연결H,0),0)/100,"") | I11: =IFERROR(VLOOKUP($D11,BS연결,MATCH(I$1,BS연결H,0),0)/100,"") | J11: =IFERROR(VLOOKUP($D11,BS연결,MATCH(J$1,BS연결H,0),0)/100,"") | K11: =IFERROR(VLOOKUP($D11,BS연결,MATCH(K$1,BS연결H,0),0)/100,"") | L11: =IFERROR(VLOOKUP($D11,BS연결,MATCH(L$1,BS연결H,0),0)/100,"") | M11: =IFERROR(VLOOKUP($D11,BS연결,MATCH(M$1,BS연결H,0),0)/100,"") | N11: =IFERROR(VLOOKUP($D11,BS연결,MATCH(N$1,BS연결H,0),0)/100,"") | ... AB11: =IFERROR(VLOOKUP($D11,BS연결,MATCH(AB$1,BS연결H,0),0)/100,"") | AC11: =IFERROR(AC12,"") | AD11: =IFERROR(AD12,"") | AE11: =SUM(AA11:AD11) | AF11: =IFERROR(AF12,"") | AG11: =IFERROR(AG12,"") | AH11: =IFERROR(AH12,"") | AI11: =IFERROR(AI12,"") | AJ11: =SUM(AF11:AI11) | AK11: =IFERROR(AK12,"") | AL11: =IFERROR(AL12,"") | AM11: =IFERROR(AM12,"") | AN11: =IFERROR(AN12,"") | AO11: =SUM(AK11:AN11)
A12: 이자손익 | B12: 손익 | C12: 억원 | D12: 이자손익 | K12: =SUM(G12:J12) | P12: =SUM(L12:O12) | U12: =SUM(Q12:T12) | Z12: =SUM(V12:Y12) | AC12: =IFERROR((AB26*변수!$D$52-AB24*변수!$D$53)/4,"") | AD12: =IFERROR((AC26*변수!$D$52-AC24*변수!$D$53)/4,"") | AE12: =SUM(AA12:AD12) | AF12: =IFERROR((AD26*변수!$D$52-AD24*변수!$D$53)/4,"") | AG12: =IFERROR((AF26*변수!$D$52-AF24*변수!$D$53)/4,"") | AH12: =IFERROR((AG26*변수!$D$52-AG24*변수!$D$53)/4,"") | AI12: =IFERROR((AH26*변수!$D$52-AH24*변수!$D$53)/4,"") | AJ12: =SUM(AF12:AI12) | AK12: =IFERROR((AI26*변수!$D$52-AI24*변수!$D$53)/4,"") | AL12: =IFERROR((AK26*변수!$D$52-AK24*변수!$D$53)/4,"") | AM12: =IFERROR((AL26*변수!$D$52-AL24*변수!$D$53)/4,"") | AN12: =IFERROR((AM26*변수!$D$52-AM24*변수!$D$53)/4,"") | AO12: =SUM(AK12:AN12)
A13: 기타영업외손익 | B13: 손익 | C13: 억원 | D13: 기타영업외손익 | E13: =IFERROR(VLOOKUP($D13,BS연결,MATCH(E$1,BS연결H,0),0)/100,"") | G13: =IFERROR(VLOOKUP($D13,BS연결,MATCH(G$1,BS연결H,0),0)/100,"") | H13: =IFERROR(VLOOKUP($D13,BS연결,MATCH(H$1,BS연결H,0),0)/100,"") | I13: =IFERROR(VLOOKUP($D13,BS연결,MATCH(I$1,BS연결H,0),0)/100,"") | J13: =IFERROR(VLOOKUP($D13,BS연결,MATCH(J$1,BS연결H,0),0)/100,"") | K13: =IFERROR(VLOOKUP($D13,BS연결,MATCH(K$1,BS연결H,0),0)/100,"") | L13: =IFERROR(VLOOKUP($D13,BS연결,MATCH(L$1,BS연결H,0),0)/100,"") | M13: =IFERROR(VLOOKUP($D13,BS연결,MATCH(M$1,BS연결H,0),0)/100,"") | N13: =IFERROR(VLOOKUP($D13,BS연결,MATCH(N$1,BS연결H,0),0)/100,"") | ... AB13: =IFERROR(VLOOKUP($D13,BS연결,MATCH(AB$1,BS연결H,0),0)/100,"") | AC13: =변수!AC24 | AD13: =변수!AD24 | AE13: =SUM(AA13:AD13) | AF13: =변수!AF24 | AG13: =변수!AG24 | AH13: =변수!AH24 | AI13: =변수!AI24 | AJ13: =SUM(AF13:AI13) | AK13: =변수!AK24 | AL13: =변수!AL24 | AM13: =변수!AM24 | AN13: =변수!AN24 | AO13: =SUM(AK13:AN13)
A14: 지분법손익 | B14: 손익 | C14: 억원 | D14: 종속기업,공동지배기업및관계기업관련손익 | E14: =IFERROR(VLOOKUP($D14,BS연결,MATCH(E$1,BS연결H,0),0)/100,"") | G14: =IFERROR(VLOOKUP($D14,BS연결,MATCH(G$1,BS연결H,0),0)/100,"") | H14: =IFERROR(VLOOKUP($D14,BS연결,MATCH(H$1,BS연결H,0),0)/100,"") | I14: =IFERROR(VLOOKUP($D14,BS연결,MATCH(I$1,BS연결H,0),0)/100,"") | J14: =IFERROR(VLOOKUP($D14,BS연결,MATCH(J$1,BS연결H,0),0)/100,"") | K14: =IFERROR(VLOOKUP($D14,BS연결,MATCH(K$1,BS연결H,0),0)/100,"") | L14: =IFERROR(VLOOKUP($D14,BS연결,MATCH(L$1,BS연결H,0),0)/100,"") | M14: =IFERROR(VLOOKUP($D14,BS연결,MATCH(M$1,BS연결H,0),0)/100,"") | N14: =IFERROR(VLOOKUP($D14,BS연결,MATCH(N$1,BS연결H,0),0)/100,"") | ... AB14: =IFERROR(VLOOKUP($D14,BS연결,MATCH(AB$1,BS연결H,0),0)/100,"") | AC14: =변수!AC25 | AD14: =변수!AD25 | AE14: =SUM(AA14:AD14) | AF14: =변수!AF25 | AG14: =변수!AG25 | AH14: =변수!AH25 | AI14: =변수!AI25 | AJ14: =SUM(AF14:AI14) | AK14: =변수!AK25 | AL14: =변수!AL25 | AM14: =변수!AM25 | AN14: =변수!AN25 | AO14: =SUM(AK14:AN14)
A15: 세전이익 | B15: 손익 | C15: 억원 | D15: 법인세비용차감전계속사업이익 | E15: =IFERROR(VLOOKUP($D15,BS연결,MATCH(E$1,BS연결H,0),0)/100,"") | G15: =IFERROR(VLOOKUP($D15,BS연결,MATCH(G$1,BS연결H,0),0)/100,"") | H15: =IFERROR(VLOOKUP($D15,BS연결,MATCH(H$1,BS연결H,0),0)/100,"") | I15: =IFERROR(VLOOKUP($D15,BS연결,MATCH(I$1,BS연결H,0),0)/100,"") | J15: =IFERROR(VLOOKUP($D15,BS연결,MATCH(J$1,BS연결H,0),0)/100,"") | K15: =IFERROR(VLOOKUP($D15,BS연결,MATCH(K$1,BS연결H,0),0)/100,"") | L15: =IFERROR(VLOOKUP($D15,BS연결,MATCH(L$1,BS연결H,0),0)/100,"") | M15: =IFERROR(VLOOKUP($D15,BS연결,MATCH(M$1,BS연결H,0),0)/100,"") | N15: =IFERROR(VLOOKUP($D15,BS연결,MATCH(N$1,BS연결H,0),0)/100,"") | ... AB15: =IFERROR(VLOOKUP($D15,BS연결,MATCH(AB$1,BS연결H,0),0)/100,"") | AC15: =IFERROR(AC9+AC11+AC13+AC14,"") | AD15: =IFERROR(AD9+AD11+AD13+AD14,"") | AE15: =SUM(AA15:AD15) | AF15: =IFERROR(AF9+AF11+AF13+AF14,"") | AG15: =IFERROR(AG9+AG11+AG13+AG14,"") | AH15: =IFERROR(AH9+AH11+AH13+AH14,"") | AI15: =IFERROR(AI9+AI11+AI13+AI14,"") | AJ15: =SUM(AF15:AI15) | AK15: =IFERROR(AK9+AK11+AK13+AK14,"") | AL15: =IFERROR(AL9+AL11+AL13+AL14,"") | AM15: =IFERROR(AM9+AM11+AM13+AM14,"") | AN15: =IFERROR(AN9+AN11+AN13+AN14,"") | AO15: =SUM(AK15:AN15)
A16: 법인세비용 | B16: 손익 | C16: 억원 | D16: 법인세비용 | E16: =IFERROR(VLOOKUP($D16,BS연결,MATCH(E$1,BS연결H,0),0)/100,"") | G16: =IFERROR(VLOOKUP($D16,BS연결,MATCH(G$1,BS연결H,0),0)/100,"") | H16: =IFERROR(VLOOKUP($D16,BS연결,MATCH(H$1,BS연결H,0),0)/100,"") | I16: =IFERROR(VLOOKUP($D16,BS연결,MATCH(I$1,BS연결H,0),0)/100,"") | J16: =IFERROR(VLOOKUP($D16,BS연결,MATCH(J$1,BS연결H,0),0)/100,"") | K16: =IFERROR(VLOOKUP($D16,BS연결,MATCH(K$1,BS연결H,0),0)/100,"") | L16: =IFERROR(VLOOKUP($D16,BS연결,MATCH(L$1,BS연결H,0),0)/100,"") | M16: =IFERROR(VLOOKUP($D16,BS연결,MATCH(M$1,BS연결H,0),0)/100,"") | N16: =IFERROR(VLOOKUP($D16,BS연결,MATCH(N$1,BS연결H,0),0)/100,"") | ... AB16: =IFERROR(VLOOKUP($D16,BS연결,MATCH(AB$1,BS연결H,0),0)/100,"") | AC16: =IFERROR(MAX(AC15,0)*변수!AC26,"") | AD16: =IFERROR(MAX(AD15,0)*변수!AD26,"") | AE16: =SUM(AA16:AD16) | AF16: =IFERROR(MAX(AF15,0)*변수!AF26,"") | AG16: =IFERROR(MAX(AG15,0)*변수!AG26,"") | AH16: =IFERROR(MAX(AH15,0)*변수!AH26,"") | AI16: =IFERROR(MAX(AI15,0)*변수!AI26,"") | AJ16: =SUM(AF16:AI16) | AK16: =IFERROR(MAX(AK15,0)*변수!AK26,"") | AL16: =IFERROR(MAX(AL15,0)*변수!AL26,"") | AM16: =IFERROR(MAX(AM15,0)*변수!AM26,"") | AN16: =IFERROR(MAX(AN15,0)*변수!AN26,"") | AO16: =SUM(AK16:AN16)
A17: 당기순이익 | B17: 손익 | C17: 억원 | D17: 당기순이익 | E17: =IFERROR(VLOOKUP($D17,BS연결,MATCH(E$1,BS연결H,0),0)/100,"") | G17: =IFERROR(VLOOKUP($D17,BS연결,MATCH(G$1,BS연결H,0),0)/100,"") | H17: =IFERROR(VLOOKUP($D17,BS연결,MATCH(H$1,BS연결H,0),0)/100,"") | I17: =IFERROR(VLOOKUP($D17,BS연결,MATCH(I$1,BS연결H,0),0)/100,"") | J17: =IFERROR(VLOOKUP($D17,BS연결,MATCH(J$1,BS연결H,0),0)/100,"") | K17: =IFERROR(VLOOKUP($D17,BS연결,MATCH(K$1,BS연결H,0),0)/100,"") | L17: =IFERROR(VLOOKUP($D17,BS연결,MATCH(L$1,BS연결H,0),0)/100,"") | M17: =IFERROR(VLOOKUP($D17,BS연결,MATCH(M$1,BS연결H,0),0)/100,"") | N17: =IFERROR(VLOOKUP($D17,BS연결,MATCH(N$1,BS연결H,0),0)/100,"") | ... AB17: =IFERROR(VLOOKUP($D17,BS연결,MATCH(AB$1,BS연결H,0),0)/100,"") | AC17: =IFERROR(AC15-AC16,"") | AD17: =IFERROR(AD15-AD16,"") | AE17: =SUM(AA17:AD17) | AF17: =IFERROR(AF15-AF16,"") | AG17: =IFERROR(AG15-AG16,"") | AH17: =IFERROR(AH15-AH16,"") | AI17: =IFERROR(AI15-AI16,"") | AJ17: =SUM(AF17:AI17) | AK17: =IFERROR(AK15-AK16,"") | AL17: =IFERROR(AL15-AL16,"") | AM17: =IFERROR(AM15-AM16,"") | AN17: =IFERROR(AN15-AN16,"") | AO17: =SUM(AK17:AN17)
A18: 지배주주순이익 | B18: 손익 | C18: 억원 | D18: (지배주주지분)당기순이익 | E18: =IFERROR(VLOOKUP($D18,BS연결,MATCH(E$1,BS연결H,0),0)/100,"") | G18: =IFERROR(VLOOKUP($D18,BS연결,MATCH(G$1,BS연결H,0),0)/100,"") | H18: =IFERROR(VLOOKUP($D18,BS연결,MATCH(H$1,BS연결H,0),0)/100,"") | I18: =IFERROR(VLOOKUP($D18,BS연결,MATCH(I$1,BS연결H,0),0)/100,"") | J18: =IFERROR(VLOOKUP($D18,BS연결,MATCH(J$1,BS연결H,0),0)/100,"") | K18: =IFERROR(VLOOKUP($D18,BS연결,MATCH(K$1,BS연결H,0),0)/100,"") | L18: =IFERROR(VLOOKUP($D18,BS연결,MATCH(L$1,BS연결H,0),0)/100,"") | M18: =IFERROR(VLOOKUP($D18,BS연결,MATCH(M$1,BS연결H,0),0)/100,"") | N18: =IFERROR(VLOOKUP($D18,BS연결,MATCH(N$1,BS연결H,0),0)/100,"") | ... Y18: =IFERROR(VLOOKUP($D18,BS연결,MATCH(Y$1,BS연결H,0),0)/100,"") | Z18: =SUM(V18:Y18) | AA18: =IFERROR(VLOOKUP($D18,BS연결,MATCH(AA$1,BS연결H,0),0)/100,"") | AB18: =IFERROR(VLOOKUP($D18,BS연결,MATCH(AB$1,BS연결H,0),0)/100,"") | AC18: =IFERROR(AC17*변수!AC27,"") | AD18: =IFERROR(AD17*변수!AD27,"") | AE18: =SUM(AA18:AD18) | AF18: =IFERROR(AF17*변수!AF27,"") | AG18: =IFERROR(AG17*변수!AG27,"") | AH18: =IFERROR(AH17*변수!AH27,"") | AI18: =IFERROR(AI17*변수!AI27,"") | AJ18: =SUM(AF18:AI18) | AK18: =IFERROR(AK17*변수!AK27,"") | AL18: =IFERROR(AL17*변수!AL27,"") | AM18: =IFERROR(AM17*변수!AM27,"") | AN18: =IFERROR(AN17*변수!AN27,"") | AO18: =SUM(AK18:AN18)
A19: 중단사업이익 | B19: 손익 | C19: 억원 | D19: 중단사업이익 | E19: =IFERROR(VLOOKUP($D19,BS연결,MATCH(E$1,BS연결H,0),0)/100,"") | G19: =IFERROR(VLOOKUP($D19,BS연결,MATCH(G$1,BS연결H,0),0)/100,"") | H19: =IFERROR(VLOOKUP($D19,BS연결,MATCH(H$1,BS연결H,0),0)/100,"") | I19: =IFERROR(VLOOKUP($D19,BS연결,MATCH(I$1,BS연결H,0),0)/100,"") | J19: =IFERROR(VLOOKUP($D19,BS연결,MATCH(J$1,BS연결H,0),0)/100,"") | K19: =IFERROR(VLOOKUP($D19,BS연결,MATCH(K$1,BS연결H,0),0)/100,"") | L19: =IFERROR(VLOOKUP($D19,BS연결,MATCH(L$1,BS연결H,0),0)/100,"") | M19: =IFERROR(VLOOKUP($D19,BS연결,MATCH(M$1,BS연결H,0),0)/100,"") | N19: =IFERROR(VLOOKUP($D19,BS연결,MATCH(N$1,BS연결H,0),0)/100,"") | ... X19: =IFERROR(VLOOKUP($D19,BS연결,MATCH(X$1,BS연결H,0),0)/100,"") | Z19: =SUM(V19:Y19) | AE19: =SUM(AA19:AD19) | AJ19: =SUM(AF19:AI19) | AO19: =SUM(AK19:AN19)
A20: 자산총계 | B20: 재무상태 | C20: 억원 | D20: 자산총계 | E20: =IFERROR(VLOOKUP($D20,BS연결,MATCH(E$1,BS연결H,0),0)/100,"") | F20: =IFERROR(VLOOKUP($D20,BS연결,MATCH(F$1,BS연결H,0),0)/100,"") | G20: =IFERROR(VLOOKUP($D20,BS연결,MATCH(G$1,BS연결H,0),0)/100,"") | H20: =IFERROR(VLOOKUP($D20,BS연결,MATCH(H$1,BS연결H,0),0)/100,"") | I20: =IFERROR(VLOOKUP($D20,BS연결,MATCH(I$1,BS연결H,0),0)/100,"") | J20: =IFERROR(VLOOKUP($D20,BS연결,MATCH(J$1,BS연결H,0),0)/100,"") | K20: =IFERROR(VLOOKUP($D20,BS연결,MATCH(K$1,BS연결H,0),0)/100,"") | L20: =IFERROR(VLOOKUP($D20,BS연결,MATCH(L$1,BS연결H,0),0)/100,"") | ... AB20: =IFERROR(VLOOKUP($D20,BS연결,MATCH(AB$1,BS연결H,0),0)/100,"") | AC20: =IFERROR(AC21+AC22,"") | AD20: =IFERROR(AD21+AD22,"") | AE20: =AD20 | AF20: =IFERROR(AF21+AF22,"") | AG20: =IFERROR(AG21+AG22,"") | AH20: =IFERROR(AH21+AH22,"") | AI20: =IFERROR(AI21+AI22,"") | AJ20: =AI20 | AK20: =IFERROR(AK21+AK22,"") | AL20: =IFERROR(AL21+AL22,"") | AM20: =IFERROR(AM21+AM22,"") | AN20: =IFERROR(AN21+AN22,"") | AO20: =AN20
A21: 부채총계 | B21: 재무상태 | C21: 억원 | D21: 부채총계 | E21: =IFERROR(VLOOKUP($D21,BS연결,MATCH(E$1,BS연결H,0),0)/100,"") | F21: =IFERROR(VLOOKUP($D21,BS연결,MATCH(F$1,BS연결H,0),0)/100,"") | G21: =IFERROR(VLOOKUP($D21,BS연결,MATCH(G$1,BS연결H,0),0)/100,"") | H21: =IFERROR(VLOOKUP($D21,BS연결,MATCH(H$1,BS연결H,0),0)/100,"") | I21: =IFERROR(VLOOKUP($D21,BS연결,MATCH(I$1,BS연결H,0),0)/100,"") | J21: =IFERROR(VLOOKUP($D21,BS연결,MATCH(J$1,BS연결H,0),0)/100,"") | K21: =IFERROR(VLOOKUP($D21,BS연결,MATCH(K$1,BS연결H,0),0)/100,"") | L21: =IFERROR(VLOOKUP($D21,BS연결,MATCH(L$1,BS연결H,0),0)/100,"") | ... AB21: =IFERROR(VLOOKUP($D21,BS연결,MATCH(AB$1,BS연결H,0),0)/100,"") | AC21: =IFERROR(AB21*(1+변수!AC29),"") | AD21: =IFERROR(AC21*(1+변수!AD29),"") | AE21: =AD21 | AF21: =IFERROR(AD21*(1+변수!AF29),"") | AG21: =IFERROR(AF21*(1+변수!AG29),"") | AH21: =IFERROR(AG21*(1+변수!AH29),"") | AI21: =IFERROR(AH21*(1+변수!AI29),"") | AJ21: =AI21 | AK21: =IFERROR(AI21*(1+변수!AK29),"") | AL21: =IFERROR(AK21*(1+변수!AL29),"") | AM21: =IFERROR(AL21*(1+변수!AM29),"") | AN21: =IFERROR(AM21*(1+변수!AN29),"") | AO21: =AN21
A22: 자본총계 | B22: 재무상태 | C22: 억원 | D22: 자본총계 | E22: =IFERROR(VLOOKUP($D22,BS연결,MATCH(E$1,BS연결H,0),0)/100,"") | F22: =IFERROR(VLOOKUP($D22,BS연결,MATCH(F$1,BS연결H,0),0)/100,"") | G22: =IFERROR(VLOOKUP($D22,BS연결,MATCH(G$1,BS연결H,0),0)/100,"") | H22: =IFERROR(VLOOKUP($D22,BS연결,MATCH(H$1,BS연결H,0),0)/100,"") | I22: =IFERROR(VLOOKUP($D22,BS연결,MATCH(I$1,BS연결H,0),0)/100,"") | J22: =IFERROR(VLOOKUP($D22,BS연결,MATCH(J$1,BS연결H,0),0)/100,"") | K22: =IFERROR(VLOOKUP($D22,BS연결,MATCH(K$1,BS연결H,0),0)/100,"") | L22: =IFERROR(VLOOKUP($D22,BS연결,MATCH(L$1,BS연결H,0),0)/100,"") | ... AB22: =IFERROR(VLOOKUP($D22,BS연결,MATCH(AB$1,BS연결H,0),0)/100,"") | AC22: =IFERROR(AB22+AC17-변수!AC30,"") | AD22: =IFERROR(AC22+AD17-변수!AD30,"") | AE22: =AD22 | AF22: =IFERROR(AD22+AF17-변수!AF30,"") | AG22: =IFERROR(AF22+AG17-변수!AG30,"") | AH22: =IFERROR(AG22+AH17-변수!AH30,"") | AI22: =IFERROR(AH22+AI17-변수!AI30,"") | AJ22: =AI22 | AK22: =IFERROR(AI22+AK17-변수!AK30,"") | AL22: =IFERROR(AK22+AL17-변수!AL30,"") | AM22: =IFERROR(AL22+AM17-변수!AM30,"") | AN22: =IFERROR(AM22+AN17-변수!AN30,"") | AO22: =AN22
A23: 지배주주지분 | B23: 재무상태 | C23: 억원 | D23: 지배주주지분 | E23: =IFERROR(VLOOKUP($D23,BS연결,MATCH(E$1,BS연결H,0),0)/100,"") | F23: =IFERROR(VLOOKUP($D23,BS연결,MATCH(F$1,BS연결H,0),0)/100,"") | G23: =IFERROR(VLOOKUP($D23,BS연결,MATCH(G$1,BS연결H,0),0)/100,"") | H23: =IFERROR(VLOOKUP($D23,BS연결,MATCH(H$1,BS연결H,0),0)/100,"") | I23: =IFERROR(VLOOKUP($D23,BS연결,MATCH(I$1,BS연결H,0),0)/100,"") | J23: =IFERROR(VLOOKUP($D23,BS연결,MATCH(J$1,BS연결H,0),0)/100,"") | K23: =IFERROR(VLOOKUP($D23,BS연결,MATCH(K$1,BS연결H,0),0)/100,"") | L23: =IFERROR(VLOOKUP($D23,BS연결,MATCH(L$1,BS연결H,0),0)/100,"") | ... AB23: =IFERROR(VLOOKUP($D23,BS연결,MATCH(AB$1,BS연결H,0),0)/100,"") | AC23: =IFERROR(AB23+AC18-변수!AC31,"") | AD23: =IFERROR(AC23+AD18-변수!AD31,"") | AE23: =AD23 | AF23: =IFERROR(AD23+AF18-변수!AF31,"") | AG23: =IFERROR(AF23+AG18-변수!AG31,"") | AH23: =IFERROR(AG23+AH18-변수!AH31,"") | AI23: =IFERROR(AH23+AI18-변수!AI31,"") | AJ23: =AI23 | AK23: =IFERROR(AI23+AK18-변수!AK31,"") | AL23: =IFERROR(AK23+AL18-변수!AL31,"") | AM23: =IFERROR(AL23+AM18-변수!AM31,"") | AN23: =IFERROR(AM23+AN18-변수!AN31,"") | AO23: =AN23
A24: 총차입금 | B24: 재무상태 | C24: 억원 | D24: 총차입금 | E24: =IFERROR(VLOOKUP($D24,BS연결,MATCH(E$1,BS연결H,0),0)/100,"") | F24: =IFERROR(VLOOKUP($D24,BS연결,MATCH(F$1,BS연결H,0),0)/100,"") | G24: =IFERROR(VLOOKUP($D24,BS연결,MATCH(G$1,BS연결H,0),0)/100,"") | H24: =IFERROR(VLOOKUP($D24,BS연결,MATCH(H$1,BS연결H,0),0)/100,"") | I24: =IFERROR(VLOOKUP($D24,BS연결,MATCH(I$1,BS연결H,0),0)/100,"") | J24: =IFERROR(VLOOKUP($D24,BS연결,MATCH(J$1,BS연결H,0),0)/100,"") | K24: =IFERROR(VLOOKUP($D24,BS연결,MATCH(K$1,BS연결H,0),0)/100,"") | L24: =IFERROR(VLOOKUP($D24,BS연결,MATCH(L$1,BS연결H,0),0)/100,"") | ... AB24: =IFERROR(VLOOKUP($D24,BS연결,MATCH(AB$1,BS연결H,0),0)/100,"") | AC24: =IFERROR(AB24*(1+변수!AC32),"") | AD24: =IFERROR(AC24*(1+변수!AD32),"") | AE24: =AD24 | AF24: =IFERROR(AD24*(1+변수!AF32),"") | AG24: =IFERROR(AF24*(1+변수!AG32),"") | AH24: =IFERROR(AG24*(1+변수!AH32),"") | AI24: =IFERROR(AH24*(1+변수!AI32),"") | AJ24: =AI24 | AK24: =IFERROR(AI24*(1+변수!AK32),"") | AL24: =IFERROR(AK24*(1+변수!AL32),"") | AM24: =IFERROR(AL24*(1+변수!AM32),"") | AN24: =IFERROR(AM24*(1+변수!AN32),"") | AO24: =AN24
A25: 순차입금 | B25: 재무상태 | C25: 억원 | D25: 순차입금 | E25: =IFERROR(VLOOKUP($D25,BS연결,MATCH(E$1,BS연결H,0),0)/100,"") | F25: =IFERROR(VLOOKUP($D25,BS연결,MATCH(F$1,BS연결H,0),0)/100,"") | G25: =IFERROR(VLOOKUP($D25,BS연결,MATCH(G$1,BS연결H,0),0)/100,"") | H25: =IFERROR(VLOOKUP($D25,BS연결,MATCH(H$1,BS연결H,0),0)/100,"") | I25: =IFERROR(VLOOKUP($D25,BS연결,MATCH(I$1,BS연결H,0),0)/100,"") | J25: =IFERROR(VLOOKUP($D25,BS연결,MATCH(J$1,BS연결H,0),0)/100,"") | K25: =IFERROR(VLOOKUP($D25,BS연결,MATCH(K$1,BS연결H,0),0)/100,"") | L25: =IFERROR(VLOOKUP($D25,BS연결,MATCH(L$1,BS연결H,0),0)/100,"") | ... AB25: =IFERROR(VLOOKUP($D25,BS연결,MATCH(AB$1,BS연결H,0),0)/100,"") | AC25: =IFERROR(AB25*(1+변수!AC33),"") | AD25: =IFERROR(AC25*(1+변수!AD33),"") | AE25: =AD25 | AF25: =IFERROR(AD25*(1+변수!AF33),"") | AG25: =IFERROR(AF25*(1+변수!AG33),"") | AH25: =IFERROR(AG25*(1+변수!AH33),"") | AI25: =IFERROR(AH25*(1+변수!AI33),"") | AJ25: =AI25 | AK25: =IFERROR(AI25*(1+변수!AK33),"") | AL25: =IFERROR(AK25*(1+변수!AL33),"") | AM25: =IFERROR(AL25*(1+변수!AM33),"") | AN25: =IFERROR(AM25*(1+변수!AN33),"") | AO25: =AN25
A26: 이자발생자산 | B26: 재무상태 | C26: 억원 | D26: 이자발생자산 | E26: =IFERROR(VLOOKUP($D26,BS연결,MATCH(E$1,BS연결H,0),0)/100,"") | F26: =IFERROR(VLOOKUP($D26,BS연결,MATCH(F$1,BS연결H,0),0)/100,"") | G26: =IFERROR(VLOOKUP($D26,BS연결,MATCH(G$1,BS연결H,0),0)/100,"") | H26: =IFERROR(VLOOKUP($D26,BS연결,MATCH(H$1,BS연결H,0),0)/100,"") | I26: =IFERROR(VLOOKUP($D26,BS연결,MATCH(I$1,BS연결H,0),0)/100,"") | J26: =IFERROR(VLOOKUP($D26,BS연결,MATCH(J$1,BS연결H,0),0)/100,"") | K26: =IFERROR(VLOOKUP($D26,BS연결,MATCH(K$1,BS연결H,0),0)/100,"") | L26: =IFERROR(VLOOKUP($D26,BS연결,MATCH(L$1,BS연결H,0),0)/100,"") | ... AB26: =IFERROR(VLOOKUP($D26,BS연결,MATCH(AB$1,BS연결H,0),0)/100,"") | AC26: =IFERROR(AB26*(1+변수!AC34),"") | AD26: =IFERROR(AC26*(1+변수!AD34),"") | AE26: =AD26 | AF26: =IFERROR(AD26*(1+변수!AF34),"") | AG26: =IFERROR(AF26*(1+변수!AG34),"") | AH26: =IFERROR(AG26*(1+변수!AH34),"") | AI26: =IFERROR(AH26*(1+변수!AI34),"") | AJ26: =AI26 | AK26: =IFERROR(AI26*(1+변수!AK34),"") | AL26: =IFERROR(AK26*(1+변수!AL34),"") | AM26: =IFERROR(AL26*(1+변수!AM34),"") | AN26: =IFERROR(AM26*(1+변수!AN34),"") | AO26: =AN26
A27: 현금및현금성자산 | B27: 재무상태 | C27: 억원 | D27: 현금및현금성자산 | E27: =IFERROR(VLOOKUP($D27,BS연결,MATCH(E$1,BS연결H,0),0)/100,"") | F27: =IFERROR(VLOOKUP($D27,BS연결,MATCH(F$1,BS연결H,0),0)/100,"") | G27: =IFERROR(VLOOKUP($D27,BS연결,MATCH(G$1,BS연결H,0),0)/100,"") | H27: =IFERROR(VLOOKUP($D27,BS연결,MATCH(H$1,BS연결H,0),0)/100,"") | I27: =IFERROR(VLOOKUP($D27,BS연결,MATCH(I$1,BS연결H,0),0)/100,"") | J27: =IFERROR(VLOOKUP($D27,BS연결,MATCH(J$1,BS연결H,0),0)/100,"") | K27: =IFERROR(VLOOKUP($D27,BS연결,MATCH(K$1,BS연결H,0),0)/100,"") | L27: =IFERROR(VLOOKUP($D27,BS연결,MATCH(L$1,BS연결H,0),0)/100,"") | ... AB27: =IFERROR(VLOOKUP($D27,BS연결,MATCH(AB$1,BS연결H,0),0)/100,"") | AE27: =AD27 | AJ27: =AI27 | AO27: =AN27
A28: CAPEX | B28: 현금흐름 | C28: 억원 | D28: CAPEX | E28: =IFERROR(VLOOKUP($D28,BS연결,MATCH(E$1,BS연결H,0),0)/100,"") | G28: =IFERROR(VLOOKUP($D28,BS연결,MATCH(G$1,BS연결H,0),0)/100,"") | H28: =IFERROR(VLOOKUP($D28,BS연결,MATCH(H$1,BS연결H,0),0)/100,"") | I28: =IFERROR(VLOOKUP($D28,BS연결,MATCH(I$1,BS연결H,0),0)/100,"") | J28: =IFERROR(VLOOKUP($D28,BS연결,MATCH(J$1,BS연결H,0),0)/100,"") | K28: =IFERROR(VLOOKUP($D28,BS연결,MATCH(K$1,BS연결H,0),0)/100,"") | L28: =IFERROR(VLOOKUP($D28,BS연결,MATCH(L$1,BS연결H,0),0)/100,"") | M28: =IFERROR(VLOOKUP($D28,BS연결,MATCH(M$1,BS연결H,0),0)/100,"") | N28: =IFERROR(VLOOKUP($D28,BS연결,MATCH(N$1,BS연결H,0),0)/100,"") | ... AB28: =IFERROR(VLOOKUP($D28,BS연결,MATCH(AB$1,BS연결H,0),0)/100,"") | AC28: =IFERROR(X28*(1+변수!AC36),"") | AD28: =IFERROR(Y28*(1+변수!AD36),"") | AE28: =SUM(AA28:AD28) | AF28: =IFERROR(AA28*(1+변수!AF36),"") | AG28: =IFERROR(AB28*(1+변수!AG36),"") | AH28: =IFERROR(AC28*(1+변수!AH36),"") | AI28: =IFERROR(AD28*(1+변수!AI36),"") | AJ28: =SUM(AF28:AI28) | AK28: =IFERROR(AF28*(1+변수!AK36),"") | AL28: =IFERROR(AG28*(1+변수!AL36),"") | AM28: =IFERROR(AH28*(1+변수!AM36),"") | AN28: =IFERROR(AI28*(1+변수!AN36),"") | AO28: =SUM(AK28:AN28)
A29: 영업활동현금흐름 | B29: 현금흐름 | C29: 억원 | D29: 영업활동으로인한현금흐름 | E29: =IFERROR(VLOOKUP($D29,BS연결,MATCH(E$1,BS연결H,0),0)/100,"") | G29: =IFERROR(VLOOKUP($D29,BS연결,MATCH(G$1,BS연결H,0),0)/100,"") | H29: =IFERROR(VLOOKUP($D29,BS연결,MATCH(H$1,BS연결H,0),0)/100,"") | I29: =IFERROR(VLOOKUP($D29,BS연결,MATCH(I$1,BS연결H,0),0)/100,"") | J29: =IFERROR(VLOOKUP($D29,BS연결,MATCH(J$1,BS연결H,0),0)/100,"") | K29: =IFERROR(VLOOKUP($D29,BS연결,MATCH(K$1,BS연결H,0),0)/100,"") | L29: =IFERROR(VLOOKUP($D29,BS연결,MATCH(L$1,BS연결H,0),0)/100,"") | M29: =IFERROR(VLOOKUP($D29,BS연결,MATCH(M$1,BS연결H,0),0)/100,"") | N29: =IFERROR(VLOOKUP($D29,BS연결,MATCH(N$1,BS연결H,0),0)/100,"") | ... AB29: =IFERROR(VLOOKUP($D29,BS연결,MATCH(AB$1,BS연결H,0),0)/100,"") | AE29: =SUM(AA29:AD29) | AJ29: =SUM(AF29:AI29) | AO29: =SUM(AK29:AN29)
A30: 주식수 | B30: 주당 | C30: 백만주 | D30: 유통주식수 | E30: 7.8880322 | F30: =E30 | G30: 7.8880322 | H30: 7.8880322 | I30: 7.8880322 | J30: 7.8880322 | K30: =J30 | L30: 7.8880322 | M30: 7.8880322 | N30: 7.8880322 | O30: 7.8880322 | P30: =O30 | Q30: 7.8880322 | R30: 7.8880322 | S30: 7.8880322 | T30: 7.8630845 | U30: =T30 | V30: 7.5678505 | W30: 6.9497113 | X30: 6.9497113 | Y30: 6.9481164 | Z30: =Y30 | AA30: 6.9481164 | AB30: 6.945 | AC30: =IFERROR(AB30*(1+변수!AC38),"") | AD30: =IFERROR(AC30*(1+변수!AD38),"") | AE30: =AD30 | AF30: =IFERROR(AD30*(1+변수!AF38),"") | AG30: =IFERROR(AF30*(1+변수!AG38),"") | AH30: =IFERROR(AG30*(1+변수!AH38),"") | AI30: =IFERROR(AH30*(1+변수!AI38),"") | AJ30: =AI30 | AK30: =IFERROR(AI30*(1+변수!AK38),"") | AL30: =IFERROR(AK30*(1+변수!AL38),"") | AM30: =IFERROR(AL30*(1+변수!AM38),"") | AN30: =IFERROR(AM30*(1+변수!AN38),"") | AO30: =AN30
A31: EPS | B31: 주당 | C31: 원 | D31: EPS | E31: =IFERROR(E18*100/E30,"") | G31: =IFERROR(G18*100/G30,"") | H31: =IFERROR(H18*100/H30,"") | I31: =IFERROR(I18*100/I30,"") | J31: =IFERROR(J18*100/J30,"") | K31: =SUM(G31:J31) | L31: =IFERROR(L18*100/L30,"") | M31: =IFERROR(M18*100/M30,"") | N31: =IFERROR(N18*100/N30,"") | O31: =IFERROR(O18*100/O30,"") | P31: =SUM(L31:O31) | Q31: =IFERROR(Q18*100/Q30,"") | R31: =IFERROR(R18*100/R30,"") | S31: =IFERROR(S18*100/S30,"") | T31: =IFERROR(T18*100/T30,"") | U31: =SUM(Q31:T31) | V31: =IFERROR(V18*100/V30,"") | W31: =IFERROR(W18*100/W30,"") | X31: =IFERROR(X18*100/X30,"") | Y31: =IFERROR(Y18*100/Y30,"") | Z31: =SUM(V31:Y31) | AA31: =IFERROR(AA18*100/AA30,"") | AB31: =IFERROR(AB18*100/AB30,"") | AC31: =IFERROR(AC18*100/AC30,"") | AD31: =IFERROR(AD18*100/AD30,"") | AE31: =SUM(AA31:AD31) | AF31: =IFERROR(AF18*100/AF30,"") | AG31: =IFERROR(AG18*100/AG30,"") | AH31: =IFERROR(AH18*100/AH30,"") | AI31: =IFERROR(AI18*100/AI30,"") | AJ31: =SUM(AF31:AI31) | AK31: =IFERROR(AK18*100/AK30,"") | AL31: =IFERROR(AL18*100/AL30,"") | AM31: =IFERROR(AM18*100/AM30,"") | AN31: =IFERROR(AN18*100/AN30,"") | AO31: =SUM(AK31:AN31)
A32: BPS | B32: 주당 | C32: 원 | D32: BPS | E32: =IFERROR(E23*100/E30,"") | F32: =E32 | G32: =IFERROR(G23*100/G30,"") | H32: =IFERROR(H23*100/H30,"") | I32: =IFERROR(I23*100/I30,"") | J32: =IFERROR(J23*100/J30,"") | K32: =J32 | L32: =IFERROR(L23*100/L30,"") | M32: =IFERROR(M23*100/M30,"") | N32: =IFERROR(N23*100/N30,"") | O32: =IFERROR(O23*100/O30,"") | P32: =O32 | Q32: =IFERROR(Q23*100/Q30,"") | R32: =IFERROR(R23*100/R30,"") | S32: =IFERROR(S23*100/S30,"") | T32: =IFERROR(T23*100/T30,"") | U32: =T32 | V32: =IFERROR(V23*100/V30,"") | W32: =IFERROR(W23*100/W30,"") | X32: =IFERROR(X23*100/X30,"") | Y32: =IFERROR(Y23*100/Y30,"") | Z32: =Y32 | AA32: =IFERROR(AA23*100/AA30,"") | AB32: =IFERROR(AB23*100/AB30,"") | AC32: =IFERROR(AC23*100/AC30,"") | AD32: =IFERROR(AD23*100/AD30,"") | AE32: =AD32 | AF32: =IFERROR(AF23*100/AF30,"") | AG32: =IFERROR(AG23*100/AG30,"") | AH32: =IFERROR(AH23*100/AH30,"") | AI32: =IFERROR(AI23*100/AI30,"") | AJ32: =AI32 | AK32: =IFERROR(AK23*100/AK30,"") | AL32: =IFERROR(AL23*100/AL30,"") | AM32: =IFERROR(AM23*100/AM30,"") | AN32: =IFERROR(AN23*100/AN30,"") | AO32: =AN32
A33: DPS | B33: 주당 | C33: 원 | D33: DPS(보통주) | E33: 0 | F33: 0 | J33: 0 | K33: =SUM(G33:J33) | O33: 0 | P33: =SUM(L33:O33) | T33: 100 | U33: =SUM(Q33:T33) | Y33: 100 | Z33: =SUM(V33:Y33) | AD33: =변수!AD39 | AE33: =SUM(AA33:AD33) | AI33: =변수!AI39 | AJ33: =SUM(AF33:AI33) | AN33: =변수!AN39 | AO33: =SUM(AK33:AN33)
A34: PER | B34: 주당 | C34: 배 | D34: PER | F34: =E34 | I34: =IFERROR(변수!I18/(E31+G31+H31+I31),"") | J34: =IFERROR(변수!J18/(G31+H31+I31+J31),"") | K34: =J34 | L34: =IFERROR(변수!L18/(H31+I31+J31+L31),"") | M34: =IFERROR(변수!M18/(I31+J31+L31+M31),"") | N34: =IFERROR(변수!N18/(J31+L31+M31+N31),"") | O34: =IFERROR(변수!O18/(L31+M31+N31+O31),"") | P34: =O34 | Q34: =IFERROR(변수!Q18/(M31+N31+O31+Q31),"") | R34: =IFERROR(변수!R18/(N31+O31+Q31+R31),"") | S34: =IFERROR(변수!S18/(O31+Q31+R31+S31),"") | U34: =T34 | Z34: =Y34 | AB34: =IFERROR(변수!AB18/(X31+Y31+AA31+AB31),"") | AC34: =IFERROR(변수!$D$42/(Y31+AA31+AB31+AC31),"") | AD34: =IFERROR(변수!$D$42/(AA31+AB31+AC31+AD31),"") | AE34: =AD34 | AF34: =IFERROR(변수!$D$42/(AB31+AC31+AD31+AF31),"") | AJ34: =AI34 | AO34: =AN34
A35: PBR | B35: 주당 | C35: 배 | D35: PBR | E35: =IFERROR(변수!E18/E32,"") | F35: =E35 | G35: =IFERROR(변수!G18/G32,"") | H35: =IFERROR(변수!H18/H32,"") | I35: =IFERROR(변수!I18/I32,"") | J35: =IFERROR(변수!J18/J32,"") | K35: =J35 | L35: =IFERROR(변수!L18/L32,"") | M35: =IFERROR(변수!M18/M32,"") | N35: =IFERROR(변수!N18/N32,"") | O35: =IFERROR(변수!O18/O32,"") | P35: =O35 | Q35: =IFERROR(변수!Q18/Q32,"") | R35: =IFERROR(변수!R18/R32,"") | S35: =IFERROR(변수!S18/S32,"") | T35: =IFERROR(변수!T18/T32,"") | U35: =T35 | V35: =IFERROR(변수!V18/V32,"") | W35: =IFERROR(변수!W18/W32,"") | X35: =IFERROR(변수!X18/X32,"") | Y35: =IFERROR(변수!Y18/Y32,"") | Z35: =Y35 | AA35: =IFERROR(변수!AA18/AA32,"") | AB35: =IFERROR(변수!AB18/AB32,"") | AC35: =IFERROR(변수!$D$42/AC32,"") | AD35: =IFERROR(변수!$D$42/AD32,"") | AE35: =AD35 | AF35: =IFERROR(변수!$D$42/AF32,"") | AG35: =IFERROR(변수!$D$42/AG32,"") | AH35: =IFERROR(변수!$D$42/AH32,"") | AI35: =IFERROR(변수!$D$42/AI32,"") | AJ35: =AI35 | AK35: =IFERROR(변수!$D$42/AK32,"") | AL35: =IFERROR(변수!$D$42/AL32,"") | AM35: =IFERROR(변수!$D$42/AM32,"") | AN35: =IFERROR(변수!$D$42/AN32,"") | AO35: =AN35
A36: 매출전사 | B36: 사업부 | C36: 억원 | D36: 매출 전사(부문 미분리) | E36: 192.25 | G36: 154.91 | H36: 171.63 | I36: 184.52 | J36: 255.82 | K36: =SUM(G36:J36) | L36: 263.05 | M36: 249.75 | N36: 173.49 | O36: 229.06 | P36: =SUM(L36:O36) | Q36: 255.29 | R36: 255.68 | S36: 238.54 | T36: 359.86 | U36: =SUM(Q36:T36) | V36: 239.45 | W36: 285.59 | X36: 285.56 | Y36: 490.43 | Z36: =SUM(V36:Y36) | AA36: 319.14 | AB36: 367.92 | AC36: =IFERROR(AC5,"") | AD36: =IFERROR(AD5,"") | AE36: =SUM(AA36:AD36) | AF36: =IFERROR(AF5,"") | AG36: =IFERROR(AG5,"") | AH36: =IFERROR(AH5,"") | AI36: =IFERROR(AI5,"") | AJ36: =SUM(AF36:AI36) | AK36: =IFERROR(AK5,"") | AL36: =IFERROR(AL5,"") | AM36: =IFERROR(AM5,"") | AN36: =IFERROR(AN5,"") | AO36: =SUM(AK36:AN36)
A37: OP전사 | B37: 사업부 | C37: 억원 | D37: OP 전사(부문 미분리) | E37: 23.75 | G37: -17.22 | H37: -15.54 | I37: 1.7 | J37: 39.77 | K37: =SUM(G37:J37) | L37: 20.72 | M37: 17.96 | N37: -20.17 | O37: -29.55 | P37: =SUM(L37:O37) | Q37: -0.16 | R37: -20.31 | S37: -13.38 | T37: -14.41 | U37: =SUM(Q37:T37) | V37: -9.62 | W37: 3.4 | X37: -50.22 | Y37: 49.97 | Z37: =SUM(V37:Y37) | AA37: 5.34 | AB37: 31.44 | AC37: =IFERROR(AC9,"") | AD37: =IFERROR(AD9,"") | AE37: =SUM(AA37:AD37) | AF37: =IFERROR(AF9,"") | AG37: =IFERROR(AG9,"") | AH37: =IFERROR(AH9,"") | AI37: =IFERROR(AI9,"") | AJ37: =SUM(AF37:AI37) | AK37: =IFERROR(AK9,"") | AL37: =IFERROR(AL9,"") | AM37: =IFERROR(AM9,"") | AN37: =IFERROR(AN9,"") | AO37: =SUM(AK37:AN37)
B38: 비율(참고)
A39: NPM | C39: % | D39: 지배주주순이익 / 매출액 | E39: =IFERROR(E18/E5,"") | F39: =IFERROR(F18/F5,"") | G39: =IFERROR(G18/G5,"") | H39: =IFERROR(H18/H5,"") | I39: =IFERROR(I18/I5,"") | J39: =IFERROR(J18/J5,"") | K39: =IFERROR(K18/K5,"") | L39: =IFERROR(L18/L5,"") | ... AO39: =IFERROR(AO18/AO5,"")
A40: 매출원가율 | C40: % | D40: 매출원가 / 매출액 | E40: =IFERROR(E6/E5,"") | F40: =IFERROR(F6/F5,"") | G40: =IFERROR(G6/G5,"") | H40: =IFERROR(H6/H5,"") | I40: =IFERROR(I6/I5,"") | J40: =IFERROR(J6/J5,"") | K40: =IFERROR(K6/K5,"") | L40: =IFERROR(L6/L5,"") | ... AO40: =IFERROR(AO6/AO5,"")
A41: 판관비율 | C41: % | D41: 판관비 / 매출액 | E41: =IFERROR(E8/E5,"") | F41: =IFERROR(F8/F5,"") | G41: =IFERROR(G8/G5,"") | H41: =IFERROR(H8/H5,"") | I41: =IFERROR(I8/I5,"") | J41: =IFERROR(J8/J5,"") | K41: =IFERROR(K8/K5,"") | L41: =IFERROR(L8/L5,"") | ... AO41: =IFERROR(AO8/AO5,"")

Sheet 분기
C1: 이름: 분기H — subQ 를 이름으로 VLOOKUP(억원) | E1: 4Q21 | F1: 1Q22 | G1: 2Q22 | H1: 3Q22 | I1: 4Q22 | J1: 1Q23 | K1: 2Q23 | L1: 3Q23 | M1: 4Q23 | N1: 1Q24 | O1: 2Q24 | P1: 3Q24 | Q1: 4Q24 | R1: 1Q25 | S1: 2Q25 | T1: 3Q25 | U1: 4Q25 | V1: 1Q26 | W1: 2Q26 | X1: 3Q26 | Y1: 4Q26 | Z1: 1Q27 | AA1: 2Q27 | AB1: 3Q27 | AC1: 4Q27 | AD1: 1Q28 | AE1: 2Q28 | AF1: 3Q28 | AG1: 4Q28
C2: 종가: | D2: =변수!D42
C3: 기준일: | D3: 20261008 | E3: 1 | F3: 2 | G3: 3 | H3: 4 | I3: 5 | J3: 6 | K3: 7 | L3: 8 | M3: 9 | N3: 10 | O3: 11 | P3: 12 | Q3: 13 | R3: 14 | S3: 15 | T3: 16 | U3: 17 | V3: 18 | W3: 19 | X3: 20 | Y3: 21 | Z3: 22 | AA3: 23 | AB3: 24 | AC3: 25 | AD3: 26 | AE3: 27 | AF3: 28 | AG3: 29
E4: 2021.12 | F4: 2022.03 | G4: 2022.06 | H4: 2022.09 | I4: 2022.12 | J4: 2023.03 | K4: 2023.06 | L4: 2023.09 | M4: 2023.12 | N4: 2024.03 | O4: 2024.06 | P4: 2024.09 | Q4: 2024.12 | R4: 2025.03 | S4: 2025.06 | T4: 2025.09 | U4: 2025.12 | V4: 2026.03 | W4: 2026.06 | X4: 2026.09 | Y4: 2026.12 | Z4: 2027.03 | AA4: 2027.06 | AB4: 2027.09 | AC4: 2027.12 | AD4: 2028.03 | AE4: 2028.06 | AF4: 2028.09 | AG4: 2028.12
A5: 매출액 | D5: 매출액 | E5: =IFERROR(VLOOKUP($A5,subQ,MATCH(E$1,SUBQH,0),0),"") | F5: =IFERROR(VLOOKUP($A5,subQ,MATCH(F$1,SUBQH,0),0),"") | G5: =IFERROR(VLOOKUP($A5,subQ,MATCH(G$1,SUBQH,0),0),"") | H5: =IFERROR(VLOOKUP($A5,subQ,MATCH(H$1,SUBQH,0),0),"") | I5: =IFERROR(VLOOKUP($A5,subQ,MATCH(I$1,SUBQH,0),0),"") | J5: =IFERROR(VLOOKUP($A5,subQ,MATCH(J$1,SUBQH,0),0),"") | K5: =IFERROR(VLOOKUP($A5,subQ,MATCH(K$1,SUBQH,0),0),"") | L5: =IFERROR(VLOOKUP($A5,subQ,MATCH(L$1,SUBQH,0),0),"") | ... AG5: =IFERROR(VLOOKUP($A5,subQ,MATCH(AG$1,SUBQH,0),0),"")
A6: 매출원가 | D6: 매출원가 | E6: =IFERROR(VLOOKUP($A6,subQ,MATCH(E$1,SUBQH,0),0),"") | F6: =IFERROR(VLOOKUP($A6,subQ,MATCH(F$1,SUBQH,0),0),"") | G6: =IFERROR(VLOOKUP($A6,subQ,MATCH(G$1,SUBQH,0),0),"") | H6: =IFERROR(VLOOKUP($A6,subQ,MATCH(H$1,SUBQH,0),0),"") | I6: =IFERROR(VLOOKUP($A6,subQ,MATCH(I$1,SUBQH,0),0),"") | J6: =IFERROR(VLOOKUP($A6,subQ,MATCH(J$1,SUBQH,0),0),"") | K6: =IFERROR(VLOOKUP($A6,subQ,MATCH(K$1,SUBQH,0),0),"") | L6: =IFERROR(VLOOKUP($A6,subQ,MATCH(L$1,SUBQH,0),0),"") | ... AG6: =IFERROR(VLOOKUP($A6,subQ,MATCH(AG$1,SUBQH,0),0),"")
A7: 매출총이익 | D7: 매출총이익 | E7: =IFERROR(VLOOKUP($A7,subQ,MATCH(E$1,SUBQH,0),0),"") | F7: =IFERROR(VLOOKUP($A7,subQ,MATCH(F$1,SUBQH,0),0),"") | G7: =IFERROR(VLOOKUP($A7,subQ,MATCH(G$1,SUBQH,0),0),"") | H7: =IFERROR(VLOOKUP($A7,subQ,MATCH(H$1,SUBQH,0),0),"") | I7: =IFERROR(VLOOKUP($A7,subQ,MATCH(I$1,SUBQH,0),0),"") | J7: =IFERROR(VLOOKUP($A7,subQ,MATCH(J$1,SUBQH,0),0),"") | K7: =IFERROR(VLOOKUP($A7,subQ,MATCH(K$1,SUBQH,0),0),"") | L7: =IFERROR(VLOOKUP($A7,subQ,MATCH(L$1,SUBQH,0),0),"") | ... AG7: =IFERROR(VLOOKUP($A7,subQ,MATCH(AG$1,SUBQH,0),0),"")
A8: 판관비 | D8: 판매비와관리비 | E8: =IFERROR(VLOOKUP($A8,subQ,MATCH(E$1,SUBQH,0),0),"") | F8: =IFERROR(VLOOKUP($A8,subQ,MATCH(F$1,SUBQH,0),0),"") | G8: =IFERROR(VLOOKUP($A8,subQ,MATCH(G$1,SUBQH,0),0),"") | H8: =IFERROR(VLOOKUP($A8,subQ,MATCH(H$1,SUBQH,0),0),"") | I8: =IFERROR(VLOOKUP($A8,subQ,MATCH(I$1,SUBQH,0),0),"") | J8: =IFERROR(VLOOKUP($A8,subQ,MATCH(J$1,SUBQH,0),0),"") | K8: =IFERROR(VLOOKUP($A8,subQ,MATCH(K$1,SUBQH,0),0),"") | L8: =IFERROR(VLOOKUP($A8,subQ,MATCH(L$1,SUBQH,0),0),"") | ... AG8: =IFERROR(VLOOKUP($A8,subQ,MATCH(AG$1,SUBQH,0),0),"")
A9: 영업이익 | D9: 영업이익 | E9: =IFERROR(VLOOKUP($A9,subQ,MATCH(E$1,SUBQH,0),0),"") | F9: =IFERROR(VLOOKUP($A9,subQ,MATCH(F$1,SUBQH,0),0),"") | G9: =IFERROR(VLOOKUP($A9,subQ,MATCH(G$1,SUBQH,0),0),"") | H9: =IFERROR(VLOOKUP($A9,subQ,MATCH(H$1,SUBQH,0),0),"") | I9: =IFERROR(VLOOKUP($A9,subQ,MATCH(I$1,SUBQH,0),0),"") | J9: =IFERROR(VLOOKUP($A9,subQ,MATCH(J$1,SUBQH,0),0),"") | K9: =IFERROR(VLOOKUP($A9,subQ,MATCH(K$1,SUBQH,0),0),"") | L9: =IFERROR(VLOOKUP($A9,subQ,MATCH(L$1,SUBQH,0),0),"") | ... AG9: =IFERROR(VLOOKUP($A9,subQ,MATCH(AG$1,SUBQH,0),0),"")
A10: OPM | D10: 영업이익률 | E10: =IFERROR(VLOOKUP($A10,subQ,MATCH(E$1,SUBQH,0),0),"") | F10: =IFERROR(VLOOKUP($A10,subQ,MATCH(F$1,SUBQH,0),0),"") | G10: =IFERROR(VLOOKUP($A10,subQ,MATCH(G$1,SUBQH,0),0),"") | H10: =IFERROR(VLOOKUP($A10,subQ,MATCH(H$1,SUBQH,0),0),"") | I10: =IFERROR(VLOOKUP($A10,subQ,MATCH(I$1,SUBQH,0),0),"") | J10: =IFERROR(VLOOKUP($A10,subQ,MATCH(J$1,SUBQH,0),0),"") | K10: =IFERROR(VLOOKUP($A10,subQ,MATCH(K$1,SUBQH,0),0),"") | L10: =IFERROR(VLOOKUP($A10,subQ,MATCH(L$1,SUBQH,0),0),"") | ... AG10: =IFERROR(VLOOKUP($A10,subQ,MATCH(AG$1,SUBQH,0),0),"")
A11: 금융손익 | D11: 금융손익(이자·환 포함) | E11: =IFERROR(VLOOKUP($A11,subQ,MATCH(E$1,SUBQH,0),0),"") | F11: =IFERROR(VLOOKUP($A11,subQ,MATCH(F$1,SUBQH,0),0),"") | G11: =IFERROR(VLOOKUP($A11,subQ,MATCH(G$1,SUBQH,0),0),"") | H11: =IFERROR(VLOOKUP($A11,subQ,MATCH(H$1,SUBQH,0),0),"") | I11: =IFERROR(VLOOKUP($A11,subQ,MATCH(I$1,SUBQH,0),0),"") | J11: =IFERROR(VLOOKUP($A11,subQ,MATCH(J$1,SUBQH,0),0),"") | K11: =IFERROR(VLOOKUP($A11,subQ,MATCH(K$1,SUBQH,0),0),"") | L11: =IFERROR(VLOOKUP($A11,subQ,MATCH(L$1,SUBQH,0),0),"") | ... AG11: =IFERROR(VLOOKUP($A11,subQ,MATCH(AG$1,SUBQH,0),0),"")
A12: 이자손익 | D12: 이자손익(이자수익 − 이자비용) | E12: =IFERROR(VLOOKUP($A12,subQ,MATCH(E$1,SUBQH,0),0),"") | F12: =IFERROR(VLOOKUP($A12,subQ,MATCH(F$1,SUBQH,0),0),"") | G12: =IFERROR(VLOOKUP($A12,subQ,MATCH(G$1,SUBQH,0),0),"") | H12: =IFERROR(VLOOKUP($A12,subQ,MATCH(H$1,SUBQH,0),0),"") | I12: =IFERROR(VLOOKUP($A12,subQ,MATCH(I$1,SUBQH,0),0),"") | J12: =IFERROR(VLOOKUP($A12,subQ,MATCH(J$1,SUBQH,0),0),"") | K12: =IFERROR(VLOOKUP($A12,subQ,MATCH(K$1,SUBQH,0),0),"") | L12: =IFERROR(VLOOKUP($A12,subQ,MATCH(L$1,SUBQH,0),0),"") | ... AG12: =IFERROR(VLOOKUP($A12,subQ,MATCH(AG$1,SUBQH,0),0),"")
A13: 기타영업외손익 | D13: 기타영업외손익 | E13: =IFERROR(VLOOKUP($A13,subQ,MATCH(E$1,SUBQH,0),0),"") | F13: =IFERROR(VLOOKUP($A13,subQ,MATCH(F$1,SUBQH,0),0),"") | G13: =IFERROR(VLOOKUP($A13,subQ,MATCH(G$1,SUBQH,0),0),"") | H13: =IFERROR(VLOOKUP($A13,subQ,MATCH(H$1,SUBQH,0),0),"") | I13: =IFERROR(VLOOKUP($A13,subQ,MATCH(I$1,SUBQH,0),0),"") | J13: =IFERROR(VLOOKUP($A13,subQ,MATCH(J$1,SUBQH,0),0),"") | K13: =IFERROR(VLOOKUP($A13,subQ,MATCH(K$1,SUBQH,0),0),"") | L13: =IFERROR(VLOOKUP($A13,subQ,MATCH(L$1,SUBQH,0),0),"") | ... AG13: =IFERROR(VLOOKUP($A13,subQ,MATCH(AG$1,SUBQH,0),0),"")
A14: 지분법손익 | D14: 지분법손익 | E14: =IFERROR(VLOOKUP($A14,subQ,MATCH(E$1,SUBQH,0),0),"") | F14: =IFERROR(VLOOKUP($A14,subQ,MATCH(F$1,SUBQH,0),0),"") | G14: =IFERROR(VLOOKUP($A14,subQ,MATCH(G$1,SUBQH,0),0),"") | H14: =IFERROR(VLOOKUP($A14,subQ,MATCH(H$1,SUBQH,0),0),"") | I14: =IFERROR(VLOOKUP($A14,subQ,MATCH(I$1,SUBQH,0),0),"") | J14: =IFERROR(VLOOKUP($A14,subQ,MATCH(J$1,SUBQH,0),0),"") | K14: =IFERROR(VLOOKUP($A14,subQ,MATCH(K$1,SUBQH,0),0),"") | L14: =IFERROR(VLOOKUP($A14,subQ,MATCH(L$1,SUBQH,0),0),"") | ... AG14: =IFERROR(VLOOKUP($A14,subQ,MATCH(AG$1,SUBQH,0),0),"")
A15: 세전이익 | D15: 법인세비용차감전이익 | E15: =IFERROR(VLOOKUP($A15,subQ,MATCH(E$1,SUBQH,0),0),"") | F15: =IFERROR(VLOOKUP($A15,subQ,MATCH(F$1,SUBQH,0),0),"") | G15: =IFERROR(VLOOKUP($A15,subQ,MATCH(G$1,SUBQH,0),0),"") | H15: =IFERROR(VLOOKUP($A15,subQ,MATCH(H$1,SUBQH,0),0),"") | I15: =IFERROR(VLOOKUP($A15,subQ,MATCH(I$1,SUBQH,0),0),"") | J15: =IFERROR(VLOOKUP($A15,subQ,MATCH(J$1,SUBQH,0),0),"") | K15: =IFERROR(VLOOKUP($A15,subQ,MATCH(K$1,SUBQH,0),0),"") | L15: =IFERROR(VLOOKUP($A15,subQ,MATCH(L$1,SUBQH,0),0),"") | ... AG15: =IFERROR(VLOOKUP($A15,subQ,MATCH(AG$1,SUBQH,0),0),"")
A16: 법인세비용 | D16: 법인세비용 | E16: =IFERROR(VLOOKUP($A16,subQ,MATCH(E$1,SUBQH,0),0),"") | F16: =IFERROR(VLOOKUP($A16,subQ,MATCH(F$1,SUBQH,0),0),"") | G16: =IFERROR(VLOOKUP($A16,subQ,MATCH(G$1,SUBQH,0),0),"") | H16: =IFERROR(VLOOKUP($A16,subQ,MATCH(H$1,SUBQH,0),0),"") | I16: =IFERROR(VLOOKUP($A16,subQ,MATCH(I$1,SUBQH,0),0),"") | J16: =IFERROR(VLOOKUP($A16,subQ,MATCH(J$1,SUBQH,0),0),"") | K16: =IFERROR(VLOOKUP($A16,subQ,MATCH(K$1,SUBQH,0),0),"") | L16: =IFERROR(VLOOKUP($A16,subQ,MATCH(L$1,SUBQH,0),0),"") | ... AG16: =IFERROR(VLOOKUP($A16,subQ,MATCH(AG$1,SUBQH,0),0),"")
... A38: NPM | D38: NPM | E38: =IFERROR(VLOOKUP($A38,subQ,MATCH(E$1,SUBQH,0),0),"") | F38: =IFERROR(VLOOKUP($A38,subQ,MATCH(F$1,SUBQH,0),0),"") | G38: =IFERROR(VLOOKUP($A38,subQ,MATCH(G$1,SUBQH,0),0),"") | H38: =IFERROR(VLOOKUP($A38,subQ,MATCH(H$1,SUBQH,0),0),"") | I38: =IFERROR(VLOOKUP($A38,subQ,MATCH(I$1,SUBQH,0),0),"") | J38: =IFERROR(VLOOKUP($A38,subQ,MATCH(J$1,SUBQH,0),0),"") | K38: =IFERROR(VLOOKUP($A38,subQ,MATCH(K$1,SUBQH,0),0),"") | L38: =IFERROR(VLOOKUP($A38,subQ,MATCH(L$1,SUBQH,0),0),"") | ... AG38: =IFERROR(VLOOKUP($A38,subQ,MATCH(AG$1,SUBQH,0),0),"")
A39: 매출액 YoY | D39: 매출액 YoY | I39: =IFERROR(I5/E5-1,"") | J39: =IFERROR(J5/F5-1,"") | K39: =IFERROR(K5/G5-1,"") | L39: =IFERROR(L5/H5-1,"") | M39: =IFERROR(M5/I5-1,"") | N39: =IFERROR(N5/J5-1,"") | O39: =IFERROR(O5/K5-1,"") | P39: =IFERROR(P5/L5-1,"") | ... AG39: =IFERROR(AG5/AC5-1,"")
A40: 영업이익 YoY | D40: 영업이익 YoY | I40: =IFERROR(I9/E9-1,"") | J40: =IFERROR(J9/F9-1,"") | K40: =IFERROR(K9/G9-1,"") | L40: =IFERROR(L9/H9-1,"") | M40: =IFERROR(M9/I9-1,"") | N40: =IFERROR(N9/J9-1,"") | O40: =IFERROR(O9/K9-1,"") | P40: =IFERROR(P9/L9-1,"") | ... AG40: =IFERROR(AG9/AC9-1,"")
A41: 지배주주순이익 YoY | D41: 지배주주순이익 YoY | I41: =IFERROR(I18/E18-1,"") | J41: =IFERROR(J18/F18-1,"") | K41: =IFERROR(K18/G18-1,"") | L41: =IFERROR(L18/H18-1,"") | M41: =IFERROR(M18/I18-1,"") | N41: =IFERROR(N18/J18-1,"") | O41: =IFERROR(O18/K18-1,"") | P41: =IFERROR(P18/L18-1,"") | ... AG41: =IFERROR(AG18/AC18-1,"")

Sheet 연간예상
C1: 이름: 연간예상H — subQ 를 이름으로 VLOOKUP(억원) | E1: 2021 | F1: 2022 | G1: 2023 | H1: 2024 | I1: 2025 | J1: 2026 | K1: 2027 | L1: 2028
C2: 종가: | D2: =변수!D42
C3: 기준일: | D3: 20261008 | E3: 1 | F3: 2 | G3: 3 | H3: 4 | I3: 5 | J3: 6 | K3: 7 | L3: 8
E4: 2021.12A | F4: 2022.12A | G4: 2023.12A | H4: 2024.12A | I4: 2025.12A | J4: 2026.12A | K4: 2027.12A | L4: 2028.12A
A5: 매출액 | D5: 매출액 | E5: =IFERROR(VLOOKUP($A5,subQ,MATCH(E$1,SUBQH,0),0),"") | F5: =IFERROR(VLOOKUP($A5,subQ,MATCH(F$1,SUBQH,0),0),"") | G5: =IFERROR(VLOOKUP($A5,subQ,MATCH(G$1,SUBQH,0),0),"") | H5: =IFERROR(VLOOKUP($A5,subQ,MATCH(H$1,SUBQH,0),0),"") | I5: =IFERROR(VLOOKUP($A5,subQ,MATCH(I$1,SUBQH,0),0),"") | J5: =IFERROR(VLOOKUP($A5,subQ,MATCH(J$1,SUBQH,0),0),"") | K5: =IFERROR(VLOOKUP($A5,subQ,MATCH(K$1,SUBQH,0),0),"") | L5: =IFERROR(VLOOKUP($A5,subQ,MATCH(L$1,SUBQH,0),0),"")
A6: 매출원가 | D6: 매출원가 | E6: =IFERROR(VLOOKUP($A6,subQ,MATCH(E$1,SUBQH,0),0),"") | F6: =IFERROR(VLOOKUP($A6,subQ,MATCH(F$1,SUBQH,0),0),"") | G6: =IFERROR(VLOOKUP($A6,subQ,MATCH(G$1,SUBQH,0),0),"") | H6: =IFERROR(VLOOKUP($A6,subQ,MATCH(H$1,SUBQH,0),0),"") | I6: =IFERROR(VLOOKUP($A6,subQ,MATCH(I$1,SUBQH,0),0),"") | J6: =IFERROR(VLOOKUP($A6,subQ,MATCH(J$1,SUBQH,0),0),"") | K6: =IFERROR(VLOOKUP($A6,subQ,MATCH(K$1,SUBQH,0),0),"") | L6: =IFERROR(VLOOKUP($A6,subQ,MATCH(L$1,SUBQH,0),0),"")
A7: 매출총이익 | D7: 매출총이익 | E7: =IFERROR(VLOOKUP($A7,subQ,MATCH(E$1,SUBQH,0),0),"") | F7: =IFERROR(VLOOKUP($A7,subQ,MATCH(F$1,SUBQH,0),0),"") | G7: =IFERROR(VLOOKUP($A7,subQ,MATCH(G$1,SUBQH,0),0),"") | H7: =IFERROR(VLOOKUP($A7,subQ,MATCH(H$1,SUBQH,0),0),"") | I7: =IFERROR(VLOOKUP($A7,subQ,MATCH(I$1,SUBQH,0),0),"") | J7: =IFERROR(VLOOKUP($A7,subQ,MATCH(J$1,SUBQH,0),0),"") | K7: =IFERROR(VLOOKUP($A7,subQ,MATCH(K$1,SUBQH,0),0),"") | L7: =IFERROR(VLOOKUP($A7,subQ,MATCH(L$1,SUBQH,0),0),"")
A8: 판관비 | D8: 판매비와관리비 | E8: =IFERROR(VLOOKUP($A8,subQ,MATCH(E$1,SUBQH,0),0),"") | F8: =IFERROR(VLOOKUP($A8,subQ,MATCH(F$1,SUBQH,0),0),"") | G8: =IFERROR(VLOOKUP($A8,subQ,MATCH(G$1,SUBQH,0),0),"") | H8: =IFERROR(VLOOKUP($A8,subQ,MATCH(H$1,SUBQH,0),0),"") | I8: =IFERROR(VLOOKUP($A8,subQ,MATCH(I$1,SUBQH,0),0),"") | J8: =IFERROR(VLOOKUP($A8,subQ,MATCH(J$1,SUBQH,0),0),"") | K8: =IFERROR(VLOOKUP($A8,subQ,MATCH(K$1,SUBQH,0),0),"") | L8: =IFERROR(VLOOKUP($A8,subQ,MATCH(L$1,SUBQH,0),0),"")
A9: 영업이익 | D9: 영업이익 | E9: =IFERROR(VLOOKUP($A9,subQ,MATCH(E$1,SUBQH,0),0),"") | F9: =IFERROR(VLOOKUP($A9,subQ,MATCH(F$1,SUBQH,0),0),"") | G9: =IFERROR(VLOOKUP($A9,subQ,MATCH(G$1,SUBQH,0),0),"") | H9: =IFERROR(VLOOKUP($A9,subQ,MATCH(H$1,SUBQH,0),0),"") | I9: =IFERROR(VLOOKUP($A9,subQ,MATCH(I$1,SUBQH,0),0),"") | J9: =IFERROR(VLOOKUP($A9,subQ,MATCH(J$1,SUBQH,0),0),"") | K9: =IFERROR(VLOOKUP($A9,subQ,MATCH(K$1,SUBQH,0),0),"") | L9: =IFERROR(VLOOKUP($A9,subQ,MATCH(L$1,SUBQH,0),0),"")
A10: OPM | D10: 영업이익률 | E10: =IFERROR(VLOOKUP($A10,subQ,MATCH(E$1,SUBQH,0),0),"") | F10: =IFERROR(VLOOKUP($A10,subQ,MATCH(F$1,SUBQH,0),0),"") | G10: =IFERROR(VLOOKUP($A10,subQ,MATCH(G$1,SUBQH,0),0),"") | H10: =IFERROR(VLOOKUP($A10,subQ,MATCH(H$1,SUBQH,0),0),"") | I10: =IFERROR(VLOOKUP($A10,subQ,MATCH(I$1,SUBQH,0),0),"") | J10: =IFERROR(VLOOKUP($A10,subQ,MATCH(J$1,SUBQH,0),0),"") | K10: =IFERROR(VLOOKUP($A10,subQ,MATCH(K$1,SUBQH,0),0),"") | L10: =IFERROR(VLOOKUP($A10,subQ,MATCH(L$1,SUBQH,0),0),"")
A11: 금융손익 | D11: 금융손익(이자·환 포함) | E11: =IFERROR(VLOOKUP($A11,subQ,MATCH(E$1,SUBQH,0),0),"") | F11: =IFERROR(VLOOKUP($A11,subQ,MATCH(F$1,SUBQH,0),0),"") | G11: =IFERROR(VLOOKUP($A11,subQ,MATCH(G$1,SUBQH,0),0),"") | H11: =IFERROR(VLOOKUP($A11,subQ,MATCH(H$1,SUBQH,0),0),"") | I11: =IFERROR(VLOOKUP($A11,subQ,MATCH(I$1,SUBQH,0),0),"") | J11: =IFERROR(VLOOKUP($A11,subQ,MATCH(J$1,SUBQH,0),0),"") | K11: =IFERROR(VLOOKUP($A11,subQ,MATCH(K$1,SUBQH,0),0),"") | L11: =IFERROR(VLOOKUP($A11,subQ,MATCH(L$1,SUBQH,0),0),"")
A12: 이자손익 | D12: 이자손익(이자수익 − 이자비용) | E12: =IFERROR(VLOOKUP($A12,subQ,MATCH(E$1,SUBQH,0),0),"") | F12: =IFERROR(VLOOKUP($A12,subQ,MATCH(F$1,SUBQH,0),0),"") | G12: =IFERROR(VLOOKUP($A12,subQ,MATCH(G$1,SUBQH,0),0),"") | H12: =IFERROR(VLOOKUP($A12,subQ,MATCH(H$1,SUBQH,0),0),"") | I12: =IFERROR(VLOOKUP($A12,subQ,MATCH(I$1,SUBQH,0),0),"") | J12: =IFERROR(VLOOKUP($A12,subQ,MATCH(J$1,SUBQH,0),0),"") | K12: =IFERROR(VLOOKUP($A12,subQ,MATCH(K$1,SUBQH,0),0),"") | L12: =IFERROR(VLOOKUP($A12,subQ,MATCH(L$1,SUBQH,0),0),"")
A13: 기타영업외손익 | D13: 기타영업외손익 | E13: =IFERROR(VLOOKUP($A13,subQ,MATCH(E$1,SUBQH,0),0),"") | F13: =IFERROR(VLOOKUP($A13,subQ,MATCH(F$1,SUBQH,0),0),"") | G13: =IFERROR(VLOOKUP($A13,subQ,MATCH(G$1,SUBQH,0),0),"") | H13: =IFERROR(VLOOKUP($A13,subQ,MATCH(H$1,SUBQH,0),0),"") | I13: =IFERROR(VLOOKUP($A13,subQ,MATCH(I$1,SUBQH,0),0),"") | J13: =IFERROR(VLOOKUP($A13,subQ,MATCH(J$1,SUBQH,0),0),"") | K13: =IFERROR(VLOOKUP($A13,subQ,MATCH(K$1,SUBQH,0),0),"") | L13: =IFERROR(VLOOKUP($A13,subQ,MATCH(L$1,SUBQH,0),0),"")
A14: 지분법손익 | D14: 지분법손익 | E14: =IFERROR(VLOOKUP($A14,subQ,MATCH(E$1,SUBQH,0),0),"") | F14: =IFERROR(VLOOKUP($A14,subQ,MATCH(F$1,SUBQH,0),0),"") | G14: =IFERROR(VLOOKUP($A14,subQ,MATCH(G$1,SUBQH,0),0),"") | H14: =IFERROR(VLOOKUP($A14,subQ,MATCH(H$1,SUBQH,0),0),"") | I14: =IFERROR(VLOOKUP($A14,subQ,MATCH(I$1,SUBQH,0),0),"") | J14: =IFERROR(VLOOKUP($A14,subQ,MATCH(J$1,SUBQH,0),0),"") | K14: =IFERROR(VLOOKUP($A14,subQ,MATCH(K$1,SUBQH,0),0),"") | L14: =IFERROR(VLOOKUP($A14,subQ,MATCH(L$1,SUBQH,0),0),"")
A15: 세전이익 | D15: 법인세비용차감전이익 | E15: =IFERROR(VLOOKUP($A15,subQ,MATCH(E$1,SUBQH,0),0),"") | F15: =IFERROR(VLOOKUP($A15,subQ,MATCH(F$1,SUBQH,0),0),"") | G15: =IFERROR(VLOOKUP($A15,subQ,MATCH(G$1,SUBQH,0),0),"") | H15: =IFERROR(VLOOKUP($A15,subQ,MATCH(H$1,SUBQH,0),0),"") | I15: =IFERROR(VLOOKUP($A15,subQ,MATCH(I$1,SUBQH,0),0),"") | J15: =IFERROR(VLOOKUP($A15,subQ,MATCH(J$1,SUBQH,0),0),"") | K15: =IFERROR(VLOOKUP($A15,subQ,MATCH(K$1,SUBQH,0),0),"") | L15: =IFERROR(VLOOKUP($A15,subQ,MATCH(L$1,SUBQH,0),0),"")
A16: 법인세비용 | D16: 법인세비용 | E16: =IFERROR(VLOOKUP($A16,subQ,MATCH(E$1,SUBQH,0),0),"") | F16: =IFERROR(VLOOKUP($A16,subQ,MATCH(F$1,SUBQH,0),0),"") | G16: =IFERROR(VLOOKUP($A16,subQ,MATCH(G$1,SUBQH,0),0),"") | H16: =IFERROR(VLOOKUP($A16,subQ,MATCH(H$1,SUBQH,0),0),"") | I16: =IFERROR(VLOOKUP($A16,subQ,MATCH(I$1,SUBQH,0),0),"") | J16: =IFERROR(VLOOKUP($A16,subQ,MATCH(J$1,SUBQH,0),0),"") | K16: =IFERROR(VLOOKUP($A16,subQ,MATCH(K$1,SUBQH,0),0),"") | L16: =IFERROR(VLOOKUP($A16,subQ,MATCH(L$1,SUBQH,0),0),"")
... A38: NPM | D38: NPM | E38: =IFERROR(VLOOKUP($A38,subQ,MATCH(E$1,SUBQH,0),0),"") | F38: =IFERROR(VLOOKUP($A38,subQ,MATCH(F$1,SUBQH,0),0),"") | G38: =IFERROR(VLOOKUP($A38,subQ,MATCH(G$1,SUBQH,0),0),"") | H38: =IFERROR(VLOOKUP($A38,subQ,MATCH(H$1,SUBQH,0),0),"") | I38: =IFERROR(VLOOKUP($A38,subQ,MATCH(I$1,SUBQH,0),0),"") | J38: =IFERROR(VLOOKUP($A38,subQ,MATCH(J$1,SUBQH,0),0),"") | K38: =IFERROR(VLOOKUP($A38,subQ,MATCH(K$1,SUBQH,0),0),"") | L38: =IFERROR(VLOOKUP($A38,subQ,MATCH(L$1,SUBQH,0),0),"")
A39: 매출액 YoY | D39: 매출액 YoY | F39: =IFERROR(F5/E5-1,"") | G39: =IFERROR(G5/F5-1,"") | H39: =IFERROR(H5/G5-1,"") | I39: =IFERROR(I5/H5-1,"") | J39: =IFERROR(J5/I5-1,"") | K39: =IFERROR(K5/J5-1,"") | L39: =IFERROR(L5/K5-1,"")
A40: 영업이익 YoY | D40: 영업이익 YoY | F40: =IFERROR(F9/E9-1,"") | G40: =IFERROR(G9/F9-1,"") | H40: =IFERROR(H9/G9-1,"") | I40: =IFERROR(I9/H9-1,"") | J40: =IFERROR(J9/I9-1,"") | K40: =IFERROR(K9/J9-1,"") | L40: =IFERROR(L9/K9-1,"")
A41: 지배주주순이익 YoY | D41: 지배주주순이익 YoY | F41: =IFERROR(F18/E18-1,"") | G41: =IFERROR(G18/F18-1,"") | H41: =IFERROR(H18/G18-1,"") | I41: =IFERROR(I18/H18-1,"") | J41: =IFERROR(J18/I18-1,"") | K41: =IFERROR(K18/J18-1,"") | L41: =IFERROR(L18/K18-1,"")

Sheet TP
B1: 종가 | C1: =변수!D42
B2: 기준일 | C2: =변수!D43
B3: 모델 산출값 — 목표주가·추천 아님. 밴드·COE 는 변수 시트 3절의 가정
C5: FY | D5: 2025 | E5: 2026 | F5: 2027 | G5: 2028
D6: A | E6: E | F6: E | G6: E
C7: EPS(원) | D7: =IFERROR(VLOOKUP("EPS",subQ,MATCH(D$5,SUBQH,0),0),"") | E7: =IFERROR(VLOOKUP("EPS",subQ,MATCH(E$5,SUBQH,0),0),"") | F7: =IFERROR(VLOOKUP("EPS",subQ,MATCH(F$5,SUBQH,0),0),"") | G7: =IFERROR(VLOOKUP("EPS",subQ,MATCH(G$5,SUBQH,0),0),"")
C8: BPS(원) | D8: =IFERROR(VLOOKUP("BPS",subQ,MATCH(D$5,SUBQH,0),0),"") | E8: =IFERROR(VLOOKUP("BPS",subQ,MATCH(E$5,SUBQH,0),0),"") | F8: =IFERROR(VLOOKUP("BPS",subQ,MATCH(F$5,SUBQH,0),0),"") | G8: =IFERROR(VLOOKUP("BPS",subQ,MATCH(G$5,SUBQH,0),0),"")
C9: 지배주주순이익(억원) | D9: =IFERROR(VLOOKUP("지배주주순이익",subQ,MATCH(D$5,SUBQH,0),0),"") | E9: =IFERROR(VLOOKUP("지배주주순이익",subQ,MATCH(E$5,SUBQH,0),0),"") | F9: =IFERROR(VLOOKUP("지배주주순이익",subQ,MATCH(F$5,SUBQH,0),0),"") | G9: =IFERROR(VLOOKUP("지배주주순이익",subQ,MATCH(G$5,SUBQH,0),0),"")
C10: 영업이익(억원) | D10: =IFERROR(VLOOKUP("영업이익",subQ,MATCH(D$5,SUBQH,0),0),"") | E10: =IFERROR(VLOOKUP("영업이익",subQ,MATCH(E$5,SUBQH,0),0),"") | F10: =IFERROR(VLOOKUP("영업이익",subQ,MATCH(F$5,SUBQH,0),0),"") | G10: =IFERROR(VLOOKUP("영업이익",subQ,MATCH(G$5,SUBQH,0),0),"")
C11: ROE(EPS/기초BPS) | E11: =IFERROR(E7/D8,"") | F11: =IFERROR(F7/E8,"") | G11: =IFERROR(G7/F8,"")
B13: PER
C14: 12M fwd EPS | D14: =IFERROR(E7*변수!D48+F7*(1-변수!D48),"")
C15: 적정가치 @PER_lo | D15: =변수!D45 | E15: =IFERROR(ROUND($D$14*D15,-2),"") | F15: =IFERROR(E15/$C$1-1,"") | G15: 배 · 원 · 종가 대비
C16: 적정가치 @PER_mid | D16: =변수!D46 | E16: =IFERROR(ROUND($D$14*D16,-2),"") | F16: =IFERROR(E16/$C$1-1,"") | G16: 배 · 원 · 종가 대비
C17: 적정가치 @PER_hi | D17: =변수!D47 | E17: =IFERROR(ROUND($D$14*D17,-2),"") | F17: =IFERROR(E17/$C$1-1,"") | G17: 배 · 원 · 종가 대비
C18: 현재 PER(종가/12M fwd EPS) | D18: =IFERROR($C$1/$D$14,"")
B20: PBR
C21: 최근 BPS(마지막 실적 분기) | D21: =IFERROR(VLOOKUP("BPS",subQ,MATCH("2Q26",SUBQH,0),0),"")
C22: ROE fwd(12M fwd EPS / BPS) | D22: =IFERROR($D$14/$D$21,"")
C23: COE | D23: =변수!D44
C24: 적정 PBR = ROE/COE | D24: =IFERROR(D22/D23,"")
C25: 적정가치(PBR) = BPS × 적정PBR | D25: =IFERROR(ROUND(D21*D24,-2),"") | E25: =IFERROR(D25/$C$1-1,"")
C26: 현재 PBR(종가/BPS) | D26: =IFERROR($C$1/D21,"")
B28: 모델 json valuation(참고)
C29: eps_fwd12m | D29: -47.4
C30: bps_latest | D30: 24272
C31: per_now
C32: pbr_now | D32: 0.37
C33: roe_fwd | D33: -0.002
C34: fair_pbr
C35: fair_value_pbr
C36: ev_ebitda
C37: note | D37: 모델 산출값 — 목표주가·추천 아님

Sheet 외화
C1: 이름: 외화QH — 환율 QoQ · 외화 순노출 × Δ기말환율 | E1: 4Q21 | F1: 1Q22 | G1: 2Q22 | H1: 3Q22 | I1: 4Q22 | J1: 1Q23 | K1: 2Q23 | L1: 3Q23 | M1: 4Q23 | N1: 1Q24 | O1: 2Q24 | P1: 3Q24 | Q1: 4Q24 | R1: 1Q25 | S1: 2Q25 | T1: 3Q25 | U1: 4Q25 | V1: 1Q26 | W1: 2Q26 | X1: 3Q26 | Y1: 4Q26 | Z1: 1Q27 | AA1: 2Q27 | AB1: 3Q27 | AC1: 4Q27 | AD1: 1Q28 | AE1: 2Q28 | AF1: 3Q28 | AG1: 4Q28
E3: 1 | F3: 2 | G3: 3 | H3: 4 | I3: 5 | J3: 6 | K3: 7 | L3: 8 | M3: 9 | N3: 10 | O3: 11 | P3: 12 | Q3: 13 | R3: 14 | S3: 15 | T3: 16 | U3: 17 | V3: 18 | W3: 19 | X3: 20 | Y3: 21 | Z3: 22 | AA3: 23 | AB3: 24 | AC3: 25 | AD3: 26 | AE3: 27 | AF3: 28 | AG3: 29
E4: 2021.12 | F4: 2022.03 | G4: 2022.06 | H4: 2022.09 | I4: 2022.12 | J4: 2023.03 | K4: 2023.06 | L4: 2023.09 | M4: 2023.12 | N4: 2024.03 | O4: 2024.06 | P4: 2024.09 | Q4: 2024.12 | R4: 2025.03 | S4: 2025.06 | T4: 2025.09 | U4: 2025.12 | V4: 2026.03 | W4: 2026.06 | X4: 2026.09 | Y4: 2026.12 | Z4: 2027.03 | AA4: 2027.06 | AB4: 2027.09 | AC4: 2027.12 | AD4: 2028.03 | AE4: 2028.06 | AF4: 2028.09 | AG4: 2028.12
D5: 원/달러(평균) | E5: =IFERROR(VLOOKUP($D5,환율,MATCH(E$1,변수H,0),0),"") | F5: =IFERROR(VLOOKUP($D5,환율,MATCH(F$1,변수H,0),0),"") | G5: =IFERROR(VLOOKUP($D5,환율,MATCH(G$1,변수H,0),0),"") | H5: =IFERROR(VLOOKUP($D5,환율,MATCH(H$1,변수H,0),0),"") | I5: =IFERROR(VLOOKUP($D5,환율,MATCH(I$1,변수H,0),0),"") | J5: =IFERROR(VLOOKUP($D5,환율,MATCH(J$1,변수H,0),0),"") | K5: =IFERROR(VLOOKUP($D5,환율,MATCH(K$1,변수H,0),0),"") | L5: =IFERROR(VLOOKUP($D5,환율,MATCH(L$1,변수H,0),0),"") | ... AG5: =IFERROR(VLOOKUP($D5,환율,MATCH(AG$1,변수H,0),0),"")
A6: 원/달러(평균) QoQ | F6: =IFERROR(F5/E5-1,"") | G6: =IFERROR(G5/F5-1,"") | H6: =IFERROR(H5/G5-1,"") | I6: =IFERROR(I5/H5-1,"") | J6: =IFERROR(J5/I5-1,"") | K6: =IFERROR(K5/J5-1,"") | L6: =IFERROR(L5/K5-1,"") | M6: =IFERROR(M5/L5-1,"") | ... AG6: =IFERROR(AG5/AF5-1,"")
D7: 원/달러(기말) | E7: =IFERROR(VLOOKUP($D7,환율,MATCH(E$1,변수H,0),0),"") | F7: =IFERROR(VLOOKUP($D7,환율,MATCH(F$1,변수H,0),0),"") | G7: =IFERROR(VLOOKUP($D7,환율,MATCH(G$1,변수H,0),0),"") | H7: =IFERROR(VLOOKUP($D7,환율,MATCH(H$1,변수H,0),0),"") | I7: =IFERROR(VLOOKUP($D7,환율,MATCH(I$1,변수H,0),0),"") | J7: =IFERROR(VLOOKUP($D7,환율,MATCH(J$1,변수H,0),0),"") | K7: =IFERROR(VLOOKUP($D7,환율,MATCH(K$1,변수H,0),0),"") | L7: =IFERROR(VLOOKUP($D7,환율,MATCH(L$1,변수H,0),0),"") | ... AG7: =IFERROR(VLOOKUP($D7,환율,MATCH(AG$1,변수H,0),0),"")
A8: 원/달러(기말) QoQ | F8: =IFERROR(F7/E7-1,"") | G8: =IFERROR(G7/F7-1,"") | H8: =IFERROR(H7/G7-1,"") | I8: =IFERROR(I7/H7-1,"") | J8: =IFERROR(J7/I7-1,"") | K8: =IFERROR(K7/J7-1,"") | L8: =IFERROR(L7/K7-1,"") | M8: =IFERROR(M7/L7-1,"") | ... AG8: =IFERROR(AG7/AF7-1,"")
D9: W/Euro(평균) | E9: =IFERROR(VLOOKUP($D9,환율,MATCH(E$1,변수H,0),0),"") | F9: =IFERROR(VLOOKUP($D9,환율,MATCH(F$1,변수H,0),0),"") | G9: =IFERROR(VLOOKUP($D9,환율,MATCH(G$1,변수H,0),0),"") | H9: =IFERROR(VLOOKUP($D9,환율,MATCH(H$1,변수H,0),0),"") | I9: =IFERROR(VLOOKUP($D9,환율,MATCH(I$1,변수H,0),0),"") | J9: =IFERROR(VLOOKUP($D9,환율,MATCH(J$1,변수H,0),0),"") | K9: =IFERROR(VLOOKUP($D9,환율,MATCH(K$1,변수H,0),0),"") | L9: =IFERROR(VLOOKUP($D9,환율,MATCH(L$1,변수H,0),0),"") | ... AG9: =IFERROR(VLOOKUP($D9,환율,MATCH(AG$1,변수H,0),0),"")
A10: W/Euro(평균) QoQ | F10: =IFERROR(F9/E9-1,"") | G10: =IFERROR(G9/F9-1,"") | H10: =IFERROR(H9/G9-1,"") | I10: =IFERROR(I9/H9-1,"") | J10: =IFERROR(J9/I9-1,"") | K10: =IFERROR(K9/J9-1,"") | L10: =IFERROR(L9/K9-1,"") | M10: =IFERROR(M9/L9-1,"") | ... AG10: =IFERROR(AG9/AF9-1,"")
D11: W/Euro(기말) | E11: =IFERROR(VLOOKUP($D11,환율,MATCH(E$1,변수H,0),0),"") | F11: =IFERROR(VLOOKUP($D11,환율,MATCH(F$1,변수H,0),0),"") | G11: =IFERROR(VLOOKUP($D11,환율,MATCH(G$1,변수H,0),0),"") | H11: =IFERROR(VLOOKUP($D11,환율,MATCH(H$1,변수H,0),0),"") | I11: =IFERROR(VLOOKUP($D11,환율,MATCH(I$1,변수H,0),0),"") | J11: =IFERROR(VLOOKUP($D11,환율,MATCH(J$1,변수H,0),0),"") | K11: =IFERROR(VLOOKUP($D11,환율,MATCH(K$1,변수H,0),0),"") | L11: =IFERROR(VLOOKUP($D11,환율,MATCH(L$1,변수H,0),0),"") | ... AG11: =IFERROR(VLOOKUP($D11,환율,MATCH(AG$1,변수H,0),0),"")
A12: W/Euro(기말) QoQ | F12: =IFERROR(F11/E11-1,"") | G12: =IFERROR(G11/F11-1,"") | H12: =IFERROR(H11/G11-1,"") | I12: =IFERROR(I11/H11-1,"") | J12: =IFERROR(J11/I11-1,"") | K12: =IFERROR(K11/J11-1,"") | L12: =IFERROR(L11/K11-1,"") | M12: =IFERROR(M11/L11-1,"") | ... AG12: =IFERROR(AG11/AF11-1,"")
D13: 원/100Y(기말) | E13: =IFERROR(VLOOKUP($D13,환율,MATCH(E$1,변수H,0),0),"") | F13: =IFERROR(VLOOKUP($D13,환율,MATCH(F$1,변수H,0),0),"") | G13: =IFERROR(VLOOKUP($D13,환율,MATCH(G$1,변수H,0),0),"") | H13: =IFERROR(VLOOKUP($D13,환율,MATCH(H$1,변수H,0),0),"") | I13: =IFERROR(VLOOKUP($D13,환율,MATCH(I$1,변수H,0),0),"") | J13: =IFERROR(VLOOKUP($D13,환율,MATCH(J$1,변수H,0),0),"") | K13: =IFERROR(VLOOKUP($D13,환율,MATCH(K$1,변수H,0),0),"") | L13: =IFERROR(VLOOKUP($D13,환율,MATCH(L$1,변수H,0),0),"") | ... AG13: =IFERROR(VLOOKUP($D13,환율,MATCH(AG$1,변수H,0),0),"")
A14: 원/100Y(기말) QoQ | F14: =IFERROR(F13/E13-1,"") | G14: =IFERROR(G13/F13-1,"") | H14: =IFERROR(H13/G13-1,"") | I14: =IFERROR(I13/H13-1,"") | J14: =IFERROR(J13/I13-1,"") | K14: =IFERROR(K13/J13-1,"") | L14: =IFERROR(L13/K13-1,"") | M14: =IFERROR(M13/L13-1,"") | ... AG14: =IFERROR(AG13/AF13-1,"")
A16: 외화순노출 | C16: 외화 순노출(백만$) | D16: =변수!D55 | E16: 외화 순노출 × Δ기말환율 (외화 시트 방식)
A17: 환관련손익추정 | C17: 환관련손익 추정(억원) = 순노출 × Δ원/달러(기말) / 100 | F17: =IFERROR($D$16*(F7-E7)/100,"") | G17: =IFERROR($D$16*(G7-F7)/100,"") | H17: =IFERROR($D$16*(H7-G7)/100,"") | I17: =IFERROR($D$16*(I7-H7)/100,"") | J17: =IFERROR($D$16*(J7-I7)/100,"") | K17: =IFERROR($D$16*(K7-J7)/100,"") | L17: =IFERROR($D$16*(L7-K7)/100,"") | M17: =IFERROR($D$16*(M7-L7)/100,"") | ... AG17: =IFERROR($D$16*(AG7-AF7)/100,"")
A18: fx_pnl.by_q | C18: 모델 fx_pnl.by_q(억원, 참고)
C19: 외화 순노출 미공시(face) → 0 + 표기
