Workbook
Name 변수H: 변수!$C$1:$AO$1
Name 환율: 변수!$C$6:$AO$13
Name BS연결H: BS연결!$C$1:$AO$1
Name BS연결: BS연결!$C$5:$AO$106
Name BS별도H: BS별도!$C$1:$AO$1
Name BS별도: BS별도!$C$5:$AO$93
Name SUBQH: subQ!$A$1:$AO$1
Name subQ: subQ!$A$5:$AO$44

Sheet README
A1: 대창솔루션(096350) 실적 모델 — ARGUS 한국조선
A2: 기준 분기 2026Q2 · 마지막 실적 2026Q2 · 생성 2026-10-19
A3: 모든 수치는 모델 산출값(DART 공개 재무제표 + 우리 추정)이다 — 목표주가·투자 추천 아님. 참고용 · 투자조언 아님.
A5: 시트
A6: 변수 가정 시계열. 환율 8행(ECB via frankfurter — L2 fx.json; 추정 분기 = 노란 가정), 추정 드라이버(노란 셀 = 모델값에서 역산한 가정, 바꾸면 재계산; 연녹 셀 = 3절 스칼라 참조 수식), 3절 스칼라 가정(세율·판관비율·지배주주비중·이자율·종가·PER 밴드·COE·외화 순노출·헤지비율)
A7: BS연결/BS별도 FnGuide 계정명 × 기간 값 덤프(백만원). 행1 분기라벨, 행4 YYYY.MM / YYYY.12A. 이름정의 BS연결H·BS연결(계정명 C열부터)
A8: subQ 분기 서브모델(억원 = 백만원/100). 확정 행: =IFERROR(VLOOKUP($D행,BS연결,MATCH(E$1,BS연결H,0),0)/100,"") 추정 행: 변수 시트 가정 셀 참조 수식. 외환손익·파생상품손익은 BS 계정 합·차, 기타금융손익은 잔차, OPM·EPS·BPS·PER·PBR 은 파생 수식
A9: SLS 선표(조선사만, sls json 있을 때): 요약 행(sls 저장값) + 계약별 스케줄(백만$) × (헤지비율 × 헤지환율 + (1−헤지비율) × 건조시점 환율[변수 원/달러(평균)]) → 원화 수식 블록 → 합계 행이 subQ 매출조선에 연결
A10: 시나리오 신규수주 보수/기준/낙관(forecast_panel 패널, 모델에 scenarios 가 있을 때만): 매출액·영업이익 = subQ 기준값 ± (시나리오 신규 − base 신규) × OPM. base 만 subQ 행에 포함, 나머지는 합산 안 함
A11: 분기/연간예상 subQ 를 이름(A열 key)으로 VLOOKUP 한 보고서 표(억원)
A12: TP PER 밴드 × 12M fwd EPS, PBR = ROE/COE × BPS — 모델 산출값 구간, 목표주가·추천 아님
A13: 외화 환율 QoQ, 외화 순노출 × Δ기말환율 → 환관련손익 추정
... A34: 백테스트: {"freeze": "2025Q2", "horizon": 4, "revenue_wape_pct": 37.4, "op_wape_pct": 99.6, "n": 4, "note": "단일 회사 4분기 — 통계 아님", "driver_at_freeze": "trend_seasonal", "selection_oos_at_freeze": {"wape_link": null, "wape_trend": null, "adopted": false, "decision": "rejected", "note": "유의성 조건 미달 → OOS 비교 전 기각"}, "frozen_inputs": "fin(연결/별도)·고객 조선사 모델·지주 자회사 모델은 2025Q2 까지의 분기만; 선표는 체결일 ≤ 2025Q2 말일 계약(원장 최신 금액·코호트 등급, 환산 없음); 잔고는 yards_cache 2025Q2; 시세·환율 forward·prices·forecast_panel 신규수주 미사용. 고객 가중치(suppliers.json 언급 비중)와 합병 체인링크는 현재 지식; 고객 연동 채택은 동결 모델 안에서도 자기 la−4분기 OOS 규칙(selection_oos_at_freeze)", "detail": [{"q": "2025Q3", "rev_pred": 109.34, "rev_act": 171.56, "op_pred": 0.07, "op_act": 11.72}, {"q": "2025Q4", "rev_pred": 149.49, "rev_act": 177.73, "op_pred": 0.09, "op_act": 1.71}, {"q": "2026Q1", "rev_pred": 87.38, "rev_act": 212.48, "op_pred": 0.05, "op_act": 14.82}, {"q": "2026Q2", "rev_pred": 123.68, "rev_act": 188.86, "op_pred": 0.08, "op_act": -1.36}]}

Sheet 변수
C1: 이름: 변수H | E1: 4Q21 | F1: 2021 | G1: 1Q22 | H1: 2Q22 | I1: 3Q22 | J1: 4Q22 | K1: 2022 | L1: 1Q23 | M1: 2Q23 | N1: 3Q23 | O1: 4Q23 | P1: 2023 | Q1: 1Q24 | R1: 2Q24 | S1: 3Q24 | T1: 4Q24 | U1: 2024 | V1: 1Q25 | W1: 2Q25 | X1: 3Q25 | Y1: 4Q25 | Z1: 2025 | AA1: 1Q26 | AB1: 2Q26 | AC1: 3Q26 | AD1: 4Q26 | AE1: 2026 | AF1: 1Q27 | AG1: 2Q27 | AH1: 3Q27 | AI1: 4Q27 | AJ1: 2027 | AK1: 1Q28 | AL1: 2Q28 | AM1: 3Q28 | AN1: 4Q28 | AO1: 2028
A2: 가정 시계열 — 노란 셀은 추정 가정(모델값에서 역산), 연녹 셀은 3절 스칼라 참조 수식. 바꾸면 subQ·분기·연간예상·TP·시나리오가 재계산됩니다.
E3: 1 | F3: 2 | G3: 3 | H3: 4 | I3: 5 | J3: 6 | K3: 7 | L3: 8 | M3: 9 | N3: 10 | O3: 11 | P3: 12 | Q3: 13 | R3: 14 | S3: 15 | T3: 16 | U3: 17 | V3: 18 | W3: 19 | X3: 20 | Y3: 21 | Z3: 22 | AA3: 23 | AB3: 24 | AC3: 25 | AD3: 26 | AE3: 27 | AF3: 28 | AG3: 29 | AH3: 30 | AI3: 31 | AJ3: 32 | AK3: 33 | AL3: 34 | AM3: 35 | AN3: 36 | AO3: 37
E4: 2021.12 | F4: 2021.12A | G4: 2022.03 | H4: 2022.06 | I4: 2022.09 | J4: 2022.12 | K4: 2022.12A | L4: 2023.03 | M4: 2023.06 | N4: 2023.09 | O4: 2023.12 | P4: 2023.12A | Q4: 2024.03 | R4: 2024.06 | S4: 2024.09 | T4: 2024.12 | U4: 2024.12A | V4: 2025.03 | W4: 2025.06 | X4: 2025.09 | Y4: 2025.12 | Z4: 2025.12A | AA4: 2026.03 | AB4: 2026.06 | AC4: 2026.09 | AD4: 2026.12 | AE4: 2026.12A | AF4: 2027.03 | AG4: 2027.06 | AH4: 2027.09 | AI4: 2027.12 | AJ4: 2027.12A | AK4: 2028.03 | AL4: 2028.06 | AM4: 2028.09 | AN4: 2028.12 | AO4: 2028.12A
B5: 1. FX | C5: 이름: 환율
A6: USDKRW_avg | C6: 원/달러(평균) | E6: 1183.5 | F6: 1145.51 | G6: 1205.78 | H6: 1262.09 | I6: 1341.93 | J6: 1360.12 | K6: 1292.98 | L6: 1276.95 | M6: 1315.69 | N6: 1313.62 | O6: 1322.01 | P6: 1306.85 | Q6: 1330.14 | R6: 1371.28 | S6: 1356.22 | T6: 1396.3 | U6: 1363.53 | V6: 1452.28 | W6: 1398.52 | X6: 1386.95 | Y6: 1449.19 | Z6: 1421.52 | AA6: 1466.12 | AB6: 1501.75 | AC6: 1418.75 | AD6: 1342.11 | AE6: 1454.27 | AF6: 1332.1 | AG6: 1332.1 | AH6: 1332.1 | AI6: 1332.1 | AK6: 1332.1 | AL6: 1332.1 | AM6: 1332.1 | AN6: 1332.1
A7: USDKRW_end | C7: 원/달러(기말) | E7: 1188.75 | F7: 1188.75 | G7: 1213.74 | H7: 1301.24 | I7: 1436.9 | J7: 1260.16 | K7: 1260.16 | L7: 1305.99 | M7: 1321.44 | N7: 1345.35 | O7: 1297.43 | P7: 1297.43 | Q7: 1349.25 | R7: 1377.73 | S7: 1312.17 | T7: 1474.78 | U7: 1474.78 | V7: 1474.54 | W7: 1355.13 | X7: 1403.67 | Y7: 1444.2 | Z7: 1444.2 | AA7: 1524.8 | AB7: 1550.89 | AC7: 1355.4 | AD7: 1332.1 | AE7: 1332.1 | AF7: 1332.1 | AG7: 1332.1 | AH7: 1332.1 | AI7: 1332.1 | AK7: 1332.1 | AL7: 1332.1 | AM7: 1332.1 | AN7: 1332.1
A8: JPY100KRW_avg | C8: 원/100Y(평균) | E8: 1041.02 | F8: 1042.74 | G8: 1036.79 | H8: 972.23 | I8: 970.61 | J8: 961.03 | K8: 985.1 | L8: 964.89 | M8: 957.36 | N8: 909 | O8: 893.22 | P8: 931.11 | Q8: 896.29 | R8: 880.14 | S8: 909.35 | T8: 917.25 | U8: 900.92 | V8: 952.59 | W8: 967.92 | X8: 940.32 | Y8: 940.77 | Z8: 950.17 | AA8: 934.39 | AB8: 942.16 | AC8: 890.41 | AD8: 848.59 | AE8: 917.39 | AF8: 842.99 | AG8: 842.99 | AH8: 842.99 | AI8: 842.99 | AK8: 842.99 | AL8: 842.99 | AM8: 842.99 | AN8: 842.99
A9: JPY100KRW_end | C9: 원/100Y(기말) | E9: 1032.62 | F9: 1032.62 | G9: 996.83 | H9: 954.9 | I9: 993.29 | J9: 955.54 | K9: 955.54 | L9: 980.62 | M9: 913.67 | N9: 901.47 | O9: 917.04 | P9: 917.04 | Q9: 892.42 | R9: 857.76 | S9: 919.21 | T9: 939.65 | U9: 939.65 | V9: 986.84 | W9: 938.85 | X9: 948.49 | Y9: 921.81 | Z9: 921.81 | AA9: 955.99 | AB9: 954.75 | AC9: 863.31 | AD9: 842.99 | AE9: 842.99 | AF9: 842.99 | AG9: 842.99 | AH9: 842.99 | AI9: 842.99 | AK9: 842.99 | AL9: 842.99 | AM9: 842.99 | AN9: 842.99
A10: EURKRW_avg | C10: W/Euro(평균) | E10: 1353.32 | F10: 1354.06 | G10: 1352.29 | H10: 1343.31 | I10: 1350.63 | J10: 1386.07 | K10: 1358.07 | L10: 1369.93 | M10: 1432.41 | N10: 1429.41 | O10: 1420.91 | P10: 1412.88 | Q10: 1444.21 | R10: 1476.42 | S10: 1489.3 | T10: 1490.78 | U10: 1475.4 | V10: 1528.33 | W10: 1585.13 | X10: 1620.04 | Y10: 1686.02 | Z10: 1605.45 | AA10: 1715.47 | AB10: 1746.09 | AC10: 1631.97 | AD10: 1505.3 | AE10: 1685.25 | AF10: 1499.02 | AG10: 1499.02 | AH10: 1499.02 | AI10: 1499.02 | AK10: 1499.02 | AL10: 1499.02 | AM10: 1499.02 | AN10: 1499.02
A11: EURKRW_end | C11: W/Euro(기말) | E11: 1346.38 | F11: 1346.38 | G11: 1347.37 | H11: 1351.6 | I11: 1400.62 | J11: 1344.08 | K11: 1344.08 | L11: 1420.26 | M11: 1435.88 | N11: 1425.26 | O11: 1433.66 | P11: 1433.66 | Q11: 1458.68 | R11: 1474.86 | S11: 1469.1 | T11: 1532.14 | U11: 1532.14 | V11: 1594.72 | W11: 1588.22 | X11: 1648.04 | Y11: 1696.94 | Z11: 1696.94 | AA11: 1753.21 | AB11: 1767.09 | AC11: 1539.06 | AD11: 1499.02 | AE11: 1499.02 | AF11: 1499.02 | AG11: 1499.02 | AH11: 1499.02 | AI11: 1499.02 | AK11: 1499.02 | AL11: 1499.02 | AM11: 1499.02 | AN11: 1499.02
A12: CNYKRW_avg | C12: 원/중국원(평균) | E12: 185.14 | F12: 177.65 | G12: 189.93 | H12: 190.76 | I12: 195.79 | J12: 191.09 | K12: 191.93 | L12: 186.59 | M12: 187.45 | N12: 181.28 | O12: 182.86 | P12: 184.52 | Q12: 185.04 | R12: 189.35 | S12: 189.24 | T12: 194.24 | U12: 189.49 | V12: 199.63 | W12: 193.41 | X12: 193.79 | Y12: 204.38 | Z12: 197.8 | AA12: 211.75 | AB12: 220.8 | AC12: 210.43 | AD12: 200.38 | AE12: 213.41 | AF12: 199.23 | AG12: 199.23 | AH12: 199.23 | AI12: 199.23 | AK12: 199.23 | AL12: 199.23 | AM12: 199.23 | AN12: 199.23
A13: CNYKRW_end | C13: 원/중국원(기말) | E13: 187.13 | F13: 187.13 | G13: 191.38 | H13: 194.13 | I13: 201.92 | J13: 182.67 | K13: 182.67 | L13: 189.97 | M13: 181.8 | N13: 184.26 | O13: 182.61 | P13: 182.61 | Q13: 186.66 | R13: 189.7 | S13: 187.12 | T13: 202.04 | U13: 202.04 | V13: 203.3 | W13: 189.14 | X13: 197.16 | Y13: 206.28 | Z13: 206.28 | AA13: 220.97 | AB13: 228.56 | AC13: 202.16 | AD13: 199.23 | AE13: 199.23 | AF13: 199.23 | AG13: 199.23 | AH13: 199.23 | AI13: 199.23 | AK13: 199.23 | AL13: 199.23 | AM13: 199.23 | AN13: 199.23
B14: 1b. 종가
A15: price_close_end | C15: 종가(기말) | E15: 2490 | G15: 2460 | H15: 2050 | I15: 1465 | J15: 1520 | L15: 1470 | M15: 3390 | N15: 2830 | O15: 2180 | Q15: 2370 | R15: 2105 | S15: 1935 | T15: 1540 | V15: 1650 | W15: 2825 | X15: 2260 | Y15: 2335 | AA15: 3115 | AB15: 1658 | AC15: 1859 | AD15: 1772
A16: price_high | C16: 종가(최고) | E16: 3275 | G16: 2725 | H16: 2880 | I16: 2400 | J16: 2395 | L16: 1835 | M16: 4030 | N16: 4015 | O16: 2870 | Q16: 2700 | R16: 2600 | S16: 2190 | T16: 1985 | V16: 2185 | W16: 3355 | X16: 3020 | Y16: 3170 | AA16: 4180 | AB16: 3355 | AC16: 2345 | AD16: 1932
A17: price_low | C17: 종가(최저) | E17: 2255 | G17: 1995 | H17: 1940 | I17: 1365 | J17: 1045 | L17: 1305 | M17: 1425 | N17: 2690 | O17: 1990 | Q17: 2000 | R17: 2040 | S17: 1600 | T17: 1460 | V17: 1530 | W17: 1580 | X17: 2010 | Y17: 1976 | AA17: 1800 | AB17: 1554 | AC17: 1348 | AD17: 1562
A18: price_avg | C18: 종가(평균) | E18: 2643.4 | G18: 2334.7 | H18: 2440.5 | I18: 1978.6 | J18: 1571.3 | L18: 1520.3 | M18: 2171.1 | N18: 3187.4 | O18: 2338 | Q18: 2297.1 | R18: 2261.4 | S18: 1929.6 | T18: 1731.6 | V18: 1700.9 | W18: 1980.9 | X18: 2279 | Y18: 2250.2 | AA18: 2469.6 | AB18: 2517.8 | AC18: 1800.6 | AD18: 1808.2
B20: 2. 추정 드라이버 | C20: 실적 열 = subQ 실현값(수식), 추정 열 = 가정(노란 = 모델값 역산, 연녹 = 3절 스칼라 참조)
A21: drv:매출액 | B21: yoy | C21: 매출액 YoY | J21: =IFERROR(subQ!J5/subQ!E5-1,"") | L21: =IFERROR(subQ!L5/subQ!G5-1,"") | M21: =IFERROR(subQ!M5/subQ!H5-1,"") | N21: =IFERROR(subQ!N5/subQ!I5-1,"") | O21: =IFERROR(subQ!O5/subQ!J5-1,"") | Q21: =IFERROR(subQ!Q5/subQ!L5-1,"") | R21: =IFERROR(subQ!R5/subQ!M5-1,"") | S21: =IFERROR(subQ!S5/subQ!N5-1,"") | T21: =IFERROR(subQ!T5/subQ!O5-1,"") | V21: =IFERROR(subQ!V5/subQ!Q5-1,"") | W21: =IFERROR(subQ!W5/subQ!R5-1,"") | X21: =IFERROR(subQ!X5/subQ!S5-1,"") | Y21: =IFERROR(subQ!Y5/subQ!T5-1,"") | AA21: =IFERROR(subQ!AA5/subQ!V5-1,"") | AB21: =IFERROR(subQ!AB5/subQ!W5-1,"") | AC21: 0.20054163 | AD21: 0.38197536 | AF21: 0.047034422 | AG21: 0.20259093 | AH21: 0.1861041 | AI21: 0.16973373 | AK21: 0.18231672 | AL21: 0.20817189 | AM21: 0.23169184 | AN21: 0.23166614
A22: drv:판관비 | B22: ratio | C22: 판관비율(/매출) | E22: =IFERROR(subQ!E8/subQ!E5,"") | F22: =IFERROR(subQ!F8/subQ!F5,"") | G22: =IFERROR(subQ!G8/subQ!G5,"") | H22: =IFERROR(subQ!H8/subQ!H5,"") | I22: =IFERROR(subQ!I8/subQ!I5,"") | J22: =IFERROR(subQ!J8/subQ!J5,"") | K22: =IFERROR(subQ!K8/subQ!K5,"") | L22: =IFERROR(subQ!L8/subQ!L5,"") | ... AB22: =IFERROR(subQ!AB8/subQ!AB5,"") | AC22: =$D$52 | AD22: =$D$52 | AE22: =IFERROR(subQ!AE8/subQ!AE5,"") | AF22: =$D$52 | AG22: =$D$52 | AH22: =$D$52 | AI22: =$D$52 | AJ22: =IFERROR(subQ!AJ8/subQ!AJ5,"") | AK22: =$D$52 | AL22: =$D$52 | AM22: =$D$52 | AN22: =$D$52 | AO22: =IFERROR(subQ!AO8/subQ!AO5,"")
A23: drv:영업이익 | B23: ratio | C23: 영업이익률(OPM) | E23: =IFERROR(subQ!E9/subQ!E5,"") | F23: =IFERROR(subQ!F9/subQ!F5,"") | G23: =IFERROR(subQ!G9/subQ!G5,"") | H23: =IFERROR(subQ!H9/subQ!H5,"") | I23: =IFERROR(subQ!I9/subQ!I5,"") | J23: =IFERROR(subQ!J9/subQ!J5,"") | K23: =IFERROR(subQ!K9/subQ!K5,"") | L23: =IFERROR(subQ!L9/subQ!L5,"") | ... AB23: =IFERROR(subQ!AB9/subQ!AB5,"") | AC23: 0.001213828 | AD23: 0.001221399 | AE23: =IFERROR(subQ!AE9/subQ!AE5,"") | AF23: 0.001213647 | AG23: 0.001232828 | AH23: 0.001228049 | AI23: 0.001218196 | AJ23: =IFERROR(subQ!AJ9/subQ!AJ5,"") | AK23: 0.001216591 | AL23: 0.001239067 | AM23: 0.001229685 | AN23: 0.001215136 | AO23: =IFERROR(subQ!AO9/subQ!AO5,"")
A24: drv:외환손익 | B24: abs | C24: 외환손익 (가정, 억원) | E24: =subQ!E13 | F24: =subQ!F13 | G24: =subQ!G13 | H24: =subQ!H13 | I24: =subQ!I13 | J24: =subQ!J13 | K24: =subQ!K13 | L24: =subQ!L13 | ... AB24: =subQ!AB13 | AC24: 0 | AD24: 0 | AE24: =subQ!AE13 | AF24: 0 | AG24: 0 | AH24: 0 | AI24: 0 | AJ24: =subQ!AJ13 | AK24: 0 | AL24: 0 | AM24: 0 | AN24: 0 | AO24: =subQ!AO13
A25: drv:파생상품손익 | B25: abs | C25: 파생상품손익 (가정, 억원) | E25: =subQ!E14 | F25: =subQ!F14 | G25: =subQ!G14 | H25: =subQ!H14 | I25: =subQ!I14 | J25: =subQ!J14 | K25: =subQ!K14 | L25: =subQ!L14 | ... AB25: =subQ!AB14 | AC25: 0 | AD25: 0 | AE25: =subQ!AE14 | AF25: 0 | AG25: 0 | AH25: 0 | AI25: 0 | AJ25: =subQ!AJ14 | AK25: 0 | AL25: 0 | AM25: 0 | AN25: 0 | AO25: =subQ!AO14
A26: drv:기타금융손익 | B26: abs | C26: 기타금융손익 (가정, 억원) | E26: =subQ!E15 | F26: =subQ!F15 | G26: =subQ!G15 | H26: =subQ!H15 | I26: =subQ!I15 | J26: =subQ!J15 | K26: =subQ!K15 | L26: =subQ!L15 | ... AB26: =subQ!AB15 | AC26: 0 | AD26: 0 | AE26: =subQ!AE15 | AF26: 0 | AG26: 0 | AH26: 0 | AI26: 0 | AJ26: =subQ!AJ15 | AK26: 0 | AL26: 0 | AM26: 0 | AN26: 0 | AO26: =subQ!AO15
A27: drv:기타영업외손익 | B27: abs | C27: 기타영업외손익 (가정, 억원) | E27: =subQ!E16 | F27: =subQ!F16 | G27: =subQ!G16 | H27: =subQ!H16 | I27: =subQ!I16 | J27: =subQ!J16 | K27: =subQ!K16 | L27: =subQ!L16 | ... AB27: =subQ!AB16 | AC27: 0 | AD27: 0 | AE27: =subQ!AE16 | AF27: 0 | AG27: 0 | AH27: 0 | AI27: 0 | AJ27: =subQ!AJ16 | AK27: 0 | AL27: 0 | AM27: 0 | AN27: 0 | AO27: =subQ!AO16
A28: drv:법인세비용 | B28: ratio | C28: 법인세율(/세전) | E28: =IFERROR(subQ!E18/subQ!E17,"") | F28: =IFERROR(subQ!F18/subQ!F17,"") | G28: =IFERROR(subQ!G18/subQ!G17,"") | H28: =IFERROR(subQ!H18/subQ!H17,"") | I28: =IFERROR(subQ!I18/subQ!I17,"") | J28: =IFERROR(subQ!J18/subQ!J17,"") | K28: =IFERROR(subQ!K18/subQ!K17,"") | L28: =IFERROR(subQ!L18/subQ!L17,"") | ... AB28: =IFERROR(subQ!AB18/subQ!AB17,"") | AC28: 0 | AD28: 0 | AE28: =IFERROR(subQ!AE18/subQ!AE17,"") | AF28: 0 | AG28: 0 | AH28: 0 | AI28: 0 | AJ28: =IFERROR(subQ!AJ18/subQ!AJ17,"") | AK28: 0 | AL28: 0 | AM28: 0 | AN28: 0 | AO28: =IFERROR(subQ!AO18/subQ!AO17,"")
A29: drv:지배주주순이익 | B29: ratio | C29: 지배주주 비중(/당기순이익) | E29: =IFERROR(subQ!E20/subQ!E19,"") | F29: =IFERROR(subQ!F20/subQ!F19,"") | G29: =IFERROR(subQ!G20/subQ!G19,"") | H29: =IFERROR(subQ!H20/subQ!H19,"") | I29: =IFERROR(subQ!I20/subQ!I19,"") | J29: =IFERROR(subQ!J20/subQ!J19,"") | K29: =IFERROR(subQ!K20/subQ!K19,"") | L29: =IFERROR(subQ!L20/subQ!L19,"") | ... AB29: =IFERROR(subQ!AB20/subQ!AB19,"") | AC29: =$D$53 | AD29: =$D$53 | AE29: =IFERROR(subQ!AE20/subQ!AE19,"") | AF29: =$D$53 | AG29: =$D$53 | AH29: =$D$53 | AI29: =$D$53 | AJ29: =IFERROR(subQ!AJ20/subQ!AJ19,"") | AK29: =$D$53 | AL29: =$D$53 | AM29: =$D$53 | AN29: =$D$53 | AO29: =IFERROR(subQ!AO20/subQ!AO19,"")
A30: drv:감가상각비 | B30: abs | C30: 감가상각비 (가정, 억원) | E30: =subQ!E21 | F30: =subQ!F21 | G30: =subQ!G21 | H30: =subQ!H21 | I30: =subQ!I21 | J30: =subQ!J21 | K30: =subQ!K21 | L30: =subQ!L21 | ... AB30: =subQ!AB21 | AC30: 2.55 | AD30: 2.55 | AE30: =subQ!AE21 | AF30: 2.55 | AG30: 2.55 | AH30: 2.55 | AI30: 2.55 | AJ30: =subQ!AJ21 | AK30: 2.55 | AL30: 2.55 | AM30: 2.55 | AN30: 2.55 | AO30: =subQ!AO21
A31: drv:부채총계 | B31: qoq | C31: 부채총계 QoQ | G31: =IFERROR(subQ!G24/subQ!E24-1,"") | H31: =IFERROR(subQ!H24/subQ!G24-1,"") | I31: =IFERROR(subQ!I24/subQ!H24-1,"") | J31: =IFERROR(subQ!J24/subQ!I24-1,"") | L31: =IFERROR(subQ!L24/subQ!J24-1,"") | M31: =IFERROR(subQ!M24/subQ!L24-1,"") | N31: =IFERROR(subQ!N24/subQ!M24-1,"") | O31: =IFERROR(subQ!O24/subQ!N24-1,"") | Q31: =IFERROR(subQ!Q24/subQ!O24-1,"") | R31: =IFERROR(subQ!R24/subQ!Q24-1,"") | S31: =IFERROR(subQ!S24/subQ!R24-1,"") | T31: =IFERROR(subQ!T24/subQ!S24-1,"") | V31: =IFERROR(subQ!V24/subQ!T24-1,"") | W31: =IFERROR(subQ!W24/subQ!V24-1,"") | X31: =IFERROR(subQ!X24/subQ!W24-1,"") | Y31: =IFERROR(subQ!Y24/subQ!X24-1,"") | AA31: =IFERROR(subQ!AA24/subQ!Y24-1,"") | AB31: =IFERROR(subQ!AB24/subQ!AA24-1,"") | AC31: -5.27e-07 | AD31: 0 | AF31: 0 | AG31: 0 | AH31: 0 | AI31: 0 | AK31: 0 | AL31: 0 | AM31: 0 | AN31: 0
A32: drv:자본총계 | B32: roll | C32: 자본총계 기타변동(배당 등, 억원) | G32: =IFERROR(subQ!E25+subQ!G19-subQ!G25,"") | H32: =IFERROR(subQ!G25+subQ!H19-subQ!H25,"") | I32: =IFERROR(subQ!H25+subQ!I19-subQ!I25,"") | J32: =IFERROR(subQ!I25+subQ!J19-subQ!J25,"") | L32: =IFERROR(subQ!J25+subQ!L19-subQ!L25,"") | M32: =IFERROR(subQ!L25+subQ!M19-subQ!M25,"") | N32: =IFERROR(subQ!M25+subQ!N19-subQ!N25,"") | O32: =IFERROR(subQ!N25+subQ!O19-subQ!O25,"") | Q32: =IFERROR(subQ!O25+subQ!Q19-subQ!Q25,"") | R32: =IFERROR(subQ!Q25+subQ!R19-subQ!R25,"") | S32: =IFERROR(subQ!R25+subQ!S19-subQ!S25,"") | T32: =IFERROR(subQ!S25+subQ!T19-subQ!T25,"") | V32: =IFERROR(subQ!T25+subQ!V19-subQ!V25,"") | W32: =IFERROR(subQ!V25+subQ!W19-subQ!W25,"") | X32: =IFERROR(subQ!W25+subQ!X19-subQ!X25,"") | Y32: =IFERROR(subQ!X25+subQ!Y19-subQ!Y25,"") | AA32: =IFERROR(subQ!Y25+subQ!AA19-subQ!AA25,"") | AB32: =IFERROR(subQ!AA25+subQ!AB19-subQ!AB25,"") | AC32: 0.003104454 | AD32: -8.7193e-05 | AF32: -0.009884698 | AG32: 0.010116286 | AH32: 8.4064e-05 | AI32: 5.1448e-05 | AK32: 0.000119734 | AL32: 2.026e-05 | AM32: 0.009920667 | AN32: -0.000145049
A33: drv:지배주주지분 | B33: roll | C33: 지배주주지분 기타변동(배당 등, 억원) | G33: =IFERROR(subQ!E26+subQ!G20-subQ!G26,"") | H33: =IFERROR(subQ!G26+subQ!H20-subQ!H26,"") | I33: =IFERROR(subQ!H26+subQ!I20-subQ!I26,"") | J33: =IFERROR(subQ!I26+subQ!J20-subQ!J26,"") | L33: =IFERROR(subQ!J26+subQ!L20-subQ!L26,"") | M33: =IFERROR(subQ!L26+subQ!M20-subQ!M26,"") | N33: =IFERROR(subQ!M26+subQ!N20-subQ!N26,"") | O33: =IFERROR(subQ!N26+subQ!O20-subQ!O26,"") | Q33: =IFERROR(subQ!O26+subQ!Q20-subQ!Q26,"") | R33: =IFERROR(subQ!Q26+subQ!R20-subQ!R26,"") | S33: =IFERROR(subQ!R26+subQ!S20-subQ!S26,"") | T33: =IFERROR(subQ!S26+subQ!T20-subQ!T26,"") | V33: =IFERROR(subQ!T26+subQ!V20-subQ!V26,"") | W33: =IFERROR(subQ!V26+subQ!W20-subQ!W26,"") | X33: =IFERROR(subQ!W26+subQ!X20-subQ!X26,"") | Y33: =IFERROR(subQ!X26+subQ!Y20-subQ!Y26,"") | AA33: =IFERROR(subQ!Y26+subQ!AA20-subQ!AA26,"") | AB33: =IFERROR(subQ!AA26+subQ!AB20-subQ!AB26,"") | AC33: 0.000504454 | AD33: -8.7193e-05 | AF33: 0.000115302 | AG33: 0.000116286 | AH33: 8.4064e-05 | AI33: 5.1448e-05 | AK33: 0.000119734 | AL33: 0.01002026 | AM33: -7.9333e-05 | AN33: -0.000145049
A34: drv:총차입금 | B34: qoq | C34: 총차입금 QoQ | G34: =IFERROR(subQ!G27/subQ!E27-1,"") | H34: =IFERROR(subQ!H27/subQ!G27-1,"") | I34: =IFERROR(subQ!I27/subQ!H27-1,"") | J34: =IFERROR(subQ!J27/subQ!I27-1,"") | L34: =IFERROR(subQ!L27/subQ!J27-1,"") | M34: =IFERROR(subQ!M27/subQ!L27-1,"") | N34: =IFERROR(subQ!N27/subQ!M27-1,"") | O34: =IFERROR(subQ!O27/subQ!N27-1,"") | Q34: =IFERROR(subQ!Q27/subQ!O27-1,"") | R34: =IFERROR(subQ!R27/subQ!Q27-1,"") | S34: =IFERROR(subQ!S27/subQ!R27-1,"") | T34: =IFERROR(subQ!T27/subQ!S27-1,"") | V34: =IFERROR(subQ!V27/subQ!T27-1,"") | W34: =IFERROR(subQ!W27/subQ!V27-1,"") | X34: =IFERROR(subQ!X27/subQ!W27-1,"") | Y34: =IFERROR(subQ!Y27/subQ!X27-1,"") | AA34: =IFERROR(subQ!AA27/subQ!Y27-1,"") | AB34: =IFERROR(subQ!AB27/subQ!AA27-1,"") | AC34: -5.486e-06 | AD34: 0 | AF34: 0 | AG34: 0 | AH34: 0 | AI34: 0 | AK34: 0 | AL34: 0 | AM34: 0 | AN34: 0
A35: drv:순차입금 | B35: qoq | C35: 순차입금 QoQ | G35: =IFERROR(subQ!G28/subQ!E28-1,"") | H35: =IFERROR(subQ!H28/subQ!G28-1,"") | I35: =IFERROR(subQ!I28/subQ!H28-1,"") | J35: =IFERROR(subQ!J28/subQ!I28-1,"") | L35: =IFERROR(subQ!L28/subQ!J28-1,"") | M35: =IFERROR(subQ!M28/subQ!L28-1,"") | N35: =IFERROR(subQ!N28/subQ!M28-1,"") | O35: =IFERROR(subQ!O28/subQ!N28-1,"") | Q35: =IFERROR(subQ!Q28/subQ!O28-1,"") | R35: =IFERROR(subQ!R28/subQ!Q28-1,"") | S35: =IFERROR(subQ!S28/subQ!R28-1,"") | T35: =IFERROR(subQ!T28/subQ!S28-1,"") | V35: =IFERROR(subQ!V28/subQ!T28-1,"") | W35: =IFERROR(subQ!W28/subQ!V28-1,"") | X35: =IFERROR(subQ!X28/subQ!W28-1,"") | Y35: =IFERROR(subQ!Y28/subQ!X28-1,"") | AA35: =IFERROR(subQ!AA28/subQ!Y28-1,"") | AB35: =IFERROR(subQ!AB28/subQ!AA28-1,"") | AC35: 0.010491073 | AD35: 0.010336505 | AF35: 0.010299998 | AG35: 0.010246393 | AH35: 0.010125509 | AI35: 0.009956848 | AK35: 0.009958437 | AL35: 0.009860245 | AM35: 0.009763969 | AN35: 0.009572699
A36: drv:이자발생자산 | B36: qoq | C36: 이자발생자산 QoQ | G36: =IFERROR(subQ!G29/subQ!E29-1,"") | H36: =IFERROR(subQ!H29/subQ!G29-1,"") | I36: =IFERROR(subQ!I29/subQ!H29-1,"") | J36: =IFERROR(subQ!J29/subQ!I29-1,"") | L36: =IFERROR(subQ!L29/subQ!J29-1,"") | M36: =IFERROR(subQ!M29/subQ!L29-1,"") | N36: =IFERROR(subQ!N29/subQ!M29-1,"") | O36: =IFERROR(subQ!O29/subQ!N29-1,"") | Q36: =IFERROR(subQ!Q29/subQ!O29-1,"") | R36: =IFERROR(subQ!R29/subQ!Q29-1,"") | S36: =IFERROR(subQ!S29/subQ!R29-1,"") | T36: =IFERROR(subQ!T29/subQ!S29-1,"") | V36: =IFERROR(subQ!V29/subQ!T29-1,"") | W36: =IFERROR(subQ!W29/subQ!V29-1,"") | X36: =IFERROR(subQ!X29/subQ!W29-1,"") | Y36: =IFERROR(subQ!Y29/subQ!X29-1,"") | AA36: =IFERROR(subQ!AA29/subQ!Y29-1,"") | AB36: =IFERROR(subQ!AB29/subQ!AA29-1,"") | AC36: -0.035924541 | AD36: -0.037009158 | AF36: -0.038822303 | AG36: -0.040458119 | AH36: -0.042163995 | AI36: -0.04379885 | AK36: -0.046190623 | AL36: -0.04842752 | AM36: -0.050807137 | AN36: -0.053168636
A37: drv:현금및현금성자산 | B37: qoq | C37: 현금및현금성자산 QoQ | G37: =IFERROR(subQ!G30/subQ!E30-1,"") | H37: =IFERROR(subQ!H30/subQ!G30-1,"") | I37: =IFERROR(subQ!I30/subQ!H30-1,"") | J37: =IFERROR(subQ!J30/subQ!I30-1,"") | L37: =IFERROR(subQ!L30/subQ!J30-1,"") | M37: =IFERROR(subQ!M30/subQ!L30-1,"") | N37: =IFERROR(subQ!N30/subQ!M30-1,"") | O37: =IFERROR(subQ!O30/subQ!N30-1,"") | Q37: =IFERROR(subQ!Q30/subQ!O30-1,"") | R37: =IFERROR(subQ!R30/subQ!Q30-1,"") | S37: =IFERROR(subQ!S30/subQ!R30-1,"") | T37: =IFERROR(subQ!T30/subQ!S30-1,"") | V37: =IFERROR(subQ!V30/subQ!T30-1,"") | W37: =IFERROR(subQ!W30/subQ!V30-1,"") | X37: =IFERROR(subQ!X30/subQ!W30-1,"") | Y37: =IFERROR(subQ!Y30/subQ!X30-1,"") | AA37: =IFERROR(subQ!AA30/subQ!Y30-1,"") | AB37: =IFERROR(subQ!AB30/subQ!AA30-1,"")
A38: drv:CAPEX | B38: yoy | C38: CAPEX YoY | J38: =IFERROR(subQ!J31/subQ!E31-1,"") | L38: =IFERROR(subQ!L31/subQ!G31-1,"") | M38: =IFERROR(subQ!M31/subQ!H31-1,"") | N38: =IFERROR(subQ!N31/subQ!I31-1,"") | O38: =IFERROR(subQ!O31/subQ!J31-1,"") | Q38: =IFERROR(subQ!Q31/subQ!L31-1,"") | R38: =IFERROR(subQ!R31/subQ!M31-1,"") | S38: =IFERROR(subQ!S31/subQ!N31-1,"") | T38: =IFERROR(subQ!T31/subQ!O31-1,"") | V38: =IFERROR(subQ!V31/subQ!Q31-1,"") | W38: =IFERROR(subQ!W31/subQ!R31-1,"") | X38: =IFERROR(subQ!X31/subQ!S31-1,"") | Y38: =IFERROR(subQ!Y31/subQ!T31-1,"") | AA38: =IFERROR(subQ!AA31/subQ!V31-1,"") | AB38: =IFERROR(subQ!AB31/subQ!W31-1,"") | AC38: 0.93347911 | AD38: -0.66260318 | AF38: 0.088717517 | AG38: -0.074635087 | AH38: 0 | AI38: 0 | AK38: 0 | AL38: 0 | AM38: 0 | AN38: 0
A39: drv:영업활동현금흐름 | B39: yoy | C39: 영업활동현금흐름 YoY | J39: =IFERROR(subQ!J32/subQ!E32-1,"") | L39: =IFERROR(subQ!L32/subQ!G32-1,"") | M39: =IFERROR(subQ!M32/subQ!H32-1,"") | N39: =IFERROR(subQ!N32/subQ!I32-1,"") | O39: =IFERROR(subQ!O32/subQ!J32-1,"") | Q39: =IFERROR(subQ!Q32/subQ!L32-1,"") | R39: =IFERROR(subQ!R32/subQ!M32-1,"") | S39: =IFERROR(subQ!S32/subQ!N32-1,"") | T39: =IFERROR(subQ!T32/subQ!O32-1,"") | V39: =IFERROR(subQ!V32/subQ!Q32-1,"") | W39: =IFERROR(subQ!W32/subQ!R32-1,"") | X39: =IFERROR(subQ!X32/subQ!S32-1,"") | Y39: =IFERROR(subQ!Y32/subQ!T32-1,"") | AA39: =IFERROR(subQ!AA32/subQ!V32-1,"") | AB39: =IFERROR(subQ!AB32/subQ!W32-1,"")
A40: drv:주식수 | B40: qoq | C40: 주식수 QoQ | G40: =IFERROR(subQ!G33/subQ!E33-1,"") | H40: =IFERROR(subQ!H33/subQ!G33-1,"") | I40: =IFERROR(subQ!I33/subQ!H33-1,"") | J40: =IFERROR(subQ!J33/subQ!I33-1,"") | L40: =IFERROR(subQ!L33/subQ!J33-1,"") | M40: =IFERROR(subQ!M33/subQ!L33-1,"") | N40: =IFERROR(subQ!N33/subQ!M33-1,"") | O40: =IFERROR(subQ!O33/subQ!N33-1,"") | Q40: =IFERROR(subQ!Q33/subQ!O33-1,"") | R40: =IFERROR(subQ!R33/subQ!Q33-1,"") | S40: =IFERROR(subQ!S33/subQ!R33-1,"") | T40: =IFERROR(subQ!T33/subQ!S33-1,"") | V40: =IFERROR(subQ!V33/subQ!T33-1,"") | W40: =IFERROR(subQ!W33/subQ!V33-1,"") | X40: =IFERROR(subQ!X33/subQ!W33-1,"") | Y40: =IFERROR(subQ!Y33/subQ!X33-1,"") | AA40: =IFERROR(subQ!AA33/subQ!Y33-1,"") | AB40: =IFERROR(subQ!AB33/subQ!AA33-1,"") | AC40: 0 | AD40: 0 | AF40: 0 | AG40: 0 | AH40: 0 | AI40: 0 | AK40: 0 | AL40: 0 | AM40: 0 | AN40: 0
A41: drv:DPS | B41: abs | C41: DPS (가정, 원) | E41: =subQ!E36 | F41: =subQ!F36 | G41: =subQ!G36 | H41: =subQ!H36 | I41: =subQ!I36 | J41: =subQ!J36 | K41: =subQ!K36 | L41: =subQ!L36 | ... AB41: =subQ!AB36 | AD41: 0 | AE41: =subQ!AE36 | AI41: 0 | AJ41: =subQ!AJ36 | AN41: 0 | AO41: =subQ!AO36
B43: 3. 밸류에이션·스칼라 | C43: 노란 셀 = 가정. '연결' 표시는 추정 전 분기 수식이 이 셀을 참조한다는 뜻
A44: sc:종가 | C44: 종가 | D44: 1772 | E44: 원 — 네이버 정규장 종가(aik 확정종가 대조 · aik 1,648원)
A45: sc:기준일 | C45: 기준일 | D45: 20261019 | E45: 종가 기준일
A46: sc:COE | C46: COE | D46: 0.09 | E46: 자기자본비용(가정) — TP 적정 PBR = ROE/COE
A47: sc:PER_lo | C47: PER_lo | D47: 10 | E47: PER 밴드 하단(배) — sector_default(레퍼런스 TP_PE PB 예시 10/15/20배; 과거 PER 중위 105.0배가 3~40 밖(턴어라운드 왜곡))
A48: sc:PER_mid | C48: PER_mid | D48: 15 | E48: PER 밴드 중단(배)
A49: sc:PER_hi | C49: PER_hi | D49: 20 | E49: PER 밴드 상단(배)
A50: sc:EPS_Y1가중 | C50: EPS_Y1가중 | D50: 0.5 | E50: 12M fwd EPS = FY(last_actual연도)E × w + FY+1E × (1−w) — 기준 분기 2Q 이면 0.5(가정)
A51: sc:세율 | C51: 세율 | D51: 0.22 | E51: 참고(연결 안 됨: MAX(세전,0)×단일 세율로 재현 불가(지주 자회사 합산 등) → 분기별 역산) — 모델 assumptions 값 · 최근 12분기 세전 합 ≤ 0; 세전 > 0 분기 중위 0.0% 도 5~27% 밖 → 법정세율 근사 22% 가정
A52: sc:판관비율 | C52: 판관비율 | D52: 0.12967817 | E52: 연결 — 판관비 = 매출액 × 판관비율(역산, 재현 오차 ≤ 0.05억 · 모델 assumptions 0.1297)
A53: sc:지배주주비중 | C53: 지배주주비중 | D53: 1 | E53: 연결 — 지배주주순이익 = 당기순이익 × 비중(역산, 재현 오차 ≤ 0.05억)
A54: sc:이자율_자산 | C54: 이자율_자산 | D54: 0.013422055 | E54: 연결 — 이자손익 = (전분기 이자발생자산 × 자산이자율 − 전분기 총차입금 × 부채이자율)/4(역산, 재현 오차 ≤ 0.05억 · 모델 assumptions 0.0136)
A55: sc:이자율_부채 | C55: 이자율_부채 | D55: 0.041776515 | E55: 연결 — 같은 수식의 부채 쪽(총차입금 행이 없으면 0)(역산, 재현 오차 ≤ 0.05억 · 모델 assumptions 0.0418)
A56: sc:배당성향 | C56: 배당성향 | E56: 배당성향(참고 — 모델은 직전 DPS 유지·Q2 지급 가정)
A57: sc:외화순노출_백만$ | C57: 외화순노출_백만$ | E57: 외화 순노출 × Δ기말환율 (외화 시트 방식) — 외화 순노출 미공시(face) → 0 + 표기
A58: sc:헤지비율 | C58: 헤지비율 | E58: sls 없음
A59: sc:헤지환율_약정 | C59: 헤지환율_약정 | E59: sls 없음

Sheet BS연결
B1: (백만원) | C1: 이름: BS연결H | E1: 4Q21 | F1: 2021 | G1: 1Q22 | H1: 2Q22 | I1: 3Q22 | J1: 4Q22 | K1: 2022 | L1: 1Q23 | M1: 2Q23 | N1: 3Q23 | O1: 4Q23 | P1: 2023 | Q1: 1Q24 | R1: 2Q24 | S1: 3Q24 | T1: 4Q24 | U1: 2024 | V1: 1Q25 | W1: 2Q25 | X1: 3Q25 | Y1: 4Q25 | Z1: 2025 | AA1: 1Q26 | AB1: 2Q26 | AC1: 3Q26 | AD1: 4Q26 | AE1: 2026 | AF1: 1Q27 | AG1: 2Q27 | AH1: 3Q27 | AI1: 4Q27 | AJ1: 2027 | AK1: 1Q28 | AL1: 2Q28 | AM1: 3Q28 | AN1: 4Q28 | AO1: 2028
B2: 연결 | D2: fin json(kship_fin.py)
B3: 대창솔루션(연) | C3: UPDATE: 26-10-19 | E3: 1 | F3: 2 | G3: 3 | H3: 4 | I3: 5 | J3: 6 | K3: 7 | L3: 8 | M3: 9 | N3: 10 | O3: 11 | P3: 12 | Q3: 13 | R3: 14 | S3: 15 | T3: 16 | U3: 17 | V3: 18 | W3: 19 | X3: 20 | Y3: 21 | Z3: 22 | AA3: 23 | AB3: 24 | AC3: 25 | AD3: 26 | AE3: 27 | AF3: 28 | AG3: 29 | AH3: 30 | AI3: 31 | AJ3: 32 | AK3: 33 | AL3: 34 | AM3: 35 | AN3: 36 | AO3: 37
B4: Account Code | C4: AccountNAME | E4: 2021.12 | F4: 2021.12A | G4: 2022.03 | H4: 2022.06 | I4: 2022.09 | J4: 2022.12 | K4: 2022.12A | L4: 2023.03 | M4: 2023.06 | N4: 2023.09 | O4: 2023.12 | P4: 2023.12A | Q4: 2024.03 | R4: 2024.06 | S4: 2024.09 | T4: 2024.12 | U4: 2024.12A | V4: 2025.03 | W4: 2025.06 | X4: 2025.09 | Y4: 2025.12 | Z4: 2025.12A | AA4: 2026.03 | AB4: 2026.06 | AC4: 2026.09 | AD4: 2026.12 | AE4: 2026.12A | AF4: 2027.03 | AG4: 2027.06 | AH4: 2027.09 | AI4: 2027.12 | AJ4: 2027.12A | AK4: 2028.03 | AL4: 2028.06 | AM4: 2028.09 | AN4: 2028.12 | AO4: 2028.12A
A5: 1 | C5: 유동자산 | E5: 24556.46 | F5: 24556.46 | G5: 25107.33 | H5: 25596.04 | I5: 26728.68 | J5: 32748.23 | K5: 32748.23 | L5: 33105.99 | M5: 34157.52 | N5: 35131.96 | O5: 33319.96 | P5: 33319.96 | Q5: 39015.31 | R5: 40092.91 | S5: 37252.08 | T5: 40739.03 | U5: 40739.03 | V5: 41302.78 | W5: 43434.69 | X5: 47226.64 | Y5: 47475.46 | Z5: 47475.46 | AA5: 52752.53 | AB5: 55269.5
A6: 1 | C6: 현금및현금성자산 | E6: 5428.9 | F6: 5428.9 | G6: 726.75 | H6: 416.23 | I6: 1551.7 | J6: 1405.13 | K6: 1405.13 | L6: 2859.69 | M6: 2956.34 | N6: 2641.36 | O6: 6154.52 | P6: 6154.52 | Q6: 10783.2 | R6: 9059.81 | S6: 8414.06 | T6: 13311.7 | U6: 13311.7 | V6: 11889.63 | W6: 11018.06 | X6: 15450.44 | Y6: 9331.88 | Z6: 9331.88 | AA6: 11124.41 | AB6: 13491.59
A7: 1 | C7: 단기금융상품 | E7: 1072.61 | F7: 1072.61 | G7: 1120.61 | H7: 1120.61 | I7: 1045.15 | J7: 1600.25 | K7: 1600.25 | L7: 1591.69 | M7: 2650.21 | N7: 2033.27 | O7: 1907.66 | P7: 1907.66 | Q7: 2072.66 | R7: 1916.3 | S7: 1916.3 | T7: 2217.4 | U7: 2217.4 | V7: 1069.4 | W7: 744.82 | X7: 745.82 | Y7: 2832.42 | Z7: 2832.42 | AA7: 2835.42 | AB7: 2838.42
A8: 1 | C8: 단기금융자산 | E8: 1072.61 | F8: 1072.61 | G8: 1120.61 | H8: 1120.61 | I8: 1045.15 | J8: 1600.25 | K8: 1600.25 | L8: 1591.69 | M8: 2650.21 | N8: 2033.27 | O8: 2154.7 | P8: 2154.7 | Q8: 2985.95 | R8: 3115.78 | S8: 3115.78 | T8: 2278.13 | U8: 2278.13 | V8: 1130.13 | W8: 1473.54 | X8: 748.39 | Y8: 2988.9 | Z8: 2988.9 | AA8: 2835.42 | AB8: 2838.42
A9: 1 | C9: 매출채권및기타채권 | E9: 6911.78 | F9: 6911.78 | G9: 8909.25 | H9: 10023.11 | I9: 7712.26 | J9: 13901.61 | K9: 13901.61 | L9: 11008.88 | M9: 9582.27 | N9: 10768.44 | O9: 10251.21 | P9: 10251.21 | Q9: 9947.95 | R9: 13154.73 | S9: 10109.55 | T9: 10924.39 | U9: 10924.39 | V9: 9493.35 | W9: 11565.88 | X9: 9805.72 | Y9: 11937.03 | Z9: 11937.03 | AA9: 15256.88 | AB9: 15939.69
A10: 1 | C10: 계약자산 | E10: 1251.92 | F10: 1251.92 | G10: 3435.05 | H10: 2702.96 | I10: 2898.46 | J10: 2540.01 | K10: 2540.01 | L10: 3657.64 | M10: 3707.98 | N10: 2710.81 | O10: 1748.47 | P10: 1748.47 | Q10: 3592.18 | R10: 2036.5 | S10: 3175.35 | T10: 2410.3 | U10: 2410.3 | V10: 3224.68 | W10: 2636.35 | X10: 2207.72 | Y10: 3023.37 | Z10: 3023.37 | AA10: 3399.35 | AB10: 2265.57
A11: 1 | C11: 당기법인세자산(선급법인세) | E11: 68.21 | F11: 68.21 | G11: 68.73 | H11: 63.1 | I11: 1.38 | J11: 3.2 | K11: 3.2 | L11: 4.16 | M11: 2.3 | N11: 3.36 | O11: 10.69 | P11: 10.69 | Q11: 11.04 | R11: 3.85 | S11: 4.58 | T11: 15.26 | U11: 15.26 | V11: 17.11 | W11: 4.92 | X11: 64.08 | Y11: 64.73 | Z11: 64.73 | AA11: 65.61 | AB11: 6.03
A12: 1 | C12: 재고자산 | E12: 9250.28 | F12: 9250.28 | G12: 9707.44 | H12: 10073.92 | I12: 12175.74 | J12: 12497.23 | K12: 12497.23 | L12: 12566.15 | M12: 13858.95 | N12: 15521.72 | O12: 12362.97 | P12: 12362.97 | Q12: 11200.3 | R12: 12261.6 | S12: 11967.29 | T12: 10649.6 | U12: 10649.6 | V12: 14349.12 | W12: 15757.27 | X12: 16874.57 | Y12: 16671.53 | Z12: 16671.53 | AA12: 17831.5 | AB12: 19118.1
A13: 1 | C13: 기타유동자산 | E13: 572.77 | F13: 572.77 | G13: 1139.5 | H13: 1196.12 | I13: 1344.01 | J13: 800.79 | K13: 800.79 | L13: 1417.77 | M13: 1399.49 | N13: 1453 | O13: 637.4 | P13: 637.4 | Q13: 494.69 | R13: 460.63 | S13: 465.47 | T13: 1149.65 | U13: 1149.65 | V13: 1198.77 | W13: 978.66 | X13: 2075.72 | Y13: 3458.02 | Z13: 3458.02 | AA13: 2239.36 | AB13: 1610.1
A14: 1 | C14: 비유동자산 | E14: 95002.15 | F14: 95002.15 | G14: 94917.05 | H14: 92615.34 | I14: 92892.73 | J14: 91430.13 | K14: 91430.13 | L14: 91280.59 | M14: 91667.57 | N14: 91849.63 | O14: 95501.62 | P14: 95501.62 | Q14: 95312.52 | R14: 95416.67 | S14: 95313.98 | T14: 94689.52 | U14: 94689.52 | V14: 94687.14 | W14: 94336.73 | X14: 94130.47 | Y14: 94357.73 | Z14: 94357.73 | AA14: 94393.23 | AB14: 94157.89
A15: 1 | C15: 장기금융자산 | E15: 2845.82 | F15: 2845.82 | G15: 2988.61 | H15: 1241.54 | I15: 1539.12 | J15: 120.31 | K15: 120.31 | L15: 115.78 | M15: 123.14 | N15: 24.53 | O15: 80.04 | P15: 80.04 | Q15: 80.04 | R15: 24.04 | S15: 63.79 | T15: 377.46 | U15: 377.46 | V15: 407.46 | W15: 287.64 | X15: 297.64 | Y15: 204.04 | Z15: 204.04 | AA15: 204.04 | AB15: 206.04
A16: 1 | C16: 투자자산 | E16: 2845.82 | F16: 2845.82 | G16: 2988.61 | H16: 1241.54 | I16: 1539.12 | J16: 120.31 | K16: 120.31 | L16: 115.78 | M16: 123.14 | N16: 24.53 | O16: 80.04 | P16: 80.04 | Q16: 80.04 | R16: 24.04 | S16: 63.79 | T16: 377.46 | U16: 377.46 | V16: 407.46 | W16: 287.64 | X16: 297.64 | Y16: 204.04 | Z16: 204.04 | AA16: 204.04 | AB16: 206.04
... A24: 1 | C24: 단기차입금 | E24: 51332.92 | F24: 51332.92 | G24: 52448.56 | H24: 51972.01 | I24: 49745.6 | J24: 54192.86 | K24: 54192.86 | L24: 51504.29 | M24: 42180.76 | N24: 46438.65 | O24: 46265.1 | P24: 46265.1 | Q24: 40887.99 | R24: 42834.43 | S24: 41256.15 | T24: 40752.57 | U24: 40752.57 | V24: 39253.75 | W24: 43128.31 | X24: 42633.48 | Y24: 29850.99 | Z24: 29850.99 | AA24: 26648.23 | AB24: 22793.98
A25: 1 | C25: 단기금융부채(face) | E25: 51332.92 | F25: 51332.92 | G25: 52448.56 | H25: 51972.01 | I25: 49745.6 | J25: 54192.86 | K25: 54192.86 | L25: 51504.29 | N25: 46438.65 | O25: 46265.1 | P25: 46265.1 | Q25: 40887.99 | R25: 42834.43 | S25: 41256.15 | T25: 40752.57 | U25: 40752.57 | V25: 39253.75 | W25: 43128.31 | X25: 42633.48 | Y25: 29850.99 | Z25: 29850.99 | AA25: 26648.23 | AB25: 22793.98
A26: 1 | C26: 단기충당부채 | E26: 109.59 | F26: 109.59 | G26: 110.9 | H26: 112.31 | I26: 110.86 | J26: 114.19 | K26: 114.19 | L26: 129.35 | M26: 140.55 | N26: 139.76 | O26: 113.78 | P26: 113.78 | Q26: 94.64 | R26: 95.11 | S26: 92.99 | T26: 100.57 | U26: 100.57 | V26: 113.38 | W26: 140.35 | X26: 152.82 | Y26: 270.49 | Z26: 270.49 | AA26: 424.21 | AB26: 423.09
A27: 1 | C27: 기타유동금융부채 | E27: 3244.45 | F27: 3244.45 | G27: 4142.7 | H27: 2868.12 | I27: 2536.4 | J27: 4350.92 | K27: 4350.92 | L27: 3438.54 | M27: 3765.69 | N27: 5272 | O27: 3243.43 | P27: 3243.43 | Q27: 3458.77 | R27: 3320.74 | S27: 2426.72 | T27: 3399.62 | U27: 3399.62 | V27: 2871.38 | W27: 2949.69 | X27: 4209.74 | Y27: 3835.66 | Z27: 3835.66 | AA27: 3171.59 | AB27: 3870.1
A28: 1 | C28: 단기금융부채 | E28: 3303.28 | F28: 3303.28 | G28: 4201.53 | H28: 2888.73 | I28: 2557.01 | J28: 4413.71 | K28: 4413.71 | L28: 3501.33 | M28: 3826.35 | N28: 5332.66 | O28: 7335.62 | P28: 7335.62 | Q28: 14812.56 | R28: 12118.3 | S28: 11223.98 | T28: 8350.93 | U28: 8350.93 | V28: 7822.69 | W28: 6539.55 | X28: 6350.99 | Y28: 6640.13 | Z28: 6640.13 | AA28: 5362.9 | AB28: 6251.13
A29: 1 | C29: 기타유동부채 | E29: 1502.21 | F29: 1502.21 | G29: 1623.16 | H29: 2982.48 | I29: 6820.91 | J29: 11000.85 | K29: 11000.85 | L29: 11155.01 | M29: 8996.44 | N29: 7797.03 | O29: 1997.42 | P29: 1997.42 | Q29: 1769.84 | R29: 2097.24 | S29: 2412.67 | T29: 1215.93 | U29: 1215.93 | V29: 1957.73 | W29: 999.66 | X29: 743.96 | Y29: 542.61 | Z29: 542.61 | AA29: 707.22 | AB29: 2242.44
A30: 1 | C30: 유동리스부채 | E30: 58.83 | F30: 58.83 | G30: 58.83 | H30: 20.61 | I30: 20.61 | J30: 62.79 | K30: 62.79 | L30: 62.79 | M30: 60.66 | N30: 60.66 | O30: 66.63 | P30: 66.63 | Q30: 66.63 | R30: 62.7 | S30: 62.4 | T30: 59.64 | U30: 59.64 | V30: 59.64 | W30: 57.31 | X30: 57.31 | Y30: 66.2 | Z30: 66.2 | AA30: 58.38 | AB30: 37.07
A31: 1 | C31: 리스부채 | E31: 108.97 | F31: 108.97 | G31: 108.97 | H31: 48.19 | I31: 48.19 | J31: 205.37 | K31: 205.37 | L31: 205.37 | M31: 162.68 | N31: 162.68 | O31: 150.73 | P31: 150.73 | Q31: 150.73 | R31: 115.99 | S31: 120.09 | T31: 101.1 | U31: 101.1 | V31: 101.1 | W31: 70.08 | X31: 70.08 | Y31: 166.95 | Z31: 166.95 | AA31: 159.13 | AB31: 105.63
A32: 1 | C32: 비유동부채 | E32: 19232.54 | F32: 19232.54 | G32: 18521.63 | H32: 18257.56 | I32: 21361.99 | J32: 14406.7 | K32: 14406.7 | L32: 16448.86 | M32: 16529.91 | N32: 20206.43 | O32: 26199.09 | P32: 26199.09 | Q32: 32410.84 | R32: 32482.39 | S32: 33895.31 | T32: 29803.9 | U32: 29803.9 | V32: 31847.4 | W32: 28803.96 | X32: 29175.87 | Y32: 43370.69 | Z32: 43370.69 | AA32: 51469.09 | AB32: 53368.58
A33: 1 | C33: 장기차입금 | E33: 9378.89 | F33: 9378.89 | G33: 8701.68 | H33: 8350.04 | I33: 11341.84 | J33: 4815.38 | K33: 4815.38 | L33: 6828.81 | M33: 6879.59 | N33: 10437.41 | O33: 10090.68 | P33: 10090.68 | Q33: 11803.64 | R33: 11608.29 | S33: 13138.43 | T33: 18409.27 | U33: 18409.27 | V33: 20251.36 | W33: 17157.01 | X33: 16932.57 | Y33: 30870 | Z33: 30870 | AA33: 38870 | AB33: 41720
A34: 1 | C34: 확정급여부채 | E34: 2632.13 | F34: 2632.13 | G34: 2762.22 | H34: 2831.3 | I34: 2926.69 | J34: 2573.94 | K34: 2573.94 | L34: 2652.66 | M34: 2642.67 | N34: 2703.26 | O34: 3272.71 | P34: 3272.71 | Q34: 3309.65 | R34: 3400.14 | S34: 3300.73 | T34: 2729.14 | U34: 2729.14 | V34: 2901.24 | W34: 2955.03 | X34: 3091.18 | Y34: 2888.72 | Z34: 2888.72 | AA34: 2959.22 | AB34: 2010.52
A35: 1 | C35: 이연법인세부채 | E35: 6160.52 | F35: 6160.52 | G35: 6160.52 | H35: 6160.52 | I35: 6160.52 | J35: 5880.5 | K35: 5880.5 | L35: 5880.5 | M35: 5880.5 | N35: 5880.5 | O35: 6848.58 | P35: 6848.58 | Q35: 6848.58 | R35: 6848.58 | S35: 6848.58 | T35: 6848.58 | U35: 6848.58 | V35: 6848.58 | W35: 6848.58 | X35: 6848.58 | Y35: 7187.47 | Z35: 7187.47 | AA35: 7187.47 | AB35: 7187.47
A36: 1 | C36: 기타비유동금융부채 | E36: 640.54 | F36: 640.54 | G36: 476.75 | H36: 517.8 | I36: 535.03 | J36: 876.82 | K36: 876.82 | L36: 826.82 | M36: 907.64 | N36: 965.74 | O36: 1052.92 | P36: 1052.92 | Q36: 1083.06 | R36: 1141.5 | S36: 911.51 | T36: 975.46 | U36: 975.46 | V36: 1004.77 | W36: 1030.57 | X36: 1090.77 | Y36: 1123.74 | Z36: 1123.74 | AA36: 1151.65 | AB36: 1182.03
A37: 1 | C37: 장기금융부채 | E37: 943.52 | F37: 943.52 | G37: 779.73 | H37: 798.22 | I37: 815.45 | J37: 1019.4 | K37: 1019.4 | L37: 969.4 | M37: 1009.66 | N37: 1067.76 | O37: 1137.02 | P37: 1137.02 | Q37: 1167.16 | R37: 1194.79 | S37: 969.2 | T37: 1016.92 | U37: 1016.92 | V37: 1046.23 | W37: 1043.34 | X37: 1103.54 | Y37: 1224.49 | Z37: 1224.49 | AA37: 1252.4 | AB37: 1250.59
... A39: 1 | C39: 비유동리스부채 | E39: 50.14 | F39: 50.14 | G39: 50.14 | H39: 27.58 | I39: 27.58 | J39: 142.58 | K39: 142.58 | L39: 142.58 | M39: 102.02 | N39: 102.02 | O39: 84.1 | P39: 84.1 | Q39: 84.1 | R39: 53.29 | S39: 57.69 | T39: 41.46 | U39: 41.46 | V39: 41.46 | W39: 12.77 | X39: 12.77 | Y39: 100.75 | Z39: 100.75 | AA39: 100.75 | AB39: 68.56
A40: 1 | C40: 장기파생상품부채 | E40: 252.84 | F40: 252.84 | G40: 252.84 | H40: 252.84 | I40: 252.84 | J40: 0 | K40: 0 | L40: 0 | O40: 0 | P40: 0 | T40: 0 | U40: 0 | V40: 0
A41: 1 | C41: 부채총계 | E41: 82707.19 | F41: 82707.19 | G41: 85322.46 | H41: 85693.54 | I41: 88946.36 | J41: 95237.19 | K41: 95237.19 | L41: 93989.89 | M41: 94071.64 | N41: 94430.52 | O41: 93059.26 | P41: 93059.26 | Q41: 98110.65 | R41: 97877.93 | S41: 96449.3 | T41: 102592.31 | U41: 102592.31 | V41: 104939.66 | W41: 102926.03 | X41: 104238.37 | Y41: 105830.49 | Z41: 105830.49 | AA41: 110121.63 | AB41: 113884.06
A42: 1 | C42: 지배주주지분 | E42: 33482.84 | F42: 33482.84 | G42: 31628.7 | H42: 29813.69 | I42: 28119.57 | J42: 26364.39 | K42: 26364.39 | L42: 27653.41 | M42: 28952.89 | N42: 28731.43 | O42: 30125.66 | P42: 30125.66 | Q42: 30514.6 | R42: 31545.53 | S42: 30393.07 | T42: 26838.75 | U42: 26838.75 | V42: 25563.18 | W42: 30000.5 | X42: 31932.96 | Y42: 31339.35 | Z42: 31339.35 | AA42: 32128.31 | AB42: 31682.07
A43: 1 | C43: 자본금 | E43: 62161.14 | F43: 62161.14 | G43: 62161.14 | H43: 62161.14 | I43: 62161.14 | J43: 62161.14 | K43: 62161.14 | L43: 62161.14 | M43: 62161.14 | N43: 62161.14 | O43: 62161.14 | P43: 62161.14 | Q43: 62161.14 | R43: 62161.14 | S43: 62161.14 | T43: 62161.14 | U43: 62161.14 | V43: 62161.14 | W43: 71804.96 | X43: 73412.66 | Y43: 73412.66 | Z43: 73412.66 | AA43: 73412.66 | AB43: 73412.66
A44: 1 | C44: 보통주자본금 | E44: 16376.1 | F44: 16376.1 | G44: 16376.1 | H44: 16376.1 | I44: 16376.1 | J44: 16376.1 | K44: 16376.1 | L44: 16376.1 | M44: 16376.1 | N44: 16376.1 | O44: 16376.1 | P44: 16376.1 | Q44: 16376.1 | R44: 16376.1 | S44: 16376.1 | T44: 16376.1 | U44: 16376.1 | V44: 16376.1 | W44: 18017.13 | X44: 18427.38 | Y44: 18427.38 | Z44: 18427.38 | AA44: 18427.38 | AB44: 18427.38
A45: 1 | C45: 자본잉여금 | E45: 45785.04 | F45: 45785.04 | G45: 45785.04 | H45: 45785.04 | I45: 45785.04 | J45: 45785.04 | K45: 45785.04 | L45: 45785.04 | M45: 45785.04 | N45: 45785.04 | O45: 45785.04 | P45: 45785.04 | Q45: 45785.04 | R45: 45785.04 | S45: 45785.04 | T45: 45785.04 | U45: 45785.04 | V45: 45785.04 | W45: 53787.83 | X45: 54985.27 | Y45: 54985.27 | Z45: 54985.27 | AA45: 54985.27 | AB45: 54985.27
A46: 1 | C46: 이익잉여금 | E46: -39726.59 | F46: -39726.59 | G46: -41692.51 | H46: -42120.45 | I46: -43807.91 | J46: -45013.72 | K46: -45013.72 | L46: -43720.17 | M46: -42428.06 | N46: -42578.49 | O46: -43175.28 | P46: -43175.28 | Q46: -42788.67 | R46: -41786.77 | S46: -42914.49 | T46: -46469.31 | U46: -46469.31 | V46: -47745.01 | W46: -52976.75 | X46: -52676.73 | Y46: -52969.67 | Z46: -52969.67 | AA46: -52161.79 | AB46: -52594.9
A47: 1 | C47: 기타포괄이익누계액 | E47: 934.99 | F47: 934.99
A48: 1 | C48: 기타자본 | E48: 10113.3 | F48: 10113.3 | G48: 11160.07 | H48: 9773 | I48: 9766.34 | J48: 9216.97 | K48: 9216.97 | L48: 9212.44 | M48: 9219.81 | N48: 9148.78 | O48: 11139.8 | P48: 11139.8 | Q48: 11142.14 | R48: 11171.17 | S48: 11146.42 | T48: 11146.92 | U48: 11146.92 | V48: 11147.05 | W48: 11172.3 | X48: 11197.03 | Y48: 10896.37 | Z48: 10896.37 | AA48: 10877.45 | AB48: 10864.32
A49: 1 | C49: 비지배주주지분 | E49: 3368.58 | F49: 3368.58 | G49: 3073.23 | H49: 2704.15 | I49: 2555.48 | J49: 2576.77 | K49: 2576.77 | L49: 2743.29 | M49: 2800.57 | N49: 3819.64 | O49: 5636.66 | P49: 5636.66 | Q49: 5702.58 | R49: 6086.11 | S49: 5723.68 | T49: 5997.49 | U49: 5997.49 | V49: 5487.08 | W49: 4844.9 | X49: 5185.77 | Y49: 4663.34 | Z49: 4663.34 | AA49: 4895.82 | AB49: 3861.26
A50: 1 | C50: 자본총계 | E50: 36851.42 | F50: 36851.42 | G50: 34701.92 | H50: 32517.84 | I50: 30675.05 | J50: 28941.16 | K50: 28941.16 | L50: 30396.69 | M50: 31753.46 | N50: 32551.07 | O50: 35762.32 | P50: 35762.32 | Q50: 36217.18 | R50: 37631.65 | S50: 36116.75 | T50: 32836.24 | U50: 32836.24 | V50: 31050.26 | W50: 34845.4 | X50: 37118.73 | Y50: 36002.69 | Z50: 36002.69 | AA50: 37024.13 | AB50: 35543.33
A51: 1 | C51: 부채와자본총계 | E51: 119558.61 | F51: 119558.61 | G51: 120024.38 | H51: 118211.38 | I51: 119621.41 | J51: 124178.35 | K51: 124178.35 | L51: 124386.58 | M51: 125825.1 | N51: 126981.6 | O51: 128821.58 | P51: 128821.58 | Q51: 134327.84 | R51: 135509.58 | S51: 132566.05 | T51: 135428.55 | U51: 135428.55 | V51: 135989.92 | W51: 137771.43 | X51: 141357.11 | Y51: 141833.19 | Z51: 141833.19 | AA51: 147145.76 | AB51: 149427.4
A52: 1 | C52: 총차입금 | E52: 60711.81 | F52: 60711.81 | G52: 61150.24 | H52: 60322.05 | I52: 61087.44 | J52: 59008.24 | K52: 59008.24 | L52: 58333.1 | M52: 99422.79 | N52: 56876.06 | O52: 59788.41 | P52: 59788.41 | Q52: 60555.96 | R52: 62955.82 | S52: 63232.95 | T52: 72456.01 | U52: 72456.01 | V52: 73081.47 | W52: 70948.64 | X52: 69638.31 | Y52: 70934.14 | Z52: 70934.14 | AA52: 73473.59 | AB52: 72912.4
A53: 1 | C53: 순차입금 | E53: 54210.3 | F53: 54210.3 | G53: 59302.88 | H53: 58785.21 | I53: 58490.59 | J53: 56002.86 | K53: 56002.86 | L53: 53881.72 | M53: 93816.24 | N53: 52201.43 | O53: 51479.19 | P53: 51479.19 | Q53: 46786.81 | R53: 50780.23 | S53: 51703.11 | T53: 56866.18 | U53: 56866.18 | V53: 60061.71 | W53: 58457.04 | X53: 53439.48 | Y53: 58613.36 | Z53: 58613.36 | AA53: 59513.76 | AB53: 56582.39
A54: 1 | C54: 이자발생자산 | E54: 9347.33 | F54: 9347.33 | G54: 4835.97 | H54: 2778.38 | I54: 4135.97 | J54: 3125.69 | K54: 3125.69 | L54: 4567.16 | M54: 5729.69 | N54: 4699.16 | O54: 8389.26 | P54: 8389.26 | Q54: 13849.19 | R54: 12199.63 | S54: 11593.63 | T54: 15967.29 | U54: 15967.29 | V54: 13427.22 | W54: 12779.24 | X54: 16496.47 | Y54: 12524.82 | Z54: 12524.82 | AA54: 14163.87 | AB54: 16536.05
A55: 1 | C55: 단기투자자산(공정가치) | G55: 0 | H55: 0
A56: 1 | C56: 종속기업및관계기업투자 | G56: 0 | H56: 0
A57: 1 | C57: 유동성장기부채 | M57: 50362.44 | O57: 0 | P57: 0 | T57: 13294.17 | U57: 13294.17 | V57: 13576.36 | W57: 10663.32 | X57: 10072.26 | Y57: 10213.15 | Z57: 10213.15 | AA57: 7955.36 | AB57: 8398.42
A58: 1 | C58: 유동파생상품자산 | O58: 247.04 | P58: 247.04 | Q58: 913.29 | R58: 1199.48 | S58: 1199.48 | T58: 60.73 | U58: 60.73 | V58: 60.73 | W58: 728.72 | X58: 2.57 | Y58: 156.48 | Z58: 156.48 | AA58: 0 | AB58: 0
A59: 1 | C59: 단기파생상품부채 | O59: 4025.56 | P59: 4025.56 | Q59: 11287.16 | R59: 8734.86 | S59: 8734.86 | T59: 4891.67 | U59: 4891.67 | V59: 4891.67 | W59: 3532.55 | X59: 2083.94 | Y59: 2738.27 | Z59: 2738.27 | AA59: 2132.93 | AB59: 2343.96
A60: 1 | C60: 사채 | O60: 3432.63 | P60: 3432.63 | Q60: 7864.33 | R60: 8513.1 | S60: 8838.37 | T60: 0 | U60: 0 | V60: 0 | Y60: 0 | Z60: 0 | AA60: 0 | AB60: 0
A61: 1 | C61: 매출액(수익) | E61: 14534.94 | G61: 12500.03 | H61: 11730.6 | I61: 12798.42 | J61: 15727.04 | K61: 52756.09 | L61: 19766.41 | M61: 17099.02 | N61: 17302.73 | O61: 17546.94 | P61: 71715.1 | Q61: 16739.95 | R61: 14064.24 | S61: 12924.18 | T61: 17670.18 | U61: 61398.55 | V61: 10329.01 | W61: 14619.54 | X61: 17155.59 | Y61: 17773.11 | Z61: 59877.25 | AA61: 21247.63 | AB61: 18885.89
A62: 1 | C62: 매출원가 | E62: 17624.61 | G62: 12307.05 | H62: 11747.91 | I62: 12346.46 | J62: 14109.24 | K62: 50510.66 | L62: 15726.9 | M62: 12811.42 | N62: 14536.99 | O62: 14740 | P62: 57815.31 | Q62: 13914.53 | R62: 11754.49 | S62: 11711.29 | T62: 14912.22 | U62: 52292.53 | V62: 9301.85 | W62: 12404.24 | X62: 13302.11 | Y62: 15165.92 | Z62: 50174.12 | AA62: 17167.26 | AB62: 17669.18
A63: 1 | C63: 매출총이익 | E63: -3089.67 | G63: 192.98 | H63: -17.31 | I63: 451.97 | J63: 1617.8 | K63: 2245.44 | L63: 4039.51 | M63: 4287.6 | N63: 2765.74 | O63: 2806.94 | P63: 13899.79 | Q63: 2825.42 | R63: 2309.75 | S63: 1212.89 | T63: 2757.96 | U63: 9106.02 | V63: 1027.16 | W63: 2215.3 | X63: 3853.48 | Y63: 2607.19 | Z63: 9703.13 | AA63: 4080.37 | AB63: 1216.71
A64: 1 | C64: 판관비 | E64: 2297.32 | G64: 1826.59 | H64: 1586.19 | I64: 1755.76 | J64: 1818.32 | K64: 6986.86 | L64: 1855.03 | M64: 2020.1 | N64: 2024.52 | O64: 2403.65 | P64: 8303.3 | Q64: 1867.24 | R64: 2463.15 | S64: 1795.51 | T64: 2543.36 | U64: 8669.26 | V64: 2194.59 | W64: 2535.3 | X64: 2681.08 | Y64: 2435.91 | Z64: 9846.88 | AA64: 2598.33 | AB64: 1352.6
A65: 1 | C65: 영업이익 | E65: -5386.99 | G65: -1633.61 | H65: -1603.5 | I65: -1303.79 | J65: -200.52 | K65: -4741.42 | L65: 2184.48 | M65: 2267.5 | N65: 741.22 | O65: 403.29 | P65: 5596.49 | Q65: 958.18 | R65: -153.39 | S65: -582.62 | T65: 214.6 | U65: 436.77 | V65: -1167.43 | W65: -320 | X65: 1172.4 | Y65: 171.28 | Z65: -143.75 | AA65: 1482.04 | AB65: -135.88
A66: 1 | C66: 기타영업외수익 | E66: 257.34 | G66: 60.59 | H66: 422.84 | I66: 235.49 | J66: -22.82 | K66: 696.1 | L66: 294.87 | M66: 69.32 | N66: 62.94 | O66: 367.07 | P66: 794.2 | Q66: 579.73 | R66: 101.24 | S66: 53.61 | T66: -96.48 | U66: 638.1 | V66: 93.08 | W66: 65.78 | X66: 319.32 | Y66: 301.15 | Z66: 779.33 | AA66: 242.22 | AB66: 146
A67: 1 | C67: 기타영업외비용 | E67: 4487.68 | G67: 52.76 | H67: 93.41 | I67: 67.66 | J67: 438.95 | K67: 652.78 | L67: 164.36 | M67: 155.99 | N67: 49.41 | O67: 752.87 | P67: 1122.63 | Q67: 223.52 | R67: 51.34 | S67: -41.68 | T67: 655.47 | U67: 888.65 | V67: 53.44 | W67: 232.25 | X67: 59.04 | Y67: 70.1 | Z67: 414.83 | AA67: 104.75 | AB67: 103.96
A68: 1 | C68: 금융수익 | E68: 28.13 | G68: 45.74 | H68: 35.16 | I68: 46.22 | J68: 296.48 | K68: 423.6 | L68: 24.42 | M68: 37.73 | N68: 76.97 | O68: 1179 | P68: 1318.12 | Q68: 15.33 | R68: 3026.96 | S68: 99.93 | T68: -817.82 | U68: 2324.4 | V68: 171.8 | W68: 1716.55 | X68: 516.65 | Y68: -476.91 | Z68: 1928.09 | AA68: 70.25 | AB68: 388.24
A69: 1 | C69: 금융비용 | E69: 745.47 | G69: 679.83 | H69: 717.98 | I69: 744.96 | J69: 892.75 | K69: 3035.52 | L69: 876.98 | M69: 866.79 | N69: 880.53 | O69: 1160.98 | P69: 3785.28 | Q69: 875.22 | R69: 1536.06 | S69: 1100.78 | T69: 1709.02 | U69: 5221.08 | V69: 830.12 | W69: 7104 | X69: 1308.44 | Y69: 682.37 | Z69: 9924.93 | AA69: 649.42 | AB69: 1437.12
A70: 1 | C70: 법인세비용차감전계속사업이익 | E70: -10634.67 | G70: -2259.86 | H70: -1956.9 | I70: -1834.71 | J70: -1775.63 | K70: -7827.1 | L70: 1462.43 | M70: 1351.76 | N70: -48.81 | O70: 35.51 | P70: 2800.89 | Q70: 454.5 | R70: 1387.4 | S70: -1488.18 | T70: -3064.22 | U70: -2710.5 | V70: -1786.1 | W70: -5873.93 | X70: 640.89 | Y70: -756.93 | Z70: -7776.07 | AA70: 1040.35 | AB70: -1142.73
A71: 1 | C71: 당기순이익 | E71: -10634.67 | G71: -2259.86 | H71: -1956.9 | I71: -1834.71 | J71: -1775.63 | K71: -7827.1 | L71: 1462.43 | M71: 1351.76 | N71: -48.81 | O71: 35.51 | P71: 2800.89 | Q71: 454.5 | R71: 1387.4 | S71: -1488.18 | T71: -3064.22 | U71: -2710.5 | V71: -1786.1 | W71: -5873.93 | X71: 640.89 | Y71: -756.93 | Z71: -7776.07 | AA71: 1040.35 | AB71: -1142.73
A72: 1 | C72: (지배주주지분)당기순이익 | E72: -9322.51 | G72: -1965.07 | H72: -1588.38 | I72: -1686.6 | J72: -1747.09 | K72: -6987.14 | L72: 1294.98 | M72: 1293.55 | N72: -149 | O72: -102.87 | P72: 2336.66 | Q72: 387.67 | R72: 1002.96 | V72: -1275.7 | W72: -5231.74 | X72: 300.02 | Y72: -336.35 | Z72: -6543.77 | AA72: 807.87 | AB72: -258.23
A73: 1 | C73: (비지배주주지분)당기순이익 | E73: -1312.15 | G73: -294.8 | H73: -368.52 | I73: -148.11 | J73: -28.54 | K73: -839.97 | L73: 167.44 | M73: 58.21 | N73: 100.2 | O73: 138.39 | P73: 464.24 | Q73: 66.83 | R73: 384.44 | S73: -361.52 | T73: 286.5 | U73: 376.25 | V73: -510.41 | W73: -642.18 | X73: 340.87 | Y73: -420.59 | Z73: -1232.31 | AA73: 232.48 | AB73: -884.5
A74: 1 | C74: 총포괄손익 | E74: -6023.73 | G74: -2149.5 | H74: -2184.09 | I74: -1836.13 | J74: -1740.55 | K74: -7910.27 | L74: 1455.53 | M74: 1356.76 | N74: -52.39 | O74: 3211.25 | P74: 5971.15 | Q74: 454.86 | R74: 1414.46 | S74: -1514.9 | T74: -3280.52 | U74: -2926.1 | V74: -1785.98 | W74: -5848.68 | X74: 665.63 | Y74: -1105.24 | Z74: -8074.27 | AA74: 1021.44 | AB74: -1480.8
A75: 1 | C75: 금융손익 | E75: -717.34 | G75: -634.09 | H75: -682.82 | I75: -698.74 | J75: -596.27 | K75: -2611.92 | L75: -852.56 | M75: -829.06 | N75: -803.56 | O75: 18.02 | P75: -2467.16 | Q75: -859.89 | R75: 1490.9 | S75: -1000.85 | T75: -2526.84 | U75: -2896.68 | V75: -658.32 | W75: -5387.45 | X75: -791.79 | Y75: -1159.28 | Z75: -7996.84 | AA75: -579.17 | AB75: -1048.88
A76: 1 | C76: 기타영업외손익 | E76: -4230.34 | G76: 7.83 | H76: 329.43 | I76: 167.83 | J76: -461.77 | K76: 43.32 | L76: 130.51 | M76: -86.67 | N76: 13.53 | O76: -385.8 | P76: -328.43 | Q76: 356.21 | R76: 49.9 | S76: 95.29 | T76: -751.95 | U76: -250.55 | V76: 39.64 | W76: -166.47 | X76: 260.28 | Y76: 231.05 | Z76: 364.5 | AA76: 137.47 | AB76: 42.04
A77: 1 | C77: 계속사업이익 | E77: -10634.67 | G77: -2259.86 | H77: -1956.9 | I77: -1834.71 | J77: -1775.63 | K77: -7827.1 | L77: 1462.43 | M77: 1351.76 | N77: -48.81 | O77: 35.51 | P77: 2800.89 | Q77: 454.5 | R77: 1387.4 | S77: -1488.18 | T77: -3064.22 | U77: -2710.5 | V77: -1786.1 | W77: -5873.93 | X77: 640.89 | Y77: -756.93 | Z77: -7776.07 | AA77: 1040.35 | AB77: -1142.73
A78: 1 | C78: 법인세비용 | G78: 0 | I78: 0 | J78: 0 | L78: 0 | M78: 0 | N78: 0 | O78: 0 | P78: 0 | Q78: 0 | R78: 0 | S78: 0 | T78: 0 | U78: 0 | V78: 0 | W78: 0 | X78: 0 | Y78: 0 | Z78: 0 | AA78: 0 | AB78: 0
A79: 1 | C79: 이자수익 | G79: 29.22 | H79: 30.45 | I79: 29.37 | J79: 58.16 | K79: 147.2 | L79: 21.79 | M79: 30.87 | N79: 48.41 | O79: 54.11 | P79: 155.18 | Q79: 8.25 | R79: 7.1 | S79: 22.93 | T79: 66.69 | U79: 104.97 | V79: 7.39 | W79: 44.25 | X79: 108.29 | Y79: -2.64 | Z79: 157.29 | AA79: 33.98 | AB79: 57.55
A80: 1 | C80: 배당금수익 | G80: 14.74 | H80: 0 | I80: 0 | J80: 0 | K80: 14.74 | M80: 6.7 | N80: 35.14 | O80: 0 | R80: 113.34 | S80: 81.2 | T80: 0 | V80: 161 | W80: 15.2 | X80: 0 | Y80: 120.4 | Z80: 296.6 | AB80: 182.2
A81: 1 | C81: 이자비용 | G81: 677.95 | H81: 716.74 | I81: 744.54 | J81: 856.08 | K81: 2995.31 | L81: 875.61 | M81: 858.4 | N81: 878.94 | O81: 1020.25 | P81: 3633.2 | Q81: 871.54 | R81: 1476.73 | S81: 1091.19 | T81: 1398.26 | U81: 4837.72 | V81: 830.12 | W81: 1522.14 | X81: 324.01 | Y81: 806.59 | Z81: 3482.86 | AA81: 644.47 | AB81: 1224.09
A82: 1 | C82: 외환차익 | G82: 1.78 | H82: 2.94 | I82: 11.36 | J82: -9.57 | K82: 6.51 | L82: 1.04 | M82: 0.34 | N82: -4.98 | O82: 2.62 | P82: -0.98 | Q82: 0.49 | R82: 0.22 | S82: 0 | T82: 0.23 | U82: 0.94 | W82: 67.86 | X82: 0.98 | Y82: 48.28 | AA82: 32.79 | AB82: 3.43
A83: 1 | C83: 외화환산손실 | G83: 1.87 | H83: -1.18 | I83: -0.7 | M83: 0.84 | N83: 0.19 | O83: 2.33 | Q83: 3.67 | R83: 0.9 | S83: 9.59 | T83: -7.95 | U83: 6.21 | AA83: -4.95 | AB83: 4.95
A84: 1 | C84: 이자손익 | G84: -648.73 | H84: -686.29 | I84: -715.17 | J84: -797.92 | K84: -2848.11 | L84: -853.82 | M84: -827.53 | N84: -830.53 | O84: -966.14 | P84: -3478.02 | Q84: -863.29 | R84: -1469.63 | S84: -1068.26 | T84: -1331.57 | U84: -4732.75 | V84: -822.73 | W84: -1477.89 | X84: -215.72 | Y84: -809.23 | Z84: -3325.57 | AA84: -610.49 | AB84: -1166.54
A85: 1 | C85: 외환차손 | H85: 2.42 | I85: 1.12 | J85: 32.92 | L85: 1.37 | M85: 7.55 | N85: 1.4 | O85: 0.53 | P85: 10.85 | R85: 1.26 | S85: 0 | T85: 0 | W85: 20.27 | X85: 1.61 | Y85: 5.73 | AA85: 2.77 | AB85: 1.69
A86: 1 | C86: 외화환산이익 | H86: 0.64 | I86: 5.5 | L86: 1.59 | M86: -1.38 | N86: -1.38 | Q86: 6.59 | R86: 9.45 | S86: -4.19 | T86: 47.34 | U86: 59.19 | AB86: 104.28
A87: 1 | C87: 파생상품이익 | R87: 2895.66 | S87: 2895.66 | T87: -942.02 | W87: 1585.89 | X87: 1853.27 | Y87: -646.64
A88: 1 | C88: 파생상품손실 | R88: 57.17 | S88: 57.17 | T88: 318.04 | W88: 5561.59 | X88: 1840.41 | Y88: -146.22 | AB88: 211.04
A89: 1 | C89: 영업활동으로인한현금흐름 | E89: 1204.04 | G89: -3916.87 | H89: -1857.46 | I89: 712.87 | J89: 2108.14 | K89: -2953.32 | L89: 1738.04 | M89: 2891.62 | N89: 631.15 | O89: -5824.89 | P89: -564.08 | Q89: -3168.15 | R89: -3013.06 | S89: -897.44 | T89: 769.01 | U89: -6309.64 | V89: -2764.95 | W89: -2011.11 | X89: 5045.41 | Y89: -4762.46 | Z89: -4493.11 | AA89: -86.1 | AB89: 3483.46
A90: 1 | C90: 감가상각비 | E90: 452.45 | G90: 269.04 | H90: 299.44 | I90: 237.14 | J90: 273.15 | K90: 1078.77 | L90: 234.26 | M90: 278.7
A91: 1 | C91: 무형자산상각비 | E91: 24.79 | G91: 3.36 | H91: 3.37 | I91: 3.36 | J91: 0.27 | K91: 10.36 | L91: 0.27 | M91: 1.7
A92: 1 | C92: 배당금수취(CF) | E92: 0 | G92: 14.74 | H92: 0 | I92: 0 | J92: 0 | K92: 14.74 | L92: 0 | M92: 6.7 | N92: 50.4 | O92: 0 | P92: 57.1 | Q92: 0 | R92: 113.34 | S92: 81.2 | T92: 0 | U92: 194.54 | V92: 161 | W92: 15.2 | X92: 0 | Y92: 120.4 | Z92: 296.6 | AA92: 0 | AB92: 182.2
A93: 1 | C93: 법인세납부(CF) | E93: -0.83 | G93: -0.52 | H93: 5.63 | I93: 61.72 | J93: -1.82 | K93: 65.01 | L93: -0.97 | M93: 1.87 | N93: -1.07 | O93: -7.32 | P93: -7.49 | Q93: -0.35 | R93: 7.19 | S93: -0.73 | T93: -10.68 | U93: -4.57 | V93: -1.85 | W93: 12.19 | X93: -59.16 | Y93: -0.65 | Z93: -49.47 | AA93: -0.88 | AB93: 59.58
A94: 1 | C94: 투자활동으로인한현금흐름 | E94: 1469.41 | G94: -1151.52 | H94: 2441.13 | I94: -349.97 | J94: -146.34 | K94: 793.3 | L94: 390.06 | M94: -1714.7 | N94: -1408.6 | O94: 1727.97 | P94: -1005.27 | Q94: 425.48 | R94: -492.97 | S94: 540.19 | T94: -722.91 | U94: -250.21 | V94: 971.06 | W94: 398.57 | X94: 62.12 | Y94: -2480.92 | Z94: -1049.17 | AA94: -229.4 | AB94: -204.39
A95: 1 | C95: 유형자산의감소 | E95: 0 | G95: 0 | H95: 0 | I95: 5 | J95: 158.07 | K95: 163.07 | L95: 4.5 | M95: 0 | N95: 0 | O95: 1 | P95: 5.5 | Q95: 9.27 | R95: 3.82 | S95: 0.64 | T95: 9 | U95: 22.73 | V95: 0 | W95: 0 | X95: 0 | Y95: 1 | Z95: 1 | AA95: 25.91 | AB95: 11.16
A96: 1 | C96: 유형자산의증가 | E96: 31.93 | G96: 0 | H96: 0 | I96: 115.01 | L96: 140.98 | M96: 56.42 | N96: 326.86 | Q96: 96.36 | R96: 68.15 | S96: 76.8 | T96: 153.62 | U96: 394.93 | V96: 113.19 | W96: 42.76 | X96: 84.99 | Y96: 497.93 | Z96: 738.87 | AA96: 146.42 | AB96: 38.01
A97: 1 | C97: CAPEX | E97: 31.93 | G97: 0 | H97: 0 | I97: 115.01 | J97: 71.09 | K97: 186.1 | L97: 140.98 | M97: 84.98 | N97: 333.86 | O97: 0 | P97: 559.82 | Q97: 103.39 | R97: 68.15 | S97: 76.8 | T97: 153.62 | U97: 401.96 | V97: 113.19 | W97: 47.62 | X97: 86.89 | Y97: 497.93 | Z97: 745.63 | AA97: 154.31 | AB97: 181.55
A98: 1 | C98: 무형자산의증가 | E98: 0 | G98: 0 | H98: 0 | I98: 0 | J98: 186.1 | K98: 186.1 | L98: 0 | M98: 28.56 | N98: 7 | O98: 0 | P98: 35.56 | Q98: 7.03 | R98: 0 | S98: 0 | T98: 0 | U98: 7.03 | V98: 0 | W98: 4.86 | X98: 1.9 | Y98: 0 | Z98: 6.76 | AA98: 7.89 | AB98: 143.54
A99: 1 | C99: 재무활동으로인한현금흐름 | E99: 987.34 | G99: 368.12 | H99: -896.01 | I99: 766.37 | J99: -2098.48 | K99: -1860 | L99: -675.13 | M99: -1078.06 | N99: 462.88 | O99: 7612.41 | P99: 6322.1 | Q99: 7368.43 | R99: 1774.11 | S99: -274.73 | T99: 4796.25 | U99: 13664.06 | V99: 371.83 | W99: 740.96 | X99: -675.15 | Y99: 1140.75 | Z99: 1578.39 | AA99: 2103.08 | AB99: -1011.22
A100: 1 | C100: 차입금의증가 | E100: 13319.53 | G100: 3076.73 | H100: 5262.22 | I100: 4795.35 | J100: 9761.99 | K100: 22896.29 | L100: 4857.9 | M100: 9017.89 | N100: 5959.07 | O100: 15328.77 | P100: 35163.63 | Q100: 3384.66 | R100: 4175.78 | S100: 3287.3 | T100: 5697.99 | U100: 16545.73 | V100: 12615.32 | W100: 6953.04 | X100: 5826.85 | Y100: 22486.54 | Z100: 47881.75 | AA100: 9610.82 | AB100: 10978.74
A101: 1 | C101: 차입금의감소 | E101: 12302.26 | G101: 2708.62 | H101: 6114.67 | I101: 4029.94 | J101: 11841.2 | K101: 24694.43 | L101: 5533.03 | M101: 10108.95 | N101: 5475.05 | O101: 15849.05 | P101: 36966.08 | Q101: 7048.8 | R101: 2424.7 | S101: 3335.44 | T101: 930.73 | U101: 13739.67 | V101: 12272.05 | W101: 6172.82 | X101: 6546.13 | Y101: 21331.6 | Z101: 46322.6 | AA101: 4813.58 | AB101: 11982.99
A102: 1 | C102: 리스부채의상환 | E102: 29.94 | G102: 0 | H102: 43.56 | I102: -0.98 | J102: 19.28 | K102: 61.86 | L102: 0 | M102: 23.74 | O102: 47.87 | T102: 37.77 | X102: 0 | Y102: 38.28 | AA102: 8.85 | AB102: 36.6
A103: 1 | C103: 현금및현금성자산의증감 | E103: 3660.82 | G103: -4702.15 | H103: -310.51 | I103: 1135.46 | J103: -146.57 | K103: -4023.77 | L103: 1454.56 | M103: 96.65 | N103: -314.98 | O103: 3513.16 | P103: 4749.39 | Q103: 4628.68 | R103: -1723.39 | S103: -645.75 | T103: 4897.64 | U103: 7157.18 | V103: -1422.06 | W103: -871.57 | X103: 4432.37 | Y103: -6118.55 | Z103: -3979.81 | AA103: 1792.53 | AB103: 2367.18
A104: 1 | C104: 기말현금및현금성자산 | E104: 3660.82 | G104: 726.75 | H104: -310.52 | I104: 1135.47 | J104: -146.57 | K104: 1405.13 | L104: 2859.69 | M104: 96.65 | N104: -314.98 | O104: 3513.16 | P104: 6154.52 | Q104: 10783.2 | R104: -1723.39 | S104: -645.75 | T104: 4897.64 | U104: 13311.7 | V104: 11889.63 | W104: -871.57 | X104: 4432.38 | Y104: -6118.56 | Z104: 9331.88 | AA104: 11124.41 | AB104: 2367.18
A105: 1 | C105: 무형자산의감소 | I105: 0 | N105: 0
A106: 1 | C106: 이자수취(CF) | O106: 26.06 | Q106: -82.92 | R106: 115.91 | S106: 17.54 | T106: 72.89 | U106: 123.42 | V106: 12.94 | W106: 37.21 | X106: 228.3 | Y106: -2.68 | Z106: 275.77 | AA106: 6.19 | AB106: 30.85

Sheet BS별도
B1: (백만원) | C1: 이름: BS별도H | E1: 4Q21 | F1: 2021 | G1: 1Q22 | H1: 2Q22 | I1: 3Q22 | J1: 4Q22 | K1: 2022 | L1: 1Q23 | M1: 2Q23 | N1: 3Q23 | O1: 4Q23 | P1: 2023 | Q1: 1Q24 | R1: 2Q24 | S1: 3Q24 | T1: 4Q24 | U1: 2024 | V1: 1Q25 | W1: 2Q25 | X1: 3Q25 | Y1: 4Q25 | Z1: 2025 | AA1: 1Q26 | AB1: 2Q26 | AC1: 3Q26 | AD1: 4Q26 | AE1: 2026 | AF1: 1Q27 | AG1: 2Q27 | AH1: 3Q27 | AI1: 4Q27 | AJ1: 2027 | AK1: 1Q28 | AL1: 2Q28 | AM1: 3Q28 | AN1: 4Q28 | AO1: 2028
B2: 별도 | D2: fin json(kship_fin.py)
B3: 대창솔루션(별) | C3: UPDATE: 26-10-19 | E3: 1 | F3: 2 | G3: 3 | H3: 4 | I3: 5 | J3: 6 | K3: 7 | L3: 8 | M3: 9 | N3: 10 | O3: 11 | P3: 12 | Q3: 13 | R3: 14 | S3: 15 | T3: 16 | U3: 17 | V3: 18 | W3: 19 | X3: 20 | Y3: 21 | Z3: 22 | AA3: 23 | AB3: 24 | AC3: 25 | AD3: 26 | AE3: 27 | AF3: 28 | AG3: 29 | AH3: 30 | AI3: 31 | AJ3: 32 | AK3: 33 | AL3: 34 | AM3: 35 | AN3: 36 | AO3: 37
B4: Account Code | C4: AccountNAME | E4: 2021.12 | F4: 2021.12A | G4: 2022.03 | H4: 2022.06 | I4: 2022.09 | J4: 2022.12 | K4: 2022.12A | L4: 2023.03 | M4: 2023.06 | N4: 2023.09 | O4: 2023.12 | P4: 2023.12A | Q4: 2024.03 | R4: 2024.06 | S4: 2024.09 | T4: 2024.12 | U4: 2024.12A | V4: 2025.03 | W4: 2025.06 | X4: 2025.09 | Y4: 2025.12 | Z4: 2025.12A | AA4: 2026.03 | AB4: 2026.06 | AC4: 2026.09 | AD4: 2026.12 | AE4: 2026.12A | AF4: 2027.03 | AG4: 2027.06 | AH4: 2027.09 | AI4: 2027.12 | AJ4: 2027.12A | AK4: 2028.03 | AL4: 2028.06 | AM4: 2028.09 | AN4: 2028.12 | AO4: 2028.12A
A5: 1 | C5: 유동자산 | E5: 18677.58 | F5: 18677.58 | G5: 18202.69 | H5: 18248.66 | I5: 18928.89 | J5: 19963.15 | K5: 19963.15 | L5: 20970.85 | M5: 20032.28 | N5: 21634.07 | O5: 24290.13 | P5: 24290.13 | Q5: 19836.79 | R5: 21608.09 | S5: 20945.45 | T5: 21373.36 | U5: 21373.36 | V5: 24151.67 | W5: 26697.05 | X5: 27654.31 | Y5: 29473.65 | Z5: 29473.65 | AA5: 32899.96 | AB5: 37546.4
A6: 1 | C6: 현금및현금성자산 | E6: 113.94 | F6: 113.94 | G6: 329.76 | H6: 261.9 | I6: 665.05 | J6: 1176.05 | K6: 1176.05 | L6: 123.5 | M6: 95.03 | N6: 955.15 | O6: 3398.27 | P6: 3398.27 | Q6: 226.09 | R6: 2446.43 | S6: 1485.81 | T6: 2970.44 | U6: 2970.44 | V6: 1748.68 | W6: 1859.65 | X6: 2788.58 | Y6: 45.69 | Z6: 45.69 | AA6: 1053.7 | AB6: 6655.07
A7: 1 | C7: 단기금융상품 | E7: 963.85 | F7: 963.85 | G7: 1011.85 | H7: 1011.85 | I7: 1011.85 | J7: 1081.85 | K7: 1081.85 | L7: 720.85 | M7: 726.36 | N7: 726.36 | O7: 726.36 | P7: 726.36 | Q7: 726.36 | R7: 570 | S7: 570 | T7: 570 | U7: 570 | V7: 570 | W7: 570 | X7: 571 | Y7: 574 | Z7: 574 | AA7: 577 | AB7: 580
A8: 1 | C8: 단기금융자산 | E8: 963.85 | F8: 963.85 | G8: 1011.85 | H8: 1011.85 | I8: 1011.85 | J8: 1081.85 | K8: 1081.85 | L8: 720.85 | M8: 726.36 | N8: 726.36 | O8: 973.4 | P8: 973.4 | Q8: 973.4 | R8: 1160.39 | S8: 1160.39 | T8: 627.44 | U8: 627.44 | V8: 627.44 | W8: 1296.15 | X8: 571 | Y8: 2408.84 | Z8: 2408.84 | AA8: 577 | AB8: 580
A9: 1 | C9: 매출채권및기타채권 | E9: 8074.28 | F9: 8074.28 | G9: 7342.91 | H9: 7950.46 | I9: 6722.98 | J9: 7205.56 | K9: 7205.56 | L9: 8671.49 | M9: 7259.96 | N9: 5561.68 | O9: 8503.21 | P9: 8503.21 | Q9: 8167.23 | R9: 6741.54 | S9: 7510.49 | T9: 7281.81 | U9: 7281.81 | V9: 6771.1 | W9: 7711.25 | X9: 7050.66 | Y9: 10590.19 | Z9: 10590.19 | AA9: 12739.95 | AB9: 11708.56
A10: 1 | C10: 단기투자자산(공정가치) | E10: 540 | F10: 540 | G10: 540 | H10: 0 | I10: 0 | J10: 0 | K10: 0 | L10: 0 | O10: 0 | P10: 0 | Q10: 0 | T10: 0 | U10: 0 | V10: 0
A11: 1 | C11: 당기법인세자산(선급법인세) | E11: 67.91 | F11: 67.91 | G11: 68.39 | H11: 62.5 | I11: 0.76 | J11: 2.43 | K11: 2.43 | L11: 2.43 | M11: 1 | N11: 1 | O11: 3.91 | P11: 3.91 | Q11: 3.91 | R11: 1.97 | S11: 1.97 | T11: 4.33 | U11: 4.33 | V11: 4.33 | W11: 1.34 | X11: 59.89 | Y11: 0 | Z11: 0 | AA11: 60.35 | AB11: 5.03
A12: 1 | C12: 재고자산 | E12: 8406.53 | F12: 8406.53 | G12: 7889.06 | H12: 7993.33 | I12: 9336.39 | J12: 9808.07 | K12: 9808.07 | L12: 10142.22 | M12: 10637.54 | N12: 13134.02 | O12: 10826.21 | P12: 10826.21 | Q12: 10034.62 | R12: 10898.72 | S12: 10389.95 | T12: 9696.68 | U12: 9696.68 | V12: 14019.08 | W12: 15226.78 | X12: 16687.53 | Y12: 59.89 | Z12: 59.89 | AA12: 17164.38 | AB12: 17301.55
A13: 1 | C13: 기타유동자산 | E13: 511.07 | F13: 511.07 | G13: 1020.71 | H13: 968.61 | I13: 1191.85 | J13: 689.2 | K13: 689.2 | L13: 1310.36 | M13: 1312.37 | N13: 1255.85 | O13: 585.13 | P13: 585.13 | Q13: 431.53 | R13: 359.04 | S13: 396.82 | T13: 792.66 | U13: 792.66 | V13: 981.05 | W13: 601.88 | X13: 496.66 | Y13: 16369.04 | Z13: 16369.04 | AA13: 1304.58 | AB13: 1296.19
A14: 1 | C14: 비유동자산 | E14: 76723.96 | F14: 76723.96 | G14: 76693.25 | H14: 73701.87 | I14: 73730.03 | J14: 72627.62 | K14: 72627.62 | L14: 72425.27 | M14: 72239.42 | N14: 72334.97 | O14: 71397.79 | P14: 71397.79 | Q14: 71215.76 | R14: 71027.22 | S14: 70967.96 | T14: 70627.26 | U14: 70627.26 | V14: 70527.99 | W14: 70415.42 | X14: 70248.67 | Y14: 70292.53 | Z14: 70292.53 | AA14: 70171.67 | AB14: 70151.15
A15: 1 | C15: 장기금융자산 | E15: 2178.8 | F15: 2178.8 | G15: 2321.59 | H15: 574.52 | I15: 597.86 | J15: 108.57 | K15: 108.57 | L15: 104.04 | M15: 111.4 | N15: 136.8 | O15: 135.79 | P15: 135.79 | Q15: 135.79 | R15: 135.79 | S15: 135.79 | T15: 335.79 | U15: 335.79 | V15: 335.79 | W15: 335.79 | X15: 345.79 | Y15: 354.52 | Z15: 354.52 | AA15: 413.2 | AB15: 444.04
A16: 1 | C16: 투자자산 | E16: 4531.32 | F16: 4531.32 | G16: 4674.11 | H16: 2226.24 | I16: 2249.58 | J16: 1314.25 | K16: 1314.25 | L16: 1309.72 | M16: 1317.08 | N16: 1342.48 | O16: 1341.47 | P16: 1341.47 | Q16: 1341.47 | R16: 1341.47 | S16: 1341.47 | T16: 1541.47 | U16: 1541.47 | V16: 1541.47 | W16: 1541.47 | X16: 1551.47 | Y16: 1560.2 | Z16: 1560.2 | AA16: 1618.88 | AB16: 1649.72
A17: 1 | C17: 종속기업및관계기업투자 | E17: 2352.52 | F17: 2352.52 | G17: 2352.52 | H17: 1651.72 | I17: 1651.72 | J17: 1205.68 | K17: 1205.68 | L17: 1205.68 | M17: 1205.68 | N17: 1205.68 | O17: 1205.68 | P17: 1205.68 | Q17: 1205.68 | R17: 1205.68 | S17: 1205.68 | T17: 1205.68 | U17: 1205.68 | V17: 1205.68 | W17: 1205.68 | X17: 1205.68 | Y17: 1205.68 | Z17: 1205.68 | AA17: 1205.68 | AB17: 1205.68
A18: 1 | C18: 유형자산 | E18: 69666.69 | F18: 69666.69 | G18: 69494.68 | H18: 69320.75 | I18: 69224.57 | J18: 69045.79 | K18: 69045.79 | L18: 68899.6 | M18: 68720.06 | N18: 68768.76 | O18: 68571.86 | P18: 68571.86 | Q18: 68416.85 | R18: 68229.25 | S18: 68228.4 | T18: 67844.67 | U18: 67844.67 | V18: 67749.77 | W18: 67596.16 | X18: 67401.06 | Y18: 67493.95 | Z18: 67493.95 | AA18: 67324.39 | AB18: 67248.14
A19: 1 | C19: 사용권자산 | E19: 162.78 | F19: 162.78 | G19: 162.78 | H19: 72.88 | I19: 72.88 | J19: 485.82 | K19: 485.82 | L19: 485.82 | M19: 412.86 | N19: 412.86 | O19: 352.71 | P19: 352.71 | Q19: 352.71 | R19: 293.09 | S19: 293.09 | T19: 264.16 | U19: 264.16 | V19: 264.16 | W19: 204.92 | X19: 204.92 | Y19: 147.49 | Z19: 147.49 | AA19: 147.49 | AB19: 148.04
A20: 1 | C20: 기타비유동자산 | E20: 248.61 | F20: 248.61 | G20: 259.1 | H20: 230.89 | I20: 331.9 | J20: 709.39 | K20: 709.39 | L20: 685.34 | M20: 672.5 | N20: 691.56 | O20: 655.68 | P20: 655.68 | Q20: 626.32 | R20: 594.55 | S20: 560.89 | T20: 493.87 | U20: 493.87 | V20: 489.38 | W20: 503.21 | X20: 506.82 | Y20: 441.56 | Z20: 441.56 | AA20: 450.49 | AB20: 443.84
A21: 1 | C21: 무형자산 | E21: 927.59 | F21: 927.59 | G21: 927.59 | H21: 588.03 | I21: 588.03 | J21: 588.03 | K21: 588.03 | L21: 588.03 | M21: 588.03 | N21: 588.03 | O21: 588.03 | P21: 588.03 | Q21: 588.03 | R21: 588.03 | S21: 588.03 | T21: 496.05 | U21: 496.05 | V21: 496.05 | W21: 496.05 | X21: 496.05 | Y21: 496.05 | Z21: 496.05 | AA21: 496.05 | AB21: 496.05
A22: 1 | C22: 자산총계 | E22: 95401.54 | F22: 95401.54 | G22: 94895.94 | H22: 91950.52 | I22: 92658.92 | J22: 92590.76 | K22: 92590.76 | L22: 93396.12 | M22: 92271.69 | N22: 93969.04 | O22: 95687.93 | P22: 95687.93 | Q22: 91052.55 | R22: 92635.3 | S22: 91913.41 | T22: 92000.63 | U22: 92000.63 | V22: 94679.66 | W22: 97112.47 | X22: 97902.98 | Y22: 99766.18 | Z22: 99766.18 | AA22: 103071.63 | AB22: 107697.56
... A25: 1 | C25: 단기차입금 | E25: 37957.05 | F25: 37957.05 | G25: 39126.71 | H25: 37978.65 | I25: 36879.24 | J25: 40443 | K25: 40443 | L25: 37802.33 | M25: 29525.9 | N25: 33707.73 | O25: 33463.14 | P25: 33463.14 | Q25: 28465.55 | R25: 30472.86 | S25: 29790.74 | T25: 29137.02 | U25: 29137.02 | V25: 29807.75 | W25: 34098.31 | X25: 34003.48 | Y25: 21220.99 | Z25: 21220.99 | AA25: 20318.23 | AB25: 16793.98
A26: 1 | C26: 단기금융부채(face) | E26: 37957.05 | F26: 37957.05 | G26: 39126.71 | H26: 37978.65 | I26: 36879.24 | J26: 40443 | K26: 40443 | L26: 37802.33 | N26: 33707.73 | O26: 33463.14 | P26: 33463.14 | Q26: 28465.55 | R26: 30472.86 | S26: 29790.74 | T26: 29137.02 | U26: 29137.02 | V26: 29807.75 | W26: 34098.31 | X26: 34003.48 | Y26: 21220.99 | Z26: 21220.99 | AA26: 20318.23 | AB26: 16793.98
A27: 1 | C27: 단기충당부채 | E27: 109.59 | F27: 109.59 | G27: 110.9 | H27: 112.31 | I27: 110.86 | J27: 114.19 | K27: 114.19 | L27: 129.35 | M27: 140.55 | N27: 139.76 | O27: 113.78 | P27: 113.78 | Q27: 94.64 | R27: 95.11 | S27: 92.99 | T27: 100.57 | U27: 100.57 | V27: 2104.99 | W27: 140.35 | X27: 152.82 | Y27: 2871.87 | Z27: 2871.87 | AA27: 424.21 | AB27: 423.09
A28: 1 | C28: 기타유동금융부채 | E28: 1572.83 | F28: 1572.83 | G28: 2504.43 | H28: 1635.19 | I28: 1624.62 | J28: 2806.7 | K28: 2806.7 | L28: 2135.69 | M28: 2077.03 | N28: 4315.38 | O28: 2394.22 | P28: 2394.22 | Q28: 1953.7 | R28: 1975.32 | S28: 1780.87 | T28: 2242.18 | U28: 2242.18 | V28: 2916.14 | W28: 2139.37 | X28: 2943.16 | Y28: 5214.62 | Z28: 5214.62 | AA28: 2315.25 | AB28: 3208.87
A29: 1 | C29: 단기금융부채 | E29: 1687.55 | F29: 1687.55 | G29: 2619.15 | H29: 1681.47 | I29: 1670.9 | J29: 2918.41 | K29: 2918.41 | L29: 2247.4 | M29: 2187.96 | N29: 4426.31 | O29: 6529.73 | P29: 6529.73 | Q29: 6089.21 | R29: 4752.54 | S29: 4558.09 | T29: 5024.8 | U29: 5024.8 | V29: 9755.06 | W29: 3701.37 | X29: 3056.55 | Y29: 5214.62 | Z29: 5214.62 | AA29: 2407.4 | AB29: 3307.91
A30: 1 | C30: 기타유동부채 | E30: 816.95 | F30: 816.95 | G30: 171.06 | H30: 1355.59 | I30: 4177.82 | J30: 6694.66 | K30: 6694.66 | L30: 7257.64 | M30: 4876.02 | N30: 4091.58 | O30: 834.69 | P30: 834.69 | Q30: 261.52 | R30: 174.07 | S30: 617.16 | T30: 985.51 | U30: 985.51 | V30: 114.21 | W30: 2907.4 | X30: 3803.11 | Y30: 92.15 | Z30: 92.15 | AA30: 4760.93 | AB30: 9675.9
A31: 1 | C31: 유동리스부채 | E31: 114.72 | F31: 114.72 | G31: 114.72 | H31: 46.28 | I31: 46.28 | J31: 111.71 | K31: 111.71 | L31: 111.71 | M31: 110.93 | N31: 110.93 | O31: 109.95 | P31: 109.95 | Q31: 109.95 | R31: 107.15 | S31: 107.15 | T31: 114.21 | U31: 114.21 | V31: 4170.51 | W31: 113.39 | X31: 113.39 | Y31: 0 | Z31: 0 | AA31: 92.15 | AB31: 99.04
A32: 1 | C32: 리스부채 | E32: 164.86 | F32: 164.86 | G32: 164.86 | H32: 73.86 | I32: 73.86 | J32: 473.83 | K32: 473.83 | L32: 473.83 | M32: 407 | N32: 407 | O32: 352.19 | P32: 352.19 | Q32: 352.19 | R32: 296.07 | S32: 296.07 | T32: 268.97 | U32: 268.97 | V32: 4325.27 | W32: 211.04 | X32: 211.04 | Y32: 62.72 | Z32: 62.72 | AA32: 154.87 | AB32: 154.11
A33: 1 | C33: 비유동부채 | E33: 15806.65 | F33: 15806.65 | G33: 15029.39 | H33: 14313.79 | I33: 14032.17 | J33: 8547.91 | K33: 8547.91 | L33: 10575.24 | M33: 10774.28 | N33: 14414.99 | O33: 19441.82 | P33: 19441.82 | Q33: 21217.18 | R33: 20914.62 | S33: 21558.47 | T33: 21032.05 | U33: 21032.05 | V33: 20943.53 | W33: 17874.09 | X33: 18265.98 | Y33: 32302.5 | Z33: 32302.5 | AA33: 34473.21 | AB33: 35975.53
A34: 1 | C34: 장기차입금 | E34: 8406.88 | F34: 8406.88 | G34: 7684.35 | H34: 6917.44 | I34: 6534.23 | J34: 882.76 | K34: 882.76 | L34: 2921.18 | M34: 2996.95 | N34: 6579.76 | O34: 6258.02 | P34: 6258.02 | Q34: 11447.32 | R34: 7792.29 | S34: 8850.6 | T34: 11600.33 | U34: 11600.33 | V34: 11311.36 | W34: 8217.01 | X34: 7992.57 | Y34: 21930 | Z34: 21930 | AA34: 23930 | AB34: 26780
A35: 1 | C35: 확정급여부채 | E35: 2085.99 | F35: 2085.99 | G35: 2195.05 | H35: 2227.88 | I35: 2312.22 | J35: 2007.92 | K35: 2007.92 | L35: 2046.82 | M35: 2155.31 | N35: 2155.1 | O35: 2737.71 | P35: 2737.71 | Q35: 2726.26 | R35: 2810.74 | S35: 2711.75 | T35: 3200.69 | U35: 3200.69 | V35: 3371.83 | W35: 3428.04 | X35: 3584.17 | Y35: 3480.42 | Z35: 3480.42 | AA35: 3623.23 | AB35: 2252.82
A36: 1 | C36: 이연법인세부채 | E36: 4505.62 | F36: 4505.62 | G36: 4505.62 | H36: 4505.62 | I36: 4505.62 | J36: 4300.82 | K36: 4300.82 | L36: 4300.82 | M36: 4300.82 | N36: 4300.82 | O36: 4300.82 | P36: 4300.82 | Q36: 4300.82 | R36: 4300.82 | S36: 4300.82 | T36: 4300.82 | U36: 4300.82 | V36: 4300.82 | W36: 4300.82 | X36: 4300.82 | Y36: 4505.62 | Z36: 4505.62 | AA36: 4505.62 | AB36: 4505.62
A37: 1 | C37: 기타비유동금융부채 | E37: 640.54 | F37: 640.54 | G37: 476.75 | H37: 517.8 | I37: 535.03 | J37: 876.82 | K37: 876.82 | L37: 826.82 | M37: 907.64 | N37: 965.74 | O37: 1052.92 | P37: 1052.92 | Q37: 1083.06 | R37: 1141.5 | S37: 911.51 | T37: 975.46 | U37: 975.46 | V37: 1004.77 | W37: 1030.57 | X37: 1090.77 | Y37: 1123.74 | Z37: 1123.74 | AA37: 1151.65 | AB37: 1182.03
A38: 1 | C38: 장기금융부채 | E38: 690.68 | F38: 690.68 | G38: 526.89 | H38: 545.38 | I38: 562.61 | J38: 1238.94 | K38: 1238.94 | L38: 1188.94 | M38: 1203.71 | N38: 1261.81 | O38: 1295.16 | P38: 1295.16 | Q38: 1325.3 | R38: 1330.42 | S38: 1100.43 | T38: 1130.22 | U38: 1130.22 | V38: 1159.53 | W38: 1128.22 | X38: 1188.42 | Y38: 1186.46 | Z38: 1186.46 | AA38: 1214.37 | AB38: 1237.1
... A45: 1 | C45: 이익잉여금 | E45: -38729.09 | F45: -38729.09 | G45: -40236.41 | H45: -40791.86 | I45: -42252.69 | J45: -44477.25 | K45: -44477.25 | L45: -43440.27 | M45: -42235.43 | N45: -42540.41 | O45: -43261.03 | P45: -43261.03 | Q45: -42950.01 | R45: -42395.53 | S45: -43101.97 | T45: -46976.29 | U45: -46976.29 | V45: 10295.27 | W45: -52143.71 | X45: -52239.74 | Y45: -52014.91 | Z45: -52014.91 | AA45: -51476.73 | AB45: -50705.7
A46: 1 | C46: 기타포괄이익누계액 | E46: 934.99 | F46: 934.99
A47: 1 | C47: 기타자본 | E47: 10636.98 | F47: 10636.98 | G47: 11683.75 | H47: 10296.68 | I47: 10290.02 | J47: 10284.06 | K47: 10284.06 | L47: 10279.53 | M47: 10286.89 | N47: 10285.68 | O47: 10288.03 | P47: 10288.03 | Q47: 10290.36 | R47: 10319.39 | S47: 10294.64 | T47: 10295.15 | U47: 10295.15 | V47: -47658.51 | W47: 10320.52 | X47: 10345.26 | Y47: 10134.17 | Z47: 10134.17 | AA47: 10115.25 | AB47: 10101.64
A48: 1 | C48: 자본총계 | E48: 35004.02 | F48: 35004.02 | G48: 33608.48 | H48: 31665.96 | I48: 30198.47 | J48: 27967.95 | K48: 27967.95 | L48: 29000.39 | M48: 30212.6 | N48: 29906.4 | O48: 29188.13 | P48: 29188.13 | Q48: 29501.49 | R48: 30084.99 | S48: 29353.81 | T48: 25479.99 | U48: 25479.99 | V48: 24797.9 | W48: 29981.77 | X48: 31518.17 | Y48: 31531.92 | Z48: 31531.92 | AA48: 32051.17 | AB48: 32808.59
A49: 1 | C49: 부채와자본총계 | E49: 95401.54 | F49: 95401.54 | G49: 94895.94 | H49: 91950.52 | I49: 92658.92 | J49: 92590.76 | K49: 92590.76 | L49: 93396.12 | M49: 92271.69 | N49: 93969.04 | O49: 95687.93 | P49: 95687.93 | Q49: 91052.55 | R49: 92635.3 | S49: 91913.41 | T49: 92000.63 | U49: 92000.63 | V49: 94679.66 | W49: 97112.47 | X49: 97902.98 | Y49: 99766.18 | Z49: 99766.18 | AA49: 103071.63 | AB49: 107697.56
A50: 1 | C50: 지배주주지분 | E50: 35004.02 | F50: 35004.02 | G50: 33608.48 | H50: 31665.96 | I50: 30198.47 | J50: 27967.95 | K50: 27967.95 | L50: 29000.39 | M50: 30212.6 | N50: 29906.4 | O50: 29188.13 | P50: 29188.13 | Q50: 29501.49 | R50: 30084.99 | S50: 29353.81 | T50: 25479.99 | U50: 25479.99 | V50: 24797.9 | W50: 29981.77 | X50: 31518.17 | Y50: 31531.92 | Z50: 31531.92 | AA50: 32051.17 | AB50: 32808.59
A51: 1 | C51: 총차입금 | E51: 46363.93 | F51: 46363.93 | G51: 46811.06 | H51: 44896.09 | I51: 43413.47 | J51: 41325.76 | K51: 41325.76 | L51: 40723.51 | M51: 39754.58 | N51: 40287.49 | O51: 43153.79 | P51: 43153.79 | Q51: 39912.87 | R51: 42028.01 | S51: 42436.21 | T51: 44875.77 | U51: 44875.77 | V51: 41232.49 | W51: 43226.78 | X51: 41996.05 | Y51: 43421.48 | Z51: 43421.48 | AA51: 44248.23 | AB51: 43573.98
A52: 1 | C52: 순차입금 | E52: 45286.14 | F52: 45286.14 | G52: 45469.45 | H52: 43622.34 | I52: 41736.57 | J52: 39067.86 | K52: 39067.86 | L52: 39879.16 | M52: 38933.19 | N52: 38605.98 | O52: 38782.12 | P52: 38782.12 | Q52: 38713.38 | R52: 38421.19 | S52: 39790.01 | T52: 41277.89 | U52: 41277.89 | V52: 38856.37 | W52: 40070.98 | X52: 38636.47 | Y52: 40966.95 | Z52: 40966.95 | AA52: 42617.53 | AB52: 36338.91
A53: 1 | C53: 이자발생자산 | E53: 3256.59 | F53: 3256.59 | G53: 3663.2 | H53: 1848.27 | I53: 2274.76 | J53: 2366.47 | K53: 2366.47 | L53: 948.39 | M53: 932.79 | N53: 1818.31 | O53: 4507.46 | P53: 4507.46 | Q53: 1335.28 | R53: 3742.61 | S53: 2781.99 | T53: 3933.67 | U53: 3933.67 | V53: 2711.91 | W53: 3491.59 | X53: 3705.37 | Y53: 2809.05 | Z53: 2809.05 | AA53: 2043.9 | AB53: 7679.11
A54: 1 | C54: 유동성장기부채 | M54: 7231.73 | T54: 4138.42 | U54: 4138.42 | V54: 113.38 | W54: 911.46 | X54: 0 | Y54: 270.49 | Z54: 270.49
A55: 1 | C55: 유동파생상품자산 | O55: 247.04 | P55: 247.04 | Q55: 247.04 | R55: 590.39 | S55: 590.39 | T55: 57.44 | U55: 57.44 | V55: 57.44 | W55: 726.15 | X55: 0 | Y55: 1834.84 | Z55: 1834.84
A56: 1 | C56: 단기파생상품부채 | O56: 4025.56 | P56: 4025.56 | Q56: 4025.56 | R56: 2670.07 | S56: 2670.07 | T56: 2668.41 | U56: 2668.41 | V56: 2668.41 | W56: 1448.61 | X56: 0 | Y56: 0 | Z56: 0
A57: 1 | C57: 사채 | O57: 3432.63 | P57: 3432.63 | R57: 3762.86 | S57: 3794.87 | T57: 0 | U57: 0 | V57: 0 | Y57: 0 | Z57: 0
A58: 1 | C58: 장기금융부채(face) | T58: 11600.33 | U58: 11600.33 | V58: 11311.36 | W58: 8217.01 | X58: 7992.57 | Y58: 21930 | Z58: 21930 | AA58: 23930 | AB58: 26780
A59: 1 | C59: 매출액(수익) | E59: 8943.52 | G59: 7750.2 | H59: 8389.39 | I59: 8493.41 | J59: 9528.67 | K59: 34161.67 | L59: 12146 | M59: 13229.35 | N59: 8963.38 | O59: 12374.66 | P59: 46713.39 | Q59: 11308.63 | R59: 9539.04 | S59: 9634.62 | T59: 10787.12 | U59: 41269.41 | V59: 6995.8 | W59: 12308.84 | X59: 10624.17 | Y59: 13688.86 | Z59: 43617.67 | AA59: 14536.88 | AB59: 15059.41
A60: 1 | C60: 매출원가 | E60: 9850.09 | G60: 7505.65 | H60: 8142.07 | I60: 8440.12 | J60: 8674.15 | K60: 32761.99 | L60: 9477.87 | M60: 10279.92 | N60: 7446.4 | O60: 11061.74 | P60: 38265.93 | Q60: 9258.49 | R60: 8493.3 | S60: 9012.69 | T60: 11146.15 | U60: 37910.63 | V60: 6307.81 | W60: 10014.3 | X60: 8969.8 | Y60: 11706.33 | Z60: 36998.24 | AA60: 11738.24 | AB60: 13506.46
A61: 1 | C61: 매출총이익 | E61: -906.58 | G61: 244.55 | H61: 247.33 | I61: 53.29 | J61: 854.52 | K61: 1399.69 | L61: 2668.13 | M61: 2949.43 | N61: 1516.98 | O61: 1312.91 | P61: 8447.45 | Q61: 2050.14 | R61: 1045.74 | S61: 621.93 | T61: -359.03 | U61: 3358.78 | V61: 687.99 | W61: 2294.54 | X61: 1654.37 | Y61: 1982.51 | Z61: 6619.41 | AA61: 2798.64 | AB61: 1552.95
A62: 1 | C62: 판관비 | E62: 1308.87 | G62: 1356.16 | H62: 1086.53 | I62: 1160.55 | J62: 1059.09 | K62: 4662.33 | L62: 1205.94 | M62: 1112.67 | N62: 1290.3 | O62: 1429.78 | P62: 5038.69 | Q62: 1237.99 | R62: 1484.43 | S62: 942.18 | T62: 1455.44 | U62: 5120.04 | V62: 1146.46 | W62: 1491.42 | X62: 1538.1 | Y62: 1711.84 | Z62: 5887.82 | AA62: 1900.22 | AB62: 542.07
A63: 1 | C63: 영업이익 | E63: -2215.45 | G63: -1111.61 | H63: -839.2 | I63: -1107.26 | J63: -204.57 | K63: -3262.64 | L63: 1462.19 | M63: 1836.76 | N63: 226.67 | O63: -116.87 | P63: 3408.75 | Q63: 812.14 | R63: -438.7 | S63: -320.25 | T63: -1814.48 | U63: -1761.29 | V63: -458.47 | W63: 803.13 | X63: 116.27 | Y63: 270.67 | Z63: 731.6 | AA63: 898.42 | AB63: 1010.88
A64: 1 | C64: 기타영업외수익 | E64: -375.62 | G64: 51.22 | H64: 378.16 | I64: 177.27 | J64: -23.84 | K64: 582.81 | L64: 286.7 | M64: 675.92 | N64: 30.25 | O64: 340.32 | P64: 1333.19 | Q64: 177.32 | R64: 98.58 | S64: 27.75 | T64: 176.21 | U64: 479.86 | V64: 90.86 | W64: 59.59 | X64: 78.75 | Y64: 339.32 | Z64: 568.52 | AA64: 207.51 | AB64: 89.23
A65: 1 | C65: 기타영업외비용 | E65: 4794.83 | G65: 44.65 | H65: 775.82 | I65: 69.5 | J65: 871.23 | K65: 1761.2 | L65: 163.25 | M65: 748.49 | N65: 49.56 | O65: 717.52 | P65: 1678.82 | Q65: 97.26 | R65: 44.13 | S65: -35.14 | T65: 505.04 | U65: 611.29 | V65: 52.33 | W65: 228.55 | X65: -27.05 | Y65: 51.06 | Z65: 304.89 | AA65: 84.37 | AB65: 72.02
A66: 1 | C66: 금융수익 | E66: 24.56 | G66: 36.95 | H66: 31.35 | I66: 34.97 | J66: 50.97 | K66: 154.24 | L66: 17.38 | M66: 16.49 | N66: 70.15 | O66: 1114.21 | P66: 1218.23 | Q66: 5.45 | R66: 1806.08 | S66: 88.89 | T66: -331.41 | U66: 1569.01 | V66: 166.69 | W66: 1454.21 | X66: 498.32 | Y66: -672.92 | Z66: 1446.3 | AA66: 30.96 | AB66: 273.01
A67: 1 | C67: 금융비용 | E67: 424.68 | G67: 439.23 | H67: 511.24 | I67: 496.31 | J67: 578.93 | K67: 2025.71 | L67: 566.04 | M67: 575.84 | N67: 582.5 | O67: 884.67 | P67: 2609.05 | Q67: 586.62 | R67: 867.36 | S67: 537.96 | T67: 1210.25 | U67: 3202.19 | V67: 428.97 | W67: 6573.58 | X67: 816.43 | Y67: -266.64 | Z67: 7552.34 | AA67: 514.34 | AB67: 530.07
A68: 1 | C68: 법인세비용차감전계속사업이익 | E68: -7480.84 | G68: -1507.32 | H68: -1716.75 | I68: -1460.83 | J68: -2734.66 | K68: -7419.56 | L68: 1036.98 | M68: 1204.84 | N68: -304.98 | O68: -264.53 | P68: 1672.31 | Q68: 311.02 | R68: 554.47 | S68: -706.44 | T68: -3684.97 | U68: -3525.92 | V68: -682.22 | W68: -4485.19 | X68: -96.04 | Y68: 152.65 | Z68: -5110.8 | AA68: 538.17 | AB68: 771.03
A69: 1 | C69: 당기순이익 | E69: -7480.84 | G69: -1507.32 | H69: -1716.75 | I69: -1460.83 | J69: -2734.66 | K69: -7419.56 | L69: 1036.98 | M69: 1204.84 | N69: -304.98 | O69: -264.53 | P69: 1672.31 | Q69: 311.02 | R69: 554.47 | S69: -706.44 | T69: -3684.97 | U69: -3525.92 | V69: -682.22 | W69: -4485.19 | X69: -96.04 | Y69: 152.65 | Z69: -5110.8 | AA69: 538.17 | AB69: 771.03
A70: 1 | C70: 총포괄손익 | E70: -2879.28 | G70: -1395.54 | H70: -1942.52 | I70: -1467.49 | J70: -2230.52 | K70: -7036.07 | L70: 1032.45 | M70: 1212.21 | N70: -306.2 | O70: -718.27 | P70: 1220.19 | Q70: 313.35 | R70: 583.5 | S70: -731.19 | T70: -3873.81 | U70: -3708.15 | V70: -682.1 | W70: -4459.95 | X70: -71.3 | Y70: 24.54 | Z70: -5188.81 | AA70: 519.26 | AB70: 757.42
... A74: 1 | C74: 계속사업이익 | E74: -7480.84 | G74: -1507.32 | H74: -1716.75 | I74: -1460.83 | J74: -2734.66 | K74: -7419.56 | L74: 1036.98 | M74: 1204.84 | N74: -304.98 | O74: -264.53 | P74: 1672.31 | Q74: 311.02 | R74: 554.47 | S74: -706.44 | T74: -3684.97 | U74: -3525.92 | V74: -682.22 | W74: -4485.19 | X74: -96.04 | Y74: 152.65 | Z74: -5110.8 | AA74: 538.17 | AB74: 771.03
A75: 1 | C75: 법인세비용 | G75: 0 | H75: 0 | I75: 0 | J75: 0 | K75: 0 | L75: 0 | M75: 0 | N75: 0 | O75: 0 | P75: 0 | Q75: 0 | R75: 0 | S75: 0 | T75: 0 | U75: 0 | X75: 0 | Y75: 0 | AA75: 0 | AB75: 0
A76: 1 | C76: 영업활동으로인한현금흐름 | E76: 655.23 | G76: -2423.91 | H76: -237.42 | I76: 2008.12 | J76: 1761.05 | K76: 1107.84 | L76: -858.89 | M76: 1425.19 | N76: 620.21 | O76: -5743.67 | P76: -4557.16 | Q76: -609.55 | R76: 211.93 | S76: -1107.45 | T76: -471.27 | U76: -1976.34 | V76: -1554.8 | W76: -1009.43 | X76: 1135.01 | Y76: -3570.01 | Z76: -4999.23 | AA76: -46.25 | AB76: 6436.89
A77: 1 | C77: 감가상각비 | E77: 352.32 | G77: 172.01 | H77: 246.52 | I77: 177.1 | J77: 243.68 | K77: 839.31 | L77: 176.17 | M77: 240.37
A78: 1 | C78: 무형자산상각비 | E78: 21.39 | G78: 0 | H78: 0 | I78: 0 | L78: 0
A79: 1 | C79: 법인세납부(CF) | E79: -0.67 | G79: -0.48 | H79: 5.89 | I79: 61.74 | J79: -1.67 | K79: 65.48 | L79: 0 | M79: 1.43 | N79: 0 | O79: -2.91 | P79: -1.48 | Q79: 0 | R79: 1.94 | S79: 0 | T79: -2.36 | U79: -0.42 | V79: 0 | W79: 3 | X79: -58.55 | Y79: 0 | Z79: -55.55 | AA79: -0.47
A80: 1 | C80: 투자활동으로인한현금흐름 | E80: -1594 | G80: 2194.48 | H80: 2157.13 | I80: -129.18 | J80: 895.46 | K80: 5117.89 | L80: 407 | M80: -464.12 | N80: -257.1 | O80: -25.2 | P80: -339.42 | Q80: 676.43 | R80: 203.33 | S80: 3.65 | T80: -159.42 | U80: 723.99 | V80: -77.28 | W80: -36.57 | X80: 72.74 | Y80: -285.82 | Z80: -326.93 | AA80: -75.09 | AB80: -187.04
A81: 1 | C81: 유형자산의감소 | E81: 0 | G81: 0 | H81: 0 | I81: 5 | J81: 0 | K81: 5 | L81: 0 | O81: 0 | Q81: 9 | R81: 3.82 | S81: 0 | T81: 0 | U81: 12.82 | V81: 12.82 | W81: 0 | X81: 0 | AA81: 25.91 | AB81: 11.16
A82: 1 | C82: 유형자산의증가 | E82: 12.93 | G82: 0 | H82: 0 | I82: 90.01 | J82: 0.14 | K82: 90.15 | L82: 0 | M82: 2.4 | N82: 264.08 | Q82: 32.57 | R82: 0.85 | S82: -0.85 | T82: 0 | U82: 32.57 | V82: 95.7 | W82: 39.36 | X82: 0.66 | Y82: 289 | Z82: 424.72 | AA82: 0 | AB82: 126.2
A83: 1 | C83: CAPEX | E83: 12.93 | G83: 0 | H83: 0 | I83: 90.01 | J83: 0.14 | K83: 90.15 | L83: 0 | M83: 2.4 | N83: 264.08 | Q83: 32.57 | R83: 0.85 | S83: -0.85 | T83: 0 | U83: 32.57 | V83: 95.7 | W83: 39.36 | X83: 0.66 | Y83: 289 | Z83: 424.72 | AA83: 0 | AB83: 126.2
A84: 1 | C84: 재무활동으로인한현금흐름 | E84: 877.46 | G84: 447.12 | H84: -1988.75 | I84: -1482.61 | J84: -2135.64 | K84: -5159.88 | L84: -602.25 | M84: -987.12 | N84: 496.17 | O84: 8212 | P84: 7118.8 | Q84: -3235.4 | R84: 1805.32 | S84: 145.51 | T84: 2114.14 | U84: 829.57 | V84: 410.31 | W84: 1156.96 | X84: -278.81 | Y84: 1117.9 | Z84: 2406.36 | AA84: 1124.39 | AB84: -717.87
A85: 1 | C85: 차입금의증가 | E85: 11944.36 | G85: 2638.64 | H85: 3250.63 | I85: 1489.5 | J85: 9481.19 | K85: 16859.96 | L85: 3297.7 | M85: 8686.88 | N85: 5731.12 | Q85: 3215.64 | R85: 3558.57 | T85: 6909 | V85: 1445.32 | W85: 6653.04 | X85: 5826.85 | Y85: 22486.54 | Z85: 36411.75 | AA85: 5910.82 | AB85: 4978.74
A86: 1 | C86: 차입금의감소 | E86: 11021.37 | G86: 2191.52 | H86: 5165.6 | I86: 2972.11 | J86: 11568.91 | K86: 21898.14 | L86: 3899.95 | M86: 9655.8 | N86: 5198.21 | Q86: 6483.61 | R86: 1746.61 | T86: 4812.98 | V86: 1063.56 | W86: 5456.82 | X86: 6146.13 | Y86: 21331.6 | Z86: 33998.11 | AA86: 4813.58 | AB86: 5652.99
A87: 1 | C87: 리스부채의상환 | E87: 45.54 | G87: 0 | H87: 73.78 | I87: 0 | J87: 47.92 | K87: 121.7 | L87: 0 | M87: 54.94 | N87: 0 | O87: 54.81 | P87: 109.75 | S87: 0 | T87: 48.61 | X87: 0 | Y87: 61.13
A88: 1 | C88: 현금및현금성자산의증감 | E88: -61.29 | G88: 215.82 | H88: -67.86 | I88: 403.15 | J88: 511 | K88: 1062.11 | L88: -1052.55 | M88: -28.47 | N88: 860.12 | O88: 2443.12 | P88: 2222.22 | Q88: -3172.18 | R88: 2220.34 | S88: -960.62 | T88: 1484.63 | U88: -427.83 | V88: -1221.77 | W88: 110.97 | X88: 928.93 | Y88: -2742.88 | Z88: -2924.75 | AA88: 1008.01 | AB88: 5601.37
A89: 1 | C89: 기말현금및현금성자산 | E89: -61.29 | G89: 329.76 | H89: -67.86 | I89: 403.15 | J89: 511 | K89: 1176.05 | L89: 123.5 | M89: -28.47 | N89: 860.12 | O89: 2443.12 | P89: 3398.27 | Q89: 226.09 | R89: 2220.34 | S89: -960.62 | T89: 1484.63 | U89: 2970.44 | V89: 1748.68 | W89: 110.97 | X89: 928.93 | Y89: -2742.89 | Z89: 45.69 | AA89: 1053.7 | AB89: 5601.37
A90: 1 | C90: 배당금수취(CF) | G90: 0 | H90: 0 | I90: 0 | J90: 0 | K90: 0 | L90: 0
A91: 1 | C91: 무형자산의증가 | G91: 0 | H91: 0
A92: 1 | C92: 무형자산의감소 | I92: 0 | J92: 0 | L92: 0 | M92: 0 | N92: 0 | O92: 0 | P92: 0
A93: 1 | C93: 이자수취(CF) | O93: 25.21 | Q93: 2.79 | R93: 15.12 | S93: 2.12 | T93: 17.25 | U93: 37.28 | V93: 0.93 | W93: 7.8 | X93: 213.92 | Y93: 17.64 | Z93: 240.29 | AA93: 3.48 | AB93: 28.61

Sheet subQ
A1: YQ | C1: subQ 분기 서브모델(억원, U=100) | E1: 4Q21 | F1: 2021 | G1: 1Q22 | H1: 2Q22 | I1: 3Q22 | J1: 4Q22 | K1: 2022 | L1: 1Q23 | M1: 2Q23 | N1: 3Q23 | O1: 4Q23 | P1: 2023 | Q1: 1Q24 | R1: 2Q24 | S1: 3Q24 | T1: 4Q24 | U1: 2024 | V1: 1Q25 | W1: 2Q25 | X1: 3Q25 | Y1: 4Q25 | Z1: 2025 | AA1: 1Q26 | AB1: 2Q26 | AC1: 3Q26 | AD1: 4Q26 | AE1: 2026 | AF1: 1Q27 | AG1: 2Q27 | AH1: 3Q27 | AI1: 4Q27 | AJ1: 2027 | AK1: 1Q28 | AL1: 2Q28 | AM1: 3Q28 | AN1: 4Q28 | AO1: 2028
A2: A=이름(key) B=그룹 C=단위 D=FnGuide 계정명(VLOOKUP 키). 확정=VLOOKUP(BS), 추정=변수 가정 참조
E3: 1 | F3: 2 | G3: 3 | H3: 4 | I3: 5 | J3: 6 | K3: 7 | L3: 8 | M3: 9 | N3: 10 | O3: 11 | P3: 12 | Q3: 13 | R3: 14 | S3: 15 | T3: 16 | U3: 17 | V3: 18 | W3: 19 | X3: 20 | Y3: 21 | Z3: 22 | AA3: 23 | AB3: 24 | AC3: 25 | AD3: 26 | AE3: 27 | AF3: 28 | AG3: 29 | AH3: 30 | AI3: 31 | AJ3: 32 | AK3: 33 | AL3: 34 | AM3: 35 | AN3: 36 | AO3: 37
E4: 2021.12 | F4: 2021.12A | G4: 2022.03 | H4: 2022.06 | I4: 2022.09 | J4: 2022.12 | K4: 2022.12A | L4: 2023.03 | M4: 2023.06 | N4: 2023.09 | O4: 2023.12 | P4: 2023.12A | Q4: 2024.03 | R4: 2024.06 | S4: 2024.09 | T4: 2024.12 | U4: 2024.12A | V4: 2025.03 | W4: 2025.06 | X4: 2025.09 | Y4: 2025.12 | Z4: 2025.12A | AA4: 2026.03 | AB4: 2026.06 | AC4: 2026.09 | AD4: 2026.12 | AE4: 2026.12A | AF4: 2027.03 | AG4: 2027.06 | AH4: 2027.09 | AI4: 2027.12 | AJ4: 2027.12A | AK4: 2028.03 | AL4: 2028.06 | AM4: 2028.09 | AN4: 2028.12 | AO4: 2028.12A
A5: 매출액 | B5: 손익 | C5: 억원 | D5: 매출액(수익) | E5: =IFERROR(VLOOKUP($D5,BS연결,MATCH(E$1,BS연결H,0),0)/100,"") | G5: =IFERROR(VLOOKUP($D5,BS연결,MATCH(G$1,BS연결H,0),0)/100,"") | H5: =IFERROR(VLOOKUP($D5,BS연결,MATCH(H$1,BS연결H,0),0)/100,"") | I5: =IFERROR(VLOOKUP($D5,BS연결,MATCH(I$1,BS연결H,0),0)/100,"") | J5: =IFERROR(VLOOKUP($D5,BS연결,MATCH(J$1,BS연결H,0),0)/100,"") | K5: =IFERROR(VLOOKUP($D5,BS연결,MATCH(K$1,BS연결H,0),0)/100,"") | L5: =IFERROR(VLOOKUP($D5,BS연결,MATCH(L$1,BS연결H,0),0)/100,"") | M5: =IFERROR(VLOOKUP($D5,BS연결,MATCH(M$1,BS연결H,0),0)/100,"") | N5: =IFERROR(VLOOKUP($D5,BS연결,MATCH(N$1,BS연결H,0),0)/100,"") | ... AB5: =IFERROR(VLOOKUP($D5,BS연결,MATCH(AB$1,BS연결H,0),0)/100,"") | AC5: =IFERROR(X5*(1+변수!AC21),"") | AD5: =IFERROR(Y5*(1+변수!AD21),"") | AE5: =SUM(AA5:AD5) | AF5: =IFERROR(AA5*(1+변수!AF21),"") | AG5: =IFERROR(AB5*(1+변수!AG21),"") | AH5: =IFERROR(AC5*(1+변수!AH21),"") | AI5: =IFERROR(AD5*(1+변수!AI21),"") | AJ5: =SUM(AF5:AI5) | AK5: =IFERROR(AF5*(1+변수!AK21),"") | AL5: =IFERROR(AG5*(1+변수!AL21),"") | AM5: =IFERROR(AH5*(1+변수!AM21),"") | AN5: =IFERROR(AI5*(1+변수!AN21),"") | AO5: =SUM(AK5:AN5)
A6: 매출원가 | B6: 손익 | C6: 억원 | D6: 매출원가 | E6: =IFERROR(VLOOKUP($D6,BS연결,MATCH(E$1,BS연결H,0),0)/100,"") | G6: =IFERROR(VLOOKUP($D6,BS연결,MATCH(G$1,BS연결H,0),0)/100,"") | H6: =IFERROR(VLOOKUP($D6,BS연결,MATCH(H$1,BS연결H,0),0)/100,"") | I6: =IFERROR(VLOOKUP($D6,BS연결,MATCH(I$1,BS연결H,0),0)/100,"") | J6: =IFERROR(VLOOKUP($D6,BS연결,MATCH(J$1,BS연결H,0),0)/100,"") | K6: =IFERROR(VLOOKUP($D6,BS연결,MATCH(K$1,BS연결H,0),0)/100,"") | L6: =IFERROR(VLOOKUP($D6,BS연결,MATCH(L$1,BS연결H,0),0)/100,"") | M6: =IFERROR(VLOOKUP($D6,BS연결,MATCH(M$1,BS연결H,0),0)/100,"") | N6: =IFERROR(VLOOKUP($D6,BS연결,MATCH(N$1,BS연결H,0),0)/100,"") | ... AB6: =IFERROR(VLOOKUP($D6,BS연결,MATCH(AB$1,BS연결H,0),0)/100,"") | AC6: =IFERROR(AC5-AC7,"") | AD6: =IFERROR(AD5-AD7,"") | AE6: =SUM(AA6:AD6) | AF6: =IFERROR(AF5-AF7,"") | AG6: =IFERROR(AG5-AG7,"") | AH6: =IFERROR(AH5-AH7,"") | AI6: =IFERROR(AI5-AI7,"") | AJ6: =SUM(AF6:AI6) | AK6: =IFERROR(AK5-AK7,"") | AL6: =IFERROR(AL5-AL7,"") | AM6: =IFERROR(AM5-AM7,"") | AN6: =IFERROR(AN5-AN7,"") | AO6: =SUM(AK6:AN6)
A7: 매출총이익 | B7: 손익 | C7: 억원 | D7: 매출총이익 | E7: =IFERROR(VLOOKUP($D7,BS연결,MATCH(E$1,BS연결H,0),0)/100,"") | G7: =IFERROR(VLOOKUP($D7,BS연결,MATCH(G$1,BS연결H,0),0)/100,"") | H7: =IFERROR(VLOOKUP($D7,BS연결,MATCH(H$1,BS연결H,0),0)/100,"") | I7: =IFERROR(VLOOKUP($D7,BS연결,MATCH(I$1,BS연결H,0),0)/100,"") | J7: =IFERROR(VLOOKUP($D7,BS연결,MATCH(J$1,BS연결H,0),0)/100,"") | K7: =IFERROR(VLOOKUP($D7,BS연결,MATCH(K$1,BS연결H,0),0)/100,"") | L7: =IFERROR(VLOOKUP($D7,BS연결,MATCH(L$1,BS연결H,0),0)/100,"") | M7: =IFERROR(VLOOKUP($D7,BS연결,MATCH(M$1,BS연결H,0),0)/100,"") | N7: =IFERROR(VLOOKUP($D7,BS연결,MATCH(N$1,BS연결H,0),0)/100,"") | O7: =IFERROR(VLOOKUP($D7,BS연결,MATCH(O$1,BS연결H,0),0)/100,"") | P7: =SUM(L7:O7) | Q7: =IFERROR(VLOOKUP($D7,BS연결,MATCH(Q$1,BS연결H,0),0)/100,"") | R7: =IFERROR(VLOOKUP($D7,BS연결,MATCH(R$1,BS연결H,0),0)/100,"") | S7: =IFERROR(VLOOKUP($D7,BS연결,MATCH(S$1,BS연결H,0),0)/100,"") | T7: =IFERROR(VLOOKUP($D7,BS연결,MATCH(T$1,BS연결H,0),0)/100,"") | U7: =IFERROR(VLOOKUP($D7,BS연결,MATCH(U$1,BS연결H,0),0)/100,"") | V7: =IFERROR(VLOOKUP($D7,BS연결,MATCH(V$1,BS연결H,0),0)/100,"") | W7: =IFERROR(VLOOKUP($D7,BS연결,MATCH(W$1,BS연결H,0),0)/100,"") | X7: =IFERROR(VLOOKUP($D7,BS연결,MATCH(X$1,BS연결H,0),0)/100,"") | Y7: =IFERROR(VLOOKUP($D7,BS연결,MATCH(Y$1,BS연결H,0),0)/100,"") | Z7: =SUM(V7:Y7) | AA7: =IFERROR(VLOOKUP($D7,BS연결,MATCH(AA$1,BS연결H,0),0)/100,"") | AB7: =IFERROR(VLOOKUP($D7,BS연결,MATCH(AB$1,BS연결H,0),0)/100,"") | AC7: =IFERROR(AC9+AC8,"") | AD7: =IFERROR(AD9+AD8,"") | AE7: =SUM(AA7:AD7) | AF7: =IFERROR(AF9+AF8,"") | AG7: =IFERROR(AG9+AG8,"") | AH7: =IFERROR(AH9+AH8,"") | AI7: =IFERROR(AI9+AI8,"") | AJ7: =SUM(AF7:AI7) | AK7: =IFERROR(AK9+AK8,"") | AL7: =IFERROR(AL9+AL8,"") | AM7: =IFERROR(AM9+AM8,"") | AN7: =IFERROR(AN9+AN8,"") | AO7: =SUM(AK7:AN7)
A8: 판관비 | B8: 손익 | C8: 억원 | D8: 판관비 | E8: =IFERROR(VLOOKUP($D8,BS연결,MATCH(E$1,BS연결H,0),0)/100,"") | G8: =IFERROR(VLOOKUP($D8,BS연결,MATCH(G$1,BS연결H,0),0)/100,"") | H8: =IFERROR(VLOOKUP($D8,BS연결,MATCH(H$1,BS연결H,0),0)/100,"") | I8: =IFERROR(VLOOKUP($D8,BS연결,MATCH(I$1,BS연결H,0),0)/100,"") | J8: =IFERROR(VLOOKUP($D8,BS연결,MATCH(J$1,BS연결H,0),0)/100,"") | K8: =IFERROR(VLOOKUP($D8,BS연결,MATCH(K$1,BS연결H,0),0)/100,"") | L8: =IFERROR(VLOOKUP($D8,BS연결,MATCH(L$1,BS연결H,0),0)/100,"") | M8: =IFERROR(VLOOKUP($D8,BS연결,MATCH(M$1,BS연결H,0),0)/100,"") | N8: =IFERROR(VLOOKUP($D8,BS연결,MATCH(N$1,BS연결H,0),0)/100,"") | ... AB8: =IFERROR(VLOOKUP($D8,BS연결,MATCH(AB$1,BS연결H,0),0)/100,"") | AC8: =IFERROR(AC5*변수!AC22,"") | AD8: =IFERROR(AD5*변수!AD22,"") | AE8: =SUM(AA8:AD8) | AF8: =IFERROR(AF5*변수!AF22,"") | AG8: =IFERROR(AG5*변수!AG22,"") | AH8: =IFERROR(AH5*변수!AH22,"") | AI8: =IFERROR(AI5*변수!AI22,"") | AJ8: =SUM(AF8:AI8) | AK8: =IFERROR(AK5*변수!AK22,"") | AL8: =IFERROR(AL5*변수!AL22,"") | AM8: =IFERROR(AM5*변수!AM22,"") | AN8: =IFERROR(AN5*변수!AN22,"") | AO8: =SUM(AK8:AN8)
A9: 영업이익 | B9: 손익 | C9: 억원 | D9: 영업이익 | E9: =IFERROR(VLOOKUP($D9,BS연결,MATCH(E$1,BS연결H,0),0)/100,"") | G9: =IFERROR(VLOOKUP($D9,BS연결,MATCH(G$1,BS연결H,0),0)/100,"") | H9: =IFERROR(VLOOKUP($D9,BS연결,MATCH(H$1,BS연결H,0),0)/100,"") | I9: =IFERROR(VLOOKUP($D9,BS연결,MATCH(I$1,BS연결H,0),0)/100,"") | J9: =IFERROR(VLOOKUP($D9,BS연결,MATCH(J$1,BS연결H,0),0)/100,"") | K9: =SUM(G9:J9) | L9: =IFERROR(VLOOKUP($D9,BS연결,MATCH(L$1,BS연결H,0),0)/100,"") | M9: =IFERROR(VLOOKUP($D9,BS연결,MATCH(M$1,BS연결H,0),0)/100,"") | N9: =IFERROR(VLOOKUP($D9,BS연결,MATCH(N$1,BS연결H,0),0)/100,"") | O9: =IFERROR(VLOOKUP($D9,BS연결,MATCH(O$1,BS연결H,0),0)/100,"") | P9: =IFERROR(VLOOKUP($D9,BS연결,MATCH(P$1,BS연결H,0),0)/100,"") | Q9: =IFERROR(VLOOKUP($D9,BS연결,MATCH(Q$1,BS연결H,0),0)/100,"") | R9: =IFERROR(VLOOKUP($D9,BS연결,MATCH(R$1,BS연결H,0),0)/100,"") | S9: =IFERROR(VLOOKUP($D9,BS연결,MATCH(S$1,BS연결H,0),0)/100,"") | ... AB9: =IFERROR(VLOOKUP($D9,BS연결,MATCH(AB$1,BS연결H,0),0)/100,"") | AC9: =IFERROR(AC5*변수!AC23,"") | AD9: =IFERROR(AD5*변수!AD23,"") | AE9: =SUM(AA9:AD9) | AF9: =IFERROR(AF5*변수!AF23,"") | AG9: =IFERROR(AG5*변수!AG23,"") | AH9: =IFERROR(AH5*변수!AH23,"") | AI9: =IFERROR(AI5*변수!AI23,"") | AJ9: =SUM(AF9:AI9) | AK9: =IFERROR(AK5*변수!AK23,"") | AL9: =IFERROR(AL5*변수!AL23,"") | AM9: =IFERROR(AM5*변수!AM23,"") | AN9: =IFERROR(AN5*변수!AN23,"") | AO9: =SUM(AK9:AN9)
A10: OPM | B10: 손익 | C10: % | D10: 영업이익률 | E10: =IFERROR(E9/E5,"") | G10: =IFERROR(G9/G5,"") | H10: =IFERROR(H9/H5,"") | I10: =IFERROR(I9/I5,"") | J10: =IFERROR(J9/J5,"") | K10: =IFERROR(K9/K5,"") | L10: =IFERROR(L9/L5,"") | M10: =IFERROR(M9/M5,"") | N10: =IFERROR(N9/N5,"") | ... AO10: =IFERROR(AO9/AO5,"")
A11: 금융손익 | B11: 손익 | C11: 억원 | D11: 금융손익 | E11: =IFERROR(VLOOKUP($D11,BS연결,MATCH(E$1,BS연결H,0),0)/100,"") | G11: =IFERROR(VLOOKUP($D11,BS연결,MATCH(G$1,BS연결H,0),0)/100,"") | H11: =IFERROR(VLOOKUP($D11,BS연결,MATCH(H$1,BS연결H,0),0)/100,"") | I11: =IFERROR(VLOOKUP($D11,BS연결,MATCH(I$1,BS연결H,0),0)/100,"") | J11: =IFERROR(VLOOKUP($D11,BS연결,MATCH(J$1,BS연결H,0),0)/100,"") | K11: =IFERROR(VLOOKUP($D11,BS연결,MATCH(K$1,BS연결H,0),0)/100,"") | L11: =IFERROR(VLOOKUP($D11,BS연결,MATCH(L$1,BS연결H,0),0)/100,"") | M11: =IFERROR(VLOOKUP($D11,BS연결,MATCH(M$1,BS연결H,0),0)/100,"") | N11: =IFERROR(VLOOKUP($D11,BS연결,MATCH(N$1,BS연결H,0),0)/100,"") | ... AB11: =IFERROR(VLOOKUP($D11,BS연결,MATCH(AB$1,BS연결H,0),0)/100,"") | AC11: =IFERROR(AC12+AC13+AC14+AC15,"") | AD11: =IFERROR(AD12+AD13+AD14+AD15,"") | AE11: =SUM(AA11:AD11) | AF11: =IFERROR(AF12+AF13+AF14+AF15,"") | AG11: =IFERROR(AG12+AG13+AG14+AG15,"") | AH11: =IFERROR(AH12+AH13+AH14+AH15,"") | AI11: =IFERROR(AI12+AI13+AI14+AI15,"") | AJ11: =SUM(AF11:AI11) | AK11: =IFERROR(AK12+AK13+AK14+AK15,"") | AL11: =IFERROR(AL12+AL13+AL14+AL15,"") | AM11: =IFERROR(AM12+AM13+AM14+AM15,"") | AN11: =IFERROR(AN12+AN13+AN14+AN15,"") | AO11: =SUM(AK11:AN11)
A12: 이자손익 | B12: 손익 | C12: 억원 | D12: 이자손익 | G12: =IFERROR(VLOOKUP($D12,BS연결,MATCH(G$1,BS연결H,0),0)/100,"") | H12: =IFERROR(VLOOKUP($D12,BS연결,MATCH(H$1,BS연결H,0),0)/100,"") | I12: =IFERROR(VLOOKUP($D12,BS연결,MATCH(I$1,BS연결H,0),0)/100,"") | J12: =IFERROR(VLOOKUP($D12,BS연결,MATCH(J$1,BS연결H,0),0)/100,"") | K12: =IFERROR(VLOOKUP($D12,BS연결,MATCH(K$1,BS연결H,0),0)/100,"") | L12: =IFERROR(VLOOKUP($D12,BS연결,MATCH(L$1,BS연결H,0),0)/100,"") | M12: =IFERROR(VLOOKUP($D12,BS연결,MATCH(M$1,BS연결H,0),0)/100,"") | N12: =IFERROR(VLOOKUP($D12,BS연결,MATCH(N$1,BS연결H,0),0)/100,"") | ... AB12: =IFERROR(VLOOKUP($D12,BS연결,MATCH(AB$1,BS연결H,0),0)/100,"") | AC12: =IFERROR((AB29*변수!$D$54-AB27*변수!$D$55)/4,"") | AD12: =IFERROR((AC29*변수!$D$54-AC27*변수!$D$55)/4,"") | AE12: =SUM(AA12:AD12) | AF12: =IFERROR((AD29*변수!$D$54-AD27*변수!$D$55)/4,"") | AG12: =IFERROR((AF29*변수!$D$54-AF27*변수!$D$55)/4,"") | AH12: =IFERROR((AG29*변수!$D$54-AG27*변수!$D$55)/4,"") | AI12: =IFERROR((AH29*변수!$D$54-AH27*변수!$D$55)/4,"") | AJ12: =SUM(AF12:AI12) | AK12: =IFERROR((AI29*변수!$D$54-AI27*변수!$D$55)/4,"") | AL12: =IFERROR((AK29*변수!$D$54-AK27*변수!$D$55)/4,"") | AM12: =IFERROR((AL29*변수!$D$54-AL27*변수!$D$55)/4,"") | AN12: =IFERROR((AM29*변수!$D$54-AM27*변수!$D$55)/4,"") | AO12: =SUM(AK12:AN12)
A13: 외환손익 | B13: 손익 | C13: 억원 | D13: 외환손익(실적만; 추정 환효과는 환관련손익) | H13: =IFERROR((VLOOKUP("외환차익",BS연결,MATCH(H$1,BS연결H,0),0)-VLOOKUP("외환차손",BS연결,MATCH(H$1,BS연결H,0),0)+VLOOKUP("외화환산이익",BS연결,MATCH(H$1,BS연결H,0),0)-VLOOKUP("외화환산손실",BS연결,MATCH(H$1,BS연결H,0),0))/100,"") | I13: =IFERROR((VLOOKUP("외환차익",BS연결,MATCH(I$1,BS연결H,0),0)-VLOOKUP("외환차손",BS연결,MATCH(I$1,BS연결H,0),0)+VLOOKUP("외화환산이익",BS연결,MATCH(I$1,BS연결H,0),0)-VLOOKUP("외화환산손실",BS연결,MATCH(I$1,BS연결H,0),0))/100,"") | K13: =SUM(G13:J13) | M13: =IFERROR((VLOOKUP("외환차익",BS연결,MATCH(M$1,BS연결H,0),0)-VLOOKUP("외환차손",BS연결,MATCH(M$1,BS연결H,0),0)+VLOOKUP("외화환산이익",BS연결,MATCH(M$1,BS연결H,0),0)-VLOOKUP("외화환산손실",BS연결,MATCH(M$1,BS연결H,0),0))/100,"") | N13: =IFERROR((VLOOKUP("외환차익",BS연결,MATCH(N$1,BS연결H,0),0)-VLOOKUP("외환차손",BS연결,MATCH(N$1,BS연결H,0),0)+VLOOKUP("외화환산이익",BS연결,MATCH(N$1,BS연결H,0),0)-VLOOKUP("외화환산손실",BS연결,MATCH(N$1,BS연결H,0),0))/100,"") | P13: =SUM(L13:O13) | R13: =IFERROR((VLOOKUP("외환차익",BS연결,MATCH(R$1,BS연결H,0),0)-VLOOKUP("외환차손",BS연결,MATCH(R$1,BS연결H,0),0)+VLOOKUP("외화환산이익",BS연결,MATCH(R$1,BS연결H,0),0)-VLOOKUP("외화환산손실",BS연결,MATCH(R$1,BS연결H,0),0))/100,"") | S13: =IFERROR((VLOOKUP("외환차익",BS연결,MATCH(S$1,BS연결H,0),0)-VLOOKUP("외환차손",BS연결,MATCH(S$1,BS연결H,0),0)+VLOOKUP("외화환산이익",BS연결,MATCH(S$1,BS연결H,0),0)-VLOOKUP("외화환산손실",BS연결,MATCH(S$1,BS연결H,0),0))/100,"") | T13: =IFERROR((VLOOKUP("외환차익",BS연결,MATCH(T$1,BS연결H,0),0)-VLOOKUP("외환차손",BS연결,MATCH(T$1,BS연결H,0),0)+VLOOKUP("외화환산이익",BS연결,MATCH(T$1,BS연결H,0),0)-VLOOKUP("외화환산손실",BS연결,MATCH(T$1,BS연결H,0),0))/100,"") | U13: =SUM(Q13:T13) | Z13: =SUM(V13:Y13) | AB13: =IFERROR((VLOOKUP("외환차익",BS연결,MATCH(AB$1,BS연결H,0),0)-VLOOKUP("외환차손",BS연결,MATCH(AB$1,BS연결H,0),0)+VLOOKUP("외화환산이익",BS연결,MATCH(AB$1,BS연결H,0),0)-VLOOKUP("외화환산손실",BS연결,MATCH(AB$1,BS연결H,0),0))/100,"") | AC13: =변수!AC24 | AD13: =변수!AD24 | AE13: =SUM(AA13:AD13) | AF13: =변수!AF24 | AG13: =변수!AG24 | AH13: =변수!AH24 | AI13: =변수!AI24 | AJ13: =SUM(AF13:AI13) | AK13: =변수!AK24 | AL13: =변수!AL24 | AM13: =변수!AM24 | AN13: =변수!AN24 | AO13: =SUM(AK13:AN13)
A14: 파생상품손익 | B14: 손익 | C14: 억원 | D14: 파생상품손익 | K14: =SUM(G14:J14) | P14: =SUM(L14:O14) | R14: =IFERROR((VLOOKUP("파생상품이익",BS연결,MATCH(R$1,BS연결H,0),0)-VLOOKUP("파생상품손실",BS연결,MATCH(R$1,BS연결H,0),0))/100,"") | S14: =IFERROR((VLOOKUP("파생상품이익",BS연결,MATCH(S$1,BS연결H,0),0)-VLOOKUP("파생상품손실",BS연결,MATCH(S$1,BS연결H,0),0))/100,"") | T14: =IFERROR((VLOOKUP("파생상품이익",BS연결,MATCH(T$1,BS연결H,0),0)-VLOOKUP("파생상품손실",BS연결,MATCH(T$1,BS연결H,0),0))/100,"") | U14: =SUM(Q14:T14) | W14: =IFERROR((VLOOKUP("파생상품이익",BS연결,MATCH(W$1,BS연결H,0),0)-VLOOKUP("파생상품손실",BS연결,MATCH(W$1,BS연결H,0),0))/100,"") | X14: =IFERROR((VLOOKUP("파생상품이익",BS연결,MATCH(X$1,BS연결H,0),0)-VLOOKUP("파생상품손실",BS연결,MATCH(X$1,BS연결H,0),0))/100,"") | Y14: =IFERROR((VLOOKUP("파생상품이익",BS연결,MATCH(Y$1,BS연결H,0),0)-VLOOKUP("파생상품손실",BS연결,MATCH(Y$1,BS연결H,0),0))/100,"") | Z14: =SUM(V14:Y14) | AC14: =변수!AC25 | AD14: =변수!AD25 | AE14: =SUM(AA14:AD14) | AF14: =변수!AF25 | AG14: =변수!AG25 | AH14: =변수!AH25 | AI14: =변수!AI25 | AJ14: =SUM(AF14:AI14) | AK14: =변수!AK25 | AL14: =변수!AL25 | AM14: =변수!AM25 | AN14: =변수!AN25 | AO14: =SUM(AK14:AN14)
A15: 기타금융손익 | B15: 손익 | C15: 억원 | D15: 기타금융손익(금융손익 잔차) | K15: =SUM(G15:J15) | P15: =SUM(L15:O15) | R15: =IFERROR(R11-R12-R13-R14,"") | S15: =IFERROR(S11-S12-S13-S14,"") | T15: =IFERROR(T11-T12-T13-T14,"") | U15: =SUM(Q15:T15) | Z15: =SUM(V15:Y15) | AC15: =변수!AC26 | AD15: =변수!AD26 | AE15: =SUM(AA15:AD15) | AF15: =변수!AF26 | AG15: =변수!AG26 | AH15: =변수!AH26 | AI15: =변수!AI26 | AJ15: =SUM(AF15:AI15) | AK15: =변수!AK26 | AL15: =변수!AL26 | AM15: =변수!AM26 | AN15: =변수!AN26 | AO15: =SUM(AK15:AN15)
A16: 기타영업외손익 | B16: 손익 | C16: 억원 | D16: 기타영업외손익 | E16: =IFERROR(VLOOKUP($D16,BS연결,MATCH(E$1,BS연결H,0),0)/100,"") | G16: =IFERROR(VLOOKUP($D16,BS연결,MATCH(G$1,BS연결H,0),0)/100,"") | H16: =IFERROR(VLOOKUP($D16,BS연결,MATCH(H$1,BS연결H,0),0)/100,"") | I16: =IFERROR(VLOOKUP($D16,BS연결,MATCH(I$1,BS연결H,0),0)/100,"") | J16: =IFERROR(VLOOKUP($D16,BS연결,MATCH(J$1,BS연결H,0),0)/100,"") | K16: =IFERROR(VLOOKUP($D16,BS연결,MATCH(K$1,BS연결H,0),0)/100,"") | L16: =IFERROR(VLOOKUP($D16,BS연결,MATCH(L$1,BS연결H,0),0)/100,"") | M16: =IFERROR(VLOOKUP($D16,BS연결,MATCH(M$1,BS연결H,0),0)/100,"") | N16: =IFERROR(VLOOKUP($D16,BS연결,MATCH(N$1,BS연결H,0),0)/100,"") | ... AB16: =IFERROR(VLOOKUP($D16,BS연결,MATCH(AB$1,BS연결H,0),0)/100,"") | AC16: =변수!AC27 | AD16: =변수!AD27 | AE16: =SUM(AA16:AD16) | AF16: =변수!AF27 | AG16: =변수!AG27 | AH16: =변수!AH27 | AI16: =변수!AI27 | AJ16: =SUM(AF16:AI16) | AK16: =변수!AK27 | AL16: =변수!AL27 | AM16: =변수!AM27 | AN16: =변수!AN27 | AO16: =SUM(AK16:AN16)
A17: 세전이익 | B17: 손익 | C17: 억원 | D17: 법인세비용차감전계속사업이익 | E17: =IFERROR(VLOOKUP($D17,BS연결,MATCH(E$1,BS연결H,0),0)/100,"") | G17: =IFERROR(VLOOKUP($D17,BS연결,MATCH(G$1,BS연결H,0),0)/100,"") | H17: =IFERROR(VLOOKUP($D17,BS연결,MATCH(H$1,BS연결H,0),0)/100,"") | I17: =IFERROR(VLOOKUP($D17,BS연결,MATCH(I$1,BS연결H,0),0)/100,"") | J17: =IFERROR(VLOOKUP($D17,BS연결,MATCH(J$1,BS연결H,0),0)/100,"") | K17: =IFERROR(VLOOKUP($D17,BS연결,MATCH(K$1,BS연결H,0),0)/100,"") | L17: =IFERROR(VLOOKUP($D17,BS연결,MATCH(L$1,BS연결H,0),0)/100,"") | M17: =IFERROR(VLOOKUP($D17,BS연결,MATCH(M$1,BS연결H,0),0)/100,"") | N17: =IFERROR(VLOOKUP($D17,BS연결,MATCH(N$1,BS연결H,0),0)/100,"") | ... AB17: =IFERROR(VLOOKUP($D17,BS연결,MATCH(AB$1,BS연결H,0),0)/100,"") | AC17: =IFERROR(AC9+AC11+AC16,"") | AD17: =IFERROR(AD9+AD11+AD16,"") | AE17: =SUM(AA17:AD17) | AF17: =IFERROR(AF9+AF11+AF16,"") | AG17: =IFERROR(AG9+AG11+AG16,"") | AH17: =IFERROR(AH9+AH11+AH16,"") | AI17: =IFERROR(AI9+AI11+AI16,"") | AJ17: =SUM(AF17:AI17) | AK17: =IFERROR(AK9+AK11+AK16,"") | AL17: =IFERROR(AL9+AL11+AL16,"") | AM17: =IFERROR(AM9+AM11+AM16,"") | AN17: =IFERROR(AN9+AN11+AN16,"") | AO17: =SUM(AK17:AN17)
A18: 법인세비용 | B18: 손익 | C18: 억원 | D18: 법인세비용 | G18: =IFERROR(VLOOKUP($D18,BS연결,MATCH(G$1,BS연결H,0),0)/100,"") | I18: =IFERROR(VLOOKUP($D18,BS연결,MATCH(I$1,BS연결H,0),0)/100,"") | J18: =IFERROR(VLOOKUP($D18,BS연결,MATCH(J$1,BS연결H,0),0)/100,"") | K18: =SUM(G18:J18) | L18: =IFERROR(VLOOKUP($D18,BS연결,MATCH(L$1,BS연결H,0),0)/100,"") | M18: =IFERROR(VLOOKUP($D18,BS연결,MATCH(M$1,BS연결H,0),0)/100,"") | N18: =IFERROR(VLOOKUP($D18,BS연결,MATCH(N$1,BS연결H,0),0)/100,"") | O18: =IFERROR(VLOOKUP($D18,BS연결,MATCH(O$1,BS연결H,0),0)/100,"") | P18: =IFERROR(VLOOKUP($D18,BS연결,MATCH(P$1,BS연결H,0),0)/100,"") | Q18: =IFERROR(VLOOKUP($D18,BS연결,MATCH(Q$1,BS연결H,0),0)/100,"") | R18: =IFERROR(VLOOKUP($D18,BS연결,MATCH(R$1,BS연결H,0),0)/100,"") | S18: =IFERROR(VLOOKUP($D18,BS연결,MATCH(S$1,BS연결H,0),0)/100,"") | ... AB18: =IFERROR(VLOOKUP($D18,BS연결,MATCH(AB$1,BS연결H,0),0)/100,"") | AC18: =IFERROR(AC17*변수!AC28,"") | AD18: =IFERROR(AD17*변수!AD28,"") | AE18: =SUM(AA18:AD18) | AF18: =IFERROR(AF17*변수!AF28,"") | AG18: =IFERROR(AG17*변수!AG28,"") | AH18: =IFERROR(AH17*변수!AH28,"") | AI18: =IFERROR(AI17*변수!AI28,"") | AJ18: =SUM(AF18:AI18) | AK18: =IFERROR(AK17*변수!AK28,"") | AL18: =IFERROR(AL17*변수!AL28,"") | AM18: =IFERROR(AM17*변수!AM28,"") | AN18: =IFERROR(AN17*변수!AN28,"") | AO18: =SUM(AK18:AN18)
A19: 당기순이익 | B19: 손익 | C19: 억원 | D19: 당기순이익 | E19: =IFERROR(VLOOKUP($D19,BS연결,MATCH(E$1,BS연결H,0),0)/100,"") | G19: =IFERROR(VLOOKUP($D19,BS연결,MATCH(G$1,BS연결H,0),0)/100,"") | H19: =IFERROR(VLOOKUP($D19,BS연결,MATCH(H$1,BS연결H,0),0)/100,"") | I19: =IFERROR(VLOOKUP($D19,BS연결,MATCH(I$1,BS연결H,0),0)/100,"") | J19: =IFERROR(VLOOKUP($D19,BS연결,MATCH(J$1,BS연결H,0),0)/100,"") | K19: =IFERROR(VLOOKUP($D19,BS연결,MATCH(K$1,BS연결H,0),0)/100,"") | L19: =IFERROR(VLOOKUP($D19,BS연결,MATCH(L$1,BS연결H,0),0)/100,"") | M19: =IFERROR(VLOOKUP($D19,BS연결,MATCH(M$1,BS연결H,0),0)/100,"") | N19: =IFERROR(VLOOKUP($D19,BS연결,MATCH(N$1,BS연결H,0),0)/100,"") | ... AB19: =IFERROR(VLOOKUP($D19,BS연결,MATCH(AB$1,BS연결H,0),0)/100,"") | AC19: =IFERROR(AC17-AC18,"") | AD19: =IFERROR(AD17-AD18,"") | AE19: =SUM(AA19:AD19) | AF19: =IFERROR(AF17-AF18,"") | AG19: =IFERROR(AG17-AG18,"") | AH19: =IFERROR(AH17-AH18,"") | AI19: =IFERROR(AI17-AI18,"") | AJ19: =SUM(AF19:AI19) | AK19: =IFERROR(AK17-AK18,"") | AL19: =IFERROR(AL17-AL18,"") | AM19: =IFERROR(AM17-AM18,"") | AN19: =IFERROR(AN17-AN18,"") | AO19: =SUM(AK19:AN19)
A20: 지배주주순이익 | B20: 손익 | C20: 억원 | D20: (지배주주지분)당기순이익 | E20: =IFERROR(VLOOKUP($D20,BS연결,MATCH(E$1,BS연결H,0),0)/100,"") | G20: =IFERROR(VLOOKUP($D20,BS연결,MATCH(G$1,BS연결H,0),0)/100,"") | H20: =IFERROR(VLOOKUP($D20,BS연결,MATCH(H$1,BS연결H,0),0)/100,"") | I20: =IFERROR(VLOOKUP($D20,BS연결,MATCH(I$1,BS연결H,0),0)/100,"") | J20: =IFERROR(VLOOKUP($D20,BS연결,MATCH(J$1,BS연결H,0),0)/100,"") | K20: =IFERROR(VLOOKUP($D20,BS연결,MATCH(K$1,BS연결H,0),0)/100,"") | L20: =IFERROR(VLOOKUP($D20,BS연결,MATCH(L$1,BS연결H,0),0)/100,"") | M20: =IFERROR(VLOOKUP($D20,BS연결,MATCH(M$1,BS연결H,0),0)/100,"") | N20: =IFERROR(VLOOKUP($D20,BS연결,MATCH(N$1,BS연결H,0),0)/100,"") | ... R20: =IFERROR(VLOOKUP($D20,BS연결,MATCH(R$1,BS연결H,0),0)/100,"") | S20: -11.27 | T20: -33.51 | U20: =SUM(Q20:T20) | V20: =IFERROR(VLOOKUP($D20,BS연결,MATCH(V$1,BS연결H,0),0)/100,"") | W20: =IFERROR(VLOOKUP($D20,BS연결,MATCH(W$1,BS연결H,0),0)/100,"") | X20: =IFERROR(VLOOKUP($D20,BS연결,MATCH(X$1,BS연결H,0),0)/100,"") | Y20: =IFERROR(VLOOKUP($D20,BS연결,MATCH(Y$1,BS연결H,0),0)/100,"") | Z20: =IFERROR(VLOOKUP($D20,BS연결,MATCH(Z$1,BS연결H,0),0)/100,"") | AA20: =IFERROR(VLOOKUP($D20,BS연결,MATCH(AA$1,BS연결H,0),0)/100,"") | AB20: =IFERROR(VLOOKUP($D20,BS연결,MATCH(AB$1,BS연결H,0),0)/100,"") | AC20: =IFERROR(AC19*변수!AC29,"") | AD20: =IFERROR(AD19*변수!AD29,"") | AE20: =SUM(AA20:AD20) | AF20: =IFERROR(AF19*변수!AF29,"") | AG20: =IFERROR(AG19*변수!AG29,"") | AH20: =IFERROR(AH19*변수!AH29,"") | AI20: =IFERROR(AI19*변수!AI29,"") | AJ20: =SUM(AF20:AI20) | AK20: =IFERROR(AK19*변수!AK29,"") | AL20: =IFERROR(AL19*변수!AL29,"") | AM20: =IFERROR(AM19*변수!AM29,"") | AN20: =IFERROR(AN19*변수!AN29,"") | AO20: =SUM(AK20:AN20)
A21: 감가상각비 | B21: 손익 | C21: 억원 | D21: 감가상각비 | E21: =IFERROR(VLOOKUP($D21,BS연결,MATCH(E$1,BS연결H,0),0)/100,"") | G21: =IFERROR(VLOOKUP($D21,BS연결,MATCH(G$1,BS연결H,0),0)/100,"") | H21: =IFERROR(VLOOKUP($D21,BS연결,MATCH(H$1,BS연결H,0),0)/100,"") | I21: =IFERROR(VLOOKUP($D21,BS연결,MATCH(I$1,BS연결H,0),0)/100,"") | J21: =IFERROR(VLOOKUP($D21,BS연결,MATCH(J$1,BS연결H,0),0)/100,"") | K21: =IFERROR(VLOOKUP($D21,BS연결,MATCH(K$1,BS연결H,0),0)/100,"") | L21: =IFERROR(VLOOKUP($D21,BS연결,MATCH(L$1,BS연결H,0),0)/100,"") | M21: =IFERROR(VLOOKUP($D21,BS연결,MATCH(M$1,BS연결H,0),0)/100,"") | P21: =SUM(L21:O21) | U21: =SUM(Q21:T21) | Z21: =SUM(V21:Y21) | AC21: =변수!AC30 | AD21: =변수!AD30 | AE21: =SUM(AA21:AD21) | AF21: =변수!AF30 | AG21: =변수!AG30 | AH21: =변수!AH30 | AI21: =변수!AI30 | AJ21: =SUM(AF21:AI21) | AK21: =변수!AK30 | AL21: =변수!AL30 | AM21: =변수!AM30 | AN21: =변수!AN30 | AO21: =SUM(AK21:AN21)
A22: EBITDA | B22: 손익 | C22: 억원 | D22: EBITDA | E22: -49.35 | G22: -13.65 | H22: -13.04 | I22: -10.67 | J22: 0.73 | K22: =SUM(G22:J22) | L22: 24.19 | M22: 25.46 | P22: =SUM(L22:O22) | U22: =SUM(Q22:T22) | Z22: =SUM(V22:Y22) | AC22: =IFERROR(AC9+AC21,"") | AD22: =IFERROR(AD9+AD21,"") | AE22: =SUM(AA22:AD22) | AF22: =IFERROR(AF9+AF21,"") | AG22: =IFERROR(AG9+AG21,"") | AH22: =IFERROR(AH9+AH21,"") | AI22: =IFERROR(AI9+AI21,"") | AJ22: =SUM(AF22:AI22) | AK22: =IFERROR(AK9+AK21,"") | AL22: =IFERROR(AL9+AL21,"") | AM22: =IFERROR(AM9+AM21,"") | AN22: =IFERROR(AN9+AN21,"") | AO22: =SUM(AK22:AN22)
A23: 자산총계 | B23: 재무상태 | C23: 억원 | D23: 자산총계 | E23: =IFERROR(VLOOKUP($D23,BS연결,MATCH(E$1,BS연결H,0),0)/100,"") | F23: =IFERROR(VLOOKUP($D23,BS연결,MATCH(F$1,BS연결H,0),0)/100,"") | G23: =IFERROR(VLOOKUP($D23,BS연결,MATCH(G$1,BS연결H,0),0)/100,"") | H23: =IFERROR(VLOOKUP($D23,BS연결,MATCH(H$1,BS연결H,0),0)/100,"") | I23: =IFERROR(VLOOKUP($D23,BS연결,MATCH(I$1,BS연결H,0),0)/100,"") | J23: =IFERROR(VLOOKUP($D23,BS연결,MATCH(J$1,BS연결H,0),0)/100,"") | K23: =IFERROR(VLOOKUP($D23,BS연결,MATCH(K$1,BS연결H,0),0)/100,"") | L23: =IFERROR(VLOOKUP($D23,BS연결,MATCH(L$1,BS연결H,0),0)/100,"") | ... AB23: =IFERROR(VLOOKUP($D23,BS연결,MATCH(AB$1,BS연결H,0),0)/100,"") | AC23: =IFERROR(AC24+AC25,"") | AD23: =IFERROR(AD24+AD25,"") | AE23: =AD23 | AF23: =IFERROR(AF24+AF25,"") | AG23: =IFERROR(AG24+AG25,"") | AH23: =IFERROR(AH24+AH25,"") | AI23: =IFERROR(AI24+AI25,"") | AJ23: =AI23 | AK23: =IFERROR(AK24+AK25,"") | AL23: =IFERROR(AL24+AL25,"") | AM23: =IFERROR(AM24+AM25,"") | AN23: =IFERROR(AN24+AN25,"") | AO23: =AN23
A24: 부채총계 | B24: 재무상태 | C24: 억원 | D24: 부채총계 | E24: =IFERROR(VLOOKUP($D24,BS연결,MATCH(E$1,BS연결H,0),0)/100,"") | F24: =IFERROR(VLOOKUP($D24,BS연결,MATCH(F$1,BS연결H,0),0)/100,"") | G24: =IFERROR(VLOOKUP($D24,BS연결,MATCH(G$1,BS연결H,0),0)/100,"") | H24: =IFERROR(VLOOKUP($D24,BS연결,MATCH(H$1,BS연결H,0),0)/100,"") | I24: =IFERROR(VLOOKUP($D24,BS연결,MATCH(I$1,BS연결H,0),0)/100,"") | J24: =IFERROR(VLOOKUP($D24,BS연결,MATCH(J$1,BS연결H,0),0)/100,"") | K24: =IFERROR(VLOOKUP($D24,BS연결,MATCH(K$1,BS연결H,0),0)/100,"") | L24: =IFERROR(VLOOKUP($D24,BS연결,MATCH(L$1,BS연결H,0),0)/100,"") | ... AB24: =IFERROR(VLOOKUP($D24,BS연결,MATCH(AB$1,BS연결H,0),0)/100,"") | AC24: =IFERROR(AB24*(1+변수!AC31),"") | AD24: =IFERROR(AC24*(1+변수!AD31),"") | AE24: =AD24 | AF24: =IFERROR(AD24*(1+변수!AF31),"") | AG24: =IFERROR(AF24*(1+변수!AG31),"") | AH24: =IFERROR(AG24*(1+변수!AH31),"") | AI24: =IFERROR(AH24*(1+변수!AI31),"") | AJ24: =AI24 | AK24: =IFERROR(AI24*(1+변수!AK31),"") | AL24: =IFERROR(AK24*(1+변수!AL31),"") | AM24: =IFERROR(AL24*(1+변수!AM31),"") | AN24: =IFERROR(AM24*(1+변수!AN31),"") | AO24: =AN24
A25: 자본총계 | B25: 재무상태 | C25: 억원 | D25: 자본총계 | E25: =IFERROR(VLOOKUP($D25,BS연결,MATCH(E$1,BS연결H,0),0)/100,"") | F25: =IFERROR(VLOOKUP($D25,BS연결,MATCH(F$1,BS연결H,0),0)/100,"") | G25: =IFERROR(VLOOKUP($D25,BS연결,MATCH(G$1,BS연결H,0),0)/100,"") | H25: =IFERROR(VLOOKUP($D25,BS연결,MATCH(H$1,BS연결H,0),0)/100,"") | I25: =IFERROR(VLOOKUP($D25,BS연결,MATCH(I$1,BS연결H,0),0)/100,"") | J25: =IFERROR(VLOOKUP($D25,BS연결,MATCH(J$1,BS연결H,0),0)/100,"") | K25: =IFERROR(VLOOKUP($D25,BS연결,MATCH(K$1,BS연결H,0),0)/100,"") | L25: =IFERROR(VLOOKUP($D25,BS연결,MATCH(L$1,BS연결H,0),0)/100,"") | ... AB25: =IFERROR(VLOOKUP($D25,BS연결,MATCH(AB$1,BS연결H,0),0)/100,"") | AC25: =IFERROR(AB25+AC19-변수!AC32,"") | AD25: =IFERROR(AC25+AD19-변수!AD32,"") | AE25: =AD25 | AF25: =IFERROR(AD25+AF19-변수!AF32,"") | AG25: =IFERROR(AF25+AG19-변수!AG32,"") | AH25: =IFERROR(AG25+AH19-변수!AH32,"") | AI25: =IFERROR(AH25+AI19-변수!AI32,"") | AJ25: =AI25 | AK25: =IFERROR(AI25+AK19-변수!AK32,"") | AL25: =IFERROR(AK25+AL19-변수!AL32,"") | AM25: =IFERROR(AL25+AM19-변수!AM32,"") | AN25: =IFERROR(AM25+AN19-변수!AN32,"") | AO25: =AN25
A26: 지배주주지분 | B26: 재무상태 | C26: 억원 | D26: 지배주주지분 | E26: =IFERROR(VLOOKUP($D26,BS연결,MATCH(E$1,BS연결H,0),0)/100,"") | F26: =IFERROR(VLOOKUP($D26,BS연결,MATCH(F$1,BS연결H,0),0)/100,"") | G26: =IFERROR(VLOOKUP($D26,BS연결,MATCH(G$1,BS연결H,0),0)/100,"") | H26: =IFERROR(VLOOKUP($D26,BS연결,MATCH(H$1,BS연결H,0),0)/100,"") | I26: =IFERROR(VLOOKUP($D26,BS연결,MATCH(I$1,BS연결H,0),0)/100,"") | J26: =IFERROR(VLOOKUP($D26,BS연결,MATCH(J$1,BS연결H,0),0)/100,"") | K26: =IFERROR(VLOOKUP($D26,BS연결,MATCH(K$1,BS연결H,0),0)/100,"") | L26: =IFERROR(VLOOKUP($D26,BS연결,MATCH(L$1,BS연결H,0),0)/100,"") | ... AB26: =IFERROR(VLOOKUP($D26,BS연결,MATCH(AB$1,BS연결H,0),0)/100,"") | AC26: =IFERROR(AB26+AC20-변수!AC33,"") | AD26: =IFERROR(AC26+AD20-변수!AD33,"") | AE26: =AD26 | AF26: =IFERROR(AD26+AF20-변수!AF33,"") | AG26: =IFERROR(AF26+AG20-변수!AG33,"") | AH26: =IFERROR(AG26+AH20-변수!AH33,"") | AI26: =IFERROR(AH26+AI20-변수!AI33,"") | AJ26: =AI26 | AK26: =IFERROR(AI26+AK20-변수!AK33,"") | AL26: =IFERROR(AK26+AL20-변수!AL33,"") | AM26: =IFERROR(AL26+AM20-변수!AM33,"") | AN26: =IFERROR(AM26+AN20-변수!AN33,"") | AO26: =AN26
A27: 총차입금 | B27: 재무상태 | C27: 억원 | D27: 총차입금 | E27: =IFERROR(VLOOKUP($D27,BS연결,MATCH(E$1,BS연결H,0),0)/100,"") | F27: =IFERROR(VLOOKUP($D27,BS연결,MATCH(F$1,BS연결H,0),0)/100,"") | G27: =IFERROR(VLOOKUP($D27,BS연결,MATCH(G$1,BS연결H,0),0)/100,"") | H27: =IFERROR(VLOOKUP($D27,BS연결,MATCH(H$1,BS연결H,0),0)/100,"") | I27: =IFERROR(VLOOKUP($D27,BS연결,MATCH(I$1,BS연결H,0),0)/100,"") | J27: =IFERROR(VLOOKUP($D27,BS연결,MATCH(J$1,BS연결H,0),0)/100,"") | K27: =IFERROR(VLOOKUP($D27,BS연결,MATCH(K$1,BS연결H,0),0)/100,"") | L27: =IFERROR(VLOOKUP($D27,BS연결,MATCH(L$1,BS연결H,0),0)/100,"") | ... AB27: =IFERROR(VLOOKUP($D27,BS연결,MATCH(AB$1,BS연결H,0),0)/100,"") | AC27: =IFERROR(AB27*(1+변수!AC34),"") | AD27: =IFERROR(AC27*(1+변수!AD34),"") | AE27: =AD27 | AF27: =IFERROR(AD27*(1+변수!AF34),"") | AG27: =IFERROR(AF27*(1+변수!AG34),"") | AH27: =IFERROR(AG27*(1+변수!AH34),"") | AI27: =IFERROR(AH27*(1+변수!AI34),"") | AJ27: =AI27 | AK27: =IFERROR(AI27*(1+변수!AK34),"") | AL27: =IFERROR(AK27*(1+변수!AL34),"") | AM27: =IFERROR(AL27*(1+변수!AM34),"") | AN27: =IFERROR(AM27*(1+변수!AN34),"") | AO27: =AN27
A28: 순차입금 | B28: 재무상태 | C28: 억원 | D28: 순차입금 | E28: =IFERROR(VLOOKUP($D28,BS연결,MATCH(E$1,BS연결H,0),0)/100,"") | F28: =IFERROR(VLOOKUP($D28,BS연결,MATCH(F$1,BS연결H,0),0)/100,"") | G28: =IFERROR(VLOOKUP($D28,BS연결,MATCH(G$1,BS연결H,0),0)/100,"") | H28: =IFERROR(VLOOKUP($D28,BS연결,MATCH(H$1,BS연결H,0),0)/100,"") | I28: =IFERROR(VLOOKUP($D28,BS연결,MATCH(I$1,BS연결H,0),0)/100,"") | J28: =IFERROR(VLOOKUP($D28,BS연결,MATCH(J$1,BS연결H,0),0)/100,"") | K28: =IFERROR(VLOOKUP($D28,BS연결,MATCH(K$1,BS연결H,0),0)/100,"") | L28: =IFERROR(VLOOKUP($D28,BS연결,MATCH(L$1,BS연결H,0),0)/100,"") | ... AB28: =IFERROR(VLOOKUP($D28,BS연결,MATCH(AB$1,BS연결H,0),0)/100,"") | AC28: =IFERROR(AB28*(1+변수!AC35),"") | AD28: =IFERROR(AC28*(1+변수!AD35),"") | AE28: =AD28 | AF28: =IFERROR(AD28*(1+변수!AF35),"") | AG28: =IFERROR(AF28*(1+변수!AG35),"") | AH28: =IFERROR(AG28*(1+변수!AH35),"") | AI28: =IFERROR(AH28*(1+변수!AI35),"") | AJ28: =AI28 | AK28: =IFERROR(AI28*(1+변수!AK35),"") | AL28: =IFERROR(AK28*(1+변수!AL35),"") | AM28: =IFERROR(AL28*(1+변수!AM35),"") | AN28: =IFERROR(AM28*(1+변수!AN35),"") | AO28: =AN28
A29: 이자발생자산 | B29: 재무상태 | C29: 억원 | D29: 이자발생자산 | E29: =IFERROR(VLOOKUP($D29,BS연결,MATCH(E$1,BS연결H,0),0)/100,"") | F29: =IFERROR(VLOOKUP($D29,BS연결,MATCH(F$1,BS연결H,0),0)/100,"") | G29: =IFERROR(VLOOKUP($D29,BS연결,MATCH(G$1,BS연결H,0),0)/100,"") | H29: =IFERROR(VLOOKUP($D29,BS연결,MATCH(H$1,BS연결H,0),0)/100,"") | I29: =IFERROR(VLOOKUP($D29,BS연결,MATCH(I$1,BS연결H,0),0)/100,"") | J29: =IFERROR(VLOOKUP($D29,BS연결,MATCH(J$1,BS연결H,0),0)/100,"") | K29: =IFERROR(VLOOKUP($D29,BS연결,MATCH(K$1,BS연결H,0),0)/100,"") | L29: =IFERROR(VLOOKUP($D29,BS연결,MATCH(L$1,BS연결H,0),0)/100,"") | ... AB29: =IFERROR(VLOOKUP($D29,BS연결,MATCH(AB$1,BS연결H,0),0)/100,"") | AC29: =IFERROR(AB29*(1+변수!AC36),"") | AD29: =IFERROR(AC29*(1+변수!AD36),"") | AE29: =AD29 | AF29: =IFERROR(AD29*(1+변수!AF36),"") | AG29: =IFERROR(AF29*(1+변수!AG36),"") | AH29: =IFERROR(AG29*(1+변수!AH36),"") | AI29: =IFERROR(AH29*(1+변수!AI36),"") | AJ29: =AI29 | AK29: =IFERROR(AI29*(1+변수!AK36),"") | AL29: =IFERROR(AK29*(1+변수!AL36),"") | AM29: =IFERROR(AL29*(1+변수!AM36),"") | AN29: =IFERROR(AM29*(1+변수!AN36),"") | AO29: =AN29
A30: 현금및현금성자산 | B30: 재무상태 | C30: 억원 | D30: 현금및현금성자산 | E30: =IFERROR(VLOOKUP($D30,BS연결,MATCH(E$1,BS연결H,0),0)/100,"") | F30: =IFERROR(VLOOKUP($D30,BS연결,MATCH(F$1,BS연결H,0),0)/100,"") | G30: =IFERROR(VLOOKUP($D30,BS연결,MATCH(G$1,BS연결H,0),0)/100,"") | H30: =IFERROR(VLOOKUP($D30,BS연결,MATCH(H$1,BS연결H,0),0)/100,"") | I30: =IFERROR(VLOOKUP($D30,BS연결,MATCH(I$1,BS연결H,0),0)/100,"") | J30: =IFERROR(VLOOKUP($D30,BS연결,MATCH(J$1,BS연결H,0),0)/100,"") | K30: =IFERROR(VLOOKUP($D30,BS연결,MATCH(K$1,BS연결H,0),0)/100,"") | L30: =IFERROR(VLOOKUP($D30,BS연결,MATCH(L$1,BS연결H,0),0)/100,"") | ... AB30: =IFERROR(VLOOKUP($D30,BS연결,MATCH(AB$1,BS연결H,0),0)/100,"") | AE30: =AD30 | AJ30: =AI30 | AO30: =AN30
A31: CAPEX | B31: 현금흐름 | C31: 억원 | D31: CAPEX | E31: =IFERROR(VLOOKUP($D31,BS연결,MATCH(E$1,BS연결H,0),0)/100,"") | G31: =IFERROR(VLOOKUP($D31,BS연결,MATCH(G$1,BS연결H,0),0)/100,"") | H31: =IFERROR(VLOOKUP($D31,BS연결,MATCH(H$1,BS연결H,0),0)/100,"") | I31: =IFERROR(VLOOKUP($D31,BS연결,MATCH(I$1,BS연결H,0),0)/100,"") | J31: =IFERROR(VLOOKUP($D31,BS연결,MATCH(J$1,BS연결H,0),0)/100,"") | K31: =IFERROR(VLOOKUP($D31,BS연결,MATCH(K$1,BS연결H,0),0)/100,"") | L31: =IFERROR(VLOOKUP($D31,BS연결,MATCH(L$1,BS연결H,0),0)/100,"") | M31: =IFERROR(VLOOKUP($D31,BS연결,MATCH(M$1,BS연결H,0),0)/100,"") | N31: =IFERROR(VLOOKUP($D31,BS연결,MATCH(N$1,BS연결H,0),0)/100,"") | ... AB31: =IFERROR(VLOOKUP($D31,BS연결,MATCH(AB$1,BS연결H,0),0)/100,"") | AC31: =IFERROR(X31*(1+변수!AC38),"") | AD31: =IFERROR(Y31*(1+변수!AD38),"") | AE31: =SUM(AA31:AD31) | AF31: =IFERROR(AA31*(1+변수!AF38),"") | AG31: =IFERROR(AB31*(1+변수!AG38),"") | AH31: =IFERROR(AC31*(1+변수!AH38),"") | AI31: =IFERROR(AD31*(1+변수!AI38),"") | AJ31: =SUM(AF31:AI31) | AK31: =IFERROR(AF31*(1+변수!AK38),"") | AL31: =IFERROR(AG31*(1+변수!AL38),"") | AM31: =IFERROR(AH31*(1+변수!AM38),"") | AN31: =IFERROR(AI31*(1+변수!AN38),"") | AO31: =SUM(AK31:AN31)
A32: 영업활동현금흐름 | B32: 현금흐름 | C32: 억원 | D32: 영업활동으로인한현금흐름 | E32: =IFERROR(VLOOKUP($D32,BS연결,MATCH(E$1,BS연결H,0),0)/100,"") | G32: =IFERROR(VLOOKUP($D32,BS연결,MATCH(G$1,BS연결H,0),0)/100,"") | H32: =IFERROR(VLOOKUP($D32,BS연결,MATCH(H$1,BS연결H,0),0)/100,"") | I32: =IFERROR(VLOOKUP($D32,BS연결,MATCH(I$1,BS연결H,0),0)/100,"") | J32: =IFERROR(VLOOKUP($D32,BS연결,MATCH(J$1,BS연결H,0),0)/100,"") | K32: =IFERROR(VLOOKUP($D32,BS연결,MATCH(K$1,BS연결H,0),0)/100,"") | L32: =IFERROR(VLOOKUP($D32,BS연결,MATCH(L$1,BS연결H,0),0)/100,"") | M32: =IFERROR(VLOOKUP($D32,BS연결,MATCH(M$1,BS연결H,0),0)/100,"") | N32: =IFERROR(VLOOKUP($D32,BS연결,MATCH(N$1,BS연결H,0),0)/100,"") | ... AB32: =IFERROR(VLOOKUP($D32,BS연결,MATCH(AB$1,BS연결H,0),0)/100,"") | AE32: =SUM(AA32:AD32) | AJ32: =SUM(AF32:AI32) | AO32: =SUM(AK32:AN32)
A33: 주식수 | B33: 주당 | C33: 백만주 | D33: 유통주식수 | E33: 31.831056 | F33: =E33 | G33: 31.831056 | H33: 31.831056 | I33: 31.831056 | J33: 31.831056 | K33: =J33 | L33: 31.831056 | M33: 31.831056 | N33: 31.831056 | O33: 31.831056 | P33: =O33 | Q33: 31.831056 | R33: 31.831056 | S33: 31.831056 | T33: 31.831056 | U33: =T33 | V33: 31.831056 | W33: 35.113107 | X33: 35.933616 | Y33: 35.93 | Z33: =Y33 | AA33: 35.93 | AB33: 35.93 | AC33: =IFERROR(AB33*(1+변수!AC40),"") | AD33: =IFERROR(AC33*(1+변수!AD40),"") | AE33: =AD33 | AF33: =IFERROR(AD33*(1+변수!AF40),"") | AG33: =IFERROR(AF33*(1+변수!AG40),"") | AH33: =IFERROR(AG33*(1+변수!AH40),"") | AI33: =IFERROR(AH33*(1+변수!AI40),"") | AJ33: =AI33 | AK33: =IFERROR(AI33*(1+변수!AK40),"") | AL33: =IFERROR(AK33*(1+변수!AL40),"") | AM33: =IFERROR(AL33*(1+변수!AM40),"") | AN33: =IFERROR(AM33*(1+변수!AN40),"") | AO33: =AN33
A34: EPS | B34: 주당 | C34: 원 | D34: EPS | E34: =IFERROR(E20*100/E33,"") | G34: =IFERROR(G20*100/G33,"") | H34: =IFERROR(H20*100/H33,"") | I34: =IFERROR(I20*100/I33,"") | J34: =IFERROR(J20*100/J33,"") | K34: =SUM(G34:J34) | L34: =IFERROR(L20*100/L33,"") | M34: =IFERROR(M20*100/M33,"") | N34: =IFERROR(N20*100/N33,"") | O34: =IFERROR(O20*100/O33,"") | P34: =SUM(L34:O34) | Q34: =IFERROR(Q20*100/Q33,"") | R34: =IFERROR(R20*100/R33,"") | S34: =IFERROR(S20*100/S33,"") | T34: =IFERROR(T20*100/T33,"") | U34: =SUM(Q34:T34) | V34: =IFERROR(V20*100/V33,"") | W34: =IFERROR(W20*100/W33,"") | X34: =IFERROR(X20*100/X33,"") | Y34: =IFERROR(Y20*100/Y33,"") | Z34: =SUM(V34:Y34) | AA34: =IFERROR(AA20*100/AA33,"") | AB34: =IFERROR(AB20*100/AB33,"") | AC34: =IFERROR(AC20*100/AC33,"") | AD34: =IFERROR(AD20*100/AD33,"") | AE34: =SUM(AA34:AD34) | AF34: =IFERROR(AF20*100/AF33,"") | AG34: =IFERROR(AG20*100/AG33,"") | AH34: =IFERROR(AH20*100/AH33,"") | AI34: =IFERROR(AI20*100/AI33,"") | AJ34: =SUM(AF34:AI34) | AK34: =IFERROR(AK20*100/AK33,"") | AL34: =IFERROR(AL20*100/AL33,"") | AM34: =IFERROR(AM20*100/AM33,"") | AN34: =IFERROR(AN20*100/AN33,"") | AO34: =SUM(AK34:AN34)
A35: BPS | B35: 주당 | C35: 원 | D35: BPS | E35: =IFERROR(E26*100/E33,"") | F35: =E35 | G35: =IFERROR(G26*100/G33,"") | H35: =IFERROR(H26*100/H33,"") | I35: =IFERROR(I26*100/I33,"") | J35: =IFERROR(J26*100/J33,"") | K35: =J35 | L35: =IFERROR(L26*100/L33,"") | M35: =IFERROR(M26*100/M33,"") | N35: =IFERROR(N26*100/N33,"") | O35: =IFERROR(O26*100/O33,"") | P35: =O35 | Q35: =IFERROR(Q26*100/Q33,"") | R35: =IFERROR(R26*100/R33,"") | S35: =IFERROR(S26*100/S33,"") | T35: =IFERROR(T26*100/T33,"") | U35: =T35 | V35: =IFERROR(V26*100/V33,"") | W35: =IFERROR(W26*100/W33,"") | X35: =IFERROR(X26*100/X33,"") | Y35: =IFERROR(Y26*100/Y33,"") | Z35: =Y35 | AA35: =IFERROR(AA26*100/AA33,"") | AB35: =IFERROR(AB26*100/AB33,"") | AC35: =IFERROR(AC26*100/AC33,"") | AD35: =IFERROR(AD26*100/AD33,"") | AE35: =AD35 | AF35: =IFERROR(AF26*100/AF33,"") | AG35: =IFERROR(AG26*100/AG33,"") | AH35: =IFERROR(AH26*100/AH33,"") | AI35: =IFERROR(AI26*100/AI33,"") | AJ35: =AI35 | AK35: =IFERROR(AK26*100/AK33,"") | AL35: =IFERROR(AL26*100/AL33,"") | AM35: =IFERROR(AM26*100/AM33,"") | AN35: =IFERROR(AN26*100/AN33,"") | AO35: =AN35
A36: DPS | B36: 주당 | C36: 원 | D36: DPS(보통주) | E36: 0 | F36: 0 | J36: 0 | K36: =SUM(G36:J36) | O36: 0 | P36: =SUM(L36:O36) | T36: 0 | U36: =SUM(Q36:T36) | Y36: 0 | Z36: =SUM(V36:Y36) | AD36: =변수!AD41 | AE36: =SUM(AA36:AD36) | AI36: =변수!AI41 | AJ36: =SUM(AF36:AI36) | AN36: =변수!AN41 | AO36: =SUM(AK36:AN36)
A37: PER | B37: 주당 | C37: 배 | D37: PER | F37: =E37 | K37: =J37 | N37: =IFERROR(변수!N18/(J34+L34+M34+N34),"") | O37: =IFERROR(변수!O18/(L34+M34+N34+O34),"") | P37: =O37 | Q37: =IFERROR(변수!Q18/(M34+N34+O34+Q34),"") | R37: =IFERROR(변수!R18/(N34+O34+Q34+R34),"") | S37: =IFERROR(변수!S18/(O34+Q34+R34+S34),"") | U37: =T37 | Z37: =Y37 | AB37: =IFERROR(변수!AB18/(X34+Y34+AA34+AB34),"") | AE37: =AD37 | AJ37: =AI37 | AO37: =AN37
A38: PBR | B38: 주당 | C38: 배 | D38: PBR | E38: =IFERROR(변수!E18/E35,"") | F38: =E38 | G38: =IFERROR(변수!G18/G35,"") | H38: =IFERROR(변수!H18/H35,"") | I38: =IFERROR(변수!I18/I35,"") | J38: =IFERROR(변수!J18/J35,"") | K38: =J38 | L38: =IFERROR(변수!L18/L35,"") | M38: =IFERROR(변수!M18/M35,"") | N38: =IFERROR(변수!N18/N35,"") | O38: =IFERROR(변수!O18/O35,"") | P38: =O38 | Q38: =IFERROR(변수!Q18/Q35,"") | R38: =IFERROR(변수!R18/R35,"") | S38: =IFERROR(변수!S18/S35,"") | T38: =IFERROR(변수!T18/T35,"") | U38: =T38 | V38: =IFERROR(변수!V18/V35,"") | W38: =IFERROR(변수!W18/W35,"") | X38: =IFERROR(변수!X18/X35,"") | Y38: =IFERROR(변수!Y18/Y35,"") | Z38: =Y38 | AA38: =IFERROR(변수!AA18/AA35,"") | AB38: =IFERROR(변수!AB18/AB35,"") | AC38: =IFERROR(변수!$D$44/AC35,"") | AD38: =IFERROR(변수!$D$44/AD35,"") | AE38: =AD38 | AF38: =IFERROR(변수!$D$44/AF35,"") | AG38: =IFERROR(변수!$D$44/AG35,"") | AH38: =IFERROR(변수!$D$44/AH35,"") | AI38: =IFERROR(변수!$D$44/AI35,"") | AJ38: =AI38 | AK38: =IFERROR(변수!$D$44/AK35,"") | AL38: =IFERROR(변수!$D$44/AL35,"") | AM38: =IFERROR(변수!$D$44/AM35,"") | AN38: =IFERROR(변수!$D$44/AN35,"") | AO38: =AN38
A39: 매출전사 | B39: 사업부 | C39: 억원 | D39: 매출 전사(부문 미분리) | E39: 145.35 | G39: 125 | H39: 117.31 | I39: 127.98 | J39: 157.27 | K39: =SUM(G39:J39) | L39: 197.66 | M39: 170.99 | N39: 173.03 | O39: 175.47 | P39: =SUM(L39:O39) | Q39: 167.4 | R39: 140.64 | S39: 129.24 | T39: 176.7 | U39: =SUM(Q39:T39) | V39: 103.29 | W39: 146.2 | X39: 171.56 | Y39: 177.73 | Z39: =SUM(V39:Y39) | AA39: 212.48 | AB39: 188.86 | AC39: =IFERROR(AC5,"") | AD39: =IFERROR(AD5,"") | AE39: =SUM(AA39:AD39) | AF39: =IFERROR(AF5,"") | AG39: =IFERROR(AG5,"") | AH39: =IFERROR(AH5,"") | AI39: =IFERROR(AI5,"") | AJ39: =SUM(AF39:AI39) | AK39: =IFERROR(AK5,"") | AL39: =IFERROR(AL5,"") | AM39: =IFERROR(AM5,"") | AN39: =IFERROR(AN5,"") | AO39: =SUM(AK39:AN39)
A40: OP전사 | B40: 사업부 | C40: 억원 | D40: OP 전사(부문 미분리) | E40: -53.87 | G40: -16.34 | H40: -16.04 | I40: -13.04 | J40: -2.01 | K40: =SUM(G40:J40) | L40: 21.84 | M40: 22.68 | N40: 7.41 | O40: 4.03 | P40: =SUM(L40:O40) | Q40: 9.58 | R40: -1.53 | S40: -5.83 | T40: 2.15 | U40: =SUM(Q40:T40) | V40: -11.67 | W40: -3.2 | X40: 11.72 | Y40: 1.71 | Z40: =SUM(V40:Y40) | AA40: 14.82 | AB40: -1.36 | AC40: =IFERROR(AC9,"") | AD40: =IFERROR(AD9,"") | AE40: =SUM(AA40:AD40) | AF40: =IFERROR(AF9,"") | AG40: =IFERROR(AG9,"") | AH40: =IFERROR(AH9,"") | AI40: =IFERROR(AI9,"") | AJ40: =SUM(AF40:AI40) | AK40: =IFERROR(AK9,"") | AL40: =IFERROR(AL9,"") | AM40: =IFERROR(AM9,"") | AN40: =IFERROR(AN9,"") | AO40: =SUM(AK40:AN40)
B41: 비율(참고)
A42: NPM | C42: % | D42: 지배주주순이익 / 매출액 | E42: =IFERROR(E20/E5,"") | F42: =IFERROR(F20/F5,"") | G42: =IFERROR(G20/G5,"") | H42: =IFERROR(H20/H5,"") | I42: =IFERROR(I20/I5,"") | J42: =IFERROR(J20/J5,"") | K42: =IFERROR(K20/K5,"") | L42: =IFERROR(L20/L5,"") | ... AO42: =IFERROR(AO20/AO5,"")
A43: 매출원가율 | C43: % | D43: 매출원가 / 매출액 | E43: =IFERROR(E6/E5,"") | F43: =IFERROR(F6/F5,"") | G43: =IFERROR(G6/G5,"") | H43: =IFERROR(H6/H5,"") | I43: =IFERROR(I6/I5,"") | J43: =IFERROR(J6/J5,"") | K43: =IFERROR(K6/K5,"") | L43: =IFERROR(L6/L5,"") | ... AO43: =IFERROR(AO6/AO5,"")
A44: 판관비율 | C44: % | D44: 판관비 / 매출액 | E44: =IFERROR(E8/E5,"") | F44: =IFERROR(F8/F5,"") | G44: =IFERROR(G8/G5,"") | H44: =IFERROR(H8/H5,"") | I44: =IFERROR(I8/I5,"") | J44: =IFERROR(J8/J5,"") | K44: =IFERROR(K8/K5,"") | L44: =IFERROR(L8/L5,"") | ... AO44: =IFERROR(AO8/AO5,"")

Sheet 분기
C1: 이름: 분기H — subQ 를 이름으로 VLOOKUP(억원) | E1: 4Q21 | F1: 1Q22 | G1: 2Q22 | H1: 3Q22 | I1: 4Q22 | J1: 1Q23 | K1: 2Q23 | L1: 3Q23 | M1: 4Q23 | N1: 1Q24 | O1: 2Q24 | P1: 3Q24 | Q1: 4Q24 | R1: 1Q25 | S1: 2Q25 | T1: 3Q25 | U1: 4Q25 | V1: 1Q26 | W1: 2Q26 | X1: 3Q26 | Y1: 4Q26 | Z1: 1Q27 | AA1: 2Q27 | AB1: 3Q27 | AC1: 4Q27 | AD1: 1Q28 | AE1: 2Q28 | AF1: 3Q28 | AG1: 4Q28
C2: 종가: | D2: =변수!D44
C3: 기준일: | D3: 20261019 | E3: 1 | F3: 2 | G3: 3 | H3: 4 | I3: 5 | J3: 6 | K3: 7 | L3: 8 | M3: 9 | N3: 10 | O3: 11 | P3: 12 | Q3: 13 | R3: 14 | S3: 15 | T3: 16 | U3: 17 | V3: 18 | W3: 19 | X3: 20 | Y3: 21 | Z3: 22 | AA3: 23 | AB3: 24 | AC3: 25 | AD3: 26 | AE3: 27 | AF3: 28 | AG3: 29
E4: 2021.12 | F4: 2022.03 | G4: 2022.06 | H4: 2022.09 | I4: 2022.12 | J4: 2023.03 | K4: 2023.06 | L4: 2023.09 | M4: 2023.12 | N4: 2024.03 | O4: 2024.06 | P4: 2024.09 | Q4: 2024.12 | R4: 2025.03 | S4: 2025.06 | T4: 2025.09 | U4: 2025.12 | V4: 2026.03 | W4: 2026.06 | X4: 2026.09 | Y4: 2026.12 | Z4: 2027.03 | AA4: 2027.06 | AB4: 2027.09 | AC4: 2027.12 | AD4: 2028.03 | AE4: 2028.06 | AF4: 2028.09 | AG4: 2028.12
A5: 매출액 | D5: 매출액 | E5: =IFERROR(VLOOKUP($A5,subQ,MATCH(E$1,SUBQH,0),0),"") | F5: =IFERROR(VLOOKUP($A5,subQ,MATCH(F$1,SUBQH,0),0),"") | G5: =IFERROR(VLOOKUP($A5,subQ,MATCH(G$1,SUBQH,0),0),"") | H5: =IFERROR(VLOOKUP($A5,subQ,MATCH(H$1,SUBQH,0),0),"") | I5: =IFERROR(VLOOKUP($A5,subQ,MATCH(I$1,SUBQH,0),0),"") | J5: =IFERROR(VLOOKUP($A5,subQ,MATCH(J$1,SUBQH,0),0),"") | K5: =IFERROR(VLOOKUP($A5,subQ,MATCH(K$1,SUBQH,0),0),"") | L5: =IFERROR(VLOOKUP($A5,subQ,MATCH(L$1,SUBQH,0),0),"") | ... AG5: =IFERROR(VLOOKUP($A5,subQ,MATCH(AG$1,SUBQH,0),0),"")
A6: 매출원가 | D6: 매출원가 | E6: =IFERROR(VLOOKUP($A6,subQ,MATCH(E$1,SUBQH,0),0),"") | F6: =IFERROR(VLOOKUP($A6,subQ,MATCH(F$1,SUBQH,0),0),"") | G6: =IFERROR(VLOOKUP($A6,subQ,MATCH(G$1,SUBQH,0),0),"") | H6: =IFERROR(VLOOKUP($A6,subQ,MATCH(H$1,SUBQH,0),0),"") | I6: =IFERROR(VLOOKUP($A6,subQ,MATCH(I$1,SUBQH,0),0),"") | J6: =IFERROR(VLOOKUP($A6,subQ,MATCH(J$1,SUBQH,0),0),"") | K6: =IFERROR(VLOOKUP($A6,subQ,MATCH(K$1,SUBQH,0),0),"") | L6: =IFERROR(VLOOKUP($A6,subQ,MATCH(L$1,SUBQH,0),0),"") | ... AG6: =IFERROR(VLOOKUP($A6,subQ,MATCH(AG$1,SUBQH,0),0),"")
A7: 매출총이익 | D7: 매출총이익 | E7: =IFERROR(VLOOKUP($A7,subQ,MATCH(E$1,SUBQH,0),0),"") | F7: =IFERROR(VLOOKUP($A7,subQ,MATCH(F$1,SUBQH,0),0),"") | G7: =IFERROR(VLOOKUP($A7,subQ,MATCH(G$1,SUBQH,0),0),"") | H7: =IFERROR(VLOOKUP($A7,subQ,MATCH(H$1,SUBQH,0),0),"") | I7: =IFERROR(VLOOKUP($A7,subQ,MATCH(I$1,SUBQH,0),0),"") | J7: =IFERROR(VLOOKUP($A7,subQ,MATCH(J$1,SUBQH,0),0),"") | K7: =IFERROR(VLOOKUP($A7,subQ,MATCH(K$1,SUBQH,0),0),"") | L7: =IFERROR(VLOOKUP($A7,subQ,MATCH(L$1,SUBQH,0),0),"") | ... AG7: =IFERROR(VLOOKUP($A7,subQ,MATCH(AG$1,SUBQH,0),0),"")
A8: 판관비 | D8: 판매비와관리비 | E8: =IFERROR(VLOOKUP($A8,subQ,MATCH(E$1,SUBQH,0),0),"") | F8: =IFERROR(VLOOKUP($A8,subQ,MATCH(F$1,SUBQH,0),0),"") | G8: =IFERROR(VLOOKUP($A8,subQ,MATCH(G$1,SUBQH,0),0),"") | H8: =IFERROR(VLOOKUP($A8,subQ,MATCH(H$1,SUBQH,0),0),"") | I8: =IFERROR(VLOOKUP($A8,subQ,MATCH(I$1,SUBQH,0),0),"") | J8: =IFERROR(VLOOKUP($A8,subQ,MATCH(J$1,SUBQH,0),0),"") | K8: =IFERROR(VLOOKUP($A8,subQ,MATCH(K$1,SUBQH,0),0),"") | L8: =IFERROR(VLOOKUP($A8,subQ,MATCH(L$1,SUBQH,0),0),"") | ... AG8: =IFERROR(VLOOKUP($A8,subQ,MATCH(AG$1,SUBQH,0),0),"")
A9: 영업이익 | D9: 영업이익 | E9: =IFERROR(VLOOKUP($A9,subQ,MATCH(E$1,SUBQH,0),0),"") | F9: =IFERROR(VLOOKUP($A9,subQ,MATCH(F$1,SUBQH,0),0),"") | G9: =IFERROR(VLOOKUP($A9,subQ,MATCH(G$1,SUBQH,0),0),"") | H9: =IFERROR(VLOOKUP($A9,subQ,MATCH(H$1,SUBQH,0),0),"") | I9: =IFERROR(VLOOKUP($A9,subQ,MATCH(I$1,SUBQH,0),0),"") | J9: =IFERROR(VLOOKUP($A9,subQ,MATCH(J$1,SUBQH,0),0),"") | K9: =IFERROR(VLOOKUP($A9,subQ,MATCH(K$1,SUBQH,0),0),"") | L9: =IFERROR(VLOOKUP($A9,subQ,MATCH(L$1,SUBQH,0),0),"") | ... AG9: =IFERROR(VLOOKUP($A9,subQ,MATCH(AG$1,SUBQH,0),0),"")
A10: OPM | D10: 영업이익률 | E10: =IFERROR(VLOOKUP($A10,subQ,MATCH(E$1,SUBQH,0),0),"") | F10: =IFERROR(VLOOKUP($A10,subQ,MATCH(F$1,SUBQH,0),0),"") | G10: =IFERROR(VLOOKUP($A10,subQ,MATCH(G$1,SUBQH,0),0),"") | H10: =IFERROR(VLOOKUP($A10,subQ,MATCH(H$1,SUBQH,0),0),"") | I10: =IFERROR(VLOOKUP($A10,subQ,MATCH(I$1,SUBQH,0),0),"") | J10: =IFERROR(VLOOKUP($A10,subQ,MATCH(J$1,SUBQH,0),0),"") | K10: =IFERROR(VLOOKUP($A10,subQ,MATCH(K$1,SUBQH,0),0),"") | L10: =IFERROR(VLOOKUP($A10,subQ,MATCH(L$1,SUBQH,0),0),"") | ... AG10: =IFERROR(VLOOKUP($A10,subQ,MATCH(AG$1,SUBQH,0),0),"")
A11: 금융손익 | D11: 금융손익(이자·환 포함) | E11: =IFERROR(VLOOKUP($A11,subQ,MATCH(E$1,SUBQH,0),0),"") | F11: =IFERROR(VLOOKUP($A11,subQ,MATCH(F$1,SUBQH,0),0),"") | G11: =IFERROR(VLOOKUP($A11,subQ,MATCH(G$1,SUBQH,0),0),"") | H11: =IFERROR(VLOOKUP($A11,subQ,MATCH(H$1,SUBQH,0),0),"") | I11: =IFERROR(VLOOKUP($A11,subQ,MATCH(I$1,SUBQH,0),0),"") | J11: =IFERROR(VLOOKUP($A11,subQ,MATCH(J$1,SUBQH,0),0),"") | K11: =IFERROR(VLOOKUP($A11,subQ,MATCH(K$1,SUBQH,0),0),"") | L11: =IFERROR(VLOOKUP($A11,subQ,MATCH(L$1,SUBQH,0),0),"") | ... AG11: =IFERROR(VLOOKUP($A11,subQ,MATCH(AG$1,SUBQH,0),0),"")
A12: 이자손익 | D12: 이자손익(이자수익 − 이자비용) | E12: =IFERROR(VLOOKUP($A12,subQ,MATCH(E$1,SUBQH,0),0),"") | F12: =IFERROR(VLOOKUP($A12,subQ,MATCH(F$1,SUBQH,0),0),"") | G12: =IFERROR(VLOOKUP($A12,subQ,MATCH(G$1,SUBQH,0),0),"") | H12: =IFERROR(VLOOKUP($A12,subQ,MATCH(H$1,SUBQH,0),0),"") | I12: =IFERROR(VLOOKUP($A12,subQ,MATCH(I$1,SUBQH,0),0),"") | J12: =IFERROR(VLOOKUP($A12,subQ,MATCH(J$1,SUBQH,0),0),"") | K12: =IFERROR(VLOOKUP($A12,subQ,MATCH(K$1,SUBQH,0),0),"") | L12: =IFERROR(VLOOKUP($A12,subQ,MATCH(L$1,SUBQH,0),0),"") | ... AG12: =IFERROR(VLOOKUP($A12,subQ,MATCH(AG$1,SUBQH,0),0),"")
A13: 외환손익 | D13: 외환손익(실적만; 추정 환효과는 환관련손익) | E13: =IFERROR(VLOOKUP($A13,subQ,MATCH(E$1,SUBQH,0),0),"") | F13: =IFERROR(VLOOKUP($A13,subQ,MATCH(F$1,SUBQH,0),0),"") | G13: =IFERROR(VLOOKUP($A13,subQ,MATCH(G$1,SUBQH,0),0),"") | H13: =IFERROR(VLOOKUP($A13,subQ,MATCH(H$1,SUBQH,0),0),"") | I13: =IFERROR(VLOOKUP($A13,subQ,MATCH(I$1,SUBQH,0),0),"") | J13: =IFERROR(VLOOKUP($A13,subQ,MATCH(J$1,SUBQH,0),0),"") | K13: =IFERROR(VLOOKUP($A13,subQ,MATCH(K$1,SUBQH,0),0),"") | L13: =IFERROR(VLOOKUP($A13,subQ,MATCH(L$1,SUBQH,0),0),"") | ... AG13: =IFERROR(VLOOKUP($A13,subQ,MATCH(AG$1,SUBQH,0),0),"")
A14: 파생상품손익 | D14: 파생상품손익 | E14: =IFERROR(VLOOKUP($A14,subQ,MATCH(E$1,SUBQH,0),0),"") | F14: =IFERROR(VLOOKUP($A14,subQ,MATCH(F$1,SUBQH,0),0),"") | G14: =IFERROR(VLOOKUP($A14,subQ,MATCH(G$1,SUBQH,0),0),"") | H14: =IFERROR(VLOOKUP($A14,subQ,MATCH(H$1,SUBQH,0),0),"") | I14: =IFERROR(VLOOKUP($A14,subQ,MATCH(I$1,SUBQH,0),0),"") | J14: =IFERROR(VLOOKUP($A14,subQ,MATCH(J$1,SUBQH,0),0),"") | K14: =IFERROR(VLOOKUP($A14,subQ,MATCH(K$1,SUBQH,0),0),"") | L14: =IFERROR(VLOOKUP($A14,subQ,MATCH(L$1,SUBQH,0),0),"") | ... AG14: =IFERROR(VLOOKUP($A14,subQ,MATCH(AG$1,SUBQH,0),0),"")
A15: 기타금융손익 | D15: 기타금융손익(금융손익 잔차) | E15: =IFERROR(VLOOKUP($A15,subQ,MATCH(E$1,SUBQH,0),0),"") | F15: =IFERROR(VLOOKUP($A15,subQ,MATCH(F$1,SUBQH,0),0),"") | G15: =IFERROR(VLOOKUP($A15,subQ,MATCH(G$1,SUBQH,0),0),"") | H15: =IFERROR(VLOOKUP($A15,subQ,MATCH(H$1,SUBQH,0),0),"") | I15: =IFERROR(VLOOKUP($A15,subQ,MATCH(I$1,SUBQH,0),0),"") | J15: =IFERROR(VLOOKUP($A15,subQ,MATCH(J$1,SUBQH,0),0),"") | K15: =IFERROR(VLOOKUP($A15,subQ,MATCH(K$1,SUBQH,0),0),"") | L15: =IFERROR(VLOOKUP($A15,subQ,MATCH(L$1,SUBQH,0),0),"") | ... AG15: =IFERROR(VLOOKUP($A15,subQ,MATCH(AG$1,SUBQH,0),0),"")
A16: 기타영업외손익 | D16: 기타영업외손익 | E16: =IFERROR(VLOOKUP($A16,subQ,MATCH(E$1,SUBQH,0),0),"") | F16: =IFERROR(VLOOKUP($A16,subQ,MATCH(F$1,SUBQH,0),0),"") | G16: =IFERROR(VLOOKUP($A16,subQ,MATCH(G$1,SUBQH,0),0),"") | H16: =IFERROR(VLOOKUP($A16,subQ,MATCH(H$1,SUBQH,0),0),"") | I16: =IFERROR(VLOOKUP($A16,subQ,MATCH(I$1,SUBQH,0),0),"") | J16: =IFERROR(VLOOKUP($A16,subQ,MATCH(J$1,SUBQH,0),0),"") | K16: =IFERROR(VLOOKUP($A16,subQ,MATCH(K$1,SUBQH,0),0),"") | L16: =IFERROR(VLOOKUP($A16,subQ,MATCH(L$1,SUBQH,0),0),"") | ... AG16: =IFERROR(VLOOKUP($A16,subQ,MATCH(AG$1,SUBQH,0),0),"")
... A41: NPM | D41: NPM | E41: =IFERROR(VLOOKUP($A41,subQ,MATCH(E$1,SUBQH,0),0),"") | F41: =IFERROR(VLOOKUP($A41,subQ,MATCH(F$1,SUBQH,0),0),"") | G41: =IFERROR(VLOOKUP($A41,subQ,MATCH(G$1,SUBQH,0),0),"") | H41: =IFERROR(VLOOKUP($A41,subQ,MATCH(H$1,SUBQH,0),0),"") | I41: =IFERROR(VLOOKUP($A41,subQ,MATCH(I$1,SUBQH,0),0),"") | J41: =IFERROR(VLOOKUP($A41,subQ,MATCH(J$1,SUBQH,0),0),"") | K41: =IFERROR(VLOOKUP($A41,subQ,MATCH(K$1,SUBQH,0),0),"") | L41: =IFERROR(VLOOKUP($A41,subQ,MATCH(L$1,SUBQH,0),0),"") | ... AG41: =IFERROR(VLOOKUP($A41,subQ,MATCH(AG$1,SUBQH,0),0),"")
A42: 매출액 YoY | D42: 매출액 YoY | I42: =IFERROR(I5/E5-1,"") | J42: =IFERROR(J5/F5-1,"") | K42: =IFERROR(K5/G5-1,"") | L42: =IFERROR(L5/H5-1,"") | M42: =IFERROR(M5/I5-1,"") | N42: =IFERROR(N5/J5-1,"") | O42: =IFERROR(O5/K5-1,"") | P42: =IFERROR(P5/L5-1,"") | ... AG42: =IFERROR(AG5/AC5-1,"")
A43: 영업이익 YoY | D43: 영업이익 YoY | I43: =IFERROR(I9/E9-1,"") | J43: =IFERROR(J9/F9-1,"") | K43: =IFERROR(K9/G9-1,"") | L43: =IFERROR(L9/H9-1,"") | M43: =IFERROR(M9/I9-1,"") | N43: =IFERROR(N9/J9-1,"") | O43: =IFERROR(O9/K9-1,"") | P43: =IFERROR(P9/L9-1,"") | ... AG43: =IFERROR(AG9/AC9-1,"")
A44: 지배주주순이익 YoY | D44: 지배주주순이익 YoY | I44: =IFERROR(I20/E20-1,"") | J44: =IFERROR(J20/F20-1,"") | K44: =IFERROR(K20/G20-1,"") | L44: =IFERROR(L20/H20-1,"") | M44: =IFERROR(M20/I20-1,"") | N44: =IFERROR(N20/J20-1,"") | O44: =IFERROR(O20/K20-1,"") | P44: =IFERROR(P20/L20-1,"") | ... AG44: =IFERROR(AG20/AC20-1,"")

Sheet 연간예상
C1: 이름: 연간예상H — subQ 를 이름으로 VLOOKUP(억원) | E1: 2021 | F1: 2022 | G1: 2023 | H1: 2024 | I1: 2025 | J1: 2026 | K1: 2027 | L1: 2028
C2: 종가: | D2: =변수!D44
C3: 기준일: | D3: 20261019 | E3: 1 | F3: 2 | G3: 3 | H3: 4 | I3: 5 | J3: 6 | K3: 7 | L3: 8
E4: 2021.12A | F4: 2022.12A | G4: 2023.12A | H4: 2024.12A | I4: 2025.12A | J4: 2026.12A | K4: 2027.12A | L4: 2028.12A
A5: 매출액 | D5: 매출액 | E5: =IFERROR(VLOOKUP($A5,subQ,MATCH(E$1,SUBQH,0),0),"") | F5: =IFERROR(VLOOKUP($A5,subQ,MATCH(F$1,SUBQH,0),0),"") | G5: =IFERROR(VLOOKUP($A5,subQ,MATCH(G$1,SUBQH,0),0),"") | H5: =IFERROR(VLOOKUP($A5,subQ,MATCH(H$1,SUBQH,0),0),"") | I5: =IFERROR(VLOOKUP($A5,subQ,MATCH(I$1,SUBQH,0),0),"") | J5: =IFERROR(VLOOKUP($A5,subQ,MATCH(J$1,SUBQH,0),0),"") | K5: =IFERROR(VLOOKUP($A5,subQ,MATCH(K$1,SUBQH,0),0),"") | L5: =IFERROR(VLOOKUP($A5,subQ,MATCH(L$1,SUBQH,0),0),"")
A6: 매출원가 | D6: 매출원가 | E6: =IFERROR(VLOOKUP($A6,subQ,MATCH(E$1,SUBQH,0),0),"") | F6: =IFERROR(VLOOKUP($A6,subQ,MATCH(F$1,SUBQH,0),0),"") | G6: =IFERROR(VLOOKUP($A6,subQ,MATCH(G$1,SUBQH,0),0),"") | H6: =IFERROR(VLOOKUP($A6,subQ,MATCH(H$1,SUBQH,0),0),"") | I6: =IFERROR(VLOOKUP($A6,subQ,MATCH(I$1,SUBQH,0),0),"") | J6: =IFERROR(VLOOKUP($A6,subQ,MATCH(J$1,SUBQH,0),0),"") | K6: =IFERROR(VLOOKUP($A6,subQ,MATCH(K$1,SUBQH,0),0),"") | L6: =IFERROR(VLOOKUP($A6,subQ,MATCH(L$1,SUBQH,0),0),"")
A7: 매출총이익 | D7: 매출총이익 | E7: =IFERROR(VLOOKUP($A7,subQ,MATCH(E$1,SUBQH,0),0),"") | F7: =IFERROR(VLOOKUP($A7,subQ,MATCH(F$1,SUBQH,0),0),"") | G7: =IFERROR(VLOOKUP($A7,subQ,MATCH(G$1,SUBQH,0),0),"") | H7: =IFERROR(VLOOKUP($A7,subQ,MATCH(H$1,SUBQH,0),0),"") | I7: =IFERROR(VLOOKUP($A7,subQ,MATCH(I$1,SUBQH,0),0),"") | J7: =IFERROR(VLOOKUP($A7,subQ,MATCH(J$1,SUBQH,0),0),"") | K7: =IFERROR(VLOOKUP($A7,subQ,MATCH(K$1,SUBQH,0),0),"") | L7: =IFERROR(VLOOKUP($A7,subQ,MATCH(L$1,SUBQH,0),0),"")
A8: 판관비 | D8: 판매비와관리비 | E8: =IFERROR(VLOOKUP($A8,subQ,MATCH(E$1,SUBQH,0),0),"") | F8: =IFERROR(VLOOKUP($A8,subQ,MATCH(F$1,SUBQH,0),0),"") | G8: =IFERROR(VLOOKUP($A8,subQ,MATCH(G$1,SUBQH,0),0),"") | H8: =IFERROR(VLOOKUP($A8,subQ,MATCH(H$1,SUBQH,0),0),"") | I8: =IFERROR(VLOOKUP($A8,subQ,MATCH(I$1,SUBQH,0),0),"") | J8: =IFERROR(VLOOKUP($A8,subQ,MATCH(J$1,SUBQH,0),0),"") | K8: =IFERROR(VLOOKUP($A8,subQ,MATCH(K$1,SUBQH,0),0),"") | L8: =IFERROR(VLOOKUP($A8,subQ,MATCH(L$1,SUBQH,0),0),"")
A9: 영업이익 | D9: 영업이익 | E9: =IFERROR(VLOOKUP($A9,subQ,MATCH(E$1,SUBQH,0),0),"") | F9: =IFERROR(VLOOKUP($A9,subQ,MATCH(F$1,SUBQH,0),0),"") | G9: =IFERROR(VLOOKUP($A9,subQ,MATCH(G$1,SUBQH,0),0),"") | H9: =IFERROR(VLOOKUP($A9,subQ,MATCH(H$1,SUBQH,0),0),"") | I9: =IFERROR(VLOOKUP($A9,subQ,MATCH(I$1,SUBQH,0),0),"") | J9: =IFERROR(VLOOKUP($A9,subQ,MATCH(J$1,SUBQH,0),0),"") | K9: =IFERROR(VLOOKUP($A9,subQ,MATCH(K$1,SUBQH,0),0),"") | L9: =IFERROR(VLOOKUP($A9,subQ,MATCH(L$1,SUBQH,0),0),"")
A10: OPM | D10: 영업이익률 | E10: =IFERROR(VLOOKUP($A10,subQ,MATCH(E$1,SUBQH,0),0),"") | F10: =IFERROR(VLOOKUP($A10,subQ,MATCH(F$1,SUBQH,0),0),"") | G10: =IFERROR(VLOOKUP($A10,subQ,MATCH(G$1,SUBQH,0),0),"") | H10: =IFERROR(VLOOKUP($A10,subQ,MATCH(H$1,SUBQH,0),0),"") | I10: =IFERROR(VLOOKUP($A10,subQ,MATCH(I$1,SUBQH,0),0),"") | J10: =IFERROR(VLOOKUP($A10,subQ,MATCH(J$1,SUBQH,0),0),"") | K10: =IFERROR(VLOOKUP($A10,subQ,MATCH(K$1,SUBQH,0),0),"") | L10: =IFERROR(VLOOKUP($A10,subQ,MATCH(L$1,SUBQH,0),0),"")
A11: 금융손익 | D11: 금융손익(이자·환 포함) | E11: =IFERROR(VLOOKUP($A11,subQ,MATCH(E$1,SUBQH,0),0),"") | F11: =IFERROR(VLOOKUP($A11,subQ,MATCH(F$1,SUBQH,0),0),"") | G11: =IFERROR(VLOOKUP($A11,subQ,MATCH(G$1,SUBQH,0),0),"") | H11: =IFERROR(VLOOKUP($A11,subQ,MATCH(H$1,SUBQH,0),0),"") | I11: =IFERROR(VLOOKUP($A11,subQ,MATCH(I$1,SUBQH,0),0),"") | J11: =IFERROR(VLOOKUP($A11,subQ,MATCH(J$1,SUBQH,0),0),"") | K11: =IFERROR(VLOOKUP($A11,subQ,MATCH(K$1,SUBQH,0),0),"") | L11: =IFERROR(VLOOKUP($A11,subQ,MATCH(L$1,SUBQH,0),0),"")
A12: 이자손익 | D12: 이자손익(이자수익 − 이자비용) | E12: =IFERROR(VLOOKUP($A12,subQ,MATCH(E$1,SUBQH,0),0),"") | F12: =IFERROR(VLOOKUP($A12,subQ,MATCH(F$1,SUBQH,0),0),"") | G12: =IFERROR(VLOOKUP($A12,subQ,MATCH(G$1,SUBQH,0),0),"") | H12: =IFERROR(VLOOKUP($A12,subQ,MATCH(H$1,SUBQH,0),0),"") | I12: =IFERROR(VLOOKUP($A12,subQ,MATCH(I$1,SUBQH,0),0),"") | J12: =IFERROR(VLOOKUP($A12,subQ,MATCH(J$1,SUBQH,0),0),"") | K12: =IFERROR(VLOOKUP($A12,subQ,MATCH(K$1,SUBQH,0),0),"") | L12: =IFERROR(VLOOKUP($A12,subQ,MATCH(L$1,SUBQH,0),0),"")
A13: 외환손익 | D13: 외환손익(실적만; 추정 환효과는 환관련손익) | E13: =IFERROR(VLOOKUP($A13,subQ,MATCH(E$1,SUBQH,0),0),"") | F13: =IFERROR(VLOOKUP($A13,subQ,MATCH(F$1,SUBQH,0),0),"") | G13: =IFERROR(VLOOKUP($A13,subQ,MATCH(G$1,SUBQH,0),0),"") | H13: =IFERROR(VLOOKUP($A13,subQ,MATCH(H$1,SUBQH,0),0),"") | I13: =IFERROR(VLOOKUP($A13,subQ,MATCH(I$1,SUBQH,0),0),"") | J13: =IFERROR(VLOOKUP($A13,subQ,MATCH(J$1,SUBQH,0),0),"") | K13: =IFERROR(VLOOKUP($A13,subQ,MATCH(K$1,SUBQH,0),0),"") | L13: =IFERROR(VLOOKUP($A13,subQ,MATCH(L$1,SUBQH,0),0),"")
A14: 파생상품손익 | D14: 파생상품손익 | E14: =IFERROR(VLOOKUP($A14,subQ,MATCH(E$1,SUBQH,0),0),"") | F14: =IFERROR(VLOOKUP($A14,subQ,MATCH(F$1,SUBQH,0),0),"") | G14: =IFERROR(VLOOKUP($A14,subQ,MATCH(G$1,SUBQH,0),0),"") | H14: =IFERROR(VLOOKUP($A14,subQ,MATCH(H$1,SUBQH,0),0),"") | I14: =IFERROR(VLOOKUP($A14,subQ,MATCH(I$1,SUBQH,0),0),"") | J14: =IFERROR(VLOOKUP($A14,subQ,MATCH(J$1,SUBQH,0),0),"") | K14: =IFERROR(VLOOKUP($A14,subQ,MATCH(K$1,SUBQH,0),0),"") | L14: =IFERROR(VLOOKUP($A14,subQ,MATCH(L$1,SUBQH,0),0),"")
A15: 기타금융손익 | D15: 기타금융손익(금융손익 잔차) | E15: =IFERROR(VLOOKUP($A15,subQ,MATCH(E$1,SUBQH,0),0),"") | F15: =IFERROR(VLOOKUP($A15,subQ,MATCH(F$1,SUBQH,0),0),"") | G15: =IFERROR(VLOOKUP($A15,subQ,MATCH(G$1,SUBQH,0),0),"") | H15: =IFERROR(VLOOKUP($A15,subQ,MATCH(H$1,SUBQH,0),0),"") | I15: =IFERROR(VLOOKUP($A15,subQ,MATCH(I$1,SUBQH,0),0),"") | J15: =IFERROR(VLOOKUP($A15,subQ,MATCH(J$1,SUBQH,0),0),"") | K15: =IFERROR(VLOOKUP($A15,subQ,MATCH(K$1,SUBQH,0),0),"") | L15: =IFERROR(VLOOKUP($A15,subQ,MATCH(L$1,SUBQH,0),0),"")
A16: 기타영업외손익 | D16: 기타영업외손익 | E16: =IFERROR(VLOOKUP($A16,subQ,MATCH(E$1,SUBQH,0),0),"") | F16: =IFERROR(VLOOKUP($A16,subQ,MATCH(F$1,SUBQH,0),0),"") | G16: =IFERROR(VLOOKUP($A16,subQ,MATCH(G$1,SUBQH,0),0),"") | H16: =IFERROR(VLOOKUP($A16,subQ,MATCH(H$1,SUBQH,0),0),"") | I16: =IFERROR(VLOOKUP($A16,subQ,MATCH(I$1,SUBQH,0),0),"") | J16: =IFERROR(VLOOKUP($A16,subQ,MATCH(J$1,SUBQH,0),0),"") | K16: =IFERROR(VLOOKUP($A16,subQ,MATCH(K$1,SUBQH,0),0),"") | L16: =IFERROR(VLOOKUP($A16,subQ,MATCH(L$1,SUBQH,0),0),"")
... A41: NPM | D41: NPM | E41: =IFERROR(VLOOKUP($A41,subQ,MATCH(E$1,SUBQH,0),0),"") | F41: =IFERROR(VLOOKUP($A41,subQ,MATCH(F$1,SUBQH,0),0),"") | G41: =IFERROR(VLOOKUP($A41,subQ,MATCH(G$1,SUBQH,0),0),"") | H41: =IFERROR(VLOOKUP($A41,subQ,MATCH(H$1,SUBQH,0),0),"") | I41: =IFERROR(VLOOKUP($A41,subQ,MATCH(I$1,SUBQH,0),0),"") | J41: =IFERROR(VLOOKUP($A41,subQ,MATCH(J$1,SUBQH,0),0),"") | K41: =IFERROR(VLOOKUP($A41,subQ,MATCH(K$1,SUBQH,0),0),"") | L41: =IFERROR(VLOOKUP($A41,subQ,MATCH(L$1,SUBQH,0),0),"")
A42: 매출액 YoY | D42: 매출액 YoY | F42: =IFERROR(F5/E5-1,"") | G42: =IFERROR(G5/F5-1,"") | H42: =IFERROR(H5/G5-1,"") | I42: =IFERROR(I5/H5-1,"") | J42: =IFERROR(J5/I5-1,"") | K42: =IFERROR(K5/J5-1,"") | L42: =IFERROR(L5/K5-1,"")
A43: 영업이익 YoY | D43: 영업이익 YoY | F43: =IFERROR(F9/E9-1,"") | G43: =IFERROR(G9/F9-1,"") | H43: =IFERROR(H9/G9-1,"") | I43: =IFERROR(I9/H9-1,"") | J43: =IFERROR(J9/I9-1,"") | K43: =IFERROR(K9/J9-1,"") | L43: =IFERROR(L9/K9-1,"")
A44: 지배주주순이익 YoY | D44: 지배주주순이익 YoY | F44: =IFERROR(F20/E20-1,"") | G44: =IFERROR(G20/F20-1,"") | H44: =IFERROR(H20/G20-1,"") | I44: =IFERROR(I20/H20-1,"") | J44: =IFERROR(J20/I20-1,"") | K44: =IFERROR(K20/J20-1,"") | L44: =IFERROR(L20/K20-1,"")

Sheet TP
B1: 종가 | C1: =변수!D44
B2: 기준일 | C2: =변수!D45
B3: 모델 산출값 — 목표주가·추천 아님. 밴드·COE 는 변수 시트 3절의 가정
C5: FY | D5: 2025 | E5: 2026 | F5: 2027 | G5: 2028
D6: A | E6: E | F6: E | G6: E
C7: EPS(원) | D7: =IFERROR(VLOOKUP("EPS",subQ,MATCH(D$5,SUBQH,0),0),"") | E7: =IFERROR(VLOOKUP("EPS",subQ,MATCH(E$5,SUBQH,0),0),"") | F7: =IFERROR(VLOOKUP("EPS",subQ,MATCH(F$5,SUBQH,0),0),"") | G7: =IFERROR(VLOOKUP("EPS",subQ,MATCH(G$5,SUBQH,0),0),"")
C8: BPS(원) | D8: =IFERROR(VLOOKUP("BPS",subQ,MATCH(D$5,SUBQH,0),0),"") | E8: =IFERROR(VLOOKUP("BPS",subQ,MATCH(E$5,SUBQH,0),0),"") | F8: =IFERROR(VLOOKUP("BPS",subQ,MATCH(F$5,SUBQH,0),0),"") | G8: =IFERROR(VLOOKUP("BPS",subQ,MATCH(G$5,SUBQH,0),0),"")
C9: 지배주주순이익(억원) | D9: =IFERROR(VLOOKUP("지배주주순이익",subQ,MATCH(D$5,SUBQH,0),0),"") | E9: =IFERROR(VLOOKUP("지배주주순이익",subQ,MATCH(E$5,SUBQH,0),0),"") | F9: =IFERROR(VLOOKUP("지배주주순이익",subQ,MATCH(F$5,SUBQH,0),0),"") | G9: =IFERROR(VLOOKUP("지배주주순이익",subQ,MATCH(G$5,SUBQH,0),0),"")
C10: 영업이익(억원) | D10: =IFERROR(VLOOKUP("영업이익",subQ,MATCH(D$5,SUBQH,0),0),"") | E10: =IFERROR(VLOOKUP("영업이익",subQ,MATCH(E$5,SUBQH,0),0),"") | F10: =IFERROR(VLOOKUP("영업이익",subQ,MATCH(F$5,SUBQH,0),0),"") | G10: =IFERROR(VLOOKUP("영업이익",subQ,MATCH(G$5,SUBQH,0),0),"")
C11: ROE(EPS/기초BPS) | E11: =IFERROR(E7/D8,"") | F11: =IFERROR(F7/E8,"") | G11: =IFERROR(G7/F8,"")
B13: PER
C14: 12M fwd EPS | D14: =IFERROR(E7*변수!D50+F7*(1-변수!D50),"")
C15: 적정가치 @PER_lo | D15: =변수!D47 | E15: =IFERROR(ROUND($D$14*D15,-2),"") | F15: =IFERROR(E15/$C$1-1,"") | G15: 배 · 원 · 종가 대비
C16: 적정가치 @PER_mid | D16: =변수!D48 | E16: =IFERROR(ROUND($D$14*D16,-2),"") | F16: =IFERROR(E16/$C$1-1,"") | G16: 배 · 원 · 종가 대비
C17: 적정가치 @PER_hi | D17: =변수!D49 | E17: =IFERROR(ROUND($D$14*D17,-2),"") | F17: =IFERROR(E17/$C$1-1,"") | G17: 배 · 원 · 종가 대비
C18: 현재 PER(종가/12M fwd EPS) | D18: =IFERROR($C$1/$D$14,"")
B20: PBR
C21: 최근 BPS(마지막 실적 분기) | D21: =IFERROR(VLOOKUP("BPS",subQ,MATCH("2Q26",SUBQH,0),0),"")
C22: ROE fwd(12M fwd EPS / BPS) | D22: =IFERROR($D$14/$D$21,"")
C23: COE | D23: =변수!D46
C24: 적정 PBR = ROE/COE | D24: =IFERROR(D22/D23,"")
C25: 적정가치(PBR) = BPS × 적정PBR | D25: =IFERROR(ROUND(D21*D24,-2),"") | E25: =IFERROR(D25/$C$1-1,"")
C26: 현재 PBR(종가/BPS) | D26: =IFERROR($C$1/D21,"")
B28: 모델 json valuation(참고)
C29: eps_fwd12m | D29: -75.8
C30: bps_latest | D30: 881.8
C31: per_now
C32: pbr_now | D32: 2.01
C33: roe_fwd | D33: -0.086
C34: fair_pbr
C35: fair_value_pbr
C36: ev_ebitda | D36: 106.42
C37: note | D37: 모델 산출값 — 목표주가·추천 아님

Sheet 외화
C1: 이름: 외화QH — 환율 QoQ · 외화 순노출 × Δ기말환율 | E1: 4Q21 | F1: 1Q22 | G1: 2Q22 | H1: 3Q22 | I1: 4Q22 | J1: 1Q23 | K1: 2Q23 | L1: 3Q23 | M1: 4Q23 | N1: 1Q24 | O1: 2Q24 | P1: 3Q24 | Q1: 4Q24 | R1: 1Q25 | S1: 2Q25 | T1: 3Q25 | U1: 4Q25 | V1: 1Q26 | W1: 2Q26 | X1: 3Q26 | Y1: 4Q26 | Z1: 1Q27 | AA1: 2Q27 | AB1: 3Q27 | AC1: 4Q27 | AD1: 1Q28 | AE1: 2Q28 | AF1: 3Q28 | AG1: 4Q28
E3: 1 | F3: 2 | G3: 3 | H3: 4 | I3: 5 | J3: 6 | K3: 7 | L3: 8 | M3: 9 | N3: 10 | O3: 11 | P3: 12 | Q3: 13 | R3: 14 | S3: 15 | T3: 16 | U3: 17 | V3: 18 | W3: 19 | X3: 20 | Y3: 21 | Z3: 22 | AA3: 23 | AB3: 24 | AC3: 25 | AD3: 26 | AE3: 27 | AF3: 28 | AG3: 29
E4: 2021.12 | F4: 2022.03 | G4: 2022.06 | H4: 2022.09 | I4: 2022.12 | J4: 2023.03 | K4: 2023.06 | L4: 2023.09 | M4: 2023.12 | N4: 2024.03 | O4: 2024.06 | P4: 2024.09 | Q4: 2024.12 | R4: 2025.03 | S4: 2025.06 | T4: 2025.09 | U4: 2025.12 | V4: 2026.03 | W4: 2026.06 | X4: 2026.09 | Y4: 2026.12 | Z4: 2027.03 | AA4: 2027.06 | AB4: 2027.09 | AC4: 2027.12 | AD4: 2028.03 | AE4: 2028.06 | AF4: 2028.09 | AG4: 2028.12
D5: 원/달러(평균) | E5: =IFERROR(VLOOKUP($D5,환율,MATCH(E$1,변수H,0),0),"") | F5: =IFERROR(VLOOKUP($D5,환율,MATCH(F$1,변수H,0),0),"") | G5: =IFERROR(VLOOKUP($D5,환율,MATCH(G$1,변수H,0),0),"") | H5: =IFERROR(VLOOKUP($D5,환율,MATCH(H$1,변수H,0),0),"") | I5: =IFERROR(VLOOKUP($D5,환율,MATCH(I$1,변수H,0),0),"") | J5: =IFERROR(VLOOKUP($D5,환율,MATCH(J$1,변수H,0),0),"") | K5: =IFERROR(VLOOKUP($D5,환율,MATCH(K$1,변수H,0),0),"") | L5: =IFERROR(VLOOKUP($D5,환율,MATCH(L$1,변수H,0),0),"") | ... AG5: =IFERROR(VLOOKUP($D5,환율,MATCH(AG$1,변수H,0),0),"")
A6: 원/달러(평균) QoQ | F6: =IFERROR(F5/E5-1,"") | G6: =IFERROR(G5/F5-1,"") | H6: =IFERROR(H5/G5-1,"") | I6: =IFERROR(I5/H5-1,"") | J6: =IFERROR(J5/I5-1,"") | K6: =IFERROR(K5/J5-1,"") | L6: =IFERROR(L5/K5-1,"") | M6: =IFERROR(M5/L5-1,"") | ... AG6: =IFERROR(AG5/AF5-1,"")
D7: 원/달러(기말) | E7: =IFERROR(VLOOKUP($D7,환율,MATCH(E$1,변수H,0),0),"") | F7: =IFERROR(VLOOKUP($D7,환율,MATCH(F$1,변수H,0),0),"") | G7: =IFERROR(VLOOKUP($D7,환율,MATCH(G$1,변수H,0),0),"") | H7: =IFERROR(VLOOKUP($D7,환율,MATCH(H$1,변수H,0),0),"") | I7: =IFERROR(VLOOKUP($D7,환율,MATCH(I$1,변수H,0),0),"") | J7: =IFERROR(VLOOKUP($D7,환율,MATCH(J$1,변수H,0),0),"") | K7: =IFERROR(VLOOKUP($D7,환율,MATCH(K$1,변수H,0),0),"") | L7: =IFERROR(VLOOKUP($D7,환율,MATCH(L$1,변수H,0),0),"") | ... AG7: =IFERROR(VLOOKUP($D7,환율,MATCH(AG$1,변수H,0),0),"")
A8: 원/달러(기말) QoQ | F8: =IFERROR(F7/E7-1,"") | G8: =IFERROR(G7/F7-1,"") | H8: =IFERROR(H7/G7-1,"") | I8: =IFERROR(I7/H7-1,"") | J8: =IFERROR(J7/I7-1,"") | K8: =IFERROR(K7/J7-1,"") | L8: =IFERROR(L7/K7-1,"") | M8: =IFERROR(M7/L7-1,"") | ... AG8: =IFERROR(AG7/AF7-1,"")
D9: W/Euro(평균) | E9: =IFERROR(VLOOKUP($D9,환율,MATCH(E$1,변수H,0),0),"") | F9: =IFERROR(VLOOKUP($D9,환율,MATCH(F$1,변수H,0),0),"") | G9: =IFERROR(VLOOKUP($D9,환율,MATCH(G$1,변수H,0),0),"") | H9: =IFERROR(VLOOKUP($D9,환율,MATCH(H$1,변수H,0),0),"") | I9: =IFERROR(VLOOKUP($D9,환율,MATCH(I$1,변수H,0),0),"") | J9: =IFERROR(VLOOKUP($D9,환율,MATCH(J$1,변수H,0),0),"") | K9: =IFERROR(VLOOKUP($D9,환율,MATCH(K$1,변수H,0),0),"") | L9: =IFERROR(VLOOKUP($D9,환율,MATCH(L$1,변수H,0),0),"") | ... AG9: =IFERROR(VLOOKUP($D9,환율,MATCH(AG$1,변수H,0),0),"")
A10: W/Euro(평균) QoQ | F10: =IFERROR(F9/E9-1,"") | G10: =IFERROR(G9/F9-1,"") | H10: =IFERROR(H9/G9-1,"") | I10: =IFERROR(I9/H9-1,"") | J10: =IFERROR(J9/I9-1,"") | K10: =IFERROR(K9/J9-1,"") | L10: =IFERROR(L9/K9-1,"") | M10: =IFERROR(M9/L9-1,"") | ... AG10: =IFERROR(AG9/AF9-1,"")
D11: W/Euro(기말) | E11: =IFERROR(VLOOKUP($D11,환율,MATCH(E$1,변수H,0),0),"") | F11: =IFERROR(VLOOKUP($D11,환율,MATCH(F$1,변수H,0),0),"") | G11: =IFERROR(VLOOKUP($D11,환율,MATCH(G$1,변수H,0),0),"") | H11: =IFERROR(VLOOKUP($D11,환율,MATCH(H$1,변수H,0),0),"") | I11: =IFERROR(VLOOKUP($D11,환율,MATCH(I$1,변수H,0),0),"") | J11: =IFERROR(VLOOKUP($D11,환율,MATCH(J$1,변수H,0),0),"") | K11: =IFERROR(VLOOKUP($D11,환율,MATCH(K$1,변수H,0),0),"") | L11: =IFERROR(VLOOKUP($D11,환율,MATCH(L$1,변수H,0),0),"") | ... AG11: =IFERROR(VLOOKUP($D11,환율,MATCH(AG$1,변수H,0),0),"")
A12: W/Euro(기말) QoQ | F12: =IFERROR(F11/E11-1,"") | G12: =IFERROR(G11/F11-1,"") | H12: =IFERROR(H11/G11-1,"") | I12: =IFERROR(I11/H11-1,"") | J12: =IFERROR(J11/I11-1,"") | K12: =IFERROR(K11/J11-1,"") | L12: =IFERROR(L11/K11-1,"") | M12: =IFERROR(M11/L11-1,"") | ... AG12: =IFERROR(AG11/AF11-1,"")
D13: 원/100Y(기말) | E13: =IFERROR(VLOOKUP($D13,환율,MATCH(E$1,변수H,0),0),"") | F13: =IFERROR(VLOOKUP($D13,환율,MATCH(F$1,변수H,0),0),"") | G13: =IFERROR(VLOOKUP($D13,환율,MATCH(G$1,변수H,0),0),"") | H13: =IFERROR(VLOOKUP($D13,환율,MATCH(H$1,변수H,0),0),"") | I13: =IFERROR(VLOOKUP($D13,환율,MATCH(I$1,변수H,0),0),"") | J13: =IFERROR(VLOOKUP($D13,환율,MATCH(J$1,변수H,0),0),"") | K13: =IFERROR(VLOOKUP($D13,환율,MATCH(K$1,변수H,0),0),"") | L13: =IFERROR(VLOOKUP($D13,환율,MATCH(L$1,변수H,0),0),"") | ... AG13: =IFERROR(VLOOKUP($D13,환율,MATCH(AG$1,변수H,0),0),"")
A14: 원/100Y(기말) QoQ | F14: =IFERROR(F13/E13-1,"") | G14: =IFERROR(G13/F13-1,"") | H14: =IFERROR(H13/G13-1,"") | I14: =IFERROR(I13/H13-1,"") | J14: =IFERROR(J13/I13-1,"") | K14: =IFERROR(K13/J13-1,"") | L14: =IFERROR(L13/K13-1,"") | M14: =IFERROR(M13/L13-1,"") | ... AG14: =IFERROR(AG13/AF13-1,"")
A16: 외화순노출 | C16: 외화 순노출(백만$) | D16: =변수!D57 | E16: 외화 순노출 × Δ기말환율 (외화 시트 방식)
A17: 환관련손익추정 | C17: 환관련손익 추정(억원) = 순노출 × Δ원/달러(기말) / 100 | F17: =IFERROR($D$16*(F7-E7)/100,"") | G17: =IFERROR($D$16*(G7-F7)/100,"") | H17: =IFERROR($D$16*(H7-G7)/100,"") | I17: =IFERROR($D$16*(I7-H7)/100,"") | J17: =IFERROR($D$16*(J7-I7)/100,"") | K17: =IFERROR($D$16*(K7-J7)/100,"") | L17: =IFERROR($D$16*(L7-K7)/100,"") | M17: =IFERROR($D$16*(M7-L7)/100,"") | ... AG17: =IFERROR($D$16*(AG7-AF7)/100,"")
A18: fx_pnl.by_q | C18: 모델 fx_pnl.by_q(억원, 참고)
C19: 외화 순노출 미공시(face) → 0 + 표기
