Workbook
Name 변수H: 변수!$C$1:$AO$1
Name 환율: 변수!$C$6:$AO$13
Name BS연결H: BS연결!$C$1:$AO$1
Name BS연결: BS연결!$C$5:$AO$102
Name BS별도H: BS별도!$C$1:$AO$1
Name BS별도: BS별도!$C$5:$AO$91
Name SUBQH: subQ!$A$1:$AO$1
Name subQ: subQ!$A$5:$AO$45
Name SLS_H: SLS!$A$1:$FE$1

Sheet README
A1: HJ중공업(097230) 실적 모델 — ARGUS 한국조선
A2: 기준 분기 2026Q2 · 마지막 실적 2026Q2 · 생성 2026-10-14
A3: 모든 수치는 모델 산출값(DART 공개 재무제표 + 우리 추정)이다 — 목표주가·투자 추천 아님. 참고용 · 투자조언 아님.
A5: 시트
A6: 변수 가정 시계열. 환율 8행(ECB via frankfurter — L2 fx.json; 추정 분기 = 노란 가정), 추정 드라이버(노란 셀 = 모델값에서 역산한 가정, 바꾸면 재계산; 연녹 셀 = 3절 스칼라 참조 수식), 3절 스칼라 가정(세율·판관비율·지배주주비중·이자율·종가·PER 밴드·COE·외화 순노출·헤지비율)
A7: BS연결/BS별도 FnGuide 계정명 × 기간 값 덤프(백만원). 행1 분기라벨, 행4 YYYY.MM / YYYY.12A. 이름정의 BS연결H·BS연결(계정명 C열부터)
A8: subQ 분기 서브모델(억원 = 백만원/100). 확정 행: =IFERROR(VLOOKUP($D행,BS연결,MATCH(E$1,BS연결H,0),0)/100,"") 추정 행: 변수 시트 가정 셀 참조 수식. 외환손익·파생상품손익은 BS 계정 합·차, 기타금융손익은 잔차, OPM·EPS·BPS·PER·PBR 은 파생 수식
A9: SLS 선표(조선사만, sls json 있을 때): 요약 행(sls 저장값) + 계약별 스케줄(백만$) × (헤지비율 × 헤지환율 + (1−헤지비율) × 건조시점 환율[변수 원/달러(평균)]) → 원화 수식 블록 → 합계 행이 subQ 매출조선에 연결
A10: 시나리오 신규수주 보수/기준/낙관(forecast_panel 패널, 모델에 scenarios 가 있을 때만): 매출액·영업이익 = subQ 기준값 ± (시나리오 신규 − base 신규) × OPM. base 만 subQ 행에 포함, 나머지는 합산 안 함
A11: 분기/연간예상 subQ 를 이름(A열 key)으로 VLOOKUP 한 보고서 표(억원)
A12: TP PER 밴드 × 12M fwd EPS, PBR = ROE/COE × BPS — 모델 산출값 구간, 목표주가·추천 아님
A13: 외화 환율 QoQ, 외화 순노출 × Δ기말환율 → 환관련손익 추정
... A36: 백테스트: {"freeze": "2025Q2", "horizon": 4, "revenue_wape_pct": 19.4, "op_wape_pct": 100.0, "n": 4, "note": "단일 회사 4분기 — 통계 아님", "driver_at_freeze": "sls_marine_plus_uncovered_backlog_runoff", "selection_oos_at_freeze": null, "frozen_inputs": "fin(연결/별도)·고객 조선사 모델·지주 자회사 모델은 2025Q2 까지의 분기만; 선표는 체결일 ≤ 2025Q2 말일 계약(원장 최신 금액·코호트 등급, 환산 없음); 잔고는 yards_cache 2025Q2; 시세·환율 forward·prices·forecast_panel 신규수주 미사용. 고객 가중치(suppliers.json 언급 비중)와 합병 체인링크는 현재 지식; 고객 연동 채택은 동결 모델 안에서도 자기 la−4분기 OOS 규칙(selection_oos_at_freeze)", "detail": [{"q": "2025Q3", "rev_pred": 4962.89, "rev_act": 4522.08, "op_pred": 0.0, "op_act": 57.94}, {"q": "2025Q4", "rev_pred": 4962.89, "rev_act": 6296.54, "op_pred": 0.0, "op_act": 504.87}, {"q": "2026Q1", "rev_pred": 4962.89, "rev_act": 5414.0, "op_pred": 0.0, "op_act": 245.81}, {"q": "2026Q2", "rev_pred": 4962.89, "rev_act": 7299.08, "op_pred": 0.0, "op_act": 648.53}]}

Sheet 변수
C1: 이름: 변수H | E1: 4Q21 | F1: 2021 | G1: 1Q22 | H1: 2Q22 | I1: 3Q22 | J1: 4Q22 | K1: 2022 | L1: 1Q23 | M1: 2Q23 | N1: 3Q23 | O1: 4Q23 | P1: 2023 | Q1: 1Q24 | R1: 2Q24 | S1: 3Q24 | T1: 4Q24 | U1: 2024 | V1: 1Q25 | W1: 2Q25 | X1: 3Q25 | Y1: 4Q25 | Z1: 2025 | AA1: 1Q26 | AB1: 2Q26 | AC1: 3Q26 | AD1: 4Q26 | AE1: 2026 | AF1: 1Q27 | AG1: 2Q27 | AH1: 3Q27 | AI1: 4Q27 | AJ1: 2027 | AK1: 1Q28 | AL1: 2Q28 | AM1: 3Q28 | AN1: 4Q28 | AO1: 2028
A2: 가정 시계열 — 노란 셀은 추정 가정(모델값에서 역산), 연녹 셀은 3절 스칼라 참조 수식. 바꾸면 subQ·분기·연간예상·TP·시나리오가 재계산됩니다.
E3: 1 | F3: 2 | G3: 3 | H3: 4 | I3: 5 | J3: 6 | K3: 7 | L3: 8 | M3: 9 | N3: 10 | O3: 11 | P3: 12 | Q3: 13 | R3: 14 | S3: 15 | T3: 16 | U3: 17 | V3: 18 | W3: 19 | X3: 20 | Y3: 21 | Z3: 22 | AA3: 23 | AB3: 24 | AC3: 25 | AD3: 26 | AE3: 27 | AF3: 28 | AG3: 29 | AH3: 30 | AI3: 31 | AJ3: 32 | AK3: 33 | AL3: 34 | AM3: 35 | AN3: 36 | AO3: 37
E4: 2021.12 | F4: 2021.12A | G4: 2022.03 | H4: 2022.06 | I4: 2022.09 | J4: 2022.12 | K4: 2022.12A | L4: 2023.03 | M4: 2023.06 | N4: 2023.09 | O4: 2023.12 | P4: 2023.12A | Q4: 2024.03 | R4: 2024.06 | S4: 2024.09 | T4: 2024.12 | U4: 2024.12A | V4: 2025.03 | W4: 2025.06 | X4: 2025.09 | Y4: 2025.12 | Z4: 2025.12A | AA4: 2026.03 | AB4: 2026.06 | AC4: 2026.09 | AD4: 2026.12 | AE4: 2026.12A | AF4: 2027.03 | AG4: 2027.06 | AH4: 2027.09 | AI4: 2027.12 | AJ4: 2027.12A | AK4: 2028.03 | AL4: 2028.06 | AM4: 2028.09 | AN4: 2028.12 | AO4: 2028.12A
B5: 1. FX | C5: 이름: 환율
A6: USDKRW_avg | C6: 원/달러(평균) | E6: 1183.5 | F6: 1145.51 | G6: 1205.78 | H6: 1262.09 | I6: 1341.93 | J6: 1360.12 | K6: 1292.98 | L6: 1276.95 | M6: 1315.69 | N6: 1313.62 | O6: 1322.01 | P6: 1306.85 | Q6: 1330.14 | R6: 1371.28 | S6: 1356.22 | T6: 1396.3 | U6: 1363.53 | V6: 1452.28 | W6: 1398.52 | X6: 1386.95 | Y6: 1449.19 | Z6: 1421.52 | AA6: 1466.12 | AB6: 1501.75 | AC6: 1418.75 | AD6: 1343.39 | AE6: 1456.01 | AF6: 1341.45 | AG6: 1341.45 | AH6: 1341.45 | AI6: 1341.45 | AK6: 1341.45 | AL6: 1341.45 | AM6: 1341.45 | AN6: 1341.45
A7: USDKRW_end | C7: 원/달러(기말) | E7: 1188.75 | F7: 1188.75 | G7: 1213.74 | H7: 1301.24 | I7: 1436.9 | J7: 1260.16 | K7: 1260.16 | L7: 1305.99 | M7: 1321.44 | N7: 1345.35 | O7: 1297.43 | P7: 1297.43 | Q7: 1349.25 | R7: 1377.73 | S7: 1312.17 | T7: 1474.78 | U7: 1474.78 | V7: 1474.54 | W7: 1355.13 | X7: 1403.67 | Y7: 1444.2 | Z7: 1444.2 | AA7: 1524.8 | AB7: 1550.89 | AC7: 1355.4 | AD7: 1341.45 | AE7: 1341.45 | AF7: 1341.45 | AG7: 1341.45 | AH7: 1341.45 | AI7: 1341.45 | AK7: 1341.45 | AL7: 1341.45 | AM7: 1341.45 | AN7: 1341.45
A8: JPY100KRW_avg | C8: 원/100Y(평균) | E8: 1041.02 | F8: 1042.74 | G8: 1036.79 | H8: 972.23 | I8: 970.61 | J8: 961.03 | K8: 985.1 | L8: 964.89 | M8: 957.36 | N8: 909 | O8: 893.22 | P8: 931.11 | Q8: 896.29 | R8: 880.14 | S8: 909.35 | T8: 917.25 | U8: 900.92 | V8: 952.59 | W8: 967.92 | X8: 940.32 | Y8: 940.77 | Z8: 950.17 | AA8: 934.39 | AB8: 942.16 | AC8: 890.41 | AD8: 849.39 | AE8: 918.46 | AF8: 848.37 | AG8: 848.37 | AH8: 848.37 | AI8: 848.37 | AK8: 848.37 | AL8: 848.37 | AM8: 848.37 | AN8: 848.37
A9: JPY100KRW_end | C9: 원/100Y(기말) | E9: 1032.62 | F9: 1032.62 | G9: 996.83 | H9: 954.9 | I9: 993.29 | J9: 955.54 | K9: 955.54 | L9: 980.62 | M9: 913.67 | N9: 901.47 | O9: 917.04 | P9: 917.04 | Q9: 892.42 | R9: 857.76 | S9: 919.21 | T9: 939.65 | U9: 939.65 | V9: 986.84 | W9: 938.85 | X9: 948.49 | Y9: 921.81 | Z9: 921.81 | AA9: 955.99 | AB9: 954.75 | AC9: 863.31 | AD9: 848.37 | AE9: 848.37 | AF9: 848.37 | AG9: 848.37 | AH9: 848.37 | AI9: 848.37 | AK9: 848.37 | AL9: 848.37 | AM9: 848.37 | AN9: 848.37
A10: EURKRW_avg | C10: W/Euro(평균) | E10: 1353.32 | F10: 1354.06 | G10: 1352.29 | H10: 1343.31 | I10: 1350.63 | J10: 1386.07 | K10: 1358.07 | L10: 1369.93 | M10: 1432.41 | N10: 1429.41 | O10: 1420.91 | P10: 1412.88 | Q10: 1444.21 | R10: 1476.42 | S10: 1489.3 | T10: 1490.78 | U10: 1475.4 | V10: 1528.33 | W10: 1585.13 | X10: 1620.04 | Y10: 1686.02 | Z10: 1605.45 | AA10: 1715.47 | AB10: 1746.09 | AC10: 1631.97 | AD10: 1506.62 | AE10: 1688.01 | AF10: 1500.82 | AG10: 1500.82 | AH10: 1500.82 | AI10: 1500.82 | AK10: 1500.82 | AL10: 1500.82 | AM10: 1500.82 | AN10: 1500.82
A11: EURKRW_end | C11: W/Euro(기말) | E11: 1346.38 | F11: 1346.38 | G11: 1347.37 | H11: 1351.6 | I11: 1400.62 | J11: 1344.08 | K11: 1344.08 | L11: 1420.26 | M11: 1435.88 | N11: 1425.26 | O11: 1433.66 | P11: 1433.66 | Q11: 1458.68 | R11: 1474.86 | S11: 1469.1 | T11: 1532.14 | U11: 1532.14 | V11: 1594.72 | W11: 1588.22 | X11: 1648.04 | Y11: 1696.94 | Z11: 1696.94 | AA11: 1753.21 | AB11: 1767.09 | AC11: 1539.06 | AD11: 1500.82 | AE11: 1500.82 | AF11: 1500.82 | AG11: 1500.82 | AH11: 1500.82 | AI11: 1500.82 | AK11: 1500.82 | AL11: 1500.82 | AM11: 1500.82 | AN11: 1500.82
A12: CNYKRW_avg | C12: 원/중국원(평균) | E12: 185.14 | F12: 177.65 | G12: 189.93 | H12: 190.76 | I12: 195.79 | J12: 191.09 | K12: 191.93 | L12: 186.59 | M12: 187.45 | N12: 181.28 | O12: 182.86 | P12: 184.52 | Q12: 185.04 | R12: 189.35 | S12: 189.24 | T12: 194.24 | U12: 189.49 | V12: 199.63 | W12: 193.41 | X12: 193.79 | Y12: 204.38 | Z12: 197.8 | AA12: 211.75 | AB12: 220.8 | AC12: 210.43 | AD12: 200.49 | AE12: 213.61 | AF12: 200.4 | AG12: 200.4 | AH12: 200.4 | AI12: 200.4 | AK12: 200.4 | AL12: 200.4 | AM12: 200.4 | AN12: 200.4
A13: CNYKRW_end | C13: 원/중국원(기말) | E13: 187.13 | F13: 187.13 | G13: 191.38 | H13: 194.13 | I13: 201.92 | J13: 182.67 | K13: 182.67 | L13: 189.97 | M13: 181.8 | N13: 184.26 | O13: 182.61 | P13: 182.61 | Q13: 186.66 | R13: 189.7 | S13: 187.12 | T13: 202.04 | U13: 202.04 | V13: 203.3 | W13: 189.14 | X13: 197.16 | Y13: 206.28 | Z13: 206.28 | AA13: 220.97 | AB13: 228.56 | AC13: 202.16 | AD13: 200.4 | AE13: 200.4 | AF13: 200.4 | AG13: 200.4 | AH13: 200.4 | AI13: 200.4 | AK13: 200.4 | AL13: 200.4 | AM13: 200.4 | AN13: 200.4
B14: 1b. 종가
A15: price_close_end | C15: 종가(기말) | E15: 8040 | G15: 7950 | H15: 7200 | I15: 4300 | J15: 3915 | L15: 3640 | M15: 4095 | N15: 3650 | O15: 4450 | Q15: 3295 | R15: 3585 | S15: 2655 | T15: 5930 | V15: 5900 | W15: 7950 | X15: 28000 | Y15: 21050 | AA15: 21750 | AB15: 20150 | AC15: 14710 | AD15: 13410
A16: price_high | C16: 종가(최고) | E16: 10500 | G16: 8300 | H16: 8450 | I16: 7260 | J16: 4850 | L16: 4225 | M16: 4285 | N16: 4975 | O16: 4500 | Q16: 4310 | R16: 3785 | S16: 3775 | T16: 7190 | V16: 9900 | W16: 8590 | X16: 34350 | Y16: 33100 | AA16: 29300 | AB16: 33800 | AC16: 20500 | AD16: 15630
A17: price_low | C17: 종가(최저) | E17: 7350 | G17: 6690 | H17: 6500 | I17: 4075 | J17: 3240 | L17: 3290 | M17: 3425 | N17: 3610 | O17: 3270 | Q17: 3250 | R17: 2875 | S17: 2585 | T17: 2180 | V17: 5540 | W17: 5630 | X17: 6950 | Y17: 19650 | AA17: 18800 | AB17: 18400 | AC17: 12910 | AD17: 12630
A18: price_avg | C18: 종가(평균) | E18: 8731.4 | G18: 7593.9 | H18: 7663.9 | I18: 6338.3 | J18: 4026.9 | L18: 3834.4 | M18: 3802.3 | N18: 4042.3 | O18: 3724.7 | Q18: 3575.7 | R18: 3208.9 | S18: 3080.5 | T18: 3454.6 | V18: 6934 | W18: 7398.3 | X18: 16561.2 | Y18: 23805.1 | AA18: 24852.4 | AB18: 24395.1 | AC18: 16326.3 | AD18: 14411.2
B20: 2. 추정 드라이버 | C20: 실적 열 = subQ 실현값(수식), 추정 열 = 가정(노란 = 모델값 역산, 연녹 = 3절 스칼라 참조)
A21: drv:판관비 | B21: ratio | C21: 판관비율(/매출) | E21: =IFERROR(subQ!E8/subQ!E5,"") | F21: =IFERROR(subQ!F8/subQ!F5,"") | G21: =IFERROR(subQ!G8/subQ!G5,"") | H21: =IFERROR(subQ!H8/subQ!H5,"") | I21: =IFERROR(subQ!I8/subQ!I5,"") | J21: =IFERROR(subQ!J8/subQ!J5,"") | K21: =IFERROR(subQ!K8/subQ!K5,"") | L21: =IFERROR(subQ!L8/subQ!L5,"") | ... AB21: =IFERROR(subQ!AB8/subQ!AB5,"") | AC21: =$D$53 | AD21: =$D$53 | AE21: =IFERROR(subQ!AE8/subQ!AE5,"") | AF21: =$D$53 | AG21: =$D$53 | AH21: =$D$53 | AI21: =$D$53 | AJ21: =IFERROR(subQ!AJ8/subQ!AJ5,"") | AK21: =$D$53 | AL21: =$D$53 | AM21: =$D$53 | AN21: =$D$53 | AO21: =IFERROR(subQ!AO8/subQ!AO5,"")
A22: drv:외환손익 | B22: abs | C22: 외환손익 (가정, 억원) | E22: =subQ!E13 | F22: =subQ!F13 | G22: =subQ!G13 | H22: =subQ!H13 | I22: =subQ!I13 | J22: =subQ!J13 | K22: =subQ!K13 | L22: =subQ!L13 | ... AB22: =subQ!AB13 | AC22: 0 | AD22: 0 | AE22: =subQ!AE13 | AF22: 0 | AG22: 0 | AH22: 0 | AI22: 0 | AJ22: =subQ!AJ13 | AK22: 0 | AL22: 0 | AM22: 0 | AN22: 0 | AO22: =subQ!AO13
A23: drv:기타영업외손익 | B23: abs | C23: 기타영업외손익 (가정, 억원) | E23: =subQ!E14 | F23: =subQ!F14 | G23: =subQ!G14 | H23: =subQ!H14 | I23: =subQ!I14 | J23: =subQ!J14 | K23: =subQ!K14 | L23: =subQ!L14 | ... AB23: =subQ!AB14 | AC23: 0 | AD23: 0 | AE23: =subQ!AE14 | AF23: 0 | AG23: 0 | AH23: 0 | AI23: 0 | AJ23: =subQ!AJ14 | AK23: 0 | AL23: 0 | AM23: 0 | AN23: 0 | AO23: =subQ!AO14
A24: drv:법인세비용 | B24: tax | C24: 법인세율(/세전) — 법인세 = MAX(세전,0) × 분기별 세율(이월결손 램프, assumptions.tax_schedule) | E24: =IFERROR(subQ!E16/subQ!E15,"") | F24: =IFERROR(subQ!F16/subQ!F15,"") | G24: =IFERROR(subQ!G16/subQ!G15,"") | H24: =IFERROR(subQ!H16/subQ!H15,"") | I24: =IFERROR(subQ!I16/subQ!I15,"") | J24: =IFERROR(subQ!J16/subQ!J15,"") | K24: =IFERROR(subQ!K16/subQ!K15,"") | L24: =IFERROR(subQ!L16/subQ!L15,"") | ... AB24: =IFERROR(subQ!AB16/subQ!AB15,"") | AC24: 0.004526838 | AD24: 0.004528014 | AE24: =IFERROR(subQ!AE16/subQ!AE15,"") | AF24: 0.031454969 | AG24: 0.058388922 | AH24: 0.085336388 | AI24: 0.1122543 | AJ24: =IFERROR(subQ!AJ16/subQ!AJ15,"") | AK24: 0.13920167 | AL24: 0.16613223 | AM24: 0.19307319 | AN24: 0.2199972 | AO24: =IFERROR(subQ!AO16/subQ!AO15,"")
A25: drv:지배주주순이익 | B25: ratio | C25: 지배주주 비중(/당기순이익) | E25: =IFERROR(subQ!E18/subQ!E17,"") | F25: =IFERROR(subQ!F18/subQ!F17,"") | G25: =IFERROR(subQ!G18/subQ!G17,"") | H25: =IFERROR(subQ!H18/subQ!H17,"") | I25: =IFERROR(subQ!I18/subQ!I17,"") | J25: =IFERROR(subQ!J18/subQ!J17,"") | K25: =IFERROR(subQ!K18/subQ!K17,"") | L25: =IFERROR(subQ!L18/subQ!L17,"") | ... AB25: =IFERROR(subQ!AB18/subQ!AB17,"") | AC25: =$D$54 | AD25: =$D$54 | AE25: =IFERROR(subQ!AE18/subQ!AE17,"") | AF25: =$D$54 | AG25: =$D$54 | AH25: =$D$54 | AI25: =$D$54 | AJ25: =IFERROR(subQ!AJ18/subQ!AJ17,"") | AK25: =$D$54 | AL25: =$D$54 | AM25: =$D$54 | AN25: =$D$54 | AO25: =IFERROR(subQ!AO18/subQ!AO17,"")
A26: drv:중단사업이익 | B26: abs | C26: 중단사업이익 (가정, 억원) | E26: =subQ!E19 | F26: =subQ!F19 | G26: =subQ!G19 | H26: =subQ!H19 | I26: =subQ!I19 | J26: =subQ!J19 | K26: =subQ!K19 | L26: =subQ!L19 | ... AB26: =subQ!AB19 | AE26: =subQ!AE19 | AJ26: =subQ!AJ19 | AO26: =subQ!AO19
A27: drv:부채총계 | B27: qoq | C27: 부채총계 QoQ | G27: =IFERROR(subQ!G21/subQ!E21-1,"") | H27: =IFERROR(subQ!H21/subQ!G21-1,"") | I27: =IFERROR(subQ!I21/subQ!H21-1,"") | J27: =IFERROR(subQ!J21/subQ!I21-1,"") | L27: =IFERROR(subQ!L21/subQ!J21-1,"") | M27: =IFERROR(subQ!M21/subQ!L21-1,"") | N27: =IFERROR(subQ!N21/subQ!M21-1,"") | O27: =IFERROR(subQ!O21/subQ!N21-1,"") | Q27: =IFERROR(subQ!Q21/subQ!O21-1,"") | R27: =IFERROR(subQ!R21/subQ!Q21-1,"") | S27: =IFERROR(subQ!S21/subQ!R21-1,"") | T27: =IFERROR(subQ!T21/subQ!S21-1,"") | V27: =IFERROR(subQ!V21/subQ!T21-1,"") | W27: =IFERROR(subQ!W21/subQ!V21-1,"") | X27: =IFERROR(subQ!X21/subQ!W21-1,"") | Y27: =IFERROR(subQ!Y21/subQ!X21-1,"") | AA27: =IFERROR(subQ!AA21/subQ!Y21-1,"") | AB27: =IFERROR(subQ!AB21/subQ!AA21-1,"") | AC27: 0 | AD27: 0 | AF27: 0 | AG27: 0 | AH27: 0 | AI27: 0 | AK27: 0 | AL27: 0 | AM27: 0 | AN27: 0
A28: drv:자본총계 | B28: roll | C28: 자본총계 기타변동(배당 등, 억원) | G28: =IFERROR(subQ!E22+subQ!G17-subQ!G22,"") | H28: =IFERROR(subQ!G22+subQ!H17-subQ!H22,"") | I28: =IFERROR(subQ!H22+subQ!I17-subQ!I22,"") | J28: =IFERROR(subQ!I22+subQ!J17-subQ!J22,"") | L28: =IFERROR(subQ!J22+subQ!L17-subQ!L22,"") | M28: =IFERROR(subQ!L22+subQ!M17-subQ!M22,"") | N28: =IFERROR(subQ!M22+subQ!N17-subQ!N22,"") | O28: =IFERROR(subQ!N22+subQ!O17-subQ!O22,"") | Q28: =IFERROR(subQ!O22+subQ!Q17-subQ!Q22,"") | R28: =IFERROR(subQ!Q22+subQ!R17-subQ!R22,"") | S28: =IFERROR(subQ!R22+subQ!S17-subQ!S22,"") | T28: =IFERROR(subQ!S22+subQ!T17-subQ!T22,"") | V28: =IFERROR(subQ!T22+subQ!V17-subQ!V22,"") | W28: =IFERROR(subQ!V22+subQ!W17-subQ!W22,"") | X28: =IFERROR(subQ!W22+subQ!X17-subQ!X22,"") | Y28: =IFERROR(subQ!X22+subQ!Y17-subQ!Y22,"") | AA28: =IFERROR(subQ!Y22+subQ!AA17-subQ!AA22,"") | AB28: =IFERROR(subQ!AA22+subQ!AB17-subQ!AB22,"") | AC28: -0.002075406 | AD28: -0.007476581 | AF28: 0.009488244 | AG28: 0.001637916 | AH28: 0.000552315 | AI28: 0.001637795 | AK28: -0.004154874 | AL28: 0.007380463 | AM28: -0.010869227 | AN28: 0.004536662
A29: drv:지배주주지분 | B29: roll | C29: 지배주주지분 기타변동(배당 등, 억원) | G29: =IFERROR(subQ!E23+subQ!G18-subQ!G23,"") | H29: =IFERROR(subQ!G23+subQ!H18-subQ!H23,"") | I29: =IFERROR(subQ!H23+subQ!I18-subQ!I23,"") | J29: =IFERROR(subQ!I23+subQ!J18-subQ!J23,"") | L29: =IFERROR(subQ!J23+subQ!L18-subQ!L23,"") | M29: =IFERROR(subQ!L23+subQ!M18-subQ!M23,"") | N29: =IFERROR(subQ!M23+subQ!N18-subQ!N23,"") | O29: =IFERROR(subQ!N23+subQ!O18-subQ!O23,"") | Q29: =IFERROR(subQ!O23+subQ!Q18-subQ!Q23,"") | R29: =IFERROR(subQ!Q23+subQ!R18-subQ!R23,"") | S29: =IFERROR(subQ!R23+subQ!S18-subQ!S23,"") | T29: =IFERROR(subQ!S23+subQ!T18-subQ!T23,"") | V29: =IFERROR(subQ!T23+subQ!V18-subQ!V23,"") | W29: =IFERROR(subQ!V23+subQ!W18-subQ!W23,"") | X29: =IFERROR(subQ!W23+subQ!X18-subQ!X23,"") | Y29: =IFERROR(subQ!X23+subQ!Y18-subQ!Y23,"") | AA29: =IFERROR(subQ!Y23+subQ!AA18-subQ!AA23,"") | AB29: =IFERROR(subQ!AA23+subQ!AB18-subQ!AB23,"") | AC29: -0.002075406 | AD29: -0.007476581 | AF29: 0.009488244 | AG29: 0.001637916 | AH29: 0.000552315 | AI29: 0.001637795 | AK29: -0.004154874 | AL29: 0.007380463 | AM29: -0.010869227 | AN29: 0.004536662
A30: drv:총차입금 | B30: qoq | C30: 총차입금 QoQ | G30: =IFERROR(subQ!G24/subQ!E24-1,"") | H30: =IFERROR(subQ!H24/subQ!G24-1,"") | I30: =IFERROR(subQ!I24/subQ!H24-1,"") | J30: =IFERROR(subQ!J24/subQ!I24-1,"") | L30: =IFERROR(subQ!L24/subQ!J24-1,"") | M30: =IFERROR(subQ!M24/subQ!L24-1,"") | N30: =IFERROR(subQ!N24/subQ!M24-1,"") | O30: =IFERROR(subQ!O24/subQ!N24-1,"") | Q30: =IFERROR(subQ!Q24/subQ!O24-1,"") | R30: =IFERROR(subQ!R24/subQ!Q24-1,"") | S30: =IFERROR(subQ!S24/subQ!R24-1,"") | T30: =IFERROR(subQ!T24/subQ!S24-1,"") | V30: =IFERROR(subQ!V24/subQ!T24-1,"") | W30: =IFERROR(subQ!W24/subQ!V24-1,"") | X30: =IFERROR(subQ!X24/subQ!W24-1,"") | Y30: =IFERROR(subQ!Y24/subQ!X24-1,"") | AA30: =IFERROR(subQ!AA24/subQ!Y24-1,"") | AB30: =IFERROR(subQ!AB24/subQ!AA24-1,"") | AC30: 0 | AD30: 0 | AF30: 0 | AG30: 0 | AH30: 0 | AI30: 0 | AK30: 0 | AL30: 0 | AM30: 0 | AN30: 0
A31: drv:순차입금 | B31: qoq | C31: 순차입금 QoQ | G31: =IFERROR(subQ!G25/subQ!E25-1,"") | H31: =IFERROR(subQ!H25/subQ!G25-1,"") | I31: =IFERROR(subQ!I25/subQ!H25-1,"") | J31: =IFERROR(subQ!J25/subQ!I25-1,"") | L31: =IFERROR(subQ!L25/subQ!J25-1,"") | M31: =IFERROR(subQ!M25/subQ!L25-1,"") | N31: =IFERROR(subQ!N25/subQ!M25-1,"") | O31: =IFERROR(subQ!O25/subQ!N25-1,"") | Q31: =IFERROR(subQ!Q25/subQ!O25-1,"") | R31: =IFERROR(subQ!R25/subQ!Q25-1,"") | S31: =IFERROR(subQ!S25/subQ!R25-1,"") | T31: =IFERROR(subQ!T25/subQ!S25-1,"") | V31: =IFERROR(subQ!V25/subQ!T25-1,"") | W31: =IFERROR(subQ!W25/subQ!V25-1,"") | X31: =IFERROR(subQ!X25/subQ!W25-1,"") | Y31: =IFERROR(subQ!Y25/subQ!X25-1,"") | AA31: =IFERROR(subQ!AA25/subQ!Y25-1,"") | AB31: =IFERROR(subQ!AB25/subQ!AA25-1,"") | AC31: -0.23126193 | AD31: -0.35660915 | AF31: -0.55617881 | AG31: -1.3170826 | AH31: 3.1594359 | AI31: 0.78355705 | AK31: 0.47894017 | AL31: 0.3478737 | AM31: 0.25051084 | AN31: 0.19533138
A32: drv:이자발생자산 | B32: qoq | C32: 이자발생자산 QoQ | G32: =IFERROR(subQ!G26/subQ!E26-1,"") | H32: =IFERROR(subQ!H26/subQ!G26-1,"") | I32: =IFERROR(subQ!I26/subQ!H26-1,"") | J32: =IFERROR(subQ!J26/subQ!I26-1,"") | L32: =IFERROR(subQ!L26/subQ!J26-1,"") | M32: =IFERROR(subQ!M26/subQ!L26-1,"") | N32: =IFERROR(subQ!N26/subQ!M26-1,"") | O32: =IFERROR(subQ!O26/subQ!N26-1,"") | Q32: =IFERROR(subQ!Q26/subQ!O26-1,"") | R32: =IFERROR(subQ!R26/subQ!Q26-1,"") | S32: =IFERROR(subQ!S26/subQ!R26-1,"") | T32: =IFERROR(subQ!T26/subQ!S26-1,"") | V32: =IFERROR(subQ!V26/subQ!T26-1,"") | W32: =IFERROR(subQ!W26/subQ!V26-1,"") | X32: =IFERROR(subQ!X26/subQ!W26-1,"") | Y32: =IFERROR(subQ!Y26/subQ!X26-1,"") | AA32: =IFERROR(subQ!AA26/subQ!Y26-1,"") | AB32: =IFERROR(subQ!AB26/subQ!AA26-1,"") | AC32: 0.16405789 | AD32: 0.16706646 | AF32: 0.14364501 | AG32: 0.13200972 | AH32: 0.088700229 | AI32: 0.084045011 | AK32: 0.084520541 | AL32: 0.083717341 | AM32: 0.074981397 | AN32: 0.068011997
A33: drv:현금및현금성자산 | B33: qoq | C33: 현금및현금성자산 QoQ | G33: =IFERROR(subQ!G27/subQ!E27-1,"") | H33: =IFERROR(subQ!H27/subQ!G27-1,"") | I33: =IFERROR(subQ!I27/subQ!H27-1,"") | J33: =IFERROR(subQ!J27/subQ!I27-1,"") | L33: =IFERROR(subQ!L27/subQ!J27-1,"") | M33: =IFERROR(subQ!M27/subQ!L27-1,"") | N33: =IFERROR(subQ!N27/subQ!M27-1,"") | O33: =IFERROR(subQ!O27/subQ!N27-1,"") | Q33: =IFERROR(subQ!Q27/subQ!O27-1,"") | R33: =IFERROR(subQ!R27/subQ!Q27-1,"") | S33: =IFERROR(subQ!S27/subQ!R27-1,"") | T33: =IFERROR(subQ!T27/subQ!S27-1,"") | V33: =IFERROR(subQ!V27/subQ!T27-1,"") | W33: =IFERROR(subQ!W27/subQ!V27-1,"") | X33: =IFERROR(subQ!X27/subQ!W27-1,"") | Y33: =IFERROR(subQ!Y27/subQ!X27-1,"") | AA33: =IFERROR(subQ!AA27/subQ!Y27-1,"") | AB33: =IFERROR(subQ!AB27/subQ!AA27-1,"")
A34: drv:CAPEX | B34: yoy | C34: CAPEX YoY | J34: =IFERROR(subQ!J28/subQ!E28-1,"") | L34: =IFERROR(subQ!L28/subQ!G28-1,"") | M34: =IFERROR(subQ!M28/subQ!H28-1,"") | N34: =IFERROR(subQ!N28/subQ!I28-1,"") | O34: =IFERROR(subQ!O28/subQ!J28-1,"") | Q34: =IFERROR(subQ!Q28/subQ!L28-1,"") | R34: =IFERROR(subQ!R28/subQ!M28-1,"") | S34: =IFERROR(subQ!S28/subQ!N28-1,"") | T34: =IFERROR(subQ!T28/subQ!O28-1,"") | V34: =IFERROR(subQ!V28/subQ!Q28-1,"") | W34: =IFERROR(subQ!W28/subQ!R28-1,"") | X34: =IFERROR(subQ!X28/subQ!S28-1,"") | Y34: =IFERROR(subQ!Y28/subQ!T28-1,"") | AA34: =IFERROR(subQ!AA28/subQ!V28-1,"") | AB34: =IFERROR(subQ!AB28/subQ!W28-1,"") | AC34: -0.33298712 | AD34: -0.012303906 | AF34: 0.012614317 | AG34: 0.15711712 | AH34: 0 | AI34: 0 | AK34: 0 | AL34: 0 | AM34: 0 | AN34: 0
A35: drv:영업활동현금흐름 | B35: yoy | C35: 영업활동현금흐름 YoY | J35: =IFERROR(subQ!J29/subQ!E29-1,"") | L35: =IFERROR(subQ!L29/subQ!G29-1,"") | M35: =IFERROR(subQ!M29/subQ!H29-1,"") | N35: =IFERROR(subQ!N29/subQ!I29-1,"") | O35: =IFERROR(subQ!O29/subQ!J29-1,"") | Q35: =IFERROR(subQ!Q29/subQ!L29-1,"") | R35: =IFERROR(subQ!R29/subQ!M29-1,"") | S35: =IFERROR(subQ!S29/subQ!N29-1,"") | T35: =IFERROR(subQ!T29/subQ!O29-1,"") | V35: =IFERROR(subQ!V29/subQ!Q29-1,"") | W35: =IFERROR(subQ!W29/subQ!R29-1,"") | X35: =IFERROR(subQ!X29/subQ!S29-1,"") | Y35: =IFERROR(subQ!Y29/subQ!T29-1,"") | AA35: =IFERROR(subQ!AA29/subQ!V29-1,"") | AB35: =IFERROR(subQ!AB29/subQ!W29-1,"")
A36: drv:주식수 | B36: qoq | C36: 주식수 QoQ | G36: =IFERROR(subQ!G30/subQ!E30-1,"") | H36: =IFERROR(subQ!H30/subQ!G30-1,"") | I36: =IFERROR(subQ!I30/subQ!H30-1,"") | J36: =IFERROR(subQ!J30/subQ!I30-1,"") | L36: =IFERROR(subQ!L30/subQ!J30-1,"") | M36: =IFERROR(subQ!M30/subQ!L30-1,"") | N36: =IFERROR(subQ!N30/subQ!M30-1,"") | O36: =IFERROR(subQ!O30/subQ!N30-1,"") | Q36: =IFERROR(subQ!Q30/subQ!O30-1,"") | R36: =IFERROR(subQ!R30/subQ!Q30-1,"") | S36: =IFERROR(subQ!S30/subQ!R30-1,"") | T36: =IFERROR(subQ!T30/subQ!S30-1,"") | V36: =IFERROR(subQ!V30/subQ!T30-1,"") | W36: =IFERROR(subQ!W30/subQ!V30-1,"") | X36: =IFERROR(subQ!X30/subQ!W30-1,"") | Y36: =IFERROR(subQ!Y30/subQ!X30-1,"") | AA36: =IFERROR(subQ!AA30/subQ!Y30-1,"") | AB36: =IFERROR(subQ!AB30/subQ!AA30-1,"") | AC36: 0 | AD36: 0 | AF36: 0 | AG36: 0 | AH36: 0 | AI36: 0 | AK36: 0 | AL36: 0 | AM36: 0 | AN36: 0
A37: drv:DPS | B37: abs | C37: DPS (가정, 원) | E37: =subQ!E33 | F37: =subQ!F33 | G37: =subQ!G33 | H37: =subQ!H33 | I37: =subQ!I33 | J37: =subQ!J33 | K37: =subQ!K33 | L37: =subQ!L33 | ... AB37: =subQ!AB33 | AD37: 0 | AE37: =subQ!AE33 | AI37: 0 | AJ37: =subQ!AJ33 | AN37: 0 | AO37: =subQ!AO33
A38: drv:매출조선 | B38: sls_link | C38: 원장 밖 잔고 소진(억원) — 매출조선 = SLS 원화/100 + 이 행 + 매출조선신규 | E38: =IFERROR(subQ!E36-SLS!S122/100,"") | G38: =IFERROR(subQ!G36-SLS!T122/100,"") | H38: =IFERROR(subQ!H36-SLS!U122/100,"") | I38: =IFERROR(subQ!I36-SLS!V122/100,"") | J38: =IFERROR(subQ!J36-SLS!W122/100,"") | L38: =IFERROR(subQ!L36-SLS!X122/100,"") | M38: =IFERROR(subQ!M36-SLS!Y122/100,"") | N38: =IFERROR(subQ!N36-SLS!Z122/100,"") | O38: =IFERROR(subQ!O36-SLS!AA122/100,"") | Q38: =IFERROR(subQ!Q36-SLS!AB122/100,"") | R38: =IFERROR(subQ!R36-SLS!AC122/100,"") | S38: =IFERROR(subQ!S36-SLS!AD122/100,"") | T38: =IFERROR(subQ!T36-SLS!AE122/100,"") | V38: =IFERROR(subQ!V36-SLS!AF122/100,"") | W38: =IFERROR(subQ!W36-SLS!AG122/100,"") | X38: =IFERROR(subQ!X36-SLS!AH122/100,"") | Y38: =IFERROR(subQ!Y36-SLS!AI122/100,"") | AA38: =IFERROR(subQ!AA36-SLS!AJ122/100,"") | AB38: =IFERROR(subQ!AB36-SLS!AK122/100,"") | AC38: 2224.2304 | AD38: 2797.9984 | AF38: 2783.7197 | AG38: 2790.7389 | AH38: 919.55968 | AI38: 644.71968 | AK38: 637.73891 | AL38: 637.73891 | AM38: 644.73862 | AN38: 644.76739
A39: drv:매출조선신규 | B39: abs | C39: 매출조선신규 (공시 계약 원장 체결 속도 폴백 신규수주 매출, 억원 — 가정) | E39: =subQ!E37 | F39: =subQ!F37 | G39: =subQ!G37 | H39: =subQ!H37 | I39: =subQ!I37 | J39: =subQ!J37 | K39: =subQ!K37 | L39: =subQ!L37 | ... AB39: =subQ!AB37 | AC39: 0 | AD39: 0 | AE39: =subQ!AE37 | AF39: 102.88 | AG39: 381.61 | AH39: 791.37 | AI39: 1287.31 | AJ39: =subQ!AJ37 | AK39: 1824.59 | AL39: 2358.38 | AM39: 2843.84 | AN39: 3236.14 | AO39: =subQ!AO37
A40: drv:OP조선 | B40: ratio | C40: OP조선 마진(/매출조선) | E40: =IFERROR(subQ!E38/subQ!E36,"") | F40: =IFERROR(subQ!F38/subQ!F36,"") | G40: =IFERROR(subQ!G38/subQ!G36,"") | H40: =IFERROR(subQ!H38/subQ!H36,"") | I40: =IFERROR(subQ!I38/subQ!I36,"") | J40: =IFERROR(subQ!J38/subQ!J36,"") | K40: =IFERROR(subQ!K38/subQ!K36,"") | L40: =IFERROR(subQ!L38/subQ!L36,"") | ... AB40: =IFERROR(subQ!AB38/subQ!AB36,"") | AC40: 0.09015805 | AD40: 0.095074961 | AE40: =IFERROR(subQ!AE38/subQ!AE36,"") | AF40: 0.096055981 | AG40: 0.097964892 | AH40: 0.098786984 | AI40: 0.099639189 | AJ40: =IFERROR(subQ!AJ38/subQ!AJ36,"") | AK40: 0.10093529 | AL40: 0.1016269 | AM40: 0.099193318 | AN40: 0.097282324 | AO40: =IFERROR(subQ!AO38/subQ!AO36,"")
A41: drv:매출기타 | B41: yoy | C41: 매출기타 YoY | J41: =IFERROR(subQ!J40/subQ!E40-1,"") | L41: =IFERROR(subQ!L40/subQ!G40-1,"") | M41: =IFERROR(subQ!M40/subQ!H40-1,"") | N41: =IFERROR(subQ!N40/subQ!I40-1,"") | O41: =IFERROR(subQ!O40/subQ!J40-1,"") | Q41: =IFERROR(subQ!Q40/subQ!L40-1,"") | R41: =IFERROR(subQ!R40/subQ!M40-1,"") | S41: =IFERROR(subQ!S40/subQ!N40-1,"") | T41: =IFERROR(subQ!T40/subQ!O40-1,"") | V41: =IFERROR(subQ!V40/subQ!Q40-1,"") | W41: =IFERROR(subQ!W40/subQ!R40-1,"") | X41: =IFERROR(subQ!X40/subQ!S40-1,"") | Y41: =IFERROR(subQ!Y40/subQ!T40-1,"") | AA41: =IFERROR(subQ!AA40/subQ!V40-1,"") | AB41: =IFERROR(subQ!AB40/subQ!W40-1,"") | AC41: 0.092004263 | AD41: 0 | AF41: 0 | AG41: -0.18588266 | AH41: 0 | AI41: 0 | AK41: 0 | AL41: 0 | AM41: 0 | AN41: 0
A42: drv:OP기타 | B42: ratio | C42: OP기타 마진(/매출기타) | E42: =IFERROR(subQ!E41/subQ!E40,"") | F42: =IFERROR(subQ!F41/subQ!F40,"") | G42: =IFERROR(subQ!G41/subQ!G40,"") | H42: =IFERROR(subQ!H41/subQ!H40,"") | I42: =IFERROR(subQ!I41/subQ!I40,"") | J42: =IFERROR(subQ!J41/subQ!J40,"") | K42: =IFERROR(subQ!K41/subQ!K40,"") | L42: =IFERROR(subQ!L41/subQ!L40,"") | ... AB42: =IFERROR(subQ!AB41/subQ!AB40,"") | AC42: 0.090155665 | AD42: 0.095075448 | AE42: =IFERROR(subQ!AE41/subQ!AE40,"") | AF42: 0.096058671 | AG42: 0.097966416 | AH42: 0.098788215 | AI42: 0.099635694 | AJ42: =IFERROR(subQ!AJ41/subQ!AJ40,"") | AK42: 0.10093443 | AL42: 0.10162782 | AM42: 0.099195445 | AN42: 0.097280362 | AO42: =IFERROR(subQ!AO41/subQ!AO40,"")
B44: 3. 밸류에이션·스칼라 | C44: 노란 셀 = 가정. '연결' 표시는 추정 전 분기 수식이 이 셀을 참조한다는 뜻
A45: sc:종가 | C45: 종가 | D45: 13410 | E45: 원 — 네이버 정규장 종가(aik 확정종가 대조 · aik 13,500원)
A46: sc:기준일 | C46: 기준일 | D46: 20261014 | E46: 종가 기준일
A47: sc:COE | C47: COE | D47: 0.09 | E47: 자기자본비용(가정) — TP 적정 PBR = ROE/COE
A48: sc:PER_lo | C48: PER_lo | D48: 15.6 | E48: PER 밴드 하단(배) — hist_quarterly(분기 평균가 ÷ TTM EPS, 6분기, 25/50/75 백분위) · 캡 5~30배 적용(원값 15.6/25.6/41.6)
A49: sc:PER_mid | C49: PER_mid | D49: 25.6 | E49: PER 밴드 중단(배)
A50: sc:PER_hi | C50: PER_hi | D50: 30 | E50: PER 밴드 상단(배)
A51: sc:EPS_Y1가중 | C51: EPS_Y1가중 | D51: 0.5 | E51: 12M fwd EPS = FY(last_actual연도)E × w + FY+1E × (1−w) — 기준 분기 2Q 이면 0.5(가정)
A52: sc:세율 | C52: 세율 | D52: 0.0045 | E52: 참고(연결 안 됨: 이월결손 램프(assumptions.tax_schedule, 0.45%→22%) — 분기별 세율 드라이버 행 사용) — 모델 assumptions 값(시작 0.45% → terminal 22%, 2026Q4 까지 유지 → 2027Q1~2028Q4 선형 램프 — 분기별 값은 2절 drv:법인세비용 행) · 최근 8분기 중 세전 > 0 인 6분기(2024Q3~2026Q2) 법인세/세전 중위 0.5%·최근 4분기 중위 0.1% 가 모두 5% 미만 → 이월결손 공제 중으로 보고 0.5% 를 2026Q4 까지 유지, 2027Q1~2028Q4 선형 램프로 법정세율 근사 22% 수렴
A53: sc:판관비율 | C53: 판관비율 | D53: 0.053597233 | E53: 연결 — 판관비 = 매출액 × 판관비율(역산, 재현 오차 ≤ 0.05억 · 모델 assumptions 0.0536)
A54: sc:지배주주비중 | C54: 지배주주비중 | D54: 1 | E54: 연결 — 지배주주순이익 = 당기순이익 × 비중(역산, 재현 오차 ≤ 0.05억)
A55: sc:이자율_자산 | C55: 이자율_자산 | D55: 0.032347975 | E55: 연결 — 이자손익 = (전분기 이자발생자산 × 자산이자율 − 전분기 총차입금 × 부채이자율)/4(역산, 재현 오차 ≤ 0.05억 · 모델 assumptions 0.0323)
A56: sc:이자율_부채 | C56: 이자율_부채 | D56: 0.078703903 | E56: 연결 — 같은 수식의 부채 쪽(총차입금 행이 없으면 0)(역산, 재현 오차 ≤ 0.05억 · 모델 assumptions 0.0787)
A57: sc:배당성향 | C57: 배당성향 | D57: 0 | E57: 배당성향(참고 — 모델은 직전 DPS 유지·Q2 지급 가정)
A58: sc:외화순노출_백만$ | C58: 외화순노출_백만$ | E58: 외화 순노출 × Δ기말환율 (외화 시트 방식) — 외화 순노출 미공시(face) → 0 + 표기
A59: sc:헤지비율 | C59: 헤지비율 | D59: 0.7 | E59: SLS 원화 = Σ 스케줄 × (헤지비율 × 헤지환율 + (1−헤지비율) × 건조시점 환율[원/달러(평균)]) — estimate · 통화선도 공시 없음 → HEDGE 70% 가정(레퍼런스 SLS 시트 HEDGE 행은 미포 65%·삼성重 100% — 그 사이에 둔 설정값). hedge_rate 는 계약별 수주시점 환율로 대체
A60: sc:헤지환율_약정 | C60: 헤지환율_약정 | E60: 정기보고서 평균 약정환율(measured) — 비어 있으면 계약별 수주시점 환율(fx_at_sign)을 쓴다

Sheet BS연결
B1: (백만원) | C1: 이름: BS연결H | E1: 4Q21 | F1: 2021 | G1: 1Q22 | H1: 2Q22 | I1: 3Q22 | J1: 4Q22 | K1: 2022 | L1: 1Q23 | M1: 2Q23 | N1: 3Q23 | O1: 4Q23 | P1: 2023 | Q1: 1Q24 | R1: 2Q24 | S1: 3Q24 | T1: 4Q24 | U1: 2024 | V1: 1Q25 | W1: 2Q25 | X1: 3Q25 | Y1: 4Q25 | Z1: 2025 | AA1: 1Q26 | AB1: 2Q26 | AC1: 3Q26 | AD1: 4Q26 | AE1: 2026 | AF1: 1Q27 | AG1: 2Q27 | AH1: 3Q27 | AI1: 4Q27 | AJ1: 2027 | AK1: 1Q28 | AL1: 2Q28 | AM1: 3Q28 | AN1: 4Q28 | AO1: 2028
B2: 연결 | D2: fin json(kship_fin.py)
B3: HJ중공업(연) | C3: UPDATE: 26-10-14 | E3: 1 | F3: 2 | G3: 3 | H3: 4 | I3: 5 | J3: 6 | K3: 7 | L3: 8 | M3: 9 | N3: 10 | O3: 11 | P3: 12 | Q3: 13 | R3: 14 | S3: 15 | T3: 16 | U3: 17 | V3: 18 | W3: 19 | X3: 20 | Y3: 21 | Z3: 22 | AA3: 23 | AB3: 24 | AC3: 25 | AD3: 26 | AE3: 27 | AF3: 28 | AG3: 29 | AH3: 30 | AI3: 31 | AJ3: 32 | AK3: 33 | AL3: 34 | AM3: 35 | AN3: 36 | AO3: 37
B4: Account Code | C4: AccountNAME | E4: 2021.12 | F4: 2021.12A | G4: 2022.03 | H4: 2022.06 | I4: 2022.09 | J4: 2022.12 | K4: 2022.12A | L4: 2023.03 | M4: 2023.06 | N4: 2023.09 | O4: 2023.12 | P4: 2023.12A | Q4: 2024.03 | R4: 2024.06 | S4: 2024.09 | T4: 2024.12 | U4: 2024.12A | V4: 2025.03 | W4: 2025.06 | X4: 2025.09 | Y4: 2025.12 | Z4: 2025.12A | AA4: 2026.03 | AB4: 2026.06 | AC4: 2026.09 | AD4: 2026.12 | AE4: 2026.12A | AF4: 2027.03 | AG4: 2027.06 | AH4: 2027.09 | AI4: 2027.12 | AJ4: 2027.12A | AK4: 2028.03 | AL4: 2028.06 | AM4: 2028.09 | AN4: 2028.12 | AO4: 2028.12A
A5: 1 | C5: 유동자산 | E5: 948999 | F5: 948999 | G5: 934919 | H5: 905536 | I5: 919574 | J5: 1430318 | K5: 1430318 | L5: 1527237 | M5: 1499074 | N5: 1721672 | O5: 1727429 | P5: 1727429 | Q5: 1684956 | R5: 1604577 | S5: 1043559 | T5: 1073183 | U5: 1073183 | V5: 1087315 | W5: 1150434 | X5: 1161936 | Y5: 1258882 | Z5: 1258882 | AA5: 1259495 | AB5: 1444391
A6: 1 | C6: 현금및현금성자산 | E6: 118309 | F6: 118309 | G6: 117115 | H6: 136160 | I6: 82734 | J6: 102233 | K6: 102233 | L6: 151777 | M6: 129563 | N6: 354177 | O6: 350257 | P6: 350257 | Q6: 286569 | R6: 257006 | S6: 195208 | T6: 207128 | U6: 207128 | V6: 80370 | W6: 170190 | X6: 202147 | Y6: 332206 | Z6: 332206 | AA6: 163666 | AB6: 249747
A7: 1 | C7: 단기금융상품 | E7: 45186 | F7: 45186 | G7: 39745 | H7: 27373 | I7: 22968 | J7: 53406 | K7: 53406 | L7: 16846 | M7: 12287 | N7: 12344 | O7: 12562 | P7: 12562 | Q7: 12582 | R7: 11366 | S7: 32232 | T7: 24244 | U7: 24244 | V7: 32937 | W7: 43023 | X7: 32489 | AA7: 22279 | AB7: 25642
A8: 1 | C8: 단기금융자산 | E8: 45186 | F8: 45186 | G8: 39745 | H8: 27373 | I8: 22968 | J8: 53406 | K8: 53406 | L8: 16846 | M8: 12287 | N8: 12344 | O8: 12562 | P8: 12562 | Q8: 12582 | R8: 11366 | S8: 32232 | T8: 24244 | U8: 24244 | V8: 32937 | W8: 43023 | X8: 32489 | AA8: 22279 | AB8: 25642
A9: 1 | C9: 매출채권및기타채권 | E9: 125946 | F9: 125946 | G9: 81033 | H9: 111314 | I9: 120201 | J9: 191243 | K9: 191243 | L9: 174100 | M9: 140661 | N9: 88754 | O9: 187650 | P9: 187650 | Q9: 202263 | R9: 206662 | S9: 134221 | T9: 140270 | U9: 140270 | V9: 152468 | W9: 165509 | X9: 152458 | Y9: 182938 | Z9: 182938 | AA9: 149796 | AB9: 186655
A10: 1 | C10: 계약자산 | E10: 267748 | F10: 267748 | G10: 244889 | H10: 158347 | I10: 217745 | J10: 233295 | K10: 233295 | L10: 220328 | M10: 268614 | N10: 330340 | O10: 387498 | P10: 387498 | Q10: 288610 | R10: 267775 | S10: 210411 | T10: 274766 | U10: 274766 | V10: 270254 | W10: 244218 | X10: 219922 | Y10: 225908 | Z10: 225908 | AA10: 371333 | AB10: 419831
A11: 1 | C11: 선급금 | E11: 149511 | F11: 149511 | G11: 197216 | H11: 195378 | I11: 186976 | J11: 166055 | K11: 166055 | L11: 213315 | M11: 213426 | N11: 194801 | O11: 204693 | P11: 204693 | Q11: 290391 | R11: 278756 | S11: 290243 | T11: 250695 | U11: 250695 | V11: 343448 | W11: 316910 | X11: 326142 | Y11: 272035 | Z11: 272035 | AA11: 313316 | AB11: 324473
A12: 1 | C12: 선급금등 | E12: 149511 | F12: 149511 | G12: 197216 | H12: 195378 | I12: 186976 | J12: 166055 | K12: 166055 | L12: 213315 | M12: 213426 | N12: 194801 | O12: 204693 | P12: 204693 | Q12: 290391 | R12: 278756 | S12: 290243 | T12: 250695 | U12: 250695 | V12: 343448 | W12: 316910 | X12: 326142 | Y12: 272035 | Z12: 272035 | AA12: 313316 | AB12: 324473
A13: 1 | C13: 기타유동자산 | E13: 211903 | F13: 211903 | G13: 265279 | H13: 260427 | I13: 249701 | J13: 226637 | K13: 226637 | L13: 281024 | M13: 273368 | N13: 251191 | O13: 261430 | P13: 261430 | Q13: 357675 | R13: 337450 | S13: 349685 | T13: 315072 | U13: 315072 | V13: 416850 | W13: 398286 | X13: 413773 | Y13: 357976 | Z13: 357976 | AA13: 415652 | AB13: 424375
A14: 1 | C14: 재고자산 | E14: 147110 | F14: 147110 | G14: 149202 | H14: 181122 | I14: 210942 | J14: 200698 | K14: 200698 | L14: 220097 | M14: 249327 | N14: 235852 | O14: 135297 | P14: 135297 | Q14: 146227 | R14: 134224 | S14: 115631 | T14: 105441 | U14: 105441 | V14: 125217 | W14: 120608 | X14: 122852 | Y14: 115769 | Z14: 115769 | AA14: 122106 | AB14: 125168
A15: 1 | C15: 기타유동금융자산 | E15: 32717 | F15: 32717 | G15: 27576 | H15: 20713 | I15: 15203 | J15: 33262 | K15: 33262 | L15: 33560 | M15: 15757 | N15: 6042 | O15: 8897 | P15: 8897 | Q15: 7199 | R15: 6269 | S15: 6091 | T15: 6262 | U15: 6262 | V15: 9219 | W15: 8600 | X15: 18295 | Y15: 17966 | Z15: 17966 | AA15: 14663 | AB15: 12973
A16: 1 | C16: 매각예정비유동자산및처분자산 | E16: 80 | F16: 80 | G16: 80 | H16: 80 | I16: 80 | J16: 379542 | K16: 379542 | L16: 379542 | M16: 379542 | N16: 379542 | O16: 379542 | P16: 379542 | Q16: 379542 | R16: 379542 | S16: 80 | T16: 0 | U16: 0 | Y16: 0 | Z16: 0
A17: 1 | C17: 비유동자산 | E17: 1436237 | F17: 1436237 | G17: 1437022 | H17: 1499898 | I17: 1508661 | J17: 1137379 | K17: 1137379 | L17: 1117654 | M17: 1124410 | N17: 1056109 | O17: 1163156 | P17: 1163156 | Q17: 1167916 | R17: 1159935 | S17: 1143077 | T17: 1131246 | U17: 1131246 | V17: 1132069 | W17: 1134733 | X17: 1126095 | Y17: 1194200 | Z17: 1194200 | AA17: 1192015 | AB17: 1199989
A18: 1 | C18: 종속기업및관계기업투자 | E18: 36250 | F18: 36250 | G18: 36057 | H18: 45863 | I18: 45985 | J18: 45985 | K18: 45985 | L18: 46138 | M18: 61401 | N18: 59818 | O18: 61737 | P18: 61737 | Q18: 59238 | R18: 60312 | S18: 57373 | T18: 52170 | U18: 52170 | V18: 58501 | W18: 60396 | X18: 39989 | Y18: 39086 | Z18: 39086 | AA18: 38893 | AB18: 40702
A19: 1 | C19: 투자자산 | E19: 88694 | F19: 88694 | G19: 90602 | H19: 109543 | I19: 130421 | J19: 130707 | K19: 130707 | L19: 142903 | M19: 150247 | N19: 151509 | O19: 156794 | P19: 156794 | Q19: 156218 | R19: 150884 | S19: 140633 | T19: 135418 | U19: 135418 | V19: 145936 | W19: 144027 | X19: 135210 | Y19: 115422 | Z19: 115422 | AA19: 119305 | AB19: 123529
A20: 1 | C20: 유형자산 | E20: 923488 | F20: 923488 | G20: 925918 | H20: 969278 | I20: 973379 | J20: 644984 | K20: 644984 | L20: 643554 | M20: 642554 | N20: 642000 | O20: 745840 | P20: 745840 | Q20: 745993 | R20: 743881 | S20: 742429 | T20: 740427 | U20: 740427 | V20: 738843 | W20: 738493 | X20: 740851 | Y20: 822328 | Z20: 822328 | AA20: 821228 | AB20: 823995
A21: 1 | C21: 투자부동산 | E21: 59891 | F21: 59891 | G21: 59798 | H21: 59704 | I21: 59611 | J21: 10643 | K21: 10643 | L21: 10643 | M21: 10643 | N21: 10643 | O21: 56345 | P21: 56345 | Q21: 55337 | R21: 52374 | S21: 50605 | T21: 48478 | U21: 48478 | V21: 46700 | W21: 44918 | X21: 43541 | Y21: 42005 | Z21: 42005 | AA21: 38820 | AB21: 38488
A22: 1 | C22: 무형자산 | E22: 6209 | F22: 6209 | G22: 6094 | H22: 5979 | I22: 5865 | J22: 5748 | K22: 5748 | L22: 5635 | M22: 6224 | N22: 5536 | O22: 5416 | P22: 5416 | Q22: 5301 | R22: 5168 | S22: 5053 | T22: 4940 | U22: 4940 | V22: 4825 | W22: 4708 | X22: 4593 | Y22: 4479 | Z22: 4479 | AA22: 4364 | AB22: 4249
A23: 1 | C23: 장기대여금 | E23: 44026 | F23: 44026 | G23: 47165 | H23: 60983 | I23: 79778 | J23: 80036 | K23: 80036 | L23: 85839 | M23: 80538 | N23: 83411 | O23: 87206 | P23: 87206 | Q23: 88692 | R23: 87067 | S23: 81840 | T23: 79469 | U23: 79469 | V23: 83954 | W23: 80064 | X23: 89654 | Y23: 71374 | Z23: 71374 | AA23: 75590 | AB23: 76730
A24: 1 | C24: 사용권자산 | E24: 185908 | F24: 185908 | G24: 184257 | H24: 183731 | I24: 183002 | J24: 181681 | K24: 181681 | L24: 180966 | M24: 180233 | N24: 93155 | O24: 46514 | P24: 46514 | Q24: 44015 | R24: 44146 | S24: 42273 | T24: 41620 | U24: 41620 | V24: 39488 | W24: 47924 | X24: 45908 | Y24: 43870 | Z24: 43870 | AA24: 43124 | AB24: 39979
A25: 1 | C25: 기타비유동자산 | E25: 224791 | F25: 224791 | G25: 222252 | H25: 223165 | I25: 206634 | J25: 210622 | K25: 210622 | L25: 210867 | M25: 211254 | N25: 134434 | O25: 89941 | P25: 89941 | Q25: 91352 | R25: 92884 | S25: 89490 | T25: 84698 | U25: 84698 | V25: 79002 | W25: 85538 | X25: 84270 | Y25: 92026 | Z25: 92026 | AA25: 90614 | AB25: 91902
A26: 1 | C26: 장기매출채권및기타채권 | E26: 339 | F26: 339 | G26: 346 | H26: 0 | I26: 0 | J26: 0 | K26: 0 | O26: 0 | P26: 0 | T26: 0 | U26: 0 | Y26: 0 | Z26: 0
A27: 1 | C27: 장기금융자산 | E27: 8418 | F27: 8418 | G27: 7380 | H27: 2697 | I27: 4658 | J27: 4686 | K27: 4686 | L27: 10926 | M27: 8308 | N27: 8280 | O27: 7851 | P27: 7851 | Q27: 8288 | R27: 3505 | S27: 1420 | T27: 3779 | U27: 3779 | V27: 3481 | W27: 3567 | X27: 5567 | Y27: 4962 | Z27: 4962 | AA27: 4822 | AB27: 6097
A28: 1 | C28: 자산총계 | E28: 2385236 | F28: 2385236 | G28: 2371941 | H28: 2405434 | I28: 2428235 | J28: 2567697 | K28: 2567697 | L28: 2644891 | M28: 2623484 | N28: 2777781 | O28: 2890585 | P28: 2890585 | Q28: 2852872 | R28: 2764512 | S28: 2186636 | T28: 2204429 | U28: 2204429 | V28: 2219384 | W28: 2285167 | X28: 2288031 | Y28: 2453082 | Z28: 2453082 | AA28: 2451510 | AB28: 2644380
A29: 1 | C29: 유동부채 | E29: 949994 | F29: 949994 | G29: 934823 | H29: 892571 | I29: 1034810 | J29: 1418222 | K29: 1418222 | L29: 1555760 | M29: 2141496 | N29: 2133838 | O29: 2125811 | P29: 2125811 | Q29: 2066092 | R29: 2017808 | S29: 1485051 | T29: 1555136 | U29: 1555136 | V29: 1560570 | W29: 1577354 | X29: 1585489 | Y29: 1491810 | Z29: 1491810 | AA29: 1458784 | AB29: 1391706
A30: 1 | C30: 매입채무및기타채무 | E30: 314782 | F30: 314782 | G30: 257206 | H30: 260808 | I30: 262620 | J30: 330500 | K30: 330500 | L30: 353136 | M30: 405750 | N30: 396293 | O30: 475323 | P30: 475323 | Q30: 436846 | R30: 511763 | S30: 381001 | T30: 386632 | U30: 386632 | V30: 393985 | W30: 409447 | X30: 439740 | Y30: 399070 | Z30: 399070 | AA30: 397446 | AB30: 401860
A31: 1 | C31: 유동성장기부채 | E31: 150785 | F31: 150785 | G31: 150785 | H31: 70785 | I31: 70785 | J31: 70785 | K31: 70785 | L31: 123685 | M31: 657143 | N31: 662313 | O31: 656520 | P31: 656520 | Q31: 662635 | R31: 623770 | S31: 452151 | T31: 70178 | U31: 70178 | V31: 68176 | W31: 65926 | X31: 62896 | Y31: 87896 | Z31: 87896 | AA31: 87896 | AB31: 42646
A32: 1 | C32: 계약부채 | E32: 298803 | F32: 298803 | G32: 356841 | H32: 401262 | I32: 372818 | J32: 472547 | K32: 472547 | L32: 554724 | M32: 546181 | N32: 711032 | O32: 616653 | P32: 616653 | Q32: 635090 | R32: 578712 | S32: 457810 | T32: 507566 | U32: 507566 | V32: 518746 | W32: 618176 | X32: 607326 | Y32: 542275 | Z32: 542275 | AA32: 519638 | AB32: 565272
A33: 1 | C33: 단기충당부채 | E33: 143937 | F33: 143937 | G33: 124560 | H33: 113702 | I33: 100629 | J33: 131793 | K33: 131793 | L33: 113111 | M33: 127901 | N33: 119811 | O33: 132953 | P33: 132953 | Q33: 86857 | R33: 65063 | S33: 55403 | T33: 71805 | U33: 71805 | V33: 66097 | W33: 59700 | X33: 59636 | Y33: 50616 | Z33: 50616 | AA33: 44973 | AB33: 47563
A34: 1 | C34: 기타유동금융부채 | E34: 28688 | F34: 28688 | G34: 28765 | H34: 29401 | I34: 194259 | J34: 193791 | K34: 193791 | L34: 193875 | M34: 194121 | N34: 33779 | O34: 35581 | P34: 35581 | Q34: 36656 | R34: 31943 | S34: 29211 | T34: 28368 | U34: 28368 | V34: 30245 | W34: 31776 | X34: 29285 | Y34: 29616 | Z34: 29616 | AA34: 31985 | AB34: 35734
A35: 1 | C35: 단기금융부채 | E35: 28688 | F35: 28688 | G35: 28765 | H35: 29401 | I35: 194259 | J35: 193791 | K35: 193791 | L35: 193875 | M35: 194121 | N35: 33779 | O35: 35581 | P35: 35581 | Q35: 36656 | R35: 31943 | S35: 29211 | T35: 28368 | U35: 28368 | V35: 30245 | W35: 31776 | X35: 29285 | Y35: 29616 | Z35: 29616 | AA35: 31985 | AB35: 35734
A36: 1 | C36: 기타유동부채 | E36: 12999 | F36: 12999 | G36: 16666 | H36: 16613 | I36: 33699 | J36: 218806 | K36: 218806 | L36: 217229 | M36: 210400 | N36: 210610 | O36: 208781 | P36: 208781 | Q36: 208008 | R36: 206557 | S36: 109475 | T36: 108840 | U36: 108840 | V36: 109148 | W36: 110152 | X36: 110513 | Y36: 111817 | Z36: 111817 | AA36: 109403 | AB36: 108598
A37: 1 | C37: 비유동부채 | E37: 1003237 | F37: 1003237 | G37: 1015066 | H37: 1105384 | I37: 1006201 | J37: 764485 | K37: 764485 | L37: 728779 | M37: 201420 | N37: 367906 | O37: 423862 | P37: 423862 | Q37: 432029 | R37: 433452 | S37: 335929 | T37: 305896 | U37: 305896 | V37: 310079 | W37: 364169 | X37: 355236 | Y37: 291684 | Z37: 291684 | AA37: 298775 | AB37: 499746
A38: 1 | C38: 사채 | E38: 28455 | F38: 28455 | G38: 28695 | H38: 28937 | I38: 29179 | J38: 29421 | K38: 29421 | L38: 29664 | M38: 0 | N38: 0 | O38: 0 | P38: 0 | T38: 0 | U38: 0 | Y38: 0 | Z38: 0
A39: 1 | C39: 장기차입금 | E39: 501064 | F39: 501064 | G39: 504714 | H39: 512205 | I39: 575853 | J39: 551007 | K39: 551007 | L39: 502539 | M39: 1571 | N39: 785 | O39: 25785 | P39: 25785 | Q39: 25785 | R39: 25785 | S39: 25000 | T39: 25000 | U39: 25000 | V39: 25000 | W39: 68428 | X39: 68610 | Y39: 43798 | Z39: 43798 | AA39: 43987 | AB39: 242397
A40: 1 | C40: 확정급여부채 | E40: 60832 | F40: 60832 | G40: 70087 | H40: 72630 | I40: 74669 | J40: 63747 | K40: 63747 | L40: 73192 | M40: 75422 | N40: 77765 | O40: 80222 | P40: 80222 | Q40: 88247 | R40: 90644 | S40: 94025 | T40: 92436 | U40: 92436 | V40: 101442 | W40: 104137 | X40: 107500 | Y40: 76072 | Z40: 76072 | AA40: 86530 | AB40: 89731
A41: 1 | C41: 장기충당부채 | E41: 17572 | F41: 17572 | G41: 16835 | H41: 16488 | I41: 17164 | J41: 17439 | K41: 17439 | L41: 18800 | M41: 20162 | N41: 19697 | O41: 24224 | P41: 24224 | Q41: 26319 | R41: 27245 | S41: 27155 | T41: 0 | U41: 0 | Y41: 0 | Z41: 0
A42: 1 | C42: 이연법인세부채 | E42: 84194 | F42: 84194 | G42: 84194 | H42: 84194 | I42: 84194 | J42: 80368 | K42: 80368 | L42: 80367 | M42: 80367 | N42: 80367 | O42: 104537 | P42: 104537 | Q42: 104430 | R42: 104391 | S42: 104525 | T42: 104525 | U42: 104525 | V42: 104448 | W42: 104430 | X42: 104524 | Y42: 100060 | Z42: 100060 | AA42: 99944 | AB42: 99894
A43: 1 | C43: 기타비유동금융부채 | E43: 183575 | F43: 183575 | G43: 182872 | H43: 182638 | I43: 17647 | J43: 17121 | K43: 17121 | L43: 18668 | M43: 18183 | N43: 79319 | O43: 77909 | P43: 77909 | Q43: 75874 | R43: 73823 | S43: 68937 | T43: 66884 | U43: 66884 | V43: 61184 | W43: 66730 | X43: 63186 | Y43: 60922 | Z43: 60922 | AA43: 57191 | AB43: 54142
A44: 1 | C44: 장기금융부채 | E44: 183575 | F44: 183575 | G44: 182872 | H44: 182638 | I44: 17647 | J44: 17121 | K44: 17121 | L44: 18668 | M44: 18183 | N44: 79319 | O44: 77909 | P44: 77909 | Q44: 75874 | R44: 73823 | S44: 68937 | T44: 66884 | U44: 66884 | V44: 61184 | W44: 66730 | X44: 63186 | Y44: 60922 | Z44: 60922 | AA44: 57191 | AB44: 54142
A45: 1 | C45: 기타비유동부채 | E45: 127545 | F45: 127545 | G45: 127669 | H45: 208292 | I45: 207495 | J45: 5382 | K45: 5382 | L45: 5549 | M45: 5715 | N45: 109973 | O45: 111185 | P45: 111185 | Q45: 111374 | R45: 111564 | S45: 6140 | T45: 8806 | U45: 8806 | V45: 9058 | W45: 9310 | X45: 8860 | Y45: 10832 | Z45: 10832 | AA45: 11123 | AB45: 11414
A46: 1 | C46: 부채총계 | E46: 1953231 | F46: 1953231 | G46: 1949889 | H46: 1997955 | I46: 2041011 | J46: 2182707 | K46: 2182707 | L46: 2284539 | M46: 2342916 | N46: 2501744 | O46: 2549673 | P46: 2549673 | Q46: 2498121 | R46: 2451260 | S46: 1820980 | T46: 1861032 | U46: 1861032 | V46: 1870649 | W46: 1941523 | X46: 1940725 | Y46: 1783494 | Z46: 1783494 | AA46: 1757559 | AB46: 1891452
A47: 1 | C47: 지배주주지분 | E47: 432073 | F47: 432073 | G47: 422120 | H47: 407547 | I47: 387291 | J47: 385056 | K47: 385056 | L47: 360417 | M47: 280134 | N47: 275749 | O47: 340793 | P47: 340793 | Q47: 354787 | R47: 313212 | S47: 365642 | T47: 343448 | U47: 343448 | V47: 348784 | W47: 343690 | X47: 347350 | Y47: 669629 | Z47: 669629 | AA47: 693989 | AB47: 752963
A48: 1 | C48: 자본금 | E48: 416371 | F48: 416371 | G48: 416371 | H48: 416371 | I48: 416371 | J48: 416371 | K48: 416371 | L48: 416371 | M48: 416371 | N48: 416371 | O48: 416371 | P48: 416371 | Q48: 416371 | R48: 416371 | S48: 416371 | T48: 416371 | U48: 416371 | V48: 416371 | W48: 416371 | X48: 416371 | Y48: 451477 | Z48: 451477 | AA48: 451477 | AB48: 451477
A49: 1 | C49: 자본잉여금 | E49: 1050101 | F49: 1050101 | G49: 1050101 | H49: 1050101 | I49: 1050101 | J49: 1050101 | K49: 1050101 | L49: 1050101 | M49: 1050101 | N49: 1050101 | O49: 1050101 | P49: 1050101 | Q49: 1050101 | R49: 1050101 | S49: 1050101 | T49: 1050101 | U49: 1050101 | V49: 1050101 | W49: 1050101 | X49: 1050101 | Y49: 1224791 | Z49: 1224791 | AA49: 1224791 | AB49: 1224791
A50: 1 | C50: 이익잉여금 | E50: -1358658 | F50: -1358658 | G50: -1367904 | H50: -1382350 | I50: -1402989 | J50: -1408225 | K50: -1408225 | L50: -1432685 | M50: -1512893 | N50: -1517304 | O50: -1532564 | P50: -1532564 | Q50: -1518585 | R50: -1560159 | S50: -1508564 | T50: -1462760 | U50: -1462760 | V50: -1457460 | W50: -1464135 | X50: -1460368 | Y50: -1408011 | Z50: -1408011 | AA50: -1382885 | AB50: -1320480
A51: 1 | C51: 기타자본 | E51: 11590 | F51: 11590 | G51: 11590 | H51: 11590 | I51: 10167 | J51: 11590 | K51: 11590 | L51: 10167 | M51: 10167 | N51: 10167 | O51: 417046 | P51: 417046 | Q51: 417061 | R51: 417060 | S51: 417895 | T51: 349897 | U51: 349897 | V51: 349933 | W51: 351514 | X51: 351407 | Y51: 411533 | Z51: 411533 | AA51: 410767 | AB51: 407336
A52: 1 | C52: 비지배주주지분 | E52: -68 | F52: -68 | G52: -68 | H52: -68 | I52: -67 | J52: -66 | K52: -66 | L52: -65 | M52: 434 | N52: 288 | O52: 119 | P52: 119 | Q52: -36 | R52: 40 | S52: 14 | T52: -51 | U52: -51 | V52: -49 | W52: -46 | X52: -44 | Y52: -41 | Z52: -41 | AA52: -38 | AB52: -35
A53: 1 | C53: 자본총계 | E53: 432005 | F53: 432005 | G53: 422052 | H53: 407479 | I53: 387224 | J53: 384990 | K53: 384990 | L53: 360352 | M53: 280568 | N53: 276037 | O53: 340912 | P53: 340912 | Q53: 354751 | R53: 313252 | S53: 365656 | T53: 343397 | U53: 343397 | V53: 348735 | W53: 343644 | X53: 347306 | Y53: 669588 | Z53: 669588 | AA53: 693951 | AB53: 752928
... A57: 1 | C57: 이자발생자산 | E57: 171913 | F57: 171913 | G57: 164240 | H57: 166230 | I57: 110360 | J57: 160325 | K57: 160325 | L57: 179549 | M57: 150158 | N57: 374801 | O57: 370670 | P57: 370670 | Q57: 307439 | R57: 271877 | S57: 228860 | T57: 235151 | U57: 235151 | V57: 116788 | W57: 216780 | X57: 240203 | Y57: 337168 | Z57: 337168 | AA57: 190767 | AB57: 281486
A58: 1 | C58: 단기차입금 | T58: 381747 | U58: 381747 | V58: 374173 | W58: 282177 | X58: 276093 | Y58: 270520 | Z58: 270520 | AA58: 267443 | AB58: 190033
A59: 1 | C59: 매출액(수익) | E59: 513363 | G59: 347994 | H59: 445457 | I59: 397849 | J59: 596863 | K59: 1788163 | L59: 405021 | M59: 501378 | N59: 490517 | O59: 765157 | P59: 2162073 | Q59: 467581 | R59: 484800 | S59: 453768 | T59: 479813 | U59: 1885962 | V59: 410066 | W59: 507777 | X59: 452208 | Y59: 629654 | Z59: 1999705 | AA59: 541400 | AB59: 729908
A60: 1 | C60: 매출원가 | E60: 582739 | G60: 324101 | H60: 422136 | I60: 370830 | J60: 574461 | K60: 1691528 | L60: 393036 | M60: 550472 | N60: 502803 | O60: 717645 | P60: 2163956 | Q60: 431551 | R60: 500573 | S60: 397443 | T60: 450134 | U60: 1779701 | V60: 379158 | W60: 474703 | X60: 421290 | Y60: 547627 | Z60: 1822778 | AA60: 485022 | AB60: 627365
A61: 1 | C61: 매출총이익 | E61: -69376 | G61: 23893 | H61: 23321 | I61: 27019 | J61: 22402 | K61: 96635 | L61: 11985 | M61: -49094 | N61: -12286 | O61: 47512 | P61: -1883 | Q61: 36030 | R61: -15773 | S61: 56325 | T61: 29679 | U61: 106261 | V61: 30908 | W61: 33074 | X61: 30918 | Y61: 82027 | Z61: 176927 | AA61: 56378 | AB61: 102543
A62: 1 | C62: 판관비 | E62: 23660 | G62: 21310 | H62: 21006 | I62: 27057 | J62: 20637 | K62: 90010 | L62: 23076 | M62: 26078 | N62: 28638 | O62: 29112 | P62: 106904 | Q62: 24131 | R62: 23771 | S62: 23418 | T62: 27689 | U62: 99009 | V62: 25454 | W62: 27735 | X62: 25124 | Y62: 31540 | Z62: 109853 | AA62: 31797 | AB62: 37690
A63: 1 | C63: 영업이익 | E63: -93036 | G63: 2583 | H63: 2315 | I63: -38 | J63: 1765 | K63: 6625 | L63: -11091 | M63: -75172 | N63: -40924 | O63: 18400 | P63: -108787 | Q63: 11899 | R63: -39544 | S63: 32907 | T63: 1990 | U63: 7252 | V63: 5454 | W63: 5339 | X63: 5794 | Y63: 50487 | Z63: 67074 | AA63: 24581 | AB63: 64853
A64: 1 | C64: 기타영업외수익 | E64: 4979 | G64: 644 | H64: 2553 | I64: 1216 | J64: 7355 | K64: 11768 | L64: 3028 | M64: 6454 | N64: 42104 | O64: 2080 | P64: 53666 | Q64: 831 | R64: 5412 | S64: 32495 | T64: 3414 | U64: 42152 | V64: 4262 | W64: 826 | X64: 4271 | Y64: 4364 | Z64: 13723 | AA64: 2342 | AB64: 6139
A65: 1 | C65: 기타영업외비용 | E65: 5923 | G65: 2082 | H65: 2630 | I65: 3731 | J65: 8657 | K65: 17100 | L65: 6851 | M65: 1064 | N65: 3012 | O65: 3865 | P65: 14792 | Q65: 509 | R65: 1976 | S65: 1813 | T65: 5950 | U65: 10248 | V65: 1959 | W65: 6338 | X65: 1397 | Y65: 27452 | Z65: 37146 | AA65: 3722 | AB65: 3506
A66: 1 | C66: 금융수익 | E66: 4518 | G66: 1094 | H66: 2325 | I66: 3313 | J66: 831 | K66: 7563 | L66: 3384 | M66: 4808 | N66: 13157 | O66: -3517 | P66: 17832 | Q66: 16372 | R66: 7029 | S66: 961 | T66: 7284 | U66: 31646 | V66: 2000 | W66: 9562 | X66: 1324 | Y66: 7172 | Z66: 20058 | AA66: 16631 | AB66: 11947
A67: 1 | C67: 금융비용 | E67: 12189 | G67: 13416 | H67: 17641 | I67: 21482 | J67: 8353 | K67: 60892 | L67: 13894 | M67: 11742 | N67: 13735 | O67: 10960 | P67: 50331 | Q67: 15085 | R67: 13342 | S67: 9617 | T67: 20672 | U67: 58716 | V67: 11349 | W67: 17906 | X67: 4713 | Y67: 9461 | Z67: 43429 | AA67: 14893 | AB67: 16974
A68: 1 | C68: 법인세비용차감전계속사업이익 | E68: -101777 | G68: -11192 | H68: -12924 | I68: -20452 | J68: -7059 | K68: -51627 | L68: -24012 | M68: -76453 | N68: -3993 | O68: 1057 | P68: -103401 | Q68: 11769 | R68: -41347 | S68: 51994 | T68: -19136 | U68: 3280 | V68: 5687 | W68: -6622 | X68: 3977 | Y68: 24207 | Z68: 27249 | AA68: 25316 | AB68: 64266
A69: 1 | C69: 법인세비용 | E69: -20239 | G69: -2161 | H69: 1232 | I69: 45 | J69: -583 | K69: -1467 | L69: 79 | M69: 3654 | N69: 483 | O69: 6702 | P69: 10918 | Q69: -2366 | R69: 27 | S69: 0 | T69: 394 | U69: -1945 | V69: 131 | W69: -7 | X69: 36 | Y69: -24355 | Z69: -24195 | AA69: -197 | AB69: 1723
A70: 1 | C70: 계속사업이익 | E70: -81538 | I70: -20497 | J70: -6476 | N70: -4476 | O70: -5645 | Q70: 14135 | R70: -41374 | S70: 51994 | T70: -19530 | U70: 5225 | V70: 5556 | W70: -6615 | X70: 3941 | Y70: 48562 | Z70: 51444 | AA70: 25513 | AB70: 62543
A71: 1 | C71: 당기순이익 | E71: -81538 | I71: -20497 | J71: -6476 | N71: -4476 | O71: -5645 | Q71: 14135 | R71: -41374 | S71: 51994 | T71: -19530 | U71: 5225 | V71: 5556 | W71: -6615 | X71: 3941 | Y71: 48562 | Z71: 51444 | AA71: 25513 | AB71: 62543
A72: 1 | C72: (지배주주지분)당기순이익 | E72: -81536 | G72: -9031 | H72: -14156 | I72: -20498 | J72: -6477 | K72: -50162 | L72: -24092 | M72: -80108 | N72: -4321 | O72: -5487 | P72: -114008 | Q72: 14295 | R72: -41444 | S72: 52016 | T72: -19524 | U72: 5343 | V72: 5554 | W72: -6618 | X72: 3939 | Y72: 48559 | Z72: 51434 | AA72: 25510 | AB72: 62540
A73: 1 | C73: (비지배주주지분)당기순이익 | E73: -2 | G73: 0 | H73: 0 | I73: 1 | J73: 1 | K73: 2 | L73: 1 | M73: 1 | N73: -155 | O73: -158 | P73: -311 | Q73: -160 | R73: 70 | S73: -22 | T73: -6 | U73: -118 | V73: 2 | W73: 3 | X73: 2 | Y73: 3 | Z73: 10 | AA73: 3 | AB73: 3
A74: 1 | C74: 금융손익 | E74: -7671 | G74: -12322 | H74: -15316 | I74: -18169 | J74: -7522 | K74: -53329 | L74: -10510 | M74: -6934 | N74: -578 | O74: -14477 | P74: -32499 | Q74: 1287 | R74: -6313 | S74: -8656 | T74: -13388 | U74: -27070 | V74: -9349 | W74: -8344 | X74: -3389 | Y74: -2289 | Z74: -23371 | AA74: 1738 | AB74: -5027
A75: 1 | C75: 기타영업외손익 | E75: -944 | G75: -1438 | H75: -77 | I75: -2515 | J75: -1302 | K75: -5332 | L75: -3823 | M75: 5390 | N75: 39092 | O75: -1785 | P75: 38874 | Q75: 322 | R75: 3436 | S75: 30682 | T75: -2536 | U75: 31904 | V75: 2303 | W75: -5512 | X75: 2874 | Y75: -23088 | Z75: -23423 | AA75: -1380 | AB75: 2633
A76: 1 | C76: 중단사업이익 | E76: 0
A77: 1 | C77: 이자수익 | G77: 845 | H77: 392 | I77: 612 | J77: 962 | K77: 2811 | L77: 1214 | M77: 1211 | N77: 2288 | Q77: 3213 | R77: 1237 | S77: 2439 | V77: 839 | W77: 1697 | X77: 1520 | AA77: 2071 | AB77: 2227
A78: 1 | C78: 이자비용 | G78: 11287 | H78: 11429 | I78: 10393 | J78: 10463 | K78: 43572 | L78: 10193 | M78: 10269 | N78: 10075 | O78: 9686 | P78: 40223 | Q78: 9949 | R78: 9576 | S78: 12419 | T78: 9953 | U78: 41897 | V78: 9595 | W78: 9387 | X78: 8151 | Y78: 8218 | Z78: 35351 | AA78: 7859 | AB78: 8911
A79: 1 | C79: 외환차익 | G79: 125 | H79: 1491 | I79: 615 | J79: 1778 | K79: 4009 | L79: 500 | M79: 3755 | N79: 3331 | O79: 1922 | P79: 9508 | Q79: 6961 | R79: 6031 | S79: 2883 | T79: 3116 | U79: 18991 | V79: 439 | W79: 684 | X79: 1617 | Y79: 5517 | Z79: 8257 | AA79: 2590 | AB79: 8458
A80: 1 | C80: 외환차손 | G80: 64 | H80: 77 | I80: 102 | J80: 2025 | K80: 2268 | L80: 401 | M80: 457 | N80: 1275 | O80: 331 | P80: 2464 | Q80: 235 | R80: 1154 | S80: 1144 | T80: 1205 | U80: 3738 | V80: 1554 | W80: 2235 | X80: 1139 | Y80: 1248 | Z80: 6176 | AA80: 459 | AB80: 4088
A81: 1 | C81: 외화환산이익 | G81: 124 | H81: 442 | I81: 2086 | J81: -1909 | K81: 743 | L81: 1670 | M81: -158 | N81: 7537 | O81: -8722 | P81: 327 | Q81: 6197 | R81: -239 | S81: -4361 | T81: 2363 | U81: 3960 | V81: 722 | W81: 7181 | X81: -1813 | Y81: -854 | Z81: 5236 | AA81: 11970 | AB81: 688
A82: 1 | C82: 외화환산손실 | G82: 2017 | H82: 6098 | I82: 10938 | J82: -4196 | K82: 14857 | L82: 3252 | M82: 979 | N82: 2336 | O82: 881 | P82: 7448 | Q82: 4853 | R82: 2575 | S82: -3996 | T82: 9452 | U82: 12884 | V82: 152 | W82: 6236 | X82: -4577 | Y82: -5 | Z82: 1806 | AA82: 6241 | AB82: 450
A83: 1 | C83: 이자손익 | G83: -10442 | H83: -11037 | I83: -9781 | J83: -9501 | K83: -40761 | L83: -8979 | M83: -9058 | N83: -7787 | Q83: -6736 | R83: -8339 | S83: -9980 | V83: -8756 | W83: -7690 | X83: -6631 | AA83: -5788 | AB83: -6684
A84: 1 | C84: 총포괄손익 | Q84: 13839 | R84: -41499 | S84: 52404 | V84: 5338 | W84: -5091 | X84: 3662 | AA84: 24363 | AB84: 58977
A85: 1 | C85: 파생상품손실 | AA85: 334
A86: 1 | C86: 영업활동으로인한현금흐름 | E86: 41500 | G86: 7785 | H86: 70019 | I86: -111398 | J86: 118169 | K86: 84575 | L86: 39948 | M86: -77319 | N86: 243178 | O86: -51019 | P86: 154788 | Q86: -50504 | R86: 19866 | S86: -77385 | T86: 21658 | U86: -86365 | V86: -102684 | W86: 146868 | X86: 38921 | Y86: -76775 | Z86: 6330 | AA86: -163853 | AB86: 21461
A87: 1 | C87: 이자수취(CF) | E87: 136 | G87: 277 | H87: 424 | I87: 429 | J87: 761 | K87: 1891 | L87: 873 | M87: 1117 | N87: 1917 | O87: 3064 | P87: 6971 | Q87: 2569 | R87: 2160 | S87: 2186 | T87: 1595 | U87: 8510 | V87: 748 | W87: 1033 | X87: 1431 | Y87: 2076 | Z87: 5288 | AA87: 1613 | AB87: 1610
A88: 1 | C88: 배당금수취(CF) | E88: 0 | G88: 10 | H88: 1014 | I88: 0 | J88: 1 | K88: 1025 | L88: 0 | M88: 501 | N88: 7 | O88: 0 | P88: 508 | Q88: 3 | R88: 418 | S88: 0 | T88: 20 | U88: 441 | V88: 0 | W88: 60 | X88: 9 | Y88: 0 | Z88: 69 | AA88: 709 | AB88: 1
A89: 1 | C89: 이자지급(CF) | E89: -6939 | G89: -6772 | H89: -7054 | I89: -5770 | J89: -5149 | K89: -24745 | L89: -6529 | M89: -4305 | N89: -11778 | O89: -7418 | P89: -30030 | Q89: -7739 | R89: -7297 | S89: -14500 | T89: -9827 | U89: -39363 | V89: -9664 | W89: -9041 | X89: -8510 | Y89: -8595 | Z89: -35810 | AA89: -7001 | AB89: -8181
A90: 1 | C90: 투자활동으로인한현금흐름 | E90: 7771 | G90: -5896 | H90: 32203 | I90: 8139 | J90: -71061 | K90: -36615 | L90: 11920 | M90: 60153 | N90: -19725 | O90: 34535 | P90: 86883 | Q90: -12273 | R90: 4515 | S90: 192327 | T90: 2965 | U90: 187534 | V90: -10995 | W90: -4995 | X90: 5853 | Y90: 7114 | Z90: -3023 | AA90: 1182 | AB90: -3243
A91: 1 | C91: 유형자산의증가 | E91: 1369 | G91: 5163 | H91: 46236 | I91: 7436 | J91: 5440 | K91: 64275 | L91: 1559 | M91: 2198 | N91: 2727 | O91: 2997 | P91: 9481 | Q91: 1981 | R91: 1593 | S91: 932 | T91: 888 | U91: 5394 | V91: 1204 | W91: 1766 | X91: 4627 | Y91: 3064 | Z91: 10661 | AA91: 2984 | AB91: 2589
A92: 1 | C92: CAPEX | E92: 1605 | G92: 5362 | H92: 46436 | I92: 7635 | J92: 5640 | K92: 65073 | L92: 1559 | M92: 2902 | N92: 2727 | O92: 2964 | P92: 10152 | Q92: 2167 | R92: 1780 | S92: 1119 | T92: 1075 | U92: 6141 | V92: 1391 | W92: 1952 | X92: 4814 | Y92: 3251 | Z92: 11408 | AA92: 3171 | AB92: 2775
A93: 1 | C93: 유형자산의감소 | E93: 4 | G93: 3 | H93: 160 | I93: 77 | L93: 22 | M93: 181 | N93: 48 | O93: 453 | P93: 704 | Q93: 148 | R93: 383 | S93: 281 | T93: 26 | U93: 838 | V93: 340 | W93: 17 | X93: 16 | Y93: 2141 | Z93: 2514 | AA93: 16 | AB93: 2
A94: 1 | C94: 무형자산의증가 | E94: 236 | G94: 199 | H94: 200 | I94: 199 | J94: 200 | K94: 798 | L94: 0 | M94: 704 | N94: 0 | Q94: 186 | R94: 187 | S94: 187 | T94: 187 | U94: 747 | V94: 187 | W94: 186 | X94: 187 | Y94: 187 | Z94: 747 | AA94: 187 | AB94: 186
A95: 1 | C95: 무형자산의감소 | E95: 13 | G95: 52 | I95: 13 | J95: 13 | L95: 13 | M95: 13 | N95: 13 | O95: 13 | P95: 52 | Q95: 0 | R95: 0 | S95: 0 | T95: 0 | U95: 0
A96: 1 | C96: 재무활동으로인한현금흐름 | E96: -5966 | G96: -3067 | H96: -83474 | I96: 48025 | J96: -18835 | K96: -57351 | L96: -3374 | M96: -3866 | N96: -4223 | O96: 20657 | P96: 9194 | Q96: -4568 | R96: -53406 | S96: -173571 | T96: -13289 | U96: -244834 | V96: -13314 | W96: -48115 | X96: -17163 | Y96: 199224 | Z96: 120632 | AA96: -11116 | AB96: 69489
A97: 1 | C97: 현금및현금성자산의증감 | E97: 43305 | G97: -1178 | H97: 18748 | I97: -55234 | J97: 28273 | K97: -9391 | L97: 48494 | M97: -21032 | N97: 219230 | O97: 4173 | P97: 250865 | Q97: -67345 | R97: -29025 | S97: -58629 | T97: 11334 | U97: -143665 | V97: -126993 | W97: 93758 | X97: 27611 | Y97: 129563 | Z97: 123939 | AA97: -173787 | AB97: 87707
A98: 1 | C98: 기말현금및현금성자산 | E98: 42932 | G98: 117115 | H98: 19045 | I98: -53426 | J98: 19499 | K98: 102233 | L98: 151777 | M98: -22214 | N98: 224614 | O98: -3920 | P98: 350257 | Q98: 286569 | R98: -29563 | S98: -61798 | T98: 11920 | U98: 207128 | V98: 80370 | W98: 89820 | X98: 31957 | Y98: 130059 | Z98: 332206 | AA98: 163666 | AB98: 86081
A99: 1 | C99: 유동성장기부채의감소 | I99: 785 | N99: 0 | O99: 4285 | S99: 664966 | V99: 2002 | W99: 0 | X99: 3030 | Y99: 1 | Z99: 5033 | AA99: 0 | AB99: 25000
A100: 1 | C100: 장기차입금의증가 | J100: 0 | O100: 25000 | X100: 0 | Y100: 0
A101: 1 | C101: 단기차입금의감소 | V101: 7361 | W101: 374386 | X101: 8588 | Y101: 7361 | Z101: 397696 | AA101: 7369 | AB101: 269100
A102: 1 | C102: 단기차입금의증가 | X102: 0 | Y102: -1

Sheet BS별도
B1: (백만원) | C1: 이름: BS별도H | E1: 4Q21 | F1: 2021 | G1: 1Q22 | H1: 2Q22 | I1: 3Q22 | J1: 4Q22 | K1: 2022 | L1: 1Q23 | M1: 2Q23 | N1: 3Q23 | O1: 4Q23 | P1: 2023 | Q1: 1Q24 | R1: 2Q24 | S1: 3Q24 | T1: 4Q24 | U1: 2024 | V1: 1Q25 | W1: 2Q25 | X1: 3Q25 | Y1: 4Q25 | Z1: 2025 | AA1: 1Q26 | AB1: 2Q26 | AC1: 3Q26 | AD1: 4Q26 | AE1: 2026 | AF1: 1Q27 | AG1: 2Q27 | AH1: 3Q27 | AI1: 4Q27 | AJ1: 2027 | AK1: 1Q28 | AL1: 2Q28 | AM1: 3Q28 | AN1: 4Q28 | AO1: 2028
B2: 별도 | D2: fin json(kship_fin.py)
B3: HJ중공업(별) | C3: UPDATE: 26-10-14 | E3: 1 | F3: 2 | G3: 3 | H3: 4 | I3: 5 | J3: 6 | K3: 7 | L3: 8 | M3: 9 | N3: 10 | O3: 11 | P3: 12 | Q3: 13 | R3: 14 | S3: 15 | T3: 16 | U3: 17 | V3: 18 | W3: 19 | X3: 20 | Y3: 21 | Z3: 22 | AA3: 23 | AB3: 24 | AC3: 25 | AD3: 26 | AE3: 27 | AF3: 28 | AG3: 29 | AH3: 30 | AI3: 31 | AJ3: 32 | AK3: 33 | AL3: 34 | AM3: 35 | AN3: 36 | AO3: 37
B4: Account Code | C4: AccountNAME | E4: 2021.12 | F4: 2021.12A | G4: 2022.03 | H4: 2022.06 | I4: 2022.09 | J4: 2022.12 | K4: 2022.12A | L4: 2023.03 | M4: 2023.06 | N4: 2023.09 | O4: 2023.12 | P4: 2023.12A | Q4: 2024.03 | R4: 2024.06 | S4: 2024.09 | T4: 2024.12 | U4: 2024.12A | V4: 2025.03 | W4: 2025.06 | X4: 2025.09 | Y4: 2025.12 | Z4: 2025.12A | AA4: 2026.03 | AB4: 2026.06 | AC4: 2026.09 | AD4: 2026.12 | AE4: 2026.12A | AF4: 2027.03 | AG4: 2027.06 | AH4: 2027.09 | AI4: 2027.12 | AJ4: 2027.12A | AK4: 2028.03 | AL4: 2028.06 | AM4: 2028.09 | AN4: 2028.12 | AO4: 2028.12A
A5: 1 | C5: 유동자산 | E5: 948911 | F5: 948911 | G5: 934811 | H5: 905456 | I5: 919500 | J5: 1430242 | K5: 1430242 | L5: 1527162 | M5: 1469744 | N5: 1717779 | O5: 1724579 | P5: 1724579 | Q5: 1682650 | R5: 1602652 | S5: 1041804 | T5: 1073132 | U5: 1073132 | V5: 1087266 | W5: 1150107 | X5: 1161613 | Y5: 1258557 | Z5: 1258557 | AA5: 1259136 | AB5: 1444063
A6: 1 | C6: 현금및현금성자산 | E6: 118298 | F6: 118298 | G6: 117104 | H6: 136138 | I6: 82718 | J6: 102217 | K6: 102217 | L6: 151763 | M6: 100845 | N6: 350400 | O6: 347519 | P6: 347519 | Q6: 284379 | R6: 255142 | S6: 193509 | T6: 207117 | U6: 207117 | V6: 80360 | W6: 169892 | X6: 201935 | Y6: 332116 | Z6: 332116 | AA6: 163576 | AB6: 249647
A7: 1 | C7: 단기금융상품 | E7: 45056 | F7: 45056 | G7: 39615 | H7: 27263 | I7: 22858 | J7: 53296 | K7: 53296 | L7: 16736 | M7: 12183 | N7: 12240 | O7: 12458 | P7: 12458 | Q7: 12478 | R7: 11276 | S7: 32142 | T7: 24154 | U7: 24154 | V7: 32847 | W7: 42942 | X7: 32408 | Y7: 26038 | Z7: 26038 | AA7: 22198 | AB7: 25560
A8: 1 | C8: 단기금융자산 | E8: 45056 | F8: 45056 | G8: 39615 | H8: 27263 | I8: 22858 | J8: 53296 | K8: 53296 | L8: 16736 | M8: 12183 | N8: 12240 | O8: 12458 | P8: 12458 | Q8: 12478 | R8: 11276 | S8: 32142 | T8: 24154 | U8: 24154 | V8: 32847 | W8: 42942 | X8: 32408 | Y8: 26038 | Z8: 26038 | AA8: 22198 | AB8: 25560
A9: 1 | C9: 매출채권및기타채권 | E9: 125998 | F9: 125998 | G9: 81066 | H9: 111366 | I9: 120253 | J9: 191295 | K9: 191295 | L9: 174153 | M9: 140611 | N9: 88751 | O9: 187649 | P9: 187649 | Q9: 202261 | R9: 206701 | S9: 134264 | T9: 140323 | U9: 140323 | V9: 152521 | W9: 165562 | X9: 152510 | Y9: 182991 | Z9: 182991 | AA9: 149848 | AB9: 186707
A10: 1 | C10: 계약자산 | E10: 267748 | F10: 267748 | G10: 244889 | H10: 158347 | I10: 217745 | J10: 233295 | K10: 233295 | L10: 220328 | M10: 268615 | N10: 330340 | O10: 387497 | P10: 387497 | Q10: 288610 | R10: 267775 | S10: 210411 | T10: 274766 | U10: 274766 | V10: 270254 | W10: 244218 | X10: 219922 | Y10: 225908 | Z10: 225908 | AA10: 371333 | AB10: 419831
A11: 1 | C11: 선급금 | E11: 149512 | F11: 149512 | G11: 197216 | H11: 195378 | I11: 186976 | J11: 166055 | K11: 166055 | L11: 213314 | M11: 213426 | N11: 194799 | O11: 204694 | P11: 204694 | Q11: 290387 | R11: 278752 | S11: 290239 | T11: 250694 | U11: 250694 | V11: 343447 | W11: 316909 | X11: 326142 | Y11: 272033 | Z11: 272033 | AA11: 313315 | AB11: 324474
A12: 1 | C12: 선급금등 | E12: 149512 | F12: 149512 | G12: 197216 | H12: 195378 | I12: 186976 | J12: 166055 | K12: 166055 | L12: 213314 | M12: 213426 | N12: 194799 | O12: 204694 | P12: 204694 | Q12: 290387 | R12: 278752 | S12: 290239 | T12: 250694 | U12: 250694 | V12: 343447 | W12: 316909 | X12: 326142 | Y12: 272033 | Z12: 272033 | AA12: 313315 | AB12: 324474
A13: 1 | C13: 기타유동자산 | E13: 211904 | F13: 211904 | G13: 265279 | H13: 260427 | I13: 249701 | J13: 226637 | K13: 226637 | L13: 281022 | M13: 272909 | N13: 251184 | O13: 261427 | P13: 261427 | Q13: 357668 | R13: 337442 | S13: 349678 | T13: 315070 | U13: 315070 | V13: 416849 | W13: 398285 | X13: 413691 | Y13: 357770 | Z13: 357770 | AA13: 415413 | AB13: 424177
A14: 1 | C14: 재고자산 | E14: 147110 | F14: 147110 | G14: 149202 | H14: 181122 | I14: 210942 | J14: 200698 | K14: 200698 | L14: 220097 | M14: 249327 | N14: 235852 | O14: 135297 | P14: 135297 | Q14: 146227 | R14: 134224 | S14: 115631 | T14: 105441 | U14: 105441 | V14: 125217 | W14: 120608 | X14: 122852 | Y14: 115769 | Z14: 115769 | AA14: 122106 | AB14: 125168
A15: 1 | C15: 기타유동금융자산 | E15: 32717 | F15: 32717 | G15: 27576 | H15: 20713 | I15: 15203 | J15: 33260 | K15: 33260 | L15: 33558 | M15: 15757 | N15: 6040 | O15: 8894 | P15: 8894 | Q15: 7196 | R15: 6267 | S15: 6089 | T15: 6261 | U15: 6261 | V15: 9218 | W15: 8600 | X15: 18295 | Y15: 17965 | Z15: 17965 | AA15: 14662 | AB15: 12973
A16: 1 | C16: 매각예정비유동자산및처분자산 | E16: 80 | F16: 80 | G16: 80 | H16: 80 | I16: 80 | J16: 379542 | K16: 379542 | L16: 379542 | M16: 379542 | N16: 379542 | O16: 379542 | P16: 379542 | Q16: 379542 | R16: 379542 | S16: 80 | T16: 0 | U16: 0 | Y16: 0 | Z16: 0
A17: 1 | C17: 비유동자산 | E17: 1432133 | F17: 1432133 | G17: 1433035 | H17: 1496027 | I17: 1504906 | J17: 1133741 | K17: 1133741 | L17: 1114133 | M17: 1122429 | N17: 1054376 | O17: 1161038 | P17: 1161038 | Q17: 1165440 | R17: 1157800 | S17: 1140982 | T17: 1129115 | U17: 1129115 | V17: 1130054 | W17: 1133118 | X17: 1124597 | Y17: 1192819 | Z17: 1192819 | AA17: 1190749 | AB17: 1198852
A18: 1 | C18: 종속기업및관계기업투자 | E18: 36250 | F18: 36250 | G18: 36057 | H18: 45863 | I18: 45985 | J18: 45985 | K18: 45985 | L18: 46138 | M18: 62896 | N18: 60869 | O18: 62275 | P18: 62275 | Q18: 59301 | R18: 60596 | S18: 57573 | T18: 52171 | U18: 52171 | V18: 58501 | W18: 60396 | X18: 39989 | Y18: 39087 | Z18: 39087 | AA18: 38893 | AB18: 40702
A19: 1 | C19: 투자자산 | E19: 88694 | F19: 88694 | G19: 90602 | H19: 109543 | I19: 130421 | J19: 130707 | K19: 130707 | L19: 142903 | M19: 151742 | N19: 152560 | O19: 157332 | P19: 157332 | Q19: 156281 | R19: 151168 | S19: 140833 | T19: 135419 | U19: 135419 | V19: 145937 | W19: 144310 | X19: 135493 | Y19: 115707 | Z19: 115707 | AA19: 119589 | AB19: 123812
A20: 1 | C20: 유형자산 | E20: 921567 | F20: 921567 | G20: 924011 | H20: 967385 | I20: 971500 | J20: 643121 | K20: 643121 | L20: 641704 | M20: 640650 | N20: 640112 | O20: 743975 | P20: 743975 | Q20: 744142 | R20: 742048 | S20: 740618 | T20: 738677 | U20: 738677 | V20: 737108 | W20: 736772 | X20: 739145 | Y20: 820636 | Z20: 820636 | AA20: 819550 | AB20: 822331
A21: 1 | C21: 투자부동산 | E21: 59891 | F21: 59891 | G21: 59798 | H21: 59705 | I21: 59611 | J21: 10643 | K21: 10643 | L21: 10643 | M21: 10643 | N21: 10643 | O21: 56345 | P21: 56345 | Q21: 55337 | R21: 52374 | S21: 50605 | T21: 48478 | U21: 48478 | V21: 46700 | W21: 44918 | X21: 43541 | Y21: 42005 | Z21: 42005 | AA21: 38820 | AB21: 38488
A22: 1 | C22: 무형자산 | E22: 2323 | F22: 2323 | G22: 2323 | H22: 2323 | I22: 2325 | J22: 2323 | K22: 2323 | L22: 2325 | M22: 3028 | N22: 3028 | O22: 3027 | P22: 3027 | Q22: 3028 | R22: 3010 | S22: 3010 | T22: 3012 | U22: 3012 | V22: 3012 | W22: 3011 | X22: 3011 | Y22: 3011 | Z22: 3011 | AA22: 3012 | AB22: 3012
A23: 1 | C23: 장기대여금 | E23: 44026 | F23: 44026 | G23: 47165 | H23: 60983 | I23: 79778 | J23: 80036 | K23: 80036 | L23: 85839 | M23: 80538 | N23: 83411 | O23: 87206 | P23: 87206 | Q23: 88692 | R23: 87067 | S23: 81840 | T23: 79469 | U23: 79469 | V23: 83955 | W23: 80347 | X23: 89937 | Y23: 71658 | Z23: 71658 | AA23: 75874 | AB23: 77013
A24: 1 | C24: 사용권자산 | E24: 185908 | F24: 185908 | G24: 184257 | H24: 183731 | I24: 183002 | J24: 181681 | K24: 181681 | L24: 180966 | M24: 180233 | N24: 93156 | O24: 46514 | P24: 46514 | Q24: 44015 | R24: 44146 | S24: 42273 | T24: 41620 | U24: 41620 | V24: 39488 | W24: 47924 | X24: 45908 | Y24: 43870 | Z24: 43870 | AA24: 43124 | AB24: 39979
A25: 1 | C25: 기타비유동자산 | E25: 224791 | F25: 224791 | G25: 222253 | H25: 223165 | I25: 206634 | J25: 210621 | K25: 210621 | L25: 210868 | M25: 211254 | N25: 134435 | O25: 89941 | P25: 89941 | Q25: 91352 | R25: 92884 | S25: 89490 | T25: 84698 | U25: 84698 | V25: 79001 | W25: 85538 | X25: 84270 | Y25: 92026 | Z25: 92026 | AA25: 90613 | AB25: 91902
A26: 1 | C26: 장기매출채권및기타채권 | E26: 2042 | F26: 2042 | G26: 2036 | H26: 1677 | I26: 1664 | J26: 1651 | K26: 1651 | L26: 1638 | M26: 1624 | N26: 1611 | O26: 1598 | P26: 1598 | Q26: 1585 | R26: 1572 | T26: 0 | U26: 0 | V26: 1533 | W26: 1520 | X26: 1507 | Y26: 0 | Z26: 0 | AA26: 1481 | AB26: 1481
A27: 1 | C27: 장기금융자산 | E27: 8418 | F27: 8418 | G27: 7380 | H27: 2697 | I27: 4658 | J27: 4686 | K27: 4686 | L27: 10926 | M27: 8308 | N27: 8280 | O27: 7851 | P27: 7851 | Q27: 8288 | R27: 3505 | S27: 1420 | T27: 3779 | U27: 3779 | V27: 3481 | W27: 3567 | X27: 5567 | Y27: 4962 | Z27: 4962 | AA27: 4822 | AB27: 6097
A28: 1 | C28: 자산총계 | E28: 2381044 | F28: 2381044 | G28: 2367846 | H28: 2401483 | I28: 2424406 | J28: 2563983 | K28: 2563983 | L28: 2641295 | M28: 2592173 | N28: 2772155 | O28: 2885617 | P28: 2885617 | Q28: 2848090 | R28: 2760452 | S28: 2182786 | T28: 2202247 | U28: 2202247 | V28: 2217320 | W28: 2283225 | X28: 2286210 | Y28: 2451376 | Z28: 2451376 | AA28: 2449885 | AB28: 2642915
A29: 1 | C29: 유동부채 | E29: 947510 | F29: 947510 | G29: 932325 | H29: 890113 | I29: 1032367 | J29: 1415824 | K29: 1415824 | L29: 1554976 | M29: 2113375 | N29: 2130565 | O29: 2122908 | P29: 2122908 | Q29: 2063119 | R29: 2015511 | S29: 1482820 | T29: 1554390 | U29: 1554390 | V29: 1559816 | W29: 1576602 | X29: 1584741 | Y29: 1491064 | Z29: 1491064 | AA29: 1457993 | AB29: 1390955
A30: 1 | C30: 매입채무및기타채무 | E30: 312298 | F30: 312298 | G30: 254708 | H30: 258352 | I30: 260178 | J30: 328103 | K30: 328103 | L30: 352352 | M30: 377630 | N30: 393842 | O30: 473208 | P30: 473208 | Q30: 434694 | R30: 510082 | S30: 379361 | T30: 385888 | U30: 385888 | V30: 393232 | W30: 408696 | X30: 438994 | Y30: 398325 | Z30: 398325 | AA30: 396656 | AB30: 401109
A31: 1 | C31: 유동성장기부채 | E31: 150785 | F31: 150785 | G31: 150785 | H31: 70785 | I31: 70785 | J31: 70785 | K31: 70785 | L31: 123685 | M31: 657143 | N31: 662313 | O31: 656520 | P31: 656520 | Q31: 662635 | R31: 623770 | S31: 452151 | T31: 70178 | U31: 70178 | V31: 68176 | W31: 65926 | X31: 62896 | Y31: 87896 | Z31: 87896 | AA31: 87896 | AB31: 42646
A32: 1 | C32: 계약부채 | E32: 298803 | F32: 298803 | G32: 356841 | H32: 401262 | I32: 372818 | J32: 472547 | K32: 472547 | L32: 554724 | M32: 546181 | N32: 711032 | O32: 616653 | P32: 616653 | Q32: 635090 | R32: 578712 | S32: 457810 | T32: 507566 | U32: 507566 | V32: 518746 | W32: 618176 | X32: 607326 | Y32: 542275 | Z32: 542275 | AA32: 519638 | AB32: 565272
A33: 1 | C33: 단기충당부채 | E33: 143937 | F33: 143937 | G33: 124560 | H33: 113702 | I33: 100629 | J33: 131793 | K33: 131793 | L33: 113111 | M33: 127901 | N33: 119811 | O33: 132953 | P33: 132953 | Q33: 86857 | R33: 65063 | S33: 55403 | T33: 71805 | U33: 71805 | V33: 66097 | W33: 59700 | X33: 59636 | Y33: 50616 | Z33: 50616 | AA33: 44973 | AB33: 47563
A34: 1 | C34: 기타유동금융부채 | E34: 28688 | F34: 28688 | G34: 28765 | H34: 29400 | I34: 194259 | J34: 193791 | K34: 193791 | L34: 193875 | M34: 194121 | N34: 33487 | O34: 35299 | P34: 35299 | Q34: 36363 | R34: 31864 | S34: 29133 | T34: 28368 | U34: 28368 | V34: 30245 | W34: 31776 | X34: 29285 | Y34: 29616 | Z34: 29616 | AA34: 31985 | AB34: 35735
A35: 1 | C35: 단기금융부채 | E35: 28688 | F35: 28688 | G35: 28765 | H35: 29400 | I35: 194259 | J35: 193791 | K35: 193791 | L35: 193875 | M35: 194121 | N35: 33487 | O35: 35299 | P35: 35299 | Q35: 36363 | R35: 31864 | S35: 29133 | T35: 28368 | U35: 28368 | V35: 30245 | W35: 31776 | X35: 29285 | Y35: 29616 | Z35: 29616 | AA35: 31985 | AB35: 35735
A36: 1 | C36: 기타유동부채 | E36: 12999 | F36: 12999 | G36: 16666 | H36: 16612 | I36: 33698 | J36: 218805 | K36: 218805 | L36: 217229 | M36: 210399 | N36: 210080 | O36: 208275 | P36: 208275 | Q36: 207480 | R36: 206020 | S36: 108962 | T36: 108838 | U36: 108838 | V36: 109147 | W36: 110151 | X36: 110511 | Y36: 111816 | Z36: 111816 | AA36: 109402 | AB36: 108597
A37: 1 | C37: 비유동부채 | E37: 1001336 | F37: 1001336 | G37: 1013278 | H37: 1103697 | I37: 1004639 | J37: 763003 | K37: 763003 | L37: 725807 | M37: 198581 | N37: 365201 | O37: 421300 | P37: 421300 | Q37: 429610 | R37: 431171 | S37: 333786 | T37: 303895 | U37: 303895 | V37: 308225 | W37: 362462 | X37: 353677 | Y37: 290276 | Z37: 290276 | AA37: 297522 | AB37: 498649
A38: 1 | C38: 사채 | E38: 28455 | F38: 28455 | G38: 28695 | H38: 28937 | I38: 29179 | J38: 29421 | K38: 29421 | L38: 29664 | M38: 0 | N38: 0 | O38: 0 | P38: 0 | T38: 0 | U38: 0 | Y38: 0 | Z38: 0
A39: 1 | C39: 장기차입금 | E39: 501064 | F39: 501064 | G39: 504714 | H39: 512205 | I39: 575853 | J39: 551007 | K39: 551007 | L39: 502539 | M39: 1571 | N39: 785 | O39: 25785 | P39: 25785 | Q39: 25785 | R39: 25785 | S39: 25000 | T39: 25000 | U39: 25000 | V39: 25000 | W39: 68428 | X39: 68610 | Y39: 43798 | Z39: 43798 | AA39: 43987 | AB39: 242397
A40: 1 | C40: 확정급여부채 | E40: 60832 | F40: 60832 | G40: 70087 | H40: 72630 | I40: 74669 | J40: 63747 | K40: 63747 | L40: 73192 | M40: 75422 | N40: 77765 | O40: 80222 | P40: 80222 | Q40: 88247 | R40: 90644 | S40: 94025 | T40: 92436 | U40: 92436 | V40: 101442 | W40: 104137 | X40: 107500 | Y40: 76072 | Z40: 76072 | AA40: 86530 | AB40: 89731
A41: 1 | C41: 장기충당부채 | E41: 17572 | F41: 17572 | G41: 16835 | H41: 16488 | I41: 17164 | J41: 17439 | K41: 17439 | L41: 18800 | M41: 20162 | N41: 19697 | O41: 24224 | P41: 24224 | Q41: 26319 | R41: 27245 | S41: 27155 | T41: 0 | U41: 0 | Y41: 0 | Z41: 0
A42: 1 | C42: 이연법인세부채 | E42: 84194 | F42: 84194 | G42: 84194 | H42: 84194 | I42: 84194 | J42: 80368 | K42: 80368 | L42: 80367 | M42: 80367 | N42: 80368 | O42: 104537 | P42: 104537 | Q42: 104430 | R42: 104391 | S42: 104525 | T42: 104525 | U42: 104525 | V42: 104448 | W42: 104431 | X42: 104524 | Y42: 100060 | Z42: 100060 | AA42: 99944 | AB42: 99894
A43: 1 | C43: 기타비유동금융부채 | E43: 181674 | F43: 181674 | G43: 181084 | H43: 180950 | I43: 16085 | J43: 15638 | K43: 15638 | L43: 15697 | M43: 15344 | N43: 76614 | O43: 75348 | P43: 75348 | Q43: 73455 | R43: 71541 | S43: 66794 | T43: 64883 | U43: 64883 | V43: 59330 | W43: 65021 | X43: 61627 | Y43: 59514 | Z43: 59514 | AA43: 55938 | AB43: 53045
A44: 1 | C44: 장기금융부채 | E44: 181674 | F44: 181674 | G44: 181084 | H44: 180950 | I44: 16085 | J44: 15638 | K44: 15638 | L44: 15697 | M44: 15344 | N44: 76614 | O44: 75348 | P44: 75348 | Q44: 73455 | R44: 71541 | S44: 66794 | T44: 64883 | U44: 64883 | V44: 59330 | W44: 65021 | X44: 61627 | Y44: 59514 | Z44: 59514 | AA44: 55938 | AB44: 53045
A45: 1 | C45: 기타비유동부채 | E45: 127545 | F45: 127545 | G45: 127669 | H45: 208293 | I45: 207495 | J45: 5383 | K45: 5383 | L45: 5548 | M45: 5715 | N45: 109972 | O45: 111184 | P45: 111184 | Q45: 111374 | R45: 111565 | S45: 6140 | T45: 8806 | U45: 8806 | V45: 9058 | W45: 9310 | X45: 8860 | Y45: 10832 | Z45: 10832 | AA45: 11123 | AB45: 11414
A46: 1 | C46: 부채총계 | E46: 1948846 | F46: 1948846 | G46: 1945603 | H46: 1993810 | I46: 2037006 | J46: 2178827 | K46: 2178827 | L46: 2280783 | M46: 2311956 | N46: 2495766 | O46: 2544208 | P46: 2544208 | Q46: 2492729 | R46: 2446682 | S46: 1816606 | T46: 1858285 | U46: 1858285 | V46: 1868041 | W46: 1939064 | X46: 1938418 | Y46: 1781340 | Z46: 1781340 | AA46: 1755515 | AB46: 1889604
A47: 1 | C47: 자본금 | E47: 416371 | F47: 416371 | G47: 416371 | H47: 416371 | I47: 416371 | J47: 416371 | K47: 416371 | L47: 416371 | M47: 416371 | N47: 416371 | O47: 416371 | P47: 416371 | Q47: 416371 | R47: 416371 | S47: 416371 | T47: 416371 | U47: 416371 | V47: 416371 | W47: 416371 | X47: 416371 | Y47: 451477 | Z47: 451477 | AA47: 451477 | AB47: 451477
A48: 1 | C48: 자본잉여금 | E48: 1050101 | F48: 1050101 | G48: 1050101 | H48: 1050101 | I48: 1050101 | J48: 1050101 | K48: 1050101 | L48: 1050101 | M48: 1050101 | N48: 1050101 | O48: 1050101 | P48: 1050101 | Q48: 1050101 | R48: 1050101 | S48: 1050101 | T48: 1050101 | U48: 1050101 | V48: 1050101 | W48: 1050101 | X48: 1050101 | Y48: 1224791 | Z48: 1224791 | AA48: 1224791 | AB48: 1224791
A49: 1 | C49: 이익잉여금 | E49: -1356822 | F49: -1356822 | G49: -1366070 | H49: -1380513 | I49: -1401169 | J49: -1406414 | K49: -1406414 | L49: -1430879 | M49: -1511099 | N49: -1514953 | O49: -1530237 | P49: -1530237 | Q49: -1516300 | R49: -1557889 | S49: -1506315 | T49: -1460536 | U49: -1460536 | V49: -1455255 | W49: -1461954 | X49: -1458216 | Y49: -1405892 | Z49: -1405892 | AA49: -1380792 | AB49: -1318421
A50: 1 | C50: 기타자본 | E50: 9938 | F50: 9938 | G50: 9938 | H50: 8515 | I50: 8515 | J50: 9938 | K50: 9938 | L50: 8515 | M50: 8515 | N50: 8515 | O50: 413689 | P50: 413689 | Q50: 413704 | R50: 413702 | S50: 414538 | T50: 346541 | U50: 346541 | V50: 346577 | W50: 348158 | X50: 348051 | Y50: 408175 | Z50: 408175 | AA50: 407409 | AB50: 403979
A51: 1 | C51: 자본총계 | E51: 432198 | F51: 432198 | G51: 422243 | H51: 407673 | I51: 387400 | J51: 385156 | K51: 385156 | L51: 360512 | M51: 280217 | N51: 276389 | O51: 341409 | P51: 341409 | Q51: 355361 | R51: 313770 | S51: 366180 | T51: 343962 | U51: 343962 | V51: 349279 | W51: 344161 | X51: 347792 | Y51: 670036 | Z51: 670036 | AA51: 694370 | AB51: 753311
A52: 1 | C52: 부채와자본총계 | E52: 2381044 | F52: 2381044 | G52: 2367846 | H52: 2401483 | I52: 2424406 | J52: 2563983 | K52: 2563983 | L52: 2641295 | M52: 2592173 | N52: 2772155 | O52: 2885617 | P52: 2885617 | Q52: 2848090 | R52: 2760452 | S52: 2182786 | T52: 2202247 | U52: 2202247 | V52: 2217320 | W52: 2283225 | X52: 2286210 | Y52: 2451376 | Z52: 2451376 | AA52: 2449885 | AB52: 2642915
A53: 1 | C53: 지배주주지분 | E53: 432198 | F53: 432198 | G53: 422243 | H53: 407673 | I53: 387400 | J53: 385156 | K53: 385156 | L53: 360512 | M53: 280217 | N53: 276389 | O53: 341409 | P53: 341409 | Q53: 355361 | R53: 313770 | S53: 366180 | T53: 343962 | U53: 343962 | V53: 349279 | W53: 344161 | X53: 347792 | Y53: 670036 | Z53: 670036 | AA53: 694370 | AB53: 753311
... A56: 1 | C56: 이자발생자산 | E56: 171772 | F56: 171772 | G56: 164099 | H56: 166098 | I56: 110234 | J56: 160199 | K56: 160199 | L56: 179425 | M56: 121336 | N56: 370920 | O56: 367828 | P56: 367828 | Q56: 305145 | R56: 269923 | S56: 227071 | T56: 235050 | U56: 235050 | V56: 116688 | W56: 216401 | X56: 239910 | Y56: 363116 | Z56: 363116 | AA56: 190596 | AB56: 281304
A57: 1 | C57: 단기차입금 | T57: 381747 | U57: 381747 | V57: 374173 | W57: 282177 | X57: 276093 | Y57: 270520 | Z57: 270520 | AA57: 267443 | AB57: 190033
A58: 1 | C58: 매출액(수익) | E58: 513126 | G58: 347795 | H58: 445257 | I58: 397650 | J58: 596664 | K58: 1787366 | L58: 404822 | M58: 501178 | N58: 490317 | O58: 764948 | P58: 2161265 | Q58: 467381 | R58: 484600 | S58: 453568 | T58: 479614 | U58: 1885163 | V58: 409866 | W58: 507577 | X58: 452009 | Y58: 629454 | Z58: 1998906 | AA58: 541201 | AB58: 729708
A59: 1 | C59: 매출원가 | E59: 582624 | G59: 323986 | H59: 422021 | I59: 370715 | J59: 574347 | K59: 1691069 | L59: 392922 | M59: 550357 | N59: 502687 | O59: 717523 | P59: 2163489 | Q59: 431435 | R59: 500459 | S59: 397328 | T59: 450019 | U59: 1779241 | V59: 379044 | W59: 474587 | X59: 421175 | Y59: 547511 | Z59: 1822317 | AA59: 484908 | AB59: 627249
A60: 1 | C60: 매출총이익 | E60: -69498 | G60: 23809 | H60: 23236 | I60: 26935 | J60: 22317 | K60: 96297 | L60: 11900 | M60: -49179 | N60: -12370 | O60: 47425 | P60: -2224 | Q60: 35946 | R60: -15859 | S60: 56240 | T60: 29595 | U60: 105922 | V60: 30822 | W60: 32990 | X60: 30834 | Y60: 81943 | Z60: 176589 | AA60: 56293 | AB60: 102459
A61: 1 | C61: 판관비 | E61: 23641 | G61: 21287 | H61: 20991 | I61: 27037 | J61: 20622 | K61: 89937 | L61: 23054 | M61: 26059 | N61: 28472 | O61: 28420 | P61: 106005 | Q61: 23483 | R61: 24055 | S61: 23266 | T61: 27661 | U61: 98465 | V61: 25433 | W61: 27717 | X61: 25109 | Y61: 31526 | Z61: 109785 | AA61: 31777 | AB61: 37671
A62: 1 | C62: 영업이익 | E62: -93139 | G62: 2522 | H62: 2245 | I62: -102 | J62: 1695 | K62: 6360 | L62: -11154 | M62: -75238 | N62: -40842 | O62: 19005 | P62: -108229 | Q62: 12463 | R62: -39914 | S62: 32974 | T62: 1934 | U62: 7457 | V62: 5389 | W62: 5273 | X62: 5725 | Y62: 50417 | Z62: 66804 | AA62: 24516 | AB62: 64788
A63: 1 | C63: 기타영업외수익 | E63: 4979 | G63: 644 | H63: 2553 | I63: 1216 | J63: 7355 | K63: 11768 | L63: 3028 | M63: 6455 | N63: 42103 | O63: 2079 | P63: 53665 | Q63: 799 | R63: 5411 | S63: 32496 | T63: 3414 | U63: 42120 | V63: 4263 | W63: 826 | X63: 4271 | Y63: 4362 | Z63: 13722 | AA63: 2343 | AB63: 6138
A64: 1 | C64: 기타영업외비용 | E64: 5923 | G64: 2082 | H64: 2630 | I64: 3731 | J64: 8657 | K64: 17100 | L64: 6850 | M64: 1064 | N64: 2440 | O64: 3865 | P64: 14219 | Q64: 509 | R64: 1976 | S64: 1813 | T64: 5950 | U64: 10248 | V64: 1957 | W64: 6338 | X64: 1398 | Y64: 27451 | Z64: 37144 | AA64: 3719 | AB64: 3506
A65: 1 | C65: 금융수익 | E65: 4518 | G65: 1094 | H65: 2325 | I65: 3312 | J65: 829 | K65: 7560 | L65: 3384 | M65: 4807 | N65: 13152 | O65: -3520 | P65: 17823 | Q65: 16371 | R65: 7029 | S65: 959 | T65: 7283 | U65: 31642 | V65: 2001 | W65: 9560 | X65: 1324 | Y65: 7170 | Z65: 20055 | AA65: 16623 | AB65: 11954
A66: 1 | C66: 금융비용 | E66: 12059 | G66: 13357 | H66: 17567 | I66: 21436 | J66: 8292 | K66: 60652 | L66: 13839 | M66: 11688 | N66: 13204 | O66: 10946 | P66: 49677 | Q66: 15006 | R66: 13262 | S66: 9611 | T66: 20608 | U66: 58487 | V66: 11308 | W66: 17867 | X66: 4675 | Y66: 9425 | Z66: 43275 | AA66: 14853 | AB66: 16951
A67: 1 | C67: 법인세비용차감전계속사업이익 | E67: -101750 | G67: -11194 | H67: -12920 | I67: -20471 | J67: -7070 | K67: -51655 | L67: -24019 | M67: -76466 | N67: -3282 | O67: 1191 | P67: -102576 | Q67: 11887 | R67: -41433 | S67: 51994 | T67: -19154 | U67: 3294 | V67: 5667 | W67: -6650 | X67: 3945 | Y67: 24171 | Z67: 27133 | AA67: 25287 | AB67: 64230
A68: 1 | C68: 법인세비용 | E68: -20237 | G68: -2160 | H68: 1232 | I68: 44 | J68: -584 | K68: -1468 | L68: 79 | M68: 3655 | N68: 481 | O68: 6701 | P68: 10916 | Q68: -2366 | R68: 27 | S68: -1 | T68: 395 | U68: -1945 | V68: 131 | W68: -7 | X68: 35 | Y68: -24354 | Z68: -24195 | AA68: -198 | AB68: 1724
A69: 1 | C69: 당기순이익 | E69: -81513 | I69: -20515 | J69: -6486 | N69: -3763 | O69: -5510 | Q69: 14253 | R69: -41460 | S69: 51995 | T69: -19549 | U69: 5239 | V69: 5536 | W69: -6643 | X69: 3910 | Y69: 48525 | Z69: 51328 | AA69: 25485 | AB69: 62506
A70: 1 | C70: 금융손익 | E70: -7541 | G70: -12263 | H70: -15242 | I70: -18124 | J70: -7463 | K70: -53092 | L70: -10455 | M70: -6881 | N70: -52 | O70: -14466 | P70: -31854 | Q70: 1365 | R70: -6233 | S70: -8652 | T70: -13325 | U70: -26845 | V70: -9307 | W70: -8307 | X70: -3351 | Y70: -2255 | Z70: -23220 | AA70: 1770 | AB70: -4997
A71: 1 | C71: 기타영업외손익 | E71: -944 | G71: -1438 | H71: -77 | I71: -2515 | J71: -1302 | K71: -5332 | L71: -3822 | M71: 5391 | N71: 39663 | O71: -1786 | P71: 39446 | Q71: 290 | R71: 3435 | S71: 30683 | T71: -2536 | U71: 31872 | V71: 2306 | W71: -5512 | X71: 2873 | Y71: -23089 | Z71: -23422 | AA71: -1376 | AB71: 2632
A72: 1 | C72: (지배주주지분)당기순이익 | E72: -81513 | I72: -20515 | J72: -6486 | N72: -3763 | O72: -5510 | Q72: 14253 | R72: -41460 | S72: 51995 | T72: -19549 | U72: 5239 | V72: 5536 | W72: -6643 | X72: 3910 | Y72: 48525 | Z72: 51328 | AA72: 25485 | AB72: 62506
A73: 1 | C73: 계속사업이익 | E73: -81513 | I73: -20515 | J73: -6486 | N73: -3763 | O73: -5510 | Q73: 14253 | R73: -41460 | S73: 51995 | T73: -19549 | U73: 5239 | V73: 5536 | W73: -6643 | X73: 3910 | Y73: 48525 | Z73: 51328 | AA73: 25485 | AB73: 62506
A74: 1 | C74: 총포괄손익 | E74: 171322 | G74: -9955 | I74: -20273 | J74: -2244 | L74: -24644 | M74: -80295 | N74: -3828 | O74: 65020 | P74: -43747 | Q74: 13952 | R74: -41591 | S74: 52410 | T74: -22218 | U74: 2553 | V74: 5317 | W74: -5118 | X74: 3631 | Y74: 112448 | Z74: 116278 | AA74: 24334 | AB74: 58941
A75: 1 | C75: 영업활동으로인한현금흐름 | E75: 41271 | G75: 7586 | H75: 69827 | I75: -111591 | J75: 117969 | K75: 83791 | L75: 39950 | M75: -77311 | N75: 268080 | O75: -49589 | P75: 181130 | Q75: -50175 | R75: 19753 | S75: -77372 | T75: 21594 | U75: -86200 | V75: -102883 | W75: 146674 | X75: 38807 | Y75: -76853 | Z75: 5745 | AA75: -164053 | AB75: 21263
A76: 1 | C76: 이자수취(CF) | E76: 136 | G76: 277 | H76: 422 | I76: 430 | J76: 760 | K76: 1889 | L76: 873 | M76: 1114 | N76: 1912 | O76: 3064 | P76: 6963 | Q76: 2569 | R76: 2156 | S76: 2186 | T76: 1595 | U76: 8506 | V76: 748 | W76: 1031 | X76: 1431 | Y76: 2076 | Z76: 5286 | AA76: 1605 | AB76: 1616
A77: 1 | C77: 배당금수취(CF) | E77: 1 | G77: 10 | H77: 1015 | I77: -1 | J77: 1 | K77: 1025 | L77: 0 | M77: 501 | N77: 7 | O77: 0 | P77: 508 | Q77: 3 | R77: 418 | S77: 0 | T77: 20 | U77: 441 | V77: 0 | W77: 60 | X77: 9 | Y77: 0 | Z77: 69 | AA77: 709 | AB77: 1
A78: 1 | C78: 이자지급(CF) | E78: -6939 | G78: -6772 | H78: -7054 | I78: -5770 | J78: -5149 | K78: -24745 | L78: -6529 | M78: -4305 | N78: -11778 | O78: -7418 | P78: -30030 | Q78: -7739 | R78: -7297 | S78: -14500 | T78: -9827 | U78: -39363 | V78: -9664 | W78: -9041 | X78: -8510 | Y78: -8595 | Z78: -35810 | AA78: -6993 | AB78: -8189
A79: 1 | C79: 투자활동으로인한현금흐름 | E79: 8006 | G79: -5697 | H79: 32383 | I79: 8338 | J79: -70861 | K79: -35837 | L79: 11921 | M79: 31440 | N79: -19686 | O79: 34045 | P79: 57720 | Q79: -12074 | R79: 4701 | S79: 192527 | T79: 4693 | U79: 189847 | V79: -10795 | W79: -5088 | X79: 6053 | Y79: 7314 | Z79: -2516 | AA79: 1383 | AB79: -3057
A80: 1 | C80: 유형자산의증가 | E80: 1369 | G80: 5163 | H80: 46236 | I80: 7436 | J80: 5440 | K80: 64275 | L80: 1559 | M80: 2198 | N80: 2688 | O80: 3036 | P80: 9481 | Q80: 1981 | R80: 1593 | S80: 932 | T80: 888 | U80: 5394 | V80: 1204 | W80: 1766 | X80: 4627 | Y80: 3064 | Z80: 10661 | AA80: 2984 | AB80: 2589
A81: 1 | C81: CAPEX | E81: 1369 | G81: 5163 | H81: 46236 | I81: 7436 | J81: 5440 | K81: 64275 | L81: 1559 | M81: 2902 | N81: 2688 | O81: 3036 | P81: 10185 | Q81: 1981 | R81: 1593 | S81: 932 | T81: 888 | U81: 5394 | V81: 1204 | W81: 1766 | X81: 4627 | Y81: 3064 | Z81: 10661 | AA81: 2984 | AB81: 2589
A82: 1 | C82: 유형자산의감소 | E82: 4 | G82: 3 | H82: 160 | I82: 77 | L82: 22 | M82: 181 | N82: 48 | O82: 420 | P82: 671 | Q82: 148 | R82: 383 | S82: 281 | T82: 26 | U82: 838 | V82: 340 | W82: 17 | X82: 16 | Y82: 2141 | Z82: 2514 | AA82: 16 | AB82: 2
A83: 1 | C83: 무형자산의감소 | E83: 13 | G83: 52 | I83: 13 | J83: 13 | L83: 13 | M83: 13 | N83: 13 | O83: 13 | P83: 52 | Q83: 13 | R83: 13 | S83: 13 | T83: 13 | U83: 52 | V83: 13 | W83: 13 | X83: 13 | Y83: 13 | Z83: 52 | AA83: 13 | AB83: 0
A84: 1 | C84: 재무활동으로인한현금흐름 | E84: -5967 | G84: -3067 | H84: -83474 | I84: 48025 | J84: -18835 | K84: -57351 | L84: -3375 | M84: -3865 | N84: -4223 | O84: 20657 | P84: 9194 | Q84: -4567 | R84: -53188 | S84: -173575 | T84: -13285 | U84: -244615 | V84: -13314 | W84: -48116 | X84: -17162 | Y84: 199224 | Z84: 120632 | AA84: -11116 | AB84: 69491
A85: 1 | C85: 현금및현금성자산의증감 | E85: 43310 | G85: -1178 | H85: 18736 | I85: -55228 | J85: 28273 | K85: -9397 | L85: 48496 | M85: -49736 | N85: 244171 | O85: 5113 | P85: 248044 | Q85: -66816 | R85: -28734 | S85: -58420 | T85: 13002 | U85: -140968 | V85: -126992 | W85: 93470 | X85: 27698 | Y85: 129685 | Z85: 123861 | AA85: -173786 | AB85: 87697
A86: 1 | C86: 기말현금및현금성자산 | E86: 42937 | G86: 117104 | H86: 19034 | I86: -53420 | J86: 19499 | K86: 102217 | L86: 151763 | M86: -50918 | N86: 249555 | O86: -2881 | P86: 347519 | Q86: 284379 | R86: -29237 | S86: -61633 | T86: 13608 | U86: 207117 | V86: 80360 | W86: 89532 | X86: 32043 | Y86: 130181 | Z86: 332116 | AA86: 163576 | AB86: 86071
A87: 1 | C87: 유동성장기부채의감소 | I87: 785 | N87: 0 | O87: 4285 | S87: 664966 | V87: 2002 | W87: 1 | X87: 3029 | Y87: 1 | Z87: 5033 | AA87: 0 | AB87: 25000
A88: 1 | C88: 무형자산의증가 | N88: 0 | O88: 0 | S88: 0 | T88: 0
A89: 1 | C89: 장기차입금의증가 | O89: 25000 | X89: 0 | Y89: 0
A90: 1 | C90: 단기차입금의감소 | V90: 7361 | W90: 374386 | X90: 8588 | Y90: 7361 | Z90: 397696 | AA90: 7370 | AB90: 269099
A91: 1 | C91: 단기차입금의증가 | X91: 0 | Y91: -1

Sheet subQ
A1: YQ | C1: subQ 분기 서브모델(억원, U=100) | E1: 4Q21 | F1: 2021 | G1: 1Q22 | H1: 2Q22 | I1: 3Q22 | J1: 4Q22 | K1: 2022 | L1: 1Q23 | M1: 2Q23 | N1: 3Q23 | O1: 4Q23 | P1: 2023 | Q1: 1Q24 | R1: 2Q24 | S1: 3Q24 | T1: 4Q24 | U1: 2024 | V1: 1Q25 | W1: 2Q25 | X1: 3Q25 | Y1: 4Q25 | Z1: 2025 | AA1: 1Q26 | AB1: 2Q26 | AC1: 3Q26 | AD1: 4Q26 | AE1: 2026 | AF1: 1Q27 | AG1: 2Q27 | AH1: 3Q27 | AI1: 4Q27 | AJ1: 2027 | AK1: 1Q28 | AL1: 2Q28 | AM1: 3Q28 | AN1: 4Q28 | AO1: 2028
A2: A=이름(key) B=그룹 C=단위 D=FnGuide 계정명(VLOOKUP 키). 확정=VLOOKUP(BS), 추정=변수 가정 참조
E3: 1 | F3: 2 | G3: 3 | H3: 4 | I3: 5 | J3: 6 | K3: 7 | L3: 8 | M3: 9 | N3: 10 | O3: 11 | P3: 12 | Q3: 13 | R3: 14 | S3: 15 | T3: 16 | U3: 17 | V3: 18 | W3: 19 | X3: 20 | Y3: 21 | Z3: 22 | AA3: 23 | AB3: 24 | AC3: 25 | AD3: 26 | AE3: 27 | AF3: 28 | AG3: 29 | AH3: 30 | AI3: 31 | AJ3: 32 | AK3: 33 | AL3: 34 | AM3: 35 | AN3: 36 | AO3: 37
E4: 2021.12 | F4: 2021.12A | G4: 2022.03 | H4: 2022.06 | I4: 2022.09 | J4: 2022.12 | K4: 2022.12A | L4: 2023.03 | M4: 2023.06 | N4: 2023.09 | O4: 2023.12 | P4: 2023.12A | Q4: 2024.03 | R4: 2024.06 | S4: 2024.09 | T4: 2024.12 | U4: 2024.12A | V4: 2025.03 | W4: 2025.06 | X4: 2025.09 | Y4: 2025.12 | Z4: 2025.12A | AA4: 2026.03 | AB4: 2026.06 | AC4: 2026.09 | AD4: 2026.12 | AE4: 2026.12A | AF4: 2027.03 | AG4: 2027.06 | AH4: 2027.09 | AI4: 2027.12 | AJ4: 2027.12A | AK4: 2028.03 | AL4: 2028.06 | AM4: 2028.09 | AN4: 2028.12 | AO4: 2028.12A
A5: 매출액 | B5: 손익 | C5: 억원 | D5: 매출액(수익) | E5: =IFERROR(VLOOKUP($D5,BS연결,MATCH(E$1,BS연결H,0),0)/100,"") | G5: =IFERROR(VLOOKUP($D5,BS연결,MATCH(G$1,BS연결H,0),0)/100,"") | H5: =IFERROR(VLOOKUP($D5,BS연결,MATCH(H$1,BS연결H,0),0)/100,"") | I5: =IFERROR(VLOOKUP($D5,BS연결,MATCH(I$1,BS연결H,0),0)/100,"") | J5: =IFERROR(VLOOKUP($D5,BS연결,MATCH(J$1,BS연결H,0),0)/100,"") | K5: =IFERROR(VLOOKUP($D5,BS연결,MATCH(K$1,BS연결H,0),0)/100,"") | L5: =IFERROR(VLOOKUP($D5,BS연결,MATCH(L$1,BS연결H,0),0)/100,"") | M5: =IFERROR(VLOOKUP($D5,BS연결,MATCH(M$1,BS연결H,0),0)/100,"") | N5: =IFERROR(VLOOKUP($D5,BS연결,MATCH(N$1,BS연결H,0),0)/100,"") | ... AB5: =IFERROR(VLOOKUP($D5,BS연결,MATCH(AB$1,BS연결H,0),0)/100,"") | AC5: =IFERROR(AC36+AC40,"") | AD5: =IFERROR(AD36+AD40,"") | AE5: =SUM(AA5:AD5) | AF5: =IFERROR(AF36+AF40,"") | AG5: =IFERROR(AG36+AG40,"") | AH5: =IFERROR(AH36+AH40,"") | AI5: =IFERROR(AI36+AI40,"") | AJ5: =SUM(AF5:AI5) | AK5: =IFERROR(AK36+AK40,"") | AL5: =IFERROR(AL36+AL40,"") | AM5: =IFERROR(AM36+AM40,"") | AN5: =IFERROR(AN36+AN40,"") | AO5: =SUM(AK5:AN5)
A6: 매출원가 | B6: 손익 | C6: 억원 | D6: 매출원가 | E6: =IFERROR(VLOOKUP($D6,BS연결,MATCH(E$1,BS연결H,0),0)/100,"") | G6: =IFERROR(VLOOKUP($D6,BS연결,MATCH(G$1,BS연결H,0),0)/100,"") | H6: =IFERROR(VLOOKUP($D6,BS연결,MATCH(H$1,BS연결H,0),0)/100,"") | I6: =IFERROR(VLOOKUP($D6,BS연결,MATCH(I$1,BS연결H,0),0)/100,"") | J6: =IFERROR(VLOOKUP($D6,BS연결,MATCH(J$1,BS연결H,0),0)/100,"") | K6: =IFERROR(VLOOKUP($D6,BS연결,MATCH(K$1,BS연결H,0),0)/100,"") | L6: =IFERROR(VLOOKUP($D6,BS연결,MATCH(L$1,BS연결H,0),0)/100,"") | M6: =IFERROR(VLOOKUP($D6,BS연결,MATCH(M$1,BS연결H,0),0)/100,"") | N6: =IFERROR(VLOOKUP($D6,BS연결,MATCH(N$1,BS연결H,0),0)/100,"") | ... AB6: =IFERROR(VLOOKUP($D6,BS연결,MATCH(AB$1,BS연결H,0),0)/100,"") | AC6: =IFERROR(AC5-AC7,"") | AD6: =IFERROR(AD5-AD7,"") | AE6: =SUM(AA6:AD6) | AF6: =IFERROR(AF5-AF7,"") | AG6: =IFERROR(AG5-AG7,"") | AH6: =IFERROR(AH5-AH7,"") | AI6: =IFERROR(AI5-AI7,"") | AJ6: =SUM(AF6:AI6) | AK6: =IFERROR(AK5-AK7,"") | AL6: =IFERROR(AL5-AL7,"") | AM6: =IFERROR(AM5-AM7,"") | AN6: =IFERROR(AN5-AN7,"") | AO6: =SUM(AK6:AN6)
A7: 매출총이익 | B7: 손익 | C7: 억원 | D7: 매출총이익 | E7: =IFERROR(VLOOKUP($D7,BS연결,MATCH(E$1,BS연결H,0),0)/100,"") | G7: =IFERROR(VLOOKUP($D7,BS연결,MATCH(G$1,BS연결H,0),0)/100,"") | H7: =IFERROR(VLOOKUP($D7,BS연결,MATCH(H$1,BS연결H,0),0)/100,"") | I7: =IFERROR(VLOOKUP($D7,BS연결,MATCH(I$1,BS연결H,0),0)/100,"") | J7: =IFERROR(VLOOKUP($D7,BS연결,MATCH(J$1,BS연결H,0),0)/100,"") | K7: =IFERROR(VLOOKUP($D7,BS연결,MATCH(K$1,BS연결H,0),0)/100,"") | L7: =IFERROR(VLOOKUP($D7,BS연결,MATCH(L$1,BS연결H,0),0)/100,"") | M7: =IFERROR(VLOOKUP($D7,BS연결,MATCH(M$1,BS연결H,0),0)/100,"") | N7: =IFERROR(VLOOKUP($D7,BS연결,MATCH(N$1,BS연결H,0),0)/100,"") | ... AB7: =IFERROR(VLOOKUP($D7,BS연결,MATCH(AB$1,BS연결H,0),0)/100,"") | AC7: =IFERROR(AC9+AC8,"") | AD7: =IFERROR(AD9+AD8,"") | AE7: =SUM(AA7:AD7) | AF7: =IFERROR(AF9+AF8,"") | AG7: =IFERROR(AG9+AG8,"") | AH7: =IFERROR(AH9+AH8,"") | AI7: =IFERROR(AI9+AI8,"") | AJ7: =SUM(AF7:AI7) | AK7: =IFERROR(AK9+AK8,"") | AL7: =IFERROR(AL9+AL8,"") | AM7: =IFERROR(AM9+AM8,"") | AN7: =IFERROR(AN9+AN8,"") | AO7: =SUM(AK7:AN7)
A8: 판관비 | B8: 손익 | C8: 억원 | D8: 판관비 | E8: =IFERROR(VLOOKUP($D8,BS연결,MATCH(E$1,BS연결H,0),0)/100,"") | G8: =IFERROR(VLOOKUP($D8,BS연결,MATCH(G$1,BS연결H,0),0)/100,"") | H8: =IFERROR(VLOOKUP($D8,BS연결,MATCH(H$1,BS연결H,0),0)/100,"") | I8: =IFERROR(VLOOKUP($D8,BS연결,MATCH(I$1,BS연결H,0),0)/100,"") | J8: =IFERROR(VLOOKUP($D8,BS연결,MATCH(J$1,BS연결H,0),0)/100,"") | K8: =IFERROR(VLOOKUP($D8,BS연결,MATCH(K$1,BS연결H,0),0)/100,"") | L8: =IFERROR(VLOOKUP($D8,BS연결,MATCH(L$1,BS연결H,0),0)/100,"") | M8: =IFERROR(VLOOKUP($D8,BS연결,MATCH(M$1,BS연결H,0),0)/100,"") | N8: =IFERROR(VLOOKUP($D8,BS연결,MATCH(N$1,BS연결H,0),0)/100,"") | ... AB8: =IFERROR(VLOOKUP($D8,BS연결,MATCH(AB$1,BS연결H,0),0)/100,"") | AC8: =IFERROR(AC5*변수!AC21,"") | AD8: =IFERROR(AD5*변수!AD21,"") | AE8: =SUM(AA8:AD8) | AF8: =IFERROR(AF5*변수!AF21,"") | AG8: =IFERROR(AG5*변수!AG21,"") | AH8: =IFERROR(AH5*변수!AH21,"") | AI8: =IFERROR(AI5*변수!AI21,"") | AJ8: =SUM(AF8:AI8) | AK8: =IFERROR(AK5*변수!AK21,"") | AL8: =IFERROR(AL5*변수!AL21,"") | AM8: =IFERROR(AM5*변수!AM21,"") | AN8: =IFERROR(AN5*변수!AN21,"") | AO8: =SUM(AK8:AN8)
A9: 영업이익 | B9: 손익 | C9: 억원 | D9: 영업이익 | E9: =IFERROR(VLOOKUP($D9,BS연결,MATCH(E$1,BS연결H,0),0)/100,"") | G9: =IFERROR(VLOOKUP($D9,BS연결,MATCH(G$1,BS연결H,0),0)/100,"") | H9: =IFERROR(VLOOKUP($D9,BS연결,MATCH(H$1,BS연결H,0),0)/100,"") | I9: =IFERROR(VLOOKUP($D9,BS연결,MATCH(I$1,BS연결H,0),0)/100,"") | J9: =IFERROR(VLOOKUP($D9,BS연결,MATCH(J$1,BS연결H,0),0)/100,"") | K9: =IFERROR(VLOOKUP($D9,BS연결,MATCH(K$1,BS연결H,0),0)/100,"") | L9: =IFERROR(VLOOKUP($D9,BS연결,MATCH(L$1,BS연결H,0),0)/100,"") | M9: =IFERROR(VLOOKUP($D9,BS연결,MATCH(M$1,BS연결H,0),0)/100,"") | N9: =IFERROR(VLOOKUP($D9,BS연결,MATCH(N$1,BS연결H,0),0)/100,"") | ... AB9: =IFERROR(VLOOKUP($D9,BS연결,MATCH(AB$1,BS연결H,0),0)/100,"") | AC9: =IFERROR(AC38+AC41,"") | AD9: =IFERROR(AD38+AD41,"") | AE9: =SUM(AA9:AD9) | AF9: =IFERROR(AF38+AF41,"") | AG9: =IFERROR(AG38+AG41,"") | AH9: =IFERROR(AH38+AH41,"") | AI9: =IFERROR(AI38+AI41,"") | AJ9: =SUM(AF9:AI9) | AK9: =IFERROR(AK38+AK41,"") | AL9: =IFERROR(AL38+AL41,"") | AM9: =IFERROR(AM38+AM41,"") | AN9: =IFERROR(AN38+AN41,"") | AO9: =SUM(AK9:AN9)
A10: OPM | B10: 손익 | C10: % | D10: 영업이익률 | E10: =IFERROR(E9/E5,"") | G10: =IFERROR(G9/G5,"") | H10: =IFERROR(H9/H5,"") | I10: =IFERROR(I9/I5,"") | J10: =IFERROR(J9/J5,"") | K10: =IFERROR(K9/K5,"") | L10: =IFERROR(L9/L5,"") | M10: =IFERROR(M9/M5,"") | N10: =IFERROR(N9/N5,"") | ... AO10: =IFERROR(AO9/AO5,"")
A11: 금융손익 | B11: 손익 | C11: 억원 | D11: 금융손익 | E11: =IFERROR(VLOOKUP($D11,BS연결,MATCH(E$1,BS연결H,0),0)/100,"") | G11: =IFERROR(VLOOKUP($D11,BS연결,MATCH(G$1,BS연결H,0),0)/100,"") | H11: =IFERROR(VLOOKUP($D11,BS연결,MATCH(H$1,BS연결H,0),0)/100,"") | I11: =IFERROR(VLOOKUP($D11,BS연결,MATCH(I$1,BS연결H,0),0)/100,"") | J11: =IFERROR(VLOOKUP($D11,BS연결,MATCH(J$1,BS연결H,0),0)/100,"") | K11: =IFERROR(VLOOKUP($D11,BS연결,MATCH(K$1,BS연결H,0),0)/100,"") | L11: =IFERROR(VLOOKUP($D11,BS연결,MATCH(L$1,BS연결H,0),0)/100,"") | M11: =IFERROR(VLOOKUP($D11,BS연결,MATCH(M$1,BS연결H,0),0)/100,"") | N11: =IFERROR(VLOOKUP($D11,BS연결,MATCH(N$1,BS연결H,0),0)/100,"") | ... AB11: =IFERROR(VLOOKUP($D11,BS연결,MATCH(AB$1,BS연결H,0),0)/100,"") | AC11: =IFERROR(AC12+AC13,"") | AD11: =IFERROR(AD12+AD13,"") | AE11: =SUM(AA11:AD11) | AF11: =IFERROR(AF12+AF13,"") | AG11: =IFERROR(AG12+AG13,"") | AH11: =IFERROR(AH12+AH13,"") | AI11: =IFERROR(AI12+AI13,"") | AJ11: =SUM(AF11:AI11) | AK11: =IFERROR(AK12+AK13,"") | AL11: =IFERROR(AL12+AL13,"") | AM11: =IFERROR(AM12+AM13,"") | AN11: =IFERROR(AN12+AN13,"") | AO11: =SUM(AK11:AN11)
A12: 이자손익 | B12: 손익 | C12: 억원 | D12: 이자손익 | G12: =IFERROR(VLOOKUP($D12,BS연결,MATCH(G$1,BS연결H,0),0)/100,"") | H12: =IFERROR(VLOOKUP($D12,BS연결,MATCH(H$1,BS연결H,0),0)/100,"") | I12: =IFERROR(VLOOKUP($D12,BS연결,MATCH(I$1,BS연결H,0),0)/100,"") | J12: =IFERROR(VLOOKUP($D12,BS연결,MATCH(J$1,BS연결H,0),0)/100,"") | K12: =IFERROR(VLOOKUP($D12,BS연결,MATCH(K$1,BS연결H,0),0)/100,"") | L12: =IFERROR(VLOOKUP($D12,BS연결,MATCH(L$1,BS연결H,0),0)/100,"") | M12: =IFERROR(VLOOKUP($D12,BS연결,MATCH(M$1,BS연결H,0),0)/100,"") | N12: =IFERROR(VLOOKUP($D12,BS연결,MATCH(N$1,BS연결H,0),0)/100,"") | P12: =SUM(L12:O12) | Q12: =IFERROR(VLOOKUP($D12,BS연결,MATCH(Q$1,BS연결H,0),0)/100,"") | R12: =IFERROR(VLOOKUP($D12,BS연결,MATCH(R$1,BS연결H,0),0)/100,"") | S12: =IFERROR(VLOOKUP($D12,BS연결,MATCH(S$1,BS연결H,0),0)/100,"") | U12: =SUM(Q12:T12) | V12: =IFERROR(VLOOKUP($D12,BS연결,MATCH(V$1,BS연결H,0),0)/100,"") | W12: =IFERROR(VLOOKUP($D12,BS연결,MATCH(W$1,BS연결H,0),0)/100,"") | X12: =IFERROR(VLOOKUP($D12,BS연결,MATCH(X$1,BS연결H,0),0)/100,"") | Z12: =SUM(V12:Y12) | AA12: =IFERROR(VLOOKUP($D12,BS연결,MATCH(AA$1,BS연결H,0),0)/100,"") | AB12: =IFERROR(VLOOKUP($D12,BS연결,MATCH(AB$1,BS연결H,0),0)/100,"") | AC12: =IFERROR((AB26*변수!$D$55-AB24*변수!$D$56)/4,"") | AD12: =IFERROR((AC26*변수!$D$55-AC24*변수!$D$56)/4,"") | AE12: =SUM(AA12:AD12) | AF12: =IFERROR((AD26*변수!$D$55-AD24*변수!$D$56)/4,"") | AG12: =IFERROR((AF26*변수!$D$55-AF24*변수!$D$56)/4,"") | AH12: =IFERROR((AG26*변수!$D$55-AG24*변수!$D$56)/4,"") | AI12: =IFERROR((AH26*변수!$D$55-AH24*변수!$D$56)/4,"") | AJ12: =SUM(AF12:AI12) | AK12: =IFERROR((AI26*변수!$D$55-AI24*변수!$D$56)/4,"") | AL12: =IFERROR((AK26*변수!$D$55-AK24*변수!$D$56)/4,"") | AM12: =IFERROR((AL26*변수!$D$55-AL24*변수!$D$56)/4,"") | AN12: =IFERROR((AM26*변수!$D$55-AM24*변수!$D$56)/4,"") | AO12: =SUM(AK12:AN12)
A13: 외환손익 | B13: 손익 | C13: 억원 | D13: 외환손익(실적만; 추정 환효과는 환관련손익) | G13: =IFERROR((VLOOKUP("외환차익",BS연결,MATCH(G$1,BS연결H,0),0)-VLOOKUP("외환차손",BS연결,MATCH(G$1,BS연결H,0),0)+VLOOKUP("외화환산이익",BS연결,MATCH(G$1,BS연결H,0),0)-VLOOKUP("외화환산손실",BS연결,MATCH(G$1,BS연결H,0),0))/100,"") | H13: =IFERROR((VLOOKUP("외환차익",BS연결,MATCH(H$1,BS연결H,0),0)-VLOOKUP("외환차손",BS연결,MATCH(H$1,BS연결H,0),0)+VLOOKUP("외화환산이익",BS연결,MATCH(H$1,BS연결H,0),0)-VLOOKUP("외화환산손실",BS연결,MATCH(H$1,BS연결H,0),0))/100,"") | I13: =IFERROR((VLOOKUP("외환차익",BS연결,MATCH(I$1,BS연결H,0),0)-VLOOKUP("외환차손",BS연결,MATCH(I$1,BS연결H,0),0)+VLOOKUP("외화환산이익",BS연결,MATCH(I$1,BS연결H,0),0)-VLOOKUP("외화환산손실",BS연결,MATCH(I$1,BS연결H,0),0))/100,"") | J13: =IFERROR((VLOOKUP("외환차익",BS연결,MATCH(J$1,BS연결H,0),0)-VLOOKUP("외환차손",BS연결,MATCH(J$1,BS연결H,0),0)+VLOOKUP("외화환산이익",BS연결,MATCH(J$1,BS연결H,0),0)-VLOOKUP("외화환산손실",BS연결,MATCH(J$1,BS연결H,0),0))/100,"") | K13: =SUM(G13:J13) | L13: =IFERROR((VLOOKUP("외환차익",BS연결,MATCH(L$1,BS연결H,0),0)-VLOOKUP("외환차손",BS연결,MATCH(L$1,BS연결H,0),0)+VLOOKUP("외화환산이익",BS연결,MATCH(L$1,BS연결H,0),0)-VLOOKUP("외화환산손실",BS연결,MATCH(L$1,BS연결H,0),0))/100,"") | M13: =IFERROR((VLOOKUP("외환차익",BS연결,MATCH(M$1,BS연결H,0),0)-VLOOKUP("외환차손",BS연결,MATCH(M$1,BS연결H,0),0)+VLOOKUP("외화환산이익",BS연결,MATCH(M$1,BS연결H,0),0)-VLOOKUP("외화환산손실",BS연결,MATCH(M$1,BS연결H,0),0))/100,"") | N13: =IFERROR((VLOOKUP("외환차익",BS연결,MATCH(N$1,BS연결H,0),0)-VLOOKUP("외환차손",BS연결,MATCH(N$1,BS연결H,0),0)+VLOOKUP("외화환산이익",BS연결,MATCH(N$1,BS연결H,0),0)-VLOOKUP("외화환산손실",BS연결,MATCH(N$1,BS연결H,0),0))/100,"") | O13: =IFERROR((VLOOKUP("외환차익",BS연결,MATCH(O$1,BS연결H,0),0)-VLOOKUP("외환차손",BS연결,MATCH(O$1,BS연결H,0),0)+VLOOKUP("외화환산이익",BS연결,MATCH(O$1,BS연결H,0),0)-VLOOKUP("외화환산손실",BS연결,MATCH(O$1,BS연결H,0),0))/100,"") | P13: =SUM(L13:O13) | Q13: =IFERROR((VLOOKUP("외환차익",BS연결,MATCH(Q$1,BS연결H,0),0)-VLOOKUP("외환차손",BS연결,MATCH(Q$1,BS연결H,0),0)+VLOOKUP("외화환산이익",BS연결,MATCH(Q$1,BS연결H,0),0)-VLOOKUP("외화환산손실",BS연결,MATCH(Q$1,BS연결H,0),0))/100,"") | R13: =IFERROR((VLOOKUP("외환차익",BS연결,MATCH(R$1,BS연결H,0),0)-VLOOKUP("외환차손",BS연결,MATCH(R$1,BS연결H,0),0)+VLOOKUP("외화환산이익",BS연결,MATCH(R$1,BS연결H,0),0)-VLOOKUP("외화환산손실",BS연결,MATCH(R$1,BS연결H,0),0))/100,"") | S13: =IFERROR((VLOOKUP("외환차익",BS연결,MATCH(S$1,BS연결H,0),0)-VLOOKUP("외환차손",BS연결,MATCH(S$1,BS연결H,0),0)+VLOOKUP("외화환산이익",BS연결,MATCH(S$1,BS연결H,0),0)-VLOOKUP("외화환산손실",BS연결,MATCH(S$1,BS연결H,0),0))/100,"") | T13: =IFERROR((VLOOKUP("외환차익",BS연결,MATCH(T$1,BS연결H,0),0)-VLOOKUP("외환차손",BS연결,MATCH(T$1,BS연결H,0),0)+VLOOKUP("외화환산이익",BS연결,MATCH(T$1,BS연결H,0),0)-VLOOKUP("외화환산손실",BS연결,MATCH(T$1,BS연결H,0),0))/100,"") | U13: =SUM(Q13:T13) | V13: =IFERROR((VLOOKUP("외환차익",BS연결,MATCH(V$1,BS연결H,0),0)-VLOOKUP("외환차손",BS연결,MATCH(V$1,BS연결H,0),0)+VLOOKUP("외화환산이익",BS연결,MATCH(V$1,BS연결H,0),0)-VLOOKUP("외화환산손실",BS연결,MATCH(V$1,BS연결H,0),0))/100,"") | W13: =IFERROR((VLOOKUP("외환차익",BS연결,MATCH(W$1,BS연결H,0),0)-VLOOKUP("외환차손",BS연결,MATCH(W$1,BS연결H,0),0)+VLOOKUP("외화환산이익",BS연결,MATCH(W$1,BS연결H,0),0)-VLOOKUP("외화환산손실",BS연결,MATCH(W$1,BS연결H,0),0))/100,"") | X13: =IFERROR((VLOOKUP("외환차익",BS연결,MATCH(X$1,BS연결H,0),0)-VLOOKUP("외환차손",BS연결,MATCH(X$1,BS연결H,0),0)+VLOOKUP("외화환산이익",BS연결,MATCH(X$1,BS연결H,0),0)-VLOOKUP("외화환산손실",BS연결,MATCH(X$1,BS연결H,0),0))/100,"") | Y13: =IFERROR((VLOOKUP("외환차익",BS연결,MATCH(Y$1,BS연결H,0),0)-VLOOKUP("외환차손",BS연결,MATCH(Y$1,BS연결H,0),0)+VLOOKUP("외화환산이익",BS연결,MATCH(Y$1,BS연결H,0),0)-VLOOKUP("외화환산손실",BS연결,MATCH(Y$1,BS연결H,0),0))/100,"") | Z13: =SUM(V13:Y13) | AA13: =IFERROR((VLOOKUP("외환차익",BS연결,MATCH(AA$1,BS연결H,0),0)-VLOOKUP("외환차손",BS연결,MATCH(AA$1,BS연결H,0),0)+VLOOKUP("외화환산이익",BS연결,MATCH(AA$1,BS연결H,0),0)-VLOOKUP("외화환산손실",BS연결,MATCH(AA$1,BS연결H,0),0))/100,"") | AB13: =IFERROR((VLOOKUP("외환차익",BS연결,MATCH(AB$1,BS연결H,0),0)-VLOOKUP("외환차손",BS연결,MATCH(AB$1,BS연결H,0),0)+VLOOKUP("외화환산이익",BS연결,MATCH(AB$1,BS연결H,0),0)-VLOOKUP("외화환산손실",BS연결,MATCH(AB$1,BS연결H,0),0))/100,"") | AC13: =변수!AC22 | AD13: =변수!AD22 | AE13: =SUM(AA13:AD13) | AF13: =변수!AF22 | AG13: =변수!AG22 | AH13: =변수!AH22 | AI13: =변수!AI22 | AJ13: =SUM(AF13:AI13) | AK13: =변수!AK22 | AL13: =변수!AL22 | AM13: =변수!AM22 | AN13: =변수!AN22 | AO13: =SUM(AK13:AN13)
A14: 기타영업외손익 | B14: 손익 | C14: 억원 | D14: 기타영업외손익 | E14: =IFERROR(VLOOKUP($D14,BS연결,MATCH(E$1,BS연결H,0),0)/100,"") | G14: =IFERROR(VLOOKUP($D14,BS연결,MATCH(G$1,BS연결H,0),0)/100,"") | H14: =IFERROR(VLOOKUP($D14,BS연결,MATCH(H$1,BS연결H,0),0)/100,"") | I14: =IFERROR(VLOOKUP($D14,BS연결,MATCH(I$1,BS연결H,0),0)/100,"") | J14: =IFERROR(VLOOKUP($D14,BS연결,MATCH(J$1,BS연결H,0),0)/100,"") | K14: =IFERROR(VLOOKUP($D14,BS연결,MATCH(K$1,BS연결H,0),0)/100,"") | L14: =IFERROR(VLOOKUP($D14,BS연결,MATCH(L$1,BS연결H,0),0)/100,"") | M14: =IFERROR(VLOOKUP($D14,BS연결,MATCH(M$1,BS연결H,0),0)/100,"") | N14: =IFERROR(VLOOKUP($D14,BS연결,MATCH(N$1,BS연결H,0),0)/100,"") | ... AB14: =IFERROR(VLOOKUP($D14,BS연결,MATCH(AB$1,BS연결H,0),0)/100,"") | AC14: =변수!AC23 | AD14: =변수!AD23 | AE14: =SUM(AA14:AD14) | AF14: =변수!AF23 | AG14: =변수!AG23 | AH14: =변수!AH23 | AI14: =변수!AI23 | AJ14: =SUM(AF14:AI14) | AK14: =변수!AK23 | AL14: =변수!AL23 | AM14: =변수!AM23 | AN14: =변수!AN23 | AO14: =SUM(AK14:AN14)
A15: 세전이익 | B15: 손익 | C15: 억원 | D15: 법인세비용차감전계속사업이익 | E15: =IFERROR(VLOOKUP($D15,BS연결,MATCH(E$1,BS연결H,0),0)/100,"") | G15: =IFERROR(VLOOKUP($D15,BS연결,MATCH(G$1,BS연결H,0),0)/100,"") | H15: =IFERROR(VLOOKUP($D15,BS연결,MATCH(H$1,BS연결H,0),0)/100,"") | I15: =IFERROR(VLOOKUP($D15,BS연결,MATCH(I$1,BS연결H,0),0)/100,"") | J15: =IFERROR(VLOOKUP($D15,BS연결,MATCH(J$1,BS연결H,0),0)/100,"") | K15: =IFERROR(VLOOKUP($D15,BS연결,MATCH(K$1,BS연결H,0),0)/100,"") | L15: =IFERROR(VLOOKUP($D15,BS연결,MATCH(L$1,BS연결H,0),0)/100,"") | M15: =IFERROR(VLOOKUP($D15,BS연결,MATCH(M$1,BS연결H,0),0)/100,"") | N15: =IFERROR(VLOOKUP($D15,BS연결,MATCH(N$1,BS연결H,0),0)/100,"") | ... AB15: =IFERROR(VLOOKUP($D15,BS연결,MATCH(AB$1,BS연결H,0),0)/100,"") | AC15: =IFERROR(AC9+AC11+AC14,"") | AD15: =IFERROR(AD9+AD11+AD14,"") | AE15: =SUM(AA15:AD15) | AF15: =IFERROR(AF9+AF11+AF14,"") | AG15: =IFERROR(AG9+AG11+AG14,"") | AH15: =IFERROR(AH9+AH11+AH14,"") | AI15: =IFERROR(AI9+AI11+AI14,"") | AJ15: =SUM(AF15:AI15) | AK15: =IFERROR(AK9+AK11+AK14,"") | AL15: =IFERROR(AL9+AL11+AL14,"") | AM15: =IFERROR(AM9+AM11+AM14,"") | AN15: =IFERROR(AN9+AN11+AN14,"") | AO15: =SUM(AK15:AN15)
A16: 법인세비용 | B16: 손익 | C16: 억원 | D16: 법인세비용 | E16: =IFERROR(VLOOKUP($D16,BS연결,MATCH(E$1,BS연결H,0),0)/100,"") | G16: =IFERROR(VLOOKUP($D16,BS연결,MATCH(G$1,BS연결H,0),0)/100,"") | H16: =IFERROR(VLOOKUP($D16,BS연결,MATCH(H$1,BS연결H,0),0)/100,"") | I16: =IFERROR(VLOOKUP($D16,BS연결,MATCH(I$1,BS연결H,0),0)/100,"") | J16: =IFERROR(VLOOKUP($D16,BS연결,MATCH(J$1,BS연결H,0),0)/100,"") | K16: =IFERROR(VLOOKUP($D16,BS연결,MATCH(K$1,BS연결H,0),0)/100,"") | L16: =IFERROR(VLOOKUP($D16,BS연결,MATCH(L$1,BS연결H,0),0)/100,"") | M16: =IFERROR(VLOOKUP($D16,BS연결,MATCH(M$1,BS연결H,0),0)/100,"") | N16: =IFERROR(VLOOKUP($D16,BS연결,MATCH(N$1,BS연결H,0),0)/100,"") | ... AB16: =IFERROR(VLOOKUP($D16,BS연결,MATCH(AB$1,BS연결H,0),0)/100,"") | AC16: =IFERROR(MAX(AC15,0)*변수!AC24,"") | AD16: =IFERROR(MAX(AD15,0)*변수!AD24,"") | AE16: =SUM(AA16:AD16) | AF16: =IFERROR(MAX(AF15,0)*변수!AF24,"") | AG16: =IFERROR(MAX(AG15,0)*변수!AG24,"") | AH16: =IFERROR(MAX(AH15,0)*변수!AH24,"") | AI16: =IFERROR(MAX(AI15,0)*변수!AI24,"") | AJ16: =SUM(AF16:AI16) | AK16: =IFERROR(MAX(AK15,0)*변수!AK24,"") | AL16: =IFERROR(MAX(AL15,0)*변수!AL24,"") | AM16: =IFERROR(MAX(AM15,0)*변수!AM24,"") | AN16: =IFERROR(MAX(AN15,0)*변수!AN24,"") | AO16: =SUM(AK16:AN16)
A17: 당기순이익 | B17: 손익 | C17: 억원 | D17: 당기순이익 | E17: =IFERROR(VLOOKUP($D17,BS연결,MATCH(E$1,BS연결H,0),0)/100,"") | I17: =IFERROR(VLOOKUP($D17,BS연결,MATCH(I$1,BS연결H,0),0)/100,"") | J17: =IFERROR(VLOOKUP($D17,BS연결,MATCH(J$1,BS연결H,0),0)/100,"") | K17: =SUM(G17:J17) | N17: =IFERROR(VLOOKUP($D17,BS연결,MATCH(N$1,BS연결H,0),0)/100,"") | O17: =IFERROR(VLOOKUP($D17,BS연결,MATCH(O$1,BS연결H,0),0)/100,"") | P17: =SUM(L17:O17) | Q17: =IFERROR(VLOOKUP($D17,BS연결,MATCH(Q$1,BS연결H,0),0)/100,"") | R17: =IFERROR(VLOOKUP($D17,BS연결,MATCH(R$1,BS연결H,0),0)/100,"") | S17: =IFERROR(VLOOKUP($D17,BS연결,MATCH(S$1,BS연결H,0),0)/100,"") | T17: =IFERROR(VLOOKUP($D17,BS연결,MATCH(T$1,BS연결H,0),0)/100,"") | U17: =IFERROR(VLOOKUP($D17,BS연결,MATCH(U$1,BS연결H,0),0)/100,"") | V17: =IFERROR(VLOOKUP($D17,BS연결,MATCH(V$1,BS연결H,0),0)/100,"") | W17: =IFERROR(VLOOKUP($D17,BS연결,MATCH(W$1,BS연결H,0),0)/100,"") | X17: =IFERROR(VLOOKUP($D17,BS연결,MATCH(X$1,BS연결H,0),0)/100,"") | ... AB17: =IFERROR(VLOOKUP($D17,BS연결,MATCH(AB$1,BS연결H,0),0)/100,"") | AC17: =IFERROR(AC15-AC16,"") | AD17: =IFERROR(AD15-AD16,"") | AE17: =SUM(AA17:AD17) | AF17: =IFERROR(AF15-AF16,"") | AG17: =IFERROR(AG15-AG16,"") | AH17: =IFERROR(AH15-AH16,"") | AI17: =IFERROR(AI15-AI16,"") | AJ17: =SUM(AF17:AI17) | AK17: =IFERROR(AK15-AK16,"") | AL17: =IFERROR(AL15-AL16,"") | AM17: =IFERROR(AM15-AM16,"") | AN17: =IFERROR(AN15-AN16,"") | AO17: =SUM(AK17:AN17)
A18: 지배주주순이익 | B18: 손익 | C18: 억원 | D18: (지배주주지분)당기순이익 | E18: =IFERROR(VLOOKUP($D18,BS연결,MATCH(E$1,BS연결H,0),0)/100,"") | G18: =IFERROR(VLOOKUP($D18,BS연결,MATCH(G$1,BS연결H,0),0)/100,"") | H18: =IFERROR(VLOOKUP($D18,BS연결,MATCH(H$1,BS연결H,0),0)/100,"") | I18: =IFERROR(VLOOKUP($D18,BS연결,MATCH(I$1,BS연결H,0),0)/100,"") | J18: =IFERROR(VLOOKUP($D18,BS연결,MATCH(J$1,BS연결H,0),0)/100,"") | K18: =IFERROR(VLOOKUP($D18,BS연결,MATCH(K$1,BS연결H,0),0)/100,"") | L18: =IFERROR(VLOOKUP($D18,BS연결,MATCH(L$1,BS연결H,0),0)/100,"") | M18: =IFERROR(VLOOKUP($D18,BS연결,MATCH(M$1,BS연결H,0),0)/100,"") | N18: =IFERROR(VLOOKUP($D18,BS연결,MATCH(N$1,BS연결H,0),0)/100,"") | ... AB18: =IFERROR(VLOOKUP($D18,BS연결,MATCH(AB$1,BS연결H,0),0)/100,"") | AC18: =IFERROR(AC17*변수!AC25,"") | AD18: =IFERROR(AD17*변수!AD25,"") | AE18: =SUM(AA18:AD18) | AF18: =IFERROR(AF17*변수!AF25,"") | AG18: =IFERROR(AG17*변수!AG25,"") | AH18: =IFERROR(AH17*변수!AH25,"") | AI18: =IFERROR(AI17*변수!AI25,"") | AJ18: =SUM(AF18:AI18) | AK18: =IFERROR(AK17*변수!AK25,"") | AL18: =IFERROR(AL17*변수!AL25,"") | AM18: =IFERROR(AM17*변수!AM25,"") | AN18: =IFERROR(AN17*변수!AN25,"") | AO18: =SUM(AK18:AN18)
A19: 중단사업이익 | B19: 손익 | C19: 억원 | D19: 중단사업이익 | E19: =IFERROR(VLOOKUP($D19,BS연결,MATCH(E$1,BS연결H,0),0)/100,"") | K19: =SUM(G19:J19) | P19: =SUM(L19:O19) | U19: =SUM(Q19:T19) | Z19: =SUM(V19:Y19) | AE19: =SUM(AA19:AD19) | AJ19: =SUM(AF19:AI19) | AO19: =SUM(AK19:AN19)
A20: 자산총계 | B20: 재무상태 | C20: 억원 | D20: 자산총계 | E20: =IFERROR(VLOOKUP($D20,BS연결,MATCH(E$1,BS연결H,0),0)/100,"") | F20: =IFERROR(VLOOKUP($D20,BS연결,MATCH(F$1,BS연결H,0),0)/100,"") | G20: =IFERROR(VLOOKUP($D20,BS연결,MATCH(G$1,BS연결H,0),0)/100,"") | H20: =IFERROR(VLOOKUP($D20,BS연결,MATCH(H$1,BS연결H,0),0)/100,"") | I20: =IFERROR(VLOOKUP($D20,BS연결,MATCH(I$1,BS연결H,0),0)/100,"") | J20: =IFERROR(VLOOKUP($D20,BS연결,MATCH(J$1,BS연결H,0),0)/100,"") | K20: =IFERROR(VLOOKUP($D20,BS연결,MATCH(K$1,BS연결H,0),0)/100,"") | L20: =IFERROR(VLOOKUP($D20,BS연결,MATCH(L$1,BS연결H,0),0)/100,"") | ... AB20: =IFERROR(VLOOKUP($D20,BS연결,MATCH(AB$1,BS연결H,0),0)/100,"") | AC20: =IFERROR(AC21+AC22,"") | AD20: =IFERROR(AD21+AD22,"") | AE20: =AD20 | AF20: =IFERROR(AF21+AF22,"") | AG20: =IFERROR(AG21+AG22,"") | AH20: =IFERROR(AH21+AH22,"") | AI20: =IFERROR(AI21+AI22,"") | AJ20: =AI20 | AK20: =IFERROR(AK21+AK22,"") | AL20: =IFERROR(AL21+AL22,"") | AM20: =IFERROR(AM21+AM22,"") | AN20: =IFERROR(AN21+AN22,"") | AO20: =AN20
A21: 부채총계 | B21: 재무상태 | C21: 억원 | D21: 부채총계 | E21: =IFERROR(VLOOKUP($D21,BS연결,MATCH(E$1,BS연결H,0),0)/100,"") | F21: =IFERROR(VLOOKUP($D21,BS연결,MATCH(F$1,BS연결H,0),0)/100,"") | G21: =IFERROR(VLOOKUP($D21,BS연결,MATCH(G$1,BS연결H,0),0)/100,"") | H21: =IFERROR(VLOOKUP($D21,BS연결,MATCH(H$1,BS연결H,0),0)/100,"") | I21: =IFERROR(VLOOKUP($D21,BS연결,MATCH(I$1,BS연결H,0),0)/100,"") | J21: =IFERROR(VLOOKUP($D21,BS연결,MATCH(J$1,BS연결H,0),0)/100,"") | K21: =IFERROR(VLOOKUP($D21,BS연결,MATCH(K$1,BS연결H,0),0)/100,"") | L21: =IFERROR(VLOOKUP($D21,BS연결,MATCH(L$1,BS연결H,0),0)/100,"") | ... AB21: =IFERROR(VLOOKUP($D21,BS연결,MATCH(AB$1,BS연결H,0),0)/100,"") | AC21: =IFERROR(AB21*(1+변수!AC27),"") | AD21: =IFERROR(AC21*(1+변수!AD27),"") | AE21: =AD21 | AF21: =IFERROR(AD21*(1+변수!AF27),"") | AG21: =IFERROR(AF21*(1+변수!AG27),"") | AH21: =IFERROR(AG21*(1+변수!AH27),"") | AI21: =IFERROR(AH21*(1+변수!AI27),"") | AJ21: =AI21 | AK21: =IFERROR(AI21*(1+변수!AK27),"") | AL21: =IFERROR(AK21*(1+변수!AL27),"") | AM21: =IFERROR(AL21*(1+변수!AM27),"") | AN21: =IFERROR(AM21*(1+변수!AN27),"") | AO21: =AN21
A22: 자본총계 | B22: 재무상태 | C22: 억원 | D22: 자본총계 | E22: =IFERROR(VLOOKUP($D22,BS연결,MATCH(E$1,BS연결H,0),0)/100,"") | F22: =IFERROR(VLOOKUP($D22,BS연결,MATCH(F$1,BS연결H,0),0)/100,"") | G22: =IFERROR(VLOOKUP($D22,BS연결,MATCH(G$1,BS연결H,0),0)/100,"") | H22: =IFERROR(VLOOKUP($D22,BS연결,MATCH(H$1,BS연결H,0),0)/100,"") | I22: =IFERROR(VLOOKUP($D22,BS연결,MATCH(I$1,BS연결H,0),0)/100,"") | J22: =IFERROR(VLOOKUP($D22,BS연결,MATCH(J$1,BS연결H,0),0)/100,"") | K22: =IFERROR(VLOOKUP($D22,BS연결,MATCH(K$1,BS연결H,0),0)/100,"") | L22: =IFERROR(VLOOKUP($D22,BS연결,MATCH(L$1,BS연결H,0),0)/100,"") | ... AB22: =IFERROR(VLOOKUP($D22,BS연결,MATCH(AB$1,BS연결H,0),0)/100,"") | AC22: =IFERROR(AB22+AC17-변수!AC28,"") | AD22: =IFERROR(AC22+AD17-변수!AD28,"") | AE22: =AD22 | AF22: =IFERROR(AD22+AF17-변수!AF28,"") | AG22: =IFERROR(AF22+AG17-변수!AG28,"") | AH22: =IFERROR(AG22+AH17-변수!AH28,"") | AI22: =IFERROR(AH22+AI17-변수!AI28,"") | AJ22: =AI22 | AK22: =IFERROR(AI22+AK17-변수!AK28,"") | AL22: =IFERROR(AK22+AL17-변수!AL28,"") | AM22: =IFERROR(AL22+AM17-변수!AM28,"") | AN22: =IFERROR(AM22+AN17-변수!AN28,"") | AO22: =AN22
A23: 지배주주지분 | B23: 재무상태 | C23: 억원 | D23: 지배주주지분 | E23: =IFERROR(VLOOKUP($D23,BS연결,MATCH(E$1,BS연결H,0),0)/100,"") | F23: =IFERROR(VLOOKUP($D23,BS연결,MATCH(F$1,BS연결H,0),0)/100,"") | G23: =IFERROR(VLOOKUP($D23,BS연결,MATCH(G$1,BS연결H,0),0)/100,"") | H23: =IFERROR(VLOOKUP($D23,BS연결,MATCH(H$1,BS연결H,0),0)/100,"") | I23: =IFERROR(VLOOKUP($D23,BS연결,MATCH(I$1,BS연결H,0),0)/100,"") | J23: =IFERROR(VLOOKUP($D23,BS연결,MATCH(J$1,BS연결H,0),0)/100,"") | K23: =IFERROR(VLOOKUP($D23,BS연결,MATCH(K$1,BS연결H,0),0)/100,"") | L23: =IFERROR(VLOOKUP($D23,BS연결,MATCH(L$1,BS연결H,0),0)/100,"") | ... AB23: =IFERROR(VLOOKUP($D23,BS연결,MATCH(AB$1,BS연결H,0),0)/100,"") | AC23: =IFERROR(AB23+AC18-변수!AC29,"") | AD23: =IFERROR(AC23+AD18-변수!AD29,"") | AE23: =AD23 | AF23: =IFERROR(AD23+AF18-변수!AF29,"") | AG23: =IFERROR(AF23+AG18-변수!AG29,"") | AH23: =IFERROR(AG23+AH18-변수!AH29,"") | AI23: =IFERROR(AH23+AI18-변수!AI29,"") | AJ23: =AI23 | AK23: =IFERROR(AI23+AK18-변수!AK29,"") | AL23: =IFERROR(AK23+AL18-변수!AL29,"") | AM23: =IFERROR(AL23+AM18-변수!AM29,"") | AN23: =IFERROR(AM23+AN18-변수!AN29,"") | AO23: =AN23
A24: 총차입금 | B24: 재무상태 | C24: 억원 | D24: 총차입금 | E24: =IFERROR(VLOOKUP($D24,BS연결,MATCH(E$1,BS연결H,0),0)/100,"") | F24: =IFERROR(VLOOKUP($D24,BS연결,MATCH(F$1,BS연결H,0),0)/100,"") | G24: =IFERROR(VLOOKUP($D24,BS연결,MATCH(G$1,BS연결H,0),0)/100,"") | H24: =IFERROR(VLOOKUP($D24,BS연결,MATCH(H$1,BS연결H,0),0)/100,"") | I24: =IFERROR(VLOOKUP($D24,BS연결,MATCH(I$1,BS연결H,0),0)/100,"") | J24: =IFERROR(VLOOKUP($D24,BS연결,MATCH(J$1,BS연결H,0),0)/100,"") | K24: =IFERROR(VLOOKUP($D24,BS연결,MATCH(K$1,BS연결H,0),0)/100,"") | L24: =IFERROR(VLOOKUP($D24,BS연결,MATCH(L$1,BS연결H,0),0)/100,"") | ... AB24: =IFERROR(VLOOKUP($D24,BS연결,MATCH(AB$1,BS연결H,0),0)/100,"") | AC24: =IFERROR(AB24*(1+변수!AC30),"") | AD24: =IFERROR(AC24*(1+변수!AD30),"") | AE24: =AD24 | AF24: =IFERROR(AD24*(1+변수!AF30),"") | AG24: =IFERROR(AF24*(1+변수!AG30),"") | AH24: =IFERROR(AG24*(1+변수!AH30),"") | AI24: =IFERROR(AH24*(1+변수!AI30),"") | AJ24: =AI24 | AK24: =IFERROR(AI24*(1+변수!AK30),"") | AL24: =IFERROR(AK24*(1+변수!AL30),"") | AM24: =IFERROR(AL24*(1+변수!AM30),"") | AN24: =IFERROR(AM24*(1+변수!AN30),"") | AO24: =AN24
A25: 순차입금 | B25: 재무상태 | C25: 억원 | D25: 순차입금 | E25: =IFERROR(VLOOKUP($D25,BS연결,MATCH(E$1,BS연결H,0),0)/100,"") | F25: =IFERROR(VLOOKUP($D25,BS연결,MATCH(F$1,BS연결H,0),0)/100,"") | G25: =IFERROR(VLOOKUP($D25,BS연결,MATCH(G$1,BS연결H,0),0)/100,"") | H25: =IFERROR(VLOOKUP($D25,BS연결,MATCH(H$1,BS연결H,0),0)/100,"") | I25: =IFERROR(VLOOKUP($D25,BS연결,MATCH(I$1,BS연결H,0),0)/100,"") | J25: =IFERROR(VLOOKUP($D25,BS연결,MATCH(J$1,BS연결H,0),0)/100,"") | K25: =IFERROR(VLOOKUP($D25,BS연결,MATCH(K$1,BS연결H,0),0)/100,"") | L25: =IFERROR(VLOOKUP($D25,BS연결,MATCH(L$1,BS연결H,0),0)/100,"") | ... AB25: =IFERROR(VLOOKUP($D25,BS연결,MATCH(AB$1,BS연결H,0),0)/100,"") | AC25: =IFERROR(AB25*(1+변수!AC31),"") | AD25: =IFERROR(AC25*(1+변수!AD31),"") | AE25: =AD25 | AF25: =IFERROR(AD25*(1+변수!AF31),"") | AG25: =IFERROR(AF25*(1+변수!AG31),"") | AH25: =IFERROR(AG25*(1+변수!AH31),"") | AI25: =IFERROR(AH25*(1+변수!AI31),"") | AJ25: =AI25 | AK25: =IFERROR(AI25*(1+변수!AK31),"") | AL25: =IFERROR(AK25*(1+변수!AL31),"") | AM25: =IFERROR(AL25*(1+변수!AM31),"") | AN25: =IFERROR(AM25*(1+변수!AN31),"") | AO25: =AN25
A26: 이자발생자산 | B26: 재무상태 | C26: 억원 | D26: 이자발생자산 | E26: =IFERROR(VLOOKUP($D26,BS연결,MATCH(E$1,BS연결H,0),0)/100,"") | F26: =IFERROR(VLOOKUP($D26,BS연결,MATCH(F$1,BS연결H,0),0)/100,"") | G26: =IFERROR(VLOOKUP($D26,BS연결,MATCH(G$1,BS연결H,0),0)/100,"") | H26: =IFERROR(VLOOKUP($D26,BS연결,MATCH(H$1,BS연결H,0),0)/100,"") | I26: =IFERROR(VLOOKUP($D26,BS연결,MATCH(I$1,BS연결H,0),0)/100,"") | J26: =IFERROR(VLOOKUP($D26,BS연결,MATCH(J$1,BS연결H,0),0)/100,"") | K26: =IFERROR(VLOOKUP($D26,BS연결,MATCH(K$1,BS연결H,0),0)/100,"") | L26: =IFERROR(VLOOKUP($D26,BS연결,MATCH(L$1,BS연결H,0),0)/100,"") | ... AB26: =IFERROR(VLOOKUP($D26,BS연결,MATCH(AB$1,BS연결H,0),0)/100,"") | AC26: =IFERROR(AB26*(1+변수!AC32),"") | AD26: =IFERROR(AC26*(1+변수!AD32),"") | AE26: =AD26 | AF26: =IFERROR(AD26*(1+변수!AF32),"") | AG26: =IFERROR(AF26*(1+변수!AG32),"") | AH26: =IFERROR(AG26*(1+변수!AH32),"") | AI26: =IFERROR(AH26*(1+변수!AI32),"") | AJ26: =AI26 | AK26: =IFERROR(AI26*(1+변수!AK32),"") | AL26: =IFERROR(AK26*(1+변수!AL32),"") | AM26: =IFERROR(AL26*(1+변수!AM32),"") | AN26: =IFERROR(AM26*(1+변수!AN32),"") | AO26: =AN26
A27: 현금및현금성자산 | B27: 재무상태 | C27: 억원 | D27: 현금및현금성자산 | E27: =IFERROR(VLOOKUP($D27,BS연결,MATCH(E$1,BS연결H,0),0)/100,"") | F27: =IFERROR(VLOOKUP($D27,BS연결,MATCH(F$1,BS연결H,0),0)/100,"") | G27: =IFERROR(VLOOKUP($D27,BS연결,MATCH(G$1,BS연결H,0),0)/100,"") | H27: =IFERROR(VLOOKUP($D27,BS연결,MATCH(H$1,BS연결H,0),0)/100,"") | I27: =IFERROR(VLOOKUP($D27,BS연결,MATCH(I$1,BS연결H,0),0)/100,"") | J27: =IFERROR(VLOOKUP($D27,BS연결,MATCH(J$1,BS연결H,0),0)/100,"") | K27: =IFERROR(VLOOKUP($D27,BS연결,MATCH(K$1,BS연결H,0),0)/100,"") | L27: =IFERROR(VLOOKUP($D27,BS연결,MATCH(L$1,BS연결H,0),0)/100,"") | ... AB27: =IFERROR(VLOOKUP($D27,BS연결,MATCH(AB$1,BS연결H,0),0)/100,"") | AE27: =AD27 | AJ27: =AI27 | AO27: =AN27
A28: CAPEX | B28: 현금흐름 | C28: 억원 | D28: CAPEX | E28: =IFERROR(VLOOKUP($D28,BS연결,MATCH(E$1,BS연결H,0),0)/100,"") | G28: =IFERROR(VLOOKUP($D28,BS연결,MATCH(G$1,BS연결H,0),0)/100,"") | H28: =IFERROR(VLOOKUP($D28,BS연결,MATCH(H$1,BS연결H,0),0)/100,"") | I28: =IFERROR(VLOOKUP($D28,BS연결,MATCH(I$1,BS연결H,0),0)/100,"") | J28: =IFERROR(VLOOKUP($D28,BS연결,MATCH(J$1,BS연결H,0),0)/100,"") | K28: =IFERROR(VLOOKUP($D28,BS연결,MATCH(K$1,BS연결H,0),0)/100,"") | L28: =IFERROR(VLOOKUP($D28,BS연결,MATCH(L$1,BS연결H,0),0)/100,"") | M28: =IFERROR(VLOOKUP($D28,BS연결,MATCH(M$1,BS연결H,0),0)/100,"") | N28: =IFERROR(VLOOKUP($D28,BS연결,MATCH(N$1,BS연결H,0),0)/100,"") | ... AB28: =IFERROR(VLOOKUP($D28,BS연결,MATCH(AB$1,BS연결H,0),0)/100,"") | AC28: =IFERROR(X28*(1+변수!AC34),"") | AD28: =IFERROR(Y28*(1+변수!AD34),"") | AE28: =SUM(AA28:AD28) | AF28: =IFERROR(AA28*(1+변수!AF34),"") | AG28: =IFERROR(AB28*(1+변수!AG34),"") | AH28: =IFERROR(AC28*(1+변수!AH34),"") | AI28: =IFERROR(AD28*(1+변수!AI34),"") | AJ28: =SUM(AF28:AI28) | AK28: =IFERROR(AF28*(1+변수!AK34),"") | AL28: =IFERROR(AG28*(1+변수!AL34),"") | AM28: =IFERROR(AH28*(1+변수!AM34),"") | AN28: =IFERROR(AI28*(1+변수!AN34),"") | AO28: =SUM(AK28:AN28)
A29: 영업활동현금흐름 | B29: 현금흐름 | C29: 억원 | D29: 영업활동으로인한현금흐름 | E29: =IFERROR(VLOOKUP($D29,BS연결,MATCH(E$1,BS연결H,0),0)/100,"") | G29: =IFERROR(VLOOKUP($D29,BS연결,MATCH(G$1,BS연결H,0),0)/100,"") | H29: =IFERROR(VLOOKUP($D29,BS연결,MATCH(H$1,BS연결H,0),0)/100,"") | I29: =IFERROR(VLOOKUP($D29,BS연결,MATCH(I$1,BS연결H,0),0)/100,"") | J29: =IFERROR(VLOOKUP($D29,BS연결,MATCH(J$1,BS연결H,0),0)/100,"") | K29: =IFERROR(VLOOKUP($D29,BS연결,MATCH(K$1,BS연결H,0),0)/100,"") | L29: =IFERROR(VLOOKUP($D29,BS연결,MATCH(L$1,BS연결H,0),0)/100,"") | M29: =IFERROR(VLOOKUP($D29,BS연결,MATCH(M$1,BS연결H,0),0)/100,"") | N29: =IFERROR(VLOOKUP($D29,BS연결,MATCH(N$1,BS연결H,0),0)/100,"") | ... AB29: =IFERROR(VLOOKUP($D29,BS연결,MATCH(AB$1,BS연결H,0),0)/100,"") | AE29: =SUM(AA29:AD29) | AJ29: =SUM(AF29:AI29) | AO29: =SUM(AK29:AN29)
A30: 주식수 | B30: 주당 | C30: 백만주 | D30: 유통주식수 | E30: 83.268 | F30: =E30 | G30: 83.268 | H30: 83.268 | I30: 83.268 | J30: 83.268 | K30: =J30 | L30: 83.268 | M30: 83.268 | N30: 83.268 | O30: 83.268 | P30: =O30 | Q30: 83.268 | R30: 83.268 | S30: 83.268 | T30: 83.268 | U30: =T30 | V30: 83.268 | W30: 83.268 | X30: 83.268 | Y30: 90.289 | Z30: =Y30 | AA30: 90.289 | AB30: 90.289 | AC30: =IFERROR(AB30*(1+변수!AC36),"") | AD30: =IFERROR(AC30*(1+변수!AD36),"") | AE30: =AD30 | AF30: =IFERROR(AD30*(1+변수!AF36),"") | AG30: =IFERROR(AF30*(1+변수!AG36),"") | AH30: =IFERROR(AG30*(1+변수!AH36),"") | AI30: =IFERROR(AH30*(1+변수!AI36),"") | AJ30: =AI30 | AK30: =IFERROR(AI30*(1+변수!AK36),"") | AL30: =IFERROR(AK30*(1+변수!AL36),"") | AM30: =IFERROR(AL30*(1+변수!AM36),"") | AN30: =IFERROR(AM30*(1+변수!AN36),"") | AO30: =AN30
A31: EPS | B31: 주당 | C31: 원 | D31: EPS | E31: =IFERROR(E18*100/E30,"") | G31: =IFERROR(G18*100/G30,"") | H31: =IFERROR(H18*100/H30,"") | I31: =IFERROR(I18*100/I30,"") | J31: =IFERROR(J18*100/J30,"") | K31: =SUM(G31:J31) | L31: =IFERROR(L18*100/L30,"") | M31: =IFERROR(M18*100/M30,"") | N31: =IFERROR(N18*100/N30,"") | O31: =IFERROR(O18*100/O30,"") | P31: =SUM(L31:O31) | Q31: =IFERROR(Q18*100/Q30,"") | R31: =IFERROR(R18*100/R30,"") | S31: =IFERROR(S18*100/S30,"") | T31: =IFERROR(T18*100/T30,"") | U31: =SUM(Q31:T31) | V31: =IFERROR(V18*100/V30,"") | W31: =IFERROR(W18*100/W30,"") | X31: =IFERROR(X18*100/X30,"") | Y31: =IFERROR(Y18*100/Y30,"") | Z31: =SUM(V31:Y31) | AA31: =IFERROR(AA18*100/AA30,"") | AB31: =IFERROR(AB18*100/AB30,"") | AC31: =IFERROR(AC18*100/AC30,"") | AD31: =IFERROR(AD18*100/AD30,"") | AE31: =SUM(AA31:AD31) | AF31: =IFERROR(AF18*100/AF30,"") | AG31: =IFERROR(AG18*100/AG30,"") | AH31: =IFERROR(AH18*100/AH30,"") | AI31: =IFERROR(AI18*100/AI30,"") | AJ31: =SUM(AF31:AI31) | AK31: =IFERROR(AK18*100/AK30,"") | AL31: =IFERROR(AL18*100/AL30,"") | AM31: =IFERROR(AM18*100/AM30,"") | AN31: =IFERROR(AN18*100/AN30,"") | AO31: =SUM(AK31:AN31)
A32: BPS | B32: 주당 | C32: 원 | D32: BPS | E32: =IFERROR(E23*100/E30,"") | F32: =E32 | G32: =IFERROR(G23*100/G30,"") | H32: =IFERROR(H23*100/H30,"") | I32: =IFERROR(I23*100/I30,"") | J32: =IFERROR(J23*100/J30,"") | K32: =J32 | L32: =IFERROR(L23*100/L30,"") | M32: =IFERROR(M23*100/M30,"") | N32: =IFERROR(N23*100/N30,"") | O32: =IFERROR(O23*100/O30,"") | P32: =O32 | Q32: =IFERROR(Q23*100/Q30,"") | R32: =IFERROR(R23*100/R30,"") | S32: =IFERROR(S23*100/S30,"") | T32: =IFERROR(T23*100/T30,"") | U32: =T32 | V32: =IFERROR(V23*100/V30,"") | W32: =IFERROR(W23*100/W30,"") | X32: =IFERROR(X23*100/X30,"") | Y32: =IFERROR(Y23*100/Y30,"") | Z32: =Y32 | AA32: =IFERROR(AA23*100/AA30,"") | AB32: =IFERROR(AB23*100/AB30,"") | AC32: =IFERROR(AC23*100/AC30,"") | AD32: =IFERROR(AD23*100/AD30,"") | AE32: =AD32 | AF32: =IFERROR(AF23*100/AF30,"") | AG32: =IFERROR(AG23*100/AG30,"") | AH32: =IFERROR(AH23*100/AH30,"") | AI32: =IFERROR(AI23*100/AI30,"") | AJ32: =AI32 | AK32: =IFERROR(AK23*100/AK30,"") | AL32: =IFERROR(AL23*100/AL30,"") | AM32: =IFERROR(AM23*100/AM30,"") | AN32: =IFERROR(AN23*100/AN30,"") | AO32: =AN32
A33: DPS | B33: 주당 | C33: 원 | D33: DPS(보통주) | E33: 0 | F33: 0 | J33: 0 | K33: =SUM(G33:J33) | O33: 0 | P33: =SUM(L33:O33) | T33: 0 | U33: =SUM(Q33:T33) | Y33: 0 | Z33: =SUM(V33:Y33) | AD33: =변수!AD37 | AE33: =SUM(AA33:AD33) | AI33: =변수!AI37 | AJ33: =SUM(AF33:AI33) | AN33: =변수!AN37 | AO33: =SUM(AK33:AN33)
A34: PER | B34: 주당 | C34: 배 | D34: PER | F34: =E34 | K34: =J34 | P34: =O34 | S34: =IFERROR(변수!S18/(O31+Q31+R31+S31),"") | T34: =IFERROR(변수!T18/(Q31+R31+S31+T31),"") | U34: =T34 | W34: =IFERROR(변수!W18/(S31+T31+V31+W31),"") | Y34: =IFERROR(변수!Y18/(V31+W31+X31+Y31),"") | Z34: =Y34 | AA34: =IFERROR(변수!AA18/(W31+X31+Y31+AA31),"") | AB34: =IFERROR(변수!AB18/(X31+Y31+AA31+AB31),"") | AC34: =IFERROR(변수!$D$45/(Y31+AA31+AB31+AC31),"") | AD34: =IFERROR(변수!$D$45/(AA31+AB31+AC31+AD31),"") | AE34: =AD34 | AF34: =IFERROR(변수!$D$45/(AB31+AC31+AD31+AF31),"") | AG34: =IFERROR(변수!$D$45/(AC31+AD31+AF31+AG31),"") | AH34: =IFERROR(변수!$D$45/(AD31+AF31+AG31+AH31),"") | AI34: =IFERROR(변수!$D$45/(AF31+AG31+AH31+AI31),"") | AJ34: =AI34 | AK34: =IFERROR(변수!$D$45/(AG31+AH31+AI31+AK31),"") | AL34: =IFERROR(변수!$D$45/(AH31+AI31+AK31+AL31),"") | AM34: =IFERROR(변수!$D$45/(AI31+AK31+AL31+AM31),"") | AN34: =IFERROR(변수!$D$45/(AK31+AL31+AM31+AN31),"") | AO34: =AN34
A35: PBR | B35: 주당 | C35: 배 | D35: PBR | E35: =IFERROR(변수!E18/E32,"") | F35: =E35 | G35: =IFERROR(변수!G18/G32,"") | H35: =IFERROR(변수!H18/H32,"") | I35: =IFERROR(변수!I18/I32,"") | J35: =IFERROR(변수!J18/J32,"") | K35: =J35 | L35: =IFERROR(변수!L18/L32,"") | M35: =IFERROR(변수!M18/M32,"") | N35: =IFERROR(변수!N18/N32,"") | O35: =IFERROR(변수!O18/O32,"") | P35: =O35 | Q35: =IFERROR(변수!Q18/Q32,"") | R35: =IFERROR(변수!R18/R32,"") | S35: =IFERROR(변수!S18/S32,"") | T35: =IFERROR(변수!T18/T32,"") | U35: =T35 | V35: =IFERROR(변수!V18/V32,"") | W35: =IFERROR(변수!W18/W32,"") | X35: =IFERROR(변수!X18/X32,"") | Y35: =IFERROR(변수!Y18/Y32,"") | Z35: =Y35 | AA35: =IFERROR(변수!AA18/AA32,"") | AB35: =IFERROR(변수!AB18/AB32,"") | AC35: =IFERROR(변수!$D$45/AC32,"") | AD35: =IFERROR(변수!$D$45/AD32,"") | AE35: =AD35 | AF35: =IFERROR(변수!$D$45/AF32,"") | AG35: =IFERROR(변수!$D$45/AG32,"") | AH35: =IFERROR(변수!$D$45/AH32,"") | AI35: =IFERROR(변수!$D$45/AI32,"") | AJ35: =AI35 | AK35: =IFERROR(변수!$D$45/AK32,"") | AL35: =IFERROR(변수!$D$45/AL32,"") | AM35: =IFERROR(변수!$D$45/AM32,"") | AN35: =IFERROR(변수!$D$45/AN32,"") | AO35: =AN35
A36: 매출조선 | B36: 사업부 | C36: 억원 | D36: 매출 조선·해양(방산·신조선·상선·특수선) | H36: 902 | I36: 2402 | K36: =SUM(G36:J36) | M36: 6762 | N36: 1683 | O36: 2951 | P36: =SUM(L36:O36) | R36: 2034 | S36: 1884 | U36: =SUM(Q36:T36) | W36: 2280 | X36: 2026 | Z36: =SUM(V36:Y36) | AB36: 3951 | AC36: =IFERROR(SLS!AL122/100+변수!AC38+AC37,"") | AD36: =IFERROR(SLS!AM122/100+변수!AD38+AD37,"") | AE36: =SUM(AA36:AD36) | AF36: =IFERROR(SLS!AN122/100+변수!AF38+AF37,"") | AG36: =IFERROR(SLS!AO122/100+변수!AG38+AG37,"") | AH36: =IFERROR(SLS!AP122/100+변수!AH38+AH37,"") | AI36: =IFERROR(SLS!AQ122/100+변수!AI38+AI37,"") | AJ36: =SUM(AF36:AI36) | AK36: =IFERROR(SLS!AR122/100+변수!AK38+AK37,"") | AL36: =IFERROR(SLS!AS122/100+변수!AL38+AL37,"") | AM36: =IFERROR(SLS!AT122/100+변수!AM38+AM37,"") | AN36: =IFERROR(SLS!AU122/100+변수!AN38+AN37,"") | AO36: =SUM(AK36:AN36)
A37: 매출조선신규 | B37: 사업부 | C37: 억원 | D37: 매출 조선·해양(방산·신조선·상선·특수선) 신규수주(원장 체결 속도(폴백) — 매출조선에 포함) | K37: =SUM(G37:J37) | P37: =SUM(L37:O37) | U37: =SUM(Q37:T37) | Z37: =SUM(V37:Y37) | AA37: 0 | AB37: 0 | AC37: =변수!AC39 | AD37: =변수!AD39 | AE37: =SUM(AA37:AD37) | AF37: =변수!AF39 | AG37: =변수!AG39 | AH37: =변수!AH39 | AI37: =변수!AI39 | AJ37: =SUM(AF37:AI37) | AK37: =변수!AK39 | AL37: =변수!AL39 | AM37: =변수!AM39 | AN37: =변수!AN39 | AO37: =SUM(AK37:AN37)
A38: OP조선 | B38: 사업부 | C38: 억원 | D38: OP 조선·해양(방산·신조선·상선·특수선) | K38: =SUM(G38:J38) | P38: =SUM(L38:O38) | U38: =SUM(Q38:T38) | Z38: =SUM(V38:Y38) | AC38: =IFERROR(AC36*변수!AC40,"") | AD38: =IFERROR(AD36*변수!AD40,"") | AE38: =SUM(AA38:AD38) | AF38: =IFERROR(AF36*변수!AF40,"") | AG38: =IFERROR(AG36*변수!AG40,"") | AH38: =IFERROR(AH36*변수!AH40,"") | AI38: =IFERROR(AI36*변수!AI40,"") | AJ38: =SUM(AF38:AI38) | AK38: =IFERROR(AK36*변수!AK40,"") | AL38: =IFERROR(AL36*변수!AL40,"") | AM38: =IFERROR(AM36*변수!AM40,"") | AN38: =IFERROR(AN36*변수!AN40,"") | AO38: =SUM(AK38:AN38)
A39: OP조선신규 | B39: 사업부 | C39: 억원 | D39: OP 조선·해양(방산·신조선·상선·특수선) 신규수주(매출조선신규 × OPM — OP조선에 포함) | K39: =SUM(G39:J39) | P39: =SUM(L39:O39) | U39: =SUM(Q39:T39) | Z39: =SUM(V39:Y39) | AA39: 0 | AB39: 0 | AC39: =IFERROR(AC37*변수!AC40,"") | AD39: =IFERROR(AD37*변수!AD40,"") | AE39: =SUM(AA39:AD39) | AF39: =IFERROR(AF37*변수!AF40,"") | AG39: =IFERROR(AG37*변수!AG40,"") | AH39: =IFERROR(AH37*변수!AH40,"") | AI39: =IFERROR(AI37*변수!AI40,"") | AJ39: =SUM(AF39:AI39) | AK39: =IFERROR(AK37*변수!AK40,"") | AL39: =IFERROR(AL37*변수!AL40,"") | AM39: =IFERROR(AM37*변수!AM40,"") | AN39: =IFERROR(AN37*변수!AN40,"") | AO39: =SUM(AK39:AN39)
A40: 매출기타 | B40: 사업부 | C40: 억원 | D40: 매출 기타 부문(총매출 − 조선) | H40: 3552.57 | I40: 1576.49 | K40: =SUM(G40:J40) | M40: 0 | N40: 3222.17 | O40: 4700.57 | P40: =SUM(L40:O40) | R40: 2814 | S40: 2653.68 | U40: =SUM(Q40:T40) | W40: 2797.77 | X40: 2496.08 | Z40: =SUM(V40:Y40) | AB40: 3348.08 | AC40: =IFERROR(X40*(1+변수!AC41),"") | AD40: =IFERROR(AC40*(1+변수!AD41),"") | AE40: =SUM(AA40:AD40) | AF40: =IFERROR(AD40*(1+변수!AF41),"") | AG40: =IFERROR(AB40*(1+변수!AG41),"") | AH40: =IFERROR(AC40*(1+변수!AH41),"") | AI40: =IFERROR(AD40*(1+변수!AI41),"") | AJ40: =SUM(AF40:AI40) | AK40: =IFERROR(AF40*(1+변수!AK41),"") | AL40: =IFERROR(AG40*(1+변수!AL41),"") | AM40: =IFERROR(AH40*(1+변수!AM41),"") | AN40: =IFERROR(AI40*(1+변수!AN41),"") | AO40: =SUM(AK40:AN40)
A41: OP기타 | B41: 사업부 | C41: 억원 | D41: OP 기타 부문(총매출 − 조선) | K41: =SUM(G41:J41) | P41: =SUM(L41:O41) | U41: =SUM(Q41:T41) | Z41: =SUM(V41:Y41) | AC41: =IFERROR(AC40*변수!AC42,"") | AD41: =IFERROR(AD40*변수!AD42,"") | AE41: =SUM(AA41:AD41) | AF41: =IFERROR(AF40*변수!AF42,"") | AG41: =IFERROR(AG40*변수!AG42,"") | AH41: =IFERROR(AH40*변수!AH42,"") | AI41: =IFERROR(AI40*변수!AI42,"") | AJ41: =SUM(AF41:AI41) | AK41: =IFERROR(AK40*변수!AK42,"") | AL41: =IFERROR(AL40*변수!AL42,"") | AM41: =IFERROR(AM40*변수!AM42,"") | AN41: =IFERROR(AN40*변수!AN42,"") | AO41: =SUM(AK41:AN41)
B42: 비율(참고)
A43: NPM | C43: % | D43: 지배주주순이익 / 매출액 | E43: =IFERROR(E18/E5,"") | F43: =IFERROR(F18/F5,"") | G43: =IFERROR(G18/G5,"") | H43: =IFERROR(H18/H5,"") | I43: =IFERROR(I18/I5,"") | J43: =IFERROR(J18/J5,"") | K43: =IFERROR(K18/K5,"") | L43: =IFERROR(L18/L5,"") | ... AO43: =IFERROR(AO18/AO5,"")
A44: 매출원가율 | C44: % | D44: 매출원가 / 매출액 | E44: =IFERROR(E6/E5,"") | F44: =IFERROR(F6/F5,"") | G44: =IFERROR(G6/G5,"") | H44: =IFERROR(H6/H5,"") | I44: =IFERROR(I6/I5,"") | J44: =IFERROR(J6/J5,"") | K44: =IFERROR(K6/K5,"") | L44: =IFERROR(L6/L5,"") | ... AO44: =IFERROR(AO6/AO5,"")
A45: 판관비율 | C45: % | D45: 판관비 / 매출액 | E45: =IFERROR(E8/E5,"") | F45: =IFERROR(F8/F5,"") | G45: =IFERROR(G8/G5,"") | H45: =IFERROR(H8/H5,"") | I45: =IFERROR(I8/I5,"") | J45: =IFERROR(J8/J5,"") | K45: =IFERROR(K8/K5,"") | L45: =IFERROR(L8/L5,"") | ... AO45: =IFERROR(AO8/AO5,"")

Sheet SLS
C1: 이름: SLS_H · 선표 매출인식(백만$) — sls json origin 2026Q2 | E1: 2Q18 | F1: 3Q18 | G1: 4Q18 | H1: 1Q19 | I1: 2Q19 | J1: 3Q19 | K1: 4Q19 | L1: 1Q20 | M1: 2Q20 | N1: 3Q20 | O1: 4Q20 | P1: 1Q21 | Q1: 2Q21 | R1: 3Q21 | S1: 4Q21 | T1: 1Q22 | U1: 2Q22 | V1: 3Q22 | W1: 4Q22 | X1: 1Q23 | Y1: 2Q23 | Z1: 3Q23 | AA1: 4Q23 | AB1: 1Q24 | AC1: 2Q24 | AD1: 3Q24 | AE1: 4Q24 | AF1: 1Q25 | AG1: 2Q25 | AH1: 3Q25 | AI1: 4Q25 | AJ1: 1Q26 | AK1: 2Q26 | AL1: 3Q26 | AM1: 4Q26 | AN1: 1Q27 | AO1: 2Q27 | AP1: 3Q27 | AQ1: 4Q27 | AR1: 1Q28 | AS1: 2Q28 | AT1: 3Q28 | AU1: 4Q28 | AV1: 1Q29 | AW1: 2Q29 | AX1: 3Q29 | AY1: 4Q29 | AZ1: 1Q30 | BA1: 2Q30 | BB1: 3Q30 | BC1: 4Q30 | BD1: 1Q31 | BE1: 2Q31 | BF1: 3Q31 | BG1: 4Q31 | BH1: 1Q32 | BI1: 2Q32 | BJ1: 3Q32 | BK1: 4Q32 | BL1: 1Q33 | BM1: 2Q33 | BN1: 3Q33 | BO1: 4Q33 | BP1: 1Q34 | BQ1: 2Q34 | BR1: 3Q34 | BS1: 4Q34 | BT1: 1Q35 | BU1: 2Q35 | BV1: 3Q35 | BW1: 4Q35 | BX1: 1Q36 | BY1: 2Q36 | BZ1: 3Q36 | CA1: 4Q36 | CB1: 1Q37 | CC1: 2Q37 | CD1: 3Q37 | CE1: 4Q37 | CF1: 1Q38 | CG1: 2Q38 | CH1: 3Q38 | CI1: 4Q38 | CJ1: 1Q39 | CK1: 2Q39 | CL1: 3Q39 | CM1: 4Q39 | CN1: 1Q40 | CO1: 2Q40 | CP1: 3Q40 | CQ1: 4Q40 | CR1: 1Q41 | CS1: 2Q41 | CT1: 3Q41 | CU1: 4Q41 | CV1: 1Q42 | CW1: 2Q42 | CX1: 3Q42 | CY1: 4Q42 | CZ1: 1Q43 | DA1: 2Q43 | DB1: 3Q43 | DC1: 4Q43 | DD1: 1Q44 | DE1: 2Q44 | DF1: 3Q44 | DG1: 4Q44 | DH1: 1Q45 | DI1: 2Q45 | DJ1: 3Q45 | DK1: 4Q45 | DL1: 1Q46 | DM1: 2Q46 | DN1: 3Q46 | DO1: 4Q46 | DP1: 1Q47 | DQ1: 2Q47 | DR1: 3Q47 | DS1: 4Q47 | DT1: 1Q48 | DU1: 2Q48 | DV1: 3Q48 | DW1: 4Q48 | DX1: 1Q49 | DY1: 2Q49 | DZ1: 2018 | EA1: 2019 | EB1: 2020 | EC1: 2021 | ED1: 2022 | EE1: 2023 | EF1: 2024 | EG1: 2025 | EH1: 2026 | EI1: 2027 | EJ1: 2028 | EK1: 2029 | EL1: 2030 | EM1: 2031 | EN1: 2032 | EO1: 2033 | EP1: 2034 | EQ1: 2035 | ER1: 2036 | ES1: 2037 | ET1: 2038 | EU1: 2039 | EV1: 2040 | EW1: 2041 | EX1: 2042 | EY1: 2043 | EZ1: 2044 | FA1: 2045 | FB1: 2046 | FC1: 2047 | FD1: 2048 | FE1: 2049
A2: 코호트 표(레퍼런스 실측 캘리브레이션): ①적자 −1.1% ②BEP 1% ③중마진 4.3% ④호황 5.4% ⑤초호황 10.8% — 회사별 캘리브레이션은 target_opm.basis 참조 · 코호트 모드 reference_anchor(대안 ledger_relative) · 잔고 캡 미적용
E3: 1 | F3: 2 | G3: 3 | H3: 4 | I3: 5 | J3: 6 | K3: 7 | L3: 8 | M3: 9 | N3: 10 | O3: 11 | P3: 12 | Q3: 13 | R3: 14 | S3: 15 | T3: 16 | U3: 17 | V3: 18 | W3: 19 | X3: 20 | Y3: 21 | Z3: 22 | AA3: 23 | AB3: 24 | AC3: 25 | AD3: 26 | AE3: 27 | AF3: 28 | AG3: 29 | AH3: 30 | AI3: 31 | AJ3: 32 | AK3: 33 | AL3: 34 | AM3: 35 | AN3: 36 | AO3: 37 | AP3: 38 | AQ3: 39 | AR3: 40 | AS3: 41 | AT3: 42 | AU3: 43 | AV3: 44 | AW3: 45 | AX3: 46 | AY3: 47 | AZ3: 48 | BA3: 49 | BB3: 50 | BC3: 51 | BD3: 52 | BE3: 53 | BF3: 54 | BG3: 55 | BH3: 56 | BI3: 57 | BJ3: 58 | BK3: 59 | BL3: 60 | BM3: 61 | BN3: 62 | BO3: 63 | BP3: 64 | BQ3: 65 | BR3: 66 | BS3: 67 | BT3: 68 | BU3: 69 | BV3: 70 | BW3: 71 | BX3: 72 | BY3: 73 | BZ3: 74 | CA3: 75 | CB3: 76 | CC3: 77 | CD3: 78 | CE3: 79 | CF3: 80 | CG3: 81 | CH3: 82 | CI3: 83 | CJ3: 84 | CK3: 85 | CL3: 86 | CM3: 87 | CN3: 88 | CO3: 89 | CP3: 90 | CQ3: 91 | CR3: 92 | CS3: 93 | CT3: 94 | CU3: 95 | CV3: 96 | CW3: 97 | CX3: 98 | CY3: 99 | CZ3: 100 | DA3: 101 | DB3: 102 | DC3: 103 | DD3: 104 | DE3: 105 | DF3: 106 | DG3: 107 | DH3: 108 | DI3: 109 | DJ3: 110 | DK3: 111 | DL3: 112 | DM3: 113 | DN3: 114 | DO3: 115 | DP3: 116 | DQ3: 117 | DR3: 118 | DS3: 119 | DT3: 120 | DU3: 121 | DV3: 122 | DW3: 123 | DX3: 124 | DY3: 125 | DZ3: 126 | EA3: 127 | EB3: 128 | EC3: 129 | ED3: 130 | EE3: 131 | EF3: 132 | EG3: 133 | EH3: 134 | EI3: 135 | EJ3: 136 | EK3: 137 | EL3: 138 | EM3: 139 | EN3: 140 | EO3: 141 | EP3: 142 | EQ3: 143 | ER3: 144 | ES3: 145 | ET3: 146 | EU3: 147 | EV3: 148 | EW3: 149 | EX3: 150 | EY3: 151 | EZ3: 152 | FA3: 153 | FB3: 154 | FC3: 155 | FD3: 156 | FE3: 157
E4: 2018.06 | F4: 2018.09 | G4: 2018.12 | H4: 2019.03 | I4: 2019.06 | J4: 2019.09 | K4: 2019.12 | L4: 2020.03 | M4: 2020.06 | N4: 2020.09 | O4: 2020.12 | P4: 2021.03 | Q4: 2021.06 | R4: 2021.09 | S4: 2021.12 | T4: 2022.03 | U4: 2022.06 | V4: 2022.09 | W4: 2022.12 | X4: 2023.03 | Y4: 2023.06 | Z4: 2023.09 | AA4: 2023.12 | AB4: 2024.03 | AC4: 2024.06 | AD4: 2024.09 | AE4: 2024.12 | AF4: 2025.03 | AG4: 2025.06 | AH4: 2025.09 | AI4: 2025.12 | AJ4: 2026.03 | AK4: 2026.06 | AL4: 2026.09 | AM4: 2026.12 | AN4: 2027.03 | AO4: 2027.06 | AP4: 2027.09 | AQ4: 2027.12 | AR4: 2028.03 | AS4: 2028.06 | AT4: 2028.09 | AU4: 2028.12 | AV4: 2029.03 | AW4: 2029.06 | AX4: 2029.09 | AY4: 2029.12 | AZ4: 2030.03 | BA4: 2030.06 | BB4: 2030.09 | BC4: 2030.12 | BD4: 2031.03 | BE4: 2031.06 | BF4: 2031.09 | BG4: 2031.12 | BH4: 2032.03 | BI4: 2032.06 | BJ4: 2032.09 | BK4: 2032.12 | BL4: 2033.03 | BM4: 2033.06 | BN4: 2033.09 | BO4: 2033.12 | BP4: 2034.03 | BQ4: 2034.06 | BR4: 2034.09 | BS4: 2034.12 | BT4: 2035.03 | BU4: 2035.06 | BV4: 2035.09 | BW4: 2035.12 | BX4: 2036.03 | BY4: 2036.06 | BZ4: 2036.09 | CA4: 2036.12 | CB4: 2037.03 | CC4: 2037.06 | CD4: 2037.09 | CE4: 2037.12 | CF4: 2038.03 | CG4: 2038.06 | CH4: 2038.09 | CI4: 2038.12 | CJ4: 2039.03 | CK4: 2039.06 | CL4: 2039.09 | CM4: 2039.12 | CN4: 2040.03 | CO4: 2040.06 | CP4: 2040.09 | CQ4: 2040.12 | CR4: 2041.03 | CS4: 2041.06 | CT4: 2041.09 | CU4: 2041.12 | CV4: 2042.03 | CW4: 2042.06 | CX4: 2042.09 | CY4: 2042.12 | CZ4: 2043.03 | DA4: 2043.06 | DB4: 2043.09 | DC4: 2043.12 | DD4: 2044.03 | DE4: 2044.06 | DF4: 2044.09 | DG4: 2044.12 | DH4: 2045.03 | DI4: 2045.06 | DJ4: 2045.09 | DK4: 2045.12 | DL4: 2046.03 | DM4: 2046.06 | DN4: 2046.09 | DO4: 2046.12 | DP4: 2047.03 | DQ4: 2047.06 | DR4: 2047.09 | DS4: 2047.12 | DT4: 2048.03 | DU4: 2048.06 | DV4: 2048.09 | DW4: 2048.12 | DX4: 2049.03 | DY4: 2049.06 | DZ4: 2018.12A | EA4: 2019.12A | EB4: 2020.12A | EC4: 2021.12A | ED4: 2022.12A | EE4: 2023.12A | EF4: 2024.12A | EG4: 2025.12A | EH4: 2026.12A | EI4: 2027.12A | EJ4: 2028.12A | EK4: 2029.12A | EL4: 2030.12A | EM4: 2031.12A | EN4: 2032.12A | EO4: 2033.12A | EP4: 2034.12A | EQ4: 2035.12A | ER4: 2036.12A | ES4: 2037.12A | ET4: 2038.12A | EU4: 2039.12A | EV4: 2040.12A | EW4: 2041.12A | EX4: 2042.12A | EY4: 2043.12A | EZ4: 2044.12A | FA4: 2045.12A | FB4: 2046.12A | FC4: 2047.12A | FD4: 2048.12A | FE4: 2049.12A
A5: usd_m | D5: 매출인식 합계(백만$) | E5: 2.933 | F5: 6.133 | G5: 6.133 | H5: 6.7 | I5: 12.374 | J5: 14.461 | K5: 14.729 | L5: 19.188 | M5: 19.188 | N5: 19.399 | O5: 30.827 | P5: 45.288 | Q5: 50.661 | R5: 56.415 | S5: 59.244 | T5: 58.81 | U5: 59.464 | V5: 61.318 | W5: 65.621 | X5: 73.087 | Y5: 81.759 | Z5: 100.274 | AA5: 115.314 | AB5: 115.48 | AC5: 122.384 | AD5: 123.839 | AE5: 124.336 | AF5: 125.212 | AG5: 124.929 | AH5: 125.517 | AI5: 135.044 | AJ5: 185.789 | AK5: 220.765 | AL5: 242.223 | AM5: 284.659 | AN5: 262.202 | AO5: 238.019 | AP5: 230.448 | AQ5: 220.853 | AR5: 205.334 | AS5: 199.002 | AT5: 167.999 | AU5: 143.676 | AV5: 129.805 | AW5: 91.577 | AX5: 73.018 | AY5: 59.31 | AZ5: 37.304 | BA5: 35.273 | BB5: 30.118 | BC5: 15.253 | BD5: 12.997 | BE5: 12.049 | BF5: 11.181 | BG5: 11.181 | BH5: 11.06 | BI5: 7.648 | BJ5: 6.882 | BK5: 6.882 | BL5: 6.732 | BM5: 6.807 | BN5: 5.966 | BO5: 4.25 | BP5: 4.158 | BQ5: 1.785 | BR5: 0.602 | BS5: 0.602 | BT5: 0.589 | BU5: 0.596 | BV5: 0.602 | BW5: 0.602 | BX5: 0.596 | BY5: 0.596 | BZ5: 0.602 | CA5: 0.602 | CB5: 0.589 | CC5: 0.596 | CD5: 0.602 | CE5: 0.602 | CF5: 0.589 | CG5: 0.596 | CH5: 0.602 | CI5: 0.602 | CJ5: 0.589 | CK5: 0.596 | CL5: 0.602 | CM5: 0.602 | CN5: 0.596 | CO5: 0.596 | CP5: 0.602 | CQ5: 0.602 | CR5: 0.589 | CS5: 0.596 | CT5: 0.602 | CU5: 0.602 | CV5: 0.589 | CW5: 0.596 | CX5: 0.602 | CY5: 0.602 | CZ5: 0.589 | DA5: 0.596 | DB5: 0.602 | DC5: 0.602 | DD5: 0.596 | DE5: 0.596 | DF5: 0.602 | DG5: 0.602 | DH5: 0.589 | DI5: 0.596 | DJ5: 0.602 | DK5: 0.602 | DL5: 0.589 | DM5: 0.596 | DN5: 0.602 | DO5: 0.602 | DP5: 0.589 | DQ5: 0.596 | DR5: 0.602 | DS5: 0.602 | DT5: 0.596 | DU5: 0.596 | DV5: 0.602 | DW5: 0.602 | DX5: 0.589 | DY5: 0.399 | DZ5: 15.199 | EA5: 48.264 | EB5: 88.602 | EC5: 211.608 | ED5: 245.213 | EE5: 370.434 | EF5: 486.039 | EG5: 510.702 | EH5: 933.436 | EI5: 951.522 | EJ5: 716.011 | EK5: 353.71 | EL5: 117.948 | EM5: 47.408 | EN5: 32.472 | EO5: 23.755 | EP5: 7.147 | EQ5: 2.389 | ER5: 2.396 | ES5: 2.389 | ET5: 2.389 | EU5: 2.389 | EV5: 2.396 | EW5: 2.389 | EX5: 2.389 | EY5: 2.389 | EZ5: 2.396 | FA5: 2.389 | FB5: 2.389 | FC5: 2.389 | FD5: 2.396 | FE5: 0.988
A6: marine_usd_m | D6: 해양(type≠OTHER) 합계(백만$) | E6: 0 | F6: 0 | G6: 0 | H6: 0 | I6: 0 | J6: 0 | K6: 0 | L6: 0 | M6: 0 | N6: 0 | O6: 0 | P6: 0 | Q6: 0 | R6: 0 | S6: 0 | T6: 0 | U6: 0 | V6: 0 | W6: 0 | X6: 0 | Y6: 0 | Z6: 0 | AA6: 0 | AB6: 0 | AC6: 0 | AD6: 0 | AE6: 0 | AF6: 0 | AG6: 0 | AH6: 0 | AI6: 2.682 | AJ6: 31.491 | AK6: 60.559 | AL6: 72.245 | AM6: 113.423 | AN6: 110.957 | AO6: 112.19 | AP6: 113.423 | AQ6: 113.423 | AR6: 112.19 | AS6: 112.19 | AT6: 88.001 | AU6: 71.209 | AV6: 58.914 | AW6: 28.936 | AX6: 14.024 | AY6: 4.725 | AZ6: 0 | BA6: 0 | BB6: 0 | BC6: 0 | BD6: 0 | BE6: 0 | BF6: 0 | BG6: 0 | BH6: 0 | BI6: 0 | BJ6: 0 | BK6: 0 | BL6: 0 | BM6: 0 | BN6: 0 | BO6: 0 | BP6: 0 | BQ6: 0 | BR6: 0 | BS6: 0 | BT6: 0 | BU6: 0 | BV6: 0 | BW6: 0 | BX6: 0 | BY6: 0 | BZ6: 0 | CA6: 0 | CB6: 0 | CC6: 0 | CD6: 0 | CE6: 0 | CF6: 0 | CG6: 0 | CH6: 0 | CI6: 0 | CJ6: 0 | CK6: 0 | CL6: 0 | CM6: 0 | CN6: 0 | CO6: 0 | CP6: 0 | CQ6: 0 | CR6: 0 | CS6: 0 | CT6: 0 | CU6: 0 | CV6: 0 | CW6: 0 | CX6: 0 | CY6: 0 | CZ6: 0 | DA6: 0 | DB6: 0 | DC6: 0 | DD6: 0 | DE6: 0 | DF6: 0 | DG6: 0 | DH6: 0 | DI6: 0 | DJ6: 0 | DK6: 0 | DL6: 0 | DM6: 0 | DN6: 0 | DO6: 0 | DP6: 0 | DQ6: 0 | DR6: 0 | DS6: 0 | DT6: 0 | DU6: 0 | DV6: 0 | DW6: 0 | DX6: 0 | DY6: 0 | DZ6: 0 | EA6: 0 | EB6: 0 | EC6: 0 | ED6: 0 | EE6: 0 | EF6: 0 | EG6: 2.682 | EH6: 277.718 | EI6: 449.993 | EJ6: 383.59 | EK6: 106.599 | EL6: 0 | EM6: 0 | EN6: 0 | EO6: 0 | EP6: 0 | EQ6: 0 | ER6: 0 | ES6: 0 | ET6: 0 | EU6: 0 | EV6: 0 | EW6: 0 | EX6: 0 | EY6: 0 | EZ6: 0 | FA6: 0 | FB6: 0 | FC6: 0 | FD6: 0 | FE6: 0
A7: type:OTHER | D7: 선종 OTHER | E7: 2.933 | F7: 6.133 | G7: 6.133 | H7: 6.7 | I7: 12.374 | J7: 14.461 | K7: 14.729 | L7: 19.188 | M7: 19.188 | N7: 19.399 | O7: 30.827 | P7: 45.288 | Q7: 50.661 | R7: 56.415 | S7: 59.244 | T7: 58.81 | U7: 59.464 | V7: 61.318 | W7: 65.621 | X7: 73.087 | Y7: 81.759 | Z7: 100.274 | AA7: 115.314 | AB7: 115.48 | AC7: 122.384 | AD7: 123.839 | AE7: 124.336 | AF7: 125.212 | AG7: 124.929 | AH7: 125.517 | AI7: 132.362 | AJ7: 154.299 | AK7: 160.206 | AL7: 169.978 | AM7: 171.236 | AN7: 151.245 | AO7: 125.829 | AP7: 117.026 | AQ7: 107.431 | AR7: 93.144 | AS7: 86.812 | AT7: 79.998 | AU7: 72.466 | AV7: 70.891 | AW7: 62.641 | AX7: 58.995 | AY7: 54.584 | AZ7: 37.304 | BA7: 35.273 | BB7: 30.118 | BC7: 15.253 | BD7: 12.997 | BE7: 12.049 | BF7: 11.181 | BG7: 11.181 | BH7: 11.06 | BI7: 7.648 | BJ7: 6.882 | BK7: 6.882 | BL7: 6.732 | BM7: 6.807 | BN7: 5.966 | BO7: 4.25 | BP7: 4.158 | BQ7: 1.785 | BR7: 0.602 | BS7: 0.602 | BT7: 0.589 | BU7: 0.596 | BV7: 0.602 | BW7: 0.602 | BX7: 0.596 | BY7: 0.596 | BZ7: 0.602 | CA7: 0.602 | CB7: 0.589 | CC7: 0.596 | CD7: 0.602 | CE7: 0.602 | CF7: 0.589 | CG7: 0.596 | CH7: 0.602 | CI7: 0.602 | CJ7: 0.589 | CK7: 0.596 | CL7: 0.602 | CM7: 0.602 | CN7: 0.596 | CO7: 0.596 | CP7: 0.602 | CQ7: 0.602 | CR7: 0.589 | CS7: 0.596 | CT7: 0.602 | CU7: 0.602 | CV7: 0.589 | CW7: 0.596 | CX7: 0.602 | CY7: 0.602 | CZ7: 0.589 | DA7: 0.596 | DB7: 0.602 | DC7: 0.602 | DD7: 0.596 | DE7: 0.596 | DF7: 0.602 | DG7: 0.602 | DH7: 0.589 | DI7: 0.596 | DJ7: 0.602 | DK7: 0.602 | DL7: 0.589 | DM7: 0.596 | DN7: 0.602 | DO7: 0.602 | DP7: 0.589 | DQ7: 0.596 | DR7: 0.602 | DS7: 0.602 | DT7: 0.596 | DU7: 0.596 | DV7: 0.602 | DW7: 0.602 | DX7: 0.589 | DY7: 0.399 | DZ7: 15.199 | EA7: 48.264 | EB7: 88.602 | EC7: 211.608 | ED7: 245.213 | EE7: 370.434 | EF7: 486.039 | EG7: 508.02 | EH7: 655.719 | EI7: 501.531 | EJ7: 332.42 | EK7: 247.111 | EL7: 117.948 | EM7: 47.408 | EN7: 32.472 | EO7: 23.755 | EP7: 7.147 | EQ7: 2.389 | ER7: 2.396 | ES7: 2.389 | ET7: 2.389 | EU7: 2.389 | EV7: 2.396 | EW7: 2.389 | EX7: 2.389 | EY7: 2.389 | EZ7: 2.396 | FA7: 2.389 | FB7: 2.389 | FC7: 2.389 | FD7: 2.396 | FE7: 0.988
A8: type:NAVAL | D8: 선종 NAVAL | AI8: 2.682 | AJ8: 17.675 | AK8: 17.871 | AL8: 18.067 | AM8: 18.067 | AN8: 17.675 | AO8: 17.871 | AP8: 18.067 | AQ8: 18.067 | AR8: 17.871 | AS8: 17.871 | AT8: 18.067 | AU8: 17.013 | AV8: 13.719 | AW8: 13.871 | AX8: 14.024 | AY8: 4.725 | EG8: 2.682 | EH8: 71.68 | EI8: 71.68 | EJ8: 70.822 | EK8: 46.339
A9: type:CONT | D9: 선종 CONT | AJ9: 13.816 | AK9: 42.688 | AL9: 54.177 | AM9: 95.355 | AN9: 93.282 | AO9: 94.319 | AP9: 95.355 | AQ9: 95.355 | AR9: 94.319 | AS9: 94.319 | AT9: 69.933 | AU9: 54.197 | AV9: 45.195 | AW9: 15.065 | EH9: 206.036 | EI9: 378.311 | EJ9: 312.768 | EK9: 60.26
A10: cohort:등급없음 | D10: 코호트 등급없음 | E10: 2.933 | F10: 6.133 | G10: 6.133 | H10: 6.7 | I10: 12.374 | J10: 14.461 | K10: 14.729 | L10: 19.188 | M10: 19.188 | N10: 19.399 | O10: 30.827 | P10: 45.288 | Q10: 50.661 | R10: 56.415 | S10: 59.244 | T10: 58.81 | U10: 59.464 | V10: 61.318 | W10: 65.621 | X10: 73.087 | Y10: 81.759 | Z10: 100.274 | AA10: 115.314 | AB10: 115.48 | AC10: 122.384 | AD10: 123.839 | AE10: 124.336 | AF10: 125.212 | AG10: 124.929 | AH10: 125.517 | AI10: 134.648 | AJ10: 168.017 | AK10: 174.078 | AL10: 184.002 | AM10: 185.26 | AN10: 164.964 | AO10: 139.7 | AP10: 131.049 | AQ10: 121.454 | AR10: 107.016 | AS10: 100.684 | AT10: 94.021 | AU10: 86.49 | AV10: 84.61 | AW10: 76.512 | AX10: 73.018 | AY10: 59.31 | AZ10: 37.304 | BA10: 35.273 | BB10: 30.118 | BC10: 15.253 | BD10: 12.997 | BE10: 12.049 | BF10: 11.181 | BG10: 11.181 | BH10: 11.06 | BI10: 7.648 | BJ10: 6.882 | BK10: 6.882 | BL10: 6.732 | BM10: 6.807 | BN10: 5.966 | BO10: 4.25 | BP10: 4.158 | BQ10: 1.785 | BR10: 0.602 | BS10: 0.602 | BT10: 0.589 | BU10: 0.596 | BV10: 0.602 | BW10: 0.602 | BX10: 0.596 | BY10: 0.596 | BZ10: 0.602 | CA10: 0.602 | CB10: 0.589 | CC10: 0.596 | CD10: 0.602 | CE10: 0.602 | CF10: 0.589 | CG10: 0.596 | CH10: 0.602 | CI10: 0.602 | CJ10: 0.589 | CK10: 0.596 | CL10: 0.602 | CM10: 0.602 | CN10: 0.596 | CO10: 0.596 | CP10: 0.602 | CQ10: 0.602 | CR10: 0.589 | CS10: 0.596 | CT10: 0.602 | CU10: 0.602 | CV10: 0.589 | CW10: 0.596 | CX10: 0.602 | CY10: 0.602 | CZ10: 0.589 | DA10: 0.596 | DB10: 0.602 | DC10: 0.602 | DD10: 0.596 | DE10: 0.596 | DF10: 0.602 | DG10: 0.602 | DH10: 0.589 | DI10: 0.596 | DJ10: 0.602 | DK10: 0.602 | DL10: 0.589 | DM10: 0.596 | DN10: 0.602 | DO10: 0.602 | DP10: 0.589 | DQ10: 0.596 | DR10: 0.602 | DS10: 0.602 | DT10: 0.596 | DU10: 0.596 | DV10: 0.602 | DW10: 0.602 | DX10: 0.589 | DY10: 0.399 | DZ10: 15.199 | EA10: 48.264 | EB10: 88.602 | EC10: 211.608 | ED10: 245.213 | EE10: 370.434 | EF10: 486.039 | EG10: 510.306 | EH10: 711.357 | EI10: 557.167 | EJ10: 388.211 | EK10: 293.45 | EL10: 117.948 | EM10: 47.408 | EN10: 32.472 | EO10: 23.755 | EP10: 7.147 | EQ10: 2.389 | ER10: 2.396 | ES10: 2.389 | ET10: 2.389 | EU10: 2.389 | EV10: 2.396 | EW10: 2.389 | EX10: 2.389 | EY10: 2.389 | EZ10: 2.396 | FA10: 2.389 | FB10: 2.389 | FC10: 2.389 | FD10: 2.396 | FE10: 0.988
A11: cohort:⑤초호황 | D11: 코호트 ⑤초호황 | AI11: 0.396 | AJ11: 17.772 | AK11: 46.688 | AL11: 58.221 | AM11: 99.399 | AN11: 97.238 | AO11: 98.319 | AP11: 99.399 | AQ11: 99.399 | AR11: 98.319 | AS11: 98.319 | AT11: 73.977 | AU11: 57.186 | AV11: 45.195 | AW11: 15.065 | EG11: 0.396 | EH11: 222.08 | EI11: 394.355 | EJ11: 327.801 | EK11: 60.26
A12: hedge_ratio | D12: 헤지비율 | E12: 0.7 | F12: 0.7 | G12: 0.7 | H12: 0.7 | I12: 0.7 | J12: 0.7 | K12: 0.7 | L12: 0.7 | M12: 0.7 | N12: 0.7 | O12: 0.7 | P12: 0.7 | Q12: 0.7 | R12: 0.7 | S12: 0.7 | T12: 0.7 | U12: 0.7 | V12: 0.7 | W12: 0.7 | X12: 0.7 | Y12: 0.7 | Z12: 0.7 | AA12: 0.7 | AB12: 0.7 | AC12: 0.7 | AD12: 0.7 | AE12: 0.7 | AF12: 0.7 | AG12: 0.7 | AH12: 0.7 | AI12: 0.7 | AJ12: 0.7 | AK12: 0.7 | AL12: 0.7 | AM12: 0.7 | AN12: 0.7 | AO12: 0.7 | AP12: 0.7 | AQ12: 0.7 | AR12: 0.7 | AS12: 0.7 | AT12: 0.7 | AU12: 0.7 | AV12: 0.7 | AW12: 0.7 | AX12: 0.7 | AY12: 0.7 | AZ12: 0.7 | BA12: 0.7 | BB12: 0.7 | BC12: 0.7 | BD12: 0.7 | BE12: 0.7 | BF12: 0.7 | BG12: 0.7 | BH12: 0.7 | BI12: 0.7 | BJ12: 0.7 | BK12: 0.7 | BL12: 0.7 | BM12: 0.7 | BN12: 0.7 | BO12: 0.7 | BP12: 0.7 | BQ12: 0.7 | BR12: 0.7 | BS12: 0.7 | BT12: 0.7 | BU12: 0.7 | BV12: 0.7 | BW12: 0.7 | BX12: 0.7 | BY12: 0.7 | BZ12: 0.7 | CA12: 0.7 | CB12: 0.7 | CC12: 0.7 | CD12: 0.7 | CE12: 0.7 | CF12: 0.7 | CG12: 0.7 | CH12: 0.7 | CI12: 0.7 | CJ12: 0.7 | CK12: 0.7 | CL12: 0.7 | CM12: 0.7 | CN12: 0.7 | CO12: 0.7 | CP12: 0.7 | CQ12: 0.7 | CR12: 0.7 | CS12: 0.7 | CT12: 0.7 | CU12: 0.7 | CV12: 0.7 | CW12: 0.7 | CX12: 0.7 | CY12: 0.7 | CZ12: 0.7 | DA12: 0.7 | DB12: 0.7 | DC12: 0.7 | DD12: 0.7 | DE12: 0.7 | DF12: 0.7 | DG12: 0.7 | DH12: 0.7 | DI12: 0.7 | DJ12: 0.7 | DK12: 0.7 | DL12: 0.7 | DM12: 0.7 | DN12: 0.7 | DO12: 0.7 | DP12: 0.7 | DQ12: 0.7 | DR12: 0.7 | DS12: 0.7 | DT12: 0.7 | DU12: 0.7 | DV12: 0.7 | DW12: 0.7 | DX12: 0.7 | DY12: 0.7
A13: hedge_rate | D13: 헤지환율(가중) | E13: 1080.48 | F13: 1080.48 | G13: 1080.48 | H13: 1085.22 | I13: 1106.95 | J13: 1115.14 | K13: 1116.26 | L13: 1130.69 | M13: 1130.69 | N13: 1130.69 | O13: 1125.98 | P13: 1123.3 | Q13: 1122.51 | R13: 1124.2 | S13: 1126.74 | T13: 1127.57 | U13: 1127.57 | V13: 1131.77 | W13: 1145.89 | X13: 1170.82 | Y13: 1183.49 | Z13: 1206.46 | AA13: 1220.45 | AB13: 1221.79 | AC13: 1227.91 | AD13: 1228 | AE13: 1228.67 | AF13: 1233.83 | AG13: 1249.21 | AH13: 1254.23 | AI13: 1267.98 | AJ13: 1322.94 | AK13: 1377.69 | AL13: 1386.2 | AM13: 1391.05 | AN13: 1404.14 | AO13: 1421.74 | AP13: 1427.05 | AQ13: 1432.32 | AR13: 1439.67 | AS13: 1446.65 | AT13: 1447.91 | AU13: 1445.29 | AV13: 1441.8 | AW13: 1446.14 | AX13: 1450.05 | AY13: 1455.06 | AZ13: 1461.42 | BA13: 1462.26 | BB13: 1461.55 | BC13: 1427.55 | BD13: 1461.07 | BE13: 1466.32 | BF13: 1463.15 | BG13: 1463.15 | BH13: 1463.15 | BI13: 1445.93 | BJ13: 1439.03 | BK13: 1439.03 | BL13: 1439.03 | BM13: 1439.03 | BN13: 1442.14 | BO13: 1451.59 | BP13: 1451.59 | BQ13: 1454.84 | BR13: 1466.12 | BS13: 1466.12 | BT13: 1466.12 | BU13: 1466.12 | BV13: 1466.12 | BW13: 1466.12 | BX13: 1466.12 | BY13: 1466.12 | BZ13: 1466.12 | CA13: 1466.12 | CB13: 1466.12 | CC13: 1466.12 | CD13: 1466.12 | CE13: 1466.12 | CF13: 1466.12 | CG13: 1466.12 | CH13: 1466.12 | CI13: 1466.12 | CJ13: 1466.12 | CK13: 1466.12 | CL13: 1466.12 | CM13: 1466.12 | CN13: 1466.12 | CO13: 1466.12 | CP13: 1466.12 | CQ13: 1466.12 | CR13: 1466.12 | CS13: 1466.12 | CT13: 1466.12 | CU13: 1466.12 | CV13: 1466.12 | CW13: 1466.12 | CX13: 1466.12 | CY13: 1466.12 | CZ13: 1466.12 | DA13: 1466.12 | DB13: 1466.12 | DC13: 1466.12 | DD13: 1466.12 | DE13: 1466.12 | DF13: 1466.12 | DG13: 1466.12 | DH13: 1466.12 | DI13: 1466.12 | DJ13: 1466.12 | DK13: 1466.12 | DL13: 1466.12 | DM13: 1466.12 | DN13: 1466.12 | DO13: 1466.12 | DP13: 1466.12 | DQ13: 1466.12 | DR13: 1466.12 | DS13: 1466.12 | DT13: 1466.12 | DU13: 1466.12 | DV13: 1466.12 | DW13: 1466.12 | DX13: 1466.12 | DY13: 1466.12
A14: spot_assumed | D14: 건조시점 환율(sls 가정) | E14: 1080.48 | F14: 1121.86 | G14: 1127.53 | H14: 1125.78 | I14: 1167.69 | J14: 1193.96 | K14: 1176.23 | L14: 1193.92 | M14: 1219.69 | N14: 1187.81 | O14: 1117.97 | P14: 1114.99 | Q14: 1121.13 | R14: 1159.91 | S14: 1183.5 | T14: 1205.78 | U14: 1262.09 | V14: 1341.93 | W14: 1360.12 | X14: 1276.95 | Y14: 1315.69 | Z14: 1313.62 | AA14: 1322.01 | AB14: 1330.14 | AC14: 1371.28 | AD14: 1356.22 | AE14: 1396.3 | AF14: 1452.28 | AG14: 1398.52 | AH14: 1386.95 | AI14: 1449.19 | AJ14: 1466.12 | AK14: 1501.75 | AL14: 1418.75 | AM14: 1343.39 | AN14: 1341.45 | AO14: 1341.45 | AP14: 1341.45 | AQ14: 1341.45 | AR14: 1341.45 | AS14: 1341.45 | AT14: 1341.45 | AU14: 1341.45 | AV14: 1341.45 | AW14: 1341.45 | AX14: 1341.45 | AY14: 1341.45 | AZ14: 1341.45 | BA14: 1341.45 | BB14: 1341.45 | BC14: 1341.45 | BD14: 1341.45 | BE14: 1341.45 | BF14: 1341.45 | BG14: 1341.45 | BH14: 1341.45 | BI14: 1341.45 | BJ14: 1341.45 | BK14: 1341.45 | BL14: 1341.45 | BM14: 1341.45 | BN14: 1341.45 | BO14: 1341.45 | BP14: 1341.45 | BQ14: 1341.45 | BR14: 1341.45 | BS14: 1341.45 | BT14: 1341.45 | BU14: 1341.45 | BV14: 1341.45 | BW14: 1341.45 | BX14: 1341.45 | BY14: 1341.45 | BZ14: 1341.45 | CA14: 1341.45 | CB14: 1341.45 | CC14: 1341.45 | CD14: 1341.45 | CE14: 1341.45 | CF14: 1341.45 | CG14: 1341.45 | CH14: 1341.45 | CI14: 1341.45 | CJ14: 1341.45 | CK14: 1341.45 | CL14: 1341.45 | CM14: 1341.45 | CN14: 1341.45 | CO14: 1341.45 | CP14: 1341.45 | CQ14: 1341.45 | CR14: 1341.45 | CS14: 1341.45 | CT14: 1341.45 | CU14: 1341.45 | CV14: 1341.45 | CW14: 1341.45 | CX14: 1341.45 | CY14: 1341.45 | CZ14: 1341.45 | DA14: 1341.45 | DB14: 1341.45 | DC14: 1341.45 | DD14: 1341.45 | DE14: 1341.45 | DF14: 1341.45 | DG14: 1341.45 | DH14: 1341.45 | DI14: 1341.45 | DJ14: 1341.45 | DK14: 1341.45 | DL14: 1341.45 | DM14: 1341.45 | DN14: 1341.45 | DO14: 1341.45 | DP14: 1341.45 | DQ14: 1341.45 | DR14: 1341.45 | DS14: 1341.45 | DT14: 1341.45 | DU14: 1341.45 | DV14: 1341.45 | DW14: 1341.45 | DX14: 1341.45 | DY14: 1341.45
A15: applied_rate | D15: 적용환율 | E15: 1080.48 | F15: 1092.89 | G15: 1094.6 | H15: 1097.39 | I15: 1125.17 | J15: 1138.79 | K15: 1134.25 | L15: 1149.66 | M15: 1157.39 | N15: 1147.83 | O15: 1123.57 | P15: 1120.81 | Q15: 1122.1 | R15: 1134.91 | S15: 1143.77 | T15: 1151.03 | U15: 1167.92 | V15: 1194.81 | W15: 1210.16 | X15: 1202.66 | Y15: 1223.15 | Z15: 1238.61 | AA15: 1250.91 | AB15: 1254.3 | AC15: 1270.92 | AD15: 1266.46 | AE15: 1278.96 | AF15: 1299.36 | AG15: 1294 | AH15: 1294.04 | AI15: 1322.34 | AJ15: 1365.89 | AK15: 1414.91 | AL15: 1395.96 | AM15: 1376.75 | AN15: 1385.34 | AO15: 1397.65 | AP15: 1401.37 | AQ15: 1405.06 | AR15: 1410.2 | AS15: 1415.09 | AT15: 1415.97 | AU15: 1414.14 | AV15: 1411.7 | AW15: 1414.73 | AX15: 1417.47 | AY15: 1420.98 | AZ15: 1425.43 | BA15: 1426.02 | BB15: 1425.52 | BC15: 1401.72 | BD15: 1425.18 | BE15: 1428.86 | BF15: 1426.64 | BG15: 1426.64 | BH15: 1426.64 | BI15: 1414.59 | BJ15: 1409.76 | BK15: 1409.76 | BL15: 1409.76 | BM15: 1409.76 | BN15: 1411.94 | BO15: 1418.55 | BP15: 1418.55 | BQ15: 1420.82 | BR15: 1428.72 | BS15: 1428.72 | BT15: 1428.72 | BU15: 1428.72 | BV15: 1428.72 | BW15: 1428.72 | BX15: 1428.72 | BY15: 1428.72 | BZ15: 1428.72 | CA15: 1428.72 | CB15: 1428.72 | CC15: 1428.72 | CD15: 1428.72 | CE15: 1428.72 | CF15: 1428.72 | CG15: 1428.72 | CH15: 1428.72 | CI15: 1428.72 | CJ15: 1428.72 | CK15: 1428.72 | CL15: 1428.72 | CM15: 1428.72 | CN15: 1428.72 | CO15: 1428.72 | CP15: 1428.72 | CQ15: 1428.72 | CR15: 1428.72 | CS15: 1428.72 | CT15: 1428.72 | CU15: 1428.72 | CV15: 1428.72 | CW15: 1428.72 | CX15: 1428.72 | CY15: 1428.72 | CZ15: 1428.72 | DA15: 1428.72 | DB15: 1428.72 | DC15: 1428.72 | DD15: 1428.72 | DE15: 1428.72 | DF15: 1428.72 | DG15: 1428.72 | DH15: 1428.72 | DI15: 1428.72 | DJ15: 1428.72 | DK15: 1428.72 | DL15: 1428.72 | DM15: 1428.72 | DN15: 1428.72 | DO15: 1428.72 | DP15: 1428.72 | DQ15: 1428.72 | DR15: 1428.72 | DS15: 1428.72 | DT15: 1428.72 | DU15: 1428.72 | DV15: 1428.72 | DW15: 1428.72 | DX15: 1428.72 | DY15: 1428.72
A16: hedged_krw_m | D16: 헤지적용 원화매출(백만원) | E16: 3169.1 | F16: 6702.4 | G16: 6712.8 | H16: 7352.3 | I16: 13923.4 | J16: 16467.9 | K16: 16706.7 | L16: 22060 | M16: 22208.4 | N16: 22266.9 | O16: 34636.6 | P16: 50759 | Q16: 56847.1 | R16: 64025.8 | S16: 67761.2 | T16: 67692.2 | U16: 69448.9 | V16: 73263.5 | W16: 79412 | X16: 87898.7 | Y16: 100004.1 | Z16: 124200.3 | AA16: 144247.5 | AB16: 144846.3 | AC16: 155540 | AD16: 156837.5 | AE16: 159020.9 | AF16: 162696 | AG16: 161657.6 | AH16: 162424.3 | AI16: 178574.1 | AJ16: 253768 | AK16: 312363.2 | AL16: 338133.5 | AM16: 391904.6 | AN16: 363237.5 | AO16: 332667.1 | AP16: 322943.8 | AQ16: 310312.4 | AR16: 289562.9 | AS16: 281605.5 | AT16: 237881.5 | AU16: 203177.4 | AV16: 183245.1 | AW16: 129557.2 | AX16: 103501.5 | AY16: 84277.6 | AZ16: 53174.8 | BA16: 50299.8 | BB16: 42934.1 | BC16: 21380.8 | BD16: 18523.7 | BE16: 17217 | BF16: 15951.5 | BG16: 15951.5 | BH16: 15778.1 | BI16: 10818.8 | BJ16: 9701.4 | BK16: 9701.4 | BL16: 9490.5 | BM16: 9595.9 | BN16: 8423.9 | BO16: 6028.8 | BP16: 5897.7 | BQ16: 2536.6 | BR16: 860.8 | BS16: 860.8 | BT16: 842 | BU16: 851.4 | BV16: 860.8 | BW16: 860.8 | BX16: 851.4 | BY16: 851.4 | BZ16: 860.8 | CA16: 860.8 | CB16: 842 | CC16: 851.4 | CD16: 860.8 | CE16: 860.8 | CF16: 842 | CG16: 851.4 | CH16: 860.8 | CI16: 860.8 | CJ16: 842 | CK16: 851.4 | CL16: 860.8 | CM16: 860.8 | CN16: 851.4 | CO16: 851.4 | CP16: 860.8 | CQ16: 860.8 | CR16: 842 | CS16: 851.4 | CT16: 860.8 | CU16: 860.8 | CV16: 842 | CW16: 851.4 | CX16: 860.8 | CY16: 860.8 | CZ16: 842 | DA16: 851.4 | DB16: 860.8 | DC16: 860.8 | DD16: 851.4 | DE16: 851.4 | DF16: 860.8 | DG16: 860.8 | DH16: 842 | DI16: 851.4 | DJ16: 860.8 | DK16: 860.8 | DL16: 842 | DM16: 851.4 | DN16: 860.8 | DO16: 860.8 | DP16: 842 | DQ16: 851.4 | DR16: 860.8 | DS16: 860.8 | DT16: 851.4 | DU16: 851.4 | DV16: 860.8 | DW16: 860.8 | DX16: 842 | DY16: 570.7 | DZ16: 16584.3 | EA16: 54450.3 | EB16: 101171.9 | EC16: 239393.1 | ED16: 289816.6 | EE16: 456350.6 | EF16: 616244.7 | EG16: 665352 | EH16: 1296169.3 | EI16: 1329160.8 | EJ16: 1012227.3 | EK16: 500581.4 | EL16: 167789.5 | EM16: 67643.7 | EN16: 45999.7 | EO16: 33539.1 | EP16: 10155.9 | EQ16: 3415 | ER16: 3424.4 | ES16: 3415 | ET16: 3415 | EU16: 3415 | EV16: 3424.4 | EW16: 3415 | EX16: 3415 | EY16: 3415 | EZ16: 3424.4 | FA16: 3415 | FB16: 3415 | FC16: 3415 | FD16: 3424.4 | FE16: 1412.7
A17: marine_hedged_krw_m | D17: 해양 원화(백만원) | E17: 0 | F17: 0 | G17: 0 | H17: 0 | I17: 0 | J17: 0 | K17: 0 | L17: 0 | M17: 0 | N17: 0 | O17: 0 | P17: 0 | Q17: 0 | R17: 0 | S17: 0 | T17: 0 | U17: 0 | V17: 0 | W17: 0 | X17: 0 | Y17: 0 | Z17: 0 | AA17: 0 | AB17: 0 | AC17: 0 | AD17: 0 | AE17: 0 | AF17: 0 | AG17: 0 | AH17: 0 | AI17: 3886.8 | AJ17: 45959.9 | AK17: 89659.6 | AL17: 105104.1 | AM17: 160960.9 | AN17: 157397.2 | AO17: 159146 | AP17: 160894.9 | AQ17: 160894.9 | AR17: 159146 | AS17: 159146 | AT17: 124574.5 | AU17: 100204.2 | AV17: 82510.3 | AW17: 40677.9 | AX17: 19869.7 | AY17: 6695.2 | AZ17: 0 | BA17: 0 | BB17: 0 | BC17: 0 | BD17: 0 | BE17: 0 | BF17: 0 | BG17: 0 | BH17: 0 | BI17: 0 | BJ17: 0 | BK17: 0 | BL17: 0 | BM17: 0 | BN17: 0 | BO17: 0 | BP17: 0 | BQ17: 0 | BR17: 0 | BS17: 0 | BT17: 0 | BU17: 0 | BV17: 0 | BW17: 0 | BX17: 0 | BY17: 0 | BZ17: 0 | CA17: 0 | CB17: 0 | CC17: 0 | CD17: 0 | CE17: 0 | CF17: 0 | CG17: 0 | CH17: 0 | CI17: 0 | CJ17: 0 | CK17: 0 | CL17: 0 | CM17: 0 | CN17: 0 | CO17: 0 | CP17: 0 | CQ17: 0 | CR17: 0 | CS17: 0 | CT17: 0 | CU17: 0 | CV17: 0 | CW17: 0 | CX17: 0 | CY17: 0 | CZ17: 0 | DA17: 0 | DB17: 0 | DC17: 0 | DD17: 0 | DE17: 0 | DF17: 0 | DG17: 0 | DH17: 0 | DI17: 0 | DJ17: 0 | DK17: 0 | DL17: 0 | DM17: 0 | DN17: 0 | DO17: 0 | DP17: 0 | DQ17: 0 | DR17: 0 | DS17: 0 | DT17: 0 | DU17: 0 | DV17: 0 | DW17: 0 | DX17: 0 | DY17: 0 | DZ17: 0 | EA17: 0 | EB17: 0 | EC17: 0 | ED17: 0 | EE17: 0 | EF17: 0 | EG17: 3886.8 | EH17: 401684.5 | EI17: 638333 | EJ17: 543070.7 | EK17: 149753.1 | EL17: 0 | EM17: 0 | EN17: 0 | EO17: 0 | EP17: 0 | EQ17: 0 | ER17: 0 | ES17: 0 | ET17: 0 | EU17: 0 | EV17: 0 | EW17: 0 | EX17: 0 | EY17: 0 | EZ17: 0 | FA17: 0 | FB17: 0 | FC17: 0 | FD17: 0 | FE17: 0
A18: marine_hedged_krw_m_signed_by_origin | D18: 해양 원화 — origin 분기말까지 체결분(백만원) | E18: 0 | F18: 0 | G18: 0 | H18: 0 | I18: 0 | J18: 0 | K18: 0 | L18: 0 | M18: 0 | N18: 0 | O18: 0 | P18: 0 | Q18: 0 | R18: 0 | S18: 0 | T18: 0 | U18: 0 | V18: 0 | W18: 0 | X18: 0 | Y18: 0 | Z18: 0 | AA18: 0 | AB18: 0 | AC18: 0 | AD18: 0 | AE18: 0 | AF18: 0 | AG18: 0 | AH18: 0 | AI18: 3886.8 | AJ18: 45959.9 | AK18: 89659.6 | AL18: 97979.6 | AM18: 96459.8 | AN18: 94324.6 | AO18: 95372.6 | AP18: 96420.7 | AQ18: 96420.7 | AR18: 95372.6 | AS18: 95372.6 | AT18: 60100.3 | AU18: 35729.9 | AV18: 19437.7 | AW18: 19653.7 | AX18: 19869.7 | AY18: 6695.2 | AZ18: 0 | BA18: 0 | BB18: 0 | BC18: 0 | BD18: 0 | BE18: 0 | BF18: 0 | BG18: 0 | BH18: 0 | BI18: 0 | BJ18: 0 | BK18: 0 | BL18: 0 | BM18: 0 | BN18: 0 | BO18: 0 | BP18: 0 | BQ18: 0 | BR18: 0 | BS18: 0 | BT18: 0 | BU18: 0 | BV18: 0 | BW18: 0 | BX18: 0 | BY18: 0 | BZ18: 0 | CA18: 0 | CB18: 0 | CC18: 0 | CD18: 0 | CE18: 0 | CF18: 0 | CG18: 0 | CH18: 0 | CI18: 0 | CJ18: 0 | CK18: 0 | CL18: 0 | CM18: 0 | CN18: 0 | CO18: 0 | CP18: 0 | CQ18: 0 | CR18: 0 | CS18: 0 | CT18: 0 | CU18: 0 | CV18: 0 | CW18: 0 | CX18: 0 | CY18: 0 | CZ18: 0 | DA18: 0 | DB18: 0 | DC18: 0 | DD18: 0 | DE18: 0 | DF18: 0 | DG18: 0 | DH18: 0 | DI18: 0 | DJ18: 0 | DK18: 0 | DL18: 0 | DM18: 0 | DN18: 0 | DO18: 0 | DP18: 0 | DQ18: 0 | DR18: 0 | DS18: 0 | DT18: 0 | DU18: 0 | DV18: 0 | DW18: 0 | DX18: 0 | DY18: 0
A19: marine_hedged_krw_m_post_origin | D19: 해양 원화 — origin 이후 체결분(백만원) | E19: 0 | F19: 0 | G19: 0 | H19: 0 | I19: 0 | J19: 0 | K19: 0 | L19: 0 | M19: 0 | N19: 0 | O19: 0 | P19: 0 | Q19: 0 | R19: 0 | S19: 0 | T19: 0 | U19: 0 | V19: 0 | W19: 0 | X19: 0 | Y19: 0 | Z19: 0 | AA19: 0 | AB19: 0 | AC19: 0 | AD19: 0 | AE19: 0 | AF19: 0 | AG19: 0 | AH19: 0 | AI19: 0 | AJ19: 0 | AK19: 0 | AL19: 7124.5 | AM19: 64501.1 | AN19: 63072.6 | AO19: 63773.4 | AP19: 64474.2 | AQ19: 64474.2 | AR19: 63773.4 | AS19: 63773.4 | AT19: 64474.2 | AU19: 64474.2 | AV19: 63072.6 | AW19: 21024.2 | AX19: 0 | AY19: 0 | AZ19: 0 | BA19: 0 | BB19: 0 | BC19: 0 | BD19: 0 | BE19: 0 | BF19: 0 | BG19: 0 | BH19: 0 | BI19: 0 | BJ19: 0 | BK19: 0 | BL19: 0 | BM19: 0 | BN19: 0 | BO19: 0 | BP19: 0 | BQ19: 0 | BR19: 0 | BS19: 0 | BT19: 0 | BU19: 0 | BV19: 0 | BW19: 0 | BX19: 0 | BY19: 0 | BZ19: 0 | CA19: 0 | CB19: 0 | CC19: 0 | CD19: 0 | CE19: 0 | CF19: 0 | CG19: 0 | CH19: 0 | CI19: 0 | CJ19: 0 | CK19: 0 | CL19: 0 | CM19: 0 | CN19: 0 | CO19: 0 | CP19: 0 | CQ19: 0 | CR19: 0 | CS19: 0 | CT19: 0 | CU19: 0 | CV19: 0 | CW19: 0 | CX19: 0 | CY19: 0 | CZ19: 0 | DA19: 0 | DB19: 0 | DC19: 0 | DD19: 0 | DE19: 0 | DF19: 0 | DG19: 0 | DH19: 0 | DI19: 0 | DJ19: 0 | DK19: 0 | DL19: 0 | DM19: 0 | DN19: 0 | DO19: 0 | DP19: 0 | DQ19: 0 | DR19: 0 | DS19: 0 | DT19: 0 | DU19: 0 | DV19: 0 | DW19: 0 | DX19: 0 | DY19: 0
A20: target_opm | D20: 타겟 OPM(코호트) | AI20: 0.108 | AJ20: 0.108 | AK20: 0.108 | AL20: 0.108 | AM20: 0.108 | AN20: 0.108 | AO20: 0.108 | AP20: 0.108 | AQ20: 0.108 | AR20: 0.108 | AS20: 0.108 | AT20: 0.108 | AU20: 0.108 | AV20: 0.108 | AW20: 0.108
A22: 선표 연결(수식) — 원화(백만원) = 스케줄(백만$) × 포함 × (1 + (캡배율 − 1) × origin 이후) × (헤지비율 × 헤지환율 + (1 − 헤지비율) × 건조시점 환율) | J22: subQ 매출조선 = 합계/100 + 변수 잔고 소진 + 매출조선신규
A23: 헤지비율 | D23: =변수!$D$59 | E23: 변수 3절 '헤지비율' 참조 — 통화선도 공시 없음 → HEDGE 70% 가정(레퍼런스 SLS 시트 HEDGE 행은 미포 65%·삼성重 100% — 그 사이에 둔 설정값). hedge_rate 는 계약별 수주시점 환율로 대체
A24: 헤지환율 방식 | D24: 계약별 수주시점 환율(fx_at_sign)
A25: spot_krw | D25: 건조시점 원/달러(평균) — 변수 환율 행 참조, 변수 범위 밖 분기는 sls spot_assumed | E25: =IFERROR(VLOOKUP(" 원/달러(평균)",환율,MATCH(E$1,변수H,0),0),1080.48) | F25: =IFERROR(VLOOKUP(" 원/달러(평균)",환율,MATCH(F$1,변수H,0),0),1121.86) | G25: =IFERROR(VLOOKUP(" 원/달러(평균)",환율,MATCH(G$1,변수H,0),0),1127.53) | H25: =IFERROR(VLOOKUP(" 원/달러(평균)",환율,MATCH(H$1,변수H,0),0),1125.78) | I25: =IFERROR(VLOOKUP(" 원/달러(평균)",환율,MATCH(I$1,변수H,0),0),1167.69) | J25: =IFERROR(VLOOKUP(" 원/달러(평균)",환율,MATCH(J$1,변수H,0),0),1193.96) | K25: =IFERROR(VLOOKUP(" 원/달러(평균)",환율,MATCH(K$1,변수H,0),0),1176.23) | L25: =IFERROR(VLOOKUP(" 원/달러(평균)",환율,MATCH(L$1,변수H,0),0),1193.92) | M25: =IFERROR(VLOOKUP(" 원/달러(평균)",환율,MATCH(M$1,변수H,0),0),1219.69) | N25: =IFERROR(VLOOKUP(" 원/달러(평균)",환율,MATCH(N$1,변수H,0),0),1187.81) | O25: =IFERROR(VLOOKUP(" 원/달러(평균)",환율,MATCH(O$1,변수H,0),0),1117.97) | P25: =IFERROR(VLOOKUP(" 원/달러(평균)",환율,MATCH(P$1,변수H,0),0),1114.99) | Q25: =IFERROR(VLOOKUP(" 원/달러(평균)",환율,MATCH(Q$1,변수H,0),0),1121.13) | R25: =IFERROR(VLOOKUP(" 원/달러(평균)",환율,MATCH(R$1,변수H,0),0),1159.91) | S25: =IFERROR(VLOOKUP(" 원/달러(평균)",환율,MATCH(S$1,변수H,0),0),1183.5) | T25: =IFERROR(VLOOKUP(" 원/달러(평균)",환율,MATCH(T$1,변수H,0),0),1205.78) | U25: =IFERROR(VLOOKUP(" 원/달러(평균)",환율,MATCH(U$1,변수H,0),0),1262.09) | V25: =IFERROR(VLOOKUP(" 원/달러(평균)",환율,MATCH(V$1,변수H,0),0),1341.93) | W25: =IFERROR(VLOOKUP(" 원/달러(평균)",환율,MATCH(W$1,변수H,0),0),1360.12) | X25: =IFERROR(VLOOKUP(" 원/달러(평균)",환율,MATCH(X$1,변수H,0),0),1276.95) | Y25: =IFERROR(VLOOKUP(" 원/달러(평균)",환율,MATCH(Y$1,변수H,0),0),1315.69) | Z25: =IFERROR(VLOOKUP(" 원/달러(평균)",환율,MATCH(Z$1,변수H,0),0),1313.62) | AA25: =IFERROR(VLOOKUP(" 원/달러(평균)",환율,MATCH(AA$1,변수H,0),0),1322.01) | AB25: =IFERROR(VLOOKUP(" 원/달러(평균)",환율,MATCH(AB$1,변수H,0),0),1330.14) | AC25: =IFERROR(VLOOKUP(" 원/달러(평균)",환율,MATCH(AC$1,변수H,0),0),1371.28) | AD25: =IFERROR(VLOOKUP(" 원/달러(평균)",환율,MATCH(AD$1,변수H,0),0),1356.22) | AE25: =IFERROR(VLOOKUP(" 원/달러(평균)",환율,MATCH(AE$1,변수H,0),0),1396.3) | AF25: =IFERROR(VLOOKUP(" 원/달러(평균)",환율,MATCH(AF$1,변수H,0),0),1452.28) | AG25: =IFERROR(VLOOKUP(" 원/달러(평균)",환율,MATCH(AG$1,변수H,0),0),1398.52) | AH25: =IFERROR(VLOOKUP(" 원/달러(평균)",환율,MATCH(AH$1,변수H,0),0),1386.95) | AI25: =IFERROR(VLOOKUP(" 원/달러(평균)",환율,MATCH(AI$1,변수H,0),0),1449.19) | AJ25: =IFERROR(VLOOKUP(" 원/달러(평균)",환율,MATCH(AJ$1,변수H,0),0),1466.12) | AK25: =IFERROR(VLOOKUP(" 원/달러(평균)",환율,MATCH(AK$1,변수H,0),0),1501.75) | AL25: =IFERROR(VLOOKUP(" 원/달러(평균)",환율,MATCH(AL$1,변수H,0),0),1418.75) | AM25: =IFERROR(VLOOKUP(" 원/달러(평균)",환율,MATCH(AM$1,변수H,0),0),1343.39) | AN25: =IFERROR(VLOOKUP(" 원/달러(평균)",환율,MATCH(AN$1,변수H,0),0),1341.45) | AO25: =IFERROR(VLOOKUP(" 원/달러(평균)",환율,MATCH(AO$1,변수H,0),0),1341.45) | AP25: =IFERROR(VLOOKUP(" 원/달러(평균)",환율,MATCH(AP$1,변수H,0),0),1341.45) | AQ25: =IFERROR(VLOOKUP(" 원/달러(평균)",환율,MATCH(AQ$1,변수H,0),0),1341.45) | AR25: =IFERROR(VLOOKUP(" 원/달러(평균)",환율,MATCH(AR$1,변수H,0),0),1341.45) | AS25: =IFERROR(VLOOKUP(" 원/달러(평균)",환율,MATCH(AS$1,변수H,0),0),1341.45) | AT25: =IFERROR(VLOOKUP(" 원/달러(평균)",환율,MATCH(AT$1,변수H,0),0),1341.45) | AU25: =IFERROR(VLOOKUP(" 원/달러(평균)",환율,MATCH(AU$1,변수H,0),0),1341.45) | ... DY25: =IFERROR(VLOOKUP(" 원/달러(평균)",환율,MATCH(DY$1,변수H,0),0),1341.45)
A26: after_origin | D26: origin(2026Q2) 이후 분기 = 1 (잔고 캡 배율 적용 구간) | E26: 0 | F26: 0 | G26: 0 | H26: 0 | I26: 0 | J26: 0 | K26: 0 | L26: 0 | M26: 0 | N26: 0 | O26: 0 | P26: 0 | Q26: 0 | R26: 0 | S26: 0 | T26: 0 | U26: 0 | V26: 0 | W26: 0 | X26: 0 | Y26: 0 | Z26: 0 | AA26: 0 | AB26: 0 | AC26: 0 | AD26: 0 | AE26: 0 | AF26: 0 | AG26: 0 | AH26: 0 | AI26: 0 | AJ26: 0 | AK26: 0 | AL26: 1 | AM26: 1 | AN26: 1 | AO26: 1 | AP26: 1 | AQ26: 1 | AR26: 1 | AS26: 1 | AT26: 1 | AU26: 1 | AV26: 1 | AW26: 1 | AX26: 1 | AY26: 1 | AZ26: 1 | BA26: 1 | BB26: 1 | BC26: 1 | BD26: 1 | BE26: 1 | BF26: 1 | BG26: 1 | BH26: 1 | BI26: 1 | BJ26: 1 | BK26: 1 | BL26: 1 | BM26: 1 | BN26: 1 | BO26: 1 | BP26: 1 | BQ26: 1 | BR26: 1 | BS26: 1 | BT26: 1 | BU26: 1 | BV26: 1 | BW26: 1 | BX26: 1 | BY26: 1 | BZ26: 1 | CA26: 1 | CB26: 1 | CC26: 1 | CD26: 1 | CE26: 1 | CF26: 1 | CG26: 1 | CH26: 1 | CI26: 1 | CJ26: 1 | CK26: 1 | CL26: 1 | CM26: 1 | CN26: 1 | CO26: 1 | CP26: 1 | CQ26: 1 | CR26: 1 | CS26: 1 | CT26: 1 | CU26: 1 | CV26: 1 | CW26: 1 | CX26: 1 | CY26: 1 | CZ26: 1 | DA26: 1 | DB26: 1 | DC26: 1 | DD26: 1 | DE26: 1 | DF26: 1 | DG26: 1 | DH26: 1 | DI26: 1 | DJ26: 1 | DK26: 1 | DL26: 1 | DM26: 1 | DN26: 1 | DO26: 1 | DP26: 1 | DQ26: 1 | DR26: 1 | DS26: 1 | DT26: 1 | DU26: 1 | DV26: 1 | DW26: 1 | DX26: 1 | DY26: 1
A28: ① 계약별 매출인식 스케줄(백만$, sls 저장값) | B28: type | C28: ships | D28: name | FG28: 포함(1/0) | FH28: 헤지환율 | FI28: 캡배율 | FJ28: 체결일 | FK28: origin이내 | FL28: 코호트 | FM28: 계약액(백만$) | FN28: 종료
A29: 20250930800101 | B29: OTHER | D29: 대전 도마변동9재정비촉진구역 주택재개발정비사업 | R29: 2.988 | S29: 3.715 | T29: 3.634 | U29: 3.675 | V29: 3.715 | W29: 3.715 | X29: 3.634 | Y29: 3.675 | Z29: 3.715 | AA29: 3.715 | AB29: 3.675 | AC29: 3.675 | AD29: 3.715 | AE29: 3.715 | AF29: 3.634 | AG29: 3.675 | AH29: 3.715 | AI29: 3.715 | AJ29: 3.634 | AK29: 3.675 | AL29: 3.715 | AM29: 3.715 | AN29: 2.911 | FG29: 0 | FH29: 1159.91 | FI29: 1 | FJ29: 2021-07-19 | FK29: 1 | FM29: 83.35 | FN29: 2027-03-13
A30: 20251103800145 | B30: OTHER | D30: 부천 역곡동 46번지 일원 가로주택정비사업 공사 | Y30: 2.162 | Z30: 3.108 | AA30: 3.108 | AB30: 3.074 | AC30: 3.074 | AD30: 3.108 | AE30: 3.108 | AF30: 3.04 | AG30: 3.074 | AH30: 3.108 | AI30: 3.108 | AJ30: 3.04 | AK30: 3.074 | AL30: 3.108 | AM30: 3.108 | AN30: 3.04 | AO30: 3.074 | AP30: 3.108 | AQ30: 0.706 | FG30: 0 | FH30: 1315.69 | FI30: 1 | FJ30: 2023-04-28 | FK30: 1 | FM30: 55.33 | FN30: 2027-10-21
A31: 20251110800052 | B31: OTHER | D31: 부산공동어시장 현대화사업 | AI31: 1.862 | AJ31: 3.162 | AK31: 3.198 | AL31: 3.233 | AM31: 3.233 | AN31: 3.162 | AO31: 3.198 | AP31: 3.233 | AQ31: 3.233 | AR31: 3.198 | AS31: 3.198 | AT31: 3.233 | AU31: 3.233 | AV31: 3.162 | AW31: 3.198 | AX31: 3.233 | AY31: 1.684 | FG31: 0 | FH31: 1449.19 | FI31: 1 | FJ31: 2025-11-09 | FK31: 1 | FM31: 51.653 | FN31: 2029-11-17
A32: 20251126800540 | B32: OTHER | D32: 합동해안양륙군수지원(JLOTS)체계 상세설계 및 함건조 | W32: 0.744 | X32: 6.697 | Y32: 6.772 | Z32: 6.846 | AA32: 6.846 | AB32: 6.772 | AC32: 6.772 | AD32: 6.846 | AE32: 6.846 | AF32: 6.697 | AG32: 6.772 | AH32: 6.846 | AI32: 6.846 | AJ32: 6.697 | AK32: 6.772 | AL32: 6.846 | AM32: 6.846 | AN32: 6.697 | AO32: 4.541 | FG32: 0 | FH32: 1360.12 | FI32: 1 | FJ32: 2022-12-22 | FK32: 1 | FM32: 120.701 | FN32: 2027-05-31
A33: 20251127800440 | B33: OTHER | D33: 과천갈현A-1BL 및 의왕군포안산 A1-3BL 민간참여 공공주택건설사업 | AI33: 1.427 | AJ33: 3.568 | AK33: 3.608 | AL33: 3.648 | AM33: 3.648 | AN33: 3.568 | AO33: 3.608 | AP33: 3.648 | AQ33: 3.648 | AR33: 3.608 | AS33: 3.608 | AT33: 3.648 | AU33: 3.648 | AV33: 3.568 | AW33: 3.608 | AX33: 3.648 | AY33: 3.648 | AZ33: 3.568 | BA33: 3.608 | BB33: 3.648 | BC33: 3.648 | BD33: 3.568 | BE33: 3.608 | BF33: 3.648 | BG33: 3.648 | BH33: 3.608 | BI33: 3.608 | BJ33: 3.648 | BK33: 3.648 | BL33: 3.568 | BM33: 3.608 | BN33: 3.648 | BO33: 3.648 | BP33: 3.568 | BQ33: 1.182 | FG33: 0 | FH33: 1449.19 | FI33: 1 | FJ33: 2025-11-26 | FK33: 1 | FM33: 122.033 | FN33: 2034-04-30
A34: 20251127800601 | B34: OTHER | D34: 평택지역 전기공급시설 전력구공사(신평택-고덕#3) 1공구 | AI34: 2.738 | AJ34: 7.04 | AK34: 7.119 | AL34: 7.197 | AM34: 7.197 | AN34: 7.04 | AO34: 7.119 | AP34: 7.197 | AQ34: 7.197 | AR34: 7.119 | AS34: 7.119 | AT34: 7.197 | AU34: 7.197 | AV34: 7.04 | AW34: 7.119 | AX34: 7.197 | AY34: 6.727 | FG34: 0 | FH34: 1449.19 | FI34: 1 | FJ34: 2025-11-27 | FK34: 1 | FM34: 116.559 | FN34: 2029-12-25
A35: 20251205800202 | B35: OTHER | D35: 엄궁대교 건설공사 | AE35: 0.497 | AF35: 3.197 | AG35: 3.233 | AH35: 3.268 | AI35: 3.268 | AJ35: 3.197 | AK35: 3.233 | AL35: 3.268 | AM35: 3.268 | AN35: 3.197 | AO35: 3.233 | AP35: 3.268 | AQ35: 3.268 | AR35: 3.233 | AS35: 3.233 | AT35: 3.268 | AU35: 3.268 | AV35: 3.197 | AW35: 3.233 | AX35: 3.268 | AY35: 3.268 | AZ35: 0.567 | FG35: 0 | FH35: 1396.3 | FI35: 1 | FJ35: 2024-12-18 | FK35: 1 | FM35: 65.93 | FN35: 2030-01-16
A36: 20251217800479 | B36: NAVAL | D36: 검독수리 Batch-II 후속함(13~16번함) | AI36: 2.286 | AJ36: 13.719 | AK36: 13.871 | AL36: 14.024 | AM36: 14.024 | AN36: 13.719 | AO36: 13.871 | AP36: 14.024 | AQ36: 14.024 | AR36: 13.871 | AS36: 13.871 | AT36: 14.024 | AU36: 14.024 | AV36: 13.719 | AW36: 13.871 | AX36: 14.024 | AY36: 4.724 | FG36: 1 | FH36: 1449.19 | FI36: 1 | FJ36: 2025-12-17 | FK36: 1 | FM36: 215.69 | FN36: 2029-10-31
A37: 20251222800631 | B37: OTHER | D37: 고속국도 제292호선 오송지선 건설공사 | K37: 0.268 | L37: 4.885 | M37: 4.885 | N37: 4.938 | O37: 4.938 | P37: 4.831 | Q37: 4.885 | R37: 4.938 | S37: 4.938 | T37: 4.831 | U37: 4.885 | V37: 4.938 | W37: 4.938 | X37: 4.831 | Y37: 4.885 | Z37: 4.938 | AA37: 4.938 | AB37: 4.885 | AC37: 4.885 | AD37: 4.938 | AE37: 4.938 | AF37: 4.831 | AG37: 4.885 | AH37: 4.938 | AI37: 4.938 | AJ37: 4.831 | AK37: 4.885 | AL37: 4.938 | AM37: 4.936 | FG37: 0 | FH37: 1176.23 | FI37: 1 | FJ37: 2019-12-27 | FK37: 1 | FM37: 137.518 | FN37: 2026-12-31
A38: 20251224800003 | B38: NAVAL | C38: 1 | D38: (선박) 다목적 화학방제함 1척 건조 | AI38: 0.396 | AJ38: 3.956 | AK38: 4 | AL38: 4.044 | AM38: 4.044 | AN38: 3.956 | AO38: 4 | AP38: 4.044 | AQ38: 4.044 | AR38: 4 | AS38: 4 | AT38: 4.044 | AU38: 2.987 | FG38: 1 | FH38: 1449.19 | FI38: 1 | FJ38: 2025-12-23 | FK38: 1 | FL38: ⑤초호황 | FM38: 47.515 | FN38: 2028-12-07
A39: 20251224800596 | B39: OTHER | D39: 고속국도 제50호 영동선 안산-북수원간 확장(개량)공사(제2공구) | Q39: 4.67 | R39: 6.929 | S39: 6.929 | T39: 6.779 | U39: 6.854 | V39: 6.929 | W39: 6.929 | X39: 6.779 | Y39: 6.854 | Z39: 6.929 | AA39: 6.929 | AB39: 6.854 | AC39: 6.854 | AD39: 6.929 | AE39: 6.929 | AF39: 6.779 | AG39: 6.854 | AH39: 6.929 | AI39: 6.929 | AJ39: 6.779 | AK39: 6.854 | AL39: 6.929 | AM39: 6.929 | AN39: 6.779 | AO39: 0.23 | FG39: 0 | FH39: 1114.99 | FI39: 1 | FJ39: 2021-02-18 | FK39: 1 | FM39: 163.067 | FN39: 2027-04-03
A40: 20251231800507 | B40: OTHER | D40: 인천국제공항 제2여객터미널 확장 골조 및 마감공사(서편) | O40: 5.099 | P40: 15.823 | Q40: 15.999 | R40: 16.175 | S40: 16.175 | T40: 15.823 | U40: 15.999 | V40: 16.175 | W40: 16.175 | X40: 15.823 | Y40: 15.999 | Z40: 16.175 | AA40: 16.175 | AB40: 15.999 | AC40: 15.999 | AD40: 16.175 | AE40: 16.175 | AF40: 15.823 | AG40: 15.999 | AH40: 16.175 | AI40: 16.175 | AJ40: 15.824 | FG40: 0 | FH40: 1117.97 | FI40: 1 | FJ40: 2020-12-03 | FK40: 1 | FM40: 341.959 | FN40: 2026-03-31
A41: 20251231800547 | B41: OTHER | D41: 킨텍스 제3전시장 건립공사 | AF41: 0.868 | AG41: 2.725 | AH41: 2.755 | AI41: 2.755 | AJ41: 2.695 | AK41: 2.725 | AL41: 2.755 | AM41: 2.755 | AN41: 2.695 | AO41: 2.725 | AP41: 2.755 | AQ41: 2.755 | AR41: 2.725 | AS41: 2.725 | AT41: 2.181 | FG41: 0 | FH41: 1449.19 | FI41: 1 | FJ41: 2025-12-31 | FK41: 1 | FM41: 38.594 | FN41: 2028-09-11
A42: 20260107800221 | B42: OTHER | D42: 대전 삼성6구역 재개발정비사업 공사 | AJ42: 4.12 | AK42: 4.463 | AL42: 4.512 | AM42: 4.512 | AN42: 4.414 | AO42: 4.463 | AP42: 4.512 | AQ42: 4.512 | AR42: 4.463 | AS42: 4.463 | AT42: 4.512 | AU42: 4.512 | AV42: 4.414 | AW42: 4.463 | AX42: 4.512 | AY42: 4.512 | AZ42: 4.414 | BA42: 4.463 | BB42: 0.099 | FG42: 0 | FH42: 1466.12 | FI42: 1 | FJ42: 2026-01-07 | FK42: 1 | FM42: 80.335 | FN42: 2030-07-02
A43: 20260116800164 | B43: OTHER | D43: 여수 천연가스발전소 건설공사 | AJ43: 7.9 | AK43: 9.586 | AL43: 9.691 | AM43: 9.691 | AN43: 9.481 | AO43: 9.586 | AP43: 9.691 | AQ43: 9.691 | AR43: 9.586 | AS43: 9.586 | AT43: 9.691 | AU43: 9.691 | AV43: 9.481 | AW43: 3.055 | FG43: 0 | FH43: 1466.12 | FI43: 1 | FJ43: 2026-01-16 | FK43: 1 | FM43: 126.407 | FN43: 2029-04-29
A44: 20260120800250 | B44: OTHER | D44: 포항 대잠동 행복아파트2단지 소규모재건축사업 공사 | X44: 1.005 | Y44: 3.657 | Z44: 3.698 | AA44: 3.698 | AB44: 3.658 | AC44: 3.657 | AD44: 3.698 | AE44: 3.698 | AF44: 3.617 | AG44: 3.658 | AH44: 3.698 | AI44: 3.698 | AJ44: 3.617 | AK44: 3.658 | AL44: 3.698 | AM44: 3.698 | AN44: 3.617 | AO44: 3.658 | AP44: 2.449 | FG44: 0 | FH44: 1276.95 | FI44: 1 | FJ44: 2023-03-07 | FK44: 1 | FM44: 65.835 | FN44: 2027-08-30
A45: 20260211800125 | B45: CONT | C45: 2 | D45: 컨테이너선 2척 수주 | AJ45: 13.816 | AK45: 25.145 | AL45: 25.422 | AM45: 25.422 | AN45: 24.869 | AO45: 25.145 | AP45: 25.422 | AQ45: 25.422 | AR45: 25.145 | AS45: 25.145 | FG45: 1 | FH45: 1466.12 | FI45: 1 | FJ45: 2026-02-10 | FK45: 1 | FL45: ⑤초호황 | FM45: 240.953 | FN45: 2028-06-30
A46: 20260227801603 | B46: OTHER | D46: 수도권광역급행철도A노선 민간투자시설사업 건설공사 | H46: 0.7 | I46: 5.312 | J46: 5.37 | K46: 5.37 | L46: 5.312 | M46: 5.312 | N46: 5.37 | O46: 5.37 | P46: 5.253 | Q46: 5.312 | R46: 5.37 | S46: 5.37 | T46: 5.253 | U46: 5.312 | V46: 5.37 | W46: 5.37 | X46: 5.253 | Y46: 5.312 | Z46: 5.37 | AA46: 5.37 | AB46: 5.312 | AC46: 5.312 | AD46: 5.37 | AE46: 5.37 | AF46: 5.253 | AG46: 5.312 | AH46: 5.37 | AI46: 5.37 | AJ46: 5.253 | AK46: 5.312 | AL46: 5.37 | AM46: 5.37 | AN46: 5.253 | AO46: 5.312 | AP46: 5.37 | AQ46: 5.37 | AR46: 5.312 | AS46: 1.749 | FG46: 0 | FH46: 1125.78 | FI46: 1 | FJ46: 2019-03-20 | FK46: 1 | FM46: 194.371 | FN46: 2028-04-30
A47: 20260227801809 | B47: OTHER | D47: 광교 A17블록 및 교산 A1블록 민간참여 공공주택건설사업 | AJ47: 0.216 | AK47: 0.596 | AL47: 0.602 | AM47: 0.602 | AN47: 0.589 | AO47: 0.596 | AP47: 0.602 | AQ47: 0.602 | AR47: 0.596 | AS47: 0.596 | AT47: 0.602 | AU47: 0.602 | AV47: 0.589 | AW47: 0.596 | AX47: 0.602 | AY47: 0.602 | AZ47: 0.589 | BA47: 0.596 | BB47: 0.602 | BC47: 0.602 | BD47: 0.589 | BE47: 0.596 | BF47: 0.602 | BG47: 0.602 | BH47: 0.596 | BI47: 0.596 | BJ47: 0.602 | BK47: 0.602 | BL47: 0.589 | BM47: 0.596 | BN47: 0.602 | BO47: 0.602 | BP47: 0.589 | BQ47: 0.596 | BR47: 0.602 | BS47: 0.602 | BT47: 0.589 | BU47: 0.596 | BV47: 0.602 | BW47: 0.602 | BX47: 0.596 | BY47: 0.596 | BZ47: 0.602 | CA47: 0.602 | CB47: 0.589 | CC47: 0.596 | CD47: 0.602 | CE47: 0.602 | CF47: 0.589 | CG47: 0.596 | CH47: 0.602 | CI47: 0.602 | CJ47: 0.589 | CK47: 0.596 | CL47: 0.602 | CM47: 0.602 | CN47: 0.596 | CO47: 0.596 | CP47: 0.602 | CQ47: 0.602 | CR47: 0.589 | CS47: 0.596 | CT47: 0.602 | CU47: 0.602 | CV47: 0.589 | CW47: 0.596 | CX47: 0.602 | CY47: 0.602 | CZ47: 0.589 | DA47: 0.596 | DB47: 0.602 | DC47: 0.602 | DD47: 0.596 | DE47: 0.596 | DF47: 0.602 | DG47: 0.602 | DH47: 0.589 | DI47: 0.596 | DJ47: 0.602 | DK47: 0.602 | DL47: 0.589 | DM47: 0.596 | DN47: 0.602 | DO47: 0.602 | DP47: 0.589 | DQ47: 0.596 | DR47: 0.602 | DS47: 0.602 | DT47: 0.596 | DU47: 0.596 | DV47: 0.602 | DW47: 0.602 | DX47: 0.589 | DY47: 0.425 | FG47: 0 | FH47: 1466.12 | FI47: 1 | FJ47: 2026-02-27 | FK47: 1 | FM47: 55.63 | FN47: 2049-05-31
A48: 20260304800353 | B48: OTHER | D48: 필리핀 따굼 홍수조절사업 | AJ48: 1.522 | AK48: 3.957 | AL48: 4 | AM48: 4 | AN48: 3.913 | AO48: 3.957 | AP48: 4 | AQ48: 4 | AR48: 3.957 | AS48: 3.957 | AT48: 4 | AU48: 4 | AV48: 3.913 | AW48: 3.957 | AX48: 4 | AY48: 4 | AZ48: 1.783 | FG48: 0 | FH48: 1466.12 | FI48: 1 | FJ48: 2026-02-25 | FK48: 1 | FM48: 62.916 | FN48: 2030-02-10
A49: 20260306800575 | B49: OTHER | D49: 서울 번동 3-2구역 가로주택정비사업 공사 | AJ49: 0.917 | AK49: 3.209 | AL49: 3.244 | AM49: 3.244 | AN49: 3.174 | AO49: 3.209 | AP49: 3.244 | AQ49: 3.244 | AR49: 3.209 | AS49: 3.209 | AT49: 3.244 | AU49: 3.244 | AV49: 3.174 | AW49: 3.209 | AX49: 3.244 | AY49: 3.244 | AZ49: 3.174 | BA49: 3.209 | BB49: 2.113 | FG49: 0 | FH49: 1466.12 | FI49: 1 | FJ49: 2026-03-06 | FK49: 1 | FM49: 57.758 | FN49: 2030-08-29
A50: 20260313800208 | B50: OTHER | D50: 24-F-00부대 유도로 신설 및 활주로 재포장사업(4146) | AG50: 3.204 | AH50: 4.754 | AI50: 4.754 | AJ50: 4.65 | AK50: 4.702 | AL50: 4.754 | AM50: 4.754 | AN50: 4.65 | AO50: 4.702 | AP50: 4.754 | AQ50: 4.754 | AR50: 4.702 | AS50: 4.702 | AT50: 1.136 | FG50: 0 | FH50: 1466.12 | FI50: 1 | FJ50: 2026-03-13 | FK50: 1 | FM50: 60.972 | FN50: 2028-07-22
A51: 20260401800508 | B51: OTHER | D51: 서대신4구역 주택재개발 정비사업 | O51: 6.329 | P51: 8.901 | Q51: 9 | R51: 9.099 | S51: 9.099 | T51: 8.901 | U51: 9 | V51: 9.099 | W51: 9.099 | X51: 8.901 | Y51: 9 | Z51: 9.099 | AA51: 9.099 | AB51: 9 | AC51: 9 | AD51: 9.099 | AE51: 9.099 | AF51: 8.901 | AG51: 2.268 | FG51: 0 | FH51: 1117.97 | FI51: 1 | FJ51: 2020-10-29 | FK51: 1 | FM51: 161.993 | FN51: 2025-04-23
A52: 20260410800253 | B52: OTHER | D52: 부산 범천5구역 재개발정비사업 | AK52: 11.656 | AL52: 13.078 | AM52: 13.078 | AN52: 12.793 | AO52: 12.935 | AP52: 13.078 | AQ52: 13.078 | AR52: 12.935 | AS52: 12.935 | AT52: 13.078 | AU52: 13.078 | AV52: 12.793 | AW52: 12.935 | AX52: 13.078 | AY52: 13.078 | AZ52: 12.793 | BA52: 12.935 | BB52: 13.078 | BC52: 0.425 | FG52: 0 | FH52: 1501.75 | FI52: 1 | FJ52: 2026-04-10 | FK52: 1 | FM52: 232.837 | FN52: 2030-10-03
A53: 20260422800059 | B53: OTHER | D53: 남양주왕숙2 A-6BL 및 A-7BL 통합형 민간참여 공공주택 건설사업 | AK53: 2.917 | AL53: 3.78 | AM53: 3.78 | AN53: 3.698 | AO53: 3.739 | AP53: 3.78 | AQ53: 3.78 | AR53: 3.739 | AS53: 3.739 | AT53: 3.78 | AU53: 3.78 | AV53: 3.698 | AW53: 1.237 | FG53: 0 | FH53: 1501.75 | FI53: 1 | FJ53: 2026-04-21 | FK53: 1 | FM53: 45.447 | FN53: 2029-04-30
A54: 20260423800218 | B54: OTHER | D54: 연산5구역 재개발정비사업 | Y54: 3.057 | Z54: 4.327 | AA54: 4.327 | AB54: 4.28 | AC54: 4.28 | AD54: 4.327 | AE54: 4.327 | AF54: 4.232 | AG54: 4.279 | AH54: 4.327 | AI54: 4.327 | AJ54: 4.232 | AK54: 4.28 | AL54: 4.327 | AM54: 4.327 | AN54: 4.232 | AO54: 4.28 | AP54: 4.327 | AQ54: 0.936 | FG54: 0 | FH54: 1315.69 | FI54: 1 | FJ54: 2023-04-27 | FK54: 1 | FM54: 77.031 | FN54: 2027-10-20
A55: 20260423800721 | B55: OTHER | D55: 부산 대림비치아파트 소규모재건축정비사업 | AB55: 0.152 | AC55: 3.447 | AD55: 3.485 | AE55: 3.485 | AF55: 3.409 | AG55: 3.447 | AH55: 3.485 | AI55: 3.485 | AJ55: 3.409 | AK55: 3.447 | AL55: 3.485 | AM55: 3.485 | AN55: 3.409 | AO55: 3.447 | AP55: 3.485 | AQ55: 3.485 | AR55: 3.447 | AS55: 3.447 | AT55: 3.105 | FG55: 0 | FH55: 1330.14 | FI55: 1 | FJ55: 2024-03-28 | FK55: 1 | FM55: 62.046 | FN55: 2028-09-20
A56: 20260427800078 | B56: CONT | C56: 2 | D56: 컨테이너선 2척 수주 | AK56: 17.542 | AL56: 23.734 | AM56: 23.734 | AN56: 23.218 | AO56: 23.476 | AP56: 23.734 | AQ56: 23.734 | AR56: 23.476 | AS56: 23.476 | AT56: 23.734 | AU56: 7.997 | FG56: 1 | FH56: 1501.75 | FI56: 1 | FJ56: 2026-04-24 | FK56: 1 | FL56: ⑤초호황 | FM56: 237.855 | FN56: 2028-10-31
A57: 20260506800906 | B57: OTHER | D57: 강원지역 전기공급시설 전력구공사 | Z57: 3.058 | AA57: 3.516 | AB57: 3.478 | AC57: 3.478 | AD57: 3.516 | AE57: 3.516 | AF57: 3.44 | AG57: 3.478 | AH57: 3.516 | AI57: 3.516 | AJ57: 3.44 | AK57: 3.478 | AL57: 3.516 | AM57: 3.516 | AN57: 3.44 | AO57: 3.478 | AP57: 3.516 | AQ57: 2.334 | FG57: 0 | FH57: 1315.69 | FI57: 1 | FJ57: 2023-06-23 | FK57: 1 | FM57: 61.23 | FN57: 2027-11-30
A58: 20260518800840 | B58: OTHER | D58: 500kv 동서울변환소 토건공사 | AI58: 0.817 | AJ58: 3.064 | AK58: 3.098 | AL58: 3.132 | AM58: 3.132 | AN58: 3.064 | AO58: 3.098 | AP58: 3.132 | AQ58: 3.132 | AR58: 3.098 | AS58: 3.098 | AT58: 3.132 | AU58: 3.132 | AV58: 3.064 | AW58: 3.098 | AX58: 3.132 | AY58: 3.132 | AZ58: 0.075 | FG58: 0 | FH58: 1449.19 | FI58: 1 | FJ58: 2025-12-08 | FK58: 1 | FM58: 50.63 | FN58: 2030-01-02
A59: 20260520800639 | B59: OTHER | D59: 수서~광주 복선전철 제3공구 건설공사(T/K) | AK59: 0.831 | AL59: 1.821 | AM59: 1.821 | AN59: 1.782 | AO59: 1.801 | AP59: 1.821 | AQ59: 1.821 | AR59: 1.801 | AS59: 1.801 | AT59: 1.821 | AU59: 1.821 | AV59: 1.782 | AW59: 1.801 | AX59: 1.821 | AY59: 1.821 | AZ59: 1.782 | BA59: 1.801 | BB59: 1.821 | BC59: 1.821 | BD59: 1.782 | BE59: 0.994 | FG59: 0 | FH59: 1501.75 | FI59: 1 | FJ59: 2026-05-20 | FK59: 1 | FM59: 36.168 | FN59: 2031-05-20
A60: 20260529800492 | B60: OTHER | D60: 효자·미성·으뜸 가로주택정비사업 | S60: 2.102 | T60: 2.911 | U60: 2.943 | V60: 2.975 | W60: 2.975 | X60: 2.911 | Y60: 2.943 | Z60: 2.975 | AA60: 2.975 | AB60: 2.943 | AC60: 2.943 | AD60: 2.975 | AE60: 2.975 | AF60: 2.911 | AG60: 2.943 | AH60: 2.975 | AI60: 2.975 | AJ60: 2.911 | AK60: 0.714 | FG60: 0 | FH60: 1183.5 | FI60: 1 | FJ60: 2021-10-28 | FK60: 1 | FM60: 52.975 | FN60: 2026-04-22
A61: 20260601800841 | B61: OTHER | D61: 원종동 현대목화아파트 가로주택정비사업 공사 | W61: 0.51 | X61: 2.418 | Y61: 2.445 | Z61: 2.472 | AA61: 2.472 | AB61: 2.445 | AC61: 2.445 | AD61: 2.472 | AE61: 2.472 | AF61: 2.418 | AG61: 2.445 | AH61: 2.472 | AI61: 2.472 | AJ61: 2.418 | AK61: 2.445 | AL61: 2.472 | AM61: 2.472 | AN61: 2.418 | AO61: 1.822 | FG61: 0 | FH61: 1360.12 | FI61: 1 | FJ61: 2022-12-13 | FK61: 1 | FM61: 44.005 | FN61: 2027-06-07
A62: 20260618800458 | B62: OTHER | D62: 부산오페라하우스 건립공사 | E62: 2.933 | F62: 6.133 | G62: 6.133 | H62: 5.999 | I62: 6.066 | J62: 6.133 | K62: 6.133 | L62: 6.066 | M62: 6.066 | N62: 6.133 | O62: 6.133 | P62: 5.999 | Q62: 6.066 | R62: 6.133 | S62: 6.133 | T62: 5.999 | U62: 6.066 | V62: 6.133 | W62: 6.133 | X62: 5.999 | Y62: 6.066 | Z62: 6.133 | AA62: 6.133 | AB62: 6.066 | AC62: 6.066 | AD62: 6.133 | AE62: 6.133 | AF62: 5.999 | AG62: 6.066 | AH62: 6.133 | AI62: 6.133 | AJ62: 5.999 | AK62: 6.066 | AL62: 6.133 | AM62: 6.13 | FG62: 0 | FH62: 1080.48 | FI62: 1 | FJ62: 2018-05-18 | FK62: 1 | FM62: 209.978 | FN62: 2026-12-31
A63: 20260629801171 | B63: OTHER | D63: 식만-사상간(대저대교) 도로건설공사 | P63: 1.586 | Q63: 1.805 | R63: 1.824 | S63: 1.824 | T63: 1.785 | U63: 1.805 | V63: 1.824 | W63: 1.824 | X63: 1.785 | Y63: 1.805 | Z63: 1.824 | AA63: 1.824 | AB63: 1.805 | AC63: 1.805 | AD63: 1.824 | AE63: 1.824 | AF63: 1.785 | AG63: 1.805 | AH63: 1.824 | AI63: 1.824 | AJ63: 1.785 | AK63: 1.805 | AL63: 1.824 | AM63: 1.824 | AN63: 1.785 | AO63: 1.805 | AP63: 1.824 | AQ63: 1.824 | AR63: 1.805 | AS63: 1.805 | AT63: 1.824 | AU63: 1.824 | AV63: 1.785 | AW63: 1.805 | AX63: 1.824 | AY63: 1.824 | AZ63: 1.785 | BA63: 1.805 | BB63: 1.824 | BC63: 1.824 | BD63: 0.278 | FG63: 0 | FH63: 1117.97 | FI63: 1 | FJ63: 2020-12-30 | FK63: 1 | FM63: 72.499 | FN63: 2031-01-14
A64: 20260630800457 | B64: OTHER | D64: 춘천~속초 철도건설 제1공구 노반공사 | V64: 1.201 | W64: 4.249 | X64: 4.157 | Y64: 4.203 | Z64: 4.249 | AA64: 4.249 | AB64: 4.203 | AC64: 4.203 | AD64: 4.249 | AE64: 4.249 | AF64: 4.157 | AG64: 4.203 | AH64: 4.249 | AI64: 4.249 | AJ64: 4.157 | AK64: 4.203 | AL64: 4.249 | AM64: 4.249 | AN64: 4.157 | AO64: 4.203 | AP64: 4.249 | AQ64: 4.249 | AR64: 2.777 | FG64: 0 | FH64: 1341.93 | FI64: 1 | FJ64: 2022-09-05 | FK64: 1 | FM64: 92.563 | FN64: 2028-02-29
A65: 20260630800913 | B65: OTHER | D65: 제천~영월간 고속국도 건설공사(제3공구) | AK65: 0.047 | AL65: 4.3 | AM65: 4.3 | AN65: 4.206 | AO65: 4.253 | AP65: 4.3 | AQ65: 4.3 | AR65: 4.253 | AS65: 4.253 | AT65: 4.3 | AU65: 4.3 | AV65: 4.206 | AW65: 4.253 | AX65: 4.3 | AY65: 4.3 | AZ65: 4.206 | BA65: 4.253 | BB65: 4.3 | BC65: 4.3 | BD65: 4.206 | BE65: 4.253 | BF65: 4.3 | BG65: 4.3 | BH65: 4.253 | BI65: 0.836 | FG65: 0 | FH65: 1501.75 | FI65: 1 | FJ65: 2026-06-30 | FK65: 1 | FM65: 99.078 | FN65: 2032-04-18
A66: 20260721800175 | B66: OTHER | D66: 익산 영등주공1단지 주택재건축정비사업 | Z66: 7.573 | AA66: 8.008 | AB66: 7.921 | AC66: 7.921 | AD66: 8.008 | AE66: 8.008 | AF66: 7.834 | AG66: 7.921 | AH66: 8.008 | AI66: 8.008 | AJ66: 7.834 | AK66: 7.921 | AL66: 8.008 | AM66: 8.008 | AN66: 7.834 | AO66: 7.921 | AP66: 8.008 | AQ66: 7.832 | FG66: 0 | FH66: 1313.62 | FI66: 1 | FJ66: 2023-07-06 | FK66: 1 | FM66: 142.576 | FN66: 2027-12-29
A67: 20260805800532 | B67: OTHER | D67: 평택동부 고속화도로 민간투자사업 공사도급계약 | I67: 0.997 | J67: 2.958 | K67: 2.958 | L67: 2.926 | M67: 2.926 | N67: 2.958 | O67: 2.958 | P67: 2.894 | Q67: 2.926 | R67: 2.958 | S67: 2.958 | T67: 2.894 | U67: 2.926 | V67: 2.958 | W67: 2.958 | X67: 2.894 | Y67: 2.926 | Z67: 2.958 | AA67: 2.958 | AB67: 2.926 | AC67: 2.926 | AD67: 2.958 | AE67: 2.958 | AF67: 2.894 | AG67: 2.926 | AH67: 2.958 | AI67: 2.958 | AJ67: 2.894 | AK67: 2.926 | AL67: 2.958 | AM67: 2.958 | AN67: 2.894 | AO67: 2.255 | FG67: 0 | FH67: 1167.69 | FI67: 1 | FJ67: 2019-05-31 | FK67: 1 | FM67: 94.278 | FN67: 2027-06-09
A68: 20260811800408 | B68: OTHER | D68: 통일로 우회도로 건설공사 | AC68: 2.368 | AD68: 2.504 | AE68: 2.504 | AF68: 2.449 | AG68: 2.477 | AH68: 2.504 | AI68: 2.504 | AJ68: 2.449 | AK68: 2.477 | AL68: 2.504 | AM68: 2.504 | AN68: 2.449 | AO68: 2.477 | AP68: 2.504 | AQ68: 2.504 | AR68: 2.477 | AS68: 2.477 | AT68: 2.504 | AU68: 2.504 | AV68: 2.449 | AW68: 2.477 | AX68: 2.504 | AY68: 0.107 | FG68: 0 | FH68: 1330.14 | FI68: 1 | FJ68: 2024-03-08 | FK68: 1 | FM68: 54.677 | FN68: 2029-10-04
A69: 20260818800047 | B69: OTHER | D69: 국도46호선 남양주-춘천(제2경춘국도) 도로건설공사(제4공구) | AL69: 1.373 | AM69: 2.632 | AN69: 2.574 | AO69: 2.603 | AP69: 2.632 | AQ69: 2.632 | AR69: 2.603 | AS69: 2.603 | AT69: 2.632 | AU69: 2.632 | AV69: 2.574 | AW69: 2.603 | AX69: 2.632 | AY69: 2.632 | AZ69: 2.574 | BA69: 2.603 | BB69: 2.632 | BC69: 2.632 | BD69: 2.574 | BE69: 2.603 | BF69: 2.632 | BG69: 2.632 | BH69: 2.603 | BI69: 2.603 | BJ69: 2.632 | BK69: 2.632 | BL69: 2.574 | BM69: 2.603 | BN69: 1.713 | FG69: 0 | FH69: 1418.75 | FI69: 1 | FJ69: 2026-08-14 | FK69: 0 | FM69: 73.599 | FN69: 2033-08-29
A70: 20260820800160 | B70: OTHER | D70: 500kV 신가평변환소 토건공사 | Z70: 2.827 | AA70: 4.817 | AB70: 4.764 | AC70: 4.764 | AD70: 4.817 | AE70: 4.817 | AF70: 4.712 | AG70: 4.764 | AH70: 4.817 | AI70: 4.817 | AJ70: 4.712 | AK70: 4.764 | AL70: 4.817 | AM70: 4.817 | FG70: 0 | FH70: 1313.62 | FI70: 1 | FJ70: 2023-08-08 | FK70: 1 | FM70: 65.026 | FN70: 2026-12-31
A71: 20260918800109 | B71: OTHER | D71: 울산기력 4,5,6호기 해체공사(종합심사낙찰제) | AB71: 1.268 | AC71: 2.509 | AD71: 2.537 | AE71: 2.537 | AF71: 2.481 | AG71: 2.509 | AH71: 2.537 | AI71: 2.537 | AJ71: 2.481 | AK71: 2.509 | AL71: 2.537 | AM71: 2.537 | AN71: 2.481 | AO71: 2.509 | AP71: 2.537 | AQ71: 2.537 | AR71: 2.509 | AS71: 2.509 | AT71: 1.1 | FG71: 0 | FH71: 1330.14 | FI71: 1 | FJ71: 2024-01-10 | FK71: 1 | FM71: 45.161 | FN71: 2028-08-09
A72: 20260922800008 | B72: CONT | C72: 4 | D72: 컨테이너선 4척 수주 | AL72: 5.022 | AM72: 46.2 | AN72: 45.195 | AO72: 45.697 | AP72: 46.2 | AQ72: 46.2 | AR72: 45.697 | AS72: 45.697 | AT72: 46.2 | AU72: 46.2 | AV72: 45.195 | AW72: 15.064 | FG72: 0 | FH72: 1418.75 | FI72: 1 | FJ72: 2026-09-21 | FK72: 0 | FL72: ⑤초호황 | FM72: 478.567 | FN72: 2029-04-30
A73: 20261007800209 | B73: OTHER | D73: 보령신복합 1호기 건설공사 | Z73: 2 | AA73: 14.157 | AB73: 14.003 | AC73: 14.003 | AD73: 14.157 | AE73: 14.157 | AF73: 13.849 | AG73: 14.003 | AH73: 14.157 | AI73: 14.157 | AJ73: 13.849 | AK73: 14.003 | AL73: 14.157 | AM73: 14.157 | AN73: 13.845 | FG73: 0 | FH73: 1313.62 | FI73: 1 | FJ73: 2023-09-18 | FK73: 1 | FM73: 198.654 | FN73: 2027-03-31
A75: ② 계약별 원화(백만원, 수식) | B75: type | C75: ships | D75: name
A76: 20250930800101 | B76: OTHER | D76: 대전 도마변동9재정비촉진구역 주택재개발정비사업 | R76: =IFERROR(R29*$FG29*(1+($FI29-1)*R$26)*($D$23*$FH29+(1-$D$23)*R$25),"") | S76: =IFERROR(S29*$FG29*(1+($FI29-1)*S$26)*($D$23*$FH29+(1-$D$23)*S$25),"") | T76: =IFERROR(T29*$FG29*(1+($FI29-1)*T$26)*($D$23*$FH29+(1-$D$23)*T$25),"") | U76: =IFERROR(U29*$FG29*(1+($FI29-1)*U$26)*($D$23*$FH29+(1-$D$23)*U$25),"") | V76: =IFERROR(V29*$FG29*(1+($FI29-1)*V$26)*($D$23*$FH29+(1-$D$23)*V$25),"") | W76: =IFERROR(W29*$FG29*(1+($FI29-1)*W$26)*($D$23*$FH29+(1-$D$23)*W$25),"") | X76: =IFERROR(X29*$FG29*(1+($FI29-1)*X$26)*($D$23*$FH29+(1-$D$23)*X$25),"") | Y76: =IFERROR(Y29*$FG29*(1+($FI29-1)*Y$26)*($D$23*$FH29+(1-$D$23)*Y$25),"") | ... AN76: =IFERROR(AN29*$FG29*(1+($FI29-1)*AN$26)*($D$23*$FH29+(1-$D$23)*AN$25),"")
A77: 20251103800145 | B77: OTHER | D77: 부천 역곡동 46번지 일원 가로주택정비사업 공사 | Y77: =IFERROR(Y30*$FG30*(1+($FI30-1)*Y$26)*($D$23*$FH30+(1-$D$23)*Y$25),"") | Z77: =IFERROR(Z30*$FG30*(1+($FI30-1)*Z$26)*($D$23*$FH30+(1-$D$23)*Z$25),"") | AA77: =IFERROR(AA30*$FG30*(1+($FI30-1)*AA$26)*($D$23*$FH30+(1-$D$23)*AA$25),"") | AB77: =IFERROR(AB30*$FG30*(1+($FI30-1)*AB$26)*($D$23*$FH30+(1-$D$23)*AB$25),"") | AC77: =IFERROR(AC30*$FG30*(1+($FI30-1)*AC$26)*($D$23*$FH30+(1-$D$23)*AC$25),"") | AD77: =IFERROR(AD30*$FG30*(1+($FI30-1)*AD$26)*($D$23*$FH30+(1-$D$23)*AD$25),"") | AE77: =IFERROR(AE30*$FG30*(1+($FI30-1)*AE$26)*($D$23*$FH30+(1-$D$23)*AE$25),"") | AF77: =IFERROR(AF30*$FG30*(1+($FI30-1)*AF$26)*($D$23*$FH30+(1-$D$23)*AF$25),"") | ... AQ77: =IFERROR(AQ30*$FG30*(1+($FI30-1)*AQ$26)*($D$23*$FH30+(1-$D$23)*AQ$25),"")
A78: 20251110800052 | B78: OTHER | D78: 부산공동어시장 현대화사업 | AI78: =IFERROR(AI31*$FG31*(1+($FI31-1)*AI$26)*($D$23*$FH31+(1-$D$23)*AI$25),"") | AJ78: =IFERROR(AJ31*$FG31*(1+($FI31-1)*AJ$26)*($D$23*$FH31+(1-$D$23)*AJ$25),"") | AK78: =IFERROR(AK31*$FG31*(1+($FI31-1)*AK$26)*($D$23*$FH31+(1-$D$23)*AK$25),"") | AL78: =IFERROR(AL31*$FG31*(1+($FI31-1)*AL$26)*($D$23*$FH31+(1-$D$23)*AL$25),"") | AM78: =IFERROR(AM31*$FG31*(1+($FI31-1)*AM$26)*($D$23*$FH31+(1-$D$23)*AM$25),"") | AN78: =IFERROR(AN31*$FG31*(1+($FI31-1)*AN$26)*($D$23*$FH31+(1-$D$23)*AN$25),"") | AO78: =IFERROR(AO31*$FG31*(1+($FI31-1)*AO$26)*($D$23*$FH31+(1-$D$23)*AO$25),"") | AP78: =IFERROR(AP31*$FG31*(1+($FI31-1)*AP$26)*($D$23*$FH31+(1-$D$23)*AP$25),"") | ... AY78: =IFERROR(AY31*$FG31*(1+($FI31-1)*AY$26)*($D$23*$FH31+(1-$D$23)*AY$25),"")
A79: 20251126800540 | B79: OTHER | D79: 합동해안양륙군수지원(JLOTS)체계 상세설계 및 함건조 | W79: =IFERROR(W32*$FG32*(1+($FI32-1)*W$26)*($D$23*$FH32+(1-$D$23)*W$25),"") | X79: =IFERROR(X32*$FG32*(1+($FI32-1)*X$26)*($D$23*$FH32+(1-$D$23)*X$25),"") | Y79: =IFERROR(Y32*$FG32*(1+($FI32-1)*Y$26)*($D$23*$FH32+(1-$D$23)*Y$25),"") | Z79: =IFERROR(Z32*$FG32*(1+($FI32-1)*Z$26)*($D$23*$FH32+(1-$D$23)*Z$25),"") | AA79: =IFERROR(AA32*$FG32*(1+($FI32-1)*AA$26)*($D$23*$FH32+(1-$D$23)*AA$25),"") | AB79: =IFERROR(AB32*$FG32*(1+($FI32-1)*AB$26)*($D$23*$FH32+(1-$D$23)*AB$25),"") | AC79: =IFERROR(AC32*$FG32*(1+($FI32-1)*AC$26)*($D$23*$FH32+(1-$D$23)*AC$25),"") | AD79: =IFERROR(AD32*$FG32*(1+($FI32-1)*AD$26)*($D$23*$FH32+(1-$D$23)*AD$25),"") | ... AO79: =IFERROR(AO32*$FG32*(1+($FI32-1)*AO$26)*($D$23*$FH32+(1-$D$23)*AO$25),"")
A80: 20251127800440 | B80: OTHER | D80: 과천갈현A-1BL 및 의왕군포안산 A1-3BL 민간참여 공공주택건설사업 | AI80: =IFERROR(AI33*$FG33*(1+($FI33-1)*AI$26)*($D$23*$FH33+(1-$D$23)*AI$25),"") | AJ80: =IFERROR(AJ33*$FG33*(1+($FI33-1)*AJ$26)*($D$23*$FH33+(1-$D$23)*AJ$25),"") | AK80: =IFERROR(AK33*$FG33*(1+($FI33-1)*AK$26)*($D$23*$FH33+(1-$D$23)*AK$25),"") | AL80: =IFERROR(AL33*$FG33*(1+($FI33-1)*AL$26)*($D$23*$FH33+(1-$D$23)*AL$25),"") | AM80: =IFERROR(AM33*$FG33*(1+($FI33-1)*AM$26)*($D$23*$FH33+(1-$D$23)*AM$25),"") | AN80: =IFERROR(AN33*$FG33*(1+($FI33-1)*AN$26)*($D$23*$FH33+(1-$D$23)*AN$25),"") | AO80: =IFERROR(AO33*$FG33*(1+($FI33-1)*AO$26)*($D$23*$FH33+(1-$D$23)*AO$25),"") | AP80: =IFERROR(AP33*$FG33*(1+($FI33-1)*AP$26)*($D$23*$FH33+(1-$D$23)*AP$25),"") | ... BQ80: =IFERROR(BQ33*$FG33*(1+($FI33-1)*BQ$26)*($D$23*$FH33+(1-$D$23)*BQ$25),"")
A81: 20251127800601 | B81: OTHER | D81: 평택지역 전기공급시설 전력구공사(신평택-고덕#3) 1공구 | AI81: =IFERROR(AI34*$FG34*(1+($FI34-1)*AI$26)*($D$23*$FH34+(1-$D$23)*AI$25),"") | AJ81: =IFERROR(AJ34*$FG34*(1+($FI34-1)*AJ$26)*($D$23*$FH34+(1-$D$23)*AJ$25),"") | AK81: =IFERROR(AK34*$FG34*(1+($FI34-1)*AK$26)*($D$23*$FH34+(1-$D$23)*AK$25),"") | AL81: =IFERROR(AL34*$FG34*(1+($FI34-1)*AL$26)*($D$23*$FH34+(1-$D$23)*AL$25),"") | AM81: =IFERROR(AM34*$FG34*(1+($FI34-1)*AM$26)*($D$23*$FH34+(1-$D$23)*AM$25),"") | AN81: =IFERROR(AN34*$FG34*(1+($FI34-1)*AN$26)*($D$23*$FH34+(1-$D$23)*AN$25),"") | AO81: =IFERROR(AO34*$FG34*(1+($FI34-1)*AO$26)*($D$23*$FH34+(1-$D$23)*AO$25),"") | AP81: =IFERROR(AP34*$FG34*(1+($FI34-1)*AP$26)*($D$23*$FH34+(1-$D$23)*AP$25),"") | ... AY81: =IFERROR(AY34*$FG34*(1+($FI34-1)*AY$26)*($D$23*$FH34+(1-$D$23)*AY$25),"")
A82: 20251205800202 | B82: OTHER | D82: 엄궁대교 건설공사 | AE82: =IFERROR(AE35*$FG35*(1+($FI35-1)*AE$26)*($D$23*$FH35+(1-$D$23)*AE$25),"") | AF82: =IFERROR(AF35*$FG35*(1+($FI35-1)*AF$26)*($D$23*$FH35+(1-$D$23)*AF$25),"") | AG82: =IFERROR(AG35*$FG35*(1+($FI35-1)*AG$26)*($D$23*$FH35+(1-$D$23)*AG$25),"") | AH82: =IFERROR(AH35*$FG35*(1+($FI35-1)*AH$26)*($D$23*$FH35+(1-$D$23)*AH$25),"") | AI82: =IFERROR(AI35*$FG35*(1+($FI35-1)*AI$26)*($D$23*$FH35+(1-$D$23)*AI$25),"") | AJ82: =IFERROR(AJ35*$FG35*(1+($FI35-1)*AJ$26)*($D$23*$FH35+(1-$D$23)*AJ$25),"") | AK82: =IFERROR(AK35*$FG35*(1+($FI35-1)*AK$26)*($D$23*$FH35+(1-$D$23)*AK$25),"") | AL82: =IFERROR(AL35*$FG35*(1+($FI35-1)*AL$26)*($D$23*$FH35+(1-$D$23)*AL$25),"") | ... AZ82: =IFERROR(AZ35*$FG35*(1+($FI35-1)*AZ$26)*($D$23*$FH35+(1-$D$23)*AZ$25),"")
A83: 20251217800479 | B83: NAVAL | D83: 검독수리 Batch-II 후속함(13~16번함) | AI83: =IFERROR(AI36*$FG36*(1+($FI36-1)*AI$26)*($D$23*$FH36+(1-$D$23)*AI$25),"") | AJ83: =IFERROR(AJ36*$FG36*(1+($FI36-1)*AJ$26)*($D$23*$FH36+(1-$D$23)*AJ$25),"") | AK83: =IFERROR(AK36*$FG36*(1+($FI36-1)*AK$26)*($D$23*$FH36+(1-$D$23)*AK$25),"") | AL83: =IFERROR(AL36*$FG36*(1+($FI36-1)*AL$26)*($D$23*$FH36+(1-$D$23)*AL$25),"") | AM83: =IFERROR(AM36*$FG36*(1+($FI36-1)*AM$26)*($D$23*$FH36+(1-$D$23)*AM$25),"") | AN83: =IFERROR(AN36*$FG36*(1+($FI36-1)*AN$26)*($D$23*$FH36+(1-$D$23)*AN$25),"") | AO83: =IFERROR(AO36*$FG36*(1+($FI36-1)*AO$26)*($D$23*$FH36+(1-$D$23)*AO$25),"") | AP83: =IFERROR(AP36*$FG36*(1+($FI36-1)*AP$26)*($D$23*$FH36+(1-$D$23)*AP$25),"") | ... AY83: =IFERROR(AY36*$FG36*(1+($FI36-1)*AY$26)*($D$23*$FH36+(1-$D$23)*AY$25),"")
A84: 20251222800631 | B84: OTHER | D84: 고속국도 제292호선 오송지선 건설공사 | K84: =IFERROR(K37*$FG37*(1+($FI37-1)*K$26)*($D$23*$FH37+(1-$D$23)*K$25),"") | L84: =IFERROR(L37*$FG37*(1+($FI37-1)*L$26)*($D$23*$FH37+(1-$D$23)*L$25),"") | M84: =IFERROR(M37*$FG37*(1+($FI37-1)*M$26)*($D$23*$FH37+(1-$D$23)*M$25),"") | N84: =IFERROR(N37*$FG37*(1+($FI37-1)*N$26)*($D$23*$FH37+(1-$D$23)*N$25),"") | O84: =IFERROR(O37*$FG37*(1+($FI37-1)*O$26)*($D$23*$FH37+(1-$D$23)*O$25),"") | P84: =IFERROR(P37*$FG37*(1+($FI37-1)*P$26)*($D$23*$FH37+(1-$D$23)*P$25),"") | Q84: =IFERROR(Q37*$FG37*(1+($FI37-1)*Q$26)*($D$23*$FH37+(1-$D$23)*Q$25),"") | R84: =IFERROR(R37*$FG37*(1+($FI37-1)*R$26)*($D$23*$FH37+(1-$D$23)*R$25),"") | ... AM84: =IFERROR(AM37*$FG37*(1+($FI37-1)*AM$26)*($D$23*$FH37+(1-$D$23)*AM$25),"")
A85: 20251224800003 | B85: NAVAL | C85: 1 | D85: (선박) 다목적 화학방제함 1척 건조 | AI85: =IFERROR(AI38*$FG38*(1+($FI38-1)*AI$26)*($D$23*$FH38+(1-$D$23)*AI$25),"") | AJ85: =IFERROR(AJ38*$FG38*(1+($FI38-1)*AJ$26)*($D$23*$FH38+(1-$D$23)*AJ$25),"") | AK85: =IFERROR(AK38*$FG38*(1+($FI38-1)*AK$26)*($D$23*$FH38+(1-$D$23)*AK$25),"") | AL85: =IFERROR(AL38*$FG38*(1+($FI38-1)*AL$26)*($D$23*$FH38+(1-$D$23)*AL$25),"") | AM85: =IFERROR(AM38*$FG38*(1+($FI38-1)*AM$26)*($D$23*$FH38+(1-$D$23)*AM$25),"") | AN85: =IFERROR(AN38*$FG38*(1+($FI38-1)*AN$26)*($D$23*$FH38+(1-$D$23)*AN$25),"") | AO85: =IFERROR(AO38*$FG38*(1+($FI38-1)*AO$26)*($D$23*$FH38+(1-$D$23)*AO$25),"") | AP85: =IFERROR(AP38*$FG38*(1+($FI38-1)*AP$26)*($D$23*$FH38+(1-$D$23)*AP$25),"") | ... AU85: =IFERROR(AU38*$FG38*(1+($FI38-1)*AU$26)*($D$23*$FH38+(1-$D$23)*AU$25),"")
A86: 20251224800596 | B86: OTHER | D86: 고속국도 제50호 영동선 안산-북수원간 확장(개량)공사(제2공구) | Q86: =IFERROR(Q39*$FG39*(1+($FI39-1)*Q$26)*($D$23*$FH39+(1-$D$23)*Q$25),"") | R86: =IFERROR(R39*$FG39*(1+($FI39-1)*R$26)*($D$23*$FH39+(1-$D$23)*R$25),"") | S86: =IFERROR(S39*$FG39*(1+($FI39-1)*S$26)*($D$23*$FH39+(1-$D$23)*S$25),"") | T86: =IFERROR(T39*$FG39*(1+($FI39-1)*T$26)*($D$23*$FH39+(1-$D$23)*T$25),"") | U86: =IFERROR(U39*$FG39*(1+($FI39-1)*U$26)*($D$23*$FH39+(1-$D$23)*U$25),"") | V86: =IFERROR(V39*$FG39*(1+($FI39-1)*V$26)*($D$23*$FH39+(1-$D$23)*V$25),"") | W86: =IFERROR(W39*$FG39*(1+($FI39-1)*W$26)*($D$23*$FH39+(1-$D$23)*W$25),"") | X86: =IFERROR(X39*$FG39*(1+($FI39-1)*X$26)*($D$23*$FH39+(1-$D$23)*X$25),"") | ... AO86: =IFERROR(AO39*$FG39*(1+($FI39-1)*AO$26)*($D$23*$FH39+(1-$D$23)*AO$25),"")
A87: 20251231800507 | B87: OTHER | D87: 인천국제공항 제2여객터미널 확장 골조 및 마감공사(서편) | O87: =IFERROR(O40*$FG40*(1+($FI40-1)*O$26)*($D$23*$FH40+(1-$D$23)*O$25),"") | P87: =IFERROR(P40*$FG40*(1+($FI40-1)*P$26)*($D$23*$FH40+(1-$D$23)*P$25),"") | Q87: =IFERROR(Q40*$FG40*(1+($FI40-1)*Q$26)*($D$23*$FH40+(1-$D$23)*Q$25),"") | R87: =IFERROR(R40*$FG40*(1+($FI40-1)*R$26)*($D$23*$FH40+(1-$D$23)*R$25),"") | S87: =IFERROR(S40*$FG40*(1+($FI40-1)*S$26)*($D$23*$FH40+(1-$D$23)*S$25),"") | T87: =IFERROR(T40*$FG40*(1+($FI40-1)*T$26)*($D$23*$FH40+(1-$D$23)*T$25),"") | U87: =IFERROR(U40*$FG40*(1+($FI40-1)*U$26)*($D$23*$FH40+(1-$D$23)*U$25),"") | V87: =IFERROR(V40*$FG40*(1+($FI40-1)*V$26)*($D$23*$FH40+(1-$D$23)*V$25),"") | ... AJ87: =IFERROR(AJ40*$FG40*(1+($FI40-1)*AJ$26)*($D$23*$FH40+(1-$D$23)*AJ$25),"")
A88: 20251231800547 | B88: OTHER | D88: 킨텍스 제3전시장 건립공사 | AF88: =IFERROR(AF41*$FG41*(1+($FI41-1)*AF$26)*($D$23*$FH41+(1-$D$23)*AF$25),"") | AG88: =IFERROR(AG41*$FG41*(1+($FI41-1)*AG$26)*($D$23*$FH41+(1-$D$23)*AG$25),"") | AH88: =IFERROR(AH41*$FG41*(1+($FI41-1)*AH$26)*($D$23*$FH41+(1-$D$23)*AH$25),"") | AI88: =IFERROR(AI41*$FG41*(1+($FI41-1)*AI$26)*($D$23*$FH41+(1-$D$23)*AI$25),"") | AJ88: =IFERROR(AJ41*$FG41*(1+($FI41-1)*AJ$26)*($D$23*$FH41+(1-$D$23)*AJ$25),"") | AK88: =IFERROR(AK41*$FG41*(1+($FI41-1)*AK$26)*($D$23*$FH41+(1-$D$23)*AK$25),"") | AL88: =IFERROR(AL41*$FG41*(1+($FI41-1)*AL$26)*($D$23*$FH41+(1-$D$23)*AL$25),"") | AM88: =IFERROR(AM41*$FG41*(1+($FI41-1)*AM$26)*($D$23*$FH41+(1-$D$23)*AM$25),"") | ... AT88: =IFERROR(AT41*$FG41*(1+($FI41-1)*AT$26)*($D$23*$FH41+(1-$D$23)*AT$25),"")
A89: 20260107800221 | B89: OTHER | D89: 대전 삼성6구역 재개발정비사업 공사 | AJ89: =IFERROR(AJ42*$FG42*(1+($FI42-1)*AJ$26)*($D$23*$FH42+(1-$D$23)*AJ$25),"") | AK89: =IFERROR(AK42*$FG42*(1+($FI42-1)*AK$26)*($D$23*$FH42+(1-$D$23)*AK$25),"") | AL89: =IFERROR(AL42*$FG42*(1+($FI42-1)*AL$26)*($D$23*$FH42+(1-$D$23)*AL$25),"") | AM89: =IFERROR(AM42*$FG42*(1+($FI42-1)*AM$26)*($D$23*$FH42+(1-$D$23)*AM$25),"") | AN89: =IFERROR(AN42*$FG42*(1+($FI42-1)*AN$26)*($D$23*$FH42+(1-$D$23)*AN$25),"") | AO89: =IFERROR(AO42*$FG42*(1+($FI42-1)*AO$26)*($D$23*$FH42+(1-$D$23)*AO$25),"") | AP89: =IFERROR(AP42*$FG42*(1+($FI42-1)*AP$26)*($D$23*$FH42+(1-$D$23)*AP$25),"") | AQ89: =IFERROR(AQ42*$FG42*(1+($FI42-1)*AQ$26)*($D$23*$FH42+(1-$D$23)*AQ$25),"") | ... BB89: =IFERROR(BB42*$FG42*(1+($FI42-1)*BB$26)*($D$23*$FH42+(1-$D$23)*BB$25),"")
A90: 20260116800164 | B90: OTHER | D90: 여수 천연가스발전소 건설공사 | AJ90: =IFERROR(AJ43*$FG43*(1+($FI43-1)*AJ$26)*($D$23*$FH43+(1-$D$23)*AJ$25),"") | AK90: =IFERROR(AK43*$FG43*(1+($FI43-1)*AK$26)*($D$23*$FH43+(1-$D$23)*AK$25),"") | AL90: =IFERROR(AL43*$FG43*(1+($FI43-1)*AL$26)*($D$23*$FH43+(1-$D$23)*AL$25),"") | AM90: =IFERROR(AM43*$FG43*(1+($FI43-1)*AM$26)*($D$23*$FH43+(1-$D$23)*AM$25),"") | AN90: =IFERROR(AN43*$FG43*(1+($FI43-1)*AN$26)*($D$23*$FH43+(1-$D$23)*AN$25),"") | AO90: =IFERROR(AO43*$FG43*(1+($FI43-1)*AO$26)*($D$23*$FH43+(1-$D$23)*AO$25),"") | AP90: =IFERROR(AP43*$FG43*(1+($FI43-1)*AP$26)*($D$23*$FH43+(1-$D$23)*AP$25),"") | AQ90: =IFERROR(AQ43*$FG43*(1+($FI43-1)*AQ$26)*($D$23*$FH43+(1-$D$23)*AQ$25),"") | ... AW90: =IFERROR(AW43*$FG43*(1+($FI43-1)*AW$26)*($D$23*$FH43+(1-$D$23)*AW$25),"")
A91: 20260120800250 | B91: OTHER | D91: 포항 대잠동 행복아파트2단지 소규모재건축사업 공사 | X91: =IFERROR(X44*$FG44*(1+($FI44-1)*X$26)*($D$23*$FH44+(1-$D$23)*X$25),"") | Y91: =IFERROR(Y44*$FG44*(1+($FI44-1)*Y$26)*($D$23*$FH44+(1-$D$23)*Y$25),"") | Z91: =IFERROR(Z44*$FG44*(1+($FI44-1)*Z$26)*($D$23*$FH44+(1-$D$23)*Z$25),"") | AA91: =IFERROR(AA44*$FG44*(1+($FI44-1)*AA$26)*($D$23*$FH44+(1-$D$23)*AA$25),"") | AB91: =IFERROR(AB44*$FG44*(1+($FI44-1)*AB$26)*($D$23*$FH44+(1-$D$23)*AB$25),"") | AC91: =IFERROR(AC44*$FG44*(1+($FI44-1)*AC$26)*($D$23*$FH44+(1-$D$23)*AC$25),"") | AD91: =IFERROR(AD44*$FG44*(1+($FI44-1)*AD$26)*($D$23*$FH44+(1-$D$23)*AD$25),"") | AE91: =IFERROR(AE44*$FG44*(1+($FI44-1)*AE$26)*($D$23*$FH44+(1-$D$23)*AE$25),"") | ... AP91: =IFERROR(AP44*$FG44*(1+($FI44-1)*AP$26)*($D$23*$FH44+(1-$D$23)*AP$25),"")
A92: 20260211800125 | B92: CONT | C92: 2 | D92: 컨테이너선 2척 수주 | AJ92: =IFERROR(AJ45*$FG45*(1+($FI45-1)*AJ$26)*($D$23*$FH45+(1-$D$23)*AJ$25),"") | AK92: =IFERROR(AK45*$FG45*(1+($FI45-1)*AK$26)*($D$23*$FH45+(1-$D$23)*AK$25),"") | AL92: =IFERROR(AL45*$FG45*(1+($FI45-1)*AL$26)*($D$23*$FH45+(1-$D$23)*AL$25),"") | AM92: =IFERROR(AM45*$FG45*(1+($FI45-1)*AM$26)*($D$23*$FH45+(1-$D$23)*AM$25),"") | AN92: =IFERROR(AN45*$FG45*(1+($FI45-1)*AN$26)*($D$23*$FH45+(1-$D$23)*AN$25),"") | AO92: =IFERROR(AO45*$FG45*(1+($FI45-1)*AO$26)*($D$23*$FH45+(1-$D$23)*AO$25),"") | AP92: =IFERROR(AP45*$FG45*(1+($FI45-1)*AP$26)*($D$23*$FH45+(1-$D$23)*AP$25),"") | AQ92: =IFERROR(AQ45*$FG45*(1+($FI45-1)*AQ$26)*($D$23*$FH45+(1-$D$23)*AQ$25),"") | ... AS92: =IFERROR(AS45*$FG45*(1+($FI45-1)*AS$26)*($D$23*$FH45+(1-$D$23)*AS$25),"")
A93: 20260227801603 | B93: OTHER | D93: 수도권광역급행철도A노선 민간투자시설사업 건설공사 | H93: =IFERROR(H46*$FG46*(1+($FI46-1)*H$26)*($D$23*$FH46+(1-$D$23)*H$25),"") | I93: =IFERROR(I46*$FG46*(1+($FI46-1)*I$26)*($D$23*$FH46+(1-$D$23)*I$25),"") | J93: =IFERROR(J46*$FG46*(1+($FI46-1)*J$26)*($D$23*$FH46+(1-$D$23)*J$25),"") | K93: =IFERROR(K46*$FG46*(1+($FI46-1)*K$26)*($D$23*$FH46+(1-$D$23)*K$25),"") | L93: =IFERROR(L46*$FG46*(1+($FI46-1)*L$26)*($D$23*$FH46+(1-$D$23)*L$25),"") | M93: =IFERROR(M46*$FG46*(1+($FI46-1)*M$26)*($D$23*$FH46+(1-$D$23)*M$25),"") | N93: =IFERROR(N46*$FG46*(1+($FI46-1)*N$26)*($D$23*$FH46+(1-$D$23)*N$25),"") | O93: =IFERROR(O46*$FG46*(1+($FI46-1)*O$26)*($D$23*$FH46+(1-$D$23)*O$25),"") | ... AS93: =IFERROR(AS46*$FG46*(1+($FI46-1)*AS$26)*($D$23*$FH46+(1-$D$23)*AS$25),"")
A94: 20260227801809 | B94: OTHER | D94: 광교 A17블록 및 교산 A1블록 민간참여 공공주택건설사업 | AJ94: =IFERROR(AJ47*$FG47*(1+($FI47-1)*AJ$26)*($D$23*$FH47+(1-$D$23)*AJ$25),"") | AK94: =IFERROR(AK47*$FG47*(1+($FI47-1)*AK$26)*($D$23*$FH47+(1-$D$23)*AK$25),"") | AL94: =IFERROR(AL47*$FG47*(1+($FI47-1)*AL$26)*($D$23*$FH47+(1-$D$23)*AL$25),"") | AM94: =IFERROR(AM47*$FG47*(1+($FI47-1)*AM$26)*($D$23*$FH47+(1-$D$23)*AM$25),"") | AN94: =IFERROR(AN47*$FG47*(1+($FI47-1)*AN$26)*($D$23*$FH47+(1-$D$23)*AN$25),"") | AO94: =IFERROR(AO47*$FG47*(1+($FI47-1)*AO$26)*($D$23*$FH47+(1-$D$23)*AO$25),"") | AP94: =IFERROR(AP47*$FG47*(1+($FI47-1)*AP$26)*($D$23*$FH47+(1-$D$23)*AP$25),"") | AQ94: =IFERROR(AQ47*$FG47*(1+($FI47-1)*AQ$26)*($D$23*$FH47+(1-$D$23)*AQ$25),"") | ... DY94: =IFERROR(DY47*$FG47*(1+($FI47-1)*DY$26)*($D$23*$FH47+(1-$D$23)*DY$25),"")
A95: 20260304800353 | B95: OTHER | D95: 필리핀 따굼 홍수조절사업 | AJ95: =IFERROR(AJ48*$FG48*(1+($FI48-1)*AJ$26)*($D$23*$FH48+(1-$D$23)*AJ$25),"") | AK95: =IFERROR(AK48*$FG48*(1+($FI48-1)*AK$26)*($D$23*$FH48+(1-$D$23)*AK$25),"") | AL95: =IFERROR(AL48*$FG48*(1+($FI48-1)*AL$26)*($D$23*$FH48+(1-$D$23)*AL$25),"") | AM95: =IFERROR(AM48*$FG48*(1+($FI48-1)*AM$26)*($D$23*$FH48+(1-$D$23)*AM$25),"") | AN95: =IFERROR(AN48*$FG48*(1+($FI48-1)*AN$26)*($D$23*$FH48+(1-$D$23)*AN$25),"") | AO95: =IFERROR(AO48*$FG48*(1+($FI48-1)*AO$26)*($D$23*$FH48+(1-$D$23)*AO$25),"") | AP95: =IFERROR(AP48*$FG48*(1+($FI48-1)*AP$26)*($D$23*$FH48+(1-$D$23)*AP$25),"") | AQ95: =IFERROR(AQ48*$FG48*(1+($FI48-1)*AQ$26)*($D$23*$FH48+(1-$D$23)*AQ$25),"") | ... AZ95: =IFERROR(AZ48*$FG48*(1+($FI48-1)*AZ$26)*($D$23*$FH48+(1-$D$23)*AZ$25),"")
A96: 20260306800575 | B96: OTHER | D96: 서울 번동 3-2구역 가로주택정비사업 공사 | AJ96: =IFERROR(AJ49*$FG49*(1+($FI49-1)*AJ$26)*($D$23*$FH49+(1-$D$23)*AJ$25),"") | AK96: =IFERROR(AK49*$FG49*(1+($FI49-1)*AK$26)*($D$23*$FH49+(1-$D$23)*AK$25),"") | AL96: =IFERROR(AL49*$FG49*(1+($FI49-1)*AL$26)*($D$23*$FH49+(1-$D$23)*AL$25),"") | AM96: =IFERROR(AM49*$FG49*(1+($FI49-1)*AM$26)*($D$23*$FH49+(1-$D$23)*AM$25),"") | AN96: =IFERROR(AN49*$FG49*(1+($FI49-1)*AN$26)*($D$23*$FH49+(1-$D$23)*AN$25),"") | AO96: =IFERROR(AO49*$FG49*(1+($FI49-1)*AO$26)*($D$23*$FH49+(1-$D$23)*AO$25),"") | AP96: =IFERROR(AP49*$FG49*(1+($FI49-1)*AP$26)*($D$23*$FH49+(1-$D$23)*AP$25),"") | AQ96: =IFERROR(AQ49*$FG49*(1+($FI49-1)*AQ$26)*($D$23*$FH49+(1-$D$23)*AQ$25),"") | ... BB96: =IFERROR(BB49*$FG49*(1+($FI49-1)*BB$26)*($D$23*$FH49+(1-$D$23)*BB$25),"")
A97: 20260313800208 | B97: OTHER | D97: 24-F-00부대 유도로 신설 및 활주로 재포장사업(4146) | AG97: =IFERROR(AG50*$FG50*(1+($FI50-1)*AG$26)*($D$23*$FH50+(1-$D$23)*AG$25),"") | AH97: =IFERROR(AH50*$FG50*(1+($FI50-1)*AH$26)*($D$23*$FH50+(1-$D$23)*AH$25),"") | AI97: =IFERROR(AI50*$FG50*(1+($FI50-1)*AI$26)*($D$23*$FH50+(1-$D$23)*AI$25),"") | AJ97: =IFERROR(AJ50*$FG50*(1+($FI50-1)*AJ$26)*($D$23*$FH50+(1-$D$23)*AJ$25),"") | AK97: =IFERROR(AK50*$FG50*(1+($FI50-1)*AK$26)*($D$23*$FH50+(1-$D$23)*AK$25),"") | AL97: =IFERROR(AL50*$FG50*(1+($FI50-1)*AL$26)*($D$23*$FH50+(1-$D$23)*AL$25),"") | AM97: =IFERROR(AM50*$FG50*(1+($FI50-1)*AM$26)*($D$23*$FH50+(1-$D$23)*AM$25),"") | AN97: =IFERROR(AN50*$FG50*(1+($FI50-1)*AN$26)*($D$23*$FH50+(1-$D$23)*AN$25),"") | ... AT97: =IFERROR(AT50*$FG50*(1+($FI50-1)*AT$26)*($D$23*$FH50+(1-$D$23)*AT$25),"")
A98: 20260401800508 | B98: OTHER | D98: 서대신4구역 주택재개발 정비사업 | O98: =IFERROR(O51*$FG51*(1+($FI51-1)*O$26)*($D$23*$FH51+(1-$D$23)*O$25),"") | P98: =IFERROR(P51*$FG51*(1+($FI51-1)*P$26)*($D$23*$FH51+(1-$D$23)*P$25),"") | Q98: =IFERROR(Q51*$FG51*(1+($FI51-1)*Q$26)*($D$23*$FH51+(1-$D$23)*Q$25),"") | R98: =IFERROR(R51*$FG51*(1+($FI51-1)*R$26)*($D$23*$FH51+(1-$D$23)*R$25),"") | S98: =IFERROR(S51*$FG51*(1+($FI51-1)*S$26)*($D$23*$FH51+(1-$D$23)*S$25),"") | T98: =IFERROR(T51*$FG51*(1+($FI51-1)*T$26)*($D$23*$FH51+(1-$D$23)*T$25),"") | U98: =IFERROR(U51*$FG51*(1+($FI51-1)*U$26)*($D$23*$FH51+(1-$D$23)*U$25),"") | V98: =IFERROR(V51*$FG51*(1+($FI51-1)*V$26)*($D$23*$FH51+(1-$D$23)*V$25),"") | ... AG98: =IFERROR(AG51*$FG51*(1+($FI51-1)*AG$26)*($D$23*$FH51+(1-$D$23)*AG$25),"")
A99: 20260410800253 | B99: OTHER | D99: 부산 범천5구역 재개발정비사업 | AK99: =IFERROR(AK52*$FG52*(1+($FI52-1)*AK$26)*($D$23*$FH52+(1-$D$23)*AK$25),"") | AL99: =IFERROR(AL52*$FG52*(1+($FI52-1)*AL$26)*($D$23*$FH52+(1-$D$23)*AL$25),"") | AM99: =IFERROR(AM52*$FG52*(1+($FI52-1)*AM$26)*($D$23*$FH52+(1-$D$23)*AM$25),"") | AN99: =IFERROR(AN52*$FG52*(1+($FI52-1)*AN$26)*($D$23*$FH52+(1-$D$23)*AN$25),"") | AO99: =IFERROR(AO52*$FG52*(1+($FI52-1)*AO$26)*($D$23*$FH52+(1-$D$23)*AO$25),"") | AP99: =IFERROR(AP52*$FG52*(1+($FI52-1)*AP$26)*($D$23*$FH52+(1-$D$23)*AP$25),"") | AQ99: =IFERROR(AQ52*$FG52*(1+($FI52-1)*AQ$26)*($D$23*$FH52+(1-$D$23)*AQ$25),"") | AR99: =IFERROR(AR52*$FG52*(1+($FI52-1)*AR$26)*($D$23*$FH52+(1-$D$23)*AR$25),"") | ... BC99: =IFERROR(BC52*$FG52*(1+($FI52-1)*BC$26)*($D$23*$FH52+(1-$D$23)*BC$25),"")
