Workbook
Name 변수H: 변수!$C$1:$AO$1
Name 환율: 변수!$C$6:$AO$13
Name BS연결H: BS연결!$C$1:$AO$1
Name BS연결: BS연결!$C$5:$AO$85
Name BS별도H: BS별도!$C$1:$AO$1
Name BS별도: BS별도!$C$5:$AO$81
Name SUBQH: subQ!$A$1:$AO$1
Name subQ: subQ!$A$5:$AO$40

Sheet README
A1: 서암기계공업(100660) 실적 모델 — ARGUS 한국조선
A2: 기준 분기 2026Q2 · 마지막 실적 2026Q2 · 생성 2026-10-26
A3: 모든 수치는 모델 산출값(DART 공개 재무제표 + 우리 추정)이다 — 목표주가·투자 추천 아님. 참고용 · 투자조언 아님.
A5: 시트
A6: 변수 가정 시계열. 환율 8행(ECB via frankfurter — L2 fx.json; 추정 분기 = 노란 가정), 추정 드라이버(노란 셀 = 모델값에서 역산한 가정, 바꾸면 재계산; 연녹 셀 = 3절 스칼라 참조 수식), 3절 스칼라 가정(세율·판관비율·지배주주비중·이자율·종가·PER 밴드·COE·외화 순노출·헤지비율)
A7: BS연결/BS별도 FnGuide 계정명 × 기간 값 덤프(백만원). 행1 분기라벨, 행4 YYYY.MM / YYYY.12A. 이름정의 BS연결H·BS연결(계정명 C열부터)
A8: subQ 분기 서브모델(억원 = 백만원/100). 확정 행: =IFERROR(VLOOKUP($D행,BS연결,MATCH(E$1,BS연결H,0),0)/100,"") 추정 행: 변수 시트 가정 셀 참조 수식. 외환손익·파생상품손익은 BS 계정 합·차, 기타금융손익은 잔차, OPM·EPS·BPS·PER·PBR 은 파생 수식
A9: SLS 선표(조선사만, sls json 있을 때): 요약 행(sls 저장값) + 계약별 스케줄(백만$) × (헤지비율 × 헤지환율 + (1−헤지비율) × 건조시점 환율[변수 원/달러(평균)]) → 원화 수식 블록 → 합계 행이 subQ 매출조선에 연결
A10: 시나리오 신규수주 보수/기준/낙관(forecast_panel 패널, 모델에 scenarios 가 있을 때만): 매출액·영업이익 = subQ 기준값 ± (시나리오 신규 − base 신규) × OPM. base 만 subQ 행에 포함, 나머지는 합산 안 함
A11: 분기/연간예상 subQ 를 이름(A열 key)으로 VLOOKUP 한 보고서 표(억원)
A12: TP PER 밴드 × 12M fwd EPS, PBR = ROE/COE × BPS — 모델 산출값 구간, 목표주가·추천 아님
A13: 외화 환율 QoQ, 외화 순노출 × Δ기말환율 → 환관련손익 추정
... A34: 백테스트: {"freeze": "2025Q2", "horizon": 4, "revenue_wape_pct": 17.8, "op_wape_pct": 150.6, "n": 4, "note": "단일 회사 4분기 — 통계 아님", "driver_at_freeze": "trend_seasonal", "selection_oos_at_freeze": {"wape_link": null, "wape_trend": null, "adopted": false, "decision": "rejected", "note": "유의성 조건 미달 → OOS 비교 전 기각"}, "frozen_inputs": "fin(연결/별도)·고객 조선사 모델·지주 자회사 모델은 2025Q2 까지의 분기만; 선표는 체결일 ≤ 2025Q2 말일 계약(원장 최신 금액·코호트 등급, 환산 없음); 잔고는 yards_cache 2025Q2; 시세·환율 forward·prices·forecast_panel 신규수주 미사용. 고객 가중치(suppliers.json 언급 비중)와 합병 체인링크는 현재 지식; 고객 연동 채택은 동결 모델 안에서도 자기 la−4분기 OOS 규칙(selection_oos_at_freeze)", "detail": [{"q": "2025Q3", "rev_pred": 107.47, "rev_act": 124.33, "op_pred": -4.3, "op_act": 1.52}, {"q": "2025Q4", "rev_pred": 95.29, "rev_act": 128.52, "op_pred": -3.81, "op_act": 2.9}, {"q": "2026Q1", "rev_pred": 95.09, "rev_act": 110.44, "op_pred": -3.8, "op_act": -3.69}, {"q": "2026Q2", "rev_pred": 111.26, "rev_act": 134.65, "op_pred": -4.45, "op_act": 9.63}]}

Sheet 변수
C1: 이름: 변수H | E1: 4Q21 | F1: 2021 | G1: 1Q22 | H1: 2Q22 | I1: 3Q22 | J1: 4Q22 | K1: 2022 | L1: 1Q23 | M1: 2Q23 | N1: 3Q23 | O1: 4Q23 | P1: 2023 | Q1: 1Q24 | R1: 2Q24 | S1: 3Q24 | T1: 4Q24 | U1: 2024 | V1: 1Q25 | W1: 2Q25 | X1: 3Q25 | Y1: 4Q25 | Z1: 2025 | AA1: 1Q26 | AB1: 2Q26 | AC1: 3Q26 | AD1: 4Q26 | AE1: 2026 | AF1: 1Q27 | AG1: 2Q27 | AH1: 3Q27 | AI1: 4Q27 | AJ1: 2027 | AK1: 1Q28 | AL1: 2Q28 | AM1: 3Q28 | AN1: 4Q28 | AO1: 2028
A2: 가정 시계열 — 노란 셀은 추정 가정(모델값에서 역산), 연녹 셀은 3절 스칼라 참조 수식. 바꾸면 subQ·분기·연간예상·TP·시나리오가 재계산됩니다.
E3: 1 | F3: 2 | G3: 3 | H3: 4 | I3: 5 | J3: 6 | K3: 7 | L3: 8 | M3: 9 | N3: 10 | O3: 11 | P3: 12 | Q3: 13 | R3: 14 | S3: 15 | T3: 16 | U3: 17 | V3: 18 | W3: 19 | X3: 20 | Y3: 21 | Z3: 22 | AA3: 23 | AB3: 24 | AC3: 25 | AD3: 26 | AE3: 27 | AF3: 28 | AG3: 29 | AH3: 30 | AI3: 31 | AJ3: 32 | AK3: 33 | AL3: 34 | AM3: 35 | AN3: 36 | AO3: 37
E4: 2021.12 | F4: 2021.12A | G4: 2022.03 | H4: 2022.06 | I4: 2022.09 | J4: 2022.12 | K4: 2022.12A | L4: 2023.03 | M4: 2023.06 | N4: 2023.09 | O4: 2023.12 | P4: 2023.12A | Q4: 2024.03 | R4: 2024.06 | S4: 2024.09 | T4: 2024.12 | U4: 2024.12A | V4: 2025.03 | W4: 2025.06 | X4: 2025.09 | Y4: 2025.12 | Z4: 2025.12A | AA4: 2026.03 | AB4: 2026.06 | AC4: 2026.09 | AD4: 2026.12 | AE4: 2026.12A | AF4: 2027.03 | AG4: 2027.06 | AH4: 2027.09 | AI4: 2027.12 | AJ4: 2027.12A | AK4: 2028.03 | AL4: 2028.06 | AM4: 2028.09 | AN4: 2028.12 | AO4: 2028.12A
B5: 1. FX | C5: 이름: 환율
A6: USDKRW_avg | C6: 원/달러(평균) | E6: 1183.5 | F6: 1145.51 | G6: 1205.78 | H6: 1262.09 | I6: 1341.93 | J6: 1360.12 | K6: 1292.98 | L6: 1276.95 | M6: 1315.69 | N6: 1313.62 | O6: 1322.01 | P6: 1306.85 | Q6: 1330.14 | R6: 1371.28 | S6: 1356.22 | T6: 1396.3 | U6: 1363.53 | V6: 1452.28 | W6: 1398.52 | X6: 1386.95 | Y6: 1449.19 | Z6: 1421.52 | AA6: 1466.12 | AB6: 1501.75 | AC6: 1418.75 | AD6: 1337.49 | AE6: 1451.19 | AF6: 1324.45 | AG6: 1324.45 | AH6: 1324.45 | AI6: 1324.45 | AK6: 1324.45 | AL6: 1324.45 | AM6: 1324.45 | AN6: 1324.45
A7: USDKRW_end | C7: 원/달러(기말) | E7: 1188.75 | F7: 1188.75 | G7: 1213.74 | H7: 1301.24 | I7: 1436.9 | J7: 1260.16 | K7: 1260.16 | L7: 1305.99 | M7: 1321.44 | N7: 1345.35 | O7: 1297.43 | P7: 1297.43 | Q7: 1349.25 | R7: 1377.73 | S7: 1312.17 | T7: 1474.78 | U7: 1474.78 | V7: 1474.54 | W7: 1355.13 | X7: 1403.67 | Y7: 1444.2 | Z7: 1444.2 | AA7: 1524.8 | AB7: 1550.89 | AC7: 1355.4 | AD7: 1324.45 | AE7: 1324.45 | AF7: 1324.45 | AG7: 1324.45 | AH7: 1324.45 | AI7: 1324.45 | AK7: 1324.45 | AL7: 1324.45 | AM7: 1324.45 | AN7: 1324.45
A8: JPY100KRW_avg | C8: 원/100Y(평균) | E8: 1041.02 | F8: 1042.74 | G8: 1036.79 | H8: 972.23 | I8: 970.61 | J8: 961.03 | K8: 985.1 | L8: 964.89 | M8: 957.36 | N8: 909 | O8: 893.22 | P8: 931.11 | Q8: 896.29 | R8: 880.14 | S8: 909.35 | T8: 917.25 | U8: 900.92 | V8: 952.59 | W8: 967.92 | X8: 940.32 | Y8: 940.77 | Z8: 950.17 | AA8: 934.39 | AB8: 942.16 | AC8: 890.41 | AD8: 846.51 | AE8: 915.57 | AF8: 844.67 | AG8: 844.67 | AH8: 844.67 | AI8: 844.67 | AK8: 844.67 | AL8: 844.67 | AM8: 844.67 | AN8: 844.67
A9: JPY100KRW_end | C9: 원/100Y(기말) | E9: 1032.62 | F9: 1032.62 | G9: 996.83 | H9: 954.9 | I9: 993.29 | J9: 955.54 | K9: 955.54 | L9: 980.62 | M9: 913.67 | N9: 901.47 | O9: 917.04 | P9: 917.04 | Q9: 892.42 | R9: 857.76 | S9: 919.21 | T9: 939.65 | U9: 939.65 | V9: 986.84 | W9: 938.85 | X9: 948.49 | Y9: 921.81 | Z9: 921.81 | AA9: 955.99 | AB9: 954.75 | AC9: 863.31 | AD9: 844.67 | AE9: 844.67 | AF9: 844.67 | AG9: 844.67 | AH9: 844.67 | AI9: 844.67 | AK9: 844.67 | AL9: 844.67 | AM9: 844.67 | AN9: 844.67
A10: EURKRW_avg | C10: W/Euro(평균) | E10: 1353.32 | F10: 1354.06 | G10: 1352.29 | H10: 1343.31 | I10: 1350.63 | J10: 1386.07 | K10: 1358.07 | L10: 1369.93 | M10: 1432.41 | N10: 1429.41 | O10: 1420.91 | P10: 1412.88 | Q10: 1444.21 | R10: 1476.42 | S10: 1489.3 | T10: 1490.78 | U10: 1475.4 | V10: 1528.33 | W10: 1585.13 | X10: 1620.04 | Y10: 1686.02 | Z10: 1605.45 | AA10: 1715.47 | AB10: 1746.09 | AC10: 1631.97 | AD10: 1500.06 | AE10: 1680.5 | AF10: 1482.45 | AG10: 1482.45 | AH10: 1482.45 | AI10: 1482.45 | AK10: 1482.45 | AL10: 1482.45 | AM10: 1482.45 | AN10: 1482.45
A11: EURKRW_end | C11: W/Euro(기말) | E11: 1346.38 | F11: 1346.38 | G11: 1347.37 | H11: 1351.6 | I11: 1400.62 | J11: 1344.08 | K11: 1344.08 | L11: 1420.26 | M11: 1435.88 | N11: 1425.26 | O11: 1433.66 | P11: 1433.66 | Q11: 1458.68 | R11: 1474.86 | S11: 1469.1 | T11: 1532.14 | U11: 1532.14 | V11: 1594.72 | W11: 1588.22 | X11: 1648.04 | Y11: 1696.94 | Z11: 1696.94 | AA11: 1753.21 | AB11: 1767.09 | AC11: 1539.06 | AD11: 1482.45 | AE11: 1482.45 | AF11: 1482.45 | AG11: 1482.45 | AH11: 1482.45 | AI11: 1482.45 | AK11: 1482.45 | AL11: 1482.45 | AM11: 1482.45 | AN11: 1482.45
A12: CNYKRW_avg | C12: 원/중국원(평균) | E12: 185.14 | F12: 177.65 | G12: 189.93 | H12: 190.76 | I12: 195.79 | J12: 191.09 | K12: 191.93 | L12: 186.59 | M12: 187.45 | N12: 181.28 | O12: 182.86 | P12: 184.52 | Q12: 185.04 | R12: 189.35 | S12: 189.24 | T12: 194.24 | U12: 189.49 | V12: 199.63 | W12: 193.41 | X12: 193.79 | Y12: 204.38 | Z12: 197.8 | AA12: 211.75 | AB12: 220.8 | AC12: 210.43 | AD12: 199.88 | AE12: 213.06 | AF12: 198.56 | AG12: 198.56 | AH12: 198.56 | AI12: 198.56 | AK12: 198.56 | AL12: 198.56 | AM12: 198.56 | AN12: 198.56
A13: CNYKRW_end | C13: 원/중국원(기말) | E13: 187.13 | F13: 187.13 | G13: 191.38 | H13: 194.13 | I13: 201.92 | J13: 182.67 | K13: 182.67 | L13: 189.97 | M13: 181.8 | N13: 184.26 | O13: 182.61 | P13: 182.61 | Q13: 186.66 | R13: 189.7 | S13: 187.12 | T13: 202.04 | U13: 202.04 | V13: 203.3 | W13: 189.14 | X13: 197.16 | Y13: 206.28 | Z13: 206.28 | AA13: 220.97 | AB13: 228.56 | AC13: 202.16 | AD13: 198.56 | AE13: 198.56 | AF13: 198.56 | AG13: 198.56 | AH13: 198.56 | AI13: 198.56 | AK13: 198.56 | AL13: 198.56 | AM13: 198.56 | AN13: 198.56
B14: 1b. 종가
A15: price_close_end | C15: 종가(기말) | E15: 5150 | G15: 5750 | H15: 8040 | I15: 5000 | J15: 5850 | L15: 5860 | M15: 5900 | N15: 5060 | O15: 4545 | Q15: 4770 | R15: 4565 | S15: 4030 | T15: 3620 | V15: 3335 | W15: 3595 | X15: 3800 | Y15: 4490 | AA15: 4100 | AB15: 3345 | AC15: 3155 | AD15: 2950
A16: price_high | C16: 종가(최고) | E16: 6420 | G16: 6440 | H16: 10650 | I16: 8520 | J16: 8590 | L16: 6640 | M16: 6380 | N16: 5960 | O16: 5080 | Q16: 5490 | R16: 6050 | S16: 5420 | T16: 4180 | V16: 4255 | W16: 3880 | X16: 4495 | Y16: 5790 | AA16: 6180 | AB16: 5100 | AC16: 3640 | AD16: 3400
A17: price_low | C17: 종가(최저) | E17: 4525 | G17: 4690 | H17: 5330 | I17: 4700 | J17: 4880 | L17: 5260 | M17: 5360 | N17: 4605 | O17: 4380 | Q17: 4400 | R17: 4220 | S17: 3555 | T17: 3100 | V17: 3305 | W17: 3215 | X17: 3385 | Y17: 3315 | AA17: 3810 | AB17: 3110 | AC17: 2505 | AD17: 2850
A18: price_avg | C18: 종가(평균) | E18: 5407.6 | G18: 5259.3 | H18: 7022.6 | I18: 6767.6 | J18: 6325.1 | L18: 5975.8 | M18: 5742.1 | N18: 5246 | O18: 4616.4 | Q18: 4738.3 | R18: 4586.8 | S18: 4332.5 | T18: 3782.9 | V18: 3746.5 | W18: 3526.3 | X18: 3668.2 | Y18: 3950.6 | AA18: 4742.5 | AB18: 4010.5 | AC18: 3024.2 | AD18: 3113.1
B20: 2. 추정 드라이버 | C20: 실적 열 = subQ 실현값(수식), 추정 열 = 가정(노란 = 모델값 역산, 연녹 = 3절 스칼라 참조)
A21: drv:매출액 | B21: yoy | C21: 매출액 YoY | J21: =IFERROR(subQ!J5/subQ!E5-1,"") | L21: =IFERROR(subQ!L5/subQ!G5-1,"") | M21: =IFERROR(subQ!M5/subQ!H5-1,"") | N21: =IFERROR(subQ!N5/subQ!I5-1,"") | O21: =IFERROR(subQ!O5/subQ!J5-1,"") | Q21: =IFERROR(subQ!Q5/subQ!L5-1,"") | R21: =IFERROR(subQ!R5/subQ!M5-1,"") | S21: =IFERROR(subQ!S5/subQ!N5-1,"") | T21: =IFERROR(subQ!T5/subQ!O5-1,"") | V21: =IFERROR(subQ!V5/subQ!Q5-1,"") | W21: =IFERROR(subQ!W5/subQ!R5-1,"") | X21: =IFERROR(subQ!X5/subQ!S5-1,"") | Y21: =IFERROR(subQ!Y5/subQ!T5-1,"") | AA21: =IFERROR(subQ!AA5/subQ!V5-1,"") | AB21: =IFERROR(subQ!AB5/subQ!W5-1,"") | AC21: 0.27633014 | AD21: 0.29048071 | AF21: 0.52646872 | AG21: 0.3398321 | AH21: 0.18332493 | AI21: 0.16243594 | AK21: 0.18038913 | AL21: 0.20891303 | AM21: 0.23321084 | AN21: 0.23787541
A22: drv:판관비 | B22: ratio | C22: 판관비율(/매출) | E22: =IFERROR(subQ!E8/subQ!E5,"") | F22: =IFERROR(subQ!F8/subQ!F5,"") | G22: =IFERROR(subQ!G8/subQ!G5,"") | H22: =IFERROR(subQ!H8/subQ!H5,"") | I22: =IFERROR(subQ!I8/subQ!I5,"") | J22: =IFERROR(subQ!J8/subQ!J5,"") | K22: =IFERROR(subQ!K8/subQ!K5,"") | L22: =IFERROR(subQ!L8/subQ!L5,"") | ... AB22: =IFERROR(subQ!AB8/subQ!AB5,"") | AC22: =$D$49 | AD22: =$D$49 | AE22: =IFERROR(subQ!AE8/subQ!AE5,"") | AF22: =$D$49 | AG22: =$D$49 | AH22: =$D$49 | AI22: =$D$49 | AJ22: =IFERROR(subQ!AJ8/subQ!AJ5,"") | AK22: =$D$49 | AL22: =$D$49 | AM22: =$D$49 | AN22: =$D$49 | AO22: =IFERROR(subQ!AO8/subQ!AO5,"")
A23: drv:영업이익 | B23: ratio | C23: 영업이익률(OPM) | E23: =IFERROR(subQ!E9/subQ!E5,"") | F23: =IFERROR(subQ!F9/subQ!F5,"") | G23: =IFERROR(subQ!G9/subQ!G5,"") | H23: =IFERROR(subQ!H9/subQ!H5,"") | I23: =IFERROR(subQ!I9/subQ!I5,"") | J23: =IFERROR(subQ!J9/subQ!J5,"") | K23: =IFERROR(subQ!K9/subQ!K5,"") | L23: =IFERROR(subQ!L9/subQ!L5,"") | ... AB23: =IFERROR(subQ!AB9/subQ!AB5,"") | AC23: -0.010587346 | AD23: -0.010551703 | AE23: =IFERROR(subQ!AE9/subQ!AE5,"") | AF23: -0.010558785 | AG23: -0.010586996 | AH23: -0.010544815 | AI23: -0.010581462 | AJ23: =IFERROR(subQ!AJ9/subQ!AJ5,"") | AK23: -0.010553294 | AL23: -0.010591472 | AM23: -0.010580411 | AN23: -0.010559397 | AO23: =IFERROR(subQ!AO9/subQ!AO5,"")
A24: drv:기타영업외손익 | B24: abs | C24: 기타영업외손익 (가정, 억원) | E24: =subQ!E13 | F24: =subQ!F13 | G24: =subQ!G13 | H24: =subQ!H13 | I24: =subQ!I13 | J24: =subQ!J13 | K24: =subQ!K13 | L24: =subQ!L13 | ... AB24: =subQ!AB13 | AC24: 0 | AD24: 0 | AE24: =subQ!AE13 | AF24: 0 | AG24: 0 | AH24: 0 | AI24: 0 | AJ24: =subQ!AJ13 | AK24: 0 | AL24: 0 | AM24: 0 | AN24: 0 | AO24: =subQ!AO13
A25: drv:지분법손익 | B25: abs | C25: 지분법손익 (가정, 억원) | E25: =subQ!E14 | F25: =subQ!F14 | G25: =subQ!G14 | H25: =subQ!H14 | I25: =subQ!I14 | J25: =subQ!J14 | K25: =subQ!K14 | L25: =subQ!L14 | ... AB25: =subQ!AB14 | AC25: 0.13 | AD25: 0.13 | AE25: =subQ!AE14 | AF25: 0.13 | AG25: 0.13 | AH25: 0.13 | AI25: 0.13 | AJ25: =subQ!AJ14 | AK25: 0.13 | AL25: 0.13 | AM25: 0.13 | AN25: 0.13 | AO25: =subQ!AO14
A26: drv:법인세비용 | B26: tax | C26: 법인세율(/세전) — 법인세 = MAX(세전,0) × 세율 | E26: =IFERROR(subQ!E16/subQ!E15,"") | F26: =IFERROR(subQ!F16/subQ!F15,"") | G26: =IFERROR(subQ!G16/subQ!G15,"") | H26: =IFERROR(subQ!H16/subQ!H15,"") | I26: =IFERROR(subQ!I16/subQ!I15,"") | J26: =IFERROR(subQ!J16/subQ!J15,"") | K26: =IFERROR(subQ!K16/subQ!K15,"") | L26: =IFERROR(subQ!L16/subQ!L15,"") | ... AB26: =IFERROR(subQ!AB16/subQ!AB15,"") | AC26: =$D$48 | AD26: =$D$48 | AE26: =IFERROR(subQ!AE16/subQ!AE15,"") | AF26: =$D$48 | AG26: =$D$48 | AH26: =$D$48 | AI26: =$D$48 | AJ26: =IFERROR(subQ!AJ16/subQ!AJ15,"") | AK26: =$D$48 | AL26: =$D$48 | AM26: =$D$48 | AN26: =$D$48 | AO26: =IFERROR(subQ!AO16/subQ!AO15,"")
A27: drv:지배주주순이익 | B27: ratio | C27: 지배주주 비중(/당기순이익) | E27: =IFERROR(subQ!E18/subQ!E17,"") | F27: =IFERROR(subQ!F18/subQ!F17,"") | G27: =IFERROR(subQ!G18/subQ!G17,"") | H27: =IFERROR(subQ!H18/subQ!H17,"") | I27: =IFERROR(subQ!I18/subQ!I17,"") | J27: =IFERROR(subQ!J18/subQ!J17,"") | K27: =IFERROR(subQ!K18/subQ!K17,"") | L27: =IFERROR(subQ!L18/subQ!L17,"") | ... AB27: =IFERROR(subQ!AB18/subQ!AB17,"") | AC27: =$D$50 | AD27: =$D$50 | AE27: =IFERROR(subQ!AE18/subQ!AE17,"") | AF27: =$D$50 | AG27: =$D$50 | AH27: =$D$50 | AI27: =$D$50 | AJ27: =IFERROR(subQ!AJ18/subQ!AJ17,"") | AK27: =$D$50 | AL27: =$D$50 | AM27: =$D$50 | AN27: =$D$50 | AO27: =IFERROR(subQ!AO18/subQ!AO17,"")
A28: drv:부채총계 | B28: qoq | C28: 부채총계 QoQ | G28: =IFERROR(subQ!G20/subQ!E20-1,"") | H28: =IFERROR(subQ!H20/subQ!G20-1,"") | I28: =IFERROR(subQ!I20/subQ!H20-1,"") | J28: =IFERROR(subQ!J20/subQ!I20-1,"") | L28: =IFERROR(subQ!L20/subQ!J20-1,"") | M28: =IFERROR(subQ!M20/subQ!L20-1,"") | N28: =IFERROR(subQ!N20/subQ!M20-1,"") | O28: =IFERROR(subQ!O20/subQ!N20-1,"") | Q28: =IFERROR(subQ!Q20/subQ!O20-1,"") | R28: =IFERROR(subQ!R20/subQ!Q20-1,"") | S28: =IFERROR(subQ!S20/subQ!R20-1,"") | T28: =IFERROR(subQ!T20/subQ!S20-1,"") | V28: =IFERROR(subQ!V20/subQ!T20-1,"") | W28: =IFERROR(subQ!W20/subQ!V20-1,"") | X28: =IFERROR(subQ!X20/subQ!W20-1,"") | Y28: =IFERROR(subQ!Y20/subQ!X20-1,"") | AA28: =IFERROR(subQ!AA20/subQ!Y20-1,"") | AB28: =IFERROR(subQ!AB20/subQ!AA20-1,"") | AC28: 1.195e-05 | AD28: 0 | AF28: 0 | AG28: 0 | AH28: 0 | AI28: 0 | AK28: 0 | AL28: 0 | AM28: 0 | AN28: 0
A29: drv:자본총계 | B29: roll | C29: 자본총계 기타변동(배당 등, 억원) | G29: =IFERROR(subQ!E21+subQ!G17-subQ!G21,"") | H29: =IFERROR(subQ!G21+subQ!H17-subQ!H21,"") | I29: =IFERROR(subQ!H21+subQ!I17-subQ!I21,"") | J29: =IFERROR(subQ!I21+subQ!J17-subQ!J21,"") | L29: =IFERROR(subQ!J21+subQ!L17-subQ!L21,"") | M29: =IFERROR(subQ!L21+subQ!M17-subQ!M21,"") | N29: =IFERROR(subQ!M21+subQ!N17-subQ!N21,"") | O29: =IFERROR(subQ!N21+subQ!O17-subQ!O21,"") | Q29: =IFERROR(subQ!O21+subQ!Q17-subQ!Q21,"") | R29: =IFERROR(subQ!Q21+subQ!R17-subQ!R21,"") | S29: =IFERROR(subQ!R21+subQ!S17-subQ!S21,"") | T29: =IFERROR(subQ!S21+subQ!T17-subQ!T21,"") | V29: =IFERROR(subQ!T21+subQ!V17-subQ!V21,"") | W29: =IFERROR(subQ!V21+subQ!W17-subQ!W21,"") | X29: =IFERROR(subQ!W21+subQ!X17-subQ!X21,"") | Y29: =IFERROR(subQ!X21+subQ!Y17-subQ!Y21,"") | AA29: =IFERROR(subQ!Y21+subQ!AA17-subQ!AA21,"") | AB29: =IFERROR(subQ!AA21+subQ!AB17-subQ!AB21,"") | AC29: -0.006684409 | AD29: -0.000973193 | AF29: -0.003420922 | AG29: 1.2607451 | AH29: -0.005711613 | AI29: 0.003170885 | AK29: 0.000936258 | AL29: 1.2575841 | AM29: -0.012956889 | AN29: 0.00661433
A30: drv:지배주주지분 | B30: roll | C30: 지배주주지분 기타변동(배당 등, 억원) | G30: =IFERROR(subQ!E22+subQ!G18-subQ!G22,"") | H30: =IFERROR(subQ!G22+subQ!H18-subQ!H22,"") | I30: =IFERROR(subQ!H22+subQ!I18-subQ!I22,"") | J30: =IFERROR(subQ!I22+subQ!J18-subQ!J22,"") | L30: =IFERROR(subQ!J22+subQ!L18-subQ!L22,"") | M30: =IFERROR(subQ!L22+subQ!M18-subQ!M22,"") | N30: =IFERROR(subQ!M22+subQ!N18-subQ!N22,"") | O30: =IFERROR(subQ!N22+subQ!O18-subQ!O22,"") | Q30: =IFERROR(subQ!O22+subQ!Q18-subQ!Q22,"") | R30: =IFERROR(subQ!Q22+subQ!R18-subQ!R22,"") | S30: =IFERROR(subQ!R22+subQ!S18-subQ!S22,"") | T30: =IFERROR(subQ!S22+subQ!T18-subQ!T22,"") | V30: =IFERROR(subQ!T22+subQ!V18-subQ!V22,"") | W30: =IFERROR(subQ!V22+subQ!W18-subQ!W22,"") | X30: =IFERROR(subQ!W22+subQ!X18-subQ!X22,"") | Y30: =IFERROR(subQ!X22+subQ!Y18-subQ!Y22,"") | AA30: =IFERROR(subQ!Y22+subQ!AA18-subQ!AA22,"") | AB30: =IFERROR(subQ!AA22+subQ!AB18-subQ!AB22,"") | AC30: -0.008233797 | AD30: -0.002125561 | AF30: 0.005589374 | AG30: 1.2505223 | AH30: 0.004692094 | AI30: -0.005982527 | AK30: 0.002233821 | AL30: 1.2504277 | AM30: 0.001122509 | AN30: -0.008723455
A31: drv:총차입금 | B31: qoq | C31: 총차입금 QoQ | G31: =IFERROR(subQ!G23/subQ!E23-1,"") | H31: =IFERROR(subQ!H23/subQ!G23-1,"") | I31: =IFERROR(subQ!I23/subQ!H23-1,"") | J31: =IFERROR(subQ!J23/subQ!I23-1,"") | L31: =IFERROR(subQ!L23/subQ!J23-1,"") | M31: =IFERROR(subQ!M23/subQ!L23-1,"") | N31: =IFERROR(subQ!N23/subQ!M23-1,"") | O31: =IFERROR(subQ!O23/subQ!N23-1,"") | Q31: =IFERROR(subQ!Q23/subQ!O23-1,"") | R31: =IFERROR(subQ!R23/subQ!Q23-1,"") | S31: =IFERROR(subQ!S23/subQ!R23-1,"") | T31: =IFERROR(subQ!T23/subQ!S23-1,"") | V31: =IFERROR(subQ!V23/subQ!T23-1,"") | W31: =IFERROR(subQ!W23/subQ!V23-1,"") | X31: =IFERROR(subQ!X23/subQ!W23-1,"") | Y31: =IFERROR(subQ!Y23/subQ!X23-1,"") | AA31: =IFERROR(subQ!AA23/subQ!Y23-1,"") | AB31: =IFERROR(subQ!AB23/subQ!AA23-1,"") | AC31: 2.1009e-05 | AD31: 0 | AF31: 0 | AG31: 0 | AH31: 0 | AI31: 0 | AK31: 0 | AL31: 0 | AM31: 0 | AN31: 0
A32: drv:순차입금 | B32: qoq | C32: 순차입금 QoQ | G32: =IFERROR(subQ!G24/subQ!E24-1,"") | H32: =IFERROR(subQ!H24/subQ!G24-1,"") | I32: =IFERROR(subQ!I24/subQ!H24-1,"") | J32: =IFERROR(subQ!J24/subQ!I24-1,"") | L32: =IFERROR(subQ!L24/subQ!J24-1,"") | M32: =IFERROR(subQ!M24/subQ!L24-1,"") | N32: =IFERROR(subQ!N24/subQ!M24-1,"") | O32: =IFERROR(subQ!O24/subQ!N24-1,"") | Q32: =IFERROR(subQ!Q24/subQ!O24-1,"") | R32: =IFERROR(subQ!R24/subQ!Q24-1,"") | S32: =IFERROR(subQ!S24/subQ!R24-1,"") | T32: =IFERROR(subQ!T24/subQ!S24-1,"") | V32: =IFERROR(subQ!V24/subQ!T24-1,"") | W32: =IFERROR(subQ!W24/subQ!V24-1,"") | X32: =IFERROR(subQ!X24/subQ!W24-1,"") | Y32: =IFERROR(subQ!Y24/subQ!X24-1,"") | AA32: =IFERROR(subQ!AA24/subQ!Y24-1,"") | AB32: =IFERROR(subQ!AB24/subQ!AA24-1,"") | AC32: 0.00401495 | AD32: 0.002947136 | AF32: 0.002571166 | AG32: -0.022348415 | AH32: -0.001124227 | AI32: -0.002063403 | AK32: -0.003571429 | AL32: -0.030937559 | AM32: -0.010901304 | AN32: -0.012792757
A33: drv:이자발생자산 | B33: qoq | C33: 이자발생자산 QoQ | G33: =IFERROR(subQ!G25/subQ!E25-1,"") | H33: =IFERROR(subQ!H25/subQ!G25-1,"") | I33: =IFERROR(subQ!I25/subQ!H25-1,"") | J33: =IFERROR(subQ!J25/subQ!I25-1,"") | L33: =IFERROR(subQ!L25/subQ!J25-1,"") | M33: =IFERROR(subQ!M25/subQ!L25-1,"") | N33: =IFERROR(subQ!N25/subQ!M25-1,"") | O33: =IFERROR(subQ!O25/subQ!N25-1,"") | Q33: =IFERROR(subQ!Q25/subQ!O25-1,"") | R33: =IFERROR(subQ!R25/subQ!Q25-1,"") | S33: =IFERROR(subQ!S25/subQ!R25-1,"") | T33: =IFERROR(subQ!T25/subQ!S25-1,"") | V33: =IFERROR(subQ!V25/subQ!T25-1,"") | W33: =IFERROR(subQ!W25/subQ!V25-1,"") | X33: =IFERROR(subQ!X25/subQ!W25-1,"") | Y33: =IFERROR(subQ!Y25/subQ!X25-1,"") | AA33: =IFERROR(subQ!AA25/subQ!Y25-1,"") | AB33: =IFERROR(subQ!AB25/subQ!AA25-1,"") | AC33: 0.002241055 | AD33: 0.001644906 | AF33: 0.001436929 | AG33: -0.012503843 | AH33: -0.00062273 | AI33: -0.001246235 | AK33: -0.001871686 | AL33: -0.017085113 | AM33: -0.005935347 | AN33: -0.006930376
A34: drv:현금및현금성자산 | B34: qoq | C34: 현금및현금성자산 QoQ | G34: =IFERROR(subQ!G26/subQ!E26-1,"") | H34: =IFERROR(subQ!H26/subQ!G26-1,"") | I34: =IFERROR(subQ!I26/subQ!H26-1,"") | J34: =IFERROR(subQ!J26/subQ!I26-1,"") | L34: =IFERROR(subQ!L26/subQ!J26-1,"") | M34: =IFERROR(subQ!M26/subQ!L26-1,"") | N34: =IFERROR(subQ!N26/subQ!M26-1,"") | O34: =IFERROR(subQ!O26/subQ!N26-1,"") | Q34: =IFERROR(subQ!Q26/subQ!O26-1,"") | R34: =IFERROR(subQ!R26/subQ!Q26-1,"") | S34: =IFERROR(subQ!S26/subQ!R26-1,"") | T34: =IFERROR(subQ!T26/subQ!S26-1,"") | V34: =IFERROR(subQ!V26/subQ!T26-1,"") | W34: =IFERROR(subQ!W26/subQ!V26-1,"") | X34: =IFERROR(subQ!X26/subQ!W26-1,"") | Y34: =IFERROR(subQ!Y26/subQ!X26-1,"") | AA34: =IFERROR(subQ!AA26/subQ!Y26-1,"") | AB34: =IFERROR(subQ!AB26/subQ!AA26-1,"")
A35: drv:CAPEX | B35: yoy | C35: CAPEX YoY | J35: =IFERROR(subQ!J27/subQ!E27-1,"") | L35: =IFERROR(subQ!L27/subQ!G27-1,"") | M35: =IFERROR(subQ!M27/subQ!H27-1,"") | N35: =IFERROR(subQ!N27/subQ!I27-1,"") | O35: =IFERROR(subQ!O27/subQ!J27-1,"") | Q35: =IFERROR(subQ!Q27/subQ!L27-1,"") | R35: =IFERROR(subQ!R27/subQ!M27-1,"") | S35: =IFERROR(subQ!S27/subQ!N27-1,"") | T35: =IFERROR(subQ!T27/subQ!O27-1,"") | V35: =IFERROR(subQ!V27/subQ!Q27-1,"") | W35: =IFERROR(subQ!W27/subQ!R27-1,"") | X35: =IFERROR(subQ!X27/subQ!S27-1,"") | Y35: =IFERROR(subQ!Y27/subQ!T27-1,"") | AA35: =IFERROR(subQ!AA27/subQ!V27-1,"") | AB35: =IFERROR(subQ!AB27/subQ!W27-1,"") | AC35: -0.032976585 | AD35: -0.7253256 | AF35: 56.051282 | AG35: 0.03626943 | AH35: 0 | AI35: 0 | AK35: 0 | AL35: 0 | AM35: 0 | AN35: 0
A36: drv:영업활동현금흐름 | B36: yoy | C36: 영업활동현금흐름 YoY | J36: =IFERROR(subQ!J28/subQ!E28-1,"") | L36: =IFERROR(subQ!L28/subQ!G28-1,"") | M36: =IFERROR(subQ!M28/subQ!H28-1,"") | N36: =IFERROR(subQ!N28/subQ!I28-1,"") | O36: =IFERROR(subQ!O28/subQ!J28-1,"") | Q36: =IFERROR(subQ!Q28/subQ!L28-1,"") | R36: =IFERROR(subQ!R28/subQ!M28-1,"") | S36: =IFERROR(subQ!S28/subQ!N28-1,"") | T36: =IFERROR(subQ!T28/subQ!O28-1,"") | V36: =IFERROR(subQ!V28/subQ!Q28-1,"") | W36: =IFERROR(subQ!W28/subQ!R28-1,"") | X36: =IFERROR(subQ!X28/subQ!S28-1,"") | Y36: =IFERROR(subQ!Y28/subQ!T28-1,"") | AA36: =IFERROR(subQ!AA28/subQ!V28-1,"") | AB36: =IFERROR(subQ!AB28/subQ!W28-1,"")
A37: drv:주식수 | B37: qoq | C37: 주식수 QoQ | G37: =IFERROR(subQ!G29/subQ!E29-1,"") | H37: =IFERROR(subQ!H29/subQ!G29-1,"") | I37: =IFERROR(subQ!I29/subQ!H29-1,"") | J37: =IFERROR(subQ!J29/subQ!I29-1,"") | L37: =IFERROR(subQ!L29/subQ!J29-1,"") | M37: =IFERROR(subQ!M29/subQ!L29-1,"") | N37: =IFERROR(subQ!N29/subQ!M29-1,"") | O37: =IFERROR(subQ!O29/subQ!N29-1,"") | Q37: =IFERROR(subQ!Q29/subQ!O29-1,"") | R37: =IFERROR(subQ!R29/subQ!Q29-1,"") | S37: =IFERROR(subQ!S29/subQ!R29-1,"") | T37: =IFERROR(subQ!T29/subQ!S29-1,"") | V37: =IFERROR(subQ!V29/subQ!T29-1,"") | W37: =IFERROR(subQ!W29/subQ!V29-1,"") | X37: =IFERROR(subQ!X29/subQ!W29-1,"") | Y37: =IFERROR(subQ!Y29/subQ!X29-1,"") | AA37: =IFERROR(subQ!AA29/subQ!Y29-1,"") | AB37: =IFERROR(subQ!AB29/subQ!AA29-1,"") | AC37: 0 | AD37: 0 | AF37: 0 | AG37: 0 | AH37: 0 | AI37: 0 | AK37: 0 | AL37: 0 | AM37: 0 | AN37: 0
A38: drv:DPS | B38: abs | C38: DPS (가정, 원) | E38: =subQ!E32 | F38: =subQ!F32 | G38: =subQ!G32 | H38: =subQ!H32 | I38: =subQ!I32 | J38: =subQ!J32 | K38: =subQ!K32 | L38: =subQ!L32 | ... AB38: =subQ!AB32 | AD38: 10 | AE38: =subQ!AE32 | AI38: 10 | AJ38: =subQ!AJ32 | AN38: 10 | AO38: =subQ!AO32
B40: 3. 밸류에이션·스칼라 | C40: 노란 셀 = 가정. '연결' 표시는 추정 전 분기 수식이 이 셀을 참조한다는 뜻
A41: sc:종가 | C41: 종가 | D41: 2950 | E41: 원 — 네이버 정규장 종가(aik 확정종가 대조 · aik 2,975원)
A42: sc:기준일 | C42: 기준일 | D42: 20261026 | E42: 종가 기준일
A43: sc:COE | C43: COE | D43: 0.09 | E43: 자기자본비용(가정) — TP 적정 PBR = ROE/COE
A44: sc:PER_lo | C44: PER_lo | D44: 10 | E44: PER 밴드 하단(배) — sector_default(레퍼런스 TP_PE PB 예시 10/15/20배; 과거 PER 중위 45.5배가 3~40 밖(턴어라운드 왜곡))
A45: sc:PER_mid | C45: PER_mid | D45: 15 | E45: PER 밴드 중단(배)
A46: sc:PER_hi | C46: PER_hi | D46: 20 | E46: PER 밴드 상단(배)
A47: sc:EPS_Y1가중 | C47: EPS_Y1가중 | D47: 0.5 | E47: 12M fwd EPS = FY(last_actual연도)E × w + FY+1E × (1−w) — 기준 분기 2Q 이면 0.5(가정)
A48: sc:세율 | C48: 세율 | D48: 0.16923077 | E48: 연결 — 법인세 = MAX(세전,0) × 세율(역산, 재현 오차 ≤ 0.05억 · 모델 assumptions 0.155) · 최근 12분기 유효세율 15.5%(5~27% 안 — 그대로)
A49: sc:판관비율 | C49: 판관비율 | D49: 0.14715306 | E49: 연결 — 판관비 = 매출액 × 판관비율(역산, 재현 오차 ≤ 0.05억 · 모델 assumptions 0.1472)
A50: sc:지배주주비중 | C50: 지배주주비중 | D50: 0.99275362 | E50: 연결 — 지배주주순이익 = 당기순이익 × 비중(역산, 재현 오차 ≤ 0.05억)
A51: sc:이자율_자산 | C51: 이자율_자산 | D51: 0.074490433 | E51: 연결 — 이자손익 = (전분기 이자발생자산 × 자산이자율 − 전분기 총차입금 × 부채이자율)/4(역산, 재현 오차 ≤ 0.05억 · 모델 assumptions 0.0745)
A52: sc:이자율_부채 | C52: 이자율_부채 | D52: 0 | E52: 연결 — 같은 수식의 부채 쪽(총차입금 행이 없으면 0)(역산, 재현 오차 ≤ 0.05억)
A53: sc:배당성향 | C53: 배당성향 | D53: 0.1058 | E53: 배당성향(참고 — 모델은 직전 DPS 유지·Q2 지급 가정)
A54: sc:외화순노출_백만$ | C54: 외화순노출_백만$ | E54: 외화 순노출 × Δ기말환율 (외화 시트 방식) — 외화 순노출 미공시(face) → 0 + 표기
A55: sc:헤지비율 | C55: 헤지비율 | E55: sls 없음
A56: sc:헤지환율_약정 | C56: 헤지환율_약정 | E56: sls 없음

Sheet BS연결
B1: (백만원) | C1: 이름: BS연결H | E1: 4Q21 | F1: 2021 | G1: 1Q22 | H1: 2Q22 | I1: 3Q22 | J1: 4Q22 | K1: 2022 | L1: 1Q23 | M1: 2Q23 | N1: 3Q23 | O1: 4Q23 | P1: 2023 | Q1: 1Q24 | R1: 2Q24 | S1: 3Q24 | T1: 4Q24 | U1: 2024 | V1: 1Q25 | W1: 2Q25 | X1: 3Q25 | Y1: 4Q25 | Z1: 2025 | AA1: 1Q26 | AB1: 2Q26 | AC1: 3Q26 | AD1: 4Q26 | AE1: 2026 | AF1: 1Q27 | AG1: 2Q27 | AH1: 3Q27 | AI1: 4Q27 | AJ1: 2027 | AK1: 1Q28 | AL1: 2Q28 | AM1: 3Q28 | AN1: 4Q28 | AO1: 2028
B2: 연결 | D2: fin json(kship_fin.py)
B3: 서암기계공업(연) | C3: UPDATE: 26-10-26 | E3: 1 | F3: 2 | G3: 3 | H3: 4 | I3: 5 | J3: 6 | K3: 7 | L3: 8 | M3: 9 | N3: 10 | O3: 11 | P3: 12 | Q3: 13 | R3: 14 | S3: 15 | T3: 16 | U3: 17 | V3: 18 | W3: 19 | X3: 20 | Y3: 21 | Z3: 22 | AA3: 23 | AB3: 24 | AC3: 25 | AD3: 26 | AE3: 27 | AF3: 28 | AG3: 29 | AH3: 30 | AI3: 31 | AJ3: 32 | AK3: 33 | AL3: 34 | AM3: 35 | AN3: 36 | AO3: 37
B4: Account Code | C4: AccountNAME | E4: 2021.12 | F4: 2021.12A | G4: 2022.03 | H4: 2022.06 | I4: 2022.09 | J4: 2022.12 | K4: 2022.12A | L4: 2023.03 | M4: 2023.06 | N4: 2023.09 | O4: 2023.12 | P4: 2023.12A | Q4: 2024.03 | R4: 2024.06 | S4: 2024.09 | T4: 2024.12 | U4: 2024.12A | V4: 2025.03 | W4: 2025.06 | X4: 2025.09 | Y4: 2025.12 | Z4: 2025.12A | AA4: 2026.03 | AB4: 2026.06 | AC4: 2026.09 | AD4: 2026.12 | AE4: 2026.12A | AF4: 2027.03 | AG4: 2027.06 | AH4: 2027.09 | AI4: 2027.12 | AJ4: 2027.12A | AK4: 2028.03 | AL4: 2028.06 | AM4: 2028.09 | AN4: 2028.12 | AO4: 2028.12A
A5: 1 | C5: 유동자산 | X5: 58492.5 | Y5: 57064.45 | Z5: 57064.45 | AA5: 57103.41 | AB5: 60690.01
A6: 1 | C6: 현금및현금성자산 | X6: 10922.17 | Y6: 9134.46 | Z6: 9134.46 | AA6: 7468.59 | AB6: 9215.21
A7: 1 | C7: 기타유동금융자산 | X7: 21314.3 | Y7: 23194.6 | Z7: 23194.6 | AA7: 23874.54 | AB7: 22080.68
A8: 1 | C8: 매출채권및기타채권 | X8: 9486.17 | Y8: 8073.9 | Z8: 8073.9 | AA8: 8923.29 | AB8: 9899.12
A9: 1 | C9: 재고자산 | X9: 15588 | Y9: 15763.59 | Z9: 15763.59 | AA9: 16392.61 | AB9: 16831.14
A10: 1 | C10: 당기법인세자산(선급법인세) | X10: 0 | Y10: 264.02 | Z10: 264.02 | AA10: 71.95
A11: 1 | C11: 기타유동자산 | X11: 1181.86 | Y11: 633.87 | Z11: 633.87 | AA11: 372.43 | AB11: 663.87
A12: 1 | C12: 비유동자산 | X12: 24799.19 | Y12: 25715.17 | Z12: 25715.17 | AA12: 25279.58 | AB12: 24410.74
A13: 1 | C13: 투자부동산 | X13: 1048.59 | Y13: 1031.41 | Z13: 1031.41 | AA13: 1014.23 | AB13: 997.04
A14: 1 | C14: 장기금융자산 | X14: 559.71 | Y14: 459.57 | Z14: 459.57 | AA14: 454.36 | AB14: 490.04
A15: 1 | C15: 투자자산 | X15: 559.71 | Y15: 459.57 | Z15: 459.57 | AA15: 454.36 | AB15: 490.04
A16: 1 | C16: 유형자산 | X16: 20546.72 | Y16: 20582.79 | Z16: 20582.79 | AA16: 20072.35 | AB16: 19591.44
A17: 1 | C17: 무형자산 | X17: 505.82 | Y17: 505.21 | Z17: 505.21 | AA17: 506.01 | AB17: 506.15
A18: 1 | C18: 이연법인세자산 | X18: 0 | Y18: 828.79 | Z18: 828.79 | AA18: 811.12 | AB18: 819.15
A19: 1 | C19: 자산총계 | X19: 83291.7 | Y19: 82779.61 | Z19: 82779.61 | AA19: 82382.99 | AB19: 85100.75
A20: 1 | C20: 유동부채 | X20: 15364.56 | Y20: 13055.06 | Z20: 13055.06 | AA20: 12535.35 | AB20: 14342.65
A21: 1 | C21: 매입채무및기타채무 | X21: 5466.82 | Y21: 5021.46 | Z21: 5021.46 | AA21: 4700.94 | AB21: 5361.35
A22: 1 | C22: 기타유동금융부채 | X22: 3736.19 | Y22: 3295.95 | Z22: 3295.95 | AA22: 3448.53 | AB22: 3792.54
A23: 1 | C23: 단기금융부채 | X23: 3999.78 | Y23: 3562.26 | Z23: 3562.26 | AA23: 3729.2 | AB23: 4082.31
A24: 1 | C24: 당기법인세부채(미지급법인세) | X24: 33.3 | Y24: 3.23 | Z24: 3.23 | AA24: 0
A25: 1 | C25: 유동리스부채 | X25: 263.59 | Y25: 266.31 | Z25: 266.31 | AA25: 280.67 | AB25: 289.77
A26: 1 | C26: 리스부채 | X26: 1020.38 | Y26: 1146.41 | Z26: 1146.41 | AA26: 1139.49 | AB26: 1101.18
A27: 1 | C27: 기타유동부채 | X27: 2089.73 | Y27: 797.58 | Z27: 797.58 | AA27: 318.3 | AB27: 829.12
A28: 1 | C28: 단기차입금 | X28: 3774.92 | Y28: 3670.52 | Z28: 3670.52 | AA28: 3786.92 | AB28: 3807.92
A29: 1 | C29: 단기금융부채(face) | X29: 3774.92 | AA29: 3786.92 | AB29: 3807.92
A30: 1 | C30: 비유동부채 | X30: 834.91 | Y30: 1741.01 | Z30: 1741.01 | AA30: 1426.22 | AB30: 2393.15
A31: 1 | C31: 비유동리스부채 | X31: 756.79 | Y31: 880.1 | Z31: 880.1 | AA31: 858.82 | AB31: 811.41
A32: 1 | C32: 장기금융부채 | X32: 756.79 | Y32: 880.1 | Z32: 880.1 | AA32: 858.82 | AB32: 1668.19
A33: 1 | C33: 이연법인세부채 | X33: 78.12 | Y33: 860.91 | Z33: 860.91 | AA33: 567.4 | AB33: 724.95
A34: 1 | C34: 부채총계 | X34: 16199.47 | Y34: 14796.07 | Z34: 14796.07 | AA34: 13961.57 | AB34: 16735.8
A35: 1 | C35: 지배주주지분 | X35: 66137.48 | Y35: 66944.19 | Z35: 66944.19 | AA35: 67350.85 | AB35: 68364.95
A36: 1 | C36: 자본금 | X36: 6300 | Y36: 6300 | Z36: 6300 | AA36: 6300 | AB36: 6300
A37: 1 | C37: 자본잉여금 | X37: 10412.2 | Y37: 10412.2 | Z37: 10412.2 | AA37: 10412.2 | AB37: 10412.2
A38: 1 | C38: 기타자본 | X38: 1.58 | Y38: 1.58 | Z38: 1.58 | AA38: 1.58 | AB38: 1.58
A39: 1 | C39: 기타포괄이익누계액 | X39: 622.38 | Y39: 565.12 | Z39: 565.12 | AA39: 1065.22 | AB39: 972.81
A40: 1 | C40: 이익잉여금 | X40: 48801.32 | Y40: 49665.29 | Z40: 49665.29 | AA40: 49571.85 | AB40: 50678.37
A41: 1 | C41: 비지배주주지분 | X41: 954.75 | Y41: 1039.36 | Z41: 1039.36 | AA41: 1070.56 | AB41: 0
... A46: 1 | C46: 이자발생자산 | X46: 11481.88 | Y46: 9594.03 | Z46: 9594.03 | AA46: 7922.95 | AB46: 9705.25
A47: 1 | C47: 단기투자자산(공정가치) | AB47: 2000
A48: 1 | C48: 기타비유동금융부채 | AB48: 856.78
A49: 1 | C49: 매출액(수익) | X49: 12432.52 | Y49: 12851.8 | AA49: 11043.79 | AB49: 13465.12
A50: 1 | C50: 매출원가 | X50: 10654.94 | Y50: 10681.92 | AA50: 9422.9 | AB50: 10508.31
A51: 1 | C51: 매출총이익 | X51: 1777.58 | Y51: 2169.88 | AA51: 1620.89 | AB51: 2956.81
A52: 1 | C52: 판관비 | X52: 1625.08 | Y52: 1879.59 | AA52: 1989.82 | AB52: 1993.5
A53: 1 | C53: 영업이익 | X53: 152.5 | Y53: 290.29 | AA53: -368.93 | AB53: 963.31
A54: 1 | C54: 기타영업외수익 | X54: 1589.84 | Y54: 233.53 | AA54: 363.48 | AB54: 219.5
A55: 1 | C55: 기타영업외비용 | X55: 863.03 | Y55: 63.93 | AA55: 167.65 | AB55: 47.53
A56: 1 | C56: 종속기업,공동지배기업및관계기업관련손익 | X56: 11.19 | Y56: 23.76 | AA56: 0 | AB56: 15.26
A57: 1 | C57: 지분법관련손익 | X57: 11.19 | Y57: 23.76 | AA57: 0 | AB57: 15.26
A58: 1 | C58: 금융수익 | X58: 181.17 | Y58: 180.75 | AA58: 176.74 | AB58: 184.39
A59: 1 | C59: 금융비용 | X59: 21.91 | Y59: -1.36 | AA59: 13.92 | AB59: 16.28
A60: 1 | C60: 법인세비용차감전계속사업이익 | X60: 1049.76 | Y60: 649.33 | AA60: -36.82 | AB60: 1318.65
... A69: 1 | C69: 이자수익 | X69: 181.17 | Y69: 180.74 | AA69: 176.74 | AB69: 181.75
A70: 1 | C70: 배당금수익 | X70: 0 | Y70: 0 | AB70: 2.64
A71: 1 | C71: 이자비용 | AA71: 13.92 | AB71: 16.28
A72: 1 | C72: 이자손익 | AA72: 162.82 | AB72: 165.47
A73: 1 | C73: 영업활동으로인한현금흐름 | X73: -727.64 | Y73: 1040.26 | AA73: -1437.28 | AB73: 2020.03
A74: 1 | C74: 배당금수취(CF) | X74: 0 | Y74: 0
A75: 1 | C75: 이자수취(CF) | X75: 480.96 | Y75: 374.48 | AA75: 16.5 | AB75: 5.06
A76: 1 | C76: 법인세납부(CF) | X76: -74.07 | Y76: -57.52 | AA76: -2.34 | AB76: 124.79
A77: 1 | C77: 투자활동으로인한현금흐름 | X77: 2475.23 | Y77: -2689.01 | AA77: -436.09 | AB77: -169.27
A78: 1 | C78: 유형자산의증가 | X78: 184.07 | Y78: 648.04 | AA78: 3.12 | AB78: 171.77
A79: 1 | C79: CAPEX | X79: 184.07 | Y79: 648.04 | AA79: 3.12 | AB79: 171.77
A80: 1 | C80: 유형자산의감소 | X80: 29.18 | Y80: -0.73
A81: 1 | C81: 재무활동으로인한현금흐름 | X81: 3696.77 | Y81: -69.94 | AA81: -73.39 | AB81: -197.13
A82: 1 | C82: 배당금지급 | X82: 0 | Y82: 0
A83: 1 | C83: 현금및현금성자산의증감 | X83: 11189.86 | Y83: -3506.41 | AA83: -3612.63 | AB83: 3400.25
A84: 1 | C84: 기말현금및현금성자산 | X84: 5745.5 | Y84: -1787.71 | AA84: 7468.59 | AB84: 1746.62
A85: 1 | C85: 단기차입금의증가 | Y85: 0

Sheet BS별도
B1: (백만원) | C1: 이름: BS별도H | E1: 4Q21 | F1: 2021 | G1: 1Q22 | H1: 2Q22 | I1: 3Q22 | J1: 4Q22 | K1: 2022 | L1: 1Q23 | M1: 2Q23 | N1: 3Q23 | O1: 4Q23 | P1: 2023 | Q1: 1Q24 | R1: 2Q24 | S1: 3Q24 | T1: 4Q24 | U1: 2024 | V1: 1Q25 | W1: 2Q25 | X1: 3Q25 | Y1: 4Q25 | Z1: 2025 | AA1: 1Q26 | AB1: 2Q26 | AC1: 3Q26 | AD1: 4Q26 | AE1: 2026 | AF1: 1Q27 | AG1: 2Q27 | AH1: 3Q27 | AI1: 4Q27 | AJ1: 2027 | AK1: 1Q28 | AL1: 2Q28 | AM1: 3Q28 | AN1: 4Q28 | AO1: 2028
B2: 별도 | D2: fin json(kship_fin.py)
B3: 서암기계공업(별) | C3: UPDATE: 26-10-26 | E3: 1 | F3: 2 | G3: 3 | H3: 4 | I3: 5 | J3: 6 | K3: 7 | L3: 8 | M3: 9 | N3: 10 | O3: 11 | P3: 12 | Q3: 13 | R3: 14 | S3: 15 | T3: 16 | U3: 17 | V3: 18 | W3: 19 | X3: 20 | Y3: 21 | Z3: 22 | AA3: 23 | AB3: 24 | AC3: 25 | AD3: 26 | AE3: 27 | AF3: 28 | AG3: 29 | AH3: 30 | AI3: 31 | AJ3: 32 | AK3: 33 | AL3: 34 | AM3: 35 | AN3: 36 | AO3: 37
B4: Account Code | C4: AccountNAME | E4: 2021.12 | F4: 2021.12A | G4: 2022.03 | H4: 2022.06 | I4: 2022.09 | J4: 2022.12 | K4: 2022.12A | L4: 2023.03 | M4: 2023.06 | N4: 2023.09 | O4: 2023.12 | P4: 2023.12A | Q4: 2024.03 | R4: 2024.06 | S4: 2024.09 | T4: 2024.12 | U4: 2024.12A | V4: 2025.03 | W4: 2025.06 | X4: 2025.09 | Y4: 2025.12 | Z4: 2025.12A | AA4: 2026.03 | AB4: 2026.06 | AC4: 2026.09 | AD4: 2026.12 | AE4: 2026.12A | AF4: 2027.03 | AG4: 2027.06 | AH4: 2027.09 | AI4: 2027.12 | AJ4: 2027.12A | AK4: 2028.03 | AL4: 2028.06 | AM4: 2028.09 | AN4: 2028.12 | AO4: 2028.12A
A5: 1 | C5: 유동자산 | E5: 51725.68 | F5: 51725.68 | G5: 52600.82 | H5: 52502.54 | I5: 54399.41 | J5: 54124.44 | K5: 54124.44 | L5: 51837.69 | M5: 51984.93 | N5: 51456.51 | O5: 52714.72 | P5: 52714.72 | Q5: 52492.54 | R5: 53439.64 | S5: 52077.75 | T5: 52968.52 | U5: 52968.52 | V5: 53613.69 | W5: 54752.16 | X5: 51098.53 | Y5: 49404.82 | Z5: 49404.82 | AA5: 49869.03 | AB5: 52090.99
A6: 1 | C6: 현금및현금성자산 | E6: 1833.72 | F6: 1833.72 | G6: 1432.96 | H6: 2537.75 | I6: 2677.9 | J6: 3622.73 | K6: 3622.73 | L6: 1616.09 | M6: 2304.68 | N6: 2278.07 | O6: 3377.9 | P6: 3377.9 | Q6: 2449.17 | R6: 3471.53 | S6: 3284.26 | T6: 4307.22 | U6: 4307.22 | V6: 3753.11 | W6: 5176.67 | X6: 6004.85 | Y6: 4177.1 | Z6: 4177.1 | AA6: 1780.49 | AB6: 3255.78
A7: 1 | C7: 기타유동금융자산 | E7: 28623.55 | F7: 28623.55 | G7: 27595.31 | H7: 27338.25 | I7: 27340.22 | J7: 26927.16 | K7: 26927.16 | L7: 25616.47 | M7: 25013.26 | N7: 24117.23 | O7: 23875.48 | P7: 23875.48 | Q7: 24112.94 | R7: 24354.16 | S7: 25065.14 | T7: 24852.28 | U7: 24852.28 | V7: 25059.08 | W7: 25254.99 | X7: 21314.3 | Y7: 23194.6 | Z7: 23194.6 | AA7: 23874.54 | AB7: 22080.68
A8: 1 | C8: 매출채권및기타채권 | E8: 8084.52 | F8: 8084.52 | G8: 9131.73 | H8: 8234.24 | I8: 10358.78 | J8: 8809.91 | K8: 8809.91 | L8: 9097.44 | M8: 7961.39 | N8: 8009.15 | O8: 8326.53 | P8: 8326.53 | Q8: 8913.28 | R8: 9204.23 | S8: 7999.21 | T8: 7527.22 | U8: 7527.22 | V8: 7936.06 | W8: 8367.89 | X8: 8420.66 | Y8: 6899.87 | Z8: 6899.87 | AA8: 8379.58 | AB8: 9055.72
A9: 1 | C9: 재고자산 | E9: 12689.02 | F9: 12689.02 | G9: 12919.41 | H9: 12892.89 | I9: 13657.59 | J9: 14070.46 | K9: 14070.46 | L9: 15199.69 | M9: 16371.53 | N9: 16948.07 | O9: 17018.62 | P9: 17018.62 | Q9: 16730.64 | R9: 16311.3 | S9: 15581.75 | T9: 15959.91 | U9: 15959.91 | V9: 16146.28 | W9: 15157.7 | X9: 14612.36 | Y9: 14882.95 | Z9: 14882.95 | AA9: 15531.3 | AB9: 15424.46
A10: 1 | C10: 당기법인세자산(선급법인세) | E10: 0 | F10: 0 | J10: 0 | K10: 0 | O10: 20.78 | P10: 20.78 | Q10: 21.67 | R10: 0 | S10: 37.95 | T10: 71.67 | U10: 71.67 | V10: 72.95 | W10: 4.11 | X10: 0 | Y10: 126.42 | Z10: 126.42 | AA10: 127.6
A11: 1 | C11: 기타유동자산 | E11: 494.87 | F11: 494.87 | G11: 1521.41 | H11: 1499.41 | I11: 364.93 | J11: 694.18 | K11: 694.18 | L11: 308 | M11: 334.07 | N11: 103.99 | O11: 95.41 | P11: 95.41 | Q11: 264.84 | R11: 98.43 | S11: 109.45 | T11: 250.22 | U11: 250.22 | V11: 646.22 | W11: 790.79 | X11: 746.36 | Y11: 123.87 | Z11: 123.87 | AA11: 175.51 | AB11: 274.36
A12: 1 | C12: 비유동자산 | E12: 21265.5 | F12: 21265.5 | G12: 22564.07 | H12: 22304.12 | I12: 22016.33 | J12: 21522.19 | K12: 21522.19 | L12: 23670.01 | M12: 23682.98 | N12: 23249.81 | O12: 23088.12 | P12: 23088.12 | Q12: 22949.61 | R12: 22044.76 | S12: 21472.27 | T12: 20893.2 | U12: 20893.2 | V12: 20361.22 | W12: 20070.78 | X12: 28349.13 | Y12: 28631.62 | Z12: 28631.62 | AA12: 28285.38 | AB12: 27563.2
A13: 1 | C13: 투자부동산 | E13: 1306.32 | F13: 1306.32 | G13: 1289.13 | H13: 1271.95 | I13: 1254.77 | J13: 1237.59 | K13: 1237.59 | L13: 1220.41 | M13: 1203.22 | N13: 1186.04 | O13: 1168.86 | P13: 1168.86 | Q13: 1151.68 | R13: 1134.5 | S13: 1117.32 | T13: 1100.13 | U13: 1100.13 | V13: 1082.95 | W13: 1065.77 | X13: 1048.59 | Y13: 1031.41 | Z13: 1031.41 | AA13: 1014.23 | AB13: 997.04
A14: 1 | C14: 장기금융자산 | E14: 367.82 | F14: 367.82 | G14: 334.82 | H14: 346.04 | I14: 668.12 | J14: 431.84 | K14: 431.84 | L14: 390.26 | M14: 552.62 | N14: 15.84 | O14: 245.84 | P14: 245.84 | Q14: 258.68 | R14: 258.68 | S14: 258.68 | T14: 268.82 | U14: 268.82 | V14: 269.82 | W14: 269.82 | X14: 269.82 | Y14: 269.82 | Z14: 269.82 | AA14: 269.82 | AB14: 269.82
A15: 1 | C15: 투자자산 | E15: 367.82 | F15: 367.82 | G15: 334.82 | H15: 346.04 | I15: 668.12 | J15: 431.84 | K15: 431.84 | L15: 390.26 | M15: 552.62 | N15: 15.84 | O15: 245.84 | P15: 245.84 | Q15: 258.68 | R15: 258.68 | S15: 258.68 | T15: 268.82 | U15: 268.82 | V15: 269.82 | W15: 269.82 | X15: 8973.89 | Y15: 8973.89 | Z15: 8973.89 | AA15: 9023.89 | AB15: 269.82
A16: 1 | C16: 유형자산 | E16: 17190.44 | F16: 17190.44 | G16: 18459.78 | H16: 18282.54 | I16: 17753.54 | J16: 17549.82 | K16: 17549.82 | L16: 19703.09 | M16: 19619.17 | N16: 19052.68 | O16: 18567.59 | P16: 18567.59 | Q16: 18223.12 | R16: 17601.81 | S16: 16996.85 | T16: 16458.45 | U16: 16458.45 | V16: 15903.34 | W16: 15353.04 | X16: 14966.26 | Y16: 15104.39 | Z16: 15104.39 | AA16: 14623.06 | AB16: 14316.68
A17: 1 | C17: 무형자산 | E17: 291.82 | F17: 291.82 | G17: 330 | H17: 337.26 | I17: 337.26 | J17: 337.26 | K17: 337.26 | L17: 477.26 | M17: 480.2 | N17: 480.2 | O17: 480.2 | P17: 480.2 | Q17: 480.2 | R17: 480.2 | S17: 480.2 | T17: 480.2 | U17: 480.2 | V17: 480.2 | W17: 480.2 | X17: 480.2 | Y17: 480.2 | Z17: 480.2 | AA17: 480.2 | AB17: 480.2
A18: 1 | C18: 이연법인세자산 | E18: 638.15 | F18: 638.15 | G18: 642.13 | H18: 601.67 | I18: 543.98 | J18: 522.92 | K18: 522.92 | L18: 429.5 | M18: 389.83 | N18: 497.97 | O18: 601.08 | P18: 601.08 | Q18: 496 | R18: 599.54 | S18: 692.74 | T18: 732.05 | U18: 732.05 | V18: 712.89 | W18: 644.76 | X18: 741.84 | Y18: 828.79 | Z18: 828.79 | AA18: 811.12 | AB18: 819.15
A19: 1 | C19: 자산총계 | E19: 72991.17 | F19: 72991.17 | G19: 75164.89 | H19: 74806.65 | I19: 76415.74 | J19: 75646.63 | K19: 75646.63 | L19: 75507.7 | M19: 75667.91 | N19: 74706.32 | O19: 75802.84 | P19: 75802.84 | Q19: 75442.15 | R19: 75484.4 | S19: 73550.02 | T19: 73861.72 | U19: 73861.72 | V19: 73974.92 | W19: 74822.94 | X19: 79447.66 | Y19: 78036.43 | Z19: 78036.43 | AA19: 78154.41 | AB19: 79654.19
A20: 1 | C20: 유동부채 | E20: 10616.16 | F20: 10616.16 | G20: 12529.69 | H20: 11730.99 | I20: 12163.91 | J20: 11508.92 | K20: 11508.92 | L20: 11327.7 | M20: 10473.56 | N20: 9506.52 | O20: 10108.97 | P20: 10108.97 | Q20: 10236.06 | R20: 9928.58 | S20: 8084.92 | T20: 8287.75 | U20: 8287.75 | V20: 8901.67 | W20: 9171.73 | X20: 13363.21 | Y20: 11706.42 | Z20: 11706.42 | AA20: 11704.04 | AB20: 12972.13
A21: 1 | C21: 기타유동금융부채 | E21: 3414.49 | F21: 3414.49 | G21: 3768.95 | H21: 3744.93 | I21: 3910.48 | J21: 3526.79 | K21: 3526.79 | L21: 3442.52 | M21: 3798.33 | N21: 3611.54 | O21: 3101.76 | P21: 3101.76 | Q21: 2975.32 | R21: 3193.24 | S21: 3255.26 | T21: 3127.89 | U21: 3127.89 | V21: 3124 | W21: 3342.34 | X21: 3436.51 | Y21: 2883.44 | Z21: 2883.44 | AA21: 3015.42 | AB21: 3380.97
A22: 1 | C22: 단기금융부채 | E22: 3448.05 | F22: 3448.05 | G22: 3799.86 | H22: 3773.18 | I22: 3936.07 | J22: 3547.32 | K22: 3547.32 | L22: 3458.5 | M22: 3809.75 | N22: 3618.41 | O22: 3117.19 | P22: 3117.19 | Q22: 3005.75 | R22: 3218.77 | S22: 3275.9 | T22: 3151.17 | U22: 3151.17 | V22: 3168.47 | W22: 3382.24 | X22: 3471.83 | Y22: 2914.19 | Z22: 2914.19 | AA22: 3047.6 | AB22: 3415.69
A23: 1 | C23: 당기법인세부채(미지급법인세) | E23: 108.51 | F23: 108.51 | G23: 150.38 | H23: 227.45 | I23: 332.04 | J23: 259.09 | K23: 259.09 | L23: 241.46 | M23: 232.02 | N23: 133.54 | O23: 23.95 | P23: 23.95 | Q23: 23.95 | R23: 38.37 | S23: 8.16 | T23: 9.53 | U23: 9.53 | V23: 3.24 | W23: 0 | X23: 33.3 | Y23: 0 | Z23: 0 | AA23: 0
A24: 1 | C24: 유동리스부채 | E24: 33.56 | F24: 33.56 | G24: 30.91 | H24: 28.25 | I24: 25.59 | J24: 20.53 | K24: 20.53 | L24: 15.98 | M24: 11.42 | N24: 6.87 | O24: 15.43 | P24: 15.43 | Q24: 30.43 | R24: 25.53 | S24: 20.64 | T24: 23.28 | U24: 23.28 | V24: 44.47 | W24: 39.9 | X24: 35.32 | Y24: 30.75 | Z24: 30.75 | AA24: 32.18 | AB24: 34.72
A25: 1 | C25: 리스부채 | E25: 65.56 | F25: 65.56 | G25: 57.01 | H25: 48.46 | I25: 39.91 | J25: 25.33 | K25: 25.33 | L25: 19.58 | M25: 13.82 | N25: 8.07 | O25: 15.43 | P25: 15.43 | Q25: 82.12 | R25: 73.31 | S25: 64.52 | T25: 81.28 | U25: 81.28 | V25: 100.57 | W25: 89.31 | X25: 78.03 | Y25: 66.77 | Z25: 66.77 | AA25: 62.71 | AB25: 59.75
A26: 1 | C26: 기타유동부채 | E26: 579.46 | F26: 579.46 | G26: 1493.51 | H26: 1803.74 | I26: 592.02 | J26: 873.66 | K26: 873.66 | L26: 171.82 | M26: 196.92 | N26: 168.48 | O26: 205.51 | P26: 205.51 | Q26: 130.28 | R26: 164.48 | S26: 183.01 | T26: 146.48 | U26: 146.48 | V26: 361.14 | W26: 473.51 | X26: 624.02 | Y26: 108.17 | Z26: 108.17 | AA26: 192.36 | AB26: 360.37
A27: 1 | C27: 비유동부채 | E27: 32 | F27: 32 | G27: 26.1 | H27: 20.21 | I27: 14.32 | J27: 4.8 | K27: 4.8 | L27: 3.6 | M27: 2.4 | N27: 1.2 | O27: 0 | P27: 0 | Q27: 51.69 | R27: 47.78 | S27: 43.88 | T27: 58 | U27: 58 | V27: 56.1 | W27: 49.41 | X27: 42.71 | Y27: 36.02 | Z27: 36.02 | AA27: 30.53 | AB27: 25.03
A28: 1 | C28: 비유동리스부채 | E28: 32 | F28: 32 | G28: 26.1 | H28: 20.21 | I28: 14.32 | J28: 4.8 | K28: 4.8 | L28: 3.6 | M28: 2.4 | N28: 1.2 | O28: 0 | P28: 0 | Q28: 51.69 | R28: 47.78 | S28: 43.88 | T28: 58 | U28: 58 | V28: 56.1 | W28: 49.41 | X28: 42.71 | Y28: 36.02 | Z28: 36.02 | AA28: 30.53 | AB28: 25.03
A29: 1 | C29: 장기금융부채 | E29: 32 | F29: 32 | G29: 26.1 | H29: 20.21 | I29: 14.32 | J29: 4.8 | K29: 4.8 | L29: 3.6 | M29: 2.4 | N29: 1.2 | O29: 0 | P29: 0 | Q29: 51.69 | R29: 47.78 | S29: 43.88 | T29: 58 | U29: 58 | V29: 56.1 | W29: 49.41 | X29: 42.71 | Y29: 36.02 | Z29: 36.02 | AA29: 30.53 | AB29: 25.03
A30: 1 | C30: 부채총계 | E30: 10648.16 | F30: 10648.16 | G30: 12555.79 | H30: 11751.2 | I30: 12178.23 | J30: 11513.72 | K30: 11513.72 | L30: 11331.3 | M30: 10475.96 | N30: 9507.72 | O30: 10108.97 | P30: 10108.97 | Q30: 10287.74 | R30: 9976.37 | S30: 8128.8 | T30: 8345.75 | U30: 8345.75 | V30: 8957.78 | W30: 9221.14 | X30: 13405.93 | Y30: 11742.44 | Z30: 11742.44 | AA30: 11734.57 | AB30: 12997.16
A31: 1 | C31: 자본금 | E31: 6300 | F31: 6300 | G31: 6300 | H31: 6300 | I31: 6300 | J31: 6300 | K31: 6300 | L31: 6300 | M31: 6300 | N31: 6300 | O31: 6300 | P31: 6300 | Q31: 6300 | R31: 6300 | S31: 6300 | T31: 6300 | U31: 6300 | V31: 6300 | W31: 6300 | X31: 6300 | Y31: 6300 | Z31: 6300 | AA31: 6300 | AB31: 6300
A32: 1 | C32: 자본잉여금 | E32: 10412.2 | F32: 10412.2 | G32: 10412.2 | H32: 10412.2 | I32: 10412.2 | J32: 10412.2 | K32: 10412.2 | L32: 10412.2 | M32: 10412.2 | N32: 10412.2 | O32: 10412.2 | P32: 10412.2 | Q32: 10412.2 | R32: 10412.2 | S32: 10412.2 | T32: 10412.2 | U32: 10412.2 | V32: 10412.2 | W32: 10412.2 | X32: 10412.2 | Y32: 10412.2 | Z32: 10412.2 | AA32: 10412.2 | AB32: 10412.2
A33: 1 | C33: 기타자본 | E33: 1.58 | F33: 1.58 | G33: 1.58 | H33: 1.58 | I33: 1.58 | J33: 1.58 | K33: 1.58 | L33: 1.58 | M33: 1.58 | N33: 1.58 | O33: 1.58 | P33: 1.58 | Q33: 1.58 | R33: 1.58 | S33: 1.58 | T33: 1.58 | U33: 1.58 | V33: 1.58 | W33: 1.58 | X33: 1.58 | Y33: 1.58 | Z33: 1.58 | AA33: 1.58 | AB33: 1.58
A34: 1 | C34: 기타포괄이익누계액 | E34: 205.7 | F34: 205.7 | G34: 179.96 | H34: 188.71 | I34: 439.94 | J34: 259.24 | K34: 259.24 | L34: 226.07 | M34: 354.78 | N34: 388.71 | O34: 334.42 | P34: 334.42 | Q34: 569.35 | R34: 269.16 | S34: 240.97 | T34: 201.82 | U34: 201.82 | V34: 249.32 | W34: 518.18 | X34: 415.34 | Y34: 449.2 | Z34: 449.2 | AA34: 554.22 | AB34: 216.51
A35: 1 | C35: 이익잉여금 | E35: 45423.54 | F35: 45423.54 | G35: 45715.36 | H35: 46152.97 | I35: 47083.8 | J35: 47159.89 | K35: 47159.89 | L35: 47236.56 | M35: 48123.4 | N35: 48096.11 | O35: 48645.68 | P35: 48645.68 | Q35: 47871.28 | R35: 48525.1 | S35: 48466.47 | T35: 48600.39 | U35: 48600.39 | V35: 48054.05 | W35: 48369.84 | X35: 48912.63 | Y35: 49131.02 | Z35: 49131.02 | AA35: 49151.85 | AB35: 49726.74
... A39: 1 | C39: 이자발생자산 | E39: 2201.54 | F39: 2201.54 | G39: 1767.78 | H39: 2883.79 | I39: 3346.02 | J39: 4054.57 | K39: 4054.57 | L39: 2006.35 | M39: 2857.3 | N39: 2293.91 | O39: 3623.74 | P39: 3623.74 | Q39: 2707.85 | R39: 3730.21 | S39: 3542.94 | T39: 4576.04 | U39: 4576.04 | V39: 4022.93 | W39: 5446.49 | X39: 6274.67 | Y39: 4446.92 | Z39: 4446.92 | AA39: 2050.31 | AB39: 3525.6
A40: 1 | C40: 매입채무및기타채무 | G40: 441 | L40: 441 | N40: 5586.09 | O40: 6762.32 | P40: 6762.32 | Q40: 7076.07 | R40: 6506.97 | S40: 4617.86 | T40: 4980.57 | U40: 4980.57 | V40: 5368.81 | W40: 5315.98 | X40: 5459.13 | Y40: 5013.54 | Z40: 5013.54 | AA40: 4677.16 | AB40: 5338.79
A41: 1 | C41: 종속기업및관계기업투자 | X41: 8704.07 | Y41: 8704.07 | Z41: 8704.07 | AA41: 8754.07
A42: 1 | C42: 단기차입금 | X42: 3774.92 | Y42: 3670.52 | Z42: 3670.52 | AA42: 3786.92 | AB42: 3807.92
A43: 1 | C43: 단기금융부채(face) | X43: 3774.92 | Y43: 3670.52 | Z43: 3670.52 | AA43: 3786.92 | AB43: 3807.92
A44: 1 | C44: 총차입금 | X44: 3774.92 | Y44: 3670.52 | Z44: 3670.52 | AA44: 3786.92 | AB44: 3807.92
A45: 1 | C45: 순차입금 | X45: -2229.93 | Y45: -506.58 | Z45: -506.58 | AA45: 2006.43 | AB45: 552.14
A46: 1 | C46: 단기투자자산(공정가치) | AB46: 2000
A47: 1 | C47: 매출액(수익) | E47: 12430.92 | G47: 11967.27 | H47: 11946.73 | I47: 14222.41 | J47: 12281.8 | K47: 50418.21 | L47: 12608.78 | M47: 11502.89 | N47: 10707.58 | O47: 11017.73 | P47: 45836.98 | Q47: 10454.85 | R47: 11069.22 | S47: 11049.55 | T47: 9797.4 | U47: 42371.02 | V47: 9777 | W47: 11439.92 | X47: 10939.65 | Y47: 9985.5 | Z47: 42142.07 | AA47: 9229.63 | AB47: 11199.82
A48: 1 | C48: 매출원가 | E48: 11728.55 | G48: 9952.56 | H48: 9906.57 | I48: 12159.48 | J48: 10645.75 | K48: 42664.36 | L48: 10736.97 | M48: 9083.27 | N48: 9570.87 | O48: 9321.4 | P48: 38712.51 | Q48: 9400.05 | R48: 9339.08 | S48: 10043.26 | T48: 8775.78 | U48: 37558.17 | V48: 9076.03 | W48: 9689.47 | X48: 9550.32 | Y48: 8951.98 | Z48: 37267.8 | AA48: 7973.68 | AB48: 9352.09
A49: 1 | C49: 매출총이익 | E49: 702.37 | G49: 2014.71 | H49: 2040.15 | I49: 2062.93 | J49: 1636.04 | K49: 7753.83 | L49: 1871.81 | M49: 2419.62 | N49: 1136.71 | O49: 1696.33 | P49: 7124.47 | Q49: 1054.8 | R49: 1730.14 | S49: 1006.29 | T49: 1021.62 | U49: 4812.85 | V49: 700.97 | W49: 1750.45 | X49: 1389.33 | Y49: 1033.52 | Z49: 4874.27 | AA49: 1255.95 | AB49: 1847.73
A50: 1 | C50: 판관비 | E50: 1451.48 | G50: 1465.3 | H50: 1575.96 | I50: 1541.82 | J50: 1559.89 | K50: 6142.97 | L50: 1687.95 | M50: 1600.04 | N50: 1660.47 | O50: 1562.4 | P50: 6510.86 | Q50: 1771.18 | R50: 1477.11 | S50: 1419.91 | T50: 1438.63 | U50: 6106.83 | V50: 1467.04 | W50: 1382.91 | X50: 1299.38 | Y50: 1446.78 | Z50: 5596.11 | AA50: 1509.18 | AB50: 1492.17
A51: 1 | C51: 영업이익 | E51: -749.11 | G51: 549.4 | H51: 464.2 | I51: 521.12 | J51: 76.15 | K51: 1610.87 | L51: 183.86 | M51: 819.58 | N51: -523.76 | O51: 133.93 | P51: 613.61 | Q51: -716.39 | R51: 253.03 | S51: -413.62 | T51: -417.01 | U51: -1293.99 | V51: -766.07 | W51: 367.54 | X51: 89.94 | Y51: -413.26 | Z51: -721.85 | AA51: -253.23 | AB51: 355.56
A52: 1 | C52: 기타영업외수익 | E52: 75.48 | G52: 234.27 | H52: 147.98 | I52: 421.6 | J52: 97.86 | K52: 901.71 | L52: 271.61 | M52: 94.63 | N52: 152.4 | O52: 27.23 | P52: 545.87 | Q52: 182.39 | R52: 193.35 | S52: 99.18 | T52: 286.76 | U52: 761.68 | V52: 146.83 | W52: -18.31 | X52: 112.48 | Y52: 204.27 | Z52: 445.27 | AA52: 360.75 | AB52: 185.12
A53: 1 | C53: 기타영업외비용 | E53: 51.42 | G53: 32.13 | H53: 34.67 | I53: -29.86 | J53: 307.81 | K53: 344.75 | L53: 1.53 | M53: 112.9 | N53: -3.08 | O53: 34.78 | P53: 146.13 | Q53: 17.43 | R53: 30.52 | S53: 18.2 | T53: -53.67 | U53: 12.48 | V53: 5.77 | W53: 261.23 | X53: -198.7 | Y53: -29.12 | Z53: 39.18 | AA53: 118.32 | AB53: 21.64
A54: 1 | C54: 금융수익 | E54: 92 | G54: 106.96 | H54: 112.62 | I54: 138.68 | J54: 231.32 | K54: 589.58 | L54: 257.1 | M54: 250.49 | N54: 261.19 | O54: 260.53 | P54: 1029.31 | Q54: 242.65 | R54: 243.87 | S54: 243.77 | T54: 241.73 | U54: 972.02 | V54: 212.86 | W54: 219.62 | X54: 180.26 | Y54: 180.72 | Z54: 793.46 | AA54: 175.45 | AB54: 184.36
A55: 1 | C55: 법인세비용차감전계속사업이익 | E55: -633.07 | G55: 858.51 | H55: 646.59 | I55: 1105.26 | J55: 109.81 | K55: 2720.17 | L55: 711.04 | M55: 1040.23 | N55: -107.62 | O55: 463.02 | P55: 2106.67 | Q55: -290.39 | R55: 669.33 | S55: -96.79 | T55: 141.71 | U55: 423.86 | V55: -413.73 | W55: 312.89 | X55: 584.36 | Y55: 12.28 | Z55: 495.8 | AA55: 136.06 | AB55: 713.41
A56: 1 | C56: 법인세비용 | E56: -179.42 | G56: 125.68 | H56: 208.97 | I56: 174.43 | J56: 33.73 | K56: 542.81 | L56: 193.37 | M56: 153.39 | N56: -80.33 | O56: -86.55 | P56: 179.88 | Q56: 43.01 | R56: 15.51 | S56: -38.17 | T56: 7.8 | U56: 28.15 | V56: 6.61 | W56: -2.91 | X56: 41.58 | Y56: -206.11 | Z56: -160.83 | AA56: -10.78 | AB56: 138.52
A57: 1 | C57: 당기순이익 | E57: -453.65 | G57: 732.82 | H57: 437.61 | I57: 930.83 | J57: 76.09 | K57: 2177.35 | L57: 517.67 | M57: 886.84 | N57: -27.29 | O57: 549.57 | P57: 1926.79 | Q57: -333.39 | R57: 653.82 | S57: -58.63 | T57: 133.92 | U57: 395.72 | V57: -420.34 | W57: 315.8 | X57: 542.78 | Y57: 218.39 | Z57: 656.63 | AA57: 146.83 | AB57: 574.89
A58: 1 | C58: 총포괄손익 | E58: -471.15 | G58: 707.08 | H58: 446.36 | I58: 1182.05 | J58: -104.61 | K58: 2230.88 | L58: 484.49 | M58: 1015.55 | N58: 6.64 | O58: 495.28 | P58: 2001.96 | Q58: -98.47 | R58: 353.63 | S58: -86.82 | T58: 94.75 | U58: 263.09 | V58: -372.83 | W58: 584.66 | X58: 439.94 | Y58: 252.26 | Z58: 904.03 | AA58: 251.85 | AB58: 237.19
... A62: 1 | C62: 계속사업이익 | E62: -453.65 | G62: 732.82 | H62: 437.61 | I62: 930.83 | J62: 76.09 | K62: 2177.35 | L62: 517.67 | M62: 886.84 | N62: -27.29 | O62: 549.57 | P62: 1926.79 | Q62: -333.39 | R62: 653.82 | S62: -58.63 | T62: 133.92 | U62: 395.72 | V62: -420.34 | W62: 315.8 | X62: 542.78 | Y62: 218.39 | Z62: 656.63 | AA62: 146.83 | AB62: 574.89
A63: 1 | C63: 이자수익 | G63: 106.96 | H63: 112.62 | I63: 138.68 | J63: 231.32 | K63: 589.58 | L63: 257.1 | M63: 250.49 | N63: 257.1 | O63: 256.57 | P63: 1021.26 | Q63: 242.65 | R63: 243.87 | S63: 243.77 | T63: 237.77 | U63: 968.06 | V63: 212.86 | W63: 214.34
A64: 1 | C64: 종속기업,공동지배기업및관계기업관련손익 | H64: -43.54 | I64: -6 | M64: -11.57 | N64: -0.53 | O64: 76.11 | Q64: 18.38 | R64: 9.6 | S64: -7.92 | T64: -20.06 | U64: 0 | V64: -1.58 | W64: 5.26 | X64: 11.19 | Y64: 23.76 | Z64: 38.63 | AA64: 14.68 | AB64: 26.3
A65: 1 | C65: 지분법관련손익 | H65: -43.54 | I65: -6 | M65: -11.57 | N65: -0.53 | O65: 76.11 | Q65: 18.38 | R65: 9.6 | S65: -7.92 | T65: -20.06 | U65: 0 | V65: -1.58 | W65: 5.26 | X65: 11.19 | Y65: 23.76 | Z65: 38.63 | AA65: 14.68 | AB65: 26.3
A66: 1 | C66: 배당금수익 | W66: 5.28
A67: 1 | C67: 금융비용 | X67: 8.21 | Y67: 12.34 | AA67: 13.92 | AB67: 16.28
A68: 1 | C68: 영업활동으로인한현금흐름 | E68: 634.06 | G68: 435.16 | H68: 1571.01 | I68: 93.82 | J68: 838.87 | K68: 2938.86 | L68: -1631.22 | M68: 1745.56 | N68: -645.04 | O68: 1458.35 | P68: 927.65 | Q68: -696.9 | R68: 1491.09 | S68: 814.56 | T68: 1082.15 | U68: 2690.9 | V68: -588.2 | W68: 1783.1 | X68: 1189.48 | Y68: 1713.35 | Z68: 4097.73 | AA68: -1927.5 | AB68: 1711.26
A69: 1 | C69: 배당금수취(CF) | E69: 0 | G69: 0 | H69: 1.32 | I69: 0 | J69: 0 | K69: 1.32 | L69: 0 | M69: 3.96 | N69: 0 | O69: 0 | P69: 3.96 | Q69: 0 | R69: 0 | S69: 0 | T69: 3.96 | U69: 3.96 | V69: 0 | W69: 5.28 | X69: 0 | Y69: 0 | Z69: 5.28 | AA69: 0 | AB69: 2.64
A70: 1 | C70: 법인세납부(CF) | E70: -19.06 | G70: -80.53 | H70: -93.92 | I70: -83 | J70: -30.04 | K70: -287.49 | L70: -109.18 | M70: -156.81 | N70: -135.25 | O70: -132.59 | P70: -533.83 | Q70: -0.89 | R70: -3.65 | S70: -115.75 | T70: -69.12 | U70: -189.41 | V70: -7.57 | W70: 65.6 | X70: -74.07 | Y70: -57.52 | Z70: -73.56 | AA70: -2.34 | AB70: 125.65
A71: 1 | C71: 투자활동으로인한현금흐름 | E71: 138.06 | G71: -824.23 | H71: -19.3 | I71: -4.56 | J71: 254.73 | K71: -593.36 | L71: -384.57 | M71: -538.96 | N71: 615.26 | O71: -351.42 | P71: -659.69 | Q71: -210.06 | R71: 2.43 | S71: -1008.9 | T71: -181 | U71: -1397.53 | V71: -5.05 | W71: -28.13 | X71: -4217.4 | Y71: -3583.54 | Z71: -7834.12 | AA71: -486.09 | AB71: -168.01
A72: 1 | C72: 유형자산의증가 | E72: 517.79 | G72: 1828.8 | H72: 424.39 | I72: 44.56 | J72: 359.42 | K72: 2657.17 | L72: 1817.84 | M72: 1342.75 | N72: 34.89 | O72: 121.42 | P72: 3316.9 | Q72: 208.22 | S72: 8.9 | T72: 38.29 | V72: 4.05 | W72: 33.01 | X72: 184.07 | Y72: 648.04 | Z72: 869.17 | AA72: 3.12 | AB72: 170.51
A73: 1 | C73: CAPEX | E73: 517.79 | G73: 1866.98 | H73: 723.47 | I73: 44.56 | J73: 359.42 | K73: 2994.43 | L73: 1957.84 | M73: 1345.69 | N73: 34.89 | O73: 121.42 | P73: 3459.84 | Q73: 208.22 | R73: 0 | S73: 8.9 | T73: 38.29 | U73: 255.41 | V73: 4.05 | W73: 33.01 | X73: 184.07 | Y73: 648.04 | Z73: 869.17 | AA73: 3.12 | AB73: 170.51
A74: 1 | C74: 유형자산의감소 | E74: 0.85 | G74: 0 | H74: 6.92 | I74: 40 | J74: 164.15 | K74: 211.07 | L74: 40 | M74: 0 | N74: 0.15 | O74: 0 | P74: 40.15 | Q74: 11 | R74: 0 | S74: 0 | T74: 12.07 | U74: 23.07 | V74: 0 | W74: 4.88 | X74: 0 | Y74: 0 | Z74: 4.88
A75: 1 | C75: 재무활동으로인한현금흐름 | E75: -8.55 | G75: -8.55 | H75: -449.56 | I75: -8.55 | J75: -4.97 | K75: -471.63 | L75: -5.75 | M75: -446.76 | N75: -5.75 | O75: -5.15 | P75: -463.41 | Q75: -6.89 | R75: -449.8 | S75: -8.8 | T75: -8.71 | U75: -474.2 | V75: -8.59 | W75: -137.27 | X75: 3736.25 | Y75: -11.27 | Z75: 3579.12 | AA75: -11.27 | AB75: -136.34
A76: 1 | C76: 배당금지급 | E76: 0 | G76: 0 | H76: 441 | I76: 0 | J76: 0 | K76: 441 | L76: 0 | M76: 441 | N76: 0 | O76: 0 | P76: 441 | S76: 0 | T76: 0 | X76: 0 | Y76: 0
A77: 1 | C77: 현금및현금성자산의증감 | E77: 1506.92 | G77: -798.38 | H77: 2206.95 | I77: 220.85 | J77: 2033.47 | K77: 3662.89 | L77: -4028.2 | M77: 1448.45 | N77: -62.15 | O77: 2201.62 | P77: -440.28 | Q77: -1842.58 | R77: 2066.1 | S77: -390.43 | T77: 1915.4 | U77: 1748.49 | V77: -1155.95 | W77: 3041.27 | X77: 1536.5 | Y77: -3709.21 | Z77: -287.39 | AA77: -4821.47 | AB77: 2882.2
A78: 1 | C78: 기말현금및현금성자산 | E78: 743.36 | G78: 1432.96 | H78: 1104.79 | I78: 140.15 | J78: 944.83 | K78: 3622.73 | L78: 1616.09 | M78: 688.59 | N78: -26.61 | O78: 1099.83 | P78: 3377.9 | Q78: 2449.17 | R78: 1022.36 | S78: -187.27 | T78: 1022.96 | U78: 4307.22 | V78: 3753.11 | W78: 1423.56 | X78: 828.18 | Y78: -1827.75 | Z78: 4177.1 | AA78: 1780.49 | AB78: 1475.29
A79: 1 | C79: 무형자산의증가 | G79: 38.18 | H79: 299.08 | J79: 0 | L79: 140 | M79: 2.94 | N79: 0 | O79: 0 | P79: 142.94 | Q79: 0 | R79: 0 | S79: 0 | T79: 0 | U79: 0 | V79: 0 | W79: 0 | X79: 0 | Y79: 0 | Z79: 0
A80: 1 | C80: 이자수취(CF) | O80: 497.37 | Q80: 5.78 | R80: 3.15 | S80: 534.26 | T80: 448.82 | U80: 992.01 | V80: 8.34 | W80: 18.42 | X80: 480.96 | Y80: 373.55 | Z80: 881.27 | AA80: 15.21 | AB80: 5.04
A81: 1 | C81: 단기차입금의증가 | Y81: 0

Sheet subQ
A1: YQ | C1: subQ 분기 서브모델(억원, U=100) | E1: 4Q21 | F1: 2021 | G1: 1Q22 | H1: 2Q22 | I1: 3Q22 | J1: 4Q22 | K1: 2022 | L1: 1Q23 | M1: 2Q23 | N1: 3Q23 | O1: 4Q23 | P1: 2023 | Q1: 1Q24 | R1: 2Q24 | S1: 3Q24 | T1: 4Q24 | U1: 2024 | V1: 1Q25 | W1: 2Q25 | X1: 3Q25 | Y1: 4Q25 | Z1: 2025 | AA1: 1Q26 | AB1: 2Q26 | AC1: 3Q26 | AD1: 4Q26 | AE1: 2026 | AF1: 1Q27 | AG1: 2Q27 | AH1: 3Q27 | AI1: 4Q27 | AJ1: 2027 | AK1: 1Q28 | AL1: 2Q28 | AM1: 3Q28 | AN1: 4Q28 | AO1: 2028
A2: A=이름(key) B=그룹 C=단위 D=FnGuide 계정명(VLOOKUP 키). 확정=VLOOKUP(BS), 추정=변수 가정 참조
E3: 1 | F3: 2 | G3: 3 | H3: 4 | I3: 5 | J3: 6 | K3: 7 | L3: 8 | M3: 9 | N3: 10 | O3: 11 | P3: 12 | Q3: 13 | R3: 14 | S3: 15 | T3: 16 | U3: 17 | V3: 18 | W3: 19 | X3: 20 | Y3: 21 | Z3: 22 | AA3: 23 | AB3: 24 | AC3: 25 | AD3: 26 | AE3: 27 | AF3: 28 | AG3: 29 | AH3: 30 | AI3: 31 | AJ3: 32 | AK3: 33 | AL3: 34 | AM3: 35 | AN3: 36 | AO3: 37
E4: 2021.12 | F4: 2021.12A | G4: 2022.03 | H4: 2022.06 | I4: 2022.09 | J4: 2022.12 | K4: 2022.12A | L4: 2023.03 | M4: 2023.06 | N4: 2023.09 | O4: 2023.12 | P4: 2023.12A | Q4: 2024.03 | R4: 2024.06 | S4: 2024.09 | T4: 2024.12 | U4: 2024.12A | V4: 2025.03 | W4: 2025.06 | X4: 2025.09 | Y4: 2025.12 | Z4: 2025.12A | AA4: 2026.03 | AB4: 2026.06 | AC4: 2026.09 | AD4: 2026.12 | AE4: 2026.12A | AF4: 2027.03 | AG4: 2027.06 | AH4: 2027.09 | AI4: 2027.12 | AJ4: 2027.12A | AK4: 2028.03 | AL4: 2028.06 | AM4: 2028.09 | AN4: 2028.12 | AO4: 2028.12A
A5: 매출액 | B5: 손익 | C5: 억원 | D5: 매출액(수익) | E5: =IFERROR(VLOOKUP($D5,BS별도,MATCH(E$1,BS별도H,0),0)/100,"") | G5: =IFERROR(VLOOKUP($D5,BS별도,MATCH(G$1,BS별도H,0),0)/100,"") | H5: =IFERROR(VLOOKUP($D5,BS별도,MATCH(H$1,BS별도H,0),0)/100,"") | I5: =IFERROR(VLOOKUP($D5,BS별도,MATCH(I$1,BS별도H,0),0)/100,"") | J5: =IFERROR(VLOOKUP($D5,BS별도,MATCH(J$1,BS별도H,0),0)/100,"") | K5: =SUM(G5:J5) | L5: =IFERROR(VLOOKUP($D5,BS별도,MATCH(L$1,BS별도H,0),0)/100,"") | M5: =IFERROR(VLOOKUP($D5,BS별도,MATCH(M$1,BS별도H,0),0)/100,"") | N5: =IFERROR(VLOOKUP($D5,BS별도,MATCH(N$1,BS별도H,0),0)/100,"") | O5: =IFERROR(VLOOKUP($D5,BS별도,MATCH(O$1,BS별도H,0),0)/100,"") | P5: =SUM(L5:O5) | Q5: =IFERROR(VLOOKUP($D5,BS별도,MATCH(Q$1,BS별도H,0),0)/100,"") | R5: =IFERROR(VLOOKUP($D5,BS별도,MATCH(R$1,BS별도H,0),0)/100,"") | S5: =IFERROR(VLOOKUP($D5,BS별도,MATCH(S$1,BS별도H,0),0)/100,"") | T5: =IFERROR(VLOOKUP($D5,BS별도,MATCH(T$1,BS별도H,0),0)/100,"") | U5: =SUM(Q5:T5) | V5: =IFERROR(VLOOKUP($D5,BS별도,MATCH(V$1,BS별도H,0),0)/100,"") | W5: =IFERROR(VLOOKUP($D5,BS별도,MATCH(W$1,BS별도H,0),0)/100,"") | X5: =IFERROR(VLOOKUP($D5,BS연결,MATCH(X$1,BS연결H,0),0)/100,"") | Y5: =IFERROR(VLOOKUP($D5,BS연결,MATCH(Y$1,BS연결H,0),0)/100,"") | Z5: =SUM(V5:Y5) | AA5: =IFERROR(VLOOKUP($D5,BS연결,MATCH(AA$1,BS연결H,0),0)/100,"") | AB5: =IFERROR(VLOOKUP($D5,BS연결,MATCH(AB$1,BS연결H,0),0)/100,"") | AC5: =IFERROR(X5*(1+변수!AC21),"") | AD5: =IFERROR(Y5*(1+변수!AD21),"") | AE5: =SUM(AA5:AD5) | AF5: =IFERROR(AA5*(1+변수!AF21),"") | AG5: =IFERROR(AB5*(1+변수!AG21),"") | AH5: =IFERROR(AC5*(1+변수!AH21),"") | AI5: =IFERROR(AD5*(1+변수!AI21),"") | AJ5: =SUM(AF5:AI5) | AK5: =IFERROR(AF5*(1+변수!AK21),"") | AL5: =IFERROR(AG5*(1+변수!AL21),"") | AM5: =IFERROR(AH5*(1+변수!AM21),"") | AN5: =IFERROR(AI5*(1+변수!AN21),"") | AO5: =SUM(AK5:AN5)
A6: 매출원가 | B6: 손익 | C6: 억원 | D6: 매출원가 | E6: =IFERROR(VLOOKUP($D6,BS별도,MATCH(E$1,BS별도H,0),0)/100,"") | G6: =IFERROR(VLOOKUP($D6,BS별도,MATCH(G$1,BS별도H,0),0)/100,"") | H6: =IFERROR(VLOOKUP($D6,BS별도,MATCH(H$1,BS별도H,0),0)/100,"") | I6: =IFERROR(VLOOKUP($D6,BS별도,MATCH(I$1,BS별도H,0),0)/100,"") | J6: =IFERROR(VLOOKUP($D6,BS별도,MATCH(J$1,BS별도H,0),0)/100,"") | K6: =SUM(G6:J6) | L6: =IFERROR(VLOOKUP($D6,BS별도,MATCH(L$1,BS별도H,0),0)/100,"") | M6: =IFERROR(VLOOKUP($D6,BS별도,MATCH(M$1,BS별도H,0),0)/100,"") | N6: =IFERROR(VLOOKUP($D6,BS별도,MATCH(N$1,BS별도H,0),0)/100,"") | O6: =IFERROR(VLOOKUP($D6,BS별도,MATCH(O$1,BS별도H,0),0)/100,"") | P6: =SUM(L6:O6) | Q6: =IFERROR(VLOOKUP($D6,BS별도,MATCH(Q$1,BS별도H,0),0)/100,"") | R6: =IFERROR(VLOOKUP($D6,BS별도,MATCH(R$1,BS별도H,0),0)/100,"") | S6: =IFERROR(VLOOKUP($D6,BS별도,MATCH(S$1,BS별도H,0),0)/100,"") | T6: =IFERROR(VLOOKUP($D6,BS별도,MATCH(T$1,BS별도H,0),0)/100,"") | U6: =SUM(Q6:T6) | V6: =IFERROR(VLOOKUP($D6,BS별도,MATCH(V$1,BS별도H,0),0)/100,"") | W6: =IFERROR(VLOOKUP($D6,BS별도,MATCH(W$1,BS별도H,0),0)/100,"") | X6: =IFERROR(VLOOKUP($D6,BS연결,MATCH(X$1,BS연결H,0),0)/100,"") | Y6: =IFERROR(VLOOKUP($D6,BS연결,MATCH(Y$1,BS연결H,0),0)/100,"") | Z6: =SUM(V6:Y6) | AA6: =IFERROR(VLOOKUP($D6,BS연결,MATCH(AA$1,BS연결H,0),0)/100,"") | AB6: =IFERROR(VLOOKUP($D6,BS연결,MATCH(AB$1,BS연결H,0),0)/100,"") | AC6: =IFERROR(AC5-AC7,"") | AD6: =IFERROR(AD5-AD7,"") | AE6: =SUM(AA6:AD6) | AF6: =IFERROR(AF5-AF7,"") | AG6: =IFERROR(AG5-AG7,"") | AH6: =IFERROR(AH5-AH7,"") | AI6: =IFERROR(AI5-AI7,"") | AJ6: =SUM(AF6:AI6) | AK6: =IFERROR(AK5-AK7,"") | AL6: =IFERROR(AL5-AL7,"") | AM6: =IFERROR(AM5-AM7,"") | AN6: =IFERROR(AN5-AN7,"") | AO6: =SUM(AK6:AN6)
A7: 매출총이익 | B7: 손익 | C7: 억원 | D7: 매출총이익 | E7: =IFERROR(VLOOKUP($D7,BS별도,MATCH(E$1,BS별도H,0),0)/100,"") | G7: =IFERROR(VLOOKUP($D7,BS별도,MATCH(G$1,BS별도H,0),0)/100,"") | H7: =IFERROR(VLOOKUP($D7,BS별도,MATCH(H$1,BS별도H,0),0)/100,"") | I7: =IFERROR(VLOOKUP($D7,BS별도,MATCH(I$1,BS별도H,0),0)/100,"") | J7: =IFERROR(VLOOKUP($D7,BS별도,MATCH(J$1,BS별도H,0),0)/100,"") | K7: =SUM(G7:J7) | L7: =IFERROR(VLOOKUP($D7,BS별도,MATCH(L$1,BS별도H,0),0)/100,"") | M7: =IFERROR(VLOOKUP($D7,BS별도,MATCH(M$1,BS별도H,0),0)/100,"") | N7: =IFERROR(VLOOKUP($D7,BS별도,MATCH(N$1,BS별도H,0),0)/100,"") | O7: =IFERROR(VLOOKUP($D7,BS별도,MATCH(O$1,BS별도H,0),0)/100,"") | P7: =SUM(L7:O7) | Q7: =IFERROR(VLOOKUP($D7,BS별도,MATCH(Q$1,BS별도H,0),0)/100,"") | R7: =IFERROR(VLOOKUP($D7,BS별도,MATCH(R$1,BS별도H,0),0)/100,"") | S7: =IFERROR(VLOOKUP($D7,BS별도,MATCH(S$1,BS별도H,0),0)/100,"") | T7: =IFERROR(VLOOKUP($D7,BS별도,MATCH(T$1,BS별도H,0),0)/100,"") | U7: =SUM(Q7:T7) | V7: =IFERROR(VLOOKUP($D7,BS별도,MATCH(V$1,BS별도H,0),0)/100,"") | W7: =IFERROR(VLOOKUP($D7,BS별도,MATCH(W$1,BS별도H,0),0)/100,"") | X7: =IFERROR(VLOOKUP($D7,BS연결,MATCH(X$1,BS연결H,0),0)/100,"") | Y7: =IFERROR(VLOOKUP($D7,BS연결,MATCH(Y$1,BS연결H,0),0)/100,"") | Z7: =SUM(V7:Y7) | AA7: =IFERROR(VLOOKUP($D7,BS연결,MATCH(AA$1,BS연결H,0),0)/100,"") | AB7: =IFERROR(VLOOKUP($D7,BS연결,MATCH(AB$1,BS연결H,0),0)/100,"") | AC7: =IFERROR(AC9+AC8,"") | AD7: =IFERROR(AD9+AD8,"") | AE7: =SUM(AA7:AD7) | AF7: =IFERROR(AF9+AF8,"") | AG7: =IFERROR(AG9+AG8,"") | AH7: =IFERROR(AH9+AH8,"") | AI7: =IFERROR(AI9+AI8,"") | AJ7: =SUM(AF7:AI7) | AK7: =IFERROR(AK9+AK8,"") | AL7: =IFERROR(AL9+AL8,"") | AM7: =IFERROR(AM9+AM8,"") | AN7: =IFERROR(AN9+AN8,"") | AO7: =SUM(AK7:AN7)
A8: 판관비 | B8: 손익 | C8: 억원 | D8: 판관비 | E8: =IFERROR(VLOOKUP($D8,BS별도,MATCH(E$1,BS별도H,0),0)/100,"") | G8: =IFERROR(VLOOKUP($D8,BS별도,MATCH(G$1,BS별도H,0),0)/100,"") | H8: =IFERROR(VLOOKUP($D8,BS별도,MATCH(H$1,BS별도H,0),0)/100,"") | I8: =IFERROR(VLOOKUP($D8,BS별도,MATCH(I$1,BS별도H,0),0)/100,"") | J8: =IFERROR(VLOOKUP($D8,BS별도,MATCH(J$1,BS별도H,0),0)/100,"") | K8: =SUM(G8:J8) | L8: =IFERROR(VLOOKUP($D8,BS별도,MATCH(L$1,BS별도H,0),0)/100,"") | M8: =IFERROR(VLOOKUP($D8,BS별도,MATCH(M$1,BS별도H,0),0)/100,"") | N8: =IFERROR(VLOOKUP($D8,BS별도,MATCH(N$1,BS별도H,0),0)/100,"") | O8: =IFERROR(VLOOKUP($D8,BS별도,MATCH(O$1,BS별도H,0),0)/100,"") | P8: =SUM(L8:O8) | Q8: =IFERROR(VLOOKUP($D8,BS별도,MATCH(Q$1,BS별도H,0),0)/100,"") | R8: =IFERROR(VLOOKUP($D8,BS별도,MATCH(R$1,BS별도H,0),0)/100,"") | S8: =IFERROR(VLOOKUP($D8,BS별도,MATCH(S$1,BS별도H,0),0)/100,"") | T8: =IFERROR(VLOOKUP($D8,BS별도,MATCH(T$1,BS별도H,0),0)/100,"") | U8: =SUM(Q8:T8) | V8: =IFERROR(VLOOKUP($D8,BS별도,MATCH(V$1,BS별도H,0),0)/100,"") | W8: =IFERROR(VLOOKUP($D8,BS별도,MATCH(W$1,BS별도H,0),0)/100,"") | X8: =IFERROR(VLOOKUP($D8,BS연결,MATCH(X$1,BS연결H,0),0)/100,"") | Y8: =IFERROR(VLOOKUP($D8,BS연결,MATCH(Y$1,BS연결H,0),0)/100,"") | Z8: =SUM(V8:Y8) | AA8: =IFERROR(VLOOKUP($D8,BS연결,MATCH(AA$1,BS연결H,0),0)/100,"") | AB8: =IFERROR(VLOOKUP($D8,BS연결,MATCH(AB$1,BS연결H,0),0)/100,"") | AC8: =IFERROR(AC5*변수!AC22,"") | AD8: =IFERROR(AD5*변수!AD22,"") | AE8: =SUM(AA8:AD8) | AF8: =IFERROR(AF5*변수!AF22,"") | AG8: =IFERROR(AG5*변수!AG22,"") | AH8: =IFERROR(AH5*변수!AH22,"") | AI8: =IFERROR(AI5*변수!AI22,"") | AJ8: =SUM(AF8:AI8) | AK8: =IFERROR(AK5*변수!AK22,"") | AL8: =IFERROR(AL5*변수!AL22,"") | AM8: =IFERROR(AM5*변수!AM22,"") | AN8: =IFERROR(AN5*변수!AN22,"") | AO8: =SUM(AK8:AN8)
A9: 영업이익 | B9: 손익 | C9: 억원 | D9: 영업이익 | E9: =IFERROR(VLOOKUP($D9,BS별도,MATCH(E$1,BS별도H,0),0)/100,"") | G9: =IFERROR(VLOOKUP($D9,BS별도,MATCH(G$1,BS별도H,0),0)/100,"") | H9: =IFERROR(VLOOKUP($D9,BS별도,MATCH(H$1,BS별도H,0),0)/100,"") | I9: =IFERROR(VLOOKUP($D9,BS별도,MATCH(I$1,BS별도H,0),0)/100,"") | J9: =IFERROR(VLOOKUP($D9,BS별도,MATCH(J$1,BS별도H,0),0)/100,"") | K9: =SUM(G9:J9) | L9: =IFERROR(VLOOKUP($D9,BS별도,MATCH(L$1,BS별도H,0),0)/100,"") | M9: =IFERROR(VLOOKUP($D9,BS별도,MATCH(M$1,BS별도H,0),0)/100,"") | N9: =IFERROR(VLOOKUP($D9,BS별도,MATCH(N$1,BS별도H,0),0)/100,"") | O9: =IFERROR(VLOOKUP($D9,BS별도,MATCH(O$1,BS별도H,0),0)/100,"") | P9: =SUM(L9:O9) | Q9: =IFERROR(VLOOKUP($D9,BS별도,MATCH(Q$1,BS별도H,0),0)/100,"") | R9: =IFERROR(VLOOKUP($D9,BS별도,MATCH(R$1,BS별도H,0),0)/100,"") | S9: =IFERROR(VLOOKUP($D9,BS별도,MATCH(S$1,BS별도H,0),0)/100,"") | T9: =IFERROR(VLOOKUP($D9,BS별도,MATCH(T$1,BS별도H,0),0)/100,"") | U9: =SUM(Q9:T9) | V9: =IFERROR(VLOOKUP($D9,BS별도,MATCH(V$1,BS별도H,0),0)/100,"") | W9: =IFERROR(VLOOKUP($D9,BS별도,MATCH(W$1,BS별도H,0),0)/100,"") | X9: =IFERROR(VLOOKUP($D9,BS연결,MATCH(X$1,BS연결H,0),0)/100,"") | Y9: =IFERROR(VLOOKUP($D9,BS연결,MATCH(Y$1,BS연결H,0),0)/100,"") | Z9: =SUM(V9:Y9) | AA9: =IFERROR(VLOOKUP($D9,BS연결,MATCH(AA$1,BS연결H,0),0)/100,"") | AB9: =IFERROR(VLOOKUP($D9,BS연결,MATCH(AB$1,BS연결H,0),0)/100,"") | AC9: =IFERROR(AC5*변수!AC23,"") | AD9: =IFERROR(AD5*변수!AD23,"") | AE9: =SUM(AA9:AD9) | AF9: =IFERROR(AF5*변수!AF23,"") | AG9: =IFERROR(AG5*변수!AG23,"") | AH9: =IFERROR(AH5*변수!AH23,"") | AI9: =IFERROR(AI5*변수!AI23,"") | AJ9: =SUM(AF9:AI9) | AK9: =IFERROR(AK5*변수!AK23,"") | AL9: =IFERROR(AL5*변수!AL23,"") | AM9: =IFERROR(AM5*변수!AM23,"") | AN9: =IFERROR(AN5*변수!AN23,"") | AO9: =SUM(AK9:AN9)
A10: OPM | B10: 손익 | C10: % | D10: 영업이익률 | E10: =IFERROR(E9/E5,"") | G10: =IFERROR(G9/G5,"") | H10: =IFERROR(H9/H5,"") | I10: =IFERROR(I9/I5,"") | J10: =IFERROR(J9/J5,"") | K10: =IFERROR(K9/K5,"") | L10: =IFERROR(L9/L5,"") | M10: =IFERROR(M9/M5,"") | N10: =IFERROR(N9/N5,"") | ... AO10: =IFERROR(AO9/AO5,"")
A11: 금융손익 | B11: 손익 | C11: 억원 | D11: 금융손익 | E11: =IFERROR(VLOOKUP($D11,BS별도,MATCH(E$1,BS별도H,0),0)/100,"") | G11: =IFERROR(VLOOKUP($D11,BS별도,MATCH(G$1,BS별도H,0),0)/100,"") | H11: =IFERROR(VLOOKUP($D11,BS별도,MATCH(H$1,BS별도H,0),0)/100,"") | I11: =IFERROR(VLOOKUP($D11,BS별도,MATCH(I$1,BS별도H,0),0)/100,"") | J11: =IFERROR(VLOOKUP($D11,BS별도,MATCH(J$1,BS별도H,0),0)/100,"") | K11: =SUM(G11:J11) | L11: =IFERROR(VLOOKUP($D11,BS별도,MATCH(L$1,BS별도H,0),0)/100,"") | M11: =IFERROR(VLOOKUP($D11,BS별도,MATCH(M$1,BS별도H,0),0)/100,"") | N11: =IFERROR(VLOOKUP($D11,BS별도,MATCH(N$1,BS별도H,0),0)/100,"") | O11: =IFERROR(VLOOKUP($D11,BS별도,MATCH(O$1,BS별도H,0),0)/100,"") | P11: =SUM(L11:O11) | Q11: =IFERROR(VLOOKUP($D11,BS별도,MATCH(Q$1,BS별도H,0),0)/100,"") | R11: =IFERROR(VLOOKUP($D11,BS별도,MATCH(R$1,BS별도H,0),0)/100,"") | S11: =IFERROR(VLOOKUP($D11,BS별도,MATCH(S$1,BS별도H,0),0)/100,"") | T11: =IFERROR(VLOOKUP($D11,BS별도,MATCH(T$1,BS별도H,0),0)/100,"") | U11: =SUM(Q11:T11) | V11: =IFERROR(VLOOKUP($D11,BS별도,MATCH(V$1,BS별도H,0),0)/100,"") | W11: =IFERROR(VLOOKUP($D11,BS별도,MATCH(W$1,BS별도H,0),0)/100,"") | X11: =IFERROR(VLOOKUP($D11,BS연결,MATCH(X$1,BS연결H,0),0)/100,"") | Y11: =IFERROR(VLOOKUP($D11,BS연결,MATCH(Y$1,BS연결H,0),0)/100,"") | Z11: =SUM(V11:Y11) | AA11: =IFERROR(VLOOKUP($D11,BS연결,MATCH(AA$1,BS연결H,0),0)/100,"") | AB11: =IFERROR(VLOOKUP($D11,BS연결,MATCH(AB$1,BS연결H,0),0)/100,"") | AC11: =IFERROR(AC12,"") | AD11: =IFERROR(AD12,"") | AE11: =SUM(AA11:AD11) | AF11: =IFERROR(AF12,"") | AG11: =IFERROR(AG12,"") | AH11: =IFERROR(AH12,"") | AI11: =IFERROR(AI12,"") | AJ11: =SUM(AF11:AI11) | AK11: =IFERROR(AK12,"") | AL11: =IFERROR(AL12,"") | AM11: =IFERROR(AM12,"") | AN11: =IFERROR(AN12,"") | AO11: =SUM(AK11:AN11)
A12: 이자손익 | B12: 손익 | C12: 억원 | D12: 이자손익 | K12: =SUM(G12:J12) | P12: =SUM(L12:O12) | U12: =SUM(Q12:T12) | Z12: =SUM(V12:Y12) | AA12: =IFERROR(VLOOKUP($D12,BS연결,MATCH(AA$1,BS연결H,0),0)/100,"") | AB12: =IFERROR(VLOOKUP($D12,BS연결,MATCH(AB$1,BS연결H,0),0)/100,"") | AC12: =IFERROR((AB25*변수!$D$51-AB23*변수!$D$52)/4,"") | AD12: =IFERROR((AC25*변수!$D$51-AC23*변수!$D$52)/4,"") | AE12: =SUM(AA12:AD12) | AF12: =IFERROR((AD25*변수!$D$51-AD23*변수!$D$52)/4,"") | AG12: =IFERROR((AF25*변수!$D$51-AF23*변수!$D$52)/4,"") | AH12: =IFERROR((AG25*변수!$D$51-AG23*변수!$D$52)/4,"") | AI12: =IFERROR((AH25*변수!$D$51-AH23*변수!$D$52)/4,"") | AJ12: =SUM(AF12:AI12) | AK12: =IFERROR((AI25*변수!$D$51-AI23*변수!$D$52)/4,"") | AL12: =IFERROR((AK25*변수!$D$51-AK23*변수!$D$52)/4,"") | AM12: =IFERROR((AL25*변수!$D$51-AL23*변수!$D$52)/4,"") | AN12: =IFERROR((AM25*변수!$D$51-AM23*변수!$D$52)/4,"") | AO12: =SUM(AK12:AN12)
A13: 기타영업외손익 | B13: 손익 | C13: 억원 | D13: 기타영업외손익 | E13: =IFERROR(VLOOKUP($D13,BS별도,MATCH(E$1,BS별도H,0),0)/100,"") | G13: =IFERROR(VLOOKUP($D13,BS별도,MATCH(G$1,BS별도H,0),0)/100,"") | H13: =IFERROR(VLOOKUP($D13,BS별도,MATCH(H$1,BS별도H,0),0)/100,"") | I13: =IFERROR(VLOOKUP($D13,BS별도,MATCH(I$1,BS별도H,0),0)/100,"") | J13: =IFERROR(VLOOKUP($D13,BS별도,MATCH(J$1,BS별도H,0),0)/100,"") | K13: =SUM(G13:J13) | L13: =IFERROR(VLOOKUP($D13,BS별도,MATCH(L$1,BS별도H,0),0)/100,"") | M13: =IFERROR(VLOOKUP($D13,BS별도,MATCH(M$1,BS별도H,0),0)/100,"") | N13: =IFERROR(VLOOKUP($D13,BS별도,MATCH(N$1,BS별도H,0),0)/100,"") | O13: =IFERROR(VLOOKUP($D13,BS별도,MATCH(O$1,BS별도H,0),0)/100,"") | P13: =SUM(L13:O13) | Q13: =IFERROR(VLOOKUP($D13,BS별도,MATCH(Q$1,BS별도H,0),0)/100,"") | R13: =IFERROR(VLOOKUP($D13,BS별도,MATCH(R$1,BS별도H,0),0)/100,"") | S13: =IFERROR(VLOOKUP($D13,BS별도,MATCH(S$1,BS별도H,0),0)/100,"") | T13: =IFERROR(VLOOKUP($D13,BS별도,MATCH(T$1,BS별도H,0),0)/100,"") | U13: =SUM(Q13:T13) | V13: =IFERROR(VLOOKUP($D13,BS별도,MATCH(V$1,BS별도H,0),0)/100,"") | W13: =IFERROR(VLOOKUP($D13,BS별도,MATCH(W$1,BS별도H,0),0)/100,"") | X13: =IFERROR(VLOOKUP($D13,BS연결,MATCH(X$1,BS연결H,0),0)/100,"") | Y13: =IFERROR(VLOOKUP($D13,BS연결,MATCH(Y$1,BS연결H,0),0)/100,"") | Z13: =SUM(V13:Y13) | AA13: =IFERROR(VLOOKUP($D13,BS연결,MATCH(AA$1,BS연결H,0),0)/100,"") | AB13: =IFERROR(VLOOKUP($D13,BS연결,MATCH(AB$1,BS연결H,0),0)/100,"") | AC13: =변수!AC24 | AD13: =변수!AD24 | AE13: =SUM(AA13:AD13) | AF13: =변수!AF24 | AG13: =변수!AG24 | AH13: =변수!AH24 | AI13: =변수!AI24 | AJ13: =SUM(AF13:AI13) | AK13: =변수!AK24 | AL13: =변수!AL24 | AM13: =변수!AM24 | AN13: =변수!AN24 | AO13: =SUM(AK13:AN13)
A14: 지분법손익 | B14: 손익 | C14: 억원 | D14: 종속기업,공동지배기업및관계기업관련손익 | H14: =IFERROR(VLOOKUP($D14,BS별도,MATCH(H$1,BS별도H,0),0)/100,"") | I14: =IFERROR(VLOOKUP($D14,BS별도,MATCH(I$1,BS별도H,0),0)/100,"") | K14: =SUM(G14:J14) | M14: =IFERROR(VLOOKUP($D14,BS별도,MATCH(M$1,BS별도H,0),0)/100,"") | N14: =IFERROR(VLOOKUP($D14,BS별도,MATCH(N$1,BS별도H,0),0)/100,"") | O14: =IFERROR(VLOOKUP($D14,BS별도,MATCH(O$1,BS별도H,0),0)/100,"") | P14: =SUM(L14:O14) | Q14: =IFERROR(VLOOKUP($D14,BS별도,MATCH(Q$1,BS별도H,0),0)/100,"") | R14: =IFERROR(VLOOKUP($D14,BS별도,MATCH(R$1,BS별도H,0),0)/100,"") | S14: =IFERROR(VLOOKUP($D14,BS별도,MATCH(S$1,BS별도H,0),0)/100,"") | T14: =IFERROR(VLOOKUP($D14,BS별도,MATCH(T$1,BS별도H,0),0)/100,"") | U14: =SUM(Q14:T14) | V14: =IFERROR(VLOOKUP($D14,BS별도,MATCH(V$1,BS별도H,0),0)/100,"") | W14: =IFERROR(VLOOKUP($D14,BS별도,MATCH(W$1,BS별도H,0),0)/100,"") | X14: =IFERROR(VLOOKUP($D14,BS연결,MATCH(X$1,BS연결H,0),0)/100,"") | Y14: =IFERROR(VLOOKUP($D14,BS연결,MATCH(Y$1,BS연결H,0),0)/100,"") | Z14: =SUM(V14:Y14) | AA14: =IFERROR(VLOOKUP($D14,BS연결,MATCH(AA$1,BS연결H,0),0)/100,"") | AB14: =IFERROR(VLOOKUP($D14,BS연결,MATCH(AB$1,BS연결H,0),0)/100,"") | AC14: =변수!AC25 | AD14: =변수!AD25 | AE14: =SUM(AA14:AD14) | AF14: =변수!AF25 | AG14: =변수!AG25 | AH14: =변수!AH25 | AI14: =변수!AI25 | AJ14: =SUM(AF14:AI14) | AK14: =변수!AK25 | AL14: =변수!AL25 | AM14: =변수!AM25 | AN14: =변수!AN25 | AO14: =SUM(AK14:AN14)
A15: 세전이익 | B15: 손익 | C15: 억원 | D15: 법인세비용차감전계속사업이익 | E15: =IFERROR(VLOOKUP($D15,BS별도,MATCH(E$1,BS별도H,0),0)/100,"") | G15: =IFERROR(VLOOKUP($D15,BS별도,MATCH(G$1,BS별도H,0),0)/100,"") | H15: =IFERROR(VLOOKUP($D15,BS별도,MATCH(H$1,BS별도H,0),0)/100,"") | I15: =IFERROR(VLOOKUP($D15,BS별도,MATCH(I$1,BS별도H,0),0)/100,"") | J15: =IFERROR(VLOOKUP($D15,BS별도,MATCH(J$1,BS별도H,0),0)/100,"") | K15: =SUM(G15:J15) | L15: =IFERROR(VLOOKUP($D15,BS별도,MATCH(L$1,BS별도H,0),0)/100,"") | M15: =IFERROR(VLOOKUP($D15,BS별도,MATCH(M$1,BS별도H,0),0)/100,"") | N15: =IFERROR(VLOOKUP($D15,BS별도,MATCH(N$1,BS별도H,0),0)/100,"") | O15: =IFERROR(VLOOKUP($D15,BS별도,MATCH(O$1,BS별도H,0),0)/100,"") | P15: =SUM(L15:O15) | Q15: =IFERROR(VLOOKUP($D15,BS별도,MATCH(Q$1,BS별도H,0),0)/100,"") | R15: =IFERROR(VLOOKUP($D15,BS별도,MATCH(R$1,BS별도H,0),0)/100,"") | S15: =IFERROR(VLOOKUP($D15,BS별도,MATCH(S$1,BS별도H,0),0)/100,"") | T15: =IFERROR(VLOOKUP($D15,BS별도,MATCH(T$1,BS별도H,0),0)/100,"") | U15: =SUM(Q15:T15) | V15: =IFERROR(VLOOKUP($D15,BS별도,MATCH(V$1,BS별도H,0),0)/100,"") | W15: =IFERROR(VLOOKUP($D15,BS별도,MATCH(W$1,BS별도H,0),0)/100,"") | X15: =IFERROR(VLOOKUP($D15,BS연결,MATCH(X$1,BS연결H,0),0)/100,"") | Y15: =IFERROR(VLOOKUP($D15,BS연결,MATCH(Y$1,BS연결H,0),0)/100,"") | Z15: =SUM(V15:Y15) | AA15: =IFERROR(VLOOKUP($D15,BS연결,MATCH(AA$1,BS연결H,0),0)/100,"") | AB15: =IFERROR(VLOOKUP($D15,BS연결,MATCH(AB$1,BS연결H,0),0)/100,"") | AC15: =IFERROR(AC9+AC11+AC13+AC14,"") | AD15: =IFERROR(AD9+AD11+AD13+AD14,"") | AE15: =SUM(AA15:AD15) | AF15: =IFERROR(AF9+AF11+AF13+AF14,"") | AG15: =IFERROR(AG9+AG11+AG13+AG14,"") | AH15: =IFERROR(AH9+AH11+AH13+AH14,"") | AI15: =IFERROR(AI9+AI11+AI13+AI14,"") | AJ15: =SUM(AF15:AI15) | AK15: =IFERROR(AK9+AK11+AK13+AK14,"") | AL15: =IFERROR(AL9+AL11+AL13+AL14,"") | AM15: =IFERROR(AM9+AM11+AM13+AM14,"") | AN15: =IFERROR(AN9+AN11+AN13+AN14,"") | AO15: =SUM(AK15:AN15)
A16: 법인세비용 | B16: 손익 | C16: 억원 | D16: 법인세비용 | E16: =IFERROR(VLOOKUP($D16,BS별도,MATCH(E$1,BS별도H,0),0)/100,"") | G16: =IFERROR(VLOOKUP($D16,BS별도,MATCH(G$1,BS별도H,0),0)/100,"") | H16: =IFERROR(VLOOKUP($D16,BS별도,MATCH(H$1,BS별도H,0),0)/100,"") | I16: =IFERROR(VLOOKUP($D16,BS별도,MATCH(I$1,BS별도H,0),0)/100,"") | J16: =IFERROR(VLOOKUP($D16,BS별도,MATCH(J$1,BS별도H,0),0)/100,"") | K16: =SUM(G16:J16) | L16: =IFERROR(VLOOKUP($D16,BS별도,MATCH(L$1,BS별도H,0),0)/100,"") | M16: =IFERROR(VLOOKUP($D16,BS별도,MATCH(M$1,BS별도H,0),0)/100,"") | N16: =IFERROR(VLOOKUP($D16,BS별도,MATCH(N$1,BS별도H,0),0)/100,"") | O16: =IFERROR(VLOOKUP($D16,BS별도,MATCH(O$1,BS별도H,0),0)/100,"") | P16: =SUM(L16:O16) | Q16: =IFERROR(VLOOKUP($D16,BS별도,MATCH(Q$1,BS별도H,0),0)/100,"") | R16: =IFERROR(VLOOKUP($D16,BS별도,MATCH(R$1,BS별도H,0),0)/100,"") | S16: =IFERROR(VLOOKUP($D16,BS별도,MATCH(S$1,BS별도H,0),0)/100,"") | T16: =IFERROR(VLOOKUP($D16,BS별도,MATCH(T$1,BS별도H,0),0)/100,"") | U16: =SUM(Q16:T16) | V16: =IFERROR(VLOOKUP($D16,BS별도,MATCH(V$1,BS별도H,0),0)/100,"") | W16: =IFERROR(VLOOKUP($D16,BS별도,MATCH(W$1,BS별도H,0),0)/100,"") | X16: =IFERROR(VLOOKUP($D16,BS연결,MATCH(X$1,BS연결H,0),0)/100,"") | Y16: =IFERROR(VLOOKUP($D16,BS연결,MATCH(Y$1,BS연결H,0),0)/100,"") | Z16: =SUM(V16:Y16) | AA16: =IFERROR(VLOOKUP($D16,BS연결,MATCH(AA$1,BS연결H,0),0)/100,"") | AB16: =IFERROR(VLOOKUP($D16,BS연결,MATCH(AB$1,BS연결H,0),0)/100,"") | AC16: =IFERROR(MAX(AC15,0)*변수!AC26,"") | AD16: =IFERROR(MAX(AD15,0)*변수!AD26,"") | AE16: =SUM(AA16:AD16) | AF16: =IFERROR(MAX(AF15,0)*변수!AF26,"") | AG16: =IFERROR(MAX(AG15,0)*변수!AG26,"") | AH16: =IFERROR(MAX(AH15,0)*변수!AH26,"") | AI16: =IFERROR(MAX(AI15,0)*변수!AI26,"") | AJ16: =SUM(AF16:AI16) | AK16: =IFERROR(MAX(AK15,0)*변수!AK26,"") | AL16: =IFERROR(MAX(AL15,0)*변수!AL26,"") | AM16: =IFERROR(MAX(AM15,0)*변수!AM26,"") | AN16: =IFERROR(MAX(AN15,0)*변수!AN26,"") | AO16: =SUM(AK16:AN16)
A17: 당기순이익 | B17: 손익 | C17: 억원 | D17: 당기순이익 | E17: =IFERROR(VLOOKUP($D17,BS별도,MATCH(E$1,BS별도H,0),0)/100,"") | G17: =IFERROR(VLOOKUP($D17,BS별도,MATCH(G$1,BS별도H,0),0)/100,"") | H17: =IFERROR(VLOOKUP($D17,BS별도,MATCH(H$1,BS별도H,0),0)/100,"") | I17: =IFERROR(VLOOKUP($D17,BS별도,MATCH(I$1,BS별도H,0),0)/100,"") | J17: =IFERROR(VLOOKUP($D17,BS별도,MATCH(J$1,BS별도H,0),0)/100,"") | K17: =SUM(G17:J17) | L17: =IFERROR(VLOOKUP($D17,BS별도,MATCH(L$1,BS별도H,0),0)/100,"") | M17: =IFERROR(VLOOKUP($D17,BS별도,MATCH(M$1,BS별도H,0),0)/100,"") | N17: =IFERROR(VLOOKUP($D17,BS별도,MATCH(N$1,BS별도H,0),0)/100,"") | O17: =IFERROR(VLOOKUP($D17,BS별도,MATCH(O$1,BS별도H,0),0)/100,"") | P17: =SUM(L17:O17) | Q17: =IFERROR(VLOOKUP($D17,BS별도,MATCH(Q$1,BS별도H,0),0)/100,"") | R17: =IFERROR(VLOOKUP($D17,BS별도,MATCH(R$1,BS별도H,0),0)/100,"") | S17: =IFERROR(VLOOKUP($D17,BS별도,MATCH(S$1,BS별도H,0),0)/100,"") | T17: =IFERROR(VLOOKUP($D17,BS별도,MATCH(T$1,BS별도H,0),0)/100,"") | U17: =SUM(Q17:T17) | V17: =IFERROR(VLOOKUP($D17,BS별도,MATCH(V$1,BS별도H,0),0)/100,"") | W17: =IFERROR(VLOOKUP($D17,BS별도,MATCH(W$1,BS별도H,0),0)/100,"") | X17: =IFERROR(VLOOKUP($D17,BS연결,MATCH(X$1,BS연결H,0),0)/100,"") | Y17: =IFERROR(VLOOKUP($D17,BS연결,MATCH(Y$1,BS연결H,0),0)/100,"") | Z17: =SUM(V17:Y17) | AA17: =IFERROR(VLOOKUP($D17,BS연결,MATCH(AA$1,BS연결H,0),0)/100,"") | AB17: =IFERROR(VLOOKUP($D17,BS연결,MATCH(AB$1,BS연결H,0),0)/100,"") | AC17: =IFERROR(AC15-AC16,"") | AD17: =IFERROR(AD15-AD16,"") | AE17: =SUM(AA17:AD17) | AF17: =IFERROR(AF15-AF16,"") | AG17: =IFERROR(AG15-AG16,"") | AH17: =IFERROR(AH15-AH16,"") | AI17: =IFERROR(AI15-AI16,"") | AJ17: =SUM(AF17:AI17) | AK17: =IFERROR(AK15-AK16,"") | AL17: =IFERROR(AL15-AL16,"") | AM17: =IFERROR(AM15-AM16,"") | AN17: =IFERROR(AN15-AN16,"") | AO17: =SUM(AK17:AN17)
A18: 지배주주순이익 | B18: 손익 | C18: 억원 | D18: (지배주주지분)당기순이익 | E18: =IFERROR(VLOOKUP($D18,BS별도,MATCH(E$1,BS별도H,0),0)/100,"") | G18: =IFERROR(VLOOKUP($D18,BS별도,MATCH(G$1,BS별도H,0),0)/100,"") | H18: =IFERROR(VLOOKUP($D18,BS별도,MATCH(H$1,BS별도H,0),0)/100,"") | I18: =IFERROR(VLOOKUP($D18,BS별도,MATCH(I$1,BS별도H,0),0)/100,"") | J18: =IFERROR(VLOOKUP($D18,BS별도,MATCH(J$1,BS별도H,0),0)/100,"") | K18: =SUM(G18:J18) | L18: =IFERROR(VLOOKUP($D18,BS별도,MATCH(L$1,BS별도H,0),0)/100,"") | M18: =IFERROR(VLOOKUP($D18,BS별도,MATCH(M$1,BS별도H,0),0)/100,"") | N18: =IFERROR(VLOOKUP($D18,BS별도,MATCH(N$1,BS별도H,0),0)/100,"") | O18: =IFERROR(VLOOKUP($D18,BS별도,MATCH(O$1,BS별도H,0),0)/100,"") | P18: =SUM(L18:O18) | Q18: =IFERROR(VLOOKUP($D18,BS별도,MATCH(Q$1,BS별도H,0),0)/100,"") | R18: =IFERROR(VLOOKUP($D18,BS별도,MATCH(R$1,BS별도H,0),0)/100,"") | S18: =IFERROR(VLOOKUP($D18,BS별도,MATCH(S$1,BS별도H,0),0)/100,"") | T18: =IFERROR(VLOOKUP($D18,BS별도,MATCH(T$1,BS별도H,0),0)/100,"") | U18: =SUM(Q18:T18) | V18: =IFERROR(VLOOKUP($D18,BS별도,MATCH(V$1,BS별도H,0),0)/100,"") | W18: =IFERROR(VLOOKUP($D18,BS별도,MATCH(W$1,BS별도H,0),0)/100,"") | X18: =IFERROR(VLOOKUP($D18,BS연결,MATCH(X$1,BS연결H,0),0)/100,"") | Y18: =IFERROR(VLOOKUP($D18,BS연결,MATCH(Y$1,BS연결H,0),0)/100,"") | Z18: =SUM(V18:Y18) | AA18: =IFERROR(VLOOKUP($D18,BS연결,MATCH(AA$1,BS연결H,0),0)/100,"") | AB18: =IFERROR(VLOOKUP($D18,BS연결,MATCH(AB$1,BS연결H,0),0)/100,"") | AC18: =IFERROR(AC17*변수!AC27,"") | AD18: =IFERROR(AD17*변수!AD27,"") | AE18: =SUM(AA18:AD18) | AF18: =IFERROR(AF17*변수!AF27,"") | AG18: =IFERROR(AG17*변수!AG27,"") | AH18: =IFERROR(AH17*변수!AH27,"") | AI18: =IFERROR(AI17*변수!AI27,"") | AJ18: =SUM(AF18:AI18) | AK18: =IFERROR(AK17*변수!AK27,"") | AL18: =IFERROR(AL17*변수!AL27,"") | AM18: =IFERROR(AM17*변수!AM27,"") | AN18: =IFERROR(AN17*변수!AN27,"") | AO18: =SUM(AK18:AN18)
A19: 자산총계 | B19: 재무상태 | C19: 억원 | D19: 자산총계 | E19: =IFERROR(VLOOKUP($D19,BS별도,MATCH(E$1,BS별도H,0),0)/100,"") | F19: 729.91 | G19: =IFERROR(VLOOKUP($D19,BS별도,MATCH(G$1,BS별도H,0),0)/100,"") | H19: =IFERROR(VLOOKUP($D19,BS별도,MATCH(H$1,BS별도H,0),0)/100,"") | I19: =IFERROR(VLOOKUP($D19,BS별도,MATCH(I$1,BS별도H,0),0)/100,"") | J19: =IFERROR(VLOOKUP($D19,BS별도,MATCH(J$1,BS별도H,0),0)/100,"") | K19: =J19 | L19: =IFERROR(VLOOKUP($D19,BS별도,MATCH(L$1,BS별도H,0),0)/100,"") | M19: =IFERROR(VLOOKUP($D19,BS별도,MATCH(M$1,BS별도H,0),0)/100,"") | N19: =IFERROR(VLOOKUP($D19,BS별도,MATCH(N$1,BS별도H,0),0)/100,"") | O19: =IFERROR(VLOOKUP($D19,BS별도,MATCH(O$1,BS별도H,0),0)/100,"") | P19: =O19 | Q19: =IFERROR(VLOOKUP($D19,BS별도,MATCH(Q$1,BS별도H,0),0)/100,"") | R19: =IFERROR(VLOOKUP($D19,BS별도,MATCH(R$1,BS별도H,0),0)/100,"") | S19: =IFERROR(VLOOKUP($D19,BS별도,MATCH(S$1,BS별도H,0),0)/100,"") | T19: =IFERROR(VLOOKUP($D19,BS별도,MATCH(T$1,BS별도H,0),0)/100,"") | U19: =T19 | V19: =IFERROR(VLOOKUP($D19,BS별도,MATCH(V$1,BS별도H,0),0)/100,"") | W19: =IFERROR(VLOOKUP($D19,BS별도,MATCH(W$1,BS별도H,0),0)/100,"") | X19: =IFERROR(VLOOKUP($D19,BS연결,MATCH(X$1,BS연결H,0),0)/100,"") | Y19: =IFERROR(VLOOKUP($D19,BS연결,MATCH(Y$1,BS연결H,0),0)/100,"") | Z19: =IFERROR(VLOOKUP($D19,BS연결,MATCH(Z$1,BS연결H,0),0)/100,"") | AA19: =IFERROR(VLOOKUP($D19,BS연결,MATCH(AA$1,BS연결H,0),0)/100,"") | AB19: =IFERROR(VLOOKUP($D19,BS연결,MATCH(AB$1,BS연결H,0),0)/100,"") | AC19: =IFERROR(AC20+AC21,"") | AD19: =IFERROR(AD20+AD21,"") | AE19: =AD19 | AF19: =IFERROR(AF20+AF21,"") | AG19: =IFERROR(AG20+AG21,"") | AH19: =IFERROR(AH20+AH21,"") | AI19: =IFERROR(AI20+AI21,"") | AJ19: =AI19 | AK19: =IFERROR(AK20+AK21,"") | AL19: =IFERROR(AL20+AL21,"") | AM19: =IFERROR(AM20+AM21,"") | AN19: =IFERROR(AN20+AN21,"") | AO19: =AN19
A20: 부채총계 | B20: 재무상태 | C20: 억원 | D20: 부채총계 | E20: =IFERROR(VLOOKUP($D20,BS별도,MATCH(E$1,BS별도H,0),0)/100,"") | F20: 106.48 | G20: =IFERROR(VLOOKUP($D20,BS별도,MATCH(G$1,BS별도H,0),0)/100,"") | H20: =IFERROR(VLOOKUP($D20,BS별도,MATCH(H$1,BS별도H,0),0)/100,"") | I20: =IFERROR(VLOOKUP($D20,BS별도,MATCH(I$1,BS별도H,0),0)/100,"") | J20: =IFERROR(VLOOKUP($D20,BS별도,MATCH(J$1,BS별도H,0),0)/100,"") | K20: =J20 | L20: =IFERROR(VLOOKUP($D20,BS별도,MATCH(L$1,BS별도H,0),0)/100,"") | M20: =IFERROR(VLOOKUP($D20,BS별도,MATCH(M$1,BS별도H,0),0)/100,"") | N20: =IFERROR(VLOOKUP($D20,BS별도,MATCH(N$1,BS별도H,0),0)/100,"") | O20: =IFERROR(VLOOKUP($D20,BS별도,MATCH(O$1,BS별도H,0),0)/100,"") | P20: =O20 | Q20: =IFERROR(VLOOKUP($D20,BS별도,MATCH(Q$1,BS별도H,0),0)/100,"") | R20: =IFERROR(VLOOKUP($D20,BS별도,MATCH(R$1,BS별도H,0),0)/100,"") | S20: =IFERROR(VLOOKUP($D20,BS별도,MATCH(S$1,BS별도H,0),0)/100,"") | T20: =IFERROR(VLOOKUP($D20,BS별도,MATCH(T$1,BS별도H,0),0)/100,"") | U20: =T20 | V20: =IFERROR(VLOOKUP($D20,BS별도,MATCH(V$1,BS별도H,0),0)/100,"") | W20: =IFERROR(VLOOKUP($D20,BS별도,MATCH(W$1,BS별도H,0),0)/100,"") | X20: =IFERROR(VLOOKUP($D20,BS연결,MATCH(X$1,BS연결H,0),0)/100,"") | Y20: =IFERROR(VLOOKUP($D20,BS연결,MATCH(Y$1,BS연결H,0),0)/100,"") | Z20: =IFERROR(VLOOKUP($D20,BS연결,MATCH(Z$1,BS연결H,0),0)/100,"") | AA20: =IFERROR(VLOOKUP($D20,BS연결,MATCH(AA$1,BS연결H,0),0)/100,"") | AB20: =IFERROR(VLOOKUP($D20,BS연결,MATCH(AB$1,BS연결H,0),0)/100,"") | AC20: =IFERROR(AB20*(1+변수!AC28),"") | AD20: =IFERROR(AC20*(1+변수!AD28),"") | AE20: =AD20 | AF20: =IFERROR(AD20*(1+변수!AF28),"") | AG20: =IFERROR(AF20*(1+변수!AG28),"") | AH20: =IFERROR(AG20*(1+변수!AH28),"") | AI20: =IFERROR(AH20*(1+변수!AI28),"") | AJ20: =AI20 | AK20: =IFERROR(AI20*(1+변수!AK28),"") | AL20: =IFERROR(AK20*(1+변수!AL28),"") | AM20: =IFERROR(AL20*(1+변수!AM28),"") | AN20: =IFERROR(AM20*(1+변수!AN28),"") | AO20: =AN20
A21: 자본총계 | B21: 재무상태 | C21: 억원 | D21: 자본총계 | E21: =IFERROR(VLOOKUP($D21,BS별도,MATCH(E$1,BS별도H,0),0)/100,"") | F21: 623.43 | G21: =IFERROR(VLOOKUP($D21,BS별도,MATCH(G$1,BS별도H,0),0)/100,"") | H21: =IFERROR(VLOOKUP($D21,BS별도,MATCH(H$1,BS별도H,0),0)/100,"") | I21: =IFERROR(VLOOKUP($D21,BS별도,MATCH(I$1,BS별도H,0),0)/100,"") | J21: =IFERROR(VLOOKUP($D21,BS별도,MATCH(J$1,BS별도H,0),0)/100,"") | K21: =J21 | L21: =IFERROR(VLOOKUP($D21,BS별도,MATCH(L$1,BS별도H,0),0)/100,"") | M21: =IFERROR(VLOOKUP($D21,BS별도,MATCH(M$1,BS별도H,0),0)/100,"") | N21: =IFERROR(VLOOKUP($D21,BS별도,MATCH(N$1,BS별도H,0),0)/100,"") | O21: =IFERROR(VLOOKUP($D21,BS별도,MATCH(O$1,BS별도H,0),0)/100,"") | P21: =O21 | Q21: =IFERROR(VLOOKUP($D21,BS별도,MATCH(Q$1,BS별도H,0),0)/100,"") | R21: =IFERROR(VLOOKUP($D21,BS별도,MATCH(R$1,BS별도H,0),0)/100,"") | S21: =IFERROR(VLOOKUP($D21,BS별도,MATCH(S$1,BS별도H,0),0)/100,"") | T21: =IFERROR(VLOOKUP($D21,BS별도,MATCH(T$1,BS별도H,0),0)/100,"") | U21: =T21 | V21: =IFERROR(VLOOKUP($D21,BS별도,MATCH(V$1,BS별도H,0),0)/100,"") | W21: =IFERROR(VLOOKUP($D21,BS별도,MATCH(W$1,BS별도H,0),0)/100,"") | X21: =IFERROR(VLOOKUP($D21,BS연결,MATCH(X$1,BS연결H,0),0)/100,"") | Y21: =IFERROR(VLOOKUP($D21,BS연결,MATCH(Y$1,BS연결H,0),0)/100,"") | Z21: =IFERROR(VLOOKUP($D21,BS연결,MATCH(Z$1,BS연결H,0),0)/100,"") | AA21: =IFERROR(VLOOKUP($D21,BS연결,MATCH(AA$1,BS연결H,0),0)/100,"") | AB21: =IFERROR(VLOOKUP($D21,BS연결,MATCH(AB$1,BS연결H,0),0)/100,"") | AC21: =IFERROR(AB21+AC17-변수!AC29,"") | AD21: =IFERROR(AC21+AD17-변수!AD29,"") | AE21: =AD21 | AF21: =IFERROR(AD21+AF17-변수!AF29,"") | AG21: =IFERROR(AF21+AG17-변수!AG29,"") | AH21: =IFERROR(AG21+AH17-변수!AH29,"") | AI21: =IFERROR(AH21+AI17-변수!AI29,"") | AJ21: =AI21 | AK21: =IFERROR(AI21+AK17-변수!AK29,"") | AL21: =IFERROR(AK21+AL17-변수!AL29,"") | AM21: =IFERROR(AL21+AM17-변수!AM29,"") | AN21: =IFERROR(AM21+AN17-변수!AN29,"") | AO21: =AN21
A22: 지배주주지분 | B22: 재무상태 | C22: 억원 | D22: 지배주주지분 | E22: =IFERROR(VLOOKUP($D22,BS별도,MATCH(E$1,BS별도H,0),0)/100,"") | F22: 623.43 | G22: =IFERROR(VLOOKUP($D22,BS별도,MATCH(G$1,BS별도H,0),0)/100,"") | H22: =IFERROR(VLOOKUP($D22,BS별도,MATCH(H$1,BS별도H,0),0)/100,"") | I22: =IFERROR(VLOOKUP($D22,BS별도,MATCH(I$1,BS별도H,0),0)/100,"") | J22: =IFERROR(VLOOKUP($D22,BS별도,MATCH(J$1,BS별도H,0),0)/100,"") | K22: =J22 | L22: =IFERROR(VLOOKUP($D22,BS별도,MATCH(L$1,BS별도H,0),0)/100,"") | M22: =IFERROR(VLOOKUP($D22,BS별도,MATCH(M$1,BS별도H,0),0)/100,"") | N22: =IFERROR(VLOOKUP($D22,BS별도,MATCH(N$1,BS별도H,0),0)/100,"") | O22: =IFERROR(VLOOKUP($D22,BS별도,MATCH(O$1,BS별도H,0),0)/100,"") | P22: =O22 | Q22: =IFERROR(VLOOKUP($D22,BS별도,MATCH(Q$1,BS별도H,0),0)/100,"") | R22: =IFERROR(VLOOKUP($D22,BS별도,MATCH(R$1,BS별도H,0),0)/100,"") | S22: =IFERROR(VLOOKUP($D22,BS별도,MATCH(S$1,BS별도H,0),0)/100,"") | T22: =IFERROR(VLOOKUP($D22,BS별도,MATCH(T$1,BS별도H,0),0)/100,"") | U22: =T22 | V22: =IFERROR(VLOOKUP($D22,BS별도,MATCH(V$1,BS별도H,0),0)/100,"") | W22: =IFERROR(VLOOKUP($D22,BS별도,MATCH(W$1,BS별도H,0),0)/100,"") | X22: =IFERROR(VLOOKUP($D22,BS연결,MATCH(X$1,BS연결H,0),0)/100,"") | Y22: =IFERROR(VLOOKUP($D22,BS연결,MATCH(Y$1,BS연결H,0),0)/100,"") | Z22: =IFERROR(VLOOKUP($D22,BS연결,MATCH(Z$1,BS연결H,0),0)/100,"") | AA22: =IFERROR(VLOOKUP($D22,BS연결,MATCH(AA$1,BS연결H,0),0)/100,"") | AB22: =IFERROR(VLOOKUP($D22,BS연결,MATCH(AB$1,BS연결H,0),0)/100,"") | AC22: =IFERROR(AB22+AC18-변수!AC30,"") | AD22: =IFERROR(AC22+AD18-변수!AD30,"") | AE22: =AD22 | AF22: =IFERROR(AD22+AF18-변수!AF30,"") | AG22: =IFERROR(AF22+AG18-변수!AG30,"") | AH22: =IFERROR(AG22+AH18-변수!AH30,"") | AI22: =IFERROR(AH22+AI18-변수!AI30,"") | AJ22: =AI22 | AK22: =IFERROR(AI22+AK18-변수!AK30,"") | AL22: =IFERROR(AK22+AL18-변수!AL30,"") | AM22: =IFERROR(AL22+AM18-변수!AM30,"") | AN22: =IFERROR(AM22+AN18-변수!AN30,"") | AO22: =AN22
A23: 총차입금 | B23: 재무상태 | C23: 억원 | D23: 총차입금 | F23: =E23 | K23: =J23 | P23: =O23 | U23: =T23 | X23: =IFERROR(VLOOKUP($D23,BS연결,MATCH(X$1,BS연결H,0),0)/100,"") | Y23: =IFERROR(VLOOKUP($D23,BS연결,MATCH(Y$1,BS연결H,0),0)/100,"") | Z23: =IFERROR(VLOOKUP($D23,BS연결,MATCH(Z$1,BS연결H,0),0)/100,"") | AA23: =IFERROR(VLOOKUP($D23,BS연결,MATCH(AA$1,BS연결H,0),0)/100,"") | AB23: =IFERROR(VLOOKUP($D23,BS연결,MATCH(AB$1,BS연결H,0),0)/100,"") | AC23: =IFERROR(AB23*(1+변수!AC31),"") | AD23: =IFERROR(AC23*(1+변수!AD31),"") | AE23: =AD23 | AF23: =IFERROR(AD23*(1+변수!AF31),"") | AG23: =IFERROR(AF23*(1+변수!AG31),"") | AH23: =IFERROR(AG23*(1+변수!AH31),"") | AI23: =IFERROR(AH23*(1+변수!AI31),"") | AJ23: =AI23 | AK23: =IFERROR(AI23*(1+변수!AK31),"") | AL23: =IFERROR(AK23*(1+변수!AL31),"") | AM23: =IFERROR(AL23*(1+변수!AM31),"") | AN23: =IFERROR(AM23*(1+변수!AN31),"") | AO23: =AN23
A24: 순차입금 | B24: 재무상태 | C24: 억원 | D24: 순차입금 | F24: =E24 | K24: =J24 | P24: =O24 | U24: =T24 | X24: =IFERROR(VLOOKUP($D24,BS연결,MATCH(X$1,BS연결H,0),0)/100,"") | Y24: =IFERROR(VLOOKUP($D24,BS연결,MATCH(Y$1,BS연결H,0),0)/100,"") | Z24: =IFERROR(VLOOKUP($D24,BS연결,MATCH(Z$1,BS연결H,0),0)/100,"") | AA24: =IFERROR(VLOOKUP($D24,BS연결,MATCH(AA$1,BS연결H,0),0)/100,"") | AB24: =IFERROR(VLOOKUP($D24,BS연결,MATCH(AB$1,BS연결H,0),0)/100,"") | AC24: =IFERROR(AB24*(1+변수!AC32),"") | AD24: =IFERROR(AC24*(1+변수!AD32),"") | AE24: =AD24 | AF24: =IFERROR(AD24*(1+변수!AF32),"") | AG24: =IFERROR(AF24*(1+변수!AG32),"") | AH24: =IFERROR(AG24*(1+변수!AH32),"") | AI24: =IFERROR(AH24*(1+변수!AI32),"") | AJ24: =AI24 | AK24: =IFERROR(AI24*(1+변수!AK32),"") | AL24: =IFERROR(AK24*(1+변수!AL32),"") | AM24: =IFERROR(AL24*(1+변수!AM32),"") | AN24: =IFERROR(AM24*(1+변수!AN32),"") | AO24: =AN24
A25: 이자발생자산 | B25: 재무상태 | C25: 억원 | D25: 이자발생자산 | E25: =IFERROR(VLOOKUP($D25,BS별도,MATCH(E$1,BS별도H,0),0)/100,"") | F25: 22.02 | G25: =IFERROR(VLOOKUP($D25,BS별도,MATCH(G$1,BS별도H,0),0)/100,"") | H25: =IFERROR(VLOOKUP($D25,BS별도,MATCH(H$1,BS별도H,0),0)/100,"") | I25: =IFERROR(VLOOKUP($D25,BS별도,MATCH(I$1,BS별도H,0),0)/100,"") | J25: =IFERROR(VLOOKUP($D25,BS별도,MATCH(J$1,BS별도H,0),0)/100,"") | K25: =J25 | L25: =IFERROR(VLOOKUP($D25,BS별도,MATCH(L$1,BS별도H,0),0)/100,"") | M25: =IFERROR(VLOOKUP($D25,BS별도,MATCH(M$1,BS별도H,0),0)/100,"") | N25: =IFERROR(VLOOKUP($D25,BS별도,MATCH(N$1,BS별도H,0),0)/100,"") | O25: =IFERROR(VLOOKUP($D25,BS별도,MATCH(O$1,BS별도H,0),0)/100,"") | P25: =O25 | Q25: =IFERROR(VLOOKUP($D25,BS별도,MATCH(Q$1,BS별도H,0),0)/100,"") | R25: =IFERROR(VLOOKUP($D25,BS별도,MATCH(R$1,BS별도H,0),0)/100,"") | S25: =IFERROR(VLOOKUP($D25,BS별도,MATCH(S$1,BS별도H,0),0)/100,"") | T25: =IFERROR(VLOOKUP($D25,BS별도,MATCH(T$1,BS별도H,0),0)/100,"") | U25: =T25 | V25: =IFERROR(VLOOKUP($D25,BS별도,MATCH(V$1,BS별도H,0),0)/100,"") | W25: =IFERROR(VLOOKUP($D25,BS별도,MATCH(W$1,BS별도H,0),0)/100,"") | X25: =IFERROR(VLOOKUP($D25,BS연결,MATCH(X$1,BS연결H,0),0)/100,"") | Y25: =IFERROR(VLOOKUP($D25,BS연결,MATCH(Y$1,BS연결H,0),0)/100,"") | Z25: =IFERROR(VLOOKUP($D25,BS연결,MATCH(Z$1,BS연결H,0),0)/100,"") | AA25: =IFERROR(VLOOKUP($D25,BS연결,MATCH(AA$1,BS연결H,0),0)/100,"") | AB25: =IFERROR(VLOOKUP($D25,BS연결,MATCH(AB$1,BS연결H,0),0)/100,"") | AC25: =IFERROR(AB25*(1+변수!AC33),"") | AD25: =IFERROR(AC25*(1+변수!AD33),"") | AE25: =AD25 | AF25: =IFERROR(AD25*(1+변수!AF33),"") | AG25: =IFERROR(AF25*(1+변수!AG33),"") | AH25: =IFERROR(AG25*(1+변수!AH33),"") | AI25: =IFERROR(AH25*(1+변수!AI33),"") | AJ25: =AI25 | AK25: =IFERROR(AI25*(1+변수!AK33),"") | AL25: =IFERROR(AK25*(1+변수!AL33),"") | AM25: =IFERROR(AL25*(1+변수!AM33),"") | AN25: =IFERROR(AM25*(1+변수!AN33),"") | AO25: =AN25
A26: 현금및현금성자산 | B26: 재무상태 | C26: 억원 | D26: 현금및현금성자산 | E26: =IFERROR(VLOOKUP($D26,BS별도,MATCH(E$1,BS별도H,0),0)/100,"") | F26: 18.34 | G26: =IFERROR(VLOOKUP($D26,BS별도,MATCH(G$1,BS별도H,0),0)/100,"") | H26: =IFERROR(VLOOKUP($D26,BS별도,MATCH(H$1,BS별도H,0),0)/100,"") | I26: =IFERROR(VLOOKUP($D26,BS별도,MATCH(I$1,BS별도H,0),0)/100,"") | J26: =IFERROR(VLOOKUP($D26,BS별도,MATCH(J$1,BS별도H,0),0)/100,"") | K26: =J26 | L26: =IFERROR(VLOOKUP($D26,BS별도,MATCH(L$1,BS별도H,0),0)/100,"") | M26: =IFERROR(VLOOKUP($D26,BS별도,MATCH(M$1,BS별도H,0),0)/100,"") | N26: =IFERROR(VLOOKUP($D26,BS별도,MATCH(N$1,BS별도H,0),0)/100,"") | O26: =IFERROR(VLOOKUP($D26,BS별도,MATCH(O$1,BS별도H,0),0)/100,"") | P26: =O26 | Q26: =IFERROR(VLOOKUP($D26,BS별도,MATCH(Q$1,BS별도H,0),0)/100,"") | R26: =IFERROR(VLOOKUP($D26,BS별도,MATCH(R$1,BS별도H,0),0)/100,"") | S26: =IFERROR(VLOOKUP($D26,BS별도,MATCH(S$1,BS별도H,0),0)/100,"") | T26: =IFERROR(VLOOKUP($D26,BS별도,MATCH(T$1,BS별도H,0),0)/100,"") | U26: =T26 | V26: =IFERROR(VLOOKUP($D26,BS별도,MATCH(V$1,BS별도H,0),0)/100,"") | W26: =IFERROR(VLOOKUP($D26,BS별도,MATCH(W$1,BS별도H,0),0)/100,"") | X26: =IFERROR(VLOOKUP($D26,BS연결,MATCH(X$1,BS연결H,0),0)/100,"") | Y26: =IFERROR(VLOOKUP($D26,BS연결,MATCH(Y$1,BS연결H,0),0)/100,"") | Z26: =IFERROR(VLOOKUP($D26,BS연결,MATCH(Z$1,BS연결H,0),0)/100,"") | AA26: =IFERROR(VLOOKUP($D26,BS연결,MATCH(AA$1,BS연결H,0),0)/100,"") | AB26: =IFERROR(VLOOKUP($D26,BS연결,MATCH(AB$1,BS연결H,0),0)/100,"") | AE26: =AD26 | AJ26: =AI26 | AO26: =AN26
A27: CAPEX | B27: 현금흐름 | C27: 억원 | D27: CAPEX | E27: =IFERROR(VLOOKUP($D27,BS별도,MATCH(E$1,BS별도H,0),0)/100,"") | G27: =IFERROR(VLOOKUP($D27,BS별도,MATCH(G$1,BS별도H,0),0)/100,"") | H27: =IFERROR(VLOOKUP($D27,BS별도,MATCH(H$1,BS별도H,0),0)/100,"") | I27: =IFERROR(VLOOKUP($D27,BS별도,MATCH(I$1,BS별도H,0),0)/100,"") | J27: =IFERROR(VLOOKUP($D27,BS별도,MATCH(J$1,BS별도H,0),0)/100,"") | K27: =SUM(G27:J27) | L27: =IFERROR(VLOOKUP($D27,BS별도,MATCH(L$1,BS별도H,0),0)/100,"") | M27: =IFERROR(VLOOKUP($D27,BS별도,MATCH(M$1,BS별도H,0),0)/100,"") | N27: =IFERROR(VLOOKUP($D27,BS별도,MATCH(N$1,BS별도H,0),0)/100,"") | O27: =IFERROR(VLOOKUP($D27,BS별도,MATCH(O$1,BS별도H,0),0)/100,"") | P27: =SUM(L27:O27) | Q27: =IFERROR(VLOOKUP($D27,BS별도,MATCH(Q$1,BS별도H,0),0)/100,"") | R27: =IFERROR(VLOOKUP($D27,BS별도,MATCH(R$1,BS별도H,0),0)/100,"") | S27: =IFERROR(VLOOKUP($D27,BS별도,MATCH(S$1,BS별도H,0),0)/100,"") | T27: =IFERROR(VLOOKUP($D27,BS별도,MATCH(T$1,BS별도H,0),0)/100,"") | U27: =SUM(Q27:T27) | V27: =IFERROR(VLOOKUP($D27,BS별도,MATCH(V$1,BS별도H,0),0)/100,"") | W27: =IFERROR(VLOOKUP($D27,BS별도,MATCH(W$1,BS별도H,0),0)/100,"") | X27: =IFERROR(VLOOKUP($D27,BS연결,MATCH(X$1,BS연결H,0),0)/100,"") | Y27: =IFERROR(VLOOKUP($D27,BS연결,MATCH(Y$1,BS연결H,0),0)/100,"") | Z27: =SUM(V27:Y27) | AA27: =IFERROR(VLOOKUP($D27,BS연결,MATCH(AA$1,BS연결H,0),0)/100,"") | AB27: =IFERROR(VLOOKUP($D27,BS연결,MATCH(AB$1,BS연결H,0),0)/100,"") | AC27: =IFERROR(X27*(1+변수!AC35),"") | AD27: =IFERROR(Y27*(1+변수!AD35),"") | AE27: =SUM(AA27:AD27) | AF27: =IFERROR(AA27*(1+변수!AF35),"") | AG27: =IFERROR(AB27*(1+변수!AG35),"") | AH27: =IFERROR(AC27*(1+변수!AH35),"") | AI27: =IFERROR(AD27*(1+변수!AI35),"") | AJ27: =SUM(AF27:AI27) | AK27: =IFERROR(AF27*(1+변수!AK35),"") | AL27: =IFERROR(AG27*(1+변수!AL35),"") | AM27: =IFERROR(AH27*(1+변수!AM35),"") | AN27: =IFERROR(AI27*(1+변수!AN35),"") | AO27: =SUM(AK27:AN27)
A28: 영업활동현금흐름 | B28: 현금흐름 | C28: 억원 | D28: 영업활동으로인한현금흐름 | E28: =IFERROR(VLOOKUP($D28,BS별도,MATCH(E$1,BS별도H,0),0)/100,"") | G28: =IFERROR(VLOOKUP($D28,BS별도,MATCH(G$1,BS별도H,0),0)/100,"") | H28: =IFERROR(VLOOKUP($D28,BS별도,MATCH(H$1,BS별도H,0),0)/100,"") | I28: =IFERROR(VLOOKUP($D28,BS별도,MATCH(I$1,BS별도H,0),0)/100,"") | J28: =IFERROR(VLOOKUP($D28,BS별도,MATCH(J$1,BS별도H,0),0)/100,"") | K28: =SUM(G28:J28) | L28: =IFERROR(VLOOKUP($D28,BS별도,MATCH(L$1,BS별도H,0),0)/100,"") | M28: =IFERROR(VLOOKUP($D28,BS별도,MATCH(M$1,BS별도H,0),0)/100,"") | N28: =IFERROR(VLOOKUP($D28,BS별도,MATCH(N$1,BS별도H,0),0)/100,"") | O28: =IFERROR(VLOOKUP($D28,BS별도,MATCH(O$1,BS별도H,0),0)/100,"") | P28: =SUM(L28:O28) | Q28: =IFERROR(VLOOKUP($D28,BS별도,MATCH(Q$1,BS별도H,0),0)/100,"") | R28: =IFERROR(VLOOKUP($D28,BS별도,MATCH(R$1,BS별도H,0),0)/100,"") | S28: =IFERROR(VLOOKUP($D28,BS별도,MATCH(S$1,BS별도H,0),0)/100,"") | T28: =IFERROR(VLOOKUP($D28,BS별도,MATCH(T$1,BS별도H,0),0)/100,"") | U28: =SUM(Q28:T28) | V28: =IFERROR(VLOOKUP($D28,BS별도,MATCH(V$1,BS별도H,0),0)/100,"") | W28: =IFERROR(VLOOKUP($D28,BS별도,MATCH(W$1,BS별도H,0),0)/100,"") | X28: =IFERROR(VLOOKUP($D28,BS연결,MATCH(X$1,BS연결H,0),0)/100,"") | Y28: =IFERROR(VLOOKUP($D28,BS연결,MATCH(Y$1,BS연결H,0),0)/100,"") | Z28: =SUM(V28:Y28) | AA28: =IFERROR(VLOOKUP($D28,BS연결,MATCH(AA$1,BS연결H,0),0)/100,"") | AB28: =IFERROR(VLOOKUP($D28,BS연결,MATCH(AB$1,BS연결H,0),0)/100,"") | AE28: =SUM(AA28:AD28) | AJ28: =SUM(AF28:AI28) | AO28: =SUM(AK28:AN28)
A29: 주식수 | B29: 주당 | C29: 백만주 | D29: 유통주식수 | E29: 12.6 | F29: =E29 | G29: 12.6 | H29: 12.6 | I29: 12.6 | J29: 12.6 | K29: =J29 | L29: 12.6 | M29: 12.6 | N29: 12.6 | O29: 12.6 | P29: =O29 | Q29: 12.6 | R29: 12.6 | S29: 12.6 | T29: 12.6 | U29: =T29 | V29: 12.6 | W29: 12.6 | X29: 12.6 | Y29: 12.6 | Z29: =Y29 | AA29: 12.6 | AB29: 12.6 | AC29: =IFERROR(AB29*(1+변수!AC37),"") | AD29: =IFERROR(AC29*(1+변수!AD37),"") | AE29: =AD29 | AF29: =IFERROR(AD29*(1+변수!AF37),"") | AG29: =IFERROR(AF29*(1+변수!AG37),"") | AH29: =IFERROR(AG29*(1+변수!AH37),"") | AI29: =IFERROR(AH29*(1+변수!AI37),"") | AJ29: =AI29 | AK29: =IFERROR(AI29*(1+변수!AK37),"") | AL29: =IFERROR(AK29*(1+변수!AL37),"") | AM29: =IFERROR(AL29*(1+변수!AM37),"") | AN29: =IFERROR(AM29*(1+변수!AN37),"") | AO29: =AN29
A30: EPS | B30: 주당 | C30: 원 | D30: EPS | E30: =IFERROR(E18*100/E29,"") | G30: =IFERROR(G18*100/G29,"") | H30: =IFERROR(H18*100/H29,"") | I30: =IFERROR(I18*100/I29,"") | J30: =IFERROR(J18*100/J29,"") | K30: =SUM(G30:J30) | L30: =IFERROR(L18*100/L29,"") | M30: =IFERROR(M18*100/M29,"") | N30: =IFERROR(N18*100/N29,"") | O30: =IFERROR(O18*100/O29,"") | P30: =SUM(L30:O30) | Q30: =IFERROR(Q18*100/Q29,"") | R30: =IFERROR(R18*100/R29,"") | S30: =IFERROR(S18*100/S29,"") | T30: =IFERROR(T18*100/T29,"") | U30: =SUM(Q30:T30) | V30: =IFERROR(V18*100/V29,"") | W30: =IFERROR(W18*100/W29,"") | X30: =IFERROR(X18*100/X29,"") | Y30: =IFERROR(Y18*100/Y29,"") | Z30: =SUM(V30:Y30) | AA30: =IFERROR(AA18*100/AA29,"") | AB30: =IFERROR(AB18*100/AB29,"") | AC30: =IFERROR(AC18*100/AC29,"") | AD30: =IFERROR(AD18*100/AD29,"") | AE30: =SUM(AA30:AD30) | AF30: =IFERROR(AF18*100/AF29,"") | AG30: =IFERROR(AG18*100/AG29,"") | AH30: =IFERROR(AH18*100/AH29,"") | AI30: =IFERROR(AI18*100/AI29,"") | AJ30: =SUM(AF30:AI30) | AK30: =IFERROR(AK18*100/AK29,"") | AL30: =IFERROR(AL18*100/AL29,"") | AM30: =IFERROR(AM18*100/AM29,"") | AN30: =IFERROR(AN18*100/AN29,"") | AO30: =SUM(AK30:AN30)
A31: BPS | B31: 주당 | C31: 원 | D31: BPS | E31: =IFERROR(E22*100/E29,"") | F31: =E31 | G31: =IFERROR(G22*100/G29,"") | H31: =IFERROR(H22*100/H29,"") | I31: =IFERROR(I22*100/I29,"") | J31: =IFERROR(J22*100/J29,"") | K31: =J31 | L31: =IFERROR(L22*100/L29,"") | M31: =IFERROR(M22*100/M29,"") | N31: =IFERROR(N22*100/N29,"") | O31: =IFERROR(O22*100/O29,"") | P31: =O31 | Q31: =IFERROR(Q22*100/Q29,"") | R31: =IFERROR(R22*100/R29,"") | S31: =IFERROR(S22*100/S29,"") | T31: =IFERROR(T22*100/T29,"") | U31: =T31 | V31: =IFERROR(V22*100/V29,"") | W31: =IFERROR(W22*100/W29,"") | X31: =IFERROR(X22*100/X29,"") | Y31: =IFERROR(Y22*100/Y29,"") | Z31: =Y31 | AA31: =IFERROR(AA22*100/AA29,"") | AB31: =IFERROR(AB22*100/AB29,"") | AC31: =IFERROR(AC22*100/AC29,"") | AD31: =IFERROR(AD22*100/AD29,"") | AE31: =AD31 | AF31: =IFERROR(AF22*100/AF29,"") | AG31: =IFERROR(AG22*100/AG29,"") | AH31: =IFERROR(AH22*100/AH29,"") | AI31: =IFERROR(AI22*100/AI29,"") | AJ31: =AI31 | AK31: =IFERROR(AK22*100/AK29,"") | AL31: =IFERROR(AL22*100/AL29,"") | AM31: =IFERROR(AM22*100/AM29,"") | AN31: =IFERROR(AN22*100/AN29,"") | AO31: =AN31
A32: DPS | B32: 주당 | C32: 원 | D32: DPS(보통주) | E32: 35 | F32: 35 | J32: 35 | K32: =SUM(G32:J32) | O32: 35 | P32: =SUM(L32:O32) | T32: 10 | U32: =SUM(Q32:T32) | Y32: 10 | Z32: =SUM(V32:Y32) | AD32: =변수!AD38 | AE32: =SUM(AA32:AD32) | AI32: =변수!AI38 | AJ32: =SUM(AF32:AI32) | AN32: =변수!AN38 | AO32: =SUM(AK32:AN32)
A33: PER | B33: 주당 | C33: 배 | D33: PER | F33: =E33 | I33: =IFERROR(변수!I18/(E30+G30+H30+I30),"") | J33: =IFERROR(변수!J18/(G30+H30+I30+J30),"") | K33: =J33 | L33: =IFERROR(변수!L18/(H30+I30+J30+L30),"") | M33: =IFERROR(변수!M18/(I30+J30+L30+M30),"") | N33: =IFERROR(변수!N18/(J30+L30+M30+N30),"") | O33: =IFERROR(변수!O18/(L30+M30+N30+O30),"") | P33: =O33 | Q33: =IFERROR(변수!Q18/(M30+N30+O30+Q30),"") | R33: =IFERROR(변수!R18/(N30+O30+Q30+R30),"") | S33: =IFERROR(변수!S18/(O30+Q30+R30+S30),"") | T33: =IFERROR(변수!T18/(Q30+R30+S30+T30),"") | U33: =T33 | V33: =IFERROR(변수!V18/(R30+S30+T30+V30),"") | X33: =IFERROR(변수!X18/(T30+V30+W30+X30),"") | Y33: =IFERROR(변수!Y18/(V30+W30+X30+Y30),"") | Z33: =Y33 | AA33: =IFERROR(변수!AA18/(W30+X30+Y30+AA30),"") | AB33: =IFERROR(변수!AB18/(X30+Y30+AA30+AB30),"") | AC33: =IFERROR(변수!$D$41/(Y30+AA30+AB30+AC30),"") | AD33: =IFERROR(변수!$D$41/(AA30+AB30+AC30+AD30),"") | AE33: =AD33 | AF33: =IFERROR(변수!$D$41/(AB30+AC30+AD30+AF30),"") | AG33: =IFERROR(변수!$D$41/(AC30+AD30+AF30+AG30),"") | AH33: =IFERROR(변수!$D$41/(AD30+AF30+AG30+AH30),"") | AI33: =IFERROR(변수!$D$41/(AF30+AG30+AH30+AI30),"") | AJ33: =AI33 | AO33: =AN33
A34: PBR | B34: 주당 | C34: 배 | D34: PBR | E34: =IFERROR(변수!E18/E31,"") | F34: =E34 | G34: =IFERROR(변수!G18/G31,"") | H34: =IFERROR(변수!H18/H31,"") | I34: =IFERROR(변수!I18/I31,"") | J34: =IFERROR(변수!J18/J31,"") | K34: =J34 | L34: =IFERROR(변수!L18/L31,"") | M34: =IFERROR(변수!M18/M31,"") | N34: =IFERROR(변수!N18/N31,"") | O34: =IFERROR(변수!O18/O31,"") | P34: =O34 | Q34: =IFERROR(변수!Q18/Q31,"") | R34: =IFERROR(변수!R18/R31,"") | S34: =IFERROR(변수!S18/S31,"") | T34: =IFERROR(변수!T18/T31,"") | U34: =T34 | V34: =IFERROR(변수!V18/V31,"") | W34: =IFERROR(변수!W18/W31,"") | X34: =IFERROR(변수!X18/X31,"") | Y34: =IFERROR(변수!Y18/Y31,"") | Z34: =Y34 | AA34: =IFERROR(변수!AA18/AA31,"") | AB34: =IFERROR(변수!AB18/AB31,"") | AC34: =IFERROR(변수!$D$41/AC31,"") | AD34: =IFERROR(변수!$D$41/AD31,"") | AE34: =AD34 | AF34: =IFERROR(변수!$D$41/AF31,"") | AG34: =IFERROR(변수!$D$41/AG31,"") | AH34: =IFERROR(변수!$D$41/AH31,"") | AI34: =IFERROR(변수!$D$41/AI31,"") | AJ34: =AI34 | AK34: =IFERROR(변수!$D$41/AK31,"") | AL34: =IFERROR(변수!$D$41/AL31,"") | AM34: =IFERROR(변수!$D$41/AM31,"") | AN34: =IFERROR(변수!$D$41/AN31,"") | AO34: =AN34
A35: 매출전사 | B35: 사업부 | C35: 억원 | D35: 매출 전사(부문 미분리) | E35: 124.31 | G35: 119.67 | H35: 119.47 | I35: 142.22 | J35: 122.82 | K35: =SUM(G35:J35) | L35: 126.09 | M35: 115.03 | N35: 107.08 | O35: 110.18 | P35: =SUM(L35:O35) | Q35: 104.55 | R35: 110.69 | S35: 110.5 | T35: 97.97 | U35: =SUM(Q35:T35) | V35: 97.77 | W35: 114.4 | X35: 124.33 | Y35: 128.52 | Z35: =SUM(V35:Y35) | AA35: 110.44 | AB35: 134.65 | AC35: =IFERROR(AC5,"") | AD35: =IFERROR(AD5,"") | AE35: =SUM(AA35:AD35) | AF35: =IFERROR(AF5,"") | AG35: =IFERROR(AG5,"") | AH35: =IFERROR(AH5,"") | AI35: =IFERROR(AI5,"") | AJ35: =SUM(AF35:AI35) | AK35: =IFERROR(AK5,"") | AL35: =IFERROR(AL5,"") | AM35: =IFERROR(AM5,"") | AN35: =IFERROR(AN5,"") | AO35: =SUM(AK35:AN35)
A36: OP전사 | B36: 사업부 | C36: 억원 | D36: OP 전사(부문 미분리) | E36: -7.49 | G36: 5.49 | H36: 4.64 | I36: 5.21 | J36: 0.76 | K36: =SUM(G36:J36) | L36: 1.84 | M36: 8.2 | N36: -5.24 | O36: 1.34 | P36: =SUM(L36:O36) | Q36: -7.16 | R36: 2.53 | S36: -4.14 | T36: -4.17 | U36: =SUM(Q36:T36) | V36: -7.66 | W36: 3.68 | X36: 1.52 | Y36: 2.9 | Z36: =SUM(V36:Y36) | AA36: -3.69 | AB36: 9.63 | AC36: =IFERROR(AC9,"") | AD36: =IFERROR(AD9,"") | AE36: =SUM(AA36:AD36) | AF36: =IFERROR(AF9,"") | AG36: =IFERROR(AG9,"") | AH36: =IFERROR(AH9,"") | AI36: =IFERROR(AI9,"") | AJ36: =SUM(AF36:AI36) | AK36: =IFERROR(AK9,"") | AL36: =IFERROR(AL9,"") | AM36: =IFERROR(AM9,"") | AN36: =IFERROR(AN9,"") | AO36: =SUM(AK36:AN36)
B37: 비율(참고)
A38: NPM | C38: % | D38: 지배주주순이익 / 매출액 | E38: =IFERROR(E18/E5,"") | F38: =IFERROR(F18/F5,"") | G38: =IFERROR(G18/G5,"") | H38: =IFERROR(H18/H5,"") | I38: =IFERROR(I18/I5,"") | J38: =IFERROR(J18/J5,"") | K38: =IFERROR(K18/K5,"") | L38: =IFERROR(L18/L5,"") | ... AO38: =IFERROR(AO18/AO5,"")
A39: 매출원가율 | C39: % | D39: 매출원가 / 매출액 | E39: =IFERROR(E6/E5,"") | F39: =IFERROR(F6/F5,"") | G39: =IFERROR(G6/G5,"") | H39: =IFERROR(H6/H5,"") | I39: =IFERROR(I6/I5,"") | J39: =IFERROR(J6/J5,"") | K39: =IFERROR(K6/K5,"") | L39: =IFERROR(L6/L5,"") | ... AO39: =IFERROR(AO6/AO5,"")
A40: 판관비율 | C40: % | D40: 판관비 / 매출액 | E40: =IFERROR(E8/E5,"") | F40: =IFERROR(F8/F5,"") | G40: =IFERROR(G8/G5,"") | H40: =IFERROR(H8/H5,"") | I40: =IFERROR(I8/I5,"") | J40: =IFERROR(J8/J5,"") | K40: =IFERROR(K8/K5,"") | L40: =IFERROR(L8/L5,"") | ... AO40: =IFERROR(AO8/AO5,"")

Sheet 분기
C1: 이름: 분기H — subQ 를 이름으로 VLOOKUP(억원) | E1: 4Q21 | F1: 1Q22 | G1: 2Q22 | H1: 3Q22 | I1: 4Q22 | J1: 1Q23 | K1: 2Q23 | L1: 3Q23 | M1: 4Q23 | N1: 1Q24 | O1: 2Q24 | P1: 3Q24 | Q1: 4Q24 | R1: 1Q25 | S1: 2Q25 | T1: 3Q25 | U1: 4Q25 | V1: 1Q26 | W1: 2Q26 | X1: 3Q26 | Y1: 4Q26 | Z1: 1Q27 | AA1: 2Q27 | AB1: 3Q27 | AC1: 4Q27 | AD1: 1Q28 | AE1: 2Q28 | AF1: 3Q28 | AG1: 4Q28
C2: 종가: | D2: =변수!D41
C3: 기준일: | D3: 20261026 | E3: 1 | F3: 2 | G3: 3 | H3: 4 | I3: 5 | J3: 6 | K3: 7 | L3: 8 | M3: 9 | N3: 10 | O3: 11 | P3: 12 | Q3: 13 | R3: 14 | S3: 15 | T3: 16 | U3: 17 | V3: 18 | W3: 19 | X3: 20 | Y3: 21 | Z3: 22 | AA3: 23 | AB3: 24 | AC3: 25 | AD3: 26 | AE3: 27 | AF3: 28 | AG3: 29
E4: 2021.12 | F4: 2022.03 | G4: 2022.06 | H4: 2022.09 | I4: 2022.12 | J4: 2023.03 | K4: 2023.06 | L4: 2023.09 | M4: 2023.12 | N4: 2024.03 | O4: 2024.06 | P4: 2024.09 | Q4: 2024.12 | R4: 2025.03 | S4: 2025.06 | T4: 2025.09 | U4: 2025.12 | V4: 2026.03 | W4: 2026.06 | X4: 2026.09 | Y4: 2026.12 | Z4: 2027.03 | AA4: 2027.06 | AB4: 2027.09 | AC4: 2027.12 | AD4: 2028.03 | AE4: 2028.06 | AF4: 2028.09 | AG4: 2028.12
A5: 매출액 | D5: 매출액 | E5: =IFERROR(VLOOKUP($A5,subQ,MATCH(E$1,SUBQH,0),0),"") | F5: =IFERROR(VLOOKUP($A5,subQ,MATCH(F$1,SUBQH,0),0),"") | G5: =IFERROR(VLOOKUP($A5,subQ,MATCH(G$1,SUBQH,0),0),"") | H5: =IFERROR(VLOOKUP($A5,subQ,MATCH(H$1,SUBQH,0),0),"") | I5: =IFERROR(VLOOKUP($A5,subQ,MATCH(I$1,SUBQH,0),0),"") | J5: =IFERROR(VLOOKUP($A5,subQ,MATCH(J$1,SUBQH,0),0),"") | K5: =IFERROR(VLOOKUP($A5,subQ,MATCH(K$1,SUBQH,0),0),"") | L5: =IFERROR(VLOOKUP($A5,subQ,MATCH(L$1,SUBQH,0),0),"") | ... AG5: =IFERROR(VLOOKUP($A5,subQ,MATCH(AG$1,SUBQH,0),0),"")
A6: 매출원가 | D6: 매출원가 | E6: =IFERROR(VLOOKUP($A6,subQ,MATCH(E$1,SUBQH,0),0),"") | F6: =IFERROR(VLOOKUP($A6,subQ,MATCH(F$1,SUBQH,0),0),"") | G6: =IFERROR(VLOOKUP($A6,subQ,MATCH(G$1,SUBQH,0),0),"") | H6: =IFERROR(VLOOKUP($A6,subQ,MATCH(H$1,SUBQH,0),0),"") | I6: =IFERROR(VLOOKUP($A6,subQ,MATCH(I$1,SUBQH,0),0),"") | J6: =IFERROR(VLOOKUP($A6,subQ,MATCH(J$1,SUBQH,0),0),"") | K6: =IFERROR(VLOOKUP($A6,subQ,MATCH(K$1,SUBQH,0),0),"") | L6: =IFERROR(VLOOKUP($A6,subQ,MATCH(L$1,SUBQH,0),0),"") | ... AG6: =IFERROR(VLOOKUP($A6,subQ,MATCH(AG$1,SUBQH,0),0),"")
A7: 매출총이익 | D7: 매출총이익 | E7: =IFERROR(VLOOKUP($A7,subQ,MATCH(E$1,SUBQH,0),0),"") | F7: =IFERROR(VLOOKUP($A7,subQ,MATCH(F$1,SUBQH,0),0),"") | G7: =IFERROR(VLOOKUP($A7,subQ,MATCH(G$1,SUBQH,0),0),"") | H7: =IFERROR(VLOOKUP($A7,subQ,MATCH(H$1,SUBQH,0),0),"") | I7: =IFERROR(VLOOKUP($A7,subQ,MATCH(I$1,SUBQH,0),0),"") | J7: =IFERROR(VLOOKUP($A7,subQ,MATCH(J$1,SUBQH,0),0),"") | K7: =IFERROR(VLOOKUP($A7,subQ,MATCH(K$1,SUBQH,0),0),"") | L7: =IFERROR(VLOOKUP($A7,subQ,MATCH(L$1,SUBQH,0),0),"") | ... AG7: =IFERROR(VLOOKUP($A7,subQ,MATCH(AG$1,SUBQH,0),0),"")
A8: 판관비 | D8: 판매비와관리비 | E8: =IFERROR(VLOOKUP($A8,subQ,MATCH(E$1,SUBQH,0),0),"") | F8: =IFERROR(VLOOKUP($A8,subQ,MATCH(F$1,SUBQH,0),0),"") | G8: =IFERROR(VLOOKUP($A8,subQ,MATCH(G$1,SUBQH,0),0),"") | H8: =IFERROR(VLOOKUP($A8,subQ,MATCH(H$1,SUBQH,0),0),"") | I8: =IFERROR(VLOOKUP($A8,subQ,MATCH(I$1,SUBQH,0),0),"") | J8: =IFERROR(VLOOKUP($A8,subQ,MATCH(J$1,SUBQH,0),0),"") | K8: =IFERROR(VLOOKUP($A8,subQ,MATCH(K$1,SUBQH,0),0),"") | L8: =IFERROR(VLOOKUP($A8,subQ,MATCH(L$1,SUBQH,0),0),"") | ... AG8: =IFERROR(VLOOKUP($A8,subQ,MATCH(AG$1,SUBQH,0),0),"")
A9: 영업이익 | D9: 영업이익 | E9: =IFERROR(VLOOKUP($A9,subQ,MATCH(E$1,SUBQH,0),0),"") | F9: =IFERROR(VLOOKUP($A9,subQ,MATCH(F$1,SUBQH,0),0),"") | G9: =IFERROR(VLOOKUP($A9,subQ,MATCH(G$1,SUBQH,0),0),"") | H9: =IFERROR(VLOOKUP($A9,subQ,MATCH(H$1,SUBQH,0),0),"") | I9: =IFERROR(VLOOKUP($A9,subQ,MATCH(I$1,SUBQH,0),0),"") | J9: =IFERROR(VLOOKUP($A9,subQ,MATCH(J$1,SUBQH,0),0),"") | K9: =IFERROR(VLOOKUP($A9,subQ,MATCH(K$1,SUBQH,0),0),"") | L9: =IFERROR(VLOOKUP($A9,subQ,MATCH(L$1,SUBQH,0),0),"") | ... AG9: =IFERROR(VLOOKUP($A9,subQ,MATCH(AG$1,SUBQH,0),0),"")
A10: OPM | D10: 영업이익률 | E10: =IFERROR(VLOOKUP($A10,subQ,MATCH(E$1,SUBQH,0),0),"") | F10: =IFERROR(VLOOKUP($A10,subQ,MATCH(F$1,SUBQH,0),0),"") | G10: =IFERROR(VLOOKUP($A10,subQ,MATCH(G$1,SUBQH,0),0),"") | H10: =IFERROR(VLOOKUP($A10,subQ,MATCH(H$1,SUBQH,0),0),"") | I10: =IFERROR(VLOOKUP($A10,subQ,MATCH(I$1,SUBQH,0),0),"") | J10: =IFERROR(VLOOKUP($A10,subQ,MATCH(J$1,SUBQH,0),0),"") | K10: =IFERROR(VLOOKUP($A10,subQ,MATCH(K$1,SUBQH,0),0),"") | L10: =IFERROR(VLOOKUP($A10,subQ,MATCH(L$1,SUBQH,0),0),"") | ... AG10: =IFERROR(VLOOKUP($A10,subQ,MATCH(AG$1,SUBQH,0),0),"")
A11: 금융손익 | D11: 금융손익(이자·환 포함) | E11: =IFERROR(VLOOKUP($A11,subQ,MATCH(E$1,SUBQH,0),0),"") | F11: =IFERROR(VLOOKUP($A11,subQ,MATCH(F$1,SUBQH,0),0),"") | G11: =IFERROR(VLOOKUP($A11,subQ,MATCH(G$1,SUBQH,0),0),"") | H11: =IFERROR(VLOOKUP($A11,subQ,MATCH(H$1,SUBQH,0),0),"") | I11: =IFERROR(VLOOKUP($A11,subQ,MATCH(I$1,SUBQH,0),0),"") | J11: =IFERROR(VLOOKUP($A11,subQ,MATCH(J$1,SUBQH,0),0),"") | K11: =IFERROR(VLOOKUP($A11,subQ,MATCH(K$1,SUBQH,0),0),"") | L11: =IFERROR(VLOOKUP($A11,subQ,MATCH(L$1,SUBQH,0),0),"") | ... AG11: =IFERROR(VLOOKUP($A11,subQ,MATCH(AG$1,SUBQH,0),0),"")
A12: 이자손익 | D12: 이자손익(이자수익 − 이자비용) | E12: =IFERROR(VLOOKUP($A12,subQ,MATCH(E$1,SUBQH,0),0),"") | F12: =IFERROR(VLOOKUP($A12,subQ,MATCH(F$1,SUBQH,0),0),"") | G12: =IFERROR(VLOOKUP($A12,subQ,MATCH(G$1,SUBQH,0),0),"") | H12: =IFERROR(VLOOKUP($A12,subQ,MATCH(H$1,SUBQH,0),0),"") | I12: =IFERROR(VLOOKUP($A12,subQ,MATCH(I$1,SUBQH,0),0),"") | J12: =IFERROR(VLOOKUP($A12,subQ,MATCH(J$1,SUBQH,0),0),"") | K12: =IFERROR(VLOOKUP($A12,subQ,MATCH(K$1,SUBQH,0),0),"") | L12: =IFERROR(VLOOKUP($A12,subQ,MATCH(L$1,SUBQH,0),0),"") | ... AG12: =IFERROR(VLOOKUP($A12,subQ,MATCH(AG$1,SUBQH,0),0),"")
A13: 기타영업외손익 | D13: 기타영업외손익 | E13: =IFERROR(VLOOKUP($A13,subQ,MATCH(E$1,SUBQH,0),0),"") | F13: =IFERROR(VLOOKUP($A13,subQ,MATCH(F$1,SUBQH,0),0),"") | G13: =IFERROR(VLOOKUP($A13,subQ,MATCH(G$1,SUBQH,0),0),"") | H13: =IFERROR(VLOOKUP($A13,subQ,MATCH(H$1,SUBQH,0),0),"") | I13: =IFERROR(VLOOKUP($A13,subQ,MATCH(I$1,SUBQH,0),0),"") | J13: =IFERROR(VLOOKUP($A13,subQ,MATCH(J$1,SUBQH,0),0),"") | K13: =IFERROR(VLOOKUP($A13,subQ,MATCH(K$1,SUBQH,0),0),"") | L13: =IFERROR(VLOOKUP($A13,subQ,MATCH(L$1,SUBQH,0),0),"") | ... AG13: =IFERROR(VLOOKUP($A13,subQ,MATCH(AG$1,SUBQH,0),0),"")
A14: 지분법손익 | D14: 지분법손익 | E14: =IFERROR(VLOOKUP($A14,subQ,MATCH(E$1,SUBQH,0),0),"") | F14: =IFERROR(VLOOKUP($A14,subQ,MATCH(F$1,SUBQH,0),0),"") | G14: =IFERROR(VLOOKUP($A14,subQ,MATCH(G$1,SUBQH,0),0),"") | H14: =IFERROR(VLOOKUP($A14,subQ,MATCH(H$1,SUBQH,0),0),"") | I14: =IFERROR(VLOOKUP($A14,subQ,MATCH(I$1,SUBQH,0),0),"") | J14: =IFERROR(VLOOKUP($A14,subQ,MATCH(J$1,SUBQH,0),0),"") | K14: =IFERROR(VLOOKUP($A14,subQ,MATCH(K$1,SUBQH,0),0),"") | L14: =IFERROR(VLOOKUP($A14,subQ,MATCH(L$1,SUBQH,0),0),"") | ... AG14: =IFERROR(VLOOKUP($A14,subQ,MATCH(AG$1,SUBQH,0),0),"")
A15: 세전이익 | D15: 법인세비용차감전이익 | E15: =IFERROR(VLOOKUP($A15,subQ,MATCH(E$1,SUBQH,0),0),"") | F15: =IFERROR(VLOOKUP($A15,subQ,MATCH(F$1,SUBQH,0),0),"") | G15: =IFERROR(VLOOKUP($A15,subQ,MATCH(G$1,SUBQH,0),0),"") | H15: =IFERROR(VLOOKUP($A15,subQ,MATCH(H$1,SUBQH,0),0),"") | I15: =IFERROR(VLOOKUP($A15,subQ,MATCH(I$1,SUBQH,0),0),"") | J15: =IFERROR(VLOOKUP($A15,subQ,MATCH(J$1,SUBQH,0),0),"") | K15: =IFERROR(VLOOKUP($A15,subQ,MATCH(K$1,SUBQH,0),0),"") | L15: =IFERROR(VLOOKUP($A15,subQ,MATCH(L$1,SUBQH,0),0),"") | ... AG15: =IFERROR(VLOOKUP($A15,subQ,MATCH(AG$1,SUBQH,0),0),"")
A16: 법인세비용 | D16: 법인세비용 | E16: =IFERROR(VLOOKUP($A16,subQ,MATCH(E$1,SUBQH,0),0),"") | F16: =IFERROR(VLOOKUP($A16,subQ,MATCH(F$1,SUBQH,0),0),"") | G16: =IFERROR(VLOOKUP($A16,subQ,MATCH(G$1,SUBQH,0),0),"") | H16: =IFERROR(VLOOKUP($A16,subQ,MATCH(H$1,SUBQH,0),0),"") | I16: =IFERROR(VLOOKUP($A16,subQ,MATCH(I$1,SUBQH,0),0),"") | J16: =IFERROR(VLOOKUP($A16,subQ,MATCH(J$1,SUBQH,0),0),"") | K16: =IFERROR(VLOOKUP($A16,subQ,MATCH(K$1,SUBQH,0),0),"") | L16: =IFERROR(VLOOKUP($A16,subQ,MATCH(L$1,SUBQH,0),0),"") | ... AG16: =IFERROR(VLOOKUP($A16,subQ,MATCH(AG$1,SUBQH,0),0),"")
... A37: NPM | D37: NPM | E37: =IFERROR(VLOOKUP($A37,subQ,MATCH(E$1,SUBQH,0),0),"") | F37: =IFERROR(VLOOKUP($A37,subQ,MATCH(F$1,SUBQH,0),0),"") | G37: =IFERROR(VLOOKUP($A37,subQ,MATCH(G$1,SUBQH,0),0),"") | H37: =IFERROR(VLOOKUP($A37,subQ,MATCH(H$1,SUBQH,0),0),"") | I37: =IFERROR(VLOOKUP($A37,subQ,MATCH(I$1,SUBQH,0),0),"") | J37: =IFERROR(VLOOKUP($A37,subQ,MATCH(J$1,SUBQH,0),0),"") | K37: =IFERROR(VLOOKUP($A37,subQ,MATCH(K$1,SUBQH,0),0),"") | L37: =IFERROR(VLOOKUP($A37,subQ,MATCH(L$1,SUBQH,0),0),"") | ... AG37: =IFERROR(VLOOKUP($A37,subQ,MATCH(AG$1,SUBQH,0),0),"")
A38: 매출액 YoY | D38: 매출액 YoY | I38: =IFERROR(I5/E5-1,"") | J38: =IFERROR(J5/F5-1,"") | K38: =IFERROR(K5/G5-1,"") | L38: =IFERROR(L5/H5-1,"") | M38: =IFERROR(M5/I5-1,"") | N38: =IFERROR(N5/J5-1,"") | O38: =IFERROR(O5/K5-1,"") | P38: =IFERROR(P5/L5-1,"") | ... AG38: =IFERROR(AG5/AC5-1,"")
A39: 영업이익 YoY | D39: 영업이익 YoY | I39: =IFERROR(I9/E9-1,"") | J39: =IFERROR(J9/F9-1,"") | K39: =IFERROR(K9/G9-1,"") | L39: =IFERROR(L9/H9-1,"") | M39: =IFERROR(M9/I9-1,"") | N39: =IFERROR(N9/J9-1,"") | O39: =IFERROR(O9/K9-1,"") | P39: =IFERROR(P9/L9-1,"") | ... AG39: =IFERROR(AG9/AC9-1,"")
A40: 지배주주순이익 YoY | D40: 지배주주순이익 YoY | I40: =IFERROR(I18/E18-1,"") | J40: =IFERROR(J18/F18-1,"") | K40: =IFERROR(K18/G18-1,"") | L40: =IFERROR(L18/H18-1,"") | M40: =IFERROR(M18/I18-1,"") | N40: =IFERROR(N18/J18-1,"") | O40: =IFERROR(O18/K18-1,"") | P40: =IFERROR(P18/L18-1,"") | ... AG40: =IFERROR(AG18/AC18-1,"")

Sheet 연간예상
C1: 이름: 연간예상H — subQ 를 이름으로 VLOOKUP(억원) | E1: 2021 | F1: 2022 | G1: 2023 | H1: 2024 | I1: 2025 | J1: 2026 | K1: 2027 | L1: 2028
C2: 종가: | D2: =변수!D41
C3: 기준일: | D3: 20261026 | E3: 1 | F3: 2 | G3: 3 | H3: 4 | I3: 5 | J3: 6 | K3: 7 | L3: 8
E4: 2021.12A | F4: 2022.12A | G4: 2023.12A | H4: 2024.12A | I4: 2025.12A | J4: 2026.12A | K4: 2027.12A | L4: 2028.12A
A5: 매출액 | D5: 매출액 | E5: =IFERROR(VLOOKUP($A5,subQ,MATCH(E$1,SUBQH,0),0),"") | F5: =IFERROR(VLOOKUP($A5,subQ,MATCH(F$1,SUBQH,0),0),"") | G5: =IFERROR(VLOOKUP($A5,subQ,MATCH(G$1,SUBQH,0),0),"") | H5: =IFERROR(VLOOKUP($A5,subQ,MATCH(H$1,SUBQH,0),0),"") | I5: =IFERROR(VLOOKUP($A5,subQ,MATCH(I$1,SUBQH,0),0),"") | J5: =IFERROR(VLOOKUP($A5,subQ,MATCH(J$1,SUBQH,0),0),"") | K5: =IFERROR(VLOOKUP($A5,subQ,MATCH(K$1,SUBQH,0),0),"") | L5: =IFERROR(VLOOKUP($A5,subQ,MATCH(L$1,SUBQH,0),0),"")
A6: 매출원가 | D6: 매출원가 | E6: =IFERROR(VLOOKUP($A6,subQ,MATCH(E$1,SUBQH,0),0),"") | F6: =IFERROR(VLOOKUP($A6,subQ,MATCH(F$1,SUBQH,0),0),"") | G6: =IFERROR(VLOOKUP($A6,subQ,MATCH(G$1,SUBQH,0),0),"") | H6: =IFERROR(VLOOKUP($A6,subQ,MATCH(H$1,SUBQH,0),0),"") | I6: =IFERROR(VLOOKUP($A6,subQ,MATCH(I$1,SUBQH,0),0),"") | J6: =IFERROR(VLOOKUP($A6,subQ,MATCH(J$1,SUBQH,0),0),"") | K6: =IFERROR(VLOOKUP($A6,subQ,MATCH(K$1,SUBQH,0),0),"") | L6: =IFERROR(VLOOKUP($A6,subQ,MATCH(L$1,SUBQH,0),0),"")
A7: 매출총이익 | D7: 매출총이익 | E7: =IFERROR(VLOOKUP($A7,subQ,MATCH(E$1,SUBQH,0),0),"") | F7: =IFERROR(VLOOKUP($A7,subQ,MATCH(F$1,SUBQH,0),0),"") | G7: =IFERROR(VLOOKUP($A7,subQ,MATCH(G$1,SUBQH,0),0),"") | H7: =IFERROR(VLOOKUP($A7,subQ,MATCH(H$1,SUBQH,0),0),"") | I7: =IFERROR(VLOOKUP($A7,subQ,MATCH(I$1,SUBQH,0),0),"") | J7: =IFERROR(VLOOKUP($A7,subQ,MATCH(J$1,SUBQH,0),0),"") | K7: =IFERROR(VLOOKUP($A7,subQ,MATCH(K$1,SUBQH,0),0),"") | L7: =IFERROR(VLOOKUP($A7,subQ,MATCH(L$1,SUBQH,0),0),"")
A8: 판관비 | D8: 판매비와관리비 | E8: =IFERROR(VLOOKUP($A8,subQ,MATCH(E$1,SUBQH,0),0),"") | F8: =IFERROR(VLOOKUP($A8,subQ,MATCH(F$1,SUBQH,0),0),"") | G8: =IFERROR(VLOOKUP($A8,subQ,MATCH(G$1,SUBQH,0),0),"") | H8: =IFERROR(VLOOKUP($A8,subQ,MATCH(H$1,SUBQH,0),0),"") | I8: =IFERROR(VLOOKUP($A8,subQ,MATCH(I$1,SUBQH,0),0),"") | J8: =IFERROR(VLOOKUP($A8,subQ,MATCH(J$1,SUBQH,0),0),"") | K8: =IFERROR(VLOOKUP($A8,subQ,MATCH(K$1,SUBQH,0),0),"") | L8: =IFERROR(VLOOKUP($A8,subQ,MATCH(L$1,SUBQH,0),0),"")
A9: 영업이익 | D9: 영업이익 | E9: =IFERROR(VLOOKUP($A9,subQ,MATCH(E$1,SUBQH,0),0),"") | F9: =IFERROR(VLOOKUP($A9,subQ,MATCH(F$1,SUBQH,0),0),"") | G9: =IFERROR(VLOOKUP($A9,subQ,MATCH(G$1,SUBQH,0),0),"") | H9: =IFERROR(VLOOKUP($A9,subQ,MATCH(H$1,SUBQH,0),0),"") | I9: =IFERROR(VLOOKUP($A9,subQ,MATCH(I$1,SUBQH,0),0),"") | J9: =IFERROR(VLOOKUP($A9,subQ,MATCH(J$1,SUBQH,0),0),"") | K9: =IFERROR(VLOOKUP($A9,subQ,MATCH(K$1,SUBQH,0),0),"") | L9: =IFERROR(VLOOKUP($A9,subQ,MATCH(L$1,SUBQH,0),0),"")
A10: OPM | D10: 영업이익률 | E10: =IFERROR(VLOOKUP($A10,subQ,MATCH(E$1,SUBQH,0),0),"") | F10: =IFERROR(VLOOKUP($A10,subQ,MATCH(F$1,SUBQH,0),0),"") | G10: =IFERROR(VLOOKUP($A10,subQ,MATCH(G$1,SUBQH,0),0),"") | H10: =IFERROR(VLOOKUP($A10,subQ,MATCH(H$1,SUBQH,0),0),"") | I10: =IFERROR(VLOOKUP($A10,subQ,MATCH(I$1,SUBQH,0),0),"") | J10: =IFERROR(VLOOKUP($A10,subQ,MATCH(J$1,SUBQH,0),0),"") | K10: =IFERROR(VLOOKUP($A10,subQ,MATCH(K$1,SUBQH,0),0),"") | L10: =IFERROR(VLOOKUP($A10,subQ,MATCH(L$1,SUBQH,0),0),"")
A11: 금융손익 | D11: 금융손익(이자·환 포함) | E11: =IFERROR(VLOOKUP($A11,subQ,MATCH(E$1,SUBQH,0),0),"") | F11: =IFERROR(VLOOKUP($A11,subQ,MATCH(F$1,SUBQH,0),0),"") | G11: =IFERROR(VLOOKUP($A11,subQ,MATCH(G$1,SUBQH,0),0),"") | H11: =IFERROR(VLOOKUP($A11,subQ,MATCH(H$1,SUBQH,0),0),"") | I11: =IFERROR(VLOOKUP($A11,subQ,MATCH(I$1,SUBQH,0),0),"") | J11: =IFERROR(VLOOKUP($A11,subQ,MATCH(J$1,SUBQH,0),0),"") | K11: =IFERROR(VLOOKUP($A11,subQ,MATCH(K$1,SUBQH,0),0),"") | L11: =IFERROR(VLOOKUP($A11,subQ,MATCH(L$1,SUBQH,0),0),"")
A12: 이자손익 | D12: 이자손익(이자수익 − 이자비용) | E12: =IFERROR(VLOOKUP($A12,subQ,MATCH(E$1,SUBQH,0),0),"") | F12: =IFERROR(VLOOKUP($A12,subQ,MATCH(F$1,SUBQH,0),0),"") | G12: =IFERROR(VLOOKUP($A12,subQ,MATCH(G$1,SUBQH,0),0),"") | H12: =IFERROR(VLOOKUP($A12,subQ,MATCH(H$1,SUBQH,0),0),"") | I12: =IFERROR(VLOOKUP($A12,subQ,MATCH(I$1,SUBQH,0),0),"") | J12: =IFERROR(VLOOKUP($A12,subQ,MATCH(J$1,SUBQH,0),0),"") | K12: =IFERROR(VLOOKUP($A12,subQ,MATCH(K$1,SUBQH,0),0),"") | L12: =IFERROR(VLOOKUP($A12,subQ,MATCH(L$1,SUBQH,0),0),"")
A13: 기타영업외손익 | D13: 기타영업외손익 | E13: =IFERROR(VLOOKUP($A13,subQ,MATCH(E$1,SUBQH,0),0),"") | F13: =IFERROR(VLOOKUP($A13,subQ,MATCH(F$1,SUBQH,0),0),"") | G13: =IFERROR(VLOOKUP($A13,subQ,MATCH(G$1,SUBQH,0),0),"") | H13: =IFERROR(VLOOKUP($A13,subQ,MATCH(H$1,SUBQH,0),0),"") | I13: =IFERROR(VLOOKUP($A13,subQ,MATCH(I$1,SUBQH,0),0),"") | J13: =IFERROR(VLOOKUP($A13,subQ,MATCH(J$1,SUBQH,0),0),"") | K13: =IFERROR(VLOOKUP($A13,subQ,MATCH(K$1,SUBQH,0),0),"") | L13: =IFERROR(VLOOKUP($A13,subQ,MATCH(L$1,SUBQH,0),0),"")
A14: 지분법손익 | D14: 지분법손익 | E14: =IFERROR(VLOOKUP($A14,subQ,MATCH(E$1,SUBQH,0),0),"") | F14: =IFERROR(VLOOKUP($A14,subQ,MATCH(F$1,SUBQH,0),0),"") | G14: =IFERROR(VLOOKUP($A14,subQ,MATCH(G$1,SUBQH,0),0),"") | H14: =IFERROR(VLOOKUP($A14,subQ,MATCH(H$1,SUBQH,0),0),"") | I14: =IFERROR(VLOOKUP($A14,subQ,MATCH(I$1,SUBQH,0),0),"") | J14: =IFERROR(VLOOKUP($A14,subQ,MATCH(J$1,SUBQH,0),0),"") | K14: =IFERROR(VLOOKUP($A14,subQ,MATCH(K$1,SUBQH,0),0),"") | L14: =IFERROR(VLOOKUP($A14,subQ,MATCH(L$1,SUBQH,0),0),"")
A15: 세전이익 | D15: 법인세비용차감전이익 | E15: =IFERROR(VLOOKUP($A15,subQ,MATCH(E$1,SUBQH,0),0),"") | F15: =IFERROR(VLOOKUP($A15,subQ,MATCH(F$1,SUBQH,0),0),"") | G15: =IFERROR(VLOOKUP($A15,subQ,MATCH(G$1,SUBQH,0),0),"") | H15: =IFERROR(VLOOKUP($A15,subQ,MATCH(H$1,SUBQH,0),0),"") | I15: =IFERROR(VLOOKUP($A15,subQ,MATCH(I$1,SUBQH,0),0),"") | J15: =IFERROR(VLOOKUP($A15,subQ,MATCH(J$1,SUBQH,0),0),"") | K15: =IFERROR(VLOOKUP($A15,subQ,MATCH(K$1,SUBQH,0),0),"") | L15: =IFERROR(VLOOKUP($A15,subQ,MATCH(L$1,SUBQH,0),0),"")
A16: 법인세비용 | D16: 법인세비용 | E16: =IFERROR(VLOOKUP($A16,subQ,MATCH(E$1,SUBQH,0),0),"") | F16: =IFERROR(VLOOKUP($A16,subQ,MATCH(F$1,SUBQH,0),0),"") | G16: =IFERROR(VLOOKUP($A16,subQ,MATCH(G$1,SUBQH,0),0),"") | H16: =IFERROR(VLOOKUP($A16,subQ,MATCH(H$1,SUBQH,0),0),"") | I16: =IFERROR(VLOOKUP($A16,subQ,MATCH(I$1,SUBQH,0),0),"") | J16: =IFERROR(VLOOKUP($A16,subQ,MATCH(J$1,SUBQH,0),0),"") | K16: =IFERROR(VLOOKUP($A16,subQ,MATCH(K$1,SUBQH,0),0),"") | L16: =IFERROR(VLOOKUP($A16,subQ,MATCH(L$1,SUBQH,0),0),"")
... A37: NPM | D37: NPM | E37: =IFERROR(VLOOKUP($A37,subQ,MATCH(E$1,SUBQH,0),0),"") | F37: =IFERROR(VLOOKUP($A37,subQ,MATCH(F$1,SUBQH,0),0),"") | G37: =IFERROR(VLOOKUP($A37,subQ,MATCH(G$1,SUBQH,0),0),"") | H37: =IFERROR(VLOOKUP($A37,subQ,MATCH(H$1,SUBQH,0),0),"") | I37: =IFERROR(VLOOKUP($A37,subQ,MATCH(I$1,SUBQH,0),0),"") | J37: =IFERROR(VLOOKUP($A37,subQ,MATCH(J$1,SUBQH,0),0),"") | K37: =IFERROR(VLOOKUP($A37,subQ,MATCH(K$1,SUBQH,0),0),"") | L37: =IFERROR(VLOOKUP($A37,subQ,MATCH(L$1,SUBQH,0),0),"")
A38: 매출액 YoY | D38: 매출액 YoY | F38: =IFERROR(F5/E5-1,"") | G38: =IFERROR(G5/F5-1,"") | H38: =IFERROR(H5/G5-1,"") | I38: =IFERROR(I5/H5-1,"") | J38: =IFERROR(J5/I5-1,"") | K38: =IFERROR(K5/J5-1,"") | L38: =IFERROR(L5/K5-1,"")
A39: 영업이익 YoY | D39: 영업이익 YoY | F39: =IFERROR(F9/E9-1,"") | G39: =IFERROR(G9/F9-1,"") | H39: =IFERROR(H9/G9-1,"") | I39: =IFERROR(I9/H9-1,"") | J39: =IFERROR(J9/I9-1,"") | K39: =IFERROR(K9/J9-1,"") | L39: =IFERROR(L9/K9-1,"")
A40: 지배주주순이익 YoY | D40: 지배주주순이익 YoY | F40: =IFERROR(F18/E18-1,"") | G40: =IFERROR(G18/F18-1,"") | H40: =IFERROR(H18/G18-1,"") | I40: =IFERROR(I18/H18-1,"") | J40: =IFERROR(J18/I18-1,"") | K40: =IFERROR(K18/J18-1,"") | L40: =IFERROR(L18/K18-1,"")

Sheet TP
B1: 종가 | C1: =변수!D41
B2: 기준일 | C2: =변수!D42
B3: 모델 산출값 — 목표주가·추천 아님. 밴드·COE 는 변수 시트 3절의 가정
C5: FY | D5: 2025 | E5: 2026 | F5: 2027 | G5: 2028
D6: A | E6: E | F6: E | G6: E
C7: EPS(원) | D7: =IFERROR(VLOOKUP("EPS",subQ,MATCH(D$5,SUBQH,0),0),"") | E7: =IFERROR(VLOOKUP("EPS",subQ,MATCH(E$5,SUBQH,0),0),"") | F7: =IFERROR(VLOOKUP("EPS",subQ,MATCH(F$5,SUBQH,0),0),"") | G7: =IFERROR(VLOOKUP("EPS",subQ,MATCH(G$5,SUBQH,0),0),"")
C8: BPS(원) | D8: =IFERROR(VLOOKUP("BPS",subQ,MATCH(D$5,SUBQH,0),0),"") | E8: =IFERROR(VLOOKUP("BPS",subQ,MATCH(E$5,SUBQH,0),0),"") | F8: =IFERROR(VLOOKUP("BPS",subQ,MATCH(F$5,SUBQH,0),0),"") | G8: =IFERROR(VLOOKUP("BPS",subQ,MATCH(G$5,SUBQH,0),0),"")
C9: 지배주주순이익(억원) | D9: =IFERROR(VLOOKUP("지배주주순이익",subQ,MATCH(D$5,SUBQH,0),0),"") | E9: =IFERROR(VLOOKUP("지배주주순이익",subQ,MATCH(E$5,SUBQH,0),0),"") | F9: =IFERROR(VLOOKUP("지배주주순이익",subQ,MATCH(F$5,SUBQH,0),0),"") | G9: =IFERROR(VLOOKUP("지배주주순이익",subQ,MATCH(G$5,SUBQH,0),0),"")
C10: 영업이익(억원) | D10: =IFERROR(VLOOKUP("영업이익",subQ,MATCH(D$5,SUBQH,0),0),"") | E10: =IFERROR(VLOOKUP("영업이익",subQ,MATCH(E$5,SUBQH,0),0),"") | F10: =IFERROR(VLOOKUP("영업이익",subQ,MATCH(F$5,SUBQH,0),0),"") | G10: =IFERROR(VLOOKUP("영업이익",subQ,MATCH(G$5,SUBQH,0),0),"")
C11: ROE(EPS/기초BPS) | E11: =IFERROR(E7/D8,"") | F11: =IFERROR(F7/E8,"") | G11: =IFERROR(G7/F8,"")
B13: PER
C14: 12M fwd EPS | D14: =IFERROR(E7*변수!D47+F7*(1-변수!D47),"")
C15: 적정가치 @PER_lo | D15: =변수!D44 | E15: =IFERROR(ROUND($D$14*D15,-2),"") | F15: =IFERROR(E15/$C$1-1,"") | G15: 배 · 원 · 종가 대비
C16: 적정가치 @PER_mid | D16: =변수!D45 | E16: =IFERROR(ROUND($D$14*D16,-2),"") | F16: =IFERROR(E16/$C$1-1,"") | G16: 배 · 원 · 종가 대비
C17: 적정가치 @PER_hi | D17: =변수!D46 | E17: =IFERROR(ROUND($D$14*D17,-2),"") | F17: =IFERROR(E17/$C$1-1,"") | G17: 배 · 원 · 종가 대비
C18: 현재 PER(종가/12M fwd EPS) | D18: =IFERROR($C$1/$D$14,"")
B20: PBR
C21: 최근 BPS(마지막 실적 분기) | D21: =IFERROR(VLOOKUP("BPS",subQ,MATCH("2Q26",SUBQH,0),0),"")
C22: ROE fwd(12M fwd EPS / BPS) | D22: =IFERROR($D$14/$D$21,"")
C23: COE | D23: =변수!D43
C24: 적정 PBR = ROE/COE | D24: =IFERROR(D22/D23,"")
C25: 적정가치(PBR) = BPS × 적정PBR | D25: =IFERROR(ROUND(D21*D24,-2),"") | E25: =IFERROR(D25/$C$1-1,"")
C26: 현재 PBR(종가/BPS) | D26: =IFERROR($C$1/D21,"")
B28: 모델 json valuation(참고)
C29: eps_fwd12m | D29: 4.4
C30: bps_latest | D30: 5425.8
C31: per_now | D31: 670.45
C32: pbr_now | D32: 0.54
C33: roe_fwd | D33: 0.0008
C34: fair_pbr | D34: 0.01
C35: fair_value_pbr | D35: 100
C36: ev_ebitda
C37: note | D37: 모델 산출값 — 목표주가·추천 아님

Sheet 외화
C1: 이름: 외화QH — 환율 QoQ · 외화 순노출 × Δ기말환율 | E1: 4Q21 | F1: 1Q22 | G1: 2Q22 | H1: 3Q22 | I1: 4Q22 | J1: 1Q23 | K1: 2Q23 | L1: 3Q23 | M1: 4Q23 | N1: 1Q24 | O1: 2Q24 | P1: 3Q24 | Q1: 4Q24 | R1: 1Q25 | S1: 2Q25 | T1: 3Q25 | U1: 4Q25 | V1: 1Q26 | W1: 2Q26 | X1: 3Q26 | Y1: 4Q26 | Z1: 1Q27 | AA1: 2Q27 | AB1: 3Q27 | AC1: 4Q27 | AD1: 1Q28 | AE1: 2Q28 | AF1: 3Q28 | AG1: 4Q28
E3: 1 | F3: 2 | G3: 3 | H3: 4 | I3: 5 | J3: 6 | K3: 7 | L3: 8 | M3: 9 | N3: 10 | O3: 11 | P3: 12 | Q3: 13 | R3: 14 | S3: 15 | T3: 16 | U3: 17 | V3: 18 | W3: 19 | X3: 20 | Y3: 21 | Z3: 22 | AA3: 23 | AB3: 24 | AC3: 25 | AD3: 26 | AE3: 27 | AF3: 28 | AG3: 29
E4: 2021.12 | F4: 2022.03 | G4: 2022.06 | H4: 2022.09 | I4: 2022.12 | J4: 2023.03 | K4: 2023.06 | L4: 2023.09 | M4: 2023.12 | N4: 2024.03 | O4: 2024.06 | P4: 2024.09 | Q4: 2024.12 | R4: 2025.03 | S4: 2025.06 | T4: 2025.09 | U4: 2025.12 | V4: 2026.03 | W4: 2026.06 | X4: 2026.09 | Y4: 2026.12 | Z4: 2027.03 | AA4: 2027.06 | AB4: 2027.09 | AC4: 2027.12 | AD4: 2028.03 | AE4: 2028.06 | AF4: 2028.09 | AG4: 2028.12
D5: 원/달러(평균) | E5: =IFERROR(VLOOKUP($D5,환율,MATCH(E$1,변수H,0),0),"") | F5: =IFERROR(VLOOKUP($D5,환율,MATCH(F$1,변수H,0),0),"") | G5: =IFERROR(VLOOKUP($D5,환율,MATCH(G$1,변수H,0),0),"") | H5: =IFERROR(VLOOKUP($D5,환율,MATCH(H$1,변수H,0),0),"") | I5: =IFERROR(VLOOKUP($D5,환율,MATCH(I$1,변수H,0),0),"") | J5: =IFERROR(VLOOKUP($D5,환율,MATCH(J$1,변수H,0),0),"") | K5: =IFERROR(VLOOKUP($D5,환율,MATCH(K$1,변수H,0),0),"") | L5: =IFERROR(VLOOKUP($D5,환율,MATCH(L$1,변수H,0),0),"") | ... AG5: =IFERROR(VLOOKUP($D5,환율,MATCH(AG$1,변수H,0),0),"")
A6: 원/달러(평균) QoQ | F6: =IFERROR(F5/E5-1,"") | G6: =IFERROR(G5/F5-1,"") | H6: =IFERROR(H5/G5-1,"") | I6: =IFERROR(I5/H5-1,"") | J6: =IFERROR(J5/I5-1,"") | K6: =IFERROR(K5/J5-1,"") | L6: =IFERROR(L5/K5-1,"") | M6: =IFERROR(M5/L5-1,"") | ... AG6: =IFERROR(AG5/AF5-1,"")
D7: 원/달러(기말) | E7: =IFERROR(VLOOKUP($D7,환율,MATCH(E$1,변수H,0),0),"") | F7: =IFERROR(VLOOKUP($D7,환율,MATCH(F$1,변수H,0),0),"") | G7: =IFERROR(VLOOKUP($D7,환율,MATCH(G$1,변수H,0),0),"") | H7: =IFERROR(VLOOKUP($D7,환율,MATCH(H$1,변수H,0),0),"") | I7: =IFERROR(VLOOKUP($D7,환율,MATCH(I$1,변수H,0),0),"") | J7: =IFERROR(VLOOKUP($D7,환율,MATCH(J$1,변수H,0),0),"") | K7: =IFERROR(VLOOKUP($D7,환율,MATCH(K$1,변수H,0),0),"") | L7: =IFERROR(VLOOKUP($D7,환율,MATCH(L$1,변수H,0),0),"") | ... AG7: =IFERROR(VLOOKUP($D7,환율,MATCH(AG$1,변수H,0),0),"")
A8: 원/달러(기말) QoQ | F8: =IFERROR(F7/E7-1,"") | G8: =IFERROR(G7/F7-1,"") | H8: =IFERROR(H7/G7-1,"") | I8: =IFERROR(I7/H7-1,"") | J8: =IFERROR(J7/I7-1,"") | K8: =IFERROR(K7/J7-1,"") | L8: =IFERROR(L7/K7-1,"") | M8: =IFERROR(M7/L7-1,"") | ... AG8: =IFERROR(AG7/AF7-1,"")
D9: W/Euro(평균) | E9: =IFERROR(VLOOKUP($D9,환율,MATCH(E$1,변수H,0),0),"") | F9: =IFERROR(VLOOKUP($D9,환율,MATCH(F$1,변수H,0),0),"") | G9: =IFERROR(VLOOKUP($D9,환율,MATCH(G$1,변수H,0),0),"") | H9: =IFERROR(VLOOKUP($D9,환율,MATCH(H$1,변수H,0),0),"") | I9: =IFERROR(VLOOKUP($D9,환율,MATCH(I$1,변수H,0),0),"") | J9: =IFERROR(VLOOKUP($D9,환율,MATCH(J$1,변수H,0),0),"") | K9: =IFERROR(VLOOKUP($D9,환율,MATCH(K$1,변수H,0),0),"") | L9: =IFERROR(VLOOKUP($D9,환율,MATCH(L$1,변수H,0),0),"") | ... AG9: =IFERROR(VLOOKUP($D9,환율,MATCH(AG$1,변수H,0),0),"")
A10: W/Euro(평균) QoQ | F10: =IFERROR(F9/E9-1,"") | G10: =IFERROR(G9/F9-1,"") | H10: =IFERROR(H9/G9-1,"") | I10: =IFERROR(I9/H9-1,"") | J10: =IFERROR(J9/I9-1,"") | K10: =IFERROR(K9/J9-1,"") | L10: =IFERROR(L9/K9-1,"") | M10: =IFERROR(M9/L9-1,"") | ... AG10: =IFERROR(AG9/AF9-1,"")
D11: W/Euro(기말) | E11: =IFERROR(VLOOKUP($D11,환율,MATCH(E$1,변수H,0),0),"") | F11: =IFERROR(VLOOKUP($D11,환율,MATCH(F$1,변수H,0),0),"") | G11: =IFERROR(VLOOKUP($D11,환율,MATCH(G$1,변수H,0),0),"") | H11: =IFERROR(VLOOKUP($D11,환율,MATCH(H$1,변수H,0),0),"") | I11: =IFERROR(VLOOKUP($D11,환율,MATCH(I$1,변수H,0),0),"") | J11: =IFERROR(VLOOKUP($D11,환율,MATCH(J$1,변수H,0),0),"") | K11: =IFERROR(VLOOKUP($D11,환율,MATCH(K$1,변수H,0),0),"") | L11: =IFERROR(VLOOKUP($D11,환율,MATCH(L$1,변수H,0),0),"") | ... AG11: =IFERROR(VLOOKUP($D11,환율,MATCH(AG$1,변수H,0),0),"")
A12: W/Euro(기말) QoQ | F12: =IFERROR(F11/E11-1,"") | G12: =IFERROR(G11/F11-1,"") | H12: =IFERROR(H11/G11-1,"") | I12: =IFERROR(I11/H11-1,"") | J12: =IFERROR(J11/I11-1,"") | K12: =IFERROR(K11/J11-1,"") | L12: =IFERROR(L11/K11-1,"") | M12: =IFERROR(M11/L11-1,"") | ... AG12: =IFERROR(AG11/AF11-1,"")
D13: 원/100Y(기말) | E13: =IFERROR(VLOOKUP($D13,환율,MATCH(E$1,변수H,0),0),"") | F13: =IFERROR(VLOOKUP($D13,환율,MATCH(F$1,변수H,0),0),"") | G13: =IFERROR(VLOOKUP($D13,환율,MATCH(G$1,변수H,0),0),"") | H13: =IFERROR(VLOOKUP($D13,환율,MATCH(H$1,변수H,0),0),"") | I13: =IFERROR(VLOOKUP($D13,환율,MATCH(I$1,변수H,0),0),"") | J13: =IFERROR(VLOOKUP($D13,환율,MATCH(J$1,변수H,0),0),"") | K13: =IFERROR(VLOOKUP($D13,환율,MATCH(K$1,변수H,0),0),"") | L13: =IFERROR(VLOOKUP($D13,환율,MATCH(L$1,변수H,0),0),"") | ... AG13: =IFERROR(VLOOKUP($D13,환율,MATCH(AG$1,변수H,0),0),"")
A14: 원/100Y(기말) QoQ | F14: =IFERROR(F13/E13-1,"") | G14: =IFERROR(G13/F13-1,"") | H14: =IFERROR(H13/G13-1,"") | I14: =IFERROR(I13/H13-1,"") | J14: =IFERROR(J13/I13-1,"") | K14: =IFERROR(K13/J13-1,"") | L14: =IFERROR(L13/K13-1,"") | M14: =IFERROR(M13/L13-1,"") | ... AG14: =IFERROR(AG13/AF13-1,"")
A16: 외화순노출 | C16: 외화 순노출(백만$) | D16: =변수!D54 | E16: 외화 순노출 × Δ기말환율 (외화 시트 방식)
A17: 환관련손익추정 | C17: 환관련손익 추정(억원) = 순노출 × Δ원/달러(기말) / 100 | F17: =IFERROR($D$16*(F7-E7)/100,"") | G17: =IFERROR($D$16*(G7-F7)/100,"") | H17: =IFERROR($D$16*(H7-G7)/100,"") | I17: =IFERROR($D$16*(I7-H7)/100,"") | J17: =IFERROR($D$16*(J7-I7)/100,"") | K17: =IFERROR($D$16*(K7-J7)/100,"") | L17: =IFERROR($D$16*(L7-K7)/100,"") | M17: =IFERROR($D$16*(M7-L7)/100,"") | ... AG17: =IFERROR($D$16*(AG7-AF7)/100,"")
A18: fx_pnl.by_q | C18: 모델 fx_pnl.by_q(억원, 참고)
C19: 외화 순노출 미공시(face) → 0 + 표기
