Workbook
Name 변수H: 변수!$C$1:$AO$1
Name 환율: 변수!$C$6:$AO$13
Name BS연결H: BS연결!$C$1:$AO$1
Name BS연결: BS연결!$C$5:$AO$104
Name BS별도H: BS별도!$C$1:$AO$1
Name BS별도: BS별도!$C$5:$AO$91
Name SUBQH: subQ!$A$1:$AO$1
Name subQ: subQ!$A$5:$AO$45

Sheet README
A1: KS인더스트리(101000) 실적 모델 — ARGUS 한국조선
A2: 기준 분기 2026Q2 · 마지막 실적 2026Q2 · 생성 2026-10-11
A3: 모든 수치는 모델 산출값(DART 공개 재무제표 + 우리 추정)이다 — 목표주가·투자 추천 아님. 참고용 · 투자조언 아님.
A5: 시트
A6: 변수 가정 시계열. 환율 8행(ECB via frankfurter — L2 fx.json; 추정 분기 = 노란 가정), 추정 드라이버(노란 셀 = 모델값에서 역산한 가정, 바꾸면 재계산; 연녹 셀 = 3절 스칼라 참조 수식), 3절 스칼라 가정(세율·판관비율·지배주주비중·이자율·종가·PER 밴드·COE·외화 순노출·헤지비율)
A7: BS연결/BS별도 FnGuide 계정명 × 기간 값 덤프(백만원). 행1 분기라벨, 행4 YYYY.MM / YYYY.12A. 이름정의 BS연결H·BS연결(계정명 C열부터)
A8: subQ 분기 서브모델(억원 = 백만원/100). 확정 행: =IFERROR(VLOOKUP($D행,BS연결,MATCH(E$1,BS연결H,0),0)/100,"") 추정 행: 변수 시트 가정 셀 참조 수식. 외환손익·파생상품손익은 BS 계정 합·차, 기타금융손익은 잔차, OPM·EPS·BPS·PER·PBR 은 파생 수식, 조정EPS 는 EPS 참조(일회성 의심 분기만 산식 셀)
A9: SLS 선표(조선사만, sls json 있을 때): 요약 행(sls 저장값) + 계약별 스케줄(백만$) × (헤지비율 × 헤지환율 + (1−헤지비율) × 건조시점 환율[변수 원/달러(평균)]) → 원화 수식 블록 → 합계 행이 subQ 매출조선에 연결
A10: 시나리오 신규수주 보수/기준/낙관(forecast_panel 패널, 모델에 scenarios 가 있을 때만): 매출액·영업이익 = subQ 기준값 ± (시나리오 신규 − base 신규) × OPM. base 만 subQ 행에 포함, 나머지는 합산 안 함
A11: 분기/연간예상 subQ 를 이름(A열 key)으로 VLOOKUP 한 보고서 표(억원)
A12: TP PER 밴드 × 12M fwd EPS, PBR = ROE/COE × BPS — 모델 산출값 구간, 목표주가·추천 아님
A13: 외화 환율 QoQ, 외화 순노출 × Δ기말환율 → 환관련손익 추정
... A35: 백테스트: {"freeze": "2025Q2", "horizon": 4, "revenue_wape_pct": 38.4, "op_wape_pct": 77.8, "n": 4, "note": "단일 회사 4분기 — 통계 아님", "driver_at_freeze": "trend_seasonal", "selection_oos_at_freeze": {"wape_link": null, "wape_trend": null, "adopted": false, "decision": "rejected", "note": "유의성 조건 미달 → OOS 비교 전 기각"}, "frozen_inputs": "fin(연결/별도)·고객 조선사 모델·지주 자회사 모델은 2025Q2 까지의 분기만; 선표는 체결일 ≤ 2025Q2 말일 계약(원장 최신 금액·코호트 등급, 환산 없음); 잔고는 yards_cache 2025Q2; 시세·환율 forward·prices·forecast_panel 신규수주 미사용. 고객 가중치(suppliers.json 언급 비중)와 합병 체인링크는 현재 지식; 고객 연동 채택은 동결 모델 안에서도 자기 la−4분기 OOS 규칙(selection_oos_at_freeze)", "detail": [{"q": "2025Q3", "rev_pred": 42.42, "rev_act": 120.4, "op_pred": -1.17, "op_act": -10.12}, {"q": "2025Q4", "rev_pred": 56.65, "rev_act": 71.77, "op_pred": -1.56, "op_act": -3.76}, {"q": "2026Q1", "rev_pred": 63.15, "rev_act": 104.01, "op_pred": -1.74, "op_act": -7.94}, {"q": "2026Q2", "rev_pred": 78.46, "rev_act": 94.65, "op_pred": -2.16, "op_act": -8.06}]}

Sheet 변수
C1: 이름: 변수H | E1: 4Q21 | F1: 2021 | G1: 1Q22 | H1: 2Q22 | I1: 3Q22 | J1: 4Q22 | K1: 2022 | L1: 1Q23 | M1: 2Q23 | N1: 3Q23 | O1: 4Q23 | P1: 2023 | Q1: 1Q24 | R1: 2Q24 | S1: 3Q24 | T1: 4Q24 | U1: 2024 | V1: 1Q25 | W1: 2Q25 | X1: 3Q25 | Y1: 4Q25 | Z1: 2025 | AA1: 1Q26 | AB1: 2Q26 | AC1: 3Q26 | AD1: 4Q26 | AE1: 2026 | AF1: 1Q27 | AG1: 2Q27 | AH1: 3Q27 | AI1: 4Q27 | AJ1: 2027 | AK1: 1Q28 | AL1: 2Q28 | AM1: 3Q28 | AN1: 4Q28 | AO1: 2028
A2: 가정 시계열 — 노란 셀은 추정 가정(모델값에서 역산), 연녹 셀은 3절 스칼라 참조 수식. 바꾸면 subQ·분기·연간예상·TP·시나리오가 재계산됩니다.
E3: 1 | F3: 2 | G3: 3 | H3: 4 | I3: 5 | J3: 6 | K3: 7 | L3: 8 | M3: 9 | N3: 10 | O3: 11 | P3: 12 | Q3: 13 | R3: 14 | S3: 15 | T3: 16 | U3: 17 | V3: 18 | W3: 19 | X3: 20 | Y3: 21 | Z3: 22 | AA3: 23 | AB3: 24 | AC3: 25 | AD3: 26 | AE3: 27 | AF3: 28 | AG3: 29 | AH3: 30 | AI3: 31 | AJ3: 32 | AK3: 33 | AL3: 34 | AM3: 35 | AN3: 36 | AO3: 37
E4: 2021.12 | F4: 2021.12A | G4: 2022.03 | H4: 2022.06 | I4: 2022.09 | J4: 2022.12 | K4: 2022.12A | L4: 2023.03 | M4: 2023.06 | N4: 2023.09 | O4: 2023.12 | P4: 2023.12A | Q4: 2024.03 | R4: 2024.06 | S4: 2024.09 | T4: 2024.12 | U4: 2024.12A | V4: 2025.03 | W4: 2025.06 | X4: 2025.09 | Y4: 2025.12 | Z4: 2025.12A | AA4: 2026.03 | AB4: 2026.06 | AC4: 2026.09 | AD4: 2026.12 | AE4: 2026.12A | AF4: 2027.03 | AG4: 2027.06 | AH4: 2027.09 | AI4: 2027.12 | AJ4: 2027.12A | AK4: 2028.03 | AL4: 2028.06 | AM4: 2028.09 | AN4: 2028.12 | AO4: 2028.12A
B5: 1. FX | C5: 이름: 환율
A6: USDKRW_avg | C6: 원/달러(평균) | E6: 1183.5 | F6: 1145.51 | G6: 1205.78 | H6: 1262.09 | I6: 1341.93 | J6: 1360.12 | K6: 1292.98 | L6: 1276.95 | M6: 1315.69 | N6: 1313.62 | O6: 1322.01 | P6: 1306.85 | Q6: 1330.14 | R6: 1371.28 | S6: 1356.22 | T6: 1396.3 | U6: 1363.53 | V6: 1452.28 | W6: 1398.52 | X6: 1386.95 | Y6: 1449.19 | Z6: 1421.52 | AA6: 1466.12 | AB6: 1501.75 | AC6: 1418.75 | AD6: 1345.14 | AE6: 1457.21 | AF6: 1341.49 | AG6: 1341.49 | AH6: 1341.49 | AI6: 1341.49 | AK6: 1341.49 | AL6: 1341.49 | AM6: 1341.49 | AN6: 1341.49
A7: USDKRW_end | C7: 원/달러(기말) | E7: 1188.75 | F7: 1188.75 | G7: 1213.74 | H7: 1301.24 | I7: 1436.9 | J7: 1260.16 | K7: 1260.16 | L7: 1305.99 | M7: 1321.44 | N7: 1345.35 | O7: 1297.43 | P7: 1297.43 | Q7: 1349.25 | R7: 1377.73 | S7: 1312.17 | T7: 1474.78 | U7: 1474.78 | V7: 1474.54 | W7: 1355.13 | X7: 1403.67 | Y7: 1444.2 | Z7: 1444.2 | AA7: 1524.8 | AB7: 1550.89 | AC7: 1355.4 | AD7: 1341.49 | AE7: 1341.49 | AF7: 1341.49 | AG7: 1341.49 | AH7: 1341.49 | AI7: 1341.49 | AK7: 1341.49 | AL7: 1341.49 | AM7: 1341.49 | AN7: 1341.49
A8: JPY100KRW_avg | C8: 원/100Y(평균) | E8: 1041.02 | F8: 1042.74 | G8: 1036.79 | H8: 972.23 | I8: 970.61 | J8: 961.03 | K8: 985.1 | L8: 964.89 | M8: 957.36 | N8: 909 | O8: 893.22 | P8: 931.11 | Q8: 896.29 | R8: 880.14 | S8: 909.35 | T8: 917.25 | U8: 900.92 | V8: 952.59 | W8: 967.92 | X8: 940.32 | Y8: 940.77 | Z8: 950.17 | AA8: 934.39 | AB8: 942.16 | AC8: 890.41 | AD8: 850.79 | AE8: 919.21 | AF8: 847.7 | AG8: 847.7 | AH8: 847.7 | AI8: 847.7 | AK8: 847.7 | AL8: 847.7 | AM8: 847.7 | AN8: 847.7
A9: JPY100KRW_end | C9: 원/100Y(기말) | E9: 1032.62 | F9: 1032.62 | G9: 996.83 | H9: 954.9 | I9: 993.29 | J9: 955.54 | K9: 955.54 | L9: 980.62 | M9: 913.67 | N9: 901.47 | O9: 917.04 | P9: 917.04 | Q9: 892.42 | R9: 857.76 | S9: 919.21 | T9: 939.65 | U9: 939.65 | V9: 986.84 | W9: 938.85 | X9: 948.49 | Y9: 921.81 | Z9: 921.81 | AA9: 955.99 | AB9: 954.75 | AC9: 863.31 | AD9: 847.7 | AE9: 847.7 | AF9: 847.7 | AG9: 847.7 | AH9: 847.7 | AI9: 847.7 | AK9: 847.7 | AL9: 847.7 | AM9: 847.7 | AN9: 847.7
A10: EURKRW_avg | C10: W/Euro(평균) | E10: 1353.32 | F10: 1354.06 | G10: 1352.29 | H10: 1343.31 | I10: 1350.63 | J10: 1386.07 | K10: 1358.07 | L10: 1369.93 | M10: 1432.41 | N10: 1429.41 | O10: 1420.91 | P10: 1412.88 | Q10: 1444.21 | R10: 1476.42 | S10: 1489.3 | T10: 1490.78 | U10: 1475.4 | V10: 1528.33 | W10: 1585.13 | X10: 1620.04 | Y10: 1686.02 | Z10: 1605.45 | AA10: 1715.47 | AB10: 1746.09 | AC10: 1631.97 | AD10: 1509.74 | AE10: 1689.95 | AF10: 1503.27 | AG10: 1503.27 | AH10: 1503.27 | AI10: 1503.27 | AK10: 1503.27 | AL10: 1503.27 | AM10: 1503.27 | AN10: 1503.27
A11: EURKRW_end | C11: W/Euro(기말) | E11: 1346.38 | F11: 1346.38 | G11: 1347.37 | H11: 1351.6 | I11: 1400.62 | J11: 1344.08 | K11: 1344.08 | L11: 1420.26 | M11: 1435.88 | N11: 1425.26 | O11: 1433.66 | P11: 1433.66 | Q11: 1458.68 | R11: 1474.86 | S11: 1469.1 | T11: 1532.14 | U11: 1532.14 | V11: 1594.72 | W11: 1588.22 | X11: 1648.04 | Y11: 1696.94 | Z11: 1696.94 | AA11: 1753.21 | AB11: 1767.09 | AC11: 1539.06 | AD11: 1503.27 | AE11: 1503.27 | AF11: 1503.27 | AG11: 1503.27 | AH11: 1503.27 | AI11: 1503.27 | AK11: 1503.27 | AL11: 1503.27 | AM11: 1503.27 | AN11: 1503.27
A12: CNYKRW_avg | C12: 원/중국원(평균) | E12: 185.14 | F12: 177.65 | G12: 189.93 | H12: 190.76 | I12: 195.79 | J12: 191.09 | K12: 191.93 | L12: 186.59 | M12: 187.45 | N12: 181.28 | O12: 182.86 | P12: 184.52 | Q12: 185.04 | R12: 189.35 | S12: 189.24 | T12: 194.24 | U12: 189.49 | V12: 199.63 | W12: 193.41 | X12: 193.79 | Y12: 204.38 | Z12: 197.8 | AA12: 211.75 | AB12: 220.8 | AC12: 210.43 | AD12: 200.69 | AE12: 213.75 | AF12: 200.46 | AG12: 200.46 | AH12: 200.46 | AI12: 200.46 | AK12: 200.46 | AL12: 200.46 | AM12: 200.46 | AN12: 200.46
A13: CNYKRW_end | C13: 원/중국원(기말) | E13: 187.13 | F13: 187.13 | G13: 191.38 | H13: 194.13 | I13: 201.92 | J13: 182.67 | K13: 182.67 | L13: 189.97 | M13: 181.8 | N13: 184.26 | O13: 182.61 | P13: 182.61 | Q13: 186.66 | R13: 189.7 | S13: 187.12 | T13: 202.04 | U13: 202.04 | V13: 203.3 | W13: 189.14 | X13: 197.16 | Y13: 206.28 | Z13: 206.28 | AA13: 220.97 | AB13: 228.56 | AC13: 202.16 | AD13: 200.46 | AE13: 200.46 | AF13: 200.46 | AG13: 200.46 | AH13: 200.46 | AI13: 200.46 | AK13: 200.46 | AL13: 200.46 | AM13: 200.46 | AN13: 200.46
B14: 1b. 종가
A15: price_close_end | C15: 종가(기말) | E15: 11673 | G15: 12310 | H15: 9393 | I15: 7374 | J15: 6613 | L15: 3981 | M15: 5174 | N15: 5513 | O15: 5855 | Q15: 7689 | R15: 7223 | S15: 5554 | T15: 5924 | V15: 5568 | W15: 6033 | X15: 2681 | Y15: 1811 | AA15: 2758 | AB15: 1102 | AC15: 1443 | AD15: 1427
A16: price_high | C16: 종가(최고) | E16: 14576 | G16: 13903 | H16: 12494 | I16: 11574 | J16: 8219 | L16: 7349 | M16: 7689 | N16: 6225 | O16: 6074 | Q16: 11561 | R16: 8482 | S16: 8263 | T16: 6936 | V16: 7251 | W16: 8920 | X16: 6731 | Y16: 4224 | AA16: 3803 | AB16: 2897 | AC16: 2305 | AD16: 1646
A17: price_low | C17: 종가(최저) | E17: 10718 | G17: 11500 | H17: 8622 | I17: 7311 | J17: 6416 | L17: 3562 | M17: 3784 | N17: 4320 | O17: 5458 | Q17: 5442 | R17: 5188 | S17: 5308 | T17: 5097 | V17: 4255 | W17: 5335 | X17: 2060 | Y17: 1767 | AA17: 1699 | AB17: 985 | AC17: 680 | AD17: 1331
A18: price_avg | C18: 종가(평균) | E18: 11833.3 | G18: 12350.5 | H18: 10507.7 | I18: 8807 | J18: 6948.8 | L18: 5418.8 | M18: 5658.6 | N18: 5396.4 | O18: 5787.6 | Q18: 6886.9 | R18: 6790.7 | S18: 6735.7 | T18: 6019 | V18: 6062.9 | W18: 6244.6 | X18: 5001.5 | Y18: 2377.5 | AA18: 2765.9 | AB18: 2023.5 | AC18: 1132.7 | AD18: 1509.8
B20: 2. 추정 드라이버 | C20: 실적 열 = subQ 실현값(수식), 추정 열 = 가정(노란 = 모델값 역산, 연녹 = 3절 스칼라 참조)
A21: drv:매출액 | B21: yoy | C21: 매출액 YoY | J21: =IFERROR(subQ!J5/subQ!E5-1,"") | L21: =IFERROR(subQ!L5/subQ!G5-1,"") | M21: =IFERROR(subQ!M5/subQ!H5-1,"") | N21: =IFERROR(subQ!N5/subQ!I5-1,"") | O21: =IFERROR(subQ!O5/subQ!J5-1,"") | Q21: =IFERROR(subQ!Q5/subQ!L5-1,"") | R21: =IFERROR(subQ!R5/subQ!M5-1,"") | S21: =IFERROR(subQ!S5/subQ!N5-1,"") | T21: =IFERROR(subQ!T5/subQ!O5-1,"") | V21: =IFERROR(subQ!V5/subQ!Q5-1,"") | W21: =IFERROR(subQ!W5/subQ!R5-1,"") | X21: =IFERROR(subQ!X5/subQ!S5-1,"") | Y21: =IFERROR(subQ!Y5/subQ!T5-1,"") | AA21: =IFERROR(subQ!AA5/subQ!V5-1,"") | AB21: =IFERROR(subQ!AB5/subQ!W5-1,"") | AC21: 0.13668264 | AD21: 0.13668505 | AF21: 0.13669249 | AG21: 0.13673823 | AH21: 0.068391057 | AI21: 0.068399117 | AK21: 0.068341369 | AL21: 0.068314899 | AM21: 0.034195049 | AN21: 0.034189995
A22: drv:판관비 | B22: ratio | C22: 판관비율(/매출) | E22: =IFERROR(subQ!E8/subQ!E5,"") | F22: =IFERROR(subQ!F8/subQ!F5,"") | G22: =IFERROR(subQ!G8/subQ!G5,"") | H22: =IFERROR(subQ!H8/subQ!H5,"") | I22: =IFERROR(subQ!I8/subQ!I5,"") | J22: =IFERROR(subQ!J8/subQ!J5,"") | K22: =IFERROR(subQ!K8/subQ!K5,"") | L22: =IFERROR(subQ!L8/subQ!L5,"") | ... AB22: =IFERROR(subQ!AB8/subQ!AB5,"") | AC22: =$D$53 | AD22: =$D$53 | AE22: =IFERROR(subQ!AE8/subQ!AE5,"") | AF22: =$D$53 | AG22: =$D$53 | AH22: =$D$53 | AI22: =$D$53 | AJ22: =IFERROR(subQ!AJ8/subQ!AJ5,"") | AK22: =$D$53 | AL22: =$D$53 | AM22: =$D$53 | AN22: =$D$53 | AO22: =IFERROR(subQ!AO8/subQ!AO5,"")
A23: drv:영업이익 | B23: ratio | C23: 영업이익률(OPM) | E23: =IFERROR(subQ!E9/subQ!E5,"") | F23: =IFERROR(subQ!F9/subQ!F5,"") | G23: =IFERROR(subQ!G9/subQ!G5,"") | H23: =IFERROR(subQ!H9/subQ!H5,"") | I23: =IFERROR(subQ!I9/subQ!I5,"") | J23: =IFERROR(subQ!J9/subQ!J5,"") | K23: =IFERROR(subQ!K9/subQ!K5,"") | L23: =IFERROR(subQ!L9/subQ!L5,"") | ... AB23: =IFERROR(subQ!AB9/subQ!AB5,"") | AC23: -0.10565541 | AD23: -0.10566315 | AE23: =IFERROR(subQ!AE9/subQ!AE5,"") | AF23: -0.10564155 | AG23: -0.10567897 | AH23: -0.1056627 | AI23: -0.10566774 | AJ23: =IFERROR(subQ!AJ9/subQ!AJ5,"") | AK23: -0.10569234 | AL23: -0.10570733 | AM23: -0.10567385 | AN23: -0.10572443 | AO23: =IFERROR(subQ!AO9/subQ!AO5,"")
A24: drv:외환손익 | B24: abs | C24: 외환손익 (가정, 억원) | E24: =subQ!E13 | F24: =subQ!F13 | G24: =subQ!G13 | H24: =subQ!H13 | I24: =subQ!I13 | J24: =subQ!J13 | K24: =subQ!K13 | L24: =subQ!L13 | ... AB24: =subQ!AB13 | AC24: 0 | AD24: 0 | AE24: =subQ!AE13 | AF24: 0 | AG24: 0 | AH24: 0 | AI24: 0 | AJ24: =subQ!AJ13 | AK24: 0 | AL24: 0 | AM24: 0 | AN24: 0 | AO24: =subQ!AO13
A25: drv:파생상품손익 | B25: abs | C25: 파생상품손익 (가정, 억원) | E25: =subQ!E14 | F25: =subQ!F14 | G25: =subQ!G14 | H25: =subQ!H14 | I25: =subQ!I14 | J25: =subQ!J14 | K25: =subQ!K14 | L25: =subQ!L14 | ... AB25: =subQ!AB14 | AC25: 0 | AD25: 0 | AE25: =subQ!AE14 | AF25: 0 | AG25: 0 | AH25: 0 | AI25: 0 | AJ25: =subQ!AJ14 | AK25: 0 | AL25: 0 | AM25: 0 | AN25: 0 | AO25: =subQ!AO14
A26: drv:기타금융손익 | B26: abs | C26: 기타금융손익 (가정, 억원) | E26: =subQ!E15 | F26: =subQ!F15 | G26: =subQ!G15 | H26: =subQ!H15 | I26: =subQ!I15 | J26: =subQ!J15 | K26: =subQ!K15 | L26: =subQ!L15 | ... AB26: =subQ!AB15 | AC26: 0 | AD26: 0 | AE26: =subQ!AE15 | AF26: 0 | AG26: 0 | AH26: 0 | AI26: 0 | AJ26: =subQ!AJ15 | AK26: 0 | AL26: 0 | AM26: 0 | AN26: 0 | AO26: =subQ!AO15
A27: drv:기타영업외손익 | B27: abs | C27: 기타영업외손익 (가정, 억원) | E27: =subQ!E16 | F27: =subQ!F16 | G27: =subQ!G16 | H27: =subQ!H16 | I27: =subQ!I16 | J27: =subQ!J16 | K27: =subQ!K16 | L27: =subQ!L16 | ... AB27: =subQ!AB16 | AC27: 0 | AD27: 0 | AE27: =subQ!AE16 | AF27: 0 | AG27: 0 | AH27: 0 | AI27: 0 | AJ27: =subQ!AJ16 | AK27: 0 | AL27: 0 | AM27: 0 | AN27: 0 | AO27: =subQ!AO16
A28: drv:지분법손익 | B28: abs | C28: 지분법손익 (가정, 억원) | E28: =subQ!E17 | F28: =subQ!F17 | G28: =subQ!G17 | H28: =subQ!H17 | I28: =subQ!I17 | J28: =subQ!J17 | K28: =subQ!K17 | L28: =subQ!L17 | ... AB28: =subQ!AB17 | AC28: -7.62 | AD28: -7.62 | AE28: =subQ!AE17 | AF28: -7.62 | AG28: -7.62 | AH28: -7.62 | AI28: -7.62 | AJ28: =subQ!AJ17 | AK28: -7.62 | AL28: -7.62 | AM28: -7.62 | AN28: -7.62 | AO28: =subQ!AO17
A29: drv:법인세비용 | B29: ratio | C29: 법인세율(/세전) | E29: =IFERROR(subQ!E19/subQ!E18,"") | F29: =IFERROR(subQ!F19/subQ!F18,"") | G29: =IFERROR(subQ!G19/subQ!G18,"") | H29: =IFERROR(subQ!H19/subQ!H18,"") | I29: =IFERROR(subQ!I19/subQ!I18,"") | J29: =IFERROR(subQ!J19/subQ!J18,"") | K29: =IFERROR(subQ!K19/subQ!K18,"") | L29: =IFERROR(subQ!L19/subQ!L18,"") | ... AB29: =IFERROR(subQ!AB19/subQ!AB18,"") | AC29: 0 | AD29: 0 | AE29: =IFERROR(subQ!AE19/subQ!AE18,"") | AF29: 0 | AG29: 0 | AH29: 0 | AI29: 0 | AJ29: =IFERROR(subQ!AJ19/subQ!AJ18,"") | AK29: 0 | AL29: 0 | AM29: 0 | AN29: 0 | AO29: =IFERROR(subQ!AO19/subQ!AO18,"")
A30: drv:지배주주순이익 | B30: ratio | C30: 지배주주 비중(/당기순이익) | E30: =IFERROR(subQ!E21/subQ!E20,"") | F30: =IFERROR(subQ!F21/subQ!F20,"") | G30: =IFERROR(subQ!G21/subQ!G20,"") | H30: =IFERROR(subQ!H21/subQ!H20,"") | I30: =IFERROR(subQ!I21/subQ!I20,"") | J30: =IFERROR(subQ!J21/subQ!J20,"") | K30: =IFERROR(subQ!K21/subQ!K20,"") | L30: =IFERROR(subQ!L21/subQ!L20,"") | ... AB30: =IFERROR(subQ!AB21/subQ!AB20,"") | AC30: =$D$54 | AD30: =$D$54 | AE30: =IFERROR(subQ!AE21/subQ!AE20,"") | AF30: =$D$54 | AG30: =$D$54 | AH30: =$D$54 | AI30: =$D$54 | AJ30: =IFERROR(subQ!AJ21/subQ!AJ20,"") | AK30: =$D$54 | AL30: =$D$54 | AM30: =$D$54 | AN30: =$D$54 | AO30: =IFERROR(subQ!AO21/subQ!AO20,"")
A31: drv:중단사업이익 | B31: abs | C31: 중단사업이익 (가정, 억원) | E31: =subQ!E22 | F31: =subQ!F22 | G31: =subQ!G22 | H31: =subQ!H22 | I31: =subQ!I22 | J31: =subQ!J22 | K31: =subQ!K22 | L31: =subQ!L22 | ... AB31: =subQ!AB22 | AE31: =subQ!AE22 | AJ31: =subQ!AJ22 | AO31: =subQ!AO22
A32: drv:부채총계 | B32: qoq | C32: 부채총계 QoQ | G32: =IFERROR(subQ!G24/subQ!E24-1,"") | H32: =IFERROR(subQ!H24/subQ!G24-1,"") | I32: =IFERROR(subQ!I24/subQ!H24-1,"") | J32: =IFERROR(subQ!J24/subQ!I24-1,"") | L32: =IFERROR(subQ!L24/subQ!J24-1,"") | M32: =IFERROR(subQ!M24/subQ!L24-1,"") | N32: =IFERROR(subQ!N24/subQ!M24-1,"") | O32: =IFERROR(subQ!O24/subQ!N24-1,"") | Q32: =IFERROR(subQ!Q24/subQ!O24-1,"") | R32: =IFERROR(subQ!R24/subQ!Q24-1,"") | S32: =IFERROR(subQ!S24/subQ!R24-1,"") | T32: =IFERROR(subQ!T24/subQ!S24-1,"") | V32: =IFERROR(subQ!V24/subQ!T24-1,"") | W32: =IFERROR(subQ!W24/subQ!V24-1,"") | X32: =IFERROR(subQ!X24/subQ!W24-1,"") | Y32: =IFERROR(subQ!Y24/subQ!X24-1,"") | AA32: =IFERROR(subQ!AA24/subQ!Y24-1,"") | AB32: =IFERROR(subQ!AB24/subQ!AA24-1,"") | AC32: -1.3497e-05 | AD32: 0 | AF32: 0 | AG32: 0 | AH32: 0 | AI32: 0 | AK32: 0 | AL32: 0 | AM32: 0 | AN32: 0
A33: drv:자본총계 | B33: roll | C33: 자본총계 기타변동(배당 등, 억원) | G33: =IFERROR(subQ!E25+subQ!G20-subQ!G25,"") | H33: =IFERROR(subQ!G25+subQ!H20-subQ!H25,"") | I33: =IFERROR(subQ!H25+subQ!I20-subQ!I25,"") | J33: =IFERROR(subQ!I25+subQ!J20-subQ!J25,"") | L33: =IFERROR(subQ!J25+subQ!L20-subQ!L25,"") | M33: =IFERROR(subQ!L25+subQ!M20-subQ!M25,"") | N33: =IFERROR(subQ!M25+subQ!N20-subQ!N25,"") | O33: =IFERROR(subQ!N25+subQ!O20-subQ!O25,"") | Q33: =IFERROR(subQ!O25+subQ!Q20-subQ!Q25,"") | R33: =IFERROR(subQ!Q25+subQ!R20-subQ!R25,"") | S33: =IFERROR(subQ!R25+subQ!S20-subQ!S25,"") | T33: =IFERROR(subQ!S25+subQ!T20-subQ!T25,"") | V33: =IFERROR(subQ!T25+subQ!V20-subQ!V25,"") | W33: =IFERROR(subQ!V25+subQ!W20-subQ!W25,"") | X33: =IFERROR(subQ!W25+subQ!X20-subQ!X25,"") | Y33: =IFERROR(subQ!X25+subQ!Y20-subQ!Y25,"") | AA33: =IFERROR(subQ!Y25+subQ!AA20-subQ!AA25,"") | AB33: =IFERROR(subQ!AA25+subQ!AB20-subQ!AB25,"") | AC33: 0.006926205 | AD33: 0.002789916 | AF33: 0.012269244 | AG33: 0.003367536 | AH33: 0.006747604 | AI33: 0.001298913 | AK33: 0.009029466 | AL33: -0.002196851 | AM33: 0.009029348 | AN33: 0.001938567
A34: drv:지배주주지분 | B34: roll | C34: 지배주주지분 기타변동(배당 등, 억원) | G34: =IFERROR(subQ!E26+subQ!G21-subQ!G26,"") | H34: =IFERROR(subQ!G26+subQ!H21-subQ!H26,"") | I34: =IFERROR(subQ!H26+subQ!I21-subQ!I26,"") | J34: =IFERROR(subQ!I26+subQ!J21-subQ!J26,"") | L34: =IFERROR(subQ!J26+subQ!L21-subQ!L26,"") | M34: =IFERROR(subQ!L26+subQ!M21-subQ!M26,"") | N34: =IFERROR(subQ!M26+subQ!N21-subQ!N26,"") | O34: =IFERROR(subQ!N26+subQ!O21-subQ!O26,"") | Q34: =IFERROR(subQ!O26+subQ!Q21-subQ!Q26,"") | R34: =IFERROR(subQ!Q26+subQ!R21-subQ!R26,"") | S34: =IFERROR(subQ!R26+subQ!S21-subQ!S26,"") | T34: =IFERROR(subQ!S26+subQ!T21-subQ!T26,"") | V34: =IFERROR(subQ!T26+subQ!V21-subQ!V26,"") | W34: =IFERROR(subQ!V26+subQ!W21-subQ!W26,"") | X34: =IFERROR(subQ!W26+subQ!X21-subQ!X26,"") | Y34: =IFERROR(subQ!X26+subQ!Y21-subQ!Y26,"") | AA34: =IFERROR(subQ!Y26+subQ!AA21-subQ!AA26,"") | AB34: =IFERROR(subQ!AA26+subQ!AB21-subQ!AB26,"") | AC34: 0.006926205 | AD34: 0.002789916 | AF34: 0.012269244 | AG34: 0.003367536 | AH34: 0.006747604 | AI34: 0.001298913 | AK34: 0.009029466 | AL34: -0.002196851 | AM34: 0.009029348 | AN34: 0.001938567
A35: drv:총차입금 | B35: qoq | C35: 총차입금 QoQ | G35: =IFERROR(subQ!G27/subQ!E27-1,"") | H35: =IFERROR(subQ!H27/subQ!G27-1,"") | I35: =IFERROR(subQ!I27/subQ!H27-1,"") | J35: =IFERROR(subQ!J27/subQ!I27-1,"") | L35: =IFERROR(subQ!L27/subQ!J27-1,"") | M35: =IFERROR(subQ!M27/subQ!L27-1,"") | N35: =IFERROR(subQ!N27/subQ!M27-1,"") | O35: =IFERROR(subQ!O27/subQ!N27-1,"") | Q35: =IFERROR(subQ!Q27/subQ!O27-1,"") | R35: =IFERROR(subQ!R27/subQ!Q27-1,"") | S35: =IFERROR(subQ!S27/subQ!R27-1,"") | T35: =IFERROR(subQ!T27/subQ!S27-1,"") | V35: =IFERROR(subQ!V27/subQ!T27-1,"") | W35: =IFERROR(subQ!W27/subQ!V27-1,"") | X35: =IFERROR(subQ!X27/subQ!W27-1,"") | Y35: =IFERROR(subQ!Y27/subQ!X27-1,"") | AA35: =IFERROR(subQ!AA27/subQ!Y27-1,"") | AB35: =IFERROR(subQ!AB27/subQ!AA27-1,"") | AC35: 1.1784e-05 | AD35: 0 | AF35: 0 | AG35: 0 | AH35: 0 | AI35: 0 | AK35: 0 | AL35: 0 | AM35: 0 | AN35: 0
A36: drv:순차입금 | B36: qoq | C36: 순차입금 QoQ | G36: =IFERROR(subQ!G28/subQ!E28-1,"") | H36: =IFERROR(subQ!H28/subQ!G28-1,"") | I36: =IFERROR(subQ!I28/subQ!H28-1,"") | J36: =IFERROR(subQ!J28/subQ!I28-1,"") | L36: =IFERROR(subQ!L28/subQ!J28-1,"") | M36: =IFERROR(subQ!M28/subQ!L28-1,"") | N36: =IFERROR(subQ!N28/subQ!M28-1,"") | O36: =IFERROR(subQ!O28/subQ!N28-1,"") | Q36: =IFERROR(subQ!Q28/subQ!O28-1,"") | R36: =IFERROR(subQ!R28/subQ!Q28-1,"") | S36: =IFERROR(subQ!S28/subQ!R28-1,"") | T36: =IFERROR(subQ!T28/subQ!S28-1,"") | V36: =IFERROR(subQ!V28/subQ!T28-1,"") | W36: =IFERROR(subQ!W28/subQ!V28-1,"") | X36: =IFERROR(subQ!X28/subQ!W28-1,"") | Y36: =IFERROR(subQ!Y28/subQ!X28-1,"") | AA36: =IFERROR(subQ!AA28/subQ!Y28-1,"") | AB36: =IFERROR(subQ!AB28/subQ!AA28-1,"") | AC36: 0.16443948 | AD36: 0.11357646 | AF36: 0.11881912 | AG36: 0.10212324 | AH36: 0.1071092 | AI36: 0.077296513 | AK36: 0.083981975 | AL36: 0.074398013 | AM36: 0.079045226 | AN36: 0.058375635
A37: drv:이자발생자산 | B37: qoq | C37: 이자발생자산 QoQ | G37: =IFERROR(subQ!G29/subQ!E29-1,"") | H37: =IFERROR(subQ!H29/subQ!G29-1,"") | I37: =IFERROR(subQ!I29/subQ!H29-1,"") | J37: =IFERROR(subQ!J29/subQ!I29-1,"") | L37: =IFERROR(subQ!L29/subQ!J29-1,"") | M37: =IFERROR(subQ!M29/subQ!L29-1,"") | N37: =IFERROR(subQ!N29/subQ!M29-1,"") | O37: =IFERROR(subQ!O29/subQ!N29-1,"") | Q37: =IFERROR(subQ!Q29/subQ!O29-1,"") | R37: =IFERROR(subQ!R29/subQ!Q29-1,"") | S37: =IFERROR(subQ!S29/subQ!R29-1,"") | T37: =IFERROR(subQ!T29/subQ!S29-1,"") | V37: =IFERROR(subQ!V29/subQ!T29-1,"") | W37: =IFERROR(subQ!W29/subQ!V29-1,"") | X37: =IFERROR(subQ!X29/subQ!W29-1,"") | Y37: =IFERROR(subQ!Y29/subQ!X29-1,"") | AA37: =IFERROR(subQ!AA29/subQ!Y29-1,"") | AB37: =IFERROR(subQ!AB29/subQ!AA29-1,"") | AC37: -1.0268286 | AD37: 30.766234 | AF37: 1.1291905 | AG37: 0.50979263 | AH37: 0.39030904 | AI37: 0.22420417 | AK37: 0.21452589 | AL37: 0.16955826 | AM37: 0.16549185 | AN37: 0.11315219
A38: drv:현금및현금성자산 | B38: qoq | C38: 현금및현금성자산 QoQ | G38: =IFERROR(subQ!G30/subQ!E30-1,"") | H38: =IFERROR(subQ!H30/subQ!G30-1,"") | I38: =IFERROR(subQ!I30/subQ!H30-1,"") | J38: =IFERROR(subQ!J30/subQ!I30-1,"") | L38: =IFERROR(subQ!L30/subQ!J30-1,"") | M38: =IFERROR(subQ!M30/subQ!L30-1,"") | N38: =IFERROR(subQ!N30/subQ!M30-1,"") | O38: =IFERROR(subQ!O30/subQ!N30-1,"") | Q38: =IFERROR(subQ!Q30/subQ!O30-1,"") | R38: =IFERROR(subQ!R30/subQ!Q30-1,"") | S38: =IFERROR(subQ!S30/subQ!R30-1,"") | T38: =IFERROR(subQ!T30/subQ!S30-1,"") | V38: =IFERROR(subQ!V30/subQ!T30-1,"") | W38: =IFERROR(subQ!W30/subQ!V30-1,"") | X38: =IFERROR(subQ!X30/subQ!W30-1,"") | Y38: =IFERROR(subQ!Y30/subQ!X30-1,"") | AA38: =IFERROR(subQ!AA30/subQ!Y30-1,"") | AB38: =IFERROR(subQ!AB30/subQ!AA30-1,"")
A39: drv:CAPEX | B39: yoy | C39: CAPEX YoY | J39: =IFERROR(subQ!J31/subQ!E31-1,"") | L39: =IFERROR(subQ!L31/subQ!G31-1,"") | M39: =IFERROR(subQ!M31/subQ!H31-1,"") | N39: =IFERROR(subQ!N31/subQ!I31-1,"") | O39: =IFERROR(subQ!O31/subQ!J31-1,"") | Q39: =IFERROR(subQ!Q31/subQ!L31-1,"") | R39: =IFERROR(subQ!R31/subQ!M31-1,"") | S39: =IFERROR(subQ!S31/subQ!N31-1,"") | T39: =IFERROR(subQ!T31/subQ!O31-1,"") | V39: =IFERROR(subQ!V31/subQ!Q31-1,"") | W39: =IFERROR(subQ!W31/subQ!R31-1,"") | X39: =IFERROR(subQ!X31/subQ!S31-1,"") | Y39: =IFERROR(subQ!Y31/subQ!T31-1,"") | AA39: =IFERROR(subQ!AA31/subQ!V31-1,"") | AB39: =IFERROR(subQ!AB31/subQ!W31-1,"") | AC39: 1.3058664 | AD39: -0.23189879 | AF39: 0.42155326 | AG39: -0.40303749 | AH39: 0 | AI39: 0 | AK39: 0 | AL39: 0 | AM39: 0 | AN39: 0
A40: drv:영업활동현금흐름 | B40: yoy | C40: 영업활동현금흐름 YoY | J40: =IFERROR(subQ!J32/subQ!E32-1,"") | L40: =IFERROR(subQ!L32/subQ!G32-1,"") | M40: =IFERROR(subQ!M32/subQ!H32-1,"") | N40: =IFERROR(subQ!N32/subQ!I32-1,"") | O40: =IFERROR(subQ!O32/subQ!J32-1,"") | Q40: =IFERROR(subQ!Q32/subQ!L32-1,"") | R40: =IFERROR(subQ!R32/subQ!M32-1,"") | S40: =IFERROR(subQ!S32/subQ!N32-1,"") | T40: =IFERROR(subQ!T32/subQ!O32-1,"") | V40: =IFERROR(subQ!V32/subQ!Q32-1,"") | W40: =IFERROR(subQ!W32/subQ!R32-1,"") | X40: =IFERROR(subQ!X32/subQ!S32-1,"") | Y40: =IFERROR(subQ!Y32/subQ!T32-1,"") | AA40: =IFERROR(subQ!AA32/subQ!V32-1,"") | AB40: =IFERROR(subQ!AB32/subQ!W32-1,"")
A41: drv:주식수 | B41: qoq | C41: 주식수 QoQ | G41: =IFERROR(subQ!G33/subQ!E33-1,"") | H41: =IFERROR(subQ!H33/subQ!G33-1,"") | I41: =IFERROR(subQ!I33/subQ!H33-1,"") | J41: =IFERROR(subQ!J33/subQ!I33-1,"") | L41: =IFERROR(subQ!L33/subQ!J33-1,"") | M41: =IFERROR(subQ!M33/subQ!L33-1,"") | N41: =IFERROR(subQ!N33/subQ!M33-1,"") | O41: =IFERROR(subQ!O33/subQ!N33-1,"") | Q41: =IFERROR(subQ!Q33/subQ!O33-1,"") | R41: =IFERROR(subQ!R33/subQ!Q33-1,"") | S41: =IFERROR(subQ!S33/subQ!R33-1,"") | T41: =IFERROR(subQ!T33/subQ!S33-1,"") | V41: =IFERROR(subQ!V33/subQ!T33-1,"") | W41: =IFERROR(subQ!W33/subQ!V33-1,"") | X41: =IFERROR(subQ!X33/subQ!W33-1,"") | Y41: =IFERROR(subQ!Y33/subQ!X33-1,"") | AA41: =IFERROR(subQ!AA33/subQ!Y33-1,"") | AB41: =IFERROR(subQ!AB33/subQ!AA33-1,"") | AC41: -2.5e-08 | AD41: 0 | AF41: 0 | AG41: 0 | AH41: 0 | AI41: 0 | AK41: 0 | AL41: 0 | AM41: 0 | AN41: 0
A42: drv:DPS | B42: abs | C42: DPS (가정, 원) | E42: =subQ!E37 | F42: =subQ!F37 | G42: =subQ!G37 | H42: =subQ!H37 | I42: =subQ!I37 | J42: =subQ!J37 | K42: =subQ!K37 | L42: =subQ!L37 | ... AB42: =subQ!AB37 | AD42: 0 | AE42: =subQ!AE37 | AI42: 0 | AJ42: =subQ!AJ37 | AN42: 0 | AO42: =subQ!AO37
B44: 3. 밸류에이션·스칼라 | C44: 노란 셀 = 가정. '연결' 표시는 추정 전 분기 수식이 이 셀을 참조한다는 뜻
A45: sc:종가 | C45: 종가 | D45: 1427 | E45: 원 — 네이버 정규장 종가(aik 확정종가 대조 · aik 1,586원)
A46: sc:기준일 | C46: 기준일 | D46: 20261008 | E46: 종가 기준일
A47: sc:COE | C47: COE | D47: 0.09 | E47: 자기자본비용(가정) — TP 적정 PBR = ROE/COE
A48: sc:PER_lo | C48: PER_lo | D48: 10 | E48: PER 밴드 하단(배) — sector_default(레퍼런스 TP_PE PB 예시 10/15/20배; 과거 양(+)EPS 분기 2개 < 4)
A49: sc:PER_mid | C49: PER_mid | D49: 15 | E49: PER 밴드 중단(배)
A50: sc:PER_hi | C50: PER_hi | D50: 20 | E50: PER 밴드 상단(배)
A51: sc:EPS_Y1가중 | C51: EPS_Y1가중 | D51: 0.5 | E51: 12M fwd EPS = FY(last_actual연도)E × w + FY+1E × (1−w) — 기준 분기 2Q 이면 0.5(가정)
A52: sc:세율 | C52: 세율 | D52: 0.22 | E52: 참고(연결 안 됨: MAX(세전,0)×단일 세율로 재현 불가(지주 자회사 합산 등) → 분기별 역산) — 모델 assumptions 값 · 최근 12분기 세전 합 ≤ 0; 세전 > 0 분기 중위 0.2% 도 5~27% 밖 → 법정세율 근사 22% 가정
A53: sc:판관비율 | C53: 판관비율 | D53: 0.24959276 | E53: 연결 — 판관비 = 매출액 × 판관비율(역산, 재현 오차 ≤ 0.05억 · 모델 assumptions 0.2496)
A54: sc:지배주주비중 | C54: 지배주주비중 | D54: 1 | E54: 연결 — 지배주주순이익 = 당기순이익 × 비중(역산, 재현 오차 ≤ 0.05억)
A55: sc:이자율_자산 | C55: 이자율_자산 | D55: 0.008530302 | E55: 연결 — 이자손익 = (전분기 이자발생자산 × 자산이자율 − 전분기 총차입금 × 부채이자율)/4(역산, 재현 오차 ≤ 0.05억 · 모델 assumptions 0.0086)
A56: sc:이자율_부채 | C56: 이자율_부채 | D56: 0.1595194 | E56: 연결 — 같은 수식의 부채 쪽(총차입금 행이 없으면 0)(역산, 재현 오차 ≤ 0.05억 · 모델 assumptions 0.1595)
A57: sc:배당성향 | C57: 배당성향 | E57: 배당성향(참고 — 모델은 직전 DPS 유지·Q2 지급 가정)
A58: sc:외화순노출_백만$ | C58: 외화순노출_백만$ | E58: 외화 순노출 × Δ기말환율 (외화 시트 방식) — 외화 순노출 미공시(face) → 0 + 표기
A59: sc:헤지비율 | C59: 헤지비율 | E59: sls 없음
A60: sc:헤지환율_약정 | C60: 헤지환율_약정 | E60: sls 없음

Sheet BS연결
B1: (백만원) | C1: 이름: BS연결H | E1: 4Q21 | F1: 2021 | G1: 1Q22 | H1: 2Q22 | I1: 3Q22 | J1: 4Q22 | K1: 2022 | L1: 1Q23 | M1: 2Q23 | N1: 3Q23 | O1: 4Q23 | P1: 2023 | Q1: 1Q24 | R1: 2Q24 | S1: 3Q24 | T1: 4Q24 | U1: 2024 | V1: 1Q25 | W1: 2Q25 | X1: 3Q25 | Y1: 4Q25 | Z1: 2025 | AA1: 1Q26 | AB1: 2Q26 | AC1: 3Q26 | AD1: 4Q26 | AE1: 2026 | AF1: 1Q27 | AG1: 2Q27 | AH1: 3Q27 | AI1: 4Q27 | AJ1: 2027 | AK1: 1Q28 | AL1: 2Q28 | AM1: 3Q28 | AN1: 4Q28 | AO1: 2028
B2: 연결 | D2: fin json(kship_fin.py)
B3: KS인더스트리(연) | C3: UPDATE: 26-10-11 | E3: 1 | F3: 2 | G3: 3 | H3: 4 | I3: 5 | J3: 6 | K3: 7 | L3: 8 | M3: 9 | N3: 10 | O3: 11 | P3: 12 | Q3: 13 | R3: 14 | S3: 15 | T3: 16 | U3: 17 | V3: 18 | W3: 19 | X3: 20 | Y3: 21 | Z3: 22 | AA3: 23 | AB3: 24 | AC3: 25 | AD3: 26 | AE3: 27 | AF3: 28 | AG3: 29 | AH3: 30 | AI3: 31 | AJ3: 32 | AK3: 33 | AL3: 34 | AM3: 35 | AN3: 36 | AO3: 37
B4: Account Code | C4: AccountNAME | E4: 2021.12 | F4: 2021.12A | G4: 2022.03 | H4: 2022.06 | I4: 2022.09 | J4: 2022.12 | K4: 2022.12A | L4: 2023.03 | M4: 2023.06 | N4: 2023.09 | O4: 2023.12 | P4: 2023.12A | Q4: 2024.03 | R4: 2024.06 | S4: 2024.09 | T4: 2024.12 | U4: 2024.12A | V4: 2025.03 | W4: 2025.06 | X4: 2025.09 | Y4: 2025.12 | Z4: 2025.12A | AA4: 2026.03 | AB4: 2026.06 | AC4: 2026.09 | AD4: 2026.12 | AE4: 2026.12A | AF4: 2027.03 | AG4: 2027.06 | AH4: 2027.09 | AI4: 2027.12 | AJ4: 2027.12A | AK4: 2028.03 | AL4: 2028.06 | AM4: 2028.09 | AN4: 2028.12 | AO4: 2028.12A
A5: 1 | C5: 유동자산 | E5: 26377.33 | F5: 26377.33 | G5: 21070.51 | H5: 28814.52 | I5: 28181.07 | J5: 26887.14 | K5: 26887.14 | L5: 29627.19 | M5: 28900.32 | N5: 27575.94 | O5: 18136.22 | P5: 18136.22 | Q5: 35882.04 | R5: 35531.42 | S5: 26584.13 | T5: 25980.5 | U5: 25980.5 | V5: 22528.81 | W5: 22120.28 | X5: 21400.44 | Y5: 18664.24 | Z5: 18664.24 | AA5: 36218.6 | AB5: 26441.94
A6: 1 | C6: 현금및현금성자산 | E6: 1273.35 | F6: 1273.35 | G6: 1139.15 | H6: 853.64 | I6: 537.71 | J6: 717.83 | K6: 717.83 | L6: 421.39 | M6: 1502.1 | N6: 1390.21 | O6: 1206.27 | P6: 1206.27 | Q6: 12913.09 | R6: 16906.03 | S6: 9791.26 | T6: 11326.81 | U6: 11326.81 | V6: 8117.89 | W6: 6205.44 | X6: 2954.31 | Y6: 3381.75 | Z6: 3381.75 | AA6: 22604.41 | AB6: 743.57
A7: 1 | C7: 매출채권및기타채권 | E7: 2827.61 | F7: 2827.61 | G7: 3605.47 | H7: 6684.61 | I7: 8067.23 | J7: 8106.44 | K7: 8106.44 | L7: 7403.9 | M7: 6850.1 | N7: 5727.77 | O7: 4999.29 | P7: 4999.29 | Q7: 13006.2 | R7: 7705.54 | S7: 3010.89 | T7: 6297.56 | U7: 6297.56 | V7: 4518.12 | W7: 5299.15 | X7: 7010.62 | Y7: 7047.48 | Z7: 7047.48 | AA7: 4938.42 | AB7: 15957.42
A8: 1 | C8: 재고자산 | E8: 12149.58 | F8: 12149.58 | G8: 9706.18 | H8: 8440.08 | I8: 12617.06 | J8: 8553.1 | K8: 8553.1 | L8: 9161.58 | M8: 9465.48 | N8: 6995.26 | O8: 5571.81 | P8: 5571.81 | Q8: 5998.67 | R8: 6752.09 | S8: 6694.7 | T8: 6827.28 | U8: 6827.28 | V8: 7310.22 | W8: 6978.76 | X8: 7386.13 | Y8: 6888.22 | Z8: 6888.22 | AA8: 7277.42 | AB8: 8321.64
A9: 1 | C9: 당기법인세자산(선급법인세) | E9: 6.6 | F9: 6.6 | G9: 7.66 | H9: 4.56 | I9: 5.33 | J9: 5.57 | K9: 5.57 | L9: 5.58 | M9: 0.53 | N9: 0.03 | R9: 0.38 | S9: 14 | T9: 34.02 | U9: 34.02 | V9: 33.1 | W9: 9.99 | X9: 29.28 | Y9: 15.52 | Z9: 15.52 | AA9: 17.39 | AB9: 4.03
A10: 1 | C10: 비유동자산 | E10: 20521.6 | F10: 20521.6 | G10: 21939.39 | H10: 26283.73 | I10: 26642.11 | J10: 27288.78 | K10: 27288.78 | L10: 26986.12 | M10: 26163.31 | N10: 25687.56 | O10: 25420.68 | P10: 25420.68 | Q10: 16273.7 | R10: 7529.54 | S10: 29015.89 | T10: 39838.3 | U10: 39838.3 | V10: 46034.51 | W10: 45974.1 | X10: 44854.93 | Y10: 42529.37 | Z10: 42529.37 | AA10: 42145.44 | AB10: 49991.61
A11: 1 | C11: 장기금융자산 | E11: 28.76 | F11: 28.76 | G11: 34.76 | H11: 39.93 | J11: 158.58 | K11: 158.58 | L11: 93.13 | M11: 48.7 | O11: 237.48 | P11: 237.48 | Q11: 346.04 | S11: 4619.99 | T11: 2673.72 | U11: 2673.72 | V11: 5373.72 | W11: 5519.01 | X11: 4818.4 | Y11: 2889.71 | Z11: 2889.71 | AA11: 2876.2 | AB11: 2120.5
A12: 1 | C12: 투자자산 | E12: 28.76 | F12: 28.76 | G12: 34.76 | H12: 39.93 | J12: 158.58 | K12: 158.58 | L12: 93.13 | M12: 48.7 | O12: 237.48 | P12: 237.48 | Q12: 346.04 | S12: 4620.56 | T12: 2673.72 | U12: 2673.72 | V12: 5373.72 | W12: 5519.01 | X12: 4818.4 | Y12: 2889.71 | Z12: 2889.71 | AA12: 2876.2 | AB12: 11806.07
A13: 1 | C13: 유형자산 | E13: 16058.32 | F13: 16058.32 | G13: 17412.18 | H13: 18306.58 | I13: 18618.41 | J13: 18895.27 | K13: 18895.27 | L13: 18572.44 | M13: 17721.05 | N13: 17219.4 | O13: 16610.9 | P13: 16610.9 | Q13: 15239.23 | R13: 6160.38 | S13: 22787.77 | T13: 27023.09 | U13: 27023.09 | V13: 28205.55 | W13: 28350.4 | X13: 28107.07 | Y13: 27972.89 | Z13: 27972.89 | AA13: 27683.45 | AB13: 26599.21
A14: 1 | C14: 무형자산 | E14: 67.68 | F14: 67.68 | G14: 82.58 | H14: 76.6 | I14: 80.06 | J14: 196.89 | K14: 196.89 | L14: 186.69 | M14: 172.97 | N14: 161.69 | O14: 148.67 | P14: 148.67 | Q14: 135.66 | R14: 122.65 | S14: 109.64 | T14: 7969.09 | U14: 7969.09 | V14: 7950.59 | W14: 7838.34 | X14: 7726.08 | Y14: 7613.82 | Z14: 7613.82 | AA14: 7501.56 | AB14: 7644.36
A15: 1 | C15: 자산총계 | E15: 46898.93 | F15: 46898.93 | G15: 43009.9 | H15: 55098.25 | I15: 54823.18 | J15: 54175.92 | K15: 54175.92 | L15: 56613.31 | M15: 55063.64 | N15: 53263.51 | O15: 43556.9 | P15: 43556.9 | Q15: 52155.74 | R15: 43060.96 | S15: 55600.02 | T15: 65818.8 | U15: 65818.8 | V15: 68563.32 | W15: 68094.39 | X15: 66255.38 | Y15: 61193.61 | Z15: 61193.61 | AA15: 78364.04 | AB15: 76433.55
A16: 1 | C16: 유동부채 | E16: 20865.72 | F16: 20865.72 | G16: 18845.78 | H16: 32061.53 | I16: 35288.41 | J16: 42714.35 | K16: 42714.35 | L16: 46291.61 | M16: 41625.97 | N16: 39235.08 | O16: 27540.69 | P16: 27540.69 | Q16: 29807.34 | R16: 7073.1 | S16: 8657.76 | T16: 18613.96 | U16: 18613.96 | V16: 18255.73 | W16: 15322.09 | X16: 14709.23 | Y16: 13371.43 | Z16: 13371.43 | AA16: 23470.07 | AB16: 18890.11
A17: 1 | C17: 매입채무및기타채무 | E17: 8159.73 | F17: 8159.73 | G17: 7342.42 | H17: 9583.38 | I17: 10071.16 | J17: 10939.39 | K17: 10939.39 | L17: 23480.38 | M17: 8796.3 | N17: 7214.51 | O17: 5385.93 | P17: 5385.93 | Q17: 5032.72 | R17: 4145.25 | S17: 3309.31 | T17: 5771.63 | U17: 5771.63 | V17: 4271.11 | W17: 5085.52 | X17: 5446.89 | Y17: 4737.07 | Z17: 4737.07 | AA17: 4518.27 | AB17: 5015.07
A18: 1 | C18: 단기차입금 | E18: 4800 | F18: 4800 | G18: 4800 | H18: 6800 | I18: 7600 | J18: 6800 | K18: 6800 | L18: 6500 | M18: 6850 | N18: 5100 | O18: 5850 | P18: 5850 | Q18: 3500 | R18: 1720 | S18: 1720 | T18: 3823.6 | U18: 3823.6 | V18: 3823.6 | W18: 823.6 | X18: 303.59 | Y18: 303.59 | Z18: 303.59 | AA18: 303.59
A19: 1 | C19: 유동리스부채 | E19: 511.42 | F19: 511.42 | G19: 516.3 | H19: 260.97 | I19: 263.75 | J19: 266.57 | K19: 266.57 | L19: 269.42 | M19: 272.3 | N19: 251.84 | Q19: 833.96 | R19: 148.07 | S19: 252.14 | T19: 379.77 | U19: 379.77 | V19: 471.07 | W19: 391.47 | X19: 408.03 | Y19: 313.88 | Z19: 313.88 | AA19: 349.37 | AB19: 359.39
A20: 1 | C20: 리스부채 | E20: 1916.5 | F20: 1916.5 | G20: 1790.46 | H20: 851.99 | I20: 779.53 | J20: 714.64 | K20: 714.64 | L20: 649.06 | M20: 582.78 | N20: 540.69 | O20: 229.21 | P20: 229.21 | Q20: 1487.19 | R20: 276.75 | S20: 430.64 | T20: 673.3 | U20: 673.3 | V20: 786.98 | W20: 630.68 | X20: 617.01 | Y20: 534.86 | Z20: 534.86 | AA20: 667.52 | AB20: 706.52
A21: 1 | C21: 단기금융부채 | E21: 511.42 | F21: 511.42 | G21: 516.3 | H21: 3543.86 | I21: 2957.95 | J21: 266.57 | K21: 266.57 | L21: 269.42 | M21: 272.3 | N21: 251.84 | O21: 9540.93 | P21: 9540.93 | Q21: 833.96 | R21: 148.07 | S21: 2025.22 | T21: 3904.2 | U21: 3904.2 | V21: 4651.62 | W21: 3892.06 | X21: 3393.19 | Y21: 1523.71 | Z21: 1523.71 | AA21: 10957.5 | AB21: 5736.01
A22: 1 | C22: 유동성장기부채 | E22: 3111.11 | F22: 3111.11 | G22: 2777.78 | H22: 9079.13 | I22: 9091.06 | J22: 9344.25 | K22: 9344.25 | L22: 2000 | M22: 6349.16 | N22: 6704.54 | O22: 5220.13 | P22: 5220.13 | Q22: 5661.06 | R22: 245.31 | S22: 984.28 | T22: 4624.32 | U22: 4624.32 | V22: 5180.44 | W22: 5202.76 | X22: 4817.79 | Y22: 5304.72 | Z22: 5304.72 | AA22: 6280.79 | AB22: 6669.78
A23: 1 | C23: 비유동부채 | E23: 1461.79 | F23: 1461.79 | G23: 1379.56 | H23: 797.96 | I23: 568.71 | J23: 448.07 | K23: 448.07 | L23: 379.64 | M23: 310.48 | N23: 354.92 | O23: 386.28 | P23: 386.28 | Q23: 785.15 | R23: 234.68 | S23: 10005.28 | T23: 10373.46 | U23: 10373.46 | V23: 10429.28 | W23: 14323.65 | X23: 14307.64 | Y23: 12817.78 | Z23: 12817.78 | AA23: 12912.7 | AB23: 12968.32
A24: 1 | C24: 확정급여부채 | E24: 41.71 | F24: 41.71 | G24: 105.4 | H24: 206.94 | I24: 52.93 | N24: 66.07 | T24: 97.63 | U24: 97.63 | V24: 111.84 | W24: 126.05 | X24: 140.27 | Y24: 161.45 | Z24: 161.45 | AA24: 180.39 | AB24: 199.33
A25: 1 | C25: 비유동리스부채 | E25: 1405.08 | F25: 1405.08 | G25: 1274.16 | H25: 591.02 | I25: 515.78 | J25: 448.07 | K25: 448.07 | L25: 379.64 | M25: 310.48 | N25: 288.85 | O25: 229.21 | P25: 229.21 | Q25: 653.23 | R25: 128.68 | S25: 178.5 | T25: 293.53 | U25: 293.53 | V25: 315.91 | W25: 239.21 | X25: 208.98 | Y25: 220.98 | Z25: 220.98 | AA25: 318.15 | AB25: 347.13
A26: 1 | C26: 장기금융부채 | E26: 1405.08 | F26: 1405.08 | G26: 1274.16 | H26: 591.02 | I26: 515.78 | J26: 448.07 | K26: 448.07 | L26: 379.64 | M26: 310.48 | N26: 288.85 | O26: 229.21 | P26: 229.21 | Q26: 653.23 | R26: 128.68 | S26: 1843.37 | T26: 2217.09 | U26: 2217.09 | V26: 2258.07 | W26: 1625.33 | X26: -1177.14 | Y26: 220.98 | Z26: 220.98 | AA26: 318.15 | AB26: 347.13
A27: 1 | C27: 기타비유동부채 | E27: 15 | F27: 15 | T27: 58.74 | U27: 58.74 | V27: 59.38
A28: 1 | C28: 부채총계 | E28: 22327.51 | F28: 22327.51 | G28: 20225.34 | H28: 32859.49 | I28: 35857.12 | J28: 43162.43 | K28: 43162.43 | L28: 46671.25 | M28: 41936.45 | N28: 39590 | O28: 27926.98 | P28: 27926.98 | Q28: 30592.49 | R28: 7307.78 | S28: 18663.04 | T28: 28987.42 | U28: 28987.42 | V28: 28685.02 | W28: 29645.74 | X28: 29016.87 | Y28: 26189.21 | Z28: 26189.21 | AA28: 36382.77 | AB28: 31858.43
A29: 1 | C29: 지배주주지분 | E29: 24571.42 | F29: 24571.42 | G29: 22784.56 | H29: 22238.76 | I29: 18966.06 | J29: 11013.49 | K29: 11013.49 | L29: 9942.07 | M29: 13127.19 | N29: 13673.51 | O29: 15629.93 | P29: 15629.93 | Q29: 21563.25 | R29: 35753.19 | S29: 36936.97 | T29: 36831.38 | U29: 36831.38 | V29: 39878.3 | W29: 38448.65 | X29: 37238.51 | Y29: 35004.4 | Z29: 35004.4 | AA29: 41981.27 | AB29: 44575.12
A30: 1 | C30: 자본금 | E30: 35875.4 | F30: 35875.4 | G30: 35875.4 | H30: 35875.4 | I30: 35875.4 | J30: 35875.4 | K30: 35875.4 | L30: 8968.85 | M30: 9389.72 | N30: 9389.72 | O30: 9389.72 | P30: 9389.72 | Q30: 11421.21 | R30: 15074.81 | S30: 15074.81 | T30: 15323.57 | U30: 15323.57 | V30: 16635.9 | W30: 16723.4 | X30: 16723.4 | Y30: 16723.4 | Z30: 16723.4 | AA30: 19820.97 | AB30: 19820.97
A31: 1 | C31: 자본잉여금 | E31: 41176.71 | F31: 41176.71 | G31: 41176.71 | H31: 41176.71 | I31: 41176.71 | J31: 41176.71 | K31: 41176.71 | L31: 41176.71 | M31: 41753.57 | N31: 41753.57 | O31: 41749.49 | P31: 41749.49 | Q31: 47718 | R31: 61845.21 | S31: 61845.21 | T31: 62577 | U31: 62577 | V31: 66255.65 | W31: 66574.31 | X31: 66574.31 | Y31: 66574.31 | Z31: 66574.31 | AA31: 71480.34 | AB31: 71480.34
A32: 1 | C32: 이익잉여금 | E32: -52480.69 | F32: -52480.69 | G32: -54267.55 | H32: -54813.35 | I32: -58086.05 | J32: -66038.62 | K32: -66038.62 | L32: -40203.5 | M32: -38012.03 | N32: -37465.7 | O32: -35509.29 | P32: -35509.29 | Q32: -37575.96 | R32: -41130.31 | S32: -39945.79 | T32: -41034.61 | U32: -41034.61 | V32: -42980.69 | W32: -44818.53 | X32: -46030.73 | Y32: -48256.34 | Z32: -48256.34 | AA32: -49282.79 | AB32: -46764.5
A33: 1 | C33: 자본총계 | E33: 24571.42 | F33: 24571.42 | G33: 22784.56 | H33: 22238.76 | I33: 18966.06 | J33: 11013.49 | K33: 11013.49 | L33: 9942.07 | M33: 13127.19 | N33: 13673.51 | O33: 15629.93 | P33: 15629.93 | Q33: 21563.25 | R33: 35753.19 | S33: 36936.97 | T33: 36831.38 | U33: 36831.38 | V33: 39878.3 | W33: 38448.65 | X33: 37238.51 | Y33: 35004.4 | Z33: 35004.4 | AA33: 41981.27 | AB33: 44575.12
A34: 1 | C34: 부채와자본총계 | E34: 46898.93 | F34: 46898.93 | G34: 43009.9 | H34: 55098.25 | I34: 54823.18 | J34: 54175.92 | K34: 54175.92 | L34: 56613.31 | M34: 55063.64 | N34: 53263.51 | O34: 43556.9 | P34: 43556.9 | Q34: 52155.74 | R34: 43060.96 | S34: 55600.02 | T34: 65818.8 | U34: 65818.8 | V34: 68563.32 | W34: 68094.39 | X34: 66255.38 | Y34: 61193.61 | Z34: 61193.61 | AA34: 78364.04 | AB34: 76433.55
A35: 1 | C35: 총차입금 | E35: 9022.22 | F35: 9022.22 | G35: 8355.56 | H35: 16323.57 | I35: 16802.17 | J35: 18144.25 | K35: 18144.25 | L35: 10500 | M35: 15199.16 | N35: 12089.32 | O35: 11227.2 | P35: 11227.2 | Q35: 9292.98 | R35: 2071.31 | S35: 2885.99 | T35: 16447.92 | U35: 16447.92 | V35: 17004.04 | W35: 18026.36 | X35: 17121.38 | Y35: 17608.31 | Z35: 17608.31 | AA35: 18584.38 | AB35: 18669.78
A36: 1 | C36: 순차입금 | E36: 7748.87 | F36: 7748.87 | G36: 7216.41 | H36: 13469.93 | I36: 16264.46 | J36: 17426.42 | K36: 17426.42 | L36: 10078.61 | M36: 13697.06 | N36: 10699.11 | O36: 10020.93 | P36: 10020.93 | Q36: -3620.11 | R36: -14834.72 | S36: -6905.27 | T36: 5121.11 | U36: 5121.11 | V36: 8886.15 | W36: 11820.92 | X36: 14167.07 | Y36: 14226.56 | Z36: 14226.56 | AA36: -4020.03 | AB36: 17920.21
A37: 1 | C37: 이자발생자산 | E37: 1302.11 | F37: 1302.11 | G37: 1173.91 | H37: 2893.57 | I37: 537.71 | J37: 876.41 | K37: 876.41 | L37: 514.52 | M37: 1550.8 | N37: 1390.21 | O37: 1443.75 | P37: 1443.75 | Q37: 13259.13 | R37: 16906.03 | S37: 14411.25 | T37: 14000.53 | U37: 14000.53 | V37: 13491.61 | W37: 11724.45 | X37: 7772.71 | Y37: 6271.46 | Z37: 6271.46 | AA37: 25480.61 | AB37: 2870.07
A38: 1 | C38: 장기차입금 | E38: 1111.11 | F38: 1111.11 | G38: 777.78 | H38: 444.44 | I38: 111.11 | J38: 2000 | K38: 2000 | L38: 2000 | M38: 2000 | N38: 284.78 | O38: 157.07 | P38: 157.07 | Q38: 131.92 | R38: 106 | S38: 181.71 | T38: 8000 | U38: 8000 | V38: 8000 | W38: 12000 | X38: 12000 | Y38: 12000 | Z38: 12000 | AA38: 12000 | AB38: 12000
A39: 1 | C39: 단기금융상품 | H39: 2000 | AB39: 6
A40: 1 | C40: 단기금융자산 | H40: 2000 | AB40: 6
A41: 1 | C41: 단기파생상품부채 | H41: 3282.89 | I41: 2694.2 | O41: 9540.93 | P41: 9540.93 | S41: 1773.08
A42: 1 | C42: 기타유동자산 | M42: 11082.11 | N42: 13462.67 | O42: 6358.86 | P42: 6358.86 | Q42: 3964.07 | R42: 4008.23 | S42: 6648.48 | T42: 1055.08 | U42: 1055.08 | V42: 2116.15 | W42: 3163.79 | X42: 3556.22 | Y42: 1156.93 | Z42: 1156.93 | AA42: 1201.39 | AB42: 1409.27
A43: 1 | C43: 기타유동부채 | M43: 10235.16 | N43: 10173.55 | O43: 1173.49 | P43: 1173.49 | R43: 506.82 | S43: 618.95 | T43: 490.2 | U43: 490.2 | V43: 322.48 | W43: 318.14 | X43: 747.74 | Y43: 657.12 | Z43: 657.12 | AA43: 615.25 | AB43: 676.76
A44: 1 | C44: 기타자본 | M44: -4.08 | N44: -4.08 | R44: -36.53 | S44: -37.25 | T44: -34.57 | U44: -34.57 | V44: -32.56 | W44: -30.53 | X44: -28.47 | Y44: -36.97 | Z44: -36.97 | AA44: -37.25 | AB44: -37.25
A45: 1 | C45: 당기법인세부채(미지급법인세) | O45: 151.08 | P45: 151.08 | Q45: 198.04 | V45: 6.48 | X45: 0.03 | Y45: 232.06 | Z45: 232.06 | AA45: 160.16 | AB45: 135.66
A46: 1 | C46: 단기투자자산(공정가치) | R46: 159.16 | S46: 424.79 | T46: 439.75 | U46: 439.75 | V46: 433.33 | W46: 463.14 | X46: 463.87 | AA46: 179.58 | AB46: 0
A47: 1 | C47: 사용권자산 | R47: 299.71 | S47: 461.03 | T47: 738.71 | U47: 738.71 | V47: 848.95 | W47: 676.41 | X47: 648.24 | Y47: 551.45 | Z47: 551.45 | AA47: 675.19 | AB47: 708.8
A48: 1 | C48: 기타비유동자산 | R48: 447.12 | S48: 461.03 | T48: 1067.97 | U48: 1067.97 | V48: 962.14 | W48: 1341.97 | X48: 1256.78 | Y48: 1100.28 | Z48: 1100.28 | AA48: 1113.14 | AB48: 3941.97
A49: 1 | C49: 종속기업및관계기업투자 | S49: 0.57 | AB49: 9685.57
A50: 1 | C50: 장기매입채무및기타채무 | S50: 8080.05
A51: 1 | C51: 장기파생상품부채 | S51: 1664.87
A52: 1 | C52: 기타유동금융부채 | T52: 3524.43 | U52: 3524.43 | V52: 4180.55 | W52: 3500.59 | X52: 2985.16 | Y52: 1209.83 | Z52: 1209.83 | AA52: 10608.13 | AB52: 5376.62
A53: 1 | C53: 기타비유동금융부채 | T53: 1923.56 | U53: 1923.56 | V53: 1942.16 | W53: 1386.12 | X53: -1386.12
A54: 1 | C54: 이연법인세부채 | Y54: 435.35 | Z54: 435.35 | AA54: 414.15 | AB54: 421.86
A55: 1 | C55: 기타포괄이익누계액 | AB55: 75.56
A56: 1 | C56: 매출액(수익) | E56: 8501.73 | G56: 14734.67 | H56: 18706.69 | I56: 17176.15 | J56: 23811.88 | K56: 74429.39 | L56: 21526.67 | M56: 23408.9 | N56: 23294.52 | O56: 18121.3 | P56: 86351.39 | Q56: 15367.8 | R56: 5503.84 | S56: 6059.55 | T56: 8093.04 | U56: 35024.23 | V56: 9021.13 | W56: 11208.93 | X56: 12040.3 | Y56: 7177.01 | Z56: 39447.37 | AA56: 10401.23 | AB56: 9464.8
A57: 1 | C57: 매출원가 | E57: 11253.74 | G57: 15572.74 | H57: 19449.38 | I57: 19874.92 | J57: 30638.83 | K57: 85535.87 | L57: 20490.95 | M57: 16524.19 | N57: 20829.35 | O57: 14128.64 | P57: 71973.13 | Q57: 11803.12 | R57: 3991.34 | S57: 6053.69 | T57: 7555.47 | U57: 29403.62 | V57: 8351.78 | W57: 10159.19 | X57: 10694.91 | Y57: 5596.68 | Z57: 34802.56 | AA57: 8229.17 | AB57: 8125.4
A58: 1 | C58: 매출총이익 | E58: -2752.01 | G58: -838.06 | H58: -742.69 | I58: -2698.77 | J58: -6826.94 | K58: -11106.46 | L58: 1035.72 | M58: 6884.71 | N58: 2465.16 | O58: 3992.68 | P58: 14378.27 | Q58: 3564.68 | R58: 1512.5 | S58: 5.86 | T58: 537.56 | U58: 5620.6 | V58: 669.35 | W58: 1049.74 | X58: 1345.4 | Y58: 1580.33 | Z58: 4644.82 | AA58: 2172.06 | AB58: 1339.4
A59: 1 | C59: 판관비 | E59: 816.87 | G59: 855.68 | H59: 860.66 | I59: 822.04 | J59: 907.22 | K59: 3445.6 | L59: 830.85 | M59: 832.03 | N59: 808.7 | O59: 1042.66 | P59: 3514.24 | Q59: 1023.17 | R59: 864.87 | S59: 1101.73 | T59: 1559.26 | U59: 4549.03 | V59: 2425.54 | W59: 2525.66 | X59: 2357.89 | Y59: 1956.29 | Z59: 9265.38 | AA59: 2966.35 | AB59: 2144.91
A60: 1 | C60: 영업이익 | E60: -3568.88 | G60: -1693.75 | H60: -1603.36 | I60: -3520.82 | J60: -7734.16 | K60: -14552.09 | L60: 204.86 | M60: 6052.68 | N60: 1656.47 | O60: 2950.02 | P60: 10864.03 | Q60: 2541.5 | R60: 647.63 | S60: -1095.87 | T60: -1021.68 | U60: 1071.58 | V60: -1756.19 | W60: -1475.91 | X60: -1012.49 | Y60: -375.95 | Z60: -4620.54 | AA60: -794.29 | AB60: -805.51
A61: 1 | C61: 금융수익 | E61: 49.54 | G61: 63.72 | H61: 1518.18 | I61: 786.16 | J61: 131.95 | K61: 2500.01 | L61: 249.96 | M61: 120.15 | N61: 124.3 | O61: 90.36 | P61: 584.77 | Q61: 173.87 | R61: 61.67 | S61: 74.11 | T61: 196.12 | U61: 505.77 | V61: 95.16 | W61: 753.74 | X61: 110.19 | Y61: 3246.21 | Z61: 4205.3 | AA61: 207 | AB61: 5529.13
A62: 1 | C62: 금융비용 | E62: 161.76 | G62: 100.45 | H62: 469.14 | I62: 541.35 | J62: 651.15 | K62: 1762.09 | L62: 1532.26 | M62: 3910 | N62: 1236.99 | O62: 381.12 | P62: 7060.37 | Q62: 5099.82 | R62: -47.96 | S62: 410.29 | T62: 92.46 | U62: 5554.61 | V62: 363.91 | W62: 530.97 | X62: 309.94 | Y62: 2744.96 | Z62: 3949.78 | AA62: 530.73 | AB62: 1389.13
A63: 1 | C63: 기타영업외수익 | E63: 50.5 | G63: 4.29 | H63: 10.02 | I63: 2.46 | J63: 0.01 | K63: 16.78 | L63: 6.05 | M63: 57.68 | N63: 8.41 | O63: 0.01 | P63: 72.15 | Q63: 438 | R63: -88.44 | S63: 1060.51 | T63: 257.86 | U63: 1667.93 | V63: 56.83 | W63: 32.62 | X63: 62.59 | Y63: 5.34 | Z63: 157.38 | AA63: 94.57 | AB63: 108.17
A64: 1 | C64: 기타영업외비용 | E64: 1182.2 | G64: 60.67 | H64: 1.5 | I64: 0 | J64: 11.3 | K64: 73.47 | L64: 0.03 | M64: 129.04 | N64: -24.49 | O64: 524.24 | P64: 628.82 | Q64: 0 | R64: 86.59 | S64: -50.72 | T64: 138.98 | U64: 174.85 | V64: 0.05 | W64: 617.32 | X64: 62.54 | Y64: 1704.63 | Z64: 2384.54 | AA64: 4.67 | AB64: 156.73
A65: 1 | C65: 법인세비용차감전계속사업이익 | E65: -4812.8 | G65: -1786.86 | H65: -545.8 | I65: -3273.54 | J65: -8264.66 | K65: -13870.86 | L65: -1071.43 | M65: 2191.47 | N65: 576.67 | O65: 2135.01 | P65: 3831.72 | Q65: -1946.44 | R65: 582.23 | S65: -320.82 | T65: -799.15 | U65: -2484.18 | V65: -1968.17 | W65: -1837.85 | X65: -1212.2 | Y65: -1574.01 | Z65: -6592.23 | AA65: -1028.12 | AB65: 2523.54
A66: 1 | C66: 당기순이익 | E66: -4812.8 | G66: -1786.86 | H66: -545.8 | I66: -3273.54 | J66: -8264.66 | K66: -13870.86 | L66: -1071.43 | M66: 2191.47 | N66: 546.32 | O66: 2013.5 | P66: 3679.86 | Q66: -2066.68 | R66: -3669.72 | S66: 1183.51 | T66: -694.41 | U66: -5247.3 | V66: -1946.08 | W66: -1837.85 | X66: -1212.2 | Y66: -2259.9 | Z66: -7256.03 | AA66: -1026.45 | AB66: 2518.29
A67: 1 | C67: (지배주주지분)당기순이익 | E67: -4812.8 | G67: -1786.86 | H67: -545.8 | I67: -3273.54 | J67: -8264.66 | K67: -13870.86 | L67: -1071.43 | M67: 2191.47 | N67: 546.32 | O67: 2013.5 | P67: 3679.86 | Q67: -2066.68 | R67: -3669.72 | S67: 1183.51 | T67: -694.41 | U67: -5247.3 | V67: -1946.08 | W67: -1837.85 | X67: -1212.2 | Y67: -2259.9 | Z67: -7256.03 | AA67: -1026.45 | AB67: 2518.29
... A70: 1 | C70: 계속사업이익 | E70: -4812.8 | G70: -1786.86 | H70: -545.8 | I70: -3273.54 | J70: -8264.66 | K70: -13870.86 | L70: -1071.43 | M70: 2191.47 | N70: 546.32 | O70: 2013.5 | P70: 3679.86 | Q70: -2066.68 | R70: 577.93 | S70: -321.53 | T70: -608.73 | U70: -2419.01 | V70: -1946.08 | W70: -1837.85 | X70: -1212.2 | Y70: -2259.9 | Z70: -7256.03 | AA70: -1026.45 | AB70: 2518.29
A71: 1 | C71: 총포괄손익 | E71: -4802.66 | G71: -1786.86 | H71: -545.8 | I71: -3273.54 | J71: -7952.57 | K71: -13558.77 | M71: 2191.47 | N71: 546.32 | O71: 1956.41 | Q71: -2066.68 | R71: -3669.72 | S71: 1183.51 | AA71: -1026.45 | AB71: 2593.84
A72: 1 | C72: 이자수익 | G72: 48.42 | H72: 22.19 | I72: 17.23 | J72: 205.49 | K72: 293.33 | L72: 85.92 | M72: 0.92 | N72: 1.22 | O72: 263.79 | P72: 351.85 | Q72: 90.32 | V72: 47.59 | X72: 124.53 | Y72: 155.04 | AA72: 40.98
A73: 1 | C73: 이자비용 | G73: 89.27 | H73: 339.61 | I73: 45.94 | J73: 1051.46 | K73: 1526.28 | L73: 362.98 | M73: 351.84 | N73: -179.5 | O73: 1629.33 | P73: 2164.65 | Q73: 561.97 | V73: 253.5 | X73: 827.37 | Y73: 1311.31 | AA73: 412.19
A74: 1 | C74: 외환차익 | G74: 11.1 | H74: 33.81 | I74: 39.24 | J74: 58.42 | K74: 142.57 | L74: 157.92 | M74: -129.67 | N74: 7.12 | O74: 197.54 | P74: 232.91 | Q74: 62.37 | V74: 31.18 | X74: 50.82 | Y74: 107.39 | AA74: 38.43
A75: 1 | C75: 외환차손 | G75: 1.21 | H75: 10.96 | I75: -6.78 | J75: 177.86 | K75: 183.25 | L75: 111.23 | M75: -85.54 | N75: -8.11 | O75: 210.43 | P75: 228.01 | Q75: 10.37 | V75: 70.36 | X75: 183.13 | Y75: 185.9 | AA75: 73.26
A76: 1 | C76: 외화환산이익 | G76: 4.19 | H76: 4.56 | I76: 16.73 | J76: -25.06 | K76: 0.42 | L76: 6.11 | M76: -1.05 | N76: -4.19 | Q76: 21.18 | V76: 16.39 | X76: 64.89 | Y76: 53.69 | AA76: 122.37
A77: 1 | C77: 외화환산손실 | G77: 9.96 | H77: 17.3 | I77: 32.9 | J77: -9.41 | K77: 50.75 | L77: 15.4 | M77: -11.73 | N77: 12.83 | O77: 24.87 | P77: 41.37 | Q77: 32.78 | V77: 33.64 | X77: 90.3 | Y77: 61.78 | AA77: 45.28
A78: 1 | C78: 이자손익 | G78: -40.85 | H78: -317.42 | I78: -28.71 | J78: -845.97 | K78: -1232.95 | L78: -277.06 | M78: -350.92 | N78: 180.72 | O78: -1365.54 | P78: -1812.8 | Q78: -471.65 | V78: -205.91 | X78: -702.84 | Y78: -1156.27 | AA78: -371.21
A79: 1 | C79: 파생상품이익 | I79: -805.21 | J79: 1475 | X79: 507
A80: 1 | C80: 법인세비용 | N80: 30.35 | O80: 121.51 | Q80: 120.24 | R80: 4.3 | S80: 0.71 | T80: -190.42 | U80: -65.17 | V80: -22.09 | Y80: 685.9 | AA80: -1.67 | AB80: 5.25
A81: 1 | C81: 파생상품손실 | N81: -2588.74 | O81: 3006.61 | X81: 39.23
A82: 1 | C82: 중단사업이익 | R82: -4247.65 | S82: 1505.04 | T82: -85.69
A83: 1 | C83: 배당금수익 | X83: 3.2
A84: 1 | C84: 종속기업,공동지배기업및관계기업관련손익 | AB84: -762.39
A85: 1 | C85: 지분법관련손익 | AB85: -762.39
A86: 1 | C86: 영업활동으로인한현금흐름 | E86: 2337.26 | G86: -5389.2 | H86: -5213.64 | I86: -1901.21 | J86: 2138.13 | K86: -10365.92 | L86: 346.5 | M86: 720.85 | N86: 1769.88 | O86: 924.79 | P86: 3762.02 | Q86: 5058.97 | R86: 9.85 | S86: -1599.88 | T86: 3119.97 | U86: 6588.91 | V86: -1714.89 | W86: -1711.72 | X86: -1313.6 | Y86: 1072.91 | Z86: -3667.3 | AA86: 154.59 | AB86: -767.73
A87: 1 | C87: 이자수취(CF) | E87: 3.11 | G87: 6.88 | H87: 27.49 | I87: 5.02 | J87: 1.54 | K87: 40.93 | L87: 0.1 | M87: 0.11 | N87: 0.06 | O87: 0.16 | P87: 0.43 | Q87: 0.09 | R87: 13.86 | S87: 65.19 | T87: 64.34 | U87: 143.48 | V87: 39.79 | W87: 29.67 | X87: 25.52 | Y87: 31.95 | Z87: 126.93 | AA87: 15.78 | AB87: 17.47
A88: 1 | C88: 이자지급(CF) | E88: -72.56 | G88: -70.7 | H88: -75.36 | I88: -101.9 | J88: -448.38 | K88: -696.34 | L88: -104.98 | M88: -120.07 | Q88: -98.4
A89: 1 | C89: 법인세납부(CF) | E89: -0.48 | G89: -1.06 | H89: 3.1 | I89: -0.77 | J89: -0.24 | K89: 1.03 | L89: -0.01 | M89: 5.05 | N89: -0.23 | O89: -0.03 | P89: 4.78 | Q89: -73.27 | R89: 4.91 | S89: -17.97 | T89: -21.44 | U89: -107.77 | V89: 29.49 | W89: 16.63 | X89: -19.26 | Y89: -3.69 | Z89: 23.17 | AA89: -93.3 | AB89: -8.69
A90: 1 | C90: 투자활동으로인한현금흐름 | E90: -4210.31 | G90: 5745.3 | H90: -7593.11 | I90: 1192.14 | J90: -968.06 | K90: -1623.73 | L90: -269.94 | M90: 188.97 | N90: -45.41 | O90: -18.56 | P90: -144.94 | Q90: 1088.41 | R90: 5832.28 | S90: -17365.49 | T90: -1618.66 | U90: -12063.46 | V90: -7361.92 | W90: -1090.71 | X90: -1014.16 | Y90: -528.79 | Z90: -9995.58 | AA90: 1024.76 | AB90: -20627.95
A91: 1 | C91: 유형자산의감소 | E91: 445.21 | G91: 1.79 | H91: 0 | I91: 0 | J91: 0 | K91: 1.79 | N91: 0 | O91: 0 | Q91: 1715.34 | R91: 141.5 | S91: 68.23 | T91: 764.85 | U91: 2689.92 | V91: 801.3 | X91: 36.37
A92: 1 | C92: 유형자산의증가 | E92: 2149.52 | G92: 1387.64 | H92: 1587.12 | I92: 839.04 | J92: 958.56 | K92: 4772.36 | L92: 256.3 | M92: 26.45 | N92: 45.42 | O92: 18.56 | P92: 346.73 | Q92: 26.93 | R92: 356.42 | S92: 16848.55 | T92: 3604.34 | U92: 20836.24 | V92: 2057.85 | W92: 1751.09 | X92: 58.98 | Y92: 177.06 | Z92: 4044.98 | AA92: 95.67 | AB92: 123.02
A93: 1 | C93: CAPEX | E93: 2149.52 | G93: 1407.84 | H93: 1587.12 | I93: 848.64 | J93: 958.56 | K93: 4802.16 | L93: 259.94 | M93: 26.45 | N93: 45.42 | O93: 18.56 | P93: 350.37 | Q93: 26.93 | R93: 356.42 | S93: 16848.55 | T93: 3664.82 | U93: 20896.72 | V93: 2148.81 | W93: 1751.09 | X93: 58.98 | Y93: 177.06 | Z93: 4135.94 | AA93: 95.67 | AB93: 227.82
A94: 1 | C94: 재무활동으로인한현금흐름 | E94: -468.87 | G94: -492.33 | H94: 12522.67 | I94: 393.68 | J94: -984.11 | K94: 11439.91 | L94: -372.99 | M94: 170.65 | N94: -1843.32 | O94: -1059.02 | P94: -3104.68 | Q94: 5550.3 | R94: -1859.83 | S94: 11910.43 | T94: -10.27 | U94: 15590.63 | V94: 5864.19 | W94: 893.83 | X94: -932.96 | Y94: -107.24 | Z94: 5717.82 | AA94: 17989.06 | AB94: -410.9
A95: 1 | C95: 단기차입금의증가 | E95: 0 | I95: 2800 | J95: 0 | N95: 0 | O95: 0 | Y95: 0
A96: 1 | C96: 장기차입금의증가 | E96: 0 | T96: 0 | X96: 0 | Y96: 0
A97: 1 | C97: 장기차입금의감소 | E97: 0
A98: 1 | C98: 유동성장기부채의감소 | E98: 333.34 | G98: 333.33 | H98: 333.34 | I98: 333.33 | J98: 111.11 | K98: 1111.11 | O98: 30.93 | Q98: 23.61 | R98: 23.99 | S98: 24.54 | T98: 181.71 | U98: 253.85
A99: 1 | C99: 현금및현금성자산의증감 | E99: -2429.19 | G99: -134.19 | H99: -285.52 | I99: -315.93 | J99: 180.12 | K99: -555.52 | L99: -296.43 | M99: 1080.71 | N99: -111.9 | O99: -183.94 | P99: 488.44 | Q99: 11706.82 | R99: 3973.16 | S99: -7054.94 | T99: 1495.51 | U99: 10120.55 | V99: -3208.93 | W99: -1912.44 | X99: -3251.13 | Y99: 427.44 | Z99: -7945.06 | AA99: 19222.66 | AB99: -21860.84
A100: 1 | C100: 기말현금및현금성자산 | E100: -2429.18 | G100: 1139.15 | H100: -285.51 | I100: -315.93 | J100: 180.12 | K100: 717.83 | L100: 421.39 | M100: 1080.71 | N100: -111.89 | O100: -183.94 | P100: 1206.27 | Q100: 12913.09 | R100: 3992.94 | S100: -7114.77 | T100: 1535.55 | U100: 11326.81 | V100: 8117.89 | W100: -1912.45 | X100: -3251.13 | Y100: 427.44 | Z100: 3381.75 | AA100: 22604.41 | AB100: -21860.84
A101: 1 | C101: 무형자산의증가 | G101: 20.2 | H101: 0 | I101: 9.6 | J101: 0 | K101: 29.8 | L101: 3.64 | M101: 0 | N101: 0 | O101: 0 | P101: 3.64 | V101: 90.96 | W101: 0 | X101: 0 | Y101: 0 | Z101: 90.96
A102: 1 | C102: 단기차입금의감소 | J102: 800 | L102: 300 | M102: 0 | N102: 1750 | O102: 950 | P102: 3000 | Q102: 2350 | R102: 1780 | S102: 8000 | X102: 708.98 | Y102: 0
...

Sheet BS별도
B1: (백만원) | C1: 이름: BS별도H | E1: 4Q21 | F1: 2021 | G1: 1Q22 | H1: 2Q22 | I1: 3Q22 | J1: 4Q22 | K1: 2022 | L1: 1Q23 | M1: 2Q23 | N1: 3Q23 | O1: 4Q23 | P1: 2023 | Q1: 1Q24 | R1: 2Q24 | S1: 3Q24 | T1: 4Q24 | U1: 2024 | V1: 1Q25 | W1: 2Q25 | X1: 3Q25 | Y1: 4Q25 | Z1: 2025 | AA1: 1Q26 | AB1: 2Q26 | AC1: 3Q26 | AD1: 4Q26 | AE1: 2026 | AF1: 1Q27 | AG1: 2Q27 | AH1: 3Q27 | AI1: 4Q27 | AJ1: 2027 | AK1: 1Q28 | AL1: 2Q28 | AM1: 3Q28 | AN1: 4Q28 | AO1: 2028
B2: 별도 | D2: fin json(kship_fin.py)
B3: KS인더스트리(별) | C3: UPDATE: 26-10-11 | E3: 1 | F3: 2 | G3: 3 | H3: 4 | I3: 5 | J3: 6 | K3: 7 | L3: 8 | M3: 9 | N3: 10 | O3: 11 | P3: 12 | Q3: 13 | R3: 14 | S3: 15 | T3: 16 | U3: 17 | V3: 18 | W3: 19 | X3: 20 | Y3: 21 | Z3: 22 | AA3: 23 | AB3: 24 | AC3: 25 | AD3: 26 | AE3: 27 | AF3: 28 | AG3: 29 | AH3: 30 | AI3: 31 | AJ3: 32 | AK3: 33 | AL3: 34 | AM3: 35 | AN3: 36 | AO3: 37
B4: Account Code | C4: AccountNAME | E4: 2021.12 | F4: 2021.12A | G4: 2022.03 | H4: 2022.06 | I4: 2022.09 | J4: 2022.12 | K4: 2022.12A | L4: 2023.03 | M4: 2023.06 | N4: 2023.09 | O4: 2023.12 | P4: 2023.12A | Q4: 2024.03 | R4: 2024.06 | S4: 2024.09 | T4: 2024.12 | U4: 2024.12A | V4: 2025.03 | W4: 2025.06 | X4: 2025.09 | Y4: 2025.12 | Z4: 2025.12A | AA4: 2026.03 | AB4: 2026.06 | AC4: 2026.09 | AD4: 2026.12 | AE4: 2026.12A | AF4: 2027.03 | AG4: 2027.06 | AH4: 2027.09 | AI4: 2027.12 | AJ4: 2027.12A | AK4: 2028.03 | AL4: 2028.06 | AM4: 2028.09 | AN4: 2028.12 | AO4: 2028.12A
A5: 1 | C5: 유동자산 | E5: 26350.64 | F5: 26350.64 | G5: 21048.11 | H5: 28795.41 | I5: 28166.64 | J5: 26872.71 | K5: 26872.71 | L5: 29612.76 | M5: 28886.55 | N5: 27561.3 | O5: 18123.06 | P5: 18123.06 | Q5: 35868.79 | R5: 35419.29 | S5: 26472.57 | T5: 22896.7 | U5: 22896.7 | V5: 18857.18 | W5: 18489.99 | X5: 17218.14 | Y5: 14439.05 | Z5: 14439.05 | AA5: 32220.18 | AB5: 23080.42
A6: 1 | C6: 현금및현금성자산 | E6: 1252.26 | F6: 1252.26 | G6: 1122.42 | H6: 834.63 | I6: 523.27 | J6: 703.39 | K6: 703.39 | L6: 406.99 | M6: 1488.37 | N6: 1375.67 | O6: 1193.21 | P6: 1193.21 | Q6: 12899.94 | R6: 16794.03 | S6: 9679.77 | T6: 10650.47 | U6: 10650.47 | V6: 7222.99 | W6: 5472.07 | X6: 2298.13 | Y6: 2456.36 | Z6: 2456.36 | AA6: 21379.59 | AB6: 479.77
A7: 1 | C7: 매출채권및기타채권 | E7: 2827.58 | F7: 2827.58 | G7: 3605.37 | H7: 6684.51 | I7: 8067.23 | J7: 8106.44 | K7: 8106.44 | L7: 7403.87 | M7: 6850.05 | N7: 5727.67 | O7: 4999.19 | P7: 4999.19 | Q7: 13006.1 | R7: 7705.42 | S7: 3010.83 | T7: 4339.23 | U7: 4339.23 | V7: 2022.44 | W7: 3601.15 | X7: 4645.49 | Y7: 4600.86 | Z7: 4600.86 | AA7: 3096.41 | AB7: 13756.25
A8: 1 | C8: 재고자산 | E8: 12149.58 | F8: 12149.58 | G8: 9706.18 | H8: 8440.08 | I8: 12617.06 | J8: 8553.1 | K8: 8553.1 | L8: 9161.58 | M8: 9465.48 | N8: 6995.26 | O8: 5571.81 | P8: 5571.81 | Q8: 5998.67 | R8: 6752.09 | S8: 6694.7 | T8: 6537.24 | U8: 6537.24 | V8: 6841.31 | W8: 6215.69 | X8: 6616.43 | Y8: 6346.35 | Z8: 6346.35 | AA8: 6672.22 | AB8: 7766.79
A9: 1 | C9: 당기법인세자산(선급법인세) | E9: 1.03 | F9: 1.03 | G9: 2.09 | H9: 4.56 | I9: 5.33 | J9: 5.57 | K9: 5.57 | L9: 5.58 | M9: 0.53 | N9: 0.03 | R9: 0.37 | S9: 13.99 | T9: 27.41 | U9: 27.41 | V9: 33.09 | W9: 9.98 | X9: 13.63 | Y9: 15.5 | Z9: 15.5 | AA9: 17.37 | AB9: 4.02
A10: 1 | C10: 비유동자산 | E10: 20543.74 | F10: 20543.74 | G10: 21961.53 | H10: 26299.28 | I10: 26657.65 | J10: 27303.21 | K10: 27303.21 | L10: 27000.56 | M10: 26177.09 | N10: 25701.34 | O10: 25433.84 | P10: 25433.84 | Q10: 16286.86 | R10: 7641.67 | S10: 29127.44 | T10: 40756.97 | U10: 40756.97 | V10: 47842.35 | W10: 46995.92 | X10: 45986.97 | Y10: 43767.83 | Z10: 43767.83 | AA10: 43473.64 | AB10: 52017.73
A11: 1 | C11: 장기금융자산 | E11: 28.76 | F11: 28.76 | G11: 34.76 | H11: 39.93 | J11: 158.58 | K11: 158.58 | L11: 93.13 | M11: 48.7 | O11: 237.48 | P11: 237.48 | Q11: 346.04 | S11: 4619.99 | T11: 2673.72 | U11: 2673.72 | V11: 5373.72 | W11: 5519.01 | X11: 4819.01 | Y11: 2876.81 | Z11: 2876.81 | AA11: 2876.2 | AB11: 2120.5
A12: 1 | C12: 투자자산 | E12: 50.9 | F12: 50.9 | G12: 56.9 | H12: 55.48 | I12: 15.55 | J12: 173.01 | K12: 173.01 | L12: 107.56 | M12: 62.47 | N12: 13.77 | O12: 250.64 | P12: 250.64 | Q12: 359.2 | R12: 112.13 | S12: 4732.12 | T12: 11593.76 | U12: 11593.76 | V12: 14293.76 | W12: 14342.8 | X12: 13642.8 | Y12: 11696.85 | Z12: 11696.85 | AA12: 11696.24 | AB12: 21214.77
A13: 1 | C13: 종속기업및관계기업투자 | E13: 22.14 | F13: 22.14 | G13: 22.14 | H13: 15.55 | I13: 15.55 | J13: 14.43 | K13: 14.43 | L13: 14.43 | M13: 13.77 | N13: 13.77 | O13: 13.16 | P13: 13.16 | Q13: 13.16 | R13: 112.13 | S13: 112.13 | T13: 8920.04 | U13: 8920.04 | V13: 8920.04 | W13: 8823.79 | X13: 8823.79 | Y13: 8820.04 | Z13: 8820.04 | AA13: 8820.04 | AB13: 19094.27
A14: 1 | C14: 유형자산 | E14: 16058.32 | F14: 16058.32 | G14: 17412.18 | H14: 18306.58 | I14: 18618.41 | J14: 18895.27 | K14: 18895.27 | L14: 18572.44 | M14: 17721.05 | N14: 17219.4 | O14: 16610.9 | P14: 16610.9 | Q14: 15239.23 | R14: 6160.38 | S14: 22787.77 | T14: 26976.29 | U14: 26976.29 | V14: 28160.77 | W14: 28308.55 | X14: 28068.18 | Y14: 27936.96 | Z14: 27936.96 | AA14: 27650.41 | AB14: 26569.1
A15: 1 | C15: 무형자산 | E15: 67.68 | F15: 67.68 | G15: 82.58 | H15: 76.6 | I15: 80.06 | J15: 196.89 | K15: 196.89 | L15: 186.69 | M15: 172.97 | N15: 161.69 | O15: 148.67 | P15: 148.67 | Q15: 135.66 | R15: 122.65 | S15: 109.64 | T15: 157.09 | U15: 157.09 | V15: 234.98 | W15: 219.09 | X15: 203.19 | Y15: 187.3 | Z15: 187.3 | AA15: 171.41 | AB15: 410.57
A16: 1 | C16: 자산총계 | E16: 46894.38 | F16: 46894.38 | G16: 43009.64 | H16: 55094.69 | I16: 54824.29 | J16: 54175.92 | K16: 54175.92 | L16: 56613.31 | M16: 55063.64 | N16: 53262.64 | O16: 43556.9 | P16: 43556.9 | Q16: 52155.65 | R16: 43060.96 | S16: 55600.02 | T16: 63653.67 | U16: 63653.67 | V16: 66699.53 | W16: 65485.9 | X16: 63205.11 | Y16: 58206.88 | Z16: 58206.88 | AA16: 75693.82 | AB16: 75098.14
A17: 1 | C17: 유동부채 | E17: 20865.54 | F17: 20865.54 | G17: 18845.6 | H17: 32061.35 | I17: 35288.41 | J17: 42714.35 | K17: 42714.35 | L17: 46290.94 | M17: 41625.97 | N17: 39233.59 | O17: 27540.69 | P17: 27540.69 | Q17: 29806.24 | R17: 7073.1 | S17: 8657.76 | T17: 16928.97 | U17: 16928.97 | V17: 16806.95 | W17: 13210.27 | X17: 12597.99 | Y17: 11454.54 | Z17: 11454.54 | AA17: 22027.37 | AB17: 18121.01
A18: 1 | C18: 매입채무및기타채무 | E18: 8159.73 | F18: 8159.73 | G18: 7342.42 | H18: 9583.38 | I18: 10071.16 | J18: 10939.39 | K18: 10939.39 | L18: 23479.72 | M18: 8796.3 | N18: 7213.41 | O18: 5385.93 | P18: 5385.93 | Q18: 5031.62 | R18: 4145.25 | S18: 3309.31 | T18: 4965.52 | U18: 4965.52 | V18: 3707.41 | W18: 3862.23 | X18: 3824.53 | Y18: 3411.3 | Z18: 3411.3 | AA18: 3595.75 | AB18: 4440.36
A19: 1 | C19: 단기차입금 | E19: 4800 | F19: 4800 | G19: 4800 | H19: 6800 | I19: 7600 | J19: 6800 | K19: 6800 | L19: 6500 | M19: 6850 | N19: 5100 | O19: 5850 | P19: 5850 | Q19: 3500 | R19: 1720 | S19: 1720 | T19: 3000 | U19: 3000 | V19: 3000
A20: 1 | C20: 유동리스부채 | E20: 511.42 | F20: 511.42 | G20: 516.3 | H20: 260.97 | I20: 263.75 | J20: 266.57 | K20: 266.57 | L20: 269.42 | M20: 272.3 | N20: 251.84 | Q20: 833.96 | R20: 148.07 | S20: 252.14 | T20: 338.33 | U20: 338.33 | V20: 427.44 | W20: 352.81 | X20: 374.46 | Y20: 285.53 | Z20: 285.53 | AA20: 305.48 | AB20: 320.58
A21: 1 | C21: 리스부채 | E21: 1916.5 | F21: 1916.5 | G21: 1790.46 | H21: 851.99 | I21: 779.53 | J21: 714.64 | K21: 714.64 | L21: 649.06 | M21: 582.78 | N21: 540.69 | O21: 229.21 | P21: 229.21 | Q21: 1487.19 | R21: 276.75 | S21: 430.64 | T21: 586.84 | U21: 586.84 | V21: 693.54 | W21: 546.68 | X21: 542.72 | Y21: 470.53 | Z21: 470.53 | AA21: 592.54 | AB21: 641.64
A22: 1 | C22: 단기금융부채 | E22: 511.42 | F22: 511.42 | G22: 516.3 | H22: 3543.86 | I22: 2957.95 | J22: 266.57 | K22: 266.57 | L22: 269.42 | M22: 272.3 | N22: 251.84 | O22: 9540.93 | P22: 9540.93 | Q22: 833.96 | R22: 455.72 | S22: 2025.22 | T22: 3862.76 | U22: 3862.76 | V22: 4607.99 | W22: 3853.4 | X22: 3359.62 | Y22: 1495.36 | Z22: 1495.36 | AA22: 10913.61 | AB22: 5697.2
A23: 1 | C23: 유동성장기부채 | E23: 3111.11 | F23: 3111.11 | G23: 2777.78 | H23: 9079.13 | I23: 9091.06 | J23: 9344.25 | K23: 9344.25 | L23: 2000 | M23: 6349.16 | N23: 6704.54 | O23: 5220.13 | P23: 5220.13 | Q23: 5661.06 | R23: 245.31 | S23: 984.28 | T23: 4624.32 | U23: 4624.32 | V23: 5180.44 | W23: 5202.76 | X23: 4817.79 | Y23: 5304.72 | Z23: 5304.72 | AA23: 6280.79 | AB23: 6669.78
A24: 1 | C24: 비유동부채 | E24: 1457.42 | F24: 1457.42 | G24: 1376.43 | H24: 794.59 | I24: 568.71 | J24: 448.07 | K24: 448.07 | L24: 379.64 | M24: 310.48 | N24: 354.92 | O24: 386.28 | P24: 386.28 | Q24: 785.15 | R24: 234.68 | S24: 10005.28 | T24: 10221.95 | U24: 10221.95 | V24: 10258.58 | W24: 14152.26 | X24: 14126.65 | Y24: 12185 | Z24: 12185 | AA24: 12287.06 | AB24: 12321.06
A25: 1 | C25: 확정급여부채 | E25: 37.34 | F25: 37.34 | G25: 102.27 | H25: 203.56 | I25: 52.93 | N25: 66.07
A26: 1 | C26: 비유동리스부채 | E26: 1405.08 | F26: 1405.08 | G26: 1274.16 | H26: 591.02 | I26: 515.78 | J26: 448.07 | K26: 448.07 | L26: 379.64 | M26: 310.48 | N26: 288.85 | O26: 229.21 | P26: 229.21 | Q26: 653.23 | R26: 128.68 | S26: 178.5 | T26: 248.51 | U26: 248.51 | V26: 266.1 | W26: 193.87 | X26: 168.26 | Y26: 185 | Z26: 185 | AA26: 287.06 | AB26: 321.06
A27: 1 | C27: 장기금융부채 | E27: 1405.08 | F27: 1405.08 | G27: 1274.16 | H27: 591.02 | I27: 515.78 | J27: 448.07 | K27: 448.07 | L27: 379.64 | M27: 310.48 | N27: 288.85 | O27: 229.21 | P27: 229.21 | Q27: 653.23 | R27: 128.68 | S27: 1843.37 | T27: 2172.07 | U27: 2172.07 | V27: 2208.26 | W27: 1579.99 | X27: 1554.38 | Y27: 185 | Z27: 185 | AA27: 287.06 | AB27: 321.06
A28: 1 | C28: 기타비유동부채 | E28: 15 | F28: 15 | T28: 49.88 | U28: 49.88 | V28: 50.32
A29: 1 | C29: 부채총계 | E29: 22322.96 | F29: 22322.96 | G29: 20222.03 | H29: 32855.93 | I29: 35857.12 | J29: 43162.43 | K29: 43162.43 | L29: 46670.59 | M29: 41936.45 | N29: 39588.51 | O29: 27926.98 | P29: 27926.98 | Q29: 30591.39 | R29: 7307.78 | S29: 18663.04 | T29: 27150.92 | U29: 27150.92 | V29: 27065.53 | W29: 27362.53 | X29: 26724.64 | Y29: 23639.54 | Z29: 23639.54 | AA29: 34314.42 | AB29: 30442.08
A30: 1 | C30: 자본금 | E30: 35875.4 | F30: 35875.4 | G30: 35875.4 | H30: 35875.4 | I30: 35875.4 | J30: 35875.4 | K30: 35875.4 | L30: 8968.85 | M30: 9389.72 | N30: 9389.72 | O30: 9389.72 | P30: 9389.72 | Q30: 11421.21 | R30: 15074.81 | S30: 15074.81 | T30: 15323.57 | U30: 15323.57 | V30: 16635.9 | W30: 16723.4 | X30: 16723.4 | Y30: 16723.4 | Z30: 16723.4 | AA30: 19820.97 | AB30: 19820.97
A31: 1 | C31: 자본잉여금 | E31: 41176.71 | F31: 41176.71 | G31: 41176.71 | H31: 41176.71 | I31: 41176.71 | J31: 41176.71 | K31: 41176.71 | L31: 41176.71 | M31: 41753.57 | N31: 41753.57 | O31: 41749.49 | P31: 41749.49 | Q31: 47718 | R31: 61845.21 | S31: 61845.21 | T31: 62577 | U31: 62577 | V31: 66255.65 | W31: 66574.31 | X31: 66574.31 | Y31: 66574.31 | Z31: 66574.31 | AA31: 71480.34 | AB31: 71480.34
A32: 1 | C32: 이익잉여금 | E32: -52480.69 | F32: -52480.69 | G32: -54264.5 | H32: -54813.35 | I32: -58084.94 | J32: -66038.62 | K32: -66038.62 | L32: -40202.83 | M32: -38012.03 | N32: -37465.09 | O32: -35509.29 | P32: -35509.29 | Q32: -37574.95 | R32: -41130.31 | S32: -39945.79 | T32: -41363.24 | U32: -41363.24 | V32: -43224.98 | W32: -45143.81 | X32: -46788.77 | Y32: -48693.39 | Z32: -48693.39 | AA32: -49884.67 | AB32: -46607.99
A33: 1 | C33: 자본총계 | E33: 24571.42 | F33: 24571.42 | G33: 22787.61 | H33: 22238.76 | I33: 18967.17 | J33: 11013.49 | K33: 11013.49 | L33: 9942.73 | M33: 13127.19 | N33: 13674.13 | O33: 15629.93 | P33: 15629.93 | Q33: 21564.26 | R33: 35753.19 | S33: 36936.97 | T33: 36502.75 | U33: 36502.75 | V33: 39634 | W33: 38123.38 | X33: 36480.47 | Y33: 34567.35 | Z33: 34567.35 | AA33: 41379.4 | AB33: 44656.07
A34: 1 | C34: 부채와자본총계 | E34: 46894.38 | F34: 46894.38 | G34: 43009.64 | H34: 55094.69 | I34: 54824.29 | J34: 54175.92 | K34: 54175.92 | L34: 56613.31 | M34: 55063.64 | N34: 53262.64 | O34: 43556.9 | P34: 43556.9 | Q34: 52155.65 | R34: 43060.96 | S34: 55600.02 | T34: 63653.67 | U34: 63653.67 | V34: 66699.53 | W34: 65485.9 | X34: 63205.11 | Y34: 58206.88 | Z34: 58206.88 | AA34: 75693.82 | AB34: 75098.14
A35: 1 | C35: 지배주주지분 | E35: 24571.42 | F35: 24571.42 | G35: 22787.61 | H35: 22238.76 | I35: 18967.17 | J35: 11013.49 | K35: 11013.49 | L35: 9942.73 | M35: 13127.19 | N35: 13674.13 | O35: 15629.93 | P35: 15629.93 | Q35: 21564.26 | R35: 35753.19 | S35: 36936.97 | T35: 36502.75 | U35: 36502.75 | V35: 39634 | W35: 38123.38 | X35: 36480.47 | Y35: 34567.35 | Z35: 34567.35 | AA35: 41379.4 | AB35: 44656.07
A36: 1 | C36: 총차입금 | E36: 7911.11 | F36: 7911.11 | G36: 7577.78 | H36: 15879.13 | I36: 16691.06 | J36: 16144.25 | K36: 16144.25 | L36: 8500 | M36: 13199.16 | N36: 11804.54 | O36: 11227.2 | P36: 11227.2 | Q36: 9292.98 | R36: 2071.31 | S36: 2704.28 | T36: 15624.32 | U36: 15624.32 | V36: 16180.44 | W36: 17202.76 | X36: 16817.79 | Y36: 17304.72 | Z36: 17304.72 | AA36: 18280.79 | AB36: 18669.78
A37: 1 | C37: 순차입금 | E37: 6658.85 | F37: 6658.85 | G37: 6455.36 | H37: 13044.5 | I37: 16167.79 | J37: 15440.86 | K37: 15440.86 | L37: 8093.01 | M37: 11710.79 | N37: 10428.87 | O37: 10033.99 | P37: 10033.99 | Q37: -3606.96 | R37: -14722.72 | S37: -6975.49 | T37: 4973.85 | U37: 4973.85 | V37: 8957.45 | W37: 11730.69 | X37: 14519.66 | Y37: 14848.36 | Z37: 14848.36 | AA37: -3098.8 | AB37: 18190.01
A38: 1 | C38: 이자발생자산 | E38: 1281.02 | F38: 1281.02 | G38: 1157.18 | H38: 2874.56 | I38: 523.27 | J38: 861.97 | K38: 861.97 | L38: 500.12 | M38: 1537.07 | N38: 1375.67 | O38: 1430.69 | P38: 1430.69 | Q38: 13245.98 | R38: 16794.03 | S38: 14299.76 | T38: 13324.19 | U38: 13324.19 | V38: 12596.71 | W38: 10991.08 | X38: 7117.14 | Y38: 5333.17 | Z38: 5333.17 | AA38: 24255.79 | AB38: 2600.27
A39: 1 | C39: 단기금융상품 | H39: 2000
A40: 1 | C40: 단기금융자산 | H40: 2000
A41: 1 | C41: 단기파생상품부채 | H41: 3282.89 | I41: 2694.2 | O41: 9540.93 | P41: 9540.93 | R41: 307.65 | S41: 1773.08 | T41: 3524.43 | U41: 3524.43 | V41: 4180.55 | Y41: 1209.83 | Z41: 1209.83 | AA41: 10608.13 | AB41: 5376.62
A42: 1 | C42: 기타유동자산 | M42: 11082.11 | N42: 13462.67 | O42: 6358.86 | P42: 6358.86 | R42: 4008.23 | S42: 6648.48 | T42: 902.61 | U42: 902.61 | V42: 2304.02 | W42: 2727.96 | X42: 3180.57 | Y42: 845.64 | Z42: 845.64 | AA42: 875.02 | AB42: 1073.59
A43: 1 | C43: 기타유동부채 | M43: 10235.16 | N43: 10173.16 | O43: 1173.49 | P43: 1173.49 | R43: 506.82 | S43: 618.95 | T43: 476.36 | U43: 476.36 | V43: 311.11 | W43: 291.88 | X43: 596.02 | Y43: 630 | Z43: 630 | AA43: 602.71 | AB43: 656.85
A44: 1 | C44: 기타자본 | M44: -4.08 | N44: -4.08 | R44: -36.53 | S44: -37.25 | T44: -34.57 | U44: -34.57 | V44: -32.56 | W44: -30.53 | X44: -28.47 | Y44: -36.97 | Z44: -36.97 | AA44: -37.25 | AB44: -37.25
A45: 1 | C45: 당기법인세부채(미지급법인세) | O45: 151.08 | P45: 151.08 | Q45: 198.04 | R45: 0 | X45: 0.03
A46: 1 | C46: 장기차입금 | O46: 157.07 | P46: 157.07 | Q46: 131.92 | R46: 106 | T46: 8000 | U46: 8000 | V46: 8000 | W46: 12000 | X46: 12000 | Y46: 12000 | Z46: 12000 | AA46: 12000 | AB46: 12000
A47: 1 | C47: 단기투자자산(공정가치) | R47: 159.16 | S47: 424.79 | T47: 439.75 | U47: 439.75 | V47: 433.33 | W47: 463.14 | X47: 463.87 | AA47: 179.58 | AB47: 0
A48: 1 | C48: 사용권자산 | R48: 299.71 | S48: 461.03 | T48: 642.79 | U48: 642.79 | V48: 744.4 | W48: 584.13 | X48: 568.21 | Y48: 483.68 | Z48: 483.68 | AA48: 597.89 | AB48: 642.77
A49: 1 | C49: 기타비유동자산 | R49: 447.12 | S49: 461.03 | T49: 972.05 | U49: 972.05 | V49: 857.59 | W49: 1249.69 | X49: 1176.75 | Y49: 1045.41 | Z49: 1045.41 | AA49: 1035.84 | AB49: 1067.18
A50: 1 | C50: 장기매입채무및기타채무 | S50: 8080.05
A51: 1 | C51: 장기파생상품부채 | S51: 1664.87
A52: 1 | C52: 기타비유동금융부채 | T52: 1923.56 | U52: 1923.56 | V52: 1942.16 | W52: 1386.12 | X52: 1386.12
A53: 1 | C53: 기타유동금융부채 | W53: 3500.59 | X53: 2985.16
A54: 1 | C54: 장기금융부채(face) | AA54: 12000
A55: 1 | C55: 매출액(수익) | E55: 8501.73 | G55: 14734.67 | H55: 18706.69 | I55: 17176.15 | J55: 23811.88 | K55: 74429.39 | L55: 21526.67 | M55: 23408.9 | N55: 23294.52 | O55: 18121.3 | P55: 86351.39 | Q55: 15367.8 | R55: 5503.84 | S55: 6059.55 | T55: 6937.74 | U55: 33868.93 | V55: 7104.47 | W55: 8471.33 | X55: 7557.75 | Y55: 7760.26 | Z55: 30893.81 | AA55: 7980.48 | AB55: 7785.26
A56: 1 | C56: 매출원가 | E56: 11253.74 | G56: 15572.74 | H56: 19449.38 | I56: 19874.92 | J56: 30638.83 | K56: 85535.87 | L56: 20490.95 | M56: 16524.19 | N56: 20829.35 | O56: 14128.64 | P56: 71973.13 | Q56: 11803.12 | R56: 3991.34 | S56: 6053.69 | T56: 6603.4 | U56: 28451.55 | V56: 6753.93 | W56: 7844.04 | X56: 6967.28 | Y56: 6804.78 | Z56: 28370.03 | AA56: 6263.46 | AB56: 6717.58
A57: 1 | C57: 매출총이익 | E57: -2752.01 | G57: -838.06 | H57: -742.69 | I57: -2698.77 | J57: -6826.94 | K57: -11106.46 | L57: 1035.72 | M57: 6884.71 | N57: 2465.16 | O57: 3992.68 | P57: 14378.27 | Q57: 3564.68 | R57: 1512.5 | S57: 5.86 | T57: 334.34 | U57: 5417.38 | V57: 350.54 | W57: 627.29 | X57: 590.47 | Y57: 955.48 | Z57: 2523.78 | AA57: 1717.02 | AB57: 1067.68
A58: 1 | C58: 판관비 | E58: 812.58 | G58: 852.63 | H58: 857.13 | I58: 820.92 | J58: 907.22 | K58: 3437.9 | L58: 830.19 | M58: 832.03 | N58: 808.08 | O58: 1042.66 | P58: 3512.96 | Q58: 1022.17 | R58: 863.82 | S58: 1101.13 | T58: 1455.87 | U58: 4442.99 | V58: 2011.63 | W58: 2171.1 | X58: 2075.74 | Y58: 1604.11 | Z58: 7862.58 | AA58: 2584.57 | AB58: 1790.78
A59: 1 | C59: 영업이익 | E59: -3564.59 | G59: -1690.69 | H59: -1599.82 | I59: -3519.69 | J59: -7734.17 | K59: -14544.37 | L59: 205.52 | M59: 6052.68 | N59: 1657.08 | O59: 2950.02 | P59: 10865.3 | Q59: 2542.51 | R59: 648.68 | S59: -1095.27 | T59: -1121.52 | U59: 974.4 | V59: -1661.09 | W59: -1543.81 | X59: -1485.27 | Y59: -648.63 | Z59: -5338.8 | AA59: -867.55 | AB59: -723.1
A60: 1 | C60: 금융수익 | E60: 49.42 | G60: 63.72 | H60: 1518.18 | I60: 786.16 | J60: 131.95 | K60: 2500.01 | L60: 249.95 | M60: 120.15 | N60: 124.3 | O60: 90.36 | P60: 584.76 | Q60: 173.87 | R60: 61.66 | S60: 74.08 | T60: 162.71 | U60: 472.32 | V60: 65.02 | W60: 782.6 | X60: 101.36 | Y60: 3191.29 | Z60: 4140.27 | AA60: 185.35 | AB60: 5512.71
A61: 1 | C61: 금융비용 | E61: 161.76 | G61: 100.45 | H61: 469.14 | I61: 540.51 | J61: 651.15 | K61: 1761.25 | L61: 1532.26 | M61: 3910 | N61: 1236.99 | O61: 381.12 | P61: 7060.37 | Q61: 5099.82 | R61: -47.96 | S61: 410.29 | T61: 74.18 | U61: 5536.33 | V61: 318.39 | W61: 475.65 | X61: 257.49 | Y61: 2783.18 | Z61: 3834.71 | AA61: 511.88 | AB61: 1367.97
A62: 1 | C62: 기타영업외수익 | E62: 50.5 | G62: 4.29 | H62: 10.02 | I62: 2.45 | J62: 0.01 | K62: 16.77 | L62: 6.05 | M62: 57.68 | N62: 8.41 | O62: 0.01 | P62: 72.15 | Q62: 438 | R62: -88.46 | S62: 1060.51 | T62: 257.85 | U62: 1667.9 | V62: 52.77 | W62: 31.6 | X62: 58.42 | Y62: 5.3 | Z62: 148.09 | AA62: 7.48 | AB62: 9.98
A63: 1 | C63: 기타영업외비용 | E63: 1260.06 | G63: 60.67 | H63: 8.09 | I63: 0 | J63: 12.41 | K63: 81.17 | L63: 0.03 | M63: 129.7 | N63: -24.49 | O63: 524.86 | P63: 630.1 | Q63: 0 | R63: 87.02 | S63: -51.15 | T63: 126.11 | U63: 161.98 | V63: 0.05 | W63: 713.56 | X63: 61.99 | Y63: 1707.94 | Z63: 2483.54 | AA63: 4.67 | AB63: 154.95
A64: 1 | C64: 법인세비용차감전계속사업이익 | E64: -4886.49 | G64: -1783.81 | H64: -548.85 | I64: -3271.59 | J64: -8265.77 | K64: -13870.02 | L64: -1070.76 | M64: 2190.81 | N64: 577.29 | O64: 2134.39 | P64: 3831.73 | Q64: -1945.43 | R64: 582.82 | S64: -319.81 | T64: -901.25 | U64: -2583.67 | V64: -1861.74 | W64: -1918.82 | X64: -1644.96 | Y64: -1943.15 | Z64: -7368.67 | AA64: -1191.27 | AB64: 3276.67
A65: 1 | C65: 당기순이익 | E65: -4886.49 | G65: -1783.81 | H65: -548.85 | I65: -3271.59 | J65: -8265.77 | K65: -13870.02 | L65: -1070.76 | M65: 2190.81 | N65: 546.94 | O65: 2012.89 | P65: 3679.88 | Q65: -2065.67 | R65: -3669.72 | S65: 1184.52 | T65: -1023.5 | U65: -5574.37 | V65: -1861.74 | W65: -1918.82 | X65: -1644.96 | Y65: -1943.15 | Z65: -7368.67 | AA65: -1191.27 | AB65: 3276.67
A66: 1 | C66: 금융손익 | E66: -112.34 | G66: -36.73 | H66: 1049.04 | I66: 245.65 | J66: -519.2 | K66: 738.76 | L66: -1282.31 | M66: -3789.85 | N66: -1112.69 | O66: -290.76 | P66: -6475.61 | Q66: -4925.95 | R66: 109.62 | S66: -336.21 | T66: 88.53 | U66: -5064.01 | V66: -253.37 | W66: 306.95 | X66: -156.13 | Y66: 408.11 | Z66: 305.56 | AA66: -326.53 | AB66: 4144.74
... A69: 1 | C69: 계속사업이익 | E69: -4886.49 | G69: -1783.81 | H69: -548.85 | I69: -3271.59 | J69: -8265.77 | K69: -13870.02 | L69: -1070.76 | M69: 2190.81 | N69: 546.94 | O69: 2012.89 | P69: 3679.88 | Q69: -2065.67 | R69: 578.52 | S69: -320.52 | T69: -937.12 | U69: -2744.79 | V69: -1861.74 | W69: -1918.82 | X69: -1644.96 | Y69: -1943.15 | Z69: -7368.67 | AA69: -1191.27 | AB69: 3276.67
A70: 1 | C70: 총포괄손익 | E70: -4876.35 | G70: -1783.81 | H70: -548.85 | I70: -3271.59 | J70: -7953.68 | K70: -13557.93 | L70: -1070.76 | M70: 2190.81 | N70: 546.94 | O70: 1955.8 | P70: 3622.79 | Q70: -2065.67 | R70: -3669.72 | S70: 1184.52 | X70: -1644.96 | AA70: -1191.27 | AB70: 3276.67
A71: 1 | C71: 법인세비용 | N71: 30.35 | O71: 121.51 | Q71: 120.24 | R71: 4.3 | S71: 0.71 | T71: 35.88 | U71: 161.13
A72: 1 | C72: 중단사업이익 | R72: -4248.24 | S72: 1505.04 | T72: -86.38
A73: 1 | C73: 영업활동으로인한현금흐름 | E73: 2340.44 | G73: -5384.84 | H73: -5215.92 | I73: -1896.63 | J73: 2138.13 | K73: -10359.26 | L73: 346.54 | M73: 721.52 | N73: 1769.07 | O73: 926.27 | P73: 3763.4 | Q73: 5058.88 | R73: 10.99 | S73: -1599.37 | T73: 3144.36 | U73: 6614.86 | V73: -1942.63 | W73: -1399.83 | X73: -5922.52 | Y73: 4205.08 | Z73: -5059.9 | AA73: 175.49 | AB73: -956.42
A74: 1 | C74: 이자수취(CF) | E74: 2.99 | G74: 6.88 | H74: 27.49 | I74: 5.01 | J74: 1.55 | K74: 40.93 | L74: 0.1 | M74: 0.11 | N74: 0.06 | O74: 0.16 | P74: 0.43 | Q74: 0.09 | R74: 13.86 | S74: 65.16 | T74: 64.26 | U74: 143.37 | V74: 39.53 | W74: 29.53 | X74: 25.43 | Y74: 25.39 | Z74: 119.88 | AA74: 14.01 | AB74: 8.25
A75: 1 | C75: 이자지급(CF) | E75: -72.56 | G75: -70.7 | H75: -75.36 | I75: -101.9 | J75: -448.38 | K75: -696.34 | L75: -104.98 | M75: -120.07 | Q75: -98.4 | R75: 98.4
A76: 1 | C76: 법인세납부(CF) | E76: -0.46 | G76: -1.06 | H76: -2.48 | I76: -0.77 | J76: -0.23 | K76: -4.54 | L76: -0.01 | M76: 5.05 | N76: -0.23 | O76: -0.03 | P76: 4.78 | Q76: -73.27 | R76: 4.91 | S76: -17.96 | T76: -21.44 | U76: -107.76 | V76: -5.67 | W76: 23.11 | X76: -3.63 | Y76: -1.9 | Z76: 11.91 | AA76: -1.87 | AB76: 13.35
A77: 1 | C77: 투자활동으로인한현금흐름 | E77: -4210.31 | G77: 5745.3 | H77: -7593.11 | I77: 1192.14 | J77: -968.06 | K77: -1623.73 | L77: -269.94 | M77: 188.97 | N77: -45.41 | O77: -18.56 | P77: -144.94 | Q77: 1088.41 | R77: 5732.28 | S77: -17365.49 | T77: -2204.52 | U77: -12749.32 | V77: -7361.92 | W77: -1250.51 | X77: -1422.48 | Y77: 624.57 | Z77: -9410.34 | AA77: 694.33 | AB77: -19791.96
A78: 1 | C78: 유형자산의감소 | E78: 445.21 | G78: 1.79 | H78: 0 | I78: 0 | J78: 0 | K78: 1.79 | N78: 0 | O78: 0 | Q78: 1715.34 | R78: 141.5 | S78: 68.23 | T78: 764.85 | U78: 2689.92 | V78: 801.3 | X78: 21.6 | Y78: 11.8
A79: 1 | C79: 유형자산의증가 | E79: 2149.52 | G79: 1387.64 | H79: 1587.12 | I79: 839.04 | J79: 958.56 | K79: 4772.36 | L79: 256.3 | M79: 26.45 | N79: 45.42 | O79: 18.56 | P79: 346.73 | Q79: 26.93 | R79: 356.42 | S79: 16848.55 | T79: 3604.34 | U79: 20836.24 | V79: 2057.85 | W79: 1751.09 | X79: 58.98 | Y79: 177.06 | Z79: 4044.98 | AA79: 95.67 | AB79: 123.02
A80: 1 | C80: CAPEX | E80: 2149.52 | G80: 1407.84 | H80: 1587.12 | I80: 848.64 | J80: 958.56 | K80: 4802.16 | L80: 259.94 | M80: 26.45 | N80: 45.42 | O80: 18.56 | P80: 350.37 | Q80: 26.93 | R80: 356.42 | S80: 16848.55 | T80: 3664.82 | U80: 20896.72 | V80: 2148.81 | W80: 1751.09 | X80: 58.98 | Y80: 177.06 | Z80: 4135.94 | AA80: 95.67 | AB80: 227.82
A81: 1 | C81: 재무활동으로인한현금흐름 | E81: -468.87 | G81: -492.33 | H81: 12522.67 | I81: 393.68 | J81: -984.11 | K81: 11439.91 | L81: -372.99 | M81: 170.65 | N81: -1843.32 | O81: -1059.02 | P81: -3104.68 | Q81: 5550.3 | R81: -1859.83 | S81: 11910.43 | T81: -13.66 | U81: 15587.24 | V81: 5873.37 | W81: 903.28 | X81: -395.06 | Y81: -105.46 | Z81: 6276.13 | AA81: 17999.18 | AB81: -97.21
A82: 1 | C82: 단기차입금의증가 | E82: 0 | I82: 2800 | J82: 0 | N82: 0 | O82: 0
A83: 1 | C83: 장기차입금의증가 | E83: 0 | T83: 0 | X83: 0 | Y83: 0
A84: 1 | C84: 장기차입금의감소 | E84: 0
A85: 1 | C85: 유동성장기부채의감소 | E85: 333.34 | G85: 333.33 | H85: 333.34 | I85: 333.33 | J85: 111.11 | K85: 1111.11 | O85: 30.93 | Q85: 23.61 | R85: 23.99 | S85: 24.54 | T85: 181.71 | U85: 253.85
A86: 1 | C86: 현금및현금성자산의증감 | E86: -2426 | G86: -129.83 | H86: -287.79 | I86: -311.36 | J86: 180.11 | K86: -548.87 | L86: -296.4 | M86: 1081.38 | N86: -112.7 | O86: -182.46 | P86: 489.82 | Q86: 11706.73 | R86: 3874.3 | S86: -7054.43 | T86: 930.66 | U86: 9457.26 | V86: -3427.47 | W86: -1750.93 | X86: -3173.94 | Y86: 158.23 | Z86: -8194.11 | AA86: 18923.23 | AB86: -20899.82
A87: 1 | C87: 기말현금및현금성자산 | E87: -2426 | G87: 1122.42 | H87: -287.79 | I87: -311.36 | J87: 180.12 | K87: 703.39 | L87: 406.99 | M87: 1081.38 | N87: -112.7 | O87: -182.46 | P87: 1193.21 | Q87: 12899.94 | R87: 3894.09 | S87: -7114.26 | T87: 970.7 | U87: 10650.47 | V87: 7222.99 | W87: -1750.92 | X87: -3173.94 | Y87: 158.23 | Z87: 2456.36 | AA87: 21379.59 | AB87: -20899.82
A88: 1 | C88: 무형자산의증가 | G88: 20.2 | H88: 0 | I88: 9.6 | J88: 0 | K88: 29.8 | L88: 3.64 | M88: 0 | N88: 0 | O88: 0 | P88: 3.64 | V88: 90.96 | W88: 0 | X88: 0 | Y88: 0 | Z88: 90.96
A89: 1 | C89: 단기차입금의감소 | J89: 800 | L89: 300 | M89: 0 | N89: 1750 | O89: 950 | P89: 3000 | Q89: 2350 | R89: 1780 | S89: 8000 | X89: 0 | Y89: 0
A90: 1 | C90: 리스부채의상환 | N90: 78.09 | V90: 117.61 | W90: 95.7 | AA90: 104.43 | AB90: 100.21
A91: 1 | C91: 자기주식의취득 | N91: 0 | O91: 0 | S91: 0.73 | T91: 0

Sheet subQ
A1: YQ | C1: subQ 분기 서브모델(억원, U=100) | E1: 4Q21 | F1: 2021 | G1: 1Q22 | H1: 2Q22 | I1: 3Q22 | J1: 4Q22 | K1: 2022 | L1: 1Q23 | M1: 2Q23 | N1: 3Q23 | O1: 4Q23 | P1: 2023 | Q1: 1Q24 | R1: 2Q24 | S1: 3Q24 | T1: 4Q24 | U1: 2024 | V1: 1Q25 | W1: 2Q25 | X1: 3Q25 | Y1: 4Q25 | Z1: 2025 | AA1: 1Q26 | AB1: 2Q26 | AC1: 3Q26 | AD1: 4Q26 | AE1: 2026 | AF1: 1Q27 | AG1: 2Q27 | AH1: 3Q27 | AI1: 4Q27 | AJ1: 2027 | AK1: 1Q28 | AL1: 2Q28 | AM1: 3Q28 | AN1: 4Q28 | AO1: 2028
A2: A=이름(key) B=그룹 C=단위 D=FnGuide 계정명(VLOOKUP 키). 확정=VLOOKUP(BS), 추정=변수 가정 참조
E3: 1 | F3: 2 | G3: 3 | H3: 4 | I3: 5 | J3: 6 | K3: 7 | L3: 8 | M3: 9 | N3: 10 | O3: 11 | P3: 12 | Q3: 13 | R3: 14 | S3: 15 | T3: 16 | U3: 17 | V3: 18 | W3: 19 | X3: 20 | Y3: 21 | Z3: 22 | AA3: 23 | AB3: 24 | AC3: 25 | AD3: 26 | AE3: 27 | AF3: 28 | AG3: 29 | AH3: 30 | AI3: 31 | AJ3: 32 | AK3: 33 | AL3: 34 | AM3: 35 | AN3: 36 | AO3: 37
E4: 2021.12 | F4: 2021.12A | G4: 2022.03 | H4: 2022.06 | I4: 2022.09 | J4: 2022.12 | K4: 2022.12A | L4: 2023.03 | M4: 2023.06 | N4: 2023.09 | O4: 2023.12 | P4: 2023.12A | Q4: 2024.03 | R4: 2024.06 | S4: 2024.09 | T4: 2024.12 | U4: 2024.12A | V4: 2025.03 | W4: 2025.06 | X4: 2025.09 | Y4: 2025.12 | Z4: 2025.12A | AA4: 2026.03 | AB4: 2026.06 | AC4: 2026.09 | AD4: 2026.12 | AE4: 2026.12A | AF4: 2027.03 | AG4: 2027.06 | AH4: 2027.09 | AI4: 2027.12 | AJ4: 2027.12A | AK4: 2028.03 | AL4: 2028.06 | AM4: 2028.09 | AN4: 2028.12 | AO4: 2028.12A
A5: 매출액 | B5: 손익 | C5: 억원 | D5: 매출액(수익) | E5: =IFERROR(VLOOKUP($D5,BS연결,MATCH(E$1,BS연결H,0),0)/100,"") | G5: =IFERROR(VLOOKUP($D5,BS연결,MATCH(G$1,BS연결H,0),0)/100,"") | H5: =IFERROR(VLOOKUP($D5,BS연결,MATCH(H$1,BS연결H,0),0)/100,"") | I5: =IFERROR(VLOOKUP($D5,BS연결,MATCH(I$1,BS연결H,0),0)/100,"") | J5: =IFERROR(VLOOKUP($D5,BS연결,MATCH(J$1,BS연결H,0),0)/100,"") | K5: =IFERROR(VLOOKUP($D5,BS연결,MATCH(K$1,BS연결H,0),0)/100,"") | L5: =IFERROR(VLOOKUP($D5,BS연결,MATCH(L$1,BS연결H,0),0)/100,"") | M5: =IFERROR(VLOOKUP($D5,BS연결,MATCH(M$1,BS연결H,0),0)/100,"") | N5: =IFERROR(VLOOKUP($D5,BS연결,MATCH(N$1,BS연결H,0),0)/100,"") | ... AB5: =IFERROR(VLOOKUP($D5,BS연결,MATCH(AB$1,BS연결H,0),0)/100,"") | AC5: =IFERROR(X5*(1+변수!AC21),"") | AD5: =IFERROR(Y5*(1+변수!AD21),"") | AE5: =SUM(AA5:AD5) | AF5: =IFERROR(AA5*(1+변수!AF21),"") | AG5: =IFERROR(AB5*(1+변수!AG21),"") | AH5: =IFERROR(AC5*(1+변수!AH21),"") | AI5: =IFERROR(AD5*(1+변수!AI21),"") | AJ5: =SUM(AF5:AI5) | AK5: =IFERROR(AF5*(1+변수!AK21),"") | AL5: =IFERROR(AG5*(1+변수!AL21),"") | AM5: =IFERROR(AH5*(1+변수!AM21),"") | AN5: =IFERROR(AI5*(1+변수!AN21),"") | AO5: =SUM(AK5:AN5)
A6: 매출원가 | B6: 손익 | C6: 억원 | D6: 매출원가 | E6: =IFERROR(VLOOKUP($D6,BS연결,MATCH(E$1,BS연결H,0),0)/100,"") | G6: =IFERROR(VLOOKUP($D6,BS연결,MATCH(G$1,BS연결H,0),0)/100,"") | H6: =IFERROR(VLOOKUP($D6,BS연결,MATCH(H$1,BS연결H,0),0)/100,"") | I6: =IFERROR(VLOOKUP($D6,BS연결,MATCH(I$1,BS연결H,0),0)/100,"") | J6: =IFERROR(VLOOKUP($D6,BS연결,MATCH(J$1,BS연결H,0),0)/100,"") | K6: =IFERROR(VLOOKUP($D6,BS연결,MATCH(K$1,BS연결H,0),0)/100,"") | L6: =IFERROR(VLOOKUP($D6,BS연결,MATCH(L$1,BS연결H,0),0)/100,"") | M6: =IFERROR(VLOOKUP($D6,BS연결,MATCH(M$1,BS연결H,0),0)/100,"") | N6: =IFERROR(VLOOKUP($D6,BS연결,MATCH(N$1,BS연결H,0),0)/100,"") | ... AB6: =IFERROR(VLOOKUP($D6,BS연결,MATCH(AB$1,BS연결H,0),0)/100,"") | AC6: =IFERROR(AC5-AC7,"") | AD6: =IFERROR(AD5-AD7,"") | AE6: =SUM(AA6:AD6) | AF6: =IFERROR(AF5-AF7,"") | AG6: =IFERROR(AG5-AG7,"") | AH6: =IFERROR(AH5-AH7,"") | AI6: =IFERROR(AI5-AI7,"") | AJ6: =SUM(AF6:AI6) | AK6: =IFERROR(AK5-AK7,"") | AL6: =IFERROR(AL5-AL7,"") | AM6: =IFERROR(AM5-AM7,"") | AN6: =IFERROR(AN5-AN7,"") | AO6: =SUM(AK6:AN6)
A7: 매출총이익 | B7: 손익 | C7: 억원 | D7: 매출총이익 | E7: =IFERROR(VLOOKUP($D7,BS연결,MATCH(E$1,BS연결H,0),0)/100,"") | G7: =IFERROR(VLOOKUP($D7,BS연결,MATCH(G$1,BS연결H,0),0)/100,"") | H7: =IFERROR(VLOOKUP($D7,BS연결,MATCH(H$1,BS연결H,0),0)/100,"") | I7: =IFERROR(VLOOKUP($D7,BS연결,MATCH(I$1,BS연결H,0),0)/100,"") | J7: =IFERROR(VLOOKUP($D7,BS연결,MATCH(J$1,BS연결H,0),0)/100,"") | K7: =IFERROR(VLOOKUP($D7,BS연결,MATCH(K$1,BS연결H,0),0)/100,"") | L7: =IFERROR(VLOOKUP($D7,BS연결,MATCH(L$1,BS연결H,0),0)/100,"") | M7: =IFERROR(VLOOKUP($D7,BS연결,MATCH(M$1,BS연결H,0),0)/100,"") | N7: =IFERROR(VLOOKUP($D7,BS연결,MATCH(N$1,BS연결H,0),0)/100,"") | ... AB7: =IFERROR(VLOOKUP($D7,BS연결,MATCH(AB$1,BS연결H,0),0)/100,"") | AC7: =IFERROR(AC9+AC8,"") | AD7: =IFERROR(AD9+AD8,"") | AE7: =SUM(AA7:AD7) | AF7: =IFERROR(AF9+AF8,"") | AG7: =IFERROR(AG9+AG8,"") | AH7: =IFERROR(AH9+AH8,"") | AI7: =IFERROR(AI9+AI8,"") | AJ7: =SUM(AF7:AI7) | AK7: =IFERROR(AK9+AK8,"") | AL7: =IFERROR(AL9+AL8,"") | AM7: =IFERROR(AM9+AM8,"") | AN7: =IFERROR(AN9+AN8,"") | AO7: =SUM(AK7:AN7)
A8: 판관비 | B8: 손익 | C8: 억원 | D8: 판관비 | E8: =IFERROR(VLOOKUP($D8,BS연결,MATCH(E$1,BS연결H,0),0)/100,"") | G8: =IFERROR(VLOOKUP($D8,BS연결,MATCH(G$1,BS연결H,0),0)/100,"") | H8: =IFERROR(VLOOKUP($D8,BS연결,MATCH(H$1,BS연결H,0),0)/100,"") | I8: =IFERROR(VLOOKUP($D8,BS연결,MATCH(I$1,BS연결H,0),0)/100,"") | J8: =IFERROR(VLOOKUP($D8,BS연결,MATCH(J$1,BS연결H,0),0)/100,"") | K8: =IFERROR(VLOOKUP($D8,BS연결,MATCH(K$1,BS연결H,0),0)/100,"") | L8: =IFERROR(VLOOKUP($D8,BS연결,MATCH(L$1,BS연결H,0),0)/100,"") | M8: =IFERROR(VLOOKUP($D8,BS연결,MATCH(M$1,BS연결H,0),0)/100,"") | N8: =IFERROR(VLOOKUP($D8,BS연결,MATCH(N$1,BS연결H,0),0)/100,"") | ... AB8: =IFERROR(VLOOKUP($D8,BS연결,MATCH(AB$1,BS연결H,0),0)/100,"") | AC8: =IFERROR(AC5*변수!AC22,"") | AD8: =IFERROR(AD5*변수!AD22,"") | AE8: =SUM(AA8:AD8) | AF8: =IFERROR(AF5*변수!AF22,"") | AG8: =IFERROR(AG5*변수!AG22,"") | AH8: =IFERROR(AH5*변수!AH22,"") | AI8: =IFERROR(AI5*변수!AI22,"") | AJ8: =SUM(AF8:AI8) | AK8: =IFERROR(AK5*변수!AK22,"") | AL8: =IFERROR(AL5*변수!AL22,"") | AM8: =IFERROR(AM5*변수!AM22,"") | AN8: =IFERROR(AN5*변수!AN22,"") | AO8: =SUM(AK8:AN8)
A9: 영업이익 | B9: 손익 | C9: 억원 | D9: 영업이익 | E9: =IFERROR(VLOOKUP($D9,BS연결,MATCH(E$1,BS연결H,0),0)/100,"") | G9: =IFERROR(VLOOKUP($D9,BS연결,MATCH(G$1,BS연결H,0),0)/100,"") | H9: =IFERROR(VLOOKUP($D9,BS연결,MATCH(H$1,BS연결H,0),0)/100,"") | I9: =IFERROR(VLOOKUP($D9,BS연결,MATCH(I$1,BS연결H,0),0)/100,"") | J9: =IFERROR(VLOOKUP($D9,BS연결,MATCH(J$1,BS연결H,0),0)/100,"") | K9: =IFERROR(VLOOKUP($D9,BS연결,MATCH(K$1,BS연결H,0),0)/100,"") | L9: =IFERROR(VLOOKUP($D9,BS연결,MATCH(L$1,BS연결H,0),0)/100,"") | M9: =IFERROR(VLOOKUP($D9,BS연결,MATCH(M$1,BS연결H,0),0)/100,"") | N9: =IFERROR(VLOOKUP($D9,BS연결,MATCH(N$1,BS연결H,0),0)/100,"") | ... AB9: =IFERROR(VLOOKUP($D9,BS연결,MATCH(AB$1,BS연결H,0),0)/100,"") | AC9: =IFERROR(AC5*변수!AC23,"") | AD9: =IFERROR(AD5*변수!AD23,"") | AE9: =SUM(AA9:AD9) | AF9: =IFERROR(AF5*변수!AF23,"") | AG9: =IFERROR(AG5*변수!AG23,"") | AH9: =IFERROR(AH5*변수!AH23,"") | AI9: =IFERROR(AI5*변수!AI23,"") | AJ9: =SUM(AF9:AI9) | AK9: =IFERROR(AK5*변수!AK23,"") | AL9: =IFERROR(AL5*변수!AL23,"") | AM9: =IFERROR(AM5*변수!AM23,"") | AN9: =IFERROR(AN5*변수!AN23,"") | AO9: =SUM(AK9:AN9)
A10: OPM | B10: 손익 | C10: % | D10: 영업이익률 | E10: =IFERROR(E9/E5,"") | G10: =IFERROR(G9/G5,"") | H10: =IFERROR(H9/H5,"") | I10: =IFERROR(I9/I5,"") | J10: =IFERROR(J9/J5,"") | K10: =IFERROR(K9/K5,"") | L10: =IFERROR(L9/L5,"") | M10: =IFERROR(M9/M5,"") | N10: =IFERROR(N9/N5,"") | ... AO10: =IFERROR(AO9/AO5,"")
A11: 금융손익 | B11: 손익 | C11: 억원 | D11: 금융손익 | E11: =IFERROR(VLOOKUP($D11,BS연결,MATCH(E$1,BS연결H,0),0)/100,"") | G11: =IFERROR(VLOOKUP($D11,BS연결,MATCH(G$1,BS연결H,0),0)/100,"") | H11: =IFERROR(VLOOKUP($D11,BS연결,MATCH(H$1,BS연결H,0),0)/100,"") | I11: =IFERROR(VLOOKUP($D11,BS연결,MATCH(I$1,BS연결H,0),0)/100,"") | J11: =IFERROR(VLOOKUP($D11,BS연결,MATCH(J$1,BS연결H,0),0)/100,"") | K11: =IFERROR(VLOOKUP($D11,BS연결,MATCH(K$1,BS연결H,0),0)/100,"") | L11: =IFERROR(VLOOKUP($D11,BS연결,MATCH(L$1,BS연결H,0),0)/100,"") | M11: =IFERROR(VLOOKUP($D11,BS연결,MATCH(M$1,BS연결H,0),0)/100,"") | N11: =IFERROR(VLOOKUP($D11,BS연결,MATCH(N$1,BS연결H,0),0)/100,"") | ... AB11: =IFERROR(VLOOKUP($D11,BS연결,MATCH(AB$1,BS연결H,0),0)/100,"") | AC11: =IFERROR(AC12+AC13+AC14+AC15,"") | AD11: =IFERROR(AD12+AD13+AD14+AD15,"") | AE11: =SUM(AA11:AD11) | AF11: =IFERROR(AF12+AF13+AF14+AF15,"") | AG11: =IFERROR(AG12+AG13+AG14+AG15,"") | AH11: =IFERROR(AH12+AH13+AH14+AH15,"") | AI11: =IFERROR(AI12+AI13+AI14+AI15,"") | AJ11: =SUM(AF11:AI11) | AK11: =IFERROR(AK12+AK13+AK14+AK15,"") | AL11: =IFERROR(AL12+AL13+AL14+AL15,"") | AM11: =IFERROR(AM12+AM13+AM14+AM15,"") | AN11: =IFERROR(AN12+AN13+AN14+AN15,"") | AO11: =SUM(AK11:AN11)
A12: 이자손익 | B12: 손익 | C12: 억원 | D12: 이자손익 | G12: =IFERROR(VLOOKUP($D12,BS연결,MATCH(G$1,BS연결H,0),0)/100,"") | H12: =IFERROR(VLOOKUP($D12,BS연결,MATCH(H$1,BS연결H,0),0)/100,"") | I12: =IFERROR(VLOOKUP($D12,BS연결,MATCH(I$1,BS연결H,0),0)/100,"") | J12: =IFERROR(VLOOKUP($D12,BS연결,MATCH(J$1,BS연결H,0),0)/100,"") | K12: =IFERROR(VLOOKUP($D12,BS연결,MATCH(K$1,BS연결H,0),0)/100,"") | L12: =IFERROR(VLOOKUP($D12,BS연결,MATCH(L$1,BS연결H,0),0)/100,"") | M12: =IFERROR(VLOOKUP($D12,BS연결,MATCH(M$1,BS연결H,0),0)/100,"") | N12: =IFERROR(VLOOKUP($D12,BS연결,MATCH(N$1,BS연결H,0),0)/100,"") | ... Q12: =IFERROR(VLOOKUP($D12,BS연결,MATCH(Q$1,BS연결H,0),0)/100,"") | U12: =SUM(Q12:T12) | V12: =IFERROR(VLOOKUP($D12,BS연결,MATCH(V$1,BS연결H,0),0)/100,"") | X12: =IFERROR(VLOOKUP($D12,BS연결,MATCH(X$1,BS연결H,0),0)/100,"") | Y12: =IFERROR(VLOOKUP($D12,BS연결,MATCH(Y$1,BS연결H,0),0)/100,"") | Z12: =SUM(V12:Y12) | AA12: =IFERROR(VLOOKUP($D12,BS연결,MATCH(AA$1,BS연결H,0),0)/100,"") | AC12: =IFERROR((AB29*변수!$D$55-AB27*변수!$D$56)/4,"") | AD12: =IFERROR((AC29*변수!$D$55-AC27*변수!$D$56)/4,"") | AE12: =SUM(AA12:AD12) | AF12: =IFERROR((AD29*변수!$D$55-AD27*변수!$D$56)/4,"") | AG12: =IFERROR((AF29*변수!$D$55-AF27*변수!$D$56)/4,"") | AH12: =IFERROR((AG29*변수!$D$55-AG27*변수!$D$56)/4,"") | AI12: =IFERROR((AH29*변수!$D$55-AH27*변수!$D$56)/4,"") | AJ12: =SUM(AF12:AI12) | AK12: =IFERROR((AI29*변수!$D$55-AI27*변수!$D$56)/4,"") | AL12: =IFERROR((AK29*변수!$D$55-AK27*변수!$D$56)/4,"") | AM12: =IFERROR((AL29*변수!$D$55-AL27*변수!$D$56)/4,"") | AN12: =IFERROR((AM29*변수!$D$55-AM27*변수!$D$56)/4,"") | AO12: =SUM(AK12:AN12)
A13: 외환손익 | B13: 손익 | C13: 억원 | D13: 외환손익(실적만; 추정 환효과는 환관련손익) | G13: =IFERROR((VLOOKUP("외환차익",BS연결,MATCH(G$1,BS연결H,0),0)-VLOOKUP("외환차손",BS연결,MATCH(G$1,BS연결H,0),0)+VLOOKUP("외화환산이익",BS연결,MATCH(G$1,BS연결H,0),0)-VLOOKUP("외화환산손실",BS연결,MATCH(G$1,BS연결H,0),0))/100,"") | H13: =IFERROR((VLOOKUP("외환차익",BS연결,MATCH(H$1,BS연결H,0),0)-VLOOKUP("외환차손",BS연결,MATCH(H$1,BS연결H,0),0)+VLOOKUP("외화환산이익",BS연결,MATCH(H$1,BS연결H,0),0)-VLOOKUP("외화환산손실",BS연결,MATCH(H$1,BS연결H,0),0))/100,"") | I13: =IFERROR((VLOOKUP("외환차익",BS연결,MATCH(I$1,BS연결H,0),0)-VLOOKUP("외환차손",BS연결,MATCH(I$1,BS연결H,0),0)+VLOOKUP("외화환산이익",BS연결,MATCH(I$1,BS연결H,0),0)-VLOOKUP("외화환산손실",BS연결,MATCH(I$1,BS연결H,0),0))/100,"") | J13: =IFERROR((VLOOKUP("외환차익",BS연결,MATCH(J$1,BS연결H,0),0)-VLOOKUP("외환차손",BS연결,MATCH(J$1,BS연결H,0),0)+VLOOKUP("외화환산이익",BS연결,MATCH(J$1,BS연결H,0),0)-VLOOKUP("외화환산손실",BS연결,MATCH(J$1,BS연결H,0),0))/100,"") | K13: =SUM(G13:J13) | L13: =IFERROR((VLOOKUP("외환차익",BS연결,MATCH(L$1,BS연결H,0),0)-VLOOKUP("외환차손",BS연결,MATCH(L$1,BS연결H,0),0)+VLOOKUP("외화환산이익",BS연결,MATCH(L$1,BS연결H,0),0)-VLOOKUP("외화환산손실",BS연결,MATCH(L$1,BS연결H,0),0))/100,"") | M13: =IFERROR((VLOOKUP("외환차익",BS연결,MATCH(M$1,BS연결H,0),0)-VLOOKUP("외환차손",BS연결,MATCH(M$1,BS연결H,0),0)+VLOOKUP("외화환산이익",BS연결,MATCH(M$1,BS연결H,0),0)-VLOOKUP("외화환산손실",BS연결,MATCH(M$1,BS연결H,0),0))/100,"") | N13: =IFERROR((VLOOKUP("외환차익",BS연결,MATCH(N$1,BS연결H,0),0)-VLOOKUP("외환차손",BS연결,MATCH(N$1,BS연결H,0),0)+VLOOKUP("외화환산이익",BS연결,MATCH(N$1,BS연결H,0),0)-VLOOKUP("외화환산손실",BS연결,MATCH(N$1,BS연결H,0),0))/100,"") | P13: =SUM(L13:O13) | Q13: =IFERROR((VLOOKUP("외환차익",BS연결,MATCH(Q$1,BS연결H,0),0)-VLOOKUP("외환차손",BS연결,MATCH(Q$1,BS연결H,0),0)+VLOOKUP("외화환산이익",BS연결,MATCH(Q$1,BS연결H,0),0)-VLOOKUP("외화환산손실",BS연결,MATCH(Q$1,BS연결H,0),0))/100,"") | U13: =SUM(Q13:T13) | V13: =IFERROR((VLOOKUP("외환차익",BS연결,MATCH(V$1,BS연결H,0),0)-VLOOKUP("외환차손",BS연결,MATCH(V$1,BS연결H,0),0)+VLOOKUP("외화환산이익",BS연결,MATCH(V$1,BS연결H,0),0)-VLOOKUP("외화환산손실",BS연결,MATCH(V$1,BS연결H,0),0))/100,"") | X13: =IFERROR((VLOOKUP("외환차익",BS연결,MATCH(X$1,BS연결H,0),0)-VLOOKUP("외환차손",BS연결,MATCH(X$1,BS연결H,0),0)+VLOOKUP("외화환산이익",BS연결,MATCH(X$1,BS연결H,0),0)-VLOOKUP("외화환산손실",BS연결,MATCH(X$1,BS연결H,0),0))/100,"") | Y13: =IFERROR((VLOOKUP("외환차익",BS연결,MATCH(Y$1,BS연결H,0),0)-VLOOKUP("외환차손",BS연결,MATCH(Y$1,BS연결H,0),0)+VLOOKUP("외화환산이익",BS연결,MATCH(Y$1,BS연결H,0),0)-VLOOKUP("외화환산손실",BS연결,MATCH(Y$1,BS연결H,0),0))/100,"") | Z13: =SUM(V13:Y13) | AA13: =IFERROR((VLOOKUP("외환차익",BS연결,MATCH(AA$1,BS연결H,0),0)-VLOOKUP("외환차손",BS연결,MATCH(AA$1,BS연결H,0),0)+VLOOKUP("외화환산이익",BS연결,MATCH(AA$1,BS연결H,0),0)-VLOOKUP("외화환산손실",BS연결,MATCH(AA$1,BS연결H,0),0))/100,"") | AC13: =변수!AC24 | AD13: =변수!AD24 | AE13: =SUM(AA13:AD13) | AF13: =변수!AF24 | AG13: =변수!AG24 | AH13: =변수!AH24 | AI13: =변수!AI24 | AJ13: =SUM(AF13:AI13) | AK13: =변수!AK24 | AL13: =변수!AL24 | AM13: =변수!AM24 | AN13: =변수!AN24 | AO13: =SUM(AK13:AN13)
A14: 파생상품손익 | B14: 손익 | C14: 억원 | D14: 파생상품손익 | K14: =SUM(G14:J14) | P14: =SUM(L14:O14) | U14: =SUM(Q14:T14) | X14: =IFERROR((VLOOKUP("파생상품이익",BS연결,MATCH(X$1,BS연결H,0),0)-VLOOKUP("파생상품손실",BS연결,MATCH(X$1,BS연결H,0),0))/100,"") | Z14: =SUM(V14:Y14) | AC14: =변수!AC25 | AD14: =변수!AD25 | AE14: =SUM(AA14:AD14) | AF14: =변수!AF25 | AG14: =변수!AG25 | AH14: =변수!AH25 | AI14: =변수!AI25 | AJ14: =SUM(AF14:AI14) | AK14: =변수!AK25 | AL14: =변수!AL25 | AM14: =변수!AM25 | AN14: =변수!AN25 | AO14: =SUM(AK14:AN14)
A15: 기타금융손익 | B15: 손익 | C15: 억원 | D15: 기타금융손익(금융손익 잔차) | K15: =SUM(G15:J15) | P15: =SUM(L15:O15) | U15: =SUM(Q15:T15) | X15: =IFERROR(X11-X12-X13-X14,"") | Z15: =SUM(V15:Y15) | AC15: =변수!AC26 | AD15: =변수!AD26 | AE15: =SUM(AA15:AD15) | AF15: =변수!AF26 | AG15: =변수!AG26 | AH15: =변수!AH26 | AI15: =변수!AI26 | AJ15: =SUM(AF15:AI15) | AK15: =변수!AK26 | AL15: =변수!AL26 | AM15: =변수!AM26 | AN15: =변수!AN26 | AO15: =SUM(AK15:AN15)
A16: 기타영업외손익 | B16: 손익 | C16: 억원 | D16: 기타영업외손익 | E16: =IFERROR(VLOOKUP($D16,BS연결,MATCH(E$1,BS연결H,0),0)/100,"") | G16: =IFERROR(VLOOKUP($D16,BS연결,MATCH(G$1,BS연결H,0),0)/100,"") | H16: =IFERROR(VLOOKUP($D16,BS연결,MATCH(H$1,BS연결H,0),0)/100,"") | I16: =IFERROR(VLOOKUP($D16,BS연결,MATCH(I$1,BS연결H,0),0)/100,"") | J16: =IFERROR(VLOOKUP($D16,BS연결,MATCH(J$1,BS연결H,0),0)/100,"") | K16: =IFERROR(VLOOKUP($D16,BS연결,MATCH(K$1,BS연결H,0),0)/100,"") | L16: =IFERROR(VLOOKUP($D16,BS연결,MATCH(L$1,BS연결H,0),0)/100,"") | M16: =IFERROR(VLOOKUP($D16,BS연결,MATCH(M$1,BS연결H,0),0)/100,"") | N16: =IFERROR(VLOOKUP($D16,BS연결,MATCH(N$1,BS연결H,0),0)/100,"") | ... AB16: =IFERROR(VLOOKUP($D16,BS연결,MATCH(AB$1,BS연결H,0),0)/100,"") | AC16: =변수!AC27 | AD16: =변수!AD27 | AE16: =SUM(AA16:AD16) | AF16: =변수!AF27 | AG16: =변수!AG27 | AH16: =변수!AH27 | AI16: =변수!AI27 | AJ16: =SUM(AF16:AI16) | AK16: =변수!AK27 | AL16: =변수!AL27 | AM16: =변수!AM27 | AN16: =변수!AN27 | AO16: =SUM(AK16:AN16)
A17: 지분법손익 | B17: 손익 | C17: 억원 | D17: 종속기업,공동지배기업및관계기업관련손익 | K17: =SUM(G17:J17) | P17: =SUM(L17:O17) | U17: =SUM(Q17:T17) | Z17: =SUM(V17:Y17) | AB17: =IFERROR(VLOOKUP($D17,BS연결,MATCH(AB$1,BS연결H,0),0)/100,"") | AC17: =변수!AC28 | AD17: =변수!AD28 | AE17: =SUM(AA17:AD17) | AF17: =변수!AF28 | AG17: =변수!AG28 | AH17: =변수!AH28 | AI17: =변수!AI28 | AJ17: =SUM(AF17:AI17) | AK17: =변수!AK28 | AL17: =변수!AL28 | AM17: =변수!AM28 | AN17: =변수!AN28 | AO17: =SUM(AK17:AN17)
A18: 세전이익 | B18: 손익 | C18: 억원 | D18: 법인세비용차감전계속사업이익 | E18: =IFERROR(VLOOKUP($D18,BS연결,MATCH(E$1,BS연결H,0),0)/100,"") | G18: =IFERROR(VLOOKUP($D18,BS연결,MATCH(G$1,BS연결H,0),0)/100,"") | H18: =IFERROR(VLOOKUP($D18,BS연결,MATCH(H$1,BS연결H,0),0)/100,"") | I18: =IFERROR(VLOOKUP($D18,BS연결,MATCH(I$1,BS연결H,0),0)/100,"") | J18: =IFERROR(VLOOKUP($D18,BS연결,MATCH(J$1,BS연결H,0),0)/100,"") | K18: =SUM(G18:J18) | L18: =IFERROR(VLOOKUP($D18,BS연결,MATCH(L$1,BS연결H,0),0)/100,"") | M18: =IFERROR(VLOOKUP($D18,BS연결,MATCH(M$1,BS연결H,0),0)/100,"") | N18: =IFERROR(VLOOKUP($D18,BS연결,MATCH(N$1,BS연결H,0),0)/100,"") | O18: =IFERROR(VLOOKUP($D18,BS연결,MATCH(O$1,BS연결H,0),0)/100,"") | P18: =IFERROR(VLOOKUP($D18,BS연결,MATCH(P$1,BS연결H,0),0)/100,"") | Q18: =IFERROR(VLOOKUP($D18,BS연결,MATCH(Q$1,BS연결H,0),0)/100,"") | R18: =IFERROR(VLOOKUP($D18,BS연결,MATCH(R$1,BS연결H,0),0)/100,"") | S18: =IFERROR(VLOOKUP($D18,BS연결,MATCH(S$1,BS연결H,0),0)/100,"") | ... AB18: =IFERROR(VLOOKUP($D18,BS연결,MATCH(AB$1,BS연결H,0),0)/100,"") | AC18: =IFERROR(AC9+AC11+AC16+AC17,"") | AD18: =IFERROR(AD9+AD11+AD16+AD17,"") | AE18: =SUM(AA18:AD18) | AF18: =IFERROR(AF9+AF11+AF16+AF17,"") | AG18: =IFERROR(AG9+AG11+AG16+AG17,"") | AH18: =IFERROR(AH9+AH11+AH16+AH17,"") | AI18: =IFERROR(AI9+AI11+AI16+AI17,"") | AJ18: =SUM(AF18:AI18) | AK18: =IFERROR(AK9+AK11+AK16+AK17,"") | AL18: =IFERROR(AL9+AL11+AL16+AL17,"") | AM18: =IFERROR(AM9+AM11+AM16+AM17,"") | AN18: =IFERROR(AN9+AN11+AN16+AN17,"") | AO18: =SUM(AK18:AN18)
A19: 법인세비용 | B19: 손익 | C19: 억원 | D19: 법인세비용 | K19: =SUM(G19:J19) | N19: =IFERROR(VLOOKUP($D19,BS연결,MATCH(N$1,BS연결H,0),0)/100,"") | O19: =IFERROR(VLOOKUP($D19,BS연결,MATCH(O$1,BS연결H,0),0)/100,"") | P19: =SUM(L19:O19) | Q19: =IFERROR(VLOOKUP($D19,BS연결,MATCH(Q$1,BS연결H,0),0)/100,"") | R19: =IFERROR(VLOOKUP($D19,BS연결,MATCH(R$1,BS연결H,0),0)/100,"") | S19: =IFERROR(VLOOKUP($D19,BS연결,MATCH(S$1,BS연결H,0),0)/100,"") | T19: =IFERROR(VLOOKUP($D19,BS연결,MATCH(T$1,BS연결H,0),0)/100,"") | U19: =IFERROR(VLOOKUP($D19,BS연결,MATCH(U$1,BS연결H,0),0)/100,"") | V19: =IFERROR(VLOOKUP($D19,BS연결,MATCH(V$1,BS연결H,0),0)/100,"") | Y19: =IFERROR(VLOOKUP($D19,BS연결,MATCH(Y$1,BS연결H,0),0)/100,"") | Z19: =SUM(V19:Y19) | AA19: =IFERROR(VLOOKUP($D19,BS연결,MATCH(AA$1,BS연결H,0),0)/100,"") | AB19: =IFERROR(VLOOKUP($D19,BS연결,MATCH(AB$1,BS연결H,0),0)/100,"") | AC19: =IFERROR(AC18*변수!AC29,"") | AD19: =IFERROR(AD18*변수!AD29,"") | AE19: =SUM(AA19:AD19) | AF19: =IFERROR(AF18*변수!AF29,"") | AG19: =IFERROR(AG18*변수!AG29,"") | AH19: =IFERROR(AH18*변수!AH29,"") | AI19: =IFERROR(AI18*변수!AI29,"") | AJ19: =SUM(AF19:AI19) | AK19: =IFERROR(AK18*변수!AK29,"") | AL19: =IFERROR(AL18*변수!AL29,"") | AM19: =IFERROR(AM18*변수!AM29,"") | AN19: =IFERROR(AN18*변수!AN29,"") | AO19: =SUM(AK19:AN19)
A20: 당기순이익 | B20: 손익 | C20: 억원 | D20: 당기순이익 | E20: =IFERROR(VLOOKUP($D20,BS연결,MATCH(E$1,BS연결H,0),0)/100,"") | G20: =IFERROR(VLOOKUP($D20,BS연결,MATCH(G$1,BS연결H,0),0)/100,"") | H20: =IFERROR(VLOOKUP($D20,BS연결,MATCH(H$1,BS연결H,0),0)/100,"") | I20: =IFERROR(VLOOKUP($D20,BS연결,MATCH(I$1,BS연결H,0),0)/100,"") | J20: =IFERROR(VLOOKUP($D20,BS연결,MATCH(J$1,BS연결H,0),0)/100,"") | K20: =SUM(G20:J20) | L20: =IFERROR(VLOOKUP($D20,BS연결,MATCH(L$1,BS연결H,0),0)/100,"") | M20: =IFERROR(VLOOKUP($D20,BS연결,MATCH(M$1,BS연결H,0),0)/100,"") | N20: =IFERROR(VLOOKUP($D20,BS연결,MATCH(N$1,BS연결H,0),0)/100,"") | O20: =IFERROR(VLOOKUP($D20,BS연결,MATCH(O$1,BS연결H,0),0)/100,"") | P20: =IFERROR(VLOOKUP($D20,BS연결,MATCH(P$1,BS연결H,0),0)/100,"") | Q20: =IFERROR(VLOOKUP($D20,BS연결,MATCH(Q$1,BS연결H,0),0)/100,"") | R20: =IFERROR(VLOOKUP($D20,BS연결,MATCH(R$1,BS연결H,0),0)/100,"") | S20: =IFERROR(VLOOKUP($D20,BS연결,MATCH(S$1,BS연결H,0),0)/100,"") | ... AB20: =IFERROR(VLOOKUP($D20,BS연결,MATCH(AB$1,BS연결H,0),0)/100,"") | AC20: =IFERROR(AC18-AC19,"") | AD20: =IFERROR(AD18-AD19,"") | AE20: =SUM(AA20:AD20) | AF20: =IFERROR(AF18-AF19,"") | AG20: =IFERROR(AG18-AG19,"") | AH20: =IFERROR(AH18-AH19,"") | AI20: =IFERROR(AI18-AI19,"") | AJ20: =SUM(AF20:AI20) | AK20: =IFERROR(AK18-AK19,"") | AL20: =IFERROR(AL18-AL19,"") | AM20: =IFERROR(AM18-AM19,"") | AN20: =IFERROR(AN18-AN19,"") | AO20: =SUM(AK20:AN20)
A21: 지배주주순이익 | B21: 손익 | C21: 억원 | D21: (지배주주지분)당기순이익 | E21: =IFERROR(VLOOKUP($D21,BS연결,MATCH(E$1,BS연결H,0),0)/100,"") | G21: =IFERROR(VLOOKUP($D21,BS연결,MATCH(G$1,BS연결H,0),0)/100,"") | H21: =IFERROR(VLOOKUP($D21,BS연결,MATCH(H$1,BS연결H,0),0)/100,"") | I21: =IFERROR(VLOOKUP($D21,BS연결,MATCH(I$1,BS연결H,0),0)/100,"") | J21: =IFERROR(VLOOKUP($D21,BS연결,MATCH(J$1,BS연결H,0),0)/100,"") | K21: =SUM(G21:J21) | L21: =IFERROR(VLOOKUP($D21,BS연결,MATCH(L$1,BS연결H,0),0)/100,"") | M21: =IFERROR(VLOOKUP($D21,BS연결,MATCH(M$1,BS연결H,0),0)/100,"") | N21: =IFERROR(VLOOKUP($D21,BS연결,MATCH(N$1,BS연결H,0),0)/100,"") | O21: =IFERROR(VLOOKUP($D21,BS연결,MATCH(O$1,BS연결H,0),0)/100,"") | P21: =IFERROR(VLOOKUP($D21,BS연결,MATCH(P$1,BS연결H,0),0)/100,"") | Q21: =IFERROR(VLOOKUP($D21,BS연결,MATCH(Q$1,BS연결H,0),0)/100,"") | R21: =IFERROR(VLOOKUP($D21,BS연결,MATCH(R$1,BS연결H,0),0)/100,"") | S21: =IFERROR(VLOOKUP($D21,BS연결,MATCH(S$1,BS연결H,0),0)/100,"") | ... AB21: =IFERROR(VLOOKUP($D21,BS연결,MATCH(AB$1,BS연결H,0),0)/100,"") | AC21: =IFERROR(AC20*변수!AC30,"") | AD21: =IFERROR(AD20*변수!AD30,"") | AE21: =SUM(AA21:AD21) | AF21: =IFERROR(AF20*변수!AF30,"") | AG21: =IFERROR(AG20*변수!AG30,"") | AH21: =IFERROR(AH20*변수!AH30,"") | AI21: =IFERROR(AI20*변수!AI30,"") | AJ21: =SUM(AF21:AI21) | AK21: =IFERROR(AK20*변수!AK30,"") | AL21: =IFERROR(AL20*변수!AL30,"") | AM21: =IFERROR(AM20*변수!AM30,"") | AN21: =IFERROR(AN20*변수!AN30,"") | AO21: =SUM(AK21:AN21)
A22: 중단사업이익 | B22: 손익 | C22: 억원 | D22: 중단사업이익 | K22: =SUM(G22:J22) | P22: =SUM(L22:O22) | R22: =IFERROR(VLOOKUP($D22,BS연결,MATCH(R$1,BS연결H,0),0)/100,"") | S22: =IFERROR(VLOOKUP($D22,BS연결,MATCH(S$1,BS연결H,0),0)/100,"") | T22: =IFERROR(VLOOKUP($D22,BS연결,MATCH(T$1,BS연결H,0),0)/100,"") | U22: =SUM(Q22:T22) | Z22: =SUM(V22:Y22) | AE22: =SUM(AA22:AD22) | AJ22: =SUM(AF22:AI22) | AO22: =SUM(AK22:AN22)
A23: 자산총계 | B23: 재무상태 | C23: 억원 | D23: 자산총계 | E23: =IFERROR(VLOOKUP($D23,BS연결,MATCH(E$1,BS연결H,0),0)/100,"") | F23: =IFERROR(VLOOKUP($D23,BS연결,MATCH(F$1,BS연결H,0),0)/100,"") | G23: =IFERROR(VLOOKUP($D23,BS연결,MATCH(G$1,BS연결H,0),0)/100,"") | H23: =IFERROR(VLOOKUP($D23,BS연결,MATCH(H$1,BS연결H,0),0)/100,"") | I23: =IFERROR(VLOOKUP($D23,BS연결,MATCH(I$1,BS연결H,0),0)/100,"") | J23: =IFERROR(VLOOKUP($D23,BS연결,MATCH(J$1,BS연결H,0),0)/100,"") | K23: =IFERROR(VLOOKUP($D23,BS연결,MATCH(K$1,BS연결H,0),0)/100,"") | L23: =IFERROR(VLOOKUP($D23,BS연결,MATCH(L$1,BS연결H,0),0)/100,"") | ... AB23: =IFERROR(VLOOKUP($D23,BS연결,MATCH(AB$1,BS연결H,0),0)/100,"") | AC23: =IFERROR(AC24+AC25,"") | AD23: =IFERROR(AD24+AD25,"") | AE23: =AD23 | AF23: =IFERROR(AF24+AF25,"") | AG23: =IFERROR(AG24+AG25,"") | AH23: =IFERROR(AH24+AH25,"") | AI23: =IFERROR(AI24+AI25,"") | AJ23: =AI23 | AK23: =IFERROR(AK24+AK25,"") | AL23: =IFERROR(AL24+AL25,"") | AM23: =IFERROR(AM24+AM25,"") | AN23: =IFERROR(AN24+AN25,"") | AO23: =AN23
A24: 부채총계 | B24: 재무상태 | C24: 억원 | D24: 부채총계 | E24: =IFERROR(VLOOKUP($D24,BS연결,MATCH(E$1,BS연결H,0),0)/100,"") | F24: =IFERROR(VLOOKUP($D24,BS연결,MATCH(F$1,BS연결H,0),0)/100,"") | G24: =IFERROR(VLOOKUP($D24,BS연결,MATCH(G$1,BS연결H,0),0)/100,"") | H24: =IFERROR(VLOOKUP($D24,BS연결,MATCH(H$1,BS연결H,0),0)/100,"") | I24: =IFERROR(VLOOKUP($D24,BS연결,MATCH(I$1,BS연결H,0),0)/100,"") | J24: =IFERROR(VLOOKUP($D24,BS연결,MATCH(J$1,BS연결H,0),0)/100,"") | K24: =IFERROR(VLOOKUP($D24,BS연결,MATCH(K$1,BS연결H,0),0)/100,"") | L24: =IFERROR(VLOOKUP($D24,BS연결,MATCH(L$1,BS연결H,0),0)/100,"") | ... AB24: =IFERROR(VLOOKUP($D24,BS연결,MATCH(AB$1,BS연결H,0),0)/100,"") | AC24: =IFERROR(AB24*(1+변수!AC32),"") | AD24: =IFERROR(AC24*(1+변수!AD32),"") | AE24: =AD24 | AF24: =IFERROR(AD24*(1+변수!AF32),"") | AG24: =IFERROR(AF24*(1+변수!AG32),"") | AH24: =IFERROR(AG24*(1+변수!AH32),"") | AI24: =IFERROR(AH24*(1+변수!AI32),"") | AJ24: =AI24 | AK24: =IFERROR(AI24*(1+변수!AK32),"") | AL24: =IFERROR(AK24*(1+변수!AL32),"") | AM24: =IFERROR(AL24*(1+변수!AM32),"") | AN24: =IFERROR(AM24*(1+변수!AN32),"") | AO24: =AN24
A25: 자본총계 | B25: 재무상태 | C25: 억원 | D25: 자본총계 | E25: =IFERROR(VLOOKUP($D25,BS연결,MATCH(E$1,BS연결H,0),0)/100,"") | F25: =IFERROR(VLOOKUP($D25,BS연결,MATCH(F$1,BS연결H,0),0)/100,"") | G25: =IFERROR(VLOOKUP($D25,BS연결,MATCH(G$1,BS연결H,0),0)/100,"") | H25: =IFERROR(VLOOKUP($D25,BS연결,MATCH(H$1,BS연결H,0),0)/100,"") | I25: =IFERROR(VLOOKUP($D25,BS연결,MATCH(I$1,BS연결H,0),0)/100,"") | J25: =IFERROR(VLOOKUP($D25,BS연결,MATCH(J$1,BS연결H,0),0)/100,"") | K25: =IFERROR(VLOOKUP($D25,BS연결,MATCH(K$1,BS연결H,0),0)/100,"") | L25: =IFERROR(VLOOKUP($D25,BS연결,MATCH(L$1,BS연결H,0),0)/100,"") | ... AB25: =IFERROR(VLOOKUP($D25,BS연결,MATCH(AB$1,BS연결H,0),0)/100,"") | AC25: =IFERROR(AB25+AC20-변수!AC33,"") | AD25: =IFERROR(AC25+AD20-변수!AD33,"") | AE25: =AD25 | AF25: =IFERROR(AD25+AF20-변수!AF33,"") | AG25: =IFERROR(AF25+AG20-변수!AG33,"") | AH25: =IFERROR(AG25+AH20-변수!AH33,"") | AI25: =IFERROR(AH25+AI20-변수!AI33,"") | AJ25: =AI25 | AK25: =IFERROR(AI25+AK20-변수!AK33,"") | AL25: =IFERROR(AK25+AL20-변수!AL33,"") | AM25: =IFERROR(AL25+AM20-변수!AM33,"") | AN25: =IFERROR(AM25+AN20-변수!AN33,"") | AO25: =AN25
A26: 지배주주지분 | B26: 재무상태 | C26: 억원 | D26: 지배주주지분 | E26: =IFERROR(VLOOKUP($D26,BS연결,MATCH(E$1,BS연결H,0),0)/100,"") | F26: =IFERROR(VLOOKUP($D26,BS연결,MATCH(F$1,BS연결H,0),0)/100,"") | G26: =IFERROR(VLOOKUP($D26,BS연결,MATCH(G$1,BS연결H,0),0)/100,"") | H26: =IFERROR(VLOOKUP($D26,BS연결,MATCH(H$1,BS연결H,0),0)/100,"") | I26: =IFERROR(VLOOKUP($D26,BS연결,MATCH(I$1,BS연결H,0),0)/100,"") | J26: =IFERROR(VLOOKUP($D26,BS연결,MATCH(J$1,BS연결H,0),0)/100,"") | K26: =IFERROR(VLOOKUP($D26,BS연결,MATCH(K$1,BS연결H,0),0)/100,"") | L26: =IFERROR(VLOOKUP($D26,BS연결,MATCH(L$1,BS연결H,0),0)/100,"") | ... AB26: =IFERROR(VLOOKUP($D26,BS연결,MATCH(AB$1,BS연결H,0),0)/100,"") | AC26: =IFERROR(AB26+AC21-변수!AC34,"") | AD26: =IFERROR(AC26+AD21-변수!AD34,"") | AE26: =AD26 | AF26: =IFERROR(AD26+AF21-변수!AF34,"") | AG26: =IFERROR(AF26+AG21-변수!AG34,"") | AH26: =IFERROR(AG26+AH21-변수!AH34,"") | AI26: =IFERROR(AH26+AI21-변수!AI34,"") | AJ26: =AI26 | AK26: =IFERROR(AI26+AK21-변수!AK34,"") | AL26: =IFERROR(AK26+AL21-변수!AL34,"") | AM26: =IFERROR(AL26+AM21-변수!AM34,"") | AN26: =IFERROR(AM26+AN21-변수!AN34,"") | AO26: =AN26
A27: 총차입금 | B27: 재무상태 | C27: 억원 | D27: 총차입금 | E27: =IFERROR(VLOOKUP($D27,BS연결,MATCH(E$1,BS연결H,0),0)/100,"") | F27: =IFERROR(VLOOKUP($D27,BS연결,MATCH(F$1,BS연결H,0),0)/100,"") | G27: =IFERROR(VLOOKUP($D27,BS연결,MATCH(G$1,BS연결H,0),0)/100,"") | H27: =IFERROR(VLOOKUP($D27,BS연결,MATCH(H$1,BS연결H,0),0)/100,"") | I27: =IFERROR(VLOOKUP($D27,BS연결,MATCH(I$1,BS연결H,0),0)/100,"") | J27: =IFERROR(VLOOKUP($D27,BS연결,MATCH(J$1,BS연결H,0),0)/100,"") | K27: =IFERROR(VLOOKUP($D27,BS연결,MATCH(K$1,BS연결H,0),0)/100,"") | L27: =IFERROR(VLOOKUP($D27,BS연결,MATCH(L$1,BS연결H,0),0)/100,"") | ... AB27: =IFERROR(VLOOKUP($D27,BS연결,MATCH(AB$1,BS연결H,0),0)/100,"") | AC27: =IFERROR(AB27*(1+변수!AC35),"") | AD27: =IFERROR(AC27*(1+변수!AD35),"") | AE27: =AD27 | AF27: =IFERROR(AD27*(1+변수!AF35),"") | AG27: =IFERROR(AF27*(1+변수!AG35),"") | AH27: =IFERROR(AG27*(1+변수!AH35),"") | AI27: =IFERROR(AH27*(1+변수!AI35),"") | AJ27: =AI27 | AK27: =IFERROR(AI27*(1+변수!AK35),"") | AL27: =IFERROR(AK27*(1+변수!AL35),"") | AM27: =IFERROR(AL27*(1+변수!AM35),"") | AN27: =IFERROR(AM27*(1+변수!AN35),"") | AO27: =AN27
A28: 순차입금 | B28: 재무상태 | C28: 억원 | D28: 순차입금 | E28: =IFERROR(VLOOKUP($D28,BS연결,MATCH(E$1,BS연결H,0),0)/100,"") | F28: =IFERROR(VLOOKUP($D28,BS연결,MATCH(F$1,BS연결H,0),0)/100,"") | G28: =IFERROR(VLOOKUP($D28,BS연결,MATCH(G$1,BS연결H,0),0)/100,"") | H28: =IFERROR(VLOOKUP($D28,BS연결,MATCH(H$1,BS연결H,0),0)/100,"") | I28: =IFERROR(VLOOKUP($D28,BS연결,MATCH(I$1,BS연결H,0),0)/100,"") | J28: =IFERROR(VLOOKUP($D28,BS연결,MATCH(J$1,BS연결H,0),0)/100,"") | K28: =IFERROR(VLOOKUP($D28,BS연결,MATCH(K$1,BS연결H,0),0)/100,"") | L28: =IFERROR(VLOOKUP($D28,BS연결,MATCH(L$1,BS연결H,0),0)/100,"") | ... AB28: =IFERROR(VLOOKUP($D28,BS연결,MATCH(AB$1,BS연결H,0),0)/100,"") | AC28: =IFERROR(AB28*(1+변수!AC36),"") | AD28: =IFERROR(AC28*(1+변수!AD36),"") | AE28: =AD28 | AF28: =IFERROR(AD28*(1+변수!AF36),"") | AG28: =IFERROR(AF28*(1+변수!AG36),"") | AH28: =IFERROR(AG28*(1+변수!AH36),"") | AI28: =IFERROR(AH28*(1+변수!AI36),"") | AJ28: =AI28 | AK28: =IFERROR(AI28*(1+변수!AK36),"") | AL28: =IFERROR(AK28*(1+변수!AL36),"") | AM28: =IFERROR(AL28*(1+변수!AM36),"") | AN28: =IFERROR(AM28*(1+변수!AN36),"") | AO28: =AN28
A29: 이자발생자산 | B29: 재무상태 | C29: 억원 | D29: 이자발생자산 | E29: =IFERROR(VLOOKUP($D29,BS연결,MATCH(E$1,BS연결H,0),0)/100,"") | F29: =IFERROR(VLOOKUP($D29,BS연결,MATCH(F$1,BS연결H,0),0)/100,"") | G29: =IFERROR(VLOOKUP($D29,BS연결,MATCH(G$1,BS연결H,0),0)/100,"") | H29: =IFERROR(VLOOKUP($D29,BS연결,MATCH(H$1,BS연결H,0),0)/100,"") | I29: =IFERROR(VLOOKUP($D29,BS연결,MATCH(I$1,BS연결H,0),0)/100,"") | J29: =IFERROR(VLOOKUP($D29,BS연결,MATCH(J$1,BS연결H,0),0)/100,"") | K29: =IFERROR(VLOOKUP($D29,BS연결,MATCH(K$1,BS연결H,0),0)/100,"") | L29: =IFERROR(VLOOKUP($D29,BS연결,MATCH(L$1,BS연결H,0),0)/100,"") | ... AB29: =IFERROR(VLOOKUP($D29,BS연결,MATCH(AB$1,BS연결H,0),0)/100,"") | AC29: =IFERROR(AB29*(1+변수!AC37),"") | AD29: =IFERROR(AC29*(1+변수!AD37),"") | AE29: =AD29 | AF29: =IFERROR(AD29*(1+변수!AF37),"") | AG29: =IFERROR(AF29*(1+변수!AG37),"") | AH29: =IFERROR(AG29*(1+변수!AH37),"") | AI29: =IFERROR(AH29*(1+변수!AI37),"") | AJ29: =AI29 | AK29: =IFERROR(AI29*(1+변수!AK37),"") | AL29: =IFERROR(AK29*(1+변수!AL37),"") | AM29: =IFERROR(AL29*(1+변수!AM37),"") | AN29: =IFERROR(AM29*(1+변수!AN37),"") | AO29: =AN29
A30: 현금및현금성자산 | B30: 재무상태 | C30: 억원 | D30: 현금및현금성자산 | E30: =IFERROR(VLOOKUP($D30,BS연결,MATCH(E$1,BS연결H,0),0)/100,"") | F30: =IFERROR(VLOOKUP($D30,BS연결,MATCH(F$1,BS연결H,0),0)/100,"") | G30: =IFERROR(VLOOKUP($D30,BS연결,MATCH(G$1,BS연결H,0),0)/100,"") | H30: =IFERROR(VLOOKUP($D30,BS연결,MATCH(H$1,BS연결H,0),0)/100,"") | I30: =IFERROR(VLOOKUP($D30,BS연결,MATCH(I$1,BS연결H,0),0)/100,"") | J30: =IFERROR(VLOOKUP($D30,BS연결,MATCH(J$1,BS연결H,0),0)/100,"") | K30: =IFERROR(VLOOKUP($D30,BS연결,MATCH(K$1,BS연결H,0),0)/100,"") | L30: =IFERROR(VLOOKUP($D30,BS연결,MATCH(L$1,BS연결H,0),0)/100,"") | ... AB30: =IFERROR(VLOOKUP($D30,BS연결,MATCH(AB$1,BS연결H,0),0)/100,"") | AE30: =AD30 | AJ30: =AI30 | AO30: =AN30
A31: CAPEX | B31: 현금흐름 | C31: 억원 | D31: CAPEX | E31: =IFERROR(VLOOKUP($D31,BS연결,MATCH(E$1,BS연결H,0),0)/100,"") | G31: =IFERROR(VLOOKUP($D31,BS연결,MATCH(G$1,BS연결H,0),0)/100,"") | H31: =IFERROR(VLOOKUP($D31,BS연결,MATCH(H$1,BS연결H,0),0)/100,"") | I31: =IFERROR(VLOOKUP($D31,BS연결,MATCH(I$1,BS연결H,0),0)/100,"") | J31: =IFERROR(VLOOKUP($D31,BS연결,MATCH(J$1,BS연결H,0),0)/100,"") | K31: =IFERROR(VLOOKUP($D31,BS연결,MATCH(K$1,BS연결H,0),0)/100,"") | L31: =IFERROR(VLOOKUP($D31,BS연결,MATCH(L$1,BS연결H,0),0)/100,"") | M31: =IFERROR(VLOOKUP($D31,BS연결,MATCH(M$1,BS연결H,0),0)/100,"") | N31: =IFERROR(VLOOKUP($D31,BS연결,MATCH(N$1,BS연결H,0),0)/100,"") | ... AB31: =IFERROR(VLOOKUP($D31,BS연결,MATCH(AB$1,BS연결H,0),0)/100,"") | AC31: =IFERROR(X31*(1+변수!AC39),"") | AD31: =IFERROR(Y31*(1+변수!AD39),"") | AE31: =SUM(AA31:AD31) | AF31: =IFERROR(AA31*(1+변수!AF39),"") | AG31: =IFERROR(AB31*(1+변수!AG39),"") | AH31: =IFERROR(AC31*(1+변수!AH39),"") | AI31: =IFERROR(AD31*(1+변수!AI39),"") | AJ31: =SUM(AF31:AI31) | AK31: =IFERROR(AF31*(1+변수!AK39),"") | AL31: =IFERROR(AG31*(1+변수!AL39),"") | AM31: =IFERROR(AH31*(1+변수!AM39),"") | AN31: =IFERROR(AI31*(1+변수!AN39),"") | AO31: =SUM(AK31:AN31)
A32: 영업활동현금흐름 | B32: 현금흐름 | C32: 억원 | D32: 영업활동으로인한현금흐름 | E32: =IFERROR(VLOOKUP($D32,BS연결,MATCH(E$1,BS연결H,0),0)/100,"") | G32: =IFERROR(VLOOKUP($D32,BS연결,MATCH(G$1,BS연결H,0),0)/100,"") | H32: =IFERROR(VLOOKUP($D32,BS연결,MATCH(H$1,BS연결H,0),0)/100,"") | I32: =IFERROR(VLOOKUP($D32,BS연결,MATCH(I$1,BS연결H,0),0)/100,"") | J32: =IFERROR(VLOOKUP($D32,BS연결,MATCH(J$1,BS연결H,0),0)/100,"") | K32: =IFERROR(VLOOKUP($D32,BS연결,MATCH(K$1,BS연결H,0),0)/100,"") | L32: =IFERROR(VLOOKUP($D32,BS연결,MATCH(L$1,BS연결H,0),0)/100,"") | M32: =IFERROR(VLOOKUP($D32,BS연결,MATCH(M$1,BS연결H,0),0)/100,"") | N32: =IFERROR(VLOOKUP($D32,BS연결,MATCH(N$1,BS연결H,0),0)/100,"") | ... AB32: =IFERROR(VLOOKUP($D32,BS연결,MATCH(AB$1,BS연결H,0),0)/100,"") | AE32: =SUM(AA32:AD32) | AJ32: =SUM(AF32:AI32) | AO32: =SUM(AK32:AN32)
A33: 주식수 | B33: 주당 | C33: 백만주 | D33: 유통주식수 | E33: 4.4844245 | F33: =E33 | G33: 4.4844245 | H33: 4.4844245 | I33: 4.4844245 | J33: 4.4844245 | K33: =J33 | L33: 4.4844245 | M33: 4.694862 | N33: 4.694862 | O33: 4.694862 | P33: =O33 | Q33: 5.710606 | R33: 7.5332387 | S33: 7.53316 | T33: 7.657538 | U33: =T33 | V33: 8.3137058 | W33: 8.3574557 | X33: 8.3574557 | Y33: 8.3574557 | Z33: =Y33 | AA33: 9.9062423 | AB33: 9.9062423 | AC33: =IFERROR(AB33*(1+변수!AC41),"") | AD33: =IFERROR(AC33*(1+변수!AD41),"") | AE33: =AD33 | AF33: =IFERROR(AD33*(1+변수!AF41),"") | AG33: =IFERROR(AF33*(1+변수!AG41),"") | AH33: =IFERROR(AG33*(1+변수!AH41),"") | AI33: =IFERROR(AH33*(1+변수!AI41),"") | AJ33: =AI33 | AK33: =IFERROR(AI33*(1+변수!AK41),"") | AL33: =IFERROR(AK33*(1+변수!AL41),"") | AM33: =IFERROR(AL33*(1+변수!AM41),"") | AN33: =IFERROR(AM33*(1+변수!AN41),"") | AO33: =AN33
A34: EPS | B34: 주당 | C34: 원 | D34: EPS | E34: =IFERROR(E21*100/E33,"") | G34: =IFERROR(G21*100/G33,"") | H34: =IFERROR(H21*100/H33,"") | I34: =IFERROR(I21*100/I33,"") | J34: =IFERROR(J21*100/J33,"") | K34: =SUM(G34:J34) | L34: =IFERROR(L21*100/L33,"") | M34: =IFERROR(M21*100/M33,"") | N34: =IFERROR(N21*100/N33,"") | O34: =IFERROR(O21*100/O33,"") | P34: =SUM(L34:O34) | Q34: =IFERROR(Q21*100/Q33,"") | R34: =IFERROR(R21*100/R33,"") | S34: =IFERROR(S21*100/S33,"") | T34: =IFERROR(T21*100/T33,"") | U34: =SUM(Q34:T34) | V34: =IFERROR(V21*100/V33,"") | W34: =IFERROR(W21*100/W33,"") | X34: =IFERROR(X21*100/X33,"") | Y34: =IFERROR(Y21*100/Y33,"") | Z34: =SUM(V34:Y34) | AA34: =IFERROR(AA21*100/AA33,"") | AB34: =IFERROR(AB21*100/AB33,"") | AC34: =IFERROR(AC21*100/AC33,"") | AD34: =IFERROR(AD21*100/AD33,"") | AE34: =SUM(AA34:AD34) | AF34: =IFERROR(AF21*100/AF33,"") | AG34: =IFERROR(AG21*100/AG33,"") | AH34: =IFERROR(AH21*100/AH33,"") | AI34: =IFERROR(AI21*100/AI33,"") | AJ34: =SUM(AF34:AI34) | AK34: =IFERROR(AK21*100/AK33,"") | AL34: =IFERROR(AL21*100/AL33,"") | AM34: =IFERROR(AM21*100/AM33,"") | AN34: =IFERROR(AN21*100/AN33,"") | AO34: =SUM(AK34:AN34)
A35: 조정EPS | B35: 주당 | C35: 원 | D35: 조정 EPS(일회성 의심 분기의 초과 비영업손익 세후 차감 — 모델 추정) | E35: =IFERROR(E34,"") | G35: =IFERROR(G34,"") | H35: =IFERROR(H34,"") | I35: =IFERROR(I34,"") | J35: =IFERROR(J34,"") | K35: =SUM(G35:J35) | L35: =IFERROR(L34,"") | M35: =IFERROR(M34,"") | N35: =IFERROR(N34,"") | O35: =IFERROR(O34,"") | P35: =SUM(L35:O35) | Q35: =IFERROR(Q34,"") | R35: =IFERROR(R34,"") | S35: =IFERROR(S34,"") | T35: =IFERROR(T34,"") | U35: =SUM(Q35:T35) | V35: =IFERROR(V34,"") | W35: =IFERROR(W34,"") | X35: =IFERROR(X34,"") | Y35: =IFERROR(Y34,"") | Z35: =SUM(V35:Y35) | AA35: =IFERROR(AA34,"") | AB35: =IFERROR((AB21-(35.56)*(1.0))*100/AB33,"") | AC35: =IFERROR(AC34,"") | AD35: =IFERROR(AD34,"") | AE35: =SUM(AA35:AD35) | AF35: =IFERROR(AF34,"") | AG35: =IFERROR(AG34,"") | AH35: =IFERROR(AH34,"") | AI35: =IFERROR(AI34,"") | AJ35: =SUM(AF35:AI35) | AK35: =IFERROR(AK34,"") | AL35: =IFERROR(AL34,"") | AM35: =IFERROR(AM34,"") | AN35: =IFERROR(AN34,"") | AO35: =SUM(AK35:AN35)
A36: BPS | B36: 주당 | C36: 원 | D36: BPS | E36: =IFERROR(E26*100/E33,"") | F36: =E36 | G36: =IFERROR(G26*100/G33,"") | H36: =IFERROR(H26*100/H33,"") | I36: =IFERROR(I26*100/I33,"") | J36: =IFERROR(J26*100/J33,"") | K36: =J36 | L36: =IFERROR(L26*100/L33,"") | M36: =IFERROR(M26*100/M33,"") | N36: =IFERROR(N26*100/N33,"") | O36: =IFERROR(O26*100/O33,"") | P36: =O36 | Q36: =IFERROR(Q26*100/Q33,"") | R36: =IFERROR(R26*100/R33,"") | S36: =IFERROR(S26*100/S33,"") | T36: =IFERROR(T26*100/T33,"") | U36: =T36 | V36: =IFERROR(V26*100/V33,"") | W36: =IFERROR(W26*100/W33,"") | X36: =IFERROR(X26*100/X33,"") | Y36: =IFERROR(Y26*100/Y33,"") | Z36: =Y36 | AA36: =IFERROR(AA26*100/AA33,"") | AB36: =IFERROR(AB26*100/AB33,"") | AC36: =IFERROR(AC26*100/AC33,"") | AD36: =IFERROR(AD26*100/AD33,"") | AE36: =AD36 | AF36: =IFERROR(AF26*100/AF33,"") | AG36: =IFERROR(AG26*100/AG33,"") | AH36: =IFERROR(AH26*100/AH33,"") | AI36: =IFERROR(AI26*100/AI33,"") | AJ36: =AI36 | AK36: =IFERROR(AK26*100/AK33,"") | AL36: =IFERROR(AL26*100/AL33,"") | AM36: =IFERROR(AM26*100/AM33,"") | AN36: =IFERROR(AN26*100/AN33,"") | AO36: =AN36
A37: DPS | B37: 주당 | C37: 원 | D37: DPS(보통주) | E37: 0 | F37: 0 | J37: 0 | K37: =SUM(G37:J37) | O37: 0 | P37: =SUM(L37:O37) | T37: 0 | U37: =SUM(Q37:T37) | Y37: 0 | Z37: =SUM(V37:Y37) | AD37: =변수!AD42 | AE37: =SUM(AA37:AD37) | AI37: =변수!AI42 | AJ37: =SUM(AF37:AI37) | AN37: =변수!AN42 | AO37: =SUM(AK37:AN37)
A38: PER | B38: 주당 | C38: 배 | D38: PER | F38: =E38 | K38: =J38 | O38: =IFERROR(변수!O18/(L34+M34+N34+O34),"") | P38: =O38 | Q38: =IFERROR(변수!Q18/(M34+N34+O34+Q34),"") | U38: =T38 | Z38: =Y38 | AE38: =AD38 | AJ38: =AI38 | AO38: =AN38
A39: PBR | B39: 주당 | C39: 배 | D39: PBR | E39: =IFERROR(변수!E18/E36,"") | F39: =E39 | G39: =IFERROR(변수!G18/G36,"") | H39: =IFERROR(변수!H18/H36,"") | I39: =IFERROR(변수!I18/I36,"") | J39: =IFERROR(변수!J18/J36,"") | K39: =J39 | L39: =IFERROR(변수!L18/L36,"") | M39: =IFERROR(변수!M18/M36,"") | N39: =IFERROR(변수!N18/N36,"") | O39: =IFERROR(변수!O18/O36,"") | P39: =O39 | Q39: =IFERROR(변수!Q18/Q36,"") | R39: =IFERROR(변수!R18/R36,"") | S39: =IFERROR(변수!S18/S36,"") | T39: =IFERROR(변수!T18/T36,"") | U39: =T39 | V39: =IFERROR(변수!V18/V36,"") | W39: =IFERROR(변수!W18/W36,"") | X39: =IFERROR(변수!X18/X36,"") | Y39: =IFERROR(변수!Y18/Y36,"") | Z39: =Y39 | AA39: =IFERROR(변수!AA18/AA36,"") | AB39: =IFERROR(변수!AB18/AB36,"") | AC39: =IFERROR(변수!$D$45/AC36,"") | AD39: =IFERROR(변수!$D$45/AD36,"") | AE39: =AD39 | AF39: =IFERROR(변수!$D$45/AF36,"") | AG39: =IFERROR(변수!$D$45/AG36,"") | AH39: =IFERROR(변수!$D$45/AH36,"") | AI39: =IFERROR(변수!$D$45/AI36,"") | AJ39: =AI39 | AK39: =IFERROR(변수!$D$45/AK36,"") | AL39: =IFERROR(변수!$D$45/AL36,"") | AM39: =IFERROR(변수!$D$45/AM36,"") | AN39: =IFERROR(변수!$D$45/AN36,"") | AO39: =AN39
A40: 매출전사 | B40: 사업부 | C40: 억원 | D40: 매출 전사(부문 미분리) | E40: 85.02 | G40: 147.35 | H40: 187.07 | I40: 171.76 | J40: 238.12 | K40: =SUM(G40:J40) | L40: 215.27 | M40: 234.09 | N40: 232.95 | O40: 181.21 | P40: =SUM(L40:O40) | Q40: 153.68 | R40: 55.04 | S40: 60.6 | T40: 80.93 | U40: =SUM(Q40:T40) | V40: 90.21 | W40: 112.09 | X40: 120.4 | Y40: 71.77 | Z40: =SUM(V40:Y40) | AA40: 104.01 | AB40: 94.65 | AC40: =IFERROR(AC5,"") | AD40: =IFERROR(AD5,"") | AE40: =SUM(AA40:AD40) | AF40: =IFERROR(AF5,"") | AG40: =IFERROR(AG5,"") | AH40: =IFERROR(AH5,"") | AI40: =IFERROR(AI5,"") | AJ40: =SUM(AF40:AI40) | AK40: =IFERROR(AK5,"") | AL40: =IFERROR(AL5,"") | AM40: =IFERROR(AM5,"") | AN40: =IFERROR(AN5,"") | AO40: =SUM(AK40:AN40)
A41: OP전사 | B41: 사업부 | C41: 억원 | D41: OP 전사(부문 미분리) | E41: -35.69 | G41: -16.94 | H41: -16.03 | I41: -35.21 | J41: -77.34 | K41: =SUM(G41:J41) | L41: 2.05 | M41: 60.53 | N41: 16.56 | O41: 29.5 | P41: =SUM(L41:O41) | Q41: 25.41 | R41: 6.48 | S41: -10.96 | T41: -10.22 | U41: =SUM(Q41:T41) | V41: -17.56 | W41: -14.76 | X41: -10.12 | Y41: -3.76 | Z41: =SUM(V41:Y41) | AA41: -7.94 | AB41: -8.06 | AC41: =IFERROR(AC9,"") | AD41: =IFERROR(AD9,"") | AE41: =SUM(AA41:AD41) | AF41: =IFERROR(AF9,"") | AG41: =IFERROR(AG9,"") | AH41: =IFERROR(AH9,"") | AI41: =IFERROR(AI9,"") | AJ41: =SUM(AF41:AI41) | AK41: =IFERROR(AK9,"") | AL41: =IFERROR(AL9,"") | AM41: =IFERROR(AM9,"") | AN41: =IFERROR(AN9,"") | AO41: =SUM(AK41:AN41)
B42: 비율(참고)
A43: NPM | C43: % | D43: 지배주주순이익 / 매출액 | E43: =IFERROR(E21/E5,"") | F43: =IFERROR(F21/F5,"") | G43: =IFERROR(G21/G5,"") | H43: =IFERROR(H21/H5,"") | I43: =IFERROR(I21/I5,"") | J43: =IFERROR(J21/J5,"") | K43: =IFERROR(K21/K5,"") | L43: =IFERROR(L21/L5,"") | ... AO43: =IFERROR(AO21/AO5,"")
A44: 매출원가율 | C44: % | D44: 매출원가 / 매출액 | E44: =IFERROR(E6/E5,"") | F44: =IFERROR(F6/F5,"") | G44: =IFERROR(G6/G5,"") | H44: =IFERROR(H6/H5,"") | I44: =IFERROR(I6/I5,"") | J44: =IFERROR(J6/J5,"") | K44: =IFERROR(K6/K5,"") | L44: =IFERROR(L6/L5,"") | ... AO44: =IFERROR(AO6/AO5,"")
A45: 판관비율 | C45: % | D45: 판관비 / 매출액 | E45: =IFERROR(E8/E5,"") | F45: =IFERROR(F8/F5,"") | G45: =IFERROR(G8/G5,"") | H45: =IFERROR(H8/H5,"") | I45: =IFERROR(I8/I5,"") | J45: =IFERROR(J8/J5,"") | K45: =IFERROR(K8/K5,"") | L45: =IFERROR(L8/L5,"") | ... AO45: =IFERROR(AO8/AO5,"")

Sheet 분기
C1: 이름: 분기H — subQ 를 이름으로 VLOOKUP(억원) | E1: 4Q21 | F1: 1Q22 | G1: 2Q22 | H1: 3Q22 | I1: 4Q22 | J1: 1Q23 | K1: 2Q23 | L1: 3Q23 | M1: 4Q23 | N1: 1Q24 | O1: 2Q24 | P1: 3Q24 | Q1: 4Q24 | R1: 1Q25 | S1: 2Q25 | T1: 3Q25 | U1: 4Q25 | V1: 1Q26 | W1: 2Q26 | X1: 3Q26 | Y1: 4Q26 | Z1: 1Q27 | AA1: 2Q27 | AB1: 3Q27 | AC1: 4Q27 | AD1: 1Q28 | AE1: 2Q28 | AF1: 3Q28 | AG1: 4Q28
C2: 종가: | D2: =변수!D45
C3: 기준일: | D3: 20261008 | E3: 1 | F3: 2 | G3: 3 | H3: 4 | I3: 5 | J3: 6 | K3: 7 | L3: 8 | M3: 9 | N3: 10 | O3: 11 | P3: 12 | Q3: 13 | R3: 14 | S3: 15 | T3: 16 | U3: 17 | V3: 18 | W3: 19 | X3: 20 | Y3: 21 | Z3: 22 | AA3: 23 | AB3: 24 | AC3: 25 | AD3: 26 | AE3: 27 | AF3: 28 | AG3: 29
E4: 2021.12 | F4: 2022.03 | G4: 2022.06 | H4: 2022.09 | I4: 2022.12 | J4: 2023.03 | K4: 2023.06 | L4: 2023.09 | M4: 2023.12 | N4: 2024.03 | O4: 2024.06 | P4: 2024.09 | Q4: 2024.12 | R4: 2025.03 | S4: 2025.06 | T4: 2025.09 | U4: 2025.12 | V4: 2026.03 | W4: 2026.06 | X4: 2026.09 | Y4: 2026.12 | Z4: 2027.03 | AA4: 2027.06 | AB4: 2027.09 | AC4: 2027.12 | AD4: 2028.03 | AE4: 2028.06 | AF4: 2028.09 | AG4: 2028.12
A5: 매출액 | D5: 매출액 | E5: =IFERROR(VLOOKUP($A5,subQ,MATCH(E$1,SUBQH,0),0),"") | F5: =IFERROR(VLOOKUP($A5,subQ,MATCH(F$1,SUBQH,0),0),"") | G5: =IFERROR(VLOOKUP($A5,subQ,MATCH(G$1,SUBQH,0),0),"") | H5: =IFERROR(VLOOKUP($A5,subQ,MATCH(H$1,SUBQH,0),0),"") | I5: =IFERROR(VLOOKUP($A5,subQ,MATCH(I$1,SUBQH,0),0),"") | J5: =IFERROR(VLOOKUP($A5,subQ,MATCH(J$1,SUBQH,0),0),"") | K5: =IFERROR(VLOOKUP($A5,subQ,MATCH(K$1,SUBQH,0),0),"") | L5: =IFERROR(VLOOKUP($A5,subQ,MATCH(L$1,SUBQH,0),0),"") | ... AG5: =IFERROR(VLOOKUP($A5,subQ,MATCH(AG$1,SUBQH,0),0),"")
A6: 매출원가 | D6: 매출원가 | E6: =IFERROR(VLOOKUP($A6,subQ,MATCH(E$1,SUBQH,0),0),"") | F6: =IFERROR(VLOOKUP($A6,subQ,MATCH(F$1,SUBQH,0),0),"") | G6: =IFERROR(VLOOKUP($A6,subQ,MATCH(G$1,SUBQH,0),0),"") | H6: =IFERROR(VLOOKUP($A6,subQ,MATCH(H$1,SUBQH,0),0),"") | I6: =IFERROR(VLOOKUP($A6,subQ,MATCH(I$1,SUBQH,0),0),"") | J6: =IFERROR(VLOOKUP($A6,subQ,MATCH(J$1,SUBQH,0),0),"") | K6: =IFERROR(VLOOKUP($A6,subQ,MATCH(K$1,SUBQH,0),0),"") | L6: =IFERROR(VLOOKUP($A6,subQ,MATCH(L$1,SUBQH,0),0),"") | ... AG6: =IFERROR(VLOOKUP($A6,subQ,MATCH(AG$1,SUBQH,0),0),"")
A7: 매출총이익 | D7: 매출총이익 | E7: =IFERROR(VLOOKUP($A7,subQ,MATCH(E$1,SUBQH,0),0),"") | F7: =IFERROR(VLOOKUP($A7,subQ,MATCH(F$1,SUBQH,0),0),"") | G7: =IFERROR(VLOOKUP($A7,subQ,MATCH(G$1,SUBQH,0),0),"") | H7: =IFERROR(VLOOKUP($A7,subQ,MATCH(H$1,SUBQH,0),0),"") | I7: =IFERROR(VLOOKUP($A7,subQ,MATCH(I$1,SUBQH,0),0),"") | J7: =IFERROR(VLOOKUP($A7,subQ,MATCH(J$1,SUBQH,0),0),"") | K7: =IFERROR(VLOOKUP($A7,subQ,MATCH(K$1,SUBQH,0),0),"") | L7: =IFERROR(VLOOKUP($A7,subQ,MATCH(L$1,SUBQH,0),0),"") | ... AG7: =IFERROR(VLOOKUP($A7,subQ,MATCH(AG$1,SUBQH,0),0),"")
A8: 판관비 | D8: 판매비와관리비 | E8: =IFERROR(VLOOKUP($A8,subQ,MATCH(E$1,SUBQH,0),0),"") | F8: =IFERROR(VLOOKUP($A8,subQ,MATCH(F$1,SUBQH,0),0),"") | G8: =IFERROR(VLOOKUP($A8,subQ,MATCH(G$1,SUBQH,0),0),"") | H8: =IFERROR(VLOOKUP($A8,subQ,MATCH(H$1,SUBQH,0),0),"") | I8: =IFERROR(VLOOKUP($A8,subQ,MATCH(I$1,SUBQH,0),0),"") | J8: =IFERROR(VLOOKUP($A8,subQ,MATCH(J$1,SUBQH,0),0),"") | K8: =IFERROR(VLOOKUP($A8,subQ,MATCH(K$1,SUBQH,0),0),"") | L8: =IFERROR(VLOOKUP($A8,subQ,MATCH(L$1,SUBQH,0),0),"") | ... AG8: =IFERROR(VLOOKUP($A8,subQ,MATCH(AG$1,SUBQH,0),0),"")
A9: 영업이익 | D9: 영업이익 | E9: =IFERROR(VLOOKUP($A9,subQ,MATCH(E$1,SUBQH,0),0),"") | F9: =IFERROR(VLOOKUP($A9,subQ,MATCH(F$1,SUBQH,0),0),"") | G9: =IFERROR(VLOOKUP($A9,subQ,MATCH(G$1,SUBQH,0),0),"") | H9: =IFERROR(VLOOKUP($A9,subQ,MATCH(H$1,SUBQH,0),0),"") | I9: =IFERROR(VLOOKUP($A9,subQ,MATCH(I$1,SUBQH,0),0),"") | J9: =IFERROR(VLOOKUP($A9,subQ,MATCH(J$1,SUBQH,0),0),"") | K9: =IFERROR(VLOOKUP($A9,subQ,MATCH(K$1,SUBQH,0),0),"") | L9: =IFERROR(VLOOKUP($A9,subQ,MATCH(L$1,SUBQH,0),0),"") | ... AG9: =IFERROR(VLOOKUP($A9,subQ,MATCH(AG$1,SUBQH,0),0),"")
A10: OPM | D10: 영업이익률 | E10: =IFERROR(VLOOKUP($A10,subQ,MATCH(E$1,SUBQH,0),0),"") | F10: =IFERROR(VLOOKUP($A10,subQ,MATCH(F$1,SUBQH,0),0),"") | G10: =IFERROR(VLOOKUP($A10,subQ,MATCH(G$1,SUBQH,0),0),"") | H10: =IFERROR(VLOOKUP($A10,subQ,MATCH(H$1,SUBQH,0),0),"") | I10: =IFERROR(VLOOKUP($A10,subQ,MATCH(I$1,SUBQH,0),0),"") | J10: =IFERROR(VLOOKUP($A10,subQ,MATCH(J$1,SUBQH,0),0),"") | K10: =IFERROR(VLOOKUP($A10,subQ,MATCH(K$1,SUBQH,0),0),"") | L10: =IFERROR(VLOOKUP($A10,subQ,MATCH(L$1,SUBQH,0),0),"") | ... AG10: =IFERROR(VLOOKUP($A10,subQ,MATCH(AG$1,SUBQH,0),0),"")
A11: 금융손익 | D11: 금융손익(이자·환 포함) | E11: =IFERROR(VLOOKUP($A11,subQ,MATCH(E$1,SUBQH,0),0),"") | F11: =IFERROR(VLOOKUP($A11,subQ,MATCH(F$1,SUBQH,0),0),"") | G11: =IFERROR(VLOOKUP($A11,subQ,MATCH(G$1,SUBQH,0),0),"") | H11: =IFERROR(VLOOKUP($A11,subQ,MATCH(H$1,SUBQH,0),0),"") | I11: =IFERROR(VLOOKUP($A11,subQ,MATCH(I$1,SUBQH,0),0),"") | J11: =IFERROR(VLOOKUP($A11,subQ,MATCH(J$1,SUBQH,0),0),"") | K11: =IFERROR(VLOOKUP($A11,subQ,MATCH(K$1,SUBQH,0),0),"") | L11: =IFERROR(VLOOKUP($A11,subQ,MATCH(L$1,SUBQH,0),0),"") | ... AG11: =IFERROR(VLOOKUP($A11,subQ,MATCH(AG$1,SUBQH,0),0),"")
A12: 이자손익 | D12: 이자손익(이자수익 − 이자비용) | E12: =IFERROR(VLOOKUP($A12,subQ,MATCH(E$1,SUBQH,0),0),"") | F12: =IFERROR(VLOOKUP($A12,subQ,MATCH(F$1,SUBQH,0),0),"") | G12: =IFERROR(VLOOKUP($A12,subQ,MATCH(G$1,SUBQH,0),0),"") | H12: =IFERROR(VLOOKUP($A12,subQ,MATCH(H$1,SUBQH,0),0),"") | I12: =IFERROR(VLOOKUP($A12,subQ,MATCH(I$1,SUBQH,0),0),"") | J12: =IFERROR(VLOOKUP($A12,subQ,MATCH(J$1,SUBQH,0),0),"") | K12: =IFERROR(VLOOKUP($A12,subQ,MATCH(K$1,SUBQH,0),0),"") | L12: =IFERROR(VLOOKUP($A12,subQ,MATCH(L$1,SUBQH,0),0),"") | ... AG12: =IFERROR(VLOOKUP($A12,subQ,MATCH(AG$1,SUBQH,0),0),"")
A13: 외환손익 | D13: 외환손익(실적만; 추정 환효과는 환관련손익) | E13: =IFERROR(VLOOKUP($A13,subQ,MATCH(E$1,SUBQH,0),0),"") | F13: =IFERROR(VLOOKUP($A13,subQ,MATCH(F$1,SUBQH,0),0),"") | G13: =IFERROR(VLOOKUP($A13,subQ,MATCH(G$1,SUBQH,0),0),"") | H13: =IFERROR(VLOOKUP($A13,subQ,MATCH(H$1,SUBQH,0),0),"") | I13: =IFERROR(VLOOKUP($A13,subQ,MATCH(I$1,SUBQH,0),0),"") | J13: =IFERROR(VLOOKUP($A13,subQ,MATCH(J$1,SUBQH,0),0),"") | K13: =IFERROR(VLOOKUP($A13,subQ,MATCH(K$1,SUBQH,0),0),"") | L13: =IFERROR(VLOOKUP($A13,subQ,MATCH(L$1,SUBQH,0),0),"") | ... AG13: =IFERROR(VLOOKUP($A13,subQ,MATCH(AG$1,SUBQH,0),0),"")
A14: 파생상품손익 | D14: 파생상품손익 | E14: =IFERROR(VLOOKUP($A14,subQ,MATCH(E$1,SUBQH,0),0),"") | F14: =IFERROR(VLOOKUP($A14,subQ,MATCH(F$1,SUBQH,0),0),"") | G14: =IFERROR(VLOOKUP($A14,subQ,MATCH(G$1,SUBQH,0),0),"") | H14: =IFERROR(VLOOKUP($A14,subQ,MATCH(H$1,SUBQH,0),0),"") | I14: =IFERROR(VLOOKUP($A14,subQ,MATCH(I$1,SUBQH,0),0),"") | J14: =IFERROR(VLOOKUP($A14,subQ,MATCH(J$1,SUBQH,0),0),"") | K14: =IFERROR(VLOOKUP($A14,subQ,MATCH(K$1,SUBQH,0),0),"") | L14: =IFERROR(VLOOKUP($A14,subQ,MATCH(L$1,SUBQH,0),0),"") | ... AG14: =IFERROR(VLOOKUP($A14,subQ,MATCH(AG$1,SUBQH,0),0),"")
A15: 기타금융손익 | D15: 기타금융손익(금융손익 잔차) | E15: =IFERROR(VLOOKUP($A15,subQ,MATCH(E$1,SUBQH,0),0),"") | F15: =IFERROR(VLOOKUP($A15,subQ,MATCH(F$1,SUBQH,0),0),"") | G15: =IFERROR(VLOOKUP($A15,subQ,MATCH(G$1,SUBQH,0),0),"") | H15: =IFERROR(VLOOKUP($A15,subQ,MATCH(H$1,SUBQH,0),0),"") | I15: =IFERROR(VLOOKUP($A15,subQ,MATCH(I$1,SUBQH,0),0),"") | J15: =IFERROR(VLOOKUP($A15,subQ,MATCH(J$1,SUBQH,0),0),"") | K15: =IFERROR(VLOOKUP($A15,subQ,MATCH(K$1,SUBQH,0),0),"") | L15: =IFERROR(VLOOKUP($A15,subQ,MATCH(L$1,SUBQH,0),0),"") | ... AG15: =IFERROR(VLOOKUP($A15,subQ,MATCH(AG$1,SUBQH,0),0),"")
A16: 기타영업외손익 | D16: 기타영업외손익 | E16: =IFERROR(VLOOKUP($A16,subQ,MATCH(E$1,SUBQH,0),0),"") | F16: =IFERROR(VLOOKUP($A16,subQ,MATCH(F$1,SUBQH,0),0),"") | G16: =IFERROR(VLOOKUP($A16,subQ,MATCH(G$1,SUBQH,0),0),"") | H16: =IFERROR(VLOOKUP($A16,subQ,MATCH(H$1,SUBQH,0),0),"") | I16: =IFERROR(VLOOKUP($A16,subQ,MATCH(I$1,SUBQH,0),0),"") | J16: =IFERROR(VLOOKUP($A16,subQ,MATCH(J$1,SUBQH,0),0),"") | K16: =IFERROR(VLOOKUP($A16,subQ,MATCH(K$1,SUBQH,0),0),"") | L16: =IFERROR(VLOOKUP($A16,subQ,MATCH(L$1,SUBQH,0),0),"") | ... AG16: =IFERROR(VLOOKUP($A16,subQ,MATCH(AG$1,SUBQH,0),0),"")
... A42: NPM | D42: NPM | E42: =IFERROR(VLOOKUP($A42,subQ,MATCH(E$1,SUBQH,0),0),"") | F42: =IFERROR(VLOOKUP($A42,subQ,MATCH(F$1,SUBQH,0),0),"") | G42: =IFERROR(VLOOKUP($A42,subQ,MATCH(G$1,SUBQH,0),0),"") | H42: =IFERROR(VLOOKUP($A42,subQ,MATCH(H$1,SUBQH,0),0),"") | I42: =IFERROR(VLOOKUP($A42,subQ,MATCH(I$1,SUBQH,0),0),"") | J42: =IFERROR(VLOOKUP($A42,subQ,MATCH(J$1,SUBQH,0),0),"") | K42: =IFERROR(VLOOKUP($A42,subQ,MATCH(K$1,SUBQH,0),0),"") | L42: =IFERROR(VLOOKUP($A42,subQ,MATCH(L$1,SUBQH,0),0),"") | ... AG42: =IFERROR(VLOOKUP($A42,subQ,MATCH(AG$1,SUBQH,0),0),"")
A43: 매출액 YoY | D43: 매출액 YoY | I43: =IFERROR(I5/E5-1,"") | J43: =IFERROR(J5/F5-1,"") | K43: =IFERROR(K5/G5-1,"") | L43: =IFERROR(L5/H5-1,"") | M43: =IFERROR(M5/I5-1,"") | N43: =IFERROR(N5/J5-1,"") | O43: =IFERROR(O5/K5-1,"") | P43: =IFERROR(P5/L5-1,"") | ... AG43: =IFERROR(AG5/AC5-1,"")
A44: 영업이익 YoY | D44: 영업이익 YoY | I44: =IFERROR(I9/E9-1,"") | J44: =IFERROR(J9/F9-1,"") | K44: =IFERROR(K9/G9-1,"") | L44: =IFERROR(L9/H9-1,"") | M44: =IFERROR(M9/I9-1,"") | N44: =IFERROR(N9/J9-1,"") | O44: =IFERROR(O9/K9-1,"") | P44: =IFERROR(P9/L9-1,"") | ... AG44: =IFERROR(AG9/AC9-1,"")
A45: 지배주주순이익 YoY | D45: 지배주주순이익 YoY | I45: =IFERROR(I21/E21-1,"") | J45: =IFERROR(J21/F21-1,"") | K45: =IFERROR(K21/G21-1,"") | L45: =IFERROR(L21/H21-1,"") | M45: =IFERROR(M21/I21-1,"") | N45: =IFERROR(N21/J21-1,"") | O45: =IFERROR(O21/K21-1,"") | P45: =IFERROR(P21/L21-1,"") | ... AG45: =IFERROR(AG21/AC21-1,"")

Sheet 연간예상
C1: 이름: 연간예상H — subQ 를 이름으로 VLOOKUP(억원) | E1: 2021 | F1: 2022 | G1: 2023 | H1: 2024 | I1: 2025 | J1: 2026 | K1: 2027 | L1: 2028
C2: 종가: | D2: =변수!D45
C3: 기준일: | D3: 20261008 | E3: 1 | F3: 2 | G3: 3 | H3: 4 | I3: 5 | J3: 6 | K3: 7 | L3: 8
E4: 2021.12A | F4: 2022.12A | G4: 2023.12A | H4: 2024.12A | I4: 2025.12A | J4: 2026.12A | K4: 2027.12A | L4: 2028.12A
A5: 매출액 | D5: 매출액 | E5: =IFERROR(VLOOKUP($A5,subQ,MATCH(E$1,SUBQH,0),0),"") | F5: =IFERROR(VLOOKUP($A5,subQ,MATCH(F$1,SUBQH,0),0),"") | G5: =IFERROR(VLOOKUP($A5,subQ,MATCH(G$1,SUBQH,0),0),"") | H5: =IFERROR(VLOOKUP($A5,subQ,MATCH(H$1,SUBQH,0),0),"") | I5: =IFERROR(VLOOKUP($A5,subQ,MATCH(I$1,SUBQH,0),0),"") | J5: =IFERROR(VLOOKUP($A5,subQ,MATCH(J$1,SUBQH,0),0),"") | K5: =IFERROR(VLOOKUP($A5,subQ,MATCH(K$1,SUBQH,0),0),"") | L5: =IFERROR(VLOOKUP($A5,subQ,MATCH(L$1,SUBQH,0),0),"")
A6: 매출원가 | D6: 매출원가 | E6: =IFERROR(VLOOKUP($A6,subQ,MATCH(E$1,SUBQH,0),0),"") | F6: =IFERROR(VLOOKUP($A6,subQ,MATCH(F$1,SUBQH,0),0),"") | G6: =IFERROR(VLOOKUP($A6,subQ,MATCH(G$1,SUBQH,0),0),"") | H6: =IFERROR(VLOOKUP($A6,subQ,MATCH(H$1,SUBQH,0),0),"") | I6: =IFERROR(VLOOKUP($A6,subQ,MATCH(I$1,SUBQH,0),0),"") | J6: =IFERROR(VLOOKUP($A6,subQ,MATCH(J$1,SUBQH,0),0),"") | K6: =IFERROR(VLOOKUP($A6,subQ,MATCH(K$1,SUBQH,0),0),"") | L6: =IFERROR(VLOOKUP($A6,subQ,MATCH(L$1,SUBQH,0),0),"")
A7: 매출총이익 | D7: 매출총이익 | E7: =IFERROR(VLOOKUP($A7,subQ,MATCH(E$1,SUBQH,0),0),"") | F7: =IFERROR(VLOOKUP($A7,subQ,MATCH(F$1,SUBQH,0),0),"") | G7: =IFERROR(VLOOKUP($A7,subQ,MATCH(G$1,SUBQH,0),0),"") | H7: =IFERROR(VLOOKUP($A7,subQ,MATCH(H$1,SUBQH,0),0),"") | I7: =IFERROR(VLOOKUP($A7,subQ,MATCH(I$1,SUBQH,0),0),"") | J7: =IFERROR(VLOOKUP($A7,subQ,MATCH(J$1,SUBQH,0),0),"") | K7: =IFERROR(VLOOKUP($A7,subQ,MATCH(K$1,SUBQH,0),0),"") | L7: =IFERROR(VLOOKUP($A7,subQ,MATCH(L$1,SUBQH,0),0),"")
A8: 판관비 | D8: 판매비와관리비 | E8: =IFERROR(VLOOKUP($A8,subQ,MATCH(E$1,SUBQH,0),0),"") | F8: =IFERROR(VLOOKUP($A8,subQ,MATCH(F$1,SUBQH,0),0),"") | G8: =IFERROR(VLOOKUP($A8,subQ,MATCH(G$1,SUBQH,0),0),"") | H8: =IFERROR(VLOOKUP($A8,subQ,MATCH(H$1,SUBQH,0),0),"") | I8: =IFERROR(VLOOKUP($A8,subQ,MATCH(I$1,SUBQH,0),0),"") | J8: =IFERROR(VLOOKUP($A8,subQ,MATCH(J$1,SUBQH,0),0),"") | K8: =IFERROR(VLOOKUP($A8,subQ,MATCH(K$1,SUBQH,0),0),"") | L8: =IFERROR(VLOOKUP($A8,subQ,MATCH(L$1,SUBQH,0),0),"")
A9: 영업이익 | D9: 영업이익 | E9: =IFERROR(VLOOKUP($A9,subQ,MATCH(E$1,SUBQH,0),0),"") | F9: =IFERROR(VLOOKUP($A9,subQ,MATCH(F$1,SUBQH,0),0),"") | G9: =IFERROR(VLOOKUP($A9,subQ,MATCH(G$1,SUBQH,0),0),"") | H9: =IFERROR(VLOOKUP($A9,subQ,MATCH(H$1,SUBQH,0),0),"") | I9: =IFERROR(VLOOKUP($A9,subQ,MATCH(I$1,SUBQH,0),0),"") | J9: =IFERROR(VLOOKUP($A9,subQ,MATCH(J$1,SUBQH,0),0),"") | K9: =IFERROR(VLOOKUP($A9,subQ,MATCH(K$1,SUBQH,0),0),"") | L9: =IFERROR(VLOOKUP($A9,subQ,MATCH(L$1,SUBQH,0),0),"")
A10: OPM | D10: 영업이익률 | E10: =IFERROR(VLOOKUP($A10,subQ,MATCH(E$1,SUBQH,0),0),"") | F10: =IFERROR(VLOOKUP($A10,subQ,MATCH(F$1,SUBQH,0),0),"") | G10: =IFERROR(VLOOKUP($A10,subQ,MATCH(G$1,SUBQH,0),0),"") | H10: =IFERROR(VLOOKUP($A10,subQ,MATCH(H$1,SUBQH,0),0),"") | I10: =IFERROR(VLOOKUP($A10,subQ,MATCH(I$1,SUBQH,0),0),"") | J10: =IFERROR(VLOOKUP($A10,subQ,MATCH(J$1,SUBQH,0),0),"") | K10: =IFERROR(VLOOKUP($A10,subQ,MATCH(K$1,SUBQH,0),0),"") | L10: =IFERROR(VLOOKUP($A10,subQ,MATCH(L$1,SUBQH,0),0),"")
A11: 금융손익 | D11: 금융손익(이자·환 포함) | E11: =IFERROR(VLOOKUP($A11,subQ,MATCH(E$1,SUBQH,0),0),"") | F11: =IFERROR(VLOOKUP($A11,subQ,MATCH(F$1,SUBQH,0),0),"") | G11: =IFERROR(VLOOKUP($A11,subQ,MATCH(G$1,SUBQH,0),0),"") | H11: =IFERROR(VLOOKUP($A11,subQ,MATCH(H$1,SUBQH,0),0),"") | I11: =IFERROR(VLOOKUP($A11,subQ,MATCH(I$1,SUBQH,0),0),"") | J11: =IFERROR(VLOOKUP($A11,subQ,MATCH(J$1,SUBQH,0),0),"") | K11: =IFERROR(VLOOKUP($A11,subQ,MATCH(K$1,SUBQH,0),0),"") | L11: =IFERROR(VLOOKUP($A11,subQ,MATCH(L$1,SUBQH,0),0),"")
A12: 이자손익 | D12: 이자손익(이자수익 − 이자비용) | E12: =IFERROR(VLOOKUP($A12,subQ,MATCH(E$1,SUBQH,0),0),"") | F12: =IFERROR(VLOOKUP($A12,subQ,MATCH(F$1,SUBQH,0),0),"") | G12: =IFERROR(VLOOKUP($A12,subQ,MATCH(G$1,SUBQH,0),0),"") | H12: =IFERROR(VLOOKUP($A12,subQ,MATCH(H$1,SUBQH,0),0),"") | I12: =IFERROR(VLOOKUP($A12,subQ,MATCH(I$1,SUBQH,0),0),"") | J12: =IFERROR(VLOOKUP($A12,subQ,MATCH(J$1,SUBQH,0),0),"") | K12: =IFERROR(VLOOKUP($A12,subQ,MATCH(K$1,SUBQH,0),0),"") | L12: =IFERROR(VLOOKUP($A12,subQ,MATCH(L$1,SUBQH,0),0),"")
A13: 외환손익 | D13: 외환손익(실적만; 추정 환효과는 환관련손익) | E13: =IFERROR(VLOOKUP($A13,subQ,MATCH(E$1,SUBQH,0),0),"") | F13: =IFERROR(VLOOKUP($A13,subQ,MATCH(F$1,SUBQH,0),0),"") | G13: =IFERROR(VLOOKUP($A13,subQ,MATCH(G$1,SUBQH,0),0),"") | H13: =IFERROR(VLOOKUP($A13,subQ,MATCH(H$1,SUBQH,0),0),"") | I13: =IFERROR(VLOOKUP($A13,subQ,MATCH(I$1,SUBQH,0),0),"") | J13: =IFERROR(VLOOKUP($A13,subQ,MATCH(J$1,SUBQH,0),0),"") | K13: =IFERROR(VLOOKUP($A13,subQ,MATCH(K$1,SUBQH,0),0),"") | L13: =IFERROR(VLOOKUP($A13,subQ,MATCH(L$1,SUBQH,0),0),"")
A14: 파생상품손익 | D14: 파생상품손익 | E14: =IFERROR(VLOOKUP($A14,subQ,MATCH(E$1,SUBQH,0),0),"") | F14: =IFERROR(VLOOKUP($A14,subQ,MATCH(F$1,SUBQH,0),0),"") | G14: =IFERROR(VLOOKUP($A14,subQ,MATCH(G$1,SUBQH,0),0),"") | H14: =IFERROR(VLOOKUP($A14,subQ,MATCH(H$1,SUBQH,0),0),"") | I14: =IFERROR(VLOOKUP($A14,subQ,MATCH(I$1,SUBQH,0),0),"") | J14: =IFERROR(VLOOKUP($A14,subQ,MATCH(J$1,SUBQH,0),0),"") | K14: =IFERROR(VLOOKUP($A14,subQ,MATCH(K$1,SUBQH,0),0),"") | L14: =IFERROR(VLOOKUP($A14,subQ,MATCH(L$1,SUBQH,0),0),"")
A15: 기타금융손익 | D15: 기타금융손익(금융손익 잔차) | E15: =IFERROR(VLOOKUP($A15,subQ,MATCH(E$1,SUBQH,0),0),"") | F15: =IFERROR(VLOOKUP($A15,subQ,MATCH(F$1,SUBQH,0),0),"") | G15: =IFERROR(VLOOKUP($A15,subQ,MATCH(G$1,SUBQH,0),0),"") | H15: =IFERROR(VLOOKUP($A15,subQ,MATCH(H$1,SUBQH,0),0),"") | I15: =IFERROR(VLOOKUP($A15,subQ,MATCH(I$1,SUBQH,0),0),"") | J15: =IFERROR(VLOOKUP($A15,subQ,MATCH(J$1,SUBQH,0),0),"") | K15: =IFERROR(VLOOKUP($A15,subQ,MATCH(K$1,SUBQH,0),0),"") | L15: =IFERROR(VLOOKUP($A15,subQ,MATCH(L$1,SUBQH,0),0),"")
A16: 기타영업외손익 | D16: 기타영업외손익 | E16: =IFERROR(VLOOKUP($A16,subQ,MATCH(E$1,SUBQH,0),0),"") | F16: =IFERROR(VLOOKUP($A16,subQ,MATCH(F$1,SUBQH,0),0),"") | G16: =IFERROR(VLOOKUP($A16,subQ,MATCH(G$1,SUBQH,0),0),"") | H16: =IFERROR(VLOOKUP($A16,subQ,MATCH(H$1,SUBQH,0),0),"") | I16: =IFERROR(VLOOKUP($A16,subQ,MATCH(I$1,SUBQH,0),0),"") | J16: =IFERROR(VLOOKUP($A16,subQ,MATCH(J$1,SUBQH,0),0),"") | K16: =IFERROR(VLOOKUP($A16,subQ,MATCH(K$1,SUBQH,0),0),"") | L16: =IFERROR(VLOOKUP($A16,subQ,MATCH(L$1,SUBQH,0),0),"")
... A42: NPM | D42: NPM | E42: =IFERROR(VLOOKUP($A42,subQ,MATCH(E$1,SUBQH,0),0),"") | F42: =IFERROR(VLOOKUP($A42,subQ,MATCH(F$1,SUBQH,0),0),"") | G42: =IFERROR(VLOOKUP($A42,subQ,MATCH(G$1,SUBQH,0),0),"") | H42: =IFERROR(VLOOKUP($A42,subQ,MATCH(H$1,SUBQH,0),0),"") | I42: =IFERROR(VLOOKUP($A42,subQ,MATCH(I$1,SUBQH,0),0),"") | J42: =IFERROR(VLOOKUP($A42,subQ,MATCH(J$1,SUBQH,0),0),"") | K42: =IFERROR(VLOOKUP($A42,subQ,MATCH(K$1,SUBQH,0),0),"") | L42: =IFERROR(VLOOKUP($A42,subQ,MATCH(L$1,SUBQH,0),0),"")
A43: 매출액 YoY | D43: 매출액 YoY | F43: =IFERROR(F5/E5-1,"") | G43: =IFERROR(G5/F5-1,"") | H43: =IFERROR(H5/G5-1,"") | I43: =IFERROR(I5/H5-1,"") | J43: =IFERROR(J5/I5-1,"") | K43: =IFERROR(K5/J5-1,"") | L43: =IFERROR(L5/K5-1,"")
A44: 영업이익 YoY | D44: 영업이익 YoY | F44: =IFERROR(F9/E9-1,"") | G44: =IFERROR(G9/F9-1,"") | H44: =IFERROR(H9/G9-1,"") | I44: =IFERROR(I9/H9-1,"") | J44: =IFERROR(J9/I9-1,"") | K44: =IFERROR(K9/J9-1,"") | L44: =IFERROR(L9/K9-1,"")
A45: 지배주주순이익 YoY | D45: 지배주주순이익 YoY | F45: =IFERROR(F21/E21-1,"") | G45: =IFERROR(G21/F21-1,"") | H45: =IFERROR(H21/G21-1,"") | I45: =IFERROR(I21/H21-1,"") | J45: =IFERROR(J21/I21-1,"") | K45: =IFERROR(K21/J21-1,"") | L45: =IFERROR(L21/K21-1,"")

Sheet TP
B1: 종가 | C1: =변수!D45
B2: 기준일 | C2: =변수!D46
B3: 모델 산출값 — 목표주가·추천 아님. 밴드·COE 는 변수 시트 3절의 가정
C5: FY | D5: 2025 | E5: 2026 | F5: 2027 | G5: 2028
D6: A | E6: E | F6: E | G6: E
C7: EPS(원) | D7: =IFERROR(VLOOKUP("EPS",subQ,MATCH(D$5,SUBQH,0),0),"") | E7: =IFERROR(VLOOKUP("EPS",subQ,MATCH(E$5,SUBQH,0),0),"") | F7: =IFERROR(VLOOKUP("EPS",subQ,MATCH(F$5,SUBQH,0),0),"") | G7: =IFERROR(VLOOKUP("EPS",subQ,MATCH(G$5,SUBQH,0),0),"")
C8: BPS(원) | D8: =IFERROR(VLOOKUP("BPS",subQ,MATCH(D$5,SUBQH,0),0),"") | E8: =IFERROR(VLOOKUP("BPS",subQ,MATCH(E$5,SUBQH,0),0),"") | F8: =IFERROR(VLOOKUP("BPS",subQ,MATCH(F$5,SUBQH,0),0),"") | G8: =IFERROR(VLOOKUP("BPS",subQ,MATCH(G$5,SUBQH,0),0),"")
C9: 지배주주순이익(억원) | D9: =IFERROR(VLOOKUP("지배주주순이익",subQ,MATCH(D$5,SUBQH,0),0),"") | E9: =IFERROR(VLOOKUP("지배주주순이익",subQ,MATCH(E$5,SUBQH,0),0),"") | F9: =IFERROR(VLOOKUP("지배주주순이익",subQ,MATCH(F$5,SUBQH,0),0),"") | G9: =IFERROR(VLOOKUP("지배주주순이익",subQ,MATCH(G$5,SUBQH,0),0),"")
C10: 영업이익(억원) | D10: =IFERROR(VLOOKUP("영업이익",subQ,MATCH(D$5,SUBQH,0),0),"") | E10: =IFERROR(VLOOKUP("영업이익",subQ,MATCH(E$5,SUBQH,0),0),"") | F10: =IFERROR(VLOOKUP("영업이익",subQ,MATCH(F$5,SUBQH,0),0),"") | G10: =IFERROR(VLOOKUP("영업이익",subQ,MATCH(G$5,SUBQH,0),0),"")
C11: ROE(EPS/기초BPS) | E11: =IFERROR(E7/D8,"") | F11: =IFERROR(F7/E8,"") | G11: =IFERROR(G7/F8,"")
B13: PER
C14: 12M fwd EPS | D14: =IFERROR(E7*변수!D51+F7*(1-변수!D51),"")
C15: 적정가치 @PER_lo | D15: =변수!D48 | E15: =IFERROR(ROUND($D$14*D15,-2),"") | F15: =IFERROR(E15/$C$1-1,"") | G15: 배 · 원 · 종가 대비
C16: 적정가치 @PER_mid | D16: =변수!D49 | E16: =IFERROR(ROUND($D$14*D16,-2),"") | F16: =IFERROR(E16/$C$1-1,"") | G16: 배 · 원 · 종가 대비
C17: 적정가치 @PER_hi | D17: =변수!D50 | E17: =IFERROR(ROUND($D$14*D17,-2),"") | F17: =IFERROR(E17/$C$1-1,"") | G17: 배 · 원 · 종가 대비
C18: 현재 PER(종가/12M fwd EPS) | D18: =IFERROR($C$1/$D$14,"")
B20: PBR
C21: 최근 BPS(마지막 실적 분기) | D21: =IFERROR(VLOOKUP("BPS",subQ,MATCH("2Q26",SUBQH,0),0),"")
C22: ROE fwd(12M fwd EPS / BPS) | D22: =IFERROR($D$14/$D$21,"")
C23: COE | D23: =변수!D47
C24: 적정 PBR = ROE/COE | D24: =IFERROR(D22/D23,"")
C25: 적정가치(PBR) = BPS × 적정PBR | D25: =IFERROR(ROUND(D21*D24,-2),"") | E25: =IFERROR(D25/$C$1-1,"")
C26: 현재 PBR(종가/BPS) | D26: =IFERROR($C$1/D21,"")
B28: 모델 json valuation(참고)
C29: eps_fwd12m | D29: -1083.5
C30: bps_latest | D30: 4499.7
C31: per_now
C32: pbr_now | D32: 0.32
C33: roe_fwd | D33: -0.2408
C34: fair_pbr
C35: fair_value_pbr
C36: ev_ebitda
C37: note | D37: 모델 산출값 — 목표주가·추천 아님

Sheet 외화
C1: 이름: 외화QH — 환율 QoQ · 외화 순노출 × Δ기말환율 | E1: 4Q21 | F1: 1Q22 | G1: 2Q22 | H1: 3Q22 | I1: 4Q22 | J1: 1Q23 | K1: 2Q23 | L1: 3Q23 | M1: 4Q23 | N1: 1Q24 | O1: 2Q24 | P1: 3Q24 | Q1: 4Q24 | R1: 1Q25 | S1: 2Q25 | T1: 3Q25 | U1: 4Q25 | V1: 1Q26 | W1: 2Q26 | X1: 3Q26 | Y1: 4Q26 | Z1: 1Q27 | AA1: 2Q27 | AB1: 3Q27 | AC1: 4Q27 | AD1: 1Q28 | AE1: 2Q28 | AF1: 3Q28 | AG1: 4Q28
E3: 1 | F3: 2 | G3: 3 | H3: 4 | I3: 5 | J3: 6 | K3: 7 | L3: 8 | M3: 9 | N3: 10 | O3: 11 | P3: 12 | Q3: 13 | R3: 14 | S3: 15 | T3: 16 | U3: 17 | V3: 18 | W3: 19 | X3: 20 | Y3: 21 | Z3: 22 | AA3: 23 | AB3: 24 | AC3: 25 | AD3: 26 | AE3: 27 | AF3: 28 | AG3: 29
E4: 2021.12 | F4: 2022.03 | G4: 2022.06 | H4: 2022.09 | I4: 2022.12 | J4: 2023.03 | K4: 2023.06 | L4: 2023.09 | M4: 2023.12 | N4: 2024.03 | O4: 2024.06 | P4: 2024.09 | Q4: 2024.12 | R4: 2025.03 | S4: 2025.06 | T4: 2025.09 | U4: 2025.12 | V4: 2026.03 | W4: 2026.06 | X4: 2026.09 | Y4: 2026.12 | Z4: 2027.03 | AA4: 2027.06 | AB4: 2027.09 | AC4: 2027.12 | AD4: 2028.03 | AE4: 2028.06 | AF4: 2028.09 | AG4: 2028.12
D5: 원/달러(평균) | E5: =IFERROR(VLOOKUP($D5,환율,MATCH(E$1,변수H,0),0),"") | F5: =IFERROR(VLOOKUP($D5,환율,MATCH(F$1,변수H,0),0),"") | G5: =IFERROR(VLOOKUP($D5,환율,MATCH(G$1,변수H,0),0),"") | H5: =IFERROR(VLOOKUP($D5,환율,MATCH(H$1,변수H,0),0),"") | I5: =IFERROR(VLOOKUP($D5,환율,MATCH(I$1,변수H,0),0),"") | J5: =IFERROR(VLOOKUP($D5,환율,MATCH(J$1,변수H,0),0),"") | K5: =IFERROR(VLOOKUP($D5,환율,MATCH(K$1,변수H,0),0),"") | L5: =IFERROR(VLOOKUP($D5,환율,MATCH(L$1,변수H,0),0),"") | ... AG5: =IFERROR(VLOOKUP($D5,환율,MATCH(AG$1,변수H,0),0),"")
A6: 원/달러(평균) QoQ | F6: =IFERROR(F5/E5-1,"") | G6: =IFERROR(G5/F5-1,"") | H6: =IFERROR(H5/G5-1,"") | I6: =IFERROR(I5/H5-1,"") | J6: =IFERROR(J5/I5-1,"") | K6: =IFERROR(K5/J5-1,"") | L6: =IFERROR(L5/K5-1,"") | M6: =IFERROR(M5/L5-1,"") | ... AG6: =IFERROR(AG5/AF5-1,"")
D7: 원/달러(기말) | E7: =IFERROR(VLOOKUP($D7,환율,MATCH(E$1,변수H,0),0),"") | F7: =IFERROR(VLOOKUP($D7,환율,MATCH(F$1,변수H,0),0),"") | G7: =IFERROR(VLOOKUP($D7,환율,MATCH(G$1,변수H,0),0),"") | H7: =IFERROR(VLOOKUP($D7,환율,MATCH(H$1,변수H,0),0),"") | I7: =IFERROR(VLOOKUP($D7,환율,MATCH(I$1,변수H,0),0),"") | J7: =IFERROR(VLOOKUP($D7,환율,MATCH(J$1,변수H,0),0),"") | K7: =IFERROR(VLOOKUP($D7,환율,MATCH(K$1,변수H,0),0),"") | L7: =IFERROR(VLOOKUP($D7,환율,MATCH(L$1,변수H,0),0),"") | ... AG7: =IFERROR(VLOOKUP($D7,환율,MATCH(AG$1,변수H,0),0),"")
A8: 원/달러(기말) QoQ | F8: =IFERROR(F7/E7-1,"") | G8: =IFERROR(G7/F7-1,"") | H8: =IFERROR(H7/G7-1,"") | I8: =IFERROR(I7/H7-1,"") | J8: =IFERROR(J7/I7-1,"") | K8: =IFERROR(K7/J7-1,"") | L8: =IFERROR(L7/K7-1,"") | M8: =IFERROR(M7/L7-1,"") | ... AG8: =IFERROR(AG7/AF7-1,"")
D9: W/Euro(평균) | E9: =IFERROR(VLOOKUP($D9,환율,MATCH(E$1,변수H,0),0),"") | F9: =IFERROR(VLOOKUP($D9,환율,MATCH(F$1,변수H,0),0),"") | G9: =IFERROR(VLOOKUP($D9,환율,MATCH(G$1,변수H,0),0),"") | H9: =IFERROR(VLOOKUP($D9,환율,MATCH(H$1,변수H,0),0),"") | I9: =IFERROR(VLOOKUP($D9,환율,MATCH(I$1,변수H,0),0),"") | J9: =IFERROR(VLOOKUP($D9,환율,MATCH(J$1,변수H,0),0),"") | K9: =IFERROR(VLOOKUP($D9,환율,MATCH(K$1,변수H,0),0),"") | L9: =IFERROR(VLOOKUP($D9,환율,MATCH(L$1,변수H,0),0),"") | ... AG9: =IFERROR(VLOOKUP($D9,환율,MATCH(AG$1,변수H,0),0),"")
A10: W/Euro(평균) QoQ | F10: =IFERROR(F9/E9-1,"") | G10: =IFERROR(G9/F9-1,"") | H10: =IFERROR(H9/G9-1,"") | I10: =IFERROR(I9/H9-1,"") | J10: =IFERROR(J9/I9-1,"") | K10: =IFERROR(K9/J9-1,"") | L10: =IFERROR(L9/K9-1,"") | M10: =IFERROR(M9/L9-1,"") | ... AG10: =IFERROR(AG9/AF9-1,"")
D11: W/Euro(기말) | E11: =IFERROR(VLOOKUP($D11,환율,MATCH(E$1,변수H,0),0),"") | F11: =IFERROR(VLOOKUP($D11,환율,MATCH(F$1,변수H,0),0),"") | G11: =IFERROR(VLOOKUP($D11,환율,MATCH(G$1,변수H,0),0),"") | H11: =IFERROR(VLOOKUP($D11,환율,MATCH(H$1,변수H,0),0),"") | I11: =IFERROR(VLOOKUP($D11,환율,MATCH(I$1,변수H,0),0),"") | J11: =IFERROR(VLOOKUP($D11,환율,MATCH(J$1,변수H,0),0),"") | K11: =IFERROR(VLOOKUP($D11,환율,MATCH(K$1,변수H,0),0),"") | L11: =IFERROR(VLOOKUP($D11,환율,MATCH(L$1,변수H,0),0),"") | ... AG11: =IFERROR(VLOOKUP($D11,환율,MATCH(AG$1,변수H,0),0),"")
A12: W/Euro(기말) QoQ | F12: =IFERROR(F11/E11-1,"") | G12: =IFERROR(G11/F11-1,"") | H12: =IFERROR(H11/G11-1,"") | I12: =IFERROR(I11/H11-1,"") | J12: =IFERROR(J11/I11-1,"") | K12: =IFERROR(K11/J11-1,"") | L12: =IFERROR(L11/K11-1,"") | M12: =IFERROR(M11/L11-1,"") | ... AG12: =IFERROR(AG11/AF11-1,"")
D13: 원/100Y(기말) | E13: =IFERROR(VLOOKUP($D13,환율,MATCH(E$1,변수H,0),0),"") | F13: =IFERROR(VLOOKUP($D13,환율,MATCH(F$1,변수H,0),0),"") | G13: =IFERROR(VLOOKUP($D13,환율,MATCH(G$1,변수H,0),0),"") | H13: =IFERROR(VLOOKUP($D13,환율,MATCH(H$1,변수H,0),0),"") | I13: =IFERROR(VLOOKUP($D13,환율,MATCH(I$1,변수H,0),0),"") | J13: =IFERROR(VLOOKUP($D13,환율,MATCH(J$1,변수H,0),0),"") | K13: =IFERROR(VLOOKUP($D13,환율,MATCH(K$1,변수H,0),0),"") | L13: =IFERROR(VLOOKUP($D13,환율,MATCH(L$1,변수H,0),0),"") | ... AG13: =IFERROR(VLOOKUP($D13,환율,MATCH(AG$1,변수H,0),0),"")
A14: 원/100Y(기말) QoQ | F14: =IFERROR(F13/E13-1,"") | G14: =IFERROR(G13/F13-1,"") | H14: =IFERROR(H13/G13-1,"") | I14: =IFERROR(I13/H13-1,"") | J14: =IFERROR(J13/I13-1,"") | K14: =IFERROR(K13/J13-1,"") | L14: =IFERROR(L13/K13-1,"") | M14: =IFERROR(M13/L13-1,"") | ... AG14: =IFERROR(AG13/AF13-1,"")
A16: 외화순노출 | C16: 외화 순노출(백만$) | D16: =변수!D58 | E16: 외화 순노출 × Δ기말환율 (외화 시트 방식)
A17: 환관련손익추정 | C17: 환관련손익 추정(억원) = 순노출 × Δ원/달러(기말) / 100 | F17: =IFERROR($D$16*(F7-E7)/100,"") | G17: =IFERROR($D$16*(G7-F7)/100,"") | H17: =IFERROR($D$16*(H7-G7)/100,"") | I17: =IFERROR($D$16*(I7-H7)/100,"") | J17: =IFERROR($D$16*(J7-I7)/100,"") | K17: =IFERROR($D$16*(K7-J7)/100,"") | L17: =IFERROR($D$16*(L7-K7)/100,"") | M17: =IFERROR($D$16*(M7-L7)/100,"") | ... AG17: =IFERROR($D$16*(AG7-AF7)/100,"")
A18: fx_pnl.by_q | C18: 모델 fx_pnl.by_q(억원, 참고)
C19: 외화 순노출 미공시(face) → 0 + 표기
