Workbook
Name 변수H: 변수!$C$1:$AO$1
Name 환율: 변수!$C$6:$AO$13
Name BS연결H: BS연결!$C$1:$AO$1
Name BS연결: BS연결!$C$5:$AO$108
Name BS별도H: BS별도!$C$1:$AO$1
Name BS별도: BS별도!$C$5:$AO$94
Name SUBQH: subQ!$A$1:$AO$1
Name subQ: subQ!$A$5:$AO$45

Sheet README
A1: 인화정공(101930) 실적 모델 — ARGUS 한국조선
A2: 기준 분기 2026Q2 · 마지막 실적 2026Q2 · 생성 2026-10-26
A3: 모든 수치는 모델 산출값(DART 공개 재무제표 + 우리 추정)이다 — 목표주가·투자 추천 아님. 참고용 · 투자조언 아님.
A5: 시트
A6: 변수 가정 시계열. 환율 8행(ECB via frankfurter — L2 fx.json; 추정 분기 = 노란 가정), 추정 드라이버(노란 셀 = 모델값에서 역산한 가정, 바꾸면 재계산; 연녹 셀 = 3절 스칼라 참조 수식), 3절 스칼라 가정(세율·판관비율·지배주주비중·이자율·종가·PER 밴드·COE·외화 순노출·헤지비율)
A7: BS연결/BS별도 FnGuide 계정명 × 기간 값 덤프(백만원). 행1 분기라벨, 행4 YYYY.MM / YYYY.12A. 이름정의 BS연결H·BS연결(계정명 C열부터)
A8: subQ 분기 서브모델(억원 = 백만원/100). 확정 행: =IFERROR(VLOOKUP($D행,BS연결,MATCH(E$1,BS연결H,0),0)/100,"") 추정 행: 변수 시트 가정 셀 참조 수식. 외환손익·파생상품손익은 BS 계정 합·차, 기타금융손익은 잔차, OPM·EPS·BPS·PER·PBR 은 파생 수식
A9: SLS 선표(조선사만, sls json 있을 때): 요약 행(sls 저장값) + 계약별 스케줄(백만$) × (헤지비율 × 헤지환율 + (1−헤지비율) × 건조시점 환율[변수 원/달러(평균)]) → 원화 수식 블록 → 합계 행이 subQ 매출조선에 연결
A10: 시나리오 신규수주 보수/기준/낙관(forecast_panel 패널, 모델에 scenarios 가 있을 때만): 매출액·영업이익 = subQ 기준값 ± (시나리오 신규 − base 신규) × OPM. base 만 subQ 행에 포함, 나머지는 합산 안 함
A11: 분기/연간예상 subQ 를 이름(A열 key)으로 VLOOKUP 한 보고서 표(억원)
A12: TP PER 밴드 × 12M fwd EPS, PBR = ROE/COE × BPS — 모델 산출값 구간, 목표주가·추천 아님
A13: 외화 환율 QoQ, 외화 순노출 × Δ기말환율 → 환관련손익 추정
... A34: 백테스트: {"freeze": "2025Q2", "horizon": 4, "revenue_wape_pct": 16.1, "op_wape_pct": 51.5, "n": 4, "note": "단일 회사 4분기 — 통계 아님", "driver_at_freeze": "trend_seasonal", "selection_oos_at_freeze": {"wape_link": null, "wape_trend": null, "adopted": false, "decision": "rejected", "note": "유의성 조건 미달 → OOS 비교 전 기각"}, "frozen_inputs": "fin(연결/별도)·고객 조선사 모델·지주 자회사 모델은 2025Q2 까지의 분기만; 선표는 체결일 ≤ 2025Q2 말일 계약(원장 최신 금액·코호트 등급, 환산 없음); 잔고는 yards_cache 2025Q2; 시세·환율 forward·prices·forecast_panel 신규수주 미사용. 고객 가중치(suppliers.json 언급 비중)와 합병 체인링크는 현재 지식; 고객 연동 채택은 동결 모델 안에서도 자기 la−4분기 OOS 규칙(selection_oos_at_freeze)", "detail": [{"q": "2025Q3", "rev_pred": 236.66, "rev_act": 287.95, "op_pred": 17.87, "op_act": 48.65}, {"q": "2025Q4", "rev_pred": 287.06, "rev_act": 254.8, "op_pred": 21.68, "op_act": 36.01}, {"q": "2026Q1", "rev_pred": 328.16, "rev_act": 259.87, "op_pred": 24.78, "op_act": 41.62}, {"q": "2026Q2", "rev_pred": 289.52, "rev_act": 318.3, "op_pred": 21.87, "op_act": 51.34}]}

Sheet 변수
C1: 이름: 변수H | E1: 4Q21 | F1: 2021 | G1: 1Q22 | H1: 2Q22 | I1: 3Q22 | J1: 4Q22 | K1: 2022 | L1: 1Q23 | M1: 2Q23 | N1: 3Q23 | O1: 4Q23 | P1: 2023 | Q1: 1Q24 | R1: 2Q24 | S1: 3Q24 | T1: 4Q24 | U1: 2024 | V1: 1Q25 | W1: 2Q25 | X1: 3Q25 | Y1: 4Q25 | Z1: 2025 | AA1: 1Q26 | AB1: 2Q26 | AC1: 3Q26 | AD1: 4Q26 | AE1: 2026 | AF1: 1Q27 | AG1: 2Q27 | AH1: 3Q27 | AI1: 4Q27 | AJ1: 2027 | AK1: 1Q28 | AL1: 2Q28 | AM1: 3Q28 | AN1: 4Q28 | AO1: 2028
A2: 가정 시계열 — 노란 셀은 추정 가정(모델값에서 역산), 연녹 셀은 3절 스칼라 참조 수식. 바꾸면 subQ·분기·연간예상·TP·시나리오가 재계산됩니다.
E3: 1 | F3: 2 | G3: 3 | H3: 4 | I3: 5 | J3: 6 | K3: 7 | L3: 8 | M3: 9 | N3: 10 | O3: 11 | P3: 12 | Q3: 13 | R3: 14 | S3: 15 | T3: 16 | U3: 17 | V3: 18 | W3: 19 | X3: 20 | Y3: 21 | Z3: 22 | AA3: 23 | AB3: 24 | AC3: 25 | AD3: 26 | AE3: 27 | AF3: 28 | AG3: 29 | AH3: 30 | AI3: 31 | AJ3: 32 | AK3: 33 | AL3: 34 | AM3: 35 | AN3: 36 | AO3: 37
E4: 2021.12 | F4: 2021.12A | G4: 2022.03 | H4: 2022.06 | I4: 2022.09 | J4: 2022.12 | K4: 2022.12A | L4: 2023.03 | M4: 2023.06 | N4: 2023.09 | O4: 2023.12 | P4: 2023.12A | Q4: 2024.03 | R4: 2024.06 | S4: 2024.09 | T4: 2024.12 | U4: 2024.12A | V4: 2025.03 | W4: 2025.06 | X4: 2025.09 | Y4: 2025.12 | Z4: 2025.12A | AA4: 2026.03 | AB4: 2026.06 | AC4: 2026.09 | AD4: 2026.12 | AE4: 2026.12A | AF4: 2027.03 | AG4: 2027.06 | AH4: 2027.09 | AI4: 2027.12 | AJ4: 2027.12A | AK4: 2028.03 | AL4: 2028.06 | AM4: 2028.09 | AN4: 2028.12 | AO4: 2028.12A
B5: 1. FX | C5: 이름: 환율
A6: USDKRW_avg | C6: 원/달러(평균) | E6: 1183.5 | F6: 1145.51 | G6: 1205.78 | H6: 1262.09 | I6: 1341.93 | J6: 1360.12 | K6: 1292.98 | L6: 1276.95 | M6: 1315.69 | N6: 1313.62 | O6: 1322.01 | P6: 1306.85 | Q6: 1330.14 | R6: 1371.28 | S6: 1356.22 | T6: 1396.3 | U6: 1363.53 | V6: 1452.28 | W6: 1398.52 | X6: 1386.95 | Y6: 1449.19 | Z6: 1421.52 | AA6: 1466.12 | AB6: 1501.75 | AC6: 1418.75 | AD6: 1337.49 | AE6: 1451.19 | AF6: 1324.45 | AG6: 1324.45 | AH6: 1324.45 | AI6: 1324.45 | AK6: 1324.45 | AL6: 1324.45 | AM6: 1324.45 | AN6: 1324.45
A7: USDKRW_end | C7: 원/달러(기말) | E7: 1188.75 | F7: 1188.75 | G7: 1213.74 | H7: 1301.24 | I7: 1436.9 | J7: 1260.16 | K7: 1260.16 | L7: 1305.99 | M7: 1321.44 | N7: 1345.35 | O7: 1297.43 | P7: 1297.43 | Q7: 1349.25 | R7: 1377.73 | S7: 1312.17 | T7: 1474.78 | U7: 1474.78 | V7: 1474.54 | W7: 1355.13 | X7: 1403.67 | Y7: 1444.2 | Z7: 1444.2 | AA7: 1524.8 | AB7: 1550.89 | AC7: 1355.4 | AD7: 1324.45 | AE7: 1324.45 | AF7: 1324.45 | AG7: 1324.45 | AH7: 1324.45 | AI7: 1324.45 | AK7: 1324.45 | AL7: 1324.45 | AM7: 1324.45 | AN7: 1324.45
A8: JPY100KRW_avg | C8: 원/100Y(평균) | E8: 1041.02 | F8: 1042.74 | G8: 1036.79 | H8: 972.23 | I8: 970.61 | J8: 961.03 | K8: 985.1 | L8: 964.89 | M8: 957.36 | N8: 909 | O8: 893.22 | P8: 931.11 | Q8: 896.29 | R8: 880.14 | S8: 909.35 | T8: 917.25 | U8: 900.92 | V8: 952.59 | W8: 967.92 | X8: 940.32 | Y8: 940.77 | Z8: 950.17 | AA8: 934.39 | AB8: 942.16 | AC8: 890.41 | AD8: 846.51 | AE8: 915.57 | AF8: 844.67 | AG8: 844.67 | AH8: 844.67 | AI8: 844.67 | AK8: 844.67 | AL8: 844.67 | AM8: 844.67 | AN8: 844.67
A9: JPY100KRW_end | C9: 원/100Y(기말) | E9: 1032.62 | F9: 1032.62 | G9: 996.83 | H9: 954.9 | I9: 993.29 | J9: 955.54 | K9: 955.54 | L9: 980.62 | M9: 913.67 | N9: 901.47 | O9: 917.04 | P9: 917.04 | Q9: 892.42 | R9: 857.76 | S9: 919.21 | T9: 939.65 | U9: 939.65 | V9: 986.84 | W9: 938.85 | X9: 948.49 | Y9: 921.81 | Z9: 921.81 | AA9: 955.99 | AB9: 954.75 | AC9: 863.31 | AD9: 844.67 | AE9: 844.67 | AF9: 844.67 | AG9: 844.67 | AH9: 844.67 | AI9: 844.67 | AK9: 844.67 | AL9: 844.67 | AM9: 844.67 | AN9: 844.67
A10: EURKRW_avg | C10: W/Euro(평균) | E10: 1353.32 | F10: 1354.06 | G10: 1352.29 | H10: 1343.31 | I10: 1350.63 | J10: 1386.07 | K10: 1358.07 | L10: 1369.93 | M10: 1432.41 | N10: 1429.41 | O10: 1420.91 | P10: 1412.88 | Q10: 1444.21 | R10: 1476.42 | S10: 1489.3 | T10: 1490.78 | U10: 1475.4 | V10: 1528.33 | W10: 1585.13 | X10: 1620.04 | Y10: 1686.02 | Z10: 1605.45 | AA10: 1715.47 | AB10: 1746.09 | AC10: 1631.97 | AD10: 1500.06 | AE10: 1680.5 | AF10: 1482.45 | AG10: 1482.45 | AH10: 1482.45 | AI10: 1482.45 | AK10: 1482.45 | AL10: 1482.45 | AM10: 1482.45 | AN10: 1482.45
A11: EURKRW_end | C11: W/Euro(기말) | E11: 1346.38 | F11: 1346.38 | G11: 1347.37 | H11: 1351.6 | I11: 1400.62 | J11: 1344.08 | K11: 1344.08 | L11: 1420.26 | M11: 1435.88 | N11: 1425.26 | O11: 1433.66 | P11: 1433.66 | Q11: 1458.68 | R11: 1474.86 | S11: 1469.1 | T11: 1532.14 | U11: 1532.14 | V11: 1594.72 | W11: 1588.22 | X11: 1648.04 | Y11: 1696.94 | Z11: 1696.94 | AA11: 1753.21 | AB11: 1767.09 | AC11: 1539.06 | AD11: 1482.45 | AE11: 1482.45 | AF11: 1482.45 | AG11: 1482.45 | AH11: 1482.45 | AI11: 1482.45 | AK11: 1482.45 | AL11: 1482.45 | AM11: 1482.45 | AN11: 1482.45
A12: CNYKRW_avg | C12: 원/중국원(평균) | E12: 185.14 | F12: 177.65 | G12: 189.93 | H12: 190.76 | I12: 195.79 | J12: 191.09 | K12: 191.93 | L12: 186.59 | M12: 187.45 | N12: 181.28 | O12: 182.86 | P12: 184.52 | Q12: 185.04 | R12: 189.35 | S12: 189.24 | T12: 194.24 | U12: 189.49 | V12: 199.63 | W12: 193.41 | X12: 193.79 | Y12: 204.38 | Z12: 197.8 | AA12: 211.75 | AB12: 220.8 | AC12: 210.43 | AD12: 199.88 | AE12: 213.06 | AF12: 198.56 | AG12: 198.56 | AH12: 198.56 | AI12: 198.56 | AK12: 198.56 | AL12: 198.56 | AM12: 198.56 | AN12: 198.56
A13: CNYKRW_end | C13: 원/중국원(기말) | E13: 187.13 | F13: 187.13 | G13: 191.38 | H13: 194.13 | I13: 201.92 | J13: 182.67 | K13: 182.67 | L13: 189.97 | M13: 181.8 | N13: 184.26 | O13: 182.61 | P13: 182.61 | Q13: 186.66 | R13: 189.7 | S13: 187.12 | T13: 202.04 | U13: 202.04 | V13: 203.3 | W13: 189.14 | X13: 197.16 | Y13: 206.28 | Z13: 206.28 | AA13: 220.97 | AB13: 228.56 | AC13: 202.16 | AD13: 198.56 | AE13: 198.56 | AF13: 198.56 | AG13: 198.56 | AH13: 198.56 | AI13: 198.56 | AK13: 198.56 | AL13: 198.56 | AM13: 198.56 | AN13: 198.56
B14: 1b. 종가
A15: price_close_end | C15: 종가(기말) | E15: 2760 | G15: 3190 | H15: 3010 | I15: 2660 | J15: 2520 | L15: 1996 | M15: 2328 | N15: 2140 | O15: 2328 | Q15: 2444 | R15: 4660 | S15: 4130 | T15: 6010 | V15: 6450 | W15: 7230 | X15: 11060 | Y15: 9240 | AA15: 9240 | AB15: 7440 | AC15: 6210 | AD15: 6340
A16: price_high | C16: 종가(최고) | E16: 2810 | G16: 3590 | H16: 3490 | I16: 3410 | J16: 2800 | L16: 3024 | M16: 2414 | N16: 2626 | O16: 2440 | Q16: 2548 | R16: 5600 | S16: 4990 | T16: 6730 | V16: 7780 | W16: 8700 | X16: 12360 | Y16: 12900 | AA16: 10980 | AB16: 17000 | AC16: 8740 | AD16: 7000
A17: price_low | C17: 종가(최저) | E17: 2000 | G17: 2370 | H17: 2730 | I17: 2470 | J17: 2400 | L17: 1846 | M17: 1918 | N17: 1520 | O17: 1956 | Q17: 2060 | R17: 2346 | S17: 3616 | T17: 4120 | V17: 5740 | W17: 6320 | X17: 6190 | Y17: 8680 | AA17: 7020 | AB17: 6790 | AC17: 5480 | AD17: 5290
A18: price_avg | C18: 종가(평균) | E18: 2359.8 | G18: 2870.3 | H18: 3096.9 | I18: 2927.9 | J18: 2574.5 | L18: 2361.4 | M18: 2156.4 | N18: 2291.6 | O18: 2158.7 | Q18: 2261.4 | R18: 2852.3 | S18: 4252.5 | T18: 5182.8 | V18: 6779 | W18: 7703.5 | X18: 8976.2 | Y18: 10363.2 | AA18: 9207.1 | AB18: 10322.6 | AC18: 6807.6 | AD18: 5925
B20: 2. 추정 드라이버 | C20: 실적 열 = subQ 실현값(수식), 추정 열 = 가정(노란 = 모델값 역산, 연녹 = 3절 스칼라 참조)
A21: drv:매출액 | B21: yoy | C21: 매출액 YoY | J21: =IFERROR(subQ!J5/subQ!E5-1,"") | L21: =IFERROR(subQ!L5/subQ!G5-1,"") | M21: =IFERROR(subQ!M5/subQ!H5-1,"") | N21: =IFERROR(subQ!N5/subQ!I5-1,"") | O21: =IFERROR(subQ!O5/subQ!J5-1,"") | Q21: =IFERROR(subQ!Q5/subQ!L5-1,"") | R21: =IFERROR(subQ!R5/subQ!M5-1,"") | S21: =IFERROR(subQ!S5/subQ!N5-1,"") | T21: =IFERROR(subQ!T5/subQ!O5-1,"") | V21: =IFERROR(subQ!V5/subQ!Q5-1,"") | W21: =IFERROR(subQ!W5/subQ!R5-1,"") | X21: =IFERROR(subQ!X5/subQ!S5-1,"") | Y21: =IFERROR(subQ!Y5/subQ!T5-1,"") | AA21: =IFERROR(subQ!AA5/subQ!V5-1,"") | AB21: =IFERROR(subQ!AB5/subQ!W5-1,"") | AC21: 0.23876232 | AD21: 0.065639266 | AF21: 0.68010248 | AG21: 0.46971965 | AH21: 0.35049061 | AI21: 0.25592016 | AK21: 0.18330279 | AL21: 0.16239499 | AM21: 0.18039525 | AN21: 0.20896135
A22: drv:판관비 | B22: ratio | C22: 판관비율(/매출) | E22: =IFERROR(subQ!E8/subQ!E5,"") | F22: =IFERROR(subQ!F8/subQ!F5,"") | G22: =IFERROR(subQ!G8/subQ!G5,"") | H22: =IFERROR(subQ!H8/subQ!H5,"") | I22: =IFERROR(subQ!I8/subQ!I5,"") | J22: =IFERROR(subQ!J8/subQ!J5,"") | K22: =IFERROR(subQ!K8/subQ!K5,"") | L22: =IFERROR(subQ!L8/subQ!L5,"") | ... AB22: =IFERROR(subQ!AB8/subQ!AB5,"") | AC22: =$D$53 | AD22: =$D$53 | AE22: =IFERROR(subQ!AE8/subQ!AE5,"") | AF22: =$D$53 | AG22: =$D$53 | AH22: =$D$53 | AI22: =$D$53 | AJ22: =IFERROR(subQ!AJ8/subQ!AJ5,"") | AK22: =$D$53 | AL22: =$D$53 | AM22: =$D$53 | AN22: =$D$53 | AO22: =IFERROR(subQ!AO8/subQ!AO5,"")
A23: drv:영업이익 | B23: ratio | C23: 영업이익률(OPM) | E23: =IFERROR(subQ!E9/subQ!E5,"") | F23: =IFERROR(subQ!F9/subQ!F5,"") | G23: =IFERROR(subQ!G9/subQ!G5,"") | H23: =IFERROR(subQ!H9/subQ!H5,"") | I23: =IFERROR(subQ!I9/subQ!I5,"") | J23: =IFERROR(subQ!J9/subQ!J5,"") | K23: =IFERROR(subQ!K9/subQ!K5,"") | L23: =IFERROR(subQ!L9/subQ!L5,"") | ... AB23: =IFERROR(subQ!AB9/subQ!AB5,"") | AC23: 0.15074292 | AD23: 0.15073841 | AE23: =IFERROR(subQ!AE9/subQ!AE5,"") | AF23: 0.15073294 | AG23: 0.15074496 | AH23: 0.15075147 | AI23: 0.15075362 | AJ23: =IFERROR(subQ!AJ9/subQ!AJ5,"") | AK23: 0.15074618 | AL23: 0.15074111 | AM23: 0.15075094 | AN23: 0.15074707 | AO23: =IFERROR(subQ!AO9/subQ!AO5,"")
A24: drv:파생상품손익 | B24: abs | C24: 파생상품손익 (가정, 억원) | E24: =subQ!E13 | F24: =subQ!F13 | G24: =subQ!G13 | H24: =subQ!H13 | I24: =subQ!I13 | J24: =subQ!J13 | K24: =subQ!K13 | L24: =subQ!L13 | ... AB24: =subQ!AB13 | AC24: 0 | AD24: 0 | AE24: =subQ!AE13 | AF24: 0 | AG24: 0 | AH24: 0 | AI24: 0 | AJ24: =subQ!AJ13 | AK24: 0 | AL24: 0 | AM24: 0 | AN24: 0 | AO24: =subQ!AO13
A25: drv:기타금융손익 | B25: abs | C25: 기타금융손익 (가정, 억원) | E25: =subQ!E14 | F25: =subQ!F14 | G25: =subQ!G14 | H25: =subQ!H14 | I25: =subQ!I14 | J25: =subQ!J14 | K25: =subQ!K14 | L25: =subQ!L14 | ... AB25: =subQ!AB14 | AC25: 0 | AD25: 0 | AE25: =subQ!AE14 | AF25: 0 | AG25: 0 | AH25: 0 | AI25: 0 | AJ25: =subQ!AJ14 | AK25: 0 | AL25: 0 | AM25: 0 | AN25: 0 | AO25: =subQ!AO14
A26: drv:기타영업외손익 | B26: abs | C26: 기타영업외손익 (가정, 억원) | E26: =subQ!E15 | F26: =subQ!F15 | G26: =subQ!G15 | H26: =subQ!H15 | I26: =subQ!I15 | J26: =subQ!J15 | K26: =subQ!K15 | L26: =subQ!L15 | ... AB26: =subQ!AB15 | AC26: 0 | AD26: 0 | AE26: =subQ!AE15 | AF26: 0 | AG26: 0 | AH26: 0 | AI26: 0 | AJ26: =subQ!AJ15 | AK26: 0 | AL26: 0 | AM26: 0 | AN26: 0 | AO26: =subQ!AO15
A27: drv:지분법손익 | B27: abs | C27: 지분법손익 (가정, 억원) | E27: =subQ!E16 | F27: =subQ!F16 | G27: =subQ!G16 | H27: =subQ!H16 | I27: =subQ!I16 | J27: =subQ!J16 | K27: =subQ!K16 | L27: =subQ!L16 | ... AB27: =subQ!AB16 | AC27: 36.67 | AD27: 36.67 | AE27: =subQ!AE16 | AF27: 36.67 | AG27: 36.67 | AH27: 36.67 | AI27: 36.67 | AJ27: =subQ!AJ16 | AK27: 36.67 | AL27: 36.67 | AM27: 36.67 | AN27: 36.67 | AO27: =subQ!AO16
A28: drv:법인세비용 | B28: tax | C28: 법인세율(/세전) — 법인세 = MAX(세전,0) × 세율 | E28: =IFERROR(subQ!E18/subQ!E17,"") | F28: =IFERROR(subQ!F18/subQ!F17,"") | G28: =IFERROR(subQ!G18/subQ!G17,"") | H28: =IFERROR(subQ!H18/subQ!H17,"") | I28: =IFERROR(subQ!I18/subQ!I17,"") | J28: =IFERROR(subQ!J18/subQ!J17,"") | K28: =IFERROR(subQ!K18/subQ!K17,"") | L28: =IFERROR(subQ!L18/subQ!L17,"") | ... AB28: =IFERROR(subQ!AB18/subQ!AB17,"") | AC28: =$D$52 | AD28: =$D$52 | AE28: =IFERROR(subQ!AE18/subQ!AE17,"") | AF28: =$D$52 | AG28: =$D$52 | AH28: =$D$52 | AI28: =$D$52 | AJ28: =IFERROR(subQ!AJ18/subQ!AJ17,"") | AK28: =$D$52 | AL28: =$D$52 | AM28: =$D$52 | AN28: =$D$52 | AO28: =IFERROR(subQ!AO18/subQ!AO17,"")
A29: drv:지배주주순이익 | B29: ratio | C29: 지배주주 비중(/당기순이익) | E29: =IFERROR(subQ!E20/subQ!E19,"") | F29: =IFERROR(subQ!F20/subQ!F19,"") | G29: =IFERROR(subQ!G20/subQ!G19,"") | H29: =IFERROR(subQ!H20/subQ!H19,"") | I29: =IFERROR(subQ!I20/subQ!I19,"") | J29: =IFERROR(subQ!J20/subQ!J19,"") | K29: =IFERROR(subQ!K20/subQ!K19,"") | L29: =IFERROR(subQ!L20/subQ!L19,"") | ... AB29: =IFERROR(subQ!AB20/subQ!AB19,"") | AC29: =$D$54 | AD29: =$D$54 | AE29: =IFERROR(subQ!AE20/subQ!AE19,"") | AF29: =$D$54 | AG29: =$D$54 | AH29: =$D$54 | AI29: =$D$54 | AJ29: =IFERROR(subQ!AJ20/subQ!AJ19,"") | AK29: =$D$54 | AL29: =$D$54 | AM29: =$D$54 | AN29: =$D$54 | AO29: =IFERROR(subQ!AO20/subQ!AO19,"")
A30: drv:중단사업이익 | B30: abs | C30: 중단사업이익 (가정, 억원) | E30: =subQ!E21 | F30: =subQ!F21 | G30: =subQ!G21 | H30: =subQ!H21 | I30: =subQ!I21 | J30: =subQ!J21 | K30: =subQ!K21 | L30: =subQ!L21 | ... AB30: =subQ!AB21 | AE30: =subQ!AE21 | AJ30: =subQ!AJ21 | AO30: =subQ!AO21
A31: drv:감가상각비 | B31: abs | C31: 감가상각비 (가정, 억원) | E31: =subQ!E22 | F31: =subQ!F22 | G31: =subQ!G22 | H31: =subQ!H22 | I31: =subQ!I22 | J31: =subQ!J22 | K31: =subQ!K22 | L31: =subQ!L22 | ... AB31: =subQ!AB22 | AC31: 16.36 | AD31: 16.36 | AE31: =subQ!AE22 | AF31: 16.36 | AG31: 16.36 | AH31: 16.36 | AI31: 16.36 | AJ31: =subQ!AJ22 | AK31: 16.36 | AL31: 16.36 | AM31: 16.36 | AN31: 16.36 | AO31: =subQ!AO22
A32: drv:부채총계 | B32: qoq | C32: 부채총계 QoQ | G32: =IFERROR(subQ!G25/subQ!E25-1,"") | H32: =IFERROR(subQ!H25/subQ!G25-1,"") | I32: =IFERROR(subQ!I25/subQ!H25-1,"") | J32: =IFERROR(subQ!J25/subQ!I25-1,"") | L32: =IFERROR(subQ!L25/subQ!J25-1,"") | M32: =IFERROR(subQ!M25/subQ!L25-1,"") | N32: =IFERROR(subQ!N25/subQ!M25-1,"") | O32: =IFERROR(subQ!O25/subQ!N25-1,"") | Q32: =IFERROR(subQ!Q25/subQ!O25-1,"") | R32: =IFERROR(subQ!R25/subQ!Q25-1,"") | S32: =IFERROR(subQ!S25/subQ!R25-1,"") | T32: =IFERROR(subQ!T25/subQ!S25-1,"") | V32: =IFERROR(subQ!V25/subQ!T25-1,"") | W32: =IFERROR(subQ!W25/subQ!V25-1,"") | X32: =IFERROR(subQ!X25/subQ!W25-1,"") | Y32: =IFERROR(subQ!Y25/subQ!X25-1,"") | AA32: =IFERROR(subQ!AA25/subQ!Y25-1,"") | AB32: =IFERROR(subQ!AB25/subQ!AA25-1,"") | AC32: -2.46e-06 | AD32: 0 | AF32: 0 | AG32: 0 | AH32: 0 | AI32: 0 | AK32: 0 | AL32: 0 | AM32: 0 | AN32: 0
A33: drv:자본총계 | B33: roll | C33: 자본총계 기타변동(배당 등, 억원) | G33: =IFERROR(subQ!E26+subQ!G19-subQ!G26,"") | H33: =IFERROR(subQ!G26+subQ!H19-subQ!H26,"") | I33: =IFERROR(subQ!H26+subQ!I19-subQ!I26,"") | J33: =IFERROR(subQ!I26+subQ!J19-subQ!J26,"") | L33: =IFERROR(subQ!J26+subQ!L19-subQ!L26,"") | M33: =IFERROR(subQ!L26+subQ!M19-subQ!M26,"") | N33: =IFERROR(subQ!M26+subQ!N19-subQ!N26,"") | O33: =IFERROR(subQ!N26+subQ!O19-subQ!O26,"") | Q33: =IFERROR(subQ!O26+subQ!Q19-subQ!Q26,"") | R33: =IFERROR(subQ!Q26+subQ!R19-subQ!R26,"") | S33: =IFERROR(subQ!R26+subQ!S19-subQ!S26,"") | T33: =IFERROR(subQ!S26+subQ!T19-subQ!T26,"") | V33: =IFERROR(subQ!T26+subQ!V19-subQ!V26,"") | W33: =IFERROR(subQ!V26+subQ!W19-subQ!W26,"") | X33: =IFERROR(subQ!W26+subQ!X19-subQ!X26,"") | Y33: =IFERROR(subQ!X26+subQ!Y19-subQ!Y26,"") | AA33: =IFERROR(subQ!Y26+subQ!AA19-subQ!AA26,"") | AB33: =IFERROR(subQ!AA26+subQ!AB19-subQ!AB26,"") | AC33: -0.000809684 | AD33: -0.007846888 | AF33: -0.004257786 | AG33: 68.541078 | AH33: -0.005516347 | AI33: 0.002605387 | AK33: -0.005427026 | AL33: 68.540767 | AM33: 0.004508613 | AN33: 0.000793615
A34: drv:지배주주지분 | B34: roll | C34: 지배주주지분 기타변동(배당 등, 억원) | G34: =IFERROR(subQ!E27+subQ!G20-subQ!G27,"") | H34: =IFERROR(subQ!G27+subQ!H20-subQ!H27,"") | I34: =IFERROR(subQ!H27+subQ!I20-subQ!I27,"") | J34: =IFERROR(subQ!I27+subQ!J20-subQ!J27,"") | L34: =IFERROR(subQ!J27+subQ!L20-subQ!L27,"") | M34: =IFERROR(subQ!L27+subQ!M20-subQ!M27,"") | N34: =IFERROR(subQ!M27+subQ!N20-subQ!N27,"") | O34: =IFERROR(subQ!N27+subQ!O20-subQ!O27,"") | Q34: =IFERROR(subQ!O27+subQ!Q20-subQ!Q27,"") | R34: =IFERROR(subQ!Q27+subQ!R20-subQ!R27,"") | S34: =IFERROR(subQ!R27+subQ!S20-subQ!S27,"") | T34: =IFERROR(subQ!S27+subQ!T20-subQ!T27,"") | V34: =IFERROR(subQ!T27+subQ!V20-subQ!V27,"") | W34: =IFERROR(subQ!V27+subQ!W20-subQ!W27,"") | X34: =IFERROR(subQ!W27+subQ!X20-subQ!X27,"") | Y34: =IFERROR(subQ!X27+subQ!Y20-subQ!Y27,"") | AA34: =IFERROR(subQ!Y27+subQ!AA20-subQ!AA27,"") | AB34: =IFERROR(subQ!AA27+subQ!AB20-subQ!AB27,"") | AC34: -0.000809684 | AD34: -0.007846888 | AF34: -0.004257786 | AG34: 68.541078 | AH34: -0.005516347 | AI34: 0.002605387 | AK34: -0.005427026 | AL34: 68.540767 | AM34: 0.004508613 | AN34: 0.000793615
A35: drv:총차입금 | B35: qoq | C35: 총차입금 QoQ | G35: =IFERROR(subQ!G28/subQ!E28-1,"") | H35: =IFERROR(subQ!H28/subQ!G28-1,"") | I35: =IFERROR(subQ!I28/subQ!H28-1,"") | J35: =IFERROR(subQ!J28/subQ!I28-1,"") | L35: =IFERROR(subQ!L28/subQ!J28-1,"") | M35: =IFERROR(subQ!M28/subQ!L28-1,"") | N35: =IFERROR(subQ!N28/subQ!M28-1,"") | O35: =IFERROR(subQ!O28/subQ!N28-1,"") | Q35: =IFERROR(subQ!Q28/subQ!O28-1,"") | R35: =IFERROR(subQ!R28/subQ!Q28-1,"") | S35: =IFERROR(subQ!S28/subQ!R28-1,"") | T35: =IFERROR(subQ!T28/subQ!S28-1,"") | V35: =IFERROR(subQ!V28/subQ!T28-1,"") | W35: =IFERROR(subQ!W28/subQ!V28-1,"") | X35: =IFERROR(subQ!X28/subQ!W28-1,"") | Y35: =IFERROR(subQ!Y28/subQ!X28-1,"") | AA35: =IFERROR(subQ!AA28/subQ!Y28-1,"") | AB35: =IFERROR(subQ!AB28/subQ!AA28-1,"") | AC35: 0 | AD35: 0 | AF35: 0 | AG35: 0 | AH35: 0 | AI35: 0 | AK35: 0 | AL35: 0 | AM35: 0 | AN35: 0
A36: drv:순차입금 | B36: qoq | C36: 순차입금 QoQ | G36: =IFERROR(subQ!G29/subQ!E29-1,"") | H36: =IFERROR(subQ!H29/subQ!G29-1,"") | I36: =IFERROR(subQ!I29/subQ!H29-1,"") | J36: =IFERROR(subQ!J29/subQ!I29-1,"") | L36: =IFERROR(subQ!L29/subQ!J29-1,"") | M36: =IFERROR(subQ!M29/subQ!L29-1,"") | N36: =IFERROR(subQ!N29/subQ!M29-1,"") | O36: =IFERROR(subQ!O29/subQ!N29-1,"") | Q36: =IFERROR(subQ!Q29/subQ!O29-1,"") | R36: =IFERROR(subQ!R29/subQ!Q29-1,"") | S36: =IFERROR(subQ!S29/subQ!R29-1,"") | T36: =IFERROR(subQ!T29/subQ!S29-1,"") | V36: =IFERROR(subQ!V29/subQ!T29-1,"") | W36: =IFERROR(subQ!W29/subQ!V29-1,"") | X36: =IFERROR(subQ!X29/subQ!W29-1,"") | Y36: =IFERROR(subQ!Y29/subQ!X29-1,"") | AA36: =IFERROR(subQ!AA29/subQ!Y29-1,"") | AB36: =IFERROR(subQ!AB29/subQ!AA29-1,"") | AC36: -0.27779818 | AD36: -0.3390478 | AF36: -0.65623871 | AG36: -0.55674653 | AH36: -4.5908013 | AI36: 1.0674766 | AK36: 0.65121032 | AL36: 0.14392914 | AM36: 0.36819504 | AN36: 0.22524281
A37: drv:이자발생자산 | B37: qoq | C37: 이자발생자산 QoQ | G37: =IFERROR(subQ!G30/subQ!E30-1,"") | H37: =IFERROR(subQ!H30/subQ!G30-1,"") | I37: =IFERROR(subQ!I30/subQ!H30-1,"") | J37: =IFERROR(subQ!J30/subQ!I30-1,"") | L37: =IFERROR(subQ!L30/subQ!J30-1,"") | M37: =IFERROR(subQ!M30/subQ!L30-1,"") | N37: =IFERROR(subQ!N30/subQ!M30-1,"") | O37: =IFERROR(subQ!O30/subQ!N30-1,"") | Q37: =IFERROR(subQ!Q30/subQ!O30-1,"") | R37: =IFERROR(subQ!R30/subQ!Q30-1,"") | S37: =IFERROR(subQ!S30/subQ!R30-1,"") | T37: =IFERROR(subQ!T30/subQ!S30-1,"") | V37: =IFERROR(subQ!V30/subQ!T30-1,"") | W37: =IFERROR(subQ!W30/subQ!V30-1,"") | X37: =IFERROR(subQ!X30/subQ!W30-1,"") | Y37: =IFERROR(subQ!Y30/subQ!X30-1,"") | AA37: =IFERROR(subQ!AA30/subQ!Y30-1,"") | AB37: =IFERROR(subQ!AB30/subQ!AA30-1,"") | AC37: 0.09772563 | AD37: 0.078457594 | AF37: 0.093091893 | AG37: 0.024834763 | AH37: 0.08857054 | AI37: 0.067926653 | AK37: 0.080241425 | AL37: 0.027105976 | AM37: 0.077228594 | AN37: 0.059998947
A38: drv:현금및현금성자산 | B38: qoq | C38: 현금및현금성자산 QoQ | G38: =IFERROR(subQ!G31/subQ!E31-1,"") | H38: =IFERROR(subQ!H31/subQ!G31-1,"") | I38: =IFERROR(subQ!I31/subQ!H31-1,"") | J38: =IFERROR(subQ!J31/subQ!I31-1,"") | L38: =IFERROR(subQ!L31/subQ!J31-1,"") | M38: =IFERROR(subQ!M31/subQ!L31-1,"") | N38: =IFERROR(subQ!N31/subQ!M31-1,"") | O38: =IFERROR(subQ!O31/subQ!N31-1,"") | Q38: =IFERROR(subQ!Q31/subQ!O31-1,"") | R38: =IFERROR(subQ!R31/subQ!Q31-1,"") | S38: =IFERROR(subQ!S31/subQ!R31-1,"") | T38: =IFERROR(subQ!T31/subQ!S31-1,"") | V38: =IFERROR(subQ!V31/subQ!T31-1,"") | W38: =IFERROR(subQ!W31/subQ!V31-1,"") | X38: =IFERROR(subQ!X31/subQ!W31-1,"") | Y38: =IFERROR(subQ!Y31/subQ!X31-1,"") | AA38: =IFERROR(subQ!AA31/subQ!Y31-1,"") | AB38: =IFERROR(subQ!AB31/subQ!AA31-1,"")
A39: drv:CAPEX | B39: yoy | C39: CAPEX YoY | J39: =IFERROR(subQ!J32/subQ!E32-1,"") | L39: =IFERROR(subQ!L32/subQ!G32-1,"") | M39: =IFERROR(subQ!M32/subQ!H32-1,"") | N39: =IFERROR(subQ!N32/subQ!I32-1,"") | O39: =IFERROR(subQ!O32/subQ!J32-1,"") | Q39: =IFERROR(subQ!Q32/subQ!L32-1,"") | R39: =IFERROR(subQ!R32/subQ!M32-1,"") | S39: =IFERROR(subQ!S32/subQ!N32-1,"") | T39: =IFERROR(subQ!T32/subQ!O32-1,"") | V39: =IFERROR(subQ!V32/subQ!Q32-1,"") | W39: =IFERROR(subQ!W32/subQ!R32-1,"") | X39: =IFERROR(subQ!X32/subQ!S32-1,"") | Y39: =IFERROR(subQ!Y32/subQ!T32-1,"") | AA39: =IFERROR(subQ!AA32/subQ!V32-1,"") | AB39: =IFERROR(subQ!AB32/subQ!W32-1,"") | AC39: -0.11545521 | AD39: -0.69555124 | AF39: 1.4277001 | AG39: 0.15141048 | AH39: 0 | AI39: 0 | AK39: 0 | AL39: 0 | AM39: 0 | AN39: 0
A40: drv:영업활동현금흐름 | B40: yoy | C40: 영업활동현금흐름 YoY | J40: =IFERROR(subQ!J33/subQ!E33-1,"") | L40: =IFERROR(subQ!L33/subQ!G33-1,"") | M40: =IFERROR(subQ!M33/subQ!H33-1,"") | N40: =IFERROR(subQ!N33/subQ!I33-1,"") | O40: =IFERROR(subQ!O33/subQ!J33-1,"") | Q40: =IFERROR(subQ!Q33/subQ!L33-1,"") | R40: =IFERROR(subQ!R33/subQ!M33-1,"") | S40: =IFERROR(subQ!S33/subQ!N33-1,"") | T40: =IFERROR(subQ!T33/subQ!O33-1,"") | V40: =IFERROR(subQ!V33/subQ!Q33-1,"") | W40: =IFERROR(subQ!W33/subQ!R33-1,"") | X40: =IFERROR(subQ!X33/subQ!S33-1,"") | Y40: =IFERROR(subQ!Y33/subQ!T33-1,"") | AA40: =IFERROR(subQ!AA33/subQ!V33-1,"") | AB40: =IFERROR(subQ!AB33/subQ!W33-1,"")
A41: drv:주식수 | B41: qoq | C41: 주식수 QoQ | G41: =IFERROR(subQ!G34/subQ!E34-1,"") | H41: =IFERROR(subQ!H34/subQ!G34-1,"") | I41: =IFERROR(subQ!I34/subQ!H34-1,"") | J41: =IFERROR(subQ!J34/subQ!I34-1,"") | L41: =IFERROR(subQ!L34/subQ!J34-1,"") | M41: =IFERROR(subQ!M34/subQ!L34-1,"") | N41: =IFERROR(subQ!N34/subQ!M34-1,"") | O41: =IFERROR(subQ!O34/subQ!N34-1,"") | Q41: =IFERROR(subQ!Q34/subQ!O34-1,"") | R41: =IFERROR(subQ!R34/subQ!Q34-1,"") | S41: =IFERROR(subQ!S34/subQ!R34-1,"") | T41: =IFERROR(subQ!T34/subQ!S34-1,"") | V41: =IFERROR(subQ!V34/subQ!T34-1,"") | W41: =IFERROR(subQ!W34/subQ!V34-1,"") | X41: =IFERROR(subQ!X34/subQ!W34-1,"") | Y41: =IFERROR(subQ!Y34/subQ!X34-1,"") | AA41: =IFERROR(subQ!AA34/subQ!Y34-1,"") | AB41: =IFERROR(subQ!AB34/subQ!AA34-1,"") | AC41: 0 | AD41: 0 | AF41: 0 | AG41: 0 | AH41: 0 | AI41: 0 | AK41: 0 | AL41: 0 | AM41: 0 | AN41: 0
A42: drv:DPS | B42: abs | C42: DPS (가정, 원) | E42: =subQ!E37 | F42: =subQ!F37 | G42: =subQ!G37 | H42: =subQ!H37 | I42: =subQ!I37 | J42: =subQ!J37 | K42: =subQ!K37 | L42: =subQ!L37 | ... AB42: =subQ!AB37 | AD42: 150 | AE42: =subQ!AE37 | AI42: 150 | AJ42: =subQ!AJ37 | AN42: 150 | AO42: =subQ!AO37
B44: 3. 밸류에이션·스칼라 | C44: 노란 셀 = 가정. '연결' 표시는 추정 전 분기 수식이 이 셀을 참조한다는 뜻
A45: sc:종가 | C45: 종가 | D45: 6340 | E45: 원 — 네이버 정규장 종가(aik 확정종가 대조 · aik 5,810원)
A46: sc:기준일 | C46: 기준일 | D46: 20261026 | E46: 종가 기준일
A47: sc:COE | C47: COE | D47: 0.09 | E47: 자기자본비용(가정) — TP 적정 PBR = ROE/COE
A48: sc:PER_lo | C48: PER_lo | D48: 5 | E48: PER 밴드 하단(배) — hist_quarterly(분기 평균가 ÷ TTM EPS, 10분기, 25/50/75 백분위) · 캡 5~30배 적용(원값 3.8/15.5/22.2)
A49: sc:PER_mid | C49: PER_mid | D49: 15.5 | E49: PER 밴드 중단(배)
A50: sc:PER_hi | C50: PER_hi | D50: 22.2 | E50: PER 밴드 상단(배)
A51: sc:EPS_Y1가중 | C51: EPS_Y1가중 | D51: 0.5 | E51: 12M fwd EPS = FY(last_actual연도)E × w + FY+1E × (1−w) — 기준 분기 2Q 이면 0.5(가정)
A52: sc:세율 | C52: 세율 | D52: 0.21944323 | E52: 연결 — 법인세 = MAX(세전,0) × 세율(역산, 재현 오차 ≤ 0.05억 · 모델 assumptions 0.2194) · 최근 12분기 유효세율 21.9%(5~27% 안 — 그대로)
A53: sc:판관비율 | C53: 판관비율 | D53: 0.085835026 | E53: 연결 — 판관비 = 매출액 × 판관비율(역산, 재현 오차 ≤ 0.05억 · 모델 assumptions 0.0858)
A54: sc:지배주주비중 | C54: 지배주주비중 | D54: 1 | E54: 연결 — 지배주주순이익 = 당기순이익 × 비중(역산, 재현 오차 ≤ 0.05억)
A55: sc:이자율_자산 | C55: 이자율_자산 | D55: 0.029837492 | E55: 연결 — 이자손익 = (전분기 이자발생자산 × 자산이자율 − 전분기 총차입금 × 부채이자율)/4(역산, 재현 오차 ≤ 0.05억 · 모델 assumptions 0.0298)
A56: sc:이자율_부채 | C56: 이자율_부채 | D56: 0.035240427 | E56: 연결 — 같은 수식의 부채 쪽(총차입금 행이 없으면 0)(역산, 재현 오차 ≤ 0.05억 · 모델 assumptions 0.0352)
A57: sc:배당성향 | C57: 배당성향 | D57: 0.2681 | E57: 배당성향(참고 — 모델은 직전 DPS 유지·Q2 지급 가정)
A58: sc:외화순노출_백만$ | C58: 외화순노출_백만$ | E58: 외화 순노출 × Δ기말환율 (외화 시트 방식) — 외화 순노출 미공시(face) → 0 + 표기
A59: sc:헤지비율 | C59: 헤지비율 | E59: sls 없음
A60: sc:헤지환율_약정 | C60: 헤지환율_약정 | E60: sls 없음

Sheet BS연결
B1: (백만원) | C1: 이름: BS연결H | E1: 4Q21 | F1: 2021 | G1: 1Q22 | H1: 2Q22 | I1: 3Q22 | J1: 4Q22 | K1: 2022 | L1: 1Q23 | M1: 2Q23 | N1: 3Q23 | O1: 4Q23 | P1: 2023 | Q1: 1Q24 | R1: 2Q24 | S1: 3Q24 | T1: 4Q24 | U1: 2024 | V1: 1Q25 | W1: 2Q25 | X1: 3Q25 | Y1: 4Q25 | Z1: 2025 | AA1: 1Q26 | AB1: 2Q26 | AC1: 3Q26 | AD1: 4Q26 | AE1: 2026 | AF1: 1Q27 | AG1: 2Q27 | AH1: 3Q27 | AI1: 4Q27 | AJ1: 2027 | AK1: 1Q28 | AL1: 2Q28 | AM1: 3Q28 | AN1: 4Q28 | AO1: 2028
B2: 연결 | D2: fin json(kship_fin.py)
B3: 인화정공(연) | C3: UPDATE: 26-10-26 | E3: 1 | F3: 2 | G3: 3 | H3: 4 | I3: 5 | J3: 6 | K3: 7 | L3: 8 | M3: 9 | N3: 10 | O3: 11 | P3: 12 | Q3: 13 | R3: 14 | S3: 15 | T3: 16 | U3: 17 | V3: 18 | W3: 19 | X3: 20 | Y3: 21 | Z3: 22 | AA3: 23 | AB3: 24 | AC3: 25 | AD3: 26 | AE3: 27 | AF3: 28 | AG3: 29 | AH3: 30 | AI3: 31 | AJ3: 32 | AK3: 33 | AL3: 34 | AM3: 35 | AN3: 36 | AO3: 37
B4: Account Code | C4: AccountNAME | E4: 2021.12 | F4: 2021.12A | G4: 2022.03 | H4: 2022.06 | I4: 2022.09 | J4: 2022.12 | K4: 2022.12A | L4: 2023.03 | M4: 2023.06 | N4: 2023.09 | O4: 2023.12 | P4: 2023.12A | Q4: 2024.03 | R4: 2024.06 | S4: 2024.09 | T4: 2024.12 | U4: 2024.12A | V4: 2025.03 | W4: 2025.06 | X4: 2025.09 | Y4: 2025.12 | Z4: 2025.12A | AA4: 2026.03 | AB4: 2026.06 | AC4: 2026.09 | AD4: 2026.12 | AE4: 2026.12A | AF4: 2027.03 | AG4: 2027.06 | AH4: 2027.09 | AI4: 2027.12 | AJ4: 2027.12A | AK4: 2028.03 | AL4: 2028.06 | AM4: 2028.09 | AN4: 2028.12 | AO4: 2028.12A
A5: 1 | C5: 유동자산 | E5: 101723.74 | F5: 101723.74 | G5: 99806.1 | H5: 116046.67 | I5: 89406.79 | J5: 85858.05 | K5: 85858.05 | L5: 91617.72 | M5: 78320.56 | N5: 99152.72 | O5: 74798.44 | P5: 74798.44 | Q5: 90892.17 | R5: 105632.19 | S5: 104122.38 | T5: 104918.13 | U5: 104918.13 | V5: 211162.88 | W5: 177354.45 | X5: 221238.06 | Y5: 224602.52 | Z5: 224602.52 | AA5: 211813.39 | AB5: 179456.63
A6: 1 | C6: 현금및현금성자산 | E6: 28788.2 | F6: 28788.2 | G6: 27451.56 | H6: 45899.33 | I6: 19614.96 | J6: 12136.96 | K6: 12136.96 | L6: 10169.51 | M6: 7790.28 | N6: 23817.59 | O6: 29637.86 | P6: 29637.86 | Q6: 25376.1 | R6: 11142.13 | S6: 14042.55 | T6: 13305.55 | U6: 13305.55 | V6: 29599.31 | W6: 21715.88 | X6: 21060.28 | Y6: 18187.38 | Z6: 18187.38 | AA6: 17822.96 | AB6: 17643.95
A7: 1 | C7: 단기금융상품 | E7: 13649.67 | F7: 13649.67 | G7: 14262.76 | H7: 11898 | I7: 12198 | J7: 14298 | K7: 14298 | L7: 12306.67 | M7: 12150.67 | N7: 12477.42 | O7: 3594.41 | P7: 3594.41 | Q7: 33620.87 | R7: 24112.2 | S7: 51378.68 | T7: 46104.83 | U7: 46104.83 | V7: 136841.32 | W7: 111522.12 | X7: 168162.1
A8: 1 | C8: 단기금융자산 | E8: 19437.04 | F8: 19437.04 | G8: 18974.05 | H8: 18817.42 | I8: 16094.42 | J8: 17939.81 | K8: 17939.81 | L8: 15619.01 | M8: 15130.62 | N8: 17529.75 | O8: 5136.41 | P8: 5136.41 | Q8: 36148.47 | R8: 63936.54 | S8: 51378.68 | T8: 46104.83 | U8: 46104.83 | V8: 136841.32 | W8: 111556.35 | X8: 168162.1
A9: 1 | C9: 매출채권및기타채권 | E9: 43852.09 | F9: 43852.09 | G9: 49750.99 | H9: 35821.4 | I9: 41350.35 | J9: 55075.16 | K9: 55075.16 | L9: 64340.64 | M9: 42859.01 | N9: 44257.07 | O9: 54322.55 | P9: 54322.55 | Q9: 34498.02 | R9: 75628.44 | S9: 35520.47 | T9: 43956.1 | U9: 43956.1 | V9: 49471.95 | W9: 44276.78 | X9: 34225.3 | Y9: 15284.69 | Z9: 15284.69 | AA9: 17066.07 | AB9: 16777.91
A10: 1 | C10: 단기대여금 | E10: 1787.37 | F10: 1787.37 | G10: 1211.29 | H10: 1684.37 | I10: 1661.37 | J10: 1803.72 | K10: 1803.72 | L10: 1983.72 | M10: 2533.74 | N10: 4613.62 | O10: 1326.84 | P10: 1326.84 | Q10: 2325.59 | R10: 39824.34
A11: 1 | C11: 당기법인세자산(선급법인세) | E11: 25.28 | F11: 25.28 | G11: 13.07 | H11: 14.33 | I11: 170.16 | J11: 39.53 | K11: 39.53 | L11: 36.18 | M11: 33.48 | N11: 132.39 | O11: 326.29 | P11: 326.29 | Q11: 34.07 | R11: 19.34 | S11: 25.01 | T11: 34.55 | U11: 34.55 | V11: 31.81 | W11: 20.85 | X11: 25.41 | Y11: 29.9 | Z11: 29.9 | AA11: 32.42 | AB11: 23.19
A12: 1 | C12: 재고자산 | E12: 32539.81 | F12: 32539.81 | G12: 29153.76 | H12: 34145.5 | I12: 33589.33 | J12: 27926.1 | K12: 27926.1 | L12: 29933.31 | M12: 33779.36 | N12: 37646.26 | O12: 13443.51 | P12: 13443.51 | Q12: 13392.77 | R12: 12761.5 | S12: 14457.59 | T12: 16839.1 | U12: 16839.1 | V12: 13147.61 | W12: 14798.07 | X12: 13410.53 | Y12: 14789.23 | Z12: 14789.23 | AA12: 15617.58 | AB12: 16381.45
A13: 1 | C13: 기타유동금융자산 | E13: 4000 | F13: 4000 | G13: 3500 | H13: 5235.05 | I13: 2235.05 | J13: 1838.09 | K13: 1838.09 | L13: 1328.62 | M13: 446.21 | N13: 438.71 | O13: 215.16 | P13: 215.16 | Q13: 202.01 | R13: 0 | S13: 0 | T13: 0 | U13: 0 | W13: 34.23 | Y13: 172107.12 | Z13: 172107.12 | AA13: 158557.95 | AB13: 125341
A14: 1 | C14: 유동파생상품자산 | E14: 0 | F14: 0 | H14: 1735.05 | I14: 1735.05 | J14: 1338.09 | K14: 1338.09 | L14: 1328.62 | M14: 446.21 | N14: 438.71 | O14: 215.16 | P14: 215.16 | Q14: 202.01 | R14: 0 | S14: 0 | T14: 0 | U14: 0 | W14: 34.23
A15: 1 | C15: 비유동자산 | E15: 262975.94 | F15: 262975.94 | G15: 245866.22 | H15: 230958.45 | I15: 256459.19 | J15: 254863.66 | K15: 254863.66 | L15: 255594.17 | M15: 254568.07 | N15: 254180.01 | O15: 244392.17 | P15: 244392.17 | Q15: 265414.99 | R15: 304449.72 | S15: 289588.77 | T15: 325338.58 | U15: 325338.58 | V15: 232258.64 | W15: 268788.88 | X15: 241928.84 | Y15: 237467.73 | Z15: 237467.73 | AA15: 240715.96 | AB15: 253109.93
A16: 1 | C16: 장기금융자산 | E16: 3113.38 | F16: 3113.38 | G16: 2759.46 | H16: 2680.64 | I16: 2259.7 | J16: 2650.3 | K16: 2650.3 | L16: 2717.31 | M16: 2792.06 | N16: 2971.8 | O16: 1237.16 | P16: 1237.16 | Q16: 82706.26 | R16: 130886.66 | S16: 112929.07 | T16: 154214 | U16: 154214 | V16: 64914.86 | W16: 86030.52 | X16: 69675.14 | Y16: 54668.44 | Z16: 54668.44 | AA16: 55636.22 | AB16: 64782.84
A17: 1 | C17: 투자자산 | E17: 3613.38 | F17: 3613.38 | G17: 3159.46 | H17: 3080.64 | I17: 2659.7 | J17: 2950.3 | K17: 2950.3 | L17: 2817.31 | M17: 2892.06 | N17: 3571.8 | O17: 1822.16 | P17: 1822.16 | Q17: 83291.26 | R17: 130971.66 | S17: 112929.07 | T17: 154214 | U17: 154214 | V17: 64914.86 | W17: 86030.52 | X17: 69675.14 | Y17: 136527.32 | Z17: 136527.32 | AA17: 140054.9 | AB17: 153976.26
A18: 1 | C18: 장기매출채권및기타채권 | E18: 607.82 | F18: 607.82 | G18: 515.22 | H18: 463.73 | I18: 467.22 | J18: 377.74 | K18: 377.74 | L18: 163.12 | M18: 168.31 | N18: 667.69 | O18: 614.14 | P18: 614.14 | Q18: 614.37 | R18: 114.6 | Y18: 88.65 | Z18: 88.65 | AA18: 88.71 | AB18: 87.73
A19: 1 | C19: 장기대여금 | E19: 500 | F19: 500 | G19: 400 | H19: 400 | I19: 400 | J19: 300 | K19: 300 | L19: 100 | M19: 100 | N19: 600 | O19: 585 | P19: 585 | Q19: 585 | R19: 85
A20: 1 | C20: 유형자산 | E20: 95904.1 | F20: 95904.1 | G20: 94740.88 | H20: 93535.42 | I20: 92217.09 | J20: 91617.92 | K20: 91617.92 | L20: 90785.73 | M20: 89839.33 | N20: 88821.98 | O20: 71627.21 | P20: 71627.21 | Q20: 71242.99 | R20: 71288.51 | S20: 71347.01 | T20: 71009.16 | U20: 71009.16 | V20: 72084.03 | W20: 72164.57 | X20: 72111.12 | Y20: 73564.73 | Z20: 73564.73 | AA20: 73024.99 | AB20: 72387.9
A21: 1 | C21: 투자부동산 | E21: 38214.31 | F21: 38214.31 | G21: 38286.21 | H21: 35011.07 | I21: 32632.19 | J21: 32695.11 | K21: 32695.11 | L21: 32695.11 | M21: 32757.02 | N21: 33627.39 | O21: 28445.6 | P21: 28445.6 | Q21: 28445.6 | R21: 29252.81 | S21: 29268.81 | T21: 29268.81 | U21: 29268.81 | V21: 29205.88 | W21: 29205.88 | X21: 29205.88 | Y21: 27133.65 | Z21: 27133.65 | AA21: 26995.95 | AB21: 25607.38
A22: 1 | C22: 무형자산 | E22: 142 | F22: 142 | G22: 138.97 | H22: 128.94 | I22: 125.46 | J22: 123.85 | K22: 123.85 | L22: 122.94 | M22: 122.09 | N22: 121.5 | O22: 116.81 | P22: 116.81 | Q22: 116.67 | R22: 116.53 | S22: 116.39 | T22: 116.26 | U22: 116.26 | V22: 116.16 | W22: 116.06 | X22: 115.96 | Y22: 115.86 | Z22: 115.86 | AA22: 523.76 | AB22: 523.66
A23: 1 | C23: 이연법인세자산 | E23: 96.53 | F23: 96.53 | G23: 96.53 | J23: 0 | K23: 0 | O23: 2665.45 | P23: 2665.45 | Q23: 0 | R23: 0 | S23: 0 | T23: 0 | U23: 0 | V23: 0 | W23: 0 | Y23: 0 | Z23: 0
A24: 1 | C24: 기타비유동자산 | E24: 3.14 | F24: 3.14 | G24: 4.04 | H24: 11.43 | I24: 8.52 | J24: 7.39 | K24: 7.39 | L24: 11.81 | M24: 84463.45 | N24: 84462.51 | O24: 12.55 | P24: 12.55 | Q24: 11.56 | R24: 276.69 | S24: 103.07 | T24: 8.28 | U24: 8.28 | V24: 8.63 | W24: 6.98 | X24: 6.51 | Y24: 37.52 | Z24: 37.52 | AA24: 27.65 | AB24: 527.01
A25: 1 | C25: 자산총계 | E25: 364699.68 | F25: 364699.68 | G25: 345672.32 | H25: 347005.12 | I25: 345865.98 | J25: 340721.71 | K25: 340721.71 | L25: 347211.89 | M25: 332888.63 | N25: 353332.72 | O25: 319190.61 | P25: 319190.61 | Q25: 356307.15 | R25: 410081.9 | S25: 393711.15 | T25: 430256.71 | U25: 430256.71 | V25: 443421.53 | W25: 446143.32 | X25: 463166.9 | Y25: 462070.25 | Z25: 462070.25 | AA25: 452529.34 | AB25: 432566.56
A26: 1 | C26: 유동부채 | E26: 169586.87 | F26: 169586.87 | G26: 162047.67 | H26: 165948.12 | I26: 160920.17 | J26: 158686.2 | K26: 158686.2 | L26: 162871.2 | M26: 156116.89 | N26: 177484.85 | O26: 143470.04 | P26: 143470.04 | Q26: 133236.74 | R26: 130000.04 | S26: 131416.55 | T26: 133955.18 | U26: 133955.18 | V26: 144952.79 | W26: 122439.31 | X26: 117628 | Y26: 107007.16 | Z26: 107007.16 | AA26: 98168.73 | AB26: 62469.72
A27: 1 | C27: 매입채무및기타채무 | E27: 156919.62 | F27: 156919.62 | G27: 154814.86 | H27: 160944.21 | I27: 156115 | J27: 153694.1 | K27: 153694.1 | L27: 158386.33 | M27: 153948.19 | N27: 175558.47 | O27: 142343.96 | P27: 142343.96 | Q27: 122403.27 | R27: 121070.41 | S27: 120824.44 | T27: 123353.53 | U27: 123353.53 | V27: 118084.63 | W27: 100154.51 | X27: 83285.02 | Y27: 8383.42 | Z27: 8383.42 | AA27: 7526.44 | AB27: 8124.91
A28: 1 | C28: 단기차입금 | E28: 131396 | F28: 131396 | G28: 129456 | H28: 132156 | I28: 126576 | J28: 126576 | K28: 126576 | L28: 126726 | M28: 126576 | N28: 130836 | O28: 108680 | P28: 108680 | Q28: 103680 | R28: 109180 | S28: 109530 | T28: 109530 | U28: 109530 | V28: 99530 | W28: 74530 | X28: 58880 | Y28: 46880 | Z28: 46880 | AA28: 46880 | AB28: 45340
A29: 1 | C29: 유동성장기부채 | E29: 2579.4 | F29: 2579.4 | G29: 2079.4 | H29: 7602.9 | I29: 7763.82 | J29: 7924.78 | K29: 7924.78 | L29: 7082.23 | M29: 7248.98 | N29: 7410.69 | O29: 7574.85 | P29: 7574.85 | Q29: 7750.72 | R29: 1000 | S29: 1000 | T29: 1000 | U29: 1000 | V29: 1000 | W29: 14500 | X29: 14500 | Y29: 14500 | Z29: 14500 | AA29: 15000 | AB29: 1000
A30: 1 | C30: 유동리스부채 | E30: 46.2 | F30: 46.2 | G30: 44.07 | H30: 55.32 | I30: 56.87 | J30: 64.09 | K30: 64.09 | L30: 55.48 | M30: 73.89 | N30: 67.36 | O30: 41.71 | P30: 41.71 | Q30: 42.13 | R30: 45.09 | S30: 45.52 | T30: 45.96 | U30: 45.96 | V30: 30.6 | W30: 28.78 | X30: 25.75
A31: 1 | C31: 리스부채 | E31: 83.4 | F31: 83.4 | G31: 70.32 | H31: 105.38 | I31: 113.03 | J31: 157.98 | K31: 157.98 | L31: 139.47 | M31: 225.12 | N31: 203.91 | O31: 137.17 | P31: 137.17 | Q31: 126.26 | R31: 115.25 | S31: 104.13 | T31: 92.92 | U31: 92.92 | V31: 53.49 | W31: 45.89 | X31: 38.24 | Y31: 7.83 | Z31: 7.83 | AA31: 3.14 | AB31: 36.47
A32: 1 | C32: 단기금융부채 | E32: 46.2 | F32: 46.2 | G32: 46.45 | H32: 8711.56 | I32: 8721.93 | J32: 7678.61 | K32: 7678.61 | L32: 7670 | M32: 3676.51 | N32: 3679.68 | O32: 2236.51 | P32: 2236.51 | Q32: 2244.85 | R32: 45.09 | S32: 45.52 | T32: 97.36 | U32: 97.36 | V32: 32.04 | W32: 28.78 | X32: 25.75 | Y32: 0 | Z32: 0
A33: 1 | C33: 당기법인세부채(미지급법인세) | E33: 12667.25 | F33: 12667.25 | G33: 7231.62 | H33: 675.79 | I33: 472.63 | J33: 1184.84 | K33: 1184.84 | L33: 677.61 | M33: 367.4 | N33: 120.23 | O33: 28.68 | P33: 28.68 | Q33: 9732.1 | R33: 8929.64 | S33: 10592.11 | T33: 10575.94 | U33: 10575.94 | V33: 26867.44 | W33: 22284.79 | X33: 34342.98 | Y33: 34331.23 | Z33: 34331.23 | AA33: 19602.36 | AB33: 2268.65
A34: 1 | C34: 비유동부채 | E34: 5488.26 | F34: 5488.26 | G34: 5649.85 | H34: 10965.58 | I34: 13412.87 | J34: 11684.9 | K34: 11684.9 | L34: 11886.66 | M34: 12002.48 | N34: 12140.65 | O34: 7035.45 | P34: 7035.45 | Q34: 11092.59 | R34: 30054.15 | S34: 25324.75 | T34: 36376.77 | U34: 36376.77 | V34: 24319.48 | W34: 15069.58 | X34: 13613.61 | Y34: 13709.31 | Z34: 13709.31 | AA34: 13085.1 | AB34: 14755.47
A35: 1 | C35: 장기매입채무및기타채무 | E35: 1795.9 | F35: 1795.9 | G35: 1679.02 | H35: 7244.9 | I35: 9498.1 | J35: 9623.82 | K35: 9623.82 | L35: 9914.31 | M35: 9809.35 | N35: 9920.46 | O35: 7152.65 | P35: 7152.65 | Q35: 7293.56 | R35: 14505.22 | S35: 14341.85 | T35: 14168.91 | U35: 14168.91 | V35: 15124.54 | W35: 1098.47 | X35: 1423.55 | Y35: 127.53 | Z35: 127.53 | AA35: 120 | AB35: 50
A36: 1 | C36: 기타비유동부채 | E36: 711 | F36: 711 | G36: 661 | H36: 781 | I36: 441.15 | J36: 442.15 | K36: 442.15 | L36: 325.74 | M36: 442.4 | N36: 440.75 | O36: 190 | P36: 190 | Q36: 190 | R36: 190
A37: 1 | C37: 장기차입금 | E37: 116.2 | F37: 116.2 | G37: 96.35 | H37: 76.5 | I37: 2556.65 | J37: 2536.8 | K37: 2536.8 | L37: 2516.95 | M37: 2500 | N37: 2500 | O37: 0 | P37: 0 | Q37: 0 | R37: 14000 | S37: 14000 | T37: 14000 | U37: 14000 | V37: 15000 | W37: 1000 | X37: 1300 | Y37: 1300 | Z37: 1300 | AA37: 300 | AB37: 300
A38: 1 | C38: 비유동리스부채 | E38: 37.2 | F38: 37.2 | G38: 26.25 | H38: 50.06 | I38: 56.16 | J38: 93.89 | K38: 93.89 | L38: 83.99 | M38: 151.23 | N38: 136.55 | O38: 95.46 | P38: 95.46 | Q38: 84.13 | R38: 70.16 | S38: 58.61 | T38: 46.96 | U38: 46.96 | V38: 22.89 | W38: 17.11 | X38: 12.49 | Y38: 7.83 | Z38: 7.83 | AA38: 3.14 | AB38: 36.47
A39: 1 | C39: 장기금융부채 | E39: 37.2 | F39: 37.2 | G39: 26.25 | H39: 50.06 | I39: 56.16 | J39: 93.89 | K39: 93.89 | L39: 83.99 | M39: 151.23 | N39: 136.55 | O39: 95.46 | P39: 95.46 | Q39: 84.13 | R39: 70.16 | S39: 58.61 | T39: 46.96 | U39: 46.96 | V39: 22.89 | W39: 17.11 | X39: 12.49 | Y39: 7.83 | Z39: 7.83 | AA39: 3.14 | AB39: 36.47
A40: 1 | C40: 장기충당부채 | E40: 0 | F40: 0
A41: 1 | C41: 확정급여부채 | E41: 678.48 | F41: 678.48 | G41: 899.01 | H41: 550.85 | I41: 736.34 | J41: 0 | K41: 0 | L41: 0 | O41: 45.92 | P41: 45.92 | Q41: 226.77 | R41: 0 | S41: 0 | T41: 0 | U41: 0 | V41: 188.87 | X41: 203.68 | Y41: 6.26 | Z41: 6.26 | AA41: 220.62
A42: 1 | C42: 이연법인세부채 | E42: 3479.63 | F42: 3479.63 | G42: 3519.53 | H42: 3576.75 | I42: 3558.29 | J42: 2413.89 | K42: 2413.89 | L42: 2464.75 | M42: 2464.75 | N42: 2464.75 | O42: 0 | P42: 0 | Q42: 3715.09 | R42: 15671.46 | S42: 10982.9 | T42: 22207.87 | U42: 22207.87 | V42: 9006.06 | W42: 13971.11 | X42: 11986.39 | Y42: 12267.69 | Z42: 12267.69 | AA42: 12441.34 | AB42: 14369
A43: 1 | C43: 부채총계 | E43: 175075.13 | F43: 175075.13 | G43: 167697.52 | H43: 176913.7 | I43: 174333.04 | J43: 170371.1 | K43: 170371.1 | L43: 174757.86 | M43: 168119.38 | N43: 189625.5 | O43: 150505.49 | P43: 150505.49 | Q43: 144329.32 | R43: 160054.19 | S43: 156741.3 | T43: 170331.95 | U43: 170331.95 | V43: 169272.26 | W43: 137508.89 | X43: 131241.61 | Y43: 120716.47 | Z43: 120716.47 | AA43: 111253.84 | AB43: 77225.19
A44: 1 | C44: 지배주주지분 | E44: 189624.55 | F44: 189624.55 | G44: 177974.8 | H44: 170091.41 | I44: 171532.94 | J44: 170350.61 | K44: 170350.61 | L44: 172454.03 | M44: 164769.26 | N44: 163707.22 | O44: 168685.12 | P44: 168685.12 | Q44: 211977.83 | R44: 250027.71 | S44: 236969.85 | T44: 259924.76 | U44: 259924.76 | V44: 274149.27 | W44: 308634.44 | X44: 331925.29 | Y44: 341353.79 | Z44: 341353.79 | AA44: 341275.51 | AB44: 355341.37
A45: 1 | C45: 자본금 | E45: 4665.85 | F45: 4665.85 | G45: 4665.85 | H45: 4665.85 | I45: 4665.85 | J45: 4665.85 | K45: 4665.85 | L45: 4665.85 | M45: 4665.85 | N45: 4665.85 | O45: 4665.85 | P45: 4665.85 | Q45: 4665.85 | R45: 4940.08 | S45: 4940.08 | T45: 4940.08 | U45: 4940.08 | V45: 4940.08 | W45: 4940.08 | X45: 4940.08 | Y45: 4940.08 | Z45: 4940.08 | AA45: 4940.08 | AB45: 4940.08
A46: 1 | C46: 보통주자본금 | E46: 4665.85 | F46: 4665.85 | G46: 4665.85 | H46: 4665.85 | I46: 4665.85 | J46: 4665.85 | K46: 4665.85 | L46: 4665.85 | M46: 4665.85 | N46: 4665.85 | O46: 4665.85 | P46: 4665.85 | Q46: 4665.85 | R46: 4940.08 | S46: 4940.08 | T46: 4940.08 | U46: 4940.08 | V46: 4940.08 | W46: 4940.08 | X46: 4940.08
A47: 1 | C47: 자본잉여금 | E47: 94541.76 | F47: 94541.76 | G47: 94541.76 | H47: 94541.76 | I47: 94541.76 | J47: 94541.76 | K47: 94541.76 | L47: 94541.76 | M47: 94541.76 | N47: 94541.76 | O47: 13983.76 | P47: 13983.76 | Q47: 13983.76 | R47: 40581.88 | S47: 40581.88 | T47: 40581.88 | U47: 40581.88 | V47: 27961.88 | W47: 27961.88 | X47: 27961.88 | Y47: 13825.38 | Z47: 13825.38 | AA47: 11036.06 | AB47: 13825.38
A48: 1 | C48: 기타자본 | E48: -4391.6 | F48: -4391.6 | G48: -309.35 | H48: -309.35 | I48: -359.56 | J48: -359.56 | K48: -359.56 | L48: -359.56 | M48: -359.56 | N48: -4512.86 | O48: -6264.38 | P48: -6264.38 | Q48: -311.12 | R48: -311.12 | S48: -4895.83 | T48: -14532.13 | U48: -14532.13 | V48: -17394.4 | W48: -19941.66 | X48: -311.12 | Y48: 29098.89 | Z48: 29098.89 | AA48: 29657.46 | AB48: 36574.1
A49: 1 | C49: 기타포괄이익누계액 | E49: -696.55 | F49: -696.55 | G49: -897.92 | H49: -202 | I49: 43.58 | J49: 732.31 | K49: 732.31 | L49: 846.74 | M49: 637.59 | N49: 679.86 | O49: 158.27 | P49: 158.27 | Q49: 10815.82 | R49: 47534.88 | S49: 33708.68 | T49: 65440.32 | U49: 65440.32 | V49: 30035.84 | W49: 46568.53 | X49: 39850.4
A50: 1 | C50: 이익잉여금 | E50: 140580.17 | F50: 140580.17 | G50: 127090.66 | H50: 118511.36 | I50: 119732.4 | J50: 117861.35 | K50: 117861.35 | L50: 119850.33 | M50: 112374.71 | N50: 113347.06 | O50: 160001.31 | P50: 160001.31 | Q50: 189659.84 | R50: 177417.37 | S50: 180478.06 | T50: 176519.48 | U50: 176519.48 | V50: 233889.61 | W50: 253115.71 | X50: 273309.42 | Y50: 293489.44 | Z50: 293489.44 | AA50: 295641.91 | AB50: 300001.81
A51: 1 | C51: 자본총계 | E51: 189624.55 | F51: 189624.55 | G51: 177974.8 | H51: 170091.41 | I51: 171532.94 | J51: 170350.61 | K51: 170350.61 | L51: 172454.03 | M51: 164769.26 | N51: 163707.22 | O51: 168685.12 | P51: 168685.12 | Q51: 211977.83 | R51: 250027.71 | S51: 236969.85 | T51: 259924.76 | U51: 259924.76 | V51: 274149.27 | W51: 308634.44 | X51: 331925.29 | Y51: 341353.79 | Z51: 341353.79 | AA51: 341275.51 | AB51: 355341.37
A52: 1 | C52: 부채와자본총계 | E52: 364699.68 | F52: 364699.68 | G52: 345672.32 | H52: 347005.12 | I52: 345865.98 | J52: 340721.71 | K52: 340721.71 | L52: 347211.89 | M52: 332888.63 | N52: 353332.72 | O52: 319190.61 | P52: 319190.61 | Q52: 356307.15 | R52: 410081.9 | S52: 393711.15 | T52: 430256.71 | U52: 430256.71 | V52: 443421.53 | W52: 446143.32 | X52: 463166.9 | Y52: 462070.25 | Z52: 462070.25 | AA52: 452529.34 | AB52: 432566.56
A53: 1 | C53: 총차입금 | E53: 134091.6 | F53: 134091.6 | G53: 131631.75 | H53: 145358.9 | I53: 142580.89 | J53: 142882.96 | K53: 142882.96 | L53: 142328.01 | M53: 142497.46 | N53: 147100.73 | O53: 122795.8 | P53: 122795.8 | Q53: 118164.49 | R53: 124180 | S53: 124530 | T53: 124530 | U53: 124530 | V53: 115530 | W53: 90030 | X53: 74680 | Y53: 62680 | Z53: 62680 | AA53: 62180 | AB53: 46640
A54: 1 | C54: 순차입금 | E54: 85866.36 | F54: 85866.36 | G54: 85206.14 | H54: 80642.15 | I54: 106871.51 | J54: 112806.19 | K54: 112806.19 | L54: 116539.49 | M54: 119576.56 | N54: 105753.39 | O54: 88021.53 | P54: 88021.53 | Q54: 56639.92 | R54: 49101.33 | S54: 59108.77 | T54: 65119.62 | U54: 65119.62 | V54: -50910.63 | W54: -43242.23 | X54: -114542.38 | Y54: 44492.62 | Z54: 44492.62 | AA54: 44357.04 | AB54: 28996.05
A55: 1 | C55: 이자발생자산 | E55: 51338.62 | F55: 51338.62 | G55: 49185.07 | H55: 67397.39 | I55: 37969.08 | J55: 32727.07 | K55: 32727.07 | L55: 28505.83 | M55: 25712.96 | N55: 44319.14 | O55: 36011.43 | P55: 36011.43 | Q55: 144230.83 | R55: 205965.33 | S55: 178350.3 | T55: 213624.38 | U55: 213624.38 | V55: 231355.49 | W55: 219302.75 | X55: 258897.52 | Y55: 72855.82 | Z55: 72855.82 | AA55: 73459.18 | AB55: 82426.79
A56: 1 | C56: 기타유동금융부채 | G56: 1.19 | H56: 4328.12 | I56: 4332.53 | J56: 3807.26 | K56: 3807.26 | L56: 3807.26 | M56: 1801.31 | N56: 1806.16 | O56: 1097.4 | P56: 1097.4 | Q56: 1101.36 | R56: 0 | S56: 0 | T56: 25.7 | U56: 25.7 | V56: 0.72 | W56: 0
A57: 1 | C57: 단기파생상품부채 | G57: 1.19 | H57: 4328.12 | I57: 4332.53 | J57: 3807.26 | K57: 3807.26 | L57: 3807.26 | M57: 1801.31 | N57: 1806.16 | O57: 1097.4 | P57: 1097.4 | Q57: 1101.36 | R57: 0 | S57: 0 | T57: 25.7 | U57: 25.7 | V57: 0.72 | W57: 0 | Y57: 0 | Z57: 0
A58: 1 | C58: 사채 | H58: 5523.5 | I58: 5684.42 | J58: 5845.38 | K58: 5845.38 | L58: 6002.83 | M58: 6172.48 | N58: 6354.04 | O58: 6540.95 | P58: 6540.95 | Q58: 6733.77 | R58: 0 | S58: 0 | T58: 0 | U58: 0
A59: 1 | C59: 단기금융부채(face) | N59: 130836 | O59: 108680 | P59: 108680 | Q59: 103680 | R59: 109180 | S59: 109530 | T59: 109530 | U59: 109530 | V59: 99530 | W59: 74530 | X59: 58880
A60: 1 | C60: 장기금융부채(face) | S60: 14000 | T60: 14000 | U60: 14000 | V60: 15000 | W60: 1000 | X60: 1300
A61: 1 | C61: 기타유동자산 | Y61: 287.25 | Z61: 287.25 | AA61: 354.34 | AB61: 620.16
A62: 1 | C62: 매각예정비유동자산및처분자산 | Y62: 0 | Z62: 0
A63: 1 | C63: 종속기업및관계기업투자 | Y63: 81858.88 | Z63: 81858.88 | AA63: 84418.68 | AB63: 89193.42
A64: 1 | C64: 사용권자산 | Y64: 29.85 | Z64: 29.85 | AA64: 22.27 | AB64: 65.1
A65: 1 | C65: 기타유동부채 | Y65: 1494.23 | Z65: 1494.23 | AA65: 3148.77 | AB65: 4452.18
A66: 1 | C66: 매출액(수익) | E66: 36139.56 | G66: 39651.68 | H66: 31734.58 | I66: 35560.56 | J66: 41442.86 | K66: 148389.68 | L66: 32693.89 | M66: 32309.27 | N66: 33618.1 | O66: 5329.81 | P66: 103951.07 | Q66: 21768.5 | R66: 25498.5 | S66: 20568.31 | T66: 24948.7 | U66: 92784.01 | V66: 28520.55 | W66: 25162.4 | X66: 28794.87 | Y66: 25480.48 | Z66: 107958.3 | AA66: 25986.51 | AB66: 31829.88
A67: 1 | C67: 매출원가 | E67: 30667.84 | G67: 34679.95 | H67: 27074.08 | I67: 30848.66 | J67: 36065.32 | K67: 128668.01 | L67: 28785.12 | M67: 28007.72 | N67: 28557.18 | O67: 5660.19 | P67: 91010.21 | Q67: 18606.7 | R67: 18885.29 | S67: 16726.86 | T67: 19708.72 | U67: 73927.57 | V67: 22987.82 | W67: 18780.55 | X67: 21228.63 | Y67: 19775.09 | Z67: 82772.09 | AA67: 19800.64 | AB67: 23860.94
A68: 1 | C68: 매출총이익 | E68: 5471.71 | G68: 4971.73 | H68: 4660.5 | I68: 4711.9 | J68: 5377.54 | K68: 19721.67 | L68: 3908.77 | M68: 4301.55 | N68: 5060.92 | O68: -330.37 | P68: 12940.87 | Q68: 3161.8 | R68: 6613.21 | S68: 3841.45 | T68: 5239.98 | U68: 18856.44 | V68: 5532.73 | W68: 6381.85 | X68: 7566.23 | Y68: 5705.39 | Z68: 25186.2 | AA68: 6185.87 | AB68: 7968.94
A69: 1 | C69: 판관비 | E69: 2177.63 | G69: 2329.55 | H69: 2244.58 | I69: 2806.07 | J69: 2456.36 | K69: 9836.56 | L69: 2458.72 | M69: 2534.67 | N69: 3276.13 | O69: -214.57 | P69: 8054.95 | Q69: 2010.67 | R69: 2051.11 | S69: 2652.51 | T69: 1881.05 | U69: 8595.34 | V69: 2873.45 | W69: 1973.04 | X69: 2700.91 | Y69: 2104.51 | Z69: 9651.91 | AA69: 2023.58 | AB69: 2835.27
A70: 1 | C70: 영업이익 | E70: 3294.09 | G70: 2642.18 | H70: 2415.92 | I70: 1905.83 | J70: 2921.18 | K70: 9885.11 | L70: 1450.06 | M70: 1766.87 | N70: 1784.8 | O70: -115.8 | P70: 4885.93 | Q70: 1151.13 | R70: 4562.1 | S70: 1188.94 | T70: 3358.93 | U70: 10261.1 | V70: 2659.27 | W70: 4408.81 | X70: 4865.33 | Y70: 3600.88 | Z70: 15534.29 | AA70: 4162.29 | AB70: 5133.68
A71: 1 | C71: 기타영업외수익 | E71: 3361.37 | G71: 324.46 | H71: 657.87 | I71: 871.13 | J71: -47.51 | K71: 1805.95 | L71: 2394.01 | M71: 154.42 | N71: 937.93 | O71: -345.52 | P71: 3140.84 | Q71: 75431.19 | R71: -154.92 | S71: 8280.52 | T71: 3320.34 | U71: 86877.13 | V71: 309.24 | W71: 19873.58 | X71: 289 | Y71: 207.82 | Z71: 20679.64 | AA71: 322.19 | AB71: 404.18
A72: 1 | C72: 기타영업외비용 | E72: 292.94 | G72: 1932.65 | H72: 10925.32 | I72: 70.95 | J72: 5006.54 | K72: 17935.46 | L72: 32.44 | M72: 8604.31 | N72: 143.46 | O72: -70.97 | P72: 8709.24 | Q72: 8881.42 | R72: 10273.34 | S72: 4632.2 | T72: 8196.36 | U72: 31983.32 | V72: 4847.89 | W72: 4291.47 | X72: 7482.16 | Y72: -16016.69 | Z72: 604.83 | AA72: 5.66 | AB72: 204.86
A73: 1 | C73: 금융수익 | E73: 71.9 | G73: 140.7 | H73: 1290.19 | I73: 166.13 | J73: 781.87 | K73: 2378.89 | L73: 241.2 | M73: 2331.66 | N73: 300.62 | O73: 427.78 | P73: 3301.26 | Q73: 497.95 | R73: 533.57 | S73: 717.55 | T73: 668.45 | U73: 2417.52 | V73: 1286.7 | W73: 1201.32 | X73: 1127.18 | Y73: 1406.57 | Z73: 5021.77 | AA73: 1247.97 | AB73: 1036.39
A74: 1 | C74: 금융비용 | E74: 856.51 | G74: 951.34 | H74: 1781.96 | I74: 1562.76 | J74: 2196.3 | K74: 6492.36 | L74: 1982.95 | M74: 2863.32 | N74: 1938.56 | O74: 1410.49 | P74: 8195.32 | Q74: 1746.13 | R74: 7388.14 | S74: 1244.52 | T74: 1195.47 | U74: 11574.26 | V74: 1038.7 | W74: 753.47 | X74: 686.56 | Y74: 579.57 | Z74: 3058.3 | AA74: 485.72 | AB74: 390.82
A75: 1 | C75: 법인세비용차감전계속사업이익 | E75: 5577.92 | G75: 223.34 | H75: -8343.31 | I75: 1309.38 | J75: -3547.29 | K75: -10357.88 | L75: 2069.88 | M75: -7214.67 | N75: 941.32 | O75: -1373.06 | P75: -5576.53 | Q75: 66452.73 | R75: -12720.73 | S75: 4310.29 | T75: -2044.11 | U75: 55998.18 | V75: -1631.39 | W75: 20438.76 | X75: -1887.22
A76: 1 | C76: 법인세비용 | E76: 6202.19 | G76: 424.04 | H76: 332.86 | I76: 88.04 | J76: -431.78 | K76: 413.16 | L76: 50.92 | M76: 233.45 | N76: -19.48 | O76: -4939.91 | P76: -4675.02 | Q76: 13409.7 | R76: -479.16 | S76: 1251.39 | T76: 1793.07 | U76: 15975 | V76: 698.88 | W76: 1209.75 | X76: 1222.15 | Y76: 2511.15 | Z76: 5641.93 | AA76: 1018.7 | AB76: 1367.08
A77: 1 | C77: 당기순이익 | E77: -624.26 | G77: -200.69 | H77: -8676.16 | I77: 1221.34 | J77: -3115.52 | K77: -10771.03 | L77: 2018.96 | M77: -7448.12 | N77: 960.8 | O77: 6963.49 | P77: 2495.13 | Q77: 53043.02 | R77: -12241.57 | S77: 3058.9 | T77: -3837.18 | U77: 40023.17 | V77: -2330.27 | W77: 19229.01 | X77: -3109.36 | Y77: 11777.42 | Z77: 25566.8 | AB77: 9386.22
A78: 1 | C78: 총포괄손익 | E78: 4863.36 | G78: -411.61 | H78: -7883.39 | I78: 1466.63 | J78: -1182.34 | K78: -8010.71 | L78: 2103.42 | M78: -7684.77 | N78: 1014.62 | O78: 5853.65 | P78: 1286.92 | Q78: 63694.08 | R78: 24476.59 | S78: -10765.51 | T78: 27773.06 | U78: 105178.22 | V78: 22181.8 | W78: 35758.8 | X78: 35229.71 | Y78: 7235.96 | Z78: 100406.27 | AA78: 7327.49 | AB78: 16276.54
A79: 1 | C79: (지배주주지분)당기순이익 | E79: -624.26 | G79: -200.69 | H79: -8676.16 | I79: 1221.34 | J79: -3115.52 | K79: -10771.03 | L79: 2018.96 | M79: -7448.12 | N79: 960.8 | O79: 6963.49 | P79: 2495.13 | Q79: 53043.02 | R79: -12241.57 | S79: 3058.9 | T79: -3837.18 | U79: 40023.17 | V79: -2330.27 | W79: 19229.01 | X79: -3109.36 | Y79: 11777.42 | Z79: 25566.8 | AA79: 6782.16 | AB79: 9386.22
A80: 1 | C80: 금융손익 | E80: -784.61 | G80: -810.64 | H80: -491.77 | I80: -1396.63 | J80: -1414.43 | K80: -4113.47 | L80: -1741.75 | M80: -531.66 | N80: -1637.94 | O80: -982.71 | P80: -4894.06 | Q80: -1248.18 | R80: -6854.57 | S80: -526.97 | T80: -527.02 | U80: -9156.74 | V80: 248 | W80: 447.85 | X80: 440.62 | Y80: 827 | Z80: 1963.47 | AA80: 762.25 | AB80: 645.57
A81: 1 | C81: 기타영업외손익 | E81: 3068.43 | G81: -1608.19 | H81: -10267.45 | I81: 800.18 | J81: -5054.05 | K81: -16129.51 | L81: 2361.57 | M81: -8449.89 | N81: 794.47 | O81: -274.55 | P81: -5568.4 | Q81: 66549.77 | R81: -10428.26 | S81: 3648.32 | T81: -4876.02 | U81: 54893.81 | V81: -4538.65 | W81: 15582.11 | X81: -7193.16 | Y81: 16224.51 | Z81: 20074.81 | AA81: 316.53 | AB81: 199.32
A82: 1 | C82: 계속사업이익 | E82: -624.26 | G82: -200.69 | H82: -8676.16 | I82: 1221.34 | J82: -3115.52 | K82: -10771.03 | L82: 2018.96 | M82: -7448.12 | N82: 960.8 | O82: 3566.85 | P82: -901.51 | Q82: 53043.02 | R82: -12241.57 | S82: 3058.9 | T82: -3837.18 | U82: 40023.17 | V82: -2330.27 | W82: 19229.01 | X82: -3109.36 | Y82: 11777.42 | Z82: 25566.8 | AA82: 6782.16 | AB82: 9386.22
A83: 1 | C83: 이자수익 | G83: 134.6 | H83: 201.39 | I83: 165.96 | J83: 192.62 | K83: 694.57 | L83: 241.2 | M83: 322.8 | N83: 300.62 | O83: -289.28 | P83: 575.34 | Q83: 497.95 | R83: 527.24 | S83: 717.46 | T83: 668.36 | U83: 2411.01 | V83: 1282.54 | W83: 1153.81 | X83: 1128.54 | Y83: 1403.58 | Z83: 4968.47 | AB83: 1036.17
A84: 1 | C84: 이자비용 | G84: 950.15 | H84: 1247.14 | I84: 1542.01 | J84: 1796.85 | K84: 5536.15 | L84: 1973.49 | M84: 1665.99 | N84: 2244.71 | O84: 1176.51 | P84: 7060.7 | Q84: 1733.2 | R84: 1302.5 | S84: 1244.52 | T84: 1169.77 | U84: 5449.99 | V84: 1033.37 | W84: 754.19 | X84: 686.56 | Y84: 579.55 | Z84: 3053.67 | AB84: 390.82
A85: 1 | C85: 파생상품손실 | G85: 1.19 | H85: 534.82 | I85: 20.75 | J85: 399.44 | K85: 956.2 | L85: 9.47 | M85: 882.42 | N85: 8.76 | O85: 233.97 | P85: 1134.62 | Q85: 12.93 | R85: 6085.64 | S85: 0 | T85: 25.7 | U85: 6124.27 | V85: 5.33 | W85: -0.72 | X85: 0 | Y85: 0.02 | Z85: 4.63 | AB85: 0
A86: 1 | C86: 이자손익 | G86: -815.55 | H86: -1045.75 | I86: -1376.05 | J86: -1604.23 | K86: -4841.58 | L86: -1732.29 | M86: -1343.19 | N86: -1944.09 | O86: -1465.79 | P86: -6485.36 | Q86: -1235.25 | R86: -775.26 | S86: -527.06 | T86: -501.41 | U86: -3038.98 | V86: 249.17 | W86: 399.62 | X86: 441.98 | Y86: 824.03 | Z86: 1914.8 | AB86: 645.35
A87: 1 | C87: 파생상품이익 | I87: 0.18 | J87: 527.75 | M87: 2005.95 | N87: 0 | O87: 717.06 | R87: 5.88 | S87: 0 | T87: 0 | V87: 4.16 | W87: 47.31 | X87: -1.47 | Y87: 2.87 | Z87: 52.87 | AB87: 0
A88: 1 | C88: 중단사업이익 | O88: 3396.63 | Q88: 0 | R88: 0 | S88: 0 | T88: 0 | U88: 0
A89: 1 | C89: (비지배주주지분)당기순이익 | R89: 0
A90: 1 | C90: 종속기업,공동지배기업및관계기업관련손익 | AA90: 2559.8 | AB90: 4774.74
A91: 1 | C91: 배당금수익 | AB91: 0.22
A92: 1 | C92: 영업활동으로인한현금흐름 | E92: 2255.31 | G92: -52133.14 | H92: 47219.46 | I92: 2431.45 | J92: -1803.73 | K92: -4285.96 | L92: -3117.39 | M92: -1068.55 | N92: 10808.69 | O92: 2068.87 | P92: 8691.62 | Q92: 10746.55 | R92: 2700.93 | S92: 5901.77 | T92: -690.66 | U92: 18658.59 | V92: -1921.71 | W92: 591.96 | X92: 3954.42 | Y92: 2518.15 | Z92: 5142.82 | AA92: -9716.47 | AB92: -10867.47
A93: 1 | C93: 감가상각비 | E93: 1731.51 | G93: 1673.07 | H93: 1663.08 | I93: 1617.21 | J93: 1653.98 | K93: 6607.34 | L93: 1522.9 | M93: 1686.86
A94: 1 | C94: 무형자산상각비 | E94: 9.68 | G94: 10.03 | H94: 10.03 | I94: 4.93 | J94: 2.18 | K94: 27.17
A95: 1 | C95: 배당금수취(CF) | E95: 0 | G95: -50701.94 | H95: 50708.39 | I95: 0 | J95: 0 | K95: 6.45 | N95: 0 | O95: 0 | S95: 0.09 | T95: 0.09 | X95: 0.11 | Y95: 0.11
A96: 1 | C96: 법인세납부(CF) | E96: 26.51 | G96: -5765.74 | H96: -6935.63 | I96: -465.49 | J96: -28.76 | K96: -13195.62 | L96: -503.93 | M96: -532.01 | N96: -238.34 | O96: -507.45 | P96: -1781.73 | Q96: 194.09 | R96: 227.11 | S96: -130.28 | T96: -87.73 | U96: 203.19 | V96: -4969.31 | W96: -5781.45 | X96: -2670.21 | Y96: -2451.87 | Z96: -15872.84 | AA96: -15750.1 | AB96: -18964.15
A97: 1 | C97: 투자활동으로인한현금흐름 | E97: 8275.57 | G97: 51253.13 | H97: -45400.28 | I97: -25627.81 | J97: -5568.53 | K97: -25343.49 | L97: 1953.38 | M97: -970.95 | N97: 3076.65 | O97: 16493.94 | P97: 20553.02 | Q97: 10494.36 | R97: -28735.1 | S97: -1253.2 | T97: 4722.66 | U97: -14771.28 | V97: 28602.1 | W97: 24914.97 | X97: 20132.92 | Y97: 6679.73 | Z97: 80329.72 | AA97: 12579.28 | AB97: 33171.11
A98: 1 | C98: 유형자산의감소 | E98: 0.82 | G98: 26.55 | H98: 0 | I98: 0 | J98: 3.63 | K98: 30.18 | L98: 4.55 | M98: 0.81 | N98: 215.26 | O98: 0 | P98: 220.62 | Q98: 89 | R98: 0 | S98: 1 | T98: 0 | U98: 90 | X98: 25 | Y98: 0
A99: 1 | C99: 유형자산의증가 | E99: 1053.5 | G99: 391.32 | H99: 349.23 | I99: 241.36 | J99: 973.54 | K99: 1955.45 | L99: 604.6 | M99: 493.25 | N99: 770.87 | O99: 664.28 | P99: 2533 | Q99: 434.15 | R99: 906.65 | S99: 961.54 | T99: 548.45 | U99: 2850.79 | V99: 1900.29 | W99: 1098.41 | X99: 904.42 | Y99: 2627.7 | Z99: 6530.82 | AA99: 329.53 | AB99: 286.8
A100: 1 | C100: CAPEX | E100: 1053.5 | G100: 398.32 | H100: 349.23 | I100: 242.81 | J100: 974.1 | K100: 1964.46 | L100: 634.6 | M100: 493.25 | N100: 770.87 | O100: 664.28 | P100: 2563 | Q100: 434.15 | R100: 906.65 | S100: 961.54 | T100: 548.45 | U100: 2850.79 | V100: 1900.29 | W100: 1098.41 | X100: 904.42 | Y100: 2627.7 | Z100: 6530.82 | AA100: 329.53 | AB100: 694.8
...

Sheet BS별도
B1: (백만원) | C1: 이름: BS별도H | E1: 4Q21 | F1: 2021 | G1: 1Q22 | H1: 2Q22 | I1: 3Q22 | J1: 4Q22 | K1: 2022 | L1: 1Q23 | M1: 2Q23 | N1: 3Q23 | O1: 4Q23 | P1: 2023 | Q1: 1Q24 | R1: 2Q24 | S1: 3Q24 | T1: 4Q24 | U1: 2024 | V1: 1Q25 | W1: 2Q25 | X1: 3Q25 | Y1: 4Q25 | Z1: 2025 | AA1: 1Q26 | AB1: 2Q26 | AC1: 3Q26 | AD1: 4Q26 | AE1: 2026 | AF1: 1Q27 | AG1: 2Q27 | AH1: 3Q27 | AI1: 4Q27 | AJ1: 2027 | AK1: 1Q28 | AL1: 2Q28 | AM1: 3Q28 | AN1: 4Q28 | AO1: 2028
B2: 별도 | D2: fin json(kship_fin.py)
B3: 인화정공(별) | C3: UPDATE: 26-10-26 | E3: 1 | F3: 2 | G3: 3 | H3: 4 | I3: 5 | J3: 6 | K3: 7 | L3: 8 | M3: 9 | N3: 10 | O3: 11 | P3: 12 | Q3: 13 | R3: 14 | S3: 15 | T3: 16 | U3: 17 | V3: 18 | W3: 19 | X3: 20 | Y3: 21 | Z3: 22 | AA3: 23 | AB3: 24 | AC3: 25 | AD3: 26 | AE3: 27 | AF3: 28 | AG3: 29 | AH3: 30 | AI3: 31 | AJ3: 32 | AK3: 33 | AL3: 34 | AM3: 35 | AN3: 36 | AO3: 37
B4: Account Code | C4: AccountNAME | E4: 2021.12 | F4: 2021.12A | G4: 2022.03 | H4: 2022.06 | I4: 2022.09 | J4: 2022.12 | K4: 2022.12A | L4: 2023.03 | M4: 2023.06 | N4: 2023.09 | O4: 2023.12 | P4: 2023.12A | Q4: 2024.03 | R4: 2024.06 | S4: 2024.09 | T4: 2024.12 | U4: 2024.12A | V4: 2025.03 | W4: 2025.06 | X4: 2025.09 | Y4: 2025.12 | Z4: 2025.12A | AA4: 2026.03 | AB4: 2026.06 | AC4: 2026.09 | AD4: 2026.12 | AE4: 2026.12A | AF4: 2027.03 | AG4: 2027.06 | AH4: 2027.09 | AI4: 2027.12 | AJ4: 2027.12A | AK4: 2028.03 | AL4: 2028.06 | AM4: 2028.09 | AN4: 2028.12 | AO4: 2028.12A
A5: 1 | C5: 유동자산 | E5: 36188.84 | F5: 36188.84 | G5: 34043.97 | H5: 54813.13 | I5: 32299.22 | J5: 33484.86 | K5: 33484.86 | L5: 33451.61 | M5: 33572.3 | N5: 49575.79 | O5: 59137.79 | P5: 59137.79 | Q5: 76010.07 | R5: 91316.16 | S5: 91418.68 | T5: 90467.32 | U5: 90467.32 | V5: 196365.58 | W5: 163047.92 | X5: 207100.81 | Y5: 210447.27 | Z5: 210447.27 | AA5: 196904.1 | AB5: 163070.67
A6: 1 | C6: 현금및현금성자산 | E6: 14382.03 | F6: 14382.03 | G6: 11519.71 | H6: 30832.25 | I6: 6837.81 | J6: 4997.94 | K6: 4997.94 | L6: 3282.03 | M6: 3026.22 | N6: 17227.14 | O6: 25823 | P6: 25823 | Q6: 20315.68 | R6: 5007.86 | S6: 7788.4 | T6: 7078.57 | U6: 7078.57 | V6: 23544.42 | W6: 17190.85 | X6: 17533.8 | Y6: 13688.49 | Z6: 13688.49 | AA6: 12118.5 | AB6: 11995.39
A7: 1 | C7: 단기금융상품 | E7: 307.67 | F7: 307.67 | G7: 463.67 | H7: 256 | I7: 256 | J7: 156 | K7: 156 | L7: 164.67 | M7: 8.67 | N7: 935.42 | O7: 2094.41 | P7: 2094.41 | Q7: 32120.87 | R7: 22612.2 | S7: 49838.68 | T7: 45064.83 | U7: 45064.83 | V7: 134301.32 | W7: 108982.12 | X7: 165621.1
A8: 1 | C8: 단기금융자산 | E8: 1421.01 | F8: 1421.01 | G8: 1417.71 | H8: 2942.09 | I8: 2939.09 | J8: 2326.54 | K8: 2326.54 | L8: 4915.21 | M8: 7531.1 | N8: 11407.85 | O8: 9630.14 | P8: 9630.14 | Q8: 33156.6 | R8: 61445.92 | S8: 49838.68 | T8: 45064.83 | U8: 45064.83 | V8: 134301.32 | W8: 108982.12 | X8: 165621.1
A9: 1 | C9: 매출채권및기타채권 | E9: 23548.75 | F9: 23548.75 | G9: 25475.94 | H9: 22250.58 | I9: 24411.69 | J9: 29797.38 | K9: 29797.38 | L9: 33393.12 | M9: 31310.15 | N9: 32002.4 | O9: 35753.16 | P9: 35753.16 | Q9: 26943.04 | R9: 69621.13 | S9: 32759.25 | T9: 39334.28 | U9: 39334.28 | V9: 45027.59 | W9: 39417.83 | X9: 26733.08 | Y9: 12450.74 | Z9: 12450.74 | AA9: 15435.74 | AB9: 14287.92
A10: 1 | C10: 단기대여금 | E10: 1113.34 | F10: 1113.34 | G10: 954.04 | H10: 951.04 | I10: 948.04 | J10: 853.72 | K10: 853.72 | L10: 3433.72 | M10: 7083.72 | N10: 10033.72 | O10: 7333.72 | P10: 7333.72 | Q10: 833.72 | R10: 38833.72
A11: 1 | C11: 당기법인세자산(선급법인세) | E11: 0 | F11: 0 | I11: 170.05 | L11: 7.37 | O11: 283.05 | P11: 283.05 | Q11: 0 | R11: 0 | S11: 0 | T11: 0 | U11: 0 | V11: 0
A12: 1 | C12: 재고자산 | E12: 9452.32 | F12: 9452.32 | G12: 9139.66 | H12: 10657.67 | I12: 10913.64 | J12: 10962.94 | K12: 10962.94 | L12: 9491.65 | M12: 10152.45 | N12: 10180.94 | O12: 9428.34 | P12: 9428.34 | Q12: 9614.56 | R12: 9563.23 | S12: 11402.88 | T12: 12432.04 | U12: 12432.04 | V12: 9717.24 | W12: 10477.24 | X12: 9493.98 | Y12: 11355.36 | Z12: 11355.36 | AA12: 11428.02 | AB12: 11589
A13: 1 | C13: 비유동자산 | E13: 242563.59 | F13: 242563.59 | G13: 241815.96 | H13: 240990.23 | I13: 268999.97 | J13: 269022.1 | K13: 269022.1 | L13: 268297.36 | M13: 267732.27 | N13: 269175.26 | O13: 265478.3 | P13: 265478.3 | Q13: 271141.38 | R13: 319600.89 | S13: 301607.11 | T13: 342400.16 | U13: 342400.16 | V13: 254075.32 | W13: 275664.84 | X13: 258717.7 | Y13: 246832.24 | Z13: 246832.24 | AA13: 247641.11 | AB13: 256314.63
A14: 1 | C14: 장기금융자산 | E14: 450.02 | F14: 450.02 | G14: 457.08 | H14: 464.15 | I14: 471.21 | J14: 793.28 | K14: 793.28 | L14: 780.43 | M14: 802.5 | N14: 1124.56 | O14: 546.63 | P14: 546.63 | Q14: 163301.11 | R14: 259602.28 | S14: 223664.12 | T14: 153422.9 | U14: 153422.9 | V14: 64102.96 | W14: 85622.53 | X14: 68949.58 | Y14: 54150.44 | Z14: 54150.44 | AA14: 55107.54 | AB14: 64246.27
A15: 1 | C15: 투자자산 | E15: 158969.93 | F15: 158969.93 | G15: 158976.99 | H15: 158984.06 | I15: 32232.05 | J15: 32554.12 | K15: 32554.12 | L15: 32541.27 | M15: 32563.34 | N15: 32885.4 | O15: 17591.48 | P15: 17591.48 | Q15: 180290.32 | R15: 276591.49 | S15: 240653.33 | T15: 170412.11 | U15: 170412.11 | V15: 81092.17 | W15: 102611.74 | X15: 85938.79 | Y15: 165062.82 | Z15: 165062.82 | AA15: 166019.92 | AB15: 175158.65
A16: 1 | C16: 장기매출채권및기타채권 | E16: 42.79 | F16: 42.79 | G16: 51.04 | H16: 0.8 | I16: 0.8 | J16: 11.11 | K16: 11.11 | L16: 11.27 | M16: 11.33 | N16: 11.49 | O16: 21.09 | P16: 21.09 | Q16: 21.32 | R16: 21.55 | Y16: 10.59 | Z16: 10.59 | AA16: 10.65 | AB16: 10.71
A17: 1 | C17: 유형자산 | E17: 65888.7 | F17: 65888.7 | G17: 65126.78 | H17: 64345.23 | I17: 63426.83 | J17: 62640.07 | K17: 62640.07 | L17: 62023.64 | M17: 61380.51 | N17: 60948.53 | O17: 60612.98 | P17: 60612.98 | Q17: 60327.09 | R17: 60467.22 | S17: 60619.86 | T17: 60359.02 | U17: 60359.02 | V17: 61527.22 | W17: 61696 | X17: 61720.64 | Y17: 63109.97 | Z17: 63109.97 | AA17: 62652.57 | AB17: 62113.07
A18: 1 | C18: 투자부동산 | E18: 17549.03 | F18: 17549.03 | G18: 17549.03 | H18: 17549.03 | I18: 17549.03 | J18: 17549.03 | K18: 17549.03 | L18: 17611.95 | M18: 17549.03 | N18: 19629.99 | O18: 19629.99 | P18: 19629.99 | Q18: 19629.99 | R18: 19629.99 | S18: 19645.99 | T18: 19645.99 | U18: 19645.99 | V18: 19645.99 | W18: 19645.99 | X18: 19645.99 | Y18: 18507.85 | Z18: 18507.85 | AA18: 18413.52 | AB18: 18134.29
A19: 1 | C19: 무형자산 | E19: 115.18 | F19: 115.18 | G19: 115.18 | H19: 115.18 | I19: 115.18 | J19: 115.18 | K19: 115.18 | L19: 115.18 | M19: 115.18 | N19: 115.18 | O19: 115.18 | P19: 115.18 | Q19: 115.18 | R19: 115.18 | S19: 115.18 | T19: 115.18 | U19: 115.18 | V19: 115.18 | W19: 115.18 | X19: 115.18 | Y19: 115.18 | Z19: 115.18 | AA19: 523.18 | AB19: 523.18
A20: 1 | C20: 종속기업및관계기업투자 | E20: 158519.91 | F20: 158519.91 | G20: 158519.91 | H20: 158519.91 | I20: 31760.84 | J20: 31760.84 | K20: 31760.84 | L20: 31760.84 | M20: 31760.84 | N20: 31760.84 | O20: 17044.85 | P20: 17044.85 | Q20: 16989.21 | R20: 16989.21 | S20: 16989.21 | T20: 16989.21 | U20: 16989.21 | V20: 16989.21 | W20: 16989.21 | X20: 16989.21 | Y20: 110912.38 | Z20: 110912.38 | AA20: 110912.38 | AB20: 110912.38
A21: 1 | C21: 이연법인세자산 | E21: 0 | F21: 0 | J21: 0 | K21: 0
A22: 1 | C22: 자산총계 | E22: 278752.43 | F22: 278752.43 | G22: 275859.93 | H22: 295803.36 | I22: 301299.2 | J22: 302506.96 | K22: 302506.96 | L22: 301748.97 | M22: 301304.57 | N22: 318751.05 | O22: 324616.08 | P22: 324616.08 | Q22: 347151.45 | R22: 410917.05 | S22: 393025.8 | T22: 432867.47 | U22: 432867.47 | V22: 450440.91 | W22: 438712.76 | X22: 465818.51 | Y22: 457279.51 | Z22: 457279.51 | AA22: 444545.21 | AB22: 419385.31
A23: 1 | C23: 유동부채 | E23: 99937.8 | F23: 99937.8 | G23: 94272.52 | H23: 102922.79 | I23: 102103.62 | J23: 103446.12 | K23: 103446.12 | L23: 102659.76 | M23: 100774.77 | N23: 119756.78 | O23: 120145.99 | P23: 120145.99 | Q23: 110795.22 | R23: 107665.34 | S23: 110270.74 | T23: 110910.57 | U23: 110910.57 | V23: 122707.2 | W23: 100919.11 | X23: 96826.82 | Y23: 86337.68 | Z23: 86337.68 | AA23: 75604.14 | AB23: 39830.59
A24: 1 | C24: 매입채무및기타채무 | E24: 87297.24 | F24: 87297.24 | G24: 87194.34 | H24: 98194.9 | I24: 97789.88 | J24: 98744.72 | K24: 98744.72 | L24: 98345.54 | M24: 98606.07 | N24: 117835.25 | O24: 119048.59 | P24: 119048.59 | Q24: 99973.39 | R24: 98743.38 | S24: 99686.3 | T24: 100342.3 | U24: 100342.3 | V24: 95847.43 | W24: 78641.99 | X24: 62491.52 | Y24: 7041.08 | Z24: 7041.08 | AA24: 20004.76 | AB24: 6167.87
A25: 1 | C25: 단기차입금 | E25: 81400 | F25: 81400 | G25: 81000 | H25: 86000 | I25: 86000 | J25: 86000 | K25: 86000 | L25: 86000 | M25: 86000 | N25: 91800 | O25: 91800 | P25: 91800 | Q25: 86800 | R25: 92300 | S25: 92650 | T25: 92650 | U25: 92650 | V25: 82650 | W25: 57650 | X25: 42000 | Y25: 30000 | Z25: 30000 | AA25: 30000 | AB25: 30000
A26: 1 | C26: 유동성장기부채 | E26: 67.8 | F26: 67.8 | G26: 67.8 | H26: 5591.3 | I26: 5752.22 | J26: 5913.18 | K26: 5913.18 | L26: 6070.63 | M26: 6240.28 | N26: 6404.89 | O26: 6574.85 | P26: 6574.85 | Q26: 6750.72 | R26: 0 | S26: 0 | T26: 0 | U26: 0 | W26: 14000 | X26: 14000 | Y26: 14000 | Z26: 14000 | AB26: 0
A27: 1 | C27: 당기법인세부채(미지급법인세) | E27: 12640.56 | F27: 12640.56 | G27: 7078.18 | H27: 414.15 | J27: 894.13 | K27: 894.13 | L27: 506.96 | M27: 367.4 | N27: 120.23 | O27: 0 | P27: 0 | Q27: 9724.43 | R27: 8921.96 | S27: 10584.43 | T27: 10568.27 | U27: 10568.27 | V27: 26859.77 | W27: 22277.12 | X27: 34335.3 | Y27: 34323.56 | Z27: 34323.56 | AA27: 19594.69 | AB27: 2260.97
A28: 1 | C28: 비유동부채 | E28: 2443.4 | F28: 2443.4 | G28: 2494.31 | H28: 7819.94 | I28: 8054.85 | J28: 7515.21 | K28: 7515.21 | L28: 7646.58 | M28: 7787.73 | N28: 7958.88 | O28: 8531.07 | P28: 8531.07 | Q28: 11676.95 | R28: 30719.45 | S28: 26015.72 | T28: 37355.79 | U28: 37355.79 | V28: 24252.28 | W28: 15029.9 | X28: 13181.25 | Y28: 11001.07 | Z28: 11001.07 | AA28: 11311.78 | AB28: 12948.03
A29: 1 | C29: 장기매입채무및기타채무 | E29: 341.64 | F29: 341.64 | G29: 315.67 | H29: 5781.22 | I29: 5911.67 | J29: 6087.36 | K29: 6087.36 | L29: 6211.96 | M29: 6346.36 | N29: 6510.73 | O29: 6728.42 | P29: 6728.42 | Q29: 6899.47 | R29: 14141.3 | S29: 14085.29 | T29: 14070.03 | U29: 14070.03 | V29: 14042.38 | W29: 30.9 | X29: 19.51 | Y29: 7.02 | Z29: 7.02
A30: 1 | C30: 장기차입금 | E30: 101.7 | F30: 101.7 | G30: 84.75 | H30: 67.8 | I30: 50.85 | J30: 33.9 | K30: 33.9 | L30: 16.95 | O30: 0 | P30: 0 | Q30: 0 | R30: 14000 | S30: 14000 | T30: 14000 | U30: 14000 | V30: 14000
A31: 1 | C31: 확정급여부채 | E31: 342.19 | F31: 342.19 | G31: 456.38 | H31: 254.14 | I31: 351.84 | J31: 0 | K31: 0 | O31: 50.04 | P31: 50.04 | Q31: 162.47 | R31: 0 | S31: 0 | T31: 62.38 | U31: 62.38 | V31: 188.32 | W31: 12.36 | X31: 159.84 | Y31: 139.5 | Z31: 139.5 | AA31: 288.27
A32: 1 | C32: 이연법인세부채 | E32: 1879.54 | F32: 1879.54 | G32: 1837.73 | H32: 1879.54 | I32: 1879.54 | J32: 1509.28 | K32: 1509.28 | L32: 1509.28 | M32: 1509.28 | N32: 1509.28 | O32: 1806.99 | P32: 1806.99 | Q32: 4662.62 | R32: 16618.99 | S32: 11930.43 | T32: 23223.39 | U32: 23223.39 | V32: 10021.59 | W32: 14986.64 | X32: 13001.91 | Y32: 10846.72 | Z32: 10846.72 | AA32: 11020.37 | AB32: 12948.03
A33: 1 | C33: 부채총계 | E33: 102381.19 | F33: 102381.19 | G33: 96766.83 | H33: 110742.73 | I33: 110158.47 | J33: 110961.33 | K33: 110961.33 | L33: 110306.34 | M33: 108562.5 | N33: 127715.66 | O33: 128677.05 | P33: 128677.05 | Q33: 122472.18 | R33: 138384.79 | S33: 136286.45 | T33: 148266.36 | U33: 148266.36 | V33: 146959.48 | W33: 115949.01 | X33: 110008.07 | Y33: 97338.75 | Z33: 97338.75 | AA33: 86915.92 | AB33: 52778.62
A34: 1 | C34: 자본금 | E34: 4665.85 | F34: 4665.85 | G34: 4665.85 | H34: 4665.85 | I34: 4665.85 | J34: 4665.85 | K34: 4665.85 | L34: 4665.85 | M34: 4665.85 | N34: 4665.85 | O34: 4665.85 | P34: 4665.85 | Q34: 4665.85 | R34: 4940.08 | S34: 4940.08 | T34: 4940.08 | U34: 4940.08 | V34: 4940.08 | W34: 4940.08 | X34: 4940.08 | Y34: 4940.08 | Z34: 4940.08 | AA34: 4940.08 | AB34: 4940.08
A35: 1 | C35: 보통주자본금 | E35: 4665.85 | F35: 4665.85 | G35: 4665.85 | H35: 4665.85 | I35: 4665.85 | J35: 4665.85 | K35: 4665.85 | L35: 4665.85 | M35: 4665.85 | N35: 4665.85 | O35: 4665.85 | P35: 4665.85 | Q35: 4665.85 | R35: 4940.08 | S35: 4940.08 | T35: 4940.08 | U35: 4940.08 | V35: 4940.08 | W35: 4940.08 | X35: 4940.08
A36: 1 | C36: 자본잉여금 | E36: 94556.36 | F36: 94556.36 | G36: 94556.36 | H36: 94556.36 | I36: 94556.36 | J36: 94556.36 | K36: 94556.36 | L36: 94556.36 | M36: 94556.36 | N36: 94556.36 | O36: 13998.36 | P36: 13998.36 | Q36: 13998.36 | R36: 40596.48 | S36: 40596.48 | T36: 40596.48 | U36: 40596.48 | V36: 27976.48 | W36: 27976.48 | X36: 27976.48 | Y36: 13839.98 | Z36: 13839.98 | AA36: 11050.66 | AB36: 13839.98
A37: 1 | C37: 기타자본 | E37: -4378.76 | F37: -4378.76 | G37: -296.52 | H37: -296.52 | I37: -296.52 | J37: -296.52 | K37: -296.52 | L37: -296.52 | M37: -296.52 | N37: -4449.82 | O37: -6249.78 | P37: -6249.78 | Q37: 21331.82 | R37: 94770.04 | S37: 62531.91 | T37: 116358.28 | U37: 116358.28 | V37: 42684.96 | W37: 73200.86 | X37: 84439.6 | Y37: 32296.42 | Z37: 32296.42 | AA37: 32853.57 | AB37: 39771.58
A38: 1 | C38: 이익잉여금 | E38: 126616.58 | F38: 126616.58 | G38: 127297.33 | H38: 133264.86 | I38: 139344.95 | J38: 139749.86 | K38: 139749.86 | L38: 139646.85 | M38: 140946.29 | N38: 141316.27 | O38: 187398.89 | P38: 187398.89 | Q38: 202348.33 | R38: 199908.92 | S38: 200235.06 | T38: 201183.65 | U38: 201183.65 | V38: 263210.62 | W38: 267234.99 | X38: 294662.32 | Y38: 308864.28 | Z38: 308864.28 | AA38: 308784.97 | AB38: 308055.04
A39: 1 | C39: 자본총계 | E39: 176371.23 | F39: 176371.23 | G39: 179093.11 | H39: 185060.63 | I39: 191140.72 | J39: 191545.63 | K39: 191545.63 | L39: 191442.63 | M39: 192742.06 | N39: 191035.39 | O39: 195939.03 | P39: 195939.03 | Q39: 224679.27 | R39: 272532.26 | S39: 256739.34 | T39: 284601.11 | U39: 284601.11 | V39: 303481.43 | W39: 322763.75 | X39: 355810.44 | Y39: 359940.77 | Z39: 359940.77 | AA39: 357629.29 | AB39: 366606.69
A40: 1 | C40: 부채와자본총계 | E40: 278752.43 | F40: 278752.43 | G40: 275859.93 | H40: 295803.36 | I40: 301299.2 | J40: 302506.96 | K40: 302506.96 | L40: 301748.97 | M40: 301304.57 | N40: 318751.05 | O40: 324616.08 | P40: 324616.08 | Q40: 347151.45 | R40: 410917.05 | S40: 393025.8 | T40: 432867.47 | U40: 432867.47 | V40: 450440.91 | W40: 438712.76 | X40: 465818.51 | Y40: 457279.51 | Z40: 457279.51 | AA40: 444545.21 | AB40: 419385.31
A41: 1 | C41: 지배주주지분 | E41: 176371.23 | F41: 176371.23 | G41: 179093.11 | H41: 185060.63 | I41: 191140.72 | J41: 191545.63 | K41: 191545.63 | L41: 191442.63 | M41: 192742.06 | N41: 191035.39 | O41: 195939.03 | P41: 195939.03 | Q41: 224679.27 | R41: 272532.26 | S41: 256739.34 | T41: 284601.11 | U41: 284601.11 | V41: 303481.43 | W41: 322763.75 | X41: 355810.44 | Y41: 359940.77 | Z41: 359940.77 | AA41: 357629.29 | AB41: 366606.69
A42: 1 | C42: 총차입금 | E42: 81569.5 | F42: 81569.5 | G42: 81152.55 | H42: 97182.6 | I42: 97487.49 | J42: 97792.46 | K42: 97792.46 | L42: 98090.41 | M42: 98412.76 | N42: 104558.93 | O42: 104915.8 | P42: 104915.8 | Q42: 100284.49 | R42: 106300 | S42: 106650 | T42: 106650 | U42: 106650 | V42: 96650 | W42: 71650 | X42: 56000 | Y42: 44000 | Z42: 44000 | AA42: 30000 | AB42: 30000
A43: 1 | C43: 순차입금 | E43: 65766.46 | F43: 65766.46 | G43: 68215.13 | H43: 63408.26 | I43: 87710.59 | J43: 90467.98 | K43: 90467.98 | L43: 89893.17 | M43: 87855.44 | N43: 75923.94 | O43: 69462.66 | P43: 69462.66 | Q43: 46812.21 | R43: 39846.22 | S43: 49022.92 | T43: 54506.6 | U43: 54506.6 | V43: -61195.74 | W43: -54522.97 | X43: -127154.9 | Y43: 30311.51 | Z43: 30311.51 | AA43: 17881.5 | AB43: 18004.61
A44: 1 | C44: 이자발생자산 | E44: 16253.06 | F44: 16253.06 | G44: 13394.5 | H44: 34238.49 | I44: 10248.11 | J44: 8117.76 | K44: 8117.76 | L44: 8977.67 | M44: 11359.82 | N44: 29759.55 | O44: 35999.77 | P44: 35999.77 | Q44: 216773.39 | R44: 326056.06 | S44: 281291.2 | T44: 205566.3 | U44: 205566.3 | V44: 221948.7 | W44: 211795.5 | X44: 252104.48 | Y44: 67838.93 | Z44: 67838.93 | AA44: 67226.04 | AB44: 76241.66
A45: 1 | C45: 기타유동금융자산 | H45: 1735.05 | I45: 1735.05 | J45: 1316.82 | K45: 1316.82 | L45: 1316.82 | M45: 438.71 | N45: 438.71 | O45: 202.01 | P45: 202.01 | Q45: 202.01 | R45: 0 | S45: 0 | T45: 0 | U45: 0 | Y45: 169566.12 | Z45: 169566.12 | AA45: 156216.95 | AB45: 123000
A46: 1 | C46: 유동파생상품자산 | H46: 1735.05 | I46: 1735.05 | J46: 1316.82 | K46: 1316.82 | L46: 1316.82 | M46: 438.71 | N46: 438.71 | O46: 202.01 | P46: 202.01 | Q46: 202.01 | R46: 0 | S46: 0 | T46: 0 | U46: 0
A47: 1 | C47: 기타유동금융부채 | H47: 4313.74 | I47: 4313.74 | J47: 3807.26 | K47: 3807.26 | L47: 3807.26 | M47: 1801.31 | N47: 1801.31 | O47: 1097.4 | P47: 1097.4 | Q47: 1097.4 | R47: 0 | S47: 0 | T47: 0 | U47: 0
A48: 1 | C48: 단기금융부채 | H48: 8627.48 | I48: 8627.48 | J48: 7629.35 | K48: 7629.35 | L48: 7628.38 | M48: 3617.88 | N48: 3618.09 | O48: 2224.36 | P48: 2224.36 | Q48: 2224.7 | R48: 32.77 | S48: 33.11 | T48: 33.46 | U48: 33.46 | V48: 18.02 | W48: 18.24 | X48: 18.35
A49: 1 | C49: 단기파생상품부채 | H49: 4313.74 | I49: 4313.74 | J49: 3807.26 | K49: 3807.26 | L49: 3807.26 | M49: 1801.31 | N49: 1801.31 | O49: 1097.4 | P49: 1097.4 | Q49: 1097.4 | R49: 0 | S49: 0 | T49: 0 | U49: 0
A50: 1 | C50: 사채 | H50: 5523.5 | I50: 5684.42 | J50: 5845.38 | K50: 5845.38 | L50: 6002.83 | M50: 6172.48 | N50: 6354.04 | O50: 6540.95 | P50: 6540.95 | Q50: 6733.77 | R50: 0 | S50: 0 | T50: 0 | U50: 0
A51: 1 | C51: 기타비유동자산 | J51: 62.92 | K51: 62.92 | M51: 101373.27 | N51: 101369.33 | O51: 109.46 | P51: 109.46 | Q51: 100.97 | R51: 353.5 | S51: 243.12 | T51: 106.63 | U51: 106.63 | V51: 39.49 | W51: 34.93 | X51: 30.37 | Y51: 25.82 | Z51: 25.82 | AA51: 21.26 | AB51: 374.73
A52: 1 | C52: 유동리스부채 | J52: 14.83 | K52: 14.83 | L52: 13.86 | M52: 15.26 | N52: 15.47 | O52: 29.56 | P52: 29.56 | Q52: 29.9 | R52: 32.77 | S52: 33.11 | T52: 33.46 | U52: 33.46 | V52: 18.02 | W52: 18.24 | X52: 18.35
A53: 1 | C53: 리스부채 | J53: 60.04 | K53: 60.04 | L53: 56.7 | M53: 53.32 | N53: 49.88 | O53: 108.27 | P53: 108.27 | Q53: 100.38 | R53: 92.39 | S53: 84.32 | T53: 76.17 | U53: 76.17 | V53: 39.85 | W53: 35.35 | X53: 30.84 | Y53: 7.83 | Z53: 7.83 | AA53: 3.14
A54: 1 | C54: 비유동리스부채 | J54: 45.21 | K54: 45.21 | L54: 42.84 | M54: 38.06 | N54: 34.41 | O54: 78.71 | P54: 78.71 | Q54: 70.48 | R54: 59.62 | S54: 51.21 | T54: 42.71 | U54: 42.71 | V54: 21.83 | W54: 17.11 | X54: 12.49 | Y54: 7.83 | Z54: 7.83 | AA54: 3.14
A55: 1 | C55: 장기금융부채 | J55: 45.21 | K55: 45.21 | L55: 42.84 | M55: 38.06 | N55: 34.41 | O55: 78.71 | P55: 78.71 | Q55: 70.48 | R55: 59.62 | S55: 51.21 | T55: 42.71 | U55: 42.71 | V55: 21.83 | W55: 17.11 | X55: 12.49 | Y55: 7.83 | Z55: 7.83 | AA55: 3.14
A56: 1 | C56: 단기금융부채(face) | N56: 91800 | O56: 91800 | P56: 91800 | Q56: 86800 | R56: 92300 | S56: 92650 | T56: 92650 | U56: 92650 | V56: 82650 | W56: 57650 | X56: 42000
A57: 1 | C57: 장기금융부채(face) | S57: 14000 | T57: 14000 | U57: 14000 | V57: 14000
A58: 1 | C58: 기타유동자산 | Y58: 119.86 | Z58: 119.86 | AA58: 35.17 | AB58: 41.37
A59: 1 | C59: 사용권자산 | Y59: 25.82 | Z59: 25.82 | AA59: 21.26 | AB59: 16.71
A60: 1 | C60: 기타유동부채 | Y60: 177.49 | Z60: 177.49 | AA60: 519.55 | AB60: 655.93
A61: 1 | C61: 매출액(수익) | E61: 18287.73 | G61: 18483.47 | H61: 18475.2 | I61: 17595.95 | J61: 19585.46 | K61: 74140.08 | L61: 19035.77 | M61: 18045.1 | N61: 17122.97 | O61: 17679.72 | P61: 71883.56 | Q61: 17685.27 | R61: 22152.44 | S61: 18091.47 | T61: 22244.79 | U61: 80173.97 | V61: 24460.07 | W61: 22126.77 | X61: 24232.69 | Y61: 21533.84 | Z61: 92353.37 | AA61: 24490.37 | AB61: 27365.98
A62: 1 | C62: 매출원가 | E62: 15684.25 | G62: 16209.19 | H62: 16156.16 | I62: 15562.39 | J62: 16958.39 | K62: 64886.13 | L62: 16903.97 | M62: 15215.1 | N62: 14434.58 | O62: 15557.7 | P62: 62111.35 | Q62: 15070.06 | R62: 16266.15 | S62: 14412.47 | T62: 17649.57 | U62: 63398.25 | V62: 19584.11 | W62: 16427.51 | X62: 17559.5 | Y62: 16891.26 | Z62: 70462.38 | AA62: 18664.25 | AB62: 20450.79
A63: 1 | C63: 매출총이익 | E63: 2603.48 | G63: 2274.28 | H63: 2319.03 | I63: 2033.56 | J63: 2627.06 | K63: 9253.93 | L63: 2131.8 | M63: 2830 | N63: 2688.39 | O63: 2122.02 | P63: 9772.21 | Q63: 2615.21 | R63: 5886.29 | S63: 3679 | T63: 4595.24 | U63: 16775.74 | V63: 4875.96 | W63: 5699.27 | X63: 6673.19 | Y63: 4642.57 | Z63: 21890.99 | AA63: 5826.12 | AB63: 6915.19
A64: 1 | C64: 판관비 | E64: 799.43 | G64: 862.57 | H64: 737.72 | I64: 1183.91 | J64: 914.11 | K64: 3698.31 | L64: 940.62 | M64: 980.2 | N64: 1619.83 | O64: 1039.56 | P64: 4580.21 | Q64: 1220.84 | R64: 1265.89 | S64: 1796.74 | T64: 1161.94 | U64: 5445.41 | V64: 2101.44 | W64: 1191.76 | X64: 1943.97 | Y64: 1270.03 | Z64: 6507.2 | AA64: 1287.14 | AB64: 2054.91
A65: 1 | C65: 영업이익 | E65: 1804.04 | G65: 1411.71 | H65: 1581.31 | I65: 849.65 | J65: 1712.95 | K65: 5555.62 | L65: 1191.18 | M65: 1849.8 | N65: 1068.56 | O65: 1082.46 | P65: 5192 | Q65: 1394.38 | R65: 4620.4 | S65: 1882.26 | T65: 3433.29 | U65: 11330.33 | V65: 2774.52 | W65: 4507.51 | X65: 4729.22 | Y65: 3372.55 | Z65: 15383.8 | AA65: 4538.98 | AB65: 4860.28
A66: 1 | C66: 기타영업외수익 | E66: 31.99 | G66: 33.26 | H66: 60.34 | I66: 127.56 | J66: -15.86 | K66: 205.3 | L66: 151.13 | M66: 3.58 | N66: 601.45 | O66: 70.34 | P66: 826.5 | Q66: 47826.29 | R66: -272.96 | S66: 28.96 | T66: 36.72 | U66: 47619.01 | V66: 98.26 | W66: 403.89 | X66: 50.17 | Y66: 1489.92 | Z66: 2042.24 | AA66: 151.51 | AB66: 268.24
A67: 1 | C67: 기타영업외비용 | E67: 159.43 | G67: 5.42 | H67: 131.6 | I67: 3.97 | J67: 179.14 | K67: 320.13 | L67: 6.34 | M67: 42.45 | N67: 46.66 | O67: 5639.18 | P67: 5734.63 | Q67: 21.69 | R67: 521.19 | S67: -27.27 | T67: 102.43 | U67: 618.04 | V67: 223.41 | W67: 183.22 | X67: -7.55 | Y67: 134.7 | Z67: 533.78 | AA67: 4 | AB67: 204.81
A68: 1 | C68: 금융수익 | E68: 50704.28 | G68: 46.23 | H68: 6111.66 | I68: 6082.49 | J68: 563.6 | K68: 12803.98 | L68: 56.26 | M68: 2082.96 | N68: 191.08 | O68: 12807.04 | P68: 15137.34 | Q68: 460.39 | R68: 440.8 | S68: 697.47 | T68: 613.25 | U68: 2211.91 | V68: 1242.83 | W68: 1097.91 | X68: 1079.45 | Y68: 1351.78 | Z68: 4771.97 | AA68: 1206.16 | AB68: 986.68
A69: 1 | C69: 금융비용 | E69: 570.12 | G69: 612.84 | H69: 1365.31 | I69: 1119.59 | J69: 1759.89 | K69: 4857.63 | L69: 1465.25 | M69: 2316.88 | N69: 1452.98 | O69: 1830.43 | P69: 7065.54 | Q69: 1523.88 | R69: 7184.73 | S69: 1060.2 | T69: 988.66 | U69: 10757.47 | V69: 866.72 | W69: 589.06 | X69: 520 | Y69: 412.55 | Z69: 2388.33 | AA69: 323.56 | AB69: 246.93
A70: 1 | C70: 법인세비용차감전계속사업이익 | E70: 51810.76 | G70: 872.94 | H70: 6256.41 | I70: 5936.14 | J70: 321.66 | K70: 13387.15 | L70: -73.02 | M70: 1577.01 | N70: 361.45 | O70: 6490.23 | P70: 8355.67 | Q70: 48135.49 | R70: -2917.68 | S70: 1575.74 | T70: 2992.19 | U70: 49785.74 | V70: 3025.46 | W70: 5237.03 | X70: 5346.4 | Y70: 5667 | Z70: 19275.89 | AA70: 5569.09 | AB70: 5663.47
A71: 1 | C71: 법인세비용 | E71: 12079.23 | G71: 186.55 | H71: 281.91 | I71: -144.25 | J71: 668.93 | K71: 993.14 | M71: 250.08 | N71: -22.31 | O71: 339.8 | Q71: 9801.55 | R71: -479.16 | S71: 1251.39 | T71: 1874.12 | U71: 12447.9 | V71: 698.88 | W71: 1209.75 | X71: 1222.15 | Y71: 101.74 | Z71: 3232.52 | AA71: 1018.7 | AB71: 1367.08
A72: 1 | C72: 당기순이익 | E72: 39731.53 | G72: 686.4 | H72: 5974.5 | I72: 6080.39 | J72: -347.27 | K72: 12394.02 | L72: -73.02 | M72: 1326.93 | N72: 383.76 | O72: 6150.43 | P72: 7788.1 | Q72: 38333.94 | R72: -2438.52 | S72: 324.35 | T72: 1118.07 | U72: 37337.84 | V72: 2326.58 | W72: 4027.27 | X72: 4124.25 | Y72: 5565.26 | Z72: 16043.36 | AA72: 4550.38 | AB72: 4296.39
A73: 1 | C73: 총포괄손익 | E73: 45063.61 | G73: 680.75 | H73: 5967.52 | I73: 6080.09 | J73: 404.9 | K73: 13133.26 | L73: -103 | M73: 1299.43 | N73: 369.98 | O73: 5803.62 | P73: 7370.03 | Q73: 49141.6 | R73: 34279.7 | S73: -13500.57 | T73: 32679.92 | U73: 102600.65 | V73: 26837.61 | W73: 20555.95 | X73: 42464.27 | Y73: 4130.33 | Z73: 93988.16 | AA73: 5094.29 | AB73: 11188.07
A74: 1 | C74: 금융손익 | E74: 50134.16 | G74: -566.61 | H74: 4746.35 | I74: 4962.9 | J74: -1196.29 | K74: 7946.35 | L74: -1408.99 | M74: -233.92 | N74: -1261.9 | O74: 10976.61 | P74: 8071.8 | Q74: -1063.49 | R74: -6743.93 | S74: -362.73 | T74: -375.41 | U74: -8545.56 | V74: 376.11 | W74: 508.85 | X74: 559.45 | Y74: 939.23 | Z74: 2383.64 | AA74: 882.6 | AB74: 739.75
A75: 1 | C75: 기타영업외손익 | E75: -127.44 | G75: 27.84 | H75: -71.26 | I75: 123.59 | J75: -195 | K75: -114.83 | L75: 144.79 | M75: -38.87 | N75: 554.79 | O75: -5568.84 | P75: -4908.13 | Q75: 47804.6 | R75: -794.15 | S75: 56.23 | T75: -65.71 | U75: 47000.97 | V75: -125.15 | W75: 220.67 | X75: 57.72 | Y75: 1355.22 | Z75: 1508.46 | AA75: 147.51 | AB75: 63.43
A76: 1 | C76: (지배주주지분)당기순이익 | E76: 39731.53 | G76: 686.4 | H76: 5974.5 | I76: 6080.39 | J76: -347.27 | K76: 12394.02 | L76: -73.02 | M76: 1326.93 | N76: 383.76 | O76: 6150.43 | P76: 7788.1 | Q76: 38333.94 | R76: -2438.52 | S76: 324.35 | T76: 1118.07 | U76: 37337.84 | V76: 2326.58 | W76: 4027.27 | X76: 4124.25 | Y76: 5565.26 | Z76: 16043.36 | AA76: 4550.38 | AB76: 4296.39
A77: 1 | C77: 계속사업이익 | E77: 39731.53 | G77: 686.4 | H77: 5974.5 | I77: 6080.39 | J77: -347.27 | K77: 12394.02 | L77: -73.02 | M77: 1326.93 | N77: 383.76 | O77: 6150.43 | P77: 7788.1 | Q77: 38333.94 | R77: -2438.52 | S77: 324.35 | T77: 1118.07 | U77: 37337.84 | V77: 2326.58 | W77: 4027.27 | X77: 4124.25 | Y77: 5565.26 | Z77: 16043.36 | AA77: 4550.38 | AB77: 4296.39
A78: 1 | C78: 영업활동으로인한현금흐름 | E78: 49071.91 | G78: -4235.89 | H78: 301.02 | I78: 5007.33 | J78: 508.59 | K78: 1581.05 | L78: 1008.91 | M78: 3564.33 | N78: 1129.91 | O78: 11260.49 | P78: 16963.64 | Q78: 2243.93 | R78: 2498.81 | S78: 5904.67 | T78: -124.48 | U78: 10522.93 | V78: -2239.13 | W78: 1894.71 | X78: 5145.55 | Y78: 1358.22 | Z78: 6159.35 | AA78: -11212.07 | AB78: -12358.9
A79: 1 | C79: 감가상각비 | E79: 1127.51 | G79: 985.57 | H79: 1009.53 | I79: 1015.88 | J79: 1018.69 | K79: 4029.67 | L79: 874.52 | M79: 1051.45
A80: 1 | C80: 법인세납부(CF) | E80: -14.41 | G80: -5748.93 | H80: -6904.12 | I80: -439.96 | J80: -10.88 | K80: -13103.89 | L80: -394.54 | M80: -382.27 | N80: -224.86 | O80: -317.88 | P80: -1319.55 | Q80: 205.93 | R80: 212.38 | S80: -124.61 | T80: -78.19 | U80: 215.51 | V80: -4972.05 | W80: -5792.41 | X80: -2665.65 | Y80: -2447.38 | Z80: -15877.49 | AA80: -15747.57 | AB80: -18973.39
A81: 1 | C81: 투자활동으로인한현금흐름 | E81: -45894.73 | G81: -234.64 | H81: 26.87 | I81: -29022.63 | J81: -2285.1 | K81: -31515.5 | L81: -2728.27 | M81: -3758.1 | N81: 9364.73 | O81: -1745.67 | P81: 1132.69 | Q81: 17695.68 | R81: -30030.6 | S81: -907.73 | T81: 4219.84 | U81: -9022.81 | V81: 30126.19 | W81: 24599.93 | X81: 20240.34 | Y81: 6838.64 | Z81: 81805.1 | AA81: 12403.82 | AB81: 33095.98
A82: 1 | C82: 유형자산의감소 | E82: 0 | N82: 0 | O82: 0 | Q82: 89 | R82: 0 | S82: 1 | T82: 0 | U82: 90 | V82: 0 | W82: 400 | X82: 25 | Y82: 0 | Z82: 425
A83: 1 | C83: 유형자산의증가 | E83: 292.39 | G83: 222.63 | H83: 226.98 | I83: 96.46 | J83: 230.9 | K83: 776.97 | L83: 253.14 | M83: 242.95 | N83: 480.26 | O83: 597.19 | P83: 1573.54 | Q83: 434.15 | R83: 906.65 | S83: 961.54 | T83: 531.95 | U83: 2834.29 | V83: 1900.29 | W83: 1097.21 | X83: 895.42 | Y83: 2473.34 | Z83: 6366.26 | AA83: 315.28 | AB83: 286.8
A84: 1 | C84: CAPEX | E84: 292.39 | G84: 222.63 | H84: 226.98 | I84: 96.46 | J84: 230.9 | K84: 776.97 | L84: 253.14 | M84: 242.95 | N84: 480.26 | O84: 597.19 | P84: 1573.54 | Q84: 434.15 | R84: 906.65 | S84: 961.54 | T84: 531.95 | U84: 2834.29 | V84: 1900.29 | W84: 1097.21 | X84: 895.42 | Y84: 2473.34 | Z84: 6366.26 | AA84: 723.28 | AB84: 286.8
A85: 1 | C85: 재무활동으로인한현금흐름 | E85: 177.98 | G85: 1582.36 | H85: 18983.05 | I85: -16.95 | J85: -16.95 | K85: 20531.51 | L85: -20.28 | M85: -22.11 | N85: 3702.15 | O85: -917.84 | P85: 2741.92 | Q85: -25426.22 | R85: 12244.8 | S85: -2267.79 | T85: -4826.31 | U85: -20275.52 | V85: -11439.37 | W85: -32804.28 | X85: -25072.1 | Y85: -12004.54 | Z85: -81320.29 | AA85: -2793.9 | AB85: -20831.71
A86: 1 | C86: 차입금의감소 | E86: 16.95 | G86: 416.95 | H86: 16.95 | I86: 16.95 | J86: 16.95 | K86: 467.8 | L86: 16.95 | M86: 10016.95 | N86: 16.95 | O86: 6016.95 | P86: 16067.8 | Q86: 15016.95 | R86: 39016.95 | S86: 25300 | T86: 24000 | U86: 103333.9 | V86: 10000 | W86: 25000 | X86: 15650 | Y86: 12000 | Z86: 62650
A87: 1 | C87: 현금및현금성자산의증감 | E87: 6709.37 | G87: -5750.49 | H87: 38623.48 | I87: -48026.69 | J87: -3633.33 | K87: -18787.03 | L87: -3455.56 | M87: -471.68 | N87: 28397.71 | O87: 17192.84 | P87: 41663.31 | Q87: -10993.92 | R87: -30594.82 | S87: 5509.69 | T87: -1440.77 | U87: -37519.82 | V87: 32913.55 | W87: -12663.22 | X87: 656.75 | Y87: -14297.16 | Z87: 6609.92 | AA87: -1569.99 | AB87: -123.11
A88: 1 | C88: 기말현금및현금성자산 | E88: 3354.21 | G88: 11519.71 | H88: 19312.54 | I88: -23994.44 | J88: -1839.87 | K88: 4997.94 | L88: 3282.03 | M88: -255.81 | N88: 14200.92 | O88: 8595.86 | P88: 25823 | Q88: 20315.68 | R88: -15307.82 | S88: 2780.54 | T88: -709.83 | U88: 7078.57 | V88: 23544.42 | W88: -6353.57 | X88: 342.95 | Y88: -3845.31 | Z88: 13688.49 | AA88: 12118.5 | AB88: -123.11
A89: 1 | C89: 배당금수취(CF) | I89: 6000 | J89: 0 | V89: 0
A90: 1 | C90: 이자수취(CF) | O90: 329.02 | Q90: 303.82 | R90: 308.03 | S90: 321.97 | T90: 187.7 | U90: 1121.52 | V90: 1068.65 | W90: 289.12 | X90: 1299.07 | Y90: 271.55 | Z90: 2928.39 | AA90: 2816.29 | AB90: 502.83
A91: 1 | C91: 배당금지급 | Q91: 20401.36 | R91: 0 | S91: 0 | T91: 0 | U91: 20401.36 | V91: 0 | W91: 6526.16 | X91: 9232.88 | Y91: 0 | Z91: 15759.04
A92: 1 | C92: 무형자산의증가 | AA92: 408 | AB92: 0
A93: 1 | C93: 리스부채의상환 | AA93: 4.57 | AB93: 4.6
A94: 1 | C94: 자기주식의취득 | AA94: 2789.32 | AB94: 2210.68

Sheet subQ
A1: YQ | C1: subQ 분기 서브모델(억원, U=100) | E1: 4Q21 | F1: 2021 | G1: 1Q22 | H1: 2Q22 | I1: 3Q22 | J1: 4Q22 | K1: 2022 | L1: 1Q23 | M1: 2Q23 | N1: 3Q23 | O1: 4Q23 | P1: 2023 | Q1: 1Q24 | R1: 2Q24 | S1: 3Q24 | T1: 4Q24 | U1: 2024 | V1: 1Q25 | W1: 2Q25 | X1: 3Q25 | Y1: 4Q25 | Z1: 2025 | AA1: 1Q26 | AB1: 2Q26 | AC1: 3Q26 | AD1: 4Q26 | AE1: 2026 | AF1: 1Q27 | AG1: 2Q27 | AH1: 3Q27 | AI1: 4Q27 | AJ1: 2027 | AK1: 1Q28 | AL1: 2Q28 | AM1: 3Q28 | AN1: 4Q28 | AO1: 2028
A2: A=이름(key) B=그룹 C=단위 D=FnGuide 계정명(VLOOKUP 키). 확정=VLOOKUP(BS), 추정=변수 가정 참조
E3: 1 | F3: 2 | G3: 3 | H3: 4 | I3: 5 | J3: 6 | K3: 7 | L3: 8 | M3: 9 | N3: 10 | O3: 11 | P3: 12 | Q3: 13 | R3: 14 | S3: 15 | T3: 16 | U3: 17 | V3: 18 | W3: 19 | X3: 20 | Y3: 21 | Z3: 22 | AA3: 23 | AB3: 24 | AC3: 25 | AD3: 26 | AE3: 27 | AF3: 28 | AG3: 29 | AH3: 30 | AI3: 31 | AJ3: 32 | AK3: 33 | AL3: 34 | AM3: 35 | AN3: 36 | AO3: 37
E4: 2021.12 | F4: 2021.12A | G4: 2022.03 | H4: 2022.06 | I4: 2022.09 | J4: 2022.12 | K4: 2022.12A | L4: 2023.03 | M4: 2023.06 | N4: 2023.09 | O4: 2023.12 | P4: 2023.12A | Q4: 2024.03 | R4: 2024.06 | S4: 2024.09 | T4: 2024.12 | U4: 2024.12A | V4: 2025.03 | W4: 2025.06 | X4: 2025.09 | Y4: 2025.12 | Z4: 2025.12A | AA4: 2026.03 | AB4: 2026.06 | AC4: 2026.09 | AD4: 2026.12 | AE4: 2026.12A | AF4: 2027.03 | AG4: 2027.06 | AH4: 2027.09 | AI4: 2027.12 | AJ4: 2027.12A | AK4: 2028.03 | AL4: 2028.06 | AM4: 2028.09 | AN4: 2028.12 | AO4: 2028.12A
A5: 매출액 | B5: 손익 | C5: 억원 | D5: 매출액(수익) | E5: =IFERROR(VLOOKUP($D5,BS연결,MATCH(E$1,BS연결H,0),0)/100,"") | G5: =IFERROR(VLOOKUP($D5,BS연결,MATCH(G$1,BS연결H,0),0)/100,"") | H5: =IFERROR(VLOOKUP($D5,BS연결,MATCH(H$1,BS연결H,0),0)/100,"") | I5: =IFERROR(VLOOKUP($D5,BS연결,MATCH(I$1,BS연결H,0),0)/100,"") | J5: =IFERROR(VLOOKUP($D5,BS연결,MATCH(J$1,BS연결H,0),0)/100,"") | K5: =SUM(G5:J5) | L5: =IFERROR(VLOOKUP($D5,BS연결,MATCH(L$1,BS연결H,0),0)/100,"") | M5: =IFERROR(VLOOKUP($D5,BS연결,MATCH(M$1,BS연결H,0),0)/100,"") | N5: =IFERROR(VLOOKUP($D5,BS연결,MATCH(N$1,BS연결H,0),0)/100,"") | O5: =IFERROR(VLOOKUP($D5,BS연결,MATCH(O$1,BS연결H,0),0)/100,"") | P5: =IFERROR(VLOOKUP($D5,BS연결,MATCH(P$1,BS연결H,0),0)/100,"") | Q5: =IFERROR(VLOOKUP($D5,BS연결,MATCH(Q$1,BS연결H,0),0)/100,"") | R5: =IFERROR(VLOOKUP($D5,BS연결,MATCH(R$1,BS연결H,0),0)/100,"") | S5: =IFERROR(VLOOKUP($D5,BS연결,MATCH(S$1,BS연결H,0),0)/100,"") | ... AB5: =IFERROR(VLOOKUP($D5,BS연결,MATCH(AB$1,BS연결H,0),0)/100,"") | AC5: =IFERROR(X5*(1+변수!AC21),"") | AD5: =IFERROR(Y5*(1+변수!AD21),"") | AE5: =SUM(AA5:AD5) | AF5: =IFERROR(AA5*(1+변수!AF21),"") | AG5: =IFERROR(AB5*(1+변수!AG21),"") | AH5: =IFERROR(AC5*(1+변수!AH21),"") | AI5: =IFERROR(AD5*(1+변수!AI21),"") | AJ5: =SUM(AF5:AI5) | AK5: =IFERROR(AF5*(1+변수!AK21),"") | AL5: =IFERROR(AG5*(1+변수!AL21),"") | AM5: =IFERROR(AH5*(1+변수!AM21),"") | AN5: =IFERROR(AI5*(1+변수!AN21),"") | AO5: =SUM(AK5:AN5)
A6: 매출원가 | B6: 손익 | C6: 억원 | D6: 매출원가 | E6: =IFERROR(VLOOKUP($D6,BS연결,MATCH(E$1,BS연결H,0),0)/100,"") | G6: =IFERROR(VLOOKUP($D6,BS연결,MATCH(G$1,BS연결H,0),0)/100,"") | H6: =IFERROR(VLOOKUP($D6,BS연결,MATCH(H$1,BS연결H,0),0)/100,"") | I6: =IFERROR(VLOOKUP($D6,BS연결,MATCH(I$1,BS연결H,0),0)/100,"") | J6: =IFERROR(VLOOKUP($D6,BS연결,MATCH(J$1,BS연결H,0),0)/100,"") | K6: =IFERROR(VLOOKUP($D6,BS연결,MATCH(K$1,BS연결H,0),0)/100,"") | L6: =IFERROR(VLOOKUP($D6,BS연결,MATCH(L$1,BS연결H,0),0)/100,"") | M6: =IFERROR(VLOOKUP($D6,BS연결,MATCH(M$1,BS연결H,0),0)/100,"") | N6: =IFERROR(VLOOKUP($D6,BS연결,MATCH(N$1,BS연결H,0),0)/100,"") | ... AB6: =IFERROR(VLOOKUP($D6,BS연결,MATCH(AB$1,BS연결H,0),0)/100,"") | AC6: =IFERROR(AC5-AC7,"") | AD6: =IFERROR(AD5-AD7,"") | AE6: =SUM(AA6:AD6) | AF6: =IFERROR(AF5-AF7,"") | AG6: =IFERROR(AG5-AG7,"") | AH6: =IFERROR(AH5-AH7,"") | AI6: =IFERROR(AI5-AI7,"") | AJ6: =SUM(AF6:AI6) | AK6: =IFERROR(AK5-AK7,"") | AL6: =IFERROR(AL5-AL7,"") | AM6: =IFERROR(AM5-AM7,"") | AN6: =IFERROR(AN5-AN7,"") | AO6: =SUM(AK6:AN6)
A7: 매출총이익 | B7: 손익 | C7: 억원 | D7: 매출총이익 | E7: =IFERROR(VLOOKUP($D7,BS연결,MATCH(E$1,BS연결H,0),0)/100,"") | G7: =IFERROR(VLOOKUP($D7,BS연결,MATCH(G$1,BS연결H,0),0)/100,"") | H7: =IFERROR(VLOOKUP($D7,BS연결,MATCH(H$1,BS연결H,0),0)/100,"") | I7: =IFERROR(VLOOKUP($D7,BS연결,MATCH(I$1,BS연결H,0),0)/100,"") | J7: =IFERROR(VLOOKUP($D7,BS연결,MATCH(J$1,BS연결H,0),0)/100,"") | K7: =IFERROR(VLOOKUP($D7,BS연결,MATCH(K$1,BS연결H,0),0)/100,"") | L7: =IFERROR(VLOOKUP($D7,BS연결,MATCH(L$1,BS연결H,0),0)/100,"") | M7: =IFERROR(VLOOKUP($D7,BS연결,MATCH(M$1,BS연결H,0),0)/100,"") | N7: =IFERROR(VLOOKUP($D7,BS연결,MATCH(N$1,BS연결H,0),0)/100,"") | O7: =IFERROR(VLOOKUP($D7,BS연결,MATCH(O$1,BS연결H,0),0)/100,"") | P7: =SUM(L7:O7) | Q7: =IFERROR(VLOOKUP($D7,BS연결,MATCH(Q$1,BS연결H,0),0)/100,"") | R7: =IFERROR(VLOOKUP($D7,BS연결,MATCH(R$1,BS연결H,0),0)/100,"") | S7: =IFERROR(VLOOKUP($D7,BS연결,MATCH(S$1,BS연결H,0),0)/100,"") | T7: =IFERROR(VLOOKUP($D7,BS연결,MATCH(T$1,BS연결H,0),0)/100,"") | U7: =IFERROR(VLOOKUP($D7,BS연결,MATCH(U$1,BS연결H,0),0)/100,"") | V7: =IFERROR(VLOOKUP($D7,BS연결,MATCH(V$1,BS연결H,0),0)/100,"") | W7: =IFERROR(VLOOKUP($D7,BS연결,MATCH(W$1,BS연결H,0),0)/100,"") | X7: =IFERROR(VLOOKUP($D7,BS연결,MATCH(X$1,BS연결H,0),0)/100,"") | ... AB7: =IFERROR(VLOOKUP($D7,BS연결,MATCH(AB$1,BS연결H,0),0)/100,"") | AC7: =IFERROR(AC9+AC8,"") | AD7: =IFERROR(AD9+AD8,"") | AE7: =SUM(AA7:AD7) | AF7: =IFERROR(AF9+AF8,"") | AG7: =IFERROR(AG9+AG8,"") | AH7: =IFERROR(AH9+AH8,"") | AI7: =IFERROR(AI9+AI8,"") | AJ7: =SUM(AF7:AI7) | AK7: =IFERROR(AK9+AK8,"") | AL7: =IFERROR(AL9+AL8,"") | AM7: =IFERROR(AM9+AM8,"") | AN7: =IFERROR(AN9+AN8,"") | AO7: =SUM(AK7:AN7)
A8: 판관비 | B8: 손익 | C8: 억원 | D8: 판관비 | E8: =IFERROR(VLOOKUP($D8,BS연결,MATCH(E$1,BS연결H,0),0)/100,"") | G8: =IFERROR(VLOOKUP($D8,BS연결,MATCH(G$1,BS연결H,0),0)/100,"") | H8: =IFERROR(VLOOKUP($D8,BS연결,MATCH(H$1,BS연결H,0),0)/100,"") | I8: =IFERROR(VLOOKUP($D8,BS연결,MATCH(I$1,BS연결H,0),0)/100,"") | J8: =IFERROR(VLOOKUP($D8,BS연결,MATCH(J$1,BS연결H,0),0)/100,"") | K8: =IFERROR(VLOOKUP($D8,BS연결,MATCH(K$1,BS연결H,0),0)/100,"") | L8: =IFERROR(VLOOKUP($D8,BS연결,MATCH(L$1,BS연결H,0),0)/100,"") | M8: =IFERROR(VLOOKUP($D8,BS연결,MATCH(M$1,BS연결H,0),0)/100,"") | N8: =IFERROR(VLOOKUP($D8,BS연결,MATCH(N$1,BS연결H,0),0)/100,"") | ... AB8: =IFERROR(VLOOKUP($D8,BS연결,MATCH(AB$1,BS연결H,0),0)/100,"") | AC8: =IFERROR(AC5*변수!AC22,"") | AD8: =IFERROR(AD5*변수!AD22,"") | AE8: =SUM(AA8:AD8) | AF8: =IFERROR(AF5*변수!AF22,"") | AG8: =IFERROR(AG5*변수!AG22,"") | AH8: =IFERROR(AH5*변수!AH22,"") | AI8: =IFERROR(AI5*변수!AI22,"") | AJ8: =SUM(AF8:AI8) | AK8: =IFERROR(AK5*변수!AK22,"") | AL8: =IFERROR(AL5*변수!AL22,"") | AM8: =IFERROR(AM5*변수!AM22,"") | AN8: =IFERROR(AN5*변수!AN22,"") | AO8: =SUM(AK8:AN8)
A9: 영업이익 | B9: 손익 | C9: 억원 | D9: 영업이익 | E9: =IFERROR(VLOOKUP($D9,BS연결,MATCH(E$1,BS연결H,0),0)/100,"") | G9: =IFERROR(VLOOKUP($D9,BS연결,MATCH(G$1,BS연결H,0),0)/100,"") | H9: =IFERROR(VLOOKUP($D9,BS연결,MATCH(H$1,BS연결H,0),0)/100,"") | I9: =IFERROR(VLOOKUP($D9,BS연결,MATCH(I$1,BS연결H,0),0)/100,"") | J9: =IFERROR(VLOOKUP($D9,BS연결,MATCH(J$1,BS연결H,0),0)/100,"") | K9: =IFERROR(VLOOKUP($D9,BS연결,MATCH(K$1,BS연결H,0),0)/100,"") | L9: =IFERROR(VLOOKUP($D9,BS연결,MATCH(L$1,BS연결H,0),0)/100,"") | M9: =IFERROR(VLOOKUP($D9,BS연결,MATCH(M$1,BS연결H,0),0)/100,"") | N9: =IFERROR(VLOOKUP($D9,BS연결,MATCH(N$1,BS연결H,0),0)/100,"") | ... AB9: =IFERROR(VLOOKUP($D9,BS연결,MATCH(AB$1,BS연결H,0),0)/100,"") | AC9: =IFERROR(AC5*변수!AC23,"") | AD9: =IFERROR(AD5*변수!AD23,"") | AE9: =SUM(AA9:AD9) | AF9: =IFERROR(AF5*변수!AF23,"") | AG9: =IFERROR(AG5*변수!AG23,"") | AH9: =IFERROR(AH5*변수!AH23,"") | AI9: =IFERROR(AI5*변수!AI23,"") | AJ9: =SUM(AF9:AI9) | AK9: =IFERROR(AK5*변수!AK23,"") | AL9: =IFERROR(AL5*변수!AL23,"") | AM9: =IFERROR(AM5*변수!AM23,"") | AN9: =IFERROR(AN5*변수!AN23,"") | AO9: =SUM(AK9:AN9)
A10: OPM | B10: 손익 | C10: % | D10: 영업이익률 | E10: =IFERROR(E9/E5,"") | G10: =IFERROR(G9/G5,"") | H10: =IFERROR(H9/H5,"") | I10: =IFERROR(I9/I5,"") | J10: =IFERROR(J9/J5,"") | K10: =IFERROR(K9/K5,"") | L10: =IFERROR(L9/L5,"") | M10: =IFERROR(M9/M5,"") | N10: =IFERROR(N9/N5,"") | ... AO10: =IFERROR(AO9/AO5,"")
A11: 금융손익 | B11: 손익 | C11: 억원 | D11: 금융손익 | E11: =IFERROR(VLOOKUP($D11,BS연결,MATCH(E$1,BS연결H,0),0)/100,"") | G11: =IFERROR(VLOOKUP($D11,BS연결,MATCH(G$1,BS연결H,0),0)/100,"") | H11: =IFERROR(VLOOKUP($D11,BS연결,MATCH(H$1,BS연결H,0),0)/100,"") | I11: =IFERROR(VLOOKUP($D11,BS연결,MATCH(I$1,BS연결H,0),0)/100,"") | J11: =IFERROR(VLOOKUP($D11,BS연결,MATCH(J$1,BS연결H,0),0)/100,"") | K11: =IFERROR(VLOOKUP($D11,BS연결,MATCH(K$1,BS연결H,0),0)/100,"") | L11: =IFERROR(VLOOKUP($D11,BS연결,MATCH(L$1,BS연결H,0),0)/100,"") | M11: =IFERROR(VLOOKUP($D11,BS연결,MATCH(M$1,BS연결H,0),0)/100,"") | N11: =IFERROR(VLOOKUP($D11,BS연결,MATCH(N$1,BS연결H,0),0)/100,"") | ... AB11: =IFERROR(VLOOKUP($D11,BS연결,MATCH(AB$1,BS연결H,0),0)/100,"") | AC11: =IFERROR(AC12+AC13+AC14,"") | AD11: =IFERROR(AD12+AD13+AD14,"") | AE11: =SUM(AA11:AD11) | AF11: =IFERROR(AF12+AF13+AF14,"") | AG11: =IFERROR(AG12+AG13+AG14,"") | AH11: =IFERROR(AH12+AH13+AH14,"") | AI11: =IFERROR(AI12+AI13+AI14,"") | AJ11: =SUM(AF11:AI11) | AK11: =IFERROR(AK12+AK13+AK14,"") | AL11: =IFERROR(AL12+AL13+AL14,"") | AM11: =IFERROR(AM12+AM13+AM14,"") | AN11: =IFERROR(AN12+AN13+AN14,"") | AO11: =SUM(AK11:AN11)
A12: 이자손익 | B12: 손익 | C12: 억원 | D12: 이자손익 | G12: =IFERROR(VLOOKUP($D12,BS연결,MATCH(G$1,BS연결H,0),0)/100,"") | H12: =IFERROR(VLOOKUP($D12,BS연결,MATCH(H$1,BS연결H,0),0)/100,"") | I12: =IFERROR(VLOOKUP($D12,BS연결,MATCH(I$1,BS연결H,0),0)/100,"") | J12: =IFERROR(VLOOKUP($D12,BS연결,MATCH(J$1,BS연결H,0),0)/100,"") | K12: =IFERROR(VLOOKUP($D12,BS연결,MATCH(K$1,BS연결H,0),0)/100,"") | L12: =IFERROR(VLOOKUP($D12,BS연결,MATCH(L$1,BS연결H,0),0)/100,"") | M12: =IFERROR(VLOOKUP($D12,BS연결,MATCH(M$1,BS연결H,0),0)/100,"") | N12: =IFERROR(VLOOKUP($D12,BS연결,MATCH(N$1,BS연결H,0),0)/100,"") | ... Z12: =IFERROR(VLOOKUP($D12,BS연결,MATCH(Z$1,BS연결H,0),0)/100,"") | AB12: =IFERROR(VLOOKUP($D12,BS연결,MATCH(AB$1,BS연결H,0),0)/100,"") | AC12: =IFERROR((AB30*변수!$D$55-AB28*변수!$D$56)/4,"") | AD12: =IFERROR((AC30*변수!$D$55-AC28*변수!$D$56)/4,"") | AE12: =SUM(AA12:AD12) | AF12: =IFERROR((AD30*변수!$D$55-AD28*변수!$D$56)/4,"") | AG12: =IFERROR((AF30*변수!$D$55-AF28*변수!$D$56)/4,"") | AH12: =IFERROR((AG30*변수!$D$55-AG28*변수!$D$56)/4,"") | AI12: =IFERROR((AH30*변수!$D$55-AH28*변수!$D$56)/4,"") | AJ12: =SUM(AF12:AI12) | AK12: =IFERROR((AI30*변수!$D$55-AI28*변수!$D$56)/4,"") | AL12: =IFERROR((AK30*변수!$D$55-AK28*변수!$D$56)/4,"") | AM12: =IFERROR((AL30*변수!$D$55-AL28*변수!$D$56)/4,"") | AN12: =IFERROR((AM30*변수!$D$55-AM28*변수!$D$56)/4,"") | AO12: =SUM(AK12:AN12)
A13: 파생상품손익 | B13: 손익 | C13: 억원 | D13: 파생상품손익 | I13: =IFERROR((VLOOKUP("파생상품이익",BS연결,MATCH(I$1,BS연결H,0),0)-VLOOKUP("파생상품손실",BS연결,MATCH(I$1,BS연결H,0),0))/100,"") | J13: =IFERROR((VLOOKUP("파생상품이익",BS연결,MATCH(J$1,BS연결H,0),0)-VLOOKUP("파생상품손실",BS연결,MATCH(J$1,BS연결H,0),0))/100,"") | K13: =SUM(G13:J13) | M13: =IFERROR((VLOOKUP("파생상품이익",BS연결,MATCH(M$1,BS연결H,0),0)-VLOOKUP("파생상품손실",BS연결,MATCH(M$1,BS연결H,0),0))/100,"") | N13: =IFERROR((VLOOKUP("파생상품이익",BS연결,MATCH(N$1,BS연결H,0),0)-VLOOKUP("파생상품손실",BS연결,MATCH(N$1,BS연결H,0),0))/100,"") | O13: =IFERROR((VLOOKUP("파생상품이익",BS연결,MATCH(O$1,BS연결H,0),0)-VLOOKUP("파생상품손실",BS연결,MATCH(O$1,BS연결H,0),0))/100,"") | P13: =SUM(L13:O13) | R13: =IFERROR((VLOOKUP("파생상품이익",BS연결,MATCH(R$1,BS연결H,0),0)-VLOOKUP("파생상품손실",BS연결,MATCH(R$1,BS연결H,0),0))/100,"") | S13: =IFERROR((VLOOKUP("파생상품이익",BS연결,MATCH(S$1,BS연결H,0),0)-VLOOKUP("파생상품손실",BS연결,MATCH(S$1,BS연결H,0),0))/100,"") | T13: =IFERROR((VLOOKUP("파생상품이익",BS연결,MATCH(T$1,BS연결H,0),0)-VLOOKUP("파생상품손실",BS연결,MATCH(T$1,BS연결H,0),0))/100,"") | U13: =SUM(Q13:T13) | V13: =IFERROR((VLOOKUP("파생상품이익",BS연결,MATCH(V$1,BS연결H,0),0)-VLOOKUP("파생상품손실",BS연결,MATCH(V$1,BS연결H,0),0))/100,"") | W13: =IFERROR((VLOOKUP("파생상품이익",BS연결,MATCH(W$1,BS연결H,0),0)-VLOOKUP("파생상품손실",BS연결,MATCH(W$1,BS연결H,0),0))/100,"") | X13: =IFERROR((VLOOKUP("파생상품이익",BS연결,MATCH(X$1,BS연결H,0),0)-VLOOKUP("파생상품손실",BS연결,MATCH(X$1,BS연결H,0),0))/100,"") | Y13: =IFERROR((VLOOKUP("파생상품이익",BS연결,MATCH(Y$1,BS연결H,0),0)-VLOOKUP("파생상품손실",BS연결,MATCH(Y$1,BS연결H,0),0))/100,"") | Z13: =SUM(V13:Y13) | AB13: =IFERROR((VLOOKUP("파생상품이익",BS연결,MATCH(AB$1,BS연결H,0),0)-VLOOKUP("파생상품손실",BS연결,MATCH(AB$1,BS연결H,0),0))/100,"") | AC13: =변수!AC24 | AD13: =변수!AD24 | AE13: =SUM(AA13:AD13) | AF13: =변수!AF24 | AG13: =변수!AG24 | AH13: =변수!AH24 | AI13: =변수!AI24 | AJ13: =SUM(AF13:AI13) | AK13: =변수!AK24 | AL13: =변수!AL24 | AM13: =변수!AM24 | AN13: =변수!AN24 | AO13: =SUM(AK13:AN13)
A14: 기타금융손익 | B14: 손익 | C14: 억원 | D14: 기타금융손익(금융손익 잔차) | I14: 0 | J14: 0.62 | K14: =SUM(G14:J14) | M14: -3.13 | N14: 3.15 | O14: 0 | P14: =SUM(L14:O14) | R14: 0 | S14: 0 | T14: 0 | U14: =SUM(Q14:T14) | V14: 0 | W14: 0 | X14: 0 | Y14: 0 | Z14: =SUM(V14:Y14) | AB14: 0.01 | AC14: =변수!AC25 | AD14: =변수!AD25 | AE14: =SUM(AA14:AD14) | AF14: =변수!AF25 | AG14: =변수!AG25 | AH14: =변수!AH25 | AI14: =변수!AI25 | AJ14: =SUM(AF14:AI14) | AK14: =변수!AK25 | AL14: =변수!AL25 | AM14: =변수!AM25 | AN14: =변수!AN25 | AO14: =SUM(AK14:AN14)
A15: 기타영업외손익 | B15: 손익 | C15: 억원 | D15: 기타영업외손익 | E15: =IFERROR(VLOOKUP($D15,BS연결,MATCH(E$1,BS연결H,0),0)/100,"") | G15: =IFERROR(VLOOKUP($D15,BS연결,MATCH(G$1,BS연결H,0),0)/100,"") | H15: =IFERROR(VLOOKUP($D15,BS연결,MATCH(H$1,BS연결H,0),0)/100,"") | I15: =IFERROR(VLOOKUP($D15,BS연결,MATCH(I$1,BS연결H,0),0)/100,"") | J15: =IFERROR(VLOOKUP($D15,BS연결,MATCH(J$1,BS연결H,0),0)/100,"") | K15: =IFERROR(VLOOKUP($D15,BS연결,MATCH(K$1,BS연결H,0),0)/100,"") | L15: =IFERROR(VLOOKUP($D15,BS연결,MATCH(L$1,BS연결H,0),0)/100,"") | M15: =IFERROR(VLOOKUP($D15,BS연결,MATCH(M$1,BS연결H,0),0)/100,"") | N15: =IFERROR(VLOOKUP($D15,BS연결,MATCH(N$1,BS연결H,0),0)/100,"") | ... AB15: =IFERROR(VLOOKUP($D15,BS연결,MATCH(AB$1,BS연결H,0),0)/100,"") | AC15: =변수!AC26 | AD15: =변수!AD26 | AE15: =SUM(AA15:AD15) | AF15: =변수!AF26 | AG15: =변수!AG26 | AH15: =변수!AH26 | AI15: =변수!AI26 | AJ15: =SUM(AF15:AI15) | AK15: =변수!AK26 | AL15: =변수!AL26 | AM15: =변수!AM26 | AN15: =변수!AN26 | AO15: =SUM(AK15:AN15)
A16: 지분법손익 | B16: 손익 | C16: 억원 | D16: 종속기업,공동지배기업및관계기업관련손익 | K16: =SUM(G16:J16) | P16: =SUM(L16:O16) | U16: =SUM(Q16:T16) | Z16: =SUM(V16:Y16) | AA16: =IFERROR(VLOOKUP($D16,BS연결,MATCH(AA$1,BS연결H,0),0)/100,"") | AB16: =IFERROR(VLOOKUP($D16,BS연결,MATCH(AB$1,BS연결H,0),0)/100,"") | AC16: =변수!AC27 | AD16: =변수!AD27 | AE16: =SUM(AA16:AD16) | AF16: =변수!AF27 | AG16: =변수!AG27 | AH16: =변수!AH27 | AI16: =변수!AI27 | AJ16: =SUM(AF16:AI16) | AK16: =변수!AK27 | AL16: =변수!AL27 | AM16: =변수!AM27 | AN16: =변수!AN27 | AO16: =SUM(AK16:AN16)
A17: 세전이익 | B17: 손익 | C17: 억원 | D17: 법인세비용차감전계속사업이익 | E17: =IFERROR(VLOOKUP($D17,BS연결,MATCH(E$1,BS연결H,0),0)/100,"") | G17: =IFERROR(VLOOKUP($D17,BS연결,MATCH(G$1,BS연결H,0),0)/100,"") | H17: =IFERROR(VLOOKUP($D17,BS연결,MATCH(H$1,BS연결H,0),0)/100,"") | I17: =IFERROR(VLOOKUP($D17,BS연결,MATCH(I$1,BS연결H,0),0)/100,"") | J17: =IFERROR(VLOOKUP($D17,BS연결,MATCH(J$1,BS연결H,0),0)/100,"") | K17: =IFERROR(VLOOKUP($D17,BS연결,MATCH(K$1,BS연결H,0),0)/100,"") | L17: =IFERROR(VLOOKUP($D17,BS연결,MATCH(L$1,BS연결H,0),0)/100,"") | M17: =IFERROR(VLOOKUP($D17,BS연결,MATCH(M$1,BS연결H,0),0)/100,"") | N17: =IFERROR(VLOOKUP($D17,BS연결,MATCH(N$1,BS연결H,0),0)/100,"") | ... X17: =IFERROR(VLOOKUP($D17,BS연결,MATCH(X$1,BS연결H,0),0)/100,"") | Z17: =SUM(V17:Y17) | AC17: =IFERROR(AC9+AC11+AC15+AC16,"") | AD17: =IFERROR(AD9+AD11+AD15+AD16,"") | AE17: =SUM(AA17:AD17) | AF17: =IFERROR(AF9+AF11+AF15+AF16,"") | AG17: =IFERROR(AG9+AG11+AG15+AG16,"") | AH17: =IFERROR(AH9+AH11+AH15+AH16,"") | AI17: =IFERROR(AI9+AI11+AI15+AI16,"") | AJ17: =SUM(AF17:AI17) | AK17: =IFERROR(AK9+AK11+AK15+AK16,"") | AL17: =IFERROR(AL9+AL11+AL15+AL16,"") | AM17: =IFERROR(AM9+AM11+AM15+AM16,"") | AN17: =IFERROR(AN9+AN11+AN15+AN16,"") | AO17: =SUM(AK17:AN17)
A18: 법인세비용 | B18: 손익 | C18: 억원 | D18: 법인세비용 | E18: =IFERROR(VLOOKUP($D18,BS연결,MATCH(E$1,BS연결H,0),0)/100,"") | G18: =IFERROR(VLOOKUP($D18,BS연결,MATCH(G$1,BS연결H,0),0)/100,"") | H18: =IFERROR(VLOOKUP($D18,BS연결,MATCH(H$1,BS연결H,0),0)/100,"") | I18: =IFERROR(VLOOKUP($D18,BS연결,MATCH(I$1,BS연결H,0),0)/100,"") | J18: =IFERROR(VLOOKUP($D18,BS연결,MATCH(J$1,BS연결H,0),0)/100,"") | K18: =IFERROR(VLOOKUP($D18,BS연결,MATCH(K$1,BS연결H,0),0)/100,"") | L18: =IFERROR(VLOOKUP($D18,BS연결,MATCH(L$1,BS연결H,0),0)/100,"") | M18: =IFERROR(VLOOKUP($D18,BS연결,MATCH(M$1,BS연결H,0),0)/100,"") | N18: =IFERROR(VLOOKUP($D18,BS연결,MATCH(N$1,BS연결H,0),0)/100,"") | ... AB18: =IFERROR(VLOOKUP($D18,BS연결,MATCH(AB$1,BS연결H,0),0)/100,"") | AC18: =IFERROR(MAX(AC17,0)*변수!AC28,"") | AD18: =IFERROR(MAX(AD17,0)*변수!AD28,"") | AE18: =SUM(AA18:AD18) | AF18: =IFERROR(MAX(AF17,0)*변수!AF28,"") | AG18: =IFERROR(MAX(AG17,0)*변수!AG28,"") | AH18: =IFERROR(MAX(AH17,0)*변수!AH28,"") | AI18: =IFERROR(MAX(AI17,0)*변수!AI28,"") | AJ18: =SUM(AF18:AI18) | AK18: =IFERROR(MAX(AK17,0)*변수!AK28,"") | AL18: =IFERROR(MAX(AL17,0)*변수!AL28,"") | AM18: =IFERROR(MAX(AM17,0)*변수!AM28,"") | AN18: =IFERROR(MAX(AN17,0)*변수!AN28,"") | AO18: =SUM(AK18:AN18)
A19: 당기순이익 | B19: 손익 | C19: 억원 | D19: 당기순이익 | E19: =IFERROR(VLOOKUP($D19,BS연결,MATCH(E$1,BS연결H,0),0)/100,"") | G19: =IFERROR(VLOOKUP($D19,BS연결,MATCH(G$1,BS연결H,0),0)/100,"") | H19: =IFERROR(VLOOKUP($D19,BS연결,MATCH(H$1,BS연결H,0),0)/100,"") | I19: =IFERROR(VLOOKUP($D19,BS연결,MATCH(I$1,BS연결H,0),0)/100,"") | J19: =IFERROR(VLOOKUP($D19,BS연결,MATCH(J$1,BS연결H,0),0)/100,"") | K19: =IFERROR(VLOOKUP($D19,BS연결,MATCH(K$1,BS연결H,0),0)/100,"") | L19: =IFERROR(VLOOKUP($D19,BS연결,MATCH(L$1,BS연결H,0),0)/100,"") | M19: =IFERROR(VLOOKUP($D19,BS연결,MATCH(M$1,BS연결H,0),0)/100,"") | N19: =IFERROR(VLOOKUP($D19,BS연결,MATCH(N$1,BS연결H,0),0)/100,"") | ... Z19: =IFERROR(VLOOKUP($D19,BS연결,MATCH(Z$1,BS연결H,0),0)/100,"") | AB19: =IFERROR(VLOOKUP($D19,BS연결,MATCH(AB$1,BS연결H,0),0)/100,"") | AC19: =IFERROR(AC17-AC18,"") | AD19: =IFERROR(AD17-AD18,"") | AE19: =SUM(AA19:AD19) | AF19: =IFERROR(AF17-AF18,"") | AG19: =IFERROR(AG17-AG18,"") | AH19: =IFERROR(AH17-AH18,"") | AI19: =IFERROR(AI17-AI18,"") | AJ19: =SUM(AF19:AI19) | AK19: =IFERROR(AK17-AK18,"") | AL19: =IFERROR(AL17-AL18,"") | AM19: =IFERROR(AM17-AM18,"") | AN19: =IFERROR(AN17-AN18,"") | AO19: =SUM(AK19:AN19)
A20: 지배주주순이익 | B20: 손익 | C20: 억원 | D20: (지배주주지분)당기순이익 | E20: =IFERROR(VLOOKUP($D20,BS연결,MATCH(E$1,BS연결H,0),0)/100,"") | G20: =IFERROR(VLOOKUP($D20,BS연결,MATCH(G$1,BS연결H,0),0)/100,"") | H20: =IFERROR(VLOOKUP($D20,BS연결,MATCH(H$1,BS연결H,0),0)/100,"") | I20: =IFERROR(VLOOKUP($D20,BS연결,MATCH(I$1,BS연결H,0),0)/100,"") | J20: =IFERROR(VLOOKUP($D20,BS연결,MATCH(J$1,BS연결H,0),0)/100,"") | K20: =IFERROR(VLOOKUP($D20,BS연결,MATCH(K$1,BS연결H,0),0)/100,"") | L20: =IFERROR(VLOOKUP($D20,BS연결,MATCH(L$1,BS연결H,0),0)/100,"") | M20: =IFERROR(VLOOKUP($D20,BS연결,MATCH(M$1,BS연결H,0),0)/100,"") | N20: =IFERROR(VLOOKUP($D20,BS연결,MATCH(N$1,BS연결H,0),0)/100,"") | ... AB20: =IFERROR(VLOOKUP($D20,BS연결,MATCH(AB$1,BS연결H,0),0)/100,"") | AC20: =IFERROR(AC19*변수!AC29,"") | AD20: =IFERROR(AD19*변수!AD29,"") | AE20: =SUM(AA20:AD20) | AF20: =IFERROR(AF19*변수!AF29,"") | AG20: =IFERROR(AG19*변수!AG29,"") | AH20: =IFERROR(AH19*변수!AH29,"") | AI20: =IFERROR(AI19*변수!AI29,"") | AJ20: =SUM(AF20:AI20) | AK20: =IFERROR(AK19*변수!AK29,"") | AL20: =IFERROR(AL19*변수!AL29,"") | AM20: =IFERROR(AM19*변수!AM29,"") | AN20: =IFERROR(AN19*변수!AN29,"") | AO20: =SUM(AK20:AN20)
A21: 중단사업이익 | B21: 손익 | C21: 억원 | D21: 중단사업이익 | K21: =SUM(G21:J21) | O21: =IFERROR(VLOOKUP($D21,BS연결,MATCH(O$1,BS연결H,0),0)/100,"") | P21: =SUM(L21:O21) | Q21: =IFERROR(VLOOKUP($D21,BS연결,MATCH(Q$1,BS연결H,0),0)/100,"") | R21: =IFERROR(VLOOKUP($D21,BS연결,MATCH(R$1,BS연결H,0),0)/100,"") | S21: =IFERROR(VLOOKUP($D21,BS연결,MATCH(S$1,BS연결H,0),0)/100,"") | T21: =IFERROR(VLOOKUP($D21,BS연결,MATCH(T$1,BS연결H,0),0)/100,"") | U21: =IFERROR(VLOOKUP($D21,BS연결,MATCH(U$1,BS연결H,0),0)/100,"") | Z21: =SUM(V21:Y21) | AE21: =SUM(AA21:AD21) | AJ21: =SUM(AF21:AI21) | AO21: =SUM(AK21:AN21)
A22: 감가상각비 | B22: 손익 | C22: 억원 | D22: 감가상각비 | E22: =IFERROR(VLOOKUP($D22,BS연결,MATCH(E$1,BS연결H,0),0)/100,"") | G22: =IFERROR(VLOOKUP($D22,BS연결,MATCH(G$1,BS연결H,0),0)/100,"") | H22: =IFERROR(VLOOKUP($D22,BS연결,MATCH(H$1,BS연결H,0),0)/100,"") | I22: =IFERROR(VLOOKUP($D22,BS연결,MATCH(I$1,BS연결H,0),0)/100,"") | J22: =IFERROR(VLOOKUP($D22,BS연결,MATCH(J$1,BS연결H,0),0)/100,"") | K22: =IFERROR(VLOOKUP($D22,BS연결,MATCH(K$1,BS연결H,0),0)/100,"") | L22: =IFERROR(VLOOKUP($D22,BS연결,MATCH(L$1,BS연결H,0),0)/100,"") | M22: =IFERROR(VLOOKUP($D22,BS연결,MATCH(M$1,BS연결H,0),0)/100,"") | P22: =SUM(L22:O22) | U22: =SUM(Q22:T22) | Z22: =SUM(V22:Y22) | AC22: =변수!AC31 | AD22: =변수!AD31 | AE22: =SUM(AA22:AD22) | AF22: =변수!AF31 | AG22: =변수!AG31 | AH22: =변수!AH31 | AI22: =변수!AI31 | AJ22: =SUM(AF22:AI22) | AK22: =변수!AK31 | AL22: =변수!AL31 | AM22: =변수!AM31 | AN22: =변수!AN31 | AO22: =SUM(AK22:AN22)
A23: EBITDA | B23: 손익 | C23: 억원 | D23: EBITDA | E23: 50.26 | G23: 43.15 | H23: 40.79 | I23: 35.23 | J23: 45.75 | K23: =SUM(G23:J23) | L23: 29.73 | M23: 34.54 | P23: =SUM(L23:O23) | U23: =SUM(Q23:T23) | Z23: =SUM(V23:Y23) | AC23: =IFERROR(AC9+AC22,"") | AD23: =IFERROR(AD9+AD22,"") | AE23: =SUM(AA23:AD23) | AF23: =IFERROR(AF9+AF22,"") | AG23: =IFERROR(AG9+AG22,"") | AH23: =IFERROR(AH9+AH22,"") | AI23: =IFERROR(AI9+AI22,"") | AJ23: =SUM(AF23:AI23) | AK23: =IFERROR(AK9+AK22,"") | AL23: =IFERROR(AL9+AL22,"") | AM23: =IFERROR(AM9+AM22,"") | AN23: =IFERROR(AN9+AN22,"") | AO23: =SUM(AK23:AN23)
A24: 자산총계 | B24: 재무상태 | C24: 억원 | D24: 자산총계 | E24: =IFERROR(VLOOKUP($D24,BS연결,MATCH(E$1,BS연결H,0),0)/100,"") | F24: =IFERROR(VLOOKUP($D24,BS연결,MATCH(F$1,BS연결H,0),0)/100,"") | G24: =IFERROR(VLOOKUP($D24,BS연결,MATCH(G$1,BS연결H,0),0)/100,"") | H24: =IFERROR(VLOOKUP($D24,BS연결,MATCH(H$1,BS연결H,0),0)/100,"") | I24: =IFERROR(VLOOKUP($D24,BS연결,MATCH(I$1,BS연결H,0),0)/100,"") | J24: =IFERROR(VLOOKUP($D24,BS연결,MATCH(J$1,BS연결H,0),0)/100,"") | K24: =IFERROR(VLOOKUP($D24,BS연결,MATCH(K$1,BS연결H,0),0)/100,"") | L24: =IFERROR(VLOOKUP($D24,BS연결,MATCH(L$1,BS연결H,0),0)/100,"") | ... AB24: =IFERROR(VLOOKUP($D24,BS연결,MATCH(AB$1,BS연결H,0),0)/100,"") | AC24: =IFERROR(AC25+AC26,"") | AD24: =IFERROR(AD25+AD26,"") | AE24: =AD24 | AF24: =IFERROR(AF25+AF26,"") | AG24: =IFERROR(AG25+AG26,"") | AH24: =IFERROR(AH25+AH26,"") | AI24: =IFERROR(AI25+AI26,"") | AJ24: =AI24 | AK24: =IFERROR(AK25+AK26,"") | AL24: =IFERROR(AL25+AL26,"") | AM24: =IFERROR(AM25+AM26,"") | AN24: =IFERROR(AN25+AN26,"") | AO24: =AN24
A25: 부채총계 | B25: 재무상태 | C25: 억원 | D25: 부채총계 | E25: =IFERROR(VLOOKUP($D25,BS연결,MATCH(E$1,BS연결H,0),0)/100,"") | F25: =IFERROR(VLOOKUP($D25,BS연결,MATCH(F$1,BS연결H,0),0)/100,"") | G25: =IFERROR(VLOOKUP($D25,BS연결,MATCH(G$1,BS연결H,0),0)/100,"") | H25: =IFERROR(VLOOKUP($D25,BS연결,MATCH(H$1,BS연결H,0),0)/100,"") | I25: =IFERROR(VLOOKUP($D25,BS연결,MATCH(I$1,BS연결H,0),0)/100,"") | J25: =IFERROR(VLOOKUP($D25,BS연결,MATCH(J$1,BS연결H,0),0)/100,"") | K25: =IFERROR(VLOOKUP($D25,BS연결,MATCH(K$1,BS연결H,0),0)/100,"") | L25: =IFERROR(VLOOKUP($D25,BS연결,MATCH(L$1,BS연결H,0),0)/100,"") | ... AB25: =IFERROR(VLOOKUP($D25,BS연결,MATCH(AB$1,BS연결H,0),0)/100,"") | AC25: =IFERROR(AB25*(1+변수!AC32),"") | AD25: =IFERROR(AC25*(1+변수!AD32),"") | AE25: =AD25 | AF25: =IFERROR(AD25*(1+변수!AF32),"") | AG25: =IFERROR(AF25*(1+변수!AG32),"") | AH25: =IFERROR(AG25*(1+변수!AH32),"") | AI25: =IFERROR(AH25*(1+변수!AI32),"") | AJ25: =AI25 | AK25: =IFERROR(AI25*(1+변수!AK32),"") | AL25: =IFERROR(AK25*(1+변수!AL32),"") | AM25: =IFERROR(AL25*(1+변수!AM32),"") | AN25: =IFERROR(AM25*(1+변수!AN32),"") | AO25: =AN25
A26: 자본총계 | B26: 재무상태 | C26: 억원 | D26: 자본총계 | E26: =IFERROR(VLOOKUP($D26,BS연결,MATCH(E$1,BS연결H,0),0)/100,"") | F26: =IFERROR(VLOOKUP($D26,BS연결,MATCH(F$1,BS연결H,0),0)/100,"") | G26: =IFERROR(VLOOKUP($D26,BS연결,MATCH(G$1,BS연결H,0),0)/100,"") | H26: =IFERROR(VLOOKUP($D26,BS연결,MATCH(H$1,BS연결H,0),0)/100,"") | I26: =IFERROR(VLOOKUP($D26,BS연결,MATCH(I$1,BS연결H,0),0)/100,"") | J26: =IFERROR(VLOOKUP($D26,BS연결,MATCH(J$1,BS연결H,0),0)/100,"") | K26: =IFERROR(VLOOKUP($D26,BS연결,MATCH(K$1,BS연결H,0),0)/100,"") | L26: =IFERROR(VLOOKUP($D26,BS연결,MATCH(L$1,BS연결H,0),0)/100,"") | ... AB26: =IFERROR(VLOOKUP($D26,BS연결,MATCH(AB$1,BS연결H,0),0)/100,"") | AC26: =IFERROR(AB26+AC19-변수!AC33,"") | AD26: =IFERROR(AC26+AD19-변수!AD33,"") | AE26: =AD26 | AF26: =IFERROR(AD26+AF19-변수!AF33,"") | AG26: =IFERROR(AF26+AG19-변수!AG33,"") | AH26: =IFERROR(AG26+AH19-변수!AH33,"") | AI26: =IFERROR(AH26+AI19-변수!AI33,"") | AJ26: =AI26 | AK26: =IFERROR(AI26+AK19-변수!AK33,"") | AL26: =IFERROR(AK26+AL19-변수!AL33,"") | AM26: =IFERROR(AL26+AM19-변수!AM33,"") | AN26: =IFERROR(AM26+AN19-변수!AN33,"") | AO26: =AN26
A27: 지배주주지분 | B27: 재무상태 | C27: 억원 | D27: 지배주주지분 | E27: =IFERROR(VLOOKUP($D27,BS연결,MATCH(E$1,BS연결H,0),0)/100,"") | F27: =IFERROR(VLOOKUP($D27,BS연결,MATCH(F$1,BS연결H,0),0)/100,"") | G27: =IFERROR(VLOOKUP($D27,BS연결,MATCH(G$1,BS연결H,0),0)/100,"") | H27: =IFERROR(VLOOKUP($D27,BS연결,MATCH(H$1,BS연결H,0),0)/100,"") | I27: =IFERROR(VLOOKUP($D27,BS연결,MATCH(I$1,BS연결H,0),0)/100,"") | J27: =IFERROR(VLOOKUP($D27,BS연결,MATCH(J$1,BS연결H,0),0)/100,"") | K27: =IFERROR(VLOOKUP($D27,BS연결,MATCH(K$1,BS연결H,0),0)/100,"") | L27: =IFERROR(VLOOKUP($D27,BS연결,MATCH(L$1,BS연결H,0),0)/100,"") | ... AB27: =IFERROR(VLOOKUP($D27,BS연결,MATCH(AB$1,BS연결H,0),0)/100,"") | AC27: =IFERROR(AB27+AC20-변수!AC34,"") | AD27: =IFERROR(AC27+AD20-변수!AD34,"") | AE27: =AD27 | AF27: =IFERROR(AD27+AF20-변수!AF34,"") | AG27: =IFERROR(AF27+AG20-변수!AG34,"") | AH27: =IFERROR(AG27+AH20-변수!AH34,"") | AI27: =IFERROR(AH27+AI20-변수!AI34,"") | AJ27: =AI27 | AK27: =IFERROR(AI27+AK20-변수!AK34,"") | AL27: =IFERROR(AK27+AL20-변수!AL34,"") | AM27: =IFERROR(AL27+AM20-변수!AM34,"") | AN27: =IFERROR(AM27+AN20-변수!AN34,"") | AO27: =AN27
A28: 총차입금 | B28: 재무상태 | C28: 억원 | D28: 총차입금 | E28: =IFERROR(VLOOKUP($D28,BS연결,MATCH(E$1,BS연결H,0),0)/100,"") | F28: =IFERROR(VLOOKUP($D28,BS연결,MATCH(F$1,BS연결H,0),0)/100,"") | G28: =IFERROR(VLOOKUP($D28,BS연결,MATCH(G$1,BS연결H,0),0)/100,"") | H28: =IFERROR(VLOOKUP($D28,BS연결,MATCH(H$1,BS연결H,0),0)/100,"") | I28: =IFERROR(VLOOKUP($D28,BS연결,MATCH(I$1,BS연결H,0),0)/100,"") | J28: =IFERROR(VLOOKUP($D28,BS연결,MATCH(J$1,BS연결H,0),0)/100,"") | K28: =IFERROR(VLOOKUP($D28,BS연결,MATCH(K$1,BS연결H,0),0)/100,"") | L28: =IFERROR(VLOOKUP($D28,BS연결,MATCH(L$1,BS연결H,0),0)/100,"") | ... AB28: =IFERROR(VLOOKUP($D28,BS연결,MATCH(AB$1,BS연결H,0),0)/100,"") | AC28: =IFERROR(AB28*(1+변수!AC35),"") | AD28: =IFERROR(AC28*(1+변수!AD35),"") | AE28: =AD28 | AF28: =IFERROR(AD28*(1+변수!AF35),"") | AG28: =IFERROR(AF28*(1+변수!AG35),"") | AH28: =IFERROR(AG28*(1+변수!AH35),"") | AI28: =IFERROR(AH28*(1+변수!AI35),"") | AJ28: =AI28 | AK28: =IFERROR(AI28*(1+변수!AK35),"") | AL28: =IFERROR(AK28*(1+변수!AL35),"") | AM28: =IFERROR(AL28*(1+변수!AM35),"") | AN28: =IFERROR(AM28*(1+변수!AN35),"") | AO28: =AN28
A29: 순차입금 | B29: 재무상태 | C29: 억원 | D29: 순차입금 | E29: =IFERROR(VLOOKUP($D29,BS연결,MATCH(E$1,BS연결H,0),0)/100,"") | F29: =IFERROR(VLOOKUP($D29,BS연결,MATCH(F$1,BS연결H,0),0)/100,"") | G29: =IFERROR(VLOOKUP($D29,BS연결,MATCH(G$1,BS연결H,0),0)/100,"") | H29: =IFERROR(VLOOKUP($D29,BS연결,MATCH(H$1,BS연결H,0),0)/100,"") | I29: =IFERROR(VLOOKUP($D29,BS연결,MATCH(I$1,BS연결H,0),0)/100,"") | J29: =IFERROR(VLOOKUP($D29,BS연결,MATCH(J$1,BS연결H,0),0)/100,"") | K29: =IFERROR(VLOOKUP($D29,BS연결,MATCH(K$1,BS연결H,0),0)/100,"") | L29: =IFERROR(VLOOKUP($D29,BS연결,MATCH(L$1,BS연결H,0),0)/100,"") | ... AB29: =IFERROR(VLOOKUP($D29,BS연결,MATCH(AB$1,BS연결H,0),0)/100,"") | AC29: =IFERROR(AB29*(1+변수!AC36),"") | AD29: =IFERROR(AC29*(1+변수!AD36),"") | AE29: =AD29 | AF29: =IFERROR(AD29*(1+변수!AF36),"") | AG29: =IFERROR(AF29*(1+변수!AG36),"") | AH29: =IFERROR(AG29*(1+변수!AH36),"") | AI29: =IFERROR(AH29*(1+변수!AI36),"") | AJ29: =AI29 | AK29: =IFERROR(AI29*(1+변수!AK36),"") | AL29: =IFERROR(AK29*(1+변수!AL36),"") | AM29: =IFERROR(AL29*(1+변수!AM36),"") | AN29: =IFERROR(AM29*(1+변수!AN36),"") | AO29: =AN29
A30: 이자발생자산 | B30: 재무상태 | C30: 억원 | D30: 이자발생자산 | E30: =IFERROR(VLOOKUP($D30,BS연결,MATCH(E$1,BS연결H,0),0)/100,"") | F30: =IFERROR(VLOOKUP($D30,BS연결,MATCH(F$1,BS연결H,0),0)/100,"") | G30: =IFERROR(VLOOKUP($D30,BS연결,MATCH(G$1,BS연결H,0),0)/100,"") | H30: =IFERROR(VLOOKUP($D30,BS연결,MATCH(H$1,BS연결H,0),0)/100,"") | I30: =IFERROR(VLOOKUP($D30,BS연결,MATCH(I$1,BS연결H,0),0)/100,"") | J30: =IFERROR(VLOOKUP($D30,BS연결,MATCH(J$1,BS연결H,0),0)/100,"") | K30: =IFERROR(VLOOKUP($D30,BS연결,MATCH(K$1,BS연결H,0),0)/100,"") | L30: =IFERROR(VLOOKUP($D30,BS연결,MATCH(L$1,BS연결H,0),0)/100,"") | ... AB30: =IFERROR(VLOOKUP($D30,BS연결,MATCH(AB$1,BS연결H,0),0)/100,"") | AC30: =IFERROR(AB30*(1+변수!AC37),"") | AD30: =IFERROR(AC30*(1+변수!AD37),"") | AE30: =AD30 | AF30: =IFERROR(AD30*(1+변수!AF37),"") | AG30: =IFERROR(AF30*(1+변수!AG37),"") | AH30: =IFERROR(AG30*(1+변수!AH37),"") | AI30: =IFERROR(AH30*(1+변수!AI37),"") | AJ30: =AI30 | AK30: =IFERROR(AI30*(1+변수!AK37),"") | AL30: =IFERROR(AK30*(1+변수!AL37),"") | AM30: =IFERROR(AL30*(1+변수!AM37),"") | AN30: =IFERROR(AM30*(1+변수!AN37),"") | AO30: =AN30
A31: 현금및현금성자산 | B31: 재무상태 | C31: 억원 | D31: 현금및현금성자산 | E31: =IFERROR(VLOOKUP($D31,BS연결,MATCH(E$1,BS연결H,0),0)/100,"") | F31: =IFERROR(VLOOKUP($D31,BS연결,MATCH(F$1,BS연결H,0),0)/100,"") | G31: =IFERROR(VLOOKUP($D31,BS연결,MATCH(G$1,BS연결H,0),0)/100,"") | H31: =IFERROR(VLOOKUP($D31,BS연결,MATCH(H$1,BS연결H,0),0)/100,"") | I31: =IFERROR(VLOOKUP($D31,BS연결,MATCH(I$1,BS연결H,0),0)/100,"") | J31: =IFERROR(VLOOKUP($D31,BS연결,MATCH(J$1,BS연결H,0),0)/100,"") | K31: =IFERROR(VLOOKUP($D31,BS연결,MATCH(K$1,BS연결H,0),0)/100,"") | L31: =IFERROR(VLOOKUP($D31,BS연결,MATCH(L$1,BS연결H,0),0)/100,"") | ... AB31: =IFERROR(VLOOKUP($D31,BS연결,MATCH(AB$1,BS연결H,0),0)/100,"") | AE31: =AD31 | AJ31: =AI31 | AO31: =AN31
A32: CAPEX | B32: 현금흐름 | C32: 억원 | D32: CAPEX | E32: =IFERROR(VLOOKUP($D32,BS연결,MATCH(E$1,BS연결H,0),0)/100,"") | G32: =IFERROR(VLOOKUP($D32,BS연결,MATCH(G$1,BS연결H,0),0)/100,"") | H32: =IFERROR(VLOOKUP($D32,BS연결,MATCH(H$1,BS연결H,0),0)/100,"") | I32: =IFERROR(VLOOKUP($D32,BS연결,MATCH(I$1,BS연결H,0),0)/100,"") | J32: =IFERROR(VLOOKUP($D32,BS연결,MATCH(J$1,BS연결H,0),0)/100,"") | K32: =IFERROR(VLOOKUP($D32,BS연결,MATCH(K$1,BS연결H,0),0)/100,"") | L32: =IFERROR(VLOOKUP($D32,BS연결,MATCH(L$1,BS연결H,0),0)/100,"") | M32: =IFERROR(VLOOKUP($D32,BS연결,MATCH(M$1,BS연결H,0),0)/100,"") | N32: =IFERROR(VLOOKUP($D32,BS연결,MATCH(N$1,BS연결H,0),0)/100,"") | ... AB32: =IFERROR(VLOOKUP($D32,BS연결,MATCH(AB$1,BS연결H,0),0)/100,"") | AC32: =IFERROR(X32*(1+변수!AC39),"") | AD32: =IFERROR(Y32*(1+변수!AD39),"") | AE32: =SUM(AA32:AD32) | AF32: =IFERROR(AA32*(1+변수!AF39),"") | AG32: =IFERROR(AB32*(1+변수!AG39),"") | AH32: =IFERROR(AC32*(1+변수!AH39),"") | AI32: =IFERROR(AD32*(1+변수!AI39),"") | AJ32: =SUM(AF32:AI32) | AK32: =IFERROR(AF32*(1+변수!AK39),"") | AL32: =IFERROR(AG32*(1+변수!AL39),"") | AM32: =IFERROR(AH32*(1+변수!AM39),"") | AN32: =IFERROR(AI32*(1+변수!AN39),"") | AO32: =SUM(AK32:AN32)
A33: 영업활동현금흐름 | B33: 현금흐름 | C33: 억원 | D33: 영업활동으로인한현금흐름 | E33: =IFERROR(VLOOKUP($D33,BS연결,MATCH(E$1,BS연결H,0),0)/100,"") | G33: =IFERROR(VLOOKUP($D33,BS연결,MATCH(G$1,BS연결H,0),0)/100,"") | H33: =IFERROR(VLOOKUP($D33,BS연결,MATCH(H$1,BS연결H,0),0)/100,"") | I33: =IFERROR(VLOOKUP($D33,BS연결,MATCH(I$1,BS연결H,0),0)/100,"") | J33: =IFERROR(VLOOKUP($D33,BS연결,MATCH(J$1,BS연결H,0),0)/100,"") | K33: =IFERROR(VLOOKUP($D33,BS연결,MATCH(K$1,BS연결H,0),0)/100,"") | L33: =IFERROR(VLOOKUP($D33,BS연결,MATCH(L$1,BS연결H,0),0)/100,"") | M33: =IFERROR(VLOOKUP($D33,BS연결,MATCH(M$1,BS연결H,0),0)/100,"") | N33: =IFERROR(VLOOKUP($D33,BS연결,MATCH(N$1,BS연결H,0),0)/100,"") | ... AB33: =IFERROR(VLOOKUP($D33,BS연결,MATCH(AB$1,BS연결H,0),0)/100,"") | AE33: =SUM(AA33:AD33) | AJ33: =SUM(AF33:AI33) | AO33: =SUM(AK33:AN33)
A34: 주식수 | B34: 주당 | C34: 백만주 | D34: 유통주식수 | E34: 45.90424 | F34: =E34 | G34: 46.658525 | H34: 46.658525 | I34: 46.658525 | J34: 46.658525 | K34: =J34 | L34: 46.658525 | M34: 46.658525 | N34: 45.758525 | O34: 45.336365 | P34: =O34 | Q34: 45.336365 | R34: 48.078665 | S34: 48.078665 | T34: 46.615415 | U34: =T34 | V34: 46.370415 | W34: 46.190235 | X34: 46.16441 | Y34: 46.16441 | Z34: =Y34 | AA34: 45.87941 | AB34: 45.695 | AC34: =IFERROR(AB34*(1+변수!AC41),"") | AD34: =IFERROR(AC34*(1+변수!AD41),"") | AE34: =AD34 | AF34: =IFERROR(AD34*(1+변수!AF41),"") | AG34: =IFERROR(AF34*(1+변수!AG41),"") | AH34: =IFERROR(AG34*(1+변수!AH41),"") | AI34: =IFERROR(AH34*(1+변수!AI41),"") | AJ34: =AI34 | AK34: =IFERROR(AI34*(1+변수!AK41),"") | AL34: =IFERROR(AK34*(1+변수!AL41),"") | AM34: =IFERROR(AL34*(1+변수!AM41),"") | AN34: =IFERROR(AM34*(1+변수!AN41),"") | AO34: =AN34
A35: EPS | B35: 주당 | C35: 원 | D35: EPS | E35: =IFERROR(E20*100/E34,"") | G35: =IFERROR(G20*100/G34,"") | H35: =IFERROR(H20*100/H34,"") | I35: =IFERROR(I20*100/I34,"") | J35: =IFERROR(J20*100/J34,"") | K35: =SUM(G35:J35) | L35: =IFERROR(L20*100/L34,"") | M35: =IFERROR(M20*100/M34,"") | N35: =IFERROR(N20*100/N34,"") | O35: =IFERROR(O20*100/O34,"") | P35: =SUM(L35:O35) | Q35: =IFERROR(Q20*100/Q34,"") | R35: =IFERROR(R20*100/R34,"") | S35: =IFERROR(S20*100/S34,"") | T35: =IFERROR(T20*100/T34,"") | U35: =SUM(Q35:T35) | V35: =IFERROR(V20*100/V34,"") | W35: =IFERROR(W20*100/W34,"") | X35: =IFERROR(X20*100/X34,"") | Y35: =IFERROR(Y20*100/Y34,"") | Z35: =SUM(V35:Y35) | AA35: =IFERROR(AA20*100/AA34,"") | AB35: =IFERROR(AB20*100/AB34,"") | AC35: =IFERROR(AC20*100/AC34,"") | AD35: =IFERROR(AD20*100/AD34,"") | AE35: =SUM(AA35:AD35) | AF35: =IFERROR(AF20*100/AF34,"") | AG35: =IFERROR(AG20*100/AG34,"") | AH35: =IFERROR(AH20*100/AH34,"") | AI35: =IFERROR(AI20*100/AI34,"") | AJ35: =SUM(AF35:AI35) | AK35: =IFERROR(AK20*100/AK34,"") | AL35: =IFERROR(AL20*100/AL34,"") | AM35: =IFERROR(AM20*100/AM34,"") | AN35: =IFERROR(AN20*100/AN34,"") | AO35: =SUM(AK35:AN35)
A36: BPS | B36: 주당 | C36: 원 | D36: BPS | E36: =IFERROR(E27*100/E34,"") | F36: =E36 | G36: =IFERROR(G27*100/G34,"") | H36: =IFERROR(H27*100/H34,"") | I36: =IFERROR(I27*100/I34,"") | J36: =IFERROR(J27*100/J34,"") | K36: =J36 | L36: =IFERROR(L27*100/L34,"") | M36: =IFERROR(M27*100/M34,"") | N36: =IFERROR(N27*100/N34,"") | O36: =IFERROR(O27*100/O34,"") | P36: =O36 | Q36: =IFERROR(Q27*100/Q34,"") | R36: =IFERROR(R27*100/R34,"") | S36: =IFERROR(S27*100/S34,"") | T36: =IFERROR(T27*100/T34,"") | U36: =T36 | V36: =IFERROR(V27*100/V34,"") | W36: =IFERROR(W27*100/W34,"") | X36: =IFERROR(X27*100/X34,"") | Y36: =IFERROR(Y27*100/Y34,"") | Z36: =Y36 | AA36: =IFERROR(AA27*100/AA34,"") | AB36: =IFERROR(AB27*100/AB34,"") | AC36: =IFERROR(AC27*100/AC34,"") | AD36: =IFERROR(AD27*100/AD34,"") | AE36: =AD36 | AF36: =IFERROR(AF27*100/AF34,"") | AG36: =IFERROR(AG27*100/AG34,"") | AH36: =IFERROR(AH27*100/AH34,"") | AI36: =IFERROR(AI27*100/AI34,"") | AJ36: =AI36 | AK36: =IFERROR(AK27*100/AK34,"") | AL36: =IFERROR(AL27*100/AL34,"") | AM36: =IFERROR(AM27*100/AM34,"") | AN36: =IFERROR(AN27*100/AN34,"") | AO36: =AN36
A37: DPS | B37: 주당 | C37: 원 | D37: DPS(보통주) | E37: 0 | F37: 0 | J37: 0 | K37: =SUM(G37:J37) | O37: 450 | P37: =SUM(L37:O37) | T37: 140 | U37: =SUM(Q37:T37) | Y37: 150 | Z37: =SUM(V37:Y37) | AD37: =변수!AD42 | AE37: =SUM(AA37:AD37) | AI37: =변수!AI42 | AJ37: =SUM(AF37:AI37) | AN37: =변수!AN42 | AO37: =SUM(AK37:AN37)
A38: PER | B38: 주당 | C38: 배 | D38: PER | F38: =E38 | K38: =J38 | O38: =IFERROR(변수!O18/(L35+M35+N35+O35),"") | P38: =O38 | Q38: =IFERROR(변수!Q18/(M35+N35+O35+Q35),"") | R38: =IFERROR(변수!R18/(N35+O35+Q35+R35),"") | S38: =IFERROR(변수!S18/(O35+Q35+R35+S35),"") | T38: =IFERROR(변수!T18/(Q35+R35+S35+T35),"") | U38: =T38 | W38: =IFERROR(변수!W18/(S35+T35+V35+W35),"") | X38: =IFERROR(변수!X18/(T35+V35+W35+X35),"") | Y38: =IFERROR(변수!Y18/(V35+W35+X35+Y35),"") | Z38: =Y38 | AA38: =IFERROR(변수!AA18/(W35+X35+Y35+AA35),"") | AB38: =IFERROR(변수!AB18/(X35+Y35+AA35+AB35),"") | AC38: =IFERROR(변수!$D$45/(Y35+AA35+AB35+AC35),"") | AD38: =IFERROR(변수!$D$45/(AA35+AB35+AC35+AD35),"") | AE38: =AD38 | AF38: =IFERROR(변수!$D$45/(AB35+AC35+AD35+AF35),"") | AG38: =IFERROR(변수!$D$45/(AC35+AD35+AF35+AG35),"") | AH38: =IFERROR(변수!$D$45/(AD35+AF35+AG35+AH35),"") | AI38: =IFERROR(변수!$D$45/(AF35+AG35+AH35+AI35),"") | AJ38: =AI38 | AK38: =IFERROR(변수!$D$45/(AG35+AH35+AI35+AK35),"") | AL38: =IFERROR(변수!$D$45/(AH35+AI35+AK35+AL35),"") | AM38: =IFERROR(변수!$D$45/(AI35+AK35+AL35+AM35),"") | AN38: =IFERROR(변수!$D$45/(AK35+AL35+AM35+AN35),"") | AO38: =AN38
A39: PBR | B39: 주당 | C39: 배 | D39: PBR | E39: =IFERROR(변수!E18/E36,"") | F39: =E39 | G39: =IFERROR(변수!G18/G36,"") | H39: =IFERROR(변수!H18/H36,"") | I39: =IFERROR(변수!I18/I36,"") | J39: =IFERROR(변수!J18/J36,"") | K39: =J39 | L39: =IFERROR(변수!L18/L36,"") | M39: =IFERROR(변수!M18/M36,"") | N39: =IFERROR(변수!N18/N36,"") | O39: =IFERROR(변수!O18/O36,"") | P39: =O39 | Q39: =IFERROR(변수!Q18/Q36,"") | R39: =IFERROR(변수!R18/R36,"") | S39: =IFERROR(변수!S18/S36,"") | T39: =IFERROR(변수!T18/T36,"") | U39: =T39 | V39: =IFERROR(변수!V18/V36,"") | W39: =IFERROR(변수!W18/W36,"") | X39: =IFERROR(변수!X18/X36,"") | Y39: =IFERROR(변수!Y18/Y36,"") | Z39: =Y39 | AA39: =IFERROR(변수!AA18/AA36,"") | AB39: =IFERROR(변수!AB18/AB36,"") | AC39: =IFERROR(변수!$D$45/AC36,"") | AD39: =IFERROR(변수!$D$45/AD36,"") | AE39: =AD39 | AF39: =IFERROR(변수!$D$45/AF36,"") | AG39: =IFERROR(변수!$D$45/AG36,"") | AH39: =IFERROR(변수!$D$45/AH36,"") | AI39: =IFERROR(변수!$D$45/AI36,"") | AJ39: =AI39 | AK39: =IFERROR(변수!$D$45/AK36,"") | AL39: =IFERROR(변수!$D$45/AL36,"") | AM39: =IFERROR(변수!$D$45/AM36,"") | AN39: =IFERROR(변수!$D$45/AN36,"") | AO39: =AN39
A40: 매출전사 | B40: 사업부 | C40: 억원 | D40: 매출 전사(부문 미분리) | E40: 361.4 | G40: 396.52 | H40: 317.35 | I40: 355.61 | J40: 414.43 | K40: =SUM(G40:J40) | L40: 326.94 | M40: 323.09 | N40: 336.18 | O40: 53.3 | P40: =SUM(L40:O40) | Q40: 217.69 | R40: 254.99 | S40: 205.68 | T40: 249.49 | U40: =SUM(Q40:T40) | V40: 285.21 | W40: 251.62 | X40: 287.95 | Y40: 254.8 | Z40: =SUM(V40:Y40) | AA40: 259.87 | AB40: 318.3 | AC40: =IFERROR(AC5,"") | AD40: =IFERROR(AD5,"") | AE40: =SUM(AA40:AD40) | AF40: =IFERROR(AF5,"") | AG40: =IFERROR(AG5,"") | AH40: =IFERROR(AH5,"") | AI40: =IFERROR(AI5,"") | AJ40: =SUM(AF40:AI40) | AK40: =IFERROR(AK5,"") | AL40: =IFERROR(AL5,"") | AM40: =IFERROR(AM5,"") | AN40: =IFERROR(AN5,"") | AO40: =SUM(AK40:AN40)
A41: OP전사 | B41: 사업부 | C41: 억원 | D41: OP 전사(부문 미분리) | E41: 32.94 | G41: 26.42 | H41: 24.16 | I41: 19.06 | J41: 29.21 | K41: =SUM(G41:J41) | L41: 14.5 | M41: 17.67 | N41: 17.85 | O41: -1.16 | P41: =SUM(L41:O41) | Q41: 11.51 | R41: 45.62 | S41: 11.89 | T41: 33.59 | U41: =SUM(Q41:T41) | V41: 26.59 | W41: 44.09 | X41: 48.65 | Y41: 36.01 | Z41: =SUM(V41:Y41) | AA41: 41.62 | AB41: 51.34 | AC41: =IFERROR(AC9,"") | AD41: =IFERROR(AD9,"") | AE41: =SUM(AA41:AD41) | AF41: =IFERROR(AF9,"") | AG41: =IFERROR(AG9,"") | AH41: =IFERROR(AH9,"") | AI41: =IFERROR(AI9,"") | AJ41: =SUM(AF41:AI41) | AK41: =IFERROR(AK9,"") | AL41: =IFERROR(AL9,"") | AM41: =IFERROR(AM9,"") | AN41: =IFERROR(AN9,"") | AO41: =SUM(AK41:AN41)
B42: 비율(참고)
A43: NPM | C43: % | D43: 지배주주순이익 / 매출액 | E43: =IFERROR(E20/E5,"") | F43: =IFERROR(F20/F5,"") | G43: =IFERROR(G20/G5,"") | H43: =IFERROR(H20/H5,"") | I43: =IFERROR(I20/I5,"") | J43: =IFERROR(J20/J5,"") | K43: =IFERROR(K20/K5,"") | L43: =IFERROR(L20/L5,"") | ... AO43: =IFERROR(AO20/AO5,"")
A44: 매출원가율 | C44: % | D44: 매출원가 / 매출액 | E44: =IFERROR(E6/E5,"") | F44: =IFERROR(F6/F5,"") | G44: =IFERROR(G6/G5,"") | H44: =IFERROR(H6/H5,"") | I44: =IFERROR(I6/I5,"") | J44: =IFERROR(J6/J5,"") | K44: =IFERROR(K6/K5,"") | L44: =IFERROR(L6/L5,"") | ... AO44: =IFERROR(AO6/AO5,"")
A45: 판관비율 | C45: % | D45: 판관비 / 매출액 | E45: =IFERROR(E8/E5,"") | F45: =IFERROR(F8/F5,"") | G45: =IFERROR(G8/G5,"") | H45: =IFERROR(H8/H5,"") | I45: =IFERROR(I8/I5,"") | J45: =IFERROR(J8/J5,"") | K45: =IFERROR(K8/K5,"") | L45: =IFERROR(L8/L5,"") | ... AO45: =IFERROR(AO8/AO5,"")

Sheet 분기
C1: 이름: 분기H — subQ 를 이름으로 VLOOKUP(억원) | E1: 4Q21 | F1: 1Q22 | G1: 2Q22 | H1: 3Q22 | I1: 4Q22 | J1: 1Q23 | K1: 2Q23 | L1: 3Q23 | M1: 4Q23 | N1: 1Q24 | O1: 2Q24 | P1: 3Q24 | Q1: 4Q24 | R1: 1Q25 | S1: 2Q25 | T1: 3Q25 | U1: 4Q25 | V1: 1Q26 | W1: 2Q26 | X1: 3Q26 | Y1: 4Q26 | Z1: 1Q27 | AA1: 2Q27 | AB1: 3Q27 | AC1: 4Q27 | AD1: 1Q28 | AE1: 2Q28 | AF1: 3Q28 | AG1: 4Q28
C2: 종가: | D2: =변수!D45
C3: 기준일: | D3: 20261026 | E3: 1 | F3: 2 | G3: 3 | H3: 4 | I3: 5 | J3: 6 | K3: 7 | L3: 8 | M3: 9 | N3: 10 | O3: 11 | P3: 12 | Q3: 13 | R3: 14 | S3: 15 | T3: 16 | U3: 17 | V3: 18 | W3: 19 | X3: 20 | Y3: 21 | Z3: 22 | AA3: 23 | AB3: 24 | AC3: 25 | AD3: 26 | AE3: 27 | AF3: 28 | AG3: 29
E4: 2021.12 | F4: 2022.03 | G4: 2022.06 | H4: 2022.09 | I4: 2022.12 | J4: 2023.03 | K4: 2023.06 | L4: 2023.09 | M4: 2023.12 | N4: 2024.03 | O4: 2024.06 | P4: 2024.09 | Q4: 2024.12 | R4: 2025.03 | S4: 2025.06 | T4: 2025.09 | U4: 2025.12 | V4: 2026.03 | W4: 2026.06 | X4: 2026.09 | Y4: 2026.12 | Z4: 2027.03 | AA4: 2027.06 | AB4: 2027.09 | AC4: 2027.12 | AD4: 2028.03 | AE4: 2028.06 | AF4: 2028.09 | AG4: 2028.12
A5: 매출액 | D5: 매출액 | E5: =IFERROR(VLOOKUP($A5,subQ,MATCH(E$1,SUBQH,0),0),"") | F5: =IFERROR(VLOOKUP($A5,subQ,MATCH(F$1,SUBQH,0),0),"") | G5: =IFERROR(VLOOKUP($A5,subQ,MATCH(G$1,SUBQH,0),0),"") | H5: =IFERROR(VLOOKUP($A5,subQ,MATCH(H$1,SUBQH,0),0),"") | I5: =IFERROR(VLOOKUP($A5,subQ,MATCH(I$1,SUBQH,0),0),"") | J5: =IFERROR(VLOOKUP($A5,subQ,MATCH(J$1,SUBQH,0),0),"") | K5: =IFERROR(VLOOKUP($A5,subQ,MATCH(K$1,SUBQH,0),0),"") | L5: =IFERROR(VLOOKUP($A5,subQ,MATCH(L$1,SUBQH,0),0),"") | ... AG5: =IFERROR(VLOOKUP($A5,subQ,MATCH(AG$1,SUBQH,0),0),"")
A6: 매출원가 | D6: 매출원가 | E6: =IFERROR(VLOOKUP($A6,subQ,MATCH(E$1,SUBQH,0),0),"") | F6: =IFERROR(VLOOKUP($A6,subQ,MATCH(F$1,SUBQH,0),0),"") | G6: =IFERROR(VLOOKUP($A6,subQ,MATCH(G$1,SUBQH,0),0),"") | H6: =IFERROR(VLOOKUP($A6,subQ,MATCH(H$1,SUBQH,0),0),"") | I6: =IFERROR(VLOOKUP($A6,subQ,MATCH(I$1,SUBQH,0),0),"") | J6: =IFERROR(VLOOKUP($A6,subQ,MATCH(J$1,SUBQH,0),0),"") | K6: =IFERROR(VLOOKUP($A6,subQ,MATCH(K$1,SUBQH,0),0),"") | L6: =IFERROR(VLOOKUP($A6,subQ,MATCH(L$1,SUBQH,0),0),"") | ... AG6: =IFERROR(VLOOKUP($A6,subQ,MATCH(AG$1,SUBQH,0),0),"")
A7: 매출총이익 | D7: 매출총이익 | E7: =IFERROR(VLOOKUP($A7,subQ,MATCH(E$1,SUBQH,0),0),"") | F7: =IFERROR(VLOOKUP($A7,subQ,MATCH(F$1,SUBQH,0),0),"") | G7: =IFERROR(VLOOKUP($A7,subQ,MATCH(G$1,SUBQH,0),0),"") | H7: =IFERROR(VLOOKUP($A7,subQ,MATCH(H$1,SUBQH,0),0),"") | I7: =IFERROR(VLOOKUP($A7,subQ,MATCH(I$1,SUBQH,0),0),"") | J7: =IFERROR(VLOOKUP($A7,subQ,MATCH(J$1,SUBQH,0),0),"") | K7: =IFERROR(VLOOKUP($A7,subQ,MATCH(K$1,SUBQH,0),0),"") | L7: =IFERROR(VLOOKUP($A7,subQ,MATCH(L$1,SUBQH,0),0),"") | ... AG7: =IFERROR(VLOOKUP($A7,subQ,MATCH(AG$1,SUBQH,0),0),"")
A8: 판관비 | D8: 판매비와관리비 | E8: =IFERROR(VLOOKUP($A8,subQ,MATCH(E$1,SUBQH,0),0),"") | F8: =IFERROR(VLOOKUP($A8,subQ,MATCH(F$1,SUBQH,0),0),"") | G8: =IFERROR(VLOOKUP($A8,subQ,MATCH(G$1,SUBQH,0),0),"") | H8: =IFERROR(VLOOKUP($A8,subQ,MATCH(H$1,SUBQH,0),0),"") | I8: =IFERROR(VLOOKUP($A8,subQ,MATCH(I$1,SUBQH,0),0),"") | J8: =IFERROR(VLOOKUP($A8,subQ,MATCH(J$1,SUBQH,0),0),"") | K8: =IFERROR(VLOOKUP($A8,subQ,MATCH(K$1,SUBQH,0),0),"") | L8: =IFERROR(VLOOKUP($A8,subQ,MATCH(L$1,SUBQH,0),0),"") | ... AG8: =IFERROR(VLOOKUP($A8,subQ,MATCH(AG$1,SUBQH,0),0),"")
A9: 영업이익 | D9: 영업이익 | E9: =IFERROR(VLOOKUP($A9,subQ,MATCH(E$1,SUBQH,0),0),"") | F9: =IFERROR(VLOOKUP($A9,subQ,MATCH(F$1,SUBQH,0),0),"") | G9: =IFERROR(VLOOKUP($A9,subQ,MATCH(G$1,SUBQH,0),0),"") | H9: =IFERROR(VLOOKUP($A9,subQ,MATCH(H$1,SUBQH,0),0),"") | I9: =IFERROR(VLOOKUP($A9,subQ,MATCH(I$1,SUBQH,0),0),"") | J9: =IFERROR(VLOOKUP($A9,subQ,MATCH(J$1,SUBQH,0),0),"") | K9: =IFERROR(VLOOKUP($A9,subQ,MATCH(K$1,SUBQH,0),0),"") | L9: =IFERROR(VLOOKUP($A9,subQ,MATCH(L$1,SUBQH,0),0),"") | ... AG9: =IFERROR(VLOOKUP($A9,subQ,MATCH(AG$1,SUBQH,0),0),"")
A10: OPM | D10: 영업이익률 | E10: =IFERROR(VLOOKUP($A10,subQ,MATCH(E$1,SUBQH,0),0),"") | F10: =IFERROR(VLOOKUP($A10,subQ,MATCH(F$1,SUBQH,0),0),"") | G10: =IFERROR(VLOOKUP($A10,subQ,MATCH(G$1,SUBQH,0),0),"") | H10: =IFERROR(VLOOKUP($A10,subQ,MATCH(H$1,SUBQH,0),0),"") | I10: =IFERROR(VLOOKUP($A10,subQ,MATCH(I$1,SUBQH,0),0),"") | J10: =IFERROR(VLOOKUP($A10,subQ,MATCH(J$1,SUBQH,0),0),"") | K10: =IFERROR(VLOOKUP($A10,subQ,MATCH(K$1,SUBQH,0),0),"") | L10: =IFERROR(VLOOKUP($A10,subQ,MATCH(L$1,SUBQH,0),0),"") | ... AG10: =IFERROR(VLOOKUP($A10,subQ,MATCH(AG$1,SUBQH,0),0),"")
A11: 금융손익 | D11: 금융손익(이자·환 포함) | E11: =IFERROR(VLOOKUP($A11,subQ,MATCH(E$1,SUBQH,0),0),"") | F11: =IFERROR(VLOOKUP($A11,subQ,MATCH(F$1,SUBQH,0),0),"") | G11: =IFERROR(VLOOKUP($A11,subQ,MATCH(G$1,SUBQH,0),0),"") | H11: =IFERROR(VLOOKUP($A11,subQ,MATCH(H$1,SUBQH,0),0),"") | I11: =IFERROR(VLOOKUP($A11,subQ,MATCH(I$1,SUBQH,0),0),"") | J11: =IFERROR(VLOOKUP($A11,subQ,MATCH(J$1,SUBQH,0),0),"") | K11: =IFERROR(VLOOKUP($A11,subQ,MATCH(K$1,SUBQH,0),0),"") | L11: =IFERROR(VLOOKUP($A11,subQ,MATCH(L$1,SUBQH,0),0),"") | ... AG11: =IFERROR(VLOOKUP($A11,subQ,MATCH(AG$1,SUBQH,0),0),"")
A12: 이자손익 | D12: 이자손익(이자수익 − 이자비용) | E12: =IFERROR(VLOOKUP($A12,subQ,MATCH(E$1,SUBQH,0),0),"") | F12: =IFERROR(VLOOKUP($A12,subQ,MATCH(F$1,SUBQH,0),0),"") | G12: =IFERROR(VLOOKUP($A12,subQ,MATCH(G$1,SUBQH,0),0),"") | H12: =IFERROR(VLOOKUP($A12,subQ,MATCH(H$1,SUBQH,0),0),"") | I12: =IFERROR(VLOOKUP($A12,subQ,MATCH(I$1,SUBQH,0),0),"") | J12: =IFERROR(VLOOKUP($A12,subQ,MATCH(J$1,SUBQH,0),0),"") | K12: =IFERROR(VLOOKUP($A12,subQ,MATCH(K$1,SUBQH,0),0),"") | L12: =IFERROR(VLOOKUP($A12,subQ,MATCH(L$1,SUBQH,0),0),"") | ... AG12: =IFERROR(VLOOKUP($A12,subQ,MATCH(AG$1,SUBQH,0),0),"")
A13: 파생상품손익 | D13: 파생상품손익 | E13: =IFERROR(VLOOKUP($A13,subQ,MATCH(E$1,SUBQH,0),0),"") | F13: =IFERROR(VLOOKUP($A13,subQ,MATCH(F$1,SUBQH,0),0),"") | G13: =IFERROR(VLOOKUP($A13,subQ,MATCH(G$1,SUBQH,0),0),"") | H13: =IFERROR(VLOOKUP($A13,subQ,MATCH(H$1,SUBQH,0),0),"") | I13: =IFERROR(VLOOKUP($A13,subQ,MATCH(I$1,SUBQH,0),0),"") | J13: =IFERROR(VLOOKUP($A13,subQ,MATCH(J$1,SUBQH,0),0),"") | K13: =IFERROR(VLOOKUP($A13,subQ,MATCH(K$1,SUBQH,0),0),"") | L13: =IFERROR(VLOOKUP($A13,subQ,MATCH(L$1,SUBQH,0),0),"") | ... AG13: =IFERROR(VLOOKUP($A13,subQ,MATCH(AG$1,SUBQH,0),0),"")
A14: 기타금융손익 | D14: 기타금융손익(금융손익 잔차) | E14: =IFERROR(VLOOKUP($A14,subQ,MATCH(E$1,SUBQH,0),0),"") | F14: =IFERROR(VLOOKUP($A14,subQ,MATCH(F$1,SUBQH,0),0),"") | G14: =IFERROR(VLOOKUP($A14,subQ,MATCH(G$1,SUBQH,0),0),"") | H14: =IFERROR(VLOOKUP($A14,subQ,MATCH(H$1,SUBQH,0),0),"") | I14: =IFERROR(VLOOKUP($A14,subQ,MATCH(I$1,SUBQH,0),0),"") | J14: =IFERROR(VLOOKUP($A14,subQ,MATCH(J$1,SUBQH,0),0),"") | K14: =IFERROR(VLOOKUP($A14,subQ,MATCH(K$1,SUBQH,0),0),"") | L14: =IFERROR(VLOOKUP($A14,subQ,MATCH(L$1,SUBQH,0),0),"") | ... AG14: =IFERROR(VLOOKUP($A14,subQ,MATCH(AG$1,SUBQH,0),0),"")
A15: 기타영업외손익 | D15: 기타영업외손익 | E15: =IFERROR(VLOOKUP($A15,subQ,MATCH(E$1,SUBQH,0),0),"") | F15: =IFERROR(VLOOKUP($A15,subQ,MATCH(F$1,SUBQH,0),0),"") | G15: =IFERROR(VLOOKUP($A15,subQ,MATCH(G$1,SUBQH,0),0),"") | H15: =IFERROR(VLOOKUP($A15,subQ,MATCH(H$1,SUBQH,0),0),"") | I15: =IFERROR(VLOOKUP($A15,subQ,MATCH(I$1,SUBQH,0),0),"") | J15: =IFERROR(VLOOKUP($A15,subQ,MATCH(J$1,SUBQH,0),0),"") | K15: =IFERROR(VLOOKUP($A15,subQ,MATCH(K$1,SUBQH,0),0),"") | L15: =IFERROR(VLOOKUP($A15,subQ,MATCH(L$1,SUBQH,0),0),"") | ... AG15: =IFERROR(VLOOKUP($A15,subQ,MATCH(AG$1,SUBQH,0),0),"")
A16: 지분법손익 | D16: 지분법손익 | E16: =IFERROR(VLOOKUP($A16,subQ,MATCH(E$1,SUBQH,0),0),"") | F16: =IFERROR(VLOOKUP($A16,subQ,MATCH(F$1,SUBQH,0),0),"") | G16: =IFERROR(VLOOKUP($A16,subQ,MATCH(G$1,SUBQH,0),0),"") | H16: =IFERROR(VLOOKUP($A16,subQ,MATCH(H$1,SUBQH,0),0),"") | I16: =IFERROR(VLOOKUP($A16,subQ,MATCH(I$1,SUBQH,0),0),"") | J16: =IFERROR(VLOOKUP($A16,subQ,MATCH(J$1,SUBQH,0),0),"") | K16: =IFERROR(VLOOKUP($A16,subQ,MATCH(K$1,SUBQH,0),0),"") | L16: =IFERROR(VLOOKUP($A16,subQ,MATCH(L$1,SUBQH,0),0),"") | ... AG16: =IFERROR(VLOOKUP($A16,subQ,MATCH(AG$1,SUBQH,0),0),"")
... A42: NPM | D42: NPM | E42: =IFERROR(VLOOKUP($A42,subQ,MATCH(E$1,SUBQH,0),0),"") | F42: =IFERROR(VLOOKUP($A42,subQ,MATCH(F$1,SUBQH,0),0),"") | G42: =IFERROR(VLOOKUP($A42,subQ,MATCH(G$1,SUBQH,0),0),"") | H42: =IFERROR(VLOOKUP($A42,subQ,MATCH(H$1,SUBQH,0),0),"") | I42: =IFERROR(VLOOKUP($A42,subQ,MATCH(I$1,SUBQH,0),0),"") | J42: =IFERROR(VLOOKUP($A42,subQ,MATCH(J$1,SUBQH,0),0),"") | K42: =IFERROR(VLOOKUP($A42,subQ,MATCH(K$1,SUBQH,0),0),"") | L42: =IFERROR(VLOOKUP($A42,subQ,MATCH(L$1,SUBQH,0),0),"") | ... AG42: =IFERROR(VLOOKUP($A42,subQ,MATCH(AG$1,SUBQH,0),0),"")
A43: 매출액 YoY | D43: 매출액 YoY | I43: =IFERROR(I5/E5-1,"") | J43: =IFERROR(J5/F5-1,"") | K43: =IFERROR(K5/G5-1,"") | L43: =IFERROR(L5/H5-1,"") | M43: =IFERROR(M5/I5-1,"") | N43: =IFERROR(N5/J5-1,"") | O43: =IFERROR(O5/K5-1,"") | P43: =IFERROR(P5/L5-1,"") | ... AG43: =IFERROR(AG5/AC5-1,"")
A44: 영업이익 YoY | D44: 영업이익 YoY | I44: =IFERROR(I9/E9-1,"") | J44: =IFERROR(J9/F9-1,"") | K44: =IFERROR(K9/G9-1,"") | L44: =IFERROR(L9/H9-1,"") | M44: =IFERROR(M9/I9-1,"") | N44: =IFERROR(N9/J9-1,"") | O44: =IFERROR(O9/K9-1,"") | P44: =IFERROR(P9/L9-1,"") | ... AG44: =IFERROR(AG9/AC9-1,"")
A45: 지배주주순이익 YoY | D45: 지배주주순이익 YoY | I45: =IFERROR(I20/E20-1,"") | J45: =IFERROR(J20/F20-1,"") | K45: =IFERROR(K20/G20-1,"") | L45: =IFERROR(L20/H20-1,"") | M45: =IFERROR(M20/I20-1,"") | N45: =IFERROR(N20/J20-1,"") | O45: =IFERROR(O20/K20-1,"") | P45: =IFERROR(P20/L20-1,"") | ... AG45: =IFERROR(AG20/AC20-1,"")

Sheet 연간예상
C1: 이름: 연간예상H — subQ 를 이름으로 VLOOKUP(억원) | E1: 2021 | F1: 2022 | G1: 2023 | H1: 2024 | I1: 2025 | J1: 2026 | K1: 2027 | L1: 2028
C2: 종가: | D2: =변수!D45
C3: 기준일: | D3: 20261026 | E3: 1 | F3: 2 | G3: 3 | H3: 4 | I3: 5 | J3: 6 | K3: 7 | L3: 8
E4: 2021.12A | F4: 2022.12A | G4: 2023.12A | H4: 2024.12A | I4: 2025.12A | J4: 2026.12A | K4: 2027.12A | L4: 2028.12A
A5: 매출액 | D5: 매출액 | E5: =IFERROR(VLOOKUP($A5,subQ,MATCH(E$1,SUBQH,0),0),"") | F5: =IFERROR(VLOOKUP($A5,subQ,MATCH(F$1,SUBQH,0),0),"") | G5: =IFERROR(VLOOKUP($A5,subQ,MATCH(G$1,SUBQH,0),0),"") | H5: =IFERROR(VLOOKUP($A5,subQ,MATCH(H$1,SUBQH,0),0),"") | I5: =IFERROR(VLOOKUP($A5,subQ,MATCH(I$1,SUBQH,0),0),"") | J5: =IFERROR(VLOOKUP($A5,subQ,MATCH(J$1,SUBQH,0),0),"") | K5: =IFERROR(VLOOKUP($A5,subQ,MATCH(K$1,SUBQH,0),0),"") | L5: =IFERROR(VLOOKUP($A5,subQ,MATCH(L$1,SUBQH,0),0),"")
A6: 매출원가 | D6: 매출원가 | E6: =IFERROR(VLOOKUP($A6,subQ,MATCH(E$1,SUBQH,0),0),"") | F6: =IFERROR(VLOOKUP($A6,subQ,MATCH(F$1,SUBQH,0),0),"") | G6: =IFERROR(VLOOKUP($A6,subQ,MATCH(G$1,SUBQH,0),0),"") | H6: =IFERROR(VLOOKUP($A6,subQ,MATCH(H$1,SUBQH,0),0),"") | I6: =IFERROR(VLOOKUP($A6,subQ,MATCH(I$1,SUBQH,0),0),"") | J6: =IFERROR(VLOOKUP($A6,subQ,MATCH(J$1,SUBQH,0),0),"") | K6: =IFERROR(VLOOKUP($A6,subQ,MATCH(K$1,SUBQH,0),0),"") | L6: =IFERROR(VLOOKUP($A6,subQ,MATCH(L$1,SUBQH,0),0),"")
A7: 매출총이익 | D7: 매출총이익 | E7: =IFERROR(VLOOKUP($A7,subQ,MATCH(E$1,SUBQH,0),0),"") | F7: =IFERROR(VLOOKUP($A7,subQ,MATCH(F$1,SUBQH,0),0),"") | G7: =IFERROR(VLOOKUP($A7,subQ,MATCH(G$1,SUBQH,0),0),"") | H7: =IFERROR(VLOOKUP($A7,subQ,MATCH(H$1,SUBQH,0),0),"") | I7: =IFERROR(VLOOKUP($A7,subQ,MATCH(I$1,SUBQH,0),0),"") | J7: =IFERROR(VLOOKUP($A7,subQ,MATCH(J$1,SUBQH,0),0),"") | K7: =IFERROR(VLOOKUP($A7,subQ,MATCH(K$1,SUBQH,0),0),"") | L7: =IFERROR(VLOOKUP($A7,subQ,MATCH(L$1,SUBQH,0),0),"")
A8: 판관비 | D8: 판매비와관리비 | E8: =IFERROR(VLOOKUP($A8,subQ,MATCH(E$1,SUBQH,0),0),"") | F8: =IFERROR(VLOOKUP($A8,subQ,MATCH(F$1,SUBQH,0),0),"") | G8: =IFERROR(VLOOKUP($A8,subQ,MATCH(G$1,SUBQH,0),0),"") | H8: =IFERROR(VLOOKUP($A8,subQ,MATCH(H$1,SUBQH,0),0),"") | I8: =IFERROR(VLOOKUP($A8,subQ,MATCH(I$1,SUBQH,0),0),"") | J8: =IFERROR(VLOOKUP($A8,subQ,MATCH(J$1,SUBQH,0),0),"") | K8: =IFERROR(VLOOKUP($A8,subQ,MATCH(K$1,SUBQH,0),0),"") | L8: =IFERROR(VLOOKUP($A8,subQ,MATCH(L$1,SUBQH,0),0),"")
A9: 영업이익 | D9: 영업이익 | E9: =IFERROR(VLOOKUP($A9,subQ,MATCH(E$1,SUBQH,0),0),"") | F9: =IFERROR(VLOOKUP($A9,subQ,MATCH(F$1,SUBQH,0),0),"") | G9: =IFERROR(VLOOKUP($A9,subQ,MATCH(G$1,SUBQH,0),0),"") | H9: =IFERROR(VLOOKUP($A9,subQ,MATCH(H$1,SUBQH,0),0),"") | I9: =IFERROR(VLOOKUP($A9,subQ,MATCH(I$1,SUBQH,0),0),"") | J9: =IFERROR(VLOOKUP($A9,subQ,MATCH(J$1,SUBQH,0),0),"") | K9: =IFERROR(VLOOKUP($A9,subQ,MATCH(K$1,SUBQH,0),0),"") | L9: =IFERROR(VLOOKUP($A9,subQ,MATCH(L$1,SUBQH,0),0),"")
A10: OPM | D10: 영업이익률 | E10: =IFERROR(VLOOKUP($A10,subQ,MATCH(E$1,SUBQH,0),0),"") | F10: =IFERROR(VLOOKUP($A10,subQ,MATCH(F$1,SUBQH,0),0),"") | G10: =IFERROR(VLOOKUP($A10,subQ,MATCH(G$1,SUBQH,0),0),"") | H10: =IFERROR(VLOOKUP($A10,subQ,MATCH(H$1,SUBQH,0),0),"") | I10: =IFERROR(VLOOKUP($A10,subQ,MATCH(I$1,SUBQH,0),0),"") | J10: =IFERROR(VLOOKUP($A10,subQ,MATCH(J$1,SUBQH,0),0),"") | K10: =IFERROR(VLOOKUP($A10,subQ,MATCH(K$1,SUBQH,0),0),"") | L10: =IFERROR(VLOOKUP($A10,subQ,MATCH(L$1,SUBQH,0),0),"")
A11: 금융손익 | D11: 금융손익(이자·환 포함) | E11: =IFERROR(VLOOKUP($A11,subQ,MATCH(E$1,SUBQH,0),0),"") | F11: =IFERROR(VLOOKUP($A11,subQ,MATCH(F$1,SUBQH,0),0),"") | G11: =IFERROR(VLOOKUP($A11,subQ,MATCH(G$1,SUBQH,0),0),"") | H11: =IFERROR(VLOOKUP($A11,subQ,MATCH(H$1,SUBQH,0),0),"") | I11: =IFERROR(VLOOKUP($A11,subQ,MATCH(I$1,SUBQH,0),0),"") | J11: =IFERROR(VLOOKUP($A11,subQ,MATCH(J$1,SUBQH,0),0),"") | K11: =IFERROR(VLOOKUP($A11,subQ,MATCH(K$1,SUBQH,0),0),"") | L11: =IFERROR(VLOOKUP($A11,subQ,MATCH(L$1,SUBQH,0),0),"")
A12: 이자손익 | D12: 이자손익(이자수익 − 이자비용) | E12: =IFERROR(VLOOKUP($A12,subQ,MATCH(E$1,SUBQH,0),0),"") | F12: =IFERROR(VLOOKUP($A12,subQ,MATCH(F$1,SUBQH,0),0),"") | G12: =IFERROR(VLOOKUP($A12,subQ,MATCH(G$1,SUBQH,0),0),"") | H12: =IFERROR(VLOOKUP($A12,subQ,MATCH(H$1,SUBQH,0),0),"") | I12: =IFERROR(VLOOKUP($A12,subQ,MATCH(I$1,SUBQH,0),0),"") | J12: =IFERROR(VLOOKUP($A12,subQ,MATCH(J$1,SUBQH,0),0),"") | K12: =IFERROR(VLOOKUP($A12,subQ,MATCH(K$1,SUBQH,0),0),"") | L12: =IFERROR(VLOOKUP($A12,subQ,MATCH(L$1,SUBQH,0),0),"")
A13: 파생상품손익 | D13: 파생상품손익 | E13: =IFERROR(VLOOKUP($A13,subQ,MATCH(E$1,SUBQH,0),0),"") | F13: =IFERROR(VLOOKUP($A13,subQ,MATCH(F$1,SUBQH,0),0),"") | G13: =IFERROR(VLOOKUP($A13,subQ,MATCH(G$1,SUBQH,0),0),"") | H13: =IFERROR(VLOOKUP($A13,subQ,MATCH(H$1,SUBQH,0),0),"") | I13: =IFERROR(VLOOKUP($A13,subQ,MATCH(I$1,SUBQH,0),0),"") | J13: =IFERROR(VLOOKUP($A13,subQ,MATCH(J$1,SUBQH,0),0),"") | K13: =IFERROR(VLOOKUP($A13,subQ,MATCH(K$1,SUBQH,0),0),"") | L13: =IFERROR(VLOOKUP($A13,subQ,MATCH(L$1,SUBQH,0),0),"")
A14: 기타금융손익 | D14: 기타금융손익(금융손익 잔차) | E14: =IFERROR(VLOOKUP($A14,subQ,MATCH(E$1,SUBQH,0),0),"") | F14: =IFERROR(VLOOKUP($A14,subQ,MATCH(F$1,SUBQH,0),0),"") | G14: =IFERROR(VLOOKUP($A14,subQ,MATCH(G$1,SUBQH,0),0),"") | H14: =IFERROR(VLOOKUP($A14,subQ,MATCH(H$1,SUBQH,0),0),"") | I14: =IFERROR(VLOOKUP($A14,subQ,MATCH(I$1,SUBQH,0),0),"") | J14: =IFERROR(VLOOKUP($A14,subQ,MATCH(J$1,SUBQH,0),0),"") | K14: =IFERROR(VLOOKUP($A14,subQ,MATCH(K$1,SUBQH,0),0),"") | L14: =IFERROR(VLOOKUP($A14,subQ,MATCH(L$1,SUBQH,0),0),"")
A15: 기타영업외손익 | D15: 기타영업외손익 | E15: =IFERROR(VLOOKUP($A15,subQ,MATCH(E$1,SUBQH,0),0),"") | F15: =IFERROR(VLOOKUP($A15,subQ,MATCH(F$1,SUBQH,0),0),"") | G15: =IFERROR(VLOOKUP($A15,subQ,MATCH(G$1,SUBQH,0),0),"") | H15: =IFERROR(VLOOKUP($A15,subQ,MATCH(H$1,SUBQH,0),0),"") | I15: =IFERROR(VLOOKUP($A15,subQ,MATCH(I$1,SUBQH,0),0),"") | J15: =IFERROR(VLOOKUP($A15,subQ,MATCH(J$1,SUBQH,0),0),"") | K15: =IFERROR(VLOOKUP($A15,subQ,MATCH(K$1,SUBQH,0),0),"") | L15: =IFERROR(VLOOKUP($A15,subQ,MATCH(L$1,SUBQH,0),0),"")
A16: 지분법손익 | D16: 지분법손익 | E16: =IFERROR(VLOOKUP($A16,subQ,MATCH(E$1,SUBQH,0),0),"") | F16: =IFERROR(VLOOKUP($A16,subQ,MATCH(F$1,SUBQH,0),0),"") | G16: =IFERROR(VLOOKUP($A16,subQ,MATCH(G$1,SUBQH,0),0),"") | H16: =IFERROR(VLOOKUP($A16,subQ,MATCH(H$1,SUBQH,0),0),"") | I16: =IFERROR(VLOOKUP($A16,subQ,MATCH(I$1,SUBQH,0),0),"") | J16: =IFERROR(VLOOKUP($A16,subQ,MATCH(J$1,SUBQH,0),0),"") | K16: =IFERROR(VLOOKUP($A16,subQ,MATCH(K$1,SUBQH,0),0),"") | L16: =IFERROR(VLOOKUP($A16,subQ,MATCH(L$1,SUBQH,0),0),"")
... A42: NPM | D42: NPM | E42: =IFERROR(VLOOKUP($A42,subQ,MATCH(E$1,SUBQH,0),0),"") | F42: =IFERROR(VLOOKUP($A42,subQ,MATCH(F$1,SUBQH,0),0),"") | G42: =IFERROR(VLOOKUP($A42,subQ,MATCH(G$1,SUBQH,0),0),"") | H42: =IFERROR(VLOOKUP($A42,subQ,MATCH(H$1,SUBQH,0),0),"") | I42: =IFERROR(VLOOKUP($A42,subQ,MATCH(I$1,SUBQH,0),0),"") | J42: =IFERROR(VLOOKUP($A42,subQ,MATCH(J$1,SUBQH,0),0),"") | K42: =IFERROR(VLOOKUP($A42,subQ,MATCH(K$1,SUBQH,0),0),"") | L42: =IFERROR(VLOOKUP($A42,subQ,MATCH(L$1,SUBQH,0),0),"")
A43: 매출액 YoY | D43: 매출액 YoY | F43: =IFERROR(F5/E5-1,"") | G43: =IFERROR(G5/F5-1,"") | H43: =IFERROR(H5/G5-1,"") | I43: =IFERROR(I5/H5-1,"") | J43: =IFERROR(J5/I5-1,"") | K43: =IFERROR(K5/J5-1,"") | L43: =IFERROR(L5/K5-1,"")
A44: 영업이익 YoY | D44: 영업이익 YoY | F44: =IFERROR(F9/E9-1,"") | G44: =IFERROR(G9/F9-1,"") | H44: =IFERROR(H9/G9-1,"") | I44: =IFERROR(I9/H9-1,"") | J44: =IFERROR(J9/I9-1,"") | K44: =IFERROR(K9/J9-1,"") | L44: =IFERROR(L9/K9-1,"")
A45: 지배주주순이익 YoY | D45: 지배주주순이익 YoY | F45: =IFERROR(F20/E20-1,"") | G45: =IFERROR(G20/F20-1,"") | H45: =IFERROR(H20/G20-1,"") | I45: =IFERROR(I20/H20-1,"") | J45: =IFERROR(J20/I20-1,"") | K45: =IFERROR(K20/J20-1,"") | L45: =IFERROR(L20/K20-1,"")

Sheet TP
B1: 종가 | C1: =변수!D45
B2: 기준일 | C2: =변수!D46
B3: 모델 산출값 — 목표주가·추천 아님. 밴드·COE 는 변수 시트 3절의 가정
C5: FY | D5: 2025 | E5: 2026 | F5: 2027 | G5: 2028
D6: A | E6: E | F6: E | G6: E
C7: EPS(원) | D7: =IFERROR(VLOOKUP("EPS",subQ,MATCH(D$5,SUBQH,0),0),"") | E7: =IFERROR(VLOOKUP("EPS",subQ,MATCH(E$5,SUBQH,0),0),"") | F7: =IFERROR(VLOOKUP("EPS",subQ,MATCH(F$5,SUBQH,0),0),"") | G7: =IFERROR(VLOOKUP("EPS",subQ,MATCH(G$5,SUBQH,0),0),"")
C8: BPS(원) | D8: =IFERROR(VLOOKUP("BPS",subQ,MATCH(D$5,SUBQH,0),0),"") | E8: =IFERROR(VLOOKUP("BPS",subQ,MATCH(E$5,SUBQH,0),0),"") | F8: =IFERROR(VLOOKUP("BPS",subQ,MATCH(F$5,SUBQH,0),0),"") | G8: =IFERROR(VLOOKUP("BPS",subQ,MATCH(G$5,SUBQH,0),0),"")
C9: 지배주주순이익(억원) | D9: =IFERROR(VLOOKUP("지배주주순이익",subQ,MATCH(D$5,SUBQH,0),0),"") | E9: =IFERROR(VLOOKUP("지배주주순이익",subQ,MATCH(E$5,SUBQH,0),0),"") | F9: =IFERROR(VLOOKUP("지배주주순이익",subQ,MATCH(F$5,SUBQH,0),0),"") | G9: =IFERROR(VLOOKUP("지배주주순이익",subQ,MATCH(G$5,SUBQH,0),0),"")
C10: 영업이익(억원) | D10: =IFERROR(VLOOKUP("영업이익",subQ,MATCH(D$5,SUBQH,0),0),"") | E10: =IFERROR(VLOOKUP("영업이익",subQ,MATCH(E$5,SUBQH,0),0),"") | F10: =IFERROR(VLOOKUP("영업이익",subQ,MATCH(F$5,SUBQH,0),0),"") | G10: =IFERROR(VLOOKUP("영업이익",subQ,MATCH(G$5,SUBQH,0),0),"")
C11: ROE(EPS/기초BPS) | E11: =IFERROR(E7/D8,"") | F11: =IFERROR(F7/E8,"") | G11: =IFERROR(G7/F8,"")
B13: PER
C14: 12M fwd EPS | D14: =IFERROR(E7*변수!D51+F7*(1-변수!D51),"")
C15: 적정가치 @PER_lo | D15: =변수!D48 | E15: =IFERROR(ROUND($D$14*D15,-2),"") | F15: =IFERROR(E15/$C$1-1,"") | G15: 배 · 원 · 종가 대비
C16: 적정가치 @PER_mid | D16: =변수!D49 | E16: =IFERROR(ROUND($D$14*D16,-2),"") | F16: =IFERROR(E16/$C$1-1,"") | G16: 배 · 원 · 종가 대비
C17: 적정가치 @PER_hi | D17: =변수!D50 | E17: =IFERROR(ROUND($D$14*D17,-2),"") | F17: =IFERROR(E17/$C$1-1,"") | G17: 배 · 원 · 종가 대비
C18: 현재 PER(종가/12M fwd EPS) | D18: =IFERROR($C$1/$D$14,"")
B20: PBR
C21: 최근 BPS(마지막 실적 분기) | D21: =IFERROR(VLOOKUP("BPS",subQ,MATCH("2Q26",SUBQH,0),0),"")
C22: ROE fwd(12M fwd EPS / BPS) | D22: =IFERROR($D$14/$D$21,"")
C23: COE | D23: =변수!D47
C24: 적정 PBR = ROE/COE | D24: =IFERROR(D22/D23,"")
C25: 적정가치(PBR) = BPS × 적정PBR | D25: =IFERROR(ROUND(D21*D24,-2),"") | E25: =IFERROR(D25/$C$1-1,"")
C26: 현재 PBR(종가/BPS) | D26: =IFERROR($C$1/D21,"")
B28: 모델 json valuation(참고)
C29: eps_fwd12m | D29: 665.3
C30: bps_latest | D30: 7776.4
C31: per_now | D31: 9.53
C32: pbr_now | D32: 0.82
C33: roe_fwd | D33: 0.0856
C34: fair_pbr | D34: 0.95
C35: fair_value_pbr | D35: 7400
C36: ev_ebitda | D36: 10.75
C37: note | D37: 모델 산출값 — 목표주가·추천 아님

Sheet 외화
C1: 이름: 외화QH — 환율 QoQ · 외화 순노출 × Δ기말환율 | E1: 4Q21 | F1: 1Q22 | G1: 2Q22 | H1: 3Q22 | I1: 4Q22 | J1: 1Q23 | K1: 2Q23 | L1: 3Q23 | M1: 4Q23 | N1: 1Q24 | O1: 2Q24 | P1: 3Q24 | Q1: 4Q24 | R1: 1Q25 | S1: 2Q25 | T1: 3Q25 | U1: 4Q25 | V1: 1Q26 | W1: 2Q26 | X1: 3Q26 | Y1: 4Q26 | Z1: 1Q27 | AA1: 2Q27 | AB1: 3Q27 | AC1: 4Q27 | AD1: 1Q28 | AE1: 2Q28 | AF1: 3Q28 | AG1: 4Q28
E3: 1 | F3: 2 | G3: 3 | H3: 4 | I3: 5 | J3: 6 | K3: 7 | L3: 8 | M3: 9 | N3: 10 | O3: 11 | P3: 12 | Q3: 13 | R3: 14 | S3: 15 | T3: 16 | U3: 17 | V3: 18 | W3: 19 | X3: 20 | Y3: 21 | Z3: 22 | AA3: 23 | AB3: 24 | AC3: 25 | AD3: 26 | AE3: 27 | AF3: 28 | AG3: 29
E4: 2021.12 | F4: 2022.03 | G4: 2022.06 | H4: 2022.09 | I4: 2022.12 | J4: 2023.03 | K4: 2023.06 | L4: 2023.09 | M4: 2023.12 | N4: 2024.03 | O4: 2024.06 | P4: 2024.09 | Q4: 2024.12 | R4: 2025.03 | S4: 2025.06 | T4: 2025.09 | U4: 2025.12 | V4: 2026.03 | W4: 2026.06 | X4: 2026.09 | Y4: 2026.12 | Z4: 2027.03 | AA4: 2027.06 | AB4: 2027.09 | AC4: 2027.12 | AD4: 2028.03 | AE4: 2028.06 | AF4: 2028.09 | AG4: 2028.12
D5: 원/달러(평균) | E5: =IFERROR(VLOOKUP($D5,환율,MATCH(E$1,변수H,0),0),"") | F5: =IFERROR(VLOOKUP($D5,환율,MATCH(F$1,변수H,0),0),"") | G5: =IFERROR(VLOOKUP($D5,환율,MATCH(G$1,변수H,0),0),"") | H5: =IFERROR(VLOOKUP($D5,환율,MATCH(H$1,변수H,0),0),"") | I5: =IFERROR(VLOOKUP($D5,환율,MATCH(I$1,변수H,0),0),"") | J5: =IFERROR(VLOOKUP($D5,환율,MATCH(J$1,변수H,0),0),"") | K5: =IFERROR(VLOOKUP($D5,환율,MATCH(K$1,변수H,0),0),"") | L5: =IFERROR(VLOOKUP($D5,환율,MATCH(L$1,변수H,0),0),"") | ... AG5: =IFERROR(VLOOKUP($D5,환율,MATCH(AG$1,변수H,0),0),"")
A6: 원/달러(평균) QoQ | F6: =IFERROR(F5/E5-1,"") | G6: =IFERROR(G5/F5-1,"") | H6: =IFERROR(H5/G5-1,"") | I6: =IFERROR(I5/H5-1,"") | J6: =IFERROR(J5/I5-1,"") | K6: =IFERROR(K5/J5-1,"") | L6: =IFERROR(L5/K5-1,"") | M6: =IFERROR(M5/L5-1,"") | ... AG6: =IFERROR(AG5/AF5-1,"")
D7: 원/달러(기말) | E7: =IFERROR(VLOOKUP($D7,환율,MATCH(E$1,변수H,0),0),"") | F7: =IFERROR(VLOOKUP($D7,환율,MATCH(F$1,변수H,0),0),"") | G7: =IFERROR(VLOOKUP($D7,환율,MATCH(G$1,변수H,0),0),"") | H7: =IFERROR(VLOOKUP($D7,환율,MATCH(H$1,변수H,0),0),"") | I7: =IFERROR(VLOOKUP($D7,환율,MATCH(I$1,변수H,0),0),"") | J7: =IFERROR(VLOOKUP($D7,환율,MATCH(J$1,변수H,0),0),"") | K7: =IFERROR(VLOOKUP($D7,환율,MATCH(K$1,변수H,0),0),"") | L7: =IFERROR(VLOOKUP($D7,환율,MATCH(L$1,변수H,0),0),"") | ... AG7: =IFERROR(VLOOKUP($D7,환율,MATCH(AG$1,변수H,0),0),"")
A8: 원/달러(기말) QoQ | F8: =IFERROR(F7/E7-1,"") | G8: =IFERROR(G7/F7-1,"") | H8: =IFERROR(H7/G7-1,"") | I8: =IFERROR(I7/H7-1,"") | J8: =IFERROR(J7/I7-1,"") | K8: =IFERROR(K7/J7-1,"") | L8: =IFERROR(L7/K7-1,"") | M8: =IFERROR(M7/L7-1,"") | ... AG8: =IFERROR(AG7/AF7-1,"")
D9: W/Euro(평균) | E9: =IFERROR(VLOOKUP($D9,환율,MATCH(E$1,변수H,0),0),"") | F9: =IFERROR(VLOOKUP($D9,환율,MATCH(F$1,변수H,0),0),"") | G9: =IFERROR(VLOOKUP($D9,환율,MATCH(G$1,변수H,0),0),"") | H9: =IFERROR(VLOOKUP($D9,환율,MATCH(H$1,변수H,0),0),"") | I9: =IFERROR(VLOOKUP($D9,환율,MATCH(I$1,변수H,0),0),"") | J9: =IFERROR(VLOOKUP($D9,환율,MATCH(J$1,변수H,0),0),"") | K9: =IFERROR(VLOOKUP($D9,환율,MATCH(K$1,변수H,0),0),"") | L9: =IFERROR(VLOOKUP($D9,환율,MATCH(L$1,변수H,0),0),"") | ... AG9: =IFERROR(VLOOKUP($D9,환율,MATCH(AG$1,변수H,0),0),"")
A10: W/Euro(평균) QoQ | F10: =IFERROR(F9/E9-1,"") | G10: =IFERROR(G9/F9-1,"") | H10: =IFERROR(H9/G9-1,"") | I10: =IFERROR(I9/H9-1,"") | J10: =IFERROR(J9/I9-1,"") | K10: =IFERROR(K9/J9-1,"") | L10: =IFERROR(L9/K9-1,"") | M10: =IFERROR(M9/L9-1,"") | ... AG10: =IFERROR(AG9/AF9-1,"")
D11: W/Euro(기말) | E11: =IFERROR(VLOOKUP($D11,환율,MATCH(E$1,변수H,0),0),"") | F11: =IFERROR(VLOOKUP($D11,환율,MATCH(F$1,변수H,0),0),"") | G11: =IFERROR(VLOOKUP($D11,환율,MATCH(G$1,변수H,0),0),"") | H11: =IFERROR(VLOOKUP($D11,환율,MATCH(H$1,변수H,0),0),"") | I11: =IFERROR(VLOOKUP($D11,환율,MATCH(I$1,변수H,0),0),"") | J11: =IFERROR(VLOOKUP($D11,환율,MATCH(J$1,변수H,0),0),"") | K11: =IFERROR(VLOOKUP($D11,환율,MATCH(K$1,변수H,0),0),"") | L11: =IFERROR(VLOOKUP($D11,환율,MATCH(L$1,변수H,0),0),"") | ... AG11: =IFERROR(VLOOKUP($D11,환율,MATCH(AG$1,변수H,0),0),"")
A12: W/Euro(기말) QoQ | F12: =IFERROR(F11/E11-1,"") | G12: =IFERROR(G11/F11-1,"") | H12: =IFERROR(H11/G11-1,"") | I12: =IFERROR(I11/H11-1,"") | J12: =IFERROR(J11/I11-1,"") | K12: =IFERROR(K11/J11-1,"") | L12: =IFERROR(L11/K11-1,"") | M12: =IFERROR(M11/L11-1,"") | ... AG12: =IFERROR(AG11/AF11-1,"")
D13: 원/100Y(기말) | E13: =IFERROR(VLOOKUP($D13,환율,MATCH(E$1,변수H,0),0),"") | F13: =IFERROR(VLOOKUP($D13,환율,MATCH(F$1,변수H,0),0),"") | G13: =IFERROR(VLOOKUP($D13,환율,MATCH(G$1,변수H,0),0),"") | H13: =IFERROR(VLOOKUP($D13,환율,MATCH(H$1,변수H,0),0),"") | I13: =IFERROR(VLOOKUP($D13,환율,MATCH(I$1,변수H,0),0),"") | J13: =IFERROR(VLOOKUP($D13,환율,MATCH(J$1,변수H,0),0),"") | K13: =IFERROR(VLOOKUP($D13,환율,MATCH(K$1,변수H,0),0),"") | L13: =IFERROR(VLOOKUP($D13,환율,MATCH(L$1,변수H,0),0),"") | ... AG13: =IFERROR(VLOOKUP($D13,환율,MATCH(AG$1,변수H,0),0),"")
A14: 원/100Y(기말) QoQ | F14: =IFERROR(F13/E13-1,"") | G14: =IFERROR(G13/F13-1,"") | H14: =IFERROR(H13/G13-1,"") | I14: =IFERROR(I13/H13-1,"") | J14: =IFERROR(J13/I13-1,"") | K14: =IFERROR(K13/J13-1,"") | L14: =IFERROR(L13/K13-1,"") | M14: =IFERROR(M13/L13-1,"") | ... AG14: =IFERROR(AG13/AF13-1,"")
A16: 외화순노출 | C16: 외화 순노출(백만$) | D16: =변수!D58 | E16: 외화 순노출 × Δ기말환율 (외화 시트 방식)
A17: 환관련손익추정 | C17: 환관련손익 추정(억원) = 순노출 × Δ원/달러(기말) / 100 | F17: =IFERROR($D$16*(F7-E7)/100,"") | G17: =IFERROR($D$16*(G7-F7)/100,"") | H17: =IFERROR($D$16*(H7-G7)/100,"") | I17: =IFERROR($D$16*(I7-H7)/100,"") | J17: =IFERROR($D$16*(J7-I7)/100,"") | K17: =IFERROR($D$16*(K7-J7)/100,"") | L17: =IFERROR($D$16*(L7-K7)/100,"") | M17: =IFERROR($D$16*(M7-L7)/100,"") | ... AG17: =IFERROR($D$16*(AG7-AF7)/100,"")
A18: fx_pnl.by_q | C18: 모델 fx_pnl.by_q(억원, 참고)
C19: 외화 순노출 미공시(face) → 0 + 표기
