Workbook
Name 변수H: 변수!$C$1:$AO$1
Name 환율: 변수!$C$6:$AO$13
Name BS연결H: BS연결!$C$1:$AO$1
Name BS연결: BS연결!$C$5:$AO$5
Name BS별도H: BS별도!$C$1:$AO$1
Name BS별도: BS별도!$C$5:$AO$88
Name SUBQH: subQ!$A$1:$AO$1
Name subQ: subQ!$A$5:$AO$42

Sheet README
A1: 에스앤더블류(103230) 실적 모델 — ARGUS 한국조선
A2: 기준 분기 2026Q2 · 마지막 실적 2026Q2 · 생성 2026-10-13
A3: 모든 수치는 모델 산출값(DART 공개 재무제표 + 우리 추정)이다 — 목표주가·투자 추천 아님. 참고용 · 투자조언 아님.
A5: 시트
A6: 변수 가정 시계열. 환율 8행(ECB via frankfurter — L2 fx.json; 추정 분기 = 노란 가정), 추정 드라이버(노란 셀 = 모델값에서 역산한 가정, 바꾸면 재계산; 연녹 셀 = 3절 스칼라 참조 수식), 3절 스칼라 가정(세율·판관비율·지배주주비중·이자율·종가·PER 밴드·COE·외화 순노출·헤지비율)
A7: BS연결/BS별도 FnGuide 계정명 × 기간 값 덤프(백만원). 행1 분기라벨, 행4 YYYY.MM / YYYY.12A. 이름정의 BS연결H·BS연결(계정명 C열부터)
A8: subQ 분기 서브모델(억원 = 백만원/100). 확정 행: =IFERROR(VLOOKUP($D행,BS연결,MATCH(E$1,BS연결H,0),0)/100,"") 추정 행: 변수 시트 가정 셀 참조 수식. 외환손익·파생상품손익은 BS 계정 합·차, 기타금융손익은 잔차, OPM·EPS·BPS·PER·PBR 은 파생 수식, 조정EPS 는 EPS 참조(일회성 의심 분기만 산식 셀)
A9: SLS 선표(조선사만, sls json 있을 때): 요약 행(sls 저장값) + 계약별 스케줄(백만$) × (헤지비율 × 헤지환율 + (1−헤지비율) × 건조시점 환율[변수 원/달러(평균)]) → 원화 수식 블록 → 합계 행이 subQ 매출조선에 연결
A10: 시나리오 신규수주 보수/기준/낙관(forecast_panel 패널, 모델에 scenarios 가 있을 때만): 매출액·영업이익 = subQ 기준값 ± (시나리오 신규 − base 신규) × OPM. base 만 subQ 행에 포함, 나머지는 합산 안 함
A11: 분기/연간예상 subQ 를 이름(A열 key)으로 VLOOKUP 한 보고서 표(억원)
A12: TP PER 밴드 × 12M fwd EPS, PBR = ROE/COE × BPS — 모델 산출값 구간, 목표주가·추천 아님
A13: 외화 환율 QoQ, 외화 순노출 × Δ기말환율 → 환관련손익 추정
... A35: 백테스트: {"freeze": "2025Q2", "horizon": 4, "revenue_wape_pct": 18.5, "op_wape_pct": 205.4, "n": 4, "note": "단일 회사 4분기 — 통계 아님", "driver_at_freeze": "customer_yard_revenue_weighted", "selection_oos_at_freeze": {"freeze": "2024Q2", "n": 4, "wape_link": 11.8, "wape_trend": 11.2, "adopted": true, "decision": "adopted"}, "frozen_inputs": "fin(연결/별도)·고객 조선사 모델·지주 자회사 모델은 2025Q2 까지의 분기만; 선표는 체결일 ≤ 2025Q2 말일 계약(원장 최신 금액·코호트 등급, 환산 없음); 잔고는 yards_cache 2025Q2; 시세·환율 forward·prices·forecast_panel 신규수주 미사용. 고객 가중치(suppliers.json 언급 비중)와 합병 체인링크는 현재 지식; 고객 연동 채택은 동결 모델 안에서도 자기 la−4분기 OOS 규칙(selection_oos_at_freeze)", "detail": [{"q": "2025Q3", "rev_pred": 127.59, "rev_act": 116.42, "op_pred": 7.65, "op_act": 3.7}, {"q": "2025Q4", "rev_pred": 163.85, "rev_act": 125.9, "op_pred": 9.82, "op_act": -1.02}, {"q": "2026Q1", "rev_pred": 132.61, "rev_act": 114.94, "op_pred": 7.95, "op_act": 3.09}, {"q": "2026Q2", "rev_pred": 151.15, "rev_act": 127.96, "op_pred": 9.06, "op_act": 4.15}]}

Sheet 변수
C1: 이름: 변수H | E1: 4Q21 | F1: 2021 | G1: 1Q22 | H1: 2Q22 | I1: 3Q22 | J1: 4Q22 | K1: 2022 | L1: 1Q23 | M1: 2Q23 | N1: 3Q23 | O1: 4Q23 | P1: 2023 | Q1: 1Q24 | R1: 2Q24 | S1: 3Q24 | T1: 4Q24 | U1: 2024 | V1: 1Q25 | W1: 2Q25 | X1: 3Q25 | Y1: 4Q25 | Z1: 2025 | AA1: 1Q26 | AB1: 2Q26 | AC1: 3Q26 | AD1: 4Q26 | AE1: 2026 | AF1: 1Q27 | AG1: 2Q27 | AH1: 3Q27 | AI1: 4Q27 | AJ1: 2027 | AK1: 1Q28 | AL1: 2Q28 | AM1: 3Q28 | AN1: 4Q28 | AO1: 2028
A2: 가정 시계열 — 노란 셀은 추정 가정(모델값에서 역산), 연녹 셀은 3절 스칼라 참조 수식. 바꾸면 subQ·분기·연간예상·TP·시나리오가 재계산됩니다.
E3: 1 | F3: 2 | G3: 3 | H3: 4 | I3: 5 | J3: 6 | K3: 7 | L3: 8 | M3: 9 | N3: 10 | O3: 11 | P3: 12 | Q3: 13 | R3: 14 | S3: 15 | T3: 16 | U3: 17 | V3: 18 | W3: 19 | X3: 20 | Y3: 21 | Z3: 22 | AA3: 23 | AB3: 24 | AC3: 25 | AD3: 26 | AE3: 27 | AF3: 28 | AG3: 29 | AH3: 30 | AI3: 31 | AJ3: 32 | AK3: 33 | AL3: 34 | AM3: 35 | AN3: 36 | AO3: 37
E4: 2021.12 | F4: 2021.12A | G4: 2022.03 | H4: 2022.06 | I4: 2022.09 | J4: 2022.12 | K4: 2022.12A | L4: 2023.03 | M4: 2023.06 | N4: 2023.09 | O4: 2023.12 | P4: 2023.12A | Q4: 2024.03 | R4: 2024.06 | S4: 2024.09 | T4: 2024.12 | U4: 2024.12A | V4: 2025.03 | W4: 2025.06 | X4: 2025.09 | Y4: 2025.12 | Z4: 2025.12A | AA4: 2026.03 | AB4: 2026.06 | AC4: 2026.09 | AD4: 2026.12 | AE4: 2026.12A | AF4: 2027.03 | AG4: 2027.06 | AH4: 2027.09 | AI4: 2027.12 | AJ4: 2027.12A | AK4: 2028.03 | AL4: 2028.06 | AM4: 2028.09 | AN4: 2028.12 | AO4: 2028.12A
B5: 1. FX | C5: 이름: 환율
A6: USDKRW_avg | C6: 원/달러(평균) | E6: 1183.5 | F6: 1145.51 | G6: 1205.78 | H6: 1262.09 | I6: 1341.93 | J6: 1360.12 | K6: 1292.98 | L6: 1276.95 | M6: 1315.69 | N6: 1313.62 | O6: 1322.01 | P6: 1306.85 | Q6: 1330.14 | R6: 1371.28 | S6: 1356.22 | T6: 1396.3 | U6: 1363.53 | V6: 1452.28 | W6: 1398.52 | X6: 1386.95 | Y6: 1449.19 | Z6: 1421.52 | AA6: 1466.12 | AB6: 1501.75 | AC6: 1418.75 | AD6: 1343.63 | AE6: 1456.58 | AF6: 1333.09 | AG6: 1333.09 | AH6: 1333.09 | AI6: 1333.09 | AK6: 1333.09 | AL6: 1333.09 | AM6: 1333.09 | AN6: 1333.09
A7: USDKRW_end | C7: 원/달러(기말) | E7: 1188.75 | F7: 1188.75 | G7: 1213.74 | H7: 1301.24 | I7: 1436.9 | J7: 1260.16 | K7: 1260.16 | L7: 1305.99 | M7: 1321.44 | N7: 1345.35 | O7: 1297.43 | P7: 1297.43 | Q7: 1349.25 | R7: 1377.73 | S7: 1312.17 | T7: 1474.78 | U7: 1474.78 | V7: 1474.54 | W7: 1355.13 | X7: 1403.67 | Y7: 1444.2 | Z7: 1444.2 | AA7: 1524.8 | AB7: 1550.89 | AC7: 1355.4 | AD7: 1333.09 | AE7: 1333.09 | AF7: 1333.09 | AG7: 1333.09 | AH7: 1333.09 | AI7: 1333.09 | AK7: 1333.09 | AL7: 1333.09 | AM7: 1333.09 | AN7: 1333.09
A8: JPY100KRW_avg | C8: 원/100Y(평균) | E8: 1041.02 | F8: 1042.74 | G8: 1036.79 | H8: 972.23 | I8: 970.61 | J8: 961.03 | K8: 985.1 | L8: 964.89 | M8: 957.36 | N8: 909 | O8: 893.22 | P8: 931.11 | Q8: 896.29 | R8: 880.14 | S8: 909.35 | T8: 917.25 | U8: 900.92 | V8: 952.59 | W8: 967.92 | X8: 940.32 | Y8: 940.77 | Z8: 950.17 | AA8: 934.39 | AB8: 942.16 | AC8: 890.41 | AD8: 849.51 | AE8: 918.81 | AF8: 840.54 | AG8: 840.54 | AH8: 840.54 | AI8: 840.54 | AK8: 840.54 | AL8: 840.54 | AM8: 840.54 | AN8: 840.54
A9: JPY100KRW_end | C9: 원/100Y(기말) | E9: 1032.62 | F9: 1032.62 | G9: 996.83 | H9: 954.9 | I9: 993.29 | J9: 955.54 | K9: 955.54 | L9: 980.62 | M9: 913.67 | N9: 901.47 | O9: 917.04 | P9: 917.04 | Q9: 892.42 | R9: 857.76 | S9: 919.21 | T9: 939.65 | U9: 939.65 | V9: 986.84 | W9: 938.85 | X9: 948.49 | Y9: 921.81 | Z9: 921.81 | AA9: 955.99 | AB9: 954.75 | AC9: 863.31 | AD9: 840.54 | AE9: 840.54 | AF9: 840.54 | AG9: 840.54 | AH9: 840.54 | AI9: 840.54 | AK9: 840.54 | AL9: 840.54 | AM9: 840.54 | AN9: 840.54
A10: EURKRW_avg | C10: W/Euro(평균) | E10: 1353.32 | F10: 1354.06 | G10: 1352.29 | H10: 1343.31 | I10: 1350.63 | J10: 1386.07 | K10: 1358.07 | L10: 1369.93 | M10: 1432.41 | N10: 1429.41 | O10: 1420.91 | P10: 1412.88 | Q10: 1444.21 | R10: 1476.42 | S10: 1489.3 | T10: 1490.78 | U10: 1475.4 | V10: 1528.33 | W10: 1585.13 | X10: 1620.04 | Y10: 1686.02 | Z10: 1605.45 | AA10: 1715.47 | AB10: 1746.09 | AC10: 1631.97 | AD10: 1507.34 | AE10: 1688.95 | AF10: 1490.54 | AG10: 1490.54 | AH10: 1490.54 | AI10: 1490.54 | AK10: 1490.54 | AL10: 1490.54 | AM10: 1490.54 | AN10: 1490.54
A11: EURKRW_end | C11: W/Euro(기말) | E11: 1346.38 | F11: 1346.38 | G11: 1347.37 | H11: 1351.6 | I11: 1400.62 | J11: 1344.08 | K11: 1344.08 | L11: 1420.26 | M11: 1435.88 | N11: 1425.26 | O11: 1433.66 | P11: 1433.66 | Q11: 1458.68 | R11: 1474.86 | S11: 1469.1 | T11: 1532.14 | U11: 1532.14 | V11: 1594.72 | W11: 1588.22 | X11: 1648.04 | Y11: 1696.94 | Z11: 1696.94 | AA11: 1753.21 | AB11: 1767.09 | AC11: 1539.06 | AD11: 1490.54 | AE11: 1490.54 | AF11: 1490.54 | AG11: 1490.54 | AH11: 1490.54 | AI11: 1490.54 | AK11: 1490.54 | AL11: 1490.54 | AM11: 1490.54 | AN11: 1490.54
A12: CNYKRW_avg | C12: 원/중국원(평균) | E12: 185.14 | F12: 177.65 | G12: 189.93 | H12: 190.76 | I12: 195.79 | J12: 191.09 | K12: 191.93 | L12: 186.59 | M12: 187.45 | N12: 181.28 | O12: 182.86 | P12: 184.52 | Q12: 185.04 | R12: 189.35 | S12: 189.24 | T12: 194.24 | U12: 189.49 | V12: 199.63 | W12: 193.41 | X12: 193.79 | Y12: 204.38 | Z12: 197.8 | AA12: 211.75 | AB12: 220.8 | AC12: 210.43 | AD12: 200.5 | AE12: 213.68 | AF12: 199.18 | AG12: 199.18 | AH12: 199.18 | AI12: 199.18 | AK12: 199.18 | AL12: 199.18 | AM12: 199.18 | AN12: 199.18
A13: CNYKRW_end | C13: 원/중국원(기말) | E13: 187.13 | F13: 187.13 | G13: 191.38 | H13: 194.13 | I13: 201.92 | J13: 182.67 | K13: 182.67 | L13: 189.97 | M13: 181.8 | N13: 184.26 | O13: 182.61 | P13: 182.61 | Q13: 186.66 | R13: 189.7 | S13: 187.12 | T13: 202.04 | U13: 202.04 | V13: 203.3 | W13: 189.14 | X13: 197.16 | Y13: 206.28 | Z13: 206.28 | AA13: 220.97 | AB13: 228.56 | AC13: 202.16 | AD13: 199.18 | AE13: 199.18 | AF13: 199.18 | AG13: 199.18 | AH13: 199.18 | AI13: 199.18 | AK13: 199.18 | AL13: 199.18 | AM13: 199.18 | AN13: 199.18
B14: 1b. 종가
A15: price_close_end | C15: 종가(기말) | L15: 3750 | M15: 4810 | N15: 4410 | O15: 4030 | Q15: 3945 | R15: 4540 | S15: 3670 | T15: 3250 | V15: 3150 | W15: 3365 | X15: 4440 | Y15: 4160 | AA15: 3685 | AB15: 2360 | AC15: 1746 | AD15: 1507
A16: price_high | C16: 종가(최고) | L16: 4690 | M16: 5050 | N16: 8780 | O16: 4850 | Q16: 4345 | R16: 5120 | S16: 4845 | T16: 3880 | V16: 3640 | W16: 3940 | X16: 6100 | Y16: 5000 | AA16: 4390 | AB16: 4800 | AC16: 2850 | AD16: 1689
A17: price_low | C17: 종가(최저) | L17: 3425 | M17: 3600 | N17: 4055 | O17: 3840 | Q17: 3300 | R17: 3735 | S17: 3250 | T17: 2500 | V17: 2725 | W17: 3140 | X17: 3155 | Y17: 3980 | AA17: 3280 | AB17: 2100 | AC17: 1700 | AD17: 1287
A18: price_avg | C18: 종가(평균) | L18: 3683.8 | M18: 4265.5 | N18: 5268.7 | O18: 4167.9 | Q18: 3811.4 | R18: 4340.5 | S18: 4000.3 | T18: 3302.6 | V18: 3127.7 | W18: 3478.2 | X18: 3941.2 | Y18: 4345.1 | AA18: 3910 | AB18: 3432 | AC18: 2401.1 | AD18: 1503.6
B20: 2. 추정 드라이버 | C20: 실적 열 = subQ 실현값(수식), 추정 열 = 가정(노란 = 모델값 역산, 연녹 = 3절 스칼라 참조)
A21: drv:매출액 | B21: yoy | C21: 매출액 YoY | J21: =IFERROR(subQ!J5/subQ!E5-1,"") | L21: =IFERROR(subQ!L5/subQ!G5-1,"") | M21: =IFERROR(subQ!M5/subQ!H5-1,"") | N21: =IFERROR(subQ!N5/subQ!I5-1,"") | O21: =IFERROR(subQ!O5/subQ!J5-1,"") | Q21: =IFERROR(subQ!Q5/subQ!L5-1,"") | R21: =IFERROR(subQ!R5/subQ!M5-1,"") | S21: =IFERROR(subQ!S5/subQ!N5-1,"") | T21: =IFERROR(subQ!T5/subQ!O5-1,"") | V21: =IFERROR(subQ!V5/subQ!Q5-1,"") | W21: =IFERROR(subQ!W5/subQ!R5-1,"") | X21: =IFERROR(subQ!X5/subQ!S5-1,"") | Y21: =IFERROR(subQ!Y5/subQ!T5-1,"") | AA21: =IFERROR(subQ!AA5/subQ!V5-1,"") | AB21: =IFERROR(subQ!AB5/subQ!W5-1,"") | AC21: -0.019529529 | AD21: -0.019580587 | AF21: -0.019533632 | AG21: -0.019564939 | AH21: -0.009811651 | AI21: -0.009803127 | AK21: -0.009850031 | AL21: -0.009803922 | AM21: -0.004865965 | AN21: -0.00482736
A22: drv:판관비 | B22: ratio | C22: 판관비율(/매출) | E22: =IFERROR(subQ!E8/subQ!E5,"") | F22: =IFERROR(subQ!F8/subQ!F5,"") | G22: =IFERROR(subQ!G8/subQ!G5,"") | H22: =IFERROR(subQ!H8/subQ!H5,"") | I22: =IFERROR(subQ!I8/subQ!I5,"") | J22: =IFERROR(subQ!J8/subQ!J5,"") | K22: =IFERROR(subQ!K8/subQ!K5,"") | L22: =IFERROR(subQ!L8/subQ!L5,"") | ... AB22: =IFERROR(subQ!AB8/subQ!AB5,"") | AC22: =$D$50 | AD22: =$D$50 | AE22: =IFERROR(subQ!AE8/subQ!AE5,"") | AF22: =$D$50 | AG22: =$D$50 | AH22: =$D$50 | AI22: =$D$50 | AJ22: =IFERROR(subQ!AJ8/subQ!AJ5,"") | AK22: =$D$50 | AL22: =$D$50 | AM22: =$D$50 | AN22: =$D$50 | AO22: =IFERROR(subQ!AO8/subQ!AO5,"")
A23: drv:영업이익 | B23: ratio | C23: 영업이익률(OPM) | E23: =IFERROR(subQ!E9/subQ!E5,"") | F23: =IFERROR(subQ!F9/subQ!F5,"") | G23: =IFERROR(subQ!G9/subQ!G5,"") | H23: =IFERROR(subQ!H9/subQ!H5,"") | I23: =IFERROR(subQ!I9/subQ!I5,"") | J23: =IFERROR(subQ!J9/subQ!J5,"") | K23: =IFERROR(subQ!K9/subQ!K5,"") | L23: =IFERROR(subQ!L9/subQ!L5,"") | ... AB23: =IFERROR(subQ!AB9/subQ!AB5,"") | AC23: 0.02934735 | AD23: 0.029328364 | AE23: =IFERROR(subQ!AE9/subQ!AE5,"") | AF23: 0.029283876 | AG23: 0.029332058 | AH23: 0.029284261 | AI23: 0.029291442 | AJ23: =IFERROR(subQ!AJ9/subQ!AJ5,"") | AK23: 0.029306327 | AL23: 0.029300491 | AM23: 0.029338549 | AN23: 0.029351311 | AO23: =IFERROR(subQ!AO9/subQ!AO5,"")
A24: drv:외환손익 | B24: abs | C24: 외환손익 (가정, 억원) | E24: =subQ!E13 | F24: =subQ!F13 | G24: =subQ!G13 | H24: =subQ!H13 | I24: =subQ!I13 | J24: =subQ!J13 | K24: =subQ!K13 | L24: =subQ!L13 | ... AB24: =subQ!AB13 | AC24: 0 | AD24: 0 | AE24: =subQ!AE13 | AF24: 0 | AG24: 0 | AH24: 0 | AI24: 0 | AJ24: =subQ!AJ13 | AK24: 0 | AL24: 0 | AM24: 0 | AN24: 0 | AO24: =subQ!AO13
A25: drv:기타영업외손익 | B25: abs | C25: 기타영업외손익 (가정, 억원) | E25: =subQ!E14 | F25: =subQ!F14 | G25: =subQ!G14 | H25: =subQ!H14 | I25: =subQ!I14 | J25: =subQ!J14 | K25: =subQ!K14 | L25: =subQ!L14 | ... AB25: =subQ!AB14 | AC25: 0 | AD25: 0 | AE25: =subQ!AE14 | AF25: 0 | AG25: 0 | AH25: 0 | AI25: 0 | AJ25: =subQ!AJ14 | AK25: 0 | AL25: 0 | AM25: 0 | AN25: 0 | AO25: =subQ!AO14
A26: drv:지분법손익 | B26: abs | C26: 지분법손익 (가정, 억원) | E26: =subQ!E15 | F26: =subQ!F15 | G26: =subQ!G15 | H26: =subQ!H15 | I26: =subQ!I15 | J26: =subQ!J15 | K26: =subQ!K15 | L26: =subQ!L15 | ... AB26: =subQ!AB15 | AC26: 0 | AD26: 0 | AE26: =subQ!AE15 | AF26: 0 | AG26: 0 | AH26: 0 | AI26: 0 | AJ26: =subQ!AJ15 | AK26: 0 | AL26: 0 | AM26: 0 | AN26: 0 | AO26: =subQ!AO15
A27: drv:법인세비용 | B27: tax | C27: 법인세율(/세전) — 법인세 = MAX(세전,0) × 분기별 세율(이월결손 램프, assumptions.tax_schedule) | E27: =IFERROR(subQ!E17/subQ!E16,"") | F27: =IFERROR(subQ!F17/subQ!F16,"") | G27: =IFERROR(subQ!G17/subQ!G16,"") | H27: =IFERROR(subQ!H17/subQ!H16,"") | I27: =IFERROR(subQ!I17/subQ!I16,"") | J27: =IFERROR(subQ!J17/subQ!J16,"") | K27: =IFERROR(subQ!K17/subQ!K16,"") | L27: =IFERROR(subQ!L17/subQ!L16,"") | ... AB27: =IFERROR(subQ!AB17/subQ!AB16,"") | AC27: 0 | AD27: 0 | AE27: =IFERROR(subQ!AE17/subQ!AE16,"") | AF27: 0.026578073 | AG27: 0.056047198 | AH27: 0.082236842 | AI27: 0.11144578 | AJ27: =IFERROR(subQ!AJ17/subQ!AJ16,"") | AK27: 0.13907285 | AL27: 0.16470588 | AM27: 0.19218241 | AN27: 0.22089552 | AO27: =IFERROR(subQ!AO17/subQ!AO16,"")
A28: drv:지배주주순이익 | B28: ratio | C28: 지배주주 비중(/당기순이익) | E28: =IFERROR(subQ!E19/subQ!E18,"") | F28: =IFERROR(subQ!F19/subQ!F18,"") | G28: =IFERROR(subQ!G19/subQ!G18,"") | H28: =IFERROR(subQ!H19/subQ!H18,"") | I28: =IFERROR(subQ!I19/subQ!I18,"") | J28: =IFERROR(subQ!J19/subQ!J18,"") | K28: =IFERROR(subQ!K19/subQ!K18,"") | L28: =IFERROR(subQ!L19/subQ!L18,"") | ... AB28: =IFERROR(subQ!AB19/subQ!AB18,"") | AC28: =$D$51 | AD28: =$D$51 | AE28: =IFERROR(subQ!AE19/subQ!AE18,"") | AF28: =$D$51 | AG28: =$D$51 | AH28: =$D$51 | AI28: =$D$51 | AJ28: =IFERROR(subQ!AJ19/subQ!AJ18,"") | AK28: =$D$51 | AL28: =$D$51 | AM28: =$D$51 | AN28: =$D$51 | AO28: =IFERROR(subQ!AO19/subQ!AO18,"")
A29: drv:부채총계 | B29: qoq | C29: 부채총계 QoQ | G29: =IFERROR(subQ!G21/subQ!E21-1,"") | H29: =IFERROR(subQ!H21/subQ!G21-1,"") | I29: =IFERROR(subQ!I21/subQ!H21-1,"") | J29: =IFERROR(subQ!J21/subQ!I21-1,"") | L29: =IFERROR(subQ!L21/subQ!J21-1,"") | M29: =IFERROR(subQ!M21/subQ!L21-1,"") | N29: =IFERROR(subQ!N21/subQ!M21-1,"") | O29: =IFERROR(subQ!O21/subQ!N21-1,"") | Q29: =IFERROR(subQ!Q21/subQ!O21-1,"") | R29: =IFERROR(subQ!R21/subQ!Q21-1,"") | S29: =IFERROR(subQ!S21/subQ!R21-1,"") | T29: =IFERROR(subQ!T21/subQ!S21-1,"") | V29: =IFERROR(subQ!V21/subQ!T21-1,"") | W29: =IFERROR(subQ!W21/subQ!V21-1,"") | X29: =IFERROR(subQ!X21/subQ!W21-1,"") | Y29: =IFERROR(subQ!Y21/subQ!X21-1,"") | AA29: =IFERROR(subQ!AA21/subQ!Y21-1,"") | AB29: =IFERROR(subQ!AB21/subQ!AA21-1,"") | AC29: -4.145e-06 | AD29: 0 | AF29: 0 | AG29: 0 | AH29: 0 | AI29: 0 | AK29: 0 | AL29: 0 | AM29: 0 | AN29: 0
A30: drv:자본총계 | B30: roll | C30: 자본총계 기타변동(배당 등, 억원) | G30: =IFERROR(subQ!E22+subQ!G18-subQ!G22,"") | H30: =IFERROR(subQ!G22+subQ!H18-subQ!H22,"") | I30: =IFERROR(subQ!H22+subQ!I18-subQ!I22,"") | J30: =IFERROR(subQ!I22+subQ!J18-subQ!J22,"") | L30: =IFERROR(subQ!J22+subQ!L18-subQ!L22,"") | M30: =IFERROR(subQ!L22+subQ!M18-subQ!M22,"") | N30: =IFERROR(subQ!M22+subQ!N18-subQ!N22,"") | O30: =IFERROR(subQ!N22+subQ!O18-subQ!O22,"") | Q30: =IFERROR(subQ!O22+subQ!Q18-subQ!Q22,"") | R30: =IFERROR(subQ!Q22+subQ!R18-subQ!R22,"") | S30: =IFERROR(subQ!R22+subQ!S18-subQ!S22,"") | T30: =IFERROR(subQ!S22+subQ!T18-subQ!T22,"") | V30: =IFERROR(subQ!T22+subQ!V18-subQ!V22,"") | W30: =IFERROR(subQ!V22+subQ!W18-subQ!W22,"") | X30: =IFERROR(subQ!W22+subQ!X18-subQ!X22,"") | Y30: =IFERROR(subQ!X22+subQ!Y18-subQ!Y22,"") | AA30: =IFERROR(subQ!Y22+subQ!AA18-subQ!AA22,"") | AB30: =IFERROR(subQ!AA22+subQ!AB18-subQ!AB22,"") | AC30: 0.005180418 | AD30: 0.001460245 | AF30: -0.005600626 | AG30: 0.005252865 | AH30: -0.00190339 | AI30: -0.011151955 | AK30: -0.009881481 | AL30: 0.000183645 | AM30: 0.000961695 | AN30: 0.000600254
A31: drv:지배주주지분 | B31: roll | C31: 지배주주지분 기타변동(배당 등, 억원) | G31: =IFERROR(subQ!E23+subQ!G19-subQ!G23,"") | H31: =IFERROR(subQ!G23+subQ!H19-subQ!H23,"") | I31: =IFERROR(subQ!H23+subQ!I19-subQ!I23,"") | J31: =IFERROR(subQ!I23+subQ!J19-subQ!J23,"") | L31: =IFERROR(subQ!J23+subQ!L19-subQ!L23,"") | M31: =IFERROR(subQ!L23+subQ!M19-subQ!M23,"") | N31: =IFERROR(subQ!M23+subQ!N19-subQ!N23,"") | O31: =IFERROR(subQ!N23+subQ!O19-subQ!O23,"") | Q31: =IFERROR(subQ!O23+subQ!Q19-subQ!Q23,"") | R31: =IFERROR(subQ!Q23+subQ!R19-subQ!R23,"") | S31: =IFERROR(subQ!R23+subQ!S19-subQ!S23,"") | T31: =IFERROR(subQ!S23+subQ!T19-subQ!T23,"") | V31: =IFERROR(subQ!T23+subQ!V19-subQ!V23,"") | W31: =IFERROR(subQ!V23+subQ!W19-subQ!W23,"") | X31: =IFERROR(subQ!W23+subQ!X19-subQ!X23,"") | Y31: =IFERROR(subQ!X23+subQ!Y19-subQ!Y23,"") | AA31: =IFERROR(subQ!Y23+subQ!AA19-subQ!AA23,"") | AB31: =IFERROR(subQ!AA23+subQ!AB19-subQ!AB23,"") | AC31: 0.005180418 | AD31: 0.001460245 | AF31: -0.005600626 | AG31: 0.005252865 | AH31: -0.00190339 | AI31: -0.011151955 | AK31: -0.009881481 | AL31: 0.000183645 | AM31: 0.000961695 | AN31: 0.000600254
A32: drv:총차입금 | B32: qoq | C32: 총차입금 QoQ | G32: =IFERROR(subQ!G24/subQ!E24-1,"") | H32: =IFERROR(subQ!H24/subQ!G24-1,"") | I32: =IFERROR(subQ!I24/subQ!H24-1,"") | J32: =IFERROR(subQ!J24/subQ!I24-1,"") | L32: =IFERROR(subQ!L24/subQ!J24-1,"") | M32: =IFERROR(subQ!M24/subQ!L24-1,"") | N32: =IFERROR(subQ!N24/subQ!M24-1,"") | O32: =IFERROR(subQ!O24/subQ!N24-1,"") | Q32: =IFERROR(subQ!Q24/subQ!O24-1,"") | R32: =IFERROR(subQ!R24/subQ!Q24-1,"") | S32: =IFERROR(subQ!S24/subQ!R24-1,"") | T32: =IFERROR(subQ!T24/subQ!S24-1,"") | V32: =IFERROR(subQ!V24/subQ!T24-1,"") | W32: =IFERROR(subQ!W24/subQ!V24-1,"") | X32: =IFERROR(subQ!X24/subQ!W24-1,"") | Y32: =IFERROR(subQ!Y24/subQ!X24-1,"") | AA32: =IFERROR(subQ!AA24/subQ!Y24-1,"") | AB32: =IFERROR(subQ!AB24/subQ!AA24-1,"") | AC32: 0 | AD32: 0 | AF32: 0 | AG32: 0 | AH32: 0 | AI32: 0 | AK32: 0 | AL32: 0 | AM32: 0 | AN32: 0
A33: drv:순차입금 | B33: qoq | C33: 순차입금 QoQ | G33: =IFERROR(subQ!G25/subQ!E25-1,"") | H33: =IFERROR(subQ!H25/subQ!G25-1,"") | I33: =IFERROR(subQ!I25/subQ!H25-1,"") | J33: =IFERROR(subQ!J25/subQ!I25-1,"") | L33: =IFERROR(subQ!L25/subQ!J25-1,"") | M33: =IFERROR(subQ!M25/subQ!L25-1,"") | N33: =IFERROR(subQ!N25/subQ!M25-1,"") | O33: =IFERROR(subQ!O25/subQ!N25-1,"") | Q33: =IFERROR(subQ!Q25/subQ!O25-1,"") | R33: =IFERROR(subQ!R25/subQ!Q25-1,"") | S33: =IFERROR(subQ!S25/subQ!R25-1,"") | T33: =IFERROR(subQ!T25/subQ!S25-1,"") | V33: =IFERROR(subQ!V25/subQ!T25-1,"") | W33: =IFERROR(subQ!W25/subQ!V25-1,"") | X33: =IFERROR(subQ!X25/subQ!W25-1,"") | Y33: =IFERROR(subQ!Y25/subQ!X25-1,"") | AA33: =IFERROR(subQ!AA25/subQ!Y25-1,"") | AB33: =IFERROR(subQ!AB25/subQ!AA25-1,"") | AC33: -0.024868486 | AD33: -0.027918354 | AF33: -0.025422993 | AG33: -0.028490028 | AH33: -0.025568182 | AI33: -0.027837863 | AK33: -0.025249105 | AL33: -0.028185788 | AM33: -0.025326797 | AN33: -0.027347024
A34: drv:이자발생자산 | B34: qoq | C34: 이자발생자산 QoQ | G34: =IFERROR(subQ!G26/subQ!E26-1,"") | H34: =IFERROR(subQ!H26/subQ!G26-1,"") | I34: =IFERROR(subQ!I26/subQ!H26-1,"") | J34: =IFERROR(subQ!J26/subQ!I26-1,"") | L34: =IFERROR(subQ!L26/subQ!J26-1,"") | M34: =IFERROR(subQ!M26/subQ!L26-1,"") | N34: =IFERROR(subQ!N26/subQ!M26-1,"") | O34: =IFERROR(subQ!O26/subQ!N26-1,"") | Q34: =IFERROR(subQ!Q26/subQ!O26-1,"") | R34: =IFERROR(subQ!R26/subQ!Q26-1,"") | S34: =IFERROR(subQ!S26/subQ!R26-1,"") | T34: =IFERROR(subQ!T26/subQ!S26-1,"") | V34: =IFERROR(subQ!V26/subQ!T26-1,"") | W34: =IFERROR(subQ!W26/subQ!V26-1,"") | X34: =IFERROR(subQ!X26/subQ!W26-1,"") | Y34: =IFERROR(subQ!Y26/subQ!X26-1,"") | AA34: =IFERROR(subQ!AA26/subQ!Y26-1,"") | AB34: =IFERROR(subQ!AB26/subQ!AA26-1,"") | AC34: 0.098116587 | AD34: 0.097813239 | AF34: 0.078869448 | AG34: 0.079840319 | AH34: 0.064463956 | AI34: 0.064250054 | AK34: 0.053232715 | AL34: 0.054996127 | AM34: 0.045521292 | AN34: 0.045821629
A35: drv:현금및현금성자산 | B35: qoq | C35: 현금및현금성자산 QoQ | G35: =IFERROR(subQ!G27/subQ!E27-1,"") | H35: =IFERROR(subQ!H27/subQ!G27-1,"") | I35: =IFERROR(subQ!I27/subQ!H27-1,"") | J35: =IFERROR(subQ!J27/subQ!I27-1,"") | L35: =IFERROR(subQ!L27/subQ!J27-1,"") | M35: =IFERROR(subQ!M27/subQ!L27-1,"") | N35: =IFERROR(subQ!N27/subQ!M27-1,"") | O35: =IFERROR(subQ!O27/subQ!N27-1,"") | Q35: =IFERROR(subQ!Q27/subQ!O27-1,"") | R35: =IFERROR(subQ!R27/subQ!Q27-1,"") | S35: =IFERROR(subQ!S27/subQ!R27-1,"") | T35: =IFERROR(subQ!T27/subQ!S27-1,"") | V35: =IFERROR(subQ!V27/subQ!T27-1,"") | W35: =IFERROR(subQ!W27/subQ!V27-1,"") | X35: =IFERROR(subQ!X27/subQ!W27-1,"") | Y35: =IFERROR(subQ!Y27/subQ!X27-1,"") | AA35: =IFERROR(subQ!AA27/subQ!Y27-1,"") | AB35: =IFERROR(subQ!AB27/subQ!AA27-1,"")
A36: drv:CAPEX | B36: yoy | C36: CAPEX YoY | J36: =IFERROR(subQ!J28/subQ!E28-1,"") | L36: =IFERROR(subQ!L28/subQ!G28-1,"") | M36: =IFERROR(subQ!M28/subQ!H28-1,"") | N36: =IFERROR(subQ!N28/subQ!I28-1,"") | O36: =IFERROR(subQ!O28/subQ!J28-1,"") | Q36: =IFERROR(subQ!Q28/subQ!L28-1,"") | R36: =IFERROR(subQ!R28/subQ!M28-1,"") | S36: =IFERROR(subQ!S28/subQ!N28-1,"") | T36: =IFERROR(subQ!T28/subQ!O28-1,"") | V36: =IFERROR(subQ!V28/subQ!Q28-1,"") | W36: =IFERROR(subQ!W28/subQ!R28-1,"") | X36: =IFERROR(subQ!X28/subQ!S28-1,"") | Y36: =IFERROR(subQ!Y28/subQ!T28-1,"") | AA36: =IFERROR(subQ!AA28/subQ!V28-1,"") | AB36: =IFERROR(subQ!AB28/subQ!W28-1,"") | AC36: -0.032107957 | AD36: 0.034043907 | AF36: 6.9963094 | AG36: -0.55326844 | AH36: 0 | AI36: 0 | AK36: 0 | AL36: 0 | AM36: 0 | AN36: 0
A37: drv:영업활동현금흐름 | B37: yoy | C37: 영업활동현금흐름 YoY | J37: =IFERROR(subQ!J29/subQ!E29-1,"") | L37: =IFERROR(subQ!L29/subQ!G29-1,"") | M37: =IFERROR(subQ!M29/subQ!H29-1,"") | N37: =IFERROR(subQ!N29/subQ!I29-1,"") | O37: =IFERROR(subQ!O29/subQ!J29-1,"") | Q37: =IFERROR(subQ!Q29/subQ!L29-1,"") | R37: =IFERROR(subQ!R29/subQ!M29-1,"") | S37: =IFERROR(subQ!S29/subQ!N29-1,"") | T37: =IFERROR(subQ!T29/subQ!O29-1,"") | V37: =IFERROR(subQ!V29/subQ!Q29-1,"") | W37: =IFERROR(subQ!W29/subQ!R29-1,"") | X37: =IFERROR(subQ!X29/subQ!S29-1,"") | Y37: =IFERROR(subQ!Y29/subQ!T29-1,"") | AA37: =IFERROR(subQ!AA29/subQ!V29-1,"") | AB37: =IFERROR(subQ!AB29/subQ!W29-1,"")
A38: drv:주식수 | B38: qoq | C38: 주식수 QoQ | G38: =IFERROR(subQ!G30/subQ!E30-1,"") | H38: =IFERROR(subQ!H30/subQ!G30-1,"") | I38: =IFERROR(subQ!I30/subQ!H30-1,"") | J38: =IFERROR(subQ!J30/subQ!I30-1,"") | L38: =IFERROR(subQ!L30/subQ!J30-1,"") | M38: =IFERROR(subQ!M30/subQ!L30-1,"") | N38: =IFERROR(subQ!N30/subQ!M30-1,"") | O38: =IFERROR(subQ!O30/subQ!N30-1,"") | Q38: =IFERROR(subQ!Q30/subQ!O30-1,"") | R38: =IFERROR(subQ!R30/subQ!Q30-1,"") | S38: =IFERROR(subQ!S30/subQ!R30-1,"") | T38: =IFERROR(subQ!T30/subQ!S30-1,"") | V38: =IFERROR(subQ!V30/subQ!T30-1,"") | W38: =IFERROR(subQ!W30/subQ!V30-1,"") | X38: =IFERROR(subQ!X30/subQ!W30-1,"") | Y38: =IFERROR(subQ!Y30/subQ!X30-1,"") | AA38: =IFERROR(subQ!AA30/subQ!Y30-1,"") | AB38: =IFERROR(subQ!AB30/subQ!AA30-1,"") | AC38: 0 | AD38: 0 | AF38: 0 | AG38: 0 | AH38: 0 | AI38: 0 | AK38: 0 | AL38: 0 | AM38: 0 | AN38: 0
A39: drv:DPS | B39: abs | C39: DPS (가정, 원) | E39: =subQ!E34 | F39: =subQ!F34 | G39: =subQ!G34 | H39: =subQ!H34 | I39: =subQ!I34 | J39: =subQ!J34 | K39: =subQ!K34 | L39: =subQ!L34 | ... AB39: =subQ!AB34 | AD39: 0 | AE39: =subQ!AE34 | AI39: 0 | AJ39: =subQ!AJ34 | AN39: 0 | AO39: =subQ!AO34
B41: 3. 밸류에이션·스칼라 | C41: 노란 셀 = 가정. '연결' 표시는 추정 전 분기 수식이 이 셀을 참조한다는 뜻
A42: sc:종가 | C42: 종가 | D42: 1507 | E42: 원 — 네이버 정규장 종가(aik 확정종가 대조 · aik 1,645원)
A43: sc:기준일 | C43: 기준일 | D43: 20261013 | E43: 종가 기준일
A44: sc:COE | C44: COE | D44: 0.09 | E44: 자기자본비용(가정) — TP 적정 PBR = ROE/COE
A45: sc:PER_lo | C45: PER_lo | D45: 5 | E45: PER 밴드 하단(배) — hist_quarterly(분기 평균가 ÷ TTM EPS, 14분기, 25/50/75 백분위)
A46: sc:PER_mid | C46: PER_mid | D46: 8.3 | E46: PER 밴드 중단(배)
A47: sc:PER_hi | C47: PER_hi | D47: 10.2 | E47: PER 밴드 상단(배)
A48: sc:EPS_Y1가중 | C48: EPS_Y1가중 | D48: 0.5 | E48: 12M fwd EPS = FY(last_actual연도)E × w + FY+1E × (1−w) — 기준 분기 2Q 이면 0.5(가정)
A49: sc:세율 | C49: 세율 | D49: 0 | E49: 참고(연결 안 됨: 이월결손 램프(assumptions.tax_schedule, 0%→22%) — 분기별 세율 드라이버 행 사용) — 모델 assumptions 값(시작 0% → terminal 22%, 2026Q4 까지 유지 → 2027Q1~2028Q4 선형 램프 — 분기별 값은 2절 drv:법인세비용 행) · 최근 8분기 중 세전 > 0 인 6분기(2024Q4~2026Q2) 법인세/세전 중위 -35.1%·최근 4분기 중위 -35.1% 가 모두 5% 미만 → 이월결손 공제 중으로 보고 0.0% 를 2026Q4 까지 유지, 2027Q1~2028Q4 선형 램프로 법정세율 근사 22% 수렴
A50: sc:판관비율 | C50: 판관비율 | D50: 0.10497078 | E50: 연결 — 판관비 = 매출액 × 판관비율(역산, 재현 오차 ≤ 0.05억 · 모델 assumptions 0.105)
A51: sc:지배주주비중 | C51: 지배주주비중 | D51: 1 | E51: 연결 — 지배주주순이익 = 당기순이익 × 비중(역산, 재현 오차 ≤ 0.05억)
A52: sc:이자율_자산 | C52: 이자율_자산 | D52: 0.015451592 | E52: 연결 — 이자손익 = (전분기 이자발생자산 × 자산이자율 − 전분기 총차입금 × 부채이자율)/4(역산, 재현 오차 ≤ 0.05억 · 모델 assumptions 0.0158)
A53: sc:이자율_부채 | C53: 이자율_부채 | D53: 0.011529139 | E53: 연결 — 같은 수식의 부채 쪽(총차입금 행이 없으면 0)(역산, 재현 오차 ≤ 0.05억 · 모델 assumptions 0.0116)
A54: sc:배당성향 | C54: 배당성향 | D54: 0 | E54: 배당성향(참고 — 모델은 직전 DPS 유지·Q2 지급 가정)
A55: sc:외화순노출_백만$ | C55: 외화순노출_백만$ | E55: 외화 순노출 × Δ기말환율 (외화 시트 방식) — 외화 순노출 미공시(face) → 0 + 표기
A56: sc:헤지비율 | C56: 헤지비율 | E56: sls 없음
A57: sc:헤지환율_약정 | C57: 헤지환율_약정 | E57: sls 없음

Sheet BS연결
B1: (백만원) | C1: 이름: BS연결H | E1: 4Q21 | F1: 2021 | G1: 1Q22 | H1: 2Q22 | I1: 3Q22 | J1: 4Q22 | K1: 2022 | L1: 1Q23 | M1: 2Q23 | N1: 3Q23 | O1: 4Q23 | P1: 2023 | Q1: 1Q24 | R1: 2Q24 | S1: 3Q24 | T1: 4Q24 | U1: 2024 | V1: 1Q25 | W1: 2Q25 | X1: 3Q25 | Y1: 4Q25 | Z1: 2025 | AA1: 1Q26 | AB1: 2Q26 | AC1: 3Q26 | AD1: 4Q26 | AE1: 2026 | AF1: 1Q27 | AG1: 2Q27 | AH1: 3Q27 | AI1: 4Q27 | AJ1: 2027 | AK1: 1Q28 | AL1: 2Q28 | AM1: 3Q28 | AN1: 4Q28 | AO1: 2028
B2: 연결 | D2: fin json(kship_fin.py)
B3: 에스앤더블류(연) | C3: UPDATE: 26-10-13 | E3: 1 | F3: 2 | G3: 3 | H3: 4 | I3: 5 | J3: 6 | K3: 7 | L3: 8 | M3: 9 | N3: 10 | O3: 11 | P3: 12 | Q3: 13 | R3: 14 | S3: 15 | T3: 16 | U3: 17 | V3: 18 | W3: 19 | X3: 20 | Y3: 21 | Z3: 22 | AA3: 23 | AB3: 24 | AC3: 25 | AD3: 26 | AE3: 27 | AF3: 28 | AG3: 29 | AH3: 30 | AI3: 31 | AJ3: 32 | AK3: 33 | AL3: 34 | AM3: 35 | AN3: 36 | AO3: 37
B4: Account Code | C4: AccountNAME | E4: 2021.12 | F4: 2021.12A | G4: 2022.03 | H4: 2022.06 | I4: 2022.09 | J4: 2022.12 | K4: 2022.12A | L4: 2023.03 | M4: 2023.06 | N4: 2023.09 | O4: 2023.12 | P4: 2023.12A | Q4: 2024.03 | R4: 2024.06 | S4: 2024.09 | T4: 2024.12 | U4: 2024.12A | V4: 2025.03 | W4: 2025.06 | X4: 2025.09 | Y4: 2025.12 | Z4: 2025.12A | AA4: 2026.03 | AB4: 2026.06 | AC4: 2026.09 | AD4: 2026.12 | AE4: 2026.12A | AF4: 2027.03 | AG4: 2027.06 | AH4: 2027.09 | AI4: 2027.12 | AJ4: 2027.12A | AK4: 2028.03 | AL4: 2028.06 | AM4: 2028.09 | AN4: 2028.12 | AO4: 2028.12A

Sheet BS별도
B1: (백만원) | C1: 이름: BS별도H | E1: 4Q21 | F1: 2021 | G1: 1Q22 | H1: 2Q22 | I1: 3Q22 | J1: 4Q22 | K1: 2022 | L1: 1Q23 | M1: 2Q23 | N1: 3Q23 | O1: 4Q23 | P1: 2023 | Q1: 1Q24 | R1: 2Q24 | S1: 3Q24 | T1: 4Q24 | U1: 2024 | V1: 1Q25 | W1: 2Q25 | X1: 3Q25 | Y1: 4Q25 | Z1: 2025 | AA1: 1Q26 | AB1: 2Q26 | AC1: 3Q26 | AD1: 4Q26 | AE1: 2026 | AF1: 1Q27 | AG1: 2Q27 | AH1: 3Q27 | AI1: 4Q27 | AJ1: 2027 | AK1: 1Q28 | AL1: 2Q28 | AM1: 3Q28 | AN1: 4Q28 | AO1: 2028
B2: 별도 | D2: fin json(kship_fin.py)
B3: 에스앤더블류(별) | C3: UPDATE: 26-10-13 | E3: 1 | F3: 2 | G3: 3 | H3: 4 | I3: 5 | J3: 6 | K3: 7 | L3: 8 | M3: 9 | N3: 10 | O3: 11 | P3: 12 | Q3: 13 | R3: 14 | S3: 15 | T3: 16 | U3: 17 | V3: 18 | W3: 19 | X3: 20 | Y3: 21 | Z3: 22 | AA3: 23 | AB3: 24 | AC3: 25 | AD3: 26 | AE3: 27 | AF3: 28 | AG3: 29 | AH3: 30 | AI3: 31 | AJ3: 32 | AK3: 33 | AL3: 34 | AM3: 35 | AN3: 36 | AO3: 37
B4: Account Code | C4: AccountNAME | E4: 2021.12 | F4: 2021.12A | G4: 2022.03 | H4: 2022.06 | I4: 2022.09 | J4: 2022.12 | K4: 2022.12A | L4: 2023.03 | M4: 2023.06 | N4: 2023.09 | O4: 2023.12 | P4: 2023.12A | Q4: 2024.03 | R4: 2024.06 | S4: 2024.09 | T4: 2024.12 | U4: 2024.12A | V4: 2025.03 | W4: 2025.06 | X4: 2025.09 | Y4: 2025.12 | Z4: 2025.12A | AA4: 2026.03 | AB4: 2026.06 | AC4: 2026.09 | AD4: 2026.12 | AE4: 2026.12A | AF4: 2027.03 | AG4: 2027.06 | AH4: 2027.09 | AI4: 2027.12 | AJ4: 2027.12A | AK4: 2028.03 | AL4: 2028.06 | AM4: 2028.09 | AN4: 2028.12 | AO4: 2028.12A
A5: 1 | C5: 유동자산 | E5: 16928.95 | F5: 16928.95 | G5: 18372.65 | H5: 37453.11 | I5: 37007.74 | J5: 38407.88 | K5: 38407.88 | L5: 40090.49 | M5: 39103.81 | N5: 43720.72 | O5: 42551 | P5: 42551 | Q5: 44210.47 | R5: 45311.7 | S5: 41982.95 | T5: 23323.59 | U5: 23323.59 | V5: 21691.17 | W5: 21230.91 | X5: 20855.8 | Y5: 23330.81 | Z5: 23330.81 | AA5: 24350.91 | AB5: 23212.71
A6: 1 | C6: 현금및현금성자산 | E6: 774.77 | F6: 774.77 | G6: 3152.38 | H6: 6286.13 | I6: 5475.69 | J6: 5083.15 | K6: 5083.15 | L6: 4268.21 | M6: 2169.39 | N6: 5101.68 | O6: 4000.15 | P6: 4000.15 | Q6: 3339.54 | R6: 3698.95 | S6: 502.96 | T6: 2709.56 | U6: 2709.56 | V6: 1889.31 | W6: 1127.1 | X6: 1173.68 | Y6: 2382 | Z6: 2382 | AA6: 4081.32 | AB6: 3081.64
A7: 1 | C7: 기타유동금융자산 | E7: 0.01 | F7: 0.01 | G7: 40.84 | H7: 220.07 | I7: 288.56 | J7: 2058.36 | K7: 2058.36 | L7: 2128.47 | M7: 3919.04 | N7: 4317.3 | O7: 3751.17 | P7: 3751.17 | Q7: 2531.14 | R7: 4032.68 | S7: 3904.06 | T7: 0 | U7: 0 | V7: 220.41 | W7: 0 | X7: 0 | Y7: 0 | Z7: 0 | AA7: 0 | AB7: 0
A8: 1 | C8: 단기투자자산(공정가치) | E8: 112.07 | F8: 112.07 | G8: 112.93 | H8: 88.17 | I8: 72.35 | J8: 75.95 | K8: 75.95 | L8: 71.95 | M8: 75.48 | N8: 67.7 | O8: 69.2 | P8: 69.2 | Q8: 66.29 | R8: 61.38 | S8: 53.49 | T8: 51.55 | U8: 51.55 | V8: 49.47 | W8: 57.78 | X8: 53.12 | Y8: 51.57 | Z8: 51.57 | AA8: 28.45 | AB8: 19.97
A9: 1 | C9: 매출채권및기타채권 | E9: 9930.82 | F9: 9930.82 | G9: 8339.34 | H9: 11169.15 | I9: 5164.94 | J9: 10519.41 | K9: 10519.41 | L9: 12759.46 | M9: 11013.32 | N9: 9836.11 | O9: 11665.64 | P9: 11665.64 | Q9: 14062.97 | R9: 12906.34 | S9: 11362.36 | T9: 11713.06 | U9: 11713.06 | V9: 12721.13 | W9: 11943.74 | X9: 9929.68 | Y9: 13634.38 | Z9: 13634.38 | AA9: 11364.46 | AB9: 8272.76
A10: 1 | C10: 기타유동자산 | E10: 66.52 | F10: 66.52 | G10: 36.27 | H10: 29.96 | I10: 179.2 | J10: 38.43 | K10: 38.43 | L10: 56.01 | M10: 42.86 | N10: 47.04 | O10: 49.74 | P10: 49.74 | Q10: 74.42 | R10: 60.61 | S10: 286.37 | T10: 506.18 | U10: 506.18 | V10: 459.79 | W10: 82.25 | X10: 128.17 | Y10: 21.03 | Z10: 21.03 | AA10: 34.46 | AB10: 21.89
A11: 1 | C11: 재고자산 | E11: 10999.32 | F11: 10999.32 | G11: 10838.31 | H11: 10001.6 | I11: 10594.01 | J11: 10642.13 | K11: 10642.13 | L11: 11921.84 | M11: 12125.94 | N11: 13989.97 | O11: 13589.6 | P11: 13589.6 | Q11: 15448.07 | R11: 15739.04 | S11: 16278.67 | T11: 14185.98 | U11: 14185.98 | V11: 12682.12 | W11: 13962.43 | X11: 14511.86 | Y11: 13901.08 | Z11: 13901.08 | AA11: 14504.53 | AB11: 15936.01
A12: 1 | C12: 비유동자산 | E12: 36322.59 | F12: 36322.59 | G12: 36131.97 | H12: 22988.86 | I12: 23831.45 | J12: 23627.08 | K12: 23627.08 | L12: 23476.88 | M12: 23731.51 | N12: 23684.08 | O12: 24217.56 | P12: 24217.56 | Q12: 28816.39 | R12: 29778.16 | S12: 30589.54 | T12: 47973.46 | U12: 47973.46 | V12: 61114.9 | W12: 61541.91 | X12: 63177.54 | Y12: 61946.79 | Z12: 61946.79 | AA12: 62273.3 | AB12: 62703.97
A13: 1 | C13: 장기금융자산 | E13: 0.74 | F13: 0.74 | G13: 0.74 | H13: 1.48 | J13: 0.74 | K13: 0.74 | L13: 0.74 | M13: 1.48 | N13: 1.48 | O13: 0.74 | P13: 0.74 | Q13: 0.74 | R13: 1.48 | S13: 1.48 | T13: 0 | U13: 0 | W13: 0 | X13: 0 | Y13: 0 | Z13: 0 | AA13: 0 | AB13: 0
A14: 1 | C14: 투자자산 | E14: 0.74 | F14: 0.74 | G14: 0.74 | H14: 1.48 | I14: 530.2 | J14: 0.74 | K14: 0.74 | L14: 0.74 | M14: 1.48 | N14: 1.48 | O14: 0.74 | P14: 0.74 | Q14: 0.74 | R14: 1.48 | S14: 1.48 | T14: 0 | U14: 0 | W14: 0 | X14: 0 | Y14: 0 | Z14: 0 | AA14: 0 | AB14: 0
A15: 1 | C15: 유형자산 | E15: 33691.92 | F15: 33691.92 | G15: 34623.78 | H15: 21467.48 | I15: 22416.92 | J15: 22735.83 | K15: 22735.83 | L15: 22572.07 | M15: 22801.31 | N15: 22745.46 | O15: 23215.51 | P15: 23215.51 | Q15: 27861.49 | R15: 28842.58 | S15: 29679.33 | T15: 46812.68 | U15: 46812.68 | V15: 59895.62 | W15: 60520.05 | X15: 62073.44 | Y15: 60777.4 | Z15: 60777.4 | AA15: 61101.38 | AB15: 61501.49
A16: 1 | C16: 무형자산 | E16: 55.32 | F16: 55.32 | G16: 55.53 | H16: 55.46 | I16: 55.38 | J16: 55.31 | K16: 55.31 | L16: 55.23 | M16: 55.15 | N16: 55.08 | O16: 55 | P16: 55 | Q16: 54.93 | R16: 72.25 | S16: 72.32 | T16: 71.29 | U16: 71.29 | V16: 75.9 | W16: 74.58 | X16: 130.89 | Y16: 129.39 | Z16: 129.39 | AA16: 127.93 | AB16: 154.5
A17: 1 | C17: 자산총계 | E17: 53251.54 | F17: 53251.54 | G17: 54504.62 | H17: 60441.97 | I17: 60839.19 | J17: 62034.96 | K17: 62034.96 | L17: 63567.37 | M17: 62835.32 | N17: 67404.8 | O17: 66768.56 | P17: 66768.56 | Q17: 73026.85 | R17: 75089.85 | S17: 72572.48 | T17: 71297.05 | U17: 71297.05 | V17: 82806.08 | W17: 82772.83 | X17: 84033.35 | Y17: 85277.6 | Z17: 85277.6 | AA17: 86624.21 | AB17: 85916.67
A18: 1 | C18: 유동부채 | E18: 5366.02 | F18: 5366.02 | G18: 6467.92 | H18: 10470.27 | I18: 10788.67 | J18: 13414.47 | K18: 13414.47 | L18: 13625.12 | M18: 11445.06 | N18: 15018.61 | O18: 13902.76 | P18: 13902.76 | Q18: 18643.42 | R18: 19702.85 | S18: 17409.02 | T18: 14169.7 | U18: 14169.7 | V18: 10693.51 | W18: 7262.29 | X18: 8109.99 | Y18: 9546.24 | Z18: 9546.24 | AA18: 10788.96 | AB18: 9211.67
A19: 1 | C19: 매입채무및기타채무 | E19: 8247.65 | F19: 8247.65 | G19: 9090.2 | H19: 7941.37 | I19: 4048.77 | J19: 10683.05 | K19: 10683.05 | L19: 12598.01 | M19: 7612.66 | N19: 12186.82 | O19: 5698.67 | P19: 5698.67 | Q19: 5730.02 | R19: 12600.26 | S19: 8508.49 | T19: 9044.78 | U19: 9044.78 | V19: 11622.91 | W19: 10800.42 | X19: 11141.23 | Y19: 13488.81 | Z19: 13488.81 | AA19: 17773.51 | AB19: 13907.61
A20: 1 | C20: 단기차입금 | E20: 320 | F20: 320 | G20: 0 | H20: 0 | J20: 0 | K20: 0 | L20: 0 | M20: 0 | N20: 0 | O20: 0 | P20: 0 | Q20: 4193.09 | Y20: 860.64 | Z20: 860.64 | AA20: 0 | AB20: 0
A21: 1 | C21: 기타유동부채 | E21: 377.01 | F21: 377.01 | G21: 1241.54 | H21: 5807.58 | I21: 5739.9 | J21: 5835.98 | K21: 5835.98 | L21: 6716.62 | M21: 6882.56 | N21: 8113.56 | O21: 8204.09 | P21: 8204.09 | Q21: 12913.4 | R21: 12531.12 | S21: 12362.81 | T21: 8630.71 | U21: 8630.71 | V21: 3495.53 | W21: 645.17 | X21: 732.4 | Y21: 713.75 | Z21: 713.75 | AA21: 270.75 | AB21: 806.26
A22: 1 | C22: 비유동부채 | E22: 9149.87 | F22: 9149.87 | G22: 9316.31 | H22: 9025.17 | I22: 7943.03 | J22: 6093.22 | K22: 6093.22 | L22: 6404 | M22: 6664.96 | N22: 6802.27 | O22: 7436.18 | P22: 7436.18 | Q22: 7896.67 | R22: 8252.68 | S22: 8350.25 | T22: 7306.07 | U22: 7306.07 | V22: 20682.55 | W22: 22971.64 | X22: 22280.92 | Y22: 22252.9 | Z22: 22252.9 | AA22: 22232.3 | AB22: 22154.46
A23: 1 | C23: 장기매입채무및기타채무 | E23: 3000 | F23: 3000 | G23: 3000 | H23: 3000 | I23: 2000 | J23: 0 | K23: 0 | L23: 0 | V23: 12000 | W23: 14500 | X23: 14500 | Y23: 14860 | Z23: 14860 | AA23: 15000 | AB23: 15240
A24: 1 | C24: 장기차입금 | E24: 3000 | F24: 3000 | G24: 3000 | H24: 3000 | I24: 2000 | J24: 0 | K24: 0 | L24: 0 | V24: 12000 | W24: 14500 | X24: 14500 | Y24: 14860 | Z24: 14860 | AA24: 15000 | AB24: 15240
A25: 1 | C25: 확정급여부채 | E25: 3595.35 | F25: 3595.35 | G25: 3767.15 | H25: 3436.41 | I25: 3323.4 | J25: 3562.16 | K25: 3562.16 | L25: 3901.37 | M25: 4086.59 | N25: 4087.58 | O25: 4675.69 | P25: 4675.69 | Q25: 5009.42 | R25: 5336.45 | S25: 5398.64 | T25: 5639.28 | U25: 5639.28 | V25: 6148.22 | W25: 6335.48 | X25: 6232.32 | Y25: 6262.72 | Z25: 6262.72 | AA25: 6588.67 | AB25: 6361.85
A26: 1 | C26: 이연법인세부채 | E26: 2437.34 | F26: 2437.34 | G26: 2437.34 | H26: 2437.34 | I26: 2437.34 | J26: 2326.55 | K26: 2326.55 | L26: 2326.55 | M26: 2326.55 | N26: 2326.55 | O26: 2326.55 | P26: 2326.55 | Q26: 2326.55 | R26: 2326.55 | S26: 2326.55 | T26: 1040.86 | U26: 1040.86 | V26: 1040.86 | W26: 937.16 | X26: 428.76 | Y26: 0 | Z26: 0 | AA26: 0 | AB26: 0
A27: 1 | C27: 기타비유동부채 | E27: 58.12 | F27: 58.12 | G27: 50.18 | H27: 51.62 | I27: 52.26 | J27: 54.12 | K27: 54.12 | L27: 53 | M27: 84.63 | N27: 228.05 | O27: 240.36 | P27: 240.36 | Q27: 370.77 | R27: 387.61 | S27: 429.91 | T27: 432.22 | U27: 432.22 | V27: 556.62 | W27: 369.77 | X27: 281.9 | Y27: 381.99 | Z27: 381.99 | AA27: 0.76 | AB27: 14.35
A28: 1 | C28: 부채총계 | E28: 14515.89 | F28: 14515.89 | G28: 15784.23 | H28: 19495.44 | I28: 18731.7 | J28: 19507.69 | K28: 19507.69 | L28: 20029.13 | M28: 18110.02 | N28: 21820.88 | O28: 21338.94 | P28: 21338.94 | Q28: 26540.09 | R28: 27955.53 | S28: 25759.27 | T28: 21475.77 | U28: 21475.77 | V28: 31376.06 | W28: 30233.93 | X28: 30390.91 | Y28: 31799.14 | Z28: 31799.14 | AA28: 33021.26 | AB28: 31366.13
A29: 1 | C29: 자본금 | E29: 3600 | F29: 3600 | G29: 3600 | H29: 3600 | I29: 3600 | J29: 3600 | K29: 3600 | L29: 3600 | M29: 3600 | N29: 3600 | O29: 3600 | P29: 3600 | Q29: 3600 | R29: 3600 | S29: 3600 | T29: 3600 | U29: 3600 | V29: 3600 | W29: 3600 | X29: 3600 | Y29: 3600 | Z29: 3600 | AA29: 3600 | AB29: 3600
A30: 1 | C30: 자본잉여금 | E30: 24698.88 | F30: 24698.88 | G30: 24698.88 | H30: 26189.24 | I30: 26189.24 | J30: 25861.36 | K30: 25861.36 | L30: 25861.36 | M30: 25861.36 | N30: 25861.36 | O30: 13511.92 | P30: 13511.92 | Q30: 13511.92 | R30: 25861.36 | S30: 25861.36 | T30: 25861.36 | U30: 25861.36 | V30: 25861.36 | W30: 25861.36 | X30: 25861.36 | Y30: 25861.36 | Z30: 25861.36 | AA30: 25861.36 | AB30: 25861.36
A31: 1 | C31: 이익잉여금 | E31: 22786.21 | F31: 22786.21 | G31: 22770.96 | H31: 23506.74 | I31: 24667.69 | J31: 25415.36 | K31: 25415.36 | L31: 26426.33 | M31: 27613.38 | N31: 28472.01 | O31: 28317.7 | P31: 28317.7 | Q31: 29374.85 | R31: 30022.4 | S31: 29701.3 | T31: 32709.36 | U31: 32709.36 | V31: 34318.1 | W31: 35426.98 | X31: 36530.52 | Y31: 36366.54 | Z31: 36366.54 | AA31: 36491.04 | AB31: 37438.63
A32: 1 | C32: 자본총계 | E32: 38735.65 | F32: 38735.65 | G32: 38720.4 | H32: 40946.53 | I32: 42107.49 | J32: 42527.27 | K32: 42527.27 | L32: 43538.24 | M32: 44725.3 | N32: 45583.92 | O32: 45429.62 | P32: 45429.62 | Q32: 46486.76 | R32: 47134.32 | S32: 46813.21 | T32: 49821.27 | U32: 49821.27 | V32: 51430.01 | W32: 52538.9 | X32: 53642.44 | Y32: 53478.46 | Z32: 53478.46 | AA32: 53602.95 | AB32: 54550.54
A33: 1 | C33: 부채와자본총계 | E33: 53251.54 | F33: 53251.54 | G33: 54504.62 | H33: 60441.97 | I33: 60839.19 | J33: 62034.96 | K33: 62034.96 | L33: 63567.37 | M33: 62835.32 | N33: 67404.8 | O33: 66768.56 | P33: 66768.56 | Q33: 73026.85 | R33: 75089.85 | S33: 72572.48 | T33: 71297.05 | U33: 71297.05 | V33: 82806.08 | W33: 82772.83 | X33: 84033.35 | Y33: 85277.6 | Z33: 85277.6 | AA33: 86624.21 | AB33: 85916.67
A34: 1 | C34: 지배주주지분 | E34: 38735.65 | F34: 38735.65 | G34: 38720.4 | H34: 40946.53 | I34: 42107.49 | J34: 42527.27 | K34: 42527.27 | L34: 43538.24 | M34: 44725.3 | N34: 45583.92 | O34: 45429.62 | P34: 45429.62 | Q34: 46486.76 | R34: 47134.32 | S34: 46813.21 | T34: 49821.27 | U34: 49821.27 | V34: 51430.01 | W34: 52538.9 | X34: 53642.44 | Y34: 53478.46 | Z34: 53478.46 | AA34: 53602.95 | AB34: 54550.54
A35: 1 | C35: 총차입금 | E35: 3320 | F35: 3320 | G35: 3000 | H35: 3000 | I35: 3000 | J35: 3000 | K35: 3000 | L35: 0 | M35: 0 | N35: 0 | O35: 0 | P35: 0 | Q35: 4193.09 | T35: 0 | U35: 0 | V35: 12000 | W35: 14500 | X35: 14500 | Y35: 15720.64 | Z35: 15720.64 | AA35: 15000 | AB35: 15240
A36: 1 | C36: 순차입금 | E36: 2545.23 | F36: 2545.23 | G36: -152.38 | H36: -3286.13 | I36: -2475.69 | J36: -2083.15 | K36: -2083.15 | L36: -4268.21 | M36: -2169.39 | N36: -5101.68 | O36: -4000.15 | P36: -4000.15 | Q36: 853.55 | T36: -2709.56 | U36: -2709.56 | V36: 10110.69 | W36: 13372.9 | X36: 13326.32 | Y36: 13338.64 | Z36: 13338.64 | AA36: 10918.68 | AB36: 12158.36
A37: 1 | C37: 이자발생자산 | E37: 775.51 | F37: 775.51 | G37: 3153.12 | H37: 6287.61 | I37: 5475.69 | J37: 5083.89 | K37: 5083.89 | L37: 4268.95 | M37: 2170.87 | N37: 5103.16 | O37: 4000.89 | P37: 4000.89 | Q37: 3340.28 | R37: 3700.43 | S37: 504.44 | T37: 2709.56 | U37: 2709.56 | V37: 1889.31 | W37: 1127.1 | X37: 1173.68 | Y37: 2382 | Z37: 2382 | AA37: 4081.32 | AB37: 3081.64
A38: 1 | C38: 매각예정비유동자산및처분자산 | H38: 15233 | I38: 15233 | J38: 15233 | K38: 15233 | L38: 15233 | M38: 15233 | N38: 15233 | O38: 15233 | P38: 15233 | Q38: 15233 | R38: 15233 | S38: 15233 | T38: 0 | U38: 0 | Y38: 0 | Z38: 0
A39: 1 | C39: 기타자본 | H39: 1490.36 | I39: 1490.36 | J39: 1162.48 | K39: 1162.48 | L39: 1162.48 | M39: 1162.48 | N39: 1162.48 | R39: 1162.48 | S39: 1162.48 | T39: 1162.48 | U39: 1162.48 | V39: 1162.48 | W39: 1162.48 | X39: 1162.48 | Y39: 1162.48 | Z39: 1162.48 | AA39: 1162.48 | AB39: 1162.48
A40: 1 | C40: 종속기업및관계기업투자 | I40: 530.2
A41: 1 | C41: 유동성장기부채 | I41: 1000 | J41: 3000 | K41: 3000 | L41: 0 | M41: 0 | N41: 0 | T41: 0 | U41: 0 | V41: 0 | Y41: 0 | Z41: 0 | AA41: 0 | AB41: 0
A42: 1 | C42: 단기금융부채(face) | N42: 0
A43: 1 | C43: 기타비유동자산 | T43: 0 | U43: 0 | W43: 0 | X43: 0
A44: 1 | C44: 당기법인세부채(미지급법인세) | V44: 256.75 | W44: 56.94 | X44: 62.35 | Y44: 31.71 | Z44: 31.71 | AA44: 96.27 | AB44: 1.49
A45: 1 | C45: 이연법인세자산 | Y45: 84.88 | Z45: 84.88 | AA45: 84.88 | AB45: 84.88
A46: 1 | C46: 매출액(수익) | E46: 9305.26 | G46: 7359.45 | H46: 9565.54 | I46: 8897.04 | J46: 10193.84 | K46: 36015.87 | L46: 10968.43 | M46: 11538.2 | N46: 9901.18 | O46: 11225.78 | P46: 43633.59 | Q46: 10688.52 | R46: 11523.92 | S46: 9710.02 | T46: 15207.78 | U46: 47130.24 | V46: 12538.68 | W46: 12033.72 | X46: 11642.37 | Y46: 12589.51 | Z46: 48804.28 | AA46: 11493.51 | AB46: 12796.36
A47: 1 | C47: 매출원가 | E47: 7223.52 | G47: 6658.74 | H47: 8451.78 | I47: 7010.25 | J47: 8470.38 | K47: 30591.15 | L47: 8997.12 | M47: 9369.71 | N47: 8136.14 | O47: 10124.41 | P47: 36627.38 | Q47: 8468.72 | R47: 9669.03 | S47: 9143.21 | T47: 12092.46 | U47: 39373.42 | V47: 11297.74 | W47: 10117.16 | X47: 9852.09 | Y47: 11378.46 | Z47: 42645.45 | AA47: 10412.41 | AB47: 11030.16
A48: 1 | C48: 매출총이익 | E48: 2081.74 | G48: 700.71 | H48: 1113.76 | I48: 1886.79 | J48: 1723.46 | K48: 5424.72 | L48: 1971.31 | M48: 2168.49 | N48: 1765.04 | O48: 1101.37 | P48: 7006.21 | Q48: 2219.8 | R48: 1854.89 | S48: 566.81 | T48: 3115.32 | U48: 7756.82 | V48: 1240.95 | W48: 1916.56 | X48: 1790.28 | Y48: 1211.05 | Z48: 6158.84 | AA48: 1081.1 | AB48: 1766.2
A49: 1 | C49: 판관비 | E49: 621.68 | G49: 643.48 | H49: 749.59 | I49: 943.4 | J49: 588.63 | K49: 2925.1 | L49: 859.03 | M49: 1024.24 | N49: 1161.9 | O49: 728.38 | P49: 3773.55 | Q49: 1162.96 | R49: 1098.62 | S49: 1038.47 | T49: 1000.9 | U49: 4300.95 | V49: 1317.12 | W49: 1207.04 | X49: 1420.5 | Y49: 1313.19 | Z49: 5257.85 | AA49: 772.16 | AB49: 1351.5
A50: 1 | C50: 영업이익 | E50: 1460.06 | G50: 57.23 | H50: 364.18 | I50: 943.39 | J50: 1134.83 | K50: 2499.63 | L50: 1112.29 | M50: 1144.25 | N50: 603.14 | O50: 372.99 | P50: 3232.67 | Q50: 1056.84 | R50: 756.27 | S50: -471.66 | T50: 2114.43 | U50: 3455.88 | V50: -76.18 | W50: 709.52 | X50: 369.78 | Y50: -102.14 | Z50: 900.98 | AA50: 308.94 | AB50: 414.7
A51: 1 | C51: 기타영업외수익 | E51: 51.97 | G51: 144.88 | H51: 6.75 | I51: 47.24 | J51: 16.26 | K51: 215.13 | L51: 46.29 | M51: 9.2 | N51: 22.55 | O51: 71.91 | P51: 149.95 | Q51: 30.88 | R51: 25.89 | S51: 29.31 | T51: 46.74 | U51: 132.82 | V51: 2320.71 | W51: 64.1 | X51: 17.89 | Y51: 49.38 | Z51: 2452.08 | AA51: 46.53 | AB51: 56.72
A52: 1 | C52: 기타영업외비용 | E52: 90.28 | G52: 5.61 | H52: 2.5 | I52: -4.74 | J52: 17.29 | K52: 20.66 | L52: 29.55 | M52: -5.59 | N52: 30.13 | O52: 3.56 | P52: 57.65 | Q52: 0.88 | R52: 1.28 | S52: 1.77 | T52: 316.19 | U52: 320.12 | V52: 113.82 | W52: 6.47 | X52: 1.72 | Y52: 724.76 | Z52: 846.77 | AA52: 0.69 | AB52: 0.39
A53: 1 | C53: 금융수익 | E53: -0.06 | G53: 35.41 | H53: 24.47 | I53: 58.73 | J53: 30.42 | K53: 149.03 | L53: 112.94 | M53: 90 | N53: 104.46 | O53: 18.48 | P53: 325.88 | Q53: 98.61 | R53: 115.38 | S53: 11.73 | T53: 125.01 | U53: 350.73 | V53: 94.23 | W53: 24.74 | X53: 49.7 | Y53: 25.94 | Z53: 194.61 | AA53: 90.47 | AB53: 74.9
A54: 1 | C54: 금융비용 | E54: 27.8 | G54: 20.16 | H54: 38.82 | I54: 36.15 | J54: 79.86 | K54: 174.99 | L54: 24.37 | M54: 3.88 | N54: 7.8 | O54: -2.04 | P54: 34.01 | Q54: 6.9 | R54: 7.56 | S54: 37.56 | T54: -5.29 | U54: 46.73 | V54: 58.12 | W54: 18.44 | X54: 67.68 | Y54: 21.51 | Z54: 165.75 | AA54: 62.91 | AB54: 58.09
A55: 1 | C55: 종속기업,공동지배기업및관계기업관련손익 | E55: -370.16 | G55: -225.81 | H55: 4.31 | I55: -110.75 | J55: -530.2 | K55: -862.45 | L55: 0 | M55: 0 | N55: 0 | R55: 0 | S55: 0 | T55: 0 | V55: 0 | X55: 0 | Y55: 0 | AA55: 0 | AB55: 0
A56: 1 | C56: 지분법관련손익 | E56: -370.16 | G56: -225.81 | H56: 4.31 | I56: -110.75 | J56: -530.2 | K56: -862.45 | L56: 0 | M56: 0 | N56: 0 | R56: 0 | S56: 0 | T56: 0 | V56: 0 | X56: 0 | Y56: 0 | AA56: 0 | AB56: 0
A57: 1 | C57: 법인세비용차감전계속사업이익 | E57: 1023.73 | G57: -14.07 | H57: 358.39 | I57: 907.18 | J57: 554.16 | K57: 1805.66 | L57: 1217.6 | M57: 1245.17 | N57: 692.23 | O57: 461.87 | P57: 3616.87 | Q57: 1178.54 | R57: 891.26 | S57: -466.4 | T57: 1970.96 | U57: 3574.36 | V57: 2166.82 | W57: 773.45 | X57: 367.98 | Y57: -773.08 | Z57: 2535.17 | AA57: 382.33 | AB57: 487.84
A58: 1 | C58: 법인세비용 | E58: -71.75 | G58: 0.26 | H58: -0.26 | I58: 0 | J58: -519.48 | K58: -519.48 | L58: 43.39 | M58: 12.2 | N58: -34.94 | O58: 129.4 | P58: 150.05 | Q58: 25.49 | R58: 51.59 | S58: -30.51 | T58: -1233.48 | U58: -1186.91 | V58: 321.17 | W58: -308.91 | X58: -551.2 | Y58: -557.06 | Z58: -1096 | AA58: 116.18 | AB58: -147.18
A59: 1 | C59: 당기순이익 | E59: 1095.48 | G59: -14.33 | H59: 358.65 | I59: 907.18 | J59: 1073.64 | K59: 2325.14 | L59: 1174.21 | M59: 1232.97 | N59: 727.17 | O59: 332.48 | P59: 3466.83 | Q59: 1153.05 | R59: 839.67 | S59: -435.89 | T59: 3204.44 | U59: 4761.27 | V59: 1845.65 | W59: 1082.36 | X59: 919.17 | Y59: -216.02 | Z59: 3631.16 | AA59: 266.15 | AB59: 635.01
A60: 1 | C60: 금융손익 | E60: -27.86 | G60: 15.25 | H60: -14.35 | I60: 22.58 | J60: -49.44 | K60: -25.96 | L60: 88.57 | M60: 86.12 | N60: 96.66 | O60: 20.52 | P60: 291.87 | Q60: 91.71 | R60: 107.82 | S60: -25.83 | T60: 130.3 | U60: 304 | V60: 36.11 | W60: 6.3 | X60: -17.98 | Y60: 4.43 | Z60: 28.86 | AA60: 27.56 | AB60: 16.81
A61: 1 | C61: 기타영업외손익 | E61: -38.31 | G61: 139.27 | H61: 4.25 | I61: 51.98 | J61: -1.03 | K61: 194.47 | L61: 16.74 | M61: 14.79 | N61: -7.58 | O61: 68.35 | P61: 92.3 | Q61: 30 | R61: 24.61 | S61: 27.54 | T61: -269.45 | U61: -187.3 | V61: 2206.89 | W61: 57.63 | X61: 16.17 | Y61: -675.38 | Z61: 1605.31 | AA61: 45.84 | AB61: 56.33
A62: 1 | C62: (지배주주지분)당기순이익 | E62: 1095.48 | G62: -14.33 | H62: 358.65 | I62: 907.18 | J62: 1073.64 | K62: 2325.14 | L62: 1174.21 | M62: 1232.97 | N62: 727.17 | O62: 332.48 | P62: 3466.83 | Q62: 1153.05 | R62: 839.67 | S62: -435.89 | T62: 3204.44 | U62: 4761.27 | V62: 1845.65 | W62: 1082.36 | X62: 919.17 | Y62: -216.02 | Z62: 3631.16 | AA62: 266.15 | AB62: 635.01
A63: 1 | C63: 계속사업이익 | E63: 1095.48 | G63: -14.33 | H63: 358.65 | I63: 907.18 | J63: 1073.64 | K63: 2325.14 | L63: 1174.21 | M63: 1232.97 | N63: 727.17 | O63: 332.48 | P63: 3466.83 | Q63: 1153.05 | R63: 839.67 | S63: -435.89 | T63: 3204.44 | U63: 4761.27 | V63: 1845.65 | W63: 1082.36 | X63: 919.17 | Y63: -216.02 | Z63: 3631.16 | AA63: 266.15 | AB63: 635.01
A64: 1 | C64: 총포괄손익 | G64: -15.25 | H64: 735.78 | L64: 1010.97 | M64: 1187.06 | N64: 858.62 | O64: -154.3 | P64: 2902.35 | Q64: 1057.14 | R64: 645.6 | S64: -321.11 | T64: 3008.07 | U64: 4389.7 | V64: 1608.74 | W64: 1108.88 | X64: 1103.54 | Y64: -163.98 | Z64: 3657.18 | AA64: 124.5 | AB64: 947.59
A65: 1 | C65: 이자수익 | AA65: 12.38
A66: 1 | C66: 이자비용 | AA66: 46.49
A67: 1 | C67: 외환차익 | AA67: 4.44
A68: 1 | C68: 외환차손 | AA68: 6.09
A69: 1 | C69: 외화환산이익 | AA69: 72.7
A70: 1 | C70: 외화환산손실 | AA70: 5.66
A71: 1 | C71: 이자손익 | AA71: -34.11
A72: 1 | C72: 영업활동으로인한현금흐름 | E72: 895.74 | G72: 2927.98 | H72: -1662.71 | I72: 194.59 | J72: 2230.76 | K72: 3690.62 | L72: 1517.47 | M72: 53.35 | N72: 2096.93 | O72: 544.15 | P72: 4211.9 | Q72: 3799.22 | R72: 2002.58 | S72: -2283.35 | T72: 938.89 | U72: 4457.34 | V72: -409.92 | W72: 1939.8 | X72: 861.85 | Y72: 411.74 | Z72: 2803.47 | AA72: 3402.04 | AB72: -7.16
A73: 1 | C73: 이자수취(CF) | E73: 2.15 | G73: 27.73 | H73: 3.99 | I73: 29.2 | J73: 35.4 | K73: 96.32 | L73: 37.65 | M73: 40.74 | N73: 53.4 | O73: 60.85 | P73: 192.64 | Q73: 53.55 | R73: 42.96 | S73: 61.13 | T73: 26.05 | U73: 183.69 | V73: 42.88 | W73: 10.74 | X73: -10.31 | Y73: -11.47 | Z73: 31.84 | AA73: 12.17 | AB73: 8.44
A74: 1 | C74: 이자지급(CF) | E74: -12.46 | G74: -13.28 | H74: -17.31 | I74: -19.85 | J74: -22.95 | K74: -73.39 | L74: -16.48 | M74: 0 | Q74: -0.04 | V74: -30.57
A75: 1 | C75: 투자활동으로인한현금흐름 | E75: 368.47 | G75: -239.42 | H75: 3285.88 | I75: -998.02 | J75: -2613.12 | K75: -564.68 | L75: 650.79 | M75: -2156.83 | N75: 842.71 | O75: -1747.77 | P75: -2411.1 | Q75: -4470.03 | R75: -1629.69 | S75: -894.57 | T75: 1132.21 | U75: -5862.08 | V75: -12366.56 | W75: -5067.68 | X75: -721.79 | Y75: -444.15 | Z75: -18600.18 | AA75: -909.24 | AB75: -1150.86
A76: 1 | C76: 유형자산의감소 | E76: 185.84 | G76: 30 | H76: 6.82 | I76: 7.17 | J76: 1 | K76: 44.99 | L76: 39.69 | M76: 0 | N76: 0 | O76: 91.38 | P76: 131.07 | Q76: 6.56 | R76: 0.37 | S76: 0 | T76: 6.85 | U76: 13.78 | V76: 285.77 | W76: 1.18 | X76: 4.83 | Y76: 31.27 | Z76: 323.05
A77: 1 | C77: 유형자산의증가 | E77: 108.74 | G77: 978 | H77: 2114.58 | I77: 1039.2 | J77: 779.95 | K77: 4911.73 | L77: 102.59 | M77: 324.47 | N77: 65.45 | O77: 1036.97 | P77: 1529.48 | Q77: 4860.91 | R77: 1032.39 | S77: 1049.54 | T77: 2530.72 | U77: 9473.56 | V77: 12134.73 | W77: 1234.71 | X77: 479.46 | Y77: 502.88 | Z77: 14351.78 | AA77: 65.03 | AB77: 1164.01
A78: 1 | C78: CAPEX | E78: 108.74 | G78: 978.29 | H78: 2114.58 | I78: 1039.2 | J78: 779.95 | K78: 4912.02 | L78: 102.59 | M78: 324.47 | N78: 65.45 | O78: 1036.97 | P78: 1529.48 | Q78: 4860.91 | R78: 1041.39 | S78: 1050.62 | T78: 2530.72 | U78: 9483.64 | V78: 12140.57 | W78: 1234.71 | X78: 537.25 | Y78: 502.88 | Z78: 14415.41 | AA78: 65.03 | AB78: 1164.01
A79: 1 | C79: 무형자산의증가 | E79: 0 | G79: 0.29 | H79: 0 | I79: 0 | J79: 0 | K79: 0.29 | L79: 0 | M79: 0 | S79: 1.08 | T79: 0 | V79: 5.84 | W79: 0 | X79: 57.79 | Y79: 0 | Z79: 63.63
A80: 1 | C80: 재무활동으로인한현금흐름 | E80: -902.02 | G80: -317.43 | H80: 1491.95 | I80: 4.1 | J80: 60.15 | K80: 1238.77 | L80: -2982.25 | M80: -2.83 | N80: -4.25 | O80: 104.45 | P80: -2884.88 | Q80: -6.25 | R80: -8.25 | S80: -7.43 | T80: 131.74 | U80: 109.81 | V80: 11932.92 | W80: 2388.94 | X80: -93.43 | Y80: 1230.45 | Z80: 15458.88 | AA80: -828.57 | AB80: 134.83
A81: 1 | C81: 단기차입금의증가 | E81: 5780 | G81: 1690 | H81: 60 | I81: 0 | J81: 0 | K81: 1750 | L81: 0 | M81: 0 | Q81: 196 | R81: 0 | S81: 0 | T81: 0 | U81: 196
A82: 1 | C82: 장기차입금의증가 | E82: 0 | L82: 0 | M82: 0 | V82: 12000 | W82: 2500 | X82: 0 | Y82: 360 | Z82: 14860 | AA82: 140 | AB82: 240
A83: 1 | C83: 단기차입금의감소 | E83: 6686 | G83: 2010 | H83: 60 | I83: 0 | J83: 0 | K83: 2070 | L83: 0 | Q83: 196 | R83: 0 | S83: 0 | T83: 0 | U83: 196 | AA83: 860.64 | AB83: 0
A84: 1 | C84: 리스부채의상환 | E84: 0 | I84: 2.48 | J84: 10.93 | L84: 8.69 | M84: 8.33 | N84: 8.77 | O84: 8.77 | P84: 34.56 | Q84: 8.77 | R84: 10.09 | S84: 9.25 | T84: 8.91 | U84: 37.02 | V84: 78.91 | W84: 99.64 | X84: 106.43 | Y84: 107.17 | Z84: 392.15 | AA84: 107.92 | AB84: 105.18
A85: 1 | C85: 현금및현금성자산의증감 | E85: 357.51 | G85: 2377.62 | H85: 3133.75 | I85: -810.45 | J85: -392.54 | K85: 4308.38 | L85: -814.94 | M85: -2098.81 | N85: 2932.29 | O85: -1101.54 | P85: -1083 | Q85: -660.61 | R85: 359.42 | S85: -3195.99 | T85: 2206.59 | U85: -1290.59 | V85: -820.25 | W85: -762.21 | X85: 46.58 | Y85: 1208.32 | Z85: -327.56 | AA85: 1699.32 | AB85: -999.68
A86: 1 | C86: 기말현금및현금성자산 | E86: 357.52 | G86: 3152.38 | H86: 3133.75 | I86: -810.44 | J86: -392.54 | K86: 5083.15 | L86: 4268.21 | M86: -2098.82 | N86: 2932.29 | O86: -1101.53 | P86: 4000.15 | Q86: 3339.54 | R86: 359.41 | S86: -3195.99 | T86: 2206.6 | U86: 2709.56 | V86: 1889.31 | W86: -762.21 | X86: 46.58 | Y86: 1208.32 | Z86: 2382 | AA86: 4081.32 | AB86: -999.68
A87: 1 | C87: 법인세납부(CF) | L87: -5.75 | M87: 11.59 | N87: -8.25 | V87: -1.44
A88: 1 | C88: 유동성장기부채의감소 | L88: 3000 | M88: 0 | N88: 0 | O88: 0 | P88: 3000

Sheet subQ
A1: YQ | C1: subQ 분기 서브모델(억원, U=100) | E1: 4Q21 | F1: 2021 | G1: 1Q22 | H1: 2Q22 | I1: 3Q22 | J1: 4Q22 | K1: 2022 | L1: 1Q23 | M1: 2Q23 | N1: 3Q23 | O1: 4Q23 | P1: 2023 | Q1: 1Q24 | R1: 2Q24 | S1: 3Q24 | T1: 4Q24 | U1: 2024 | V1: 1Q25 | W1: 2Q25 | X1: 3Q25 | Y1: 4Q25 | Z1: 2025 | AA1: 1Q26 | AB1: 2Q26 | AC1: 3Q26 | AD1: 4Q26 | AE1: 2026 | AF1: 1Q27 | AG1: 2Q27 | AH1: 3Q27 | AI1: 4Q27 | AJ1: 2027 | AK1: 1Q28 | AL1: 2Q28 | AM1: 3Q28 | AN1: 4Q28 | AO1: 2028
A2: A=이름(key) B=그룹 C=단위 D=FnGuide 계정명(VLOOKUP 키). 확정=VLOOKUP(BS), 추정=변수 가정 참조
E3: 1 | F3: 2 | G3: 3 | H3: 4 | I3: 5 | J3: 6 | K3: 7 | L3: 8 | M3: 9 | N3: 10 | O3: 11 | P3: 12 | Q3: 13 | R3: 14 | S3: 15 | T3: 16 | U3: 17 | V3: 18 | W3: 19 | X3: 20 | Y3: 21 | Z3: 22 | AA3: 23 | AB3: 24 | AC3: 25 | AD3: 26 | AE3: 27 | AF3: 28 | AG3: 29 | AH3: 30 | AI3: 31 | AJ3: 32 | AK3: 33 | AL3: 34 | AM3: 35 | AN3: 36 | AO3: 37
E4: 2021.12 | F4: 2021.12A | G4: 2022.03 | H4: 2022.06 | I4: 2022.09 | J4: 2022.12 | K4: 2022.12A | L4: 2023.03 | M4: 2023.06 | N4: 2023.09 | O4: 2023.12 | P4: 2023.12A | Q4: 2024.03 | R4: 2024.06 | S4: 2024.09 | T4: 2024.12 | U4: 2024.12A | V4: 2025.03 | W4: 2025.06 | X4: 2025.09 | Y4: 2025.12 | Z4: 2025.12A | AA4: 2026.03 | AB4: 2026.06 | AC4: 2026.09 | AD4: 2026.12 | AE4: 2026.12A | AF4: 2027.03 | AG4: 2027.06 | AH4: 2027.09 | AI4: 2027.12 | AJ4: 2027.12A | AK4: 2028.03 | AL4: 2028.06 | AM4: 2028.09 | AN4: 2028.12 | AO4: 2028.12A
A5: 매출액 | B5: 손익 | C5: 억원 | D5: 매출액(수익) | E5: =IFERROR(VLOOKUP($D5,BS별도,MATCH(E$1,BS별도H,0),0)/100,"") | G5: =IFERROR(VLOOKUP($D5,BS별도,MATCH(G$1,BS별도H,0),0)/100,"") | H5: =IFERROR(VLOOKUP($D5,BS별도,MATCH(H$1,BS별도H,0),0)/100,"") | I5: =IFERROR(VLOOKUP($D5,BS별도,MATCH(I$1,BS별도H,0),0)/100,"") | J5: =IFERROR(VLOOKUP($D5,BS별도,MATCH(J$1,BS별도H,0),0)/100,"") | K5: =SUM(G5:J5) | L5: =IFERROR(VLOOKUP($D5,BS별도,MATCH(L$1,BS별도H,0),0)/100,"") | M5: =IFERROR(VLOOKUP($D5,BS별도,MATCH(M$1,BS별도H,0),0)/100,"") | N5: =IFERROR(VLOOKUP($D5,BS별도,MATCH(N$1,BS별도H,0),0)/100,"") | O5: =IFERROR(VLOOKUP($D5,BS별도,MATCH(O$1,BS별도H,0),0)/100,"") | P5: =SUM(L5:O5) | Q5: =IFERROR(VLOOKUP($D5,BS별도,MATCH(Q$1,BS별도H,0),0)/100,"") | R5: =IFERROR(VLOOKUP($D5,BS별도,MATCH(R$1,BS별도H,0),0)/100,"") | S5: =IFERROR(VLOOKUP($D5,BS별도,MATCH(S$1,BS별도H,0),0)/100,"") | T5: =IFERROR(VLOOKUP($D5,BS별도,MATCH(T$1,BS별도H,0),0)/100,"") | U5: =SUM(Q5:T5) | V5: =IFERROR(VLOOKUP($D5,BS별도,MATCH(V$1,BS별도H,0),0)/100,"") | W5: =IFERROR(VLOOKUP($D5,BS별도,MATCH(W$1,BS별도H,0),0)/100,"") | X5: =IFERROR(VLOOKUP($D5,BS별도,MATCH(X$1,BS별도H,0),0)/100,"") | Y5: =IFERROR(VLOOKUP($D5,BS별도,MATCH(Y$1,BS별도H,0),0)/100,"") | Z5: =SUM(V5:Y5) | AA5: =IFERROR(VLOOKUP($D5,BS별도,MATCH(AA$1,BS별도H,0),0)/100,"") | AB5: =IFERROR(VLOOKUP($D5,BS별도,MATCH(AB$1,BS별도H,0),0)/100,"") | AC5: =IFERROR(X5*(1+변수!AC21),"") | AD5: =IFERROR(Y5*(1+변수!AD21),"") | AE5: =SUM(AA5:AD5) | AF5: =IFERROR(AA5*(1+변수!AF21),"") | AG5: =IFERROR(AB5*(1+변수!AG21),"") | AH5: =IFERROR(AC5*(1+변수!AH21),"") | AI5: =IFERROR(AD5*(1+변수!AI21),"") | AJ5: =SUM(AF5:AI5) | AK5: =IFERROR(AF5*(1+변수!AK21),"") | AL5: =IFERROR(AG5*(1+변수!AL21),"") | AM5: =IFERROR(AH5*(1+변수!AM21),"") | AN5: =IFERROR(AI5*(1+변수!AN21),"") | AO5: =SUM(AK5:AN5)
A6: 매출원가 | B6: 손익 | C6: 억원 | D6: 매출원가 | E6: =IFERROR(VLOOKUP($D6,BS별도,MATCH(E$1,BS별도H,0),0)/100,"") | G6: =IFERROR(VLOOKUP($D6,BS별도,MATCH(G$1,BS별도H,0),0)/100,"") | H6: =IFERROR(VLOOKUP($D6,BS별도,MATCH(H$1,BS별도H,0),0)/100,"") | I6: =IFERROR(VLOOKUP($D6,BS별도,MATCH(I$1,BS별도H,0),0)/100,"") | J6: =IFERROR(VLOOKUP($D6,BS별도,MATCH(J$1,BS별도H,0),0)/100,"") | K6: =SUM(G6:J6) | L6: =IFERROR(VLOOKUP($D6,BS별도,MATCH(L$1,BS별도H,0),0)/100,"") | M6: =IFERROR(VLOOKUP($D6,BS별도,MATCH(M$1,BS별도H,0),0)/100,"") | N6: =IFERROR(VLOOKUP($D6,BS별도,MATCH(N$1,BS별도H,0),0)/100,"") | O6: =IFERROR(VLOOKUP($D6,BS별도,MATCH(O$1,BS별도H,0),0)/100,"") | P6: =SUM(L6:O6) | Q6: =IFERROR(VLOOKUP($D6,BS별도,MATCH(Q$1,BS별도H,0),0)/100,"") | R6: =IFERROR(VLOOKUP($D6,BS별도,MATCH(R$1,BS별도H,0),0)/100,"") | S6: =IFERROR(VLOOKUP($D6,BS별도,MATCH(S$1,BS별도H,0),0)/100,"") | T6: =IFERROR(VLOOKUP($D6,BS별도,MATCH(T$1,BS별도H,0),0)/100,"") | U6: =SUM(Q6:T6) | V6: =IFERROR(VLOOKUP($D6,BS별도,MATCH(V$1,BS별도H,0),0)/100,"") | W6: =IFERROR(VLOOKUP($D6,BS별도,MATCH(W$1,BS별도H,0),0)/100,"") | X6: =IFERROR(VLOOKUP($D6,BS별도,MATCH(X$1,BS별도H,0),0)/100,"") | Y6: =IFERROR(VLOOKUP($D6,BS별도,MATCH(Y$1,BS별도H,0),0)/100,"") | Z6: =SUM(V6:Y6) | AA6: =IFERROR(VLOOKUP($D6,BS별도,MATCH(AA$1,BS별도H,0),0)/100,"") | AB6: =IFERROR(VLOOKUP($D6,BS별도,MATCH(AB$1,BS별도H,0),0)/100,"") | AC6: =IFERROR(AC5-AC7,"") | AD6: =IFERROR(AD5-AD7,"") | AE6: =SUM(AA6:AD6) | AF6: =IFERROR(AF5-AF7,"") | AG6: =IFERROR(AG5-AG7,"") | AH6: =IFERROR(AH5-AH7,"") | AI6: =IFERROR(AI5-AI7,"") | AJ6: =SUM(AF6:AI6) | AK6: =IFERROR(AK5-AK7,"") | AL6: =IFERROR(AL5-AL7,"") | AM6: =IFERROR(AM5-AM7,"") | AN6: =IFERROR(AN5-AN7,"") | AO6: =SUM(AK6:AN6)
A7: 매출총이익 | B7: 손익 | C7: 억원 | D7: 매출총이익 | E7: =IFERROR(VLOOKUP($D7,BS별도,MATCH(E$1,BS별도H,0),0)/100,"") | G7: =IFERROR(VLOOKUP($D7,BS별도,MATCH(G$1,BS별도H,0),0)/100,"") | H7: =IFERROR(VLOOKUP($D7,BS별도,MATCH(H$1,BS별도H,0),0)/100,"") | I7: =IFERROR(VLOOKUP($D7,BS별도,MATCH(I$1,BS별도H,0),0)/100,"") | J7: =IFERROR(VLOOKUP($D7,BS별도,MATCH(J$1,BS별도H,0),0)/100,"") | K7: =SUM(G7:J7) | L7: =IFERROR(VLOOKUP($D7,BS별도,MATCH(L$1,BS별도H,0),0)/100,"") | M7: =IFERROR(VLOOKUP($D7,BS별도,MATCH(M$1,BS별도H,0),0)/100,"") | N7: =IFERROR(VLOOKUP($D7,BS별도,MATCH(N$1,BS별도H,0),0)/100,"") | O7: =IFERROR(VLOOKUP($D7,BS별도,MATCH(O$1,BS별도H,0),0)/100,"") | P7: =SUM(L7:O7) | Q7: =IFERROR(VLOOKUP($D7,BS별도,MATCH(Q$1,BS별도H,0),0)/100,"") | R7: =IFERROR(VLOOKUP($D7,BS별도,MATCH(R$1,BS별도H,0),0)/100,"") | S7: =IFERROR(VLOOKUP($D7,BS별도,MATCH(S$1,BS별도H,0),0)/100,"") | T7: =IFERROR(VLOOKUP($D7,BS별도,MATCH(T$1,BS별도H,0),0)/100,"") | U7: =SUM(Q7:T7) | V7: =IFERROR(VLOOKUP($D7,BS별도,MATCH(V$1,BS별도H,0),0)/100,"") | W7: =IFERROR(VLOOKUP($D7,BS별도,MATCH(W$1,BS별도H,0),0)/100,"") | X7: =IFERROR(VLOOKUP($D7,BS별도,MATCH(X$1,BS별도H,0),0)/100,"") | Y7: =IFERROR(VLOOKUP($D7,BS별도,MATCH(Y$1,BS별도H,0),0)/100,"") | Z7: =SUM(V7:Y7) | AA7: =IFERROR(VLOOKUP($D7,BS별도,MATCH(AA$1,BS별도H,0),0)/100,"") | AB7: =IFERROR(VLOOKUP($D7,BS별도,MATCH(AB$1,BS별도H,0),0)/100,"") | AC7: =IFERROR(AC9+AC8,"") | AD7: =IFERROR(AD9+AD8,"") | AE7: =SUM(AA7:AD7) | AF7: =IFERROR(AF9+AF8,"") | AG7: =IFERROR(AG9+AG8,"") | AH7: =IFERROR(AH9+AH8,"") | AI7: =IFERROR(AI9+AI8,"") | AJ7: =SUM(AF7:AI7) | AK7: =IFERROR(AK9+AK8,"") | AL7: =IFERROR(AL9+AL8,"") | AM7: =IFERROR(AM9+AM8,"") | AN7: =IFERROR(AN9+AN8,"") | AO7: =SUM(AK7:AN7)
A8: 판관비 | B8: 손익 | C8: 억원 | D8: 판관비 | E8: =IFERROR(VLOOKUP($D8,BS별도,MATCH(E$1,BS별도H,0),0)/100,"") | G8: =IFERROR(VLOOKUP($D8,BS별도,MATCH(G$1,BS별도H,0),0)/100,"") | H8: =IFERROR(VLOOKUP($D8,BS별도,MATCH(H$1,BS별도H,0),0)/100,"") | I8: =IFERROR(VLOOKUP($D8,BS별도,MATCH(I$1,BS별도H,0),0)/100,"") | J8: =IFERROR(VLOOKUP($D8,BS별도,MATCH(J$1,BS별도H,0),0)/100,"") | K8: =SUM(G8:J8) | L8: =IFERROR(VLOOKUP($D8,BS별도,MATCH(L$1,BS별도H,0),0)/100,"") | M8: =IFERROR(VLOOKUP($D8,BS별도,MATCH(M$1,BS별도H,0),0)/100,"") | N8: =IFERROR(VLOOKUP($D8,BS별도,MATCH(N$1,BS별도H,0),0)/100,"") | O8: =IFERROR(VLOOKUP($D8,BS별도,MATCH(O$1,BS별도H,0),0)/100,"") | P8: =SUM(L8:O8) | Q8: =IFERROR(VLOOKUP($D8,BS별도,MATCH(Q$1,BS별도H,0),0)/100,"") | R8: =IFERROR(VLOOKUP($D8,BS별도,MATCH(R$1,BS별도H,0),0)/100,"") | S8: =IFERROR(VLOOKUP($D8,BS별도,MATCH(S$1,BS별도H,0),0)/100,"") | T8: =IFERROR(VLOOKUP($D8,BS별도,MATCH(T$1,BS별도H,0),0)/100,"") | U8: =SUM(Q8:T8) | V8: =IFERROR(VLOOKUP($D8,BS별도,MATCH(V$1,BS별도H,0),0)/100,"") | W8: =IFERROR(VLOOKUP($D8,BS별도,MATCH(W$1,BS별도H,0),0)/100,"") | X8: =IFERROR(VLOOKUP($D8,BS별도,MATCH(X$1,BS별도H,0),0)/100,"") | Y8: =IFERROR(VLOOKUP($D8,BS별도,MATCH(Y$1,BS별도H,0),0)/100,"") | Z8: =SUM(V8:Y8) | AA8: =IFERROR(VLOOKUP($D8,BS별도,MATCH(AA$1,BS별도H,0),0)/100,"") | AB8: =IFERROR(VLOOKUP($D8,BS별도,MATCH(AB$1,BS별도H,0),0)/100,"") | AC8: =IFERROR(AC5*변수!AC22,"") | AD8: =IFERROR(AD5*변수!AD22,"") | AE8: =SUM(AA8:AD8) | AF8: =IFERROR(AF5*변수!AF22,"") | AG8: =IFERROR(AG5*변수!AG22,"") | AH8: =IFERROR(AH5*변수!AH22,"") | AI8: =IFERROR(AI5*변수!AI22,"") | AJ8: =SUM(AF8:AI8) | AK8: =IFERROR(AK5*변수!AK22,"") | AL8: =IFERROR(AL5*변수!AL22,"") | AM8: =IFERROR(AM5*변수!AM22,"") | AN8: =IFERROR(AN5*변수!AN22,"") | AO8: =SUM(AK8:AN8)
A9: 영업이익 | B9: 손익 | C9: 억원 | D9: 영업이익 | E9: =IFERROR(VLOOKUP($D9,BS별도,MATCH(E$1,BS별도H,0),0)/100,"") | G9: =IFERROR(VLOOKUP($D9,BS별도,MATCH(G$1,BS별도H,0),0)/100,"") | H9: =IFERROR(VLOOKUP($D9,BS별도,MATCH(H$1,BS별도H,0),0)/100,"") | I9: =IFERROR(VLOOKUP($D9,BS별도,MATCH(I$1,BS별도H,0),0)/100,"") | J9: =IFERROR(VLOOKUP($D9,BS별도,MATCH(J$1,BS별도H,0),0)/100,"") | K9: =SUM(G9:J9) | L9: =IFERROR(VLOOKUP($D9,BS별도,MATCH(L$1,BS별도H,0),0)/100,"") | M9: =IFERROR(VLOOKUP($D9,BS별도,MATCH(M$1,BS별도H,0),0)/100,"") | N9: =IFERROR(VLOOKUP($D9,BS별도,MATCH(N$1,BS별도H,0),0)/100,"") | O9: =IFERROR(VLOOKUP($D9,BS별도,MATCH(O$1,BS별도H,0),0)/100,"") | P9: =SUM(L9:O9) | Q9: =IFERROR(VLOOKUP($D9,BS별도,MATCH(Q$1,BS별도H,0),0)/100,"") | R9: =IFERROR(VLOOKUP($D9,BS별도,MATCH(R$1,BS별도H,0),0)/100,"") | S9: =IFERROR(VLOOKUP($D9,BS별도,MATCH(S$1,BS별도H,0),0)/100,"") | T9: =IFERROR(VLOOKUP($D9,BS별도,MATCH(T$1,BS별도H,0),0)/100,"") | U9: =SUM(Q9:T9) | V9: =IFERROR(VLOOKUP($D9,BS별도,MATCH(V$1,BS별도H,0),0)/100,"") | W9: =IFERROR(VLOOKUP($D9,BS별도,MATCH(W$1,BS별도H,0),0)/100,"") | X9: =IFERROR(VLOOKUP($D9,BS별도,MATCH(X$1,BS별도H,0),0)/100,"") | Y9: =IFERROR(VLOOKUP($D9,BS별도,MATCH(Y$1,BS별도H,0),0)/100,"") | Z9: =SUM(V9:Y9) | AA9: =IFERROR(VLOOKUP($D9,BS별도,MATCH(AA$1,BS별도H,0),0)/100,"") | AB9: =IFERROR(VLOOKUP($D9,BS별도,MATCH(AB$1,BS별도H,0),0)/100,"") | AC9: =IFERROR(AC5*변수!AC23,"") | AD9: =IFERROR(AD5*변수!AD23,"") | AE9: =SUM(AA9:AD9) | AF9: =IFERROR(AF5*변수!AF23,"") | AG9: =IFERROR(AG5*변수!AG23,"") | AH9: =IFERROR(AH5*변수!AH23,"") | AI9: =IFERROR(AI5*변수!AI23,"") | AJ9: =SUM(AF9:AI9) | AK9: =IFERROR(AK5*변수!AK23,"") | AL9: =IFERROR(AL5*변수!AL23,"") | AM9: =IFERROR(AM5*변수!AM23,"") | AN9: =IFERROR(AN5*변수!AN23,"") | AO9: =SUM(AK9:AN9)
A10: OPM | B10: 손익 | C10: % | D10: 영업이익률 | E10: =IFERROR(E9/E5,"") | G10: =IFERROR(G9/G5,"") | H10: =IFERROR(H9/H5,"") | I10: =IFERROR(I9/I5,"") | J10: =IFERROR(J9/J5,"") | K10: =IFERROR(K9/K5,"") | L10: =IFERROR(L9/L5,"") | M10: =IFERROR(M9/M5,"") | N10: =IFERROR(N9/N5,"") | ... AO10: =IFERROR(AO9/AO5,"")
A11: 금융손익 | B11: 손익 | C11: 억원 | D11: 금융손익 | E11: =IFERROR(VLOOKUP($D11,BS별도,MATCH(E$1,BS별도H,0),0)/100,"") | G11: =IFERROR(VLOOKUP($D11,BS별도,MATCH(G$1,BS별도H,0),0)/100,"") | H11: =IFERROR(VLOOKUP($D11,BS별도,MATCH(H$1,BS별도H,0),0)/100,"") | I11: =IFERROR(VLOOKUP($D11,BS별도,MATCH(I$1,BS별도H,0),0)/100,"") | J11: =IFERROR(VLOOKUP($D11,BS별도,MATCH(J$1,BS별도H,0),0)/100,"") | K11: =SUM(G11:J11) | L11: =IFERROR(VLOOKUP($D11,BS별도,MATCH(L$1,BS별도H,0),0)/100,"") | M11: =IFERROR(VLOOKUP($D11,BS별도,MATCH(M$1,BS별도H,0),0)/100,"") | N11: =IFERROR(VLOOKUP($D11,BS별도,MATCH(N$1,BS별도H,0),0)/100,"") | O11: =IFERROR(VLOOKUP($D11,BS별도,MATCH(O$1,BS별도H,0),0)/100,"") | P11: =SUM(L11:O11) | Q11: =IFERROR(VLOOKUP($D11,BS별도,MATCH(Q$1,BS별도H,0),0)/100,"") | R11: =IFERROR(VLOOKUP($D11,BS별도,MATCH(R$1,BS별도H,0),0)/100,"") | S11: =IFERROR(VLOOKUP($D11,BS별도,MATCH(S$1,BS별도H,0),0)/100,"") | T11: =IFERROR(VLOOKUP($D11,BS별도,MATCH(T$1,BS별도H,0),0)/100,"") | U11: =SUM(Q11:T11) | V11: =IFERROR(VLOOKUP($D11,BS별도,MATCH(V$1,BS별도H,0),0)/100,"") | W11: =IFERROR(VLOOKUP($D11,BS별도,MATCH(W$1,BS별도H,0),0)/100,"") | X11: =IFERROR(VLOOKUP($D11,BS별도,MATCH(X$1,BS별도H,0),0)/100,"") | Y11: =IFERROR(VLOOKUP($D11,BS별도,MATCH(Y$1,BS별도H,0),0)/100,"") | Z11: =SUM(V11:Y11) | AA11: =IFERROR(VLOOKUP($D11,BS별도,MATCH(AA$1,BS별도H,0),0)/100,"") | AB11: =IFERROR(VLOOKUP($D11,BS별도,MATCH(AB$1,BS별도H,0),0)/100,"") | AC11: =IFERROR(AC12+AC13,"") | AD11: =IFERROR(AD12+AD13,"") | AE11: =SUM(AA11:AD11) | AF11: =IFERROR(AF12+AF13,"") | AG11: =IFERROR(AG12+AG13,"") | AH11: =IFERROR(AH12+AH13,"") | AI11: =IFERROR(AI12+AI13,"") | AJ11: =SUM(AF11:AI11) | AK11: =IFERROR(AK12+AK13,"") | AL11: =IFERROR(AL12+AL13,"") | AM11: =IFERROR(AM12+AM13,"") | AN11: =IFERROR(AN12+AN13,"") | AO11: =SUM(AK11:AN11)
A12: 이자손익 | B12: 손익 | C12: 억원 | D12: 이자손익 | K12: =SUM(G12:J12) | P12: =SUM(L12:O12) | U12: =SUM(Q12:T12) | Z12: =SUM(V12:Y12) | AA12: =IFERROR(VLOOKUP($D12,BS별도,MATCH(AA$1,BS별도H,0),0)/100,"") | AC12: =IFERROR((AB26*변수!$D$52-AB24*변수!$D$53)/4,"") | AD12: =IFERROR((AC26*변수!$D$52-AC24*변수!$D$53)/4,"") | AE12: =SUM(AA12:AD12) | AF12: =IFERROR((AD26*변수!$D$52-AD24*변수!$D$53)/4,"") | AG12: =IFERROR((AF26*변수!$D$52-AF24*변수!$D$53)/4,"") | AH12: =IFERROR((AG26*변수!$D$52-AG24*변수!$D$53)/4,"") | AI12: =IFERROR((AH26*변수!$D$52-AH24*변수!$D$53)/4,"") | AJ12: =SUM(AF12:AI12) | AK12: =IFERROR((AI26*변수!$D$52-AI24*변수!$D$53)/4,"") | AL12: =IFERROR((AK26*변수!$D$52-AK24*변수!$D$53)/4,"") | AM12: =IFERROR((AL26*변수!$D$52-AL24*변수!$D$53)/4,"") | AN12: =IFERROR((AM26*변수!$D$52-AM24*변수!$D$53)/4,"") | AO12: =SUM(AK12:AN12)
A13: 외환손익 | B13: 손익 | C13: 억원 | D13: 외환손익(실적만; 추정 환효과는 환관련손익) | K13: =SUM(G13:J13) | P13: =SUM(L13:O13) | U13: =SUM(Q13:T13) | Z13: =SUM(V13:Y13) | AA13: =IFERROR((VLOOKUP("외환차익",BS별도,MATCH(AA$1,BS별도H,0),0)-VLOOKUP("외환차손",BS별도,MATCH(AA$1,BS별도H,0),0)+VLOOKUP("외화환산이익",BS별도,MATCH(AA$1,BS별도H,0),0)-VLOOKUP("외화환산손실",BS별도,MATCH(AA$1,BS별도H,0),0))/100,"") | AC13: =변수!AC24 | AD13: =변수!AD24 | AE13: =SUM(AA13:AD13) | AF13: =변수!AF24 | AG13: =변수!AG24 | AH13: =변수!AH24 | AI13: =변수!AI24 | AJ13: =SUM(AF13:AI13) | AK13: =변수!AK24 | AL13: =변수!AL24 | AM13: =변수!AM24 | AN13: =변수!AN24 | AO13: =SUM(AK13:AN13)
A14: 기타영업외손익 | B14: 손익 | C14: 억원 | D14: 기타영업외손익 | E14: =IFERROR(VLOOKUP($D14,BS별도,MATCH(E$1,BS별도H,0),0)/100,"") | G14: =IFERROR(VLOOKUP($D14,BS별도,MATCH(G$1,BS별도H,0),0)/100,"") | H14: =IFERROR(VLOOKUP($D14,BS별도,MATCH(H$1,BS별도H,0),0)/100,"") | I14: =IFERROR(VLOOKUP($D14,BS별도,MATCH(I$1,BS별도H,0),0)/100,"") | J14: =IFERROR(VLOOKUP($D14,BS별도,MATCH(J$1,BS별도H,0),0)/100,"") | K14: =SUM(G14:J14) | L14: =IFERROR(VLOOKUP($D14,BS별도,MATCH(L$1,BS별도H,0),0)/100,"") | M14: =IFERROR(VLOOKUP($D14,BS별도,MATCH(M$1,BS별도H,0),0)/100,"") | N14: =IFERROR(VLOOKUP($D14,BS별도,MATCH(N$1,BS별도H,0),0)/100,"") | O14: =IFERROR(VLOOKUP($D14,BS별도,MATCH(O$1,BS별도H,0),0)/100,"") | P14: =SUM(L14:O14) | Q14: =IFERROR(VLOOKUP($D14,BS별도,MATCH(Q$1,BS별도H,0),0)/100,"") | R14: =IFERROR(VLOOKUP($D14,BS별도,MATCH(R$1,BS별도H,0),0)/100,"") | S14: =IFERROR(VLOOKUP($D14,BS별도,MATCH(S$1,BS별도H,0),0)/100,"") | T14: =IFERROR(VLOOKUP($D14,BS별도,MATCH(T$1,BS별도H,0),0)/100,"") | U14: =SUM(Q14:T14) | V14: =IFERROR(VLOOKUP($D14,BS별도,MATCH(V$1,BS별도H,0),0)/100,"") | W14: =IFERROR(VLOOKUP($D14,BS별도,MATCH(W$1,BS별도H,0),0)/100,"") | X14: =IFERROR(VLOOKUP($D14,BS별도,MATCH(X$1,BS별도H,0),0)/100,"") | Y14: =IFERROR(VLOOKUP($D14,BS별도,MATCH(Y$1,BS별도H,0),0)/100,"") | Z14: =SUM(V14:Y14) | AA14: =IFERROR(VLOOKUP($D14,BS별도,MATCH(AA$1,BS별도H,0),0)/100,"") | AB14: =IFERROR(VLOOKUP($D14,BS별도,MATCH(AB$1,BS별도H,0),0)/100,"") | AC14: =변수!AC25 | AD14: =변수!AD25 | AE14: =SUM(AA14:AD14) | AF14: =변수!AF25 | AG14: =변수!AG25 | AH14: =변수!AH25 | AI14: =변수!AI25 | AJ14: =SUM(AF14:AI14) | AK14: =변수!AK25 | AL14: =변수!AL25 | AM14: =변수!AM25 | AN14: =변수!AN25 | AO14: =SUM(AK14:AN14)
A15: 지분법손익 | B15: 손익 | C15: 억원 | D15: 종속기업,공동지배기업및관계기업관련손익 | E15: =IFERROR(VLOOKUP($D15,BS별도,MATCH(E$1,BS별도H,0),0)/100,"") | G15: =IFERROR(VLOOKUP($D15,BS별도,MATCH(G$1,BS별도H,0),0)/100,"") | H15: =IFERROR(VLOOKUP($D15,BS별도,MATCH(H$1,BS별도H,0),0)/100,"") | I15: =IFERROR(VLOOKUP($D15,BS별도,MATCH(I$1,BS별도H,0),0)/100,"") | J15: =IFERROR(VLOOKUP($D15,BS별도,MATCH(J$1,BS별도H,0),0)/100,"") | K15: =SUM(G15:J15) | L15: =IFERROR(VLOOKUP($D15,BS별도,MATCH(L$1,BS별도H,0),0)/100,"") | M15: =IFERROR(VLOOKUP($D15,BS별도,MATCH(M$1,BS별도H,0),0)/100,"") | N15: =IFERROR(VLOOKUP($D15,BS별도,MATCH(N$1,BS별도H,0),0)/100,"") | P15: =SUM(L15:O15) | R15: =IFERROR(VLOOKUP($D15,BS별도,MATCH(R$1,BS별도H,0),0)/100,"") | S15: =IFERROR(VLOOKUP($D15,BS별도,MATCH(S$1,BS별도H,0),0)/100,"") | T15: =IFERROR(VLOOKUP($D15,BS별도,MATCH(T$1,BS별도H,0),0)/100,"") | U15: =SUM(Q15:T15) | V15: =IFERROR(VLOOKUP($D15,BS별도,MATCH(V$1,BS별도H,0),0)/100,"") | X15: =IFERROR(VLOOKUP($D15,BS별도,MATCH(X$1,BS별도H,0),0)/100,"") | Y15: =IFERROR(VLOOKUP($D15,BS별도,MATCH(Y$1,BS별도H,0),0)/100,"") | Z15: =SUM(V15:Y15) | AA15: =IFERROR(VLOOKUP($D15,BS별도,MATCH(AA$1,BS별도H,0),0)/100,"") | AB15: =IFERROR(VLOOKUP($D15,BS별도,MATCH(AB$1,BS별도H,0),0)/100,"") | AC15: =변수!AC26 | AD15: =변수!AD26 | AE15: =SUM(AA15:AD15) | AF15: =변수!AF26 | AG15: =변수!AG26 | AH15: =변수!AH26 | AI15: =변수!AI26 | AJ15: =SUM(AF15:AI15) | AK15: =변수!AK26 | AL15: =변수!AL26 | AM15: =변수!AM26 | AN15: =변수!AN26 | AO15: =SUM(AK15:AN15)
A16: 세전이익 | B16: 손익 | C16: 억원 | D16: 법인세비용차감전계속사업이익 | E16: =IFERROR(VLOOKUP($D16,BS별도,MATCH(E$1,BS별도H,0),0)/100,"") | G16: =IFERROR(VLOOKUP($D16,BS별도,MATCH(G$1,BS별도H,0),0)/100,"") | H16: =IFERROR(VLOOKUP($D16,BS별도,MATCH(H$1,BS별도H,0),0)/100,"") | I16: =IFERROR(VLOOKUP($D16,BS별도,MATCH(I$1,BS별도H,0),0)/100,"") | J16: =IFERROR(VLOOKUP($D16,BS별도,MATCH(J$1,BS별도H,0),0)/100,"") | K16: =SUM(G16:J16) | L16: =IFERROR(VLOOKUP($D16,BS별도,MATCH(L$1,BS별도H,0),0)/100,"") | M16: =IFERROR(VLOOKUP($D16,BS별도,MATCH(M$1,BS별도H,0),0)/100,"") | N16: =IFERROR(VLOOKUP($D16,BS별도,MATCH(N$1,BS별도H,0),0)/100,"") | O16: =IFERROR(VLOOKUP($D16,BS별도,MATCH(O$1,BS별도H,0),0)/100,"") | P16: =SUM(L16:O16) | Q16: =IFERROR(VLOOKUP($D16,BS별도,MATCH(Q$1,BS별도H,0),0)/100,"") | R16: =IFERROR(VLOOKUP($D16,BS별도,MATCH(R$1,BS별도H,0),0)/100,"") | S16: =IFERROR(VLOOKUP($D16,BS별도,MATCH(S$1,BS별도H,0),0)/100,"") | T16: =IFERROR(VLOOKUP($D16,BS별도,MATCH(T$1,BS별도H,0),0)/100,"") | U16: =SUM(Q16:T16) | V16: =IFERROR(VLOOKUP($D16,BS별도,MATCH(V$1,BS별도H,0),0)/100,"") | W16: =IFERROR(VLOOKUP($D16,BS별도,MATCH(W$1,BS별도H,0),0)/100,"") | X16: =IFERROR(VLOOKUP($D16,BS별도,MATCH(X$1,BS별도H,0),0)/100,"") | Y16: =IFERROR(VLOOKUP($D16,BS별도,MATCH(Y$1,BS별도H,0),0)/100,"") | Z16: =SUM(V16:Y16) | AA16: =IFERROR(VLOOKUP($D16,BS별도,MATCH(AA$1,BS별도H,0),0)/100,"") | AB16: =IFERROR(VLOOKUP($D16,BS별도,MATCH(AB$1,BS별도H,0),0)/100,"") | AC16: =IFERROR(AC9+AC11+AC14+AC15,"") | AD16: =IFERROR(AD9+AD11+AD14+AD15,"") | AE16: =SUM(AA16:AD16) | AF16: =IFERROR(AF9+AF11+AF14+AF15,"") | AG16: =IFERROR(AG9+AG11+AG14+AG15,"") | AH16: =IFERROR(AH9+AH11+AH14+AH15,"") | AI16: =IFERROR(AI9+AI11+AI14+AI15,"") | AJ16: =SUM(AF16:AI16) | AK16: =IFERROR(AK9+AK11+AK14+AK15,"") | AL16: =IFERROR(AL9+AL11+AL14+AL15,"") | AM16: =IFERROR(AM9+AM11+AM14+AM15,"") | AN16: =IFERROR(AN9+AN11+AN14+AN15,"") | AO16: =SUM(AK16:AN16)
A17: 법인세비용 | B17: 손익 | C17: 억원 | D17: 법인세비용 | E17: =IFERROR(VLOOKUP($D17,BS별도,MATCH(E$1,BS별도H,0),0)/100,"") | G17: =IFERROR(VLOOKUP($D17,BS별도,MATCH(G$1,BS별도H,0),0)/100,"") | H17: =IFERROR(VLOOKUP($D17,BS별도,MATCH(H$1,BS별도H,0),0)/100,"") | I17: =IFERROR(VLOOKUP($D17,BS별도,MATCH(I$1,BS별도H,0),0)/100,"") | J17: =IFERROR(VLOOKUP($D17,BS별도,MATCH(J$1,BS별도H,0),0)/100,"") | K17: =SUM(G17:J17) | L17: =IFERROR(VLOOKUP($D17,BS별도,MATCH(L$1,BS별도H,0),0)/100,"") | M17: =IFERROR(VLOOKUP($D17,BS별도,MATCH(M$1,BS별도H,0),0)/100,"") | N17: =IFERROR(VLOOKUP($D17,BS별도,MATCH(N$1,BS별도H,0),0)/100,"") | O17: =IFERROR(VLOOKUP($D17,BS별도,MATCH(O$1,BS별도H,0),0)/100,"") | P17: =SUM(L17:O17) | Q17: =IFERROR(VLOOKUP($D17,BS별도,MATCH(Q$1,BS별도H,0),0)/100,"") | R17: =IFERROR(VLOOKUP($D17,BS별도,MATCH(R$1,BS별도H,0),0)/100,"") | S17: =IFERROR(VLOOKUP($D17,BS별도,MATCH(S$1,BS별도H,0),0)/100,"") | T17: =IFERROR(VLOOKUP($D17,BS별도,MATCH(T$1,BS별도H,0),0)/100,"") | U17: =SUM(Q17:T17) | V17: =IFERROR(VLOOKUP($D17,BS별도,MATCH(V$1,BS별도H,0),0)/100,"") | W17: =IFERROR(VLOOKUP($D17,BS별도,MATCH(W$1,BS별도H,0),0)/100,"") | X17: =IFERROR(VLOOKUP($D17,BS별도,MATCH(X$1,BS별도H,0),0)/100,"") | Y17: =IFERROR(VLOOKUP($D17,BS별도,MATCH(Y$1,BS별도H,0),0)/100,"") | Z17: =SUM(V17:Y17) | AA17: =IFERROR(VLOOKUP($D17,BS별도,MATCH(AA$1,BS별도H,0),0)/100,"") | AB17: =IFERROR(VLOOKUP($D17,BS별도,MATCH(AB$1,BS별도H,0),0)/100,"") | AC17: =IFERROR(MAX(AC16,0)*변수!AC27,"") | AD17: =IFERROR(MAX(AD16,0)*변수!AD27,"") | AE17: =SUM(AA17:AD17) | AF17: =IFERROR(MAX(AF16,0)*변수!AF27,"") | AG17: =IFERROR(MAX(AG16,0)*변수!AG27,"") | AH17: =IFERROR(MAX(AH16,0)*변수!AH27,"") | AI17: =IFERROR(MAX(AI16,0)*변수!AI27,"") | AJ17: =SUM(AF17:AI17) | AK17: =IFERROR(MAX(AK16,0)*변수!AK27,"") | AL17: =IFERROR(MAX(AL16,0)*변수!AL27,"") | AM17: =IFERROR(MAX(AM16,0)*변수!AM27,"") | AN17: =IFERROR(MAX(AN16,0)*변수!AN27,"") | AO17: =SUM(AK17:AN17)
A18: 당기순이익 | B18: 손익 | C18: 억원 | D18: 당기순이익 | E18: =IFERROR(VLOOKUP($D18,BS별도,MATCH(E$1,BS별도H,0),0)/100,"") | G18: =IFERROR(VLOOKUP($D18,BS별도,MATCH(G$1,BS별도H,0),0)/100,"") | H18: =IFERROR(VLOOKUP($D18,BS별도,MATCH(H$1,BS별도H,0),0)/100,"") | I18: =IFERROR(VLOOKUP($D18,BS별도,MATCH(I$1,BS별도H,0),0)/100,"") | J18: =IFERROR(VLOOKUP($D18,BS별도,MATCH(J$1,BS별도H,0),0)/100,"") | K18: =SUM(G18:J18) | L18: =IFERROR(VLOOKUP($D18,BS별도,MATCH(L$1,BS별도H,0),0)/100,"") | M18: =IFERROR(VLOOKUP($D18,BS별도,MATCH(M$1,BS별도H,0),0)/100,"") | N18: =IFERROR(VLOOKUP($D18,BS별도,MATCH(N$1,BS별도H,0),0)/100,"") | O18: =IFERROR(VLOOKUP($D18,BS별도,MATCH(O$1,BS별도H,0),0)/100,"") | P18: =SUM(L18:O18) | Q18: =IFERROR(VLOOKUP($D18,BS별도,MATCH(Q$1,BS별도H,0),0)/100,"") | R18: =IFERROR(VLOOKUP($D18,BS별도,MATCH(R$1,BS별도H,0),0)/100,"") | S18: =IFERROR(VLOOKUP($D18,BS별도,MATCH(S$1,BS별도H,0),0)/100,"") | T18: =IFERROR(VLOOKUP($D18,BS별도,MATCH(T$1,BS별도H,0),0)/100,"") | U18: =SUM(Q18:T18) | V18: =IFERROR(VLOOKUP($D18,BS별도,MATCH(V$1,BS별도H,0),0)/100,"") | W18: =IFERROR(VLOOKUP($D18,BS별도,MATCH(W$1,BS별도H,0),0)/100,"") | X18: =IFERROR(VLOOKUP($D18,BS별도,MATCH(X$1,BS별도H,0),0)/100,"") | Y18: =IFERROR(VLOOKUP($D18,BS별도,MATCH(Y$1,BS별도H,0),0)/100,"") | Z18: =SUM(V18:Y18) | AA18: =IFERROR(VLOOKUP($D18,BS별도,MATCH(AA$1,BS별도H,0),0)/100,"") | AB18: =IFERROR(VLOOKUP($D18,BS별도,MATCH(AB$1,BS별도H,0),0)/100,"") | AC18: =IFERROR(AC16-AC17,"") | AD18: =IFERROR(AD16-AD17,"") | AE18: =SUM(AA18:AD18) | AF18: =IFERROR(AF16-AF17,"") | AG18: =IFERROR(AG16-AG17,"") | AH18: =IFERROR(AH16-AH17,"") | AI18: =IFERROR(AI16-AI17,"") | AJ18: =SUM(AF18:AI18) | AK18: =IFERROR(AK16-AK17,"") | AL18: =IFERROR(AL16-AL17,"") | AM18: =IFERROR(AM16-AM17,"") | AN18: =IFERROR(AN16-AN17,"") | AO18: =SUM(AK18:AN18)
A19: 지배주주순이익 | B19: 손익 | C19: 억원 | D19: (지배주주지분)당기순이익 | E19: =IFERROR(VLOOKUP($D19,BS별도,MATCH(E$1,BS별도H,0),0)/100,"") | G19: =IFERROR(VLOOKUP($D19,BS별도,MATCH(G$1,BS별도H,0),0)/100,"") | H19: =IFERROR(VLOOKUP($D19,BS별도,MATCH(H$1,BS별도H,0),0)/100,"") | I19: =IFERROR(VLOOKUP($D19,BS별도,MATCH(I$1,BS별도H,0),0)/100,"") | J19: =IFERROR(VLOOKUP($D19,BS별도,MATCH(J$1,BS별도H,0),0)/100,"") | K19: =SUM(G19:J19) | L19: =IFERROR(VLOOKUP($D19,BS별도,MATCH(L$1,BS별도H,0),0)/100,"") | M19: =IFERROR(VLOOKUP($D19,BS별도,MATCH(M$1,BS별도H,0),0)/100,"") | N19: =IFERROR(VLOOKUP($D19,BS별도,MATCH(N$1,BS별도H,0),0)/100,"") | O19: =IFERROR(VLOOKUP($D19,BS별도,MATCH(O$1,BS별도H,0),0)/100,"") | P19: =SUM(L19:O19) | Q19: =IFERROR(VLOOKUP($D19,BS별도,MATCH(Q$1,BS별도H,0),0)/100,"") | R19: =IFERROR(VLOOKUP($D19,BS별도,MATCH(R$1,BS별도H,0),0)/100,"") | S19: =IFERROR(VLOOKUP($D19,BS별도,MATCH(S$1,BS별도H,0),0)/100,"") | T19: =IFERROR(VLOOKUP($D19,BS별도,MATCH(T$1,BS별도H,0),0)/100,"") | U19: =SUM(Q19:T19) | V19: =IFERROR(VLOOKUP($D19,BS별도,MATCH(V$1,BS별도H,0),0)/100,"") | W19: =IFERROR(VLOOKUP($D19,BS별도,MATCH(W$1,BS별도H,0),0)/100,"") | X19: =IFERROR(VLOOKUP($D19,BS별도,MATCH(X$1,BS별도H,0),0)/100,"") | Y19: =IFERROR(VLOOKUP($D19,BS별도,MATCH(Y$1,BS별도H,0),0)/100,"") | Z19: =SUM(V19:Y19) | AA19: =IFERROR(VLOOKUP($D19,BS별도,MATCH(AA$1,BS별도H,0),0)/100,"") | AB19: =IFERROR(VLOOKUP($D19,BS별도,MATCH(AB$1,BS별도H,0),0)/100,"") | AC19: =IFERROR(AC18*변수!AC28,"") | AD19: =IFERROR(AD18*변수!AD28,"") | AE19: =SUM(AA19:AD19) | AF19: =IFERROR(AF18*변수!AF28,"") | AG19: =IFERROR(AG18*변수!AG28,"") | AH19: =IFERROR(AH18*변수!AH28,"") | AI19: =IFERROR(AI18*변수!AI28,"") | AJ19: =SUM(AF19:AI19) | AK19: =IFERROR(AK18*변수!AK28,"") | AL19: =IFERROR(AL18*변수!AL28,"") | AM19: =IFERROR(AM18*변수!AM28,"") | AN19: =IFERROR(AN18*변수!AN28,"") | AO19: =SUM(AK19:AN19)
A20: 자산총계 | B20: 재무상태 | C20: 억원 | D20: 자산총계 | E20: =IFERROR(VLOOKUP($D20,BS별도,MATCH(E$1,BS별도H,0),0)/100,"") | F20: 532.52 | G20: =IFERROR(VLOOKUP($D20,BS별도,MATCH(G$1,BS별도H,0),0)/100,"") | H20: =IFERROR(VLOOKUP($D20,BS별도,MATCH(H$1,BS별도H,0),0)/100,"") | I20: =IFERROR(VLOOKUP($D20,BS별도,MATCH(I$1,BS별도H,0),0)/100,"") | J20: =IFERROR(VLOOKUP($D20,BS별도,MATCH(J$1,BS별도H,0),0)/100,"") | K20: =J20 | L20: =IFERROR(VLOOKUP($D20,BS별도,MATCH(L$1,BS별도H,0),0)/100,"") | M20: =IFERROR(VLOOKUP($D20,BS별도,MATCH(M$1,BS별도H,0),0)/100,"") | N20: =IFERROR(VLOOKUP($D20,BS별도,MATCH(N$1,BS별도H,0),0)/100,"") | O20: =IFERROR(VLOOKUP($D20,BS별도,MATCH(O$1,BS별도H,0),0)/100,"") | P20: =O20 | Q20: =IFERROR(VLOOKUP($D20,BS별도,MATCH(Q$1,BS별도H,0),0)/100,"") | R20: =IFERROR(VLOOKUP($D20,BS별도,MATCH(R$1,BS별도H,0),0)/100,"") | S20: =IFERROR(VLOOKUP($D20,BS별도,MATCH(S$1,BS별도H,0),0)/100,"") | T20: =IFERROR(VLOOKUP($D20,BS별도,MATCH(T$1,BS별도H,0),0)/100,"") | U20: =T20 | V20: =IFERROR(VLOOKUP($D20,BS별도,MATCH(V$1,BS별도H,0),0)/100,"") | W20: =IFERROR(VLOOKUP($D20,BS별도,MATCH(W$1,BS별도H,0),0)/100,"") | X20: =IFERROR(VLOOKUP($D20,BS별도,MATCH(X$1,BS별도H,0),0)/100,"") | Y20: =IFERROR(VLOOKUP($D20,BS별도,MATCH(Y$1,BS별도H,0),0)/100,"") | Z20: =Y20 | AA20: =IFERROR(VLOOKUP($D20,BS별도,MATCH(AA$1,BS별도H,0),0)/100,"") | AB20: =IFERROR(VLOOKUP($D20,BS별도,MATCH(AB$1,BS별도H,0),0)/100,"") | AC20: =IFERROR(AC21+AC22,"") | AD20: =IFERROR(AD21+AD22,"") | AE20: =AD20 | AF20: =IFERROR(AF21+AF22,"") | AG20: =IFERROR(AG21+AG22,"") | AH20: =IFERROR(AH21+AH22,"") | AI20: =IFERROR(AI21+AI22,"") | AJ20: =AI20 | AK20: =IFERROR(AK21+AK22,"") | AL20: =IFERROR(AL21+AL22,"") | AM20: =IFERROR(AM21+AM22,"") | AN20: =IFERROR(AN21+AN22,"") | AO20: =AN20
A21: 부채총계 | B21: 재무상태 | C21: 억원 | D21: 부채총계 | E21: =IFERROR(VLOOKUP($D21,BS별도,MATCH(E$1,BS별도H,0),0)/100,"") | F21: 145.16 | G21: =IFERROR(VLOOKUP($D21,BS별도,MATCH(G$1,BS별도H,0),0)/100,"") | H21: =IFERROR(VLOOKUP($D21,BS별도,MATCH(H$1,BS별도H,0),0)/100,"") | I21: =IFERROR(VLOOKUP($D21,BS별도,MATCH(I$1,BS별도H,0),0)/100,"") | J21: =IFERROR(VLOOKUP($D21,BS별도,MATCH(J$1,BS별도H,0),0)/100,"") | K21: =J21 | L21: =IFERROR(VLOOKUP($D21,BS별도,MATCH(L$1,BS별도H,0),0)/100,"") | M21: =IFERROR(VLOOKUP($D21,BS별도,MATCH(M$1,BS별도H,0),0)/100,"") | N21: =IFERROR(VLOOKUP($D21,BS별도,MATCH(N$1,BS별도H,0),0)/100,"") | O21: =IFERROR(VLOOKUP($D21,BS별도,MATCH(O$1,BS별도H,0),0)/100,"") | P21: =O21 | Q21: =IFERROR(VLOOKUP($D21,BS별도,MATCH(Q$1,BS별도H,0),0)/100,"") | R21: =IFERROR(VLOOKUP($D21,BS별도,MATCH(R$1,BS별도H,0),0)/100,"") | S21: =IFERROR(VLOOKUP($D21,BS별도,MATCH(S$1,BS별도H,0),0)/100,"") | T21: =IFERROR(VLOOKUP($D21,BS별도,MATCH(T$1,BS별도H,0),0)/100,"") | U21: =T21 | V21: =IFERROR(VLOOKUP($D21,BS별도,MATCH(V$1,BS별도H,0),0)/100,"") | W21: =IFERROR(VLOOKUP($D21,BS별도,MATCH(W$1,BS별도H,0),0)/100,"") | X21: =IFERROR(VLOOKUP($D21,BS별도,MATCH(X$1,BS별도H,0),0)/100,"") | Y21: =IFERROR(VLOOKUP($D21,BS별도,MATCH(Y$1,BS별도H,0),0)/100,"") | Z21: =Y21 | AA21: =IFERROR(VLOOKUP($D21,BS별도,MATCH(AA$1,BS별도H,0),0)/100,"") | AB21: =IFERROR(VLOOKUP($D21,BS별도,MATCH(AB$1,BS별도H,0),0)/100,"") | AC21: =IFERROR(AB21*(1+변수!AC29),"") | AD21: =IFERROR(AC21*(1+변수!AD29),"") | AE21: =AD21 | AF21: =IFERROR(AD21*(1+변수!AF29),"") | AG21: =IFERROR(AF21*(1+변수!AG29),"") | AH21: =IFERROR(AG21*(1+변수!AH29),"") | AI21: =IFERROR(AH21*(1+변수!AI29),"") | AJ21: =AI21 | AK21: =IFERROR(AI21*(1+변수!AK29),"") | AL21: =IFERROR(AK21*(1+변수!AL29),"") | AM21: =IFERROR(AL21*(1+변수!AM29),"") | AN21: =IFERROR(AM21*(1+변수!AN29),"") | AO21: =AN21
A22: 자본총계 | B22: 재무상태 | C22: 억원 | D22: 자본총계 | E22: =IFERROR(VLOOKUP($D22,BS별도,MATCH(E$1,BS별도H,0),0)/100,"") | F22: 387.36 | G22: =IFERROR(VLOOKUP($D22,BS별도,MATCH(G$1,BS별도H,0),0)/100,"") | H22: =IFERROR(VLOOKUP($D22,BS별도,MATCH(H$1,BS별도H,0),0)/100,"") | I22: =IFERROR(VLOOKUP($D22,BS별도,MATCH(I$1,BS별도H,0),0)/100,"") | J22: =IFERROR(VLOOKUP($D22,BS별도,MATCH(J$1,BS별도H,0),0)/100,"") | K22: =J22 | L22: =IFERROR(VLOOKUP($D22,BS별도,MATCH(L$1,BS별도H,0),0)/100,"") | M22: =IFERROR(VLOOKUP($D22,BS별도,MATCH(M$1,BS별도H,0),0)/100,"") | N22: =IFERROR(VLOOKUP($D22,BS별도,MATCH(N$1,BS별도H,0),0)/100,"") | O22: =IFERROR(VLOOKUP($D22,BS별도,MATCH(O$1,BS별도H,0),0)/100,"") | P22: =O22 | Q22: =IFERROR(VLOOKUP($D22,BS별도,MATCH(Q$1,BS별도H,0),0)/100,"") | R22: =IFERROR(VLOOKUP($D22,BS별도,MATCH(R$1,BS별도H,0),0)/100,"") | S22: =IFERROR(VLOOKUP($D22,BS별도,MATCH(S$1,BS별도H,0),0)/100,"") | T22: =IFERROR(VLOOKUP($D22,BS별도,MATCH(T$1,BS별도H,0),0)/100,"") | U22: =T22 | V22: =IFERROR(VLOOKUP($D22,BS별도,MATCH(V$1,BS별도H,0),0)/100,"") | W22: =IFERROR(VLOOKUP($D22,BS별도,MATCH(W$1,BS별도H,0),0)/100,"") | X22: =IFERROR(VLOOKUP($D22,BS별도,MATCH(X$1,BS별도H,0),0)/100,"") | Y22: =IFERROR(VLOOKUP($D22,BS별도,MATCH(Y$1,BS별도H,0),0)/100,"") | Z22: =Y22 | AA22: =IFERROR(VLOOKUP($D22,BS별도,MATCH(AA$1,BS별도H,0),0)/100,"") | AB22: =IFERROR(VLOOKUP($D22,BS별도,MATCH(AB$1,BS별도H,0),0)/100,"") | AC22: =IFERROR(AB22+AC18-변수!AC30,"") | AD22: =IFERROR(AC22+AD18-변수!AD30,"") | AE22: =AD22 | AF22: =IFERROR(AD22+AF18-변수!AF30,"") | AG22: =IFERROR(AF22+AG18-변수!AG30,"") | AH22: =IFERROR(AG22+AH18-변수!AH30,"") | AI22: =IFERROR(AH22+AI18-변수!AI30,"") | AJ22: =AI22 | AK22: =IFERROR(AI22+AK18-변수!AK30,"") | AL22: =IFERROR(AK22+AL18-변수!AL30,"") | AM22: =IFERROR(AL22+AM18-변수!AM30,"") | AN22: =IFERROR(AM22+AN18-변수!AN30,"") | AO22: =AN22
A23: 지배주주지분 | B23: 재무상태 | C23: 억원 | D23: 지배주주지분 | E23: =IFERROR(VLOOKUP($D23,BS별도,MATCH(E$1,BS별도H,0),0)/100,"") | F23: 387.36 | G23: =IFERROR(VLOOKUP($D23,BS별도,MATCH(G$1,BS별도H,0),0)/100,"") | H23: =IFERROR(VLOOKUP($D23,BS별도,MATCH(H$1,BS별도H,0),0)/100,"") | I23: =IFERROR(VLOOKUP($D23,BS별도,MATCH(I$1,BS별도H,0),0)/100,"") | J23: =IFERROR(VLOOKUP($D23,BS별도,MATCH(J$1,BS별도H,0),0)/100,"") | K23: =J23 | L23: =IFERROR(VLOOKUP($D23,BS별도,MATCH(L$1,BS별도H,0),0)/100,"") | M23: =IFERROR(VLOOKUP($D23,BS별도,MATCH(M$1,BS별도H,0),0)/100,"") | N23: =IFERROR(VLOOKUP($D23,BS별도,MATCH(N$1,BS별도H,0),0)/100,"") | O23: =IFERROR(VLOOKUP($D23,BS별도,MATCH(O$1,BS별도H,0),0)/100,"") | P23: =O23 | Q23: =IFERROR(VLOOKUP($D23,BS별도,MATCH(Q$1,BS별도H,0),0)/100,"") | R23: =IFERROR(VLOOKUP($D23,BS별도,MATCH(R$1,BS별도H,0),0)/100,"") | S23: =IFERROR(VLOOKUP($D23,BS별도,MATCH(S$1,BS별도H,0),0)/100,"") | T23: =IFERROR(VLOOKUP($D23,BS별도,MATCH(T$1,BS별도H,0),0)/100,"") | U23: =T23 | V23: =IFERROR(VLOOKUP($D23,BS별도,MATCH(V$1,BS별도H,0),0)/100,"") | W23: =IFERROR(VLOOKUP($D23,BS별도,MATCH(W$1,BS별도H,0),0)/100,"") | X23: =IFERROR(VLOOKUP($D23,BS별도,MATCH(X$1,BS별도H,0),0)/100,"") | Y23: =IFERROR(VLOOKUP($D23,BS별도,MATCH(Y$1,BS별도H,0),0)/100,"") | Z23: =Y23 | AA23: =IFERROR(VLOOKUP($D23,BS별도,MATCH(AA$1,BS별도H,0),0)/100,"") | AB23: =IFERROR(VLOOKUP($D23,BS별도,MATCH(AB$1,BS별도H,0),0)/100,"") | AC23: =IFERROR(AB23+AC19-변수!AC31,"") | AD23: =IFERROR(AC23+AD19-변수!AD31,"") | AE23: =AD23 | AF23: =IFERROR(AD23+AF19-변수!AF31,"") | AG23: =IFERROR(AF23+AG19-변수!AG31,"") | AH23: =IFERROR(AG23+AH19-변수!AH31,"") | AI23: =IFERROR(AH23+AI19-변수!AI31,"") | AJ23: =AI23 | AK23: =IFERROR(AI23+AK19-변수!AK31,"") | AL23: =IFERROR(AK23+AL19-변수!AL31,"") | AM23: =IFERROR(AL23+AM19-변수!AM31,"") | AN23: =IFERROR(AM23+AN19-변수!AN31,"") | AO23: =AN23
A24: 총차입금 | B24: 재무상태 | C24: 억원 | D24: 총차입금 | E24: =IFERROR(VLOOKUP($D24,BS별도,MATCH(E$1,BS별도H,0),0)/100,"") | F24: 33.2 | G24: =IFERROR(VLOOKUP($D24,BS별도,MATCH(G$1,BS별도H,0),0)/100,"") | H24: =IFERROR(VLOOKUP($D24,BS별도,MATCH(H$1,BS별도H,0),0)/100,"") | I24: =IFERROR(VLOOKUP($D24,BS별도,MATCH(I$1,BS별도H,0),0)/100,"") | J24: =IFERROR(VLOOKUP($D24,BS별도,MATCH(J$1,BS별도H,0),0)/100,"") | K24: =J24 | L24: =IFERROR(VLOOKUP($D24,BS별도,MATCH(L$1,BS별도H,0),0)/100,"") | M24: =IFERROR(VLOOKUP($D24,BS별도,MATCH(M$1,BS별도H,0),0)/100,"") | N24: =IFERROR(VLOOKUP($D24,BS별도,MATCH(N$1,BS별도H,0),0)/100,"") | O24: =IFERROR(VLOOKUP($D24,BS별도,MATCH(O$1,BS별도H,0),0)/100,"") | P24: =O24 | Q24: =IFERROR(VLOOKUP($D24,BS별도,MATCH(Q$1,BS별도H,0),0)/100,"") | T24: =IFERROR(VLOOKUP($D24,BS별도,MATCH(T$1,BS별도H,0),0)/100,"") | U24: =T24 | V24: =IFERROR(VLOOKUP($D24,BS별도,MATCH(V$1,BS별도H,0),0)/100,"") | W24: =IFERROR(VLOOKUP($D24,BS별도,MATCH(W$1,BS별도H,0),0)/100,"") | X24: =IFERROR(VLOOKUP($D24,BS별도,MATCH(X$1,BS별도H,0),0)/100,"") | Y24: =IFERROR(VLOOKUP($D24,BS별도,MATCH(Y$1,BS별도H,0),0)/100,"") | Z24: =Y24 | AA24: =IFERROR(VLOOKUP($D24,BS별도,MATCH(AA$1,BS별도H,0),0)/100,"") | AB24: =IFERROR(VLOOKUP($D24,BS별도,MATCH(AB$1,BS별도H,0),0)/100,"") | AC24: =IFERROR(AB24*(1+변수!AC32),"") | AD24: =IFERROR(AC24*(1+변수!AD32),"") | AE24: =AD24 | AF24: =IFERROR(AD24*(1+변수!AF32),"") | AG24: =IFERROR(AF24*(1+변수!AG32),"") | AH24: =IFERROR(AG24*(1+변수!AH32),"") | AI24: =IFERROR(AH24*(1+변수!AI32),"") | AJ24: =AI24 | AK24: =IFERROR(AI24*(1+변수!AK32),"") | AL24: =IFERROR(AK24*(1+변수!AL32),"") | AM24: =IFERROR(AL24*(1+변수!AM32),"") | AN24: =IFERROR(AM24*(1+변수!AN32),"") | AO24: =AN24
A25: 순차입금 | B25: 재무상태 | C25: 억원 | D25: 순차입금 | E25: =IFERROR(VLOOKUP($D25,BS별도,MATCH(E$1,BS별도H,0),0)/100,"") | F25: 25.45 | G25: =IFERROR(VLOOKUP($D25,BS별도,MATCH(G$1,BS별도H,0),0)/100,"") | H25: =IFERROR(VLOOKUP($D25,BS별도,MATCH(H$1,BS별도H,0),0)/100,"") | I25: =IFERROR(VLOOKUP($D25,BS별도,MATCH(I$1,BS별도H,0),0)/100,"") | J25: =IFERROR(VLOOKUP($D25,BS별도,MATCH(J$1,BS별도H,0),0)/100,"") | K25: =J25 | L25: =IFERROR(VLOOKUP($D25,BS별도,MATCH(L$1,BS별도H,0),0)/100,"") | M25: =IFERROR(VLOOKUP($D25,BS별도,MATCH(M$1,BS별도H,0),0)/100,"") | N25: =IFERROR(VLOOKUP($D25,BS별도,MATCH(N$1,BS별도H,0),0)/100,"") | O25: =IFERROR(VLOOKUP($D25,BS별도,MATCH(O$1,BS별도H,0),0)/100,"") | P25: =O25 | Q25: =IFERROR(VLOOKUP($D25,BS별도,MATCH(Q$1,BS별도H,0),0)/100,"") | T25: =IFERROR(VLOOKUP($D25,BS별도,MATCH(T$1,BS별도H,0),0)/100,"") | U25: =T25 | V25: =IFERROR(VLOOKUP($D25,BS별도,MATCH(V$1,BS별도H,0),0)/100,"") | W25: =IFERROR(VLOOKUP($D25,BS별도,MATCH(W$1,BS별도H,0),0)/100,"") | X25: =IFERROR(VLOOKUP($D25,BS별도,MATCH(X$1,BS별도H,0),0)/100,"") | Y25: =IFERROR(VLOOKUP($D25,BS별도,MATCH(Y$1,BS별도H,0),0)/100,"") | Z25: =Y25 | AA25: =IFERROR(VLOOKUP($D25,BS별도,MATCH(AA$1,BS별도H,0),0)/100,"") | AB25: =IFERROR(VLOOKUP($D25,BS별도,MATCH(AB$1,BS별도H,0),0)/100,"") | AC25: =IFERROR(AB25*(1+변수!AC33),"") | AD25: =IFERROR(AC25*(1+변수!AD33),"") | AE25: =AD25 | AF25: =IFERROR(AD25*(1+변수!AF33),"") | AG25: =IFERROR(AF25*(1+변수!AG33),"") | AH25: =IFERROR(AG25*(1+변수!AH33),"") | AI25: =IFERROR(AH25*(1+변수!AI33),"") | AJ25: =AI25 | AK25: =IFERROR(AI25*(1+변수!AK33),"") | AL25: =IFERROR(AK25*(1+변수!AL33),"") | AM25: =IFERROR(AL25*(1+변수!AM33),"") | AN25: =IFERROR(AM25*(1+변수!AN33),"") | AO25: =AN25
A26: 이자발생자산 | B26: 재무상태 | C26: 억원 | D26: 이자발생자산 | E26: =IFERROR(VLOOKUP($D26,BS별도,MATCH(E$1,BS별도H,0),0)/100,"") | F26: 7.76 | G26: =IFERROR(VLOOKUP($D26,BS별도,MATCH(G$1,BS별도H,0),0)/100,"") | H26: =IFERROR(VLOOKUP($D26,BS별도,MATCH(H$1,BS별도H,0),0)/100,"") | I26: =IFERROR(VLOOKUP($D26,BS별도,MATCH(I$1,BS별도H,0),0)/100,"") | J26: =IFERROR(VLOOKUP($D26,BS별도,MATCH(J$1,BS별도H,0),0)/100,"") | K26: =J26 | L26: =IFERROR(VLOOKUP($D26,BS별도,MATCH(L$1,BS별도H,0),0)/100,"") | M26: =IFERROR(VLOOKUP($D26,BS별도,MATCH(M$1,BS별도H,0),0)/100,"") | N26: =IFERROR(VLOOKUP($D26,BS별도,MATCH(N$1,BS별도H,0),0)/100,"") | O26: =IFERROR(VLOOKUP($D26,BS별도,MATCH(O$1,BS별도H,0),0)/100,"") | P26: =O26 | Q26: =IFERROR(VLOOKUP($D26,BS별도,MATCH(Q$1,BS별도H,0),0)/100,"") | R26: =IFERROR(VLOOKUP($D26,BS별도,MATCH(R$1,BS별도H,0),0)/100,"") | S26: =IFERROR(VLOOKUP($D26,BS별도,MATCH(S$1,BS별도H,0),0)/100,"") | T26: =IFERROR(VLOOKUP($D26,BS별도,MATCH(T$1,BS별도H,0),0)/100,"") | U26: =T26 | V26: =IFERROR(VLOOKUP($D26,BS별도,MATCH(V$1,BS별도H,0),0)/100,"") | W26: =IFERROR(VLOOKUP($D26,BS별도,MATCH(W$1,BS별도H,0),0)/100,"") | X26: =IFERROR(VLOOKUP($D26,BS별도,MATCH(X$1,BS별도H,0),0)/100,"") | Y26: =IFERROR(VLOOKUP($D26,BS별도,MATCH(Y$1,BS별도H,0),0)/100,"") | Z26: =Y26 | AA26: =IFERROR(VLOOKUP($D26,BS별도,MATCH(AA$1,BS별도H,0),0)/100,"") | AB26: =IFERROR(VLOOKUP($D26,BS별도,MATCH(AB$1,BS별도H,0),0)/100,"") | AC26: =IFERROR(AB26*(1+변수!AC34),"") | AD26: =IFERROR(AC26*(1+변수!AD34),"") | AE26: =AD26 | AF26: =IFERROR(AD26*(1+변수!AF34),"") | AG26: =IFERROR(AF26*(1+변수!AG34),"") | AH26: =IFERROR(AG26*(1+변수!AH34),"") | AI26: =IFERROR(AH26*(1+변수!AI34),"") | AJ26: =AI26 | AK26: =IFERROR(AI26*(1+변수!AK34),"") | AL26: =IFERROR(AK26*(1+변수!AL34),"") | AM26: =IFERROR(AL26*(1+변수!AM34),"") | AN26: =IFERROR(AM26*(1+변수!AN34),"") | AO26: =AN26
A27: 현금및현금성자산 | B27: 재무상태 | C27: 억원 | D27: 현금및현금성자산 | E27: =IFERROR(VLOOKUP($D27,BS별도,MATCH(E$1,BS별도H,0),0)/100,"") | F27: 7.75 | G27: =IFERROR(VLOOKUP($D27,BS별도,MATCH(G$1,BS별도H,0),0)/100,"") | H27: =IFERROR(VLOOKUP($D27,BS별도,MATCH(H$1,BS별도H,0),0)/100,"") | I27: =IFERROR(VLOOKUP($D27,BS별도,MATCH(I$1,BS별도H,0),0)/100,"") | J27: =IFERROR(VLOOKUP($D27,BS별도,MATCH(J$1,BS별도H,0),0)/100,"") | K27: =J27 | L27: =IFERROR(VLOOKUP($D27,BS별도,MATCH(L$1,BS별도H,0),0)/100,"") | M27: =IFERROR(VLOOKUP($D27,BS별도,MATCH(M$1,BS별도H,0),0)/100,"") | N27: =IFERROR(VLOOKUP($D27,BS별도,MATCH(N$1,BS별도H,0),0)/100,"") | O27: =IFERROR(VLOOKUP($D27,BS별도,MATCH(O$1,BS별도H,0),0)/100,"") | P27: =O27 | Q27: =IFERROR(VLOOKUP($D27,BS별도,MATCH(Q$1,BS별도H,0),0)/100,"") | R27: =IFERROR(VLOOKUP($D27,BS별도,MATCH(R$1,BS별도H,0),0)/100,"") | S27: =IFERROR(VLOOKUP($D27,BS별도,MATCH(S$1,BS별도H,0),0)/100,"") | T27: =IFERROR(VLOOKUP($D27,BS별도,MATCH(T$1,BS별도H,0),0)/100,"") | U27: =T27 | V27: =IFERROR(VLOOKUP($D27,BS별도,MATCH(V$1,BS별도H,0),0)/100,"") | W27: =IFERROR(VLOOKUP($D27,BS별도,MATCH(W$1,BS별도H,0),0)/100,"") | X27: =IFERROR(VLOOKUP($D27,BS별도,MATCH(X$1,BS별도H,0),0)/100,"") | Y27: =IFERROR(VLOOKUP($D27,BS별도,MATCH(Y$1,BS별도H,0),0)/100,"") | Z27: =Y27 | AA27: =IFERROR(VLOOKUP($D27,BS별도,MATCH(AA$1,BS별도H,0),0)/100,"") | AB27: =IFERROR(VLOOKUP($D27,BS별도,MATCH(AB$1,BS별도H,0),0)/100,"") | AE27: =AD27 | AJ27: =AI27 | AO27: =AN27
A28: CAPEX | B28: 현금흐름 | C28: 억원 | D28: CAPEX | E28: =IFERROR(VLOOKUP($D28,BS별도,MATCH(E$1,BS별도H,0),0)/100,"") | G28: =IFERROR(VLOOKUP($D28,BS별도,MATCH(G$1,BS별도H,0),0)/100,"") | H28: =IFERROR(VLOOKUP($D28,BS별도,MATCH(H$1,BS별도H,0),0)/100,"") | I28: =IFERROR(VLOOKUP($D28,BS별도,MATCH(I$1,BS별도H,0),0)/100,"") | J28: =IFERROR(VLOOKUP($D28,BS별도,MATCH(J$1,BS별도H,0),0)/100,"") | K28: =SUM(G28:J28) | L28: =IFERROR(VLOOKUP($D28,BS별도,MATCH(L$1,BS별도H,0),0)/100,"") | M28: =IFERROR(VLOOKUP($D28,BS별도,MATCH(M$1,BS별도H,0),0)/100,"") | N28: =IFERROR(VLOOKUP($D28,BS별도,MATCH(N$1,BS별도H,0),0)/100,"") | O28: =IFERROR(VLOOKUP($D28,BS별도,MATCH(O$1,BS별도H,0),0)/100,"") | P28: =SUM(L28:O28) | Q28: =IFERROR(VLOOKUP($D28,BS별도,MATCH(Q$1,BS별도H,0),0)/100,"") | R28: =IFERROR(VLOOKUP($D28,BS별도,MATCH(R$1,BS별도H,0),0)/100,"") | S28: =IFERROR(VLOOKUP($D28,BS별도,MATCH(S$1,BS별도H,0),0)/100,"") | T28: =IFERROR(VLOOKUP($D28,BS별도,MATCH(T$1,BS별도H,0),0)/100,"") | U28: =SUM(Q28:T28) | V28: =IFERROR(VLOOKUP($D28,BS별도,MATCH(V$1,BS별도H,0),0)/100,"") | W28: =IFERROR(VLOOKUP($D28,BS별도,MATCH(W$1,BS별도H,0),0)/100,"") | X28: =IFERROR(VLOOKUP($D28,BS별도,MATCH(X$1,BS별도H,0),0)/100,"") | Y28: =IFERROR(VLOOKUP($D28,BS별도,MATCH(Y$1,BS별도H,0),0)/100,"") | Z28: =SUM(V28:Y28) | AA28: =IFERROR(VLOOKUP($D28,BS별도,MATCH(AA$1,BS별도H,0),0)/100,"") | AB28: =IFERROR(VLOOKUP($D28,BS별도,MATCH(AB$1,BS별도H,0),0)/100,"") | AC28: =IFERROR(X28*(1+변수!AC36),"") | AD28: =IFERROR(Y28*(1+변수!AD36),"") | AE28: =SUM(AA28:AD28) | AF28: =IFERROR(AA28*(1+변수!AF36),"") | AG28: =IFERROR(AB28*(1+변수!AG36),"") | AH28: =IFERROR(AC28*(1+변수!AH36),"") | AI28: =IFERROR(AD28*(1+변수!AI36),"") | AJ28: =SUM(AF28:AI28) | AK28: =IFERROR(AF28*(1+변수!AK36),"") | AL28: =IFERROR(AG28*(1+변수!AL36),"") | AM28: =IFERROR(AH28*(1+변수!AM36),"") | AN28: =IFERROR(AI28*(1+변수!AN36),"") | AO28: =SUM(AK28:AN28)
A29: 영업활동현금흐름 | B29: 현금흐름 | C29: 억원 | D29: 영업활동으로인한현금흐름 | E29: =IFERROR(VLOOKUP($D29,BS별도,MATCH(E$1,BS별도H,0),0)/100,"") | G29: =IFERROR(VLOOKUP($D29,BS별도,MATCH(G$1,BS별도H,0),0)/100,"") | H29: =IFERROR(VLOOKUP($D29,BS별도,MATCH(H$1,BS별도H,0),0)/100,"") | I29: =IFERROR(VLOOKUP($D29,BS별도,MATCH(I$1,BS별도H,0),0)/100,"") | J29: =IFERROR(VLOOKUP($D29,BS별도,MATCH(J$1,BS별도H,0),0)/100,"") | K29: =SUM(G29:J29) | L29: =IFERROR(VLOOKUP($D29,BS별도,MATCH(L$1,BS별도H,0),0)/100,"") | M29: =IFERROR(VLOOKUP($D29,BS별도,MATCH(M$1,BS별도H,0),0)/100,"") | N29: =IFERROR(VLOOKUP($D29,BS별도,MATCH(N$1,BS별도H,0),0)/100,"") | O29: =IFERROR(VLOOKUP($D29,BS별도,MATCH(O$1,BS별도H,0),0)/100,"") | P29: =SUM(L29:O29) | Q29: =IFERROR(VLOOKUP($D29,BS별도,MATCH(Q$1,BS별도H,0),0)/100,"") | R29: =IFERROR(VLOOKUP($D29,BS별도,MATCH(R$1,BS별도H,0),0)/100,"") | S29: =IFERROR(VLOOKUP($D29,BS별도,MATCH(S$1,BS별도H,0),0)/100,"") | T29: =IFERROR(VLOOKUP($D29,BS별도,MATCH(T$1,BS별도H,0),0)/100,"") | U29: =SUM(Q29:T29) | V29: =IFERROR(VLOOKUP($D29,BS별도,MATCH(V$1,BS별도H,0),0)/100,"") | W29: =IFERROR(VLOOKUP($D29,BS별도,MATCH(W$1,BS별도H,0),0)/100,"") | X29: =IFERROR(VLOOKUP($D29,BS별도,MATCH(X$1,BS별도H,0),0)/100,"") | Y29: =IFERROR(VLOOKUP($D29,BS별도,MATCH(Y$1,BS별도H,0),0)/100,"") | Z29: =SUM(V29:Y29) | AA29: =IFERROR(VLOOKUP($D29,BS별도,MATCH(AA$1,BS별도H,0),0)/100,"") | AB29: =IFERROR(VLOOKUP($D29,BS별도,MATCH(AB$1,BS별도H,0),0)/100,"") | AE29: =SUM(AA29:AD29) | AJ29: =SUM(AF29:AI29) | AO29: =SUM(AK29:AN29)
A30: 주식수 | B30: 주당 | C30: 백만주 | D30: 유통주식수 | E30: 7.2 | F30: =E30 | G30: 7.2 | H30: 7.2 | I30: 7.2 | J30: 7.2 | K30: =J30 | L30: 7.2 | M30: 7.2 | N30: 7.2 | O30: 7.2 | P30: =O30 | Q30: 7.2 | R30: 7.2 | S30: 7.2 | T30: 7.2 | U30: =T30 | V30: 7.2 | W30: 7.2 | X30: 7.2 | Y30: 7.2 | Z30: =Y30 | AA30: 7.2 | AB30: 7.2 | AC30: =IFERROR(AB30*(1+변수!AC38),"") | AD30: =IFERROR(AC30*(1+변수!AD38),"") | AE30: =AD30 | AF30: =IFERROR(AD30*(1+변수!AF38),"") | AG30: =IFERROR(AF30*(1+변수!AG38),"") | AH30: =IFERROR(AG30*(1+변수!AH38),"") | AI30: =IFERROR(AH30*(1+변수!AI38),"") | AJ30: =AI30 | AK30: =IFERROR(AI30*(1+변수!AK38),"") | AL30: =IFERROR(AK30*(1+변수!AL38),"") | AM30: =IFERROR(AL30*(1+변수!AM38),"") | AN30: =IFERROR(AM30*(1+변수!AN38),"") | AO30: =AN30
A31: EPS | B31: 주당 | C31: 원 | D31: EPS | E31: =IFERROR(E19*100/E30,"") | G31: =IFERROR(G19*100/G30,"") | H31: =IFERROR(H19*100/H30,"") | I31: =IFERROR(I19*100/I30,"") | J31: =IFERROR(J19*100/J30,"") | K31: =SUM(G31:J31) | L31: =IFERROR(L19*100/L30,"") | M31: =IFERROR(M19*100/M30,"") | N31: =IFERROR(N19*100/N30,"") | O31: =IFERROR(O19*100/O30,"") | P31: =SUM(L31:O31) | Q31: =IFERROR(Q19*100/Q30,"") | R31: =IFERROR(R19*100/R30,"") | S31: =IFERROR(S19*100/S30,"") | T31: =IFERROR(T19*100/T30,"") | U31: =SUM(Q31:T31) | V31: =IFERROR(V19*100/V30,"") | W31: =IFERROR(W19*100/W30,"") | X31: =IFERROR(X19*100/X30,"") | Y31: =IFERROR(Y19*100/Y30,"") | Z31: =SUM(V31:Y31) | AA31: =IFERROR(AA19*100/AA30,"") | AB31: =IFERROR(AB19*100/AB30,"") | AC31: =IFERROR(AC19*100/AC30,"") | AD31: =IFERROR(AD19*100/AD30,"") | AE31: =SUM(AA31:AD31) | AF31: =IFERROR(AF19*100/AF30,"") | AG31: =IFERROR(AG19*100/AG30,"") | AH31: =IFERROR(AH19*100/AH30,"") | AI31: =IFERROR(AI19*100/AI30,"") | AJ31: =SUM(AF31:AI31) | AK31: =IFERROR(AK19*100/AK30,"") | AL31: =IFERROR(AL19*100/AL30,"") | AM31: =IFERROR(AM19*100/AM30,"") | AN31: =IFERROR(AN19*100/AN30,"") | AO31: =SUM(AK31:AN31)
A32: 조정EPS | B32: 주당 | C32: 원 | D32: 조정 EPS(일회성 의심 분기의 초과 비영업손익 세후 차감 — 모델 추정) | E32: =IFERROR(E31,"") | G32: =IFERROR(G31,"") | H32: =IFERROR(H31,"") | I32: =IFERROR(I31,"") | J32: =IFERROR(J31,"") | K32: =SUM(G32:J32) | L32: =IFERROR(L31,"") | M32: =IFERROR(M31,"") | N32: =IFERROR(N31,"") | O32: =IFERROR(O31,"") | P32: =SUM(L32:O32) | Q32: =IFERROR(Q31,"") | R32: =IFERROR(R31,"") | S32: =IFERROR(S31,"") | T32: =IFERROR(T31,"") | U32: =SUM(Q32:T32) | V32: =IFERROR(V31,"") | W32: =IFERROR(W31,"") | X32: =IFERROR(X31,"") | Y32: =IFERROR((Y19-(-7.44)*(1.0))*100/Y30,"") | Z32: =SUM(V32:Y32) | AA32: =IFERROR(AA31,"") | AB32: =IFERROR(AB31,"") | AC32: =IFERROR(AC31,"") | AD32: =IFERROR(AD31,"") | AE32: =SUM(AA32:AD32) | AF32: =IFERROR(AF31,"") | AG32: =IFERROR(AG31,"") | AH32: =IFERROR(AH31,"") | AI32: =IFERROR(AI31,"") | AJ32: =SUM(AF32:AI32) | AK32: =IFERROR(AK31,"") | AL32: =IFERROR(AL31,"") | AM32: =IFERROR(AM31,"") | AN32: =IFERROR(AN31,"") | AO32: =SUM(AK32:AN32)
A33: BPS | B33: 주당 | C33: 원 | D33: BPS | E33: =IFERROR(E23*100/E30,"") | F33: =E33 | G33: =IFERROR(G23*100/G30,"") | H33: =IFERROR(H23*100/H30,"") | I33: =IFERROR(I23*100/I30,"") | J33: =IFERROR(J23*100/J30,"") | K33: =J33 | L33: =IFERROR(L23*100/L30,"") | M33: =IFERROR(M23*100/M30,"") | N33: =IFERROR(N23*100/N30,"") | O33: =IFERROR(O23*100/O30,"") | P33: =O33 | Q33: =IFERROR(Q23*100/Q30,"") | R33: =IFERROR(R23*100/R30,"") | S33: =IFERROR(S23*100/S30,"") | T33: =IFERROR(T23*100/T30,"") | U33: =T33 | V33: =IFERROR(V23*100/V30,"") | W33: =IFERROR(W23*100/W30,"") | X33: =IFERROR(X23*100/X30,"") | Y33: =IFERROR(Y23*100/Y30,"") | Z33: =Y33 | AA33: =IFERROR(AA23*100/AA30,"") | AB33: =IFERROR(AB23*100/AB30,"") | AC33: =IFERROR(AC23*100/AC30,"") | AD33: =IFERROR(AD23*100/AD30,"") | AE33: =AD33 | AF33: =IFERROR(AF23*100/AF30,"") | AG33: =IFERROR(AG23*100/AG30,"") | AH33: =IFERROR(AH23*100/AH30,"") | AI33: =IFERROR(AI23*100/AI30,"") | AJ33: =AI33 | AK33: =IFERROR(AK23*100/AK30,"") | AL33: =IFERROR(AL23*100/AL30,"") | AM33: =IFERROR(AM23*100/AM30,"") | AN33: =IFERROR(AN23*100/AN30,"") | AO33: =AN33
A34: DPS | B34: 주당 | C34: 원 | D34: DPS(보통주) | E34: 0 | F34: 0 | J34: 0 | K34: =SUM(G34:J34) | O34: 0 | P34: =SUM(L34:O34) | T34: 0 | U34: =SUM(Q34:T34) | Y34: 0 | Z34: =SUM(V34:Y34) | AD34: =변수!AD39 | AE34: =SUM(AA34:AD34) | AI34: =변수!AI39 | AJ34: =SUM(AF34:AI34) | AN34: =변수!AN39 | AO34: =SUM(AK34:AN34)
A35: PER | B35: 주당 | C35: 배 | D35: PER | F35: =E35 | K35: =J35 | L35: =IFERROR(변수!L18/(H31+I31+J31+L31),"") | M35: =IFERROR(변수!M18/(I31+J31+L31+M31),"") | N35: =IFERROR(변수!N18/(J31+L31+M31+N31),"") | O35: =IFERROR(변수!O18/(L31+M31+N31+O31),"") | P35: =O35 | Q35: =IFERROR(변수!Q18/(M31+N31+O31+Q31),"") | R35: =IFERROR(변수!R18/(N31+O31+Q31+R31),"") | S35: =IFERROR(변수!S18/(O31+Q31+R31+S31),"") | T35: =IFERROR(변수!T18/(Q31+R31+S31+T31),"") | U35: =T35 | V35: =IFERROR(변수!V18/(R31+S31+T31+V31),"") | W35: =IFERROR(변수!W18/(S31+T31+V31+W31),"") | X35: =IFERROR(변수!X18/(T31+V31+W31+X31),"") | Y35: =IFERROR(변수!Y18/(V31+W31+X31+Y31),"") | Z35: =Y35 | AA35: =IFERROR(변수!AA18/(W31+X31+Y31+AA31),"") | AB35: =IFERROR(변수!AB18/(X31+Y31+AA31+AB31),"") | AC35: =IFERROR(변수!$D$42/(Y31+AA31+AB31+AC31),"") | AD35: =IFERROR(변수!$D$42/(AA31+AB31+AC31+AD31),"") | AE35: =AD35 | AF35: =IFERROR(변수!$D$42/(AB31+AC31+AD31+AF31),"") | AG35: =IFERROR(변수!$D$42/(AC31+AD31+AF31+AG31),"") | AH35: =IFERROR(변수!$D$42/(AD31+AF31+AG31+AH31),"") | AI35: =IFERROR(변수!$D$42/(AF31+AG31+AH31+AI31),"") | AJ35: =AI35 | AK35: =IFERROR(변수!$D$42/(AG31+AH31+AI31+AK31),"") | AL35: =IFERROR(변수!$D$42/(AH31+AI31+AK31+AL31),"") | AM35: =IFERROR(변수!$D$42/(AI31+AK31+AL31+AM31),"") | AN35: =IFERROR(변수!$D$42/(AK31+AL31+AM31+AN31),"") | AO35: =AN35
A36: PBR | B36: 주당 | C36: 배 | D36: PBR | F36: =E36 | K36: =J36 | L36: =IFERROR(변수!L18/L33,"") | M36: =IFERROR(변수!M18/M33,"") | N36: =IFERROR(변수!N18/N33,"") | O36: =IFERROR(변수!O18/O33,"") | P36: =O36 | Q36: =IFERROR(변수!Q18/Q33,"") | R36: =IFERROR(변수!R18/R33,"") | S36: =IFERROR(변수!S18/S33,"") | T36: =IFERROR(변수!T18/T33,"") | U36: =T36 | V36: =IFERROR(변수!V18/V33,"") | W36: =IFERROR(변수!W18/W33,"") | X36: =IFERROR(변수!X18/X33,"") | Y36: =IFERROR(변수!Y18/Y33,"") | Z36: =Y36 | AA36: =IFERROR(변수!AA18/AA33,"") | AB36: =IFERROR(변수!AB18/AB33,"") | AC36: =IFERROR(변수!$D$42/AC33,"") | AD36: =IFERROR(변수!$D$42/AD33,"") | AE36: =AD36 | AF36: =IFERROR(변수!$D$42/AF33,"") | AG36: =IFERROR(변수!$D$42/AG33,"") | AH36: =IFERROR(변수!$D$42/AH33,"") | AI36: =IFERROR(변수!$D$42/AI33,"") | AJ36: =AI36 | AK36: =IFERROR(변수!$D$42/AK33,"") | AL36: =IFERROR(변수!$D$42/AL33,"") | AM36: =IFERROR(변수!$D$42/AM33,"") | AN36: =IFERROR(변수!$D$42/AN33,"") | AO36: =AN36
A37: 매출전사 | B37: 사업부 | C37: 억원 | D37: 매출 전사(부문 미분리) | E37: 93.05 | G37: 73.59 | H37: 95.66 | I37: 88.97 | J37: 101.94 | K37: =SUM(G37:J37) | L37: 109.68 | M37: 115.38 | N37: 99.01 | O37: 112.26 | P37: =SUM(L37:O37) | Q37: 106.89 | R37: 115.24 | S37: 97.1 | T37: 152.08 | U37: =SUM(Q37:T37) | V37: 125.39 | W37: 120.34 | X37: 116.42 | Y37: 125.9 | Z37: =SUM(V37:Y37) | AA37: 114.94 | AB37: 127.96 | AC37: =IFERROR(AC5,"") | AD37: =IFERROR(AD5,"") | AE37: =SUM(AA37:AD37) | AF37: =IFERROR(AF5,"") | AG37: =IFERROR(AG5,"") | AH37: =IFERROR(AH5,"") | AI37: =IFERROR(AI5,"") | AJ37: =SUM(AF37:AI37) | AK37: =IFERROR(AK5,"") | AL37: =IFERROR(AL5,"") | AM37: =IFERROR(AM5,"") | AN37: =IFERROR(AN5,"") | AO37: =SUM(AK37:AN37)
A38: OP전사 | B38: 사업부 | C38: 억원 | D38: OP 전사(부문 미분리) | E38: 14.6 | G38: 0.57 | H38: 3.64 | I38: 9.43 | J38: 11.35 | K38: =SUM(G38:J38) | L38: 11.12 | M38: 11.44 | N38: 6.03 | O38: 3.73 | P38: =SUM(L38:O38) | Q38: 10.57 | R38: 7.56 | S38: -4.72 | T38: 21.14 | U38: =SUM(Q38:T38) | V38: -0.76 | W38: 7.1 | X38: 3.7 | Y38: -1.02 | Z38: =SUM(V38:Y38) | AA38: 3.09 | AB38: 4.15 | AC38: =IFERROR(AC9,"") | AD38: =IFERROR(AD9,"") | AE38: =SUM(AA38:AD38) | AF38: =IFERROR(AF9,"") | AG38: =IFERROR(AG9,"") | AH38: =IFERROR(AH9,"") | AI38: =IFERROR(AI9,"") | AJ38: =SUM(AF38:AI38) | AK38: =IFERROR(AK9,"") | AL38: =IFERROR(AL9,"") | AM38: =IFERROR(AM9,"") | AN38: =IFERROR(AN9,"") | AO38: =SUM(AK38:AN38)
B39: 비율(참고)
A40: NPM | C40: % | D40: 지배주주순이익 / 매출액 | E40: =IFERROR(E19/E5,"") | F40: =IFERROR(F19/F5,"") | G40: =IFERROR(G19/G5,"") | H40: =IFERROR(H19/H5,"") | I40: =IFERROR(I19/I5,"") | J40: =IFERROR(J19/J5,"") | K40: =IFERROR(K19/K5,"") | L40: =IFERROR(L19/L5,"") | ... AO40: =IFERROR(AO19/AO5,"")
A41: 매출원가율 | C41: % | D41: 매출원가 / 매출액 | E41: =IFERROR(E6/E5,"") | F41: =IFERROR(F6/F5,"") | G41: =IFERROR(G6/G5,"") | H41: =IFERROR(H6/H5,"") | I41: =IFERROR(I6/I5,"") | J41: =IFERROR(J6/J5,"") | K41: =IFERROR(K6/K5,"") | L41: =IFERROR(L6/L5,"") | ... AO41: =IFERROR(AO6/AO5,"")
A42: 판관비율 | C42: % | D42: 판관비 / 매출액 | E42: =IFERROR(E8/E5,"") | F42: =IFERROR(F8/F5,"") | G42: =IFERROR(G8/G5,"") | H42: =IFERROR(H8/H5,"") | I42: =IFERROR(I8/I5,"") | J42: =IFERROR(J8/J5,"") | K42: =IFERROR(K8/K5,"") | L42: =IFERROR(L8/L5,"") | ... AO42: =IFERROR(AO8/AO5,"")

Sheet 분기
C1: 이름: 분기H — subQ 를 이름으로 VLOOKUP(억원) | E1: 4Q21 | F1: 1Q22 | G1: 2Q22 | H1: 3Q22 | I1: 4Q22 | J1: 1Q23 | K1: 2Q23 | L1: 3Q23 | M1: 4Q23 | N1: 1Q24 | O1: 2Q24 | P1: 3Q24 | Q1: 4Q24 | R1: 1Q25 | S1: 2Q25 | T1: 3Q25 | U1: 4Q25 | V1: 1Q26 | W1: 2Q26 | X1: 3Q26 | Y1: 4Q26 | Z1: 1Q27 | AA1: 2Q27 | AB1: 3Q27 | AC1: 4Q27 | AD1: 1Q28 | AE1: 2Q28 | AF1: 3Q28 | AG1: 4Q28
C2: 종가: | D2: =변수!D42
C3: 기준일: | D3: 20261013 | E3: 1 | F3: 2 | G3: 3 | H3: 4 | I3: 5 | J3: 6 | K3: 7 | L3: 8 | M3: 9 | N3: 10 | O3: 11 | P3: 12 | Q3: 13 | R3: 14 | S3: 15 | T3: 16 | U3: 17 | V3: 18 | W3: 19 | X3: 20 | Y3: 21 | Z3: 22 | AA3: 23 | AB3: 24 | AC3: 25 | AD3: 26 | AE3: 27 | AF3: 28 | AG3: 29
E4: 2021.12 | F4: 2022.03 | G4: 2022.06 | H4: 2022.09 | I4: 2022.12 | J4: 2023.03 | K4: 2023.06 | L4: 2023.09 | M4: 2023.12 | N4: 2024.03 | O4: 2024.06 | P4: 2024.09 | Q4: 2024.12 | R4: 2025.03 | S4: 2025.06 | T4: 2025.09 | U4: 2025.12 | V4: 2026.03 | W4: 2026.06 | X4: 2026.09 | Y4: 2026.12 | Z4: 2027.03 | AA4: 2027.06 | AB4: 2027.09 | AC4: 2027.12 | AD4: 2028.03 | AE4: 2028.06 | AF4: 2028.09 | AG4: 2028.12
A5: 매출액 | D5: 매출액 | E5: =IFERROR(VLOOKUP($A5,subQ,MATCH(E$1,SUBQH,0),0),"") | F5: =IFERROR(VLOOKUP($A5,subQ,MATCH(F$1,SUBQH,0),0),"") | G5: =IFERROR(VLOOKUP($A5,subQ,MATCH(G$1,SUBQH,0),0),"") | H5: =IFERROR(VLOOKUP($A5,subQ,MATCH(H$1,SUBQH,0),0),"") | I5: =IFERROR(VLOOKUP($A5,subQ,MATCH(I$1,SUBQH,0),0),"") | J5: =IFERROR(VLOOKUP($A5,subQ,MATCH(J$1,SUBQH,0),0),"") | K5: =IFERROR(VLOOKUP($A5,subQ,MATCH(K$1,SUBQH,0),0),"") | L5: =IFERROR(VLOOKUP($A5,subQ,MATCH(L$1,SUBQH,0),0),"") | ... AG5: =IFERROR(VLOOKUP($A5,subQ,MATCH(AG$1,SUBQH,0),0),"")
A6: 매출원가 | D6: 매출원가 | E6: =IFERROR(VLOOKUP($A6,subQ,MATCH(E$1,SUBQH,0),0),"") | F6: =IFERROR(VLOOKUP($A6,subQ,MATCH(F$1,SUBQH,0),0),"") | G6: =IFERROR(VLOOKUP($A6,subQ,MATCH(G$1,SUBQH,0),0),"") | H6: =IFERROR(VLOOKUP($A6,subQ,MATCH(H$1,SUBQH,0),0),"") | I6: =IFERROR(VLOOKUP($A6,subQ,MATCH(I$1,SUBQH,0),0),"") | J6: =IFERROR(VLOOKUP($A6,subQ,MATCH(J$1,SUBQH,0),0),"") | K6: =IFERROR(VLOOKUP($A6,subQ,MATCH(K$1,SUBQH,0),0),"") | L6: =IFERROR(VLOOKUP($A6,subQ,MATCH(L$1,SUBQH,0),0),"") | ... AG6: =IFERROR(VLOOKUP($A6,subQ,MATCH(AG$1,SUBQH,0),0),"")
A7: 매출총이익 | D7: 매출총이익 | E7: =IFERROR(VLOOKUP($A7,subQ,MATCH(E$1,SUBQH,0),0),"") | F7: =IFERROR(VLOOKUP($A7,subQ,MATCH(F$1,SUBQH,0),0),"") | G7: =IFERROR(VLOOKUP($A7,subQ,MATCH(G$1,SUBQH,0),0),"") | H7: =IFERROR(VLOOKUP($A7,subQ,MATCH(H$1,SUBQH,0),0),"") | I7: =IFERROR(VLOOKUP($A7,subQ,MATCH(I$1,SUBQH,0),0),"") | J7: =IFERROR(VLOOKUP($A7,subQ,MATCH(J$1,SUBQH,0),0),"") | K7: =IFERROR(VLOOKUP($A7,subQ,MATCH(K$1,SUBQH,0),0),"") | L7: =IFERROR(VLOOKUP($A7,subQ,MATCH(L$1,SUBQH,0),0),"") | ... AG7: =IFERROR(VLOOKUP($A7,subQ,MATCH(AG$1,SUBQH,0),0),"")
A8: 판관비 | D8: 판매비와관리비 | E8: =IFERROR(VLOOKUP($A8,subQ,MATCH(E$1,SUBQH,0),0),"") | F8: =IFERROR(VLOOKUP($A8,subQ,MATCH(F$1,SUBQH,0),0),"") | G8: =IFERROR(VLOOKUP($A8,subQ,MATCH(G$1,SUBQH,0),0),"") | H8: =IFERROR(VLOOKUP($A8,subQ,MATCH(H$1,SUBQH,0),0),"") | I8: =IFERROR(VLOOKUP($A8,subQ,MATCH(I$1,SUBQH,0),0),"") | J8: =IFERROR(VLOOKUP($A8,subQ,MATCH(J$1,SUBQH,0),0),"") | K8: =IFERROR(VLOOKUP($A8,subQ,MATCH(K$1,SUBQH,0),0),"") | L8: =IFERROR(VLOOKUP($A8,subQ,MATCH(L$1,SUBQH,0),0),"") | ... AG8: =IFERROR(VLOOKUP($A8,subQ,MATCH(AG$1,SUBQH,0),0),"")
A9: 영업이익 | D9: 영업이익 | E9: =IFERROR(VLOOKUP($A9,subQ,MATCH(E$1,SUBQH,0),0),"") | F9: =IFERROR(VLOOKUP($A9,subQ,MATCH(F$1,SUBQH,0),0),"") | G9: =IFERROR(VLOOKUP($A9,subQ,MATCH(G$1,SUBQH,0),0),"") | H9: =IFERROR(VLOOKUP($A9,subQ,MATCH(H$1,SUBQH,0),0),"") | I9: =IFERROR(VLOOKUP($A9,subQ,MATCH(I$1,SUBQH,0),0),"") | J9: =IFERROR(VLOOKUP($A9,subQ,MATCH(J$1,SUBQH,0),0),"") | K9: =IFERROR(VLOOKUP($A9,subQ,MATCH(K$1,SUBQH,0),0),"") | L9: =IFERROR(VLOOKUP($A9,subQ,MATCH(L$1,SUBQH,0),0),"") | ... AG9: =IFERROR(VLOOKUP($A9,subQ,MATCH(AG$1,SUBQH,0),0),"")
A10: OPM | D10: 영업이익률 | E10: =IFERROR(VLOOKUP($A10,subQ,MATCH(E$1,SUBQH,0),0),"") | F10: =IFERROR(VLOOKUP($A10,subQ,MATCH(F$1,SUBQH,0),0),"") | G10: =IFERROR(VLOOKUP($A10,subQ,MATCH(G$1,SUBQH,0),0),"") | H10: =IFERROR(VLOOKUP($A10,subQ,MATCH(H$1,SUBQH,0),0),"") | I10: =IFERROR(VLOOKUP($A10,subQ,MATCH(I$1,SUBQH,0),0),"") | J10: =IFERROR(VLOOKUP($A10,subQ,MATCH(J$1,SUBQH,0),0),"") | K10: =IFERROR(VLOOKUP($A10,subQ,MATCH(K$1,SUBQH,0),0),"") | L10: =IFERROR(VLOOKUP($A10,subQ,MATCH(L$1,SUBQH,0),0),"") | ... AG10: =IFERROR(VLOOKUP($A10,subQ,MATCH(AG$1,SUBQH,0),0),"")
A11: 금융손익 | D11: 금융손익(이자·환 포함) | E11: =IFERROR(VLOOKUP($A11,subQ,MATCH(E$1,SUBQH,0),0),"") | F11: =IFERROR(VLOOKUP($A11,subQ,MATCH(F$1,SUBQH,0),0),"") | G11: =IFERROR(VLOOKUP($A11,subQ,MATCH(G$1,SUBQH,0),0),"") | H11: =IFERROR(VLOOKUP($A11,subQ,MATCH(H$1,SUBQH,0),0),"") | I11: =IFERROR(VLOOKUP($A11,subQ,MATCH(I$1,SUBQH,0),0),"") | J11: =IFERROR(VLOOKUP($A11,subQ,MATCH(J$1,SUBQH,0),0),"") | K11: =IFERROR(VLOOKUP($A11,subQ,MATCH(K$1,SUBQH,0),0),"") | L11: =IFERROR(VLOOKUP($A11,subQ,MATCH(L$1,SUBQH,0),0),"") | ... AG11: =IFERROR(VLOOKUP($A11,subQ,MATCH(AG$1,SUBQH,0),0),"")
A12: 이자손익 | D12: 이자손익(이자수익 − 이자비용) | E12: =IFERROR(VLOOKUP($A12,subQ,MATCH(E$1,SUBQH,0),0),"") | F12: =IFERROR(VLOOKUP($A12,subQ,MATCH(F$1,SUBQH,0),0),"") | G12: =IFERROR(VLOOKUP($A12,subQ,MATCH(G$1,SUBQH,0),0),"") | H12: =IFERROR(VLOOKUP($A12,subQ,MATCH(H$1,SUBQH,0),0),"") | I12: =IFERROR(VLOOKUP($A12,subQ,MATCH(I$1,SUBQH,0),0),"") | J12: =IFERROR(VLOOKUP($A12,subQ,MATCH(J$1,SUBQH,0),0),"") | K12: =IFERROR(VLOOKUP($A12,subQ,MATCH(K$1,SUBQH,0),0),"") | L12: =IFERROR(VLOOKUP($A12,subQ,MATCH(L$1,SUBQH,0),0),"") | ... AG12: =IFERROR(VLOOKUP($A12,subQ,MATCH(AG$1,SUBQH,0),0),"")
A13: 외환손익 | D13: 외환손익(실적만; 추정 환효과는 환관련손익) | E13: =IFERROR(VLOOKUP($A13,subQ,MATCH(E$1,SUBQH,0),0),"") | F13: =IFERROR(VLOOKUP($A13,subQ,MATCH(F$1,SUBQH,0),0),"") | G13: =IFERROR(VLOOKUP($A13,subQ,MATCH(G$1,SUBQH,0),0),"") | H13: =IFERROR(VLOOKUP($A13,subQ,MATCH(H$1,SUBQH,0),0),"") | I13: =IFERROR(VLOOKUP($A13,subQ,MATCH(I$1,SUBQH,0),0),"") | J13: =IFERROR(VLOOKUP($A13,subQ,MATCH(J$1,SUBQH,0),0),"") | K13: =IFERROR(VLOOKUP($A13,subQ,MATCH(K$1,SUBQH,0),0),"") | L13: =IFERROR(VLOOKUP($A13,subQ,MATCH(L$1,SUBQH,0),0),"") | ... AG13: =IFERROR(VLOOKUP($A13,subQ,MATCH(AG$1,SUBQH,0),0),"")
A14: 기타영업외손익 | D14: 기타영업외손익 | E14: =IFERROR(VLOOKUP($A14,subQ,MATCH(E$1,SUBQH,0),0),"") | F14: =IFERROR(VLOOKUP($A14,subQ,MATCH(F$1,SUBQH,0),0),"") | G14: =IFERROR(VLOOKUP($A14,subQ,MATCH(G$1,SUBQH,0),0),"") | H14: =IFERROR(VLOOKUP($A14,subQ,MATCH(H$1,SUBQH,0),0),"") | I14: =IFERROR(VLOOKUP($A14,subQ,MATCH(I$1,SUBQH,0),0),"") | J14: =IFERROR(VLOOKUP($A14,subQ,MATCH(J$1,SUBQH,0),0),"") | K14: =IFERROR(VLOOKUP($A14,subQ,MATCH(K$1,SUBQH,0),0),"") | L14: =IFERROR(VLOOKUP($A14,subQ,MATCH(L$1,SUBQH,0),0),"") | ... AG14: =IFERROR(VLOOKUP($A14,subQ,MATCH(AG$1,SUBQH,0),0),"")
A15: 지분법손익 | D15: 지분법손익 | E15: =IFERROR(VLOOKUP($A15,subQ,MATCH(E$1,SUBQH,0),0),"") | F15: =IFERROR(VLOOKUP($A15,subQ,MATCH(F$1,SUBQH,0),0),"") | G15: =IFERROR(VLOOKUP($A15,subQ,MATCH(G$1,SUBQH,0),0),"") | H15: =IFERROR(VLOOKUP($A15,subQ,MATCH(H$1,SUBQH,0),0),"") | I15: =IFERROR(VLOOKUP($A15,subQ,MATCH(I$1,SUBQH,0),0),"") | J15: =IFERROR(VLOOKUP($A15,subQ,MATCH(J$1,SUBQH,0),0),"") | K15: =IFERROR(VLOOKUP($A15,subQ,MATCH(K$1,SUBQH,0),0),"") | L15: =IFERROR(VLOOKUP($A15,subQ,MATCH(L$1,SUBQH,0),0),"") | ... AG15: =IFERROR(VLOOKUP($A15,subQ,MATCH(AG$1,SUBQH,0),0),"")
A16: 세전이익 | D16: 법인세비용차감전이익 | E16: =IFERROR(VLOOKUP($A16,subQ,MATCH(E$1,SUBQH,0),0),"") | F16: =IFERROR(VLOOKUP($A16,subQ,MATCH(F$1,SUBQH,0),0),"") | G16: =IFERROR(VLOOKUP($A16,subQ,MATCH(G$1,SUBQH,0),0),"") | H16: =IFERROR(VLOOKUP($A16,subQ,MATCH(H$1,SUBQH,0),0),"") | I16: =IFERROR(VLOOKUP($A16,subQ,MATCH(I$1,SUBQH,0),0),"") | J16: =IFERROR(VLOOKUP($A16,subQ,MATCH(J$1,SUBQH,0),0),"") | K16: =IFERROR(VLOOKUP($A16,subQ,MATCH(K$1,SUBQH,0),0),"") | L16: =IFERROR(VLOOKUP($A16,subQ,MATCH(L$1,SUBQH,0),0),"") | ... AG16: =IFERROR(VLOOKUP($A16,subQ,MATCH(AG$1,SUBQH,0),0),"")
... A39: NPM | D39: NPM | E39: =IFERROR(VLOOKUP($A39,subQ,MATCH(E$1,SUBQH,0),0),"") | F39: =IFERROR(VLOOKUP($A39,subQ,MATCH(F$1,SUBQH,0),0),"") | G39: =IFERROR(VLOOKUP($A39,subQ,MATCH(G$1,SUBQH,0),0),"") | H39: =IFERROR(VLOOKUP($A39,subQ,MATCH(H$1,SUBQH,0),0),"") | I39: =IFERROR(VLOOKUP($A39,subQ,MATCH(I$1,SUBQH,0),0),"") | J39: =IFERROR(VLOOKUP($A39,subQ,MATCH(J$1,SUBQH,0),0),"") | K39: =IFERROR(VLOOKUP($A39,subQ,MATCH(K$1,SUBQH,0),0),"") | L39: =IFERROR(VLOOKUP($A39,subQ,MATCH(L$1,SUBQH,0),0),"") | ... AG39: =IFERROR(VLOOKUP($A39,subQ,MATCH(AG$1,SUBQH,0),0),"")
A40: 매출액 YoY | D40: 매출액 YoY | I40: =IFERROR(I5/E5-1,"") | J40: =IFERROR(J5/F5-1,"") | K40: =IFERROR(K5/G5-1,"") | L40: =IFERROR(L5/H5-1,"") | M40: =IFERROR(M5/I5-1,"") | N40: =IFERROR(N5/J5-1,"") | O40: =IFERROR(O5/K5-1,"") | P40: =IFERROR(P5/L5-1,"") | ... AG40: =IFERROR(AG5/AC5-1,"")
A41: 영업이익 YoY | D41: 영업이익 YoY | I41: =IFERROR(I9/E9-1,"") | J41: =IFERROR(J9/F9-1,"") | K41: =IFERROR(K9/G9-1,"") | L41: =IFERROR(L9/H9-1,"") | M41: =IFERROR(M9/I9-1,"") | N41: =IFERROR(N9/J9-1,"") | O41: =IFERROR(O9/K9-1,"") | P41: =IFERROR(P9/L9-1,"") | ... AG41: =IFERROR(AG9/AC9-1,"")
A42: 지배주주순이익 YoY | D42: 지배주주순이익 YoY | I42: =IFERROR(I19/E19-1,"") | J42: =IFERROR(J19/F19-1,"") | K42: =IFERROR(K19/G19-1,"") | L42: =IFERROR(L19/H19-1,"") | M42: =IFERROR(M19/I19-1,"") | N42: =IFERROR(N19/J19-1,"") | O42: =IFERROR(O19/K19-1,"") | P42: =IFERROR(P19/L19-1,"") | ... AG42: =IFERROR(AG19/AC19-1,"")

Sheet 연간예상
C1: 이름: 연간예상H — subQ 를 이름으로 VLOOKUP(억원) | E1: 2021 | F1: 2022 | G1: 2023 | H1: 2024 | I1: 2025 | J1: 2026 | K1: 2027 | L1: 2028
C2: 종가: | D2: =변수!D42
C3: 기준일: | D3: 20261013 | E3: 1 | F3: 2 | G3: 3 | H3: 4 | I3: 5 | J3: 6 | K3: 7 | L3: 8
E4: 2021.12A | F4: 2022.12A | G4: 2023.12A | H4: 2024.12A | I4: 2025.12A | J4: 2026.12A | K4: 2027.12A | L4: 2028.12A
A5: 매출액 | D5: 매출액 | E5: =IFERROR(VLOOKUP($A5,subQ,MATCH(E$1,SUBQH,0),0),"") | F5: =IFERROR(VLOOKUP($A5,subQ,MATCH(F$1,SUBQH,0),0),"") | G5: =IFERROR(VLOOKUP($A5,subQ,MATCH(G$1,SUBQH,0),0),"") | H5: =IFERROR(VLOOKUP($A5,subQ,MATCH(H$1,SUBQH,0),0),"") | I5: =IFERROR(VLOOKUP($A5,subQ,MATCH(I$1,SUBQH,0),0),"") | J5: =IFERROR(VLOOKUP($A5,subQ,MATCH(J$1,SUBQH,0),0),"") | K5: =IFERROR(VLOOKUP($A5,subQ,MATCH(K$1,SUBQH,0),0),"") | L5: =IFERROR(VLOOKUP($A5,subQ,MATCH(L$1,SUBQH,0),0),"")
A6: 매출원가 | D6: 매출원가 | E6: =IFERROR(VLOOKUP($A6,subQ,MATCH(E$1,SUBQH,0),0),"") | F6: =IFERROR(VLOOKUP($A6,subQ,MATCH(F$1,SUBQH,0),0),"") | G6: =IFERROR(VLOOKUP($A6,subQ,MATCH(G$1,SUBQH,0),0),"") | H6: =IFERROR(VLOOKUP($A6,subQ,MATCH(H$1,SUBQH,0),0),"") | I6: =IFERROR(VLOOKUP($A6,subQ,MATCH(I$1,SUBQH,0),0),"") | J6: =IFERROR(VLOOKUP($A6,subQ,MATCH(J$1,SUBQH,0),0),"") | K6: =IFERROR(VLOOKUP($A6,subQ,MATCH(K$1,SUBQH,0),0),"") | L6: =IFERROR(VLOOKUP($A6,subQ,MATCH(L$1,SUBQH,0),0),"")
A7: 매출총이익 | D7: 매출총이익 | E7: =IFERROR(VLOOKUP($A7,subQ,MATCH(E$1,SUBQH,0),0),"") | F7: =IFERROR(VLOOKUP($A7,subQ,MATCH(F$1,SUBQH,0),0),"") | G7: =IFERROR(VLOOKUP($A7,subQ,MATCH(G$1,SUBQH,0),0),"") | H7: =IFERROR(VLOOKUP($A7,subQ,MATCH(H$1,SUBQH,0),0),"") | I7: =IFERROR(VLOOKUP($A7,subQ,MATCH(I$1,SUBQH,0),0),"") | J7: =IFERROR(VLOOKUP($A7,subQ,MATCH(J$1,SUBQH,0),0),"") | K7: =IFERROR(VLOOKUP($A7,subQ,MATCH(K$1,SUBQH,0),0),"") | L7: =IFERROR(VLOOKUP($A7,subQ,MATCH(L$1,SUBQH,0),0),"")
A8: 판관비 | D8: 판매비와관리비 | E8: =IFERROR(VLOOKUP($A8,subQ,MATCH(E$1,SUBQH,0),0),"") | F8: =IFERROR(VLOOKUP($A8,subQ,MATCH(F$1,SUBQH,0),0),"") | G8: =IFERROR(VLOOKUP($A8,subQ,MATCH(G$1,SUBQH,0),0),"") | H8: =IFERROR(VLOOKUP($A8,subQ,MATCH(H$1,SUBQH,0),0),"") | I8: =IFERROR(VLOOKUP($A8,subQ,MATCH(I$1,SUBQH,0),0),"") | J8: =IFERROR(VLOOKUP($A8,subQ,MATCH(J$1,SUBQH,0),0),"") | K8: =IFERROR(VLOOKUP($A8,subQ,MATCH(K$1,SUBQH,0),0),"") | L8: =IFERROR(VLOOKUP($A8,subQ,MATCH(L$1,SUBQH,0),0),"")
A9: 영업이익 | D9: 영업이익 | E9: =IFERROR(VLOOKUP($A9,subQ,MATCH(E$1,SUBQH,0),0),"") | F9: =IFERROR(VLOOKUP($A9,subQ,MATCH(F$1,SUBQH,0),0),"") | G9: =IFERROR(VLOOKUP($A9,subQ,MATCH(G$1,SUBQH,0),0),"") | H9: =IFERROR(VLOOKUP($A9,subQ,MATCH(H$1,SUBQH,0),0),"") | I9: =IFERROR(VLOOKUP($A9,subQ,MATCH(I$1,SUBQH,0),0),"") | J9: =IFERROR(VLOOKUP($A9,subQ,MATCH(J$1,SUBQH,0),0),"") | K9: =IFERROR(VLOOKUP($A9,subQ,MATCH(K$1,SUBQH,0),0),"") | L9: =IFERROR(VLOOKUP($A9,subQ,MATCH(L$1,SUBQH,0),0),"")
A10: OPM | D10: 영업이익률 | E10: =IFERROR(VLOOKUP($A10,subQ,MATCH(E$1,SUBQH,0),0),"") | F10: =IFERROR(VLOOKUP($A10,subQ,MATCH(F$1,SUBQH,0),0),"") | G10: =IFERROR(VLOOKUP($A10,subQ,MATCH(G$1,SUBQH,0),0),"") | H10: =IFERROR(VLOOKUP($A10,subQ,MATCH(H$1,SUBQH,0),0),"") | I10: =IFERROR(VLOOKUP($A10,subQ,MATCH(I$1,SUBQH,0),0),"") | J10: =IFERROR(VLOOKUP($A10,subQ,MATCH(J$1,SUBQH,0),0),"") | K10: =IFERROR(VLOOKUP($A10,subQ,MATCH(K$1,SUBQH,0),0),"") | L10: =IFERROR(VLOOKUP($A10,subQ,MATCH(L$1,SUBQH,0),0),"")
A11: 금융손익 | D11: 금융손익(이자·환 포함) | E11: =IFERROR(VLOOKUP($A11,subQ,MATCH(E$1,SUBQH,0),0),"") | F11: =IFERROR(VLOOKUP($A11,subQ,MATCH(F$1,SUBQH,0),0),"") | G11: =IFERROR(VLOOKUP($A11,subQ,MATCH(G$1,SUBQH,0),0),"") | H11: =IFERROR(VLOOKUP($A11,subQ,MATCH(H$1,SUBQH,0),0),"") | I11: =IFERROR(VLOOKUP($A11,subQ,MATCH(I$1,SUBQH,0),0),"") | J11: =IFERROR(VLOOKUP($A11,subQ,MATCH(J$1,SUBQH,0),0),"") | K11: =IFERROR(VLOOKUP($A11,subQ,MATCH(K$1,SUBQH,0),0),"") | L11: =IFERROR(VLOOKUP($A11,subQ,MATCH(L$1,SUBQH,0),0),"")
A12: 이자손익 | D12: 이자손익(이자수익 − 이자비용) | E12: =IFERROR(VLOOKUP($A12,subQ,MATCH(E$1,SUBQH,0),0),"") | F12: =IFERROR(VLOOKUP($A12,subQ,MATCH(F$1,SUBQH,0),0),"") | G12: =IFERROR(VLOOKUP($A12,subQ,MATCH(G$1,SUBQH,0),0),"") | H12: =IFERROR(VLOOKUP($A12,subQ,MATCH(H$1,SUBQH,0),0),"") | I12: =IFERROR(VLOOKUP($A12,subQ,MATCH(I$1,SUBQH,0),0),"") | J12: =IFERROR(VLOOKUP($A12,subQ,MATCH(J$1,SUBQH,0),0),"") | K12: =IFERROR(VLOOKUP($A12,subQ,MATCH(K$1,SUBQH,0),0),"") | L12: =IFERROR(VLOOKUP($A12,subQ,MATCH(L$1,SUBQH,0),0),"")
A13: 외환손익 | D13: 외환손익(실적만; 추정 환효과는 환관련손익) | E13: =IFERROR(VLOOKUP($A13,subQ,MATCH(E$1,SUBQH,0),0),"") | F13: =IFERROR(VLOOKUP($A13,subQ,MATCH(F$1,SUBQH,0),0),"") | G13: =IFERROR(VLOOKUP($A13,subQ,MATCH(G$1,SUBQH,0),0),"") | H13: =IFERROR(VLOOKUP($A13,subQ,MATCH(H$1,SUBQH,0),0),"") | I13: =IFERROR(VLOOKUP($A13,subQ,MATCH(I$1,SUBQH,0),0),"") | J13: =IFERROR(VLOOKUP($A13,subQ,MATCH(J$1,SUBQH,0),0),"") | K13: =IFERROR(VLOOKUP($A13,subQ,MATCH(K$1,SUBQH,0),0),"") | L13: =IFERROR(VLOOKUP($A13,subQ,MATCH(L$1,SUBQH,0),0),"")
A14: 기타영업외손익 | D14: 기타영업외손익 | E14: =IFERROR(VLOOKUP($A14,subQ,MATCH(E$1,SUBQH,0),0),"") | F14: =IFERROR(VLOOKUP($A14,subQ,MATCH(F$1,SUBQH,0),0),"") | G14: =IFERROR(VLOOKUP($A14,subQ,MATCH(G$1,SUBQH,0),0),"") | H14: =IFERROR(VLOOKUP($A14,subQ,MATCH(H$1,SUBQH,0),0),"") | I14: =IFERROR(VLOOKUP($A14,subQ,MATCH(I$1,SUBQH,0),0),"") | J14: =IFERROR(VLOOKUP($A14,subQ,MATCH(J$1,SUBQH,0),0),"") | K14: =IFERROR(VLOOKUP($A14,subQ,MATCH(K$1,SUBQH,0),0),"") | L14: =IFERROR(VLOOKUP($A14,subQ,MATCH(L$1,SUBQH,0),0),"")
A15: 지분법손익 | D15: 지분법손익 | E15: =IFERROR(VLOOKUP($A15,subQ,MATCH(E$1,SUBQH,0),0),"") | F15: =IFERROR(VLOOKUP($A15,subQ,MATCH(F$1,SUBQH,0),0),"") | G15: =IFERROR(VLOOKUP($A15,subQ,MATCH(G$1,SUBQH,0),0),"") | H15: =IFERROR(VLOOKUP($A15,subQ,MATCH(H$1,SUBQH,0),0),"") | I15: =IFERROR(VLOOKUP($A15,subQ,MATCH(I$1,SUBQH,0),0),"") | J15: =IFERROR(VLOOKUP($A15,subQ,MATCH(J$1,SUBQH,0),0),"") | K15: =IFERROR(VLOOKUP($A15,subQ,MATCH(K$1,SUBQH,0),0),"") | L15: =IFERROR(VLOOKUP($A15,subQ,MATCH(L$1,SUBQH,0),0),"")
A16: 세전이익 | D16: 법인세비용차감전이익 | E16: =IFERROR(VLOOKUP($A16,subQ,MATCH(E$1,SUBQH,0),0),"") | F16: =IFERROR(VLOOKUP($A16,subQ,MATCH(F$1,SUBQH,0),0),"") | G16: =IFERROR(VLOOKUP($A16,subQ,MATCH(G$1,SUBQH,0),0),"") | H16: =IFERROR(VLOOKUP($A16,subQ,MATCH(H$1,SUBQH,0),0),"") | I16: =IFERROR(VLOOKUP($A16,subQ,MATCH(I$1,SUBQH,0),0),"") | J16: =IFERROR(VLOOKUP($A16,subQ,MATCH(J$1,SUBQH,0),0),"") | K16: =IFERROR(VLOOKUP($A16,subQ,MATCH(K$1,SUBQH,0),0),"") | L16: =IFERROR(VLOOKUP($A16,subQ,MATCH(L$1,SUBQH,0),0),"")
... A39: NPM | D39: NPM | E39: =IFERROR(VLOOKUP($A39,subQ,MATCH(E$1,SUBQH,0),0),"") | F39: =IFERROR(VLOOKUP($A39,subQ,MATCH(F$1,SUBQH,0),0),"") | G39: =IFERROR(VLOOKUP($A39,subQ,MATCH(G$1,SUBQH,0),0),"") | H39: =IFERROR(VLOOKUP($A39,subQ,MATCH(H$1,SUBQH,0),0),"") | I39: =IFERROR(VLOOKUP($A39,subQ,MATCH(I$1,SUBQH,0),0),"") | J39: =IFERROR(VLOOKUP($A39,subQ,MATCH(J$1,SUBQH,0),0),"") | K39: =IFERROR(VLOOKUP($A39,subQ,MATCH(K$1,SUBQH,0),0),"") | L39: =IFERROR(VLOOKUP($A39,subQ,MATCH(L$1,SUBQH,0),0),"")
A40: 매출액 YoY | D40: 매출액 YoY | F40: =IFERROR(F5/E5-1,"") | G40: =IFERROR(G5/F5-1,"") | H40: =IFERROR(H5/G5-1,"") | I40: =IFERROR(I5/H5-1,"") | J40: =IFERROR(J5/I5-1,"") | K40: =IFERROR(K5/J5-1,"") | L40: =IFERROR(L5/K5-1,"")
A41: 영업이익 YoY | D41: 영업이익 YoY | F41: =IFERROR(F9/E9-1,"") | G41: =IFERROR(G9/F9-1,"") | H41: =IFERROR(H9/G9-1,"") | I41: =IFERROR(I9/H9-1,"") | J41: =IFERROR(J9/I9-1,"") | K41: =IFERROR(K9/J9-1,"") | L41: =IFERROR(L9/K9-1,"")
A42: 지배주주순이익 YoY | D42: 지배주주순이익 YoY | F42: =IFERROR(F19/E19-1,"") | G42: =IFERROR(G19/F19-1,"") | H42: =IFERROR(H19/G19-1,"") | I42: =IFERROR(I19/H19-1,"") | J42: =IFERROR(J19/I19-1,"") | K42: =IFERROR(K19/J19-1,"") | L42: =IFERROR(L19/K19-1,"")

Sheet TP
B1: 종가 | C1: =변수!D42
B2: 기준일 | C2: =변수!D43
B3: 모델 산출값 — 목표주가·추천 아님. 밴드·COE 는 변수 시트 3절의 가정
C5: FY | D5: 2025 | E5: 2026 | F5: 2027 | G5: 2028
D6: A | E6: E | F6: E | G6: E
C7: EPS(원) | D7: =IFERROR(VLOOKUP("EPS",subQ,MATCH(D$5,SUBQH,0),0),"") | E7: =IFERROR(VLOOKUP("EPS",subQ,MATCH(E$5,SUBQH,0),0),"") | F7: =IFERROR(VLOOKUP("EPS",subQ,MATCH(F$5,SUBQH,0),0),"") | G7: =IFERROR(VLOOKUP("EPS",subQ,MATCH(G$5,SUBQH,0),0),"")
C8: BPS(원) | D8: =IFERROR(VLOOKUP("BPS",subQ,MATCH(D$5,SUBQH,0),0),"") | E8: =IFERROR(VLOOKUP("BPS",subQ,MATCH(E$5,SUBQH,0),0),"") | F8: =IFERROR(VLOOKUP("BPS",subQ,MATCH(F$5,SUBQH,0),0),"") | G8: =IFERROR(VLOOKUP("BPS",subQ,MATCH(G$5,SUBQH,0),0),"")
C9: 지배주주순이익(억원) | D9: =IFERROR(VLOOKUP("지배주주순이익",subQ,MATCH(D$5,SUBQH,0),0),"") | E9: =IFERROR(VLOOKUP("지배주주순이익",subQ,MATCH(E$5,SUBQH,0),0),"") | F9: =IFERROR(VLOOKUP("지배주주순이익",subQ,MATCH(F$5,SUBQH,0),0),"") | G9: =IFERROR(VLOOKUP("지배주주순이익",subQ,MATCH(G$5,SUBQH,0),0),"")
C10: 영업이익(억원) | D10: =IFERROR(VLOOKUP("영업이익",subQ,MATCH(D$5,SUBQH,0),0),"") | E10: =IFERROR(VLOOKUP("영업이익",subQ,MATCH(E$5,SUBQH,0),0),"") | F10: =IFERROR(VLOOKUP("영업이익",subQ,MATCH(F$5,SUBQH,0),0),"") | G10: =IFERROR(VLOOKUP("영업이익",subQ,MATCH(G$5,SUBQH,0),0),"")
C11: ROE(EPS/기초BPS) | E11: =IFERROR(E7/D8,"") | F11: =IFERROR(F7/E8,"") | G11: =IFERROR(G7/F8,"")
B13: PER
C14: 12M fwd EPS | D14: =IFERROR(E7*변수!D48+F7*(1-변수!D48),"")
C15: 적정가치 @PER_lo | D15: =변수!D45 | E15: =IFERROR(ROUND($D$14*D15,-2),"") | F15: =IFERROR(E15/$C$1-1,"") | G15: 배 · 원 · 종가 대비
C16: 적정가치 @PER_mid | D16: =변수!D46 | E16: =IFERROR(ROUND($D$14*D16,-2),"") | F16: =IFERROR(E16/$C$1-1,"") | G16: 배 · 원 · 종가 대비
C17: 적정가치 @PER_hi | D17: =변수!D47 | E17: =IFERROR(ROUND($D$14*D17,-2),"") | F17: =IFERROR(E17/$C$1-1,"") | G17: 배 · 원 · 종가 대비
C18: 현재 PER(종가/12M fwd EPS) | D18: =IFERROR($C$1/$D$14,"")
B20: PBR
C21: 최근 BPS(마지막 실적 분기) | D21: =IFERROR(VLOOKUP("BPS",subQ,MATCH("2Q26",SUBQH,0),0),"")
C22: ROE fwd(12M fwd EPS / BPS) | D22: =IFERROR($D$14/$D$21,"")
C23: COE | D23: =변수!D44
C24: 적정 PBR = ROE/COE | D24: =IFERROR(D22/D23,"")
C25: 적정가치(PBR) = BPS × 적정PBR | D25: =IFERROR(ROUND(D21*D24,-2),"") | E25: =IFERROR(D25/$C$1-1,"")
C26: 현재 PBR(종가/BPS) | D26: =IFERROR($C$1/D21,"")
B28: 모델 json valuation(참고)
C29: eps_fwd12m | D29: 173.1
C30: bps_latest | D30: 7576.5
C31: per_now | D31: 8.71
C32: pbr_now | D32: 0.2
C33: roe_fwd | D33: 0.0228
C34: fair_pbr | D34: 0.25
C35: fair_value_pbr | D35: 1900
C36: ev_ebitda
C37: note | D37: 모델 산출값 — 목표주가·추천 아님

Sheet 외화
C1: 이름: 외화QH — 환율 QoQ · 외화 순노출 × Δ기말환율 | E1: 4Q21 | F1: 1Q22 | G1: 2Q22 | H1: 3Q22 | I1: 4Q22 | J1: 1Q23 | K1: 2Q23 | L1: 3Q23 | M1: 4Q23 | N1: 1Q24 | O1: 2Q24 | P1: 3Q24 | Q1: 4Q24 | R1: 1Q25 | S1: 2Q25 | T1: 3Q25 | U1: 4Q25 | V1: 1Q26 | W1: 2Q26 | X1: 3Q26 | Y1: 4Q26 | Z1: 1Q27 | AA1: 2Q27 | AB1: 3Q27 | AC1: 4Q27 | AD1: 1Q28 | AE1: 2Q28 | AF1: 3Q28 | AG1: 4Q28
E3: 1 | F3: 2 | G3: 3 | H3: 4 | I3: 5 | J3: 6 | K3: 7 | L3: 8 | M3: 9 | N3: 10 | O3: 11 | P3: 12 | Q3: 13 | R3: 14 | S3: 15 | T3: 16 | U3: 17 | V3: 18 | W3: 19 | X3: 20 | Y3: 21 | Z3: 22 | AA3: 23 | AB3: 24 | AC3: 25 | AD3: 26 | AE3: 27 | AF3: 28 | AG3: 29
E4: 2021.12 | F4: 2022.03 | G4: 2022.06 | H4: 2022.09 | I4: 2022.12 | J4: 2023.03 | K4: 2023.06 | L4: 2023.09 | M4: 2023.12 | N4: 2024.03 | O4: 2024.06 | P4: 2024.09 | Q4: 2024.12 | R4: 2025.03 | S4: 2025.06 | T4: 2025.09 | U4: 2025.12 | V4: 2026.03 | W4: 2026.06 | X4: 2026.09 | Y4: 2026.12 | Z4: 2027.03 | AA4: 2027.06 | AB4: 2027.09 | AC4: 2027.12 | AD4: 2028.03 | AE4: 2028.06 | AF4: 2028.09 | AG4: 2028.12
D5: 원/달러(평균) | E5: =IFERROR(VLOOKUP($D5,환율,MATCH(E$1,변수H,0),0),"") | F5: =IFERROR(VLOOKUP($D5,환율,MATCH(F$1,변수H,0),0),"") | G5: =IFERROR(VLOOKUP($D5,환율,MATCH(G$1,변수H,0),0),"") | H5: =IFERROR(VLOOKUP($D5,환율,MATCH(H$1,변수H,0),0),"") | I5: =IFERROR(VLOOKUP($D5,환율,MATCH(I$1,변수H,0),0),"") | J5: =IFERROR(VLOOKUP($D5,환율,MATCH(J$1,변수H,0),0),"") | K5: =IFERROR(VLOOKUP($D5,환율,MATCH(K$1,변수H,0),0),"") | L5: =IFERROR(VLOOKUP($D5,환율,MATCH(L$1,변수H,0),0),"") | ... AG5: =IFERROR(VLOOKUP($D5,환율,MATCH(AG$1,변수H,0),0),"")
A6: 원/달러(평균) QoQ | F6: =IFERROR(F5/E5-1,"") | G6: =IFERROR(G5/F5-1,"") | H6: =IFERROR(H5/G5-1,"") | I6: =IFERROR(I5/H5-1,"") | J6: =IFERROR(J5/I5-1,"") | K6: =IFERROR(K5/J5-1,"") | L6: =IFERROR(L5/K5-1,"") | M6: =IFERROR(M5/L5-1,"") | ... AG6: =IFERROR(AG5/AF5-1,"")
D7: 원/달러(기말) | E7: =IFERROR(VLOOKUP($D7,환율,MATCH(E$1,변수H,0),0),"") | F7: =IFERROR(VLOOKUP($D7,환율,MATCH(F$1,변수H,0),0),"") | G7: =IFERROR(VLOOKUP($D7,환율,MATCH(G$1,변수H,0),0),"") | H7: =IFERROR(VLOOKUP($D7,환율,MATCH(H$1,변수H,0),0),"") | I7: =IFERROR(VLOOKUP($D7,환율,MATCH(I$1,변수H,0),0),"") | J7: =IFERROR(VLOOKUP($D7,환율,MATCH(J$1,변수H,0),0),"") | K7: =IFERROR(VLOOKUP($D7,환율,MATCH(K$1,변수H,0),0),"") | L7: =IFERROR(VLOOKUP($D7,환율,MATCH(L$1,변수H,0),0),"") | ... AG7: =IFERROR(VLOOKUP($D7,환율,MATCH(AG$1,변수H,0),0),"")
A8: 원/달러(기말) QoQ | F8: =IFERROR(F7/E7-1,"") | G8: =IFERROR(G7/F7-1,"") | H8: =IFERROR(H7/G7-1,"") | I8: =IFERROR(I7/H7-1,"") | J8: =IFERROR(J7/I7-1,"") | K8: =IFERROR(K7/J7-1,"") | L8: =IFERROR(L7/K7-1,"") | M8: =IFERROR(M7/L7-1,"") | ... AG8: =IFERROR(AG7/AF7-1,"")
D9: W/Euro(평균) | E9: =IFERROR(VLOOKUP($D9,환율,MATCH(E$1,변수H,0),0),"") | F9: =IFERROR(VLOOKUP($D9,환율,MATCH(F$1,변수H,0),0),"") | G9: =IFERROR(VLOOKUP($D9,환율,MATCH(G$1,변수H,0),0),"") | H9: =IFERROR(VLOOKUP($D9,환율,MATCH(H$1,변수H,0),0),"") | I9: =IFERROR(VLOOKUP($D9,환율,MATCH(I$1,변수H,0),0),"") | J9: =IFERROR(VLOOKUP($D9,환율,MATCH(J$1,변수H,0),0),"") | K9: =IFERROR(VLOOKUP($D9,환율,MATCH(K$1,변수H,0),0),"") | L9: =IFERROR(VLOOKUP($D9,환율,MATCH(L$1,변수H,0),0),"") | ... AG9: =IFERROR(VLOOKUP($D9,환율,MATCH(AG$1,변수H,0),0),"")
A10: W/Euro(평균) QoQ | F10: =IFERROR(F9/E9-1,"") | G10: =IFERROR(G9/F9-1,"") | H10: =IFERROR(H9/G9-1,"") | I10: =IFERROR(I9/H9-1,"") | J10: =IFERROR(J9/I9-1,"") | K10: =IFERROR(K9/J9-1,"") | L10: =IFERROR(L9/K9-1,"") | M10: =IFERROR(M9/L9-1,"") | ... AG10: =IFERROR(AG9/AF9-1,"")
D11: W/Euro(기말) | E11: =IFERROR(VLOOKUP($D11,환율,MATCH(E$1,변수H,0),0),"") | F11: =IFERROR(VLOOKUP($D11,환율,MATCH(F$1,변수H,0),0),"") | G11: =IFERROR(VLOOKUP($D11,환율,MATCH(G$1,변수H,0),0),"") | H11: =IFERROR(VLOOKUP($D11,환율,MATCH(H$1,변수H,0),0),"") | I11: =IFERROR(VLOOKUP($D11,환율,MATCH(I$1,변수H,0),0),"") | J11: =IFERROR(VLOOKUP($D11,환율,MATCH(J$1,변수H,0),0),"") | K11: =IFERROR(VLOOKUP($D11,환율,MATCH(K$1,변수H,0),0),"") | L11: =IFERROR(VLOOKUP($D11,환율,MATCH(L$1,변수H,0),0),"") | ... AG11: =IFERROR(VLOOKUP($D11,환율,MATCH(AG$1,변수H,0),0),"")
A12: W/Euro(기말) QoQ | F12: =IFERROR(F11/E11-1,"") | G12: =IFERROR(G11/F11-1,"") | H12: =IFERROR(H11/G11-1,"") | I12: =IFERROR(I11/H11-1,"") | J12: =IFERROR(J11/I11-1,"") | K12: =IFERROR(K11/J11-1,"") | L12: =IFERROR(L11/K11-1,"") | M12: =IFERROR(M11/L11-1,"") | ... AG12: =IFERROR(AG11/AF11-1,"")
D13: 원/100Y(기말) | E13: =IFERROR(VLOOKUP($D13,환율,MATCH(E$1,변수H,0),0),"") | F13: =IFERROR(VLOOKUP($D13,환율,MATCH(F$1,변수H,0),0),"") | G13: =IFERROR(VLOOKUP($D13,환율,MATCH(G$1,변수H,0),0),"") | H13: =IFERROR(VLOOKUP($D13,환율,MATCH(H$1,변수H,0),0),"") | I13: =IFERROR(VLOOKUP($D13,환율,MATCH(I$1,변수H,0),0),"") | J13: =IFERROR(VLOOKUP($D13,환율,MATCH(J$1,변수H,0),0),"") | K13: =IFERROR(VLOOKUP($D13,환율,MATCH(K$1,변수H,0),0),"") | L13: =IFERROR(VLOOKUP($D13,환율,MATCH(L$1,변수H,0),0),"") | ... AG13: =IFERROR(VLOOKUP($D13,환율,MATCH(AG$1,변수H,0),0),"")
A14: 원/100Y(기말) QoQ | F14: =IFERROR(F13/E13-1,"") | G14: =IFERROR(G13/F13-1,"") | H14: =IFERROR(H13/G13-1,"") | I14: =IFERROR(I13/H13-1,"") | J14: =IFERROR(J13/I13-1,"") | K14: =IFERROR(K13/J13-1,"") | L14: =IFERROR(L13/K13-1,"") | M14: =IFERROR(M13/L13-1,"") | ... AG14: =IFERROR(AG13/AF13-1,"")
A16: 외화순노출 | C16: 외화 순노출(백만$) | D16: =변수!D55 | E16: 외화 순노출 × Δ기말환율 (외화 시트 방식)
A17: 환관련손익추정 | C17: 환관련손익 추정(억원) = 순노출 × Δ원/달러(기말) / 100 | F17: =IFERROR($D$16*(F7-E7)/100,"") | G17: =IFERROR($D$16*(G7-F7)/100,"") | H17: =IFERROR($D$16*(H7-G7)/100,"") | I17: =IFERROR($D$16*(I7-H7)/100,"") | J17: =IFERROR($D$16*(J7-I7)/100,"") | K17: =IFERROR($D$16*(K7-J7)/100,"") | L17: =IFERROR($D$16*(L7-K7)/100,"") | M17: =IFERROR($D$16*(M7-L7)/100,"") | ... AG17: =IFERROR($D$16*(AG7-AF7)/100,"")
A18: fx_pnl.by_q | C18: 모델 fx_pnl.by_q(억원, 참고)
C19: 외화 순노출 미공시(face) → 0 + 표기
