Workbook
Name 변수H: 변수!$C$1:$AO$1
Name 환율: 변수!$C$6:$AO$13
Name BS연결H: BS연결!$C$1:$AO$1
Name BS연결: BS연결!$C$5:$AO$86
Name BS별도H: BS별도!$C$1:$AO$1
Name BS별도: BS별도!$C$5:$AO$82
Name SUBQH: subQ!$A$1:$AO$1
Name subQ: subQ!$A$5:$AO$39

Sheet README
A1: 대양전기공업(108380) 실적 모델 — ARGUS 한국조선
A2: 기준 분기 2026Q2 · 마지막 실적 2026Q2 · 생성 2026-10-26
A3: 모든 수치는 모델 산출값(DART 공개 재무제표 + 우리 추정)이다 — 목표주가·투자 추천 아님. 참고용 · 투자조언 아님.
A5: 시트
A6: 변수 가정 시계열. 환율 8행(ECB via frankfurter — L2 fx.json; 추정 분기 = 노란 가정), 추정 드라이버(노란 셀 = 모델값에서 역산한 가정, 바꾸면 재계산; 연녹 셀 = 3절 스칼라 참조 수식), 3절 스칼라 가정(세율·판관비율·지배주주비중·이자율·종가·PER 밴드·COE·외화 순노출·헤지비율)
A7: BS연결/BS별도 FnGuide 계정명 × 기간 값 덤프(백만원). 행1 분기라벨, 행4 YYYY.MM / YYYY.12A. 이름정의 BS연결H·BS연결(계정명 C열부터)
A8: subQ 분기 서브모델(억원 = 백만원/100). 확정 행: =IFERROR(VLOOKUP($D행,BS연결,MATCH(E$1,BS연결H,0),0)/100,"") 추정 행: 변수 시트 가정 셀 참조 수식. 외환손익·파생상품손익은 BS 계정 합·차, 기타금융손익은 잔차, OPM·EPS·BPS·PER·PBR 은 파생 수식
A9: SLS 선표(조선사만, sls json 있을 때): 요약 행(sls 저장값) + 계약별 스케줄(백만$) × (헤지비율 × 헤지환율 + (1−헤지비율) × 건조시점 환율[변수 원/달러(평균)]) → 원화 수식 블록 → 합계 행이 subQ 매출조선에 연결
A10: 시나리오 신규수주 보수/기준/낙관(forecast_panel 패널, 모델에 scenarios 가 있을 때만): 매출액·영업이익 = subQ 기준값 ± (시나리오 신규 − base 신규) × OPM. base 만 subQ 행에 포함, 나머지는 합산 안 함
A11: 분기/연간예상 subQ 를 이름(A열 key)으로 VLOOKUP 한 보고서 표(억원)
A12: TP PER 밴드 × 12M fwd EPS, PBR = ROE/COE × BPS — 모델 산출값 구간, 목표주가·추천 아님
A13: 외화 환율 QoQ, 외화 순노출 × Δ기말환율 → 환관련손익 추정
... A34: 백테스트: {"freeze": "2025Q2", "horizon": 4, "revenue_wape_pct": 17.9, "op_wape_pct": 43.3, "n": 4, "note": "단일 회사 4분기 — 통계 아님", "driver_at_freeze": "trend_seasonal", "selection_oos_at_freeze": null, "frozen_inputs": "fin(연결/별도)·고객 조선사 모델·지주 자회사 모델은 2025Q2 까지의 분기만; 선표는 체결일 ≤ 2025Q2 말일 계약(원장 최신 금액·코호트 등급, 환산 없음); 잔고는 yards_cache 2025Q2; 시세·환율 forward·prices·forecast_panel 신규수주 미사용. 고객 가중치(suppliers.json 언급 비중)와 합병 체인링크는 현재 지식; 고객 연동 채택은 동결 모델 안에서도 자기 la−4분기 OOS 규칙(selection_oos_at_freeze)", "detail": [{"q": "2025Q3", "rev_pred": 543.67, "rev_act": 615.33, "op_pred": 34.39, "op_act": 77.43}, {"q": "2025Q4", "rev_pred": 732.64, "rev_act": 565.96, "op_pred": 46.35, "op_act": 78.24}, {"q": "2026Q1", "rev_pred": 676.16, "rev_act": 508.96, "op_pred": 42.77, "op_act": 62.74}, {"q": "2026Q2", "rev_pred": 684.5, "rev_act": 708.34, "op_pred": 43.3, "op_act": 75.59}]}

Sheet 변수
C1: 이름: 변수H | E1: 4Q21 | F1: 2021 | G1: 1Q22 | H1: 2Q22 | I1: 3Q22 | J1: 4Q22 | K1: 2022 | L1: 1Q23 | M1: 2Q23 | N1: 3Q23 | O1: 4Q23 | P1: 2023 | Q1: 1Q24 | R1: 2Q24 | S1: 3Q24 | T1: 4Q24 | U1: 2024 | V1: 1Q25 | W1: 2Q25 | X1: 3Q25 | Y1: 4Q25 | Z1: 2025 | AA1: 1Q26 | AB1: 2Q26 | AC1: 3Q26 | AD1: 4Q26 | AE1: 2026 | AF1: 1Q27 | AG1: 2Q27 | AH1: 3Q27 | AI1: 4Q27 | AJ1: 2027 | AK1: 1Q28 | AL1: 2Q28 | AM1: 3Q28 | AN1: 4Q28 | AO1: 2028
A2: 가정 시계열 — 노란 셀은 추정 가정(모델값에서 역산), 연녹 셀은 3절 스칼라 참조 수식. 바꾸면 subQ·분기·연간예상·TP·시나리오가 재계산됩니다.
E3: 1 | F3: 2 | G3: 3 | H3: 4 | I3: 5 | J3: 6 | K3: 7 | L3: 8 | M3: 9 | N3: 10 | O3: 11 | P3: 12 | Q3: 13 | R3: 14 | S3: 15 | T3: 16 | U3: 17 | V3: 18 | W3: 19 | X3: 20 | Y3: 21 | Z3: 22 | AA3: 23 | AB3: 24 | AC3: 25 | AD3: 26 | AE3: 27 | AF3: 28 | AG3: 29 | AH3: 30 | AI3: 31 | AJ3: 32 | AK3: 33 | AL3: 34 | AM3: 35 | AN3: 36 | AO3: 37
E4: 2021.12 | F4: 2021.12A | G4: 2022.03 | H4: 2022.06 | I4: 2022.09 | J4: 2022.12 | K4: 2022.12A | L4: 2023.03 | M4: 2023.06 | N4: 2023.09 | O4: 2023.12 | P4: 2023.12A | Q4: 2024.03 | R4: 2024.06 | S4: 2024.09 | T4: 2024.12 | U4: 2024.12A | V4: 2025.03 | W4: 2025.06 | X4: 2025.09 | Y4: 2025.12 | Z4: 2025.12A | AA4: 2026.03 | AB4: 2026.06 | AC4: 2026.09 | AD4: 2026.12 | AE4: 2026.12A | AF4: 2027.03 | AG4: 2027.06 | AH4: 2027.09 | AI4: 2027.12 | AJ4: 2027.12A | AK4: 2028.03 | AL4: 2028.06 | AM4: 2028.09 | AN4: 2028.12 | AO4: 2028.12A
B5: 1. FX | C5: 이름: 환율
A6: USDKRW_avg | C6: 원/달러(평균) | E6: 1183.5 | F6: 1145.51 | G6: 1205.78 | H6: 1262.09 | I6: 1341.93 | J6: 1360.12 | K6: 1292.98 | L6: 1276.95 | M6: 1315.69 | N6: 1313.62 | O6: 1322.01 | P6: 1306.85 | Q6: 1330.14 | R6: 1371.28 | S6: 1356.22 | T6: 1396.3 | U6: 1363.53 | V6: 1452.28 | W6: 1398.52 | X6: 1386.95 | Y6: 1449.19 | Z6: 1421.52 | AA6: 1466.12 | AB6: 1501.75 | AC6: 1418.75 | AD6: 1337.49 | AE6: 1451.19 | AF6: 1324.45 | AG6: 1324.45 | AH6: 1324.45 | AI6: 1324.45 | AK6: 1324.45 | AL6: 1324.45 | AM6: 1324.45 | AN6: 1324.45
A7: USDKRW_end | C7: 원/달러(기말) | E7: 1188.75 | F7: 1188.75 | G7: 1213.74 | H7: 1301.24 | I7: 1436.9 | J7: 1260.16 | K7: 1260.16 | L7: 1305.99 | M7: 1321.44 | N7: 1345.35 | O7: 1297.43 | P7: 1297.43 | Q7: 1349.25 | R7: 1377.73 | S7: 1312.17 | T7: 1474.78 | U7: 1474.78 | V7: 1474.54 | W7: 1355.13 | X7: 1403.67 | Y7: 1444.2 | Z7: 1444.2 | AA7: 1524.8 | AB7: 1550.89 | AC7: 1355.4 | AD7: 1324.45 | AE7: 1324.45 | AF7: 1324.45 | AG7: 1324.45 | AH7: 1324.45 | AI7: 1324.45 | AK7: 1324.45 | AL7: 1324.45 | AM7: 1324.45 | AN7: 1324.45
A8: JPY100KRW_avg | C8: 원/100Y(평균) | E8: 1041.02 | F8: 1042.74 | G8: 1036.79 | H8: 972.23 | I8: 970.61 | J8: 961.03 | K8: 985.1 | L8: 964.89 | M8: 957.36 | N8: 909 | O8: 893.22 | P8: 931.11 | Q8: 896.29 | R8: 880.14 | S8: 909.35 | T8: 917.25 | U8: 900.92 | V8: 952.59 | W8: 967.92 | X8: 940.32 | Y8: 940.77 | Z8: 950.17 | AA8: 934.39 | AB8: 942.16 | AC8: 890.41 | AD8: 846.51 | AE8: 915.57 | AF8: 844.67 | AG8: 844.67 | AH8: 844.67 | AI8: 844.67 | AK8: 844.67 | AL8: 844.67 | AM8: 844.67 | AN8: 844.67
A9: JPY100KRW_end | C9: 원/100Y(기말) | E9: 1032.62 | F9: 1032.62 | G9: 996.83 | H9: 954.9 | I9: 993.29 | J9: 955.54 | K9: 955.54 | L9: 980.62 | M9: 913.67 | N9: 901.47 | O9: 917.04 | P9: 917.04 | Q9: 892.42 | R9: 857.76 | S9: 919.21 | T9: 939.65 | U9: 939.65 | V9: 986.84 | W9: 938.85 | X9: 948.49 | Y9: 921.81 | Z9: 921.81 | AA9: 955.99 | AB9: 954.75 | AC9: 863.31 | AD9: 844.67 | AE9: 844.67 | AF9: 844.67 | AG9: 844.67 | AH9: 844.67 | AI9: 844.67 | AK9: 844.67 | AL9: 844.67 | AM9: 844.67 | AN9: 844.67
A10: EURKRW_avg | C10: W/Euro(평균) | E10: 1353.32 | F10: 1354.06 | G10: 1352.29 | H10: 1343.31 | I10: 1350.63 | J10: 1386.07 | K10: 1358.07 | L10: 1369.93 | M10: 1432.41 | N10: 1429.41 | O10: 1420.91 | P10: 1412.88 | Q10: 1444.21 | R10: 1476.42 | S10: 1489.3 | T10: 1490.78 | U10: 1475.4 | V10: 1528.33 | W10: 1585.13 | X10: 1620.04 | Y10: 1686.02 | Z10: 1605.45 | AA10: 1715.47 | AB10: 1746.09 | AC10: 1631.97 | AD10: 1500.06 | AE10: 1680.5 | AF10: 1482.45 | AG10: 1482.45 | AH10: 1482.45 | AI10: 1482.45 | AK10: 1482.45 | AL10: 1482.45 | AM10: 1482.45 | AN10: 1482.45
A11: EURKRW_end | C11: W/Euro(기말) | E11: 1346.38 | F11: 1346.38 | G11: 1347.37 | H11: 1351.6 | I11: 1400.62 | J11: 1344.08 | K11: 1344.08 | L11: 1420.26 | M11: 1435.88 | N11: 1425.26 | O11: 1433.66 | P11: 1433.66 | Q11: 1458.68 | R11: 1474.86 | S11: 1469.1 | T11: 1532.14 | U11: 1532.14 | V11: 1594.72 | W11: 1588.22 | X11: 1648.04 | Y11: 1696.94 | Z11: 1696.94 | AA11: 1753.21 | AB11: 1767.09 | AC11: 1539.06 | AD11: 1482.45 | AE11: 1482.45 | AF11: 1482.45 | AG11: 1482.45 | AH11: 1482.45 | AI11: 1482.45 | AK11: 1482.45 | AL11: 1482.45 | AM11: 1482.45 | AN11: 1482.45
A12: CNYKRW_avg | C12: 원/중국원(평균) | E12: 185.14 | F12: 177.65 | G12: 189.93 | H12: 190.76 | I12: 195.79 | J12: 191.09 | K12: 191.93 | L12: 186.59 | M12: 187.45 | N12: 181.28 | O12: 182.86 | P12: 184.52 | Q12: 185.04 | R12: 189.35 | S12: 189.24 | T12: 194.24 | U12: 189.49 | V12: 199.63 | W12: 193.41 | X12: 193.79 | Y12: 204.38 | Z12: 197.8 | AA12: 211.75 | AB12: 220.8 | AC12: 210.43 | AD12: 199.88 | AE12: 213.06 | AF12: 198.56 | AG12: 198.56 | AH12: 198.56 | AI12: 198.56 | AK12: 198.56 | AL12: 198.56 | AM12: 198.56 | AN12: 198.56
A13: CNYKRW_end | C13: 원/중국원(기말) | E13: 187.13 | F13: 187.13 | G13: 191.38 | H13: 194.13 | I13: 201.92 | J13: 182.67 | K13: 182.67 | L13: 189.97 | M13: 181.8 | N13: 184.26 | O13: 182.61 | P13: 182.61 | Q13: 186.66 | R13: 189.7 | S13: 187.12 | T13: 202.04 | U13: 202.04 | V13: 203.3 | W13: 189.14 | X13: 197.16 | Y13: 206.28 | Z13: 206.28 | AA13: 220.97 | AB13: 228.56 | AC13: 202.16 | AD13: 198.56 | AE13: 198.56 | AF13: 198.56 | AG13: 198.56 | AH13: 198.56 | AI13: 198.56 | AK13: 198.56 | AL13: 198.56 | AM13: 198.56 | AN13: 198.56
B14: 1b. 종가
A15: price_close_end | C15: 종가(기말) | E15: 15000 | G15: 14700 | H15: 12550 | I15: 11700 | J15: 12000 | L15: 10730 | M15: 13000 | N15: 11000 | O15: 11720 | Q15: 12840 | R15: 13850 | S15: 12060 | T15: 12850 | V15: 15820 | W15: 23850 | X15: 29100 | Y15: 27700 | AA15: 24500 | AB15: 17720 | AC15: 18520 | AD15: 14720
A16: price_high | C16: 종가(최고) | E16: 17850 | G16: 17100 | H16: 16150 | I16: 16500 | J16: 14250 | L16: 12750 | M16: 13900 | N16: 14000 | O16: 12150 | Q16: 13950 | R16: 20800 | S16: 14300 | T16: 13870 | V16: 20900 | W16: 24900 | X16: 32600 | Y16: 33850 | AA16: 36650 | AB16: 32800 | AC16: 19600 | AD16: 18970
A17: price_low | C17: 종가(최저) | E17: 13750 | G17: 13800 | H17: 11000 | I17: 11200 | J17: 11300 | L17: 10110 | M17: 10490 | N17: 10770 | O17: 10450 | Q17: 10730 | R17: 12540 | S17: 10750 | T17: 11090 | V17: 12800 | W17: 14420 | X17: 20550 | Y17: 25350 | AA17: 24500 | AB17: 15430 | AC17: 14000 | AD17: 14690
A18: price_avg | C18: 종가(평균) | E18: 15838.9 | G18: 15232.2 | H18: 13832.3 | I18: 12938.1 | J18: 12306.5 | L18: 11685.5 | M18: 11720.3 | N18: 12504.8 | O18: 11417.2 | Q18: 11987.9 | R18: 14608.8 | S18: 12791.5 | T18: 12228.4 | V18: 16177.4 | W18: 19891.3 | X18: 26083.1 | Y18: 28694.1 | AA18: 28323.7 | AB18: 24136.7 | AC18: 17674.8 | AD18: 16833.1
B20: 2. 추정 드라이버 | C20: 실적 열 = subQ 실현값(수식), 추정 열 = 가정(노란 = 모델값 역산, 연녹 = 3절 스칼라 참조)
A21: drv:매출액 | B21: yoy | C21: 매출액 YoY | J21: =IFERROR(subQ!J5/subQ!E5-1,"") | L21: =IFERROR(subQ!L5/subQ!G5-1,"") | M21: =IFERROR(subQ!M5/subQ!H5-1,"") | N21: =IFERROR(subQ!N5/subQ!I5-1,"") | O21: =IFERROR(subQ!O5/subQ!J5-1,"") | Q21: =IFERROR(subQ!Q5/subQ!L5-1,"") | R21: =IFERROR(subQ!R5/subQ!M5-1,"") | S21: =IFERROR(subQ!S5/subQ!N5-1,"") | T21: =IFERROR(subQ!T5/subQ!O5-1,"") | V21: =IFERROR(subQ!V5/subQ!Q5-1,"") | W21: =IFERROR(subQ!W5/subQ!R5-1,"") | X21: =IFERROR(subQ!X5/subQ!S5-1,"") | Y21: =IFERROR(subQ!Y5/subQ!T5-1,"") | AA21: =IFERROR(subQ!AA5/subQ!V5-1,"") | AB21: =IFERROR(subQ!AB5/subQ!W5-1,"") | AC21: 0.10539563 | AD21: 0.10539028 | AF21: 0.10540126 | AG21: 0.10539637 | AH21: 0.052706636 | AI21: 0.052700564 | AK21: 0.052700805 | AL21: 0.052694764 | AM21: 0.026339679 | AN21: 0.026359744
A22: drv:판관비 | B22: ratio | C22: 판관비율(/매출) | E22: =IFERROR(subQ!E8/subQ!E5,"") | F22: =IFERROR(subQ!F8/subQ!F5,"") | G22: =IFERROR(subQ!G8/subQ!G5,"") | H22: =IFERROR(subQ!H8/subQ!H5,"") | I22: =IFERROR(subQ!I8/subQ!I5,"") | J22: =IFERROR(subQ!J8/subQ!J5,"") | K22: =IFERROR(subQ!K8/subQ!K5,"") | L22: =IFERROR(subQ!L8/subQ!L5,"") | ... AB22: =IFERROR(subQ!AB8/subQ!AB5,"") | AC22: =$D$47 | AD22: =$D$47 | AE22: =IFERROR(subQ!AE8/subQ!AE5,"") | AF22: =$D$47 | AG22: =$D$47 | AH22: =$D$47 | AI22: =$D$47 | AJ22: =IFERROR(subQ!AJ8/subQ!AJ5,"") | AK22: =$D$47 | AL22: =$D$47 | AM22: =$D$47 | AN22: =$D$47 | AO22: =IFERROR(subQ!AO8/subQ!AO5,"")
A23: drv:영업이익 | B23: ratio | C23: 영업이익률(OPM) | E23: =IFERROR(subQ!E9/subQ!E5,"") | F23: =IFERROR(subQ!F9/subQ!F5,"") | G23: =IFERROR(subQ!G9/subQ!G5,"") | H23: =IFERROR(subQ!H9/subQ!H5,"") | I23: =IFERROR(subQ!I9/subQ!I5,"") | J23: =IFERROR(subQ!J9/subQ!J5,"") | K23: =IFERROR(subQ!K9/subQ!K5,"") | L23: =IFERROR(subQ!L9/subQ!L5,"") | ... AB23: =IFERROR(subQ!AB9/subQ!AB5,"") | AC23: 0.11416096 | AD23: 0.11416058 | AE23: =IFERROR(subQ!AE9/subQ!AE5,"") | AF23: 0.11416434 | AG23: 0.11416347 | AH23: 0.11415723 | AI23: 0.1141547 | AJ23: =IFERROR(subQ!AJ9/subQ!AJ5,"") | AK23: 0.11415594 | AL23: 0.11416301 | AM23: 0.11416675 | AN23: 0.11416694 | AO23: =IFERROR(subQ!AO9/subQ!AO5,"")
A24: drv:기타영업외손익 | B24: abs | C24: 기타영업외손익 (가정, 억원) | E24: =subQ!E13 | F24: =subQ!F13 | G24: =subQ!G13 | H24: =subQ!H13 | I24: =subQ!I13 | J24: =subQ!J13 | K24: =subQ!K13 | L24: =subQ!L13 | ... AB24: =subQ!AB13 | AC24: 0 | AD24: 0 | AE24: =subQ!AE13 | AF24: 0 | AG24: 0 | AH24: 0 | AI24: 0 | AJ24: =subQ!AJ13 | AK24: 0 | AL24: 0 | AM24: 0 | AN24: 0 | AO24: =subQ!AO13
A25: drv:법인세비용 | B25: tax | C25: 법인세율(/세전) — 법인세 = MAX(세전,0) × 세율 | E25: =IFERROR(subQ!E15/subQ!E14,"") | F25: =IFERROR(subQ!F15/subQ!F14,"") | G25: =IFERROR(subQ!G15/subQ!G14,"") | H25: =IFERROR(subQ!H15/subQ!H14,"") | I25: =IFERROR(subQ!I15/subQ!I14,"") | J25: =IFERROR(subQ!J15/subQ!J14,"") | K25: =IFERROR(subQ!K15/subQ!K14,"") | L25: =IFERROR(subQ!L15/subQ!L14,"") | ... AB25: =IFERROR(subQ!AB15/subQ!AB14,"") | AC25: =$D$46 | AD25: =$D$46 | AE25: =IFERROR(subQ!AE15/subQ!AE14,"") | AF25: =$D$46 | AG25: =$D$46 | AH25: =$D$46 | AI25: =$D$46 | AJ25: =IFERROR(subQ!AJ15/subQ!AJ14,"") | AK25: =$D$46 | AL25: =$D$46 | AM25: =$D$46 | AN25: =$D$46 | AO25: =IFERROR(subQ!AO15/subQ!AO14,"")
A26: drv:지배주주순이익 | B26: ratio | C26: 지배주주 비중(/당기순이익) | E26: =IFERROR(subQ!E17/subQ!E16,"") | F26: =IFERROR(subQ!F17/subQ!F16,"") | G26: =IFERROR(subQ!G17/subQ!G16,"") | H26: =IFERROR(subQ!H17/subQ!H16,"") | I26: =IFERROR(subQ!I17/subQ!I16,"") | J26: =IFERROR(subQ!J17/subQ!J16,"") | K26: =IFERROR(subQ!K17/subQ!K16,"") | L26: =IFERROR(subQ!L17/subQ!L16,"") | ... AB26: =IFERROR(subQ!AB17/subQ!AB16,"") | AC26: =$D$48 | AD26: =$D$48 | AE26: =IFERROR(subQ!AE17/subQ!AE16,"") | AF26: =$D$48 | AG26: =$D$48 | AH26: =$D$48 | AI26: =$D$48 | AJ26: =IFERROR(subQ!AJ17/subQ!AJ16,"") | AK26: =$D$48 | AL26: =$D$48 | AM26: =$D$48 | AN26: =$D$48 | AO26: =IFERROR(subQ!AO17/subQ!AO16,"")
A27: drv:감가상각비 | B27: abs | C27: 감가상각비 (가정, 억원) | E27: =subQ!E18 | F27: =subQ!F18 | G27: =subQ!G18 | H27: =subQ!H18 | I27: =subQ!I18 | J27: =subQ!J18 | K27: =subQ!K18 | L27: =subQ!L18 | ... AB27: =subQ!AB18 | AC27: 10.22 | AD27: 10.22 | AE27: =subQ!AE18 | AF27: 10.22 | AG27: 10.22 | AH27: 10.22 | AI27: 10.22 | AJ27: =subQ!AJ18 | AK27: 10.22 | AL27: 10.22 | AM27: 10.22 | AN27: 10.22 | AO27: =subQ!AO18
A28: drv:부채총계 | B28: qoq | C28: 부채총계 QoQ | G28: =IFERROR(subQ!G21/subQ!E21-1,"") | H28: =IFERROR(subQ!H21/subQ!G21-1,"") | I28: =IFERROR(subQ!I21/subQ!H21-1,"") | J28: =IFERROR(subQ!J21/subQ!I21-1,"") | L28: =IFERROR(subQ!L21/subQ!J21-1,"") | M28: =IFERROR(subQ!M21/subQ!L21-1,"") | N28: =IFERROR(subQ!N21/subQ!M21-1,"") | O28: =IFERROR(subQ!O21/subQ!N21-1,"") | Q28: =IFERROR(subQ!Q21/subQ!O21-1,"") | R28: =IFERROR(subQ!R21/subQ!Q21-1,"") | S28: =IFERROR(subQ!S21/subQ!R21-1,"") | T28: =IFERROR(subQ!T21/subQ!S21-1,"") | V28: =IFERROR(subQ!V21/subQ!T21-1,"") | W28: =IFERROR(subQ!W21/subQ!V21-1,"") | X28: =IFERROR(subQ!X21/subQ!W21-1,"") | Y28: =IFERROR(subQ!Y21/subQ!X21-1,"") | AA28: =IFERROR(subQ!AA21/subQ!Y21-1,"") | AB28: =IFERROR(subQ!AB21/subQ!AA21-1,"") | AC28: -5.842e-06 | AD28: 0 | AF28: 0 | AG28: 0 | AH28: 0 | AI28: 0 | AK28: 0 | AL28: 0 | AM28: 0 | AN28: 0
A29: drv:자본총계 | B29: roll | C29: 자본총계 기타변동(배당 등, 억원) | G29: =IFERROR(subQ!E22+subQ!G16-subQ!G22,"") | H29: =IFERROR(subQ!G22+subQ!H16-subQ!H22,"") | I29: =IFERROR(subQ!H22+subQ!I16-subQ!I22,"") | J29: =IFERROR(subQ!I22+subQ!J16-subQ!J22,"") | L29: =IFERROR(subQ!J22+subQ!L16-subQ!L22,"") | M29: =IFERROR(subQ!L22+subQ!M16-subQ!M22,"") | N29: =IFERROR(subQ!M22+subQ!N16-subQ!N22,"") | O29: =IFERROR(subQ!N22+subQ!O16-subQ!O22,"") | Q29: =IFERROR(subQ!O22+subQ!Q16-subQ!Q22,"") | R29: =IFERROR(subQ!Q22+subQ!R16-subQ!R22,"") | S29: =IFERROR(subQ!R22+subQ!S16-subQ!S22,"") | T29: =IFERROR(subQ!S22+subQ!T16-subQ!T22,"") | V29: =IFERROR(subQ!T22+subQ!V16-subQ!V22,"") | W29: =IFERROR(subQ!V22+subQ!W16-subQ!W22,"") | X29: =IFERROR(subQ!W22+subQ!X16-subQ!X22,"") | Y29: =IFERROR(subQ!X22+subQ!Y16-subQ!Y22,"") | AA29: =IFERROR(subQ!Y22+subQ!AA16-subQ!AA22,"") | AB29: =IFERROR(subQ!AA22+subQ!AB16-subQ!AB22,"") | AC29: -0.004736154 | AD29: 0.003494381 | AF29: 0.007968544 | AG29: 18.581169 | AH29: 0.00266492 | AI29: -0.006976671 | AK29: 0.004632015 | AL29: 18.578053 | AM29: 0.008174249 | AN29: 0.003590014
A30: drv:지배주주지분 | B30: roll | C30: 지배주주지분 기타변동(배당 등, 억원) | G30: =IFERROR(subQ!E23+subQ!G17-subQ!G23,"") | H30: =IFERROR(subQ!G23+subQ!H17-subQ!H23,"") | I30: =IFERROR(subQ!H23+subQ!I17-subQ!I23,"") | J30: =IFERROR(subQ!I23+subQ!J17-subQ!J23,"") | L30: =IFERROR(subQ!J23+subQ!L17-subQ!L23,"") | M30: =IFERROR(subQ!L23+subQ!M17-subQ!M23,"") | N30: =IFERROR(subQ!M23+subQ!N17-subQ!N23,"") | O30: =IFERROR(subQ!N23+subQ!O17-subQ!O23,"") | Q30: =IFERROR(subQ!O23+subQ!Q17-subQ!Q23,"") | R30: =IFERROR(subQ!Q23+subQ!R17-subQ!R23,"") | S30: =IFERROR(subQ!R23+subQ!S17-subQ!S23,"") | T30: =IFERROR(subQ!S23+subQ!T17-subQ!T23,"") | V30: =IFERROR(subQ!T23+subQ!V17-subQ!V23,"") | W30: =IFERROR(subQ!V23+subQ!W17-subQ!W23,"") | X30: =IFERROR(subQ!W23+subQ!X17-subQ!X23,"") | Y30: =IFERROR(subQ!X23+subQ!Y17-subQ!Y23,"") | AA30: =IFERROR(subQ!Y23+subQ!AA17-subQ!AA23,"") | AB30: =IFERROR(subQ!AA23+subQ!AB17-subQ!AB23,"") | AC30: -0.004736154 | AD30: 0.003494381 | AF30: 0.007968544 | AG30: 18.581169 | AH30: 0.00266492 | AI30: -0.006976671 | AK30: 0.004632015 | AL30: 18.578053 | AM30: 0.008174249 | AN30: 0.003590014
A31: drv:이자발생자산 | B31: qoq | C31: 이자발생자산 QoQ | G31: =IFERROR(subQ!G24/subQ!E24-1,"") | H31: =IFERROR(subQ!H24/subQ!G24-1,"") | I31: =IFERROR(subQ!I24/subQ!H24-1,"") | J31: =IFERROR(subQ!J24/subQ!I24-1,"") | L31: =IFERROR(subQ!L24/subQ!J24-1,"") | M31: =IFERROR(subQ!M24/subQ!L24-1,"") | N31: =IFERROR(subQ!N24/subQ!M24-1,"") | O31: =IFERROR(subQ!O24/subQ!N24-1,"") | Q31: =IFERROR(subQ!Q24/subQ!O24-1,"") | R31: =IFERROR(subQ!R24/subQ!Q24-1,"") | S31: =IFERROR(subQ!S24/subQ!R24-1,"") | T31: =IFERROR(subQ!T24/subQ!S24-1,"") | V31: =IFERROR(subQ!V24/subQ!T24-1,"") | W31: =IFERROR(subQ!W24/subQ!V24-1,"") | X31: =IFERROR(subQ!X24/subQ!W24-1,"") | Y31: =IFERROR(subQ!Y24/subQ!X24-1,"") | AA31: =IFERROR(subQ!AA24/subQ!Y24-1,"") | AB31: =IFERROR(subQ!AB24/subQ!AA24-1,"") | AC31: 0.11738804 | AD31: 0.098235499 | AF31: 0.082035306 | AG31: 0.079054702 | AH31: 0.089395343 | AI31: 0.076945755 | AK31: 0.065783655 | AL31: 0.065250035 | AM31: 0.071510048 | AN31: 0.0627564
A32: drv:현금및현금성자산 | B32: qoq | C32: 현금및현금성자산 QoQ | G32: =IFERROR(subQ!G25/subQ!E25-1,"") | H32: =IFERROR(subQ!H25/subQ!G25-1,"") | I32: =IFERROR(subQ!I25/subQ!H25-1,"") | J32: =IFERROR(subQ!J25/subQ!I25-1,"") | L32: =IFERROR(subQ!L25/subQ!J25-1,"") | M32: =IFERROR(subQ!M25/subQ!L25-1,"") | N32: =IFERROR(subQ!N25/subQ!M25-1,"") | O32: =IFERROR(subQ!O25/subQ!N25-1,"") | Q32: =IFERROR(subQ!Q25/subQ!O25-1,"") | R32: =IFERROR(subQ!R25/subQ!Q25-1,"") | S32: =IFERROR(subQ!S25/subQ!R25-1,"") | T32: =IFERROR(subQ!T25/subQ!S25-1,"") | V32: =IFERROR(subQ!V25/subQ!T25-1,"") | W32: =IFERROR(subQ!W25/subQ!V25-1,"") | X32: =IFERROR(subQ!X25/subQ!W25-1,"") | Y32: =IFERROR(subQ!Y25/subQ!X25-1,"") | AA32: =IFERROR(subQ!AA25/subQ!Y25-1,"") | AB32: =IFERROR(subQ!AB25/subQ!AA25-1,"")
A33: drv:CAPEX | B33: yoy | C33: CAPEX YoY | J33: =IFERROR(subQ!J26/subQ!E26-1,"") | L33: =IFERROR(subQ!L26/subQ!G26-1,"") | M33: =IFERROR(subQ!M26/subQ!H26-1,"") | N33: =IFERROR(subQ!N26/subQ!I26-1,"") | O33: =IFERROR(subQ!O26/subQ!J26-1,"") | Q33: =IFERROR(subQ!Q26/subQ!L26-1,"") | R33: =IFERROR(subQ!R26/subQ!M26-1,"") | S33: =IFERROR(subQ!S26/subQ!N26-1,"") | T33: =IFERROR(subQ!T26/subQ!O26-1,"") | V33: =IFERROR(subQ!V26/subQ!Q26-1,"") | W33: =IFERROR(subQ!W26/subQ!R26-1,"") | X33: =IFERROR(subQ!X26/subQ!S26-1,"") | Y33: =IFERROR(subQ!Y26/subQ!T26-1,"") | AA33: =IFERROR(subQ!AA26/subQ!V26-1,"") | AB33: =IFERROR(subQ!AB26/subQ!W26-1,"") | AC33: 1.0164761 | AD33: 0.26348228 | AF33: -0.17244859 | AG33: -0.81842112 | AH33: 0 | AI33: 0 | AK33: 0 | AL33: 0 | AM33: 0 | AN33: 0
A34: drv:영업활동현금흐름 | B34: yoy | C34: 영업활동현금흐름 YoY | J34: =IFERROR(subQ!J27/subQ!E27-1,"") | L34: =IFERROR(subQ!L27/subQ!G27-1,"") | M34: =IFERROR(subQ!M27/subQ!H27-1,"") | N34: =IFERROR(subQ!N27/subQ!I27-1,"") | O34: =IFERROR(subQ!O27/subQ!J27-1,"") | Q34: =IFERROR(subQ!Q27/subQ!L27-1,"") | R34: =IFERROR(subQ!R27/subQ!M27-1,"") | S34: =IFERROR(subQ!S27/subQ!N27-1,"") | T34: =IFERROR(subQ!T27/subQ!O27-1,"") | V34: =IFERROR(subQ!V27/subQ!Q27-1,"") | W34: =IFERROR(subQ!W27/subQ!R27-1,"") | X34: =IFERROR(subQ!X27/subQ!S27-1,"") | Y34: =IFERROR(subQ!Y27/subQ!T27-1,"") | AA34: =IFERROR(subQ!AA27/subQ!V27-1,"") | AB34: =IFERROR(subQ!AB27/subQ!W27-1,"")
A35: drv:주식수 | B35: qoq | C35: 주식수 QoQ | G35: =IFERROR(subQ!G28/subQ!E28-1,"") | H35: =IFERROR(subQ!H28/subQ!G28-1,"") | I35: =IFERROR(subQ!I28/subQ!H28-1,"") | J35: =IFERROR(subQ!J28/subQ!I28-1,"") | L35: =IFERROR(subQ!L28/subQ!J28-1,"") | M35: =IFERROR(subQ!M28/subQ!L28-1,"") | N35: =IFERROR(subQ!N28/subQ!M28-1,"") | O35: =IFERROR(subQ!O28/subQ!N28-1,"") | Q35: =IFERROR(subQ!Q28/subQ!O28-1,"") | R35: =IFERROR(subQ!R28/subQ!Q28-1,"") | S35: =IFERROR(subQ!S28/subQ!R28-1,"") | T35: =IFERROR(subQ!T28/subQ!S28-1,"") | V35: =IFERROR(subQ!V28/subQ!T28-1,"") | W35: =IFERROR(subQ!W28/subQ!V28-1,"") | X35: =IFERROR(subQ!X28/subQ!W28-1,"") | Y35: =IFERROR(subQ!Y28/subQ!X28-1,"") | AA35: =IFERROR(subQ!AA28/subQ!Y28-1,"") | AB35: =IFERROR(subQ!AB28/subQ!AA28-1,"") | AC35: 0 | AD35: 0 | AF35: 0 | AG35: 0 | AH35: 0 | AI35: 0 | AK35: 0 | AL35: 0 | AM35: 0 | AN35: 0
A36: drv:DPS | B36: abs | C36: DPS (가정, 원) | E36: =subQ!E31 | F36: =subQ!F31 | G36: =subQ!G31 | H36: =subQ!H31 | I36: =subQ!I31 | J36: =subQ!J31 | K36: =subQ!K31 | L36: =subQ!L31 | ... AB36: =subQ!AB31 | AD36: 200 | AE36: =subQ!AE31 | AI36: 200 | AJ36: =subQ!AJ31 | AN36: 200 | AO36: =subQ!AO31
B38: 3. 밸류에이션·스칼라 | C38: 노란 셀 = 가정. '연결' 표시는 추정 전 분기 수식이 이 셀을 참조한다는 뜻
A39: sc:종가 | C39: 종가 | D39: 14720 | E39: 원 — 네이버 정규장 종가(aik 확정종가 대조 · aik 15,550원)
A40: sc:기준일 | C40: 기준일 | D40: 20261026 | E40: 종가 기준일
A41: sc:COE | C41: COE | D41: 0.09 | E41: 자기자본비용(가정) — TP 적정 PBR = ROE/COE
A42: sc:PER_lo | C42: PER_lo | D42: 8.4 | E42: PER 밴드 하단(배) — hist_quarterly(분기 평균가 ÷ TTM EPS, 12분기, 25/50/75 백분위)
A43: sc:PER_mid | C43: PER_mid | D43: 9.5 | E43: PER 밴드 중단(배)
A44: sc:PER_hi | C44: PER_hi | D44: 10.7 | E44: PER 밴드 상단(배)
A45: sc:EPS_Y1가중 | C45: EPS_Y1가중 | D45: 0.5 | E45: 12M fwd EPS = FY(last_actual연도)E × w + FY+1E × (1−w) — 기준 분기 2Q 이면 0.5(가정)
A46: sc:세율 | C46: 세율 | D46: 0.18961339 | E46: 연결 — 법인세 = MAX(세전,0) × 세율(역산, 재현 오차 ≤ 0.05억 · 모델 assumptions 0.1896) · 최근 12분기 유효세율 19.0%(5~27% 안 — 그대로)
A47: sc:판관비율 | C47: 판관비율 | D47: 0.069225898 | E47: 연결 — 판관비 = 매출액 × 판관비율(역산, 재현 오차 ≤ 0.05억 · 모델 assumptions 0.0692)
A48: sc:지배주주비중 | C48: 지배주주비중 | D48: 1 | E48: 연결 — 지배주주순이익 = 당기순이익 × 비중(역산, 재현 오차 ≤ 0.05억)
A49: sc:이자율_자산 | C49: 이자율_자산 | D49: 0.05500608 | E49: 연결 — 이자손익 = (전분기 이자발생자산 × 자산이자율 − 전분기 총차입금 × 부채이자율)/4(역산, 재현 오차 ≤ 0.05억 · 모델 assumptions 0.055)
A50: sc:이자율_부채 | C50: 이자율_부채 | E50: 연결 — 같은 수식의 부채 쪽(총차입금 행이 없으면 0)(역산, 재현 오차 ≤ 0.05억)
A51: sc:배당성향 | C51: 배당성향 | D51: 0.075 | E51: 배당성향(참고 — 모델은 직전 DPS 유지·Q2 지급 가정)
A52: sc:외화순노출_백만$ | C52: 외화순노출_백만$ | E52: 외화 순노출 × Δ기말환율 (외화 시트 방식) — 외화 순노출 미공시(face) → 0 + 표기
A53: sc:헤지비율 | C53: 헤지비율 | E53: sls 없음
A54: sc:헤지환율_약정 | C54: 헤지환율_약정 | E54: sls 없음

Sheet BS연결
B1: (백만원) | C1: 이름: BS연결H | E1: 4Q21 | F1: 2021 | G1: 1Q22 | H1: 2Q22 | I1: 3Q22 | J1: 4Q22 | K1: 2022 | L1: 1Q23 | M1: 2Q23 | N1: 3Q23 | O1: 4Q23 | P1: 2023 | Q1: 1Q24 | R1: 2Q24 | S1: 3Q24 | T1: 4Q24 | U1: 2024 | V1: 1Q25 | W1: 2Q25 | X1: 3Q25 | Y1: 4Q25 | Z1: 2025 | AA1: 1Q26 | AB1: 2Q26 | AC1: 3Q26 | AD1: 4Q26 | AE1: 2026 | AF1: 1Q27 | AG1: 2Q27 | AH1: 3Q27 | AI1: 4Q27 | AJ1: 2027 | AK1: 1Q28 | AL1: 2Q28 | AM1: 3Q28 | AN1: 4Q28 | AO1: 2028
B2: 연결 | D2: fin json(kship_fin.py)
B3: 대양전기공업(연) | C3: UPDATE: 26-10-26 | E3: 1 | F3: 2 | G3: 3 | H3: 4 | I3: 5 | J3: 6 | K3: 7 | L3: 8 | M3: 9 | N3: 10 | O3: 11 | P3: 12 | Q3: 13 | R3: 14 | S3: 15 | T3: 16 | U3: 17 | V3: 18 | W3: 19 | X3: 20 | Y3: 21 | Z3: 22 | AA3: 23 | AB3: 24 | AC3: 25 | AD3: 26 | AE3: 27 | AF3: 28 | AG3: 29 | AH3: 30 | AI3: 31 | AJ3: 32 | AK3: 33 | AL3: 34 | AM3: 35 | AN3: 36 | AO3: 37
B4: Account Code | C4: AccountNAME | E4: 2021.12 | F4: 2021.12A | G4: 2022.03 | H4: 2022.06 | I4: 2022.09 | J4: 2022.12 | K4: 2022.12A | L4: 2023.03 | M4: 2023.06 | N4: 2023.09 | O4: 2023.12 | P4: 2023.12A | Q4: 2024.03 | R4: 2024.06 | S4: 2024.09 | T4: 2024.12 | U4: 2024.12A | V4: 2025.03 | W4: 2025.06 | X4: 2025.09 | Y4: 2025.12 | Z4: 2025.12A | AA4: 2026.03 | AB4: 2026.06 | AC4: 2026.09 | AD4: 2026.12 | AE4: 2026.12A | AF4: 2027.03 | AG4: 2027.06 | AH4: 2027.09 | AI4: 2027.12 | AJ4: 2027.12A | AK4: 2028.03 | AL4: 2028.06 | AM4: 2028.09 | AN4: 2028.12 | AO4: 2028.12A
A5: 1 | C5: 유동자산 | E5: 114662.75 | F5: 114662.75 | G5: 122240.36 | H5: 123615.1 | I5: 127884.24 | J5: 127196.71 | K5: 127196.71 | L5: 132207.02 | M5: 141007.44 | N5: 138400.79 | O5: 152193.85 | P5: 152193.85 | Q5: 151004.98 | R5: 155385.01 | S5: 157717.24 | T5: 167739.87 | U5: 167739.87 | V5: 183607.42 | W5: 203513.93 | X5: 204339.94 | Y5: 207302.69 | Z5: 207302.69 | AA5: 223867.46 | AB5: 225180.68
A6: 1 | C6: 현금및현금성자산 | E6: 38439.6 | F6: 38439.6 | G6: 27317.76 | H6: 26668.27 | I6: 29176.22 | J6: 27883.82 | K6: 27883.82 | L6: 25275.5 | M6: 31968.84 | N6: 21958.54 | O6: 39294.44 | P6: 39294.44 | Q6: 30995.1 | R6: 34067.27 | S6: 35879.5 | T6: 34949.76 | U6: 34949.76 | V6: 38014.46 | W6: 35112.52 | X6: 38137.1 | Y6: 43446.84 | Z6: 43446.84 | AA6: 43188.11 | AB6: 44253.17
A7: 1 | C7: 매출채권및기타채권 | E7: 24636.45 | F7: 24636.45 | G7: 26585.57 | H7: 28011.21 | I7: 26968.27 | J7: 23386.03 | K7: 23386.03 | L7: 27155.77 | M7: 25816.15 | N7: 30065.16 | O7: 29997.79 | P7: 29997.79 | Q7: 24779.77 | R7: 26812.57 | S7: 28844.94 | T7: 36861.09 | U7: 36861.09 | V7: 38818.49 | W7: 39506.09 | X7: 36326.96 | Y7: 37268.06 | Z7: 37268.06 | AA7: 34151.85 | AB7: 50671.56
A8: 1 | C8: 단기투자자산(공정가치) | E8: 4185.91 | F8: 4185.91 | G8: 4275.47 | H8: 6559.14 | I8: 7250.59 | J8: 10352.3 | K8: 10352.3 | L8: 10706.2 | M8: 10835 | N8: 8371.18 | O8: 4097.66 | P8: 4097.66 | Q8: 4281.83 | R8: 4466.09 | S8: 4288.21 | T8: 12155.52 | U8: 12155.52 | V8: 24521.68 | W8: 38933.25 | X8: 34460.12 | Y8: 34769.73 | Z8: 34769.73 | AA8: 40501.05 | AB8: 30461.19
A9: 1 | C9: 기타유동금융자산 | E9: 9935.31 | F9: 9935.31 | G9: 27061.86 | H9: 27150.2 | I9: 27220.74 | J9: 29539.42 | K9: 29539.42 | L9: 29532.67 | M9: 29207.07 | N9: 30376.83 | O9: 30183 | P9: 30183 | Q9: 32340.55 | R9: 32591.88 | S9: 32770.64 | T9: 31990.05 | U9: 31990.05 | V9: 31173.51 | W9: 31662.29 | X9: 36655.54 | Y9: 36809.09 | Z9: 36809.09 | AA9: 36933.97 | AB9: 38343
A10: 1 | C10: 당기법인세자산(선급법인세) | E10: 567.6 | F10: 567.6 | G10: 568.04 | H10: 98.47 | I10: 157.51 | J10: 250.06 | K10: 250.06 | L10: 412.2 | M10: 283.51 | N10: 369.61 | O10: 24.3 | P10: 24.3 | Q10: 30.46 | R10: 0 | S10: 26.92 | T10: 41.98 | U10: 41.98 | V10: 56.11 | W10: 17.9 | X10: 0 | Y10: 0 | Z10: 0 | AA10: 0
A11: 1 | C11: 재고자산 | E11: 29020.6 | F11: 29020.6 | G11: 27948.39 | H11: 28352.22 | I11: 31545.25 | J11: 25689.56 | K11: 25689.56 | L11: 29376.08 | M11: 34923.37 | N11: 38119.12 | O11: 38466.57 | P11: 38466.57 | Q11: 44248.95 | R11: 42418.41 | S11: 42899.8 | T11: 38204.64 | U11: 38204.64 | V11: 41740.88 | W11: 42997.2 | X11: 39982.46 | Y11: 35932.39 | Z11: 35932.39 | AA11: 48678.08 | AB11: 46027.62
A12: 1 | C12: 매각예정비유동자산및처분자산 | E12: 0 | F12: 0 | J12: 0 | K12: 0 | L12: 0
A13: 1 | C13: 비유동자산 | E13: 145340.64 | F13: 145340.64 | G13: 135820.12 | H13: 135195.14 | I13: 134729.92 | J13: 133915.81 | K13: 133915.81 | L13: 134063.15 | M13: 138247.38 | N13: 141884.87 | O13: 145756.43 | P13: 145756.43 | Q13: 144952.59 | R13: 147464.64 | S13: 145947.16 | T13: 140866.02 | U13: 140866.02 | V13: 126986.11 | W13: 115327.82 | X13: 115610.24 | Y13: 114680.87 | Z13: 114680.87 | AA13: 109014.32 | AB13: 121134.94
A14: 1 | C14: 장기매출채권및기타채권 | E14: 813.69 | F14: 813.69 | G14: 924.67 | H14: 1230.12 | I14: 1484.21 | J14: 81.14 | K14: 81.14 | L14: 37.83 | M14: 104.49 | N14: 177.2 | O14: 726.05 | P14: 726.05 | Q14: 1009.24 | R14: 1930.09 | S14: 611.43 | T14: 1662.41 | U14: 1662.41 | V14: 606.57 | W14: 1060.04 | X14: 1083.31 | Y14: 809.54 | Z14: 809.54 | AA14: 922.35 | AB14: 1030.21
A15: 1 | C15: 장기금융자산 | E15: 39885.42 | F15: 39885.42 | G15: 43835.27 | H15: 41818.64 | I15: 41735.44 | J15: 41153.41 | K15: 41153.41 | L15: 42357.96 | M15: 42790.39 | N15: 45250.98 | O15: 46702.02 | P15: 46702.02 | Q15: 47140.66 | R15: 47547.47 | S15: 47672.28 | T15: 41548.17 | U15: 41548.17 | V15: 27616.13 | W15: 12751.34 | X15: 13445.04 | Y15: 14471.83 | Z15: 14471.83 | AA15: 9497.84 | AB15: 12248.24
A16: 1 | C16: 투자자산 | E16: 39885.42 | F16: 39885.42 | G16: 43835.27 | H16: 41818.64 | I16: 41735.44 | J16: 41153.41 | K16: 41153.41 | L16: 42357.96 | M16: 42790.39 | N16: 45250.98 | O16: 46702.02 | P16: 46702.02 | Q16: 47140.66 | R16: 47547.47 | S16: 47672.28 | T16: 41548.17 | U16: 41548.17 | V16: 27616.13 | W16: 12751.34 | X16: 13445.04 | Y16: 14471.83 | Z16: 14471.83 | AA16: 9497.84 | AB16: 12248.24
A17: 1 | C17: 유형자산 | E17: 72261.42 | F17: 72261.42 | G17: 76101.88 | H17: 76939.6 | I17: 76874.77 | J17: 76491.86 | K17: 76491.86 | L17: 75953.3 | M17: 79693.95 | N17: 81650.54 | O17: 83082.81 | P17: 83082.81 | Q17: 82231.88 | R17: 83275.2 | S17: 82602.88 | T17: 79646.8 | U17: 79646.8 | V17: 80262.65 | W17: 82623.93 | X17: 72019.5 | Y17: 79391.81 | Z17: 79391.81 | AA17: 79496.72 | AB17: 90293.77
A18: 1 | C18: 투자부동산 | E18: 1876.49 | F18: 1876.49 | G18: 1863.36 | H18: 1850.22 | I18: 1837.08 | J18: 1906.88 | K18: 1906.88 | L18: 1897.7 | M18: 1888.53 | N18: 1879.36 | O18: 1870.19 | P18: 1870.19 | Q18: 1861.01 | R18: 1851.84 | S18: 1842.67 | T18: 5487.18 | U18: 5487.18 | V18: 5470.99 | W18: 5454.81 | X18: 15623.2 | Y18: 8063.26 | Z18: 8063.26 | AA18: 8033.02 | AB18: 5403.94
A19: 1 | C19: 무형자산 | E19: 8010.42 | F19: 8010.42 | G19: 7954.13 | H19: 7893.01 | I19: 7863.45 | J19: 7812.28 | K19: 7812.28 | L19: 7750.25 | M19: 7701.07 | N19: 1195.09 | O19: 1148.8 | P19: 1148.8 | Q19: 1136.21 | R19: 7405.21 | S19: 7396.57 | T19: 943.05 | U19: 943.05 | V19: 947.13 | W19: 1250.01 | X19: 1241.37 | Y19: 7688.87 | Z19: 7688.87 | AA19: 7695.78 | AB19: 7850.17
A20: 1 | C20: 이연법인세자산 | E20: 1233.72 | F20: 1233.72 | G20: 1733.62 | H20: 2052.15 | I20: 1516.31 | J20: 4131.95 | K20: 4131.95 | L20: 3746.08 | M20: 3685.98 | N20: 2940.21 | O20: 3249.19 | P20: 3249.19 | Q20: 2680.62 | R20: 2746.1 | S20: 2965.36 | T20: 2400.37 | U20: 2400.37 | V20: 3086.21 | W20: 3390.1 | X20: 3365.58 | Y20: 3853.02 | Z20: 3853.02 | AA20: 3030.66 | AB20: 3940.26
A21: 1 | C21: 자산총계 | E21: 260003.39 | F21: 260003.39 | G21: 258060.48 | H21: 258810.24 | I21: 262614.16 | J21: 261112.52 | K21: 261112.52 | L21: 266270.17 | M21: 279254.82 | N21: 280285.66 | O21: 297950.27 | P21: 297950.27 | Q21: 295957.58 | R21: 302849.65 | S21: 303664.4 | T21: 308605.89 | U21: 308605.89 | V21: 310593.54 | W21: 318841.75 | X21: 319950.18 | Y21: 321983.56 | Z21: 321983.56 | AA21: 332881.78 | AB21: 346315.62
A22: 1 | C22: 유동부채 | E22: 32079.87 | F22: 32079.87 | G22: 32653.45 | H22: 34194.32 | I22: 36116.54 | J22: 41386.24 | K22: 41386.24 | L22: 44968 | M22: 57779.65 | N22: 55734.54 | O22: 70905.91 | P22: 70905.91 | Q22: 65168.3 | R22: 67858.48 | S22: 66041.77 | T22: 61797.78 | U22: 61797.78 | V22: 58716.67 | W22: 62691.42 | X22: 55559.82 | Y22: 50824.59 | Z22: 50824.59 | AA22: 56460.74 | AB22: 66524.95
A23: 1 | C23: 매입채무및기타채무 | E23: 13670.01 | F23: 13670.01 | G23: 13892.8 | H23: 13093.45 | I23: 13550.6 | J23: 11171.8 | K23: 11171.8 | L23: 13443.66 | M23: 14536.27 | N23: 15167.55 | O23: 18152.99 | P23: 18152.99 | Q23: 15945.6 | R23: 16866.88 | S23: 16529.28 | T23: 20068.52 | U23: 20068.52 | V23: 20742.33 | W23: 23899.03 | X23: 21092.94 | Y23: 19052.81 | Z23: 19052.81 | AA23: 28895.42 | AB23: 27651.01
A24: 1 | C24: 유동리스부채 | E24: 197.24 | F24: 197.24 | G24: 193.24 | H24: 189.25 | I24: 185.25 | J24: 197.04 | K24: 197.04 | L24: 248.44 | M24: 199.63 | N24: 203.96 | O24: 201 | P24: 201 | Q24: 198.01 | R24: 195.01 | S24: 191.97 | T24: 194.52 | U24: 194.52 | V24: 144.01 | W24: 90.75 | X24: 35.06 | Y24: 228.13 | Z24: 228.13 | AA24: 221.64 | AB24: 247.57
... A26: 1 | C26: 단기금융부채 | E26: 197.24 | F26: 197.24 | G26: 193.24 | H26: 189.25 | I26: 185.25 | J26: 197.04 | K26: 197.04 | L26: 248.44 | M26: 199.63 | N26: 203.96 | O26: 201 | P26: 201 | Q26: 198.01 | R26: 195.01 | S26: 191.97 | T26: 194.52 | U26: 194.52 | V26: 144.01 | W26: 90.75 | X26: 35.06 | Y26: 228.13 | Z26: 228.13 | AA26: 221.64 | AB26: 247.57
A27: 1 | C27: 당기법인세부채(미지급법인세) | E27: 0 | F27: 0 | J27: 0 | K27: 0 | L27: 0 | Q27: 178.14 | R27: 1097.22 | S27: 1640.07 | T27: 3186.94 | U27: 3186.94 | V27: 3854.63 | W27: 2956.4 | X27: 4268.49 | Y27: 5633.29 | Z27: 5633.29 | AA27: 4113.22 | AB27: 4279.1
A28: 1 | C28: 비유동부채 | E28: 1233.46 | F28: 1233.46 | G28: 1333.26 | H28: 1317.18 | I28: 1168.27 | J28: 1257.11 | K28: 1257.11 | L28: 1210.79 | M28: 1332.36 | N28: 1448.72 | O28: 1366.55 | P28: 1366.55 | Q28: 1406.38 | R28: 1312.81 | S28: 1400.34 | T28: 1539.37 | U28: 1539.37 | V28: 1772.99 | W28: 1688.73 | X28: 1818.63 | Y28: 1959.13 | Z28: 1959.13 | AA28: 1806.73 | AB28: 1949.45
A29: 1 | C29: 기타비유동금융부채 | E29: 622.18 | F29: 622.18 | G29: 616.25 | H29: 706.27 | I29: 694.15 | J29: 718.39 | K29: 718.39 | L29: 703.98 | M29: 745.63 | Y29: 290 | Z29: 290 | AA29: 964.35 | AB29: 360
A30: 1 | C30: 장기금융부채 | E30: 1146.25 | F30: 1146.25 | G30: 1095.6 | H30: 1140.61 | I30: 1083.2 | J30: 1077.52 | K30: 1077.52 | L30: 962.93 | M30: 1004.29 | N30: 204.91 | O30: 158.13 | P30: 158.13 | Q30: 111.04 | R30: 63.66 | S30: 15.97 | T30: 9.83 | U30: 9.83 | V30: 4.33 | W30: 1.16 | X30: 0 | Y30: 453.37 | Z30: 453.37 | AA30: 1074.92 | AB30: 453.43
A31: 1 | C31: 확정급여부채 | E31: 87.2 | F31: 87.2 | G31: 237.65 | H31: 176.57 | I31: 85.08 | J31: 0 | K31: 0 | L31: 21.22 | M31: 54.37 | N31: 157.34 | O31: 0 | P31: 0 | Q31: 57.1 | R31: 67.94 | S31: 170.52 | T31: 168.52 | U31: 168.52 | V31: 412.87 | W31: 417.54 | X31: 548.58
A32: 1 | C32: 비유동리스부채 | E32: 524.07 | F32: 524.07 | G32: 479.35 | H32: 434.34 | I32: 389.05 | J32: 359.13 | K32: 359.13 | L32: 258.95 | M32: 258.66 | N32: 204.91 | O32: 158.13 | P32: 158.13 | Q32: 111.04 | R32: 63.66 | S32: 15.97 | T32: 9.83 | U32: 9.83 | V32: 4.33 | W32: 1.16 | X32: 0 | Y32: 163.37 | Z32: 163.37 | AA32: 110.57 | AB32: 93.43
A33: 1 | C33: 부채총계 | E33: 33313.33 | F33: 33313.33 | G33: 33986.7 | H33: 35511.5 | I33: 37284.81 | J33: 42643.35 | K33: 42643.35 | L33: 46178.79 | M33: 59112 | N33: 57183.26 | O33: 72272.46 | P33: 72272.46 | Q33: 66574.68 | R33: 69171.29 | S33: 67442.12 | T33: 63337.14 | U33: 63337.14 | V33: 60489.66 | W33: 64380.14 | X33: 57378.45 | Y33: 52783.72 | Z33: 52783.72 | AA33: 58267.46 | AB33: 68474.4
A34: 1 | C34: 지배주주지분 | E34: 226690.06 | F34: 226690.06 | G34: 224073.78 | H34: 223298.74 | I34: 225329.35 | J34: 218469.18 | K34: 218469.18 | L34: 220091.38 | M34: 220142.81 | N34: 223102.4 | O34: 225677.81 | P34: 225677.81 | Q34: 229382.89 | R34: 233678.36 | S34: 236222.29 | T34: 245268.75 | U34: 245268.75 | V34: 250103.88 | W34: 254461.61 | X34: 262571.73 | Y34: 269199.84 | Z34: 269199.84 | AA34: 274614.32 | AB34: 277841.22
A35: 1 | C35: 자본금 | E35: 4783.67 | F35: 4783.67 | G35: 4783.67 | H35: 4783.67 | I35: 4783.67 | J35: 4783.67 | K35: 4783.67 | L35: 4783.67 | M35: 4783.67 | N35: 4783.67 | O35: 4783.67 | P35: 4783.67 | Q35: 4783.67 | R35: 4783.67 | S35: 4783.67 | T35: 4783.67 | U35: 4783.67 | V35: 4783.67 | W35: 4783.67 | X35: 4783.67 | Y35: 4783.67 | Z35: 4783.67 | AA35: 4783.67 | AB35: 4783.67
A36: 1 | C36: 자본잉여금 | E36: 24958.68 | F36: 24958.68 | G36: 24974.84 | H36: 24977.78 | I36: 24977.78 | J36: 24978.48 | K36: 24978.48 | L36: 25026.82 | M36: 25034.91 | N36: 25034.91 | O36: 25035.47 | P36: 25035.47 | Q36: 25048.84 | R36: 25053.11 | S36: 25053.11 | T36: 25053.11 | U36: 25053.11 | V36: 25053.11 | W36: 25086.07 | X36: 25086.07 | Y36: 25272.22 | Z36: 25272.22 | AA36: 25272.22 | AB36: 20460.2
A37: 1 | C37: 기타자본 | E37: -2586.62 | F37: -2586.62 | G37: -2597.23 | H37: -2562.52 | I37: -2554.74 | J37: -2541.49 | K37: -2541.49 | L37: -2581.8 | M37: -3490.35 | N37: -3523.92 | O37: -3508.07 | P37: -3508.07 | Q37: -3509.47 | R37: -3471.66 | S37: -3455.64 | T37: -3436.7 | U37: -3436.7 | V37: -3419.11 | W37: -3374.2 | X37: -3334.46 | Y37: -3296.14 | Z37: -3296.14 | AA37: -3296.14 | AB37: -2920.76
A38: 1 | C38: 기타포괄이익누계액 | E38: 9330.27 | F38: 9330.27 | G38: 9330.27 | H38: 9330.27 | I38: 9330.27 | J38: 9330.27 | K38: 9330.27 | L38: 9330.27 | M38: 9330.27 | N38: 9330.27 | O38: 9330.27 | P38: 9330.27 | Q38: 9330.27 | R38: 9330.27 | S38: 9330.27 | T38: 9330.27 | U38: 9330.27 | V38: 9330.27 | W38: 9330.27 | X38: 9330.27 | Y38: 9330.27 | Z38: 9330.27 | AA38: 9330.27 | AB38: 9330.27
A39: 1 | C39: 이익잉여금 | E39: 190204.06 | F39: 190204.06 | G39: 187582.23 | H39: 186769.55 | I39: 188792.37 | J39: 181918.26 | K39: 181918.26 | L39: 183532.43 | M39: 184484.32 | N39: 187477.48 | O39: 190036.48 | P39: 190036.48 | Q39: 193729.59 | R39: 197982.97 | S39: 200510.88 | T39: 209538.41 | U39: 209538.41 | V39: 214355.95 | W39: 218635.81 | X39: 226706.19 | Y39: 233109.82 | Z39: 233109.82 | AA39: 238524.3 | AB39: 246187.85
A40: 1 | C40: 비지배주주지분 | E40: 0 | F40: 0 | G40: 0 | H40: 0 | I40: 0 | J40: 0 | K40: 0 | L40: 0 | M40: 0 | N40: 0 | O40: 0 | P40: 0 | Q40: 0 | R40: 0 | S40: 0 | T40: 0 | U40: 0 | V40: 0 | W40: 0 | X40: 0
A41: 1 | C41: 자본총계 | E41: 226690.06 | F41: 226690.06 | G41: 224073.78 | H41: 223298.74 | I41: 225329.35 | J41: 218469.18 | K41: 218469.18 | L41: 220091.38 | M41: 220142.81 | N41: 223102.4 | O41: 225677.81 | P41: 225677.81 | Q41: 229382.89 | R41: 233678.36 | S41: 236222.29 | T41: 245268.75 | U41: 245268.75 | V41: 250103.88 | W41: 254461.61 | X41: 262571.73 | Y41: 269199.84 | Z41: 269199.84 | AA41: 274614.32 | AB41: 277841.22
A42: 1 | C42: 부채와자본총계 | E42: 260003.39 | F42: 260003.39 | G42: 258060.48 | H42: 258810.24 | I42: 262614.16 | J42: 261112.52 | K42: 261112.52 | L42: 266270.17 | M42: 279254.82 | N42: 280285.66 | O42: 297950.27 | P42: 297950.27 | Q42: 295957.58 | R42: 302849.65 | S42: 303664.4 | T42: 308605.89 | U42: 308605.89 | V42: 310593.54 | W42: 318841.75 | X42: 319950.18 | Y42: 321983.56 | Z42: 321983.56 | AA42: 332881.78 | AB42: 346315.62
A43: 1 | C43: 이자발생자산 | E43: 78325.02 | F43: 78325.02 | G43: 71153.03 | H43: 68486.91 | I43: 70911.66 | J43: 69037.23 | K43: 69037.23 | L43: 67633.46 | M43: 74759.23 | N43: 67209.52 | O43: 85996.46 | P43: 85996.46 | Q43: 78135.76 | R43: 81614.74 | S43: 83551.78 | T43: 76497.93 | U43: 76497.93 | V43: 65630.59 | W43: 47863.86 | X43: 51582.14 | Y43: 57918.67 | Z43: 57918.67 | AA43: 52685.95 | AB43: 56501.41
A44: 1 | C44: 기타비유동자산 | N44: 2.37 | O44: 2.11 | P44: 2.11 | Q44: 2.12 | T44: 1.06 | U44: 1.06 | V44: 1.06 | W44: 1.11 | X44: 1.67 | Y44: 402.55 | Z44: 402.55 | AA44: 337.96 | AB44: 368.35
A45: 1 | C45: 기타비유동부채 | N45: 765.73 | O45: 806.37 | P45: 806.37 | Q45: 804.06 | T45: 837.96 | U45: 837.96 | V45: 832.74 | W45: 290 | X45: 747
A46: 1 | C46: 기타유동자산 | Y46: 19076.58 | Z46: 19076.58 | AA46: 20414.41 | AB46: 15424.14
A47: 1 | C47: 사용권자산 | Y47: 401.66 | Z47: 401.66 | AA47: 337.07 | AB47: 367.46
A48: 1 | C48: 기타유동부채 | Y48: 25910.36 | Z48: 25910.36 | AA48: 23230.45 | AB48: 34347.26
A49: 1 | C49: 매출액(수익) | E49: 40364.41 | G49: 30760.24 | H49: 34726.78 | I49: 31341.79 | J49: 33567.21 | K49: 130396.02 | L49: 32157.99 | M49: 34889.6 | N49: 37204.92 | O49: 50094.67 | P49: 154347.18 | Q49: 41354.84 | R49: 49900.4 | S49: 44736.91 | T49: 60286.73 | U49: 196278.88 | V49: 55639.79 | W49: 56326.02 | X49: 61532.72 | Y49: 56596.3 | Z49: 230094.83 | AA49: 50896.45 | AB49: 70834.32
A50: 1 | C50: 매출원가 | E50: 36747.87 | G50: 30070.79 | H50: 33536.53 | I50: 28341.51 | J50: 36789.4 | K50: 128738.23 | L50: 30291.59 | M50: 31955.58 | N50: 32852.99 | O50: 44055.93 | P50: 139156.09 | Q50: 35900.87 | R50: 42994.71 | S50: 38709.68 | T50: 49486.31 | U50: 167091.57 | V50: 44410 | W50: 47924.64 | X50: 50918.09 | Y50: 44639.94 | Z50: 187892.67 | AA50: 41209.13 | AB50: 58218.05
A51: 1 | C51: 매출총이익 | E51: 3616.54 | G51: 689.45 | H51: 1190.25 | I51: 3000.29 | J51: -3222.19 | K51: 1657.8 | L51: 1866.4 | M51: 2934.02 | N51: 4351.93 | O51: 6038.73 | P51: 15191.08 | Q51: 5453.97 | R51: 6905.69 | S51: 6027.22 | T51: 10800.42 | U51: 29187.3 | V51: 11229.79 | W51: 8401.38 | X51: 10614.62 | Y51: 11956.35 | Z51: 42202.14 | AA51: 9687.32 | AB51: 12616.27
A52: 1 | C52: 판관비 | E52: 3085.13 | G52: 2415.14 | H52: 3102.41 | I52: 2635.02 | J52: 3390.87 | K52: 11543.44 | L52: 2797.12 | M52: 2667.08 | N52: 2631.94 | O52: 3360.53 | P52: 11456.67 | Q52: 3075.92 | R52: 3843.8 | S52: 3112.1 | T52: 3469.18 | U52: 13501 | V52: 5518.86 | W52: 2619.31 | X52: 2871.29 | Y52: 4132.21 | Z52: 15141.67 | AA52: 3413.12 | AB52: 5057.11
A53: 1 | C53: 영업이익 | E53: 531.42 | G53: -1725.69 | H53: -1912.15 | I53: 365.27 | J53: -6613.06 | K53: -9885.63 | L53: -930.71 | M53: 266.94 | N53: 1720 | O53: 2678.21 | P53: 3734.44 | Q53: 2378.05 | R53: 3061.89 | S53: 2915.12 | T53: 7331.24 | U53: 15686.3 | V53: 5710.93 | W53: 5782.07 | X53: 7743.34 | Y53: 7824.14 | Z53: 27060.48 | AA53: 6274.2 | AB53: 7559.16
A54: 1 | C54: 기타영업외수익 | E54: 79.11 | G54: 165.16 | H54: 117.17 | I54: 172.53 | J54: 166.44 | K54: 621.3 | L54: 309.79 | M54: 176.41 | N54: 356.42 | O54: 218.39 | P54: 1061.01 | Q54: 184.46 | R54: 298.71 | S54: 203.08 | T54: 226.13 | U54: 912.38 | V54: 634.87 | W54: 366 | X54: 690.73 | Y54: 726.29 | Z54: 2417.89 | AA54: 258.7 | AB54: 274.29
A55: 1 | C55: 기타영업외비용 | E55: 17.83 | G55: 1.85 | H55: 43.95 | I55: 2.35 | J55: 365.85 | K55: 414 | L55: 4.22 | M55: 501.53 | N55: 2.85 | O55: 547.01 | P55: 1055.61 | Q55: 1.89 | R55: 36.76 | S55: -13.38 | T55: -5.08 | U55: 20.19 | V55: 38.95 | W55: 435.88 | X55: -1.56 | Y55: -314.19 | Z55: 159.08 | AA55: 3.43 | AB55: 26.62
A56: 1 | C56: 금융수익 | E56: 1758.44 | G56: 745.51 | H56: 1590.89 | I56: 2689.87 | J56: -413.83 | K56: 4612.44 | L56: 3004.21 | M56: 1359.21 | N56: 1757.84 | O56: 1730.32 | P56: 7851.58 | Q56: 2374.1 | R56: 1965.52 | S56: 471.25 | T56: 4476.67 | U56: 9287.54 | V56: 1160.91 | W56: 1143.52 | X56: 1130.23 | Y56: 1471.3 | Z56: 4905.96 | AA56: 3106.81 | AB56: 2215.93
A57: 1 | C57: 금융비용 | E57: 141.59 | G57: 1218.39 | H57: 1921.66 | I57: 844.56 | J57: 2268.05 | K57: 6252.66 | L57: 265.84 | M57: 273.59 | N57: 88.41 | O57: 1161.81 | P57: 1789.65 | Q57: 357.38 | R57: 142.15 | S57: 647.28 | T57: 527.76 | U57: 1674.57 | V57: 294.34 | W57: 2754.1 | X57: -772.51 | Y57: 1487.71 | Z57: 3763.64 | AA57: 396.7 | AB57: 414.71
A58: 1 | C58: 법인세비용차감전계속사업이익 | E58: 2209.55 | G58: -2035.26 | H58: -2169.71 | I58: 2380.77 | J58: -9494.35 | K58: -11318.55 | L58: 2121.66 | M58: 1027.43 | N58: 3743 | O58: 2918.09 | P58: 9810.18 | Q58: 4577.35 | R58: 5147.21 | S58: 2955.55 | T58: 11511.36 | U58: 24191.47 | V58: 7173.42 | W58: 4973.36 | X58: 10335.24 | Y58: 8057.49 | Z58: 30539.51 | AA58: 9239.57 | AB58: 9608.06
A59: 1 | C59: 법인세비용 | E59: -208.3 | G59: -426.36 | H59: -1270.07 | I59: 499.01 | J59: -2624.79 | K59: -3822.21 | L59: 411.75 | M59: 62.87 | N59: 749.85 | O59: 206.94 | P59: 1431.41 | Q59: 884.23 | R59: 949.2 | S59: 427.64 | T59: 2330.9 | U59: 4591.97 | V59: 1431.51 | W59: 538.98 | X59: 2264.86 | Y59: 1514.78 | Z59: 5750.13 | AA59: 1971.25 | AB59: 1943.64
A60: 1 | C60: 당기순이익 | E60: 2417.85 | G60: -1608.9 | H60: -899.64 | I60: 1881.75 | J60: -6869.56 | K60: -7496.35 | L60: 1709.92 | M60: 964.56 | N60: 2993.16 | O60: 2711.16 | P60: 8378.8 | Q60: 3693.11 | R60: 4198.01 | S60: 2527.91 | T60: 9180.46 | U60: 19599.49 | V60: 5741.91 | W60: 4434.38 | X60: 8070.38 | Y60: 6542.72 | Z60: 24789.39 | AA60: 7268.32 | AB60: 7664.42
A61: 1 | C61: 총포괄손익 | E61: 2588.24 | G61: -1689.76 | H61: -812.69 | I61: 2022.82 | J61: -6874.11 | K61: -7353.74 | L61: 1614.17 | M61: 951.9 | N61: 2993.16 | O61: 2559 | P61: 8118.23 | Q61: 3693.11 | R61: 4300.31 | S61: 2527.91 | T61: 8980.6 | U61: 19501.93 | V61: 5741.91 | W61: 4279.86 | X61: 8070.38 | Y61: 6403.63 | Z61: 24495.78 | AA61: 7268.32 | AB61: 7663.55
A62: 1 | C62: (지배주주지분)당기순이익 | E62: 2417.85 | G62: -1608.9 | H62: -899.64 | I62: 1881.75 | J62: -6869.56 | K62: -7496.35 | L62: 1709.92 | M62: 964.56 | N62: 2993.16 | O62: 2711.16 | P62: 8378.8 | Q62: 3693.11 | R62: 4198.01 | S62: 2527.91 | T62: 9180.46 | U62: 19599.49 | V62: 5741.91 | W62: 4434.38 | X62: 8070.38 | Y62: 6542.72 | Z62: 24789.39 | AA62: 7268.32
A63: 1 | C63: 금융손익 | E63: 1616.85 | G63: -472.88 | H63: -330.77 | I63: 1845.31 | J63: -2681.88 | K63: -1640.22 | L63: 2738.37 | M63: 1085.62 | N63: 1669.43 | O63: 568.51 | P63: 6061.93 | Q63: 2016.72 | R63: 1823.37 | S63: -176.03 | T63: 3948.91 | U63: 7612.97 | V63: 866.57 | W63: -1610.58 | X63: 1902.74 | Y63: -16.41 | Z63: 1142.32 | AA63: 2710.11 | AB63: 1801.22
A64: 1 | C64: 기타영업외손익 | E64: 61.28 | G64: 163.31 | H64: 73.22 | I64: 170.18 | J64: -199.41 | K64: 207.3 | L64: 305.57 | M64: -325.12 | N64: 353.57 | O64: -328.62 | P64: 5.4 | Q64: 182.57 | R64: 261.95 | S64: 216.46 | T64: 231.21 | U64: 892.19 | V64: 595.92 | W64: -69.88 | X64: 692.29 | Y64: 1040.48 | Z64: 2258.81 | AA64: 255.27 | AB64: 247.67
A65: 1 | C65: 계속사업이익 | E65: 2417.85 | G65: -1608.9 | H65: -899.64 | I65: 1881.75 | J65: -6869.56 | K65: -7496.35 | L65: 1709.92 | M65: 964.56 | N65: 2993.16 | O65: 2711.16 | P65: 8378.8 | Q65: 3693.11 | R65: 4198.01 | S65: 2527.91 | T65: 9180.46 | U65: 19599.49 | V65: 5741.91 | W65: 4434.38 | X65: 8070.38 | Y65: 6542.72 | Z65: 24789.39 | AA65: 7268.32 | AB65: 7664.42
A66: 1 | C66: 이자수익 | G66: 412.62 | L66: 761.67 | Q66: 1077.16 | V66: 733.36 | W66: 799.23 | AB66: 801.82
A67: 1 | C67: 이자비용 | G67: 4.49 | L67: 3.51
A68: 1 | C68: 이자손익 | G68: 408.13 | L68: 758.16
A69: 1 | C69: (비지배주주지분)당기순이익 | AA69: 0 | AB69: 0
A70: 1 | C70: 영업활동으로인한현금흐름 | E70: -2021.08 | G70: -2106.41 | H70: -1064.97 | I70: 3475.43 | J70: 1252.2 | K70: 1556.25 | L70: -1921.42 | M70: 10344.92 | N70: -5291.58 | O70: 20819.54 | P70: 23951.46 | Q70: -5922.09 | R70: 852.43 | S70: 2627.91 | T70: -1822.15 | U70: -4263.9 | V70: -684.32 | W70: 5477.81 | X70: -1425.65 | Y70: 12197.11 | Z70: 15564.95 | AA70: -1071.33 | AB70: 13163.98
A71: 1 | C71: 감가상각비 | E71: 873.66 | G71: 890.37 | H71: 935.65 | I71: 909.11 | J71: 903.46 | K71: 3638.59 | L71: 1018.41 | M71: 1026 | S71: 1274.43
A72: 1 | C72: 무형자산상각비 | E72: 286.54 | G72: 64.31 | H72: 64.67 | I72: 70.65 | J72: 71.55 | K72: 271.18 | L72: 66.24 | M72: 69.7 | S72: 24.42
A73: 1 | C73: 배당금수취(CF) | E73: 24.13 | G73: 0 | H73: 0.16 | I73: 0 | J73: 0 | K73: 0.16 | N73: 0 | O73: 0 | V73: 0
A74: 1 | C74: 법인세납부(CF) | E74: 380.97 | G74: -51.17 | H74: 1078.28 | I74: -4.15 | J74: 178.33 | K74: 1201.29 | L74: -162.56 | M74: 161.75 | N74: -122.81 | O74: -130.4 | P74: -254.02 | Q74: -143.69 | R74: -139.11 | S74: -130.96 | T74: -134.36 | U74: -548.12 | V74: -1463.8 | W74: -1662.06 | X74: -910.35 | Y74: -692.93 | Z74: -4729.14 | AA74: -2628.39 | AB74: -3268.93
A75: 1 | C75: 투자활동으로인한현금흐름 | E75: -9118.13 | G75: -8931.38 | H75: -1454.67 | I75: -1729.73 | J75: -1660.56 | K75: -13776.34 | L75: -1998.76 | M75: -4132.58 | N75: -6298.03 | O75: -3875.81 | P75: -16305.18 | Q75: -2651.72 | R75: -2828.43 | S75: -790.13 | T75: -2556.5 | U75: -8826.78 | V75: 1089.33 | W75: -3797.75 | X75: -1999.43 | Y75: -1251.82 | Z75: -5959.67 | AA75: -1962.85 | AB75: -8154.67
A76: 1 | C76: 유형자산의감소 | E76: 31.27 | G76: 493.39 | H76: 52.65 | J76: 3.63 | L76: 0 | M76: 15.23 | N76: 100.2 | O76: 7.69 | P76: 123.12 | Q76: 1 | R76: 15.37 | S76: 3.15 | T76: 0 | U76: 19.52 | V76: 2.73 | W76: 5.28 | X76: 0.34 | Y76: 6.48 | Z76: 14.83 | AA76: 3.7 | AB76: 1.46
A77: 1 | C77: 유형자산의증가 | E77: 4117.28 | G77: 4224.3 | H77: 1707.59 | I77: 1377.17 | J77: 593.84 | K77: 7902.9 | L77: 478.92 | M77: 4775.9 | N77: 3064.44 | O77: 2557.4 | P77: 10876.66 | Q77: 360.45 | R77: 2282.96 | S77: 592.94 | T77: 1931.61 | U77: 5167.96 | V77: 1884.92 | W77: 3191.58 | X77: 1062.93 | Y77: 1099.92 | Z77: 7239.35 | AA77: 1585.4 | AB77: 7225.51
A78: 1 | C78: CAPEX | E78: 4117.28 | G78: 4224.3 | H78: 1707.59 | I78: 1377.17 | J78: 593.84 | K78: 7902.9 | L78: 478.92 | M78: 4775.9 | N78: 3064.44 | O78: 2557.4 | P78: 10876.66 | Q78: 360.45 | R78: 2282.96 | S78: 592.94 | T78: 1931.61 | U78: 5167.96 | V78: 1884.92 | W78: 3665.39 | X78: 650.64 | Y78: 1038.4 | Z78: 7239.35 | AA78: 1585.4 | AB78: 7225.51
A79: 1 | C79: 재무활동으로인한현금흐름 | E79: 293.26 | G79: -53.22 | H79: 1885.67 | I79: 54.81 | J79: 37.69 | K79: 1924.95 | L79: -52.06 | M79: 1631.23 | N79: 1437.69 | O79: 709.11 | P79: 3725.97 | Q79: -34.18 | R79: 4797.94 | S79: 538.13 | T79: 2028.97 | U79: 7330.86 | V79: 2595.38 | W79: -3627.7 | X79: 6048.52 | Y79: -5809.48 | Z79: -793.28 | AA79: 1716.66 | AB79: -3594
A80: 1 | C80: 이자지급(CF) | E80: -5.23 | G80: -4.49 | H80: 4.49 | I80: -12.57 | J80: -3.59 | K80: -16.16 | L80: -3.28 | M80: -2.99 | N80: -2.7 | O80: -2.41 | P80: -11.38 | Q80: -2.11 | R80: -1.82 | S80: -1.52 | T80: -3.41 | U80: -8.86 | V80: -1.44 | W80: 1.44 | X80: 0 | Y80: 0 | Z80: 0 | AA80: 0
A81: 1 | C81: 리스부채의상환 | E81: 53.91 | G81: 48.72 | H81: 49 | I81: 49.3 | J81: 50.22 | K81: 197.24 | L81: 48.78 | M81: 49.1 | N81: 49.42 | O81: 49.74 | P81: 197.04 | Q81: 50.07 | R81: 50.39 | S81: 50.73 | T81: 75.12 | U81: 226.31 | V81: 46.17 | W81: 68.74 | X81: 37.09 | Y81: 108.83 | Z81: 260.83 | AA81: 53.34 | AB81: 84.68
A82: 1 | C82: 배당금지급 | E82: 0 | I82: 0 | J82: 0 | N82: 0 | O82: 0 | X82: 0 | Y82: 0
A83: 1 | C83: 자기주식의취득 | E83: 0
A84: 1 | C84: 현금및현금성자산의증감 | E84: -10920.66 | G84: -11121.84 | H84: -649.49 | I84: 2507.94 | J84: -1292.4 | K84: -10555.79 | L84: -3661.85 | M84: 7746.88 | N84: -10010.3 | O84: 17335.9 | P84: 11410.63 | Q84: -8299.34 | R84: 3072.16 | S84: 1812.24 | T84: -929.74 | U84: -4344.68 | V84: 3064.69 | W84: -2901.93 | X84: 3024.57 | Y84: 5309.75 | Z84: 8497.08 | AA84: -258.74 | AB84: 1065.06
A85: 1 | C85: 기말현금및현금성자산 | E85: -10920.67 | G85: 27317.76 | H85: -649.49 | I85: 2507.95 | J85: -1292.4 | K85: 27883.82 | L85: 24221.97 | M85: 7746.87 | N85: -10010.3 | O85: 17335.9 | P85: 39294.44 | Q85: 30995.1 | R85: 3072.17 | S85: 1812.23 | T85: -929.74 | U85: 34949.76 | V85: 38014.46 | W85: -2901.94 | X85: 3024.58 | Y85: 5309.74 | Z85: 43446.84 | AA85: 43188.11 | AB85: 1065.06
A86: 1 | C86: 이자수취(CF) | O86: 819.29 | Q86: 1038.7 | R86: 795 | S86: 846.61 | T86: 881.49 | U86: 3561.8 | V86: 549.9 | W86: 892.44 | X86: 822.8 | Y86: 612.28 | Z86: 2877.42 | AA86: 642.38 | AB86: 849.44

Sheet BS별도
B1: (백만원) | C1: 이름: BS별도H | E1: 4Q21 | F1: 2021 | G1: 1Q22 | H1: 2Q22 | I1: 3Q22 | J1: 4Q22 | K1: 2022 | L1: 1Q23 | M1: 2Q23 | N1: 3Q23 | O1: 4Q23 | P1: 2023 | Q1: 1Q24 | R1: 2Q24 | S1: 3Q24 | T1: 4Q24 | U1: 2024 | V1: 1Q25 | W1: 2Q25 | X1: 3Q25 | Y1: 4Q25 | Z1: 2025 | AA1: 1Q26 | AB1: 2Q26 | AC1: 3Q26 | AD1: 4Q26 | AE1: 2026 | AF1: 1Q27 | AG1: 2Q27 | AH1: 3Q27 | AI1: 4Q27 | AJ1: 2027 | AK1: 1Q28 | AL1: 2Q28 | AM1: 3Q28 | AN1: 4Q28 | AO1: 2028
B2: 별도 | D2: fin json(kship_fin.py)
B3: 대양전기공업(별) | C3: UPDATE: 26-10-26 | E3: 1 | F3: 2 | G3: 3 | H3: 4 | I3: 5 | J3: 6 | K3: 7 | L3: 8 | M3: 9 | N3: 10 | O3: 11 | P3: 12 | Q3: 13 | R3: 14 | S3: 15 | T3: 16 | U3: 17 | V3: 18 | W3: 19 | X3: 20 | Y3: 21 | Z3: 22 | AA3: 23 | AB3: 24 | AC3: 25 | AD3: 26 | AE3: 27 | AF3: 28 | AG3: 29 | AH3: 30 | AI3: 31 | AJ3: 32 | AK3: 33 | AL3: 34 | AM3: 35 | AN3: 36 | AO3: 37
B4: Account Code | C4: AccountNAME | E4: 2021.12 | F4: 2021.12A | G4: 2022.03 | H4: 2022.06 | I4: 2022.09 | J4: 2022.12 | K4: 2022.12A | L4: 2023.03 | M4: 2023.06 | N4: 2023.09 | O4: 2023.12 | P4: 2023.12A | Q4: 2024.03 | R4: 2024.06 | S4: 2024.09 | T4: 2024.12 | U4: 2024.12A | V4: 2025.03 | W4: 2025.06 | X4: 2025.09 | Y4: 2025.12 | Z4: 2025.12A | AA4: 2026.03 | AB4: 2026.06 | AC4: 2026.09 | AD4: 2026.12 | AE4: 2026.12A | AF4: 2027.03 | AG4: 2027.06 | AH4: 2027.09 | AI4: 2027.12 | AJ4: 2027.12A | AK4: 2028.03 | AL4: 2028.06 | AM4: 2028.09 | AN4: 2028.12 | AO4: 2028.12A
A5: 1 | C5: 유동자산 | E5: 97172.65 | F5: 97172.65 | G5: 102530.55 | H5: 104020.24 | I5: 108327.68 | J5: 106215.92 | K5: 106215.92 | L5: 112621.69 | M5: 121892.71 | N5: 120413.22 | O5: 131349.45 | P5: 131349.45 | Q5: 132983.35 | R5: 136910.05 | S5: 135894.9 | T5: 150078.23 | U5: 150078.23 | V5: 165809.25 | W5: 182890.62 | X5: 184723.35 | Y5: 186662.15 | Z5: 186662.15 | AA5: 205524.86 | AB5: 181961.11
A6: 1 | C6: 현금및현금성자산 | E6: 36607.43 | F6: 36607.43 | G6: 22415.6 | H6: 22021.35 | I6: 25178.13 | J6: 21659.58 | K6: 21659.58 | L6: 20035.41 | M6: 25451.96 | N6: 17921.71 | O6: 29984.55 | P6: 29984.55 | Q6: 24578.62 | R6: 29218.42 | S6: 29322.15 | T6: 30793.59 | U6: 30793.59 | V6: 32180.7 | W6: 27156.16 | X6: 34691.89 | Y6: 39287.94 | Z6: 39287.94 | AA6: 39719.24 | AB6: 33239.97
A7: 1 | C7: 매출채권및기타채권 | E7: 17897.47 | F7: 17897.47 | G7: 20591.17 | H7: 20041.38 | I7: 17469.51 | J7: 18129.7 | K7: 18129.7 | L7: 21528.18 | M7: 21149.99 | N7: 23078.92 | O7: 25462.94 | P7: 25462.94 | Q7: 22424.26 | R7: 23138.37 | S7: 23559.18 | T7: 32328.7 | U7: 32328.7 | V7: 35943.19 | W7: 35172.95 | X7: 31596.91 | Y7: 32859.08 | Z7: 32859.08 | AA7: 30969.12 | AB7: 43577.38
A8: 1 | C8: 단기투자자산(공정가치) | E8: 4185.91 | F8: 4185.91 | G8: 4275.47 | H8: 6559.14 | I8: 7250.59 | J8: 10352.3 | K8: 10352.3 | L8: 10706.2 | M8: 10835 | N8: 8371.18 | O8: 4097.66 | P8: 4097.66 | Q8: 4281.83 | R8: 4466.09 | S8: 4288.21 | T8: 12155.52 | U8: 12155.52 | V8: 24521.68 | W8: 38933.25 | X8: 34460.12 | Y8: 34769.73 | Z8: 34769.73 | AA8: 40501.05 | AB8: 19876.64
A9: 1 | C9: 기타유동금융자산 | E9: 7924.02 | F9: 7924.02 | G9: 26053.09 | H9: 26141.43 | I9: 26208.01 | J9: 27338.3 | K9: 27338.3 | L9: 27489.55 | M9: 27142.21 | N9: 27311.73 | O9: 27025.47 | P9: 27025.47 | Q9: 27246.94 | R9: 27459.82 | S9: 27670.39 | T9: 27890.26 | U9: 27890.26 | V9: 28128.24 | W9: 28592.47 | X9: 32626.91 | Y9: 32752.46 | Z9: 32752.46 | AA9: 32878.85 | AB9: 32884.83
A10: 1 | C10: 당기법인세자산(선급법인세) | E10: 423.54 | F10: 423.54 | G10: 423.54 | H10: 105.24 | I10: 163.09 | J10: 240.55 | K10: 240.55 | L10: 397.28 | M10: 273.19 | N10: 351.91 | O10: 2.45 | P10: 2.45 | Q10: 2.45 | R10: 0 | S10: 0 | T10: 0 | U10: 0 | Y10: 0 | Z10: 0 | AA10: 0
A11: 1 | C11: 재고자산 | E11: 26699.72 | F11: 26699.72 | G11: 24665.28 | H11: 25399.1 | I11: 28173.54 | J11: 23035.99 | K11: 23035.99 | L11: 26098.23 | M11: 31202.1 | N11: 35096.88 | O11: 35944.53 | P11: 35944.53 | Q11: 41530.27 | R11: 39486.88 | S11: 39695.24 | T11: 35108.31 | U11: 35108.31 | V11: 37816.22 | W11: 39994.42 | X11: 36993.11 | Y11: 32674.91 | Z11: 32674.91 | AA11: 45381.18 | AB11: 40269.66
A12: 1 | C12: 매각예정비유동자산및처분자산 | E12: 0 | F12: 0 | J12: 0 | K12: 0 | L12: 0
A13: 1 | C13: 비유동자산 | E13: 144259.07 | F13: 144259.07 | G13: 134398.19 | H13: 134025.69 | I13: 133693.72 | J13: 132870.06 | K13: 132870.06 | L13: 133144.53 | M13: 137123.73 | N13: 140917.65 | O13: 144350.37 | P13: 144350.37 | Q13: 143607.76 | R13: 146306.52 | S13: 144885.84 | T13: 139692.58 | U13: 139692.58 | V13: 126029.11 | W13: 114345.29 | X13: 114593.24 | Y13: 113487.44 | Z13: 113487.44 | AA13: 107459.24 | AB13: 148609.85
A14: 1 | C14: 장기매출채권및기타채권 | E14: 813.69 | F14: 813.69 | G14: 924.67 | H14: 1230.12 | I14: 1484.21 | J14: 81.14 | K14: 81.14 | L14: 37.83 | M14: 104.49 | N14: 177.2 | O14: 726.05 | P14: 726.05 | Q14: 1009.24 | R14: 1930.09 | S14: 611.43 | T14: 1662.41 | U14: 1662.41 | V14: 606.57 | W14: 1060.04 | X14: 1083.31 | Y14: 809.54 | Z14: 809.54 | AA14: 922.35 | AB14: 1030.21
A15: 1 | C15: 장기금융자산 | E15: 39580.42 | F15: 39580.42 | G15: 43530.27 | H15: 41513.64 | I15: 41430.44 | J15: 40848.41 | K15: 40848.41 | L15: 42052.96 | M15: 42485.39 | N15: 44945.98 | O15: 46172.47 | P15: 46172.47 | Q15: 46611.11 | R15: 47017.92 | S15: 47142.73 | T15: 41014.85 | U15: 41014.85 | V15: 27082.82 | W15: 12218.02 | X15: 12911.72 | Y15: 13921.85 | Z15: 13921.85 | AA15: 8949.14 | AB15: 9481.4
A16: 1 | C16: 투자자산 | E16: 47580.42 | F16: 47580.42 | G16: 51530.27 | H16: 49513.64 | I16: 49430.44 | J16: 48848.41 | K16: 48848.41 | L16: 50052.96 | M16: 50485.39 | N16: 52945.98 | O16: 54172.47 | P16: 54172.47 | Q16: 54611.11 | R16: 55017.92 | S16: 55142.73 | T16: 49014.85 | U16: 49014.85 | V16: 35082.82 | W16: 20218.02 | X16: 20911.72 | Y16: 21921.85 | Z16: 21921.85 | AA16: 16949.14 | AB16: 49436.48
A17: 1 | C17: 종속기업및관계기업투자 | E17: 8000 | F17: 8000 | G17: 8000 | H17: 8000 | I17: 8000 | J17: 8000 | K17: 8000 | L17: 8000 | M17: 8000 | N17: 8000 | O17: 8000 | P17: 8000 | Q17: 8000 | R17: 8000 | S17: 8000 | T17: 8000 | U17: 8000 | V17: 8000 | W17: 8000 | X17: 8000 | Y17: 8000 | Z17: 8000 | AA17: 8000 | AB17: 39955.08
A18: 1 | C18: 유형자산 | E18: 70528 | F18: 70528 | G18: 74046.16 | H18: 75007.48 | I18: 75040.81 | J18: 74727.63 | K18: 74727.63 | L18: 74299.91 | M18: 77956.76 | N18: 79991.79 | O18: 81179.59 | P18: 81179.59 | Q18: 80387.2 | R18: 81383.59 | S18: 80801.12 | T18: 77890 | U18: 77890 | V18: 78572.48 | W18: 70839.6 | X18: 70452.2 | Y18: 67447.06 | Z18: 67447.06 | AA18: 67153.91 | AB18: 74798.1
A19: 1 | C19: 투자부동산 | E19: 1876.49 | F19: 1876.49 | G19: 1863.36 | H19: 1850.22 | I19: 1837.08 | J19: 1906.88 | K19: 1906.88 | L19: 1897.7 | M19: 1888.53 | N19: 1879.36 | O19: 1870.19 | P19: 1870.19 | Q19: 1861.01 | R19: 1851.84 | S19: 1842.67 | T19: 5487.18 | U19: 5487.18 | V19: 5470.99 | W19: 15642.89 | X19: 15623.2 | Y19: 18244.34 | Z19: 18244.34 | AA19: 18210.59 | AB19: 18190.73
A20: 1 | C20: 무형자산 | E20: 1410.97 | F20: 1410.97 | G20: 1354.67 | H20: 1293.55 | I20: 1263.99 | J20: 1212.83 | K20: 1212.83 | L20: 1150.79 | M20: 1101.94 | N20: 1040.07 | O20: 993.78 | P20: 993.78 | Q20: 981.19 | R20: 961.1 | S20: 952.46 | T20: 943.05 | U20: 943.05 | V20: 947.13 | W20: 1250.01 | X20: 1241.37 | Y20: 1244.76 | Z20: 1244.76 | AA20: 1251.67 | AB20: 1270.71
A21: 1 | C21: 이연법인세자산 | E21: 802.05 | F21: 802.05 | G21: 1284.25 | H21: 1731.67 | I21: 1233.96 | J21: 3762.71 | K21: 3762.71 | L21: 3392.41 | M21: 3217.04 | N21: 2544.4 | O21: 2882.6 | P21: 2882.6 | Q21: 2316.57 | R21: 2461.18 | S21: 2689.66 | T21: 1967.58 | U21: 1967.58 | V21: 2803.15 | W21: 2987.19 | X21: 2908.61 | Y21: 3418.23 | Z21: 3418.23 | AA21: 2634.51 | AB21: 3522.74
A22: 1 | C22: 자산총계 | E22: 241431.73 | F22: 241431.73 | G22: 236928.74 | H22: 238045.93 | I22: 242021.41 | J22: 239085.99 | K22: 239085.99 | L22: 245766.22 | M22: 259016.44 | N22: 261330.87 | O22: 275699.82 | P22: 275699.82 | Q22: 276591.11 | R22: 283216.57 | S22: 280780.74 | T22: 289770.81 | U22: 289770.81 | V22: 291838.36 | W22: 297235.91 | X22: 299316.59 | Y22: 300149.59 | Z22: 300149.59 | AA22: 312984.1 | AB22: 330570.96
A23: 1 | C23: 유동부채 | E23: 23726.09 | F23: 23726.09 | G23: 21903.97 | H23: 24245.92 | I23: 26466.13 | J23: 30018 | K23: 30018 | L23: 35307.28 | M23: 48152.46 | N23: 47989.91 | O23: 59956.38 | P23: 59956.38 | Q23: 57239.05 | R23: 59647.1 | S23: 55010.77 | T23: 54592.39 | U23: 54592.39 | V23: 52506.68 | W23: 53217.08 | X23: 47531.54 | Y23: 41767.89 | Z23: 41767.89 | AA23: 49737.36 | AB23: 59055.91
A24: 1 | C24: 매입채무및기타채무 | E24: 12528.12 | F24: 12528.12 | G24: 12527.52 | H24: 11542.38 | I24: 12005.87 | J24: 10024.45 | K24: 10024.45 | L24: 12301.5 | M24: 13375.88 | N24: 13126.53 | O24: 16048.64 | P24: 16048.64 | Q24: 14694.96 | R24: 15453.44 | S24: 14105.37 | T24: 17868.25 | U24: 17868.25 | V24: 18520.94 | W24: 22080.58 | X24: 18905.12 | Y24: 16596.13 | Z24: 16596.13 | AA24: 26542.28 | AB24: 23857.82
... A27: 1 | C27: 단기금융부채 | E27: 197.24 | F27: 197.24 | G27: 193.24 | H27: 189.25 | I27: 185.25 | J27: 180.62 | K27: 180.62 | L27: 181.78 | M27: 182.96 | N27: 184.14 | O27: 185.33 | P27: 185.33 | Q27: 186.52 | R27: 187.73 | S27: 188.94 | T27: 194.52 | U27: 194.52 | V27: 144.01 | W27: 90.75 | X27: 35.06 | Y27: 228.13 | Z27: 228.13 | AA27: 221.64 | AB27: 241.13
A28: 1 | C28: 당기법인세부채(미지급법인세) | E28: 0 | F28: 0 | J28: 0 | K28: 0 | L28: 0 | Q28: 178.14 | R28: 1109.07 | S28: 1640.07 | T28: 3186.94 | U28: 3186.94 | V28: 3841.17 | W28: 2948.23 | X28: 4204.01 | Y28: 5509.96 | Z28: 5509.96 | AA28: 4009.33 | AB28: 3723.49
A29: 1 | C29: 비유동부채 | E29: 834.07 | F29: 834.07 | G29: 789.35 | H29: 822.34 | I29: 777.05 | J29: 911.04 | K29: 911.04 | L29: 912.21 | M29: 913.07 | N29: 913.64 | O29: 928.18 | P29: 928.18 | Q29: 913.22 | R29: 897.95 | S29: 882.38 | T29: 900.88 | U29: 900.88 | V29: 895.38 | W29: 814.22 | X29: 813.05 | Y29: 1012.33 | Z29: 1012.33 | AA29: 939.53 | AB29: 997.59
A30: 1 | C30: 기타비유동금융부채 | E30: 310 | F30: 310 | G30: 310 | H30: 388 | I30: 388 | J30: 388 | K30: 388 | L30: 388 | M30: 388 | Y30: 290 | Z30: 290 | AA30: 270 | AB30: 360
A31: 1 | C31: 장기금융부채 | E31: 834.07 | F31: 834.07 | G31: 789.35 | H31: 822.34 | I31: 777.05 | J31: 731.45 | K31: 731.45 | L31: 685.57 | M31: 639.39 | N31: 204.91 | O31: 158.13 | P31: 158.13 | Q31: 111.04 | R31: 63.66 | S31: 15.97 | T31: 9.83 | U31: 9.83 | V31: 4.33 | W31: 1.16 | X31: 0 | Y31: 453.37 | Z31: 453.37 | AA31: 380.57 | AB31: 453.43
A32: 1 | C32: 비유동리스부채 | E32: 524.07 | F32: 524.07 | G32: 479.35 | H32: 434.34 | I32: 389.05 | J32: 343.45 | K32: 343.45 | L32: 297.57 | M32: 251.39 | N32: 204.91 | O32: 158.13 | P32: 158.13 | Q32: 111.04 | R32: 63.66 | S32: 15.97 | T32: 9.83 | U32: 9.83 | V32: 4.33 | W32: 1.16 | X32: 0 | Y32: 163.37 | Z32: 163.37 | AA32: 110.57 | AB32: 93.43
A33: 1 | C33: 부채총계 | E33: 24560.17 | F33: 24560.17 | G33: 22693.32 | H33: 25068.26 | I33: 27243.18 | J33: 30929.05 | K33: 30929.05 | L33: 36219.49 | M33: 49065.53 | N33: 48903.56 | O33: 60884.57 | P33: 60884.57 | Q33: 58152.27 | R33: 60545.06 | S33: 55893.15 | T33: 55493.28 | U33: 55493.28 | V33: 53402.06 | W33: 54031.3 | X33: 48344.6 | Y33: 42780.22 | Z33: 42780.22 | AA33: 50676.89 | AB33: 60053.51
A34: 1 | C34: 자본금 | E34: 4783.67 | F34: 4783.67 | G34: 4783.67 | H34: 4783.67 | I34: 4783.67 | J34: 4783.67 | K34: 4783.67 | L34: 4783.67 | M34: 4783.67 | N34: 4783.67 | O34: 4783.67 | P34: 4783.67 | Q34: 4783.67 | R34: 4783.67 | S34: 4783.67 | T34: 4783.67 | U34: 4783.67 | V34: 4783.67 | W34: 4783.67 | X34: 4783.67 | Y34: 4783.67 | Z34: 4783.67 | AA34: 4783.67 | AB34: 4783.67
A35: 1 | C35: 자본잉여금 | E35: 24958.68 | F35: 24958.68 | G35: 24974.84 | H35: 24977.78 | I35: 24977.78 | J35: 24978.48 | K35: 24978.48 | L35: 25026.82 | M35: 25034.91 | N35: 25034.91 | O35: 25035.47 | P35: 25035.47 | Q35: 25048.84 | R35: 25053.11 | S35: 25053.11 | T35: 25053.11 | U35: 25053.11 | V35: 25053.11 | W35: 25086.07 | X35: 25086.07 | Y35: 25272.22 | Z35: 25272.22 | AA35: 25272.22 | AB35: 25536.36
A36: 1 | C36: 기타자본 | E36: -2586.62 | F36: -2586.62 | G36: -2597.23 | H36: -2562.52 | I36: -2554.74 | J36: -2541.49 | K36: -2541.49 | L36: -2581.8 | M36: -3490.35 | N36: -3523.92 | O36: -3508.07 | P36: -3508.07 | Q36: -3509.47 | R36: -3471.66 | S36: -3455.64 | T36: -3436.7 | U36: -3436.7 | V36: -3419.11 | W36: -3374.2 | X36: -3334.46 | Y36: -3296.14 | Z36: -3296.14 | AA36: -3296.14 | AB36: -2920.76
A37: 1 | C37: 기타포괄이익누계액 | E37: 9330.27 | F37: 9330.27 | G37: 9330.27 | H37: 9330.27 | I37: 9330.27 | J37: 9330.27 | K37: 9330.27 | L37: 9330.27 | M37: 9330.27 | N37: 9330.27 | O37: 9330.27 | P37: 9330.27 | Q37: 9330.27 | R37: 9330.27 | S37: 9330.27 | T37: 9330.27 | U37: 9330.27 | V37: 9330.27 | W37: 9330.27 | X37: 9330.27 | Y37: 9330.27 | Z37: 9330.27 | AA37: 9330.27 | AB37: 9330.27
A38: 1 | C38: 이익잉여금 | E38: 180385.56 | F38: 180385.56 | G38: 177743.87 | H38: 176448.47 | I38: 178241.25 | J38: 171606.02 | K38: 171606.02 | L38: 172987.78 | M38: 174292.42 | N38: 176802.39 | O38: 179173.92 | P38: 179173.92 | Q38: 182785.54 | R38: 186976.13 | S38: 189176.18 | T38: 198547.19 | U38: 198547.19 | V38: 202688.36 | W38: 207378.81 | X38: 215106.46 | Y38: 221279.35 | Z38: 221279.35 | AA38: 226217.19 | AB38: 233787.92
A39: 1 | C39: 자본총계 | E39: 216871.56 | F39: 216871.56 | G39: 214235.41 | H39: 212977.67 | I39: 214778.23 | J39: 208156.94 | K39: 208156.94 | L39: 209546.73 | M39: 209950.91 | N39: 212427.32 | O39: 214815.25 | P39: 214815.25 | Q39: 218438.84 | R39: 222671.51 | S39: 224887.59 | T39: 234277.53 | U39: 234277.53 | V39: 238436.3 | W39: 243204.61 | X39: 250972 | Y39: 257369.37 | Z39: 257369.37 | AA39: 262307.21 | AB39: 270517.45
A40: 1 | C40: 부채와자본총계 | E40: 241431.73 | F40: 241431.73 | G40: 236928.74 | H40: 238045.93 | I40: 242021.41 | J40: 239085.99 | K40: 239085.99 | L40: 245766.22 | M40: 259016.44 | N40: 261330.87 | O40: 275699.82 | P40: 275699.82 | Q40: 276591.11 | R40: 283216.57 | S40: 280780.74 | T40: 289770.81 | U40: 289770.81 | V40: 291838.36 | W40: 297235.91 | X40: 299316.59 | Y40: 300149.59 | Z40: 300149.59 | AA40: 312984.1 | AB40: 330570.96
A41: 1 | C41: 지배주주지분 | E41: 216871.56 | F41: 216871.56 | G41: 214235.41 | H41: 212977.67 | I41: 214778.23 | J41: 208156.94 | K41: 208156.94 | L41: 209546.73 | M41: 209950.91 | N41: 212427.32 | O41: 214815.25 | P41: 214815.25 | Q41: 218438.84 | R41: 222671.51 | S41: 224887.59 | T41: 234277.53 | U41: 234277.53 | V41: 238436.3 | W41: 243204.61 | X41: 250972 | Y41: 257369.37 | Z41: 257369.37 | AA41: 262307.21 | AB41: 270517.45
A42: 1 | C42: 이자발생자산 | E42: 76187.85 | F42: 76187.85 | G42: 65945.87 | H42: 63534.99 | I42: 66608.57 | J42: 62507.99 | K42: 62507.99 | L42: 62088.37 | M42: 67937.35 | N42: 62867.69 | O42: 76157.02 | P42: 76157.02 | Q42: 71189.73 | R42: 76236.34 | S42: 76464.88 | T42: 71808.44 | U42: 71808.44 | V42: 59263.52 | W42: 39374.18 | X42: 47603.61 | Y42: 53209.79 | Z42: 53209.79 | AA42: 48668.38 | AB42: 42721.37
A43: 1 | C43: 기타비유동부채 | N43: 388 | O43: 368 | P43: 368 | Q43: 368 | R43: 368 | S43: 368 | T43: 368 | U43: 368 | V43: 368 | W43: 290 | X43: 290
A44: 1 | C44: 기타유동자산 | Y44: 14318.03 | Z44: 14318.03 | AA44: 16075.42 | AB44: 12112.62
A45: 1 | C45: 사용권자산 | Y45: 401.66 | Z45: 401.66 | AA45: 337.07 | AB45: 360.87
A46: 1 | C46: 기타비유동자산 | Y46: 401.66 | Z46: 401.66 | AA46: 337.07 | AB46: 360.87
A47: 1 | C47: 기타유동부채 | Y47: 19433.67 | Z47: 19433.67 | AA47: 18964.12 | AB47: 31233.47
A48: 1 | C48: 매출액(수익) | E48: 37244.01 | G48: 27074.95 | H48: 28004.04 | I48: 26253.3 | J48: 30307.72 | K48: 111640.01 | L48: 27568.56 | M48: 30927.48 | N48: 30377.56 | O48: 45382.62 | P48: 134256.22 | Q48: 37298.12 | R48: 45783.65 | S48: 39766.68 | T48: 56765.57 | U48: 179614.02 | V48: 50060.95 | W48: 51854.45 | X48: 54840.61 | Y48: 51817.39 | Z48: 208573.4 | AA48: 44957.17 | AB48: 64854.21
A49: 1 | C49: 매출원가 | E49: 33950.83 | G49: 27001.76 | H49: 27806.24 | I49: 23839.57 | J49: 33676.96 | K49: 112324.53 | L49: 26469.53 | M49: 28024.14 | N49: 27050.58 | O49: 40026.92 | P49: 121571.17 | Q49: 32377.39 | R49: 39331.15 | S49: 34536.54 | T49: 46191.58 | U49: 152436.66 | V49: 40035.11 | W49: 43658.13 | X49: 45215.61 | Y49: 40977.27 | Z49: 169886.12 | AA49: 36450.01 | AB49: 53019.05
A50: 1 | C50: 매출총이익 | E50: 3293.19 | G50: 73.2 | H50: 197.8 | I50: 2413.73 | J50: -3369.23 | K50: -684.5 | L50: 1099.04 | M50: 2903.34 | N50: 3326.99 | O50: 5355.69 | P50: 12685.06 | Q50: 4920.73 | R50: 6452.5 | S50: 5230.15 | T50: 10573.99 | U50: 27177.37 | V50: 10025.84 | W50: 8196.33 | X50: 9625.01 | Y50: 10840.12 | Z50: 38687.3 | AA50: 8507.16 | AB50: 11835.16
A51: 1 | C51: 판관비 | E51: 2657.13 | G51: 2058.23 | H51: 2741.38 | I51: 2268.01 | J51: 3020.27 | K51: 10087.89 | L51: 2391.16 | M51: 2263.99 | N51: 2252.75 | O51: 2976.37 | P51: 9884.27 | Q51: 2681.42 | R51: 3462.98 | S51: 2732.54 | T51: 3069.13 | U51: 11946.07 | V51: 5103.19 | W51: 2181.29 | X51: 2427.83 | Y51: 3590.83 | Z51: 13303.14 | AA51: 2961.56 | AB51: 4518.03
A52: 1 | C52: 영업이익 | E52: 636.05 | G52: -1985.04 | H52: -2543.57 | I52: 145.72 | J52: -6389.5 | K52: -10772.39 | L52: -1292.12 | M52: 639.35 | N52: 1074.24 | O52: 2379.34 | P52: 2800.81 | Q52: 2239.3 | R52: 2989.52 | S52: 2497.6 | T52: 7504.86 | U52: 15231.28 | V52: 4922.66 | W52: 6015.04 | X52: 7197.17 | Y52: 7249.29 | Z52: 25384.16 | AA52: 5545.6 | AB52: 7317.13
A53: 1 | C53: 기타영업외수익 | E53: 175.96 | G53: 317.52 | H53: 279.44 | I53: 319.49 | J53: 317.41 | K53: 1233.86 | L53: 358.28 | M53: 307.13 | N53: 509.2 | O53: 382.8 | P53: 1557.41 | Q53: 335.48 | R53: 432.37 | S53: 363.1 | T53: 374.91 | U53: 1505.86 | V53: 623.96 | W53: 518.83 | X53: 841.72 | Y53: 860.19 | Z53: 2844.7 | AA53: 421.82 | AB53: 438.15
A54: 1 | C54: 기타영업외비용 | E54: 16.59 | G54: 1.85 | H54: 43.95 | I54: 2.35 | J54: 365.84 | K54: 413.99 | L54: 4.32 | M54: 501.45 | N54: 2.85 | O54: 547.01 | P54: 1055.63 | Q54: 1.89 | R54: 36.75 | S54: -13.47 | T54: -5.09 | U54: 20.08 | V54: 38.95 | W54: 435.88 | X54: 18.44 | Y54: -354.21 | Z54: 139.06 | AA54: 3.42 | AB54: 15.6
A55: 1 | C55: 금융수익 | E55: 1748.08 | G55: 745.2 | H55: 1587.98 | I55: 2658.99 | J55: -454.81 | K55: 4537.36 | L55: 2945.63 | M55: 1308.38 | N55: 1683.17 | O55: 1446.19 | P55: 7383.37 | Q55: 2274.63 | R55: 1890.12 | S55: 384.81 | T55: 4394.57 | U55: 8944.13 | V55: 1109.01 | W55: 1094.1 | X55: 1078.24 | Y55: 1415.7 | Z55: 4697.05 | AA55: 3065.39 | AB55: 2179.92
A56: 1 | C56: 금융비용 | E56: 139.81 | G56: 1216.92 | H56: 1921.19 | I56: 831.36 | J56: 2271.22 | K56: 6240.69 | L56: 264.06 | M56: 273.4 | N56: 81.15 | O56: 1161.67 | P56: 1780.28 | Q56: 354.22 | R56: 141.41 | S56: 643.42 | T56: 517.27 | U56: 1656.32 | V56: 284.21 | W56: 2750.49 | X56: -782.64 | Y56: 1486.59 | Z56: 3738.65 | AA56: 385.4 | AB56: 410.6
A57: 1 | C57: 법인세비용차감전계속사업이익 | E57: 2403.69 | G57: -2141.08 | H57: -2641.29 | I57: 2290.49 | J57: -9163.98 | K57: -11655.86 | L57: 1752.05 | M57: 1480.01 | N57: 3182.61 | O57: 2499.65 | P57: 8914.32 | Q57: 4493.31 | R57: 5133.84 | S57: 2615.57 | T57: 11762.16 | U57: 24004.88 | V57: 6332.46 | W57: 5313.36 | X57: 9918.21 | Y57: 7562.07 | Z57: 29126.1 | AA57: 8643.99 | AB57: 9509
A58: 1 | C58: 법인세비용 | E58: -127.98 | G58: -431.46 | H58: -1345.89 | I58: 497.71 | J58: -2528.75 | K58: -3808.39 | L58: 370.3 | M58: 175.37 | N58: 672.64 | O58: 128.12 | P58: 1346.43 | Q58: 881.69 | R58: 943.25 | S58: 415.51 | T58: 2391.15 | U58: 4631.6 | V58: 1266.92 | W58: 622.91 | X58: 2190.56 | Y58: 1389.19 | Z58: 5469.58 | AA58: 1852.3 | AB58: 1938.27
A59: 1 | C59: 당기순이익 | E59: 2531.67 | G59: -1709.62 | H59: -1295.4 | I59: 1792.78 | J59: -6635.22 | K59: -7847.46 | L59: 1381.76 | M59: 1304.64 | N59: 2509.97 | O59: 2371.53 | P59: 7567.9 | Q59: 3611.62 | R59: 4190.59 | S59: 2200.05 | T59: 9371.01 | U59: 19373.27 | V59: 5065.54 | W59: 4690.45 | X59: 7727.65 | Y59: 6172.89 | Z59: 23656.53 | AA59: 6791.69 | AB59: 7570.73
... A65: 1 | C65: 영업활동으로인한현금흐름 | E65: 1387.9 | G65: -4669.8 | H65: -862.37 | I65: 4094.12 | J65: -2014.44 | K65: -3452.49 | L65: -919.98 | M65: 8781.63 | N65: -3914.5 | O65: 15168.72 | P65: 19115.87 | Q65: -5101.61 | R65: 2258.36 | S65: 891.86 | T65: 1507.6 | U65: -443.79 | V65: -1394.67 | W65: 3332.11 | X65: 2031.67 | Y65: 11161.14 | Z65: 15130.25 | AA65: -910.92 | AB65: 15261.84
A66: 1 | C66: 감가상각비 | E66: 702.06 | G66: 719.28 | H66: 759.41 | I66: 780.8 | J66: 761.92 | K66: 3021.41 | L66: 883.64 | M66: 889.68 | S66: 1162.49 | V66: 1175.93 | W66: 1270.9 | X66: 1257.68
A67: 1 | C67: 무형자산상각비 | E67: 270.58 | G67: 64.31 | H67: 64.67 | I67: 70.65 | J67: 71.55 | K67: 271.18 | L67: 66.24 | M67: 69.37 | S67: 24.42 | V67: 13.07 | W67: 16.77 | X67: 16.03
A68: 1 | C68: 법인세납부(CF) | E68: 381.35 | G68: -50.74 | H68: 898.48 | I68: -0.01 | J68: 183 | K68: 1030.73 | L68: -156.72 | M68: 156.72 | N68: -111.36 | O68: -116.85 | P68: -228.21 | Q68: -137.53 | R68: -154.47 | S68: -112.99 | T68: -122.21 | U68: -527.2 | V68: -1448.25 | W68: -1699.9 | X68: -856.21 | Y68: -690.36 | Z68: -4694.72 | AA68: -2569.21 | AB68: -3196.67
A69: 1 | C69: 배당금수취(CF) | E69: 24.13 | G69: 0 | H69: 0.16 | I69: 0 | J69: 0 | K69: 0.16 | N69: 0 | O69: 0 | V69: 0
A70: 1 | C70: 투자활동으로인한현금흐름 | E70: -8081.13 | G70: -9437.99 | H70: -1402.02 | I70: -1699.58 | J70: -587.98 | K70: -13127.57 | L70: -966.59 | M70: -4909.28 | N70: -5193.6 | O70: -3502.21 | P70: -14571.68 | Q70: -582.97 | R70: -2671.29 | S70: -768.06 | T70: -3486.67 | U70: -7508.99 | V70: 131.94 | W70: -3784.5 | X70: -923.99 | Y70: -951.15 | Z70: -5527.7 | AA70: -1423.68 | AB70: -17806.4
A71: 1 | C71: 유형자산의증가 | E71: 4035.21 | G71: 4224.3 | H71: 1707.59 | I71: 800.99 | J71: 518.54 | K71: 7251.42 | L71: 446.75 | M71: 4549.18 | N71: 2960.01 | O71: 2181.6 | P71: 10137.54 | Q71: 291.7 | R71: 2125.83 | S71: 570.86 | T71: 1861.78 | U71: 4850.17 | V71: 1842.22 | W71: 3177.88 | X71: 987.68 | Y71: 744.74 | Z71: 6752.52 | AA71: 1042.53 | AB71: 6887.49
A72: 1 | C72: CAPEX | E72: 4035.21 | G72: 4224.3 | H72: 1707.59 | I72: 800.99 | J72: 518.54 | K72: 7251.42 | L72: 446.75 | M72: 4549.18 | N72: 2960.01 | O72: 2181.6 | P72: 10137.54 | Q72: 291.7 | R72: 2125.83 | S72: 570.86 | T72: 1861.78 | U72: 4850.17 | V72: 1842.22 | W72: 3651.69 | X72: 575.39 | Y72: 683.22 | Z72: 6752.52 | AA72: 1042.53 | AB72: 6887.49
A73: 1 | C73: 재무활동으로인한현금흐름 | E73: 298.62 | G73: -53.22 | H73: 1885.67 | I73: 54.81 | J73: 5.59 | K73: 1892.85 | L73: -48 | M73: 1640.9 | N73: 1436.23 | O73: 713.26 | P73: 3742.39 | Q73: -30 | R73: 4802.5 | S73: 543.61 | T73: 2030.57 | U73: 7346.68 | V73: 2585.53 | W73: -3617.85 | X73: 6026.9 | Y73: -5787.86 | Z73: -793.28 | AA73: 1707.11 | AB73: -3584.45
A74: 1 | C74: 이자지급(CF) | E74: -4.79 | G74: -4.49 | H74: -4.2 | I74: -3.88 | J74: -3.59 | K74: -16.16 | L74: -3.28 | M74: -2.99 | N74: -2.7 | O74: -2.41 | P74: -11.38 | Q74: -2.11 | R74: -1.82 | S74: -1.52 | T74: -3.41 | U74: -8.86 | V74: -1.44 | W74: 1.44 | X74: 0 | Y74: 0 | Z74: 0 | AA74: 0
A75: 1 | C75: 자기주식의취득 | E75: 0
A76: 1 | C76: 리스부채의상환 | E76: 48.98 | G76: 48.72 | H76: 49 | I76: 49.3 | J76: 50.22 | K76: 197.24 | L76: 44.72 | M76: 45.01 | N76: 45.3 | O76: 45.59 | P76: 180.62 | Q76: 45.89 | R76: 46.18 | S76: 46.48 | T76: 71.85 | U76: 210.4 | V76: 56.02 | W76: 58.89 | X76: 58.71 | Y76: 87.21 | Z76: 260.83 | AA76: 62.89 | AB76: 75.13
A77: 1 | C77: 배당금지급 | E77: 0 | I77: 0 | J77: 0 | N77: 0 | O77: 0 | X77: 0 | Y77: 0
A78: 1 | C78: 현금및현금성자산의증감 | E78: -6469.32 | G78: -14191.84 | H78: -394.25 | I78: 3156.78 | J78: -3518.54 | K78: -14947.85 | L78: -1624.17 | M78: 5416.55 | N78: -7530.25 | O78: 12062.84 | P78: 8324.97 | Q78: -5405.93 | R78: 4639.8 | S78: 103.72 | T78: 1471.45 | U78: 809.04 | V78: 1387.11 | W78: -5024.54 | X78: 7535.73 | Y78: 4596.05 | Z78: 8494.35 | AA78: 431.3 | AB78: -6479.27
A79: 1 | C79: 기말현금및현금성자산 | E79: -6469.32 | G79: 22415.6 | H79: -394.25 | I79: 3156.78 | J79: -3518.55 | K79: 21659.58 | L79: 20035.41 | M79: 5416.55 | N79: -7530.25 | O79: 12062.84 | P79: 29984.55 | Q79: 24578.62 | R79: 4639.8 | S79: 103.73 | T79: 1471.44 | U79: 30793.59 | V79: 32180.7 | W79: -5024.54 | X79: 7535.73 | Y79: 4596.05 | Z79: 39287.94 | AA79: 39719.24 | AB79: -6479.27
A80: 1 | C80: 유형자산의감소 | G80: 0 | H80: 0 | I80: 0 | J80: 0 | K80: 0 | N80: 100.2 | O80: 5.46 | Q80: 1 | R80: 15.37 | S80: 3.15 | T80: 0 | U80: 19.52 | V80: 2.73 | W80: 5.28 | X80: 0 | Y80: 0 | Z80: 8.01 | AA80: 0 | AB80: 0
A81: 1 | C81: 이자수취(CF) | O81: 731.33 | Q81: 998.67 | R81: 758.04 | S81: 729.97 | T81: 802.48 | U81: 3289.16 | V81: 448.94 | W81: 865.54 | X81: 729.62 | Y81: 595.54 | Z81: 2639.64 | AA81: 599.44 | AB81: 839.76
A82: 1 | C82: 무형자산의감소 | X82: 0

Sheet subQ
A1: YQ | C1: subQ 분기 서브모델(억원, U=100) | E1: 4Q21 | F1: 2021 | G1: 1Q22 | H1: 2Q22 | I1: 3Q22 | J1: 4Q22 | K1: 2022 | L1: 1Q23 | M1: 2Q23 | N1: 3Q23 | O1: 4Q23 | P1: 2023 | Q1: 1Q24 | R1: 2Q24 | S1: 3Q24 | T1: 4Q24 | U1: 2024 | V1: 1Q25 | W1: 2Q25 | X1: 3Q25 | Y1: 4Q25 | Z1: 2025 | AA1: 1Q26 | AB1: 2Q26 | AC1: 3Q26 | AD1: 4Q26 | AE1: 2026 | AF1: 1Q27 | AG1: 2Q27 | AH1: 3Q27 | AI1: 4Q27 | AJ1: 2027 | AK1: 1Q28 | AL1: 2Q28 | AM1: 3Q28 | AN1: 4Q28 | AO1: 2028
A2: A=이름(key) B=그룹 C=단위 D=FnGuide 계정명(VLOOKUP 키). 확정=VLOOKUP(BS), 추정=변수 가정 참조
E3: 1 | F3: 2 | G3: 3 | H3: 4 | I3: 5 | J3: 6 | K3: 7 | L3: 8 | M3: 9 | N3: 10 | O3: 11 | P3: 12 | Q3: 13 | R3: 14 | S3: 15 | T3: 16 | U3: 17 | V3: 18 | W3: 19 | X3: 20 | Y3: 21 | Z3: 22 | AA3: 23 | AB3: 24 | AC3: 25 | AD3: 26 | AE3: 27 | AF3: 28 | AG3: 29 | AH3: 30 | AI3: 31 | AJ3: 32 | AK3: 33 | AL3: 34 | AM3: 35 | AN3: 36 | AO3: 37
E4: 2021.12 | F4: 2021.12A | G4: 2022.03 | H4: 2022.06 | I4: 2022.09 | J4: 2022.12 | K4: 2022.12A | L4: 2023.03 | M4: 2023.06 | N4: 2023.09 | O4: 2023.12 | P4: 2023.12A | Q4: 2024.03 | R4: 2024.06 | S4: 2024.09 | T4: 2024.12 | U4: 2024.12A | V4: 2025.03 | W4: 2025.06 | X4: 2025.09 | Y4: 2025.12 | Z4: 2025.12A | AA4: 2026.03 | AB4: 2026.06 | AC4: 2026.09 | AD4: 2026.12 | AE4: 2026.12A | AF4: 2027.03 | AG4: 2027.06 | AH4: 2027.09 | AI4: 2027.12 | AJ4: 2027.12A | AK4: 2028.03 | AL4: 2028.06 | AM4: 2028.09 | AN4: 2028.12 | AO4: 2028.12A
A5: 매출액 | B5: 손익 | C5: 억원 | D5: 매출액(수익) | E5: =IFERROR(VLOOKUP($D5,BS연결,MATCH(E$1,BS연결H,0),0)/100,"") | G5: =IFERROR(VLOOKUP($D5,BS연결,MATCH(G$1,BS연결H,0),0)/100,"") | H5: =IFERROR(VLOOKUP($D5,BS연결,MATCH(H$1,BS연결H,0),0)/100,"") | I5: =IFERROR(VLOOKUP($D5,BS연결,MATCH(I$1,BS연결H,0),0)/100,"") | J5: =IFERROR(VLOOKUP($D5,BS연결,MATCH(J$1,BS연결H,0),0)/100,"") | K5: =IFERROR(VLOOKUP($D5,BS연결,MATCH(K$1,BS연결H,0),0)/100,"") | L5: =IFERROR(VLOOKUP($D5,BS연결,MATCH(L$1,BS연결H,0),0)/100,"") | M5: =IFERROR(VLOOKUP($D5,BS연결,MATCH(M$1,BS연결H,0),0)/100,"") | N5: =IFERROR(VLOOKUP($D5,BS연결,MATCH(N$1,BS연결H,0),0)/100,"") | ... AB5: =IFERROR(VLOOKUP($D5,BS연결,MATCH(AB$1,BS연결H,0),0)/100,"") | AC5: =IFERROR(X5*(1+변수!AC21),"") | AD5: =IFERROR(Y5*(1+변수!AD21),"") | AE5: =SUM(AA5:AD5) | AF5: =IFERROR(AA5*(1+변수!AF21),"") | AG5: =IFERROR(AB5*(1+변수!AG21),"") | AH5: =IFERROR(AC5*(1+변수!AH21),"") | AI5: =IFERROR(AD5*(1+변수!AI21),"") | AJ5: =SUM(AF5:AI5) | AK5: =IFERROR(AF5*(1+변수!AK21),"") | AL5: =IFERROR(AG5*(1+변수!AL21),"") | AM5: =IFERROR(AH5*(1+변수!AM21),"") | AN5: =IFERROR(AI5*(1+변수!AN21),"") | AO5: =SUM(AK5:AN5)
A6: 매출원가 | B6: 손익 | C6: 억원 | D6: 매출원가 | E6: =IFERROR(VLOOKUP($D6,BS연결,MATCH(E$1,BS연결H,0),0)/100,"") | G6: =IFERROR(VLOOKUP($D6,BS연결,MATCH(G$1,BS연결H,0),0)/100,"") | H6: =IFERROR(VLOOKUP($D6,BS연결,MATCH(H$1,BS연결H,0),0)/100,"") | I6: =IFERROR(VLOOKUP($D6,BS연결,MATCH(I$1,BS연결H,0),0)/100,"") | J6: =IFERROR(VLOOKUP($D6,BS연결,MATCH(J$1,BS연결H,0),0)/100,"") | K6: =IFERROR(VLOOKUP($D6,BS연결,MATCH(K$1,BS연결H,0),0)/100,"") | L6: =IFERROR(VLOOKUP($D6,BS연결,MATCH(L$1,BS연결H,0),0)/100,"") | M6: =IFERROR(VLOOKUP($D6,BS연결,MATCH(M$1,BS연결H,0),0)/100,"") | N6: =IFERROR(VLOOKUP($D6,BS연결,MATCH(N$1,BS연결H,0),0)/100,"") | ... AB6: =IFERROR(VLOOKUP($D6,BS연결,MATCH(AB$1,BS연결H,0),0)/100,"") | AC6: =IFERROR(AC5-AC7,"") | AD6: =IFERROR(AD5-AD7,"") | AE6: =SUM(AA6:AD6) | AF6: =IFERROR(AF5-AF7,"") | AG6: =IFERROR(AG5-AG7,"") | AH6: =IFERROR(AH5-AH7,"") | AI6: =IFERROR(AI5-AI7,"") | AJ6: =SUM(AF6:AI6) | AK6: =IFERROR(AK5-AK7,"") | AL6: =IFERROR(AL5-AL7,"") | AM6: =IFERROR(AM5-AM7,"") | AN6: =IFERROR(AN5-AN7,"") | AO6: =SUM(AK6:AN6)
A7: 매출총이익 | B7: 손익 | C7: 억원 | D7: 매출총이익 | E7: =IFERROR(VLOOKUP($D7,BS연결,MATCH(E$1,BS연결H,0),0)/100,"") | G7: =IFERROR(VLOOKUP($D7,BS연결,MATCH(G$1,BS연결H,0),0)/100,"") | H7: =IFERROR(VLOOKUP($D7,BS연결,MATCH(H$1,BS연결H,0),0)/100,"") | I7: =IFERROR(VLOOKUP($D7,BS연결,MATCH(I$1,BS연결H,0),0)/100,"") | J7: =IFERROR(VLOOKUP($D7,BS연결,MATCH(J$1,BS연결H,0),0)/100,"") | K7: =IFERROR(VLOOKUP($D7,BS연결,MATCH(K$1,BS연결H,0),0)/100,"") | L7: =IFERROR(VLOOKUP($D7,BS연결,MATCH(L$1,BS연결H,0),0)/100,"") | M7: =IFERROR(VLOOKUP($D7,BS연결,MATCH(M$1,BS연결H,0),0)/100,"") | N7: =IFERROR(VLOOKUP($D7,BS연결,MATCH(N$1,BS연결H,0),0)/100,"") | ... AB7: =IFERROR(VLOOKUP($D7,BS연결,MATCH(AB$1,BS연결H,0),0)/100,"") | AC7: =IFERROR(AC9+AC8,"") | AD7: =IFERROR(AD9+AD8,"") | AE7: =SUM(AA7:AD7) | AF7: =IFERROR(AF9+AF8,"") | AG7: =IFERROR(AG9+AG8,"") | AH7: =IFERROR(AH9+AH8,"") | AI7: =IFERROR(AI9+AI8,"") | AJ7: =SUM(AF7:AI7) | AK7: =IFERROR(AK9+AK8,"") | AL7: =IFERROR(AL9+AL8,"") | AM7: =IFERROR(AM9+AM8,"") | AN7: =IFERROR(AN9+AN8,"") | AO7: =SUM(AK7:AN7)
A8: 판관비 | B8: 손익 | C8: 억원 | D8: 판관비 | E8: =IFERROR(VLOOKUP($D8,BS연결,MATCH(E$1,BS연결H,0),0)/100,"") | G8: =IFERROR(VLOOKUP($D8,BS연결,MATCH(G$1,BS연결H,0),0)/100,"") | H8: =IFERROR(VLOOKUP($D8,BS연결,MATCH(H$1,BS연결H,0),0)/100,"") | I8: =IFERROR(VLOOKUP($D8,BS연결,MATCH(I$1,BS연결H,0),0)/100,"") | J8: =IFERROR(VLOOKUP($D8,BS연결,MATCH(J$1,BS연결H,0),0)/100,"") | K8: =IFERROR(VLOOKUP($D8,BS연결,MATCH(K$1,BS연결H,0),0)/100,"") | L8: =IFERROR(VLOOKUP($D8,BS연결,MATCH(L$1,BS연결H,0),0)/100,"") | M8: =IFERROR(VLOOKUP($D8,BS연결,MATCH(M$1,BS연결H,0),0)/100,"") | N8: =IFERROR(VLOOKUP($D8,BS연결,MATCH(N$1,BS연결H,0),0)/100,"") | ... AB8: =IFERROR(VLOOKUP($D8,BS연결,MATCH(AB$1,BS연결H,0),0)/100,"") | AC8: =IFERROR(AC5*변수!AC22,"") | AD8: =IFERROR(AD5*변수!AD22,"") | AE8: =SUM(AA8:AD8) | AF8: =IFERROR(AF5*변수!AF22,"") | AG8: =IFERROR(AG5*변수!AG22,"") | AH8: =IFERROR(AH5*변수!AH22,"") | AI8: =IFERROR(AI5*변수!AI22,"") | AJ8: =SUM(AF8:AI8) | AK8: =IFERROR(AK5*변수!AK22,"") | AL8: =IFERROR(AL5*변수!AL22,"") | AM8: =IFERROR(AM5*변수!AM22,"") | AN8: =IFERROR(AN5*변수!AN22,"") | AO8: =SUM(AK8:AN8)
A9: 영업이익 | B9: 손익 | C9: 억원 | D9: 영업이익 | E9: =IFERROR(VLOOKUP($D9,BS연결,MATCH(E$1,BS연결H,0),0)/100,"") | G9: =IFERROR(VLOOKUP($D9,BS연결,MATCH(G$1,BS연결H,0),0)/100,"") | H9: =IFERROR(VLOOKUP($D9,BS연결,MATCH(H$1,BS연결H,0),0)/100,"") | I9: =IFERROR(VLOOKUP($D9,BS연결,MATCH(I$1,BS연결H,0),0)/100,"") | J9: =IFERROR(VLOOKUP($D9,BS연결,MATCH(J$1,BS연결H,0),0)/100,"") | K9: =IFERROR(VLOOKUP($D9,BS연결,MATCH(K$1,BS연결H,0),0)/100,"") | L9: =IFERROR(VLOOKUP($D9,BS연결,MATCH(L$1,BS연결H,0),0)/100,"") | M9: =IFERROR(VLOOKUP($D9,BS연결,MATCH(M$1,BS연결H,0),0)/100,"") | N9: =IFERROR(VLOOKUP($D9,BS연결,MATCH(N$1,BS연결H,0),0)/100,"") | ... AB9: =IFERROR(VLOOKUP($D9,BS연결,MATCH(AB$1,BS연결H,0),0)/100,"") | AC9: =IFERROR(AC5*변수!AC23,"") | AD9: =IFERROR(AD5*변수!AD23,"") | AE9: =SUM(AA9:AD9) | AF9: =IFERROR(AF5*변수!AF23,"") | AG9: =IFERROR(AG5*변수!AG23,"") | AH9: =IFERROR(AH5*변수!AH23,"") | AI9: =IFERROR(AI5*변수!AI23,"") | AJ9: =SUM(AF9:AI9) | AK9: =IFERROR(AK5*변수!AK23,"") | AL9: =IFERROR(AL5*변수!AL23,"") | AM9: =IFERROR(AM5*변수!AM23,"") | AN9: =IFERROR(AN5*변수!AN23,"") | AO9: =SUM(AK9:AN9)
A10: OPM | B10: 손익 | C10: % | D10: 영업이익률 | E10: =IFERROR(E9/E5,"") | G10: =IFERROR(G9/G5,"") | H10: =IFERROR(H9/H5,"") | I10: =IFERROR(I9/I5,"") | J10: =IFERROR(J9/J5,"") | K10: =IFERROR(K9/K5,"") | L10: =IFERROR(L9/L5,"") | M10: =IFERROR(M9/M5,"") | N10: =IFERROR(N9/N5,"") | ... AO10: =IFERROR(AO9/AO5,"")
A11: 금융손익 | B11: 손익 | C11: 억원 | D11: 금융손익 | E11: =IFERROR(VLOOKUP($D11,BS연결,MATCH(E$1,BS연결H,0),0)/100,"") | G11: =IFERROR(VLOOKUP($D11,BS연결,MATCH(G$1,BS연결H,0),0)/100,"") | H11: =IFERROR(VLOOKUP($D11,BS연결,MATCH(H$1,BS연결H,0),0)/100,"") | I11: =IFERROR(VLOOKUP($D11,BS연결,MATCH(I$1,BS연결H,0),0)/100,"") | J11: =IFERROR(VLOOKUP($D11,BS연결,MATCH(J$1,BS연결H,0),0)/100,"") | K11: =IFERROR(VLOOKUP($D11,BS연결,MATCH(K$1,BS연결H,0),0)/100,"") | L11: =IFERROR(VLOOKUP($D11,BS연결,MATCH(L$1,BS연결H,0),0)/100,"") | M11: =IFERROR(VLOOKUP($D11,BS연결,MATCH(M$1,BS연결H,0),0)/100,"") | N11: =IFERROR(VLOOKUP($D11,BS연결,MATCH(N$1,BS연결H,0),0)/100,"") | ... AB11: =IFERROR(VLOOKUP($D11,BS연결,MATCH(AB$1,BS연결H,0),0)/100,"") | AC11: =IFERROR(AC12,"") | AD11: =IFERROR(AD12,"") | AE11: =SUM(AA11:AD11) | AF11: =IFERROR(AF12,"") | AG11: =IFERROR(AG12,"") | AH11: =IFERROR(AH12,"") | AI11: =IFERROR(AI12,"") | AJ11: =SUM(AF11:AI11) | AK11: =IFERROR(AK12,"") | AL11: =IFERROR(AL12,"") | AM11: =IFERROR(AM12,"") | AN11: =IFERROR(AN12,"") | AO11: =SUM(AK11:AN11)
A12: 이자손익 | B12: 손익 | C12: 억원 | D12: 이자손익 | G12: =IFERROR(VLOOKUP($D12,BS연결,MATCH(G$1,BS연결H,0),0)/100,"") | K12: =SUM(G12:J12) | L12: =IFERROR(VLOOKUP($D12,BS연결,MATCH(L$1,BS연결H,0),0)/100,"") | P12: =SUM(L12:O12) | U12: =SUM(Q12:T12) | Z12: =SUM(V12:Y12) | AC12: =IFERROR((AB24*변수!$D$49)/4,"") | AD12: =IFERROR((AC24*변수!$D$49)/4,"") | AE12: =SUM(AA12:AD12) | AF12: =IFERROR((AD24*변수!$D$49)/4,"") | AG12: =IFERROR((AF24*변수!$D$49)/4,"") | AH12: =IFERROR((AG24*변수!$D$49)/4,"") | AI12: =IFERROR((AH24*변수!$D$49)/4,"") | AJ12: =SUM(AF12:AI12) | AK12: =IFERROR((AI24*변수!$D$49)/4,"") | AL12: =IFERROR((AK24*변수!$D$49)/4,"") | AM12: =IFERROR((AL24*변수!$D$49)/4,"") | AN12: =IFERROR((AM24*변수!$D$49)/4,"") | AO12: =SUM(AK12:AN12)
A13: 기타영업외손익 | B13: 손익 | C13: 억원 | D13: 기타영업외손익 | E13: =IFERROR(VLOOKUP($D13,BS연결,MATCH(E$1,BS연결H,0),0)/100,"") | G13: =IFERROR(VLOOKUP($D13,BS연결,MATCH(G$1,BS연결H,0),0)/100,"") | H13: =IFERROR(VLOOKUP($D13,BS연결,MATCH(H$1,BS연결H,0),0)/100,"") | I13: =IFERROR(VLOOKUP($D13,BS연결,MATCH(I$1,BS연결H,0),0)/100,"") | J13: =IFERROR(VLOOKUP($D13,BS연결,MATCH(J$1,BS연결H,0),0)/100,"") | K13: =IFERROR(VLOOKUP($D13,BS연결,MATCH(K$1,BS연결H,0),0)/100,"") | L13: =IFERROR(VLOOKUP($D13,BS연결,MATCH(L$1,BS연결H,0),0)/100,"") | M13: =IFERROR(VLOOKUP($D13,BS연결,MATCH(M$1,BS연결H,0),0)/100,"") | N13: =IFERROR(VLOOKUP($D13,BS연결,MATCH(N$1,BS연결H,0),0)/100,"") | ... AB13: =IFERROR(VLOOKUP($D13,BS연결,MATCH(AB$1,BS연결H,0),0)/100,"") | AC13: =변수!AC24 | AD13: =변수!AD24 | AE13: =SUM(AA13:AD13) | AF13: =변수!AF24 | AG13: =변수!AG24 | AH13: =변수!AH24 | AI13: =변수!AI24 | AJ13: =SUM(AF13:AI13) | AK13: =변수!AK24 | AL13: =변수!AL24 | AM13: =변수!AM24 | AN13: =변수!AN24 | AO13: =SUM(AK13:AN13)
A14: 세전이익 | B14: 손익 | C14: 억원 | D14: 법인세비용차감전계속사업이익 | E14: =IFERROR(VLOOKUP($D14,BS연결,MATCH(E$1,BS연결H,0),0)/100,"") | G14: =IFERROR(VLOOKUP($D14,BS연결,MATCH(G$1,BS연결H,0),0)/100,"") | H14: =IFERROR(VLOOKUP($D14,BS연결,MATCH(H$1,BS연결H,0),0)/100,"") | I14: =IFERROR(VLOOKUP($D14,BS연결,MATCH(I$1,BS연결H,0),0)/100,"") | J14: =IFERROR(VLOOKUP($D14,BS연결,MATCH(J$1,BS연결H,0),0)/100,"") | K14: =IFERROR(VLOOKUP($D14,BS연결,MATCH(K$1,BS연결H,0),0)/100,"") | L14: =IFERROR(VLOOKUP($D14,BS연결,MATCH(L$1,BS연결H,0),0)/100,"") | M14: =IFERROR(VLOOKUP($D14,BS연결,MATCH(M$1,BS연결H,0),0)/100,"") | N14: =IFERROR(VLOOKUP($D14,BS연결,MATCH(N$1,BS연결H,0),0)/100,"") | ... Y14: =IFERROR(VLOOKUP($D14,BS연결,MATCH(Y$1,BS연결H,0),0)/100,"") | Z14: =SUM(V14:Y14) | AA14: =IFERROR(VLOOKUP($D14,BS연결,MATCH(AA$1,BS연결H,0),0)/100,"") | AB14: =IFERROR(VLOOKUP($D14,BS연결,MATCH(AB$1,BS연결H,0),0)/100,"") | AC14: =IFERROR(AC9+AC11+AC13,"") | AD14: =IFERROR(AD9+AD11+AD13,"") | AE14: =SUM(AA14:AD14) | AF14: =IFERROR(AF9+AF11+AF13,"") | AG14: =IFERROR(AG9+AG11+AG13,"") | AH14: =IFERROR(AH9+AH11+AH13,"") | AI14: =IFERROR(AI9+AI11+AI13,"") | AJ14: =SUM(AF14:AI14) | AK14: =IFERROR(AK9+AK11+AK13,"") | AL14: =IFERROR(AL9+AL11+AL13,"") | AM14: =IFERROR(AM9+AM11+AM13,"") | AN14: =IFERROR(AN9+AN11+AN13,"") | AO14: =SUM(AK14:AN14)
A15: 법인세비용 | B15: 손익 | C15: 억원 | D15: 법인세비용 | E15: =IFERROR(VLOOKUP($D15,BS연결,MATCH(E$1,BS연결H,0),0)/100,"") | G15: =IFERROR(VLOOKUP($D15,BS연결,MATCH(G$1,BS연결H,0),0)/100,"") | H15: =IFERROR(VLOOKUP($D15,BS연결,MATCH(H$1,BS연결H,0),0)/100,"") | I15: =IFERROR(VLOOKUP($D15,BS연결,MATCH(I$1,BS연결H,0),0)/100,"") | J15: =IFERROR(VLOOKUP($D15,BS연결,MATCH(J$1,BS연결H,0),0)/100,"") | K15: =IFERROR(VLOOKUP($D15,BS연결,MATCH(K$1,BS연결H,0),0)/100,"") | L15: =IFERROR(VLOOKUP($D15,BS연결,MATCH(L$1,BS연결H,0),0)/100,"") | M15: =IFERROR(VLOOKUP($D15,BS연결,MATCH(M$1,BS연결H,0),0)/100,"") | N15: =IFERROR(VLOOKUP($D15,BS연결,MATCH(N$1,BS연결H,0),0)/100,"") | ... AB15: =IFERROR(VLOOKUP($D15,BS연결,MATCH(AB$1,BS연결H,0),0)/100,"") | AC15: =IFERROR(MAX(AC14,0)*변수!AC25,"") | AD15: =IFERROR(MAX(AD14,0)*변수!AD25,"") | AE15: =SUM(AA15:AD15) | AF15: =IFERROR(MAX(AF14,0)*변수!AF25,"") | AG15: =IFERROR(MAX(AG14,0)*변수!AG25,"") | AH15: =IFERROR(MAX(AH14,0)*변수!AH25,"") | AI15: =IFERROR(MAX(AI14,0)*변수!AI25,"") | AJ15: =SUM(AF15:AI15) | AK15: =IFERROR(MAX(AK14,0)*변수!AK25,"") | AL15: =IFERROR(MAX(AL14,0)*변수!AL25,"") | AM15: =IFERROR(MAX(AM14,0)*변수!AM25,"") | AN15: =IFERROR(MAX(AN14,0)*변수!AN25,"") | AO15: =SUM(AK15:AN15)
A16: 당기순이익 | B16: 손익 | C16: 억원 | D16: 당기순이익 | E16: =IFERROR(VLOOKUP($D16,BS연결,MATCH(E$1,BS연결H,0),0)/100,"") | G16: =IFERROR(VLOOKUP($D16,BS연결,MATCH(G$1,BS연결H,0),0)/100,"") | H16: =IFERROR(VLOOKUP($D16,BS연결,MATCH(H$1,BS연결H,0),0)/100,"") | I16: =IFERROR(VLOOKUP($D16,BS연결,MATCH(I$1,BS연결H,0),0)/100,"") | J16: =IFERROR(VLOOKUP($D16,BS연결,MATCH(J$1,BS연결H,0),0)/100,"") | K16: =IFERROR(VLOOKUP($D16,BS연결,MATCH(K$1,BS연결H,0),0)/100,"") | L16: =IFERROR(VLOOKUP($D16,BS연결,MATCH(L$1,BS연결H,0),0)/100,"") | M16: =IFERROR(VLOOKUP($D16,BS연결,MATCH(M$1,BS연결H,0),0)/100,"") | N16: =IFERROR(VLOOKUP($D16,BS연결,MATCH(N$1,BS연결H,0),0)/100,"") | ... AB16: =IFERROR(VLOOKUP($D16,BS연결,MATCH(AB$1,BS연결H,0),0)/100,"") | AC16: =IFERROR(AC14-AC15,"") | AD16: =IFERROR(AD14-AD15,"") | AE16: =SUM(AA16:AD16) | AF16: =IFERROR(AF14-AF15,"") | AG16: =IFERROR(AG14-AG15,"") | AH16: =IFERROR(AH14-AH15,"") | AI16: =IFERROR(AI14-AI15,"") | AJ16: =SUM(AF16:AI16) | AK16: =IFERROR(AK14-AK15,"") | AL16: =IFERROR(AL14-AL15,"") | AM16: =IFERROR(AM14-AM15,"") | AN16: =IFERROR(AN14-AN15,"") | AO16: =SUM(AK16:AN16)
A17: 지배주주순이익 | B17: 손익 | C17: 억원 | D17: (지배주주지분)당기순이익 | E17: =IFERROR(VLOOKUP($D17,BS연결,MATCH(E$1,BS연결H,0),0)/100,"") | G17: =IFERROR(VLOOKUP($D17,BS연결,MATCH(G$1,BS연결H,0),0)/100,"") | H17: =IFERROR(VLOOKUP($D17,BS연결,MATCH(H$1,BS연결H,0),0)/100,"") | I17: =IFERROR(VLOOKUP($D17,BS연결,MATCH(I$1,BS연결H,0),0)/100,"") | J17: =IFERROR(VLOOKUP($D17,BS연결,MATCH(J$1,BS연결H,0),0)/100,"") | K17: =IFERROR(VLOOKUP($D17,BS연결,MATCH(K$1,BS연결H,0),0)/100,"") | L17: =IFERROR(VLOOKUP($D17,BS연결,MATCH(L$1,BS연결H,0),0)/100,"") | M17: =IFERROR(VLOOKUP($D17,BS연결,MATCH(M$1,BS연결H,0),0)/100,"") | N17: =IFERROR(VLOOKUP($D17,BS연결,MATCH(N$1,BS연결H,0),0)/100,"") | ... AA17: =IFERROR(VLOOKUP($D17,BS연결,MATCH(AA$1,BS연결H,0),0)/100,"") | AB17: 76.64 | AC17: =IFERROR(AC16*변수!AC26,"") | AD17: =IFERROR(AD16*변수!AD26,"") | AE17: =SUM(AA17:AD17) | AF17: =IFERROR(AF16*변수!AF26,"") | AG17: =IFERROR(AG16*변수!AG26,"") | AH17: =IFERROR(AH16*변수!AH26,"") | AI17: =IFERROR(AI16*변수!AI26,"") | AJ17: =SUM(AF17:AI17) | AK17: =IFERROR(AK16*변수!AK26,"") | AL17: =IFERROR(AL16*변수!AL26,"") | AM17: =IFERROR(AM16*변수!AM26,"") | AN17: =IFERROR(AN16*변수!AN26,"") | AO17: =SUM(AK17:AN17)
A18: 감가상각비 | B18: 손익 | C18: 억원 | D18: 감가상각비 | E18: =IFERROR(VLOOKUP($D18,BS연결,MATCH(E$1,BS연결H,0),0)/100,"") | G18: =IFERROR(VLOOKUP($D18,BS연결,MATCH(G$1,BS연결H,0),0)/100,"") | H18: =IFERROR(VLOOKUP($D18,BS연결,MATCH(H$1,BS연결H,0),0)/100,"") | I18: =IFERROR(VLOOKUP($D18,BS연결,MATCH(I$1,BS연결H,0),0)/100,"") | J18: =IFERROR(VLOOKUP($D18,BS연결,MATCH(J$1,BS연결H,0),0)/100,"") | K18: =IFERROR(VLOOKUP($D18,BS연결,MATCH(K$1,BS연결H,0),0)/100,"") | L18: =IFERROR(VLOOKUP($D18,BS연결,MATCH(L$1,BS연결H,0),0)/100,"") | M18: =IFERROR(VLOOKUP($D18,BS연결,MATCH(M$1,BS연결H,0),0)/100,"") | P18: =SUM(L18:O18) | S18: =IFERROR(VLOOKUP($D18,BS연결,MATCH(S$1,BS연결H,0),0)/100,"") | U18: =SUM(Q18:T18) | Z18: =SUM(V18:Y18) | AC18: =변수!AC27 | AD18: =변수!AD27 | AE18: =SUM(AA18:AD18) | AF18: =변수!AF27 | AG18: =변수!AG27 | AH18: =변수!AH27 | AI18: =변수!AI27 | AJ18: =SUM(AF18:AI18) | AK18: =변수!AK27 | AL18: =변수!AL27 | AM18: =변수!AM27 | AN18: =변수!AN27 | AO18: =SUM(AK18:AN18)
A19: EBITDA | B19: 손익 | C19: 억원 | D19: EBITDA | E19: 14.05 | G19: -8.35 | H19: -9.77 | I19: 12.74 | J19: -57.1 | K19: =SUM(G19:J19) | L19: 0.88 | M19: 12.93 | P19: =SUM(L19:O19) | S19: 41.9 | U19: =SUM(Q19:T19) | Z19: =SUM(V19:Y19) | AC19: =IFERROR(AC9+AC18,"") | AD19: =IFERROR(AD9+AD18,"") | AE19: =SUM(AA19:AD19) | AF19: =IFERROR(AF9+AF18,"") | AG19: =IFERROR(AG9+AG18,"") | AH19: =IFERROR(AH9+AH18,"") | AI19: =IFERROR(AI9+AI18,"") | AJ19: =SUM(AF19:AI19) | AK19: =IFERROR(AK9+AK18,"") | AL19: =IFERROR(AL9+AL18,"") | AM19: =IFERROR(AM9+AM18,"") | AN19: =IFERROR(AN9+AN18,"") | AO19: =SUM(AK19:AN19)
A20: 자산총계 | B20: 재무상태 | C20: 억원 | D20: 자산총계 | E20: =IFERROR(VLOOKUP($D20,BS연결,MATCH(E$1,BS연결H,0),0)/100,"") | F20: =IFERROR(VLOOKUP($D20,BS연결,MATCH(F$1,BS연결H,0),0)/100,"") | G20: =IFERROR(VLOOKUP($D20,BS연결,MATCH(G$1,BS연결H,0),0)/100,"") | H20: =IFERROR(VLOOKUP($D20,BS연결,MATCH(H$1,BS연결H,0),0)/100,"") | I20: =IFERROR(VLOOKUP($D20,BS연결,MATCH(I$1,BS연결H,0),0)/100,"") | J20: =IFERROR(VLOOKUP($D20,BS연결,MATCH(J$1,BS연결H,0),0)/100,"") | K20: =IFERROR(VLOOKUP($D20,BS연결,MATCH(K$1,BS연결H,0),0)/100,"") | L20: =IFERROR(VLOOKUP($D20,BS연결,MATCH(L$1,BS연결H,0),0)/100,"") | ... AB20: =IFERROR(VLOOKUP($D20,BS연결,MATCH(AB$1,BS연결H,0),0)/100,"") | AC20: =IFERROR(AC21+AC22,"") | AD20: =IFERROR(AD21+AD22,"") | AE20: =AD20 | AF20: =IFERROR(AF21+AF22,"") | AG20: =IFERROR(AG21+AG22,"") | AH20: =IFERROR(AH21+AH22,"") | AI20: =IFERROR(AI21+AI22,"") | AJ20: =AI20 | AK20: =IFERROR(AK21+AK22,"") | AL20: =IFERROR(AL21+AL22,"") | AM20: =IFERROR(AM21+AM22,"") | AN20: =IFERROR(AN21+AN22,"") | AO20: =AN20
A21: 부채총계 | B21: 재무상태 | C21: 억원 | D21: 부채총계 | E21: =IFERROR(VLOOKUP($D21,BS연결,MATCH(E$1,BS연결H,0),0)/100,"") | F21: =IFERROR(VLOOKUP($D21,BS연결,MATCH(F$1,BS연결H,0),0)/100,"") | G21: =IFERROR(VLOOKUP($D21,BS연결,MATCH(G$1,BS연결H,0),0)/100,"") | H21: =IFERROR(VLOOKUP($D21,BS연결,MATCH(H$1,BS연결H,0),0)/100,"") | I21: =IFERROR(VLOOKUP($D21,BS연결,MATCH(I$1,BS연결H,0),0)/100,"") | J21: =IFERROR(VLOOKUP($D21,BS연결,MATCH(J$1,BS연결H,0),0)/100,"") | K21: =IFERROR(VLOOKUP($D21,BS연결,MATCH(K$1,BS연결H,0),0)/100,"") | L21: =IFERROR(VLOOKUP($D21,BS연결,MATCH(L$1,BS연결H,0),0)/100,"") | ... AB21: =IFERROR(VLOOKUP($D21,BS연결,MATCH(AB$1,BS연결H,0),0)/100,"") | AC21: =IFERROR(AB21*(1+변수!AC28),"") | AD21: =IFERROR(AC21*(1+변수!AD28),"") | AE21: =AD21 | AF21: =IFERROR(AD21*(1+변수!AF28),"") | AG21: =IFERROR(AF21*(1+변수!AG28),"") | AH21: =IFERROR(AG21*(1+변수!AH28),"") | AI21: =IFERROR(AH21*(1+변수!AI28),"") | AJ21: =AI21 | AK21: =IFERROR(AI21*(1+변수!AK28),"") | AL21: =IFERROR(AK21*(1+변수!AL28),"") | AM21: =IFERROR(AL21*(1+변수!AM28),"") | AN21: =IFERROR(AM21*(1+변수!AN28),"") | AO21: =AN21
A22: 자본총계 | B22: 재무상태 | C22: 억원 | D22: 자본총계 | E22: =IFERROR(VLOOKUP($D22,BS연결,MATCH(E$1,BS연결H,0),0)/100,"") | F22: =IFERROR(VLOOKUP($D22,BS연결,MATCH(F$1,BS연결H,0),0)/100,"") | G22: =IFERROR(VLOOKUP($D22,BS연결,MATCH(G$1,BS연결H,0),0)/100,"") | H22: =IFERROR(VLOOKUP($D22,BS연결,MATCH(H$1,BS연결H,0),0)/100,"") | I22: =IFERROR(VLOOKUP($D22,BS연결,MATCH(I$1,BS연결H,0),0)/100,"") | J22: =IFERROR(VLOOKUP($D22,BS연결,MATCH(J$1,BS연결H,0),0)/100,"") | K22: =IFERROR(VLOOKUP($D22,BS연결,MATCH(K$1,BS연결H,0),0)/100,"") | L22: =IFERROR(VLOOKUP($D22,BS연결,MATCH(L$1,BS연결H,0),0)/100,"") | ... AB22: =IFERROR(VLOOKUP($D22,BS연결,MATCH(AB$1,BS연결H,0),0)/100,"") | AC22: =IFERROR(AB22+AC16-변수!AC29,"") | AD22: =IFERROR(AC22+AD16-변수!AD29,"") | AE22: =AD22 | AF22: =IFERROR(AD22+AF16-변수!AF29,"") | AG22: =IFERROR(AF22+AG16-변수!AG29,"") | AH22: =IFERROR(AG22+AH16-변수!AH29,"") | AI22: =IFERROR(AH22+AI16-변수!AI29,"") | AJ22: =AI22 | AK22: =IFERROR(AI22+AK16-변수!AK29,"") | AL22: =IFERROR(AK22+AL16-변수!AL29,"") | AM22: =IFERROR(AL22+AM16-변수!AM29,"") | AN22: =IFERROR(AM22+AN16-변수!AN29,"") | AO22: =AN22
A23: 지배주주지분 | B23: 재무상태 | C23: 억원 | D23: 지배주주지분 | E23: =IFERROR(VLOOKUP($D23,BS연결,MATCH(E$1,BS연결H,0),0)/100,"") | F23: =IFERROR(VLOOKUP($D23,BS연결,MATCH(F$1,BS연결H,0),0)/100,"") | G23: =IFERROR(VLOOKUP($D23,BS연결,MATCH(G$1,BS연결H,0),0)/100,"") | H23: =IFERROR(VLOOKUP($D23,BS연결,MATCH(H$1,BS연결H,0),0)/100,"") | I23: =IFERROR(VLOOKUP($D23,BS연결,MATCH(I$1,BS연결H,0),0)/100,"") | J23: =IFERROR(VLOOKUP($D23,BS연결,MATCH(J$1,BS연결H,0),0)/100,"") | K23: =IFERROR(VLOOKUP($D23,BS연결,MATCH(K$1,BS연결H,0),0)/100,"") | L23: =IFERROR(VLOOKUP($D23,BS연결,MATCH(L$1,BS연결H,0),0)/100,"") | ... AB23: =IFERROR(VLOOKUP($D23,BS연결,MATCH(AB$1,BS연결H,0),0)/100,"") | AC23: =IFERROR(AB23+AC17-변수!AC30,"") | AD23: =IFERROR(AC23+AD17-변수!AD30,"") | AE23: =AD23 | AF23: =IFERROR(AD23+AF17-변수!AF30,"") | AG23: =IFERROR(AF23+AG17-변수!AG30,"") | AH23: =IFERROR(AG23+AH17-변수!AH30,"") | AI23: =IFERROR(AH23+AI17-변수!AI30,"") | AJ23: =AI23 | AK23: =IFERROR(AI23+AK17-변수!AK30,"") | AL23: =IFERROR(AK23+AL17-변수!AL30,"") | AM23: =IFERROR(AL23+AM17-변수!AM30,"") | AN23: =IFERROR(AM23+AN17-변수!AN30,"") | AO23: =AN23
A24: 이자발생자산 | B24: 재무상태 | C24: 억원 | D24: 이자발생자산 | E24: =IFERROR(VLOOKUP($D24,BS연결,MATCH(E$1,BS연결H,0),0)/100,"") | F24: =IFERROR(VLOOKUP($D24,BS연결,MATCH(F$1,BS연결H,0),0)/100,"") | G24: =IFERROR(VLOOKUP($D24,BS연결,MATCH(G$1,BS연결H,0),0)/100,"") | H24: =IFERROR(VLOOKUP($D24,BS연결,MATCH(H$1,BS연결H,0),0)/100,"") | I24: =IFERROR(VLOOKUP($D24,BS연결,MATCH(I$1,BS연결H,0),0)/100,"") | J24: =IFERROR(VLOOKUP($D24,BS연결,MATCH(J$1,BS연결H,0),0)/100,"") | K24: =IFERROR(VLOOKUP($D24,BS연결,MATCH(K$1,BS연결H,0),0)/100,"") | L24: =IFERROR(VLOOKUP($D24,BS연결,MATCH(L$1,BS연결H,0),0)/100,"") | ... AB24: =IFERROR(VLOOKUP($D24,BS연결,MATCH(AB$1,BS연결H,0),0)/100,"") | AC24: =IFERROR(AB24*(1+변수!AC31),"") | AD24: =IFERROR(AC24*(1+변수!AD31),"") | AE24: =AD24 | AF24: =IFERROR(AD24*(1+변수!AF31),"") | AG24: =IFERROR(AF24*(1+변수!AG31),"") | AH24: =IFERROR(AG24*(1+변수!AH31),"") | AI24: =IFERROR(AH24*(1+변수!AI31),"") | AJ24: =AI24 | AK24: =IFERROR(AI24*(1+변수!AK31),"") | AL24: =IFERROR(AK24*(1+변수!AL31),"") | AM24: =IFERROR(AL24*(1+변수!AM31),"") | AN24: =IFERROR(AM24*(1+변수!AN31),"") | AO24: =AN24
A25: 현금및현금성자산 | B25: 재무상태 | C25: 억원 | D25: 현금및현금성자산 | E25: =IFERROR(VLOOKUP($D25,BS연결,MATCH(E$1,BS연결H,0),0)/100,"") | F25: =IFERROR(VLOOKUP($D25,BS연결,MATCH(F$1,BS연결H,0),0)/100,"") | G25: =IFERROR(VLOOKUP($D25,BS연결,MATCH(G$1,BS연결H,0),0)/100,"") | H25: =IFERROR(VLOOKUP($D25,BS연결,MATCH(H$1,BS연결H,0),0)/100,"") | I25: =IFERROR(VLOOKUP($D25,BS연결,MATCH(I$1,BS연결H,0),0)/100,"") | J25: =IFERROR(VLOOKUP($D25,BS연결,MATCH(J$1,BS연결H,0),0)/100,"") | K25: =IFERROR(VLOOKUP($D25,BS연결,MATCH(K$1,BS연결H,0),0)/100,"") | L25: =IFERROR(VLOOKUP($D25,BS연결,MATCH(L$1,BS연결H,0),0)/100,"") | ... AB25: =IFERROR(VLOOKUP($D25,BS연결,MATCH(AB$1,BS연결H,0),0)/100,"") | AE25: =AD25 | AJ25: =AI25 | AO25: =AN25
A26: CAPEX | B26: 현금흐름 | C26: 억원 | D26: CAPEX | E26: =IFERROR(VLOOKUP($D26,BS연결,MATCH(E$1,BS연결H,0),0)/100,"") | G26: =IFERROR(VLOOKUP($D26,BS연결,MATCH(G$1,BS연결H,0),0)/100,"") | H26: =IFERROR(VLOOKUP($D26,BS연결,MATCH(H$1,BS연결H,0),0)/100,"") | I26: =IFERROR(VLOOKUP($D26,BS연결,MATCH(I$1,BS연결H,0),0)/100,"") | J26: =IFERROR(VLOOKUP($D26,BS연결,MATCH(J$1,BS연결H,0),0)/100,"") | K26: =IFERROR(VLOOKUP($D26,BS연결,MATCH(K$1,BS연결H,0),0)/100,"") | L26: =IFERROR(VLOOKUP($D26,BS연결,MATCH(L$1,BS연결H,0),0)/100,"") | M26: =IFERROR(VLOOKUP($D26,BS연결,MATCH(M$1,BS연결H,0),0)/100,"") | N26: =IFERROR(VLOOKUP($D26,BS연결,MATCH(N$1,BS연결H,0),0)/100,"") | ... AB26: =IFERROR(VLOOKUP($D26,BS연결,MATCH(AB$1,BS연결H,0),0)/100,"") | AC26: =IFERROR(X26*(1+변수!AC33),"") | AD26: =IFERROR(Y26*(1+변수!AD33),"") | AE26: =SUM(AA26:AD26) | AF26: =IFERROR(AA26*(1+변수!AF33),"") | AG26: =IFERROR(AB26*(1+변수!AG33),"") | AH26: =IFERROR(AC26*(1+변수!AH33),"") | AI26: =IFERROR(AD26*(1+변수!AI33),"") | AJ26: =SUM(AF26:AI26) | AK26: =IFERROR(AF26*(1+변수!AK33),"") | AL26: =IFERROR(AG26*(1+변수!AL33),"") | AM26: =IFERROR(AH26*(1+변수!AM33),"") | AN26: =IFERROR(AI26*(1+변수!AN33),"") | AO26: =SUM(AK26:AN26)
A27: 영업활동현금흐름 | B27: 현금흐름 | C27: 억원 | D27: 영업활동으로인한현금흐름 | E27: =IFERROR(VLOOKUP($D27,BS연결,MATCH(E$1,BS연결H,0),0)/100,"") | G27: =IFERROR(VLOOKUP($D27,BS연결,MATCH(G$1,BS연결H,0),0)/100,"") | H27: =IFERROR(VLOOKUP($D27,BS연결,MATCH(H$1,BS연결H,0),0)/100,"") | I27: =IFERROR(VLOOKUP($D27,BS연결,MATCH(I$1,BS연결H,0),0)/100,"") | J27: =IFERROR(VLOOKUP($D27,BS연결,MATCH(J$1,BS연결H,0),0)/100,"") | K27: =IFERROR(VLOOKUP($D27,BS연결,MATCH(K$1,BS연결H,0),0)/100,"") | L27: =IFERROR(VLOOKUP($D27,BS연결,MATCH(L$1,BS연결H,0),0)/100,"") | M27: =IFERROR(VLOOKUP($D27,BS연결,MATCH(M$1,BS연결H,0),0)/100,"") | N27: =IFERROR(VLOOKUP($D27,BS연결,MATCH(N$1,BS연결H,0),0)/100,"") | ... AB27: =IFERROR(VLOOKUP($D27,BS연결,MATCH(AB$1,BS연결H,0),0)/100,"") | AE27: =SUM(AA27:AD27) | AJ27: =SUM(AF27:AI27) | AO27: =SUM(AK27:AN27)
A28: 주식수 | B28: 주당 | C28: 백만주 | D28: 유통주식수 | E28: 9.321 | F28: =E28 | G28: 9.321 | H28: 9.323 | I28: 9.323 | J28: 9.324 | K28: =J28 | L28: 9.324 | M28: 9.245 | N28: 9.241 | O28: 9.242 | P28: =O28 | Q28: 9.242 | R28: 9.244 | S28: 9.244 | T28: 9.244 | U28: =T28 | V28: 9.244 | W28: 9.246 | X28: 9.246 | Y28: 9.269 | Z28: =Y28 | AA28: 9.269 | AB28: 9.292 | AC28: =IFERROR(AB28*(1+변수!AC35),"") | AD28: =IFERROR(AC28*(1+변수!AD35),"") | AE28: =AD28 | AF28: =IFERROR(AD28*(1+변수!AF35),"") | AG28: =IFERROR(AF28*(1+변수!AG35),"") | AH28: =IFERROR(AG28*(1+변수!AH35),"") | AI28: =IFERROR(AH28*(1+변수!AI35),"") | AJ28: =AI28 | AK28: =IFERROR(AI28*(1+변수!AK35),"") | AL28: =IFERROR(AK28*(1+변수!AL35),"") | AM28: =IFERROR(AL28*(1+변수!AM35),"") | AN28: =IFERROR(AM28*(1+변수!AN35),"") | AO28: =AN28
A29: EPS | B29: 주당 | C29: 원 | D29: EPS | E29: =IFERROR(E17*100/E28,"") | G29: =IFERROR(G17*100/G28,"") | H29: =IFERROR(H17*100/H28,"") | I29: =IFERROR(I17*100/I28,"") | J29: =IFERROR(J17*100/J28,"") | K29: =SUM(G29:J29) | L29: =IFERROR(L17*100/L28,"") | M29: =IFERROR(M17*100/M28,"") | N29: =IFERROR(N17*100/N28,"") | O29: =IFERROR(O17*100/O28,"") | P29: =SUM(L29:O29) | Q29: =IFERROR(Q17*100/Q28,"") | R29: =IFERROR(R17*100/R28,"") | S29: =IFERROR(S17*100/S28,"") | T29: =IFERROR(T17*100/T28,"") | U29: =SUM(Q29:T29) | V29: =IFERROR(V17*100/V28,"") | W29: =IFERROR(W17*100/W28,"") | X29: =IFERROR(X17*100/X28,"") | Y29: =IFERROR(Y17*100/Y28,"") | Z29: =SUM(V29:Y29) | AA29: =IFERROR(AA17*100/AA28,"") | AB29: =IFERROR(AB17*100/AB28,"") | AC29: =IFERROR(AC17*100/AC28,"") | AD29: =IFERROR(AD17*100/AD28,"") | AE29: =SUM(AA29:AD29) | AF29: =IFERROR(AF17*100/AF28,"") | AG29: =IFERROR(AG17*100/AG28,"") | AH29: =IFERROR(AH17*100/AH28,"") | AI29: =IFERROR(AI17*100/AI28,"") | AJ29: =SUM(AF29:AI29) | AK29: =IFERROR(AK17*100/AK28,"") | AL29: =IFERROR(AL17*100/AL28,"") | AM29: =IFERROR(AM17*100/AM28,"") | AN29: =IFERROR(AN17*100/AN28,"") | AO29: =SUM(AK29:AN29)
A30: BPS | B30: 주당 | C30: 원 | D30: BPS | E30: =IFERROR(E23*100/E28,"") | F30: =E30 | G30: =IFERROR(G23*100/G28,"") | H30: =IFERROR(H23*100/H28,"") | I30: =IFERROR(I23*100/I28,"") | J30: =IFERROR(J23*100/J28,"") | K30: =J30 | L30: =IFERROR(L23*100/L28,"") | M30: =IFERROR(M23*100/M28,"") | N30: =IFERROR(N23*100/N28,"") | O30: =IFERROR(O23*100/O28,"") | P30: =O30 | Q30: =IFERROR(Q23*100/Q28,"") | R30: =IFERROR(R23*100/R28,"") | S30: =IFERROR(S23*100/S28,"") | T30: =IFERROR(T23*100/T28,"") | U30: =T30 | V30: =IFERROR(V23*100/V28,"") | W30: =IFERROR(W23*100/W28,"") | X30: =IFERROR(X23*100/X28,"") | Y30: =IFERROR(Y23*100/Y28,"") | Z30: =Y30 | AA30: =IFERROR(AA23*100/AA28,"") | AB30: =IFERROR(AB23*100/AB28,"") | AC30: =IFERROR(AC23*100/AC28,"") | AD30: =IFERROR(AD23*100/AD28,"") | AE30: =AD30 | AF30: =IFERROR(AF23*100/AF28,"") | AG30: =IFERROR(AG23*100/AG28,"") | AH30: =IFERROR(AH23*100/AH28,"") | AI30: =IFERROR(AI23*100/AI28,"") | AJ30: =AI30 | AK30: =IFERROR(AK23*100/AK28,"") | AL30: =IFERROR(AL23*100/AL28,"") | AM30: =IFERROR(AM23*100/AM28,"") | AN30: =IFERROR(AN23*100/AN28,"") | AO30: =AN30
A31: DPS | B31: 주당 | C31: 원 | D31: DPS(보통주) | E31: 100 | F31: 100 | J31: 0 | K31: =SUM(G31:J31) | O31: 0 | P31: =SUM(L31:O31) | T31: 100 | U31: =SUM(Q31:T31) | Y31: 200 | Z31: =SUM(V31:Y31) | AD31: =변수!AD36 | AE31: =SUM(AA31:AD31) | AI31: =변수!AI36 | AJ31: =SUM(AF31:AI31) | AN31: =변수!AN36 | AO31: =SUM(AK31:AN31)
A32: PER | B32: 주당 | C32: 배 | D32: PER | F32: =E32 | I32: =IFERROR(변수!I18/(E29+G29+H29+I29),"") | K32: =J32 | O32: =IFERROR(변수!O18/(L29+M29+N29+O29),"") | P32: =O32 | Q32: =IFERROR(변수!Q18/(M29+N29+O29+Q29),"") | R32: =IFERROR(변수!R18/(N29+O29+Q29+R29),"") | S32: =IFERROR(변수!S18/(O29+Q29+R29+S29),"") | T32: =IFERROR(변수!T18/(Q29+R29+S29+T29),"") | U32: =T32 | V32: =IFERROR(변수!V18/(R29+S29+T29+V29),"") | W32: =IFERROR(변수!W18/(S29+T29+V29+W29),"") | X32: =IFERROR(변수!X18/(T29+V29+W29+X29),"") | Y32: =IFERROR(변수!Y18/(V29+W29+X29+Y29),"") | Z32: =Y32 | AA32: =IFERROR(변수!AA18/(W29+X29+Y29+AA29),"") | AB32: =IFERROR(변수!AB18/(X29+Y29+AA29+AB29),"") | AC32: =IFERROR(변수!$D$39/(Y29+AA29+AB29+AC29),"") | AD32: =IFERROR(변수!$D$39/(AA29+AB29+AC29+AD29),"") | AE32: =AD32 | AF32: =IFERROR(변수!$D$39/(AB29+AC29+AD29+AF29),"") | AG32: =IFERROR(변수!$D$39/(AC29+AD29+AF29+AG29),"") | AH32: =IFERROR(변수!$D$39/(AD29+AF29+AG29+AH29),"") | AI32: =IFERROR(변수!$D$39/(AF29+AG29+AH29+AI29),"") | AJ32: =AI32 | AK32: =IFERROR(변수!$D$39/(AG29+AH29+AI29+AK29),"") | AL32: =IFERROR(변수!$D$39/(AH29+AI29+AK29+AL29),"") | AM32: =IFERROR(변수!$D$39/(AI29+AK29+AL29+AM29),"") | AN32: =IFERROR(변수!$D$39/(AK29+AL29+AM29+AN29),"") | AO32: =AN32
A33: PBR | B33: 주당 | C33: 배 | D33: PBR | E33: =IFERROR(변수!E18/E30,"") | F33: =E33 | G33: =IFERROR(변수!G18/G30,"") | H33: =IFERROR(변수!H18/H30,"") | I33: =IFERROR(변수!I18/I30,"") | J33: =IFERROR(변수!J18/J30,"") | K33: =J33 | L33: =IFERROR(변수!L18/L30,"") | M33: =IFERROR(변수!M18/M30,"") | N33: =IFERROR(변수!N18/N30,"") | O33: =IFERROR(변수!O18/O30,"") | P33: =O33 | Q33: =IFERROR(변수!Q18/Q30,"") | R33: =IFERROR(변수!R18/R30,"") | S33: =IFERROR(변수!S18/S30,"") | T33: =IFERROR(변수!T18/T30,"") | U33: =T33 | V33: =IFERROR(변수!V18/V30,"") | W33: =IFERROR(변수!W18/W30,"") | X33: =IFERROR(변수!X18/X30,"") | Y33: =IFERROR(변수!Y18/Y30,"") | Z33: =Y33 | AA33: =IFERROR(변수!AA18/AA30,"") | AB33: =IFERROR(변수!AB18/AB30,"") | AC33: =IFERROR(변수!$D$39/AC30,"") | AD33: =IFERROR(변수!$D$39/AD30,"") | AE33: =AD33 | AF33: =IFERROR(변수!$D$39/AF30,"") | AG33: =IFERROR(변수!$D$39/AG30,"") | AH33: =IFERROR(변수!$D$39/AH30,"") | AI33: =IFERROR(변수!$D$39/AI30,"") | AJ33: =AI33 | AK33: =IFERROR(변수!$D$39/AK30,"") | AL33: =IFERROR(변수!$D$39/AL30,"") | AM33: =IFERROR(변수!$D$39/AM30,"") | AN33: =IFERROR(변수!$D$39/AN30,"") | AO33: =AN33
A34: 매출전사 | B34: 사업부 | C34: 억원 | D34: 매출 전사(부문 미분리) | E34: 403.64 | G34: 307.6 | H34: 347.27 | I34: 313.42 | J34: 335.67 | K34: =SUM(G34:J34) | L34: 321.58 | M34: 348.9 | N34: 372.05 | O34: 500.95 | P34: =SUM(L34:O34) | Q34: 413.55 | R34: 499 | S34: 447.37 | T34: 602.87 | U34: =SUM(Q34:T34) | V34: 556.4 | W34: 563.26 | X34: 615.33 | Y34: 565.96 | Z34: =SUM(V34:Y34) | AA34: 508.96 | AB34: 708.34 | AC34: =IFERROR(AC5,"") | AD34: =IFERROR(AD5,"") | AE34: =SUM(AA34:AD34) | AF34: =IFERROR(AF5,"") | AG34: =IFERROR(AG5,"") | AH34: =IFERROR(AH5,"") | AI34: =IFERROR(AI5,"") | AJ34: =SUM(AF34:AI34) | AK34: =IFERROR(AK5,"") | AL34: =IFERROR(AL5,"") | AM34: =IFERROR(AM5,"") | AN34: =IFERROR(AN5,"") | AO34: =SUM(AK34:AN34)
A35: OP전사 | B35: 사업부 | C35: 억원 | D35: OP 전사(부문 미분리) | E35: 5.31 | G35: -17.26 | H35: -19.12 | I35: 3.65 | J35: -66.13 | K35: =SUM(G35:J35) | L35: -9.31 | M35: 2.67 | N35: 17.2 | O35: 26.78 | P35: =SUM(L35:O35) | Q35: 23.78 | R35: 30.62 | S35: 29.15 | T35: 73.31 | U35: =SUM(Q35:T35) | V35: 57.11 | W35: 57.82 | X35: 77.43 | Y35: 78.24 | Z35: =SUM(V35:Y35) | AA35: 62.74 | AB35: 75.59 | AC35: =IFERROR(AC9,"") | AD35: =IFERROR(AD9,"") | AE35: =SUM(AA35:AD35) | AF35: =IFERROR(AF9,"") | AG35: =IFERROR(AG9,"") | AH35: =IFERROR(AH9,"") | AI35: =IFERROR(AI9,"") | AJ35: =SUM(AF35:AI35) | AK35: =IFERROR(AK9,"") | AL35: =IFERROR(AL9,"") | AM35: =IFERROR(AM9,"") | AN35: =IFERROR(AN9,"") | AO35: =SUM(AK35:AN35)
B36: 비율(참고)
A37: NPM | C37: % | D37: 지배주주순이익 / 매출액 | E37: =IFERROR(E17/E5,"") | F37: =IFERROR(F17/F5,"") | G37: =IFERROR(G17/G5,"") | H37: =IFERROR(H17/H5,"") | I37: =IFERROR(I17/I5,"") | J37: =IFERROR(J17/J5,"") | K37: =IFERROR(K17/K5,"") | L37: =IFERROR(L17/L5,"") | ... AO37: =IFERROR(AO17/AO5,"")
A38: 매출원가율 | C38: % | D38: 매출원가 / 매출액 | E38: =IFERROR(E6/E5,"") | F38: =IFERROR(F6/F5,"") | G38: =IFERROR(G6/G5,"") | H38: =IFERROR(H6/H5,"") | I38: =IFERROR(I6/I5,"") | J38: =IFERROR(J6/J5,"") | K38: =IFERROR(K6/K5,"") | L38: =IFERROR(L6/L5,"") | ... AO38: =IFERROR(AO6/AO5,"")
A39: 판관비율 | C39: % | D39: 판관비 / 매출액 | E39: =IFERROR(E8/E5,"") | F39: =IFERROR(F8/F5,"") | G39: =IFERROR(G8/G5,"") | H39: =IFERROR(H8/H5,"") | I39: =IFERROR(I8/I5,"") | J39: =IFERROR(J8/J5,"") | K39: =IFERROR(K8/K5,"") | L39: =IFERROR(L8/L5,"") | ... AO39: =IFERROR(AO8/AO5,"")

Sheet 분기
C1: 이름: 분기H — subQ 를 이름으로 VLOOKUP(억원) | E1: 4Q21 | F1: 1Q22 | G1: 2Q22 | H1: 3Q22 | I1: 4Q22 | J1: 1Q23 | K1: 2Q23 | L1: 3Q23 | M1: 4Q23 | N1: 1Q24 | O1: 2Q24 | P1: 3Q24 | Q1: 4Q24 | R1: 1Q25 | S1: 2Q25 | T1: 3Q25 | U1: 4Q25 | V1: 1Q26 | W1: 2Q26 | X1: 3Q26 | Y1: 4Q26 | Z1: 1Q27 | AA1: 2Q27 | AB1: 3Q27 | AC1: 4Q27 | AD1: 1Q28 | AE1: 2Q28 | AF1: 3Q28 | AG1: 4Q28
C2: 종가: | D2: =변수!D39
C3: 기준일: | D3: 20261026 | E3: 1 | F3: 2 | G3: 3 | H3: 4 | I3: 5 | J3: 6 | K3: 7 | L3: 8 | M3: 9 | N3: 10 | O3: 11 | P3: 12 | Q3: 13 | R3: 14 | S3: 15 | T3: 16 | U3: 17 | V3: 18 | W3: 19 | X3: 20 | Y3: 21 | Z3: 22 | AA3: 23 | AB3: 24 | AC3: 25 | AD3: 26 | AE3: 27 | AF3: 28 | AG3: 29
E4: 2021.12 | F4: 2022.03 | G4: 2022.06 | H4: 2022.09 | I4: 2022.12 | J4: 2023.03 | K4: 2023.06 | L4: 2023.09 | M4: 2023.12 | N4: 2024.03 | O4: 2024.06 | P4: 2024.09 | Q4: 2024.12 | R4: 2025.03 | S4: 2025.06 | T4: 2025.09 | U4: 2025.12 | V4: 2026.03 | W4: 2026.06 | X4: 2026.09 | Y4: 2026.12 | Z4: 2027.03 | AA4: 2027.06 | AB4: 2027.09 | AC4: 2027.12 | AD4: 2028.03 | AE4: 2028.06 | AF4: 2028.09 | AG4: 2028.12
A5: 매출액 | D5: 매출액 | E5: =IFERROR(VLOOKUP($A5,subQ,MATCH(E$1,SUBQH,0),0),"") | F5: =IFERROR(VLOOKUP($A5,subQ,MATCH(F$1,SUBQH,0),0),"") | G5: =IFERROR(VLOOKUP($A5,subQ,MATCH(G$1,SUBQH,0),0),"") | H5: =IFERROR(VLOOKUP($A5,subQ,MATCH(H$1,SUBQH,0),0),"") | I5: =IFERROR(VLOOKUP($A5,subQ,MATCH(I$1,SUBQH,0),0),"") | J5: =IFERROR(VLOOKUP($A5,subQ,MATCH(J$1,SUBQH,0),0),"") | K5: =IFERROR(VLOOKUP($A5,subQ,MATCH(K$1,SUBQH,0),0),"") | L5: =IFERROR(VLOOKUP($A5,subQ,MATCH(L$1,SUBQH,0),0),"") | ... AG5: =IFERROR(VLOOKUP($A5,subQ,MATCH(AG$1,SUBQH,0),0),"")
A6: 매출원가 | D6: 매출원가 | E6: =IFERROR(VLOOKUP($A6,subQ,MATCH(E$1,SUBQH,0),0),"") | F6: =IFERROR(VLOOKUP($A6,subQ,MATCH(F$1,SUBQH,0),0),"") | G6: =IFERROR(VLOOKUP($A6,subQ,MATCH(G$1,SUBQH,0),0),"") | H6: =IFERROR(VLOOKUP($A6,subQ,MATCH(H$1,SUBQH,0),0),"") | I6: =IFERROR(VLOOKUP($A6,subQ,MATCH(I$1,SUBQH,0),0),"") | J6: =IFERROR(VLOOKUP($A6,subQ,MATCH(J$1,SUBQH,0),0),"") | K6: =IFERROR(VLOOKUP($A6,subQ,MATCH(K$1,SUBQH,0),0),"") | L6: =IFERROR(VLOOKUP($A6,subQ,MATCH(L$1,SUBQH,0),0),"") | ... AG6: =IFERROR(VLOOKUP($A6,subQ,MATCH(AG$1,SUBQH,0),0),"")
A7: 매출총이익 | D7: 매출총이익 | E7: =IFERROR(VLOOKUP($A7,subQ,MATCH(E$1,SUBQH,0),0),"") | F7: =IFERROR(VLOOKUP($A7,subQ,MATCH(F$1,SUBQH,0),0),"") | G7: =IFERROR(VLOOKUP($A7,subQ,MATCH(G$1,SUBQH,0),0),"") | H7: =IFERROR(VLOOKUP($A7,subQ,MATCH(H$1,SUBQH,0),0),"") | I7: =IFERROR(VLOOKUP($A7,subQ,MATCH(I$1,SUBQH,0),0),"") | J7: =IFERROR(VLOOKUP($A7,subQ,MATCH(J$1,SUBQH,0),0),"") | K7: =IFERROR(VLOOKUP($A7,subQ,MATCH(K$1,SUBQH,0),0),"") | L7: =IFERROR(VLOOKUP($A7,subQ,MATCH(L$1,SUBQH,0),0),"") | ... AG7: =IFERROR(VLOOKUP($A7,subQ,MATCH(AG$1,SUBQH,0),0),"")
A8: 판관비 | D8: 판매비와관리비 | E8: =IFERROR(VLOOKUP($A8,subQ,MATCH(E$1,SUBQH,0),0),"") | F8: =IFERROR(VLOOKUP($A8,subQ,MATCH(F$1,SUBQH,0),0),"") | G8: =IFERROR(VLOOKUP($A8,subQ,MATCH(G$1,SUBQH,0),0),"") | H8: =IFERROR(VLOOKUP($A8,subQ,MATCH(H$1,SUBQH,0),0),"") | I8: =IFERROR(VLOOKUP($A8,subQ,MATCH(I$1,SUBQH,0),0),"") | J8: =IFERROR(VLOOKUP($A8,subQ,MATCH(J$1,SUBQH,0),0),"") | K8: =IFERROR(VLOOKUP($A8,subQ,MATCH(K$1,SUBQH,0),0),"") | L8: =IFERROR(VLOOKUP($A8,subQ,MATCH(L$1,SUBQH,0),0),"") | ... AG8: =IFERROR(VLOOKUP($A8,subQ,MATCH(AG$1,SUBQH,0),0),"")
A9: 영업이익 | D9: 영업이익 | E9: =IFERROR(VLOOKUP($A9,subQ,MATCH(E$1,SUBQH,0),0),"") | F9: =IFERROR(VLOOKUP($A9,subQ,MATCH(F$1,SUBQH,0),0),"") | G9: =IFERROR(VLOOKUP($A9,subQ,MATCH(G$1,SUBQH,0),0),"") | H9: =IFERROR(VLOOKUP($A9,subQ,MATCH(H$1,SUBQH,0),0),"") | I9: =IFERROR(VLOOKUP($A9,subQ,MATCH(I$1,SUBQH,0),0),"") | J9: =IFERROR(VLOOKUP($A9,subQ,MATCH(J$1,SUBQH,0),0),"") | K9: =IFERROR(VLOOKUP($A9,subQ,MATCH(K$1,SUBQH,0),0),"") | L9: =IFERROR(VLOOKUP($A9,subQ,MATCH(L$1,SUBQH,0),0),"") | ... AG9: =IFERROR(VLOOKUP($A9,subQ,MATCH(AG$1,SUBQH,0),0),"")
A10: OPM | D10: 영업이익률 | E10: =IFERROR(VLOOKUP($A10,subQ,MATCH(E$1,SUBQH,0),0),"") | F10: =IFERROR(VLOOKUP($A10,subQ,MATCH(F$1,SUBQH,0),0),"") | G10: =IFERROR(VLOOKUP($A10,subQ,MATCH(G$1,SUBQH,0),0),"") | H10: =IFERROR(VLOOKUP($A10,subQ,MATCH(H$1,SUBQH,0),0),"") | I10: =IFERROR(VLOOKUP($A10,subQ,MATCH(I$1,SUBQH,0),0),"") | J10: =IFERROR(VLOOKUP($A10,subQ,MATCH(J$1,SUBQH,0),0),"") | K10: =IFERROR(VLOOKUP($A10,subQ,MATCH(K$1,SUBQH,0),0),"") | L10: =IFERROR(VLOOKUP($A10,subQ,MATCH(L$1,SUBQH,0),0),"") | ... AG10: =IFERROR(VLOOKUP($A10,subQ,MATCH(AG$1,SUBQH,0),0),"")
A11: 금융손익 | D11: 금융손익(이자·환 포함) | E11: =IFERROR(VLOOKUP($A11,subQ,MATCH(E$1,SUBQH,0),0),"") | F11: =IFERROR(VLOOKUP($A11,subQ,MATCH(F$1,SUBQH,0),0),"") | G11: =IFERROR(VLOOKUP($A11,subQ,MATCH(G$1,SUBQH,0),0),"") | H11: =IFERROR(VLOOKUP($A11,subQ,MATCH(H$1,SUBQH,0),0),"") | I11: =IFERROR(VLOOKUP($A11,subQ,MATCH(I$1,SUBQH,0),0),"") | J11: =IFERROR(VLOOKUP($A11,subQ,MATCH(J$1,SUBQH,0),0),"") | K11: =IFERROR(VLOOKUP($A11,subQ,MATCH(K$1,SUBQH,0),0),"") | L11: =IFERROR(VLOOKUP($A11,subQ,MATCH(L$1,SUBQH,0),0),"") | ... AG11: =IFERROR(VLOOKUP($A11,subQ,MATCH(AG$1,SUBQH,0),0),"")
A12: 이자손익 | D12: 이자손익(이자수익 − 이자비용) | E12: =IFERROR(VLOOKUP($A12,subQ,MATCH(E$1,SUBQH,0),0),"") | F12: =IFERROR(VLOOKUP($A12,subQ,MATCH(F$1,SUBQH,0),0),"") | G12: =IFERROR(VLOOKUP($A12,subQ,MATCH(G$1,SUBQH,0),0),"") | H12: =IFERROR(VLOOKUP($A12,subQ,MATCH(H$1,SUBQH,0),0),"") | I12: =IFERROR(VLOOKUP($A12,subQ,MATCH(I$1,SUBQH,0),0),"") | J12: =IFERROR(VLOOKUP($A12,subQ,MATCH(J$1,SUBQH,0),0),"") | K12: =IFERROR(VLOOKUP($A12,subQ,MATCH(K$1,SUBQH,0),0),"") | L12: =IFERROR(VLOOKUP($A12,subQ,MATCH(L$1,SUBQH,0),0),"") | ... AG12: =IFERROR(VLOOKUP($A12,subQ,MATCH(AG$1,SUBQH,0),0),"")
A13: 기타영업외손익 | D13: 기타영업외손익 | E13: =IFERROR(VLOOKUP($A13,subQ,MATCH(E$1,SUBQH,0),0),"") | F13: =IFERROR(VLOOKUP($A13,subQ,MATCH(F$1,SUBQH,0),0),"") | G13: =IFERROR(VLOOKUP($A13,subQ,MATCH(G$1,SUBQH,0),0),"") | H13: =IFERROR(VLOOKUP($A13,subQ,MATCH(H$1,SUBQH,0),0),"") | I13: =IFERROR(VLOOKUP($A13,subQ,MATCH(I$1,SUBQH,0),0),"") | J13: =IFERROR(VLOOKUP($A13,subQ,MATCH(J$1,SUBQH,0),0),"") | K13: =IFERROR(VLOOKUP($A13,subQ,MATCH(K$1,SUBQH,0),0),"") | L13: =IFERROR(VLOOKUP($A13,subQ,MATCH(L$1,SUBQH,0),0),"") | ... AG13: =IFERROR(VLOOKUP($A13,subQ,MATCH(AG$1,SUBQH,0),0),"")
A14: 세전이익 | D14: 법인세비용차감전이익 | E14: =IFERROR(VLOOKUP($A14,subQ,MATCH(E$1,SUBQH,0),0),"") | F14: =IFERROR(VLOOKUP($A14,subQ,MATCH(F$1,SUBQH,0),0),"") | G14: =IFERROR(VLOOKUP($A14,subQ,MATCH(G$1,SUBQH,0),0),"") | H14: =IFERROR(VLOOKUP($A14,subQ,MATCH(H$1,SUBQH,0),0),"") | I14: =IFERROR(VLOOKUP($A14,subQ,MATCH(I$1,SUBQH,0),0),"") | J14: =IFERROR(VLOOKUP($A14,subQ,MATCH(J$1,SUBQH,0),0),"") | K14: =IFERROR(VLOOKUP($A14,subQ,MATCH(K$1,SUBQH,0),0),"") | L14: =IFERROR(VLOOKUP($A14,subQ,MATCH(L$1,SUBQH,0),0),"") | ... AG14: =IFERROR(VLOOKUP($A14,subQ,MATCH(AG$1,SUBQH,0),0),"")
A15: 법인세비용 | D15: 법인세비용 | E15: =IFERROR(VLOOKUP($A15,subQ,MATCH(E$1,SUBQH,0),0),"") | F15: =IFERROR(VLOOKUP($A15,subQ,MATCH(F$1,SUBQH,0),0),"") | G15: =IFERROR(VLOOKUP($A15,subQ,MATCH(G$1,SUBQH,0),0),"") | H15: =IFERROR(VLOOKUP($A15,subQ,MATCH(H$1,SUBQH,0),0),"") | I15: =IFERROR(VLOOKUP($A15,subQ,MATCH(I$1,SUBQH,0),0),"") | J15: =IFERROR(VLOOKUP($A15,subQ,MATCH(J$1,SUBQH,0),0),"") | K15: =IFERROR(VLOOKUP($A15,subQ,MATCH(K$1,SUBQH,0),0),"") | L15: =IFERROR(VLOOKUP($A15,subQ,MATCH(L$1,SUBQH,0),0),"") | ... AG15: =IFERROR(VLOOKUP($A15,subQ,MATCH(AG$1,SUBQH,0),0),"")
A16: 당기순이익 | D16: 당기순이익 | E16: =IFERROR(VLOOKUP($A16,subQ,MATCH(E$1,SUBQH,0),0),"") | F16: =IFERROR(VLOOKUP($A16,subQ,MATCH(F$1,SUBQH,0),0),"") | G16: =IFERROR(VLOOKUP($A16,subQ,MATCH(G$1,SUBQH,0),0),"") | H16: =IFERROR(VLOOKUP($A16,subQ,MATCH(H$1,SUBQH,0),0),"") | I16: =IFERROR(VLOOKUP($A16,subQ,MATCH(I$1,SUBQH,0),0),"") | J16: =IFERROR(VLOOKUP($A16,subQ,MATCH(J$1,SUBQH,0),0),"") | K16: =IFERROR(VLOOKUP($A16,subQ,MATCH(K$1,SUBQH,0),0),"") | L16: =IFERROR(VLOOKUP($A16,subQ,MATCH(L$1,SUBQH,0),0),"") | ... AG16: =IFERROR(VLOOKUP($A16,subQ,MATCH(AG$1,SUBQH,0),0),"")
... A36: NPM | D36: NPM | E36: =IFERROR(VLOOKUP($A36,subQ,MATCH(E$1,SUBQH,0),0),"") | F36: =IFERROR(VLOOKUP($A36,subQ,MATCH(F$1,SUBQH,0),0),"") | G36: =IFERROR(VLOOKUP($A36,subQ,MATCH(G$1,SUBQH,0),0),"") | H36: =IFERROR(VLOOKUP($A36,subQ,MATCH(H$1,SUBQH,0),0),"") | I36: =IFERROR(VLOOKUP($A36,subQ,MATCH(I$1,SUBQH,0),0),"") | J36: =IFERROR(VLOOKUP($A36,subQ,MATCH(J$1,SUBQH,0),0),"") | K36: =IFERROR(VLOOKUP($A36,subQ,MATCH(K$1,SUBQH,0),0),"") | L36: =IFERROR(VLOOKUP($A36,subQ,MATCH(L$1,SUBQH,0),0),"") | ... AG36: =IFERROR(VLOOKUP($A36,subQ,MATCH(AG$1,SUBQH,0),0),"")
A37: 매출액 YoY | D37: 매출액 YoY | I37: =IFERROR(I5/E5-1,"") | J37: =IFERROR(J5/F5-1,"") | K37: =IFERROR(K5/G5-1,"") | L37: =IFERROR(L5/H5-1,"") | M37: =IFERROR(M5/I5-1,"") | N37: =IFERROR(N5/J5-1,"") | O37: =IFERROR(O5/K5-1,"") | P37: =IFERROR(P5/L5-1,"") | ... AG37: =IFERROR(AG5/AC5-1,"")
A38: 영업이익 YoY | D38: 영업이익 YoY | I38: =IFERROR(I9/E9-1,"") | J38: =IFERROR(J9/F9-1,"") | K38: =IFERROR(K9/G9-1,"") | L38: =IFERROR(L9/H9-1,"") | M38: =IFERROR(M9/I9-1,"") | N38: =IFERROR(N9/J9-1,"") | O38: =IFERROR(O9/K9-1,"") | P38: =IFERROR(P9/L9-1,"") | ... AG38: =IFERROR(AG9/AC9-1,"")
A39: 지배주주순이익 YoY | D39: 지배주주순이익 YoY | I39: =IFERROR(I17/E17-1,"") | J39: =IFERROR(J17/F17-1,"") | K39: =IFERROR(K17/G17-1,"") | L39: =IFERROR(L17/H17-1,"") | M39: =IFERROR(M17/I17-1,"") | N39: =IFERROR(N17/J17-1,"") | O39: =IFERROR(O17/K17-1,"") | P39: =IFERROR(P17/L17-1,"") | ... AG39: =IFERROR(AG17/AC17-1,"")

Sheet 연간예상
C1: 이름: 연간예상H — subQ 를 이름으로 VLOOKUP(억원) | E1: 2021 | F1: 2022 | G1: 2023 | H1: 2024 | I1: 2025 | J1: 2026 | K1: 2027 | L1: 2028
C2: 종가: | D2: =변수!D39
C3: 기준일: | D3: 20261026 | E3: 1 | F3: 2 | G3: 3 | H3: 4 | I3: 5 | J3: 6 | K3: 7 | L3: 8
E4: 2021.12A | F4: 2022.12A | G4: 2023.12A | H4: 2024.12A | I4: 2025.12A | J4: 2026.12A | K4: 2027.12A | L4: 2028.12A
A5: 매출액 | D5: 매출액 | E5: =IFERROR(VLOOKUP($A5,subQ,MATCH(E$1,SUBQH,0),0),"") | F5: =IFERROR(VLOOKUP($A5,subQ,MATCH(F$1,SUBQH,0),0),"") | G5: =IFERROR(VLOOKUP($A5,subQ,MATCH(G$1,SUBQH,0),0),"") | H5: =IFERROR(VLOOKUP($A5,subQ,MATCH(H$1,SUBQH,0),0),"") | I5: =IFERROR(VLOOKUP($A5,subQ,MATCH(I$1,SUBQH,0),0),"") | J5: =IFERROR(VLOOKUP($A5,subQ,MATCH(J$1,SUBQH,0),0),"") | K5: =IFERROR(VLOOKUP($A5,subQ,MATCH(K$1,SUBQH,0),0),"") | L5: =IFERROR(VLOOKUP($A5,subQ,MATCH(L$1,SUBQH,0),0),"")
A6: 매출원가 | D6: 매출원가 | E6: =IFERROR(VLOOKUP($A6,subQ,MATCH(E$1,SUBQH,0),0),"") | F6: =IFERROR(VLOOKUP($A6,subQ,MATCH(F$1,SUBQH,0),0),"") | G6: =IFERROR(VLOOKUP($A6,subQ,MATCH(G$1,SUBQH,0),0),"") | H6: =IFERROR(VLOOKUP($A6,subQ,MATCH(H$1,SUBQH,0),0),"") | I6: =IFERROR(VLOOKUP($A6,subQ,MATCH(I$1,SUBQH,0),0),"") | J6: =IFERROR(VLOOKUP($A6,subQ,MATCH(J$1,SUBQH,0),0),"") | K6: =IFERROR(VLOOKUP($A6,subQ,MATCH(K$1,SUBQH,0),0),"") | L6: =IFERROR(VLOOKUP($A6,subQ,MATCH(L$1,SUBQH,0),0),"")
A7: 매출총이익 | D7: 매출총이익 | E7: =IFERROR(VLOOKUP($A7,subQ,MATCH(E$1,SUBQH,0),0),"") | F7: =IFERROR(VLOOKUP($A7,subQ,MATCH(F$1,SUBQH,0),0),"") | G7: =IFERROR(VLOOKUP($A7,subQ,MATCH(G$1,SUBQH,0),0),"") | H7: =IFERROR(VLOOKUP($A7,subQ,MATCH(H$1,SUBQH,0),0),"") | I7: =IFERROR(VLOOKUP($A7,subQ,MATCH(I$1,SUBQH,0),0),"") | J7: =IFERROR(VLOOKUP($A7,subQ,MATCH(J$1,SUBQH,0),0),"") | K7: =IFERROR(VLOOKUP($A7,subQ,MATCH(K$1,SUBQH,0),0),"") | L7: =IFERROR(VLOOKUP($A7,subQ,MATCH(L$1,SUBQH,0),0),"")
A8: 판관비 | D8: 판매비와관리비 | E8: =IFERROR(VLOOKUP($A8,subQ,MATCH(E$1,SUBQH,0),0),"") | F8: =IFERROR(VLOOKUP($A8,subQ,MATCH(F$1,SUBQH,0),0),"") | G8: =IFERROR(VLOOKUP($A8,subQ,MATCH(G$1,SUBQH,0),0),"") | H8: =IFERROR(VLOOKUP($A8,subQ,MATCH(H$1,SUBQH,0),0),"") | I8: =IFERROR(VLOOKUP($A8,subQ,MATCH(I$1,SUBQH,0),0),"") | J8: =IFERROR(VLOOKUP($A8,subQ,MATCH(J$1,SUBQH,0),0),"") | K8: =IFERROR(VLOOKUP($A8,subQ,MATCH(K$1,SUBQH,0),0),"") | L8: =IFERROR(VLOOKUP($A8,subQ,MATCH(L$1,SUBQH,0),0),"")
A9: 영업이익 | D9: 영업이익 | E9: =IFERROR(VLOOKUP($A9,subQ,MATCH(E$1,SUBQH,0),0),"") | F9: =IFERROR(VLOOKUP($A9,subQ,MATCH(F$1,SUBQH,0),0),"") | G9: =IFERROR(VLOOKUP($A9,subQ,MATCH(G$1,SUBQH,0),0),"") | H9: =IFERROR(VLOOKUP($A9,subQ,MATCH(H$1,SUBQH,0),0),"") | I9: =IFERROR(VLOOKUP($A9,subQ,MATCH(I$1,SUBQH,0),0),"") | J9: =IFERROR(VLOOKUP($A9,subQ,MATCH(J$1,SUBQH,0),0),"") | K9: =IFERROR(VLOOKUP($A9,subQ,MATCH(K$1,SUBQH,0),0),"") | L9: =IFERROR(VLOOKUP($A9,subQ,MATCH(L$1,SUBQH,0),0),"")
A10: OPM | D10: 영업이익률 | E10: =IFERROR(VLOOKUP($A10,subQ,MATCH(E$1,SUBQH,0),0),"") | F10: =IFERROR(VLOOKUP($A10,subQ,MATCH(F$1,SUBQH,0),0),"") | G10: =IFERROR(VLOOKUP($A10,subQ,MATCH(G$1,SUBQH,0),0),"") | H10: =IFERROR(VLOOKUP($A10,subQ,MATCH(H$1,SUBQH,0),0),"") | I10: =IFERROR(VLOOKUP($A10,subQ,MATCH(I$1,SUBQH,0),0),"") | J10: =IFERROR(VLOOKUP($A10,subQ,MATCH(J$1,SUBQH,0),0),"") | K10: =IFERROR(VLOOKUP($A10,subQ,MATCH(K$1,SUBQH,0),0),"") | L10: =IFERROR(VLOOKUP($A10,subQ,MATCH(L$1,SUBQH,0),0),"")
A11: 금융손익 | D11: 금융손익(이자·환 포함) | E11: =IFERROR(VLOOKUP($A11,subQ,MATCH(E$1,SUBQH,0),0),"") | F11: =IFERROR(VLOOKUP($A11,subQ,MATCH(F$1,SUBQH,0),0),"") | G11: =IFERROR(VLOOKUP($A11,subQ,MATCH(G$1,SUBQH,0),0),"") | H11: =IFERROR(VLOOKUP($A11,subQ,MATCH(H$1,SUBQH,0),0),"") | I11: =IFERROR(VLOOKUP($A11,subQ,MATCH(I$1,SUBQH,0),0),"") | J11: =IFERROR(VLOOKUP($A11,subQ,MATCH(J$1,SUBQH,0),0),"") | K11: =IFERROR(VLOOKUP($A11,subQ,MATCH(K$1,SUBQH,0),0),"") | L11: =IFERROR(VLOOKUP($A11,subQ,MATCH(L$1,SUBQH,0),0),"")
A12: 이자손익 | D12: 이자손익(이자수익 − 이자비용) | E12: =IFERROR(VLOOKUP($A12,subQ,MATCH(E$1,SUBQH,0),0),"") | F12: =IFERROR(VLOOKUP($A12,subQ,MATCH(F$1,SUBQH,0),0),"") | G12: =IFERROR(VLOOKUP($A12,subQ,MATCH(G$1,SUBQH,0),0),"") | H12: =IFERROR(VLOOKUP($A12,subQ,MATCH(H$1,SUBQH,0),0),"") | I12: =IFERROR(VLOOKUP($A12,subQ,MATCH(I$1,SUBQH,0),0),"") | J12: =IFERROR(VLOOKUP($A12,subQ,MATCH(J$1,SUBQH,0),0),"") | K12: =IFERROR(VLOOKUP($A12,subQ,MATCH(K$1,SUBQH,0),0),"") | L12: =IFERROR(VLOOKUP($A12,subQ,MATCH(L$1,SUBQH,0),0),"")
A13: 기타영업외손익 | D13: 기타영업외손익 | E13: =IFERROR(VLOOKUP($A13,subQ,MATCH(E$1,SUBQH,0),0),"") | F13: =IFERROR(VLOOKUP($A13,subQ,MATCH(F$1,SUBQH,0),0),"") | G13: =IFERROR(VLOOKUP($A13,subQ,MATCH(G$1,SUBQH,0),0),"") | H13: =IFERROR(VLOOKUP($A13,subQ,MATCH(H$1,SUBQH,0),0),"") | I13: =IFERROR(VLOOKUP($A13,subQ,MATCH(I$1,SUBQH,0),0),"") | J13: =IFERROR(VLOOKUP($A13,subQ,MATCH(J$1,SUBQH,0),0),"") | K13: =IFERROR(VLOOKUP($A13,subQ,MATCH(K$1,SUBQH,0),0),"") | L13: =IFERROR(VLOOKUP($A13,subQ,MATCH(L$1,SUBQH,0),0),"")
A14: 세전이익 | D14: 법인세비용차감전이익 | E14: =IFERROR(VLOOKUP($A14,subQ,MATCH(E$1,SUBQH,0),0),"") | F14: =IFERROR(VLOOKUP($A14,subQ,MATCH(F$1,SUBQH,0),0),"") | G14: =IFERROR(VLOOKUP($A14,subQ,MATCH(G$1,SUBQH,0),0),"") | H14: =IFERROR(VLOOKUP($A14,subQ,MATCH(H$1,SUBQH,0),0),"") | I14: =IFERROR(VLOOKUP($A14,subQ,MATCH(I$1,SUBQH,0),0),"") | J14: =IFERROR(VLOOKUP($A14,subQ,MATCH(J$1,SUBQH,0),0),"") | K14: =IFERROR(VLOOKUP($A14,subQ,MATCH(K$1,SUBQH,0),0),"") | L14: =IFERROR(VLOOKUP($A14,subQ,MATCH(L$1,SUBQH,0),0),"")
A15: 법인세비용 | D15: 법인세비용 | E15: =IFERROR(VLOOKUP($A15,subQ,MATCH(E$1,SUBQH,0),0),"") | F15: =IFERROR(VLOOKUP($A15,subQ,MATCH(F$1,SUBQH,0),0),"") | G15: =IFERROR(VLOOKUP($A15,subQ,MATCH(G$1,SUBQH,0),0),"") | H15: =IFERROR(VLOOKUP($A15,subQ,MATCH(H$1,SUBQH,0),0),"") | I15: =IFERROR(VLOOKUP($A15,subQ,MATCH(I$1,SUBQH,0),0),"") | J15: =IFERROR(VLOOKUP($A15,subQ,MATCH(J$1,SUBQH,0),0),"") | K15: =IFERROR(VLOOKUP($A15,subQ,MATCH(K$1,SUBQH,0),0),"") | L15: =IFERROR(VLOOKUP($A15,subQ,MATCH(L$1,SUBQH,0),0),"")
A16: 당기순이익 | D16: 당기순이익 | E16: =IFERROR(VLOOKUP($A16,subQ,MATCH(E$1,SUBQH,0),0),"") | F16: =IFERROR(VLOOKUP($A16,subQ,MATCH(F$1,SUBQH,0),0),"") | G16: =IFERROR(VLOOKUP($A16,subQ,MATCH(G$1,SUBQH,0),0),"") | H16: =IFERROR(VLOOKUP($A16,subQ,MATCH(H$1,SUBQH,0),0),"") | I16: =IFERROR(VLOOKUP($A16,subQ,MATCH(I$1,SUBQH,0),0),"") | J16: =IFERROR(VLOOKUP($A16,subQ,MATCH(J$1,SUBQH,0),0),"") | K16: =IFERROR(VLOOKUP($A16,subQ,MATCH(K$1,SUBQH,0),0),"") | L16: =IFERROR(VLOOKUP($A16,subQ,MATCH(L$1,SUBQH,0),0),"")
... A36: NPM | D36: NPM | E36: =IFERROR(VLOOKUP($A36,subQ,MATCH(E$1,SUBQH,0),0),"") | F36: =IFERROR(VLOOKUP($A36,subQ,MATCH(F$1,SUBQH,0),0),"") | G36: =IFERROR(VLOOKUP($A36,subQ,MATCH(G$1,SUBQH,0),0),"") | H36: =IFERROR(VLOOKUP($A36,subQ,MATCH(H$1,SUBQH,0),0),"") | I36: =IFERROR(VLOOKUP($A36,subQ,MATCH(I$1,SUBQH,0),0),"") | J36: =IFERROR(VLOOKUP($A36,subQ,MATCH(J$1,SUBQH,0),0),"") | K36: =IFERROR(VLOOKUP($A36,subQ,MATCH(K$1,SUBQH,0),0),"") | L36: =IFERROR(VLOOKUP($A36,subQ,MATCH(L$1,SUBQH,0),0),"")
A37: 매출액 YoY | D37: 매출액 YoY | F37: =IFERROR(F5/E5-1,"") | G37: =IFERROR(G5/F5-1,"") | H37: =IFERROR(H5/G5-1,"") | I37: =IFERROR(I5/H5-1,"") | J37: =IFERROR(J5/I5-1,"") | K37: =IFERROR(K5/J5-1,"") | L37: =IFERROR(L5/K5-1,"")
A38: 영업이익 YoY | D38: 영업이익 YoY | F38: =IFERROR(F9/E9-1,"") | G38: =IFERROR(G9/F9-1,"") | H38: =IFERROR(H9/G9-1,"") | I38: =IFERROR(I9/H9-1,"") | J38: =IFERROR(J9/I9-1,"") | K38: =IFERROR(K9/J9-1,"") | L38: =IFERROR(L9/K9-1,"")
A39: 지배주주순이익 YoY | D39: 지배주주순이익 YoY | F39: =IFERROR(F17/E17-1,"") | G39: =IFERROR(G17/F17-1,"") | H39: =IFERROR(H17/G17-1,"") | I39: =IFERROR(I17/H17-1,"") | J39: =IFERROR(J17/I17-1,"") | K39: =IFERROR(K17/J17-1,"") | L39: =IFERROR(L17/K17-1,"")

Sheet TP
B1: 종가 | C1: =변수!D39
B2: 기준일 | C2: =변수!D40
B3: 모델 산출값 — 목표주가·추천 아님. 밴드·COE 는 변수 시트 3절의 가정
C5: FY | D5: 2025 | E5: 2026 | F5: 2027 | G5: 2028
D6: A | E6: E | F6: E | G6: E
C7: EPS(원) | D7: =IFERROR(VLOOKUP("EPS",subQ,MATCH(D$5,SUBQH,0),0),"") | E7: =IFERROR(VLOOKUP("EPS",subQ,MATCH(E$5,SUBQH,0),0),"") | F7: =IFERROR(VLOOKUP("EPS",subQ,MATCH(F$5,SUBQH,0),0),"") | G7: =IFERROR(VLOOKUP("EPS",subQ,MATCH(G$5,SUBQH,0),0),"")
C8: BPS(원) | D8: =IFERROR(VLOOKUP("BPS",subQ,MATCH(D$5,SUBQH,0),0),"") | E8: =IFERROR(VLOOKUP("BPS",subQ,MATCH(E$5,SUBQH,0),0),"") | F8: =IFERROR(VLOOKUP("BPS",subQ,MATCH(F$5,SUBQH,0),0),"") | G8: =IFERROR(VLOOKUP("BPS",subQ,MATCH(G$5,SUBQH,0),0),"")
C9: 지배주주순이익(억원) | D9: =IFERROR(VLOOKUP("지배주주순이익",subQ,MATCH(D$5,SUBQH,0),0),"") | E9: =IFERROR(VLOOKUP("지배주주순이익",subQ,MATCH(E$5,SUBQH,0),0),"") | F9: =IFERROR(VLOOKUP("지배주주순이익",subQ,MATCH(F$5,SUBQH,0),0),"") | G9: =IFERROR(VLOOKUP("지배주주순이익",subQ,MATCH(G$5,SUBQH,0),0),"")
C10: 영업이익(억원) | D10: =IFERROR(VLOOKUP("영업이익",subQ,MATCH(D$5,SUBQH,0),0),"") | E10: =IFERROR(VLOOKUP("영업이익",subQ,MATCH(E$5,SUBQH,0),0),"") | F10: =IFERROR(VLOOKUP("영업이익",subQ,MATCH(F$5,SUBQH,0),0),"") | G10: =IFERROR(VLOOKUP("영업이익",subQ,MATCH(G$5,SUBQH,0),0),"")
C11: ROE(EPS/기초BPS) | E11: =IFERROR(E7/D8,"") | F11: =IFERROR(F7/E8,"") | G11: =IFERROR(G7/F8,"")
B13: PER
C14: 12M fwd EPS | D14: =IFERROR(E7*변수!D45+F7*(1-변수!D45),"")
C15: 적정가치 @PER_lo | D15: =변수!D42 | E15: =IFERROR(ROUND($D$14*D15,-2),"") | F15: =IFERROR(E15/$C$1-1,"") | G15: 배 · 원 · 종가 대비
C16: 적정가치 @PER_mid | D16: =변수!D43 | E16: =IFERROR(ROUND($D$14*D16,-2),"") | F16: =IFERROR(E16/$C$1-1,"") | G16: 배 · 원 · 종가 대비
C17: 적정가치 @PER_hi | D17: =변수!D44 | E17: =IFERROR(ROUND($D$14*D17,-2),"") | F17: =IFERROR(E17/$C$1-1,"") | G17: 배 · 원 · 종가 대비
C18: 현재 PER(종가/12M fwd EPS) | D18: =IFERROR($C$1/$D$14,"")
B20: PBR
C21: 최근 BPS(마지막 실적 분기) | D21: =IFERROR(VLOOKUP("BPS",subQ,MATCH("2Q26",SUBQH,0),0),"")
C22: ROE fwd(12M fwd EPS / BPS) | D22: =IFERROR($D$14/$D$21,"")
C23: COE | D23: =변수!D41
C24: 적정 PBR = ROE/COE | D24: =IFERROR(D22/D23,"")
C25: 적정가치(PBR) = BPS × 적정PBR | D25: =IFERROR(ROUND(D21*D24,-2),"") | E25: =IFERROR(D25/$C$1-1,"")
C26: 현재 PBR(종가/BPS) | D26: =IFERROR($C$1/D21,"")
B28: 모델 json valuation(참고)
C29: eps_fwd12m | D29: 2956.3
C30: bps_latest | D30: 29899.8
C31: per_now | D31: 4.98
C32: pbr_now | D32: 0.49
C33: roe_fwd | D33: 0.0989
C34: fair_pbr | D34: 1.1
C35: fair_value_pbr | D35: 32900
C36: ev_ebitda
C37: note | D37: 모델 산출값 — 목표주가·추천 아님

Sheet 외화
C1: 이름: 외화QH — 환율 QoQ · 외화 순노출 × Δ기말환율 | E1: 4Q21 | F1: 1Q22 | G1: 2Q22 | H1: 3Q22 | I1: 4Q22 | J1: 1Q23 | K1: 2Q23 | L1: 3Q23 | M1: 4Q23 | N1: 1Q24 | O1: 2Q24 | P1: 3Q24 | Q1: 4Q24 | R1: 1Q25 | S1: 2Q25 | T1: 3Q25 | U1: 4Q25 | V1: 1Q26 | W1: 2Q26 | X1: 3Q26 | Y1: 4Q26 | Z1: 1Q27 | AA1: 2Q27 | AB1: 3Q27 | AC1: 4Q27 | AD1: 1Q28 | AE1: 2Q28 | AF1: 3Q28 | AG1: 4Q28
E3: 1 | F3: 2 | G3: 3 | H3: 4 | I3: 5 | J3: 6 | K3: 7 | L3: 8 | M3: 9 | N3: 10 | O3: 11 | P3: 12 | Q3: 13 | R3: 14 | S3: 15 | T3: 16 | U3: 17 | V3: 18 | W3: 19 | X3: 20 | Y3: 21 | Z3: 22 | AA3: 23 | AB3: 24 | AC3: 25 | AD3: 26 | AE3: 27 | AF3: 28 | AG3: 29
E4: 2021.12 | F4: 2022.03 | G4: 2022.06 | H4: 2022.09 | I4: 2022.12 | J4: 2023.03 | K4: 2023.06 | L4: 2023.09 | M4: 2023.12 | N4: 2024.03 | O4: 2024.06 | P4: 2024.09 | Q4: 2024.12 | R4: 2025.03 | S4: 2025.06 | T4: 2025.09 | U4: 2025.12 | V4: 2026.03 | W4: 2026.06 | X4: 2026.09 | Y4: 2026.12 | Z4: 2027.03 | AA4: 2027.06 | AB4: 2027.09 | AC4: 2027.12 | AD4: 2028.03 | AE4: 2028.06 | AF4: 2028.09 | AG4: 2028.12
D5: 원/달러(평균) | E5: =IFERROR(VLOOKUP($D5,환율,MATCH(E$1,변수H,0),0),"") | F5: =IFERROR(VLOOKUP($D5,환율,MATCH(F$1,변수H,0),0),"") | G5: =IFERROR(VLOOKUP($D5,환율,MATCH(G$1,변수H,0),0),"") | H5: =IFERROR(VLOOKUP($D5,환율,MATCH(H$1,변수H,0),0),"") | I5: =IFERROR(VLOOKUP($D5,환율,MATCH(I$1,변수H,0),0),"") | J5: =IFERROR(VLOOKUP($D5,환율,MATCH(J$1,변수H,0),0),"") | K5: =IFERROR(VLOOKUP($D5,환율,MATCH(K$1,변수H,0),0),"") | L5: =IFERROR(VLOOKUP($D5,환율,MATCH(L$1,변수H,0),0),"") | ... AG5: =IFERROR(VLOOKUP($D5,환율,MATCH(AG$1,변수H,0),0),"")
A6: 원/달러(평균) QoQ | F6: =IFERROR(F5/E5-1,"") | G6: =IFERROR(G5/F5-1,"") | H6: =IFERROR(H5/G5-1,"") | I6: =IFERROR(I5/H5-1,"") | J6: =IFERROR(J5/I5-1,"") | K6: =IFERROR(K5/J5-1,"") | L6: =IFERROR(L5/K5-1,"") | M6: =IFERROR(M5/L5-1,"") | ... AG6: =IFERROR(AG5/AF5-1,"")
D7: 원/달러(기말) | E7: =IFERROR(VLOOKUP($D7,환율,MATCH(E$1,변수H,0),0),"") | F7: =IFERROR(VLOOKUP($D7,환율,MATCH(F$1,변수H,0),0),"") | G7: =IFERROR(VLOOKUP($D7,환율,MATCH(G$1,변수H,0),0),"") | H7: =IFERROR(VLOOKUP($D7,환율,MATCH(H$1,변수H,0),0),"") | I7: =IFERROR(VLOOKUP($D7,환율,MATCH(I$1,변수H,0),0),"") | J7: =IFERROR(VLOOKUP($D7,환율,MATCH(J$1,변수H,0),0),"") | K7: =IFERROR(VLOOKUP($D7,환율,MATCH(K$1,변수H,0),0),"") | L7: =IFERROR(VLOOKUP($D7,환율,MATCH(L$1,변수H,0),0),"") | ... AG7: =IFERROR(VLOOKUP($D7,환율,MATCH(AG$1,변수H,0),0),"")
A8: 원/달러(기말) QoQ | F8: =IFERROR(F7/E7-1,"") | G8: =IFERROR(G7/F7-1,"") | H8: =IFERROR(H7/G7-1,"") | I8: =IFERROR(I7/H7-1,"") | J8: =IFERROR(J7/I7-1,"") | K8: =IFERROR(K7/J7-1,"") | L8: =IFERROR(L7/K7-1,"") | M8: =IFERROR(M7/L7-1,"") | ... AG8: =IFERROR(AG7/AF7-1,"")
D9: W/Euro(평균) | E9: =IFERROR(VLOOKUP($D9,환율,MATCH(E$1,변수H,0),0),"") | F9: =IFERROR(VLOOKUP($D9,환율,MATCH(F$1,변수H,0),0),"") | G9: =IFERROR(VLOOKUP($D9,환율,MATCH(G$1,변수H,0),0),"") | H9: =IFERROR(VLOOKUP($D9,환율,MATCH(H$1,변수H,0),0),"") | I9: =IFERROR(VLOOKUP($D9,환율,MATCH(I$1,변수H,0),0),"") | J9: =IFERROR(VLOOKUP($D9,환율,MATCH(J$1,변수H,0),0),"") | K9: =IFERROR(VLOOKUP($D9,환율,MATCH(K$1,변수H,0),0),"") | L9: =IFERROR(VLOOKUP($D9,환율,MATCH(L$1,변수H,0),0),"") | ... AG9: =IFERROR(VLOOKUP($D9,환율,MATCH(AG$1,변수H,0),0),"")
A10: W/Euro(평균) QoQ | F10: =IFERROR(F9/E9-1,"") | G10: =IFERROR(G9/F9-1,"") | H10: =IFERROR(H9/G9-1,"") | I10: =IFERROR(I9/H9-1,"") | J10: =IFERROR(J9/I9-1,"") | K10: =IFERROR(K9/J9-1,"") | L10: =IFERROR(L9/K9-1,"") | M10: =IFERROR(M9/L9-1,"") | ... AG10: =IFERROR(AG9/AF9-1,"")
D11: W/Euro(기말) | E11: =IFERROR(VLOOKUP($D11,환율,MATCH(E$1,변수H,0),0),"") | F11: =IFERROR(VLOOKUP($D11,환율,MATCH(F$1,변수H,0),0),"") | G11: =IFERROR(VLOOKUP($D11,환율,MATCH(G$1,변수H,0),0),"") | H11: =IFERROR(VLOOKUP($D11,환율,MATCH(H$1,변수H,0),0),"") | I11: =IFERROR(VLOOKUP($D11,환율,MATCH(I$1,변수H,0),0),"") | J11: =IFERROR(VLOOKUP($D11,환율,MATCH(J$1,변수H,0),0),"") | K11: =IFERROR(VLOOKUP($D11,환율,MATCH(K$1,변수H,0),0),"") | L11: =IFERROR(VLOOKUP($D11,환율,MATCH(L$1,변수H,0),0),"") | ... AG11: =IFERROR(VLOOKUP($D11,환율,MATCH(AG$1,변수H,0),0),"")
A12: W/Euro(기말) QoQ | F12: =IFERROR(F11/E11-1,"") | G12: =IFERROR(G11/F11-1,"") | H12: =IFERROR(H11/G11-1,"") | I12: =IFERROR(I11/H11-1,"") | J12: =IFERROR(J11/I11-1,"") | K12: =IFERROR(K11/J11-1,"") | L12: =IFERROR(L11/K11-1,"") | M12: =IFERROR(M11/L11-1,"") | ... AG12: =IFERROR(AG11/AF11-1,"")
D13: 원/100Y(기말) | E13: =IFERROR(VLOOKUP($D13,환율,MATCH(E$1,변수H,0),0),"") | F13: =IFERROR(VLOOKUP($D13,환율,MATCH(F$1,변수H,0),0),"") | G13: =IFERROR(VLOOKUP($D13,환율,MATCH(G$1,변수H,0),0),"") | H13: =IFERROR(VLOOKUP($D13,환율,MATCH(H$1,변수H,0),0),"") | I13: =IFERROR(VLOOKUP($D13,환율,MATCH(I$1,변수H,0),0),"") | J13: =IFERROR(VLOOKUP($D13,환율,MATCH(J$1,변수H,0),0),"") | K13: =IFERROR(VLOOKUP($D13,환율,MATCH(K$1,변수H,0),0),"") | L13: =IFERROR(VLOOKUP($D13,환율,MATCH(L$1,변수H,0),0),"") | ... AG13: =IFERROR(VLOOKUP($D13,환율,MATCH(AG$1,변수H,0),0),"")
A14: 원/100Y(기말) QoQ | F14: =IFERROR(F13/E13-1,"") | G14: =IFERROR(G13/F13-1,"") | H14: =IFERROR(H13/G13-1,"") | I14: =IFERROR(I13/H13-1,"") | J14: =IFERROR(J13/I13-1,"") | K14: =IFERROR(K13/J13-1,"") | L14: =IFERROR(L13/K13-1,"") | M14: =IFERROR(M13/L13-1,"") | ... AG14: =IFERROR(AG13/AF13-1,"")
A16: 외화순노출 | C16: 외화 순노출(백만$) | D16: =변수!D52 | E16: 외화 순노출 × Δ기말환율 (외화 시트 방식)
A17: 환관련손익추정 | C17: 환관련손익 추정(억원) = 순노출 × Δ원/달러(기말) / 100 | F17: =IFERROR($D$16*(F7-E7)/100,"") | G17: =IFERROR($D$16*(G7-F7)/100,"") | H17: =IFERROR($D$16*(H7-G7)/100,"") | I17: =IFERROR($D$16*(I7-H7)/100,"") | J17: =IFERROR($D$16*(J7-I7)/100,"") | K17: =IFERROR($D$16*(K7-J7)/100,"") | L17: =IFERROR($D$16*(L7-K7)/100,"") | M17: =IFERROR($D$16*(M7-L7)/100,"") | ... AG17: =IFERROR($D$16*(AG7-AF7)/100,"")
A18: fx_pnl.by_q | C18: 모델 fx_pnl.by_q(억원, 참고)
C19: 외화 순노출 미공시(face) → 0 + 표기
