Workbook
Name 변수H: 변수!$C$1:$AO$1
Name 환율: 변수!$C$6:$AO$13
Name BS연결H: BS연결!$C$1:$AO$1
Name BS연결: BS연결!$C$5:$AO$93
Name BS별도H: BS별도!$C$1:$AO$1
Name BS별도: BS별도!$C$5:$AO$94
Name SUBQH: subQ!$A$1:$AO$1
Name subQ: subQ!$A$5:$AO$42

Sheet README
A1: 화인베스틸(133820) 실적 모델 — ARGUS 한국조선
A2: 기준 분기 2026Q2 · 마지막 실적 2026Q2 · 생성 2026-10-13
A3: 모든 수치는 모델 산출값(DART 공개 재무제표 + 우리 추정)이다 — 목표주가·투자 추천 아님. 참고용 · 투자조언 아님.
A5: 시트
A6: 변수 가정 시계열. 환율 8행(ECB via frankfurter — L2 fx.json; 추정 분기 = 노란 가정), 추정 드라이버(노란 셀 = 모델값에서 역산한 가정, 바꾸면 재계산; 연녹 셀 = 3절 스칼라 참조 수식), 3절 스칼라 가정(세율·판관비율·지배주주비중·이자율·종가·PER 밴드·COE·외화 순노출·헤지비율)
A7: BS연결/BS별도 FnGuide 계정명 × 기간 값 덤프(백만원). 행1 분기라벨, 행4 YYYY.MM / YYYY.12A. 이름정의 BS연결H·BS연결(계정명 C열부터)
A8: subQ 분기 서브모델(억원 = 백만원/100). 확정 행: =IFERROR(VLOOKUP($D행,BS연결,MATCH(E$1,BS연결H,0),0)/100,"") 추정 행: 변수 시트 가정 셀 참조 수식. 외환손익·파생상품손익은 BS 계정 합·차, 기타금융손익은 잔차, OPM·EPS·BPS·PER·PBR 은 파생 수식
A9: SLS 선표(조선사만, sls json 있을 때): 요약 행(sls 저장값) + 계약별 스케줄(백만$) × (헤지비율 × 헤지환율 + (1−헤지비율) × 건조시점 환율[변수 원/달러(평균)]) → 원화 수식 블록 → 합계 행이 subQ 매출조선에 연결
A10: 시나리오 신규수주 보수/기준/낙관(forecast_panel 패널, 모델에 scenarios 가 있을 때만): 매출액·영업이익 = subQ 기준값 ± (시나리오 신규 − base 신규) × OPM. base 만 subQ 행에 포함, 나머지는 합산 안 함
A11: 분기/연간예상 subQ 를 이름(A열 key)으로 VLOOKUP 한 보고서 표(억원)
A12: TP PER 밴드 × 12M fwd EPS, PBR = ROE/COE × BPS — 모델 산출값 구간, 목표주가·추천 아님
A13: 외화 환율 QoQ, 외화 순노출 × Δ기말환율 → 환관련손익 추정
... A34: 백테스트: {"freeze": "2025Q2", "horizon": 4, "revenue_wape_pct": 17.2, "op_wape_pct": 622.3, "n": 4, "note": "단일 회사 4분기 — 통계 아님", "driver_at_freeze": "customer_yard_revenue_weighted", "selection_oos_at_freeze": {"freeze": "2024Q2", "n": 4, "wape_link": 17.3, "wape_trend": 39.8, "adopted": true, "decision": "adopted"}, "frozen_inputs": "fin(연결/별도)·고객 조선사 모델·지주 자회사 모델은 2025Q2 까지의 분기만; 선표는 체결일 ≤ 2025Q2 말일 계약(원장 최신 금액·코호트 등급, 환산 없음); 잔고는 yards_cache 2025Q2; 시세·환율 forward·prices·forecast_panel 신규수주 미사용. 고객 가중치(suppliers.json 언급 비중)와 합병 체인링크는 현재 지식; 고객 연동 채택은 동결 모델 안에서도 자기 la−4분기 OOS 규칙(selection_oos_at_freeze)", "detail": [{"q": "2025Q3", "rev_pred": 393.21, "rev_act": 485.14, "op_pred": -59.92, "op_act": 0.32}, {"q": "2025Q4", "rev_pred": 427.6, "rev_act": 533.85, "op_pred": -65.16, "op_act": 21.67}, {"q": "2026Q1", "rev_pred": 424.35, "rev_act": 506.2, "op_pred": -64.67, "op_act": 13.94}, {"q": "2026Q2", "rev_pred": 424.35, "rev_act": 491.36, "op_pred": -64.67, "op_act": 12.78}]}

Sheet 변수
C1: 이름: 변수H | E1: 4Q21 | F1: 2021 | G1: 1Q22 | H1: 2Q22 | I1: 3Q22 | J1: 4Q22 | K1: 2022 | L1: 1Q23 | M1: 2Q23 | N1: 3Q23 | O1: 4Q23 | P1: 2023 | Q1: 1Q24 | R1: 2Q24 | S1: 3Q24 | T1: 4Q24 | U1: 2024 | V1: 1Q25 | W1: 2Q25 | X1: 3Q25 | Y1: 4Q25 | Z1: 2025 | AA1: 1Q26 | AB1: 2Q26 | AC1: 3Q26 | AD1: 4Q26 | AE1: 2026 | AF1: 1Q27 | AG1: 2Q27 | AH1: 3Q27 | AI1: 4Q27 | AJ1: 2027 | AK1: 1Q28 | AL1: 2Q28 | AM1: 3Q28 | AN1: 4Q28 | AO1: 2028
A2: 가정 시계열 — 노란 셀은 추정 가정(모델값에서 역산), 연녹 셀은 3절 스칼라 참조 수식. 바꾸면 subQ·분기·연간예상·TP·시나리오가 재계산됩니다.
E3: 1 | F3: 2 | G3: 3 | H3: 4 | I3: 5 | J3: 6 | K3: 7 | L3: 8 | M3: 9 | N3: 10 | O3: 11 | P3: 12 | Q3: 13 | R3: 14 | S3: 15 | T3: 16 | U3: 17 | V3: 18 | W3: 19 | X3: 20 | Y3: 21 | Z3: 22 | AA3: 23 | AB3: 24 | AC3: 25 | AD3: 26 | AE3: 27 | AF3: 28 | AG3: 29 | AH3: 30 | AI3: 31 | AJ3: 32 | AK3: 33 | AL3: 34 | AM3: 35 | AN3: 36 | AO3: 37
E4: 2021.12 | F4: 2021.12A | G4: 2022.03 | H4: 2022.06 | I4: 2022.09 | J4: 2022.12 | K4: 2022.12A | L4: 2023.03 | M4: 2023.06 | N4: 2023.09 | O4: 2023.12 | P4: 2023.12A | Q4: 2024.03 | R4: 2024.06 | S4: 2024.09 | T4: 2024.12 | U4: 2024.12A | V4: 2025.03 | W4: 2025.06 | X4: 2025.09 | Y4: 2025.12 | Z4: 2025.12A | AA4: 2026.03 | AB4: 2026.06 | AC4: 2026.09 | AD4: 2026.12 | AE4: 2026.12A | AF4: 2027.03 | AG4: 2027.06 | AH4: 2027.09 | AI4: 2027.12 | AJ4: 2027.12A | AK4: 2028.03 | AL4: 2028.06 | AM4: 2028.09 | AN4: 2028.12 | AO4: 2028.12A
B5: 1. FX | C5: 이름: 환율
A6: USDKRW_avg | C6: 원/달러(평균) | E6: 1183.5 | F6: 1145.51 | G6: 1205.78 | H6: 1262.09 | I6: 1341.93 | J6: 1360.12 | K6: 1292.98 | L6: 1276.95 | M6: 1315.69 | N6: 1313.62 | O6: 1322.01 | P6: 1306.85 | Q6: 1330.14 | R6: 1371.28 | S6: 1356.22 | T6: 1396.3 | U6: 1363.53 | V6: 1452.28 | W6: 1398.52 | X6: 1386.95 | Y6: 1449.19 | Z6: 1421.52 | AA6: 1466.12 | AB6: 1501.75 | AC6: 1418.75 | AD6: 1343.63 | AE6: 1456.58 | AF6: 1333.09 | AG6: 1333.09 | AH6: 1333.09 | AI6: 1333.09 | AK6: 1333.09 | AL6: 1333.09 | AM6: 1333.09 | AN6: 1333.09
A7: USDKRW_end | C7: 원/달러(기말) | E7: 1188.75 | F7: 1188.75 | G7: 1213.74 | H7: 1301.24 | I7: 1436.9 | J7: 1260.16 | K7: 1260.16 | L7: 1305.99 | M7: 1321.44 | N7: 1345.35 | O7: 1297.43 | P7: 1297.43 | Q7: 1349.25 | R7: 1377.73 | S7: 1312.17 | T7: 1474.78 | U7: 1474.78 | V7: 1474.54 | W7: 1355.13 | X7: 1403.67 | Y7: 1444.2 | Z7: 1444.2 | AA7: 1524.8 | AB7: 1550.89 | AC7: 1355.4 | AD7: 1333.09 | AE7: 1333.09 | AF7: 1333.09 | AG7: 1333.09 | AH7: 1333.09 | AI7: 1333.09 | AK7: 1333.09 | AL7: 1333.09 | AM7: 1333.09 | AN7: 1333.09
A8: JPY100KRW_avg | C8: 원/100Y(평균) | E8: 1041.02 | F8: 1042.74 | G8: 1036.79 | H8: 972.23 | I8: 970.61 | J8: 961.03 | K8: 985.1 | L8: 964.89 | M8: 957.36 | N8: 909 | O8: 893.22 | P8: 931.11 | Q8: 896.29 | R8: 880.14 | S8: 909.35 | T8: 917.25 | U8: 900.92 | V8: 952.59 | W8: 967.92 | X8: 940.32 | Y8: 940.77 | Z8: 950.17 | AA8: 934.39 | AB8: 942.16 | AC8: 890.41 | AD8: 849.51 | AE8: 918.81 | AF8: 840.54 | AG8: 840.54 | AH8: 840.54 | AI8: 840.54 | AK8: 840.54 | AL8: 840.54 | AM8: 840.54 | AN8: 840.54
A9: JPY100KRW_end | C9: 원/100Y(기말) | E9: 1032.62 | F9: 1032.62 | G9: 996.83 | H9: 954.9 | I9: 993.29 | J9: 955.54 | K9: 955.54 | L9: 980.62 | M9: 913.67 | N9: 901.47 | O9: 917.04 | P9: 917.04 | Q9: 892.42 | R9: 857.76 | S9: 919.21 | T9: 939.65 | U9: 939.65 | V9: 986.84 | W9: 938.85 | X9: 948.49 | Y9: 921.81 | Z9: 921.81 | AA9: 955.99 | AB9: 954.75 | AC9: 863.31 | AD9: 840.54 | AE9: 840.54 | AF9: 840.54 | AG9: 840.54 | AH9: 840.54 | AI9: 840.54 | AK9: 840.54 | AL9: 840.54 | AM9: 840.54 | AN9: 840.54
A10: EURKRW_avg | C10: W/Euro(평균) | E10: 1353.32 | F10: 1354.06 | G10: 1352.29 | H10: 1343.31 | I10: 1350.63 | J10: 1386.07 | K10: 1358.07 | L10: 1369.93 | M10: 1432.41 | N10: 1429.41 | O10: 1420.91 | P10: 1412.88 | Q10: 1444.21 | R10: 1476.42 | S10: 1489.3 | T10: 1490.78 | U10: 1475.4 | V10: 1528.33 | W10: 1585.13 | X10: 1620.04 | Y10: 1686.02 | Z10: 1605.45 | AA10: 1715.47 | AB10: 1746.09 | AC10: 1631.97 | AD10: 1507.34 | AE10: 1688.95 | AF10: 1490.54 | AG10: 1490.54 | AH10: 1490.54 | AI10: 1490.54 | AK10: 1490.54 | AL10: 1490.54 | AM10: 1490.54 | AN10: 1490.54
A11: EURKRW_end | C11: W/Euro(기말) | E11: 1346.38 | F11: 1346.38 | G11: 1347.37 | H11: 1351.6 | I11: 1400.62 | J11: 1344.08 | K11: 1344.08 | L11: 1420.26 | M11: 1435.88 | N11: 1425.26 | O11: 1433.66 | P11: 1433.66 | Q11: 1458.68 | R11: 1474.86 | S11: 1469.1 | T11: 1532.14 | U11: 1532.14 | V11: 1594.72 | W11: 1588.22 | X11: 1648.04 | Y11: 1696.94 | Z11: 1696.94 | AA11: 1753.21 | AB11: 1767.09 | AC11: 1539.06 | AD11: 1490.54 | AE11: 1490.54 | AF11: 1490.54 | AG11: 1490.54 | AH11: 1490.54 | AI11: 1490.54 | AK11: 1490.54 | AL11: 1490.54 | AM11: 1490.54 | AN11: 1490.54
A12: CNYKRW_avg | C12: 원/중국원(평균) | E12: 185.14 | F12: 177.65 | G12: 189.93 | H12: 190.76 | I12: 195.79 | J12: 191.09 | K12: 191.93 | L12: 186.59 | M12: 187.45 | N12: 181.28 | O12: 182.86 | P12: 184.52 | Q12: 185.04 | R12: 189.35 | S12: 189.24 | T12: 194.24 | U12: 189.49 | V12: 199.63 | W12: 193.41 | X12: 193.79 | Y12: 204.38 | Z12: 197.8 | AA12: 211.75 | AB12: 220.8 | AC12: 210.43 | AD12: 200.5 | AE12: 213.68 | AF12: 199.18 | AG12: 199.18 | AH12: 199.18 | AI12: 199.18 | AK12: 199.18 | AL12: 199.18 | AM12: 199.18 | AN12: 199.18
A13: CNYKRW_end | C13: 원/중국원(기말) | E13: 187.13 | F13: 187.13 | G13: 191.38 | H13: 194.13 | I13: 201.92 | J13: 182.67 | K13: 182.67 | L13: 189.97 | M13: 181.8 | N13: 184.26 | O13: 182.61 | P13: 182.61 | Q13: 186.66 | R13: 189.7 | S13: 187.12 | T13: 202.04 | U13: 202.04 | V13: 203.3 | W13: 189.14 | X13: 197.16 | Y13: 206.28 | Z13: 206.28 | AA13: 220.97 | AB13: 228.56 | AC13: 202.16 | AD13: 199.18 | AE13: 199.18 | AF13: 199.18 | AG13: 199.18 | AH13: 199.18 | AI13: 199.18 | AK13: 199.18 | AL13: 199.18 | AM13: 199.18 | AN13: 199.18
B14: 1b. 종가
A15: price_close_end | C15: 종가(기말) | E15: 3045 | G15: 3355 | H15: 2805 | I15: 2280 | J15: 2090 | L15: 1819 | M15: 2490 | N15: 1431 | O15: 1263 | Q15: 1331 | R15: 1087 | S15: 900 | T15: 916 | V15: 810 | W15: 829 | X15: 1860 | Y15: 1643 | AA15: 1217 | AB15: 1002 | AC15: 1004 | AD15: 978
A16: price_high | C16: 종가(최고) | E16: 3670 | G16: 3960 | H16: 3755 | I16: 3055 | J16: 2390 | L16: 2245 | M16: 2985 | N16: 2765 | O16: 1460 | Q16: 1557 | R16: 1483 | S16: 1149 | T16: 1201 | V16: 1300 | W16: 1029 | X16: 2950 | Y16: 2620 | AA16: 1985 | AB16: 1838 | AC16: 1219 | AD16: 1149
A17: price_low | C17: 종가(최저) | E17: 2610 | G17: 2930 | H17: 2475 | I17: 2105 | J17: 2005 | L17: 1682 | M17: 1686 | N17: 1350 | O17: 1125 | Q17: 973 | R17: 1078 | S17: 801 | T17: 831 | V17: 810 | W17: 782 | X17: 821 | Y17: 1622 | AA17: 1151 | AB17: 921 | AC17: 875 | AD17: 940
A18: price_avg | C18: 종가(평균) | E18: 3083.4 | G18: 3366.2 | H18: 3127 | I18: 2624.3 | J18: 2222.2 | L18: 2017.2 | M18: 2246 | N18: 1953.1 | O18: 1297.3 | Q18: 1144.6 | R18: 1233.4 | S18: 958.7 | T18: 968.4 | V18: 1060.7 | W18: 861.7 | X18: 1506.7 | Y18: 1930 | AA18: 1541.3 | AB18: 1302.1 | AC18: 1003.3 | AD18: 990.6
B20: 2. 추정 드라이버 | C20: 실적 열 = subQ 실현값(수식), 추정 열 = 가정(노란 = 모델값 역산, 연녹 = 3절 스칼라 참조)
A21: drv:매출액 | B21: yoy | C21: 매출액 YoY | J21: =IFERROR(subQ!J5/subQ!E5-1,"") | L21: =IFERROR(subQ!L5/subQ!G5-1,"") | M21: =IFERROR(subQ!M5/subQ!H5-1,"") | N21: =IFERROR(subQ!N5/subQ!I5-1,"") | O21: =IFERROR(subQ!O5/subQ!J5-1,"") | Q21: =IFERROR(subQ!Q5/subQ!L5-1,"") | R21: =IFERROR(subQ!R5/subQ!M5-1,"") | S21: =IFERROR(subQ!S5/subQ!N5-1,"") | T21: =IFERROR(subQ!T5/subQ!O5-1,"") | V21: =IFERROR(subQ!V5/subQ!Q5-1,"") | W21: =IFERROR(subQ!W5/subQ!R5-1,"") | X21: =IFERROR(subQ!X5/subQ!S5-1,"") | Y21: =IFERROR(subQ!Y5/subQ!T5-1,"") | AA21: =IFERROR(subQ!AA5/subQ!V5-1,"") | AB21: =IFERROR(subQ!AB5/subQ!W5-1,"") | AC21: 0.013803759 | AD21: -0.006342281 | AF21: 0.017404791 | AG21: 0.12955303 | AH21: 0.23304327 | AI21: 0.24393922 | AK21: 0.23964583 | AL21: 0.17379554 | AM21: 0.14390067 | AN21: 0.14851635
A22: drv:판관비 | B22: ratio | C22: 판관비율(/매출) | E22: =IFERROR(subQ!E8/subQ!E5,"") | F22: =IFERROR(subQ!F8/subQ!F5,"") | G22: =IFERROR(subQ!G8/subQ!G5,"") | H22: =IFERROR(subQ!H8/subQ!H5,"") | I22: =IFERROR(subQ!I8/subQ!I5,"") | J22: =IFERROR(subQ!J8/subQ!J5,"") | K22: =IFERROR(subQ!K8/subQ!K5,"") | L22: =IFERROR(subQ!L8/subQ!L5,"") | ... AB22: =IFERROR(subQ!AB8/subQ!AB5,"") | AC22: =$D$50 | AD22: =$D$50 | AE22: =IFERROR(subQ!AE8/subQ!AE5,"") | AF22: =$D$50 | AG22: =$D$50 | AH22: =$D$50 | AI22: =$D$50 | AJ22: =IFERROR(subQ!AJ8/subQ!AJ5,"") | AK22: =$D$50 | AL22: =$D$50 | AM22: =$D$50 | AN22: =$D$50 | AO22: =IFERROR(subQ!AO8/subQ!AO5,"")
A23: drv:영업이익 | B23: ratio | C23: 영업이익률(OPM) | E23: =IFERROR(subQ!E9/subQ!E5,"") | F23: =IFERROR(subQ!F9/subQ!F5,"") | G23: =IFERROR(subQ!G9/subQ!G5,"") | H23: =IFERROR(subQ!H9/subQ!H5,"") | I23: =IFERROR(subQ!I9/subQ!I5,"") | J23: =IFERROR(subQ!J9/subQ!J5,"") | K23: =IFERROR(subQ!K9/subQ!K5,"") | L23: =IFERROR(subQ!L9/subQ!L5,"") | ... AB23: =IFERROR(subQ!AB9/subQ!AB5,"") | AC23: 0.013337671 | AD23: 0.013328055 | AE23: =IFERROR(subQ!AE9/subQ!AE5,"") | AF23: 0.013339547 | AG23: 0.013332853 | AH23: 0.013339709 | AI23: 0.013336162 | AJ23: =IFERROR(subQ!AJ9/subQ!AJ5,"") | AK23: 0.013329574 | AL23: 0.013338859 | AM23: 0.013333718 | AN23: 0.013340195 | AO23: =IFERROR(subQ!AO9/subQ!AO5,"")
A24: drv:파생상품손익 | B24: abs | C24: 파생상품손익 (가정, 억원) | E24: =subQ!E13 | F24: =subQ!F13 | G24: =subQ!G13 | H24: =subQ!H13 | I24: =subQ!I13 | J24: =subQ!J13 | K24: =subQ!K13 | L24: =subQ!L13 | ... AB24: =subQ!AB13 | AC24: 0 | AD24: 0 | AE24: =subQ!AE13 | AF24: 0 | AG24: 0 | AH24: 0 | AI24: 0 | AJ24: =subQ!AJ13 | AK24: 0 | AL24: 0 | AM24: 0 | AN24: 0 | AO24: =subQ!AO13
A25: drv:기타영업외손익 | B25: abs | C25: 기타영업외손익 (가정, 억원) | E25: =subQ!E14 | F25: =subQ!F14 | G25: =subQ!G14 | H25: =subQ!H14 | I25: =subQ!I14 | J25: =subQ!J14 | K25: =subQ!K14 | L25: =subQ!L14 | ... AB25: =subQ!AB14 | AC25: 0 | AD25: 0 | AE25: =subQ!AE14 | AF25: 0 | AG25: 0 | AH25: 0 | AI25: 0 | AJ25: =subQ!AJ14 | AK25: 0 | AL25: 0 | AM25: 0 | AN25: 0 | AO25: =subQ!AO14
A26: drv:법인세비용 | B26: tax | C26: 법인세율(/세전) — 법인세 = MAX(세전,0) × 세율 | E26: =IFERROR(subQ!E16/subQ!E15,"") | F26: =IFERROR(subQ!F16/subQ!F15,"") | G26: =IFERROR(subQ!G16/subQ!G15,"") | H26: =IFERROR(subQ!H16/subQ!H15,"") | I26: =IFERROR(subQ!I16/subQ!I15,"") | J26: =IFERROR(subQ!J16/subQ!J15,"") | K26: =IFERROR(subQ!K16/subQ!K15,"") | L26: =IFERROR(subQ!L16/subQ!L15,"") | ... AB26: =IFERROR(subQ!AB16/subQ!AB15,"") | AC26: =$D$49 | AD26: =$D$49 | AE26: =IFERROR(subQ!AE16/subQ!AE15,"") | AF26: =$D$49 | AG26: =$D$49 | AH26: =$D$49 | AI26: =$D$49 | AJ26: =IFERROR(subQ!AJ16/subQ!AJ15,"") | AK26: =$D$49 | AL26: =$D$49 | AM26: =$D$49 | AN26: =$D$49 | AO26: =IFERROR(subQ!AO16/subQ!AO15,"")
A27: drv:지배주주순이익 | B27: ratio | C27: 지배주주 비중(/당기순이익) | E27: =IFERROR(subQ!E18/subQ!E17,"") | F27: =IFERROR(subQ!F18/subQ!F17,"") | G27: =IFERROR(subQ!G18/subQ!G17,"") | H27: =IFERROR(subQ!H18/subQ!H17,"") | I27: =IFERROR(subQ!I18/subQ!I17,"") | J27: =IFERROR(subQ!J18/subQ!J17,"") | K27: =IFERROR(subQ!K18/subQ!K17,"") | L27: =IFERROR(subQ!L18/subQ!L17,"") | ... AB27: =IFERROR(subQ!AB18/subQ!AB17,"") | AC27: =$D$51 | AD27: =$D$51 | AE27: =IFERROR(subQ!AE18/subQ!AE17,"") | AF27: =$D$51 | AG27: =$D$51 | AH27: =$D$51 | AI27: =$D$51 | AJ27: =IFERROR(subQ!AJ18/subQ!AJ17,"") | AK27: =$D$51 | AL27: =$D$51 | AM27: =$D$51 | AN27: =$D$51 | AO27: =IFERROR(subQ!AO18/subQ!AO17,"")
A28: drv:감가상각비 | B28: abs | C28: 감가상각비 (가정, 억원) | E28: =subQ!E19 | F28: =subQ!F19 | G28: =subQ!G19 | H28: =subQ!H19 | I28: =subQ!I19 | J28: =subQ!J19 | K28: =subQ!K19 | L28: =subQ!L19 | ... AB28: =subQ!AB19 | AC28: 19.84 | AD28: 19.84 | AE28: =subQ!AE19 | AF28: 19.84 | AG28: 19.84 | AH28: 19.84 | AI28: 19.84 | AJ28: =subQ!AJ19 | AK28: 19.84 | AL28: 19.84 | AM28: 19.84 | AN28: 19.84 | AO28: =subQ!AO19
A29: drv:부채총계 | B29: qoq | C29: 부채총계 QoQ | G29: =IFERROR(subQ!G22/subQ!E22-1,"") | H29: =IFERROR(subQ!H22/subQ!G22-1,"") | I29: =IFERROR(subQ!I22/subQ!H22-1,"") | J29: =IFERROR(subQ!J22/subQ!I22-1,"") | L29: =IFERROR(subQ!L22/subQ!J22-1,"") | M29: =IFERROR(subQ!M22/subQ!L22-1,"") | N29: =IFERROR(subQ!N22/subQ!M22-1,"") | O29: =IFERROR(subQ!O22/subQ!N22-1,"") | Q29: =IFERROR(subQ!Q22/subQ!O22-1,"") | R29: =IFERROR(subQ!R22/subQ!Q22-1,"") | S29: =IFERROR(subQ!S22/subQ!R22-1,"") | T29: =IFERROR(subQ!T22/subQ!S22-1,"") | V29: =IFERROR(subQ!V22/subQ!T22-1,"") | W29: =IFERROR(subQ!W22/subQ!V22-1,"") | X29: =IFERROR(subQ!X22/subQ!W22-1,"") | Y29: =IFERROR(subQ!Y22/subQ!X22-1,"") | AA29: =IFERROR(subQ!AA22/subQ!Y22-1,"") | AB29: =IFERROR(subQ!AB22/subQ!AA22-1,"") | AC29: 2.695e-06 | AD29: 0 | AF29: 0 | AG29: 0 | AH29: 0 | AI29: 0 | AK29: 0 | AL29: 0 | AM29: 0 | AN29: 0
A30: drv:자본총계 | B30: roll | C30: 자본총계 기타변동(배당 등, 억원) | G30: =IFERROR(subQ!E23+subQ!G17-subQ!G23,"") | H30: =IFERROR(subQ!G23+subQ!H17-subQ!H23,"") | I30: =IFERROR(subQ!H23+subQ!I17-subQ!I23,"") | J30: =IFERROR(subQ!I23+subQ!J17-subQ!J23,"") | L30: =IFERROR(subQ!J23+subQ!L17-subQ!L23,"") | M30: =IFERROR(subQ!L23+subQ!M17-subQ!M23,"") | N30: =IFERROR(subQ!M23+subQ!N17-subQ!N23,"") | O30: =IFERROR(subQ!N23+subQ!O17-subQ!O23,"") | Q30: =IFERROR(subQ!O23+subQ!Q17-subQ!Q23,"") | R30: =IFERROR(subQ!Q23+subQ!R17-subQ!R23,"") | S30: =IFERROR(subQ!R23+subQ!S17-subQ!S23,"") | T30: =IFERROR(subQ!S23+subQ!T17-subQ!T23,"") | V30: =IFERROR(subQ!T23+subQ!V17-subQ!V23,"") | W30: =IFERROR(subQ!V23+subQ!W17-subQ!W23,"") | X30: =IFERROR(subQ!W23+subQ!X17-subQ!X23,"") | Y30: =IFERROR(subQ!X23+subQ!Y17-subQ!Y23,"") | AA30: =IFERROR(subQ!Y23+subQ!AA17-subQ!AA23,"") | AB30: =IFERROR(subQ!AA23+subQ!AB17-subQ!AB23,"") | AC30: 0.000410135 | AD30: -0.005496367 | AF30: 0.001310473 | AG30: -0.002655976 | AH30: -0.001780722 | AI30: -0.005210326 | AK30: 0.001659531 | AL30: -0.005004481 | AM30: -0.005319091 | AN30: 0.008387026
A31: drv:지배주주지분 | B31: roll | C31: 지배주주지분 기타변동(배당 등, 억원) | G31: =IFERROR(subQ!E24+subQ!G18-subQ!G24,"") | H31: =IFERROR(subQ!G24+subQ!H18-subQ!H24,"") | I31: =IFERROR(subQ!H24+subQ!I18-subQ!I24,"") | J31: =IFERROR(subQ!I24+subQ!J18-subQ!J24,"") | L31: =IFERROR(subQ!J24+subQ!L18-subQ!L24,"") | M31: =IFERROR(subQ!L24+subQ!M18-subQ!M24,"") | N31: =IFERROR(subQ!M24+subQ!N18-subQ!N24,"") | O31: =IFERROR(subQ!N24+subQ!O18-subQ!O24,"") | Q31: =IFERROR(subQ!O24+subQ!Q18-subQ!Q24,"") | R31: =IFERROR(subQ!Q24+subQ!R18-subQ!R24,"") | S31: =IFERROR(subQ!R24+subQ!S18-subQ!S24,"") | T31: =IFERROR(subQ!S24+subQ!T18-subQ!T24,"") | V31: =IFERROR(subQ!T24+subQ!V18-subQ!V24,"") | W31: =IFERROR(subQ!V24+subQ!W18-subQ!W24,"") | X31: =IFERROR(subQ!W24+subQ!X18-subQ!X24,"") | Y31: =IFERROR(subQ!X24+subQ!Y18-subQ!Y24,"") | AA31: =IFERROR(subQ!Y24+subQ!AA18-subQ!AA24,"") | AB31: =IFERROR(subQ!AA24+subQ!AB18-subQ!AB24,"") | AC31: 0.000910135 | AD31: -0.005496367 | AF31: 0.001310473 | AG31: -0.002655976 | AH31: -0.001780722 | AI31: -0.005210326 | AK31: 0.001659531 | AL31: -0.005004481 | AM31: -0.005319091 | AN31: 0.008387026
A32: drv:총차입금 | B32: qoq | C32: 총차입금 QoQ | G32: =IFERROR(subQ!G25/subQ!E25-1,"") | H32: =IFERROR(subQ!H25/subQ!G25-1,"") | I32: =IFERROR(subQ!I25/subQ!H25-1,"") | J32: =IFERROR(subQ!J25/subQ!I25-1,"") | L32: =IFERROR(subQ!L25/subQ!J25-1,"") | M32: =IFERROR(subQ!M25/subQ!L25-1,"") | N32: =IFERROR(subQ!N25/subQ!M25-1,"") | O32: =IFERROR(subQ!O25/subQ!N25-1,"") | Q32: =IFERROR(subQ!Q25/subQ!O25-1,"") | R32: =IFERROR(subQ!R25/subQ!Q25-1,"") | S32: =IFERROR(subQ!S25/subQ!R25-1,"") | T32: =IFERROR(subQ!T25/subQ!S25-1,"") | V32: =IFERROR(subQ!V25/subQ!T25-1,"") | W32: =IFERROR(subQ!W25/subQ!V25-1,"") | X32: =IFERROR(subQ!X25/subQ!W25-1,"") | Y32: =IFERROR(subQ!Y25/subQ!X25-1,"") | AA32: =IFERROR(subQ!AA25/subQ!Y25-1,"") | AB32: =IFERROR(subQ!AB25/subQ!AA25-1,"") | AC32: 1.774e-06 | AD32: 0 | AF32: 0 | AG32: 0 | AH32: 0 | AI32: 0 | AK32: 0 | AL32: 0 | AM32: 0 | AN32: 0
A33: drv:순차입금 | B33: qoq | C33: 순차입금 QoQ | G33: =IFERROR(subQ!G26/subQ!E26-1,"") | H33: =IFERROR(subQ!H26/subQ!G26-1,"") | I33: =IFERROR(subQ!I26/subQ!H26-1,"") | J33: =IFERROR(subQ!J26/subQ!I26-1,"") | L33: =IFERROR(subQ!L26/subQ!J26-1,"") | M33: =IFERROR(subQ!M26/subQ!L26-1,"") | N33: =IFERROR(subQ!N26/subQ!M26-1,"") | O33: =IFERROR(subQ!O26/subQ!N26-1,"") | Q33: =IFERROR(subQ!Q26/subQ!O26-1,"") | R33: =IFERROR(subQ!R26/subQ!Q26-1,"") | S33: =IFERROR(subQ!S26/subQ!R26-1,"") | T33: =IFERROR(subQ!T26/subQ!S26-1,"") | V33: =IFERROR(subQ!V26/subQ!T26-1,"") | W33: =IFERROR(subQ!W26/subQ!V26-1,"") | X33: =IFERROR(subQ!X26/subQ!W26-1,"") | Y33: =IFERROR(subQ!Y26/subQ!X26-1,"") | AA33: =IFERROR(subQ!AA26/subQ!Y26-1,"") | AB33: =IFERROR(subQ!AB26/subQ!AA26-1,"") | AC33: -0.017075663 | AD33: -0.017830609 | AF33: -0.017977023 | AG33: -0.018799572 | AH33: -0.019834407 | AI33: -0.020924063 | AK33: -0.021090035 | AL33: -0.021727209 | AM33: -0.022810389 | AN33: -0.024244328
A34: drv:이자발생자산 | B34: qoq | C34: 이자발생자산 QoQ | G34: =IFERROR(subQ!G27/subQ!E27-1,"") | H34: =IFERROR(subQ!H27/subQ!G27-1,"") | I34: =IFERROR(subQ!I27/subQ!H27-1,"") | J34: =IFERROR(subQ!J27/subQ!I27-1,"") | L34: =IFERROR(subQ!L27/subQ!J27-1,"") | M34: =IFERROR(subQ!M27/subQ!L27-1,"") | N34: =IFERROR(subQ!N27/subQ!M27-1,"") | O34: =IFERROR(subQ!O27/subQ!N27-1,"") | Q34: =IFERROR(subQ!Q27/subQ!O27-1,"") | R34: =IFERROR(subQ!R27/subQ!Q27-1,"") | S34: =IFERROR(subQ!S27/subQ!R27-1,"") | T34: =IFERROR(subQ!T27/subQ!S27-1,"") | V34: =IFERROR(subQ!V27/subQ!T27-1,"") | W34: =IFERROR(subQ!W27/subQ!V27-1,"") | X34: =IFERROR(subQ!X27/subQ!W27-1,"") | Y34: =IFERROR(subQ!Y27/subQ!X27-1,"") | AA34: =IFERROR(subQ!AA27/subQ!Y27-1,"") | AB34: =IFERROR(subQ!AB27/subQ!AA27-1,"") | AC34: 0.090500077 | AD34: 0.085177175 | AF34: 0.077724973 | AG34: 0.074063537 | AH34: 0.071384425 | AI34: 0.068894474 | AK34: 0.063605875 | AL34: 0.060309521 | AM34: 0.058417365 | AN34: 0.057324635
A35: drv:현금및현금성자산 | B35: qoq | C35: 현금및현금성자산 QoQ | G35: =IFERROR(subQ!G28/subQ!E28-1,"") | H35: =IFERROR(subQ!H28/subQ!G28-1,"") | I35: =IFERROR(subQ!I28/subQ!H28-1,"") | J35: =IFERROR(subQ!J28/subQ!I28-1,"") | L35: =IFERROR(subQ!L28/subQ!J28-1,"") | M35: =IFERROR(subQ!M28/subQ!L28-1,"") | N35: =IFERROR(subQ!N28/subQ!M28-1,"") | O35: =IFERROR(subQ!O28/subQ!N28-1,"") | Q35: =IFERROR(subQ!Q28/subQ!O28-1,"") | R35: =IFERROR(subQ!R28/subQ!Q28-1,"") | S35: =IFERROR(subQ!S28/subQ!R28-1,"") | T35: =IFERROR(subQ!T28/subQ!S28-1,"") | V35: =IFERROR(subQ!V28/subQ!T28-1,"") | W35: =IFERROR(subQ!W28/subQ!V28-1,"") | X35: =IFERROR(subQ!X28/subQ!W28-1,"") | Y35: =IFERROR(subQ!Y28/subQ!X28-1,"") | AA35: =IFERROR(subQ!AA28/subQ!Y28-1,"") | AB35: =IFERROR(subQ!AB28/subQ!AA28-1,"")
A36: drv:CAPEX | B36: yoy | C36: CAPEX YoY | J36: =IFERROR(subQ!J29/subQ!E29-1,"") | L36: =IFERROR(subQ!L29/subQ!G29-1,"") | M36: =IFERROR(subQ!M29/subQ!H29-1,"") | N36: =IFERROR(subQ!N29/subQ!I29-1,"") | O36: =IFERROR(subQ!O29/subQ!J29-1,"") | Q36: =IFERROR(subQ!Q29/subQ!L29-1,"") | R36: =IFERROR(subQ!R29/subQ!M29-1,"") | S36: =IFERROR(subQ!S29/subQ!N29-1,"") | T36: =IFERROR(subQ!T29/subQ!O29-1,"") | V36: =IFERROR(subQ!V29/subQ!Q29-1,"") | W36: =IFERROR(subQ!W29/subQ!R29-1,"") | X36: =IFERROR(subQ!X29/subQ!S29-1,"") | Y36: =IFERROR(subQ!Y29/subQ!T29-1,"") | AA36: =IFERROR(subQ!AA29/subQ!V29-1,"") | AB36: =IFERROR(subQ!AB29/subQ!W29-1,"") | AC36: 0.36139455 | AD36: -0.20983526 | AF36: 2.0630025 | AG36: -0.7805048 | AH36: 0 | AI36: 0 | AK36: 0 | AL36: 0 | AM36: 0 | AN36: 0
A37: drv:영업활동현금흐름 | B37: yoy | C37: 영업활동현금흐름 YoY | J37: =IFERROR(subQ!J30/subQ!E30-1,"") | L37: =IFERROR(subQ!L30/subQ!G30-1,"") | M37: =IFERROR(subQ!M30/subQ!H30-1,"") | N37: =IFERROR(subQ!N30/subQ!I30-1,"") | O37: =IFERROR(subQ!O30/subQ!J30-1,"") | Q37: =IFERROR(subQ!Q30/subQ!L30-1,"") | R37: =IFERROR(subQ!R30/subQ!M30-1,"") | S37: =IFERROR(subQ!S30/subQ!N30-1,"") | T37: =IFERROR(subQ!T30/subQ!O30-1,"") | V37: =IFERROR(subQ!V30/subQ!Q30-1,"") | W37: =IFERROR(subQ!W30/subQ!R30-1,"") | X37: =IFERROR(subQ!X30/subQ!S30-1,"") | Y37: =IFERROR(subQ!Y30/subQ!T30-1,"") | AA37: =IFERROR(subQ!AA30/subQ!V30-1,"") | AB37: =IFERROR(subQ!AB30/subQ!W30-1,"")
A38: drv:주식수 | B38: qoq | C38: 주식수 QoQ | G38: =IFERROR(subQ!G31/subQ!E31-1,"") | H38: =IFERROR(subQ!H31/subQ!G31-1,"") | I38: =IFERROR(subQ!I31/subQ!H31-1,"") | J38: =IFERROR(subQ!J31/subQ!I31-1,"") | L38: =IFERROR(subQ!L31/subQ!J31-1,"") | M38: =IFERROR(subQ!M31/subQ!L31-1,"") | N38: =IFERROR(subQ!N31/subQ!M31-1,"") | O38: =IFERROR(subQ!O31/subQ!N31-1,"") | Q38: =IFERROR(subQ!Q31/subQ!O31-1,"") | R38: =IFERROR(subQ!R31/subQ!Q31-1,"") | S38: =IFERROR(subQ!S31/subQ!R31-1,"") | T38: =IFERROR(subQ!T31/subQ!S31-1,"") | V38: =IFERROR(subQ!V31/subQ!T31-1,"") | W38: =IFERROR(subQ!W31/subQ!V31-1,"") | X38: =IFERROR(subQ!X31/subQ!W31-1,"") | Y38: =IFERROR(subQ!Y31/subQ!X31-1,"") | AA38: =IFERROR(subQ!AA31/subQ!Y31-1,"") | AB38: =IFERROR(subQ!AB31/subQ!AA31-1,"") | AC38: 0 | AD38: 0 | AF38: 0 | AG38: 0 | AH38: 0 | AI38: 0 | AK38: 0 | AL38: 0 | AM38: 0 | AN38: 0
A39: drv:DPS | B39: abs | C39: DPS (가정, 원) | E39: =subQ!E34 | F39: =subQ!F34 | G39: =subQ!G34 | H39: =subQ!H34 | I39: =subQ!I34 | J39: =subQ!J34 | K39: =subQ!K34 | L39: =subQ!L34 | ... AB39: =subQ!AB34 | AD39: 0 | AE39: =subQ!AE34 | AI39: 0 | AJ39: =subQ!AJ34 | AN39: 0 | AO39: =subQ!AO34
B41: 3. 밸류에이션·스칼라 | C41: 노란 셀 = 가정. '연결' 표시는 추정 전 분기 수식이 이 셀을 참조한다는 뜻
A42: sc:종가 | C42: 종가 | D42: 978 | E42: 원 — 네이버 정규장 종가(aik 확정종가 대조 · aik 1,000원)
A43: sc:기준일 | C43: 기준일 | D43: 20261013 | E43: 종가 기준일
A44: sc:COE | C44: COE | D44: 0.09 | E44: 자기자본비용(가정) — TP 적정 PBR = ROE/COE
A45: sc:PER_lo | C45: PER_lo | D45: 10 | E45: PER 밴드 하단(배) — sector_default(레퍼런스 TP_PE PB 예시 10/15/20배; 과거 양(+)EPS 분기 2개 < 4)
A46: sc:PER_mid | C46: PER_mid | D46: 15 | E46: PER 밴드 중단(배)
A47: sc:PER_hi | C47: PER_hi | D47: 20 | E47: PER 밴드 상단(배)
A48: sc:EPS_Y1가중 | C48: EPS_Y1가중 | D48: 0.5 | E48: 12M fwd EPS = FY(last_actual연도)E × w + FY+1E × (1−w) — 기준 분기 2Q 이면 0.5(가정)
A49: sc:세율 | C49: 세율 | D49: 0.22020029 | E49: 연결 — 법인세 = MAX(세전,0) × 세율(역산, 재현 오차 ≤ 0.05억 · 모델 assumptions 0.22) · 최근 12분기 세전 합 ≤ 0; 세전 > 0 분기 중위 -1.7% 도 5~27% 밖 → 법정세율 근사 22% 가정
A50: sc:판관비율 | C50: 판관비율 | D50: 0.052023311 | E50: 연결 — 판관비 = 매출액 × 판관비율(역산, 재현 오차 ≤ 0.05억 · 모델 assumptions 0.052)
A51: sc:지배주주비중 | C51: 지배주주비중 | D51: 1 | E51: 연결 — 지배주주순이익 = 당기순이익 × 비중(역산, 재현 오차 ≤ 0.05억)
A52: sc:이자율_자산 | C52: 이자율_자산 | D52: 0.00092396389 | E52: 연결 — 이자손익 = (전분기 이자발생자산 × 자산이자율 − 전분기 총차입금 × 부채이자율)/4(역산, 재현 오차 ≤ 0.05억 · 모델 assumptions 0.0009)
A53: sc:이자율_부채 | C53: 이자율_부채 | D53: 5.8786721e-06 | E53: 연결 — 같은 수식의 부채 쪽(총차입금 행이 없으면 0)(역산, 재현 오차 ≤ 0.05억)
A54: sc:배당성향 | C54: 배당성향 | E54: 배당성향(참고 — 모델은 직전 DPS 유지·Q2 지급 가정)
A55: sc:외화순노출_백만$ | C55: 외화순노출_백만$ | E55: 외화 순노출 × Δ기말환율 (외화 시트 방식) — 외화 순노출 미공시(face) → 0 + 표기
A56: sc:헤지비율 | C56: 헤지비율 | E56: sls 없음
A57: sc:헤지환율_약정 | C57: 헤지환율_약정 | E57: sls 없음

Sheet BS연결
B1: (백만원) | C1: 이름: BS연결H | E1: 4Q21 | F1: 2021 | G1: 1Q22 | H1: 2Q22 | I1: 3Q22 | J1: 4Q22 | K1: 2022 | L1: 1Q23 | M1: 2Q23 | N1: 3Q23 | O1: 4Q23 | P1: 2023 | Q1: 1Q24 | R1: 2Q24 | S1: 3Q24 | T1: 4Q24 | U1: 2024 | V1: 1Q25 | W1: 2Q25 | X1: 3Q25 | Y1: 4Q25 | Z1: 2025 | AA1: 1Q26 | AB1: 2Q26 | AC1: 3Q26 | AD1: 4Q26 | AE1: 2026 | AF1: 1Q27 | AG1: 2Q27 | AH1: 3Q27 | AI1: 4Q27 | AJ1: 2027 | AK1: 1Q28 | AL1: 2Q28 | AM1: 3Q28 | AN1: 4Q28 | AO1: 2028
B2: 연결 | D2: fin json(kship_fin.py)
B3: 화인베스틸(연) | C3: UPDATE: 26-10-13 | E3: 1 | F3: 2 | G3: 3 | H3: 4 | I3: 5 | J3: 6 | K3: 7 | L3: 8 | M3: 9 | N3: 10 | O3: 11 | P3: 12 | Q3: 13 | R3: 14 | S3: 15 | T3: 16 | U3: 17 | V3: 18 | W3: 19 | X3: 20 | Y3: 21 | Z3: 22 | AA3: 23 | AB3: 24 | AC3: 25 | AD3: 26 | AE3: 27 | AF3: 28 | AG3: 29 | AH3: 30 | AI3: 31 | AJ3: 32 | AK3: 33 | AL3: 34 | AM3: 35 | AN3: 36 | AO3: 37
B4: Account Code | C4: AccountNAME | E4: 2021.12 | F4: 2021.12A | G4: 2022.03 | H4: 2022.06 | I4: 2022.09 | J4: 2022.12 | K4: 2022.12A | L4: 2023.03 | M4: 2023.06 | N4: 2023.09 | O4: 2023.12 | P4: 2023.12A | Q4: 2024.03 | R4: 2024.06 | S4: 2024.09 | T4: 2024.12 | U4: 2024.12A | V4: 2025.03 | W4: 2025.06 | X4: 2025.09 | Y4: 2025.12 | Z4: 2025.12A | AA4: 2026.03 | AB4: 2026.06 | AC4: 2026.09 | AD4: 2026.12 | AE4: 2026.12A | AF4: 2027.03 | AG4: 2027.06 | AH4: 2027.09 | AI4: 2027.12 | AJ4: 2027.12A | AK4: 2028.03 | AL4: 2028.06 | AM4: 2028.09 | AN4: 2028.12 | AO4: 2028.12A
A5: 1 | C5: 유동자산 | N5: 80500.2 | O5: 72783.2 | P5: 72783.2 | Q5: 65031.36 | R5: 64331.43 | S5: 49508.5 | T5: 43473.53 | U5: 43473.53 | V5: 49010.07 | W5: 47356.74 | X5: 69246.15 | Y5: 62163.93 | Z5: 62163.93 | AA5: 67737.44 | AB5: 90132.46
A6: 1 | C6: 현금및현금성자산 | N6: 8451.55 | O6: 3529.8 | P6: 3529.8 | Q6: 5395.63 | R6: 7659.37 | S6: 3611 | T6: 6099.74 | U6: 6099.74 | V6: 5079.65 | W6: 5452.05 | X6: 13091.42 | Y6: 7855.11 | Z6: 7855.11 | AA6: 2499.51 | AB6: 12097.22
A7: 1 | C7: 단기금융상품 | N7: 1481.14 | O7: 1882.03 | P7: 1882.03 | Q7: 2492.16 | R7: 2482.89 | S7: 2249.52 | T7: 1.9 | U7: 1.9 | V7: 1.9 | W7: 1.91 | X7: 1.91 | Y7: 194.15 | Z7: 194.15 | AA7: 277.82 | AB7: 1705.08
A8: 1 | C8: 단기금융자산 | N8: 1481.14 | O8: 1882.03 | P8: 1882.03 | Q8: 2492.16 | R8: 2482.89 | S8: 2249.52 | T8: 1.9 | U8: 1.9 | V8: 1.9 | W8: 1.91 | X8: 1.91 | Y8: 194.15 | Z8: 194.15 | AA8: 277.82 | AB8: 1705.08
A9: 1 | C9: 매출채권및기타채권 | N9: 32090 | O9: 32239.63 | P9: 32239.63 | Q9: 25706.86 | R9: 29650.85 | S9: 18103.16 | T9: 19614.94 | U9: 19614.94 | V9: 21841.42 | W9: 20397.82 | X9: 26696.39 | Y9: 20184.13 | Z9: 20184.13 | AA9: 21495.12 | AB9: 27862.2
A10: 1 | C10: 당기법인세자산(선급법인세) | N10: 0.91 | O10: 2.51 | P10: 2.51 | Q10: 17.17 | R10: 26.62 | S10: 34.05 | T10: 36.2 | U10: 36.2 | V10: 59.78 | W10: 26.93 | X10: 27.82 | Y10: 25.63 | Z10: 25.63 | AA10: 25.84 | AB10: 3.03
A11: 1 | C11: 재고자산 | N11: 34597.77 | O11: 32576.48 | P11: 32576.48 | Q11: 28935.28 | R11: 24303.7 | S11: 24988.01 | T11: 16715 | U11: 16715 | V11: 21863.63 | W11: 18734.09 | X11: 28953.2 | Y11: 32098.86 | Z11: 32098.86 | AA11: 34655.61 | AB11: 48349.61
A12: 1 | C12: 기타유동금융자산 | N12: 1496.28
A13: 1 | C13: 기타유동자산 | N13: 2382.56 | O13: 2215.96 | P13: 2215.96 | Q13: 2147.49 | R13: 85.07 | S13: 400.81 | T13: 976.3 | U13: 976.3 | V13: 134.22 | W13: 2743.95 | X13: 475.39 | Y13: 1806.06 | Z13: 1806.06 | AA13: 8783.54 | AB13: 115.32
A14: 1 | C14: 비유동자산 | N14: 110568.15 | O14: 117512.76 | P14: 117512.76 | Q14: 114140.93 | R14: 112704.4 | S14: 112124.81 | T14: 108899.31 | U14: 108899.31 | V14: 106872.1 | W14: 102447.53 | X14: 115492.63 | Y14: 109453.55 | Z14: 109453.55 | AA14: 106646.68 | AB14: 109737.78
A15: 1 | C15: 장기금융자산 | N15: 228.65 | O15: 5110.56 | P15: 5110.56 | Q15: 2923.03 | R15: 4844.58 | S15: 5585.4 | T15: 5030.98 | U15: 5030.98 | V15: 4899.68 | W15: 4825.79 | X15: 6495.54 | Y15: 3116.31 | Z15: 3116.31 | AA15: 2257.74 | AB15: 2734.15
A16: 1 | C16: 투자자산 | N16: 228.65 | O16: 5110.56 | P16: 5110.56 | Q16: 2923.03 | R16: 4844.58 | S16: 5585.4 | T16: 5030.98 | U16: 5030.98 | V16: 4899.68 | W16: 4825.79 | X16: 6495.54 | Y16: 3116.31 | Z16: 3116.31 | AA16: 2257.74 | AB16: 2734.15
A17: 1 | C17: 장기매출채권및기타채권 | N17: 1154.78 | O17: 1063.32 | P17: 1063.32 | Q17: 1272.29 | R17: 1297.12 | S17: 1070.17 | T17: 541.73 | U17: 541.73 | V17: 502.06 | W17: 393.12 | X17: 451.12 | Y17: 507.2 | Z17: 507.2 | AA17: 243.25 | AB17: 228.25
A18: 1 | C18: 유형자산 | N18: 84925.63 | O18: 83235.47 | P18: 83235.47 | Q18: 81890.95 | R18: 80146.78 | S18: 78976.96 | T18: 77558.31 | U18: 77558.31 | V18: 75717.07 | W18: 74111.35 | X18: 90267.04 | Y18: 89708.07 | Z18: 89708.07 | AA18: 88224.57 | AB18: 91055.1
A19: 1 | C19: 투자부동산 | N19: 9149.02 | O19: 11492.49 | P19: 11492.49 | Q19: 11465.98 | R19: 11439.47 | S19: 11412.96 | T19: 11386.44 | U19: 11386.44 | V19: 11359.93 | W19: 11333.42 | X19: 8645.94 | Y19: 8619.46 | Z19: 8619.46 | AA19: 8592.95 | AB19: 7153.85
A20: 1 | C20: 무형자산 | N20: 11825.4 | O20: 12572.58 | P20: 12572.58 | Q20: 12399.65 | R20: 12226.71 | S20: 12053.77 | T20: 10127.56 | U20: 10127.56 | V20: 9981.69 | W20: 9807.35 | X20: 9632.99 | Y20: 7502.53 | Z20: 7502.53 | AA20: 7328.19 | AB20: 8566.44
A21: 1 | C21: 이연법인세자산 | N21: 3284.67 | O21: 4038.33 | P21: 4038.33 | Q21: 4189.02 | R21: 2749.74 | S21: 3025.55 | T21: 4254.28 | U21: 4254.28 | V21: 4411.67 | W21: 1976.5
A22: 1 | C22: 자산총계 | N22: 191068.35 | O22: 190295.96 | P22: 190295.96 | Q22: 179172.29 | R22: 177035.83 | S22: 161633.31 | T22: 152372.84 | U22: 152372.84 | V22: 155882.17 | W22: 149804.27 | X22: 184738.77 | Y22: 171617.47 | Z22: 171617.47 | AA22: 174384.12 | AB22: 199870.23
A23: 1 | C23: 유동부채 | N23: 94862.88 | O23: 119570.95 | P23: 119570.95 | Q23: 115069.1 | R23: 115775.1 | S23: 107417.35 | T23: 111705.16 | U23: 111705.16 | V23: 122013.56 | W23: 111044.2 | X23: 123539.14 | Y23: 106919.48 | Z23: 106919.48 | AA23: 110973.12 | AB23: 113539.58
A24: 1 | C24: 매입채무및기타채무 | N24: 92871.75 | O24: 19440.14 | P24: 19440.14 | Q24: 12959.28 | R24: 23456.22 | S24: 14261.42 | T24: 16319.29 | U24: 16319.29 | V24: 25902.6 | W24: 22774.71 | X24: 36613.25 | Y24: 25077.03 | Z24: 25077.03 | AA24: 32337.41 | AB24: 38240.86
A25: 1 | C25: 기타유동금융부채 | N25: 993.85 | O25: 6926.4 | P25: 6926.4 | Q25: 6831.94 | R25: 5743.68 | S25: 5743.68 | T25: 8276.1 | U25: 8276.1 | V25: 8276.1 | W25: 303.18 | X25: 303.18 | AA25: 44 | AB25: 15
A26: 1 | C26: 단기금융부채 | N26: 993.85 | O26: 7329.07 | P26: 7329.07 | Q26: 7224.37 | R26: 6194.73 | S26: 6169.73 | T26: 8738.25 | U26: 8738.25 | V26: 8702 | W26: 614.74 | X26: 547.22 | Y26: 193.27 | Z26: 193.27 | AA26: 182.85 | AB26: 143.13
A27: 1 | C27: 단기충당부채 | N27: 30.9
A28: 1 | C28: 기타유동부채 | N28: 966.38 | O28: 929.05 | P28: 929.05 | Q28: 303.54 | R28: 471.14 | S28: 843.92 | T28: 277.21 | U28: 277.21 | V28: 312.18 | W28: 1136.59 | X28: 1545.82 | Y28: 1088.21 | Z28: 1088.21 | AA28: 1161.93 | AB28: 1065.09
A29: 1 | C29: 비유동부채 | N29: 25880.05 | O29: 5734.35 | P29: 5734.35 | Q29: 5998.2 | R29: 6234.23 | S29: 6623.41 | T29: 7074.63 | U29: 7074.63 | V29: 6927.41 | W29: 6784.78 | X29: 8924.84 | Y29: 12932.78 | Z29: 12932.78 | AA29: 12438.68 | AB29: 34903.02
A30: 1 | C30: 장기매입채무및기타채무 | N30: 9165.89 | O30: 371.44 | P30: 371.44 | Q30: 310 | R30: 310 | S30: 300 | T30: 300 | U30: 300 | V30: 310 | W30: 310 | X30: 310 | Y30: 310 | Z30: 310 | AA30: 310 | AB30: 310
A31: 1 | C31: 기타비유동금융부채 | N31: 13311.6
A32: 1 | C32: 장기금융부채 | N32: 13311.6 | O32: 307.76 | P32: 307.76 | Q32: 367.28 | R32: 401.41 | S32: 336.07 | T32: 287.98 | U32: 287.98 | V32: 205.16 | W32: 95.95 | X32: 80.58 | Y32: 105.23 | Z32: 105.23 | AA32: 97.64 | AB32: 83.27
A33: 1 | C33: 장기충당부채 | N33: 50.67 | O33: 55.38 | P33: 55.38 | Q33: 55.38 | R33: 28.4 | S33: 25.02 | T33: 160.37 | U33: 160.37 | V33: 160.37 | W33: 158.97 | X33: 149.9 | Y33: 170.7 | Z33: 170.7 | AA33: 170.7 | AB33: 177.63
A34: 1 | C34: 확정급여부채 | N34: 3351.89 | O34: 3483.76 | P34: 3483.76 | Q34: 3821.67 | R34: 3709.69 | S34: 4249.74 | T34: 4898.77 | U34: 4898.77 | V34: 5215.37 | W34: 5219.26 | X34: 5626.31 | Y34: 5382.88 | Z34: 5382.88 | AA34: 5449.73 | AB34: 4695.29
A35: 1 | C35: 부채총계 | N35: 120742.93 | O35: 125305.3 | P35: 125305.3 | Q35: 121067.3 | R35: 122009.33 | S35: 114040.76 | T35: 118779.79 | U35: 118779.79 | V35: 128940.98 | W35: 117828.98 | X35: 132463.99 | Y35: 119852.26 | Z35: 119852.26 | AA35: 123411.79 | AB35: 148442.6
A36: 1 | C36: 지배주주지분 | N36: 67428.99 | O36: 61109.44 | P36: 61109.44 | Q36: 56349.01 | R36: 53662.97 | S36: 46514.14 | T36: 33041.82 | U36: 33041.82 | V36: 26686.19 | W36: 31060.57 | X36: 50240.53 | Y36: 50334.12 | Z36: 50334.12 | AA36: 50002.77 | AB36: 50402.68
A37: 1 | C37: 자본금 | N37: 16234.06 | O37: 16234.06 | P37: 16234.06 | Q37: 16688.06 | R37: 16688.06 | S37: 16688.06 | T37: 16688.06 | U37: 16688.06 | V37: 16688.06 | W37: 16688.06 | X37: 18732.25 | Y37: 19832.25 | Z37: 19832.25 | AA37: 19832.25 | AB37: 19832.25
A38: 1 | C38: 자본잉여금 | N38: 61458.33 | O38: 61458.33 | P38: 61458.33 | Q38: 62004.04 | R38: 62223.59 | S38: 62285.66 | T38: 62302.9 | U38: 62302.9 | V38: 62302.9 | W38: 60879.15 | X38: 65331.39 | Y38: 68187.8 | Z38: 68187.8 | AA38: 68215.06 | AB38: 68215.06
A39: 1 | C39: 기타자본 | N39: -26.25 | O39: -73.04 | P39: -73.04 | Q39: -1233.55 | R39: -1099.88 | S39: -703.61 | T39: -1101.98 | U39: -1101.98 | V39: -1189.82 | W39: -1341.16 | X39: 14317.66 | Y39: 12120.4 | Z39: 12120.4 | AA39: 11550.76 | AB39: 11876.19
A40: 1 | C40: 이익잉여금 | N40: -10237.14 | O40: -16509.91 | P40: -16509.91 | Q40: -21109.53 | R40: -24148.8 | S40: -31755.97 | T40: -44847.16 | U40: -44847.16 | V40: -51114.94 | W40: -45165.47 | X40: -48140.78 | Y40: -49806.33 | Z40: -49806.33 | AA40: -49595.29 | AB40: -49520.82
A41: 1 | C41: 비지배주주지분 | N41: 2896.43 | O41: 3881.22 | P41: 3881.22 | Q41: 1755.98 | R41: 1363.53 | S41: 1078.41 | T41: 551.23 | U41: 551.23 | V41: 255 | W41: 914.71 | X41: 2034.26 | Y41: 1431.1 | Z41: 1431.1 | AA41: 969.56 | AB41: 1024.95
A42: 1 | C42: 자본총계 | N42: 70325.42 | O42: 64990.66 | P42: 64990.66 | Q42: 58104.99 | R42: 55026.5 | S42: 47592.55 | T42: 33593.05 | U42: 33593.05 | V42: 26941.2 | W42: 31975.29 | X42: 52274.79 | Y42: 51765.22 | Z42: 51765.22 | AA42: 50972.33 | AB42: 51427.63
A43: 1 | C43: 부채와자본총계 | N43: 191068.35 | O43: 190295.96 | P43: 190295.96 | Q43: 179172.29 | R43: 177035.83 | S43: 161633.31 | T43: 152372.84 | U43: 152372.84 | V43: 155882.17 | W43: 149804.27 | X43: 184738.77 | Y43: 171617.47 | Z43: 171617.47 | AA43: 174384.12 | AB43: 199870.23
... A45: 1 | C45: 단기차입금 | N45: 73684.88 | O45: 79426.33 | P45: 79426.33 | Q45: 82808.27 | R45: 75475.61 | S45: 75473.89 | T45: 74973.21 | U45: 74973.21 | V45: 74850.48 | W45: 73797.34 | X45: 83098.69 | Y45: 79602.6 | Z45: 79602.6 | AA45: 77289.87 | AB45: 74060.86
A46: 1 | C46: 유동성장기부채 | N46: 1142.71 | O46: 12446.36 | P46: 12446.36 | Q46: 11773.63 | R46: 10177.4 | S46: 10668.39 | T46: 11397.19 | U46: 11397.19 | V46: 12246.31 | W46: 12720.82 | X46: 1734.17 | Y46: 958.38 | Z46: 958.38 | AB46: 0
A47: 1 | C47: 장기차입금 | N47: 839.12 | O47: 742.88 | P47: 742.88 | Q47: 706.64 | R47: 1083.4 | S47: 1047.16 | T47: 798 | U47: 798 | V47: 442.9 | W47: 442.9 | X47: 392.77 | Y47: 4626.14 | Z47: 4626.14 | AA47: 4091.6 | AB47: 27381.96
A48: 1 | C48: 총차입금 | N48: 75666.71 | O48: 92615.57 | P48: 92615.57 | Q48: 95288.54 | R48: 86736.41 | S48: 87189.44 | T48: 87168.4 | U48: 87168.4 | V48: 87539.69 | W48: 86961.06 | X48: 85225.63 | Y48: 85187.12 | Z48: 85187.12 | AA48: 81381.47 | AB48: 101442.82
A49: 1 | C49: 순차입금 | N49: 65734.02 | O49: 87203.74 | P49: 87203.74 | Q49: 87400.75 | R49: 76594.15 | S49: 81328.92 | T49: 81066.76 | U49: 81066.76 | V49: 82458.14 | W49: 81507.1 | X49: 72132.3 | Y49: 77137.86 | Z49: 77137.86 | AA49: 78604.14 | AB49: 87640.52
A50: 1 | C50: 단기투자자산(공정가치) | O50: 336.78 | P50: 336.78 | Q50: 336.78 | R50: 122.93 | S50: 121.95 | T50: 29.46 | U50: 29.46 | V50: 29.46
A51: 1 | C51: 유동리스부채 | O51: 402.67 | P51: 402.67 | Q51: 392.43 | R51: 451.05 | S51: 426.05 | T51: 462.15 | U51: 462.15 | V51: 425.9 | W51: 311.56 | X51: 244.04 | Y51: 193.27 | Z51: 193.27 | AA51: 138.85 | AB51: 128.13
A52: 1 | C52: 리스부채 | O52: 710.43 | P52: 710.43 | Q52: 759.71 | R52: 852.46 | S52: 762.12 | T52: 750.13 | U52: 750.13 | V52: 631.06 | W52: 407.51 | X52: 324.62 | Y52: 298.5 | Z52: 298.5 | AA52: 236.49 | AB52: 211.4
A53: 1 | C53: 이연법인세부채 | O53: 773.13 | P53: 773.13 | Q53: 737.22 | R53: 701.32 | S53: 665.42 | T53: 629.51 | U53: 629.51 | V53: 593.61 | W53: 557.7 | X53: 2365.27 | Y53: 2337.83 | Z53: 2337.83 | AA53: 2319 | AB53: 2254.86
A54: 1 | C54: 비유동리스부채 | O54: 307.76 | P54: 307.76 | Q54: 367.28 | R54: 401.41 | S54: 336.07 | T54: 287.98 | U54: 287.98 | V54: 205.16 | W54: 95.95 | X54: 80.58 | Y54: 105.23 | Z54: 105.23 | AA54: 97.64 | AB54: 83.27
A55: 1 | C55: 단기금융부채(face) | Y55: 79602.6 | Z55: 79602.6 | AA55: 77289.87 | AB55: 74060.86
A56: 1 | C56: 당기법인세부채(미지급법인세) | AA56: 1.05 | AB56: 29.64
A57: 1 | C57: 매출액(수익) | N57: 31125.15 | O57: 27924.2 | Q57: 28167.21 | R57: 26005.86 | S57: 30662.72 | T57: 34336.15 | U57: 119171.94 | V57: 36645.73 | W57: 47626.54 | X57: 48514.32 | Y57: 53384.58 | Z57: 186171.17 | AA57: 50619.97 | AB57: 49136.25
A58: 1 | C58: 매출원가 | N58: 31653.59 | O58: 31358.04 | Q58: 29349.93 | R58: 30456.13 | S58: 34633.44 | T58: 38177.14 | U58: 132616.64 | V58: 39266.93 | W58: 45540.36 | X58: 46699.86 | Y58: 48572.11 | Z58: 180079.26 | AA58: 46467.94 | AB58: 44569.76
A59: 1 | C59: 매출총이익 | N59: -528.44 | O59: -3433.83 | Q59: -1182.71 | R59: -4450.28 | S59: -3970.72 | T59: -3840.99 | U59: -13444.7 | V59: -2621.2 | W59: 2086.18 | X59: 1814.45 | Y59: 4812.47 | Z59: 6091.9 | AA59: 4152.04 | AB59: 4566.49
A60: 1 | C60: 판관비 | N60: 2862.67 | O60: 7376.09 | Q60: 3211.59 | R60: -3514.85 | S60: 2827 | T60: 3169.59 | U60: 5693.33 | V60: 2830.52 | W60: 503.43 | X60: 1782.58 | Y60: 2645.87 | Z60: 7762.4 | AA60: 2758.03 | AB60: 3288.29
A61: 1 | C61: 영업이익 | N61: -3391.11 | O61: -10809.92 | Q61: -4394.3 | R61: -935.43 | S61: -6797.72 | T61: -7010.58 | U61: -19138.03 | V61: -5451.73 | W61: 1582.75 | X61: 31.88 | Y61: 2166.6 | Z61: -1670.5 | AA61: 1394.01 | AB61: 1278.2
A62: 1 | C62: 기타영업외수익 | N62: 84.37 | O62: 199.88 | Q62: 77.34 | R62: 125.31 | S62: 45.38 | T62: 100.75 | U62: 348.78 | V62: 433.97 | W62: 248.17 | X62: 4074.42 | Y62: 38.24 | Z62: 4794.8 | AA62: 104.82 | AB62: 73.26
A63: 1 | C63: 기타영업외비용 | N63: 110.8 | O63: -13.94 | Q63: 168.77 | R63: 92.68 | S63: 3.57 | T63: 1850.71 | U63: 2115.73 | V63: 41.65 | W63: 81.17 | X63: 4184.71 | Y63: 2264.05 | Z63: 6571.58 | AA63: 42.1 | AB63: 29.13
A64: 1 | C64: 금융수익 | N64: 409.58 | O64: 5273.77 | Q64: 712.67 | R64: 1347.89 | S64: 823.34 | T64: -835.76 | U64: 2048.14 | V64: 4.96 | W64: 7966.52 | X64: 17.51 | Y64: 376.69 | Z64: 8365.68 | AA64: 1.37 | AB64: 139.13
A65: 1 | C65: 금융비용 | N65: 1862.74 | O65: 1838.99 | Q65: 1944.72 | R65: 2187.83 | S65: 2607.12 | T65: 4036.3 | U65: 10775.97 | V65: 1725.87 | W65: 1719.65 | X65: 3063.21 | Y65: 1849.33 | Z65: 8358.06 | AA65: 1383.69 | AB65: 1533.64
A66: 1 | C66: 법인세비용차감전계속사업이익 | N66: -4870.69 | O66: -7161.32 | Q66: -5717.78 | R66: -1742.75 | S66: -8539.69 | T66: -13632.6 | U66: -29632.82 | V66: -6780.31 | W66: 7996.61 | X66: -3124.12 | Y66: -1531.86 | Z66: -3439.68 | AA66: 74.41 | AB66: -72.18
A67: 1 | C67: 법인세비용 | N67: -101.82 | O67: -843.85 | Q67: -188.7 | R67: 1401.04 | S67: -313.62 | T67: -1034.31 | U67: -135.59 | V67: -193 | W67: 2391.91 | X67: 260.16 | Y67: 207.71 | Z67: 2666.78 | AA67: -24.8 | AB67: -31.54
A68: 1 | C68: 당기순이익 | N68: -4768.87 | O68: -6317.47 | Q68: -5529.07 | R68: -3143.79 | S68: -8226.07 | T68: -12598.29 | U68: -29497.22 | V68: -6587.31 | W68: 5604.69 | X68: -3384.28 | Y68: -1739.57 | Z68: -6106.47 | AA68: 99.2 | AB68: -40.64
... A74: 1 | C74: 계속사업이익 | N74: -4768.87 | O74: -6317.47 | Q74: -5529.07 | R74: -3143.79 | S74: -8226.07 | T74: -12598.29 | U74: -29497.22 | V74: -6587.31 | W74: 5604.69 | X74: -3384.28 | Y74: -1739.57 | Z74: -6106.47 | AA74: 99.2 | AB74: -40.64
A75: 1 | C75: 배당금수익 | AB75: 9.24
A76: 1 | C76: 파생상품이익 | AB76: 123.1
A77: 1 | C77: 파생상품손실 | AB77: 46.05
A78: 1 | C78: 영업활동으로인한현금흐름 | N78: -3167.93 | O78: -482.77 | Q78: -4439.69 | R78: 12379.25 | S78: -3408.45 | T78: 2530.82 | U78: 7061.93 | V78: -934.43 | W78: 2161.65 | X78: 1397.78 | Y78: -6228.95 | Z78: -3603.95 | AA78: -2527.45 | AB78: 693.63
A79: 1 | C79: 배당금수취(CF) | N79: 0 | O79: 1.6 | S79: 3.2 | T79: 0 | X79: 1.92 | Y79: 11.95
A80: 1 | C80: 이자수취(CF) | N80: -0.9 | O80: 44.02 | Q80: 31.24 | R80: 57.16 | S80: 30.06 | T80: 13.48 | U80: 131.94 | V80: 5.69 | W80: 1.66 | X80: 5.66 | Y80: 1.11 | Z80: 14.12 | AA80: 1.37 | AB80: 3.69
A81: 1 | C81: 법인세납부(CF) | N81: -0.16 | O81: -1.6 | Q81: -14.66 | R81: -9.45 | S81: -7.43 | T81: -2.15 | U81: -33.69 | V81: -23.59 | W81: 32.86 | X81: -0.9 | Y81: 2.24 | Z81: 10.61 | AA81: -0.31 | AB81: 21.77
A82: 1 | C82: 투자활동으로인한현금흐름 | N82: -5525.92 | O82: -8309.78 | Q82: 3367.83 | R82: -999.01 | S82: -481.4 | T82: 678.41 | U82: 2565.83 | V82: 201.77 | W82: -522.95 | X82: 7395.16 | Y82: -2058.34 | Z82: 5015.64 | AA82: 1039.04 | AB82: -11095.81
A83: 1 | C83: 유형자산의증가 | N83: 609.93 | O83: 5044.6 | Q83: 677.61 | R83: 227.96 | S83: 929.67 | T83: 391.87 | U83: 2227.11 | V83: 154.09 | W83: 460.05 | X83: 736.01 | Y83: 1268.09 | Z83: 2618.24 | AA83: 327.13 | AB83: 4565.02
A84: 1 | C84: CAPEX | N84: 609.93 | O84: 5058.06 | Q84: 677.61 | R84: 227.96 | S84: 929.67 | T84: 391.87 | U84: 2227.11 | V84: 182.09 | W84: 460.05 | X84: 736.01 | Y84: 1268.09 | Z84: 2646.24 | AA84: 327.13 | AB84: 4565.02
A85: 1 | C85: 재무활동으로인한현금흐름 | N85: 16723.73 | O85: 3870.8 | Q85: 2937.68 | R85: -9116.5 | S85: -158.52 | T85: -720.48 | U85: -7057.82 | V85: -287.43 | W85: -1266.3 | X85: -1153.56 | Y85: 3050.97 | Z85: 343.68 | AA85: -3867.2 | AB85: 19999.9
A86: 1 | C86: 단기차입금의증가 | N86: 730.75 | O86: 23162.54 | Q86: 18077.94 | R86: 501.6 | S86: 11318.52 | T86: 16225 | U86: 46123.06 | V86: 18726.62 | W86: 31177.49 | X86: 24613.54 | Y86: 35936.34 | Z86: 110453.99 | AA86: 30375.63 | AB86: 41927.78
A87: 1 | C87: 단기차입금의감소 | N87: 279.87 | O87: 17421.08 | Q87: 14695.99 | R87: 7834.27 | S87: 11320.24 | T87: 16725.67 | U87: 50576.17 | V87: 18849.35 | W87: 32355.1 | X87: 15187.73 | Y87: 42712.17 | Z87: 109104.35 | AA87: 33215 | AB87: 51777.45
A88: 1 | C88: 장기차입금의감소 | N88: 247.99 | O88: 546.24 | Q88: 54.64 | R88: 45.59 | S88: 36.24 | T88: 556.24 | U88: 692.71 | V88: 36.24 | AA88: 39.99 | AB88: 88.99
A89: 1 | C89: 현금및현금성자산의증감 | N89: 8029.87 | O89: -4921.74 | Q89: 1865.83 | R89: 2263.73 | S89: -4048.37 | T89: 2488.75 | U89: 2569.94 | V89: -1020.09 | W89: 372.4 | X89: 7639.37 | Y89: -5236.31 | Z89: 1755.37 | AA89: -5355.61 | AB89: 9597.72
A90: 1 | C90: 기말현금및현금성자산 | N90: 8029.87 | O90: -4921.75 | Q90: 5395.63 | R90: 2263.74 | S90: -4048.37 | T90: 2488.74 | U90: 6099.74 | V90: 5079.65 | W90: 372.4 | X90: 7639.37 | Y90: -5236.31 | Z90: 7855.11 | AA90: 2499.51 | AB90: 9597.71
A91: 1 | C91: 유형자산의감소 | Q91: 24 | R91: 43.73 | S91: 65.59 | T91: 0 | U91: 133.32 | V91: 352 | W91: 145.25 | X91: 5961.91 | Y91: 32.18 | Z91: 6491.34 | AA91: 5.64 | AB91: 1.7
A92: 1 | C92: 장기차입금의증가 | S92: 0 | T92: 520 | AA92: 32.1 | AB92: 30000
A93: 1 | C93: 무형자산의증가 | V93: 28 | W93: 0 | X93: 0 | Y93: 0 | Z93: 28

Sheet BS별도
B1: (백만원) | C1: 이름: BS별도H | E1: 4Q21 | F1: 2021 | G1: 1Q22 | H1: 2Q22 | I1: 3Q22 | J1: 4Q22 | K1: 2022 | L1: 1Q23 | M1: 2Q23 | N1: 3Q23 | O1: 4Q23 | P1: 2023 | Q1: 1Q24 | R1: 2Q24 | S1: 3Q24 | T1: 4Q24 | U1: 2024 | V1: 1Q25 | W1: 2Q25 | X1: 3Q25 | Y1: 4Q25 | Z1: 2025 | AA1: 1Q26 | AB1: 2Q26 | AC1: 3Q26 | AD1: 4Q26 | AE1: 2026 | AF1: 1Q27 | AG1: 2Q27 | AH1: 3Q27 | AI1: 4Q27 | AJ1: 2027 | AK1: 1Q28 | AL1: 2Q28 | AM1: 3Q28 | AN1: 4Q28 | AO1: 2028
B2: 별도 | D2: fin json(kship_fin.py)
B3: 화인베스틸(별) | C3: UPDATE: 26-10-13 | E3: 1 | F3: 2 | G3: 3 | H3: 4 | I3: 5 | J3: 6 | K3: 7 | L3: 8 | M3: 9 | N3: 10 | O3: 11 | P3: 12 | Q3: 13 | R3: 14 | S3: 15 | T3: 16 | U3: 17 | V3: 18 | W3: 19 | X3: 20 | Y3: 21 | Z3: 22 | AA3: 23 | AB3: 24 | AC3: 25 | AD3: 26 | AE3: 27 | AF3: 28 | AG3: 29 | AH3: 30 | AI3: 31 | AJ3: 32 | AK3: 33 | AL3: 34 | AM3: 35 | AN3: 36 | AO3: 37
B4: Account Code | C4: AccountNAME | E4: 2021.12 | F4: 2021.12A | G4: 2022.03 | H4: 2022.06 | I4: 2022.09 | J4: 2022.12 | K4: 2022.12A | L4: 2023.03 | M4: 2023.06 | N4: 2023.09 | O4: 2023.12 | P4: 2023.12A | Q4: 2024.03 | R4: 2024.06 | S4: 2024.09 | T4: 2024.12 | U4: 2024.12A | V4: 2025.03 | W4: 2025.06 | X4: 2025.09 | Y4: 2025.12 | Z4: 2025.12A | AA4: 2026.03 | AB4: 2026.06 | AC4: 2026.09 | AD4: 2026.12 | AE4: 2026.12A | AF4: 2027.03 | AG4: 2027.06 | AH4: 2027.09 | AI4: 2027.12 | AJ4: 2027.12A | AK4: 2028.03 | AL4: 2028.06 | AM4: 2028.09 | AN4: 2028.12 | AO4: 2028.12A
A5: 1 | C5: 유동자산 | E5: 76618.87 | F5: 76618.87 | G5: 71249.68 | H5: 67165.39 | I5: 74556.08 | J5: 78946.83 | K5: 78946.83 | L5: 70165.68 | M5: 68759.5 | N5: 67419.54 | O5: 64638.05 | P5: 64638.05 | Q5: 59298.97 | R5: 59606.47 | S5: 45440.73 | T5: 40903.14 | U5: 40903.14 | V5: 47270.01 | W5: 45893.3 | X5: 66350.9 | Y5: 59676.67 | Z5: 59676.67 | AA5: 65331.3 | AB5: 87978.69
A6: 1 | C6: 현금및현금성자산 | E6: 1301.24 | F6: 1301.24 | G6: 406.48 | H6: 932.31 | I6: 1139.25 | J6: 4491.94 | K6: 4491.94 | L6: 3339.27 | M6: 421.68 | N6: 210.28 | O6: 339.06 | P6: 339.06 | Q6: 440.82 | R6: 3938.09 | S6: 531.53 | T6: 3740.24 | U6: 3740.24 | V6: 3778.3 | W6: 4084.19 | X6: 11567.18 | Y6: 6191.12 | Z6: 6191.12 | AA6: 1427.71 | AB6: 11820.84
A7: 1 | C7: 단기금융상품 | E7: 0.06 | F7: 0.06 | G7: 0.06 | H7: 0.06 | I7: 764.34 | J7: 305.92 | K7: 305.92 | L7: 802.11 | M7: 1163.79 | N7: 1481.12 | O7: 1882.02 | P7: 1882.02 | Q7: 2492.14 | R7: 2482.87 | S7: 2249.51 | T7: 1.88 | U7: 1.88 | V7: 1.89 | W7: 1.89 | X7: 1.9 | Y7: 194.13 | Z7: 194.13 | AA7: 277.8 | AB7: 1705.07
A8: 1 | C8: 단기금융자산 | E8: 0.06 | F8: 0.06 | G8: 0.06 | H8: 0.06 | I8: 764.34 | J8: 305.92 | K8: 305.92 | L8: 802.11 | M8: 1163.79 | N8: 1481.12 | O8: 1882.02 | P8: 1882.02 | Q8: 2492.14 | R8: 2482.87 | S8: 2249.51 | T8: 1.88 | U8: 1.88 | V8: 1.89 | W8: 1.89 | X8: 1.9 | Y8: 194.13 | Z8: 194.13 | AA8: 277.8 | AB8: 1705.07
A9: 1 | C9: 매출채권및기타채권 | E9: 34607 | F9: 34607 | G9: 27578.88 | H9: 24043.96 | I9: 26163.63 | J9: 25018.66 | K9: 25018.66 | L9: 28603.8 | M9: 28119.84 | N9: 27671.89 | O9: 27311.27 | P9: 27311.27 | Q9: 25295.68 | R9: 28697.81 | S9: 17228.58 | T9: 19475.52 | U9: 19475.52 | V9: 21488.43 | W9: 20391.43 | X9: 25395.91 | Y9: 19435.74 | Z9: 19435.74 | AA9: 20203.12 | AB9: 26034.91
A10: 1 | C10: 기타유동자산 | E10: 2703.72 | F10: 2703.72 | G10: 2722.15 | H10: 2647.12 | I10: 3168.19 | J10: 3291.39 | K10: 3291.39 | L10: 2230.49 | M10: 2903.39 | N10: 2321.89 | O10: 2190.46 | P10: 2190.46 | Q10: 1795.46 | R10: 52.11 | S10: 311.33 | T10: 931.05 | U10: 931.05 | V10: 75.48 | W10: 2657.95 | X10: 408.07 | Y10: 1740.07 | Z10: 1740.07 | AA10: 8742.16 | AB10: 65.38
A11: 1 | C11: 재고자산 | E11: 38006.86 | F11: 38006.86 | G11: 40541.19 | H11: 38775.86 | I11: 42554.55 | J11: 45440.89 | K11: 45440.89 | L11: 34775.11 | M11: 36145.19 | N11: 34597.77 | O11: 32576.48 | P11: 32576.48 | Q11: 28935.28 | R11: 24303.7 | S11: 24988.01 | T11: 16715 | U11: 16715 | V11: 21863.63 | W11: 18734.09 | X11: 28953.2 | Y11: 32090.94 | Z11: 32090.94 | AA11: 34655.61 | AB11: 48349.61
A12: 1 | C12: 비유동자산 | E12: 106620.06 | F12: 106620.06 | G12: 104709.19 | H12: 103085.9 | I12: 101764.84 | J12: 100676.08 | K12: 100676.08 | L12: 99006.78 | M12: 99663.09 | N12: 117572.86 | O12: 117998.24 | P12: 117998.24 | Q12: 116836.43 | R12: 114855.65 | S12: 114131.32 | T12: 107327.81 | U12: 107327.81 | V12: 105868.83 | W12: 101911.56 | X12: 113532.7 | Y12: 109010.15 | Z12: 109010.15 | AA12: 107625 | AB12: 110436.75
A13: 1 | C13: 장기금융자산 | E13: 674.3 | F13: 674.3 | G13: 129.26 | H13: 109.26 | I13: 98.22 | J13: 223.05 | K13: 223.05 | L13: 223.21 | M13: 229.93 | N13: 6007.83 | O13: 5115.75 | P13: 5115.75 | Q13: 5125.83 | R13: 6576.44 | S13: 6585.56 | T13: 5446.16 | U13: 5446.16 | V13: 1525.48 | W13: 1563.5 | X13: 1597.74 | Y13: 273.27 | Z13: 273.27 | AA13: 305.59 | AB13: 278.91
A14: 1 | C14: 투자자산 | E14: 674.3 | F14: 674.3 | G14: 129.26 | H14: 109.26 | I14: 98.22 | J14: 223.05 | K14: 223.05 | L14: 223.21 | M14: 1399.93 | N14: 20537.83 | O14: 19915.75 | P14: 19915.75 | Q14: 19925.83 | R14: 21376.44 | S14: 21385.56 | T14: 15123.06 | U14: 15123.06 | V14: 15316.82 | W14: 15354.84 | X14: 15389.08 | Y14: 11358.33 | Z14: 11358.33 | AA14: 11390.65 | AB14: 11363.97
A15: 1 | C15: 장기매출채권및기타채권 | E15: 95.29 | F15: 95.29 | G15: 113.41 | H15: 157.52 | I15: 632.52 | J15: 637.71 | K15: 637.71 | L15: 675.35 | M15: 675.02 | N15: 675 | O15: 678.02 | P15: 678.02 | Q15: 687.99 | R15: 719.82 | S15: 719.8 | T15: 221.36 | U15: 221.36 | V15: 183.69 | W15: 79.43 | X15: 79.43 | Y15: 135.7 | Z15: 135.7 | AA15: 146.75 | AB15: 146.75
A16: 1 | C16: 유형자산 | E16: 94583.32 | F16: 94583.32 | G16: 93104.91 | H16: 91415.75 | I16: 89660.41 | J16: 88540.98 | K16: 88540.98 | L16: 86740.76 | M16: 85615.12 | N16: 84188.56 | O16: 82426.7 | P16: 82426.7 | Q16: 81118.31 | R16: 79131.81 | S16: 78146.74 | T16: 76686 | U16: 76686 | V16: 74953.01 | W16: 73521.08 | X16: 89769.34 | Y16: 89245.19 | Z16: 89245.19 | AA16: 87840.59 | AB16: 90702.94
... A18: 1 | C18: 무형자산 | E18: 183.96 | F18: 183.96 | G18: 183.96 | H18: 183.96 | I18: 183.96 | J18: 183.96 | K18: 183.96 | L18: 183.96 | M18: 183.96 | N18: 183.96 | O18: 183.96 | P18: 183.96 | Q18: 183.96 | R18: 183.96 | S18: 183.96 | T18: 183.96 | U18: 183.96 | V18: 183.96 | W18: 183.96 | X18: 183.96 | Y18: 183.96 | Z18: 183.96 | AA18: 183.96 | AB18: 183.96
A19: 1 | C19: 이연법인세자산 | E19: 2400.29 | F19: 2400.29 | G19: 2507.55 | H19: 2562.12 | I19: 2545.26 | J19: 2458.71 | K19: 2458.71 | L19: 2564.64 | M19: 3183.01 | N19: 3284.67 | O19: 3854.5 | P19: 3854.5 | Q19: 4004.96 | R19: 2552.16 | S19: 2827.73 | T19: 4269.82 | U19: 4269.82 | V19: 4411.67 | W19: 1976.5
A20: 1 | C20: 자산총계 | E20: 183238.94 | F20: 183238.94 | G20: 175958.87 | H20: 170251.29 | I20: 176320.93 | J20: 179622.91 | K20: 179622.91 | L20: 169172.46 | M20: 168422.59 | N20: 184992.4 | O20: 182636.29 | P20: 182636.29 | Q20: 176135.4 | R20: 174462.12 | S20: 159572.05 | T20: 148230.95 | U20: 148230.95 | V20: 153138.84 | W20: 147804.86 | X20: 179883.6 | Y20: 168686.82 | Z20: 168686.82 | AA20: 172956.3 | AB20: 198415.43
A21: 1 | C21: 유동부채 | E21: 95245.46 | F21: 95245.46 | G21: 86135.4 | H21: 82372.42 | I21: 91532.42 | J21: 98773.91 | K21: 98773.91 | L21: 91023.52 | M21: 93923.81 | N21: 90246.94 | O21: 115884.38 | P21: 115884.38 | Q21: 112053.39 | R21: 112709.77 | S21: 104267.49 | T21: 108961.82 | U21: 108961.82 | V21: 118840.02 | W21: 106951.27 | X21: 119734.59 | Y21: 104319.91 | Z21: 104319.91 | AA21: 108329.95 | AB21: 110814.9
A22: 1 | C22: 매입채무및기타채무 | E22: 91715.21 | F22: 91715.21 | G22: 83107.57 | H22: 78205.12 | I22: 87980.43 | J22: 94820.74 | K22: 94820.74 | L22: 88797.26 | M22: 91434.39 | N22: 88586.07 | O22: 18691.38 | P22: 18691.38 | Q22: 12282.7 | R22: 22755.79 | S22: 13762.08 | T22: 15943.76 | U22: 15943.76 | V22: 25287.86 | W22: 21874.88 | X22: 35615.68 | Y22: 24734.44 | Z22: 24734.44 | AA22: 31875.22 | AB22: 37876.73
A23: 1 | C23: 단기차입금 | E23: 66952.56 | F23: 66952.56 | G23: 72954.56 | H23: 52105.3 | I23: 66987.73 | J23: 66237.79 | K23: 66237.79 | L23: 67470.47 | M23: 72127.57 | N23: 72672.68 | O23: 77926.33 | P23: 77926.33 | Q23: 81428.28 | R23: 74095.61 | S23: 74093.89 | T23: 73593.21 | U23: 73593.21 | V23: 73590.48 | W23: 72537.34 | X23: 81838.69 | Y23: 77499.64 | Z23: 77499.64 | AA23: 75201.91
A24: 1 | C24: 유동성장기부채 | E24: 2787.87 | F24: 2787.87 | G24: 3082.13 | H24: 7043.89 | I24: 7347.98 | J24: 7665.2 | K24: 7665.2 | L24: 7988.82 | M24: 3923.12 | N24: 3812.18 | O24: 11753.65 | P24: 11753.65 | Q24: 11099.32 | R24: 9732.44 | S24: 10223.43 | T24: 10739.31 | U24: 10739.31 | V24: 11269.57 | W24: 11832.32 | X24: 907.02 | Y24: 958.38 | Z24: 958.38 | AB24: 0
A25: 1 | C25: 유동리스부채 | E25: 64.96 | F25: 64.96 | G25: 73.68 | H25: 109.41 | I25: 109.41 | J25: 129.82 | K25: 129.82 | L25: 156.28 | M25: 163.72 | N25: 178.15 | O25: 176.21 | P25: 176.21 | Q25: 175.72 | R25: 175.72 | S25: 174.56 | T25: 196.72 | U25: 196.72 | V25: 184.41 | W25: 164.73 | X25: 132.32 | Y25: 115.43 | Z25: 115.43 | AA25: 87.22 | AB25: 71.68
A26: 1 | C26: 리스부채 | E26: 296.81 | F26: 296.81 | G26: 299.47 | H26: 425.71 | I26: 400.23 | J26: 430.63 | K26: 430.63 | L26: 480.05 | M26: 468.24 | N26: 436.62 | O26: 395.69 | P26: 395.69 | Q26: 355.6 | R26: 315.39 | S26: 278.24 | T26: 275.52 | U26: 275.52 | V26: 226.15 | W26: 175.9 | X26: 132.32 | Y26: 161.83 | Z26: 161.83 | AA26: 132.09 | AB26: 109.1
A27: 1 | C27: 단기금융부채 | E27: 5759.24 | F27: 5759.24 | G27: 5767.96 | H27: 2986.94 | I27: 2993.64 | J27: 2143.71 | K27: 2143.71 | L27: 2154.97 | M27: 1187.93 | N27: 1172 | O27: 7102.61 | P27: 7102.61 | Q27: 7007.66 | R27: 5919.4 | S27: 5918.24 | T27: 8472.82 | U27: 8472.82 | V27: 8460.51 | W27: 467.91 | X27: 435.5 | Y27: 115.43 | Z27: 115.43 | AA27: 131.22 | AB27: 86.68
A28: 1 | C28: 당기법인세부채(미지급법인세) | E28: 525.71 | F28: 525.71 | AB28: 29.64
A29: 1 | C29: 기타유동금융부채 | E29: 5694.28 | F29: 5694.28 | G29: 5694.28 | H29: 2877.53 | I29: 2884.23 | J29: 2013.89 | K29: 2013.89 | L29: 1998.69 | M29: 1024.21 | N29: 993.85 | O29: 6926.4 | P29: 6926.4 | Q29: 6831.94 | R29: 5743.68 | S29: 5743.68 | T29: 8276.1 | U29: 8276.1 | V29: 8276.1 | W29: 303.18 | X29: 303.18 | AA29: 44 | AB29: 15
A30: 1 | C30: 기타유동부채 | E30: 157.41 | F30: 157.41 | G30: 180.7 | H30: 1289.76 | I30: 667.76 | J30: 1939.27 | K30: 1939.27 | L30: 227.56 | M30: 1465.21 | N30: 667.02 | O30: 410.41 | P30: 410.41 | Q30: 235.43 | R30: 206.52 | S30: 269.84 | T30: 212.72 | U30: 212.72 | V30: 231.6 | W30: 238.82 | X30: 937.69 | Y30: 1012.02 | Z30: 1012.02 | AA30: 1121.6 | AB30: 1027.95
A31: 1 | C31: 비유동부채 | E31: 8495.61 | F31: 8495.61 | G31: 8236.65 | H31: 4211.76 | I31: 3142.49 | J31: 2586.01 | K31: 2586.01 | L31: 2887.08 | M31: 2852.66 | N31: 24334.38 | O31: 3284.33 | P31: 3284.33 | Q31: 3535.15 | R31: 3432.15 | S31: 3775.15 | T31: 4916.92 | U31: 4916.92 | V31: 5147.92 | W31: 5189.15 | X31: 7439.25 | Y31: 11761.59 | Z31: 11761.59 | AA31: 11463.21 | AB31: 34149.94
A32: 1 | C32: 장기매입채무및기타채무 | E32: 5626.69 | F32: 5626.69 | G32: 5351.76 | H32: 986.89 | I32: 684.56 | J32: 600.81 | K32: 600.81 | L32: 623.77 | M32: 604.52 | N32: 8207.34 | O32: 300 | P32: 300 | Q32: 300 | R32: 300 | S32: 300 | T32: 300 | U32: 300 | V32: 300 | W32: 300 | X32: 300 | Y32: 300 | Z32: 300 | AA32: 300 | AB32: 300
A33: 1 | C33: 기타비유동부채 | E33: 300 | F33: 300 | G33: 300 | H33: 300 | I33: 300 | J33: 300 | K33: 300 | L33: 300 | M33: 300 | N33: 3064.77
A34: 1 | C34: 장기차입금 | E34: 913.03 | F34: 913.03 | G34: 644.15 | H34: 370.59 | I34: 93.74 | M34: 373.45 | Y34: 4333.2 | Z34: 4333.2 | AA34: 3791.55 | AB34: 27249.9
A35: 1 | C35: 사채 | E35: 4181.81 | F35: 4181.81 | G35: 4181.81 | N35: 7648.87
A36: 1 | C36: 비유동리스부채 | E36: 231.85 | F36: 231.85 | G36: 225.79 | H36: 316.3 | I36: 290.82 | J36: 300.81 | K36: 300.81 | L36: 323.77 | M36: 304.52 | N36: 258.47 | O36: 219.48 | P36: 219.48 | Q36: 179.88 | R36: 139.67 | S36: 103.68 | T36: 78.8 | U36: 78.8 | V36: 41.74 | W36: 11.17 | Y36: 46.4 | Z36: 46.4 | AA36: 44.87 | AB36: 37.42
A37: 1 | C37: 장기금융부채 | E37: 231.85 | F37: 231.85 | G37: 225.79 | H37: 316.3 | I37: 290.82 | J37: 300.81 | K37: 300.81 | L37: 323.77 | M37: 304.52 | N37: 13570.07 | O37: 219.48 | P37: 219.48 | Q37: 179.88 | R37: 139.67 | S37: 103.68 | T37: 78.8 | U37: 78.8 | V37: 41.74 | W37: 11.17 | Y37: 46.4 | Z37: 46.4 | AA37: 44.87 | AB37: 37.42
A38: 1 | C38: 확정급여부채 | E38: 2868.92 | F38: 2868.92 | G38: 2884.9 | H38: 3224.87 | I38: 2457.93 | J38: 1934.53 | K38: 1934.53 | L38: 2212.64 | M38: 2193.92 | N38: 50.67 | O38: 2709.47 | P38: 2709.47 | Q38: 2999.89 | R38: 2964.08 | S38: 3346.45 | T38: 4377.75 | U38: 4377.75 | V38: 4645.82 | W38: 4719.01 | X38: 5145.87 | Y38: 5083.64 | Z38: 5083.64 | AA38: 5309.48 | AB38: 4564.72
A39: 1 | C39: 부채총계 | E39: 103741.07 | F39: 103741.07 | G39: 94372.05 | H39: 86584.18 | I39: 94674.91 | J39: 101359.93 | K39: 101359.93 | L39: 93910.6 | M39: 96776.48 | N39: 114581.33 | O39: 119168.71 | P39: 119168.71 | Q39: 115588.54 | R39: 116141.92 | S39: 108042.64 | T39: 113878.74 | U39: 113878.74 | V39: 123987.94 | W39: 112140.42 | X39: 127173.83 | Y39: 116081.5 | Z39: 116081.5 | AA39: 119793.16 | AB39: 144964.83
A40: 1 | C40: 자본금 | E40: 16050 | F40: 16050 | G40: 16050 | H40: 16165.97 | I40: 16165.97 | J40: 16165.97 | K40: 16165.97 | L40: 16165.97 | M40: 16234.06 | N40: 16234.06 | O40: 16234.06 | P40: 16234.06 | Q40: 16688.06 | R40: 16688.06 | S40: 16688.06 | T40: 16688.06 | U40: 16688.06 | V40: 16688.06 | W40: 16688.06 | X40: 18732.25 | Y40: 19832.25 | Z40: 19832.25 | AA40: 19832.25 | AB40: 19832.25
A41: 1 | C41: 자본잉여금 | E41: 60586.78 | F41: 60586.78 | G41: 60586.78 | H41: 61209 | I41: 61209 | J41: 61209 | K41: 61209 | L41: 61209 | M41: 61460.62 | N41: 61460.62 | O41: 61460.62 | P41: 61460.62 | Q41: 62006.32 | R41: 62006.32 | S41: 62006.32 | T41: 62006.32 | U41: 62006.32 | V41: 62006.32 | W41: 62006.32 | X41: 66458.57 | Y41: 69277.79 | Z41: 69277.79 | AA41: 69277.79 | AB41: 69277.79
A42: 1 | C42: 기타자본 | E42: -27.83 | F42: -27.83 | G42: -12.04 | H42: -27.64 | I42: -36.25 | J42: -30.26 | K42: -30.26 | L42: -30.13 | M42: -24.82 | N42: -26.25 | O42: -22.58 | P42: -22.58 | Q42: -14.61 | R42: -5.75 | S42: 1.46 | T42: 0.12 | U42: 0.12 | V42: -1.02 | W42: 26.82 | X42: 13363.71 | Y42: 12138.19 | Z42: 12138.19 | AA42: 12163.4 | AB42: 12152.91
A43: 1 | C43: 이익잉여금 | E43: 2888.91 | F43: 2888.91 | G43: 4962.07 | H43: 6319.77 | I43: 4307.29 | J43: 918.27 | K43: 918.27 | L43: -2082.98 | M43: -6023.74 | N43: -7257.34 | O43: -14204.51 | P43: -14204.51 | Q43: -18132.91 | R43: -20368.43 | S43: -27166.43 | T43: -44342.29 | U43: -44342.29 | V43: -49542.47 | W43: -43056.77 | X43: -45844.76 | Y43: -48642.9 | Z43: -48642.9 | AA43: -48110.3 | AB43: -47812.35
A44: 1 | C44: 자본총계 | E44: 79497.87 | F44: 79497.87 | G44: 81586.82 | H44: 83667.11 | I44: 81646.01 | J44: 78262.98 | K44: 78262.98 | L44: 75261.86 | M44: 71646.12 | N44: 70411.08 | O44: 63467.58 | P44: 63467.58 | Q44: 60546.86 | R44: 58320.2 | S44: 51529.41 | T44: 34352.21 | U44: 34352.21 | V44: 29150.9 | W44: 35664.44 | X44: 52709.77 | Y44: 52605.32 | Z44: 52605.32 | AA44: 53163.14 | AB44: 53450.6
A45: 1 | C45: 부채와자본총계 | E45: 183238.94 | F45: 183238.94 | G45: 175958.87 | H45: 170251.29 | I45: 176320.93 | J45: 179622.91 | K45: 179622.91 | L45: 169172.46 | M45: 168422.59 | N45: 184992.4 | O45: 182636.29 | P45: 182636.29 | Q45: 176135.4 | R45: 174462.12 | S45: 159572.05 | T45: 148230.95 | U45: 148230.95 | V45: 153138.84 | W45: 147804.86 | X45: 179883.6 | Y45: 168686.82 | Z45: 168686.82 | AA45: 172956.3 | AB45: 198415.43
A46: 1 | C46: 지배주주지분 | E46: 79497.87 | F46: 79497.87 | G46: 81586.82 | H46: 83667.11 | I46: 81646.01 | J46: 78262.98 | K46: 78262.98 | L46: 75261.86 | M46: 71646.12 | N46: 70411.08 | O46: 63467.58 | P46: 63467.58 | Q46: 60546.86 | R46: 58320.2 | S46: 51529.41 | T46: 34352.21 | U46: 34352.21 | V46: 29150.9 | W46: 35664.44 | X46: 52709.77 | Y46: 52605.32 | Z46: 52605.32 | AA46: 53163.14 | AB46: 53450.6
A47: 1 | C47: 총차입금 | E47: 74835.27 | F47: 74835.27 | G47: 80862.65 | H47: 59519.78 | I47: 74429.45 | J47: 73902.99 | K47: 73902.99 | L47: 75459.29 | M47: 76424.14 | N47: 84133.73 | O47: 89679.98 | P47: 89679.98 | Q47: 92527.6 | R47: 83828.05 | S47: 84317.32 | T47: 84332.52 | U47: 84332.52 | V47: 84860.05 | W47: 84369.66 | X47: 82745.71 | Y47: 82791.22 | Z47: 82791.22 | AA47: 78993.46 | AB47: 27249.9
A48: 1 | C48: 순차입금 | E48: 73533.97 | F48: 73533.97 | G48: 80456.11 | H48: 58587.41 | I48: 72525.86 | J48: 69105.13 | K48: 69105.13 | L48: 71317.91 | M48: 74838.67 | N48: 82442.33 | O48: 87458.9 | P48: 87458.9 | Q48: 89594.64 | R48: 77407.09 | S48: 81536.28 | T48: 80590.4 | U48: 80590.4 | V48: 81079.86 | W48: 80283.58 | X48: 71176.63 | Y48: 76405.97 | Z48: 76405.97 | AA48: 77287.95 | AB48: 13723.99
A49: 1 | C49: 이자발생자산 | E49: 1975.6 | F49: 1975.6 | G49: 535.8 | H49: 1041.63 | I49: 2001.81 | J49: 5020.91 | K49: 5020.91 | L49: 4364.59 | M49: 1815.4 | N49: 7699.23 | O49: 7336.83 | P49: 7336.83 | Q49: 8058.79 | R49: 12997.4 | S49: 9366.6 | T49: 9188.28 | U49: 9188.28 | V49: 5305.67 | W49: 5649.58 | X49: 13166.82 | Y49: 6658.52 | Z49: 6658.52 | AA49: 2011.1 | AB49: 13804.82
A50: 1 | C50: 당기법인세자산(선급법인세) | G50: 0.92 | H50: 0.05 | I50: 0.08 | J50: 0.2 | K50: 0.2 | L50: 0.27 | M50: 0.23 | N50: 0.38 | O50: 1.98 | P50: 1.98 | Q50: 2.82 | R50: 8.96 | S50: 9.82 | T50: 9.98 | U50: 9.98 | V50: 32.82 | W50: 23.76 | X50: 24.64 | Y50: 24.68 | Z50: 24.68 | AA50: 24.89 | AB50: 2.89
A51: 1 | C51: 기타유동금융자산 | H51: 766.03 | I51: 766.03 | J51: 397.82 | K51: 397.82 | L51: 414.62 | M51: 5.4 | N51: 1136.21
A52: 1 | C52: 장기충당부채 | J52: 50.67 | K52: 50.67 | L52: 50.67 | M52: 54.22 | O52: 55.38 | P52: 55.38 | Q52: 55.38 | R52: 28.4 | S52: 25.02 | T52: 160.37 | U52: 160.37 | V52: 160.37 | W52: 158.97 | X52: 149.9 | Y52: 170.7 | Z52: 170.7 | AA52: 170.7 | AB52: 177.63
A53: 1 | C53: 종속기업및관계기업투자 | M53: 1170 | N53: 14530 | O53: 14800 | P53: 14800 | Q53: 14800 | R53: 14800 | S53: 14800 | T53: 9676.9 | U53: 9676.9 | V53: 13791.34 | W53: 13791.34 | X53: 13791.34 | Y53: 11085.06 | Z53: 11085.06 | AA53: 11085.06 | AB53: 11085.06
A54: 1 | C54: 기타비유동자산 | N54: 109.6
A55: 1 | C55: 단기금융부채(face) | N55: 72672.68 | O55: 77926.33 | P55: 77926.33 | Q55: 81428.28 | R55: 74095.61 | S55: 74093.89 | T55: 73593.21 | U55: 73593.21 | V55: 73590.48 | W55: 72537.34 | X55: 81838.69 | Y55: 77499.64 | Z55: 77499.64 | AA55: 75201.91
A56: 1 | C56: 기타비유동금융부채 | N56: 13311.6
A57: 1 | C57: 단기투자자산(공정가치) | O57: 336.78 | P57: 336.78 | Q57: 336.78 | R57: 122.93 | S57: 121.95 | T57: 29.46 | U57: 29.46 | V57: 29.46
A58: 1 | C58: 이연법인세부채 | X58: 1843.47 | Y58: 1827.65 | Z58: 1827.65 | AA58: 1846.61 | AB58: 1820.26
A59: 1 | C59: 장기금융부채(face) | Y59: 4333.2 | Z59: 4333.2 | AA59: 3791.55 | AB59: 27249.9
A60: 1 | C60: 매출액(수익) | E60: 45212.84 | G60: 34513.15 | H60: 35573.35 | I60: 34052.6 | J60: 35465.13 | K60: 139604.23 | L60: 39070.45 | M60: 34077.9 | N60: 30365.11 | O60: 26214.09 | P60: 129727.55 | Q60: 26805.16 | R60: 24539.59 | S60: 30202.37 | T60: 32951.15 | U60: 114498.27 | V60: 35794.76 | W60: 46322.79 | X60: 46877.87 | Y60: 51567.04 | Z60: 180562.46 | AA60: 49824.19 | AB60: 48260.87
A61: 1 | C61: 매출원가 | E61: 34080.73 | G61: 30190.09 | H61: 32389.36 | I61: 33169.29 | J61: 36741.1 | K61: 132489.84 | L61: 39400.5 | M61: 33410.48 | N61: 29702.96 | O61: 29684.17 | P61: 132198.11 | Q61: 27794.14 | R61: 29186.35 | S61: 33498.67 | T61: 36676.35 | U61: 127155.51 | V61: 37953.71 | W61: 43873.25 | X61: 44968.68 | Y61: 47363.68 | Z61: 174159.32 | AA61: 45667.99 | AB61: 43709.79
A62: 1 | C62: 매출총이익 | E62: 11132.11 | G62: 4323.07 | H62: 3183.99 | I62: 883.3 | J62: -1275.97 | K62: 7114.39 | L62: -330.05 | M62: 667.42 | N62: 662.15 | O62: -3470.07 | P62: -2470.55 | Q62: -988.98 | R62: -4646.76 | S62: -3296.3 | T62: -3725.2 | U62: -12657.24 | V62: -2158.95 | W62: 2449.54 | X62: 1909.19 | Y62: 4203.36 | Z62: 6403.14 | AA62: 4156.2 | AB62: 4551.08
A63: 1 | C63: 판관비 | E63: 1069.64 | G63: 1524.01 | H63: 1469.68 | I63: 1515.82 | J63: 1885.79 | K63: 6395.3 | L63: 1846.67 | M63: 4066.45 | N63: 2424.86 | O63: 6504.41 | P63: 14842.39 | Q63: 1890.23 | R63: -4566.32 | S63: 2052.58 | T63: 2876.17 | U63: 2252.66 | V63: 2115.38 | W63: -17.16 | X63: 1264.44 | Y63: 2221.21 | Z63: 5583.87 | AA63: 2327.09 | AB63: 2913.98
A64: 1 | C64: 영업이익 | E64: 10062.47 | G64: 2799.06 | H64: 1714.31 | I64: -632.52 | J64: -3161.77 | K64: 719.08 | L64: -2176.72 | M64: -3399.03 | N64: -1762.71 | O64: -9974.48 | P64: -17312.94 | Q64: -2879.21 | R64: -80.44 | S64: -5348.88 | T64: -6601.38 | U64: -14909.91 | V64: -4274.33 | W64: 2466.7 | X64: 644.75 | Y64: 1982.16 | Z64: 819.28 | AA64: 1829.11 | AB64: 1637.1
A65: 1 | C65: 금융수익 | E65: 0.34 | G65: 0.18 | H65: 21.11 | I65: 0.2 | J65: 1326.1 | K65: 1347.59 | L65: 363.98 | M65: 538.22 | N65: 2295.08 | O65: 4175.4 | P65: 7372.68 | Q65: 687.14 | R65: 1385.98 | S65: 800.03 | T65: -919.27 | U65: 1953.88 | V65: 217.07 | W65: 7953.7 | X65: 7.48 | Y65: 365.98 | Z65: 8544.23 | AA65: 0.85 | AB65: 134.93
A66: 1 | C66: 금융비용 | E66: 1058.79 | G66: 1112.97 | H66: 962.58 | I66: 1060.56 | J66: 1882.67 | K66: 5018.78 | L66: 1447.53 | M66: 1797.78 | N66: 1817.46 | O66: 1788.12 | P66: 6850.89 | Q66: 1905.2 | R66: 2144.23 | S66: 2563.57 | T66: 4937.49 | U66: 11550.49 | V66: 1690.2 | W66: 1679.41 | X66: 3019.37 | Y66: 1812.61 | Z66: 8201.59 | AA66: 1347.91 | AB66: 1495.13
A67: 1 | C67: 기타영업외수익 | E67: 457.93 | G67: 105.43 | H67: 560.71 | I67: 343.72 | J67: -352.05 | K67: 657.81 | L67: 187.04 | M67: 129.04 | N67: 59.23 | O67: 153.06 | P67: 528.37 | Q67: 77.31 | R67: 90.39 | S67: 62.97 | T67: 100.39 | U67: 331.06 | V67: 433.71 | W67: 204.09 | X67: 4035.84 | Y67: 87.53 | Z67: 4761.17 | AA67: 88.89 | AB67: 53.8
A68: 1 | C68: 기타영업외비용 | E68: 32.03 | G68: 36.49 | H68: 26.02 | I68: 644.03 | J68: -166.92 | K68: 539.62 | L68: 33.99 | M68: 30.99 | N68: 109.57 | O68: -17.07 | P68: 157.48 | Q68: 60.99 | R68: 36.77 | S68: 26.02 | T68: 5159.52 | U68: 5283.3 | V68: 27.99 | W68: 31.55 | X68: 4160.64 | Y68: 2983.98 | Z68: 7204.16 | AA68: 26.49 | AB68: 26.49
A69: 1 | C69: 법인세비용차감전계속사업이익 | E69: 9429.91 | G69: 1755.21 | H69: 1307.53 | I69: -1993.19 | J69: -3903.47 | K69: -2833.92 | L69: -3107.22 | M69: -4560.53 | N69: -1335.42 | O69: -7417.06 | P69: -16420.23 | Q69: -4080.96 | R69: -785.07 | S69: -7075.47 | T69: -17517.27 | U69: -29458.77 | V69: -5341.73 | W69: 8913.52 | X69: -2491.93 | Y69: -2360.92 | Z69: -1281.06 | AA69: 544.45 | AB69: 304.2
A70: 1 | C70: 법인세비용 | E70: 631.81 | G70: -157.08 | H70: -50.17 | I70: 19.29 | J70: -46.99 | K70: -234.95 | L70: -105.97 | M70: -619.77 | N70: -101.82 | O70: -588.22 | P70: -1415.78 | Q70: -152.56 | R70: 1450.45 | S70: -277.47 | T70: -1211.77 | U70: -191.35 | V70: -141.55 | W70: 2427.82 | X70: 296.07 | Y70: 219.33 | Z70: 2801.67 | AA70: 11.85 | AB70: 6.25
A71: 1 | C71: 당기순이익 | E71: 8798.09 | G71: 1912.29 | H71: 1357.7 | I71: -2012.49 | J71: -3856.49 | K71: -2598.99 | L71: -3001.25 | M71: -3940.76 | N71: -1233.6 | O71: -6828.85 | P71: -15004.46 | Q71: -3928.4 | R71: -2235.52 | S71: -6798 | T71: -16305.51 | U71: -29267.43 | V71: -5200.18 | W71: 6485.7 | X71: -2787.99 | Y71: -2580.26 | Z71: -4082.73 | AA71: 532.6 | AB71: 297.95
... A76: 1 | C76: 계속사업이익 | E76: 8798.09 | G76: 1912.29 | H76: 1357.7 | I76: -2012.49 | J76: -3856.49 | K76: -2598.99 | L76: -3001.25 | M76: -3940.76 | N76: -1233.6 | O76: -6828.85 | P76: -15004.46 | Q76: -3928.4 | R76: -2235.52 | S76: -6798 | T76: -16305.51 | U76: -29267.43 | V76: -5200.18 | W76: 6485.7 | X76: -2787.99 | Y76: -2580.26 | Z76: -4082.73 | AA76: 532.6 | AB76: 297.95
A77: 1 | C77: 이자수익 | G77: 0.18 | H77: 0.15 | L77: 0.46 | M77: 891.73
A78: 1 | C78: 이자비용 | L78: 1325.63 | M78: 1443.13
A79: 1 | C79: 이자손익 | L79: -1325.17 | M79: -551.4
A80: 1 | C80: 영업활동으로인한현금흐름 | E80: 3778.79 | G80: -6951 | H80: 21821.16 | I80: -12731.4 | J80: 4207.52 | K80: 6346.28 | L80: -1822.97 | M80: -912.14 | N80: -2028.01 | O80: -170.81 | P80: -4933.93 | Q80: -2677.23 | R80: 13178.24 | S80: -2604.55 | T80: 2996.85 | U80: 10893.31 | V80: -240.26 | W80: 1984.33 | X80: 2964.72 | Y80: -5992.57 | Z80: -1283.78 | AA80: -1680.28 | AB80: 1255.16
A81: 1 | C81: 감가상각비 | E81: 1968.07 | G81: 1961.06 | H81: 1956.7 | I81: 1950.02 | J81: 1982.4 | K81: 7850.18 | L81: 1984.9 | M81: 1996.76
A82: 1 | C82: 배당금수취(CF) | E82: 0 | G82: 0 | H82: 20.96 | I82: 0 | J82: 0 | K82: 20.96 | L82: 10 | M82: 0 | N82: 1.6 | O82: 0 | P82: 11.6 | S82: 3.2 | T82: 0 | X82: 1.92 | Y82: 1.92
A83: 1 | C83: 법인세납부(CF) | E83: -0.06 | G83: -526.62 | H83: 0.91 | I83: 0 | J83: -0.2 | K83: -525.91 | N83: -0.16 | O83: -1.6 | Q83: -0.84 | R83: -6.14 | S83: -0.86 | T83: -0.16 | U83: -8 | V83: -22.84 | W83: 9.06 | X83: -0.88 | Y83: -0.04 | Z83: -14.7 | AA83: -0.21 | AB83: 22
A84: 1 | C84: 투자활동으로인한현금흐름 | E84: -3810.47 | G84: 343.97 | H84: -154.75 | I84: -1420.45 | J84: -456.04 | K84: -1687.27 | L84: -627.82 | M84: -1811.14 | N84: -17914.77 | O84: -1302.24 | P84: -21655.97 | Q84: -449.17 | R84: -453.35 | S84: -759.4 | T84: 771.89 | U84: -890.03 | V84: 330.43 | W84: -575.05 | X84: 5525.89 | Y84: -2592.89 | Z84: 2688.38 | AA84: 760.6 | AB84: -10867.5
A85: 1 | C85: 유형자산의감소 | E85: 11.3 | S85: 0 | T85: 0 | V85: 352 | W85: 145.25 | X85: 5961.91 | Y85: 32.18 | Z85: 6491.34
A86: 1 | C86: 유형자산의증가 | E86: 1164.48 | G86: 446.33 | H86: 110.65 | I86: 181.87 | J86: 790.44 | K86: 1529.29 | L86: 88.97 | M86: 830.69 | N86: 565.47 | O86: 209.97 | P86: 1695.1 | Q86: 669.61 | R86: 0.34 | S86: 938.81 | T86: 383.6 | U86: 1992.36 | V86: 151.62 | W86: 418.48 | X86: 736.01 | Y86: 1161.66 | Z86: 2467.77 | AA86: 324.93 | AB86: 4565.02
A87: 1 | C87: CAPEX | E87: 1164.48 | G87: 446.33 | H87: 110.65 | I87: 181.87 | J87: 790.44 | K87: 1529.29 | L87: 88.97 | M87: 830.69 | N87: 565.47 | O87: 209.97 | P87: 1695.1 | Q87: 669.61 | R87: 0.34 | S87: 938.81 | T87: 383.6 | U87: 1992.36 | V87: 151.62 | W87: 418.48 | X87: 736.01 | Y87: 1161.66 | Z87: 2467.77 | AA87: 324.93 | AB87: 4565.02
A88: 1 | C88: 재무활동으로인한현금흐름 | E88: 854.18 | G88: 5712.27 | H88: -21140.58 | I88: 14358.8 | J88: -398.8 | K88: -1468.31 | L88: 1298.12 | M88: -194.32 | N88: 19731.4 | O88: 1601.83 | P88: 22437.03 | Q88: 3228.15 | R88: -9227.62 | S88: -42.6 | T88: -560.04 | U88: -6602.11 | V88: -52.11 | W88: -1103.39 | X88: -1007.62 | Y88: 3209.4 | Z88: 1046.28 | AA88: -3843.72 | AB88: 20005.47
A89: 1 | C89: 단기차입금의증가 | E89: 30716.87 | G89: 28556.69 | H89: 3665.08 | I89: 32176.09 | J89: 23959.22 | K89: 88357.08 | L89: 14584.25 | M89: 5861.66 | N89: 730.75 | O89: 22862.54 | P89: 44039.2 | Q89: 18077.94 | R89: 501.6 | S89: 11318.52 | T89: 16225 | U89: 46123.06 | V89: 18726.62 | W89: 31177.49 | X89: 24013.54 | Y89: 36336.34 | Z89: 110253.99 | AA89: 30375.63 | AB89: 41727.78
A90: 1 | C90: 단기차입금의감소 | E90: 29238.75 | G90: 22232.14 | H90: 24193.82 | I90: 17195.49 | J90: 23730.67 | K90: 87352.12 | L90: 12982.9 | M90: 1028.93 | O90: 17421.09 | Q90: 14575.99 | R90: 7834.27 | S90: 11320.24 | T90: 16725.67 | U90: 50456.17 | V90: 18729.35 | W90: 32230.62 | X90: 14712.21 | Y90: 42842.19 | Z90: 108514.37 | AA90: 33215 | AB90: 51677.45
A91: 1 | C91: 장기차입금의감소 | E91: 589.44 | G91: 591.42 | H91: 594.08 | I91: 596.32 | J91: 598.82 | K91: 2380.64 | L91: 269.74 | M91: 274.56 | N91: 185.65 | O91: 187.8 | P91: 917.75
A92: 1 | C92: 현금및현금성자산의증감 | E92: 822.5 | G92: -894.76 | H92: 525.83 | I92: 206.94 | J92: 3352.69 | K92: 3190.7 | L92: -1152.67 | M92: -2917.59 | N92: -211.39 | O92: 128.77 | P92: -4152.88 | Q92: 101.75 | R92: 3497.27 | S92: -3406.55 | T92: 3208.71 | U92: 3401.18 | V92: 38.06 | W92: 305.89 | X92: 7482.99 | Y92: -5376.06 | Z92: 2450.88 | AA92: -4763.4 | AB92: 10393.12
A93: 1 | C93: 기말현금및현금성자산 | E93: 822.5 | G93: 406.48 | H93: 525.83 | I93: 206.94 | J93: 3352.69 | K93: 4491.94 | L93: 3339.27 | M93: -2917.59 | N93: -211.4 | O93: 128.78 | P93: 339.06 | Q93: 440.82 | R93: 3497.27 | S93: -3406.56 | T93: 3208.71 | U93: 3740.24 | V93: 3778.3 | W93: 305.89 | X93: 7482.99 | Y93: -5376.06 | Z93: 6191.12 | AA93: 1427.71 | AB93: 10393.13
A94: 1 | C94: 이자수취(CF) | O94: 8.66 | Q94: 4.56 | R94: 31.52 | S94: 5.59 | T94: 2.23 | U94: 43.9 | V94: 0.81 | W94: 1.13 | X94: 5.56 | Y94: 0.43 | Z94: 7.93 | AA94: 0.85 | AB94: 3.43

Sheet subQ
A1: YQ | C1: subQ 분기 서브모델(억원, U=100) | E1: 4Q21 | F1: 2021 | G1: 1Q22 | H1: 2Q22 | I1: 3Q22 | J1: 4Q22 | K1: 2022 | L1: 1Q23 | M1: 2Q23 | N1: 3Q23 | O1: 4Q23 | P1: 2023 | Q1: 1Q24 | R1: 2Q24 | S1: 3Q24 | T1: 4Q24 | U1: 2024 | V1: 1Q25 | W1: 2Q25 | X1: 3Q25 | Y1: 4Q25 | Z1: 2025 | AA1: 1Q26 | AB1: 2Q26 | AC1: 3Q26 | AD1: 4Q26 | AE1: 2026 | AF1: 1Q27 | AG1: 2Q27 | AH1: 3Q27 | AI1: 4Q27 | AJ1: 2027 | AK1: 1Q28 | AL1: 2Q28 | AM1: 3Q28 | AN1: 4Q28 | AO1: 2028
A2: A=이름(key) B=그룹 C=단위 D=FnGuide 계정명(VLOOKUP 키). 확정=VLOOKUP(BS), 추정=변수 가정 참조
E3: 1 | F3: 2 | G3: 3 | H3: 4 | I3: 5 | J3: 6 | K3: 7 | L3: 8 | M3: 9 | N3: 10 | O3: 11 | P3: 12 | Q3: 13 | R3: 14 | S3: 15 | T3: 16 | U3: 17 | V3: 18 | W3: 19 | X3: 20 | Y3: 21 | Z3: 22 | AA3: 23 | AB3: 24 | AC3: 25 | AD3: 26 | AE3: 27 | AF3: 28 | AG3: 29 | AH3: 30 | AI3: 31 | AJ3: 32 | AK3: 33 | AL3: 34 | AM3: 35 | AN3: 36 | AO3: 37
E4: 2021.12 | F4: 2021.12A | G4: 2022.03 | H4: 2022.06 | I4: 2022.09 | J4: 2022.12 | K4: 2022.12A | L4: 2023.03 | M4: 2023.06 | N4: 2023.09 | O4: 2023.12 | P4: 2023.12A | Q4: 2024.03 | R4: 2024.06 | S4: 2024.09 | T4: 2024.12 | U4: 2024.12A | V4: 2025.03 | W4: 2025.06 | X4: 2025.09 | Y4: 2025.12 | Z4: 2025.12A | AA4: 2026.03 | AB4: 2026.06 | AC4: 2026.09 | AD4: 2026.12 | AE4: 2026.12A | AF4: 2027.03 | AG4: 2027.06 | AH4: 2027.09 | AI4: 2027.12 | AJ4: 2027.12A | AK4: 2028.03 | AL4: 2028.06 | AM4: 2028.09 | AN4: 2028.12 | AO4: 2028.12A
A5: 매출액 | B5: 손익 | C5: 억원 | D5: 매출액(수익) | E5: =IFERROR(VLOOKUP($D5,BS별도,MATCH(E$1,BS별도H,0),0)/100,"") | G5: =IFERROR(VLOOKUP($D5,BS별도,MATCH(G$1,BS별도H,0),0)/100,"") | H5: =IFERROR(VLOOKUP($D5,BS별도,MATCH(H$1,BS별도H,0),0)/100,"") | I5: =IFERROR(VLOOKUP($D5,BS별도,MATCH(I$1,BS별도H,0),0)/100,"") | J5: =IFERROR(VLOOKUP($D5,BS별도,MATCH(J$1,BS별도H,0),0)/100,"") | K5: =SUM(G5:J5) | L5: =IFERROR(VLOOKUP($D5,BS별도,MATCH(L$1,BS별도H,0),0)/100,"") | M5: =IFERROR(VLOOKUP($D5,BS별도,MATCH(M$1,BS별도H,0),0)/100,"") | N5: =IFERROR(VLOOKUP($D5,BS연결,MATCH(N$1,BS연결H,0),0)/100,"") | O5: =IFERROR(VLOOKUP($D5,BS연결,MATCH(O$1,BS연결H,0),0)/100,"") | P5: =SUM(L5:O5) | Q5: =IFERROR(VLOOKUP($D5,BS연결,MATCH(Q$1,BS연결H,0),0)/100,"") | R5: =IFERROR(VLOOKUP($D5,BS연결,MATCH(R$1,BS연결H,0),0)/100,"") | S5: =IFERROR(VLOOKUP($D5,BS연결,MATCH(S$1,BS연결H,0),0)/100,"") | T5: =IFERROR(VLOOKUP($D5,BS연결,MATCH(T$1,BS연결H,0),0)/100,"") | U5: =IFERROR(VLOOKUP($D5,BS연결,MATCH(U$1,BS연결H,0),0)/100,"") | V5: =IFERROR(VLOOKUP($D5,BS연결,MATCH(V$1,BS연결H,0),0)/100,"") | W5: =IFERROR(VLOOKUP($D5,BS연결,MATCH(W$1,BS연결H,0),0)/100,"") | X5: =IFERROR(VLOOKUP($D5,BS연결,MATCH(X$1,BS연결H,0),0)/100,"") | ... AB5: =IFERROR(VLOOKUP($D5,BS연결,MATCH(AB$1,BS연결H,0),0)/100,"") | AC5: =IFERROR(X5*(1+변수!AC21),"") | AD5: =IFERROR(Y5*(1+변수!AD21),"") | AE5: =SUM(AA5:AD5) | AF5: =IFERROR(AA5*(1+변수!AF21),"") | AG5: =IFERROR(AB5*(1+변수!AG21),"") | AH5: =IFERROR(AC5*(1+변수!AH21),"") | AI5: =IFERROR(AD5*(1+변수!AI21),"") | AJ5: =SUM(AF5:AI5) | AK5: =IFERROR(AF5*(1+변수!AK21),"") | AL5: =IFERROR(AG5*(1+변수!AL21),"") | AM5: =IFERROR(AH5*(1+변수!AM21),"") | AN5: =IFERROR(AI5*(1+변수!AN21),"") | AO5: =SUM(AK5:AN5)
A6: 매출원가 | B6: 손익 | C6: 억원 | D6: 매출원가 | E6: =IFERROR(VLOOKUP($D6,BS별도,MATCH(E$1,BS별도H,0),0)/100,"") | G6: =IFERROR(VLOOKUP($D6,BS별도,MATCH(G$1,BS별도H,0),0)/100,"") | H6: =IFERROR(VLOOKUP($D6,BS별도,MATCH(H$1,BS별도H,0),0)/100,"") | I6: =IFERROR(VLOOKUP($D6,BS별도,MATCH(I$1,BS별도H,0),0)/100,"") | J6: =IFERROR(VLOOKUP($D6,BS별도,MATCH(J$1,BS별도H,0),0)/100,"") | K6: =SUM(G6:J6) | L6: =IFERROR(VLOOKUP($D6,BS별도,MATCH(L$1,BS별도H,0),0)/100,"") | M6: =IFERROR(VLOOKUP($D6,BS별도,MATCH(M$1,BS별도H,0),0)/100,"") | N6: =IFERROR(VLOOKUP($D6,BS연결,MATCH(N$1,BS연결H,0),0)/100,"") | O6: =IFERROR(VLOOKUP($D6,BS연결,MATCH(O$1,BS연결H,0),0)/100,"") | P6: =SUM(L6:O6) | Q6: =IFERROR(VLOOKUP($D6,BS연결,MATCH(Q$1,BS연결H,0),0)/100,"") | R6: =IFERROR(VLOOKUP($D6,BS연결,MATCH(R$1,BS연결H,0),0)/100,"") | S6: =IFERROR(VLOOKUP($D6,BS연결,MATCH(S$1,BS연결H,0),0)/100,"") | T6: =IFERROR(VLOOKUP($D6,BS연결,MATCH(T$1,BS연결H,0),0)/100,"") | U6: =IFERROR(VLOOKUP($D6,BS연결,MATCH(U$1,BS연결H,0),0)/100,"") | V6: =IFERROR(VLOOKUP($D6,BS연결,MATCH(V$1,BS연결H,0),0)/100,"") | W6: =IFERROR(VLOOKUP($D6,BS연결,MATCH(W$1,BS연결H,0),0)/100,"") | X6: =IFERROR(VLOOKUP($D6,BS연결,MATCH(X$1,BS연결H,0),0)/100,"") | ... AB6: =IFERROR(VLOOKUP($D6,BS연결,MATCH(AB$1,BS연결H,0),0)/100,"") | AC6: =IFERROR(AC5-AC7,"") | AD6: =IFERROR(AD5-AD7,"") | AE6: =SUM(AA6:AD6) | AF6: =IFERROR(AF5-AF7,"") | AG6: =IFERROR(AG5-AG7,"") | AH6: =IFERROR(AH5-AH7,"") | AI6: =IFERROR(AI5-AI7,"") | AJ6: =SUM(AF6:AI6) | AK6: =IFERROR(AK5-AK7,"") | AL6: =IFERROR(AL5-AL7,"") | AM6: =IFERROR(AM5-AM7,"") | AN6: =IFERROR(AN5-AN7,"") | AO6: =SUM(AK6:AN6)
A7: 매출총이익 | B7: 손익 | C7: 억원 | D7: 매출총이익 | E7: =IFERROR(VLOOKUP($D7,BS별도,MATCH(E$1,BS별도H,0),0)/100,"") | G7: =IFERROR(VLOOKUP($D7,BS별도,MATCH(G$1,BS별도H,0),0)/100,"") | H7: =IFERROR(VLOOKUP($D7,BS별도,MATCH(H$1,BS별도H,0),0)/100,"") | I7: =IFERROR(VLOOKUP($D7,BS별도,MATCH(I$1,BS별도H,0),0)/100,"") | J7: =IFERROR(VLOOKUP($D7,BS별도,MATCH(J$1,BS별도H,0),0)/100,"") | K7: =SUM(G7:J7) | L7: =IFERROR(VLOOKUP($D7,BS별도,MATCH(L$1,BS별도H,0),0)/100,"") | M7: =IFERROR(VLOOKUP($D7,BS별도,MATCH(M$1,BS별도H,0),0)/100,"") | N7: =IFERROR(VLOOKUP($D7,BS연결,MATCH(N$1,BS연결H,0),0)/100,"") | O7: =IFERROR(VLOOKUP($D7,BS연결,MATCH(O$1,BS연결H,0),0)/100,"") | P7: =SUM(L7:O7) | Q7: =IFERROR(VLOOKUP($D7,BS연결,MATCH(Q$1,BS연결H,0),0)/100,"") | R7: =IFERROR(VLOOKUP($D7,BS연결,MATCH(R$1,BS연결H,0),0)/100,"") | S7: =IFERROR(VLOOKUP($D7,BS연결,MATCH(S$1,BS연결H,0),0)/100,"") | T7: =IFERROR(VLOOKUP($D7,BS연결,MATCH(T$1,BS연결H,0),0)/100,"") | U7: =IFERROR(VLOOKUP($D7,BS연결,MATCH(U$1,BS연결H,0),0)/100,"") | V7: =IFERROR(VLOOKUP($D7,BS연결,MATCH(V$1,BS연결H,0),0)/100,"") | W7: =IFERROR(VLOOKUP($D7,BS연결,MATCH(W$1,BS연결H,0),0)/100,"") | X7: =IFERROR(VLOOKUP($D7,BS연결,MATCH(X$1,BS연결H,0),0)/100,"") | ... AB7: =IFERROR(VLOOKUP($D7,BS연결,MATCH(AB$1,BS연결H,0),0)/100,"") | AC7: =IFERROR(AC9+AC8,"") | AD7: =IFERROR(AD9+AD8,"") | AE7: =SUM(AA7:AD7) | AF7: =IFERROR(AF9+AF8,"") | AG7: =IFERROR(AG9+AG8,"") | AH7: =IFERROR(AH9+AH8,"") | AI7: =IFERROR(AI9+AI8,"") | AJ7: =SUM(AF7:AI7) | AK7: =IFERROR(AK9+AK8,"") | AL7: =IFERROR(AL9+AL8,"") | AM7: =IFERROR(AM9+AM8,"") | AN7: =IFERROR(AN9+AN8,"") | AO7: =SUM(AK7:AN7)
A8: 판관비 | B8: 손익 | C8: 억원 | D8: 판관비 | E8: =IFERROR(VLOOKUP($D8,BS별도,MATCH(E$1,BS별도H,0),0)/100,"") | G8: =IFERROR(VLOOKUP($D8,BS별도,MATCH(G$1,BS별도H,0),0)/100,"") | H8: =IFERROR(VLOOKUP($D8,BS별도,MATCH(H$1,BS별도H,0),0)/100,"") | I8: =IFERROR(VLOOKUP($D8,BS별도,MATCH(I$1,BS별도H,0),0)/100,"") | J8: =IFERROR(VLOOKUP($D8,BS별도,MATCH(J$1,BS별도H,0),0)/100,"") | K8: =SUM(G8:J8) | L8: =IFERROR(VLOOKUP($D8,BS별도,MATCH(L$1,BS별도H,0),0)/100,"") | M8: =IFERROR(VLOOKUP($D8,BS별도,MATCH(M$1,BS별도H,0),0)/100,"") | N8: =IFERROR(VLOOKUP($D8,BS연결,MATCH(N$1,BS연결H,0),0)/100,"") | O8: =IFERROR(VLOOKUP($D8,BS연결,MATCH(O$1,BS연결H,0),0)/100,"") | P8: =SUM(L8:O8) | Q8: =IFERROR(VLOOKUP($D8,BS연결,MATCH(Q$1,BS연결H,0),0)/100,"") | R8: =IFERROR(VLOOKUP($D8,BS연결,MATCH(R$1,BS연결H,0),0)/100,"") | S8: =IFERROR(VLOOKUP($D8,BS연결,MATCH(S$1,BS연결H,0),0)/100,"") | T8: =IFERROR(VLOOKUP($D8,BS연결,MATCH(T$1,BS연결H,0),0)/100,"") | U8: =IFERROR(VLOOKUP($D8,BS연결,MATCH(U$1,BS연결H,0),0)/100,"") | V8: =IFERROR(VLOOKUP($D8,BS연결,MATCH(V$1,BS연결H,0),0)/100,"") | W8: =IFERROR(VLOOKUP($D8,BS연결,MATCH(W$1,BS연결H,0),0)/100,"") | X8: =IFERROR(VLOOKUP($D8,BS연결,MATCH(X$1,BS연결H,0),0)/100,"") | ... AB8: =IFERROR(VLOOKUP($D8,BS연결,MATCH(AB$1,BS연결H,0),0)/100,"") | AC8: =IFERROR(AC5*변수!AC22,"") | AD8: =IFERROR(AD5*변수!AD22,"") | AE8: =SUM(AA8:AD8) | AF8: =IFERROR(AF5*변수!AF22,"") | AG8: =IFERROR(AG5*변수!AG22,"") | AH8: =IFERROR(AH5*변수!AH22,"") | AI8: =IFERROR(AI5*변수!AI22,"") | AJ8: =SUM(AF8:AI8) | AK8: =IFERROR(AK5*변수!AK22,"") | AL8: =IFERROR(AL5*변수!AL22,"") | AM8: =IFERROR(AM5*변수!AM22,"") | AN8: =IFERROR(AN5*변수!AN22,"") | AO8: =SUM(AK8:AN8)
A9: 영업이익 | B9: 손익 | C9: 억원 | D9: 영업이익 | E9: =IFERROR(VLOOKUP($D9,BS별도,MATCH(E$1,BS별도H,0),0)/100,"") | G9: =IFERROR(VLOOKUP($D9,BS별도,MATCH(G$1,BS별도H,0),0)/100,"") | H9: =IFERROR(VLOOKUP($D9,BS별도,MATCH(H$1,BS별도H,0),0)/100,"") | I9: =IFERROR(VLOOKUP($D9,BS별도,MATCH(I$1,BS별도H,0),0)/100,"") | J9: =IFERROR(VLOOKUP($D9,BS별도,MATCH(J$1,BS별도H,0),0)/100,"") | K9: =SUM(G9:J9) | L9: =IFERROR(VLOOKUP($D9,BS별도,MATCH(L$1,BS별도H,0),0)/100,"") | M9: =IFERROR(VLOOKUP($D9,BS별도,MATCH(M$1,BS별도H,0),0)/100,"") | N9: =IFERROR(VLOOKUP($D9,BS연결,MATCH(N$1,BS연결H,0),0)/100,"") | O9: =IFERROR(VLOOKUP($D9,BS연결,MATCH(O$1,BS연결H,0),0)/100,"") | P9: =SUM(L9:O9) | Q9: =IFERROR(VLOOKUP($D9,BS연결,MATCH(Q$1,BS연결H,0),0)/100,"") | R9: =IFERROR(VLOOKUP($D9,BS연결,MATCH(R$1,BS연결H,0),0)/100,"") | S9: =IFERROR(VLOOKUP($D9,BS연결,MATCH(S$1,BS연결H,0),0)/100,"") | T9: =IFERROR(VLOOKUP($D9,BS연결,MATCH(T$1,BS연결H,0),0)/100,"") | U9: =IFERROR(VLOOKUP($D9,BS연결,MATCH(U$1,BS연결H,0),0)/100,"") | V9: =IFERROR(VLOOKUP($D9,BS연결,MATCH(V$1,BS연결H,0),0)/100,"") | W9: =IFERROR(VLOOKUP($D9,BS연결,MATCH(W$1,BS연결H,0),0)/100,"") | X9: =IFERROR(VLOOKUP($D9,BS연결,MATCH(X$1,BS연결H,0),0)/100,"") | ... AB9: =IFERROR(VLOOKUP($D9,BS연결,MATCH(AB$1,BS연결H,0),0)/100,"") | AC9: =IFERROR(AC5*변수!AC23,"") | AD9: =IFERROR(AD5*변수!AD23,"") | AE9: =SUM(AA9:AD9) | AF9: =IFERROR(AF5*변수!AF23,"") | AG9: =IFERROR(AG5*변수!AG23,"") | AH9: =IFERROR(AH5*변수!AH23,"") | AI9: =IFERROR(AI5*변수!AI23,"") | AJ9: =SUM(AF9:AI9) | AK9: =IFERROR(AK5*변수!AK23,"") | AL9: =IFERROR(AL5*변수!AL23,"") | AM9: =IFERROR(AM5*변수!AM23,"") | AN9: =IFERROR(AN5*변수!AN23,"") | AO9: =SUM(AK9:AN9)
A10: OPM | B10: 손익 | C10: % | D10: 영업이익률 | E10: =IFERROR(E9/E5,"") | G10: =IFERROR(G9/G5,"") | H10: =IFERROR(H9/H5,"") | I10: =IFERROR(I9/I5,"") | J10: =IFERROR(J9/J5,"") | K10: =IFERROR(K9/K5,"") | L10: =IFERROR(L9/L5,"") | M10: =IFERROR(M9/M5,"") | N10: =IFERROR(N9/N5,"") | ... AO10: =IFERROR(AO9/AO5,"")
A11: 금융손익 | B11: 손익 | C11: 억원 | D11: 금융손익 | E11: =IFERROR(VLOOKUP($D11,BS별도,MATCH(E$1,BS별도H,0),0)/100,"") | G11: =IFERROR(VLOOKUP($D11,BS별도,MATCH(G$1,BS별도H,0),0)/100,"") | H11: =IFERROR(VLOOKUP($D11,BS별도,MATCH(H$1,BS별도H,0),0)/100,"") | I11: =IFERROR(VLOOKUP($D11,BS별도,MATCH(I$1,BS별도H,0),0)/100,"") | J11: =IFERROR(VLOOKUP($D11,BS별도,MATCH(J$1,BS별도H,0),0)/100,"") | K11: =SUM(G11:J11) | L11: =IFERROR(VLOOKUP($D11,BS별도,MATCH(L$1,BS별도H,0),0)/100,"") | M11: =IFERROR(VLOOKUP($D11,BS별도,MATCH(M$1,BS별도H,0),0)/100,"") | N11: =IFERROR(VLOOKUP($D11,BS연결,MATCH(N$1,BS연결H,0),0)/100,"") | O11: =IFERROR(VLOOKUP($D11,BS연결,MATCH(O$1,BS연결H,0),0)/100,"") | P11: =SUM(L11:O11) | Q11: =IFERROR(VLOOKUP($D11,BS연결,MATCH(Q$1,BS연결H,0),0)/100,"") | R11: =IFERROR(VLOOKUP($D11,BS연결,MATCH(R$1,BS연결H,0),0)/100,"") | S11: =IFERROR(VLOOKUP($D11,BS연결,MATCH(S$1,BS연결H,0),0)/100,"") | T11: =IFERROR(VLOOKUP($D11,BS연결,MATCH(T$1,BS연결H,0),0)/100,"") | U11: =IFERROR(VLOOKUP($D11,BS연결,MATCH(U$1,BS연결H,0),0)/100,"") | V11: =IFERROR(VLOOKUP($D11,BS연결,MATCH(V$1,BS연결H,0),0)/100,"") | W11: =IFERROR(VLOOKUP($D11,BS연결,MATCH(W$1,BS연결H,0),0)/100,"") | X11: =IFERROR(VLOOKUP($D11,BS연결,MATCH(X$1,BS연결H,0),0)/100,"") | ... AB11: =IFERROR(VLOOKUP($D11,BS연결,MATCH(AB$1,BS연결H,0),0)/100,"") | AC11: =IFERROR(AC12+AC13,"") | AD11: =IFERROR(AD12+AD13,"") | AE11: =SUM(AA11:AD11) | AF11: =IFERROR(AF12+AF13,"") | AG11: =IFERROR(AG12+AG13,"") | AH11: =IFERROR(AH12+AH13,"") | AI11: =IFERROR(AI12+AI13,"") | AJ11: =SUM(AF11:AI11) | AK11: =IFERROR(AK12+AK13,"") | AL11: =IFERROR(AL12+AL13,"") | AM11: =IFERROR(AM12+AM13,"") | AN11: =IFERROR(AN12+AN13,"") | AO11: =SUM(AK11:AN11)
A12: 이자손익 | B12: 손익 | C12: 억원 | D12: 이자손익 | K12: =SUM(G12:J12) | L12: =IFERROR(VLOOKUP($D12,BS별도,MATCH(L$1,BS별도H,0),0)/100,"") | M12: =IFERROR(VLOOKUP($D12,BS별도,MATCH(M$1,BS별도H,0),0)/100,"") | P12: =SUM(L12:O12) | U12: =SUM(Q12:T12) | Z12: =SUM(V12:Y12) | AC12: =IFERROR((AB27*변수!$D$52-AB25*변수!$D$53)/4,"") | AD12: =IFERROR((AC27*변수!$D$52-AC25*변수!$D$53)/4,"") | AE12: =SUM(AA12:AD12) | AF12: =IFERROR((AD27*변수!$D$52-AD25*변수!$D$53)/4,"") | AG12: =IFERROR((AF27*변수!$D$52-AF25*변수!$D$53)/4,"") | AH12: =IFERROR((AG27*변수!$D$52-AG25*변수!$D$53)/4,"") | AI12: =IFERROR((AH27*변수!$D$52-AH25*변수!$D$53)/4,"") | AJ12: =SUM(AF12:AI12) | AK12: =IFERROR((AI27*변수!$D$52-AI25*변수!$D$53)/4,"") | AL12: =IFERROR((AK27*변수!$D$52-AK25*변수!$D$53)/4,"") | AM12: =IFERROR((AL27*변수!$D$52-AL25*변수!$D$53)/4,"") | AN12: =IFERROR((AM27*변수!$D$52-AM25*변수!$D$53)/4,"") | AO12: =SUM(AK12:AN12)
A13: 파생상품손익 | B13: 손익 | C13: 억원 | D13: 파생상품손익 | K13: =SUM(G13:J13) | P13: =SUM(L13:O13) | U13: =SUM(Q13:T13) | Z13: =SUM(V13:Y13) | AB13: =IFERROR((VLOOKUP("파생상품이익",BS연결,MATCH(AB$1,BS연결H,0),0)-VLOOKUP("파생상품손실",BS연결,MATCH(AB$1,BS연결H,0),0))/100,"") | AC13: =변수!AC24 | AD13: =변수!AD24 | AE13: =SUM(AA13:AD13) | AF13: =변수!AF24 | AG13: =변수!AG24 | AH13: =변수!AH24 | AI13: =변수!AI24 | AJ13: =SUM(AF13:AI13) | AK13: =변수!AK24 | AL13: =변수!AL24 | AM13: =변수!AM24 | AN13: =변수!AN24 | AO13: =SUM(AK13:AN13)
A14: 기타영업외손익 | B14: 손익 | C14: 억원 | D14: 기타영업외손익 | E14: =IFERROR(VLOOKUP($D14,BS별도,MATCH(E$1,BS별도H,0),0)/100,"") | G14: =IFERROR(VLOOKUP($D14,BS별도,MATCH(G$1,BS별도H,0),0)/100,"") | H14: =IFERROR(VLOOKUP($D14,BS별도,MATCH(H$1,BS별도H,0),0)/100,"") | I14: =IFERROR(VLOOKUP($D14,BS별도,MATCH(I$1,BS별도H,0),0)/100,"") | J14: =IFERROR(VLOOKUP($D14,BS별도,MATCH(J$1,BS별도H,0),0)/100,"") | K14: =SUM(G14:J14) | L14: =IFERROR(VLOOKUP($D14,BS별도,MATCH(L$1,BS별도H,0),0)/100,"") | M14: =IFERROR(VLOOKUP($D14,BS별도,MATCH(M$1,BS별도H,0),0)/100,"") | N14: =IFERROR(VLOOKUP($D14,BS연결,MATCH(N$1,BS연결H,0),0)/100,"") | O14: =IFERROR(VLOOKUP($D14,BS연결,MATCH(O$1,BS연결H,0),0)/100,"") | P14: =SUM(L14:O14) | Q14: =IFERROR(VLOOKUP($D14,BS연결,MATCH(Q$1,BS연결H,0),0)/100,"") | R14: =IFERROR(VLOOKUP($D14,BS연결,MATCH(R$1,BS연결H,0),0)/100,"") | S14: =IFERROR(VLOOKUP($D14,BS연결,MATCH(S$1,BS연결H,0),0)/100,"") | T14: =IFERROR(VLOOKUP($D14,BS연결,MATCH(T$1,BS연결H,0),0)/100,"") | U14: =IFERROR(VLOOKUP($D14,BS연결,MATCH(U$1,BS연결H,0),0)/100,"") | V14: =IFERROR(VLOOKUP($D14,BS연결,MATCH(V$1,BS연결H,0),0)/100,"") | W14: =IFERROR(VLOOKUP($D14,BS연결,MATCH(W$1,BS연결H,0),0)/100,"") | X14: =IFERROR(VLOOKUP($D14,BS연결,MATCH(X$1,BS연결H,0),0)/100,"") | ... AB14: =IFERROR(VLOOKUP($D14,BS연결,MATCH(AB$1,BS연결H,0),0)/100,"") | AC14: =변수!AC25 | AD14: =변수!AD25 | AE14: =SUM(AA14:AD14) | AF14: =변수!AF25 | AG14: =변수!AG25 | AH14: =변수!AH25 | AI14: =변수!AI25 | AJ14: =SUM(AF14:AI14) | AK14: =변수!AK25 | AL14: =변수!AL25 | AM14: =변수!AM25 | AN14: =변수!AN25 | AO14: =SUM(AK14:AN14)
A15: 세전이익 | B15: 손익 | C15: 억원 | D15: 법인세비용차감전계속사업이익 | E15: =IFERROR(VLOOKUP($D15,BS별도,MATCH(E$1,BS별도H,0),0)/100,"") | G15: =IFERROR(VLOOKUP($D15,BS별도,MATCH(G$1,BS별도H,0),0)/100,"") | H15: =IFERROR(VLOOKUP($D15,BS별도,MATCH(H$1,BS별도H,0),0)/100,"") | I15: =IFERROR(VLOOKUP($D15,BS별도,MATCH(I$1,BS별도H,0),0)/100,"") | J15: =IFERROR(VLOOKUP($D15,BS별도,MATCH(J$1,BS별도H,0),0)/100,"") | K15: =SUM(G15:J15) | L15: =IFERROR(VLOOKUP($D15,BS별도,MATCH(L$1,BS별도H,0),0)/100,"") | M15: =IFERROR(VLOOKUP($D15,BS별도,MATCH(M$1,BS별도H,0),0)/100,"") | N15: =IFERROR(VLOOKUP($D15,BS연결,MATCH(N$1,BS연결H,0),0)/100,"") | O15: =IFERROR(VLOOKUP($D15,BS연결,MATCH(O$1,BS연결H,0),0)/100,"") | P15: =SUM(L15:O15) | Q15: =IFERROR(VLOOKUP($D15,BS연결,MATCH(Q$1,BS연결H,0),0)/100,"") | R15: =IFERROR(VLOOKUP($D15,BS연결,MATCH(R$1,BS연결H,0),0)/100,"") | S15: =IFERROR(VLOOKUP($D15,BS연결,MATCH(S$1,BS연결H,0),0)/100,"") | T15: =IFERROR(VLOOKUP($D15,BS연결,MATCH(T$1,BS연결H,0),0)/100,"") | U15: =SUM(Q15:T15) | V15: =IFERROR(VLOOKUP($D15,BS연결,MATCH(V$1,BS연결H,0),0)/100,"") | W15: =IFERROR(VLOOKUP($D15,BS연결,MATCH(W$1,BS연결H,0),0)/100,"") | X15: =IFERROR(VLOOKUP($D15,BS연결,MATCH(X$1,BS연결H,0),0)/100,"") | Y15: =IFERROR(VLOOKUP($D15,BS연결,MATCH(Y$1,BS연결H,0),0)/100,"") | Z15: =IFERROR(VLOOKUP($D15,BS연결,MATCH(Z$1,BS연결H,0),0)/100,"") | AA15: =IFERROR(VLOOKUP($D15,BS연결,MATCH(AA$1,BS연결H,0),0)/100,"") | AB15: =IFERROR(VLOOKUP($D15,BS연결,MATCH(AB$1,BS연결H,0),0)/100,"") | AC15: =IFERROR(AC9+AC11+AC14,"") | AD15: =IFERROR(AD9+AD11+AD14,"") | AE15: =SUM(AA15:AD15) | AF15: =IFERROR(AF9+AF11+AF14,"") | AG15: =IFERROR(AG9+AG11+AG14,"") | AH15: =IFERROR(AH9+AH11+AH14,"") | AI15: =IFERROR(AI9+AI11+AI14,"") | AJ15: =SUM(AF15:AI15) | AK15: =IFERROR(AK9+AK11+AK14,"") | AL15: =IFERROR(AL9+AL11+AL14,"") | AM15: =IFERROR(AM9+AM11+AM14,"") | AN15: =IFERROR(AN9+AN11+AN14,"") | AO15: =SUM(AK15:AN15)
A16: 법인세비용 | B16: 손익 | C16: 억원 | D16: 법인세비용 | E16: =IFERROR(VLOOKUP($D16,BS별도,MATCH(E$1,BS별도H,0),0)/100,"") | G16: =IFERROR(VLOOKUP($D16,BS별도,MATCH(G$1,BS별도H,0),0)/100,"") | H16: =IFERROR(VLOOKUP($D16,BS별도,MATCH(H$1,BS별도H,0),0)/100,"") | I16: =IFERROR(VLOOKUP($D16,BS별도,MATCH(I$1,BS별도H,0),0)/100,"") | J16: =IFERROR(VLOOKUP($D16,BS별도,MATCH(J$1,BS별도H,0),0)/100,"") | K16: =SUM(G16:J16) | L16: =IFERROR(VLOOKUP($D16,BS별도,MATCH(L$1,BS별도H,0),0)/100,"") | M16: =IFERROR(VLOOKUP($D16,BS별도,MATCH(M$1,BS별도H,0),0)/100,"") | N16: =IFERROR(VLOOKUP($D16,BS연결,MATCH(N$1,BS연결H,0),0)/100,"") | O16: =IFERROR(VLOOKUP($D16,BS연결,MATCH(O$1,BS연결H,0),0)/100,"") | P16: =SUM(L16:O16) | Q16: =IFERROR(VLOOKUP($D16,BS연결,MATCH(Q$1,BS연결H,0),0)/100,"") | R16: =IFERROR(VLOOKUP($D16,BS연결,MATCH(R$1,BS연결H,0),0)/100,"") | S16: =IFERROR(VLOOKUP($D16,BS연결,MATCH(S$1,BS연결H,0),0)/100,"") | T16: =IFERROR(VLOOKUP($D16,BS연결,MATCH(T$1,BS연결H,0),0)/100,"") | U16: =IFERROR(VLOOKUP($D16,BS연결,MATCH(U$1,BS연결H,0),0)/100,"") | V16: =IFERROR(VLOOKUP($D16,BS연결,MATCH(V$1,BS연결H,0),0)/100,"") | W16: =IFERROR(VLOOKUP($D16,BS연결,MATCH(W$1,BS연결H,0),0)/100,"") | X16: =IFERROR(VLOOKUP($D16,BS연결,MATCH(X$1,BS연결H,0),0)/100,"") | ... AB16: =IFERROR(VLOOKUP($D16,BS연결,MATCH(AB$1,BS연결H,0),0)/100,"") | AC16: =IFERROR(MAX(AC15,0)*변수!AC26,"") | AD16: =IFERROR(MAX(AD15,0)*변수!AD26,"") | AE16: =SUM(AA16:AD16) | AF16: =IFERROR(MAX(AF15,0)*변수!AF26,"") | AG16: =IFERROR(MAX(AG15,0)*변수!AG26,"") | AH16: =IFERROR(MAX(AH15,0)*변수!AH26,"") | AI16: =IFERROR(MAX(AI15,0)*변수!AI26,"") | AJ16: =SUM(AF16:AI16) | AK16: =IFERROR(MAX(AK15,0)*변수!AK26,"") | AL16: =IFERROR(MAX(AL15,0)*변수!AL26,"") | AM16: =IFERROR(MAX(AM15,0)*변수!AM26,"") | AN16: =IFERROR(MAX(AN15,0)*변수!AN26,"") | AO16: =SUM(AK16:AN16)
A17: 당기순이익 | B17: 손익 | C17: 억원 | D17: 당기순이익 | E17: =IFERROR(VLOOKUP($D17,BS별도,MATCH(E$1,BS별도H,0),0)/100,"") | G17: =IFERROR(VLOOKUP($D17,BS별도,MATCH(G$1,BS별도H,0),0)/100,"") | H17: =IFERROR(VLOOKUP($D17,BS별도,MATCH(H$1,BS별도H,0),0)/100,"") | I17: =IFERROR(VLOOKUP($D17,BS별도,MATCH(I$1,BS별도H,0),0)/100,"") | J17: =IFERROR(VLOOKUP($D17,BS별도,MATCH(J$1,BS별도H,0),0)/100,"") | K17: =SUM(G17:J17) | L17: =IFERROR(VLOOKUP($D17,BS별도,MATCH(L$1,BS별도H,0),0)/100,"") | M17: =IFERROR(VLOOKUP($D17,BS별도,MATCH(M$1,BS별도H,0),0)/100,"") | N17: =IFERROR(VLOOKUP($D17,BS연결,MATCH(N$1,BS연결H,0),0)/100,"") | O17: =IFERROR(VLOOKUP($D17,BS연결,MATCH(O$1,BS연결H,0),0)/100,"") | P17: =SUM(L17:O17) | Q17: =IFERROR(VLOOKUP($D17,BS연결,MATCH(Q$1,BS연결H,0),0)/100,"") | R17: =IFERROR(VLOOKUP($D17,BS연결,MATCH(R$1,BS연결H,0),0)/100,"") | S17: =IFERROR(VLOOKUP($D17,BS연결,MATCH(S$1,BS연결H,0),0)/100,"") | T17: =IFERROR(VLOOKUP($D17,BS연결,MATCH(T$1,BS연결H,0),0)/100,"") | U17: =IFERROR(VLOOKUP($D17,BS연결,MATCH(U$1,BS연결H,0),0)/100,"") | V17: =IFERROR(VLOOKUP($D17,BS연결,MATCH(V$1,BS연결H,0),0)/100,"") | W17: =IFERROR(VLOOKUP($D17,BS연결,MATCH(W$1,BS연결H,0),0)/100,"") | X17: =IFERROR(VLOOKUP($D17,BS연결,MATCH(X$1,BS연결H,0),0)/100,"") | ... AB17: =IFERROR(VLOOKUP($D17,BS연결,MATCH(AB$1,BS연결H,0),0)/100,"") | AC17: =IFERROR(AC15-AC16,"") | AD17: =IFERROR(AD15-AD16,"") | AE17: =SUM(AA17:AD17) | AF17: =IFERROR(AF15-AF16,"") | AG17: =IFERROR(AG15-AG16,"") | AH17: =IFERROR(AH15-AH16,"") | AI17: =IFERROR(AI15-AI16,"") | AJ17: =SUM(AF17:AI17) | AK17: =IFERROR(AK15-AK16,"") | AL17: =IFERROR(AL15-AL16,"") | AM17: =IFERROR(AM15-AM16,"") | AN17: =IFERROR(AN15-AN16,"") | AO17: =SUM(AK17:AN17)
A18: 지배주주순이익 | B18: 손익 | C18: 억원 | D18: (지배주주지분)당기순이익 | E18: =IFERROR(VLOOKUP($D18,BS별도,MATCH(E$1,BS별도H,0),0)/100,"") | G18: =IFERROR(VLOOKUP($D18,BS별도,MATCH(G$1,BS별도H,0),0)/100,"") | H18: =IFERROR(VLOOKUP($D18,BS별도,MATCH(H$1,BS별도H,0),0)/100,"") | I18: =IFERROR(VLOOKUP($D18,BS별도,MATCH(I$1,BS별도H,0),0)/100,"") | J18: =IFERROR(VLOOKUP($D18,BS별도,MATCH(J$1,BS별도H,0),0)/100,"") | K18: =SUM(G18:J18) | L18: =IFERROR(VLOOKUP($D18,BS별도,MATCH(L$1,BS별도H,0),0)/100,"") | M18: =IFERROR(VLOOKUP($D18,BS별도,MATCH(M$1,BS별도H,0),0)/100,"") | N18: =IFERROR(VLOOKUP($D18,BS연결,MATCH(N$1,BS연결H,0),0)/100,"") | O18: =IFERROR(VLOOKUP($D18,BS연결,MATCH(O$1,BS연결H,0),0)/100,"") | P18: =SUM(L18:O18) | Q18: =IFERROR(VLOOKUP($D18,BS연결,MATCH(Q$1,BS연결H,0),0)/100,"") | R18: =IFERROR(VLOOKUP($D18,BS연결,MATCH(R$1,BS연결H,0),0)/100,"") | S18: =IFERROR(VLOOKUP($D18,BS연결,MATCH(S$1,BS연결H,0),0)/100,"") | T18: =IFERROR(VLOOKUP($D18,BS연결,MATCH(T$1,BS연결H,0),0)/100,"") | U18: =IFERROR(VLOOKUP($D18,BS연결,MATCH(U$1,BS연결H,0),0)/100,"") | V18: =IFERROR(VLOOKUP($D18,BS연결,MATCH(V$1,BS연결H,0),0)/100,"") | W18: =IFERROR(VLOOKUP($D18,BS연결,MATCH(W$1,BS연결H,0),0)/100,"") | X18: =IFERROR(VLOOKUP($D18,BS연결,MATCH(X$1,BS연결H,0),0)/100,"") | Y18: =IFERROR(VLOOKUP($D18,BS연결,MATCH(Y$1,BS연결H,0),0)/100,"") | Z18: =SUM(V18:Y18) | AA18: =IFERROR(VLOOKUP($D18,BS연결,MATCH(AA$1,BS연결H,0),0)/100,"") | AB18: =IFERROR(VLOOKUP($D18,BS연결,MATCH(AB$1,BS연결H,0),0)/100,"") | AC18: =IFERROR(AC17*변수!AC27,"") | AD18: =IFERROR(AD17*변수!AD27,"") | AE18: =SUM(AA18:AD18) | AF18: =IFERROR(AF17*변수!AF27,"") | AG18: =IFERROR(AG17*변수!AG27,"") | AH18: =IFERROR(AH17*변수!AH27,"") | AI18: =IFERROR(AI17*변수!AI27,"") | AJ18: =SUM(AF18:AI18) | AK18: =IFERROR(AK17*변수!AK27,"") | AL18: =IFERROR(AL17*변수!AL27,"") | AM18: =IFERROR(AM17*변수!AM27,"") | AN18: =IFERROR(AN17*변수!AN27,"") | AO18: =SUM(AK18:AN18)
A19: 감가상각비 | B19: 손익 | C19: 억원 | D19: 감가상각비 | E19: =IFERROR(VLOOKUP($D19,BS별도,MATCH(E$1,BS별도H,0),0)/100,"") | G19: =IFERROR(VLOOKUP($D19,BS별도,MATCH(G$1,BS별도H,0),0)/100,"") | H19: =IFERROR(VLOOKUP($D19,BS별도,MATCH(H$1,BS별도H,0),0)/100,"") | I19: =IFERROR(VLOOKUP($D19,BS별도,MATCH(I$1,BS별도H,0),0)/100,"") | J19: =IFERROR(VLOOKUP($D19,BS별도,MATCH(J$1,BS별도H,0),0)/100,"") | K19: =SUM(G19:J19) | L19: =IFERROR(VLOOKUP($D19,BS별도,MATCH(L$1,BS별도H,0),0)/100,"") | M19: =IFERROR(VLOOKUP($D19,BS별도,MATCH(M$1,BS별도H,0),0)/100,"") | P19: =SUM(L19:O19) | U19: =SUM(Q19:T19) | Z19: =SUM(V19:Y19) | AC19: =변수!AC28 | AD19: =변수!AD28 | AE19: =SUM(AA19:AD19) | AF19: =변수!AF28 | AG19: =변수!AG28 | AH19: =변수!AH28 | AI19: =변수!AI28 | AJ19: =SUM(AF19:AI19) | AK19: =변수!AK28 | AL19: =변수!AL28 | AM19: =변수!AM28 | AN19: =변수!AN28 | AO19: =SUM(AK19:AN19)
A20: EBITDA | B20: 손익 | C20: 억원 | D20: EBITDA | E20: 120.31 | G20: 47.6 | H20: 36.71 | I20: 13.18 | J20: -11.79 | K20: =SUM(G20:J20) | L20: -1.92 | M20: -14.02 | P20: =SUM(L20:O20) | U20: =SUM(Q20:T20) | Z20: =SUM(V20:Y20) | AC20: =IFERROR(AC9+AC19,"") | AD20: =IFERROR(AD9+AD19,"") | AE20: =SUM(AA20:AD20) | AF20: =IFERROR(AF9+AF19,"") | AG20: =IFERROR(AG9+AG19,"") | AH20: =IFERROR(AH9+AH19,"") | AI20: =IFERROR(AI9+AI19,"") | AJ20: =SUM(AF20:AI20) | AK20: =IFERROR(AK9+AK19,"") | AL20: =IFERROR(AL9+AL19,"") | AM20: =IFERROR(AM9+AM19,"") | AN20: =IFERROR(AN9+AN19,"") | AO20: =SUM(AK20:AN20)
A21: 자산총계 | B21: 재무상태 | C21: 억원 | D21: 자산총계 | E21: =IFERROR(VLOOKUP($D21,BS별도,MATCH(E$1,BS별도H,0),0)/100,"") | F21: 1832.39 | G21: =IFERROR(VLOOKUP($D21,BS별도,MATCH(G$1,BS별도H,0),0)/100,"") | H21: =IFERROR(VLOOKUP($D21,BS별도,MATCH(H$1,BS별도H,0),0)/100,"") | I21: =IFERROR(VLOOKUP($D21,BS별도,MATCH(I$1,BS별도H,0),0)/100,"") | J21: =IFERROR(VLOOKUP($D21,BS별도,MATCH(J$1,BS별도H,0),0)/100,"") | K21: =J21 | L21: =IFERROR(VLOOKUP($D21,BS별도,MATCH(L$1,BS별도H,0),0)/100,"") | M21: =IFERROR(VLOOKUP($D21,BS별도,MATCH(M$1,BS별도H,0),0)/100,"") | N21: =IFERROR(VLOOKUP($D21,BS연결,MATCH(N$1,BS연결H,0),0)/100,"") | O21: =IFERROR(VLOOKUP($D21,BS연결,MATCH(O$1,BS연결H,0),0)/100,"") | P21: =IFERROR(VLOOKUP($D21,BS연결,MATCH(P$1,BS연결H,0),0)/100,"") | Q21: =IFERROR(VLOOKUP($D21,BS연결,MATCH(Q$1,BS연결H,0),0)/100,"") | R21: =IFERROR(VLOOKUP($D21,BS연결,MATCH(R$1,BS연결H,0),0)/100,"") | S21: =IFERROR(VLOOKUP($D21,BS연결,MATCH(S$1,BS연결H,0),0)/100,"") | T21: =IFERROR(VLOOKUP($D21,BS연결,MATCH(T$1,BS연결H,0),0)/100,"") | U21: =IFERROR(VLOOKUP($D21,BS연결,MATCH(U$1,BS연결H,0),0)/100,"") | ... AB21: =IFERROR(VLOOKUP($D21,BS연결,MATCH(AB$1,BS연결H,0),0)/100,"") | AC21: =IFERROR(AC22+AC23,"") | AD21: =IFERROR(AD22+AD23,"") | AE21: =AD21 | AF21: =IFERROR(AF22+AF23,"") | AG21: =IFERROR(AG22+AG23,"") | AH21: =IFERROR(AH22+AH23,"") | AI21: =IFERROR(AI22+AI23,"") | AJ21: =AI21 | AK21: =IFERROR(AK22+AK23,"") | AL21: =IFERROR(AL22+AL23,"") | AM21: =IFERROR(AM22+AM23,"") | AN21: =IFERROR(AN22+AN23,"") | AO21: =AN21
A22: 부채총계 | B22: 재무상태 | C22: 억원 | D22: 부채총계 | E22: =IFERROR(VLOOKUP($D22,BS별도,MATCH(E$1,BS별도H,0),0)/100,"") | F22: 1037.41 | G22: =IFERROR(VLOOKUP($D22,BS별도,MATCH(G$1,BS별도H,0),0)/100,"") | H22: =IFERROR(VLOOKUP($D22,BS별도,MATCH(H$1,BS별도H,0),0)/100,"") | I22: =IFERROR(VLOOKUP($D22,BS별도,MATCH(I$1,BS별도H,0),0)/100,"") | J22: =IFERROR(VLOOKUP($D22,BS별도,MATCH(J$1,BS별도H,0),0)/100,"") | K22: =J22 | L22: =IFERROR(VLOOKUP($D22,BS별도,MATCH(L$1,BS별도H,0),0)/100,"") | M22: =IFERROR(VLOOKUP($D22,BS별도,MATCH(M$1,BS별도H,0),0)/100,"") | N22: =IFERROR(VLOOKUP($D22,BS연결,MATCH(N$1,BS연결H,0),0)/100,"") | O22: =IFERROR(VLOOKUP($D22,BS연결,MATCH(O$1,BS연결H,0),0)/100,"") | P22: =IFERROR(VLOOKUP($D22,BS연결,MATCH(P$1,BS연결H,0),0)/100,"") | Q22: =IFERROR(VLOOKUP($D22,BS연결,MATCH(Q$1,BS연결H,0),0)/100,"") | R22: =IFERROR(VLOOKUP($D22,BS연결,MATCH(R$1,BS연결H,0),0)/100,"") | S22: =IFERROR(VLOOKUP($D22,BS연결,MATCH(S$1,BS연결H,0),0)/100,"") | T22: =IFERROR(VLOOKUP($D22,BS연결,MATCH(T$1,BS연결H,0),0)/100,"") | U22: =IFERROR(VLOOKUP($D22,BS연결,MATCH(U$1,BS연결H,0),0)/100,"") | ... AB22: =IFERROR(VLOOKUP($D22,BS연결,MATCH(AB$1,BS연결H,0),0)/100,"") | AC22: =IFERROR(AB22*(1+변수!AC29),"") | AD22: =IFERROR(AC22*(1+변수!AD29),"") | AE22: =AD22 | AF22: =IFERROR(AD22*(1+변수!AF29),"") | AG22: =IFERROR(AF22*(1+변수!AG29),"") | AH22: =IFERROR(AG22*(1+변수!AH29),"") | AI22: =IFERROR(AH22*(1+변수!AI29),"") | AJ22: =AI22 | AK22: =IFERROR(AI22*(1+변수!AK29),"") | AL22: =IFERROR(AK22*(1+변수!AL29),"") | AM22: =IFERROR(AL22*(1+변수!AM29),"") | AN22: =IFERROR(AM22*(1+변수!AN29),"") | AO22: =AN22
A23: 자본총계 | B23: 재무상태 | C23: 억원 | D23: 자본총계 | E23: =IFERROR(VLOOKUP($D23,BS별도,MATCH(E$1,BS별도H,0),0)/100,"") | F23: 794.98 | G23: =IFERROR(VLOOKUP($D23,BS별도,MATCH(G$1,BS별도H,0),0)/100,"") | H23: =IFERROR(VLOOKUP($D23,BS별도,MATCH(H$1,BS별도H,0),0)/100,"") | I23: =IFERROR(VLOOKUP($D23,BS별도,MATCH(I$1,BS별도H,0),0)/100,"") | J23: =IFERROR(VLOOKUP($D23,BS별도,MATCH(J$1,BS별도H,0),0)/100,"") | K23: =J23 | L23: =IFERROR(VLOOKUP($D23,BS별도,MATCH(L$1,BS별도H,0),0)/100,"") | M23: =IFERROR(VLOOKUP($D23,BS별도,MATCH(M$1,BS별도H,0),0)/100,"") | N23: =IFERROR(VLOOKUP($D23,BS연결,MATCH(N$1,BS연결H,0),0)/100,"") | O23: =IFERROR(VLOOKUP($D23,BS연결,MATCH(O$1,BS연결H,0),0)/100,"") | P23: =IFERROR(VLOOKUP($D23,BS연결,MATCH(P$1,BS연결H,0),0)/100,"") | Q23: =IFERROR(VLOOKUP($D23,BS연결,MATCH(Q$1,BS연결H,0),0)/100,"") | R23: =IFERROR(VLOOKUP($D23,BS연결,MATCH(R$1,BS연결H,0),0)/100,"") | S23: =IFERROR(VLOOKUP($D23,BS연결,MATCH(S$1,BS연결H,0),0)/100,"") | T23: =IFERROR(VLOOKUP($D23,BS연결,MATCH(T$1,BS연결H,0),0)/100,"") | U23: =IFERROR(VLOOKUP($D23,BS연결,MATCH(U$1,BS연결H,0),0)/100,"") | ... AB23: =IFERROR(VLOOKUP($D23,BS연결,MATCH(AB$1,BS연결H,0),0)/100,"") | AC23: =IFERROR(AB23+AC17-변수!AC30,"") | AD23: =IFERROR(AC23+AD17-변수!AD30,"") | AE23: =AD23 | AF23: =IFERROR(AD23+AF17-변수!AF30,"") | AG23: =IFERROR(AF23+AG17-변수!AG30,"") | AH23: =IFERROR(AG23+AH17-변수!AH30,"") | AI23: =IFERROR(AH23+AI17-변수!AI30,"") | AJ23: =AI23 | AK23: =IFERROR(AI23+AK17-변수!AK30,"") | AL23: =IFERROR(AK23+AL17-변수!AL30,"") | AM23: =IFERROR(AL23+AM17-변수!AM30,"") | AN23: =IFERROR(AM23+AN17-변수!AN30,"") | AO23: =AN23
A24: 지배주주지분 | B24: 재무상태 | C24: 억원 | D24: 지배주주지분 | E24: =IFERROR(VLOOKUP($D24,BS별도,MATCH(E$1,BS별도H,0),0)/100,"") | F24: 794.98 | G24: =IFERROR(VLOOKUP($D24,BS별도,MATCH(G$1,BS별도H,0),0)/100,"") | H24: =IFERROR(VLOOKUP($D24,BS별도,MATCH(H$1,BS별도H,0),0)/100,"") | I24: =IFERROR(VLOOKUP($D24,BS별도,MATCH(I$1,BS별도H,0),0)/100,"") | J24: =IFERROR(VLOOKUP($D24,BS별도,MATCH(J$1,BS별도H,0),0)/100,"") | K24: =J24 | L24: =IFERROR(VLOOKUP($D24,BS별도,MATCH(L$1,BS별도H,0),0)/100,"") | M24: =IFERROR(VLOOKUP($D24,BS별도,MATCH(M$1,BS별도H,0),0)/100,"") | N24: =IFERROR(VLOOKUP($D24,BS연결,MATCH(N$1,BS연결H,0),0)/100,"") | O24: =IFERROR(VLOOKUP($D24,BS연결,MATCH(O$1,BS연결H,0),0)/100,"") | P24: =IFERROR(VLOOKUP($D24,BS연결,MATCH(P$1,BS연결H,0),0)/100,"") | Q24: =IFERROR(VLOOKUP($D24,BS연결,MATCH(Q$1,BS연결H,0),0)/100,"") | R24: =IFERROR(VLOOKUP($D24,BS연결,MATCH(R$1,BS연결H,0),0)/100,"") | S24: =IFERROR(VLOOKUP($D24,BS연결,MATCH(S$1,BS연결H,0),0)/100,"") | T24: =IFERROR(VLOOKUP($D24,BS연결,MATCH(T$1,BS연결H,0),0)/100,"") | U24: =IFERROR(VLOOKUP($D24,BS연결,MATCH(U$1,BS연결H,0),0)/100,"") | ... AB24: =IFERROR(VLOOKUP($D24,BS연결,MATCH(AB$1,BS연결H,0),0)/100,"") | AC24: =IFERROR(AB24+AC18-변수!AC31,"") | AD24: =IFERROR(AC24+AD18-변수!AD31,"") | AE24: =AD24 | AF24: =IFERROR(AD24+AF18-변수!AF31,"") | AG24: =IFERROR(AF24+AG18-변수!AG31,"") | AH24: =IFERROR(AG24+AH18-변수!AH31,"") | AI24: =IFERROR(AH24+AI18-변수!AI31,"") | AJ24: =AI24 | AK24: =IFERROR(AI24+AK18-변수!AK31,"") | AL24: =IFERROR(AK24+AL18-변수!AL31,"") | AM24: =IFERROR(AL24+AM18-변수!AM31,"") | AN24: =IFERROR(AM24+AN18-변수!AN31,"") | AO24: =AN24
A25: 총차입금 | B25: 재무상태 | C25: 억원 | D25: 총차입금 | E25: =IFERROR(VLOOKUP($D25,BS별도,MATCH(E$1,BS별도H,0),0)/100,"") | F25: 748.35 | G25: =IFERROR(VLOOKUP($D25,BS별도,MATCH(G$1,BS별도H,0),0)/100,"") | H25: =IFERROR(VLOOKUP($D25,BS별도,MATCH(H$1,BS별도H,0),0)/100,"") | I25: =IFERROR(VLOOKUP($D25,BS별도,MATCH(I$1,BS별도H,0),0)/100,"") | J25: =IFERROR(VLOOKUP($D25,BS별도,MATCH(J$1,BS별도H,0),0)/100,"") | K25: =J25 | L25: =IFERROR(VLOOKUP($D25,BS별도,MATCH(L$1,BS별도H,0),0)/100,"") | M25: =IFERROR(VLOOKUP($D25,BS별도,MATCH(M$1,BS별도H,0),0)/100,"") | N25: =IFERROR(VLOOKUP($D25,BS연결,MATCH(N$1,BS연결H,0),0)/100,"") | O25: =IFERROR(VLOOKUP($D25,BS연결,MATCH(O$1,BS연결H,0),0)/100,"") | P25: =IFERROR(VLOOKUP($D25,BS연결,MATCH(P$1,BS연결H,0),0)/100,"") | Q25: =IFERROR(VLOOKUP($D25,BS연결,MATCH(Q$1,BS연결H,0),0)/100,"") | R25: =IFERROR(VLOOKUP($D25,BS연결,MATCH(R$1,BS연결H,0),0)/100,"") | S25: =IFERROR(VLOOKUP($D25,BS연결,MATCH(S$1,BS연결H,0),0)/100,"") | T25: =IFERROR(VLOOKUP($D25,BS연결,MATCH(T$1,BS연결H,0),0)/100,"") | U25: =IFERROR(VLOOKUP($D25,BS연결,MATCH(U$1,BS연결H,0),0)/100,"") | ... AB25: =IFERROR(VLOOKUP($D25,BS연결,MATCH(AB$1,BS연결H,0),0)/100,"") | AC25: =IFERROR(AB25*(1+변수!AC32),"") | AD25: =IFERROR(AC25*(1+변수!AD32),"") | AE25: =AD25 | AF25: =IFERROR(AD25*(1+변수!AF32),"") | AG25: =IFERROR(AF25*(1+변수!AG32),"") | AH25: =IFERROR(AG25*(1+변수!AH32),"") | AI25: =IFERROR(AH25*(1+변수!AI32),"") | AJ25: =AI25 | AK25: =IFERROR(AI25*(1+변수!AK32),"") | AL25: =IFERROR(AK25*(1+변수!AL32),"") | AM25: =IFERROR(AL25*(1+변수!AM32),"") | AN25: =IFERROR(AM25*(1+변수!AN32),"") | AO25: =AN25
A26: 순차입금 | B26: 재무상태 | C26: 억원 | D26: 순차입금 | E26: =IFERROR(VLOOKUP($D26,BS별도,MATCH(E$1,BS별도H,0),0)/100,"") | F26: 735.34 | G26: =IFERROR(VLOOKUP($D26,BS별도,MATCH(G$1,BS별도H,0),0)/100,"") | H26: =IFERROR(VLOOKUP($D26,BS별도,MATCH(H$1,BS별도H,0),0)/100,"") | I26: =IFERROR(VLOOKUP($D26,BS별도,MATCH(I$1,BS별도H,0),0)/100,"") | J26: =IFERROR(VLOOKUP($D26,BS별도,MATCH(J$1,BS별도H,0),0)/100,"") | K26: =J26 | L26: =IFERROR(VLOOKUP($D26,BS별도,MATCH(L$1,BS별도H,0),0)/100,"") | M26: =IFERROR(VLOOKUP($D26,BS별도,MATCH(M$1,BS별도H,0),0)/100,"") | N26: =IFERROR(VLOOKUP($D26,BS연결,MATCH(N$1,BS연결H,0),0)/100,"") | O26: =IFERROR(VLOOKUP($D26,BS연결,MATCH(O$1,BS연결H,0),0)/100,"") | P26: =IFERROR(VLOOKUP($D26,BS연결,MATCH(P$1,BS연결H,0),0)/100,"") | Q26: =IFERROR(VLOOKUP($D26,BS연결,MATCH(Q$1,BS연결H,0),0)/100,"") | R26: =IFERROR(VLOOKUP($D26,BS연결,MATCH(R$1,BS연결H,0),0)/100,"") | S26: =IFERROR(VLOOKUP($D26,BS연결,MATCH(S$1,BS연결H,0),0)/100,"") | T26: =IFERROR(VLOOKUP($D26,BS연결,MATCH(T$1,BS연결H,0),0)/100,"") | U26: =IFERROR(VLOOKUP($D26,BS연결,MATCH(U$1,BS연결H,0),0)/100,"") | ... AB26: =IFERROR(VLOOKUP($D26,BS연결,MATCH(AB$1,BS연결H,0),0)/100,"") | AC26: =IFERROR(AB26*(1+변수!AC33),"") | AD26: =IFERROR(AC26*(1+변수!AD33),"") | AE26: =AD26 | AF26: =IFERROR(AD26*(1+변수!AF33),"") | AG26: =IFERROR(AF26*(1+변수!AG33),"") | AH26: =IFERROR(AG26*(1+변수!AH33),"") | AI26: =IFERROR(AH26*(1+변수!AI33),"") | AJ26: =AI26 | AK26: =IFERROR(AI26*(1+변수!AK33),"") | AL26: =IFERROR(AK26*(1+변수!AL33),"") | AM26: =IFERROR(AL26*(1+변수!AM33),"") | AN26: =IFERROR(AM26*(1+변수!AN33),"") | AO26: =AN26
A27: 이자발생자산 | B27: 재무상태 | C27: 억원 | D27: 이자발생자산 | E27: =IFERROR(VLOOKUP($D27,BS별도,MATCH(E$1,BS별도H,0),0)/100,"") | F27: 19.76 | G27: =IFERROR(VLOOKUP($D27,BS별도,MATCH(G$1,BS별도H,0),0)/100,"") | H27: =IFERROR(VLOOKUP($D27,BS별도,MATCH(H$1,BS별도H,0),0)/100,"") | I27: =IFERROR(VLOOKUP($D27,BS별도,MATCH(I$1,BS별도H,0),0)/100,"") | J27: =IFERROR(VLOOKUP($D27,BS별도,MATCH(J$1,BS별도H,0),0)/100,"") | K27: =J27 | L27: =IFERROR(VLOOKUP($D27,BS별도,MATCH(L$1,BS별도H,0),0)/100,"") | M27: =IFERROR(VLOOKUP($D27,BS별도,MATCH(M$1,BS별도H,0),0)/100,"") | N27: =IFERROR(VLOOKUP($D27,BS연결,MATCH(N$1,BS연결H,0),0)/100,"") | O27: =IFERROR(VLOOKUP($D27,BS연결,MATCH(O$1,BS연결H,0),0)/100,"") | P27: =IFERROR(VLOOKUP($D27,BS연결,MATCH(P$1,BS연결H,0),0)/100,"") | Q27: =IFERROR(VLOOKUP($D27,BS연결,MATCH(Q$1,BS연결H,0),0)/100,"") | R27: =IFERROR(VLOOKUP($D27,BS연결,MATCH(R$1,BS연결H,0),0)/100,"") | S27: =IFERROR(VLOOKUP($D27,BS연결,MATCH(S$1,BS연결H,0),0)/100,"") | T27: =IFERROR(VLOOKUP($D27,BS연결,MATCH(T$1,BS연결H,0),0)/100,"") | U27: =IFERROR(VLOOKUP($D27,BS연결,MATCH(U$1,BS연결H,0),0)/100,"") | ... AB27: =IFERROR(VLOOKUP($D27,BS연결,MATCH(AB$1,BS연결H,0),0)/100,"") | AC27: =IFERROR(AB27*(1+변수!AC34),"") | AD27: =IFERROR(AC27*(1+변수!AD34),"") | AE27: =AD27 | AF27: =IFERROR(AD27*(1+변수!AF34),"") | AG27: =IFERROR(AF27*(1+변수!AG34),"") | AH27: =IFERROR(AG27*(1+변수!AH34),"") | AI27: =IFERROR(AH27*(1+변수!AI34),"") | AJ27: =AI27 | AK27: =IFERROR(AI27*(1+변수!AK34),"") | AL27: =IFERROR(AK27*(1+변수!AL34),"") | AM27: =IFERROR(AL27*(1+변수!AM34),"") | AN27: =IFERROR(AM27*(1+변수!AN34),"") | AO27: =AN27
A28: 현금및현금성자산 | B28: 재무상태 | C28: 억원 | D28: 현금및현금성자산 | E28: =IFERROR(VLOOKUP($D28,BS별도,MATCH(E$1,BS별도H,0),0)/100,"") | F28: 13.01 | G28: =IFERROR(VLOOKUP($D28,BS별도,MATCH(G$1,BS별도H,0),0)/100,"") | H28: =IFERROR(VLOOKUP($D28,BS별도,MATCH(H$1,BS별도H,0),0)/100,"") | I28: =IFERROR(VLOOKUP($D28,BS별도,MATCH(I$1,BS별도H,0),0)/100,"") | J28: =IFERROR(VLOOKUP($D28,BS별도,MATCH(J$1,BS별도H,0),0)/100,"") | K28: =J28 | L28: =IFERROR(VLOOKUP($D28,BS별도,MATCH(L$1,BS별도H,0),0)/100,"") | M28: =IFERROR(VLOOKUP($D28,BS별도,MATCH(M$1,BS별도H,0),0)/100,"") | N28: =IFERROR(VLOOKUP($D28,BS연결,MATCH(N$1,BS연결H,0),0)/100,"") | O28: =IFERROR(VLOOKUP($D28,BS연결,MATCH(O$1,BS연결H,0),0)/100,"") | P28: =IFERROR(VLOOKUP($D28,BS연결,MATCH(P$1,BS연결H,0),0)/100,"") | Q28: =IFERROR(VLOOKUP($D28,BS연결,MATCH(Q$1,BS연결H,0),0)/100,"") | R28: =IFERROR(VLOOKUP($D28,BS연결,MATCH(R$1,BS연결H,0),0)/100,"") | S28: =IFERROR(VLOOKUP($D28,BS연결,MATCH(S$1,BS연결H,0),0)/100,"") | T28: =IFERROR(VLOOKUP($D28,BS연결,MATCH(T$1,BS연결H,0),0)/100,"") | U28: =IFERROR(VLOOKUP($D28,BS연결,MATCH(U$1,BS연결H,0),0)/100,"") | ... AB28: =IFERROR(VLOOKUP($D28,BS연결,MATCH(AB$1,BS연결H,0),0)/100,"") | AE28: =AD28 | AJ28: =AI28 | AO28: =AN28
A29: CAPEX | B29: 현금흐름 | C29: 억원 | D29: CAPEX | E29: =IFERROR(VLOOKUP($D29,BS별도,MATCH(E$1,BS별도H,0),0)/100,"") | G29: =IFERROR(VLOOKUP($D29,BS별도,MATCH(G$1,BS별도H,0),0)/100,"") | H29: =IFERROR(VLOOKUP($D29,BS별도,MATCH(H$1,BS별도H,0),0)/100,"") | I29: =IFERROR(VLOOKUP($D29,BS별도,MATCH(I$1,BS별도H,0),0)/100,"") | J29: =IFERROR(VLOOKUP($D29,BS별도,MATCH(J$1,BS별도H,0),0)/100,"") | K29: =SUM(G29:J29) | L29: =IFERROR(VLOOKUP($D29,BS별도,MATCH(L$1,BS별도H,0),0)/100,"") | M29: =IFERROR(VLOOKUP($D29,BS별도,MATCH(M$1,BS별도H,0),0)/100,"") | N29: =IFERROR(VLOOKUP($D29,BS연결,MATCH(N$1,BS연결H,0),0)/100,"") | O29: =IFERROR(VLOOKUP($D29,BS연결,MATCH(O$1,BS연결H,0),0)/100,"") | P29: =SUM(L29:O29) | Q29: =IFERROR(VLOOKUP($D29,BS연결,MATCH(Q$1,BS연결H,0),0)/100,"") | R29: =IFERROR(VLOOKUP($D29,BS연결,MATCH(R$1,BS연결H,0),0)/100,"") | S29: =IFERROR(VLOOKUP($D29,BS연결,MATCH(S$1,BS연결H,0),0)/100,"") | T29: =IFERROR(VLOOKUP($D29,BS연결,MATCH(T$1,BS연결H,0),0)/100,"") | U29: =IFERROR(VLOOKUP($D29,BS연결,MATCH(U$1,BS연결H,0),0)/100,"") | V29: =IFERROR(VLOOKUP($D29,BS연결,MATCH(V$1,BS연결H,0),0)/100,"") | W29: =IFERROR(VLOOKUP($D29,BS연결,MATCH(W$1,BS연결H,0),0)/100,"") | X29: =IFERROR(VLOOKUP($D29,BS연결,MATCH(X$1,BS연결H,0),0)/100,"") | ... AB29: =IFERROR(VLOOKUP($D29,BS연결,MATCH(AB$1,BS연결H,0),0)/100,"") | AC29: =IFERROR(X29*(1+변수!AC36),"") | AD29: =IFERROR(Y29*(1+변수!AD36),"") | AE29: =SUM(AA29:AD29) | AF29: =IFERROR(AA29*(1+변수!AF36),"") | AG29: =IFERROR(AB29*(1+변수!AG36),"") | AH29: =IFERROR(AC29*(1+변수!AH36),"") | AI29: =IFERROR(AD29*(1+변수!AI36),"") | AJ29: =SUM(AF29:AI29) | AK29: =IFERROR(AF29*(1+변수!AK36),"") | AL29: =IFERROR(AG29*(1+변수!AL36),"") | AM29: =IFERROR(AH29*(1+변수!AM36),"") | AN29: =IFERROR(AI29*(1+변수!AN36),"") | AO29: =SUM(AK29:AN29)
A30: 영업활동현금흐름 | B30: 현금흐름 | C30: 억원 | D30: 영업활동으로인한현금흐름 | E30: =IFERROR(VLOOKUP($D30,BS별도,MATCH(E$1,BS별도H,0),0)/100,"") | G30: =IFERROR(VLOOKUP($D30,BS별도,MATCH(G$1,BS별도H,0),0)/100,"") | H30: =IFERROR(VLOOKUP($D30,BS별도,MATCH(H$1,BS별도H,0),0)/100,"") | I30: =IFERROR(VLOOKUP($D30,BS별도,MATCH(I$1,BS별도H,0),0)/100,"") | J30: =IFERROR(VLOOKUP($D30,BS별도,MATCH(J$1,BS별도H,0),0)/100,"") | K30: =SUM(G30:J30) | L30: =IFERROR(VLOOKUP($D30,BS별도,MATCH(L$1,BS별도H,0),0)/100,"") | M30: =IFERROR(VLOOKUP($D30,BS별도,MATCH(M$1,BS별도H,0),0)/100,"") | N30: =IFERROR(VLOOKUP($D30,BS연결,MATCH(N$1,BS연결H,0),0)/100,"") | O30: =IFERROR(VLOOKUP($D30,BS연결,MATCH(O$1,BS연결H,0),0)/100,"") | P30: =SUM(L30:O30) | Q30: =IFERROR(VLOOKUP($D30,BS연결,MATCH(Q$1,BS연결H,0),0)/100,"") | R30: =IFERROR(VLOOKUP($D30,BS연결,MATCH(R$1,BS연결H,0),0)/100,"") | S30: =IFERROR(VLOOKUP($D30,BS연결,MATCH(S$1,BS연결H,0),0)/100,"") | T30: =IFERROR(VLOOKUP($D30,BS연결,MATCH(T$1,BS연결H,0),0)/100,"") | U30: =IFERROR(VLOOKUP($D30,BS연결,MATCH(U$1,BS연결H,0),0)/100,"") | V30: =IFERROR(VLOOKUP($D30,BS연결,MATCH(V$1,BS연결H,0),0)/100,"") | W30: =IFERROR(VLOOKUP($D30,BS연결,MATCH(W$1,BS연결H,0),0)/100,"") | X30: =IFERROR(VLOOKUP($D30,BS연결,MATCH(X$1,BS연결H,0),0)/100,"") | ... AB30: =IFERROR(VLOOKUP($D30,BS연결,MATCH(AB$1,BS연결H,0),0)/100,"") | AE30: =SUM(AA30:AD30) | AJ30: =SUM(AF30:AI30) | AO30: =SUM(AK30:AN30)
A31: 주식수 | B31: 주당 | C31: 백만주 | D31: 유통주식수 | E31: 29.55 | F31: =E31 | G31: 29.55 | H31: 29.782 | I31: 29.782 | J31: 29.782 | K31: =J31 | L31: 29.782 | M31: 29.918 | N31: 29.918 | O31: 30.826 | P31: =O31 | Q31: 30.826 | R31: 30.826 | S31: 30.826 | T31: 30.826 | U31: =T31 | V31: 30.826 | W31: 30.826 | X31: 30.826 | Y31: 37.115 | Z31: =Y31 | AA31: 37.115 | AB31: 37.115 | AC31: =IFERROR(AB31*(1+변수!AC38),"") | AD31: =IFERROR(AC31*(1+변수!AD38),"") | AE31: =AD31 | AF31: =IFERROR(AD31*(1+변수!AF38),"") | AG31: =IFERROR(AF31*(1+변수!AG38),"") | AH31: =IFERROR(AG31*(1+변수!AH38),"") | AI31: =IFERROR(AH31*(1+변수!AI38),"") | AJ31: =AI31 | AK31: =IFERROR(AI31*(1+변수!AK38),"") | AL31: =IFERROR(AK31*(1+변수!AL38),"") | AM31: =IFERROR(AL31*(1+변수!AM38),"") | AN31: =IFERROR(AM31*(1+변수!AN38),"") | AO31: =AN31
A32: EPS | B32: 주당 | C32: 원 | D32: EPS | E32: =IFERROR(E18*100/E31,"") | G32: =IFERROR(G18*100/G31,"") | H32: =IFERROR(H18*100/H31,"") | I32: =IFERROR(I18*100/I31,"") | J32: =IFERROR(J18*100/J31,"") | K32: =SUM(G32:J32) | L32: =IFERROR(L18*100/L31,"") | M32: =IFERROR(M18*100/M31,"") | N32: =IFERROR(N18*100/N31,"") | O32: =IFERROR(O18*100/O31,"") | P32: =SUM(L32:O32) | Q32: =IFERROR(Q18*100/Q31,"") | R32: =IFERROR(R18*100/R31,"") | S32: =IFERROR(S18*100/S31,"") | T32: =IFERROR(T18*100/T31,"") | U32: =SUM(Q32:T32) | V32: =IFERROR(V18*100/V31,"") | W32: =IFERROR(W18*100/W31,"") | X32: =IFERROR(X18*100/X31,"") | Y32: =IFERROR(Y18*100/Y31,"") | Z32: =SUM(V32:Y32) | AA32: =IFERROR(AA18*100/AA31,"") | AB32: =IFERROR(AB18*100/AB31,"") | AC32: =IFERROR(AC18*100/AC31,"") | AD32: =IFERROR(AD18*100/AD31,"") | AE32: =SUM(AA32:AD32) | AF32: =IFERROR(AF18*100/AF31,"") | AG32: =IFERROR(AG18*100/AG31,"") | AH32: =IFERROR(AH18*100/AH31,"") | AI32: =IFERROR(AI18*100/AI31,"") | AJ32: =SUM(AF32:AI32) | AK32: =IFERROR(AK18*100/AK31,"") | AL32: =IFERROR(AL18*100/AL31,"") | AM32: =IFERROR(AM18*100/AM31,"") | AN32: =IFERROR(AN18*100/AN31,"") | AO32: =SUM(AK32:AN32)
A33: BPS | B33: 주당 | C33: 원 | D33: BPS | E33: =IFERROR(E24*100/E31,"") | F33: =E33 | G33: =IFERROR(G24*100/G31,"") | H33: =IFERROR(H24*100/H31,"") | I33: =IFERROR(I24*100/I31,"") | J33: =IFERROR(J24*100/J31,"") | K33: =J33 | L33: =IFERROR(L24*100/L31,"") | M33: =IFERROR(M24*100/M31,"") | N33: =IFERROR(N24*100/N31,"") | O33: =IFERROR(O24*100/O31,"") | P33: =O33 | Q33: =IFERROR(Q24*100/Q31,"") | R33: =IFERROR(R24*100/R31,"") | S33: =IFERROR(S24*100/S31,"") | T33: =IFERROR(T24*100/T31,"") | U33: =T33 | V33: =IFERROR(V24*100/V31,"") | W33: =IFERROR(W24*100/W31,"") | X33: =IFERROR(X24*100/X31,"") | Y33: =IFERROR(Y24*100/Y31,"") | Z33: =Y33 | AA33: =IFERROR(AA24*100/AA31,"") | AB33: =IFERROR(AB24*100/AB31,"") | AC33: =IFERROR(AC24*100/AC31,"") | AD33: =IFERROR(AD24*100/AD31,"") | AE33: =AD33 | AF33: =IFERROR(AF24*100/AF31,"") | AG33: =IFERROR(AG24*100/AG31,"") | AH33: =IFERROR(AH24*100/AH31,"") | AI33: =IFERROR(AI24*100/AI31,"") | AJ33: =AI33 | AK33: =IFERROR(AK24*100/AK31,"") | AL33: =IFERROR(AL24*100/AL31,"") | AM33: =IFERROR(AM24*100/AM31,"") | AN33: =IFERROR(AN24*100/AN31,"") | AO33: =AN33
A34: DPS | B34: 주당 | C34: 원 | D34: DPS(보통주) | E34: 0 | F34: 0 | J34: 0 | K34: =SUM(G34:J34) | O34: 0 | P34: =SUM(L34:O34) | T34: 0 | U34: =SUM(Q34:T34) | Y34: 0 | Z34: =SUM(V34:Y34) | AD34: =변수!AD39 | AE34: =SUM(AA34:AD34) | AI34: =변수!AI39 | AJ34: =SUM(AF34:AI34) | AN34: =변수!AN39 | AO34: =SUM(AK34:AN34)
A35: PER | B35: 주당 | C35: 배 | D35: PER | F35: =E35 | I35: =IFERROR(변수!I18/(E32+G32+H32+I32),"") | K35: =J35 | P35: =O35 | U35: =T35 | Z35: =Y35 | AA35: =IFERROR(변수!AA18/(W32+X32+Y32+AA32),"") | AD35: =IFERROR(변수!$D$42/(AA32+AB32+AC32+AD32),"") | AE35: =AD35 | AF35: =IFERROR(변수!$D$42/(AB32+AC32+AD32+AF32),"") | AG35: =IFERROR(변수!$D$42/(AC32+AD32+AF32+AG32),"") | AH35: =IFERROR(변수!$D$42/(AD32+AF32+AG32+AH32),"") | AI35: =IFERROR(변수!$D$42/(AF32+AG32+AH32+AI32),"") | AJ35: =AI35 | AK35: =IFERROR(변수!$D$42/(AG32+AH32+AI32+AK32),"") | AL35: =IFERROR(변수!$D$42/(AH32+AI32+AK32+AL32),"") | AM35: =IFERROR(변수!$D$42/(AI32+AK32+AL32+AM32),"") | AN35: =IFERROR(변수!$D$42/(AK32+AL32+AM32+AN32),"") | AO35: =AN35
A36: PBR | B36: 주당 | C36: 배 | D36: PBR | E36: =IFERROR(변수!E18/E33,"") | F36: =E36 | G36: =IFERROR(변수!G18/G33,"") | H36: =IFERROR(변수!H18/H33,"") | I36: =IFERROR(변수!I18/I33,"") | J36: =IFERROR(변수!J18/J33,"") | K36: =J36 | L36: =IFERROR(변수!L18/L33,"") | M36: =IFERROR(변수!M18/M33,"") | N36: =IFERROR(변수!N18/N33,"") | O36: =IFERROR(변수!O18/O33,"") | P36: =O36 | Q36: =IFERROR(변수!Q18/Q33,"") | R36: =IFERROR(변수!R18/R33,"") | S36: =IFERROR(변수!S18/S33,"") | T36: =IFERROR(변수!T18/T33,"") | U36: =T36 | V36: =IFERROR(변수!V18/V33,"") | W36: =IFERROR(변수!W18/W33,"") | X36: =IFERROR(변수!X18/X33,"") | Y36: =IFERROR(변수!Y18/Y33,"") | Z36: =Y36 | AA36: =IFERROR(변수!AA18/AA33,"") | AB36: =IFERROR(변수!AB18/AB33,"") | AC36: =IFERROR(변수!$D$42/AC33,"") | AD36: =IFERROR(변수!$D$42/AD33,"") | AE36: =AD36 | AF36: =IFERROR(변수!$D$42/AF33,"") | AG36: =IFERROR(변수!$D$42/AG33,"") | AH36: =IFERROR(변수!$D$42/AH33,"") | AI36: =IFERROR(변수!$D$42/AI33,"") | AJ36: =AI36 | AK36: =IFERROR(변수!$D$42/AK33,"") | AL36: =IFERROR(변수!$D$42/AL33,"") | AM36: =IFERROR(변수!$D$42/AM33,"") | AN36: =IFERROR(변수!$D$42/AN33,"") | AO36: =AN36
A37: 매출전사 | B37: 사업부 | C37: 억원 | D37: 매출 전사(부문 미분리) | E37: 452.13 | G37: 345.13 | H37: 355.73 | I37: 340.53 | J37: 354.65 | K37: =SUM(G37:J37) | L37: 390.7 | M37: 340.78 | N37: 311.25 | O37: 279.24 | P37: =SUM(L37:O37) | Q37: 281.67 | R37: 260.06 | S37: 306.63 | T37: 343.36 | U37: =SUM(Q37:T37) | V37: 366.46 | W37: 476.27 | X37: 485.14 | Y37: 533.85 | Z37: =SUM(V37:Y37) | AA37: 506.2 | AB37: 491.36 | AC37: =IFERROR(AC5,"") | AD37: =IFERROR(AD5,"") | AE37: =SUM(AA37:AD37) | AF37: =IFERROR(AF5,"") | AG37: =IFERROR(AG5,"") | AH37: =IFERROR(AH5,"") | AI37: =IFERROR(AI5,"") | AJ37: =SUM(AF37:AI37) | AK37: =IFERROR(AK5,"") | AL37: =IFERROR(AL5,"") | AM37: =IFERROR(AM5,"") | AN37: =IFERROR(AN5,"") | AO37: =SUM(AK37:AN37)
A38: OP전사 | B38: 사업부 | C38: 억원 | D38: OP 전사(부문 미분리) | E38: 100.62 | G38: 27.99 | H38: 17.14 | I38: -6.33 | J38: -31.62 | K38: =SUM(G38:J38) | L38: -21.77 | M38: -33.99 | N38: -33.91 | O38: -108.1 | P38: =SUM(L38:O38) | Q38: -43.94 | R38: -9.35 | S38: -67.98 | T38: -70.11 | U38: =SUM(Q38:T38) | V38: -54.52 | W38: 15.83 | X38: 0.32 | Y38: 21.67 | Z38: =SUM(V38:Y38) | AA38: 13.94 | AB38: 12.78 | AC38: =IFERROR(AC9,"") | AD38: =IFERROR(AD9,"") | AE38: =SUM(AA38:AD38) | AF38: =IFERROR(AF9,"") | AG38: =IFERROR(AG9,"") | AH38: =IFERROR(AH9,"") | AI38: =IFERROR(AI9,"") | AJ38: =SUM(AF38:AI38) | AK38: =IFERROR(AK9,"") | AL38: =IFERROR(AL9,"") | AM38: =IFERROR(AM9,"") | AN38: =IFERROR(AN9,"") | AO38: =SUM(AK38:AN38)
B39: 비율(참고)
A40: NPM | C40: % | D40: 지배주주순이익 / 매출액 | E40: =IFERROR(E18/E5,"") | F40: =IFERROR(F18/F5,"") | G40: =IFERROR(G18/G5,"") | H40: =IFERROR(H18/H5,"") | I40: =IFERROR(I18/I5,"") | J40: =IFERROR(J18/J5,"") | K40: =IFERROR(K18/K5,"") | L40: =IFERROR(L18/L5,"") | ... AO40: =IFERROR(AO18/AO5,"")
A41: 매출원가율 | C41: % | D41: 매출원가 / 매출액 | E41: =IFERROR(E6/E5,"") | F41: =IFERROR(F6/F5,"") | G41: =IFERROR(G6/G5,"") | H41: =IFERROR(H6/H5,"") | I41: =IFERROR(I6/I5,"") | J41: =IFERROR(J6/J5,"") | K41: =IFERROR(K6/K5,"") | L41: =IFERROR(L6/L5,"") | ... AO41: =IFERROR(AO6/AO5,"")
A42: 판관비율 | C42: % | D42: 판관비 / 매출액 | E42: =IFERROR(E8/E5,"") | F42: =IFERROR(F8/F5,"") | G42: =IFERROR(G8/G5,"") | H42: =IFERROR(H8/H5,"") | I42: =IFERROR(I8/I5,"") | J42: =IFERROR(J8/J5,"") | K42: =IFERROR(K8/K5,"") | L42: =IFERROR(L8/L5,"") | ... AO42: =IFERROR(AO8/AO5,"")

Sheet 분기
C1: 이름: 분기H — subQ 를 이름으로 VLOOKUP(억원) | E1: 4Q21 | F1: 1Q22 | G1: 2Q22 | H1: 3Q22 | I1: 4Q22 | J1: 1Q23 | K1: 2Q23 | L1: 3Q23 | M1: 4Q23 | N1: 1Q24 | O1: 2Q24 | P1: 3Q24 | Q1: 4Q24 | R1: 1Q25 | S1: 2Q25 | T1: 3Q25 | U1: 4Q25 | V1: 1Q26 | W1: 2Q26 | X1: 3Q26 | Y1: 4Q26 | Z1: 1Q27 | AA1: 2Q27 | AB1: 3Q27 | AC1: 4Q27 | AD1: 1Q28 | AE1: 2Q28 | AF1: 3Q28 | AG1: 4Q28
C2: 종가: | D2: =변수!D42
C3: 기준일: | D3: 20261013 | E3: 1 | F3: 2 | G3: 3 | H3: 4 | I3: 5 | J3: 6 | K3: 7 | L3: 8 | M3: 9 | N3: 10 | O3: 11 | P3: 12 | Q3: 13 | R3: 14 | S3: 15 | T3: 16 | U3: 17 | V3: 18 | W3: 19 | X3: 20 | Y3: 21 | Z3: 22 | AA3: 23 | AB3: 24 | AC3: 25 | AD3: 26 | AE3: 27 | AF3: 28 | AG3: 29
E4: 2021.12 | F4: 2022.03 | G4: 2022.06 | H4: 2022.09 | I4: 2022.12 | J4: 2023.03 | K4: 2023.06 | L4: 2023.09 | M4: 2023.12 | N4: 2024.03 | O4: 2024.06 | P4: 2024.09 | Q4: 2024.12 | R4: 2025.03 | S4: 2025.06 | T4: 2025.09 | U4: 2025.12 | V4: 2026.03 | W4: 2026.06 | X4: 2026.09 | Y4: 2026.12 | Z4: 2027.03 | AA4: 2027.06 | AB4: 2027.09 | AC4: 2027.12 | AD4: 2028.03 | AE4: 2028.06 | AF4: 2028.09 | AG4: 2028.12
A5: 매출액 | D5: 매출액 | E5: =IFERROR(VLOOKUP($A5,subQ,MATCH(E$1,SUBQH,0),0),"") | F5: =IFERROR(VLOOKUP($A5,subQ,MATCH(F$1,SUBQH,0),0),"") | G5: =IFERROR(VLOOKUP($A5,subQ,MATCH(G$1,SUBQH,0),0),"") | H5: =IFERROR(VLOOKUP($A5,subQ,MATCH(H$1,SUBQH,0),0),"") | I5: =IFERROR(VLOOKUP($A5,subQ,MATCH(I$1,SUBQH,0),0),"") | J5: =IFERROR(VLOOKUP($A5,subQ,MATCH(J$1,SUBQH,0),0),"") | K5: =IFERROR(VLOOKUP($A5,subQ,MATCH(K$1,SUBQH,0),0),"") | L5: =IFERROR(VLOOKUP($A5,subQ,MATCH(L$1,SUBQH,0),0),"") | ... AG5: =IFERROR(VLOOKUP($A5,subQ,MATCH(AG$1,SUBQH,0),0),"")
A6: 매출원가 | D6: 매출원가 | E6: =IFERROR(VLOOKUP($A6,subQ,MATCH(E$1,SUBQH,0),0),"") | F6: =IFERROR(VLOOKUP($A6,subQ,MATCH(F$1,SUBQH,0),0),"") | G6: =IFERROR(VLOOKUP($A6,subQ,MATCH(G$1,SUBQH,0),0),"") | H6: =IFERROR(VLOOKUP($A6,subQ,MATCH(H$1,SUBQH,0),0),"") | I6: =IFERROR(VLOOKUP($A6,subQ,MATCH(I$1,SUBQH,0),0),"") | J6: =IFERROR(VLOOKUP($A6,subQ,MATCH(J$1,SUBQH,0),0),"") | K6: =IFERROR(VLOOKUP($A6,subQ,MATCH(K$1,SUBQH,0),0),"") | L6: =IFERROR(VLOOKUP($A6,subQ,MATCH(L$1,SUBQH,0),0),"") | ... AG6: =IFERROR(VLOOKUP($A6,subQ,MATCH(AG$1,SUBQH,0),0),"")
A7: 매출총이익 | D7: 매출총이익 | E7: =IFERROR(VLOOKUP($A7,subQ,MATCH(E$1,SUBQH,0),0),"") | F7: =IFERROR(VLOOKUP($A7,subQ,MATCH(F$1,SUBQH,0),0),"") | G7: =IFERROR(VLOOKUP($A7,subQ,MATCH(G$1,SUBQH,0),0),"") | H7: =IFERROR(VLOOKUP($A7,subQ,MATCH(H$1,SUBQH,0),0),"") | I7: =IFERROR(VLOOKUP($A7,subQ,MATCH(I$1,SUBQH,0),0),"") | J7: =IFERROR(VLOOKUP($A7,subQ,MATCH(J$1,SUBQH,0),0),"") | K7: =IFERROR(VLOOKUP($A7,subQ,MATCH(K$1,SUBQH,0),0),"") | L7: =IFERROR(VLOOKUP($A7,subQ,MATCH(L$1,SUBQH,0),0),"") | ... AG7: =IFERROR(VLOOKUP($A7,subQ,MATCH(AG$1,SUBQH,0),0),"")
A8: 판관비 | D8: 판매비와관리비 | E8: =IFERROR(VLOOKUP($A8,subQ,MATCH(E$1,SUBQH,0),0),"") | F8: =IFERROR(VLOOKUP($A8,subQ,MATCH(F$1,SUBQH,0),0),"") | G8: =IFERROR(VLOOKUP($A8,subQ,MATCH(G$1,SUBQH,0),0),"") | H8: =IFERROR(VLOOKUP($A8,subQ,MATCH(H$1,SUBQH,0),0),"") | I8: =IFERROR(VLOOKUP($A8,subQ,MATCH(I$1,SUBQH,0),0),"") | J8: =IFERROR(VLOOKUP($A8,subQ,MATCH(J$1,SUBQH,0),0),"") | K8: =IFERROR(VLOOKUP($A8,subQ,MATCH(K$1,SUBQH,0),0),"") | L8: =IFERROR(VLOOKUP($A8,subQ,MATCH(L$1,SUBQH,0),0),"") | ... AG8: =IFERROR(VLOOKUP($A8,subQ,MATCH(AG$1,SUBQH,0),0),"")
A9: 영업이익 | D9: 영업이익 | E9: =IFERROR(VLOOKUP($A9,subQ,MATCH(E$1,SUBQH,0),0),"") | F9: =IFERROR(VLOOKUP($A9,subQ,MATCH(F$1,SUBQH,0),0),"") | G9: =IFERROR(VLOOKUP($A9,subQ,MATCH(G$1,SUBQH,0),0),"") | H9: =IFERROR(VLOOKUP($A9,subQ,MATCH(H$1,SUBQH,0),0),"") | I9: =IFERROR(VLOOKUP($A9,subQ,MATCH(I$1,SUBQH,0),0),"") | J9: =IFERROR(VLOOKUP($A9,subQ,MATCH(J$1,SUBQH,0),0),"") | K9: =IFERROR(VLOOKUP($A9,subQ,MATCH(K$1,SUBQH,0),0),"") | L9: =IFERROR(VLOOKUP($A9,subQ,MATCH(L$1,SUBQH,0),0),"") | ... AG9: =IFERROR(VLOOKUP($A9,subQ,MATCH(AG$1,SUBQH,0),0),"")
A10: OPM | D10: 영업이익률 | E10: =IFERROR(VLOOKUP($A10,subQ,MATCH(E$1,SUBQH,0),0),"") | F10: =IFERROR(VLOOKUP($A10,subQ,MATCH(F$1,SUBQH,0),0),"") | G10: =IFERROR(VLOOKUP($A10,subQ,MATCH(G$1,SUBQH,0),0),"") | H10: =IFERROR(VLOOKUP($A10,subQ,MATCH(H$1,SUBQH,0),0),"") | I10: =IFERROR(VLOOKUP($A10,subQ,MATCH(I$1,SUBQH,0),0),"") | J10: =IFERROR(VLOOKUP($A10,subQ,MATCH(J$1,SUBQH,0),0),"") | K10: =IFERROR(VLOOKUP($A10,subQ,MATCH(K$1,SUBQH,0),0),"") | L10: =IFERROR(VLOOKUP($A10,subQ,MATCH(L$1,SUBQH,0),0),"") | ... AG10: =IFERROR(VLOOKUP($A10,subQ,MATCH(AG$1,SUBQH,0),0),"")
A11: 금융손익 | D11: 금융손익(이자·환 포함) | E11: =IFERROR(VLOOKUP($A11,subQ,MATCH(E$1,SUBQH,0),0),"") | F11: =IFERROR(VLOOKUP($A11,subQ,MATCH(F$1,SUBQH,0),0),"") | G11: =IFERROR(VLOOKUP($A11,subQ,MATCH(G$1,SUBQH,0),0),"") | H11: =IFERROR(VLOOKUP($A11,subQ,MATCH(H$1,SUBQH,0),0),"") | I11: =IFERROR(VLOOKUP($A11,subQ,MATCH(I$1,SUBQH,0),0),"") | J11: =IFERROR(VLOOKUP($A11,subQ,MATCH(J$1,SUBQH,0),0),"") | K11: =IFERROR(VLOOKUP($A11,subQ,MATCH(K$1,SUBQH,0),0),"") | L11: =IFERROR(VLOOKUP($A11,subQ,MATCH(L$1,SUBQH,0),0),"") | ... AG11: =IFERROR(VLOOKUP($A11,subQ,MATCH(AG$1,SUBQH,0),0),"")
A12: 이자손익 | D12: 이자손익(이자수익 − 이자비용) | E12: =IFERROR(VLOOKUP($A12,subQ,MATCH(E$1,SUBQH,0),0),"") | F12: =IFERROR(VLOOKUP($A12,subQ,MATCH(F$1,SUBQH,0),0),"") | G12: =IFERROR(VLOOKUP($A12,subQ,MATCH(G$1,SUBQH,0),0),"") | H12: =IFERROR(VLOOKUP($A12,subQ,MATCH(H$1,SUBQH,0),0),"") | I12: =IFERROR(VLOOKUP($A12,subQ,MATCH(I$1,SUBQH,0),0),"") | J12: =IFERROR(VLOOKUP($A12,subQ,MATCH(J$1,SUBQH,0),0),"") | K12: =IFERROR(VLOOKUP($A12,subQ,MATCH(K$1,SUBQH,0),0),"") | L12: =IFERROR(VLOOKUP($A12,subQ,MATCH(L$1,SUBQH,0),0),"") | ... AG12: =IFERROR(VLOOKUP($A12,subQ,MATCH(AG$1,SUBQH,0),0),"")
A13: 파생상품손익 | D13: 파생상품손익 | E13: =IFERROR(VLOOKUP($A13,subQ,MATCH(E$1,SUBQH,0),0),"") | F13: =IFERROR(VLOOKUP($A13,subQ,MATCH(F$1,SUBQH,0),0),"") | G13: =IFERROR(VLOOKUP($A13,subQ,MATCH(G$1,SUBQH,0),0),"") | H13: =IFERROR(VLOOKUP($A13,subQ,MATCH(H$1,SUBQH,0),0),"") | I13: =IFERROR(VLOOKUP($A13,subQ,MATCH(I$1,SUBQH,0),0),"") | J13: =IFERROR(VLOOKUP($A13,subQ,MATCH(J$1,SUBQH,0),0),"") | K13: =IFERROR(VLOOKUP($A13,subQ,MATCH(K$1,SUBQH,0),0),"") | L13: =IFERROR(VLOOKUP($A13,subQ,MATCH(L$1,SUBQH,0),0),"") | ... AG13: =IFERROR(VLOOKUP($A13,subQ,MATCH(AG$1,SUBQH,0),0),"")
A14: 기타영업외손익 | D14: 기타영업외손익 | E14: =IFERROR(VLOOKUP($A14,subQ,MATCH(E$1,SUBQH,0),0),"") | F14: =IFERROR(VLOOKUP($A14,subQ,MATCH(F$1,SUBQH,0),0),"") | G14: =IFERROR(VLOOKUP($A14,subQ,MATCH(G$1,SUBQH,0),0),"") | H14: =IFERROR(VLOOKUP($A14,subQ,MATCH(H$1,SUBQH,0),0),"") | I14: =IFERROR(VLOOKUP($A14,subQ,MATCH(I$1,SUBQH,0),0),"") | J14: =IFERROR(VLOOKUP($A14,subQ,MATCH(J$1,SUBQH,0),0),"") | K14: =IFERROR(VLOOKUP($A14,subQ,MATCH(K$1,SUBQH,0),0),"") | L14: =IFERROR(VLOOKUP($A14,subQ,MATCH(L$1,SUBQH,0),0),"") | ... AG14: =IFERROR(VLOOKUP($A14,subQ,MATCH(AG$1,SUBQH,0),0),"")
A15: 세전이익 | D15: 법인세비용차감전이익 | E15: =IFERROR(VLOOKUP($A15,subQ,MATCH(E$1,SUBQH,0),0),"") | F15: =IFERROR(VLOOKUP($A15,subQ,MATCH(F$1,SUBQH,0),0),"") | G15: =IFERROR(VLOOKUP($A15,subQ,MATCH(G$1,SUBQH,0),0),"") | H15: =IFERROR(VLOOKUP($A15,subQ,MATCH(H$1,SUBQH,0),0),"") | I15: =IFERROR(VLOOKUP($A15,subQ,MATCH(I$1,SUBQH,0),0),"") | J15: =IFERROR(VLOOKUP($A15,subQ,MATCH(J$1,SUBQH,0),0),"") | K15: =IFERROR(VLOOKUP($A15,subQ,MATCH(K$1,SUBQH,0),0),"") | L15: =IFERROR(VLOOKUP($A15,subQ,MATCH(L$1,SUBQH,0),0),"") | ... AG15: =IFERROR(VLOOKUP($A15,subQ,MATCH(AG$1,SUBQH,0),0),"")
A16: 법인세비용 | D16: 법인세비용 | E16: =IFERROR(VLOOKUP($A16,subQ,MATCH(E$1,SUBQH,0),0),"") | F16: =IFERROR(VLOOKUP($A16,subQ,MATCH(F$1,SUBQH,0),0),"") | G16: =IFERROR(VLOOKUP($A16,subQ,MATCH(G$1,SUBQH,0),0),"") | H16: =IFERROR(VLOOKUP($A16,subQ,MATCH(H$1,SUBQH,0),0),"") | I16: =IFERROR(VLOOKUP($A16,subQ,MATCH(I$1,SUBQH,0),0),"") | J16: =IFERROR(VLOOKUP($A16,subQ,MATCH(J$1,SUBQH,0),0),"") | K16: =IFERROR(VLOOKUP($A16,subQ,MATCH(K$1,SUBQH,0),0),"") | L16: =IFERROR(VLOOKUP($A16,subQ,MATCH(L$1,SUBQH,0),0),"") | ... AG16: =IFERROR(VLOOKUP($A16,subQ,MATCH(AG$1,SUBQH,0),0),"")
... A39: NPM | D39: NPM | E39: =IFERROR(VLOOKUP($A39,subQ,MATCH(E$1,SUBQH,0),0),"") | F39: =IFERROR(VLOOKUP($A39,subQ,MATCH(F$1,SUBQH,0),0),"") | G39: =IFERROR(VLOOKUP($A39,subQ,MATCH(G$1,SUBQH,0),0),"") | H39: =IFERROR(VLOOKUP($A39,subQ,MATCH(H$1,SUBQH,0),0),"") | I39: =IFERROR(VLOOKUP($A39,subQ,MATCH(I$1,SUBQH,0),0),"") | J39: =IFERROR(VLOOKUP($A39,subQ,MATCH(J$1,SUBQH,0),0),"") | K39: =IFERROR(VLOOKUP($A39,subQ,MATCH(K$1,SUBQH,0),0),"") | L39: =IFERROR(VLOOKUP($A39,subQ,MATCH(L$1,SUBQH,0),0),"") | ... AG39: =IFERROR(VLOOKUP($A39,subQ,MATCH(AG$1,SUBQH,0),0),"")
A40: 매출액 YoY | D40: 매출액 YoY | I40: =IFERROR(I5/E5-1,"") | J40: =IFERROR(J5/F5-1,"") | K40: =IFERROR(K5/G5-1,"") | L40: =IFERROR(L5/H5-1,"") | M40: =IFERROR(M5/I5-1,"") | N40: =IFERROR(N5/J5-1,"") | O40: =IFERROR(O5/K5-1,"") | P40: =IFERROR(P5/L5-1,"") | ... AG40: =IFERROR(AG5/AC5-1,"")
A41: 영업이익 YoY | D41: 영업이익 YoY | I41: =IFERROR(I9/E9-1,"") | J41: =IFERROR(J9/F9-1,"") | K41: =IFERROR(K9/G9-1,"") | L41: =IFERROR(L9/H9-1,"") | M41: =IFERROR(M9/I9-1,"") | N41: =IFERROR(N9/J9-1,"") | O41: =IFERROR(O9/K9-1,"") | P41: =IFERROR(P9/L9-1,"") | ... AG41: =IFERROR(AG9/AC9-1,"")
A42: 지배주주순이익 YoY | D42: 지배주주순이익 YoY | I42: =IFERROR(I18/E18-1,"") | J42: =IFERROR(J18/F18-1,"") | K42: =IFERROR(K18/G18-1,"") | L42: =IFERROR(L18/H18-1,"") | M42: =IFERROR(M18/I18-1,"") | N42: =IFERROR(N18/J18-1,"") | O42: =IFERROR(O18/K18-1,"") | P42: =IFERROR(P18/L18-1,"") | ... AG42: =IFERROR(AG18/AC18-1,"")

Sheet 연간예상
C1: 이름: 연간예상H — subQ 를 이름으로 VLOOKUP(억원) | E1: 2021 | F1: 2022 | G1: 2023 | H1: 2024 | I1: 2025 | J1: 2026 | K1: 2027 | L1: 2028
C2: 종가: | D2: =변수!D42
C3: 기준일: | D3: 20261013 | E3: 1 | F3: 2 | G3: 3 | H3: 4 | I3: 5 | J3: 6 | K3: 7 | L3: 8
E4: 2021.12A | F4: 2022.12A | G4: 2023.12A | H4: 2024.12A | I4: 2025.12A | J4: 2026.12A | K4: 2027.12A | L4: 2028.12A
A5: 매출액 | D5: 매출액 | E5: =IFERROR(VLOOKUP($A5,subQ,MATCH(E$1,SUBQH,0),0),"") | F5: =IFERROR(VLOOKUP($A5,subQ,MATCH(F$1,SUBQH,0),0),"") | G5: =IFERROR(VLOOKUP($A5,subQ,MATCH(G$1,SUBQH,0),0),"") | H5: =IFERROR(VLOOKUP($A5,subQ,MATCH(H$1,SUBQH,0),0),"") | I5: =IFERROR(VLOOKUP($A5,subQ,MATCH(I$1,SUBQH,0),0),"") | J5: =IFERROR(VLOOKUP($A5,subQ,MATCH(J$1,SUBQH,0),0),"") | K5: =IFERROR(VLOOKUP($A5,subQ,MATCH(K$1,SUBQH,0),0),"") | L5: =IFERROR(VLOOKUP($A5,subQ,MATCH(L$1,SUBQH,0),0),"")
A6: 매출원가 | D6: 매출원가 | E6: =IFERROR(VLOOKUP($A6,subQ,MATCH(E$1,SUBQH,0),0),"") | F6: =IFERROR(VLOOKUP($A6,subQ,MATCH(F$1,SUBQH,0),0),"") | G6: =IFERROR(VLOOKUP($A6,subQ,MATCH(G$1,SUBQH,0),0),"") | H6: =IFERROR(VLOOKUP($A6,subQ,MATCH(H$1,SUBQH,0),0),"") | I6: =IFERROR(VLOOKUP($A6,subQ,MATCH(I$1,SUBQH,0),0),"") | J6: =IFERROR(VLOOKUP($A6,subQ,MATCH(J$1,SUBQH,0),0),"") | K6: =IFERROR(VLOOKUP($A6,subQ,MATCH(K$1,SUBQH,0),0),"") | L6: =IFERROR(VLOOKUP($A6,subQ,MATCH(L$1,SUBQH,0),0),"")
A7: 매출총이익 | D7: 매출총이익 | E7: =IFERROR(VLOOKUP($A7,subQ,MATCH(E$1,SUBQH,0),0),"") | F7: =IFERROR(VLOOKUP($A7,subQ,MATCH(F$1,SUBQH,0),0),"") | G7: =IFERROR(VLOOKUP($A7,subQ,MATCH(G$1,SUBQH,0),0),"") | H7: =IFERROR(VLOOKUP($A7,subQ,MATCH(H$1,SUBQH,0),0),"") | I7: =IFERROR(VLOOKUP($A7,subQ,MATCH(I$1,SUBQH,0),0),"") | J7: =IFERROR(VLOOKUP($A7,subQ,MATCH(J$1,SUBQH,0),0),"") | K7: =IFERROR(VLOOKUP($A7,subQ,MATCH(K$1,SUBQH,0),0),"") | L7: =IFERROR(VLOOKUP($A7,subQ,MATCH(L$1,SUBQH,0),0),"")
A8: 판관비 | D8: 판매비와관리비 | E8: =IFERROR(VLOOKUP($A8,subQ,MATCH(E$1,SUBQH,0),0),"") | F8: =IFERROR(VLOOKUP($A8,subQ,MATCH(F$1,SUBQH,0),0),"") | G8: =IFERROR(VLOOKUP($A8,subQ,MATCH(G$1,SUBQH,0),0),"") | H8: =IFERROR(VLOOKUP($A8,subQ,MATCH(H$1,SUBQH,0),0),"") | I8: =IFERROR(VLOOKUP($A8,subQ,MATCH(I$1,SUBQH,0),0),"") | J8: =IFERROR(VLOOKUP($A8,subQ,MATCH(J$1,SUBQH,0),0),"") | K8: =IFERROR(VLOOKUP($A8,subQ,MATCH(K$1,SUBQH,0),0),"") | L8: =IFERROR(VLOOKUP($A8,subQ,MATCH(L$1,SUBQH,0),0),"")
A9: 영업이익 | D9: 영업이익 | E9: =IFERROR(VLOOKUP($A9,subQ,MATCH(E$1,SUBQH,0),0),"") | F9: =IFERROR(VLOOKUP($A9,subQ,MATCH(F$1,SUBQH,0),0),"") | G9: =IFERROR(VLOOKUP($A9,subQ,MATCH(G$1,SUBQH,0),0),"") | H9: =IFERROR(VLOOKUP($A9,subQ,MATCH(H$1,SUBQH,0),0),"") | I9: =IFERROR(VLOOKUP($A9,subQ,MATCH(I$1,SUBQH,0),0),"") | J9: =IFERROR(VLOOKUP($A9,subQ,MATCH(J$1,SUBQH,0),0),"") | K9: =IFERROR(VLOOKUP($A9,subQ,MATCH(K$1,SUBQH,0),0),"") | L9: =IFERROR(VLOOKUP($A9,subQ,MATCH(L$1,SUBQH,0),0),"")
A10: OPM | D10: 영업이익률 | E10: =IFERROR(VLOOKUP($A10,subQ,MATCH(E$1,SUBQH,0),0),"") | F10: =IFERROR(VLOOKUP($A10,subQ,MATCH(F$1,SUBQH,0),0),"") | G10: =IFERROR(VLOOKUP($A10,subQ,MATCH(G$1,SUBQH,0),0),"") | H10: =IFERROR(VLOOKUP($A10,subQ,MATCH(H$1,SUBQH,0),0),"") | I10: =IFERROR(VLOOKUP($A10,subQ,MATCH(I$1,SUBQH,0),0),"") | J10: =IFERROR(VLOOKUP($A10,subQ,MATCH(J$1,SUBQH,0),0),"") | K10: =IFERROR(VLOOKUP($A10,subQ,MATCH(K$1,SUBQH,0),0),"") | L10: =IFERROR(VLOOKUP($A10,subQ,MATCH(L$1,SUBQH,0),0),"")
A11: 금융손익 | D11: 금융손익(이자·환 포함) | E11: =IFERROR(VLOOKUP($A11,subQ,MATCH(E$1,SUBQH,0),0),"") | F11: =IFERROR(VLOOKUP($A11,subQ,MATCH(F$1,SUBQH,0),0),"") | G11: =IFERROR(VLOOKUP($A11,subQ,MATCH(G$1,SUBQH,0),0),"") | H11: =IFERROR(VLOOKUP($A11,subQ,MATCH(H$1,SUBQH,0),0),"") | I11: =IFERROR(VLOOKUP($A11,subQ,MATCH(I$1,SUBQH,0),0),"") | J11: =IFERROR(VLOOKUP($A11,subQ,MATCH(J$1,SUBQH,0),0),"") | K11: =IFERROR(VLOOKUP($A11,subQ,MATCH(K$1,SUBQH,0),0),"") | L11: =IFERROR(VLOOKUP($A11,subQ,MATCH(L$1,SUBQH,0),0),"")
A12: 이자손익 | D12: 이자손익(이자수익 − 이자비용) | E12: =IFERROR(VLOOKUP($A12,subQ,MATCH(E$1,SUBQH,0),0),"") | F12: =IFERROR(VLOOKUP($A12,subQ,MATCH(F$1,SUBQH,0),0),"") | G12: =IFERROR(VLOOKUP($A12,subQ,MATCH(G$1,SUBQH,0),0),"") | H12: =IFERROR(VLOOKUP($A12,subQ,MATCH(H$1,SUBQH,0),0),"") | I12: =IFERROR(VLOOKUP($A12,subQ,MATCH(I$1,SUBQH,0),0),"") | J12: =IFERROR(VLOOKUP($A12,subQ,MATCH(J$1,SUBQH,0),0),"") | K12: =IFERROR(VLOOKUP($A12,subQ,MATCH(K$1,SUBQH,0),0),"") | L12: =IFERROR(VLOOKUP($A12,subQ,MATCH(L$1,SUBQH,0),0),"")
A13: 파생상품손익 | D13: 파생상품손익 | E13: =IFERROR(VLOOKUP($A13,subQ,MATCH(E$1,SUBQH,0),0),"") | F13: =IFERROR(VLOOKUP($A13,subQ,MATCH(F$1,SUBQH,0),0),"") | G13: =IFERROR(VLOOKUP($A13,subQ,MATCH(G$1,SUBQH,0),0),"") | H13: =IFERROR(VLOOKUP($A13,subQ,MATCH(H$1,SUBQH,0),0),"") | I13: =IFERROR(VLOOKUP($A13,subQ,MATCH(I$1,SUBQH,0),0),"") | J13: =IFERROR(VLOOKUP($A13,subQ,MATCH(J$1,SUBQH,0),0),"") | K13: =IFERROR(VLOOKUP($A13,subQ,MATCH(K$1,SUBQH,0),0),"") | L13: =IFERROR(VLOOKUP($A13,subQ,MATCH(L$1,SUBQH,0),0),"")
A14: 기타영업외손익 | D14: 기타영업외손익 | E14: =IFERROR(VLOOKUP($A14,subQ,MATCH(E$1,SUBQH,0),0),"") | F14: =IFERROR(VLOOKUP($A14,subQ,MATCH(F$1,SUBQH,0),0),"") | G14: =IFERROR(VLOOKUP($A14,subQ,MATCH(G$1,SUBQH,0),0),"") | H14: =IFERROR(VLOOKUP($A14,subQ,MATCH(H$1,SUBQH,0),0),"") | I14: =IFERROR(VLOOKUP($A14,subQ,MATCH(I$1,SUBQH,0),0),"") | J14: =IFERROR(VLOOKUP($A14,subQ,MATCH(J$1,SUBQH,0),0),"") | K14: =IFERROR(VLOOKUP($A14,subQ,MATCH(K$1,SUBQH,0),0),"") | L14: =IFERROR(VLOOKUP($A14,subQ,MATCH(L$1,SUBQH,0),0),"")
A15: 세전이익 | D15: 법인세비용차감전이익 | E15: =IFERROR(VLOOKUP($A15,subQ,MATCH(E$1,SUBQH,0),0),"") | F15: =IFERROR(VLOOKUP($A15,subQ,MATCH(F$1,SUBQH,0),0),"") | G15: =IFERROR(VLOOKUP($A15,subQ,MATCH(G$1,SUBQH,0),0),"") | H15: =IFERROR(VLOOKUP($A15,subQ,MATCH(H$1,SUBQH,0),0),"") | I15: =IFERROR(VLOOKUP($A15,subQ,MATCH(I$1,SUBQH,0),0),"") | J15: =IFERROR(VLOOKUP($A15,subQ,MATCH(J$1,SUBQH,0),0),"") | K15: =IFERROR(VLOOKUP($A15,subQ,MATCH(K$1,SUBQH,0),0),"") | L15: =IFERROR(VLOOKUP($A15,subQ,MATCH(L$1,SUBQH,0),0),"")
A16: 법인세비용 | D16: 법인세비용 | E16: =IFERROR(VLOOKUP($A16,subQ,MATCH(E$1,SUBQH,0),0),"") | F16: =IFERROR(VLOOKUP($A16,subQ,MATCH(F$1,SUBQH,0),0),"") | G16: =IFERROR(VLOOKUP($A16,subQ,MATCH(G$1,SUBQH,0),0),"") | H16: =IFERROR(VLOOKUP($A16,subQ,MATCH(H$1,SUBQH,0),0),"") | I16: =IFERROR(VLOOKUP($A16,subQ,MATCH(I$1,SUBQH,0),0),"") | J16: =IFERROR(VLOOKUP($A16,subQ,MATCH(J$1,SUBQH,0),0),"") | K16: =IFERROR(VLOOKUP($A16,subQ,MATCH(K$1,SUBQH,0),0),"") | L16: =IFERROR(VLOOKUP($A16,subQ,MATCH(L$1,SUBQH,0),0),"")
... A39: NPM | D39: NPM | E39: =IFERROR(VLOOKUP($A39,subQ,MATCH(E$1,SUBQH,0),0),"") | F39: =IFERROR(VLOOKUP($A39,subQ,MATCH(F$1,SUBQH,0),0),"") | G39: =IFERROR(VLOOKUP($A39,subQ,MATCH(G$1,SUBQH,0),0),"") | H39: =IFERROR(VLOOKUP($A39,subQ,MATCH(H$1,SUBQH,0),0),"") | I39: =IFERROR(VLOOKUP($A39,subQ,MATCH(I$1,SUBQH,0),0),"") | J39: =IFERROR(VLOOKUP($A39,subQ,MATCH(J$1,SUBQH,0),0),"") | K39: =IFERROR(VLOOKUP($A39,subQ,MATCH(K$1,SUBQH,0),0),"") | L39: =IFERROR(VLOOKUP($A39,subQ,MATCH(L$1,SUBQH,0),0),"")
A40: 매출액 YoY | D40: 매출액 YoY | F40: =IFERROR(F5/E5-1,"") | G40: =IFERROR(G5/F5-1,"") | H40: =IFERROR(H5/G5-1,"") | I40: =IFERROR(I5/H5-1,"") | J40: =IFERROR(J5/I5-1,"") | K40: =IFERROR(K5/J5-1,"") | L40: =IFERROR(L5/K5-1,"")
A41: 영업이익 YoY | D41: 영업이익 YoY | F41: =IFERROR(F9/E9-1,"") | G41: =IFERROR(G9/F9-1,"") | H41: =IFERROR(H9/G9-1,"") | I41: =IFERROR(I9/H9-1,"") | J41: =IFERROR(J9/I9-1,"") | K41: =IFERROR(K9/J9-1,"") | L41: =IFERROR(L9/K9-1,"")
A42: 지배주주순이익 YoY | D42: 지배주주순이익 YoY | F42: =IFERROR(F18/E18-1,"") | G42: =IFERROR(G18/F18-1,"") | H42: =IFERROR(H18/G18-1,"") | I42: =IFERROR(I18/H18-1,"") | J42: =IFERROR(J18/I18-1,"") | K42: =IFERROR(K18/J18-1,"") | L42: =IFERROR(L18/K18-1,"")

Sheet TP
B1: 종가 | C1: =변수!D42
B2: 기준일 | C2: =변수!D43
B3: 모델 산출값 — 목표주가·추천 아님. 밴드·COE 는 변수 시트 3절의 가정
C5: FY | D5: 2025 | E5: 2026 | F5: 2027 | G5: 2028
D6: A | E6: E | F6: E | G6: E
C7: EPS(원) | D7: =IFERROR(VLOOKUP("EPS",subQ,MATCH(D$5,SUBQH,0),0),"") | E7: =IFERROR(VLOOKUP("EPS",subQ,MATCH(E$5,SUBQH,0),0),"") | F7: =IFERROR(VLOOKUP("EPS",subQ,MATCH(F$5,SUBQH,0),0),"") | G7: =IFERROR(VLOOKUP("EPS",subQ,MATCH(G$5,SUBQH,0),0),"")
C8: BPS(원) | D8: =IFERROR(VLOOKUP("BPS",subQ,MATCH(D$5,SUBQH,0),0),"") | E8: =IFERROR(VLOOKUP("BPS",subQ,MATCH(E$5,SUBQH,0),0),"") | F8: =IFERROR(VLOOKUP("BPS",subQ,MATCH(F$5,SUBQH,0),0),"") | G8: =IFERROR(VLOOKUP("BPS",subQ,MATCH(G$5,SUBQH,0),0),"")
C9: 지배주주순이익(억원) | D9: =IFERROR(VLOOKUP("지배주주순이익",subQ,MATCH(D$5,SUBQH,0),0),"") | E9: =IFERROR(VLOOKUP("지배주주순이익",subQ,MATCH(E$5,SUBQH,0),0),"") | F9: =IFERROR(VLOOKUP("지배주주순이익",subQ,MATCH(F$5,SUBQH,0),0),"") | G9: =IFERROR(VLOOKUP("지배주주순이익",subQ,MATCH(G$5,SUBQH,0),0),"")
C10: 영업이익(억원) | D10: =IFERROR(VLOOKUP("영업이익",subQ,MATCH(D$5,SUBQH,0),0),"") | E10: =IFERROR(VLOOKUP("영업이익",subQ,MATCH(E$5,SUBQH,0),0),"") | F10: =IFERROR(VLOOKUP("영업이익",subQ,MATCH(F$5,SUBQH,0),0),"") | G10: =IFERROR(VLOOKUP("영업이익",subQ,MATCH(G$5,SUBQH,0),0),"")
C11: ROE(EPS/기초BPS) | E11: =IFERROR(E7/D8,"") | F11: =IFERROR(F7/E8,"") | G11: =IFERROR(G7/F8,"")
B13: PER
C14: 12M fwd EPS | D14: =IFERROR(E7*변수!D48+F7*(1-변수!D48),"")
C15: 적정가치 @PER_lo | D15: =변수!D45 | E15: =IFERROR(ROUND($D$14*D15,-2),"") | F15: =IFERROR(E15/$C$1-1,"") | G15: 배 · 원 · 종가 대비
C16: 적정가치 @PER_mid | D16: =변수!D46 | E16: =IFERROR(ROUND($D$14*D16,-2),"") | F16: =IFERROR(E16/$C$1-1,"") | G16: 배 · 원 · 종가 대비
C17: 적정가치 @PER_hi | D17: =변수!D47 | E17: =IFERROR(ROUND($D$14*D17,-2),"") | F17: =IFERROR(E17/$C$1-1,"") | G17: 배 · 원 · 종가 대비
C18: 현재 PER(종가/12M fwd EPS) | D18: =IFERROR($C$1/$D$14,"")
B20: PBR
C21: 최근 BPS(마지막 실적 분기) | D21: =IFERROR(VLOOKUP("BPS",subQ,MATCH("2Q26",SUBQH,0),0),"")
C22: ROE fwd(12M fwd EPS / BPS) | D22: =IFERROR($D$14/$D$21,"")
C23: COE | D23: =변수!D44
C24: 적정 PBR = ROE/COE | D24: =IFERROR(D22/D23,"")
C25: 적정가치(PBR) = BPS × 적정PBR | D25: =IFERROR(ROUND(D21*D24,-2),"") | E25: =IFERROR(D25/$C$1-1,"")
C26: 현재 PBR(종가/BPS) | D26: =IFERROR($C$1/D21,"")
B28: 모델 json valuation(참고)
C29: eps_fwd12m | D29: 59.1
C30: bps_latest | D30: 1358
C31: per_now | D31: 16.55
C32: pbr_now | D32: 0.72
C33: roe_fwd | D33: 0.0435
C34: fair_pbr | D34: 0.48
C35: fair_value_pbr | D35: 700
C36: ev_ebitda | D36: 11.56
C37: note | D37: 모델 산출값 — 목표주가·추천 아님

Sheet 외화
C1: 이름: 외화QH — 환율 QoQ · 외화 순노출 × Δ기말환율 | E1: 4Q21 | F1: 1Q22 | G1: 2Q22 | H1: 3Q22 | I1: 4Q22 | J1: 1Q23 | K1: 2Q23 | L1: 3Q23 | M1: 4Q23 | N1: 1Q24 | O1: 2Q24 | P1: 3Q24 | Q1: 4Q24 | R1: 1Q25 | S1: 2Q25 | T1: 3Q25 | U1: 4Q25 | V1: 1Q26 | W1: 2Q26 | X1: 3Q26 | Y1: 4Q26 | Z1: 1Q27 | AA1: 2Q27 | AB1: 3Q27 | AC1: 4Q27 | AD1: 1Q28 | AE1: 2Q28 | AF1: 3Q28 | AG1: 4Q28
E3: 1 | F3: 2 | G3: 3 | H3: 4 | I3: 5 | J3: 6 | K3: 7 | L3: 8 | M3: 9 | N3: 10 | O3: 11 | P3: 12 | Q3: 13 | R3: 14 | S3: 15 | T3: 16 | U3: 17 | V3: 18 | W3: 19 | X3: 20 | Y3: 21 | Z3: 22 | AA3: 23 | AB3: 24 | AC3: 25 | AD3: 26 | AE3: 27 | AF3: 28 | AG3: 29
E4: 2021.12 | F4: 2022.03 | G4: 2022.06 | H4: 2022.09 | I4: 2022.12 | J4: 2023.03 | K4: 2023.06 | L4: 2023.09 | M4: 2023.12 | N4: 2024.03 | O4: 2024.06 | P4: 2024.09 | Q4: 2024.12 | R4: 2025.03 | S4: 2025.06 | T4: 2025.09 | U4: 2025.12 | V4: 2026.03 | W4: 2026.06 | X4: 2026.09 | Y4: 2026.12 | Z4: 2027.03 | AA4: 2027.06 | AB4: 2027.09 | AC4: 2027.12 | AD4: 2028.03 | AE4: 2028.06 | AF4: 2028.09 | AG4: 2028.12
D5: 원/달러(평균) | E5: =IFERROR(VLOOKUP($D5,환율,MATCH(E$1,변수H,0),0),"") | F5: =IFERROR(VLOOKUP($D5,환율,MATCH(F$1,변수H,0),0),"") | G5: =IFERROR(VLOOKUP($D5,환율,MATCH(G$1,변수H,0),0),"") | H5: =IFERROR(VLOOKUP($D5,환율,MATCH(H$1,변수H,0),0),"") | I5: =IFERROR(VLOOKUP($D5,환율,MATCH(I$1,변수H,0),0),"") | J5: =IFERROR(VLOOKUP($D5,환율,MATCH(J$1,변수H,0),0),"") | K5: =IFERROR(VLOOKUP($D5,환율,MATCH(K$1,변수H,0),0),"") | L5: =IFERROR(VLOOKUP($D5,환율,MATCH(L$1,변수H,0),0),"") | ... AG5: =IFERROR(VLOOKUP($D5,환율,MATCH(AG$1,변수H,0),0),"")
A6: 원/달러(평균) QoQ | F6: =IFERROR(F5/E5-1,"") | G6: =IFERROR(G5/F5-1,"") | H6: =IFERROR(H5/G5-1,"") | I6: =IFERROR(I5/H5-1,"") | J6: =IFERROR(J5/I5-1,"") | K6: =IFERROR(K5/J5-1,"") | L6: =IFERROR(L5/K5-1,"") | M6: =IFERROR(M5/L5-1,"") | ... AG6: =IFERROR(AG5/AF5-1,"")
D7: 원/달러(기말) | E7: =IFERROR(VLOOKUP($D7,환율,MATCH(E$1,변수H,0),0),"") | F7: =IFERROR(VLOOKUP($D7,환율,MATCH(F$1,변수H,0),0),"") | G7: =IFERROR(VLOOKUP($D7,환율,MATCH(G$1,변수H,0),0),"") | H7: =IFERROR(VLOOKUP($D7,환율,MATCH(H$1,변수H,0),0),"") | I7: =IFERROR(VLOOKUP($D7,환율,MATCH(I$1,변수H,0),0),"") | J7: =IFERROR(VLOOKUP($D7,환율,MATCH(J$1,변수H,0),0),"") | K7: =IFERROR(VLOOKUP($D7,환율,MATCH(K$1,변수H,0),0),"") | L7: =IFERROR(VLOOKUP($D7,환율,MATCH(L$1,변수H,0),0),"") | ... AG7: =IFERROR(VLOOKUP($D7,환율,MATCH(AG$1,변수H,0),0),"")
A8: 원/달러(기말) QoQ | F8: =IFERROR(F7/E7-1,"") | G8: =IFERROR(G7/F7-1,"") | H8: =IFERROR(H7/G7-1,"") | I8: =IFERROR(I7/H7-1,"") | J8: =IFERROR(J7/I7-1,"") | K8: =IFERROR(K7/J7-1,"") | L8: =IFERROR(L7/K7-1,"") | M8: =IFERROR(M7/L7-1,"") | ... AG8: =IFERROR(AG7/AF7-1,"")
D9: W/Euro(평균) | E9: =IFERROR(VLOOKUP($D9,환율,MATCH(E$1,변수H,0),0),"") | F9: =IFERROR(VLOOKUP($D9,환율,MATCH(F$1,변수H,0),0),"") | G9: =IFERROR(VLOOKUP($D9,환율,MATCH(G$1,변수H,0),0),"") | H9: =IFERROR(VLOOKUP($D9,환율,MATCH(H$1,변수H,0),0),"") | I9: =IFERROR(VLOOKUP($D9,환율,MATCH(I$1,변수H,0),0),"") | J9: =IFERROR(VLOOKUP($D9,환율,MATCH(J$1,변수H,0),0),"") | K9: =IFERROR(VLOOKUP($D9,환율,MATCH(K$1,변수H,0),0),"") | L9: =IFERROR(VLOOKUP($D9,환율,MATCH(L$1,변수H,0),0),"") | ... AG9: =IFERROR(VLOOKUP($D9,환율,MATCH(AG$1,변수H,0),0),"")
A10: W/Euro(평균) QoQ | F10: =IFERROR(F9/E9-1,"") | G10: =IFERROR(G9/F9-1,"") | H10: =IFERROR(H9/G9-1,"") | I10: =IFERROR(I9/H9-1,"") | J10: =IFERROR(J9/I9-1,"") | K10: =IFERROR(K9/J9-1,"") | L10: =IFERROR(L9/K9-1,"") | M10: =IFERROR(M9/L9-1,"") | ... AG10: =IFERROR(AG9/AF9-1,"")
D11: W/Euro(기말) | E11: =IFERROR(VLOOKUP($D11,환율,MATCH(E$1,변수H,0),0),"") | F11: =IFERROR(VLOOKUP($D11,환율,MATCH(F$1,변수H,0),0),"") | G11: =IFERROR(VLOOKUP($D11,환율,MATCH(G$1,변수H,0),0),"") | H11: =IFERROR(VLOOKUP($D11,환율,MATCH(H$1,변수H,0),0),"") | I11: =IFERROR(VLOOKUP($D11,환율,MATCH(I$1,변수H,0),0),"") | J11: =IFERROR(VLOOKUP($D11,환율,MATCH(J$1,변수H,0),0),"") | K11: =IFERROR(VLOOKUP($D11,환율,MATCH(K$1,변수H,0),0),"") | L11: =IFERROR(VLOOKUP($D11,환율,MATCH(L$1,변수H,0),0),"") | ... AG11: =IFERROR(VLOOKUP($D11,환율,MATCH(AG$1,변수H,0),0),"")
A12: W/Euro(기말) QoQ | F12: =IFERROR(F11/E11-1,"") | G12: =IFERROR(G11/F11-1,"") | H12: =IFERROR(H11/G11-1,"") | I12: =IFERROR(I11/H11-1,"") | J12: =IFERROR(J11/I11-1,"") | K12: =IFERROR(K11/J11-1,"") | L12: =IFERROR(L11/K11-1,"") | M12: =IFERROR(M11/L11-1,"") | ... AG12: =IFERROR(AG11/AF11-1,"")
D13: 원/100Y(기말) | E13: =IFERROR(VLOOKUP($D13,환율,MATCH(E$1,변수H,0),0),"") | F13: =IFERROR(VLOOKUP($D13,환율,MATCH(F$1,변수H,0),0),"") | G13: =IFERROR(VLOOKUP($D13,환율,MATCH(G$1,변수H,0),0),"") | H13: =IFERROR(VLOOKUP($D13,환율,MATCH(H$1,변수H,0),0),"") | I13: =IFERROR(VLOOKUP($D13,환율,MATCH(I$1,변수H,0),0),"") | J13: =IFERROR(VLOOKUP($D13,환율,MATCH(J$1,변수H,0),0),"") | K13: =IFERROR(VLOOKUP($D13,환율,MATCH(K$1,변수H,0),0),"") | L13: =IFERROR(VLOOKUP($D13,환율,MATCH(L$1,변수H,0),0),"") | ... AG13: =IFERROR(VLOOKUP($D13,환율,MATCH(AG$1,변수H,0),0),"")
A14: 원/100Y(기말) QoQ | F14: =IFERROR(F13/E13-1,"") | G14: =IFERROR(G13/F13-1,"") | H14: =IFERROR(H13/G13-1,"") | I14: =IFERROR(I13/H13-1,"") | J14: =IFERROR(J13/I13-1,"") | K14: =IFERROR(K13/J13-1,"") | L14: =IFERROR(L13/K13-1,"") | M14: =IFERROR(M13/L13-1,"") | ... AG14: =IFERROR(AG13/AF13-1,"")
A16: 외화순노출 | C16: 외화 순노출(백만$) | D16: =변수!D55 | E16: 외화 순노출 × Δ기말환율 (외화 시트 방식)
A17: 환관련손익추정 | C17: 환관련손익 추정(억원) = 순노출 × Δ원/달러(기말) / 100 | F17: =IFERROR($D$16*(F7-E7)/100,"") | G17: =IFERROR($D$16*(G7-F7)/100,"") | H17: =IFERROR($D$16*(H7-G7)/100,"") | I17: =IFERROR($D$16*(I7-H7)/100,"") | J17: =IFERROR($D$16*(J7-I7)/100,"") | K17: =IFERROR($D$16*(K7-J7)/100,"") | L17: =IFERROR($D$16*(L7-K7)/100,"") | M17: =IFERROR($D$16*(M7-L7)/100,"") | ... AG17: =IFERROR($D$16*(AG7-AF7)/100,"")
A18: fx_pnl.by_q | C18: 모델 fx_pnl.by_q(억원, 참고)
C19: 외화 순노출 미공시(face) → 0 + 표기
