Workbook
Name 변수H: 변수!$C$1:$AO$1
Name 환율: 변수!$C$6:$AO$13
Name BS연결H: BS연결!$C$1:$AO$1
Name BS연결: BS연결!$C$5:$AO$104
Name BS별도H: BS별도!$C$1:$AO$1
Name BS별도: BS별도!$C$5:$AO$90
Name SUBQH: subQ!$A$1:$AO$1
Name subQ: subQ!$A$5:$AO$44

Sheet README
A1: 나노(187790) 실적 모델 — ARGUS 한국조선
A2: 기준 분기 2026Q2 · 마지막 실적 2026Q2 · 생성 2026-10-14
A3: 모든 수치는 모델 산출값(DART 공개 재무제표 + 우리 추정)이다 — 목표주가·투자 추천 아님. 참고용 · 투자조언 아님.
A5: 시트
A6: 변수 가정 시계열. 환율 8행(ECB via frankfurter — L2 fx.json; 추정 분기 = 노란 가정), 추정 드라이버(노란 셀 = 모델값에서 역산한 가정, 바꾸면 재계산; 연녹 셀 = 3절 스칼라 참조 수식), 3절 스칼라 가정(세율·판관비율·지배주주비중·이자율·종가·PER 밴드·COE·외화 순노출·헤지비율)
A7: BS연결/BS별도 FnGuide 계정명 × 기간 값 덤프(백만원). 행1 분기라벨, 행4 YYYY.MM / YYYY.12A. 이름정의 BS연결H·BS연결(계정명 C열부터)
A8: subQ 분기 서브모델(억원 = 백만원/100). 확정 행: =IFERROR(VLOOKUP($D행,BS연결,MATCH(E$1,BS연결H,0),0)/100,"") 추정 행: 변수 시트 가정 셀 참조 수식. 외환손익·파생상품손익은 BS 계정 합·차, 기타금융손익은 잔차, OPM·EPS·BPS·PER·PBR 은 파생 수식, 조정EPS 는 EPS 참조(일회성 의심 분기만 산식 셀)
A9: SLS 선표(조선사만, sls json 있을 때): 요약 행(sls 저장값) + 계약별 스케줄(백만$) × (헤지비율 × 헤지환율 + (1−헤지비율) × 건조시점 환율[변수 원/달러(평균)]) → 원화 수식 블록 → 합계 행이 subQ 매출조선에 연결
A10: 시나리오 신규수주 보수/기준/낙관(forecast_panel 패널, 모델에 scenarios 가 있을 때만): 매출액·영업이익 = subQ 기준값 ± (시나리오 신규 − base 신규) × OPM. base 만 subQ 행에 포함, 나머지는 합산 안 함
A11: 분기/연간예상 subQ 를 이름(A열 key)으로 VLOOKUP 한 보고서 표(억원)
A12: TP PER 밴드 × 12M fwd EPS, PBR = ROE/COE × BPS — 모델 산출값 구간, 목표주가·추천 아님
A13: 외화 환율 QoQ, 외화 순노출 × Δ기말환율 → 환관련손익 추정
... A35: 백테스트: {"freeze": "2025Q2", "horizon": 4, "revenue_wape_pct": 29.5, "op_wape_pct": 91.0, "n": 4, "note": "단일 회사 4분기 — 통계 아님", "driver_at_freeze": "trend_seasonal", "selection_oos_at_freeze": null, "frozen_inputs": "fin(연결/별도)·고객 조선사 모델·지주 자회사 모델은 2025Q2 까지의 분기만; 선표는 체결일 ≤ 2025Q2 말일 계약(원장 최신 금액·코호트 등급, 환산 없음); 잔고는 yards_cache 2025Q2; 시세·환율 forward·prices·forecast_panel 신규수주 미사용. 고객 가중치(suppliers.json 언급 비중)와 합병 체인링크는 현재 지식; 고객 연동 채택은 동결 모델 안에서도 자기 la−4분기 OOS 규칙(selection_oos_at_freeze)", "detail": [{"q": "2025Q3", "rev_pred": 230.27, "rev_act": 344.65, "op_pred": 5.17, "op_act": 55.18}, {"q": "2025Q4", "rev_pred": 187.56, "rev_act": 217.83, "op_pred": 4.21, "op_act": 2.58}, {"q": "2026Q1", "rev_pred": 121.73, "rev_act": 110.35, "op_pred": 2.74, "op_act": -8.89}, {"q": "2026Q2", "rev_pred": 140.47, "rev_act": 259.5, "op_pred": 3.16, "op_act": 5.83}]}

Sheet 변수
C1: 이름: 변수H | E1: 4Q21 | F1: 2021 | G1: 1Q22 | H1: 2Q22 | I1: 3Q22 | J1: 4Q22 | K1: 2022 | L1: 1Q23 | M1: 2Q23 | N1: 3Q23 | O1: 4Q23 | P1: 2023 | Q1: 1Q24 | R1: 2Q24 | S1: 3Q24 | T1: 4Q24 | U1: 2024 | V1: 1Q25 | W1: 2Q25 | X1: 3Q25 | Y1: 4Q25 | Z1: 2025 | AA1: 1Q26 | AB1: 2Q26 | AC1: 3Q26 | AD1: 4Q26 | AE1: 2026 | AF1: 1Q27 | AG1: 2Q27 | AH1: 3Q27 | AI1: 4Q27 | AJ1: 2027 | AK1: 1Q28 | AL1: 2Q28 | AM1: 3Q28 | AN1: 4Q28 | AO1: 2028
A2: 가정 시계열 — 노란 셀은 추정 가정(모델값에서 역산), 연녹 셀은 3절 스칼라 참조 수식. 바꾸면 subQ·분기·연간예상·TP·시나리오가 재계산됩니다.
E3: 1 | F3: 2 | G3: 3 | H3: 4 | I3: 5 | J3: 6 | K3: 7 | L3: 8 | M3: 9 | N3: 10 | O3: 11 | P3: 12 | Q3: 13 | R3: 14 | S3: 15 | T3: 16 | U3: 17 | V3: 18 | W3: 19 | X3: 20 | Y3: 21 | Z3: 22 | AA3: 23 | AB3: 24 | AC3: 25 | AD3: 26 | AE3: 27 | AF3: 28 | AG3: 29 | AH3: 30 | AI3: 31 | AJ3: 32 | AK3: 33 | AL3: 34 | AM3: 35 | AN3: 36 | AO3: 37
E4: 2021.12 | F4: 2021.12A | G4: 2022.03 | H4: 2022.06 | I4: 2022.09 | J4: 2022.12 | K4: 2022.12A | L4: 2023.03 | M4: 2023.06 | N4: 2023.09 | O4: 2023.12 | P4: 2023.12A | Q4: 2024.03 | R4: 2024.06 | S4: 2024.09 | T4: 2024.12 | U4: 2024.12A | V4: 2025.03 | W4: 2025.06 | X4: 2025.09 | Y4: 2025.12 | Z4: 2025.12A | AA4: 2026.03 | AB4: 2026.06 | AC4: 2026.09 | AD4: 2026.12 | AE4: 2026.12A | AF4: 2027.03 | AG4: 2027.06 | AH4: 2027.09 | AI4: 2027.12 | AJ4: 2027.12A | AK4: 2028.03 | AL4: 2028.06 | AM4: 2028.09 | AN4: 2028.12 | AO4: 2028.12A
B5: 1. FX | C5: 이름: 환율
A6: USDKRW_avg | C6: 원/달러(평균) | E6: 1183.5 | F6: 1145.51 | G6: 1205.78 | H6: 1262.09 | I6: 1341.93 | J6: 1360.12 | K6: 1292.98 | L6: 1276.95 | M6: 1315.69 | N6: 1313.62 | O6: 1322.01 | P6: 1306.85 | Q6: 1330.14 | R6: 1371.28 | S6: 1356.22 | T6: 1396.3 | U6: 1363.53 | V6: 1452.28 | W6: 1398.52 | X6: 1386.95 | Y6: 1449.19 | Z6: 1421.52 | AA6: 1466.12 | AB6: 1501.75 | AC6: 1418.75 | AD6: 1343.39 | AE6: 1456.01 | AF6: 1341.45 | AG6: 1341.45 | AH6: 1341.45 | AI6: 1341.45 | AK6: 1341.45 | AL6: 1341.45 | AM6: 1341.45 | AN6: 1341.45
A7: USDKRW_end | C7: 원/달러(기말) | E7: 1188.75 | F7: 1188.75 | G7: 1213.74 | H7: 1301.24 | I7: 1436.9 | J7: 1260.16 | K7: 1260.16 | L7: 1305.99 | M7: 1321.44 | N7: 1345.35 | O7: 1297.43 | P7: 1297.43 | Q7: 1349.25 | R7: 1377.73 | S7: 1312.17 | T7: 1474.78 | U7: 1474.78 | V7: 1474.54 | W7: 1355.13 | X7: 1403.67 | Y7: 1444.2 | Z7: 1444.2 | AA7: 1524.8 | AB7: 1550.89 | AC7: 1355.4 | AD7: 1341.45 | AE7: 1341.45 | AF7: 1341.45 | AG7: 1341.45 | AH7: 1341.45 | AI7: 1341.45 | AK7: 1341.45 | AL7: 1341.45 | AM7: 1341.45 | AN7: 1341.45
A8: JPY100KRW_avg | C8: 원/100Y(평균) | E8: 1041.02 | F8: 1042.74 | G8: 1036.79 | H8: 972.23 | I8: 970.61 | J8: 961.03 | K8: 985.1 | L8: 964.89 | M8: 957.36 | N8: 909 | O8: 893.22 | P8: 931.11 | Q8: 896.29 | R8: 880.14 | S8: 909.35 | T8: 917.25 | U8: 900.92 | V8: 952.59 | W8: 967.92 | X8: 940.32 | Y8: 940.77 | Z8: 950.17 | AA8: 934.39 | AB8: 942.16 | AC8: 890.41 | AD8: 849.39 | AE8: 918.46 | AF8: 848.37 | AG8: 848.37 | AH8: 848.37 | AI8: 848.37 | AK8: 848.37 | AL8: 848.37 | AM8: 848.37 | AN8: 848.37
A9: JPY100KRW_end | C9: 원/100Y(기말) | E9: 1032.62 | F9: 1032.62 | G9: 996.83 | H9: 954.9 | I9: 993.29 | J9: 955.54 | K9: 955.54 | L9: 980.62 | M9: 913.67 | N9: 901.47 | O9: 917.04 | P9: 917.04 | Q9: 892.42 | R9: 857.76 | S9: 919.21 | T9: 939.65 | U9: 939.65 | V9: 986.84 | W9: 938.85 | X9: 948.49 | Y9: 921.81 | Z9: 921.81 | AA9: 955.99 | AB9: 954.75 | AC9: 863.31 | AD9: 848.37 | AE9: 848.37 | AF9: 848.37 | AG9: 848.37 | AH9: 848.37 | AI9: 848.37 | AK9: 848.37 | AL9: 848.37 | AM9: 848.37 | AN9: 848.37
A10: EURKRW_avg | C10: W/Euro(평균) | E10: 1353.32 | F10: 1354.06 | G10: 1352.29 | H10: 1343.31 | I10: 1350.63 | J10: 1386.07 | K10: 1358.07 | L10: 1369.93 | M10: 1432.41 | N10: 1429.41 | O10: 1420.91 | P10: 1412.88 | Q10: 1444.21 | R10: 1476.42 | S10: 1489.3 | T10: 1490.78 | U10: 1475.4 | V10: 1528.33 | W10: 1585.13 | X10: 1620.04 | Y10: 1686.02 | Z10: 1605.45 | AA10: 1715.47 | AB10: 1746.09 | AC10: 1631.97 | AD10: 1506.62 | AE10: 1688.01 | AF10: 1500.82 | AG10: 1500.82 | AH10: 1500.82 | AI10: 1500.82 | AK10: 1500.82 | AL10: 1500.82 | AM10: 1500.82 | AN10: 1500.82
A11: EURKRW_end | C11: W/Euro(기말) | E11: 1346.38 | F11: 1346.38 | G11: 1347.37 | H11: 1351.6 | I11: 1400.62 | J11: 1344.08 | K11: 1344.08 | L11: 1420.26 | M11: 1435.88 | N11: 1425.26 | O11: 1433.66 | P11: 1433.66 | Q11: 1458.68 | R11: 1474.86 | S11: 1469.1 | T11: 1532.14 | U11: 1532.14 | V11: 1594.72 | W11: 1588.22 | X11: 1648.04 | Y11: 1696.94 | Z11: 1696.94 | AA11: 1753.21 | AB11: 1767.09 | AC11: 1539.06 | AD11: 1500.82 | AE11: 1500.82 | AF11: 1500.82 | AG11: 1500.82 | AH11: 1500.82 | AI11: 1500.82 | AK11: 1500.82 | AL11: 1500.82 | AM11: 1500.82 | AN11: 1500.82
A12: CNYKRW_avg | C12: 원/중국원(평균) | E12: 185.14 | F12: 177.65 | G12: 189.93 | H12: 190.76 | I12: 195.79 | J12: 191.09 | K12: 191.93 | L12: 186.59 | M12: 187.45 | N12: 181.28 | O12: 182.86 | P12: 184.52 | Q12: 185.04 | R12: 189.35 | S12: 189.24 | T12: 194.24 | U12: 189.49 | V12: 199.63 | W12: 193.41 | X12: 193.79 | Y12: 204.38 | Z12: 197.8 | AA12: 211.75 | AB12: 220.8 | AC12: 210.43 | AD12: 200.49 | AE12: 213.61 | AF12: 200.4 | AG12: 200.4 | AH12: 200.4 | AI12: 200.4 | AK12: 200.4 | AL12: 200.4 | AM12: 200.4 | AN12: 200.4
A13: CNYKRW_end | C13: 원/중국원(기말) | E13: 187.13 | F13: 187.13 | G13: 191.38 | H13: 194.13 | I13: 201.92 | J13: 182.67 | K13: 182.67 | L13: 189.97 | M13: 181.8 | N13: 184.26 | O13: 182.61 | P13: 182.61 | Q13: 186.66 | R13: 189.7 | S13: 187.12 | T13: 202.04 | U13: 202.04 | V13: 203.3 | W13: 189.14 | X13: 197.16 | Y13: 206.28 | Z13: 206.28 | AA13: 220.97 | AB13: 228.56 | AC13: 202.16 | AD13: 200.4 | AE13: 200.4 | AF13: 200.4 | AG13: 200.4 | AH13: 200.4 | AI13: 200.4 | AK13: 200.4 | AL13: 200.4 | AM13: 200.4 | AN13: 200.4
B14: 1b. 종가
A15: price_close_end | C15: 종가(기말) | E15: 1860 | G15: 1772 | H15: 1212 | I15: 1119 | J15: 1130 | L15: 1297 | M15: 1487 | N15: 1443 | O15: 1492 | Q15: 1298 | R15: 1125 | W15: 1340 | X15: 1923 | Y15: 3480 | AA15: 3265 | AB15: 3640 | AC15: 3045 | AD15: 2680
A16: price_high | C16: 종가(최고) | E16: 2716 | G16: 2079 | H16: 1886 | I16: 1695 | J16: 1530 | L16: 1925 | M16: 1856 | N16: 2151 | O16: 1811 | Q16: 1518 | R16: 1320 | W16: 1370 | X16: 2190 | Y16: 4155 | AA16: 5000 | AB16: 7560 | AC16: 4005 | AD16: 3300
A17: price_low | C17: 종가(최저) | E17: 1662 | G17: 1579 | H17: 1075 | I17: 1075 | J17: 1033 | L17: 1118 | M17: 1245 | N17: 1294 | O17: 1241 | Q17: 1186 | R17: 1038 | W17: 936 | X17: 1261 | Y17: 1685 | AA17: 3075 | AB17: 3100 | AC17: 2160 | AD17: 2660
A18: price_avg | C18: 종가(평균) | E18: 2093.8 | G18: 1826.5 | H18: 1501 | I18: 1283.3 | J18: 1240.5 | L18: 1350.3 | M18: 1418.7 | N18: 1513.4 | O18: 1416.9 | Q18: 1431.9 | R18: 1236.6 | W18: 1080.4 | X18: 1781.7 | Y18: 2826.2 | AA18: 3846.3 | AB18: 5041.6 | AC18: 3053.3 | AD18: 3049.4
B20: 2. 추정 드라이버 | C20: 실적 열 = subQ 실현값(수식), 추정 열 = 가정(노란 = 모델값 역산, 연녹 = 3절 스칼라 참조)
A21: drv:매출액 | B21: yoy | C21: 매출액 YoY | J21: =IFERROR(subQ!J5/subQ!E5-1,"") | L21: =IFERROR(subQ!L5/subQ!G5-1,"") | M21: =IFERROR(subQ!M5/subQ!H5-1,"") | N21: =IFERROR(subQ!N5/subQ!I5-1,"") | O21: =IFERROR(subQ!O5/subQ!J5-1,"") | Q21: =IFERROR(subQ!Q5/subQ!L5-1,"") | R21: =IFERROR(subQ!R5/subQ!M5-1,"") | S21: =IFERROR(subQ!S5/subQ!N5-1,"") | T21: =IFERROR(subQ!T5/subQ!O5-1,"") | V21: =IFERROR(subQ!V5/subQ!Q5-1,"") | W21: =IFERROR(subQ!W5/subQ!R5-1,"") | X21: =IFERROR(subQ!X5/subQ!S5-1,"") | Y21: =IFERROR(subQ!Y5/subQ!T5-1,"") | AA21: =IFERROR(subQ!AA5/subQ!V5-1,"") | AB21: =IFERROR(subQ!AB5/subQ!W5-1,"") | AC21: 0.22160514 | AD21: 0.22158361 | AF21: 0.22160744 | AG21: 0.2215992 | AH21: 0.11077595 | AI21: 0.11078542 | AK21: 0.11074846 | AL21: 0.11078515 | AM21: 0.055402314 | AN21: 0.055416469
A22: drv:판관비 | B22: ratio | C22: 판관비율(/매출) | E22: =IFERROR(subQ!E8/subQ!E5,"") | F22: =IFERROR(subQ!F8/subQ!F5,"") | G22: =IFERROR(subQ!G8/subQ!G5,"") | H22: =IFERROR(subQ!H8/subQ!H5,"") | I22: =IFERROR(subQ!I8/subQ!I5,"") | J22: =IFERROR(subQ!J8/subQ!J5,"") | K22: =IFERROR(subQ!K8/subQ!K5,"") | L22: =IFERROR(subQ!L8/subQ!L5,"") | ... AB22: =IFERROR(subQ!AB8/subQ!AB5,"") | AC22: =$D$52 | AD22: =$D$52 | AE22: =IFERROR(subQ!AE8/subQ!AE5,"") | AF22: =$D$52 | AG22: =$D$52 | AH22: =$D$52 | AI22: =$D$52 | AJ22: =IFERROR(subQ!AJ8/subQ!AJ5,"") | AK22: =$D$52 | AL22: =$D$52 | AM22: =$D$52 | AN22: =$D$52 | AO22: =IFERROR(subQ!AO8/subQ!AO5,"")
A23: drv:영업이익 | B23: ratio | C23: 영업이익률(OPM) | E23: =IFERROR(subQ!E9/subQ!E5,"") | F23: =IFERROR(subQ!F9/subQ!F5,"") | G23: =IFERROR(subQ!G9/subQ!G5,"") | H23: =IFERROR(subQ!H9/subQ!H5,"") | I23: =IFERROR(subQ!I9/subQ!I5,"") | J23: =IFERROR(subQ!J9/subQ!J5,"") | K23: =IFERROR(subQ!K9/subQ!K5,"") | L23: =IFERROR(subQ!L9/subQ!L5,"") | ... AB23: =IFERROR(subQ!AB9/subQ!AB5,"") | AC23: 0.006365342 | AD23: 0.006388576 | AE23: =IFERROR(subQ!AE9/subQ!AE5,"") | AF23: 0.006379349 | AG23: 0.006372039 | AH23: 0.006372014 | AI23: 0.006360376 | AJ23: =IFERROR(subQ!AJ9/subQ!AJ5,"") | AK23: 0.00634433 | AL23: 0.006361287 | AM23: 0.006381944 | AN23: 0.006379023 | AO23: =IFERROR(subQ!AO9/subQ!AO5,"")
A24: drv:외환손익 | B24: abs | C24: 외환손익 (가정, 억원) | E24: =subQ!E13 | F24: =subQ!F13 | G24: =subQ!G13 | H24: =subQ!H13 | I24: =subQ!I13 | J24: =subQ!J13 | K24: =subQ!K13 | L24: =subQ!L13 | ... AB24: =subQ!AB13 | AC24: 0 | AD24: 0 | AE24: =subQ!AE13 | AF24: 0 | AG24: 0 | AH24: 0 | AI24: 0 | AJ24: =subQ!AJ13 | AK24: 0 | AL24: 0 | AM24: 0 | AN24: 0 | AO24: =subQ!AO13
A25: drv:파생상품손익 | B25: abs | C25: 파생상품손익 (가정, 억원) | E25: =subQ!E14 | F25: =subQ!F14 | G25: =subQ!G14 | H25: =subQ!H14 | I25: =subQ!I14 | J25: =subQ!J14 | K25: =subQ!K14 | L25: =subQ!L14 | ... AB25: =subQ!AB14 | AC25: 0 | AD25: 0 | AE25: =subQ!AE14 | AF25: 0 | AG25: 0 | AH25: 0 | AI25: 0 | AJ25: =subQ!AJ14 | AK25: 0 | AL25: 0 | AM25: 0 | AN25: 0 | AO25: =subQ!AO14
A26: drv:기타금융손익 | B26: abs | C26: 기타금융손익 (가정, 억원) | E26: =subQ!E15 | F26: =subQ!F15 | G26: =subQ!G15 | H26: =subQ!H15 | I26: =subQ!I15 | J26: =subQ!J15 | K26: =subQ!K15 | L26: =subQ!L15 | ... AB26: =subQ!AB15 | AC26: 0 | AD26: 0 | AE26: =subQ!AE15 | AF26: 0 | AG26: 0 | AH26: 0 | AI26: 0 | AJ26: =subQ!AJ15 | AK26: 0 | AL26: 0 | AM26: 0 | AN26: 0 | AO26: =subQ!AO15
A27: drv:기타영업외손익 | B27: abs | C27: 기타영업외손익 (가정, 억원) | E27: =subQ!E16 | F27: =subQ!F16 | G27: =subQ!G16 | H27: =subQ!H16 | I27: =subQ!I16 | J27: =subQ!J16 | K27: =subQ!K16 | L27: =subQ!L16 | ... AB27: =subQ!AB16 | AC27: 0 | AD27: 0 | AE27: =subQ!AE16 | AF27: 0 | AG27: 0 | AH27: 0 | AI27: 0 | AJ27: =subQ!AJ16 | AK27: 0 | AL27: 0 | AM27: 0 | AN27: 0 | AO27: =subQ!AO16
A28: drv:지분법손익 | B28: abs | C28: 지분법손익 (가정, 억원) | E28: =subQ!E17 | F28: =subQ!F17 | G28: =subQ!G17 | H28: =subQ!H17 | I28: =subQ!I17 | J28: =subQ!J17 | K28: =subQ!K17 | L28: =subQ!L17 | ... AB28: =subQ!AB17 | AC28: -3.98 | AD28: -3.98 | AE28: =subQ!AE17 | AF28: -3.98 | AG28: -3.98 | AH28: -3.98 | AI28: -3.98 | AJ28: =subQ!AJ17 | AK28: -3.98 | AL28: -3.98 | AM28: -3.98 | AN28: -3.98 | AO28: =subQ!AO17
A29: drv:법인세비용 | B29: ratio | C29: 법인세율(/세전) | E29: =IFERROR(subQ!E19/subQ!E18,"") | F29: =IFERROR(subQ!F19/subQ!F18,"") | G29: =IFERROR(subQ!G19/subQ!G18,"") | H29: =IFERROR(subQ!H19/subQ!H18,"") | I29: =IFERROR(subQ!I19/subQ!I18,"") | J29: =IFERROR(subQ!J19/subQ!J18,"") | K29: =IFERROR(subQ!K19/subQ!K18,"") | L29: =IFERROR(subQ!L19/subQ!L18,"") | ... AB29: =IFERROR(subQ!AB19/subQ!AB18,"") | AC29: 0 | AD29: 0 | AE29: =IFERROR(subQ!AE19/subQ!AE18,"") | AF29: 0 | AG29: 0 | AH29: 0 | AI29: 0 | AJ29: =IFERROR(subQ!AJ19/subQ!AJ18,"") | AK29: 0 | AL29: 0 | AM29: 0 | AN29: 0 | AO29: =IFERROR(subQ!AO19/subQ!AO18,"")
A30: drv:지배주주순이익 | B30: ratio | C30: 지배주주 비중(/당기순이익) | E30: =IFERROR(subQ!E21/subQ!E20,"") | F30: =IFERROR(subQ!F21/subQ!F20,"") | G30: =IFERROR(subQ!G21/subQ!G20,"") | H30: =IFERROR(subQ!H21/subQ!H20,"") | I30: =IFERROR(subQ!I21/subQ!I20,"") | J30: =IFERROR(subQ!J21/subQ!J20,"") | K30: =IFERROR(subQ!K21/subQ!K20,"") | L30: =IFERROR(subQ!L21/subQ!L20,"") | ... AB30: =IFERROR(subQ!AB21/subQ!AB20,"") | AC30: =$D$53 | AD30: =$D$53 | AE30: =IFERROR(subQ!AE21/subQ!AE20,"") | AF30: =$D$53 | AG30: =$D$53 | AH30: =$D$53 | AI30: =$D$53 | AJ30: =IFERROR(subQ!AJ21/subQ!AJ20,"") | AK30: =$D$53 | AL30: =$D$53 | AM30: =$D$53 | AN30: =$D$53 | AO30: =IFERROR(subQ!AO21/subQ!AO20,"")
A31: drv:부채총계 | B31: qoq | C31: 부채총계 QoQ | G31: =IFERROR(subQ!G23/subQ!E23-1,"") | H31: =IFERROR(subQ!H23/subQ!G23-1,"") | I31: =IFERROR(subQ!I23/subQ!H23-1,"") | J31: =IFERROR(subQ!J23/subQ!I23-1,"") | L31: =IFERROR(subQ!L23/subQ!J23-1,"") | M31: =IFERROR(subQ!M23/subQ!L23-1,"") | N31: =IFERROR(subQ!N23/subQ!M23-1,"") | O31: =IFERROR(subQ!O23/subQ!N23-1,"") | Q31: =IFERROR(subQ!Q23/subQ!O23-1,"") | R31: =IFERROR(subQ!R23/subQ!Q23-1,"") | S31: =IFERROR(subQ!S23/subQ!R23-1,"") | T31: =IFERROR(subQ!T23/subQ!S23-1,"") | V31: =IFERROR(subQ!V23/subQ!T23-1,"") | W31: =IFERROR(subQ!W23/subQ!V23-1,"") | X31: =IFERROR(subQ!X23/subQ!W23-1,"") | Y31: =IFERROR(subQ!Y23/subQ!X23-1,"") | AA31: =IFERROR(subQ!AA23/subQ!Y23-1,"") | AB31: =IFERROR(subQ!AB23/subQ!AA23-1,"") | AC31: 4.68e-07 | AD31: 0 | AF31: 0 | AG31: 0 | AH31: 0 | AI31: 0 | AK31: 0 | AL31: 0 | AM31: 0 | AN31: 0
A32: drv:자본총계 | B32: roll | C32: 자본총계 기타변동(배당 등, 억원) | G32: =IFERROR(subQ!E24+subQ!G20-subQ!G24,"") | H32: =IFERROR(subQ!G24+subQ!H20-subQ!H24,"") | I32: =IFERROR(subQ!H24+subQ!I20-subQ!I24,"") | J32: =IFERROR(subQ!I24+subQ!J20-subQ!J24,"") | L32: =IFERROR(subQ!J24+subQ!L20-subQ!L24,"") | M32: =IFERROR(subQ!L24+subQ!M20-subQ!M24,"") | N32: =IFERROR(subQ!M24+subQ!N20-subQ!N24,"") | O32: =IFERROR(subQ!N24+subQ!O20-subQ!O24,"") | Q32: =IFERROR(subQ!O24+subQ!Q20-subQ!Q24,"") | R32: =IFERROR(subQ!Q24+subQ!R20-subQ!R24,"") | S32: =IFERROR(subQ!R24+subQ!S20-subQ!S24,"") | T32: =IFERROR(subQ!S24+subQ!T20-subQ!T24,"") | V32: =IFERROR(subQ!T24+subQ!V20-subQ!V24,"") | W32: =IFERROR(subQ!V24+subQ!W20-subQ!W24,"") | X32: =IFERROR(subQ!W24+subQ!X20-subQ!X24,"") | Y32: =IFERROR(subQ!X24+subQ!Y20-subQ!Y24,"") | AA32: =IFERROR(subQ!Y24+subQ!AA20-subQ!AA24,"") | AB32: =IFERROR(subQ!AA24+subQ!AB20-subQ!AB24,"") | AC32: -0.001421295 | AD32: 0.005551683 | AF32: 0.003593538 | AG32: -0.002010082 | AH32: 0.007218436 | AI32: -0.00961031 | AK32: -0.001144482 | AL32: 0.00333665 | AM32: 0.003116466 | AN32: 0.006669175
A33: drv:지배주주지분 | B33: roll | C33: 지배주주지분 기타변동(배당 등, 억원) | G33: =IFERROR(subQ!E25+subQ!G21-subQ!G25,"") | H33: =IFERROR(subQ!G25+subQ!H21-subQ!H25,"") | I33: =IFERROR(subQ!H25+subQ!I21-subQ!I25,"") | J33: =IFERROR(subQ!I25+subQ!J21-subQ!J25,"") | L33: =IFERROR(subQ!J25+subQ!L21-subQ!L25,"") | M33: =IFERROR(subQ!L25+subQ!M21-subQ!M25,"") | N33: =IFERROR(subQ!M25+subQ!N21-subQ!N25,"") | O33: =IFERROR(subQ!N25+subQ!O21-subQ!O25,"") | Q33: =IFERROR(subQ!O25+subQ!Q21-subQ!Q25,"") | R33: =IFERROR(subQ!Q25+subQ!R21-subQ!R25,"") | S33: =IFERROR(subQ!R25+subQ!S21-subQ!S25,"") | T33: =IFERROR(subQ!S25+subQ!T21-subQ!T25,"") | V33: =IFERROR(subQ!T25+subQ!V21-subQ!V25,"") | W33: =IFERROR(subQ!V25+subQ!W21-subQ!W25,"") | X33: =IFERROR(subQ!W25+subQ!X21-subQ!X25,"") | Y33: =IFERROR(subQ!X25+subQ!Y21-subQ!Y25,"") | AA33: =IFERROR(subQ!Y25+subQ!AA21-subQ!AA25,"") | AB33: =IFERROR(subQ!AA25+subQ!AB21-subQ!AB25,"") | AC33: -0.005421295 | AD33: 0.005551683 | AF33: 0.003593538 | AG33: 0.007989918 | AH33: -0.002781564 | AI33: 0.00038969 | AK33: -0.001144482 | AL33: -0.00666335 | AM33: 0.013116466 | AN33: -0.003330825
A34: drv:총차입금 | B34: qoq | C34: 총차입금 QoQ | G34: =IFERROR(subQ!G26/subQ!E26-1,"") | H34: =IFERROR(subQ!H26/subQ!G26-1,"") | I34: =IFERROR(subQ!I26/subQ!H26-1,"") | J34: =IFERROR(subQ!J26/subQ!I26-1,"") | L34: =IFERROR(subQ!L26/subQ!J26-1,"") | M34: =IFERROR(subQ!M26/subQ!L26-1,"") | N34: =IFERROR(subQ!N26/subQ!M26-1,"") | O34: =IFERROR(subQ!O26/subQ!N26-1,"") | Q34: =IFERROR(subQ!Q26/subQ!O26-1,"") | R34: =IFERROR(subQ!R26/subQ!Q26-1,"") | S34: =IFERROR(subQ!S26/subQ!R26-1,"") | T34: =IFERROR(subQ!T26/subQ!S26-1,"") | V34: =IFERROR(subQ!V26/subQ!T26-1,"") | W34: =IFERROR(subQ!W26/subQ!V26-1,"") | X34: =IFERROR(subQ!X26/subQ!W26-1,"") | Y34: =IFERROR(subQ!Y26/subQ!X26-1,"") | AA34: =IFERROR(subQ!AA26/subQ!Y26-1,"") | AB34: =IFERROR(subQ!AB26/subQ!AA26-1,"") | AC34: 9.564e-06 | AD34: 0 | AF34: 0 | AG34: 0 | AH34: 0 | AI34: 0 | AK34: 0 | AL34: 0 | AM34: 0 | AN34: 0
A35: drv:순차입금 | B35: qoq | C35: 순차입금 QoQ | G35: =IFERROR(subQ!G27/subQ!E27-1,"") | H35: =IFERROR(subQ!H27/subQ!G27-1,"") | I35: =IFERROR(subQ!I27/subQ!H27-1,"") | J35: =IFERROR(subQ!J27/subQ!I27-1,"") | L35: =IFERROR(subQ!L27/subQ!J27-1,"") | M35: =IFERROR(subQ!M27/subQ!L27-1,"") | N35: =IFERROR(subQ!N27/subQ!M27-1,"") | O35: =IFERROR(subQ!O27/subQ!N27-1,"") | Q35: =IFERROR(subQ!Q27/subQ!O27-1,"") | R35: =IFERROR(subQ!R27/subQ!Q27-1,"") | S35: =IFERROR(subQ!S27/subQ!R27-1,"") | T35: =IFERROR(subQ!T27/subQ!S27-1,"") | V35: =IFERROR(subQ!V27/subQ!T27-1,"") | W35: =IFERROR(subQ!W27/subQ!V27-1,"") | X35: =IFERROR(subQ!X27/subQ!W27-1,"") | Y35: =IFERROR(subQ!Y27/subQ!X27-1,"") | AA35: =IFERROR(subQ!AA27/subQ!Y27-1,"") | AB35: =IFERROR(subQ!AB27/subQ!AA27-1,"") | AC35: 0.017396513 | AD35: 0.021236471 | AF35: 0.02424729 | AG35: 0.019244336 | AH35: 0.015227841 | AI35: 0.019241695 | AK35: 0.022408859 | AL35: 0.017301541 | AM35: 0.013898814 | AN35: 0.017796102
A36: drv:이자발생자산 | B36: qoq | C36: 이자발생자산 QoQ | G36: =IFERROR(subQ!G28/subQ!E28-1,"") | H36: =IFERROR(subQ!H28/subQ!G28-1,"") | I36: =IFERROR(subQ!I28/subQ!H28-1,"") | J36: =IFERROR(subQ!J28/subQ!I28-1,"") | L36: =IFERROR(subQ!L28/subQ!J28-1,"") | M36: =IFERROR(subQ!M28/subQ!L28-1,"") | N36: =IFERROR(subQ!N28/subQ!M28-1,"") | O36: =IFERROR(subQ!O28/subQ!N28-1,"") | Q36: =IFERROR(subQ!Q28/subQ!O28-1,"") | R36: =IFERROR(subQ!R28/subQ!Q28-1,"") | S36: =IFERROR(subQ!S28/subQ!R28-1,"") | T36: =IFERROR(subQ!T28/subQ!S28-1,"") | V36: =IFERROR(subQ!V28/subQ!T28-1,"") | W36: =IFERROR(subQ!W28/subQ!V28-1,"") | X36: =IFERROR(subQ!X28/subQ!W28-1,"") | Y36: =IFERROR(subQ!Y28/subQ!X28-1,"") | AA36: =IFERROR(subQ!AA28/subQ!Y28-1,"") | AB36: =IFERROR(subQ!AB28/subQ!AA28-1,"") | AC36: -0.024771238 | AD36: -0.031523856 | AF36: -0.037954003 | AG36: -0.032005225 | AH36: -0.026788124 | AI36: -0.035221521 | AK36: -0.043262666 | AL36: -0.03582964 | AM36: -0.030227485 | AN36: -0.0406491
A37: drv:현금및현금성자산 | B37: qoq | C37: 현금및현금성자산 QoQ | G37: =IFERROR(subQ!G29/subQ!E29-1,"") | H37: =IFERROR(subQ!H29/subQ!G29-1,"") | I37: =IFERROR(subQ!I29/subQ!H29-1,"") | J37: =IFERROR(subQ!J29/subQ!I29-1,"") | L37: =IFERROR(subQ!L29/subQ!J29-1,"") | M37: =IFERROR(subQ!M29/subQ!L29-1,"") | N37: =IFERROR(subQ!N29/subQ!M29-1,"") | O37: =IFERROR(subQ!O29/subQ!N29-1,"") | Q37: =IFERROR(subQ!Q29/subQ!O29-1,"") | R37: =IFERROR(subQ!R29/subQ!Q29-1,"") | S37: =IFERROR(subQ!S29/subQ!R29-1,"") | T37: =IFERROR(subQ!T29/subQ!S29-1,"") | V37: =IFERROR(subQ!V29/subQ!T29-1,"") | W37: =IFERROR(subQ!W29/subQ!V29-1,"") | X37: =IFERROR(subQ!X29/subQ!W29-1,"") | Y37: =IFERROR(subQ!Y29/subQ!X29-1,"") | AA37: =IFERROR(subQ!AA29/subQ!Y29-1,"") | AB37: =IFERROR(subQ!AB29/subQ!AA29-1,"")
A38: drv:CAPEX | B38: yoy | C38: CAPEX YoY | J38: =IFERROR(subQ!J30/subQ!E30-1,"") | L38: =IFERROR(subQ!L30/subQ!G30-1,"") | M38: =IFERROR(subQ!M30/subQ!H30-1,"") | N38: =IFERROR(subQ!N30/subQ!I30-1,"") | O38: =IFERROR(subQ!O30/subQ!J30-1,"") | Q38: =IFERROR(subQ!Q30/subQ!L30-1,"") | R38: =IFERROR(subQ!R30/subQ!M30-1,"") | S38: =IFERROR(subQ!S30/subQ!N30-1,"") | T38: =IFERROR(subQ!T30/subQ!O30-1,"") | V38: =IFERROR(subQ!V30/subQ!Q30-1,"") | W38: =IFERROR(subQ!W30/subQ!R30-1,"") | X38: =IFERROR(subQ!X30/subQ!S30-1,"") | Y38: =IFERROR(subQ!Y30/subQ!T30-1,"") | AA38: =IFERROR(subQ!AA30/subQ!V30-1,"") | AB38: =IFERROR(subQ!AB30/subQ!W30-1,"") | AC38: -0.64551414 | AD38: -0.39790881 | AF38: 1.9481858 | AG38: 5.5821725 | AH38: 0 | AI38: 0 | AK38: 0 | AL38: 0 | AM38: 0 | AN38: 0
A39: drv:영업활동현금흐름 | B39: yoy | C39: 영업활동현금흐름 YoY | J39: =IFERROR(subQ!J31/subQ!E31-1,"") | L39: =IFERROR(subQ!L31/subQ!G31-1,"") | M39: =IFERROR(subQ!M31/subQ!H31-1,"") | N39: =IFERROR(subQ!N31/subQ!I31-1,"") | O39: =IFERROR(subQ!O31/subQ!J31-1,"") | Q39: =IFERROR(subQ!Q31/subQ!L31-1,"") | R39: =IFERROR(subQ!R31/subQ!M31-1,"") | S39: =IFERROR(subQ!S31/subQ!N31-1,"") | T39: =IFERROR(subQ!T31/subQ!O31-1,"") | V39: =IFERROR(subQ!V31/subQ!Q31-1,"") | W39: =IFERROR(subQ!W31/subQ!R31-1,"") | X39: =IFERROR(subQ!X31/subQ!S31-1,"") | Y39: =IFERROR(subQ!Y31/subQ!T31-1,"") | AA39: =IFERROR(subQ!AA31/subQ!V31-1,"") | AB39: =IFERROR(subQ!AB31/subQ!W31-1,"")
A40: drv:주식수 | B40: qoq | C40: 주식수 QoQ | G40: =IFERROR(subQ!G32/subQ!E32-1,"") | H40: =IFERROR(subQ!H32/subQ!G32-1,"") | I40: =IFERROR(subQ!I32/subQ!H32-1,"") | J40: =IFERROR(subQ!J32/subQ!I32-1,"") | L40: =IFERROR(subQ!L32/subQ!J32-1,"") | M40: =IFERROR(subQ!M32/subQ!L32-1,"") | N40: =IFERROR(subQ!N32/subQ!M32-1,"") | O40: =IFERROR(subQ!O32/subQ!N32-1,"") | Q40: =IFERROR(subQ!Q32/subQ!O32-1,"") | R40: =IFERROR(subQ!R32/subQ!Q32-1,"") | S40: =IFERROR(subQ!S32/subQ!R32-1,"") | T40: =IFERROR(subQ!T32/subQ!S32-1,"") | V40: =IFERROR(subQ!V32/subQ!T32-1,"") | W40: =IFERROR(subQ!W32/subQ!V32-1,"") | X40: =IFERROR(subQ!X32/subQ!W32-1,"") | Y40: =IFERROR(subQ!Y32/subQ!X32-1,"") | AA40: =IFERROR(subQ!AA32/subQ!Y32-1,"") | AB40: =IFERROR(subQ!AB32/subQ!AA32-1,"") | AC40: 0 | AD40: 0 | AF40: 0 | AG40: 0 | AH40: 0 | AI40: 0 | AK40: 0 | AL40: 0 | AM40: 0 | AN40: 0
A41: drv:DPS | B41: abs | C41: DPS (가정, 원) | E41: =subQ!E36 | F41: =subQ!F36 | G41: =subQ!G36 | H41: =subQ!H36 | I41: =subQ!I36 | J41: =subQ!J36 | K41: =subQ!K36 | L41: =subQ!L36 | ... AB41: =subQ!AB36 | AD41: 0 | AE41: =subQ!AE36 | AI41: 0 | AJ41: =subQ!AJ36 | AN41: 0 | AO41: =subQ!AO36
B43: 3. 밸류에이션·스칼라 | C43: 노란 셀 = 가정. '연결' 표시는 추정 전 분기 수식이 이 셀을 참조한다는 뜻
A44: sc:종가 | C44: 종가 | D44: 2680 | E44: 원 — 네이버 정규장 종가(aik 확정종가 대조 · aik 2,850원)
A45: sc:기준일 | C45: 기준일 | D45: 20261014 | E45: 종가 기준일
A46: sc:COE | C46: COE | D46: 0.09 | E46: 자기자본비용(가정) — TP 적정 PBR = ROE/COE
A47: sc:PER_lo | C47: PER_lo | D47: 5 | E47: PER 밴드 하단(배) — hist_quarterly(분기 평균가 ÷ TTM EPS, 5분기, 25/50/75 백분위) · 캡 5~30배 적용(원값 1.9/17.9/23.2)
A48: sc:PER_mid | C48: PER_mid | D48: 17.9 | E48: PER 밴드 중단(배)
A49: sc:PER_hi | C49: PER_hi | D49: 23.2 | E49: PER 밴드 상단(배)
A50: sc:EPS_Y1가중 | C50: EPS_Y1가중 | D50: 0.5 | E50: 12M fwd EPS = FY(last_actual연도)E × w + FY+1E × (1−w) — 기준 분기 2Q 이면 0.5(가정)
A51: sc:세율 | C51: 세율 | D51: 0.22 | E51: 참고(연결 안 됨: MAX(세전,0)×단일 세율로 재현 불가(지주 자회사 합산 등) → 분기별 역산) — 모델 assumptions 값 · 최근 12분기 유효세율 -19.7% 가 5~27% 밖; 세전 > 0 분기 중위 -46.3% 도 5~27% 밖 → 법정세율 근사 22% 가정
A52: sc:판관비율 | C52: 판관비율 | D52: 0.12672256 | E52: 연결 — 판관비 = 매출액 × 판관비율(역산, 재현 오차 ≤ 0.05억 · 모델 assumptions 0.1267)
A53: sc:지배주주비중 | C53: 지배주주비중 | D53: 1 | E53: 연결 — 지배주주순이익 = 당기순이익 × 비중(역산, 재현 오차 ≤ 0.05억)
A54: sc:이자율_자산 | C54: 이자율_자산 | D54: 0.016956069 | E54: 연결 — 이자손익 = (전분기 이자발생자산 × 자산이자율 − 전분기 총차입금 × 부채이자율)/4(역산, 재현 오차 ≤ 0.05억 · 모델 assumptions 0.0171)
A55: sc:이자율_부채 | C55: 이자율_부채 | D55: 0.035223185 | E55: 연결 — 같은 수식의 부채 쪽(총차입금 행이 없으면 0)(역산, 재현 오차 ≤ 0.05억 · 모델 assumptions 0.0353)
A56: sc:배당성향 | C56: 배당성향 | D56: 0 | E56: 배당성향(참고 — 모델은 직전 DPS 유지·Q2 지급 가정)
A57: sc:외화순노출_백만$ | C57: 외화순노출_백만$ | E57: 외화 순노출 × Δ기말환율 (외화 시트 방식) — 외화 순노출 미공시(face) → 0 + 표기
A58: sc:헤지비율 | C58: 헤지비율 | E58: sls 없음
A59: sc:헤지환율_약정 | C59: 헤지환율_약정 | E59: sls 없음

Sheet BS연결
B1: (백만원) | C1: 이름: BS연결H | E1: 4Q21 | F1: 2021 | G1: 1Q22 | H1: 2Q22 | I1: 3Q22 | J1: 4Q22 | K1: 2022 | L1: 1Q23 | M1: 2Q23 | N1: 3Q23 | O1: 4Q23 | P1: 2023 | Q1: 1Q24 | R1: 2Q24 | S1: 3Q24 | T1: 4Q24 | U1: 2024 | V1: 1Q25 | W1: 2Q25 | X1: 3Q25 | Y1: 4Q25 | Z1: 2025 | AA1: 1Q26 | AB1: 2Q26 | AC1: 3Q26 | AD1: 4Q26 | AE1: 2026 | AF1: 1Q27 | AG1: 2Q27 | AH1: 3Q27 | AI1: 4Q27 | AJ1: 2027 | AK1: 1Q28 | AL1: 2Q28 | AM1: 3Q28 | AN1: 4Q28 | AO1: 2028
B2: 연결 | D2: fin json(kship_fin.py)
B3: 나노(연) | C3: UPDATE: 26-10-14 | E3: 1 | F3: 2 | G3: 3 | H3: 4 | I3: 5 | J3: 6 | K3: 7 | L3: 8 | M3: 9 | N3: 10 | O3: 11 | P3: 12 | Q3: 13 | R3: 14 | S3: 15 | T3: 16 | U3: 17 | V3: 18 | W3: 19 | X3: 20 | Y3: 21 | Z3: 22 | AA3: 23 | AB3: 24 | AC3: 25 | AD3: 26 | AE3: 27 | AF3: 28 | AG3: 29 | AH3: 30 | AI3: 31 | AJ3: 32 | AK3: 33 | AL3: 34 | AM3: 35 | AN3: 36 | AO3: 37
B4: Account Code | C4: AccountNAME | E4: 2021.12 | F4: 2021.12A | G4: 2022.03 | H4: 2022.06 | I4: 2022.09 | J4: 2022.12 | K4: 2022.12A | L4: 2023.03 | M4: 2023.06 | N4: 2023.09 | O4: 2023.12 | P4: 2023.12A | Q4: 2024.03 | R4: 2024.06 | S4: 2024.09 | T4: 2024.12 | U4: 2024.12A | V4: 2025.03 | W4: 2025.06 | X4: 2025.09 | Y4: 2025.12 | Z4: 2025.12A | AA4: 2026.03 | AB4: 2026.06 | AC4: 2026.09 | AD4: 2026.12 | AE4: 2026.12A | AF4: 2027.03 | AG4: 2027.06 | AH4: 2027.09 | AI4: 2027.12 | AJ4: 2027.12A | AK4: 2028.03 | AL4: 2028.06 | AM4: 2028.09 | AN4: 2028.12 | AO4: 2028.12A
A5: 1 | C5: 유동자산 | E5: 38107.93 | F5: 38107.93 | G5: 46979.15 | H5: 44990.71 | I5: 48326.25 | J5: 44789.52 | K5: 44789.52 | L5: 47782.65 | M5: 50014.48 | N5: 45592.34 | O5: 40389.85 | P5: 40389.85 | Q5: 47082.71 | R5: 51047.24 | S5: 50363.21 | T5: 57695.76 | U5: 57695.76 | V5: 54123.61 | W5: 57121.18 | X5: 46191.13 | Y5: 45833.72 | Z5: 45833.72 | AA5: 55112.26 | AB5: 54477.72
A6: 1 | C6: 현금및현금성자산 | E6: 4708.18 | F6: 4708.18 | G6: 8362.65 | H6: 5651.23 | I6: 8180.7 | J6: 11207.55 | K6: 11207.55 | L6: 6479.86 | M6: 9106.18 | N6: 4567.31 | O6: 8121.38 | P6: 8121.38 | Q6: 6239.84 | R6: 10080.39 | S6: 5269.31 | T6: 20758.41 | U6: 20758.41 | V6: 17012.76 | W6: 14376 | X6: 12655.87 | Y6: 13539.17 | Z6: 13539.17 | AA6: 4731.35 | AB6: 14184.69
A7: 1 | C7: 단기금융상품 | E7: 10010.19 | F7: 10010.19 | G7: 8514.68 | H7: 7029.23 | I7: 5800 | J7: 5800 | K7: 5800 | L7: 7800 | M7: 7800 | N7: 6300 | O7: 6300 | P7: 6300 | Q7: 5800 | R7: 5800 | S7: 9400 | T7: 2811.4 | U7: 2811.4 | V7: 2812.3 | W7: 2813.2 | X7: 2814.1 | Y7: 2815 | Z7: 2815 | AA7: 2620 | AB7: 2620
A8: 1 | C8: 단기금융자산 | E8: 10010.19 | F8: 10010.19 | G8: 8514.68 | H8: 7029.23 | I8: 6098.51 | J8: 5800 | K8: 5800 | L8: 7800 | M8: 7800 | N8: 6300 | O8: 6300 | P8: 6300 | Q8: 5800 | R8: 5800 | S8: 9400 | T8: 2811.4 | U8: 2811.4 | V8: 2812.3 | W8: 2813.2 | X8: 2814.1 | Y8: 2815 | Z8: 2815 | AA8: 2620 | AB8: 2620
A9: 1 | C9: 매출채권및기타채권 | E9: 7522.71 | F9: 7522.71 | G9: 4280.85 | H9: 10270.1 | I9: 14041.58 | J9: 8789.97 | K9: 8789.97 | L9: 6992.44 | M9: 10904.66 | N9: 9354.46 | O9: 5169.85 | P9: 5169.85 | Q9: 11727.15 | R9: 9019.52 | S9: 9958.97 | T9: 9591.55 | U9: 9591.55 | V9: 8513.4 | W9: 5783.09 | X9: 8802.26 | Y9: 8966.1 | Z9: 8966.1 | AA9: 18757.3 | AB9: 13495.95
A10: 1 | C10: 기타유동금융자산 | E10: 2680.06 | F10: 2680.06 | G10: 3622.82 | H10: 1690.91 | I10: 1018.01 | J10: 646.52 | K10: 646.52 | L10: 2435.33 | M10: 2154.23 | N10: 5603.06 | O10: 1122.9 | P10: 1122.9 | Q10: 1275.04 | R10: 1210.64 | S10: 1689.95 | T10: 4495.78 | U10: 4495.78 | V10: 1702.69 | W10: 2951.06 | X10: 1422.69 | Y10: 1741.92 | Z10: 1741.92 | AA10: 1487.43 | AB10: 1037.76
A11: 1 | C11: 기타유동자산 | E11: 2854.22 | F11: 2854.22 | G11: 4718.68 | H11: 4171.57 | I11: 4110.05 | J11: 2218.91 | K11: 2218.91 | L11: 2071.8 | M11: 2540.15 | N11: 3746.07 | O11: 1649.84 | P11: 1649.84 | Q11: 1515.74 | R11: 1749.61 | S11: 2295.51 | T11: 3600.4 | U11: 3600.4 | V11: 2240.39 | W11: 1502.87 | X11: 1796.94 | Y11: 4270.43 | Z11: 4270.43 | AA11: 3943.41 | AB11: 4361.01
A12: 1 | C12: 재고자산 | E12: 10312.98 | F12: 10312.98 | G12: 15859.15 | H12: 15856.23 | I12: 14737.94 | J12: 15771.71 | K12: 15771.71 | L12: 21606.47 | M12: 17141.99 | N12: 15110.46 | O12: 17114.2 | P12: 17114.2 | Q12: 19892.99 | R12: 22840.95 | S12: 21535.52 | T12: 16304.27 | U12: 16304.27 | V12: 21629.73 | W12: 29606.59 | X12: 18596.37 | Y12: 14389.76 | Z12: 14389.76 | AA12: 23451.17 | AB12: 18763.26
A13: 1 | C13: 당기법인세자산(선급법인세) | E13: 19.6 | F13: 19.6 | G13: 26.06 | H13: 11.67 | I13: 30.22 | J13: 41.8 | K13: 41.8 | L13: 52.96 | M13: 18.53 | N13: 43.21 | O13: 52.44 | P13: 52.44 | Q13: 122.71 | R13: 86.89 | S13: 104.71 | T13: 133.94 | U13: 133.94 | V13: 212.33 | W13: 88.37 | X13: 102.89 | Y13: 111.34 | Z13: 111.34 | AA13: 121.59 | AB13: 13.16
A14: 1 | C14: 비유동자산 | E14: 32955.73 | F14: 32955.73 | G14: 32935.3 | H14: 33848.38 | I14: 34736.97 | J14: 25135.22 | K14: 25135.22 | L14: 26271.06 | M14: 26863.92 | N14: 27127.01 | O14: 27395.17 | P14: 27395.17 | Q14: 27615.48 | R14: 29901.16 | S14: 28052.75 | T14: 28633.3 | U14: 28633.3 | V14: 32840.9 | W14: 38421.61 | X14: 47321.91 | Y14: 48410.52 | Z14: 48410.52 | AA14: 48116.73 | AB14: 48154.77
A15: 1 | C15: 장기금융자산 | E15: 0.6 | F15: 0.6 | G15: 1.5 | H15: 2.4 | I15: 3.3 | J15: 2402.94 | K15: 2402.94 | L15: 5.1 | M15: 6 | N15: 6.9 | O15: 2955.88 | P15: 2955.88 | Q15: 3185.15 | R15: 2822.91 | S15: 1430.86 | T15: 313.61 | U15: 313.61 | V15: 313.61 | W15: 313.61 | X15: 313.61 | Y15: 313.61 | Z15: 313.61 | AA15: 44.69 | AB15: 44.69
A16: 1 | C16: 투자자산 | E16: 103.75 | F16: 103.75 | G16: 22.94 | H16: 2.4 | I16: 3.3 | J16: 2402.94 | K16: 2402.94 | L16: 5.1 | M16: 6 | N16: 6.9 | O16: 2955.88 | P16: 2955.88 | Q16: 3185.15 | R16: 2822.91 | S16: 1430.86 | T16: 3466.05 | U16: 3466.05 | V16: 5301.48 | W16: 7814.08 | X16: 7773.2 | Y16: 8106.96 | Z16: 8106.96 | AA16: 7432.09 | AB16: 7175.86
A17: 1 | C17: 종속기업및관계기업투자 | E17: 103.15 | F17: 103.15 | G17: 21.44 | T17: 3152.44 | U17: 3152.44 | V17: 4987.87 | W17: 7500.47 | X17: 7459.59 | Y17: 7793.35 | Z17: 7793.35 | AA17: 7387.4 | AB17: 7131.17
A18: 1 | C18: 유형자산 | E18: 30042.22 | F18: 30042.22 | G18: 30194.03 | H18: 30117.83 | I18: 31196.11 | J18: 21717.25 | K18: 21717.25 | L18: 22637.85 | M18: 23368.82 | N18: 23521.34 | O18: 23373.09 | P18: 23373.09 | Q18: 23350.78 | R18: 23139.51 | S18: 22675.87 | T18: 22745.29 | U18: 22745.29 | V18: 25593.66 | W18: 28780.04 | X18: 37751.86 | Y18: 36775.1 | Z18: 36775.1 | AA18: 37066.83 | AB18: 37220.37
A19: 1 | C19: 사용권자산 | E19: 548.14 | F19: 548.14 | G19: 556.29 | H19: 500.43 | I19: 362.14 | J19: 337.3 | K19: 337.3 | L19: 357.64 | M19: 297.24 | N19: 429.08 | O19: 643.85 | P19: 643.85 | Q19: 659.69 | R19: 636.14 | S19: 644.89 | T19: 647.47 | U19: 647.47 | V19: 595.88 | W19: 596.59 | X19: 562.49 | Y19: 585.61 | Z19: 585.61 | AA19: 570.88 | AB19: 531.74
A20: 1 | C20: 기타비유동자산 | E20: 548.14 | F20: 548.14 | G20: 556.29 | H20: 500.43 | I20: 362.14 | J20: 337.3 | K20: 337.3 | L20: 357.64 | M20: 297.24 | N20: 429.08 | O20: 643.85 | P20: 643.85 | Q20: 659.69 | R20: 636.14 | S20: 644.89 | T20: 647.47 | U20: 647.47 | V20: 595.88 | W20: 596.59 | X20: 562.49 | Y20: 585.61 | Z20: 585.61 | AA20: 570.88 | AB20: 531.74
A21: 1 | C21: 무형자산 | E21: 284.66 | F21: 284.66 | G21: 260.38 | H21: 264.73 | I21: 239.04 | J21: 212.38 | K21: 212.38 | L21: 186.7 | M21: 160.55 | N21: 134.7 | O21: 108.74 | P21: 108.74 | Q21: 106.25 | R21: 103.7 | S21: 102.24 | T21: 100.78 | U21: 100.78 | V21: 99.32 | W21: 97.86 | X21: 96.4 | Y21: 94.94 | Z21: 94.94 | AA21: 146.1 | AB21: 145.25
A22: 1 | C22: 자산총계 | E22: 71063.65 | F22: 71063.65 | G22: 79914.45 | H22: 78839.09 | I22: 83063.22 | J22: 69924.74 | K22: 69924.74 | L22: 74053.71 | M22: 76878.4 | N22: 72719.35 | O22: 67785.02 | P22: 67785.02 | Q22: 74698.19 | R22: 80948.39 | S22: 78415.95 | T22: 86329.06 | U22: 86329.06 | V22: 86964.51 | W22: 95542.78 | X22: 93513.04 | Y22: 94244.24 | Z22: 94244.24 | AA22: 103228.99 | AB22: 102632.49
A23: 1 | C23: 유동부채 | E23: 34871.2 | F23: 34871.2 | G23: 43492.38 | H23: 42491.81 | I23: 46634.76 | J23: 67696.83 | K23: 67696.83 | L23: 47907.13 | M23: 45992.22 | N23: 40902.57 | O23: 64242.73 | P23: 64242.73 | Q23: 62541.13 | R23: 62609.49 | S23: 54749 | T23: 50959.95 | U23: 50959.95 | V23: 46851.51 | W23: 52966.3 | X23: 36566.45 | Y23: 39227.81 | Z23: 39227.81 | AA23: 50154.15 | AB23: 49130.91
A24: 1 | C24: 계약부채 | E24: 5024.35 | F24: 5024.35 | G24: 10094.44 | H24: 8816.62 | I24: 8183.98 | J24: 14787.93 | K24: 14787.93 | L24: 13532.69 | M24: 15325.87 | N24: 7886.78 | O24: 6128.25 | P24: 6128.25 | Q24: 7721.45 | R24: 14629.97 | S24: 6730.12 | T24: 14535.32 | U24: 14535.32 | V24: 14727.76 | W24: 20869.32 | X24: 5689.24 | Y24: 6472.55 | Z24: 6472.55 | AA24: 13965.44 | AB24: 5789.66
A25: 1 | C25: 단기파생상품부채 | E25: 2923.34 | F25: 2923.34 | G25: 2923.34 | H25: 2288.79 | I25: 2434.71 | J25: 15593.14 | K25: 15593.14 | L25: 749.21 | M25: 177.05 | O25: 15027.28 | P25: 15027.28 | Q25: 7288.71 | R25: 10001.96 | S25: 10001.96 | T25: 238.23 | U25: 238.23
A26: 1 | C26: 단기금융부채 | E26: 3090.73 | F26: 3090.73 | G26: 3092.85 | H26: 2450.19 | I26: 2556.97 | J26: 15730.14 | K26: 15730.14 | L26: 918.3 | M26: 296.67 | N26: 147.56 | O26: 15215.82 | P26: 15215.82 | Q26: 7481.08 | R26: 10190.33 | S26: 10187.4 | T26: 238.23 | U26: 238.23
A27: 1 | C27: 단기차입금 | E27: 13322.01 | F27: 13322.01 | G27: 13110.32 | H27: 12857.34 | I27: 12344.14 | J27: 12547.3 | K27: 12547.3 | L27: 13155.73 | M27: 13505.59 | N27: 16550.35 | O27: 16466.51 | P27: 16466.51 | Q27: 18109.59 | R27: 16597.89 | S27: 16574.74 | T27: 16645.76 | U27: 16645.76 | V27: 16651.18 | W27: 16848.08 | X27: 17547.66 | Y27: 17650.88 | Z27: 17650.88 | AA27: 18632.1 | AB27: 26539.61
A28: 1 | C28: 유동성장기부채 | E28: 4904.52 | F28: 4904.52 | G28: 4746.66 | H28: 4593.83 | I28: 4472.92 | J28: 2812.11 | K28: 2812.11 | L28: 1640.97 | M28: 532.18 | N28: 260 | O28: 260 | P28: 260 | Q28: 260 | R28: 260 | S28: 695 | T28: 630 | U28: 630 | V28: 565 | W28: 585 | X28: 670 | Y28: 840 | Z28: 840 | AA28: 840 | AB28: 840
A29: 1 | C29: 유동리스부채 | E29: 167.39 | F29: 167.39 | G29: 169.51 | H29: 161.4 | I29: 122.26 | J29: 137 | K29: 137 | L29: 169.09 | M29: 119.62 | N29: 147.56 | O29: 188.54 | P29: 188.54 | Q29: 192.37 | R29: 188.37 | S29: 185.44
A30: 1 | C30: 리스부채 | E30: 547.93 | F30: 547.93 | G30: 555.9 | H30: 503.38 | I30: 361.45 | J30: 337.69 | K30: 337.69 | L30: 353.87 | M30: 276.74 | N30: 432.35 | O30: 590.02 | P30: 590.02 | Q30: 604.33 | R30: 583.77 | S30: 578.06
A31: 1 | C31: 기타유동부채 | E31: 396.24 | F31: 396.24 | G31: 356.49 | H31: 383.91 | I31: 430.67 | J31: 455.48 | K31: 455.48 | L31: 651.91 | M31: 256.53 | N31: 290.07 | O31: 242.43 | P31: 242.43 | Q31: 276.96 | R31: 313.55 | S31: 378.6 | T31: 491.53 | U31: 491.53 | V31: 390.68 | W31: 291.32 | X31: 360.64 | Y31: 541.07 | Z31: 541.07 | AA31: 438.81 | AB31: 375.4
A32: 1 | C32: 비유동부채 | E32: 1359.68 | F32: 1359.68 | G32: 1301.66 | H32: 1211.08 | I32: 1048.04 | J32: 961.53 | K32: 961.53 | L32: 1780.61 | M32: 2487.95 | N32: 2602.92 | O32: 2943.1 | P32: 2943.1 | Q32: 2980.92 | R32: 2977.59 | S32: 4062.05 | T32: 4656.68 | U32: 4656.68 | V32: 4115.57 | W32: 4035.02 | X32: 12882.58 | Y32: 15131.96 | Z32: 15131.96 | AA32: 15085.2 | AB32: 14978.06
A33: 1 | C33: 장기차입금 | E33: 650 | F33: 650 | G33: 585 | H33: 520 | I33: 455 | J33: 390 | K33: 390 | L33: 1225 | M33: 1960 | N33: 1895 | O33: 1830 | P33: 1830 | Q33: 1765 | R33: 1700 | S33: 2700 | T33: 2575 | U33: 2575 | V33: 2450 | W33: 2240 | X33: 10990 | Y33: 13735 | Z33: 13735 | AA33: 13610 | AB33: 13400
A34: 1 | C34: 비유동리스부채 | E34: 380.54 | F34: 380.54 | G34: 386.39 | H34: 341.98 | I34: 239.19 | J34: 200.69 | K34: 200.69 | L34: 184.78 | M34: 157.12 | N34: 284.79 | O34: 401.48 | P34: 401.48 | Q34: 411.96 | R34: 395.4 | S34: 392.62
A35: 1 | C35: 장기금융부채 | E35: 709.68 | F35: 709.68 | G35: 716.67 | H35: 691.08 | I35: 593.03 | J35: 200.69 | K35: 200.69 | L35: 555.62 | M35: 527.96 | N35: 284.79 | O35: 401.48 | P35: 401.48 | Q35: 411.96 | R35: 395.4 | S35: 392.62
A36: 1 | C36: 기타비유동금융부채 | E36: 329.14 | F36: 329.14 | G36: 330.28 | H36: 349.1 | I36: 353.84 | L36: 370.84 | M36: 370.84
A37: 1 | C37: 부채총계 | E37: 36230.87 | F37: 36230.87 | G37: 44794.05 | H37: 43702.88 | I37: 47682.79 | J37: 68658.36 | K37: 68658.36 | L37: 49687.75 | M37: 48480.17 | N37: 43505.49 | O37: 67185.83 | P37: 67185.83 | Q37: 65522.05 | R37: 65587.08 | S37: 58811.05 | T37: 55616.63 | U37: 55616.63 | V37: 50967.08 | W37: 57001.32 | X37: 49449.03 | Y37: 54359.77 | Z37: 54359.77 | AA37: 65239.35 | AB37: 64108.97
A38: 1 | C38: 지배주주지분 | E38: 31490 | F38: 31490 | G38: 31796.8 | H38: 31870.39 | I38: 32188.04 | J38: 625.93 | K38: 625.93 | L38: 23960.02 | M38: 28203.33 | N38: 29102.58 | O38: 525.28 | P38: 525.28 | Q38: 9204.62 | R38: 15545.29 | S38: 19958.81 | T38: 31269.06 | U38: 31269.06 | V38: 36719.1 | W38: 39379.29 | X38: 45126.04 | Y38: 42706.28 | Z38: 42706.28 | AA38: 40370.85 | AB38: 41131.13
A39: 1 | C39: 자본금 | E39: 13533.85 | F39: 13533.85 | G39: 13533.85 | H39: 13533.85 | I39: 13709.29 | J39: 13709.29 | K39: 13709.29 | L39: 14551.05 | M39: 15259.42 | N39: 15420.41 | O39: 15420.41 | P39: 15420.41 | Q39: 15420.41 | R39: 15420.41 | S39: 15420.41 | T39: 15420.41 | U39: 15420.41 | V39: 15420.41 | W39: 15420.41 | X39: 15420.41 | Y39: 15420.41 | Z39: 15420.41 | AA39: 15420.41 | AB39: 15420.41
A40: 1 | C40: 자본잉여금 | E40: 24957.45 | F40: 24957.45 | G40: 24957.45 | H40: 24957.45 | I40: 25223.52 | J40: 25268.31 | K40: 25268.31 | L40: 26435.55 | M40: 27488.31 | N40: 27786.55 | O40: 28574.59 | P40: 28574.59 | Q40: 28574.59 | R40: 28574.59 | S40: 28574.59 | T40: 28574.59 | U40: 28574.59 | V40: 28574.59 | W40: 28574.59 | X40: 28574.59 | Y40: 28574.59 | Z40: 28574.59 | AA40: 23877.13 | AB40: 23877.13
A41: 1 | C41: 기타자본 | E41: -2601.22 | F41: -2601.22 | G41: -2986.22 | H41: -2986.22 | I41: -2986.22 | J41: -2601.22 | K41: -2601.22 | L41: -2601.22 | M41: -2601.22 | N41: -2601.22 | O41: -2601.22 | P41: -2601.22 | Q41: -2601.22 | R41: -2601.22 | S41: -2601.22 | T41: -2601.22 | U41: -2601.22 | V41: -2601.22 | W41: -2601.22 | X41: -2601.22 | Y41: -2601.22 | Z41: -2601.22 | AA41: -4615.15 | AB41: -4615.15
A42: 1 | C42: 기타포괄이익누계액 | E42: 1537.69 | F42: 1537.69 | G42: 1686.47 | H42: 1954.87 | I42: 2689.24 | J42: 2323.17 | K42: 2323.17 | L42: 2333.18 | M42: 2582.22 | N42: 2884.89 | O42: 2757.45 | P42: 2757.45 | Q42: 2767.97 | R42: 2880.2 | S42: 3253.66 | T42: 3639.28 | U42: 3639.28 | V42: 5548.68 | W42: 6794.66 | X42: 7201.13 | Y42: 7480.12 | Z42: 7480.12 | AA42: 6867.11 | AB42: 7120.29
A43: 1 | C43: 이익잉여금 | E43: -5937.78 | F43: -5937.78 | G43: -5394.75 | H43: -5589.56 | I43: -6447.79 | J43: -38073.62 | K43: -38073.62 | L43: -16758.54 | M43: -14525.41 | N43: -14388.06 | O43: -43625.96 | P43: -43625.96 | Q43: -34957.14 | R43: -28728.7 | S43: -24688.64 | T43: -13764.01 | U43: -13764.01 | V43: -10223.37 | W43: -8809.16 | X43: -3468.89 | Y43: -6167.64 | Z43: -6167.64 | AA43: -1178.65 | AB43: -671.56
A44: 1 | C44: 비지배주주지분 | E44: 3342.78 | F44: 3342.78 | G44: 3323.6 | H44: 3265.81 | I44: 3192.39 | J44: 640.45 | K44: 640.45 | L44: 405.94 | M44: 194.89 | N44: 111.28 | O44: 73.91 | P44: 73.91 | Q44: -28.49 | R44: -183.98 | S44: -353.91 | T44: -556.63 | U44: -556.63 | V44: -721.67 | W44: -837.83 | X44: -1062.03 | Y44: -2821.81 | Z44: -2821.81 | AA44: -2381.22 | AB44: -2607.61
A45: 1 | C45: 자본총계 | E45: 34832.78 | F45: 34832.78 | G45: 35120.4 | H45: 35136.2 | I45: 35380.42 | J45: 1266.38 | K45: 1266.38 | L45: 24365.97 | M45: 28398.22 | N45: 29213.85 | O45: 599.19 | P45: 599.19 | Q45: 9176.13 | R45: 15361.31 | S45: 19604.9 | T45: 30712.43 | U45: 30712.43 | V45: 35997.43 | W45: 38541.46 | X45: 44064.01 | Y45: 39884.47 | Z45: 39884.47 | AA45: 37989.64 | AB45: 38523.53
A46: 1 | C46: 부채와자본총계 | E46: 71063.65 | F46: 71063.65 | G46: 79914.45 | H46: 78839.09 | I46: 83063.22 | J46: 69924.74 | K46: 69924.74 | L46: 74053.71 | M46: 76878.4 | N46: 72719.35 | O46: 67785.02 | P46: 67785.02 | Q46: 74698.19 | R46: 80948.39 | S46: 78415.95 | T46: 86329.06 | U46: 86329.06 | V46: 86964.51 | W46: 95542.78 | X46: 93513.04 | Y46: 94244.24 | Z46: 94244.24 | AA46: 103228.99 | AB46: 102632.49
A47: 1 | C47: 총차입금 | E47: 24876.53 | F47: 24876.53 | G47: 22604.76 | H47: 22305 | I47: 21484.98 | J47: 15749.41 | K47: 15749.41 | L47: 17402.67 | M47: 16269.95 | N47: 18705.35 | O47: 18556.51 | P47: 18556.51 | Q47: 20134.59 | R47: 18557.89 | S47: 19969.74 | T47: 19850.76 | U47: 19850.76 | V47: 19666.18 | W47: 19673.08 | X47: 29207.66 | Y47: 32225.88 | Z47: 32225.88 | AA47: 33082.1 | AB47: 40779.61
A48: 1 | C48: 순차입금 | E48: 10158.16 | F48: 10158.16 | G48: 5727.43 | H48: 9624.54 | I48: 7205.77 | J48: -1258.14 | K48: -1258.14 | L48: 3122.81 | M48: -636.23 | N48: 7838.04 | O48: 4135.13 | P48: 4135.13 | Q48: 8094.75 | R48: 2677.5 | S48: 5300.43 | T48: -3719.05 | U48: -3719.05 | V48: -158.88 | W48: 2483.88 | X48: 13737.69 | Y48: 15871.71 | Z48: 15871.71 | AA48: 25730.75 | AB48: 23974.92
A49: 1 | C49: 이자발생자산 | E49: 14718.97 | F49: 14718.97 | G49: 16878.83 | H49: 12682.86 | I49: 14282.51 | J49: 19410.49 | K49: 19410.49 | L49: 14284.96 | M49: 16912.18 | N49: 10874.21 | O49: 17377.26 | P49: 17377.26 | Q49: 15224.99 | R49: 18703.3 | S49: 16100.17 | T49: 23883.42 | U49: 23883.42 | V49: 20138.67 | W49: 17502.81 | X49: 15783.58 | Y49: 16667.78 | Z49: 16667.78 | AA49: 7396.04 | AB49: 16849.38
A50: 1 | C50: 사채 | E50: 6000 | F50: 6000 | G50: 4162.78 | H50: 4333.83 | I50: 4212.92 | L50: 1380.97 | M50: 272.18
A51: 1 | C51: 계약자산 | G51: 1594.26 | H51: 309.76 | I51: 109.24 | J51: 313.07 | K51: 313.07 | L51: 343.78 | M51: 348.74 | N51: 867.77 | O51: 859.24 | P51: 859.24 | Q51: 509.24 | R51: 259.24 | S51: 109.24 | AB51: 1.89
A52: 1 | C52: 유동파생상품자산 | I52: 298.51
A53: 1 | C53: 단기금융부채(face) | J53: 12547.3 | K53: 12547.3 | N53: 16550.35 | O53: 16466.51 | P53: 16466.51 | Q53: 18109.59 | R53: 16597.89
A54: 1 | C54: 단기충당부채 | J54: 56.89 | K54: 56.89 | L54: 40.25 | M54: 39.75 | N54: 39.73 | O54: 39.58 | P54: 39.58 | Q54: 19.71 | R54: 19.71 | S54: 19.71 | T54: 6.37 | U54: 6.37 | V54: 6.37
A55: 1 | C55: 기타비유동부채 | J55: 370.84 | K55: 370.84 | N55: 370.84 | O55: 370.84 | P55: 370.84 | Q55: 370.84 | R55: 370.84 | S55: 369.89 | T55: 369.89 | U55: 369.89 | V55: 369.89 | W55: 369.89 | X55: 369.89 | Y55: 441.81 | Z55: 441.81 | AA55: 441.81 | AB55: 441.81
A56: 1 | C56: 확정급여부채 | N56: 52.3 | O56: 340.78 | P56: 340.78 | Q56: 433.13 | R56: 511.36 | S56: 599.55 | T56: 1333.81 | U56: 1333.81 | V56: 954.26 | W56: 1068.2 | X56: 1195.76 | Y56: 608.12 | Z56: 608.12 | AA56: 717.63 | AB56: 845.98
A57: 1 | C57: 이연법인세자산 | R57: 2885.28 | S57: 2885.28 | T57: 1447.56 | U57: 1447.56 | V57: 1014.51 | W57: 898.96 | X57: 899.52 | Y57: 2603.36 | Z57: 2603.36 | AA57: 2652.47 | AB57: 2830.3
A58: 1 | C58: 당기법인세부채(미지급법인세) | Y58: 3.39 | Z58: 3.39 | AA58: 23.74 | AB58: 33.96
A59: 1 | C59: 매출액(수익) | E59: 18006.47 | G59: 10997.85 | H59: 20502.96 | I59: 22292.65 | J59: 12885.4 | K59: 66678.86 | L59: 17642.43 | M59: 26481.14 | N59: 23263.3 | O59: 20689.57 | P59: 88076.44 | Q59: 18757.1 | R59: 22949.24 | S59: 25843.64 | T59: 21050.55 | U59: 88600.53 | V59: 13661.87 | W59: 15765.96 | X59: 34465.31 | Y59: 21783.2 | Z59: 85676.34 | AA59: 11035.46 | AB59: 25950.41
A60: 1 | C60: 매출원가 | E60: 15910.13 | G60: 8997.92 | H60: 18790.25 | I60: 20572.95 | J60: 11875.82 | K60: 60236.94 | L60: 17512.74 | M60: 22090.94 | N60: 20092.9 | O60: 17311.88 | P60: 77008.46 | Q60: 15565.71 | R60: 18267.13 | S60: 23119.3 | T60: 19919.07 | U60: 76871.21 | V60: 10386.57 | W60: 12806.14 | X60: 26660.2 | Y60: 18456.28 | Z60: 68309.19 | AA60: 9022.9 | AB60: 22447.46
A61: 1 | C61: 판관비 | E61: 1694.73 | G61: 1611.69 | H61: 2448.3 | I61: 2783.1 | J61: 3123.31 | K61: 9966.4 | L61: 2154.72 | M61: 2451.48 | N61: 2592.9 | O61: 2246.09 | P61: 9445.19 | Q61: 2325.84 | R61: 2316.19 | S61: 2204.52 | T61: 3225.17 | U61: 10071.72 | V61: 3538.91 | W61: 2945.21 | X61: 2287.23 | Y61: 3069.42 | Z61: 11840.77 | AA61: 2901.66 | AB61: 2920.43
A62: 1 | C62: 영업이익 | E62: 401.62 | G62: 388.24 | H62: -735.58 | I62: -1063.4 | J62: -2113.73 | K62: -3524.47 | L62: -2025.03 | M62: 1938.72 | N62: 577.49 | O62: 1131.6 | P62: 1622.78 | Q62: 865.55 | R62: 2365.92 | S62: 519.82 | T62: -2093.69 | U62: 1657.6 | V62: -263.61 | W62: 14.61 | X62: 5517.88 | Y62: 257.5 | Z62: 5526.38 | AA62: -889.09 | AB62: 582.53
A63: 1 | C63: 기타영업외수익 | E63: 18.82 | G63: 10.4 | H63: 22.88 | I63: 74.41 | J63: 44.16 | K63: 151.85 | L63: 47.74 | M63: 15.57 | N63: 24.92 | O63: 108.73 | P63: 196.96 | Q63: 84.1 | R63: 103.94 | S63: 178.68 | T63: 22028.5 | U63: 22395.22 | V63: 36.03 | W63: 1261.27 | X63: 22.98 | Y63: 1637.86 | Z63: 2958.14 | AA63: 78.81 | AB63: 174.53
A64: 1 | C64: 기타영업외비용 | E64: 2108.3 | G64: 24.95 | H64: 82.41 | I64: 43.5 | J64: 8102.7 | K64: 8253.56 | L64: 79.13 | M64: 60.9 | N64: 422.71 | O64: 102.31 | P64: 665.05 | Q64: 58.27 | R64: 60.96 | S64: -33.05 | T64: 239.6 | U64: 325.78 | V64: 103.03 | W64: 114.87 | X64: 310.3 | Y64: 5620.47 | Z64: 6148.67 | AA64: 34.36 | AB64: 97.38
A65: 1 | C65: 금융수익 | E65: 218.96 | G65: 236.34 | H65: 965.75 | I65: 659.69 | J65: 5029.45 | K65: 6891.23 | L65: 438.92 | M65: 537.73 | N65: 249.61 | O65: 261.4 | P65: 1487.66 | Q65: 339.68 | R65: 3836.25 | S65: 3470.18 | T65: 15451.16 | U65: 23097.27 | V65: 4154.68 | W65: 218.63 | X65: 288.69 | Y65: 256.57 | Z65: 4918.57 | AA65: 499.13 | AB65: 677.71
A66: 1 | C66: 금융비용 | E66: 1177.99 | G66: 456.24 | H66: 447.86 | I66: 653.99 | J66: 9335.44 | K66: 10893.53 | L66: 766.59 | M66: 402.48 | N66: 371.28 | O66: 2880.55 | P66: 4420.9 | Q66: 403.83 | R66: 3264.31 | S66: 333.56 | T66: -1544.61 | U66: 2457.09 | V66: 324.73 | W66: 463.35 | X66: 286.77 | Y66: 453.6 | Z66: 1528.45 | AA66: 345.29 | AB66: 703.28
A67: 1 | C67: 법인세비용차감전계속사업이익 | E67: -4885.73 | G67: 72.08 | H67: -298.67 | I67: -1026.78 | J67: -14478.25 | K67: -15731.62 | L67: -2384.1 | M67: 2028.63 | N67: 58.04 | O67: -5581.14 | P67: -5878.57 | Q67: 827.23 | R67: 3190.84 | S67: 3868.18 | T67: 20646.06 | U67: 28532.31 | AB67: 261.95
A68: 1 | C68: 계속사업이익 | E68: -4885.73 | G68: 72.08 | H68: -298.67 | I68: -1026.78 | J68: -14478.25 | K68: -15731.62 | L68: -2384.1 | M68: 2028.63 | N68: 58.04 | O68: -5581.14 | P68: -5878.57 | Q68: 827.23 | R68: 6076.12 | S68: 3868.18 | T68: 19037.56 | U68: 29809.09 | V68: 3378.7 | W68: 1247.4 | X68: 5154.15 | Y68: -4927.96 | Z68: 4852.29 | AA68: -1119.51 | AB68: 383.36
A69: 1 | C69: 당기순이익 | E69: -4885.73 | G69: 72.08 | H69: -298.67 | I69: -1026.78 | J69: -14478.25 | K69: -15731.62 | L69: -2384.1 | M69: 2028.63 | N69: 58.04 | O69: -5581.14 | P69: -5878.57 | Q69: 827.23 | R69: 6076.12 | S69: 3868.18 | T69: 19037.56 | U69: 29809.09 | V69: 3378.7 | W69: 1247.4 | X69: 5154.15 | Y69: -4927.96 | Z69: 4852.29 | AA69: -1119.51 | AB69: 383.36
A70: 1 | C70: 매출총이익 | E70: 2096.34 | G70: 1999.93 | H70: 1712.71 | I70: 1719.7 | J70: 1009.58 | K70: 6441.92 | L70: 129.69 | M70: 4390.2 | N70: 3170.4 | O70: 3377.69 | P70: 11067.98 | Q70: 3191.39 | R70: 4682.11 | S70: 2724.34 | T70: 1131.49 | U70: 11729.33 | V70: 3275.3 | W70: 2959.83 | X70: 7805.11 | Y70: 3326.92 | Z70: 17367.16 | AA70: 2012.56 | AB70: 3502.95
A71: 1 | C71: 금융손익 | E71: -959.03 | G71: -219.9 | H71: 517.89 | I71: 5.7 | J71: -4305.99 | K71: -4002.3 | L71: -327.67 | M71: 135.25 | N71: -121.67 | O71: -2619.15 | P71: -2933.24 | Q71: -64.15 | R71: 571.94 | S71: 3136.62 | T71: 16995.77 | U71: 20640.18 | V71: 3829.95 | W71: -244.72 | X71: 1.92 | Y71: -197.03 | Z71: 3390.12 | AA71: 153.84 | AB71: -25.57
A72: 1 | C72: 기타영업외손익 | E72: -2089.48 | G72: -14.55 | H72: -59.53 | I72: 30.91 | J72: -8058.54 | K72: -8101.71 | L72: -31.39 | M72: -45.33 | N72: -397.79 | O72: 6.42 | P72: -468.09 | Q72: 25.83 | R72: 42.98 | S72: 211.73 | T72: 21788.9 | U72: 22069.44 | V72: -67 | W72: 1146.4 | X72: -287.32 | Y72: -3982.61 | Z72: -3190.53 | AA72: 44.45 | AB72: 77.15
A73: 1 | C73: (지배주주지분)당기순이익 | E73: -4885.73 | G73: 72.08 | H73: -194.81 | I73: -842.78 | J73: -14860.99 | K73: -15826.5 | L73: -2127.23 | M73: 2233.13 | N73: 58.04 | O73: -5581.14 | P73: -5417.2 | Q73: 930.25 | R73: 6228.44 | S73: 4040.06 | T73: 18610.35 | U73: 29809.1 | V73: 3378.7 | W73: 1247.4 | X73: 5154.15 | Y73: -4927.96 | Z73: 4852.29 | AA73: -1119.51 | AB73: 507.1
A74: 1 | C74: 총포괄손익 | G74: 287.62 | H74: 15.8 | I74: -172.35 | J74: -15068.23 | K74: -14937.16 | L74: -2351.72 | M74: 2271.12 | N74: 356.4 | O74: -5960.4 | P74: -5684.6 | Q74: 838.37 | R74: 6185.18 | S74: 4243.59 | T74: 18846.1 | U74: 30113.24 | V74: 5285 | W74: 2544.03 | X74: 6384.04 | Y74: -4179.54 | Z74: 10033.53 | AA74: -1894.83 | AB74: 533.89
A75: 1 | C75: 이자수익 | G75: 54.62 | H75: 61.48 | I75: 64.3 | J75: 136.96 | K75: 317.36 | L75: 111.63 | M75: 169.54 | N75: 211.65 | O75: 118.83 | P75: 611.65 | Q75: 178.9 | R75: 148.04 | S75: 16 | T75: 183.89 | U75: 526.83 | V75: 149.04 | W75: 87.17 | X75: 59.57 | Y75: 81.75 | Z75: 377.53 | AA75: 60.5 | AB75: 40.49
A76: 1 | C76: 이자비용 | G76: 280.1 | H76: 295.48 | I76: 226.42 | J76: 659.83 | K76: 1461.83 | L76: 284.09 | M76: 219.94 | N76: 207.44 | O76: 257.24 | P76: 968.71 | Q76: 202.27 | R76: 227.24 | S76: 261.75 | T76: 198.7 | U76: 889.96 | V76: 235.43 | W76: 232.67 | X76: 231.7 | Y76: 265.78 | Z76: 965.58 | AA76: 125.14 | AB76: 570.17
A77: 1 | C77: 외환차익 | G77: 36.03 | H77: 102.93 | I77: 103.31 | J77: 264.9 | K77: 507.17 | L77: 61.44 | M77: 242.65 | N77: 173.31 | O77: 68.53 | P77: 545.93 | Q77: 55.22 | R77: 93.99 | S77: 47.62 | T77: 96.75 | U77: 293.58 | V77: 118.15 | W77: 277.29 | X77: 215.14 | Y77: 284.35 | Z77: 894.93 | AA77: 101.64 | AB77: 133.77
A78: 1 | C78: 외환차손 | G78: 48.17 | H78: 38.5 | I78: 105.35 | J78: 247.22 | K78: 439.24 | L78: 171.18 | M78: 269.76 | N78: 76.28 | O78: 92.98 | P78: 610.2 | Q78: 87.85 | R78: 173.77 | S78: 60.73 | T78: 59.25 | U78: 381.6 | V78: 66.28 | W78: 79.19 | X78: 86.81 | Y78: 118.55 | Z78: 350.83 | AA78: 81.14 | AB78: 215.62
A79: 1 | C79: 외화환산이익 | G79: 73.17 | H79: 90.94 | I79: 232.9 | J79: -94.06 | K79: 302.95 | L79: 207.56 | M79: 70.27 | N79: -182.27 | O79: 34.58 | P79: 130.14 | Q79: 105.56 | R79: 113.73 | S79: -73.92 | T79: 305.2 | U79: 450.57 | V79: 263.63 | W79: -145.82 | X79: 13.97 | Y79: -109.51 | Z79: 22.27 | AA79: 128.46 | AB79: 483.45
A80: 1 | C80: 외화환산손실 | G80: 4.88 | H80: 44.19 | I80: 59.07 | J80: 174.52 | K80: 282.66 | L80: 227.23 | M80: -187.15 | N80: -13.55 | O80: 14.75 | P80: 41.28 | Q80: 86.04 | R80: 0.49 | S80: -1.29 | T80: 228.72 | U80: 313.96 | V80: 23.02 | W80: 151.07 | X80: -31.74 | Y80: 69.27 | Z80: 211.62 | AA80: 139.01 | AB80: -82.51
A81: 1 | C81: 이자손익 | G81: -225.48 | H81: -234 | I81: -162.12 | J81: -522.87 | K81: -1144.47 | L81: -172.46 | M81: -50.4 | N81: 4.21 | O81: -138.41 | P81: -357.06 | Q81: -23.37 | R81: -79.2 | S81: -245.75 | T81: -14.81 | U81: -363.13 | V81: -86.39 | W81: -145.5 | X81: -172.13 | Y81: -184.03 | Z81: -588.05 | AA81: -64.64 | AB81: -529.68
A82: 1 | C82: (비지배주주지분)당기순이익 | H82: -103.86 | I82: -184 | L82: -256.87 | M82: -204.5 | Q82: -103.01 | R82: -152.32 | S82: -171.88 | AB82: -123.74
A83: 1 | C83: 파생상품이익 | I83: 198.7 | J83: -76.3 | V83: 238.22 | W83: 0 | X83: 0 | Y83: 0 | Z83: 238.22
A84: 1 | C84: 파생상품손실 | J84: 8019.27 | N84: 0 | O84: 1696.81 | S84: 0 | T84: -2636.98
A85: 1 | C85: 법인세비용 | R85: -2885.28 | T85: 1608.49 | V85: -43.92 | W85: 69.79 | X85: 18.26 | Y85: -1848.5 | Z85: -1804.37 | AA85: 4.21 | AB85: -121.41
A86: 1 | C86: 종속기업,공동지배기업및관계기업관련손익 | V86: -164.57 | W86: 400.88 | X86: -60.06 | Y86: -2854.34 | Z86: -2678.09 | AA86: -424.49 | AB86: -372.15
A87: 1 | C87: 지분법관련손익 | V87: -164.57 | W87: 400.88 | X87: -60.06 | Y87: -2854.34 | Z87: -2678.09 | AA87: -424.49 | AB87: -372.15
A88: 1 | C88: 영업활동으로인한현금흐름 | E88: 810.53 | G88: 3154.82 | H88: -4431.43 | I88: 3693.42 | J88: 3473.02 | K88: 5889.83 | L88: -3184.9 | M88: 4526.1 | N88: -5155.29 | O88: 4031.33 | P88: 217.24 | Q88: -3872.3 | R88: 5427.95 | S88: -2287.41 | T88: 8842.36 | U88: 8110.6 | V88: -3499.89 | W88: 151.74 | X88: -2243.19 | Y88: 5725.73 | Z88: 134.39 | AA88: -10365.18 | AB88: 3300.29
A89: 1 | C89: 법인세납부(CF) | E89: -3.78 | G89: -6.46 | H89: 14.39 | I89: -18.55 | J89: -11.58 | K89: -22.2 | L89: -11.17 | M89: 34.43 | N89: -24.68 | O89: -9.23 | P89: -10.65 | Q89: -70.26 | R89: 35.81 | S89: -17.81 | T89: -29.24 | U89: -81.5 | V89: -78.39 | W89: 123.96 | X89: -14.52 | Y89: -8.44 | Z89: 22.61 | AA89: -10.25 | AB89: 92.31
A90: 1 | C90: 투자활동으로인한현금흐름 | E90: -717.84 | G90: 1158.55 | H90: 2214.34 | I90: 243.79 | J90: -119.73 | K90: 3496.95 | L90: -3539.52 | M90: -1739.39 | N90: -2358.91 | O90: -488.16 | P90: -8125.98 | Q90: 278.45 | R90: 465.46 | S90: -3349.36 | T90: 7803.17 | U90: 5197.72 | V90: 525.03 | W90: -4125.64 | X90: -10623.36 | Y90: -4445.63 | Z90: -18669.6 | AA90: -198.46 | AB90: -463.92
A91: 1 | C91: 유형자산의증가 | E91: 540.61 | G91: 373.44 | H91: 300.08 | I91: 1008.02 | J91: 203.22 | K91: 1884.76 | L91: 1038.62 | M91: 1438.49 | N91: 731.39 | O91: 464.6 | P91: 3673.1 | Q91: 298.74 | R91: 133.64 | S91: 83.46 | T91: 201.66 | U91: 717.5 | V91: 927.16 | W91: 4089.43 | X91: 9317.72 | Y91: 5485.88 | Z91: 19820.19 | AA91: 1069.01 | AB91: 500.68
A92: 1 | C92: CAPEX | E92: 540.61 | G92: 373.44 | H92: 329.28 | I92: 1008.02 | J92: 203.22 | K92: 1913.96 | L92: 1038.62 | M92: 1438.49 | N92: 731.39 | O92: 464.6 | P92: 3673.1 | Q92: 298.74 | R92: 133.64 | S92: 83.46 | T92: 201.66 | U92: 717.5 | V92: 927.16 | W92: 4089.43 | X92: 9317.72 | Y92: 5485.88 | Z92: 19820.19 | AA92: 1120.35 | AB92: 501.81
A93: 1 | C93: 재무활동으로인한현금흐름 | E93: -516.09 | G93: -387.74 | H93: -758.35 | I93: -723.85 | J93: -1513.76 | K93: -3383.7 | L93: 1279.51 | M93: 1153.31 | N93: 2894.21 | O93: -238.85 | P93: 5088.18 | Q93: 190.35 | R93: -1750.97 | S93: 1355.98 | T93: -351.54 | U93: -556.18 | V93: -247.34 | W93: 115.84 | X93: 10644.52 | Y93: 1505.63 | Z93: 12018.65 | AA93: 543.22 | AB93: 7614.73
A94: 1 | C94: 단기차입금의감소 | E94: 80.9 | I94: 602.88 | J94: 37.89 | N94: -0.4 | O94: 36.73 | Q94: 498.31 | R94: 827.47 | S94: 5.97 | T94: 106.17 | U94: 1437.92 | X94: -0.22 | Y94: 0.46
A95: 1 | C95: 유동성장기부채의감소 | E95: 388.88 | G95: 388.88 | H95: 388.88 | I95: 65 | J95: 65 | K95: 907.76 | L95: 65 | M95: 65 | N95: 65 | O95: 65 | P95: 260 | Q95: 65 | R95: 65 | S95: 65 | T95: 190 | U95: 385 | V95: 190 | W95: 190 | X95: 125 | Y95: 125 | Z95: 630 | AA95: 125 | AB95: 210
A96: 1 | C96: 리스부채의상환 | E96: 57.07 | I96: 60.72 | J96: 47.87 | L96: 55.49 | M96: 44.33 | N96: 41.19 | O96: 137.13 | P96: 278.14 | S96: 72.11 | T96: 56.31 | V96: 57.34 | W96: 54.84 | X96: 73.9 | Y96: 125.71 | Z96: 311.79 | AA96: 131.78
A97: 1 | C97: 현금및현금성자산의증감 | E97: -423.4 | G97: 3925.63 | H97: -2975.44 | I97: 3213.36 | J97: 1839.54 | K97: 6003.09 | L97: -5444.91 | M97: 3940.02 | N97: -4620 | O97: 3304.32 | P97: -2820.57 | Q97: -3403.51 | R97: 4142.46 | S97: -4280.8 | T97: 16293.98 | U97: 12752.13 | V97: -3222.2 | W97: -3858.07 | X97: -2222.02 | Y97: 2785.73 | Z97: -6516.56 | AA97: -10020.43 | AB97: 10451.1
A98: 1 | C98: 기말현금및현금성자산 | E98: -174.43 | G98: 8362.65 | H98: -2711.42 | I98: 2529.47 | J98: 3026.85 | K98: 11207.55 | L98: 6479.86 | M98: 2626.32 | N98: -4538.87 | O98: 3554.07 | P98: 8121.38 | Q98: 6239.84 | R98: 3840.55 | S98: -4811.08 | T98: 15489.1 | U98: 20758.41 | V98: 17012.76 | W98: -2636.76 | X98: -1720.13 | Y98: 883.3 | Z98: 13539.17 | AA98: 4731.35 | AB98: 9453.34
A99: 1 | C99: 유형자산의감소 | G99: 1.05 | H99: 0 | I99: 0 | J99: 1.69 | K99: 2.74 | V99: 1.5 | W99: 0 | X99: 0 | Y99: 0 | Z99: 1.5
A100: 1 | C100: 무형자산의증가 | I100: 0 | J100: 0 | AA100: 51.34 | AB100: 1.13
...

Sheet BS별도
B1: (백만원) | C1: 이름: BS별도H | E1: 4Q21 | F1: 2021 | G1: 1Q22 | H1: 2Q22 | I1: 3Q22 | J1: 4Q22 | K1: 2022 | L1: 1Q23 | M1: 2Q23 | N1: 3Q23 | O1: 4Q23 | P1: 2023 | Q1: 1Q24 | R1: 2Q24 | S1: 3Q24 | T1: 4Q24 | U1: 2024 | V1: 1Q25 | W1: 2Q25 | X1: 3Q25 | Y1: 4Q25 | Z1: 2025 | AA1: 1Q26 | AB1: 2Q26 | AC1: 3Q26 | AD1: 4Q26 | AE1: 2026 | AF1: 1Q27 | AG1: 2Q27 | AH1: 3Q27 | AI1: 4Q27 | AJ1: 2027 | AK1: 1Q28 | AL1: 2Q28 | AM1: 3Q28 | AN1: 4Q28 | AO1: 2028
B2: 별도 | D2: fin json(kship_fin.py)
B3: 나노(별) | C3: UPDATE: 26-10-14 | E3: 1 | F3: 2 | G3: 3 | H3: 4 | I3: 5 | J3: 6 | K3: 7 | L3: 8 | M3: 9 | N3: 10 | O3: 11 | P3: 12 | Q3: 13 | R3: 14 | S3: 15 | T3: 16 | U3: 17 | V3: 18 | W3: 19 | X3: 20 | Y3: 21 | Z3: 22 | AA3: 23 | AB3: 24 | AC3: 25 | AD3: 26 | AE3: 27 | AF3: 28 | AG3: 29 | AH3: 30 | AI3: 31 | AJ3: 32 | AK3: 33 | AL3: 34 | AM3: 35 | AN3: 36 | AO3: 37
B4: Account Code | C4: AccountNAME | E4: 2021.12 | F4: 2021.12A | G4: 2022.03 | H4: 2022.06 | I4: 2022.09 | J4: 2022.12 | K4: 2022.12A | L4: 2023.03 | M4: 2023.06 | N4: 2023.09 | O4: 2023.12 | P4: 2023.12A | Q4: 2024.03 | R4: 2024.06 | S4: 2024.09 | T4: 2024.12 | U4: 2024.12A | V4: 2025.03 | W4: 2025.06 | X4: 2025.09 | Y4: 2025.12 | Z4: 2025.12A | AA4: 2026.03 | AB4: 2026.06 | AC4: 2026.09 | AD4: 2026.12 | AE4: 2026.12A | AF4: 2027.03 | AG4: 2027.06 | AH4: 2027.09 | AI4: 2027.12 | AJ4: 2027.12A | AK4: 2028.03 | AL4: 2028.06 | AM4: 2028.09 | AN4: 2028.12 | AO4: 2028.12A
A5: 1 | C5: 유동자산 | E5: 30900.66 | F5: 30900.66 | G5: 40515.02 | H5: 35695.16 | I5: 35126.14 | J5: 37431.81 | K5: 37431.81 | L5: 40900 | M5: 43160.42 | N5: 37337.57 | O5: 39829 | P5: 39829 | Q5: 44617.5 | R5: 48513.25 | S5: 43301.55 | T5: 51569.14 | U5: 51569.14 | V5: 48008.57 | W5: 50979.46 | X5: 41102.54 | Y5: 36530.2 | Z5: 36530.2 | AA5: 46299.88 | AB5: 44064.14
A6: 1 | C6: 현금및현금성자산 | E6: 4255.53 | F6: 4255.53 | G6: 8173.6 | H6: 5382.14 | I6: 7754.5 | J6: 10791.43 | K6: 10791.43 | L6: 5756.94 | M6: 7876.26 | N6: 3633.18 | O6: 7957.13 | P6: 7957.13 | Q6: 5831.42 | R6: 9730.15 | S6: 4837.41 | T6: 20256.12 | U6: 20256.12 | V6: 16618.2 | W6: 13999.18 | X6: 11646.56 | Y6: 13023.23 | Z6: 13023.23 | AA6: 4292.47 | AB6: 13403.77
A7: 1 | C7: 단기금융상품 | E7: 10010.19 | F7: 10010.19 | G7: 8514.68 | H7: 7029.23 | I7: 5800 | J7: 5800 | K7: 5800 | L7: 7800 | M7: 7800 | N7: 6300 | O7: 6300 | P7: 6300 | Q7: 5800 | R7: 5800 | S7: 9400 | T7: 2811.4 | U7: 2811.4 | V7: 2812.3 | W7: 2813.2 | X7: 2814.1 | Y7: 2815 | Z7: 2815 | AA7: 2620 | AB7: 2620
A8: 1 | C8: 단기금융자산 | E8: 10010.19 | F8: 10010.19 | G8: 8514.68 | H8: 7029.23 | I8: 6098.51 | J8: 5800 | K8: 5800 | L8: 7800 | M8: 7800 | N8: 6300 | O8: 6300 | P8: 6300 | Q8: 5800 | R8: 5800 | S8: 9400 | T8: 2811.4 | U8: 2811.4 | V8: 2812.3 | W8: 2813.2 | X8: 2814.1 | Y8: 2815 | Z8: 2815 | AA8: 2620 | AB8: 2620
A9: 1 | C9: 매출채권및기타채권 | E9: 3804.03 | F9: 3804.03 | G9: 2340.5 | H9: 5992.84 | I9: 5114.07 | J9: 4035.99 | K9: 4035.99 | L9: 3429.74 | M9: 6757.22 | N9: 5315.72 | O9: 3612.89 | P9: 3612.89 | Q9: 8003.3 | R9: 6797.24 | S9: 3556.65 | T9: 7363.24 | U9: 7363.24 | V9: 4715.69 | W9: 2795.19 | X9: 5517.99 | Y9: 5015.35 | Z9: 5015.35 | AA9: 11518.85 | AB9: 6508.74
A10: 1 | C10: 기타유동금융자산 | E10: 2129.58 | F10: 2129.58 | G10: 2867.49 | H10: 639.17 | I10: 481.33 | J10: 182.86 | K10: 182.86 | L10: 1294.86 | M10: 1552.34 | N10: 4964.46 | O10: 4524.61 | P10: 4524.61 | Q10: 4543.42 | R10: 3834.83 | S10: 4425.99 | T10: 3965.01 | U10: 3965.01 | V10: 840.65 | W10: 883.92 | X10: 1179.23 | Y10: 988.64 | Z10: 988.64 | AA10: 418.46 | AB10: 475.28
A11: 1 | C11: 기타유동자산 | E11: 2772.5 | F11: 2772.5 | G11: 3329.47 | H11: 2954.66 | I11: 3801.61 | J11: 2182.62 | K11: 2182.62 | L11: 2076.94 | M11: 2439.42 | N11: 2424.01 | O11: 1620.29 | P11: 1620.29 | Q11: 1428.24 | R11: 1668.7 | S11: 1643.71 | T11: 1564.66 | U11: 1564.66 | V11: 1784.87 | W11: 1311.57 | X11: 1877.02 | Y11: 1026.38 | Z11: 1026.38 | AA11: 5154.53 | AB11: 4130.14
A12: 1 | C12: 재고자산 | E12: 7910.91 | F12: 7910.91 | G12: 13670.64 | H12: 13375.69 | I12: 11736.74 | J12: 14087.97 | K12: 14087.97 | L12: 20148.69 | M12: 16367.91 | N12: 13789.22 | O12: 14902.41 | P12: 14902.41 | Q12: 18379.19 | R12: 20336.22 | S12: 19224.06 | T12: 15474.77 | U12: 15474.77 | V12: 21024.54 | W12: 29088.04 | X12: 17964.81 | Y12: 13550.27 | Z12: 13550.27 | AA12: 22174.05 | AB12: 16911.17
A13: 1 | C13: 당기법인세자산(선급법인세) | E13: 17.92 | F13: 17.92 | G13: 24.38 | H13: 11.66 | I13: 30.16 | J13: 37.88 | K13: 37.88 | L13: 49.04 | M13: 18.53 | N13: 43.21 | O13: 52.43 | P13: 52.43 | Q13: 122.7 | R13: 86.89 | S13: 104.5 | T13: 133.94 | U13: 133.94 | V13: 212.32 | W13: 88.37 | X13: 102.83 | Y13: 111.33 | Z13: 111.33 | AA13: 121.53 | AB13: 13.16
A14: 1 | C14: 비유동자산 | E14: 27330.58 | F14: 27330.58 | G14: 27068.17 | H14: 27627.46 | I14: 27986.3 | J14: 19527.66 | K14: 19527.66 | L14: 20581.94 | M14: 21759.43 | N14: 21969.23 | O14: 20218.18 | P14: 20218.18 | Q14: 20454.12 | R14: 23194.76 | S14: 22394.22 | T14: 19894.71 | U14: 19894.71 | V14: 24494.69 | W14: 28239.63 | X14: 36358.94 | Y14: 51553.56 | Z14: 51553.56 | AA14: 53603.38 | AB14: 49338.43
A15: 1 | C15: 장기금융자산 | E15: 0.6 | F15: 0.6 | G15: 1.5 | H15: 2.4 | I15: 3.3 | J15: 2353.49 | K15: 2353.49 | L15: 5.1 | M15: 6 | N15: 6.9 | O15: 2955.88 | P15: 2955.88 | Q15: 3185.15 | R15: 2822.91 | S15: 1430.86 | T15: 313.61 | U15: 313.61 | V15: 313.61 | W15: 313.61 | X15: 313.61 | Y15: 313.61 | Z15: 313.61 | AA15: 44.69 | AB15: 44.69
A16: 1 | C16: 투자자산 | E16: 10773.97 | F16: 10773.97 | G16: 10774.87 | H16: 10437.86 | I16: 10438.76 | J16: 4578.25 | K16: 4578.25 | L16: 2229.86 | M16: 2230.76 | N16: 2231.66 | O16: 3186.53 | P16: 3186.53 | Q16: 3415.8 | R16: 3443.56 | S16: 2809.37 | T16: 2392.12 | U16: 2392.12 | V16: 4392.12 | W16: 4392.12 | X16: 5670.92 | Y16: 14052.2 | Z16: 14052.2 | AA16: 15881.28 | AB16: 11515.97
... A23: 1 | C23: 유동부채 | E23: 28007.53 | F23: 28007.53 | G23: 37101.91 | H23: 32862.38 | I23: 32257.91 | J23: 57749.8 | K23: 57749.8 | L23: 36851.01 | M23: 35117.66 | N23: 28393.93 | O23: 55214.37 | P23: 55214.37 | Q23: 51294.27 | R23: 52286.02 | S23: 40491.94 | T23: 42132.97 | U23: 42132.97 | V23: 37207.09 | W23: 43292.75 | X23: 26884.07 | Y23: 24871.1 | Z23: 24871.1 | AA23: 37372.45 | AB23: 35595.4
A24: 1 | C24: 매입채무및기타채무 | E24: 3979.75 | F24: 3979.75 | G24: 8709.89 | H24: 6509.3 | I24: 8462.32 | J24: 9133.55 | K24: 9133.55 | L24: 13830.78 | M24: 10762.18 | N24: 8824.04 | O24: 10647.42 | P24: 10647.42 | Q24: 12006.45 | R24: 7041.46 | S24: 6157.08
A25: 1 | C25: 계약부채 | E25: 5015.57 | F25: 5015.57 | G25: 9879.49 | H25: 8725.85 | I25: 6802.91 | J25: 10331.9 | K25: 10331.9 | L25: 9590.71 | M25: 12260.37 | N25: 5007.16 | O25: 4916.03 | P25: 4916.03 | Q25: 7397.34 | R25: 14126.73 | S25: 6201.22 | T25: 14174.48 | U25: 14174.48 | V25: 14219.11 | W25: 20460.05 | X25: 5307.65 | Y25: 2406.41 | Z25: 2406.41 | AA25: 11200.17 | AB25: 3621.19
A26: 1 | C26: 단기파생상품부채 | E26: 2923.34 | F26: 2923.34 | G26: 2923.34 | H26: 2288.79 | I26: 2434.71 | J26: 15593.14 | K26: 15593.14 | L26: 749.21 | M26: 177.05 | O26: 15027.28 | P26: 15027.28 | Q26: 7288.71 | R26: 10001.96 | S26: 10001.96 | T26: 238.23 | U26: 238.23
A27: 1 | C27: 단기금융부채 | E27: 2985.45 | F27: 2985.45 | G27: 2985.45 | H27: 2349.03 | I27: 2493.5 | J27: 15649.18 | K27: 15649.18 | L27: 800.83 | M27: 224.25 | N27: 44.21 | O27: 15074.81 | P27: 15074.81 | Q27: 7336.24 | R27: 10052.31 | S27: 10047.21 | T27: 238.23 | U27: 238.23
A28: 1 | C28: 단기차입금 | E28: 10360.48 | F28: 10360.48 | G28: 10089 | H28: 10089 | I28: 9489 | J28: 9989 | K28: 9989 | L28: 10489 | M28: 10989 | N28: 13989 | O28: 13989 | P28: 13989 | Q28: 13989 | R28: 13989 | S28: 13989 | T28: 13989 | U28: 13989 | V28: 13989 | W28: 14389 | X28: 14989 | Y28: 14989 | Z28: 14989 | AA28: 15789 | AB28: 23589
A29: 1 | C29: 유동성장기부채 | E29: 4904.52 | F29: 4904.52 | G29: 4746.66 | H29: 4593.83 | I29: 4472.92 | J29: 2812.11 | K29: 2812.11 | L29: 1640.97 | M29: 532.18 | N29: 260 | O29: 260 | P29: 260 | Q29: 260 | R29: 260 | S29: 695 | T29: 630 | U29: 630 | V29: 565 | W29: 585 | X29: 670 | Y29: 840 | Z29: 840 | AA29: 840 | AB29: 840
A30: 1 | C30: 유동리스부채 | E30: 62.11 | F30: 62.11 | G30: 62.11 | H30: 60.24 | I30: 58.79 | J30: 56.04 | K30: 56.04 | L30: 51.62 | M30: 47.2 | N30: 44.21 | O30: 47.53 | P30: 47.53 | Q30: 47.53 | R30: 50.35 | S30: 45.25
A31: 1 | C31: 리스부채 | E31: 152.89 | F31: 152.89 | G31: 152.89 | H31: 140.65 | I31: 126.49 | J31: 112.21 | K31: 112.21 | L31: 97.76 | M31: 83.24 | N31: 70.06 | O31: 63.1 | P31: 63.1 | Q31: 63.1 | R31: 93.19 | S31: 100.18
A32: 1 | C32: 기타유동부채 | E32: 97.6 | F32: 97.6 | G32: 109.65 | H32: 79.48 | I32: 82.25 | J32: 46.1 | K32: 46.1 | L32: 134.84 | M32: 47.9 | N32: 48.93 | O32: 50.39 | P32: 50.39 | Q32: 56.19 | R32: 55.43 | S32: 120.91 | T32: 112.84 | U32: 112.84 | V32: 95.63 | W32: 69.31 | X32: 73.81 | Y32: 137.15 | Z32: 137.15 | AA32: 102.74 | AB32: 99.91
A33: 1 | C33: 비유동부채 | E33: 1069.92 | F33: 1069.92 | G33: 1006.06 | H33: 949.51 | I33: 876.54 | J33: 817 | K33: 817 | L33: 1641.98 | M33: 2366.87 | N33: 2343.98 | O33: 2557.19 | P33: 2557.19 | Q33: 2584.54 | R33: 2625.03 | S33: 3724.37 | T33: 4327.92 | U33: 4327.92 | V33: 3818.03 | W33: 3817.99 | X33: 12684.46 | Y33: 14902.48 | Z33: 14902.48 | AA33: 14895.39 | AB33: 14800.39
A34: 1 | C34: 장기차입금 | E34: 650 | F34: 650 | G34: 585 | H34: 520 | I34: 455 | J34: 390 | K34: 390 | L34: 1225 | M34: 1960 | N34: 1895 | O34: 1830 | P34: 1830 | Q34: 1765 | R34: 1700 | S34: 2700 | T34: 2575 | U34: 2575 | V34: 2450 | W34: 2240 | X34: 10990 | Y34: 13735 | Z34: 13735 | AA34: 13610 | AB34: 13400
A35: 1 | C35: 비유동리스부채 | E35: 90.78 | F35: 90.78 | G35: 90.78 | H35: 80.41 | I35: 67.7 | J35: 56.17 | K35: 56.17 | L35: 46.14 | M35: 36.04 | N35: 25.85 | O35: 15.57 | P35: 15.57 | Q35: 15.57 | R35: 42.84 | S35: 54.93
A36: 1 | C36: 장기금융부채 | E36: 419.92 | F36: 419.92 | G36: 421.06 | H36: 429.51 | I36: 421.54 | J36: 56.17 | K36: 56.17 | L36: 416.98 | M36: 406.88 | N36: 25.85 | O36: 15.57 | P36: 15.57 | Q36: 15.57 | R36: 42.84 | S36: 54.93
A37: 1 | C37: 기타비유동금융부채 | E37: 329.14 | F37: 329.14 | G37: 330.28 | H37: 349.1 | I37: 353.84 | L37: 370.84 | M37: 370.84
A38: 1 | C38: 부채총계 | E38: 29077.45 | F38: 29077.45 | G38: 38107.97 | H38: 33811.9 | I38: 33134.45 | J38: 58566.8 | K38: 58566.8 | L38: 38492.99 | M38: 37484.54 | N38: 30737.91 | O38: 57771.57 | P38: 57771.57 | Q38: 53878.81 | R38: 54911.05 | S38: 44216.31 | T38: 46460.89 | U38: 46460.89 | V38: 41025.12 | W38: 47110.74 | X38: 39568.54 | Y38: 39773.59 | Z38: 39773.59 | AA38: 52267.84 | AB38: 50395.79
A39: 1 | C39: 자본금 | E39: 13533.85 | F39: 13533.85 | G39: 13533.85 | H39: 13533.85 | I39: 13709.29 | J39: 13709.29 | K39: 13709.29 | L39: 14551.05 | M39: 15259.42 | N39: 15420.41 | O39: 15420.41 | P39: 15420.41 | Q39: 15420.41 | R39: 15420.41 | S39: 15420.41 | T39: 15420.41 | U39: 15420.41 | V39: 15420.41 | W39: 15420.41 | X39: 15420.41 | Y39: 15420.41 | Z39: 15420.41 | AA39: 15420.41 | AB39: 15420.41
A40: 1 | C40: 자본잉여금 | E40: 24957.45 | F40: 24957.45 | G40: 24957.45 | H40: 24957.45 | I40: 25223.52 | J40: 25268.31 | K40: 25268.31 | L40: 26435.55 | M40: 27488.31 | N40: 27786.55 | O40: 28574.59 | P40: 28574.59 | Q40: 28574.59 | R40: 28574.59 | S40: 28574.59 | T40: 28574.59 | U40: 28574.59 | V40: 28574.59 | W40: 28574.59 | X40: 28574.59 | Y40: 28574.59 | Z40: 28574.59 | AA40: 23877.13 | AB40: 23877.13
A41: 1 | C41: 기타자본 | E41: 877.35 | F41: 877.35 | G41: 877.35 | H41: 877.35 | I41: 877.35 | J41: 877.35 | K41: 877.35 | L41: 877.35 | M41: 877.35 | N41: 877.35 | O41: 877.35 | P41: 877.35 | Q41: 877.35 | R41: 877.35 | S41: 877.35 | T41: 877.35 | U41: 877.35 | V41: 877.35 | W41: 877.35 | X41: 877.35 | Y41: 877.35 | Z41: 877.35 | AA41: -425.19 | AB41: -425.19
A42: 1 | C42: 이익잉여금 | E42: -10214.86 | F42: -10214.86 | G42: -9893.44 | H42: -9857.93 | I42: -9832.17 | J42: -41462.28 | K42: -41462.28 | L42: -18874.99 | M42: -16189.76 | N42: -15515.42 | O42: -42596.74 | P42: -42596.74 | Q42: -33679.55 | R42: -28075.39 | S42: -23392.89 | T42: -19869.39 | U42: -19869.39 | V42: -15331.96 | W42: -14685.98 | X42: -8901.38 | Y42: 1546.2 | Z42: 1546.2 | AA42: 6871.45 | AB42: 2242.81
A43: 1 | C43: 자본총계 | E43: 29153.79 | F43: 29153.79 | G43: 29475.21 | H43: 29510.72 | I43: 29977.98 | J43: -1607.33 | K43: -1607.33 | L43: 22988.95 | M43: 27435.31 | N43: 28568.89 | O43: 2275.62 | P43: 2275.62 | Q43: 11192.81 | R43: 16796.97 | S43: 21479.46 | T43: 25002.96 | U43: 25002.96 | V43: 31478.15 | W43: 32108.34 | X43: 37892.94 | Y43: 48310.17 | Z43: 48310.17 | AA43: 47635.42 | AB43: 43006.78
A44: 1 | C44: 부채와자본총계 | E44: 58231.24 | F44: 58231.24 | G44: 67583.18 | H44: 63322.62 | I44: 63112.44 | J44: 56959.47 | K44: 56959.47 | L44: 61481.94 | M44: 64919.85 | N44: 59306.8 | O44: 60047.19 | P44: 60047.19 | Q44: 65071.62 | R44: 71708.01 | S44: 65695.77 | T44: 71463.85 | U44: 71463.85 | V44: 72503.27 | W44: 79219.08 | X44: 77461.48 | Y44: 88083.76 | Z44: 88083.76 | AA44: 99903.26 | AB44: 93402.57
A45: 1 | C45: 지배주주지분 | E45: 29153.79 | F45: 29153.79 | G45: 29475.21 | H45: 29510.72 | I45: 29977.98 | J45: -1607.33 | K45: -1607.33 | L45: 22988.95 | M45: 27435.31 | N45: 28568.89 | O45: 2275.62 | P45: 2275.62 | Q45: 11192.81 | R45: 16796.97 | S45: 21479.46 | T45: 25002.96 | U45: 25002.96 | V45: 31478.15 | W45: 32108.34 | X45: 37892.94 | Y45: 48310.17 | Z45: 48310.17 | AA45: 47635.42 | AB45: 43006.78
A46: 1 | C46: 총차입금 | E46: 15915 | F46: 15915 | G46: 15420.66 | H46: 15202.83 | I46: 14416.92 | J46: 13191.11 | K46: 13191.11 | L46: 13354.97 | M46: 13481.18 | N46: 16144 | O46: 16079 | P46: 16079 | Q46: 16014 | R46: 15949 | S46: 17384 | T46: 17194 | U46: 17194 | V46: 17004 | W46: 17214 | X46: 26649 | Y46: 29564 | Z46: 29564 | AA46: 30239 | AB46: 37829
A47: 1 | C47: 순차입금 | E47: 1649.28 | F47: 1649.28 | G47: -1267.62 | H47: 2791.46 | I47: 563.91 | J47: -3400.32 | K47: -3400.32 | L47: -201.97 | M47: -2195.08 | N47: 6210.82 | O47: 1821.87 | P47: 1821.87 | Q47: 4382.58 | R47: 418.85 | S47: 3146.59 | T47: -5873.52 | U47: -5873.52 | V47: -2426.5 | W47: 401.62 | X47: 12188.34 | Y47: 13725.77 | Z47: 13725.77 | AA47: 23326.53 | AB47: 21805.23
A48: 1 | C48: 이자발생자산 | E48: 14266.32 | F48: 14266.32 | G48: 16689.78 | H48: 12413.77 | I48: 13856.31 | J48: 18944.92 | K48: 18944.92 | L48: 13562.04 | M48: 15682.26 | N48: 9940.08 | O48: 17213.01 | P48: 17213.01 | Q48: 14816.57 | R48: 18353.06 | S48: 15668.27 | T48: 23381.13 | U48: 23381.13 | V48: 19744.11 | W48: 17125.99 | X48: 14774.27 | Y48: 16151.84 | Z48: 16151.84 | AA48: 6957.16 | AB48: 16068.46
A49: 1 | C49: 계약자산 | G49: 1594.26 | H49: 309.76 | I49: 109.24 | J49: 313.07 | K49: 313.07 | L49: 343.78 | M49: 348.74 | N49: 867.77 | O49: 859.24 | P49: 859.24 | Q49: 509.24 | R49: 259.24 | S49: 109.24 | AB49: 1.89
A50: 1 | C50: 유동파생상품자산 | I50: 298.51
A51: 1 | C51: 단기금융부채(face) | J51: 9989 | K51: 9989 | N51: 13989 | O51: 13989 | P51: 13989 | Q51: 13989 | R51: 13989
A52: 1 | C52: 단기충당부채 | J52: 56.89 | K52: 56.89 | L52: 40.25 | M52: 39.75 | N52: 39.73 | O52: 39.58 | P52: 39.58 | Q52: 19.71 | R52: 19.71 | S52: 19.71 | T52: 6.37 | U52: 6.37 | V52: 6.37
A53: 1 | C53: 기타비유동부채 | J53: 370.84 | K53: 370.84 | N53: 370.84 | O53: 370.84 | P53: 370.84 | Q53: 370.84 | R53: 370.84 | S53: 369.89 | T53: 369.89 | U53: 369.89 | V53: 369.89 | W53: 369.89 | X53: 369.89 | Y53: 441.81 | Z53: 441.81 | AA53: 441.81 | AB53: 441.81
A54: 1 | C54: 확정급여부채 | N54: 52.3 | O54: 340.78 | P54: 340.78 | Q54: 433.13 | R54: 511.36 | S54: 599.55 | T54: 1333.81 | U54: 1333.81 | V54: 954.26 | W54: 1068.2 | X54: 1195.76 | Y54: 608.12 | Z54: 608.12 | AA54: 717.63 | AB54: 845.98
A55: 1 | C55: 이연법인세자산 | R55: 2885.28 | S55: 2885.28 | T55: 1000.53 | U55: 1000.53 | V55: 522.13 | W55: 437.13 | X55: 437.13 | Y55: 2113.66 | Z55: 2113.66 | AA55: 2113.66 | AB55: 2039.51
A56: 1 | C56: 기타포괄이익누계액 | V56: 1937.75 | W56: 1921.96 | X56: 1921.96 | Y56: 1891.61 | Z56: 1891.61 | AA56: 1891.61 | AB56: 1891.61
A57: 1 | C57: 매출액(수익) | E57: 14731.06 | G57: 8991.38 | H57: 16875.34 | I57: 12892.84 | J57: 13156.22 | K57: 51915.78 | L57: 10803.46 | M57: 23381.95 | N57: 16719.4 | O57: 12781 | P57: 63685.81 | Q57: 12643.83 | R57: 13354.01 | S57: 16294.34 | T57: 14537.28 | U57: 56829.46 | V57: 12216.15 | W57: 11015.44 | X57: 29862.65 | Y57: 17367.69 | Z57: 70461.93 | AA57: 7422.1 | AB57: 22264.74
A58: 1 | C58: 매출원가 | E58: 12991.7 | G58: 7756.68 | H58: 15167.43 | I58: 11084.27 | J58: 11156.22 | K58: 45164.6 | L58: 9776.95 | M58: 19108.79 | N58: 13586.44 | O58: 10173.44 | P58: 52645.62 | Q58: 9764.15 | R58: 9210.39 | S58: 13435.52 | T58: 13549.29 | U58: 45959.35 | V58: 8956.86 | W58: 8246.2 | X58: 21989.74 | Y58: 15350.49 | Z58: 54543.29 | AA58: 5845.95 | AB58: 18962.87
A59: 1 | C59: 판관비 | E59: 812.15 | G59: 765.81 | H59: 1690.53 | I59: 1823.58 | J59: 2093.36 | K59: 6373.28 | L59: 1460.5 | M59: 1788.61 | N59: 1920.49 | O59: 1390.63 | P59: 6560.23 | Q59: 1625.2 | R59: 1889.39 | S59: 1570.65 | T59: 2150.26 | U59: 7235.5 | V59: 2456.58 | W59: 1993.19 | X59: 1667.94 | Y59: 2225.94 | Z59: 8343.65 | AA59: 2075.75 | AB59: 1780.32
A60: 1 | C60: 영업이익 | E60: 927.21 | G60: 468.89 | H60: 17.38 | I60: -15.02 | J60: -93.35 | K60: 377.9 | L60: -433.99 | M60: 2484.55 | N60: 1212.46 | O60: 1216.93 | P60: 4479.95 | Q60: 1254.49 | R60: 2254.23 | S60: 1288.17 | T60: -1162.27 | U60: 3634.62 | V60: 802.71 | W60: 776.05 | X60: 6204.97 | Y60: -208.75 | Z60: 7574.98 | AA60: -499.6 | AB60: 1521.55
A61: 1 | C61: 기타영업외수익 | E61: 4.8 | G61: 2.51 | H61: 2 | I61: 23.08 | J61: 63.86 | K61: 91.45 | L61: 36.91 | M61: 12.85 | N61: 13.98 | O61: 19.21 | P61: 82.95 | Q61: 73.33 | R61: 1.26 | S61: 58.28 | T61: 90.23 | U61: 223.1 | V61: 22.46 | W61: 0.57 | X61: 7.48 | Y61: 8434.09 | Z61: 8464.6 | AA61: 18.01 | AB61: 20.14
A62: 1 | C62: 기타영업외비용 | E62: 3425.26 | G62: 24.74 | H62: 561.38 | I62: 35.23 | J62: 8223.2 | K62: 8844.55 | L62: 229.86 | M62: 3.73 | N62: 506.88 | O62: 2081.94 | P62: 2822.41 | Q62: 168.34 | R62: 177.03 | S62: -118.66 | T62: 375.56 | U62: 602.27 | V62: 150.28 | W62: -40.58 | X62: 389.95 | Y62: -73.91 | Z62: 425.74 | AA62: 59.53 | AB62: 5861.13
A63: 1 | C63: 금융수익 | E63: 214.85 | G63: 265.79 | H63: 985.2 | I63: 741.01 | J63: 4957.36 | K63: 6949.36 | L63: 473.18 | M63: 540.13 | N63: 269.09 | O63: 286.75 | P63: 1569.15 | Q63: 358.41 | R63: 3855.65 | S63: 3480.42 | T63: 15425.03 | U63: 23119.51 | V63: 4157.78 | W63: 319.73 | X63: 222.12 | Y63: 219.27 | Z63: 4918.9 | AA63: 496.57 | AB63: 254.36
A64: 1 | C64: 금융비용 | E64: 1065.18 | G64: 391.03 | H64: 407.69 | I64: 688.08 | J64: 9183.77 | K64: 10670.57 | L64: 701.26 | M64: 348.57 | N64: 314.31 | O64: 2830.7 | P64: 4194.84 | Q64: 339.27 | R64: 3215.24 | S64: 263.03 | T64: 141.74 | U64: 3959.28 | V64: 295.24 | W64: 421.74 | X64: 260.01 | Y64: 479.94 | Z64: 1456.93 | AA64: 630.2 | AB64: 489.42
A65: 1 | C65: 법인세비용차감전계속사업이익 | E65: -3343.57 | G65: 321.42 | H65: 35.51 | I65: 25.76 | J65: -12479.1 | K65: -12096.41 | L65: -855.02 | M65: 2685.23 | N65: 674.34 | O65: -3389.76 | P65: -885.21 | Q65: 1178.62 | R65: 2718.87 | S65: 4682.49 | T65: 13835.67 | U65: 22415.65 | AB65: -4554.49
A66: 1 | C66: 당기순이익 | E66: -3343.57 | G66: 321.42 | H66: 35.51 | I66: 25.76 | J66: -12479.1 | K66: -12096.41 | L66: -855.02 | M66: 2685.23 | N66: 674.34 | O66: -3389.76 | P66: -885.21 | Q66: 1178.62 | R66: 5604.16 | S66: 4682.49 | T66: 11806.95 | U66: 23272.22 | V66: 4537.43 | W66: 645.98 | X66: 5784.6 | Y66: 9881.69 | Z66: 20849.7 | AA66: -674.75 | AB66: -4628.64
A67: 1 | C67: 총포괄손익 | E67: -3324.83 | G67: 321.42 | H67: 35.51 | I67: 25.76 | J67: -12539.5 | K67: -12156.81 | L67: -855.02 | M67: 2685.23 | N67: 674.34 | O67: -3639 | P67: -1134.45 | Q67: 1178.62 | R67: 5604.16 | S67: 4682.49 | T67: 11262.07 | U67: 22727.34 | V67: 6475.18 | W67: 630.19 | X67: 5784.6 | Y67: 10417.23 | Z67: 23307.2 | AA67: -674.75 | AB67: -4628.64
A68: 1 | C68: 매출총이익 | E68: 1739.36 | G68: 1234.7 | H68: 1707.91 | I68: 1808.57 | J68: 2000 | K68: 6751.18 | L68: 1026.51 | M68: 4273.16 | N68: 3132.96 | O68: 2607.56 | P68: 11040.19 | Q68: 2879.68 | R68: 4143.62 | S68: 2858.82 | T68: 988 | U68: 10870.12 | V68: 3259.3 | W68: 2769.24 | X68: 7872.9 | Y68: 2017.2 | Z68: 15918.64 | AA68: 1576.15 | AB68: 3301.87
A69: 1 | C69: 금융손익 | E69: -850.33 | G69: -125.24 | H69: 577.51 | I69: 52.93 | J69: -4226.41 | K69: -3721.21 | L69: -228.08 | M69: 191.56 | N69: -45.22 | O69: -2543.95 | P69: -2625.69 | Q69: 19.14 | R69: 640.41 | S69: 3217.39 | T69: 15283.29 | U69: 19160.23 | V69: 3862.54 | W69: -102.01 | X69: -37.89 | Y69: -260.67 | Z69: 3461.97 | AA69: -133.63 | AB69: -235.06
A70: 1 | C70: 기타영업외손익 | E70: -3420.46 | G70: -22.23 | H70: -559.38 | I70: -12.15 | J70: -8159.34 | K70: -8753.1 | L70: -192.95 | M70: 9.12 | N70: -492.9 | O70: -2062.73 | P70: -2739.46 | Q70: -95.01 | R70: -175.77 | S70: 176.94 | T70: -285.33 | U70: -379.17 | V70: -127.82 | W70: 41.15 | X70: -382.47 | Y70: 8508 | Z70: 8038.86 | AA70: -41.52 | AB70: -5840.99
A71: 1 | C71: (지배주주지분)당기순이익 | E71: -3343.57 | G71: 321.42 | H71: 35.51 | I71: 25.76 | J71: -12479.1 | K71: -12096.41 | L71: -855.02 | M71: 2685.23 | N71: 674.34 | O71: -3389.76 | P71: -885.21 | Q71: 1178.62 | R71: 5604.16 | S71: 4682.49 | T71: 11806.95 | U71: 23272.22 | V71: 4537.43 | W71: 645.98 | X71: 5784.6 | Y71: 9881.69 | Z71: 20849.7 | AA71: -674.75 | AB71: -4628.64
A72: 1 | C72: 계속사업이익 | E72: -3343.57 | G72: 321.42 | H72: 35.51 | I72: 25.76 | J72: -12479.1 | K72: -12096.41 | L72: -855.02 | M72: 2685.23 | N72: 674.34 | O72: -3389.76 | P72: -885.21 | Q72: 1178.62 | R72: 5604.16 | S72: 4682.49 | T72: 11806.95 | U72: 23272.22 | V72: 4537.43 | W72: 645.98 | X72: 5784.6 | Y72: 9881.69 | Z72: 20849.7 | AA72: -674.75 | AB72: -4628.64
A73: 1 | C73: 법인세비용 | R73: -2885.28 | T73: 2028.72 | W73: 69.21 | Y73: -1843.12 | AB73: 74.15
A74: 1 | C74: 영업활동으로인한현금흐름 | E74: 1332.96 | G74: 2885.41 | H74: -4766.47 | I74: 2414.24 | J74: 4871.69 | K74: 5404.87 | L74: -2847.26 | M74: 2652.61 | N74: -4813.63 | O74: 4751.94 | P74: -256.34 | Q74: -2350.29 | R74: 3417.36 | S74: -2170.62 | T74: 7760.72 | U74: 6657.17 | V74: -4043.05 | W74: 1310.27 | X74: -3293.99 | Y74: 4198.48 | Z74: -1828.29 | AA74: -7189.65 | AB74: 1972.84
A75: 1 | C75: 법인세납부(CF) | E75: -2.12 | G75: -6.46 | H75: 12.72 | I75: -18.5 | J75: -7.72 | K75: -19.96 | L75: -11.17 | M75: 30.52 | N75: -24.68 | O75: -9.22 | P75: -14.55 | Q75: -70.26 | R75: 35.81 | S75: -17.62 | T75: -29.43 | U75: -81.5 | V75: -78.39 | W75: 123.96 | X75: -14.46 | Y75: -8.51 | Z75: 22.6 | AA75: -10.19 | AB75: 108.36
A76: 1 | C76: 투자활동으로인한현금흐름 | E76: -245.84 | G76: 1410.17 | H76: 2324.15 | I76: 573.28 | J76: -75.05 | K76: 4232.55 | L76: -3538.48 | M76: -1712.65 | N76: -2346.78 | O76: -325.78 | P76: -7923.69 | Q76: 294.16 | R76: 546.38 | S76: -4102.66 | T76: 7852.39 | U76: 4590.27 | V76: 531.35 | W76: -4011.73 | X76: -8474.56 | Y76: -5643.37 | Z76: -17598.31 | AA76: -2214.1 | AB76: -462.12
A77: 1 | C77: 유형자산의증가 | E77: 238.62 | G77: 121.83 | H77: 190.26 | I77: 678.53 | J77: 156.85 | K77: 1147.47 | L77: 1037.58 | M77: 1411.75 | N77: 719.26 | O77: 302.21 | P77: 3470.8 | Q77: 283.03 | R77: 52.72 | S77: 78.9 | T77: 153.86 | U77: 568.51 | V77: 923.24 | W77: 3975.49 | X77: 7168.9 | Y77: 5404.84 | Z77: 17472.47 | AA77: 1040.53 | AB77: 500.06
A78: 1 | C78: CAPEX | E78: 238.62 | G78: 121.83 | H78: 219.46 | I78: 678.53 | J78: 156.85 | K78: 1176.67 | L78: 1037.58 | M78: 1411.75 | N78: 719.26 | O78: 302.21 | P78: 3470.8 | Q78: 283.03 | R78: 52.72 | S78: 78.9 | T78: 153.86 | U78: 568.51 | V78: 923.24 | W78: 3975.49 | X78: 7168.9 | Y78: 5404.84 | Z78: 17472.47 | AA78: 1040.53 | AB78: 500.06
A79: 1 | C79: 재무활동으로인한현금흐름 | E79: -398.92 | G79: -387.74 | H79: -398.31 | I79: -698.34 | J79: -1430.72 | K79: -2915.11 | L79: 1319.64 | M79: 1219.66 | N79: 2921.14 | O79: -78.52 | P79: 5381.92 | Q79: -65 | R79: -94.23 | S79: 1421.72 | T79: -203.65 | U79: 1058.84 | V79: -204.63 | W79: 195.13 | X79: 9420.01 | Y79: 2899.98 | Z79: 12310.49 | AA79: 659.69 | AB79: 7574.56
A80: 1 | C80: 단기차입금의감소 | E80: 0 | J80: 0
A81: 1 | C81: 유동성장기부채의감소 | E81: 388.88 | G81: 388.88 | H81: 388.88 | I81: 65 | J81: 65 | K81: 907.76 | L81: 65 | M81: 65 | N81: 65 | O81: 65 | P81: 260 | Q81: 65 | R81: 65 | S81: 65 | T81: 190 | U81: 385 | V81: 190 | W81: 190 | X81: 125 | Y81: 125 | Z81: 630 | AA81: 125 | AB81: 210
A82: 1 | C82: 리스부채의상환 | E82: 20.8 | I82: 38.08 | J82: 2.72 | L82: 15.36 | M82: 15.34 | N82: 13.86 | O82: 13.52 | P82: 58.08 | S82: 12.33 | T82: 14.6 | V82: 14.63 | W82: 14.87 | X82: 14.99 | Y82: 15.02 | Z82: 59.51 | AA82: 15.31 | AB82: 15.44
A83: 1 | C83: 현금및현금성자산의증감 | E83: 688.19 | G83: 3907.83 | H83: -2840.63 | I83: 2289.19 | J83: 3365.92 | K83: 6722.31 | L83: -5066.11 | M83: 2159.63 | N83: -4239.26 | O83: 4347.63 | P83: -2798.11 | Q83: -2121.13 | R83: 3869.52 | S83: -4851.57 | T83: 15409.46 | U83: 12306.28 | V83: -3716.33 | W83: -2506.34 | X83: -2348.53 | Y83: 1455.09 | Z83: -7116.11 | AA83: -8744.06 | AB83: 9085.28
A84: 1 | C84: 기말현금및현금성자산 | E84: 665.92 | G84: 8173.6 | H84: -2791.46 | I84: 2372.36 | J84: 3036.93 | K84: 10791.43 | L84: 5756.94 | M84: 2119.32 | N84: -4243.08 | O84: 4323.95 | P84: 7957.13 | Q84: 5831.42 | R84: 3898.73 | S84: -4892.74 | T84: 15418.71 | U84: 20256.12 | V84: 16618.2 | W84: -2619.02 | X84: -2352.62 | Y84: 1376.67 | Z84: 13023.23 | AA84: 4292.47 | AB84: 9111.3
A85: 1 | C85: 유형자산의감소 | G85: 1.05 | H85: 0 | I85: 0 | J85: 0 | K85: 1.05 | V85: 1.5 | W85: 0 | X85: 0 | Y85: 0 | Z85: 1.5
A86: 1 | C86: 무형자산의증가 | I86: 0 | J86: 0
A87: 1 | C87: 단기차입금의증가 | L87: 500 | M87: 500 | N87: 3000 | O87: 0 | P87: 4000 | X87: 600 | Y87: 0 | AA87: 800 | AB87: 7800
A88: 1 | C88: 장기차입금의증가 | L88: 900 | M88: 800 | N88: 0 | O88: 0 | P88: 1700 | T88: 0 | Y88: 3040
A89: 1 | C89: 이자수취(CF) | O89: 182.78 | Q89: 274.57 | R89: 120.02 | S89: 63.48 | T89: 197.01 | U89: 655.08 | V89: 293.66 | W89: 65.09 | X89: 93.91 | Y89: 65.79 | Z89: 518.45 | AA89: 61.16 | AB89: 19.43
A90: 1 | C90: 이자지급(CF) | V90: -202.75 | W90: -205.35 | X90: -194.72 | Y90: -254.23 | Z90: -857.05 | AA90: -284.63 | AB90: -292.95

Sheet subQ
A1: YQ | C1: subQ 분기 서브모델(억원, U=100) | E1: 4Q21 | F1: 2021 | G1: 1Q22 | H1: 2Q22 | I1: 3Q22 | J1: 4Q22 | K1: 2022 | L1: 1Q23 | M1: 2Q23 | N1: 3Q23 | O1: 4Q23 | P1: 2023 | Q1: 1Q24 | R1: 2Q24 | S1: 3Q24 | T1: 4Q24 | U1: 2024 | V1: 1Q25 | W1: 2Q25 | X1: 3Q25 | Y1: 4Q25 | Z1: 2025 | AA1: 1Q26 | AB1: 2Q26 | AC1: 3Q26 | AD1: 4Q26 | AE1: 2026 | AF1: 1Q27 | AG1: 2Q27 | AH1: 3Q27 | AI1: 4Q27 | AJ1: 2027 | AK1: 1Q28 | AL1: 2Q28 | AM1: 3Q28 | AN1: 4Q28 | AO1: 2028
A2: A=이름(key) B=그룹 C=단위 D=FnGuide 계정명(VLOOKUP 키). 확정=VLOOKUP(BS), 추정=변수 가정 참조
E3: 1 | F3: 2 | G3: 3 | H3: 4 | I3: 5 | J3: 6 | K3: 7 | L3: 8 | M3: 9 | N3: 10 | O3: 11 | P3: 12 | Q3: 13 | R3: 14 | S3: 15 | T3: 16 | U3: 17 | V3: 18 | W3: 19 | X3: 20 | Y3: 21 | Z3: 22 | AA3: 23 | AB3: 24 | AC3: 25 | AD3: 26 | AE3: 27 | AF3: 28 | AG3: 29 | AH3: 30 | AI3: 31 | AJ3: 32 | AK3: 33 | AL3: 34 | AM3: 35 | AN3: 36 | AO3: 37
E4: 2021.12 | F4: 2021.12A | G4: 2022.03 | H4: 2022.06 | I4: 2022.09 | J4: 2022.12 | K4: 2022.12A | L4: 2023.03 | M4: 2023.06 | N4: 2023.09 | O4: 2023.12 | P4: 2023.12A | Q4: 2024.03 | R4: 2024.06 | S4: 2024.09 | T4: 2024.12 | U4: 2024.12A | V4: 2025.03 | W4: 2025.06 | X4: 2025.09 | Y4: 2025.12 | Z4: 2025.12A | AA4: 2026.03 | AB4: 2026.06 | AC4: 2026.09 | AD4: 2026.12 | AE4: 2026.12A | AF4: 2027.03 | AG4: 2027.06 | AH4: 2027.09 | AI4: 2027.12 | AJ4: 2027.12A | AK4: 2028.03 | AL4: 2028.06 | AM4: 2028.09 | AN4: 2028.12 | AO4: 2028.12A
A5: 매출액 | B5: 손익 | C5: 억원 | D5: 매출액(수익) | E5: =IFERROR(VLOOKUP($D5,BS연결,MATCH(E$1,BS연결H,0),0)/100,"") | G5: =IFERROR(VLOOKUP($D5,BS연결,MATCH(G$1,BS연결H,0),0)/100,"") | H5: =IFERROR(VLOOKUP($D5,BS연결,MATCH(H$1,BS연결H,0),0)/100,"") | I5: =IFERROR(VLOOKUP($D5,BS연결,MATCH(I$1,BS연결H,0),0)/100,"") | J5: =IFERROR(VLOOKUP($D5,BS연결,MATCH(J$1,BS연결H,0),0)/100,"") | K5: =IFERROR(VLOOKUP($D5,BS연결,MATCH(K$1,BS연결H,0),0)/100,"") | L5: =IFERROR(VLOOKUP($D5,BS연결,MATCH(L$1,BS연결H,0),0)/100,"") | M5: =IFERROR(VLOOKUP($D5,BS연결,MATCH(M$1,BS연결H,0),0)/100,"") | N5: =IFERROR(VLOOKUP($D5,BS연결,MATCH(N$1,BS연결H,0),0)/100,"") | ... AB5: =IFERROR(VLOOKUP($D5,BS연결,MATCH(AB$1,BS연결H,0),0)/100,"") | AC5: =IFERROR(X5*(1+변수!AC21),"") | AD5: =IFERROR(Y5*(1+변수!AD21),"") | AE5: =SUM(AA5:AD5) | AF5: =IFERROR(AA5*(1+변수!AF21),"") | AG5: =IFERROR(AB5*(1+변수!AG21),"") | AH5: =IFERROR(AC5*(1+변수!AH21),"") | AI5: =IFERROR(AD5*(1+변수!AI21),"") | AJ5: =SUM(AF5:AI5) | AK5: =IFERROR(AF5*(1+변수!AK21),"") | AL5: =IFERROR(AG5*(1+변수!AL21),"") | AM5: =IFERROR(AH5*(1+변수!AM21),"") | AN5: =IFERROR(AI5*(1+변수!AN21),"") | AO5: =SUM(AK5:AN5)
A6: 매출원가 | B6: 손익 | C6: 억원 | D6: 매출원가 | E6: =IFERROR(VLOOKUP($D6,BS연결,MATCH(E$1,BS연결H,0),0)/100,"") | G6: =IFERROR(VLOOKUP($D6,BS연결,MATCH(G$1,BS연결H,0),0)/100,"") | H6: =IFERROR(VLOOKUP($D6,BS연결,MATCH(H$1,BS연결H,0),0)/100,"") | I6: =IFERROR(VLOOKUP($D6,BS연결,MATCH(I$1,BS연결H,0),0)/100,"") | J6: =IFERROR(VLOOKUP($D6,BS연결,MATCH(J$1,BS연결H,0),0)/100,"") | K6: =IFERROR(VLOOKUP($D6,BS연결,MATCH(K$1,BS연결H,0),0)/100,"") | L6: =IFERROR(VLOOKUP($D6,BS연결,MATCH(L$1,BS연결H,0),0)/100,"") | M6: =IFERROR(VLOOKUP($D6,BS연결,MATCH(M$1,BS연결H,0),0)/100,"") | N6: =IFERROR(VLOOKUP($D6,BS연결,MATCH(N$1,BS연결H,0),0)/100,"") | ... AB6: =IFERROR(VLOOKUP($D6,BS연결,MATCH(AB$1,BS연결H,0),0)/100,"") | AC6: =IFERROR(AC5-AC7,"") | AD6: =IFERROR(AD5-AD7,"") | AE6: =SUM(AA6:AD6) | AF6: =IFERROR(AF5-AF7,"") | AG6: =IFERROR(AG5-AG7,"") | AH6: =IFERROR(AH5-AH7,"") | AI6: =IFERROR(AI5-AI7,"") | AJ6: =SUM(AF6:AI6) | AK6: =IFERROR(AK5-AK7,"") | AL6: =IFERROR(AL5-AL7,"") | AM6: =IFERROR(AM5-AM7,"") | AN6: =IFERROR(AN5-AN7,"") | AO6: =SUM(AK6:AN6)
A7: 매출총이익 | B7: 손익 | C7: 억원 | D7: 매출총이익 | E7: =IFERROR(VLOOKUP($D7,BS연결,MATCH(E$1,BS연결H,0),0)/100,"") | G7: =IFERROR(VLOOKUP($D7,BS연결,MATCH(G$1,BS연결H,0),0)/100,"") | H7: =IFERROR(VLOOKUP($D7,BS연결,MATCH(H$1,BS연결H,0),0)/100,"") | I7: =IFERROR(VLOOKUP($D7,BS연결,MATCH(I$1,BS연결H,0),0)/100,"") | J7: =IFERROR(VLOOKUP($D7,BS연결,MATCH(J$1,BS연결H,0),0)/100,"") | K7: =IFERROR(VLOOKUP($D7,BS연결,MATCH(K$1,BS연결H,0),0)/100,"") | L7: =IFERROR(VLOOKUP($D7,BS연결,MATCH(L$1,BS연결H,0),0)/100,"") | M7: =IFERROR(VLOOKUP($D7,BS연결,MATCH(M$1,BS연결H,0),0)/100,"") | N7: =IFERROR(VLOOKUP($D7,BS연결,MATCH(N$1,BS연결H,0),0)/100,"") | ... T7: =IFERROR(VLOOKUP($D7,BS연결,MATCH(T$1,BS연결H,0),0)/100,"") | U7: =SUM(Q7:T7) | V7: =IFERROR(VLOOKUP($D7,BS연결,MATCH(V$1,BS연결H,0),0)/100,"") | W7: =IFERROR(VLOOKUP($D7,BS연결,MATCH(W$1,BS연결H,0),0)/100,"") | X7: =IFERROR(VLOOKUP($D7,BS연결,MATCH(X$1,BS연결H,0),0)/100,"") | Y7: =IFERROR(VLOOKUP($D7,BS연결,MATCH(Y$1,BS연결H,0),0)/100,"") | Z7: =IFERROR(VLOOKUP($D7,BS연결,MATCH(Z$1,BS연결H,0),0)/100,"") | AA7: =IFERROR(VLOOKUP($D7,BS연결,MATCH(AA$1,BS연결H,0),0)/100,"") | AB7: =IFERROR(VLOOKUP($D7,BS연결,MATCH(AB$1,BS연결H,0),0)/100,"") | AC7: =IFERROR(AC9+AC8,"") | AD7: =IFERROR(AD9+AD8,"") | AE7: =SUM(AA7:AD7) | AF7: =IFERROR(AF9+AF8,"") | AG7: =IFERROR(AG9+AG8,"") | AH7: =IFERROR(AH9+AH8,"") | AI7: =IFERROR(AI9+AI8,"") | AJ7: =SUM(AF7:AI7) | AK7: =IFERROR(AK9+AK8,"") | AL7: =IFERROR(AL9+AL8,"") | AM7: =IFERROR(AM9+AM8,"") | AN7: =IFERROR(AN9+AN8,"") | AO7: =SUM(AK7:AN7)
A8: 판관비 | B8: 손익 | C8: 억원 | D8: 판관비 | E8: =IFERROR(VLOOKUP($D8,BS연결,MATCH(E$1,BS연결H,0),0)/100,"") | G8: =IFERROR(VLOOKUP($D8,BS연결,MATCH(G$1,BS연결H,0),0)/100,"") | H8: =IFERROR(VLOOKUP($D8,BS연결,MATCH(H$1,BS연결H,0),0)/100,"") | I8: =IFERROR(VLOOKUP($D8,BS연결,MATCH(I$1,BS연결H,0),0)/100,"") | J8: =IFERROR(VLOOKUP($D8,BS연결,MATCH(J$1,BS연결H,0),0)/100,"") | K8: =IFERROR(VLOOKUP($D8,BS연결,MATCH(K$1,BS연결H,0),0)/100,"") | L8: =IFERROR(VLOOKUP($D8,BS연결,MATCH(L$1,BS연결H,0),0)/100,"") | M8: =IFERROR(VLOOKUP($D8,BS연결,MATCH(M$1,BS연결H,0),0)/100,"") | N8: =IFERROR(VLOOKUP($D8,BS연결,MATCH(N$1,BS연결H,0),0)/100,"") | ... AB8: =IFERROR(VLOOKUP($D8,BS연결,MATCH(AB$1,BS연결H,0),0)/100,"") | AC8: =IFERROR(AC5*변수!AC22,"") | AD8: =IFERROR(AD5*변수!AD22,"") | AE8: =SUM(AA8:AD8) | AF8: =IFERROR(AF5*변수!AF22,"") | AG8: =IFERROR(AG5*변수!AG22,"") | AH8: =IFERROR(AH5*변수!AH22,"") | AI8: =IFERROR(AI5*변수!AI22,"") | AJ8: =SUM(AF8:AI8) | AK8: =IFERROR(AK5*변수!AK22,"") | AL8: =IFERROR(AL5*변수!AL22,"") | AM8: =IFERROR(AM5*변수!AM22,"") | AN8: =IFERROR(AN5*변수!AN22,"") | AO8: =SUM(AK8:AN8)
A9: 영업이익 | B9: 손익 | C9: 억원 | D9: 영업이익 | E9: =IFERROR(VLOOKUP($D9,BS연결,MATCH(E$1,BS연결H,0),0)/100,"") | G9: =IFERROR(VLOOKUP($D9,BS연결,MATCH(G$1,BS연결H,0),0)/100,"") | H9: =IFERROR(VLOOKUP($D9,BS연결,MATCH(H$1,BS연결H,0),0)/100,"") | I9: =IFERROR(VLOOKUP($D9,BS연결,MATCH(I$1,BS연결H,0),0)/100,"") | J9: =IFERROR(VLOOKUP($D9,BS연결,MATCH(J$1,BS연결H,0),0)/100,"") | K9: =IFERROR(VLOOKUP($D9,BS연결,MATCH(K$1,BS연결H,0),0)/100,"") | L9: =IFERROR(VLOOKUP($D9,BS연결,MATCH(L$1,BS연결H,0),0)/100,"") | M9: =IFERROR(VLOOKUP($D9,BS연결,MATCH(M$1,BS연결H,0),0)/100,"") | N9: =IFERROR(VLOOKUP($D9,BS연결,MATCH(N$1,BS연결H,0),0)/100,"") | ... AB9: =IFERROR(VLOOKUP($D9,BS연결,MATCH(AB$1,BS연결H,0),0)/100,"") | AC9: =IFERROR(AC5*변수!AC23,"") | AD9: =IFERROR(AD5*변수!AD23,"") | AE9: =SUM(AA9:AD9) | AF9: =IFERROR(AF5*변수!AF23,"") | AG9: =IFERROR(AG5*변수!AG23,"") | AH9: =IFERROR(AH5*변수!AH23,"") | AI9: =IFERROR(AI5*변수!AI23,"") | AJ9: =SUM(AF9:AI9) | AK9: =IFERROR(AK5*변수!AK23,"") | AL9: =IFERROR(AL5*변수!AL23,"") | AM9: =IFERROR(AM5*변수!AM23,"") | AN9: =IFERROR(AN5*변수!AN23,"") | AO9: =SUM(AK9:AN9)
A10: OPM | B10: 손익 | C10: % | D10: 영업이익률 | E10: =IFERROR(E9/E5,"") | G10: =IFERROR(G9/G5,"") | H10: =IFERROR(H9/H5,"") | I10: =IFERROR(I9/I5,"") | J10: =IFERROR(J9/J5,"") | K10: =IFERROR(K9/K5,"") | L10: =IFERROR(L9/L5,"") | M10: =IFERROR(M9/M5,"") | N10: =IFERROR(N9/N5,"") | ... AO10: =IFERROR(AO9/AO5,"")
A11: 금융손익 | B11: 손익 | C11: 억원 | D11: 금융손익 | E11: =IFERROR(VLOOKUP($D11,BS연결,MATCH(E$1,BS연결H,0),0)/100,"") | G11: =IFERROR(VLOOKUP($D11,BS연결,MATCH(G$1,BS연결H,0),0)/100,"") | H11: =IFERROR(VLOOKUP($D11,BS연결,MATCH(H$1,BS연결H,0),0)/100,"") | I11: =IFERROR(VLOOKUP($D11,BS연결,MATCH(I$1,BS연결H,0),0)/100,"") | J11: =IFERROR(VLOOKUP($D11,BS연결,MATCH(J$1,BS연결H,0),0)/100,"") | K11: =IFERROR(VLOOKUP($D11,BS연결,MATCH(K$1,BS연결H,0),0)/100,"") | L11: =IFERROR(VLOOKUP($D11,BS연결,MATCH(L$1,BS연결H,0),0)/100,"") | M11: =IFERROR(VLOOKUP($D11,BS연결,MATCH(M$1,BS연결H,0),0)/100,"") | N11: =IFERROR(VLOOKUP($D11,BS연결,MATCH(N$1,BS연결H,0),0)/100,"") | ... AB11: =IFERROR(VLOOKUP($D11,BS연결,MATCH(AB$1,BS연결H,0),0)/100,"") | AC11: =IFERROR(AC12+AC13+AC14+AC15,"") | AD11: =IFERROR(AD12+AD13+AD14+AD15,"") | AE11: =SUM(AA11:AD11) | AF11: =IFERROR(AF12+AF13+AF14+AF15,"") | AG11: =IFERROR(AG12+AG13+AG14+AG15,"") | AH11: =IFERROR(AH12+AH13+AH14+AH15,"") | AI11: =IFERROR(AI12+AI13+AI14+AI15,"") | AJ11: =SUM(AF11:AI11) | AK11: =IFERROR(AK12+AK13+AK14+AK15,"") | AL11: =IFERROR(AL12+AL13+AL14+AL15,"") | AM11: =IFERROR(AM12+AM13+AM14+AM15,"") | AN11: =IFERROR(AN12+AN13+AN14+AN15,"") | AO11: =SUM(AK11:AN11)
A12: 이자손익 | B12: 손익 | C12: 억원 | D12: 이자손익 | G12: =IFERROR(VLOOKUP($D12,BS연결,MATCH(G$1,BS연결H,0),0)/100,"") | H12: =IFERROR(VLOOKUP($D12,BS연결,MATCH(H$1,BS연결H,0),0)/100,"") | I12: =IFERROR(VLOOKUP($D12,BS연결,MATCH(I$1,BS연결H,0),0)/100,"") | J12: =IFERROR(VLOOKUP($D12,BS연결,MATCH(J$1,BS연결H,0),0)/100,"") | K12: =IFERROR(VLOOKUP($D12,BS연결,MATCH(K$1,BS연결H,0),0)/100,"") | L12: =IFERROR(VLOOKUP($D12,BS연결,MATCH(L$1,BS연결H,0),0)/100,"") | M12: =IFERROR(VLOOKUP($D12,BS연결,MATCH(M$1,BS연결H,0),0)/100,"") | N12: =IFERROR(VLOOKUP($D12,BS연결,MATCH(N$1,BS연결H,0),0)/100,"") | ... AB12: =IFERROR(VLOOKUP($D12,BS연결,MATCH(AB$1,BS연결H,0),0)/100,"") | AC12: =IFERROR((AB28*변수!$D$54-AB26*변수!$D$55)/4,"") | AD12: =IFERROR((AC28*변수!$D$54-AC26*변수!$D$55)/4,"") | AE12: =SUM(AA12:AD12) | AF12: =IFERROR((AD28*변수!$D$54-AD26*변수!$D$55)/4,"") | AG12: =IFERROR((AF28*변수!$D$54-AF26*변수!$D$55)/4,"") | AH12: =IFERROR((AG28*변수!$D$54-AG26*변수!$D$55)/4,"") | AI12: =IFERROR((AH28*변수!$D$54-AH26*변수!$D$55)/4,"") | AJ12: =SUM(AF12:AI12) | AK12: =IFERROR((AI28*변수!$D$54-AI26*변수!$D$55)/4,"") | AL12: =IFERROR((AK28*변수!$D$54-AK26*변수!$D$55)/4,"") | AM12: =IFERROR((AL28*변수!$D$54-AL26*변수!$D$55)/4,"") | AN12: =IFERROR((AM28*변수!$D$54-AM26*변수!$D$55)/4,"") | AO12: =SUM(AK12:AN12)
A13: 외환손익 | B13: 손익 | C13: 억원 | D13: 외환손익(실적만; 추정 환효과는 환관련손익) | G13: =IFERROR((VLOOKUP("외환차익",BS연결,MATCH(G$1,BS연결H,0),0)-VLOOKUP("외환차손",BS연결,MATCH(G$1,BS연결H,0),0)+VLOOKUP("외화환산이익",BS연결,MATCH(G$1,BS연결H,0),0)-VLOOKUP("외화환산손실",BS연결,MATCH(G$1,BS연결H,0),0))/100,"") | H13: =IFERROR((VLOOKUP("외환차익",BS연결,MATCH(H$1,BS연결H,0),0)-VLOOKUP("외환차손",BS연결,MATCH(H$1,BS연결H,0),0)+VLOOKUP("외화환산이익",BS연결,MATCH(H$1,BS연결H,0),0)-VLOOKUP("외화환산손실",BS연결,MATCH(H$1,BS연결H,0),0))/100,"") | I13: =IFERROR((VLOOKUP("외환차익",BS연결,MATCH(I$1,BS연결H,0),0)-VLOOKUP("외환차손",BS연결,MATCH(I$1,BS연결H,0),0)+VLOOKUP("외화환산이익",BS연결,MATCH(I$1,BS연결H,0),0)-VLOOKUP("외화환산손실",BS연결,MATCH(I$1,BS연결H,0),0))/100,"") | J13: =IFERROR((VLOOKUP("외환차익",BS연결,MATCH(J$1,BS연결H,0),0)-VLOOKUP("외환차손",BS연결,MATCH(J$1,BS연결H,0),0)+VLOOKUP("외화환산이익",BS연결,MATCH(J$1,BS연결H,0),0)-VLOOKUP("외화환산손실",BS연결,MATCH(J$1,BS연결H,0),0))/100,"") | K13: =SUM(G13:J13) | L13: =IFERROR((VLOOKUP("외환차익",BS연결,MATCH(L$1,BS연결H,0),0)-VLOOKUP("외환차손",BS연결,MATCH(L$1,BS연결H,0),0)+VLOOKUP("외화환산이익",BS연결,MATCH(L$1,BS연결H,0),0)-VLOOKUP("외화환산손실",BS연결,MATCH(L$1,BS연결H,0),0))/100,"") | M13: =IFERROR((VLOOKUP("외환차익",BS연결,MATCH(M$1,BS연결H,0),0)-VLOOKUP("외환차손",BS연결,MATCH(M$1,BS연결H,0),0)+VLOOKUP("외화환산이익",BS연결,MATCH(M$1,BS연결H,0),0)-VLOOKUP("외화환산손실",BS연결,MATCH(M$1,BS연결H,0),0))/100,"") | N13: =IFERROR((VLOOKUP("외환차익",BS연결,MATCH(N$1,BS연결H,0),0)-VLOOKUP("외환차손",BS연결,MATCH(N$1,BS연결H,0),0)+VLOOKUP("외화환산이익",BS연결,MATCH(N$1,BS연결H,0),0)-VLOOKUP("외화환산손실",BS연결,MATCH(N$1,BS연결H,0),0))/100,"") | O13: =IFERROR((VLOOKUP("외환차익",BS연결,MATCH(O$1,BS연결H,0),0)-VLOOKUP("외환차손",BS연결,MATCH(O$1,BS연결H,0),0)+VLOOKUP("외화환산이익",BS연결,MATCH(O$1,BS연결H,0),0)-VLOOKUP("외화환산손실",BS연결,MATCH(O$1,BS연결H,0),0))/100,"") | P13: =SUM(L13:O13) | Q13: =IFERROR((VLOOKUP("외환차익",BS연결,MATCH(Q$1,BS연결H,0),0)-VLOOKUP("외환차손",BS연결,MATCH(Q$1,BS연결H,0),0)+VLOOKUP("외화환산이익",BS연결,MATCH(Q$1,BS연결H,0),0)-VLOOKUP("외화환산손실",BS연결,MATCH(Q$1,BS연결H,0),0))/100,"") | R13: =IFERROR((VLOOKUP("외환차익",BS연결,MATCH(R$1,BS연결H,0),0)-VLOOKUP("외환차손",BS연결,MATCH(R$1,BS연결H,0),0)+VLOOKUP("외화환산이익",BS연결,MATCH(R$1,BS연결H,0),0)-VLOOKUP("외화환산손실",BS연결,MATCH(R$1,BS연결H,0),0))/100,"") | S13: =IFERROR((VLOOKUP("외환차익",BS연결,MATCH(S$1,BS연결H,0),0)-VLOOKUP("외환차손",BS연결,MATCH(S$1,BS연결H,0),0)+VLOOKUP("외화환산이익",BS연결,MATCH(S$1,BS연결H,0),0)-VLOOKUP("외화환산손실",BS연결,MATCH(S$1,BS연결H,0),0))/100,"") | T13: =IFERROR((VLOOKUP("외환차익",BS연결,MATCH(T$1,BS연결H,0),0)-VLOOKUP("외환차손",BS연결,MATCH(T$1,BS연결H,0),0)+VLOOKUP("외화환산이익",BS연결,MATCH(T$1,BS연결H,0),0)-VLOOKUP("외화환산손실",BS연결,MATCH(T$1,BS연결H,0),0))/100,"") | U13: =SUM(Q13:T13) | V13: =IFERROR((VLOOKUP("외환차익",BS연결,MATCH(V$1,BS연결H,0),0)-VLOOKUP("외환차손",BS연결,MATCH(V$1,BS연결H,0),0)+VLOOKUP("외화환산이익",BS연결,MATCH(V$1,BS연결H,0),0)-VLOOKUP("외화환산손실",BS연결,MATCH(V$1,BS연결H,0),0))/100,"") | W13: =IFERROR((VLOOKUP("외환차익",BS연결,MATCH(W$1,BS연결H,0),0)-VLOOKUP("외환차손",BS연결,MATCH(W$1,BS연결H,0),0)+VLOOKUP("외화환산이익",BS연결,MATCH(W$1,BS연결H,0),0)-VLOOKUP("외화환산손실",BS연결,MATCH(W$1,BS연결H,0),0))/100,"") | X13: =IFERROR((VLOOKUP("외환차익",BS연결,MATCH(X$1,BS연결H,0),0)-VLOOKUP("외환차손",BS연결,MATCH(X$1,BS연결H,0),0)+VLOOKUP("외화환산이익",BS연결,MATCH(X$1,BS연결H,0),0)-VLOOKUP("외화환산손실",BS연결,MATCH(X$1,BS연결H,0),0))/100,"") | Y13: =IFERROR((VLOOKUP("외환차익",BS연결,MATCH(Y$1,BS연결H,0),0)-VLOOKUP("외환차손",BS연결,MATCH(Y$1,BS연결H,0),0)+VLOOKUP("외화환산이익",BS연결,MATCH(Y$1,BS연결H,0),0)-VLOOKUP("외화환산손실",BS연결,MATCH(Y$1,BS연결H,0),0))/100,"") | Z13: =SUM(V13:Y13) | AA13: =IFERROR((VLOOKUP("외환차익",BS연결,MATCH(AA$1,BS연결H,0),0)-VLOOKUP("외환차손",BS연결,MATCH(AA$1,BS연결H,0),0)+VLOOKUP("외화환산이익",BS연결,MATCH(AA$1,BS연결H,0),0)-VLOOKUP("외화환산손실",BS연결,MATCH(AA$1,BS연결H,0),0))/100,"") | AB13: =IFERROR((VLOOKUP("외환차익",BS연결,MATCH(AB$1,BS연결H,0),0)-VLOOKUP("외환차손",BS연결,MATCH(AB$1,BS연결H,0),0)+VLOOKUP("외화환산이익",BS연결,MATCH(AB$1,BS연결H,0),0)-VLOOKUP("외화환산손실",BS연결,MATCH(AB$1,BS연결H,0),0))/100,"") | AC13: =변수!AC24 | AD13: =변수!AD24 | AE13: =SUM(AA13:AD13) | AF13: =변수!AF24 | AG13: =변수!AG24 | AH13: =변수!AH24 | AI13: =변수!AI24 | AJ13: =SUM(AF13:AI13) | AK13: =변수!AK24 | AL13: =변수!AL24 | AM13: =변수!AM24 | AN13: =변수!AN24 | AO13: =SUM(AK13:AN13)
A14: 파생상품손익 | B14: 손익 | C14: 억원 | D14: 파생상품손익 | J14: =IFERROR((VLOOKUP("파생상품이익",BS연결,MATCH(J$1,BS연결H,0),0)-VLOOKUP("파생상품손실",BS연결,MATCH(J$1,BS연결H,0),0))/100,"") | K14: =SUM(G14:J14) | P14: =SUM(L14:O14) | U14: =SUM(Q14:T14) | Z14: =SUM(V14:Y14) | AC14: =변수!AC25 | AD14: =변수!AD25 | AE14: =SUM(AA14:AD14) | AF14: =변수!AF25 | AG14: =변수!AG25 | AH14: =변수!AH25 | AI14: =변수!AI25 | AJ14: =SUM(AF14:AI14) | AK14: =변수!AK25 | AL14: =변수!AL25 | AM14: =변수!AM25 | AN14: =변수!AN25 | AO14: =SUM(AK14:AN14)
A15: 기타금융손익 | B15: 손익 | C15: 억원 | D15: 기타금융손익(금융손익 잔차) | J15: =IFERROR(J11-J12-J13-J14,"") | K15: =SUM(G15:J15) | P15: =SUM(L15:O15) | U15: =SUM(Q15:T15) | Z15: =SUM(V15:Y15) | AC15: =변수!AC26 | AD15: =변수!AD26 | AE15: =SUM(AA15:AD15) | AF15: =변수!AF26 | AG15: =변수!AG26 | AH15: =변수!AH26 | AI15: =변수!AI26 | AJ15: =SUM(AF15:AI15) | AK15: =변수!AK26 | AL15: =변수!AL26 | AM15: =변수!AM26 | AN15: =변수!AN26 | AO15: =SUM(AK15:AN15)
A16: 기타영업외손익 | B16: 손익 | C16: 억원 | D16: 기타영업외손익 | E16: =IFERROR(VLOOKUP($D16,BS연결,MATCH(E$1,BS연결H,0),0)/100,"") | G16: =IFERROR(VLOOKUP($D16,BS연결,MATCH(G$1,BS연결H,0),0)/100,"") | H16: =IFERROR(VLOOKUP($D16,BS연결,MATCH(H$1,BS연결H,0),0)/100,"") | I16: =IFERROR(VLOOKUP($D16,BS연결,MATCH(I$1,BS연결H,0),0)/100,"") | J16: =IFERROR(VLOOKUP($D16,BS연결,MATCH(J$1,BS연결H,0),0)/100,"") | K16: =SUM(G16:J16) | L16: =IFERROR(VLOOKUP($D16,BS연결,MATCH(L$1,BS연결H,0),0)/100,"") | M16: =IFERROR(VLOOKUP($D16,BS연결,MATCH(M$1,BS연결H,0),0)/100,"") | N16: =IFERROR(VLOOKUP($D16,BS연결,MATCH(N$1,BS연결H,0),0)/100,"") | O16: =IFERROR(VLOOKUP($D16,BS연결,MATCH(O$1,BS연결H,0),0)/100,"") | P16: =IFERROR(VLOOKUP($D16,BS연결,MATCH(P$1,BS연결H,0),0)/100,"") | Q16: =IFERROR(VLOOKUP($D16,BS연결,MATCH(Q$1,BS연결H,0),0)/100,"") | R16: =IFERROR(VLOOKUP($D16,BS연결,MATCH(R$1,BS연결H,0),0)/100,"") | S16: =IFERROR(VLOOKUP($D16,BS연결,MATCH(S$1,BS연결H,0),0)/100,"") | ... AB16: =IFERROR(VLOOKUP($D16,BS연결,MATCH(AB$1,BS연결H,0),0)/100,"") | AC16: =변수!AC27 | AD16: =변수!AD27 | AE16: =SUM(AA16:AD16) | AF16: =변수!AF27 | AG16: =변수!AG27 | AH16: =변수!AH27 | AI16: =변수!AI27 | AJ16: =SUM(AF16:AI16) | AK16: =변수!AK27 | AL16: =변수!AL27 | AM16: =변수!AM27 | AN16: =변수!AN27 | AO16: =SUM(AK16:AN16)
A17: 지분법손익 | B17: 손익 | C17: 억원 | D17: 종속기업,공동지배기업및관계기업관련손익 | K17: =SUM(G17:J17) | P17: =SUM(L17:O17) | U17: =SUM(Q17:T17) | V17: =IFERROR(VLOOKUP($D17,BS연결,MATCH(V$1,BS연결H,0),0)/100,"") | W17: =IFERROR(VLOOKUP($D17,BS연결,MATCH(W$1,BS연결H,0),0)/100,"") | X17: =IFERROR(VLOOKUP($D17,BS연결,MATCH(X$1,BS연결H,0),0)/100,"") | Y17: =IFERROR(VLOOKUP($D17,BS연결,MATCH(Y$1,BS연결H,0),0)/100,"") | Z17: =IFERROR(VLOOKUP($D17,BS연결,MATCH(Z$1,BS연결H,0),0)/100,"") | AA17: =IFERROR(VLOOKUP($D17,BS연결,MATCH(AA$1,BS연결H,0),0)/100,"") | AB17: =IFERROR(VLOOKUP($D17,BS연결,MATCH(AB$1,BS연결H,0),0)/100,"") | AC17: =변수!AC28 | AD17: =변수!AD28 | AE17: =SUM(AA17:AD17) | AF17: =변수!AF28 | AG17: =변수!AG28 | AH17: =변수!AH28 | AI17: =변수!AI28 | AJ17: =SUM(AF17:AI17) | AK17: =변수!AK28 | AL17: =변수!AL28 | AM17: =변수!AM28 | AN17: =변수!AN28 | AO17: =SUM(AK17:AN17)
A18: 세전이익 | B18: 손익 | C18: 억원 | D18: 법인세비용차감전계속사업이익 | E18: =IFERROR(VLOOKUP($D18,BS연결,MATCH(E$1,BS연결H,0),0)/100,"") | G18: =IFERROR(VLOOKUP($D18,BS연결,MATCH(G$1,BS연결H,0),0)/100,"") | H18: =IFERROR(VLOOKUP($D18,BS연결,MATCH(H$1,BS연결H,0),0)/100,"") | I18: =IFERROR(VLOOKUP($D18,BS연결,MATCH(I$1,BS연결H,0),0)/100,"") | J18: =IFERROR(VLOOKUP($D18,BS연결,MATCH(J$1,BS연결H,0),0)/100,"") | K18: =IFERROR(VLOOKUP($D18,BS연결,MATCH(K$1,BS연결H,0),0)/100,"") | L18: =IFERROR(VLOOKUP($D18,BS연결,MATCH(L$1,BS연결H,0),0)/100,"") | M18: =IFERROR(VLOOKUP($D18,BS연결,MATCH(M$1,BS연결H,0),0)/100,"") | N18: =IFERROR(VLOOKUP($D18,BS연결,MATCH(N$1,BS연결H,0),0)/100,"") | ... U18: =IFERROR(VLOOKUP($D18,BS연결,MATCH(U$1,BS연결H,0),0)/100,"") | Z18: =SUM(V18:Y18) | AB18: =IFERROR(VLOOKUP($D18,BS연결,MATCH(AB$1,BS연결H,0),0)/100,"") | AC18: =IFERROR(AC9+AC11+AC16+AC17,"") | AD18: =IFERROR(AD9+AD11+AD16+AD17,"") | AE18: =SUM(AA18:AD18) | AF18: =IFERROR(AF9+AF11+AF16+AF17,"") | AG18: =IFERROR(AG9+AG11+AG16+AG17,"") | AH18: =IFERROR(AH9+AH11+AH16+AH17,"") | AI18: =IFERROR(AI9+AI11+AI16+AI17,"") | AJ18: =SUM(AF18:AI18) | AK18: =IFERROR(AK9+AK11+AK16+AK17,"") | AL18: =IFERROR(AL9+AL11+AL16+AL17,"") | AM18: =IFERROR(AM9+AM11+AM16+AM17,"") | AN18: =IFERROR(AN9+AN11+AN16+AN17,"") | AO18: =SUM(AK18:AN18)
A19: 법인세비용 | B19: 손익 | C19: 억원 | D19: 법인세비용 | K19: =SUM(G19:J19) | P19: =SUM(L19:O19) | R19: =IFERROR(VLOOKUP($D19,BS연결,MATCH(R$1,BS연결H,0),0)/100,"") | T19: =IFERROR(VLOOKUP($D19,BS연결,MATCH(T$1,BS연결H,0),0)/100,"") | U19: =SUM(Q19:T19) | V19: =IFERROR(VLOOKUP($D19,BS연결,MATCH(V$1,BS연결H,0),0)/100,"") | W19: =IFERROR(VLOOKUP($D19,BS연결,MATCH(W$1,BS연결H,0),0)/100,"") | X19: =IFERROR(VLOOKUP($D19,BS연결,MATCH(X$1,BS연결H,0),0)/100,"") | Y19: =IFERROR(VLOOKUP($D19,BS연결,MATCH(Y$1,BS연결H,0),0)/100,"") | Z19: =IFERROR(VLOOKUP($D19,BS연결,MATCH(Z$1,BS연결H,0),0)/100,"") | AA19: =IFERROR(VLOOKUP($D19,BS연결,MATCH(AA$1,BS연결H,0),0)/100,"") | AB19: =IFERROR(VLOOKUP($D19,BS연결,MATCH(AB$1,BS연결H,0),0)/100,"") | AC19: =IFERROR(AC18*변수!AC29,"") | AD19: =IFERROR(AD18*변수!AD29,"") | AE19: =SUM(AA19:AD19) | AF19: =IFERROR(AF18*변수!AF29,"") | AG19: =IFERROR(AG18*변수!AG29,"") | AH19: =IFERROR(AH18*변수!AH29,"") | AI19: =IFERROR(AI18*변수!AI29,"") | AJ19: =SUM(AF19:AI19) | AK19: =IFERROR(AK18*변수!AK29,"") | AL19: =IFERROR(AL18*변수!AL29,"") | AM19: =IFERROR(AM18*변수!AM29,"") | AN19: =IFERROR(AN18*변수!AN29,"") | AO19: =SUM(AK19:AN19)
A20: 당기순이익 | B20: 손익 | C20: 억원 | D20: 당기순이익 | E20: =IFERROR(VLOOKUP($D20,BS연결,MATCH(E$1,BS연결H,0),0)/100,"") | G20: =IFERROR(VLOOKUP($D20,BS연결,MATCH(G$1,BS연결H,0),0)/100,"") | H20: =IFERROR(VLOOKUP($D20,BS연결,MATCH(H$1,BS연결H,0),0)/100,"") | I20: =IFERROR(VLOOKUP($D20,BS연결,MATCH(I$1,BS연결H,0),0)/100,"") | J20: =IFERROR(VLOOKUP($D20,BS연결,MATCH(J$1,BS연결H,0),0)/100,"") | K20: =IFERROR(VLOOKUP($D20,BS연결,MATCH(K$1,BS연결H,0),0)/100,"") | L20: =IFERROR(VLOOKUP($D20,BS연결,MATCH(L$1,BS연결H,0),0)/100,"") | M20: =IFERROR(VLOOKUP($D20,BS연결,MATCH(M$1,BS연결H,0),0)/100,"") | N20: =IFERROR(VLOOKUP($D20,BS연결,MATCH(N$1,BS연결H,0),0)/100,"") | ... AB20: =IFERROR(VLOOKUP($D20,BS연결,MATCH(AB$1,BS연결H,0),0)/100,"") | AC20: =IFERROR(AC18-AC19,"") | AD20: =IFERROR(AD18-AD19,"") | AE20: =SUM(AA20:AD20) | AF20: =IFERROR(AF18-AF19,"") | AG20: =IFERROR(AG18-AG19,"") | AH20: =IFERROR(AH18-AH19,"") | AI20: =IFERROR(AI18-AI19,"") | AJ20: =SUM(AF20:AI20) | AK20: =IFERROR(AK18-AK19,"") | AL20: =IFERROR(AL18-AL19,"") | AM20: =IFERROR(AM18-AM19,"") | AN20: =IFERROR(AN18-AN19,"") | AO20: =SUM(AK20:AN20)
A21: 지배주주순이익 | B21: 손익 | C21: 억원 | D21: (지배주주지분)당기순이익 | E21: =IFERROR(VLOOKUP($D21,BS연결,MATCH(E$1,BS연결H,0),0)/100,"") | G21: =IFERROR(VLOOKUP($D21,BS연결,MATCH(G$1,BS연결H,0),0)/100,"") | H21: =IFERROR(VLOOKUP($D21,BS연결,MATCH(H$1,BS연결H,0),0)/100,"") | I21: =IFERROR(VLOOKUP($D21,BS연결,MATCH(I$1,BS연결H,0),0)/100,"") | J21: =IFERROR(VLOOKUP($D21,BS연결,MATCH(J$1,BS연결H,0),0)/100,"") | K21: =IFERROR(VLOOKUP($D21,BS연결,MATCH(K$1,BS연결H,0),0)/100,"") | L21: =IFERROR(VLOOKUP($D21,BS연결,MATCH(L$1,BS연결H,0),0)/100,"") | M21: =IFERROR(VLOOKUP($D21,BS연결,MATCH(M$1,BS연결H,0),0)/100,"") | N21: =IFERROR(VLOOKUP($D21,BS연결,MATCH(N$1,BS연결H,0),0)/100,"") | ... AB21: =IFERROR(VLOOKUP($D21,BS연결,MATCH(AB$1,BS연결H,0),0)/100,"") | AC21: =IFERROR(AC20*변수!AC30,"") | AD21: =IFERROR(AD20*변수!AD30,"") | AE21: =SUM(AA21:AD21) | AF21: =IFERROR(AF20*변수!AF30,"") | AG21: =IFERROR(AG20*변수!AG30,"") | AH21: =IFERROR(AH20*변수!AH30,"") | AI21: =IFERROR(AI20*변수!AI30,"") | AJ21: =SUM(AF21:AI21) | AK21: =IFERROR(AK20*변수!AK30,"") | AL21: =IFERROR(AL20*변수!AL30,"") | AM21: =IFERROR(AM20*변수!AM30,"") | AN21: =IFERROR(AN20*변수!AN30,"") | AO21: =SUM(AK21:AN21)
A22: 자산총계 | B22: 재무상태 | C22: 억원 | D22: 자산총계 | E22: =IFERROR(VLOOKUP($D22,BS연결,MATCH(E$1,BS연결H,0),0)/100,"") | F22: =IFERROR(VLOOKUP($D22,BS연결,MATCH(F$1,BS연결H,0),0)/100,"") | G22: =IFERROR(VLOOKUP($D22,BS연결,MATCH(G$1,BS연결H,0),0)/100,"") | H22: =IFERROR(VLOOKUP($D22,BS연결,MATCH(H$1,BS연결H,0),0)/100,"") | I22: =IFERROR(VLOOKUP($D22,BS연결,MATCH(I$1,BS연결H,0),0)/100,"") | J22: =IFERROR(VLOOKUP($D22,BS연결,MATCH(J$1,BS연결H,0),0)/100,"") | K22: =IFERROR(VLOOKUP($D22,BS연결,MATCH(K$1,BS연결H,0),0)/100,"") | L22: =IFERROR(VLOOKUP($D22,BS연결,MATCH(L$1,BS연결H,0),0)/100,"") | ... AB22: =IFERROR(VLOOKUP($D22,BS연결,MATCH(AB$1,BS연결H,0),0)/100,"") | AC22: =IFERROR(AC23+AC24,"") | AD22: =IFERROR(AD23+AD24,"") | AE22: =AD22 | AF22: =IFERROR(AF23+AF24,"") | AG22: =IFERROR(AG23+AG24,"") | AH22: =IFERROR(AH23+AH24,"") | AI22: =IFERROR(AI23+AI24,"") | AJ22: =AI22 | AK22: =IFERROR(AK23+AK24,"") | AL22: =IFERROR(AL23+AL24,"") | AM22: =IFERROR(AM23+AM24,"") | AN22: =IFERROR(AN23+AN24,"") | AO22: =AN22
A23: 부채총계 | B23: 재무상태 | C23: 억원 | D23: 부채총계 | E23: =IFERROR(VLOOKUP($D23,BS연결,MATCH(E$1,BS연결H,0),0)/100,"") | F23: =IFERROR(VLOOKUP($D23,BS연결,MATCH(F$1,BS연결H,0),0)/100,"") | G23: =IFERROR(VLOOKUP($D23,BS연결,MATCH(G$1,BS연결H,0),0)/100,"") | H23: =IFERROR(VLOOKUP($D23,BS연결,MATCH(H$1,BS연결H,0),0)/100,"") | I23: =IFERROR(VLOOKUP($D23,BS연결,MATCH(I$1,BS연결H,0),0)/100,"") | J23: =IFERROR(VLOOKUP($D23,BS연결,MATCH(J$1,BS연결H,0),0)/100,"") | K23: =IFERROR(VLOOKUP($D23,BS연결,MATCH(K$1,BS연결H,0),0)/100,"") | L23: =IFERROR(VLOOKUP($D23,BS연결,MATCH(L$1,BS연결H,0),0)/100,"") | ... AB23: =IFERROR(VLOOKUP($D23,BS연결,MATCH(AB$1,BS연결H,0),0)/100,"") | AC23: =IFERROR(AB23*(1+변수!AC31),"") | AD23: =IFERROR(AC23*(1+변수!AD31),"") | AE23: =AD23 | AF23: =IFERROR(AD23*(1+변수!AF31),"") | AG23: =IFERROR(AF23*(1+변수!AG31),"") | AH23: =IFERROR(AG23*(1+변수!AH31),"") | AI23: =IFERROR(AH23*(1+변수!AI31),"") | AJ23: =AI23 | AK23: =IFERROR(AI23*(1+변수!AK31),"") | AL23: =IFERROR(AK23*(1+변수!AL31),"") | AM23: =IFERROR(AL23*(1+변수!AM31),"") | AN23: =IFERROR(AM23*(1+변수!AN31),"") | AO23: =AN23
A24: 자본총계 | B24: 재무상태 | C24: 억원 | D24: 자본총계 | E24: =IFERROR(VLOOKUP($D24,BS연결,MATCH(E$1,BS연결H,0),0)/100,"") | F24: =IFERROR(VLOOKUP($D24,BS연결,MATCH(F$1,BS연결H,0),0)/100,"") | G24: =IFERROR(VLOOKUP($D24,BS연결,MATCH(G$1,BS연결H,0),0)/100,"") | H24: =IFERROR(VLOOKUP($D24,BS연결,MATCH(H$1,BS연결H,0),0)/100,"") | I24: =IFERROR(VLOOKUP($D24,BS연결,MATCH(I$1,BS연결H,0),0)/100,"") | J24: =IFERROR(VLOOKUP($D24,BS연결,MATCH(J$1,BS연결H,0),0)/100,"") | K24: =IFERROR(VLOOKUP($D24,BS연결,MATCH(K$1,BS연결H,0),0)/100,"") | L24: =IFERROR(VLOOKUP($D24,BS연결,MATCH(L$1,BS연결H,0),0)/100,"") | ... AB24: =IFERROR(VLOOKUP($D24,BS연결,MATCH(AB$1,BS연결H,0),0)/100,"") | AC24: =IFERROR(AB24+AC20-변수!AC32,"") | AD24: =IFERROR(AC24+AD20-변수!AD32,"") | AE24: =AD24 | AF24: =IFERROR(AD24+AF20-변수!AF32,"") | AG24: =IFERROR(AF24+AG20-변수!AG32,"") | AH24: =IFERROR(AG24+AH20-변수!AH32,"") | AI24: =IFERROR(AH24+AI20-변수!AI32,"") | AJ24: =AI24 | AK24: =IFERROR(AI24+AK20-변수!AK32,"") | AL24: =IFERROR(AK24+AL20-변수!AL32,"") | AM24: =IFERROR(AL24+AM20-변수!AM32,"") | AN24: =IFERROR(AM24+AN20-변수!AN32,"") | AO24: =AN24
A25: 지배주주지분 | B25: 재무상태 | C25: 억원 | D25: 지배주주지분 | E25: =IFERROR(VLOOKUP($D25,BS연결,MATCH(E$1,BS연결H,0),0)/100,"") | F25: =IFERROR(VLOOKUP($D25,BS연결,MATCH(F$1,BS연결H,0),0)/100,"") | G25: =IFERROR(VLOOKUP($D25,BS연결,MATCH(G$1,BS연결H,0),0)/100,"") | H25: =IFERROR(VLOOKUP($D25,BS연결,MATCH(H$1,BS연결H,0),0)/100,"") | I25: =IFERROR(VLOOKUP($D25,BS연결,MATCH(I$1,BS연결H,0),0)/100,"") | J25: =IFERROR(VLOOKUP($D25,BS연결,MATCH(J$1,BS연결H,0),0)/100,"") | K25: =IFERROR(VLOOKUP($D25,BS연결,MATCH(K$1,BS연결H,0),0)/100,"") | L25: =IFERROR(VLOOKUP($D25,BS연결,MATCH(L$1,BS연결H,0),0)/100,"") | ... AB25: =IFERROR(VLOOKUP($D25,BS연결,MATCH(AB$1,BS연결H,0),0)/100,"") | AC25: =IFERROR(AB25+AC21-변수!AC33,"") | AD25: =IFERROR(AC25+AD21-변수!AD33,"") | AE25: =AD25 | AF25: =IFERROR(AD25+AF21-변수!AF33,"") | AG25: =IFERROR(AF25+AG21-변수!AG33,"") | AH25: =IFERROR(AG25+AH21-변수!AH33,"") | AI25: =IFERROR(AH25+AI21-변수!AI33,"") | AJ25: =AI25 | AK25: =IFERROR(AI25+AK21-변수!AK33,"") | AL25: =IFERROR(AK25+AL21-변수!AL33,"") | AM25: =IFERROR(AL25+AM21-변수!AM33,"") | AN25: =IFERROR(AM25+AN21-변수!AN33,"") | AO25: =AN25
A26: 총차입금 | B26: 재무상태 | C26: 억원 | D26: 총차입금 | E26: =IFERROR(VLOOKUP($D26,BS연결,MATCH(E$1,BS연결H,0),0)/100,"") | F26: =IFERROR(VLOOKUP($D26,BS연결,MATCH(F$1,BS연결H,0),0)/100,"") | G26: =IFERROR(VLOOKUP($D26,BS연결,MATCH(G$1,BS연결H,0),0)/100,"") | H26: =IFERROR(VLOOKUP($D26,BS연결,MATCH(H$1,BS연결H,0),0)/100,"") | I26: =IFERROR(VLOOKUP($D26,BS연결,MATCH(I$1,BS연결H,0),0)/100,"") | J26: =IFERROR(VLOOKUP($D26,BS연결,MATCH(J$1,BS연결H,0),0)/100,"") | K26: =IFERROR(VLOOKUP($D26,BS연결,MATCH(K$1,BS연결H,0),0)/100,"") | L26: =IFERROR(VLOOKUP($D26,BS연결,MATCH(L$1,BS연결H,0),0)/100,"") | ... AB26: =IFERROR(VLOOKUP($D26,BS연결,MATCH(AB$1,BS연결H,0),0)/100,"") | AC26: =IFERROR(AB26*(1+변수!AC34),"") | AD26: =IFERROR(AC26*(1+변수!AD34),"") | AE26: =AD26 | AF26: =IFERROR(AD26*(1+변수!AF34),"") | AG26: =IFERROR(AF26*(1+변수!AG34),"") | AH26: =IFERROR(AG26*(1+변수!AH34),"") | AI26: =IFERROR(AH26*(1+변수!AI34),"") | AJ26: =AI26 | AK26: =IFERROR(AI26*(1+변수!AK34),"") | AL26: =IFERROR(AK26*(1+변수!AL34),"") | AM26: =IFERROR(AL26*(1+변수!AM34),"") | AN26: =IFERROR(AM26*(1+변수!AN34),"") | AO26: =AN26
A27: 순차입금 | B27: 재무상태 | C27: 억원 | D27: 순차입금 | E27: =IFERROR(VLOOKUP($D27,BS연결,MATCH(E$1,BS연결H,0),0)/100,"") | F27: =IFERROR(VLOOKUP($D27,BS연결,MATCH(F$1,BS연결H,0),0)/100,"") | G27: =IFERROR(VLOOKUP($D27,BS연결,MATCH(G$1,BS연결H,0),0)/100,"") | H27: =IFERROR(VLOOKUP($D27,BS연결,MATCH(H$1,BS연결H,0),0)/100,"") | I27: =IFERROR(VLOOKUP($D27,BS연결,MATCH(I$1,BS연결H,0),0)/100,"") | J27: =IFERROR(VLOOKUP($D27,BS연결,MATCH(J$1,BS연결H,0),0)/100,"") | K27: =IFERROR(VLOOKUP($D27,BS연결,MATCH(K$1,BS연결H,0),0)/100,"") | L27: =IFERROR(VLOOKUP($D27,BS연결,MATCH(L$1,BS연결H,0),0)/100,"") | ... AB27: =IFERROR(VLOOKUP($D27,BS연결,MATCH(AB$1,BS연결H,0),0)/100,"") | AC27: =IFERROR(AB27*(1+변수!AC35),"") | AD27: =IFERROR(AC27*(1+변수!AD35),"") | AE27: =AD27 | AF27: =IFERROR(AD27*(1+변수!AF35),"") | AG27: =IFERROR(AF27*(1+변수!AG35),"") | AH27: =IFERROR(AG27*(1+변수!AH35),"") | AI27: =IFERROR(AH27*(1+변수!AI35),"") | AJ27: =AI27 | AK27: =IFERROR(AI27*(1+변수!AK35),"") | AL27: =IFERROR(AK27*(1+변수!AL35),"") | AM27: =IFERROR(AL27*(1+변수!AM35),"") | AN27: =IFERROR(AM27*(1+변수!AN35),"") | AO27: =AN27
A28: 이자발생자산 | B28: 재무상태 | C28: 억원 | D28: 이자발생자산 | E28: =IFERROR(VLOOKUP($D28,BS연결,MATCH(E$1,BS연결H,0),0)/100,"") | F28: =IFERROR(VLOOKUP($D28,BS연결,MATCH(F$1,BS연결H,0),0)/100,"") | G28: =IFERROR(VLOOKUP($D28,BS연결,MATCH(G$1,BS연결H,0),0)/100,"") | H28: =IFERROR(VLOOKUP($D28,BS연결,MATCH(H$1,BS연결H,0),0)/100,"") | I28: =IFERROR(VLOOKUP($D28,BS연결,MATCH(I$1,BS연결H,0),0)/100,"") | J28: =IFERROR(VLOOKUP($D28,BS연결,MATCH(J$1,BS연결H,0),0)/100,"") | K28: =IFERROR(VLOOKUP($D28,BS연결,MATCH(K$1,BS연결H,0),0)/100,"") | L28: =IFERROR(VLOOKUP($D28,BS연결,MATCH(L$1,BS연결H,0),0)/100,"") | ... AB28: =IFERROR(VLOOKUP($D28,BS연결,MATCH(AB$1,BS연결H,0),0)/100,"") | AC28: =IFERROR(AB28*(1+변수!AC36),"") | AD28: =IFERROR(AC28*(1+변수!AD36),"") | AE28: =AD28 | AF28: =IFERROR(AD28*(1+변수!AF36),"") | AG28: =IFERROR(AF28*(1+변수!AG36),"") | AH28: =IFERROR(AG28*(1+변수!AH36),"") | AI28: =IFERROR(AH28*(1+변수!AI36),"") | AJ28: =AI28 | AK28: =IFERROR(AI28*(1+변수!AK36),"") | AL28: =IFERROR(AK28*(1+변수!AL36),"") | AM28: =IFERROR(AL28*(1+변수!AM36),"") | AN28: =IFERROR(AM28*(1+변수!AN36),"") | AO28: =AN28
A29: 현금및현금성자산 | B29: 재무상태 | C29: 억원 | D29: 현금및현금성자산 | E29: =IFERROR(VLOOKUP($D29,BS연결,MATCH(E$1,BS연결H,0),0)/100,"") | F29: =IFERROR(VLOOKUP($D29,BS연결,MATCH(F$1,BS연결H,0),0)/100,"") | G29: =IFERROR(VLOOKUP($D29,BS연결,MATCH(G$1,BS연결H,0),0)/100,"") | H29: =IFERROR(VLOOKUP($D29,BS연결,MATCH(H$1,BS연결H,0),0)/100,"") | I29: =IFERROR(VLOOKUP($D29,BS연결,MATCH(I$1,BS연결H,0),0)/100,"") | J29: =IFERROR(VLOOKUP($D29,BS연결,MATCH(J$1,BS연결H,0),0)/100,"") | K29: =IFERROR(VLOOKUP($D29,BS연결,MATCH(K$1,BS연결H,0),0)/100,"") | L29: =IFERROR(VLOOKUP($D29,BS연결,MATCH(L$1,BS연결H,0),0)/100,"") | ... AB29: =IFERROR(VLOOKUP($D29,BS연결,MATCH(AB$1,BS연결H,0),0)/100,"") | AE29: =AD29 | AJ29: =AI29 | AO29: =AN29
A30: CAPEX | B30: 현금흐름 | C30: 억원 | D30: CAPEX | E30: =IFERROR(VLOOKUP($D30,BS연결,MATCH(E$1,BS연결H,0),0)/100,"") | G30: =IFERROR(VLOOKUP($D30,BS연결,MATCH(G$1,BS연결H,0),0)/100,"") | H30: =IFERROR(VLOOKUP($D30,BS연결,MATCH(H$1,BS연결H,0),0)/100,"") | I30: =IFERROR(VLOOKUP($D30,BS연결,MATCH(I$1,BS연결H,0),0)/100,"") | J30: =IFERROR(VLOOKUP($D30,BS연결,MATCH(J$1,BS연결H,0),0)/100,"") | K30: =IFERROR(VLOOKUP($D30,BS연결,MATCH(K$1,BS연결H,0),0)/100,"") | L30: =IFERROR(VLOOKUP($D30,BS연결,MATCH(L$1,BS연결H,0),0)/100,"") | M30: =IFERROR(VLOOKUP($D30,BS연결,MATCH(M$1,BS연결H,0),0)/100,"") | N30: =IFERROR(VLOOKUP($D30,BS연결,MATCH(N$1,BS연결H,0),0)/100,"") | ... AB30: =IFERROR(VLOOKUP($D30,BS연결,MATCH(AB$1,BS연결H,0),0)/100,"") | AC30: =IFERROR(X30*(1+변수!AC38),"") | AD30: =IFERROR(Y30*(1+변수!AD38),"") | AE30: =SUM(AA30:AD30) | AF30: =IFERROR(AA30*(1+변수!AF38),"") | AG30: =IFERROR(AB30*(1+변수!AG38),"") | AH30: =IFERROR(AC30*(1+변수!AH38),"") | AI30: =IFERROR(AD30*(1+변수!AI38),"") | AJ30: =SUM(AF30:AI30) | AK30: =IFERROR(AF30*(1+변수!AK38),"") | AL30: =IFERROR(AG30*(1+변수!AL38),"") | AM30: =IFERROR(AH30*(1+변수!AM38),"") | AN30: =IFERROR(AI30*(1+변수!AN38),"") | AO30: =SUM(AK30:AN30)
A31: 영업활동현금흐름 | B31: 현금흐름 | C31: 억원 | D31: 영업활동으로인한현금흐름 | E31: =IFERROR(VLOOKUP($D31,BS연결,MATCH(E$1,BS연결H,0),0)/100,"") | G31: =IFERROR(VLOOKUP($D31,BS연결,MATCH(G$1,BS연결H,0),0)/100,"") | H31: =IFERROR(VLOOKUP($D31,BS연결,MATCH(H$1,BS연결H,0),0)/100,"") | I31: =IFERROR(VLOOKUP($D31,BS연결,MATCH(I$1,BS연결H,0),0)/100,"") | J31: =IFERROR(VLOOKUP($D31,BS연결,MATCH(J$1,BS연결H,0),0)/100,"") | K31: =IFERROR(VLOOKUP($D31,BS연결,MATCH(K$1,BS연결H,0),0)/100,"") | L31: =IFERROR(VLOOKUP($D31,BS연결,MATCH(L$1,BS연결H,0),0)/100,"") | M31: =IFERROR(VLOOKUP($D31,BS연결,MATCH(M$1,BS연결H,0),0)/100,"") | N31: =IFERROR(VLOOKUP($D31,BS연결,MATCH(N$1,BS연결H,0),0)/100,"") | ... AB31: =IFERROR(VLOOKUP($D31,BS연결,MATCH(AB$1,BS연결H,0),0)/100,"") | AE31: =SUM(AA31:AD31) | AJ31: =SUM(AF31:AI31) | AO31: =SUM(AK31:AN31)
A32: 주식수 | B32: 주당 | C32: 백만주 | D32: 유통주식수 | E32: 26.895 | F32: =E32 | G32: 26.895 | H32: 26.895 | I32: 27.246 | J32: 27.246 | K32: =J32 | L32: 28.93 | M32: 30.346 | N32: 30.668 | O32: 30.668 | P32: =O32 | Q32: 30.668 | R32: 30.668 | S32: 30.668 | T32: 30.668 | U32: =T32 | V32: 30.668 | W32: 30.668 | X32: 30.668 | Y32: 30.668 | Z32: =Y32 | AA32: 30.668 | AB32: 30.668 | AC32: =IFERROR(AB32*(1+변수!AC40),"") | AD32: =IFERROR(AC32*(1+변수!AD40),"") | AE32: =AD32 | AF32: =IFERROR(AD32*(1+변수!AF40),"") | AG32: =IFERROR(AF32*(1+변수!AG40),"") | AH32: =IFERROR(AG32*(1+변수!AH40),"") | AI32: =IFERROR(AH32*(1+변수!AI40),"") | AJ32: =AI32 | AK32: =IFERROR(AI32*(1+변수!AK40),"") | AL32: =IFERROR(AK32*(1+변수!AL40),"") | AM32: =IFERROR(AL32*(1+변수!AM40),"") | AN32: =IFERROR(AM32*(1+변수!AN40),"") | AO32: =AN32
A33: EPS | B33: 주당 | C33: 원 | D33: EPS | E33: =IFERROR(E21*100/E32,"") | G33: =IFERROR(G21*100/G32,"") | H33: =IFERROR(H21*100/H32,"") | I33: =IFERROR(I21*100/I32,"") | J33: =IFERROR(J21*100/J32,"") | K33: =SUM(G33:J33) | L33: =IFERROR(L21*100/L32,"") | M33: =IFERROR(M21*100/M32,"") | N33: =IFERROR(N21*100/N32,"") | O33: =IFERROR(O21*100/O32,"") | P33: =SUM(L33:O33) | Q33: =IFERROR(Q21*100/Q32,"") | R33: =IFERROR(R21*100/R32,"") | S33: =IFERROR(S21*100/S32,"") | T33: =IFERROR(T21*100/T32,"") | U33: =SUM(Q33:T33) | V33: =IFERROR(V21*100/V32,"") | W33: =IFERROR(W21*100/W32,"") | X33: =IFERROR(X21*100/X32,"") | Y33: =IFERROR(Y21*100/Y32,"") | Z33: =SUM(V33:Y33) | AA33: =IFERROR(AA21*100/AA32,"") | AB33: =IFERROR(AB21*100/AB32,"") | AC33: =IFERROR(AC21*100/AC32,"") | AD33: =IFERROR(AD21*100/AD32,"") | AE33: =SUM(AA33:AD33) | AF33: =IFERROR(AF21*100/AF32,"") | AG33: =IFERROR(AG21*100/AG32,"") | AH33: =IFERROR(AH21*100/AH32,"") | AI33: =IFERROR(AI21*100/AI32,"") | AJ33: =SUM(AF33:AI33) | AK33: =IFERROR(AK21*100/AK32,"") | AL33: =IFERROR(AL21*100/AL32,"") | AM33: =IFERROR(AM21*100/AM32,"") | AN33: =IFERROR(AN21*100/AN32,"") | AO33: =SUM(AK33:AN33)
A34: 조정EPS | B34: 주당 | C34: 원 | D34: 조정 EPS(일회성 의심 분기의 초과 비영업손익 세후 차감 — 모델 추정) | E34: =IFERROR(E33,"") | G34: =IFERROR(G33,"") | H34: =IFERROR(H33,"") | I34: =IFERROR(I33,"") | J34: =IFERROR(J33,"") | K34: =SUM(G34:J34) | L34: =IFERROR(L33,"") | M34: =IFERROR(M33,"") | N34: =IFERROR(N33,"") | O34: =IFERROR(O33,"") | P34: =SUM(L34:O34) | Q34: =IFERROR(Q33,"") | R34: =IFERROR(R33,"") | S34: =IFERROR(S33,"") | T34: =IFERROR((T21-(210.03)*(0.9776))*100/T32,"") | U34: =SUM(Q34:T34) | V34: =IFERROR(V33,"") | W34: =IFERROR(W33,"") | X34: =IFERROR(X33,"") | Y34: =IFERROR(Y33,"") | Z34: =SUM(V34:Y34) | AA34: =IFERROR(AA33,"") | AB34: =IFERROR(AB33,"") | AC34: =IFERROR(AC33,"") | AD34: =IFERROR(AD33,"") | AE34: =SUM(AA34:AD34) | AF34: =IFERROR(AF33,"") | AG34: =IFERROR(AG33,"") | AH34: =IFERROR(AH33,"") | AI34: =IFERROR(AI33,"") | AJ34: =SUM(AF34:AI34) | AK34: =IFERROR(AK33,"") | AL34: =IFERROR(AL33,"") | AM34: =IFERROR(AM33,"") | AN34: =IFERROR(AN33,"") | AO34: =SUM(AK34:AN34)
A35: BPS | B35: 주당 | C35: 원 | D35: BPS | E35: =IFERROR(E25*100/E32,"") | F35: =E35 | G35: =IFERROR(G25*100/G32,"") | H35: =IFERROR(H25*100/H32,"") | I35: =IFERROR(I25*100/I32,"") | J35: =IFERROR(J25*100/J32,"") | K35: =J35 | L35: =IFERROR(L25*100/L32,"") | M35: =IFERROR(M25*100/M32,"") | N35: =IFERROR(N25*100/N32,"") | O35: =IFERROR(O25*100/O32,"") | P35: =O35 | Q35: =IFERROR(Q25*100/Q32,"") | R35: =IFERROR(R25*100/R32,"") | S35: =IFERROR(S25*100/S32,"") | T35: =IFERROR(T25*100/T32,"") | U35: =T35 | V35: =IFERROR(V25*100/V32,"") | W35: =IFERROR(W25*100/W32,"") | X35: =IFERROR(X25*100/X32,"") | Y35: =IFERROR(Y25*100/Y32,"") | Z35: =Y35 | AA35: =IFERROR(AA25*100/AA32,"") | AB35: =IFERROR(AB25*100/AB32,"") | AC35: =IFERROR(AC25*100/AC32,"") | AD35: =IFERROR(AD25*100/AD32,"") | AE35: =AD35 | AF35: =IFERROR(AF25*100/AF32,"") | AG35: =IFERROR(AG25*100/AG32,"") | AH35: =IFERROR(AH25*100/AH32,"") | AI35: =IFERROR(AI25*100/AI32,"") | AJ35: =AI35 | AK35: =IFERROR(AK25*100/AK32,"") | AL35: =IFERROR(AL25*100/AL32,"") | AM35: =IFERROR(AM25*100/AM32,"") | AN35: =IFERROR(AN25*100/AN32,"") | AO35: =AN35
A36: DPS | B36: 주당 | C36: 원 | D36: DPS(보통주) | E36: 0 | F36: 0 | J36: 0 | K36: =SUM(G36:J36) | O36: 0 | P36: =SUM(L36:O36) | T36: 0 | U36: =SUM(Q36:T36) | Y36: 0 | Z36: =SUM(V36:Y36) | AD36: =변수!AD41 | AE36: =SUM(AA36:AD36) | AI36: =변수!AI41 | AJ36: =SUM(AF36:AI36) | AN36: =변수!AN41 | AO36: =SUM(AK36:AN36)
A37: PER | B37: 주당 | C37: 배 | D37: PER | F37: =E37 | K37: =J37 | P37: =O37 | R37: =IFERROR(변수!R18/(N33+O33+Q33+R33),"") | U37: =T37 | W37: =IFERROR(변수!W18/(S33+T33+V33+W33),"") | X37: =IFERROR(변수!X18/(T33+V33+W33+X33),"") | Y37: =IFERROR(변수!Y18/(V33+W33+X33+Y33),"") | Z37: =Y37 | AA37: =IFERROR(변수!AA18/(W33+X33+Y33+AA33),"") | AE37: =AD37 | AJ37: =AI37 | AO37: =AN37
A38: PBR | B38: 주당 | C38: 배 | D38: PBR | E38: =IFERROR(변수!E18/E35,"") | F38: =E38 | G38: =IFERROR(변수!G18/G35,"") | H38: =IFERROR(변수!H18/H35,"") | I38: =IFERROR(변수!I18/I35,"") | J38: =IFERROR(변수!J18/J35,"") | K38: =J38 | L38: =IFERROR(변수!L18/L35,"") | M38: =IFERROR(변수!M18/M35,"") | N38: =IFERROR(변수!N18/N35,"") | O38: =IFERROR(변수!O18/O35,"") | P38: =O38 | Q38: =IFERROR(변수!Q18/Q35,"") | R38: =IFERROR(변수!R18/R35,"") | U38: =T38 | W38: =IFERROR(변수!W18/W35,"") | X38: =IFERROR(변수!X18/X35,"") | Y38: =IFERROR(변수!Y18/Y35,"") | Z38: =Y38 | AA38: =IFERROR(변수!AA18/AA35,"") | AB38: =IFERROR(변수!AB18/AB35,"") | AC38: =IFERROR(변수!$D$44/AC35,"") | AD38: =IFERROR(변수!$D$44/AD35,"") | AE38: =AD38 | AF38: =IFERROR(변수!$D$44/AF35,"") | AG38: =IFERROR(변수!$D$44/AG35,"") | AH38: =IFERROR(변수!$D$44/AH35,"") | AI38: =IFERROR(변수!$D$44/AI35,"") | AJ38: =AI38 | AK38: =IFERROR(변수!$D$44/AK35,"") | AL38: =IFERROR(변수!$D$44/AL35,"") | AM38: =IFERROR(변수!$D$44/AM35,"") | AN38: =IFERROR(변수!$D$44/AN35,"") | AO38: =AN38
A39: 매출전사 | B39: 사업부 | C39: 억원 | D39: 매출 전사(부문 미분리) | E39: 180.06 | G39: 109.98 | H39: 205.03 | I39: 222.93 | J39: 128.85 | K39: =SUM(G39:J39) | L39: 176.42 | M39: 264.81 | N39: 232.63 | O39: 206.9 | P39: =SUM(L39:O39) | Q39: 187.57 | R39: 229.49 | S39: 258.44 | T39: 210.51 | U39: =SUM(Q39:T39) | V39: 136.62 | W39: 157.66 | X39: 344.65 | Y39: 217.83 | Z39: =SUM(V39:Y39) | AA39: 110.35 | AB39: 259.5 | AC39: =IFERROR(AC5,"") | AD39: =IFERROR(AD5,"") | AE39: =SUM(AA39:AD39) | AF39: =IFERROR(AF5,"") | AG39: =IFERROR(AG5,"") | AH39: =IFERROR(AH5,"") | AI39: =IFERROR(AI5,"") | AJ39: =SUM(AF39:AI39) | AK39: =IFERROR(AK5,"") | AL39: =IFERROR(AL5,"") | AM39: =IFERROR(AM5,"") | AN39: =IFERROR(AN5,"") | AO39: =SUM(AK39:AN39)
A40: OP전사 | B40: 사업부 | C40: 억원 | D40: OP 전사(부문 미분리) | E40: 4.02 | G40: 3.88 | H40: -7.36 | I40: -10.63 | J40: -21.14 | K40: =SUM(G40:J40) | L40: -20.25 | M40: 19.39 | N40: 5.77 | O40: 11.32 | P40: =SUM(L40:O40) | Q40: 8.66 | R40: 23.66 | S40: 5.2 | T40: -20.94 | U40: =SUM(Q40:T40) | V40: -2.64 | W40: 0.15 | X40: 55.18 | Y40: 2.58 | Z40: =SUM(V40:Y40) | AA40: -8.89 | AB40: 5.83 | AC40: =IFERROR(AC9,"") | AD40: =IFERROR(AD9,"") | AE40: =SUM(AA40:AD40) | AF40: =IFERROR(AF9,"") | AG40: =IFERROR(AG9,"") | AH40: =IFERROR(AH9,"") | AI40: =IFERROR(AI9,"") | AJ40: =SUM(AF40:AI40) | AK40: =IFERROR(AK9,"") | AL40: =IFERROR(AL9,"") | AM40: =IFERROR(AM9,"") | AN40: =IFERROR(AN9,"") | AO40: =SUM(AK40:AN40)
B41: 비율(참고)
A42: NPM | C42: % | D42: 지배주주순이익 / 매출액 | E42: =IFERROR(E21/E5,"") | F42: =IFERROR(F21/F5,"") | G42: =IFERROR(G21/G5,"") | H42: =IFERROR(H21/H5,"") | I42: =IFERROR(I21/I5,"") | J42: =IFERROR(J21/J5,"") | K42: =IFERROR(K21/K5,"") | L42: =IFERROR(L21/L5,"") | ... AO42: =IFERROR(AO21/AO5,"")
A43: 매출원가율 | C43: % | D43: 매출원가 / 매출액 | E43: =IFERROR(E6/E5,"") | F43: =IFERROR(F6/F5,"") | G43: =IFERROR(G6/G5,"") | H43: =IFERROR(H6/H5,"") | I43: =IFERROR(I6/I5,"") | J43: =IFERROR(J6/J5,"") | K43: =IFERROR(K6/K5,"") | L43: =IFERROR(L6/L5,"") | ... AO43: =IFERROR(AO6/AO5,"")
A44: 판관비율 | C44: % | D44: 판관비 / 매출액 | E44: =IFERROR(E8/E5,"") | F44: =IFERROR(F8/F5,"") | G44: =IFERROR(G8/G5,"") | H44: =IFERROR(H8/H5,"") | I44: =IFERROR(I8/I5,"") | J44: =IFERROR(J8/J5,"") | K44: =IFERROR(K8/K5,"") | L44: =IFERROR(L8/L5,"") | ... AO44: =IFERROR(AO8/AO5,"")

Sheet 분기
C1: 이름: 분기H — subQ 를 이름으로 VLOOKUP(억원) | E1: 4Q21 | F1: 1Q22 | G1: 2Q22 | H1: 3Q22 | I1: 4Q22 | J1: 1Q23 | K1: 2Q23 | L1: 3Q23 | M1: 4Q23 | N1: 1Q24 | O1: 2Q24 | P1: 3Q24 | Q1: 4Q24 | R1: 1Q25 | S1: 2Q25 | T1: 3Q25 | U1: 4Q25 | V1: 1Q26 | W1: 2Q26 | X1: 3Q26 | Y1: 4Q26 | Z1: 1Q27 | AA1: 2Q27 | AB1: 3Q27 | AC1: 4Q27 | AD1: 1Q28 | AE1: 2Q28 | AF1: 3Q28 | AG1: 4Q28
C2: 종가: | D2: =변수!D44
C3: 기준일: | D3: 20261014 | E3: 1 | F3: 2 | G3: 3 | H3: 4 | I3: 5 | J3: 6 | K3: 7 | L3: 8 | M3: 9 | N3: 10 | O3: 11 | P3: 12 | Q3: 13 | R3: 14 | S3: 15 | T3: 16 | U3: 17 | V3: 18 | W3: 19 | X3: 20 | Y3: 21 | Z3: 22 | AA3: 23 | AB3: 24 | AC3: 25 | AD3: 26 | AE3: 27 | AF3: 28 | AG3: 29
E4: 2021.12 | F4: 2022.03 | G4: 2022.06 | H4: 2022.09 | I4: 2022.12 | J4: 2023.03 | K4: 2023.06 | L4: 2023.09 | M4: 2023.12 | N4: 2024.03 | O4: 2024.06 | P4: 2024.09 | Q4: 2024.12 | R4: 2025.03 | S4: 2025.06 | T4: 2025.09 | U4: 2025.12 | V4: 2026.03 | W4: 2026.06 | X4: 2026.09 | Y4: 2026.12 | Z4: 2027.03 | AA4: 2027.06 | AB4: 2027.09 | AC4: 2027.12 | AD4: 2028.03 | AE4: 2028.06 | AF4: 2028.09 | AG4: 2028.12
A5: 매출액 | D5: 매출액 | E5: =IFERROR(VLOOKUP($A5,subQ,MATCH(E$1,SUBQH,0),0),"") | F5: =IFERROR(VLOOKUP($A5,subQ,MATCH(F$1,SUBQH,0),0),"") | G5: =IFERROR(VLOOKUP($A5,subQ,MATCH(G$1,SUBQH,0),0),"") | H5: =IFERROR(VLOOKUP($A5,subQ,MATCH(H$1,SUBQH,0),0),"") | I5: =IFERROR(VLOOKUP($A5,subQ,MATCH(I$1,SUBQH,0),0),"") | J5: =IFERROR(VLOOKUP($A5,subQ,MATCH(J$1,SUBQH,0),0),"") | K5: =IFERROR(VLOOKUP($A5,subQ,MATCH(K$1,SUBQH,0),0),"") | L5: =IFERROR(VLOOKUP($A5,subQ,MATCH(L$1,SUBQH,0),0),"") | ... AG5: =IFERROR(VLOOKUP($A5,subQ,MATCH(AG$1,SUBQH,0),0),"")
A6: 매출원가 | D6: 매출원가 | E6: =IFERROR(VLOOKUP($A6,subQ,MATCH(E$1,SUBQH,0),0),"") | F6: =IFERROR(VLOOKUP($A6,subQ,MATCH(F$1,SUBQH,0),0),"") | G6: =IFERROR(VLOOKUP($A6,subQ,MATCH(G$1,SUBQH,0),0),"") | H6: =IFERROR(VLOOKUP($A6,subQ,MATCH(H$1,SUBQH,0),0),"") | I6: =IFERROR(VLOOKUP($A6,subQ,MATCH(I$1,SUBQH,0),0),"") | J6: =IFERROR(VLOOKUP($A6,subQ,MATCH(J$1,SUBQH,0),0),"") | K6: =IFERROR(VLOOKUP($A6,subQ,MATCH(K$1,SUBQH,0),0),"") | L6: =IFERROR(VLOOKUP($A6,subQ,MATCH(L$1,SUBQH,0),0),"") | ... AG6: =IFERROR(VLOOKUP($A6,subQ,MATCH(AG$1,SUBQH,0),0),"")
A7: 매출총이익 | D7: 매출총이익 | E7: =IFERROR(VLOOKUP($A7,subQ,MATCH(E$1,SUBQH,0),0),"") | F7: =IFERROR(VLOOKUP($A7,subQ,MATCH(F$1,SUBQH,0),0),"") | G7: =IFERROR(VLOOKUP($A7,subQ,MATCH(G$1,SUBQH,0),0),"") | H7: =IFERROR(VLOOKUP($A7,subQ,MATCH(H$1,SUBQH,0),0),"") | I7: =IFERROR(VLOOKUP($A7,subQ,MATCH(I$1,SUBQH,0),0),"") | J7: =IFERROR(VLOOKUP($A7,subQ,MATCH(J$1,SUBQH,0),0),"") | K7: =IFERROR(VLOOKUP($A7,subQ,MATCH(K$1,SUBQH,0),0),"") | L7: =IFERROR(VLOOKUP($A7,subQ,MATCH(L$1,SUBQH,0),0),"") | ... AG7: =IFERROR(VLOOKUP($A7,subQ,MATCH(AG$1,SUBQH,0),0),"")
A8: 판관비 | D8: 판매비와관리비 | E8: =IFERROR(VLOOKUP($A8,subQ,MATCH(E$1,SUBQH,0),0),"") | F8: =IFERROR(VLOOKUP($A8,subQ,MATCH(F$1,SUBQH,0),0),"") | G8: =IFERROR(VLOOKUP($A8,subQ,MATCH(G$1,SUBQH,0),0),"") | H8: =IFERROR(VLOOKUP($A8,subQ,MATCH(H$1,SUBQH,0),0),"") | I8: =IFERROR(VLOOKUP($A8,subQ,MATCH(I$1,SUBQH,0),0),"") | J8: =IFERROR(VLOOKUP($A8,subQ,MATCH(J$1,SUBQH,0),0),"") | K8: =IFERROR(VLOOKUP($A8,subQ,MATCH(K$1,SUBQH,0),0),"") | L8: =IFERROR(VLOOKUP($A8,subQ,MATCH(L$1,SUBQH,0),0),"") | ... AG8: =IFERROR(VLOOKUP($A8,subQ,MATCH(AG$1,SUBQH,0),0),"")
A9: 영업이익 | D9: 영업이익 | E9: =IFERROR(VLOOKUP($A9,subQ,MATCH(E$1,SUBQH,0),0),"") | F9: =IFERROR(VLOOKUP($A9,subQ,MATCH(F$1,SUBQH,0),0),"") | G9: =IFERROR(VLOOKUP($A9,subQ,MATCH(G$1,SUBQH,0),0),"") | H9: =IFERROR(VLOOKUP($A9,subQ,MATCH(H$1,SUBQH,0),0),"") | I9: =IFERROR(VLOOKUP($A9,subQ,MATCH(I$1,SUBQH,0),0),"") | J9: =IFERROR(VLOOKUP($A9,subQ,MATCH(J$1,SUBQH,0),0),"") | K9: =IFERROR(VLOOKUP($A9,subQ,MATCH(K$1,SUBQH,0),0),"") | L9: =IFERROR(VLOOKUP($A9,subQ,MATCH(L$1,SUBQH,0),0),"") | ... AG9: =IFERROR(VLOOKUP($A9,subQ,MATCH(AG$1,SUBQH,0),0),"")
A10: OPM | D10: 영업이익률 | E10: =IFERROR(VLOOKUP($A10,subQ,MATCH(E$1,SUBQH,0),0),"") | F10: =IFERROR(VLOOKUP($A10,subQ,MATCH(F$1,SUBQH,0),0),"") | G10: =IFERROR(VLOOKUP($A10,subQ,MATCH(G$1,SUBQH,0),0),"") | H10: =IFERROR(VLOOKUP($A10,subQ,MATCH(H$1,SUBQH,0),0),"") | I10: =IFERROR(VLOOKUP($A10,subQ,MATCH(I$1,SUBQH,0),0),"") | J10: =IFERROR(VLOOKUP($A10,subQ,MATCH(J$1,SUBQH,0),0),"") | K10: =IFERROR(VLOOKUP($A10,subQ,MATCH(K$1,SUBQH,0),0),"") | L10: =IFERROR(VLOOKUP($A10,subQ,MATCH(L$1,SUBQH,0),0),"") | ... AG10: =IFERROR(VLOOKUP($A10,subQ,MATCH(AG$1,SUBQH,0),0),"")
A11: 금융손익 | D11: 금융손익(이자·환 포함) | E11: =IFERROR(VLOOKUP($A11,subQ,MATCH(E$1,SUBQH,0),0),"") | F11: =IFERROR(VLOOKUP($A11,subQ,MATCH(F$1,SUBQH,0),0),"") | G11: =IFERROR(VLOOKUP($A11,subQ,MATCH(G$1,SUBQH,0),0),"") | H11: =IFERROR(VLOOKUP($A11,subQ,MATCH(H$1,SUBQH,0),0),"") | I11: =IFERROR(VLOOKUP($A11,subQ,MATCH(I$1,SUBQH,0),0),"") | J11: =IFERROR(VLOOKUP($A11,subQ,MATCH(J$1,SUBQH,0),0),"") | K11: =IFERROR(VLOOKUP($A11,subQ,MATCH(K$1,SUBQH,0),0),"") | L11: =IFERROR(VLOOKUP($A11,subQ,MATCH(L$1,SUBQH,0),0),"") | ... AG11: =IFERROR(VLOOKUP($A11,subQ,MATCH(AG$1,SUBQH,0),0),"")
A12: 이자손익 | D12: 이자손익(이자수익 − 이자비용) | E12: =IFERROR(VLOOKUP($A12,subQ,MATCH(E$1,SUBQH,0),0),"") | F12: =IFERROR(VLOOKUP($A12,subQ,MATCH(F$1,SUBQH,0),0),"") | G12: =IFERROR(VLOOKUP($A12,subQ,MATCH(G$1,SUBQH,0),0),"") | H12: =IFERROR(VLOOKUP($A12,subQ,MATCH(H$1,SUBQH,0),0),"") | I12: =IFERROR(VLOOKUP($A12,subQ,MATCH(I$1,SUBQH,0),0),"") | J12: =IFERROR(VLOOKUP($A12,subQ,MATCH(J$1,SUBQH,0),0),"") | K12: =IFERROR(VLOOKUP($A12,subQ,MATCH(K$1,SUBQH,0),0),"") | L12: =IFERROR(VLOOKUP($A12,subQ,MATCH(L$1,SUBQH,0),0),"") | ... AG12: =IFERROR(VLOOKUP($A12,subQ,MATCH(AG$1,SUBQH,0),0),"")
A13: 외환손익 | D13: 외환손익(실적만; 추정 환효과는 환관련손익) | E13: =IFERROR(VLOOKUP($A13,subQ,MATCH(E$1,SUBQH,0),0),"") | F13: =IFERROR(VLOOKUP($A13,subQ,MATCH(F$1,SUBQH,0),0),"") | G13: =IFERROR(VLOOKUP($A13,subQ,MATCH(G$1,SUBQH,0),0),"") | H13: =IFERROR(VLOOKUP($A13,subQ,MATCH(H$1,SUBQH,0),0),"") | I13: =IFERROR(VLOOKUP($A13,subQ,MATCH(I$1,SUBQH,0),0),"") | J13: =IFERROR(VLOOKUP($A13,subQ,MATCH(J$1,SUBQH,0),0),"") | K13: =IFERROR(VLOOKUP($A13,subQ,MATCH(K$1,SUBQH,0),0),"") | L13: =IFERROR(VLOOKUP($A13,subQ,MATCH(L$1,SUBQH,0),0),"") | ... AG13: =IFERROR(VLOOKUP($A13,subQ,MATCH(AG$1,SUBQH,0),0),"")
A14: 파생상품손익 | D14: 파생상품손익 | E14: =IFERROR(VLOOKUP($A14,subQ,MATCH(E$1,SUBQH,0),0),"") | F14: =IFERROR(VLOOKUP($A14,subQ,MATCH(F$1,SUBQH,0),0),"") | G14: =IFERROR(VLOOKUP($A14,subQ,MATCH(G$1,SUBQH,0),0),"") | H14: =IFERROR(VLOOKUP($A14,subQ,MATCH(H$1,SUBQH,0),0),"") | I14: =IFERROR(VLOOKUP($A14,subQ,MATCH(I$1,SUBQH,0),0),"") | J14: =IFERROR(VLOOKUP($A14,subQ,MATCH(J$1,SUBQH,0),0),"") | K14: =IFERROR(VLOOKUP($A14,subQ,MATCH(K$1,SUBQH,0),0),"") | L14: =IFERROR(VLOOKUP($A14,subQ,MATCH(L$1,SUBQH,0),0),"") | ... AG14: =IFERROR(VLOOKUP($A14,subQ,MATCH(AG$1,SUBQH,0),0),"")
A15: 기타금융손익 | D15: 기타금융손익(금융손익 잔차) | E15: =IFERROR(VLOOKUP($A15,subQ,MATCH(E$1,SUBQH,0),0),"") | F15: =IFERROR(VLOOKUP($A15,subQ,MATCH(F$1,SUBQH,0),0),"") | G15: =IFERROR(VLOOKUP($A15,subQ,MATCH(G$1,SUBQH,0),0),"") | H15: =IFERROR(VLOOKUP($A15,subQ,MATCH(H$1,SUBQH,0),0),"") | I15: =IFERROR(VLOOKUP($A15,subQ,MATCH(I$1,SUBQH,0),0),"") | J15: =IFERROR(VLOOKUP($A15,subQ,MATCH(J$1,SUBQH,0),0),"") | K15: =IFERROR(VLOOKUP($A15,subQ,MATCH(K$1,SUBQH,0),0),"") | L15: =IFERROR(VLOOKUP($A15,subQ,MATCH(L$1,SUBQH,0),0),"") | ... AG15: =IFERROR(VLOOKUP($A15,subQ,MATCH(AG$1,SUBQH,0),0),"")
A16: 기타영업외손익 | D16: 기타영업외손익 | E16: =IFERROR(VLOOKUP($A16,subQ,MATCH(E$1,SUBQH,0),0),"") | F16: =IFERROR(VLOOKUP($A16,subQ,MATCH(F$1,SUBQH,0),0),"") | G16: =IFERROR(VLOOKUP($A16,subQ,MATCH(G$1,SUBQH,0),0),"") | H16: =IFERROR(VLOOKUP($A16,subQ,MATCH(H$1,SUBQH,0),0),"") | I16: =IFERROR(VLOOKUP($A16,subQ,MATCH(I$1,SUBQH,0),0),"") | J16: =IFERROR(VLOOKUP($A16,subQ,MATCH(J$1,SUBQH,0),0),"") | K16: =IFERROR(VLOOKUP($A16,subQ,MATCH(K$1,SUBQH,0),0),"") | L16: =IFERROR(VLOOKUP($A16,subQ,MATCH(L$1,SUBQH,0),0),"") | ... AG16: =IFERROR(VLOOKUP($A16,subQ,MATCH(AG$1,SUBQH,0),0),"")
... A41: NPM | D41: NPM | E41: =IFERROR(VLOOKUP($A41,subQ,MATCH(E$1,SUBQH,0),0),"") | F41: =IFERROR(VLOOKUP($A41,subQ,MATCH(F$1,SUBQH,0),0),"") | G41: =IFERROR(VLOOKUP($A41,subQ,MATCH(G$1,SUBQH,0),0),"") | H41: =IFERROR(VLOOKUP($A41,subQ,MATCH(H$1,SUBQH,0),0),"") | I41: =IFERROR(VLOOKUP($A41,subQ,MATCH(I$1,SUBQH,0),0),"") | J41: =IFERROR(VLOOKUP($A41,subQ,MATCH(J$1,SUBQH,0),0),"") | K41: =IFERROR(VLOOKUP($A41,subQ,MATCH(K$1,SUBQH,0),0),"") | L41: =IFERROR(VLOOKUP($A41,subQ,MATCH(L$1,SUBQH,0),0),"") | ... AG41: =IFERROR(VLOOKUP($A41,subQ,MATCH(AG$1,SUBQH,0),0),"")
A42: 매출액 YoY | D42: 매출액 YoY | I42: =IFERROR(I5/E5-1,"") | J42: =IFERROR(J5/F5-1,"") | K42: =IFERROR(K5/G5-1,"") | L42: =IFERROR(L5/H5-1,"") | M42: =IFERROR(M5/I5-1,"") | N42: =IFERROR(N5/J5-1,"") | O42: =IFERROR(O5/K5-1,"") | P42: =IFERROR(P5/L5-1,"") | ... AG42: =IFERROR(AG5/AC5-1,"")
A43: 영업이익 YoY | D43: 영업이익 YoY | I43: =IFERROR(I9/E9-1,"") | J43: =IFERROR(J9/F9-1,"") | K43: =IFERROR(K9/G9-1,"") | L43: =IFERROR(L9/H9-1,"") | M43: =IFERROR(M9/I9-1,"") | N43: =IFERROR(N9/J9-1,"") | O43: =IFERROR(O9/K9-1,"") | P43: =IFERROR(P9/L9-1,"") | ... AG43: =IFERROR(AG9/AC9-1,"")
A44: 지배주주순이익 YoY | D44: 지배주주순이익 YoY | I44: =IFERROR(I21/E21-1,"") | J44: =IFERROR(J21/F21-1,"") | K44: =IFERROR(K21/G21-1,"") | L44: =IFERROR(L21/H21-1,"") | M44: =IFERROR(M21/I21-1,"") | N44: =IFERROR(N21/J21-1,"") | O44: =IFERROR(O21/K21-1,"") | P44: =IFERROR(P21/L21-1,"") | ... AG44: =IFERROR(AG21/AC21-1,"")

Sheet 연간예상
C1: 이름: 연간예상H — subQ 를 이름으로 VLOOKUP(억원) | E1: 2021 | F1: 2022 | G1: 2023 | H1: 2024 | I1: 2025 | J1: 2026 | K1: 2027 | L1: 2028
C2: 종가: | D2: =변수!D44
C3: 기준일: | D3: 20261014 | E3: 1 | F3: 2 | G3: 3 | H3: 4 | I3: 5 | J3: 6 | K3: 7 | L3: 8
E4: 2021.12A | F4: 2022.12A | G4: 2023.12A | H4: 2024.12A | I4: 2025.12A | J4: 2026.12A | K4: 2027.12A | L4: 2028.12A
A5: 매출액 | D5: 매출액 | E5: =IFERROR(VLOOKUP($A5,subQ,MATCH(E$1,SUBQH,0),0),"") | F5: =IFERROR(VLOOKUP($A5,subQ,MATCH(F$1,SUBQH,0),0),"") | G5: =IFERROR(VLOOKUP($A5,subQ,MATCH(G$1,SUBQH,0),0),"") | H5: =IFERROR(VLOOKUP($A5,subQ,MATCH(H$1,SUBQH,0),0),"") | I5: =IFERROR(VLOOKUP($A5,subQ,MATCH(I$1,SUBQH,0),0),"") | J5: =IFERROR(VLOOKUP($A5,subQ,MATCH(J$1,SUBQH,0),0),"") | K5: =IFERROR(VLOOKUP($A5,subQ,MATCH(K$1,SUBQH,0),0),"") | L5: =IFERROR(VLOOKUP($A5,subQ,MATCH(L$1,SUBQH,0),0),"")
A6: 매출원가 | D6: 매출원가 | E6: =IFERROR(VLOOKUP($A6,subQ,MATCH(E$1,SUBQH,0),0),"") | F6: =IFERROR(VLOOKUP($A6,subQ,MATCH(F$1,SUBQH,0),0),"") | G6: =IFERROR(VLOOKUP($A6,subQ,MATCH(G$1,SUBQH,0),0),"") | H6: =IFERROR(VLOOKUP($A6,subQ,MATCH(H$1,SUBQH,0),0),"") | I6: =IFERROR(VLOOKUP($A6,subQ,MATCH(I$1,SUBQH,0),0),"") | J6: =IFERROR(VLOOKUP($A6,subQ,MATCH(J$1,SUBQH,0),0),"") | K6: =IFERROR(VLOOKUP($A6,subQ,MATCH(K$1,SUBQH,0),0),"") | L6: =IFERROR(VLOOKUP($A6,subQ,MATCH(L$1,SUBQH,0),0),"")
A7: 매출총이익 | D7: 매출총이익 | E7: =IFERROR(VLOOKUP($A7,subQ,MATCH(E$1,SUBQH,0),0),"") | F7: =IFERROR(VLOOKUP($A7,subQ,MATCH(F$1,SUBQH,0),0),"") | G7: =IFERROR(VLOOKUP($A7,subQ,MATCH(G$1,SUBQH,0),0),"") | H7: =IFERROR(VLOOKUP($A7,subQ,MATCH(H$1,SUBQH,0),0),"") | I7: =IFERROR(VLOOKUP($A7,subQ,MATCH(I$1,SUBQH,0),0),"") | J7: =IFERROR(VLOOKUP($A7,subQ,MATCH(J$1,SUBQH,0),0),"") | K7: =IFERROR(VLOOKUP($A7,subQ,MATCH(K$1,SUBQH,0),0),"") | L7: =IFERROR(VLOOKUP($A7,subQ,MATCH(L$1,SUBQH,0),0),"")
A8: 판관비 | D8: 판매비와관리비 | E8: =IFERROR(VLOOKUP($A8,subQ,MATCH(E$1,SUBQH,0),0),"") | F8: =IFERROR(VLOOKUP($A8,subQ,MATCH(F$1,SUBQH,0),0),"") | G8: =IFERROR(VLOOKUP($A8,subQ,MATCH(G$1,SUBQH,0),0),"") | H8: =IFERROR(VLOOKUP($A8,subQ,MATCH(H$1,SUBQH,0),0),"") | I8: =IFERROR(VLOOKUP($A8,subQ,MATCH(I$1,SUBQH,0),0),"") | J8: =IFERROR(VLOOKUP($A8,subQ,MATCH(J$1,SUBQH,0),0),"") | K8: =IFERROR(VLOOKUP($A8,subQ,MATCH(K$1,SUBQH,0),0),"") | L8: =IFERROR(VLOOKUP($A8,subQ,MATCH(L$1,SUBQH,0),0),"")
A9: 영업이익 | D9: 영업이익 | E9: =IFERROR(VLOOKUP($A9,subQ,MATCH(E$1,SUBQH,0),0),"") | F9: =IFERROR(VLOOKUP($A9,subQ,MATCH(F$1,SUBQH,0),0),"") | G9: =IFERROR(VLOOKUP($A9,subQ,MATCH(G$1,SUBQH,0),0),"") | H9: =IFERROR(VLOOKUP($A9,subQ,MATCH(H$1,SUBQH,0),0),"") | I9: =IFERROR(VLOOKUP($A9,subQ,MATCH(I$1,SUBQH,0),0),"") | J9: =IFERROR(VLOOKUP($A9,subQ,MATCH(J$1,SUBQH,0),0),"") | K9: =IFERROR(VLOOKUP($A9,subQ,MATCH(K$1,SUBQH,0),0),"") | L9: =IFERROR(VLOOKUP($A9,subQ,MATCH(L$1,SUBQH,0),0),"")
A10: OPM | D10: 영업이익률 | E10: =IFERROR(VLOOKUP($A10,subQ,MATCH(E$1,SUBQH,0),0),"") | F10: =IFERROR(VLOOKUP($A10,subQ,MATCH(F$1,SUBQH,0),0),"") | G10: =IFERROR(VLOOKUP($A10,subQ,MATCH(G$1,SUBQH,0),0),"") | H10: =IFERROR(VLOOKUP($A10,subQ,MATCH(H$1,SUBQH,0),0),"") | I10: =IFERROR(VLOOKUP($A10,subQ,MATCH(I$1,SUBQH,0),0),"") | J10: =IFERROR(VLOOKUP($A10,subQ,MATCH(J$1,SUBQH,0),0),"") | K10: =IFERROR(VLOOKUP($A10,subQ,MATCH(K$1,SUBQH,0),0),"") | L10: =IFERROR(VLOOKUP($A10,subQ,MATCH(L$1,SUBQH,0),0),"")
A11: 금융손익 | D11: 금융손익(이자·환 포함) | E11: =IFERROR(VLOOKUP($A11,subQ,MATCH(E$1,SUBQH,0),0),"") | F11: =IFERROR(VLOOKUP($A11,subQ,MATCH(F$1,SUBQH,0),0),"") | G11: =IFERROR(VLOOKUP($A11,subQ,MATCH(G$1,SUBQH,0),0),"") | H11: =IFERROR(VLOOKUP($A11,subQ,MATCH(H$1,SUBQH,0),0),"") | I11: =IFERROR(VLOOKUP($A11,subQ,MATCH(I$1,SUBQH,0),0),"") | J11: =IFERROR(VLOOKUP($A11,subQ,MATCH(J$1,SUBQH,0),0),"") | K11: =IFERROR(VLOOKUP($A11,subQ,MATCH(K$1,SUBQH,0),0),"") | L11: =IFERROR(VLOOKUP($A11,subQ,MATCH(L$1,SUBQH,0),0),"")
A12: 이자손익 | D12: 이자손익(이자수익 − 이자비용) | E12: =IFERROR(VLOOKUP($A12,subQ,MATCH(E$1,SUBQH,0),0),"") | F12: =IFERROR(VLOOKUP($A12,subQ,MATCH(F$1,SUBQH,0),0),"") | G12: =IFERROR(VLOOKUP($A12,subQ,MATCH(G$1,SUBQH,0),0),"") | H12: =IFERROR(VLOOKUP($A12,subQ,MATCH(H$1,SUBQH,0),0),"") | I12: =IFERROR(VLOOKUP($A12,subQ,MATCH(I$1,SUBQH,0),0),"") | J12: =IFERROR(VLOOKUP($A12,subQ,MATCH(J$1,SUBQH,0),0),"") | K12: =IFERROR(VLOOKUP($A12,subQ,MATCH(K$1,SUBQH,0),0),"") | L12: =IFERROR(VLOOKUP($A12,subQ,MATCH(L$1,SUBQH,0),0),"")
A13: 외환손익 | D13: 외환손익(실적만; 추정 환효과는 환관련손익) | E13: =IFERROR(VLOOKUP($A13,subQ,MATCH(E$1,SUBQH,0),0),"") | F13: =IFERROR(VLOOKUP($A13,subQ,MATCH(F$1,SUBQH,0),0),"") | G13: =IFERROR(VLOOKUP($A13,subQ,MATCH(G$1,SUBQH,0),0),"") | H13: =IFERROR(VLOOKUP($A13,subQ,MATCH(H$1,SUBQH,0),0),"") | I13: =IFERROR(VLOOKUP($A13,subQ,MATCH(I$1,SUBQH,0),0),"") | J13: =IFERROR(VLOOKUP($A13,subQ,MATCH(J$1,SUBQH,0),0),"") | K13: =IFERROR(VLOOKUP($A13,subQ,MATCH(K$1,SUBQH,0),0),"") | L13: =IFERROR(VLOOKUP($A13,subQ,MATCH(L$1,SUBQH,0),0),"")
A14: 파생상품손익 | D14: 파생상품손익 | E14: =IFERROR(VLOOKUP($A14,subQ,MATCH(E$1,SUBQH,0),0),"") | F14: =IFERROR(VLOOKUP($A14,subQ,MATCH(F$1,SUBQH,0),0),"") | G14: =IFERROR(VLOOKUP($A14,subQ,MATCH(G$1,SUBQH,0),0),"") | H14: =IFERROR(VLOOKUP($A14,subQ,MATCH(H$1,SUBQH,0),0),"") | I14: =IFERROR(VLOOKUP($A14,subQ,MATCH(I$1,SUBQH,0),0),"") | J14: =IFERROR(VLOOKUP($A14,subQ,MATCH(J$1,SUBQH,0),0),"") | K14: =IFERROR(VLOOKUP($A14,subQ,MATCH(K$1,SUBQH,0),0),"") | L14: =IFERROR(VLOOKUP($A14,subQ,MATCH(L$1,SUBQH,0),0),"")
A15: 기타금융손익 | D15: 기타금융손익(금융손익 잔차) | E15: =IFERROR(VLOOKUP($A15,subQ,MATCH(E$1,SUBQH,0),0),"") | F15: =IFERROR(VLOOKUP($A15,subQ,MATCH(F$1,SUBQH,0),0),"") | G15: =IFERROR(VLOOKUP($A15,subQ,MATCH(G$1,SUBQH,0),0),"") | H15: =IFERROR(VLOOKUP($A15,subQ,MATCH(H$1,SUBQH,0),0),"") | I15: =IFERROR(VLOOKUP($A15,subQ,MATCH(I$1,SUBQH,0),0),"") | J15: =IFERROR(VLOOKUP($A15,subQ,MATCH(J$1,SUBQH,0),0),"") | K15: =IFERROR(VLOOKUP($A15,subQ,MATCH(K$1,SUBQH,0),0),"") | L15: =IFERROR(VLOOKUP($A15,subQ,MATCH(L$1,SUBQH,0),0),"")
A16: 기타영업외손익 | D16: 기타영업외손익 | E16: =IFERROR(VLOOKUP($A16,subQ,MATCH(E$1,SUBQH,0),0),"") | F16: =IFERROR(VLOOKUP($A16,subQ,MATCH(F$1,SUBQH,0),0),"") | G16: =IFERROR(VLOOKUP($A16,subQ,MATCH(G$1,SUBQH,0),0),"") | H16: =IFERROR(VLOOKUP($A16,subQ,MATCH(H$1,SUBQH,0),0),"") | I16: =IFERROR(VLOOKUP($A16,subQ,MATCH(I$1,SUBQH,0),0),"") | J16: =IFERROR(VLOOKUP($A16,subQ,MATCH(J$1,SUBQH,0),0),"") | K16: =IFERROR(VLOOKUP($A16,subQ,MATCH(K$1,SUBQH,0),0),"") | L16: =IFERROR(VLOOKUP($A16,subQ,MATCH(L$1,SUBQH,0),0),"")
... A41: NPM | D41: NPM | E41: =IFERROR(VLOOKUP($A41,subQ,MATCH(E$1,SUBQH,0),0),"") | F41: =IFERROR(VLOOKUP($A41,subQ,MATCH(F$1,SUBQH,0),0),"") | G41: =IFERROR(VLOOKUP($A41,subQ,MATCH(G$1,SUBQH,0),0),"") | H41: =IFERROR(VLOOKUP($A41,subQ,MATCH(H$1,SUBQH,0),0),"") | I41: =IFERROR(VLOOKUP($A41,subQ,MATCH(I$1,SUBQH,0),0),"") | J41: =IFERROR(VLOOKUP($A41,subQ,MATCH(J$1,SUBQH,0),0),"") | K41: =IFERROR(VLOOKUP($A41,subQ,MATCH(K$1,SUBQH,0),0),"") | L41: =IFERROR(VLOOKUP($A41,subQ,MATCH(L$1,SUBQH,0),0),"")
A42: 매출액 YoY | D42: 매출액 YoY | F42: =IFERROR(F5/E5-1,"") | G42: =IFERROR(G5/F5-1,"") | H42: =IFERROR(H5/G5-1,"") | I42: =IFERROR(I5/H5-1,"") | J42: =IFERROR(J5/I5-1,"") | K42: =IFERROR(K5/J5-1,"") | L42: =IFERROR(L5/K5-1,"")
A43: 영업이익 YoY | D43: 영업이익 YoY | F43: =IFERROR(F9/E9-1,"") | G43: =IFERROR(G9/F9-1,"") | H43: =IFERROR(H9/G9-1,"") | I43: =IFERROR(I9/H9-1,"") | J43: =IFERROR(J9/I9-1,"") | K43: =IFERROR(K9/J9-1,"") | L43: =IFERROR(L9/K9-1,"")
A44: 지배주주순이익 YoY | D44: 지배주주순이익 YoY | F44: =IFERROR(F21/E21-1,"") | G44: =IFERROR(G21/F21-1,"") | H44: =IFERROR(H21/G21-1,"") | I44: =IFERROR(I21/H21-1,"") | J44: =IFERROR(J21/I21-1,"") | K44: =IFERROR(K21/J21-1,"") | L44: =IFERROR(L21/K21-1,"")

Sheet TP
B1: 종가 | C1: =변수!D44
B2: 기준일 | C2: =변수!D45
B3: 모델 산출값 — 목표주가·추천 아님. 밴드·COE 는 변수 시트 3절의 가정
C5: FY | D5: 2025 | E5: 2026 | F5: 2027 | G5: 2028
D6: A | E6: E | F6: E | G6: E
C7: EPS(원) | D7: =IFERROR(VLOOKUP("EPS",subQ,MATCH(D$5,SUBQH,0),0),"") | E7: =IFERROR(VLOOKUP("EPS",subQ,MATCH(E$5,SUBQH,0),0),"") | F7: =IFERROR(VLOOKUP("EPS",subQ,MATCH(F$5,SUBQH,0),0),"") | G7: =IFERROR(VLOOKUP("EPS",subQ,MATCH(G$5,SUBQH,0),0),"")
C8: BPS(원) | D8: =IFERROR(VLOOKUP("BPS",subQ,MATCH(D$5,SUBQH,0),0),"") | E8: =IFERROR(VLOOKUP("BPS",subQ,MATCH(E$5,SUBQH,0),0),"") | F8: =IFERROR(VLOOKUP("BPS",subQ,MATCH(F$5,SUBQH,0),0),"") | G8: =IFERROR(VLOOKUP("BPS",subQ,MATCH(G$5,SUBQH,0),0),"")
C9: 지배주주순이익(억원) | D9: =IFERROR(VLOOKUP("지배주주순이익",subQ,MATCH(D$5,SUBQH,0),0),"") | E9: =IFERROR(VLOOKUP("지배주주순이익",subQ,MATCH(E$5,SUBQH,0),0),"") | F9: =IFERROR(VLOOKUP("지배주주순이익",subQ,MATCH(F$5,SUBQH,0),0),"") | G9: =IFERROR(VLOOKUP("지배주주순이익",subQ,MATCH(G$5,SUBQH,0),0),"")
C10: 영업이익(억원) | D10: =IFERROR(VLOOKUP("영업이익",subQ,MATCH(D$5,SUBQH,0),0),"") | E10: =IFERROR(VLOOKUP("영업이익",subQ,MATCH(E$5,SUBQH,0),0),"") | F10: =IFERROR(VLOOKUP("영업이익",subQ,MATCH(F$5,SUBQH,0),0),"") | G10: =IFERROR(VLOOKUP("영업이익",subQ,MATCH(G$5,SUBQH,0),0),"")
C11: ROE(EPS/기초BPS) | E11: =IFERROR(E7/D8,"") | F11: =IFERROR(F7/E8,"") | G11: =IFERROR(G7/F8,"")
B13: PER
C14: 12M fwd EPS | D14: =IFERROR(E7*변수!D50+F7*(1-변수!D50),"")
C15: 적정가치 @PER_lo | D15: =변수!D47 | E15: =IFERROR(ROUND($D$14*D15,-2),"") | F15: =IFERROR(E15/$C$1-1,"") | G15: 배 · 원 · 종가 대비
C16: 적정가치 @PER_mid | D16: =변수!D48 | E16: =IFERROR(ROUND($D$14*D16,-2),"") | F16: =IFERROR(E16/$C$1-1,"") | G16: 배 · 원 · 종가 대비
C17: 적정가치 @PER_hi | D17: =변수!D49 | E17: =IFERROR(ROUND($D$14*D17,-2),"") | F17: =IFERROR(E17/$C$1-1,"") | G17: 배 · 원 · 종가 대비
C18: 현재 PER(종가/12M fwd EPS) | D18: =IFERROR($C$1/$D$14,"")
B20: PBR
C21: 최근 BPS(마지막 실적 분기) | D21: =IFERROR(VLOOKUP("BPS",subQ,MATCH("2Q26",SUBQH,0),0),"")
C22: ROE fwd(12M fwd EPS / BPS) | D22: =IFERROR($D$14/$D$21,"")
C23: COE | D23: =변수!D46
C24: 적정 PBR = ROE/COE | D24: =IFERROR(D22/D23,"")
C25: 적정가치(PBR) = BPS × 적정PBR | D25: =IFERROR(ROUND(D21*D24,-2),"") | E25: =IFERROR(D25/$C$1-1,"")
C26: 현재 PBR(종가/BPS) | D26: =IFERROR($C$1/D21,"")
B28: 모델 json valuation(참고)
C29: eps_fwd12m | D29: -66.2
C30: bps_latest | D30: 1341.2
C31: per_now
C32: pbr_now | D32: 2
C33: roe_fwd | D33: -0.0494
C34: fair_pbr
C35: fair_value_pbr
C36: ev_ebitda
C37: note | D37: 모델 산출값 — 목표주가·추천 아님

Sheet 외화
C1: 이름: 외화QH — 환율 QoQ · 외화 순노출 × Δ기말환율 | E1: 4Q21 | F1: 1Q22 | G1: 2Q22 | H1: 3Q22 | I1: 4Q22 | J1: 1Q23 | K1: 2Q23 | L1: 3Q23 | M1: 4Q23 | N1: 1Q24 | O1: 2Q24 | P1: 3Q24 | Q1: 4Q24 | R1: 1Q25 | S1: 2Q25 | T1: 3Q25 | U1: 4Q25 | V1: 1Q26 | W1: 2Q26 | X1: 3Q26 | Y1: 4Q26 | Z1: 1Q27 | AA1: 2Q27 | AB1: 3Q27 | AC1: 4Q27 | AD1: 1Q28 | AE1: 2Q28 | AF1: 3Q28 | AG1: 4Q28
E3: 1 | F3: 2 | G3: 3 | H3: 4 | I3: 5 | J3: 6 | K3: 7 | L3: 8 | M3: 9 | N3: 10 | O3: 11 | P3: 12 | Q3: 13 | R3: 14 | S3: 15 | T3: 16 | U3: 17 | V3: 18 | W3: 19 | X3: 20 | Y3: 21 | Z3: 22 | AA3: 23 | AB3: 24 | AC3: 25 | AD3: 26 | AE3: 27 | AF3: 28 | AG3: 29
E4: 2021.12 | F4: 2022.03 | G4: 2022.06 | H4: 2022.09 | I4: 2022.12 | J4: 2023.03 | K4: 2023.06 | L4: 2023.09 | M4: 2023.12 | N4: 2024.03 | O4: 2024.06 | P4: 2024.09 | Q4: 2024.12 | R4: 2025.03 | S4: 2025.06 | T4: 2025.09 | U4: 2025.12 | V4: 2026.03 | W4: 2026.06 | X4: 2026.09 | Y4: 2026.12 | Z4: 2027.03 | AA4: 2027.06 | AB4: 2027.09 | AC4: 2027.12 | AD4: 2028.03 | AE4: 2028.06 | AF4: 2028.09 | AG4: 2028.12
D5: 원/달러(평균) | E5: =IFERROR(VLOOKUP($D5,환율,MATCH(E$1,변수H,0),0),"") | F5: =IFERROR(VLOOKUP($D5,환율,MATCH(F$1,변수H,0),0),"") | G5: =IFERROR(VLOOKUP($D5,환율,MATCH(G$1,변수H,0),0),"") | H5: =IFERROR(VLOOKUP($D5,환율,MATCH(H$1,변수H,0),0),"") | I5: =IFERROR(VLOOKUP($D5,환율,MATCH(I$1,변수H,0),0),"") | J5: =IFERROR(VLOOKUP($D5,환율,MATCH(J$1,변수H,0),0),"") | K5: =IFERROR(VLOOKUP($D5,환율,MATCH(K$1,변수H,0),0),"") | L5: =IFERROR(VLOOKUP($D5,환율,MATCH(L$1,변수H,0),0),"") | ... AG5: =IFERROR(VLOOKUP($D5,환율,MATCH(AG$1,변수H,0),0),"")
A6: 원/달러(평균) QoQ | F6: =IFERROR(F5/E5-1,"") | G6: =IFERROR(G5/F5-1,"") | H6: =IFERROR(H5/G5-1,"") | I6: =IFERROR(I5/H5-1,"") | J6: =IFERROR(J5/I5-1,"") | K6: =IFERROR(K5/J5-1,"") | L6: =IFERROR(L5/K5-1,"") | M6: =IFERROR(M5/L5-1,"") | ... AG6: =IFERROR(AG5/AF5-1,"")
D7: 원/달러(기말) | E7: =IFERROR(VLOOKUP($D7,환율,MATCH(E$1,변수H,0),0),"") | F7: =IFERROR(VLOOKUP($D7,환율,MATCH(F$1,변수H,0),0),"") | G7: =IFERROR(VLOOKUP($D7,환율,MATCH(G$1,변수H,0),0),"") | H7: =IFERROR(VLOOKUP($D7,환율,MATCH(H$1,변수H,0),0),"") | I7: =IFERROR(VLOOKUP($D7,환율,MATCH(I$1,변수H,0),0),"") | J7: =IFERROR(VLOOKUP($D7,환율,MATCH(J$1,변수H,0),0),"") | K7: =IFERROR(VLOOKUP($D7,환율,MATCH(K$1,변수H,0),0),"") | L7: =IFERROR(VLOOKUP($D7,환율,MATCH(L$1,변수H,0),0),"") | ... AG7: =IFERROR(VLOOKUP($D7,환율,MATCH(AG$1,변수H,0),0),"")
A8: 원/달러(기말) QoQ | F8: =IFERROR(F7/E7-1,"") | G8: =IFERROR(G7/F7-1,"") | H8: =IFERROR(H7/G7-1,"") | I8: =IFERROR(I7/H7-1,"") | J8: =IFERROR(J7/I7-1,"") | K8: =IFERROR(K7/J7-1,"") | L8: =IFERROR(L7/K7-1,"") | M8: =IFERROR(M7/L7-1,"") | ... AG8: =IFERROR(AG7/AF7-1,"")
D9: W/Euro(평균) | E9: =IFERROR(VLOOKUP($D9,환율,MATCH(E$1,변수H,0),0),"") | F9: =IFERROR(VLOOKUP($D9,환율,MATCH(F$1,변수H,0),0),"") | G9: =IFERROR(VLOOKUP($D9,환율,MATCH(G$1,변수H,0),0),"") | H9: =IFERROR(VLOOKUP($D9,환율,MATCH(H$1,변수H,0),0),"") | I9: =IFERROR(VLOOKUP($D9,환율,MATCH(I$1,변수H,0),0),"") | J9: =IFERROR(VLOOKUP($D9,환율,MATCH(J$1,변수H,0),0),"") | K9: =IFERROR(VLOOKUP($D9,환율,MATCH(K$1,변수H,0),0),"") | L9: =IFERROR(VLOOKUP($D9,환율,MATCH(L$1,변수H,0),0),"") | ... AG9: =IFERROR(VLOOKUP($D9,환율,MATCH(AG$1,변수H,0),0),"")
A10: W/Euro(평균) QoQ | F10: =IFERROR(F9/E9-1,"") | G10: =IFERROR(G9/F9-1,"") | H10: =IFERROR(H9/G9-1,"") | I10: =IFERROR(I9/H9-1,"") | J10: =IFERROR(J9/I9-1,"") | K10: =IFERROR(K9/J9-1,"") | L10: =IFERROR(L9/K9-1,"") | M10: =IFERROR(M9/L9-1,"") | ... AG10: =IFERROR(AG9/AF9-1,"")
D11: W/Euro(기말) | E11: =IFERROR(VLOOKUP($D11,환율,MATCH(E$1,변수H,0),0),"") | F11: =IFERROR(VLOOKUP($D11,환율,MATCH(F$1,변수H,0),0),"") | G11: =IFERROR(VLOOKUP($D11,환율,MATCH(G$1,변수H,0),0),"") | H11: =IFERROR(VLOOKUP($D11,환율,MATCH(H$1,변수H,0),0),"") | I11: =IFERROR(VLOOKUP($D11,환율,MATCH(I$1,변수H,0),0),"") | J11: =IFERROR(VLOOKUP($D11,환율,MATCH(J$1,변수H,0),0),"") | K11: =IFERROR(VLOOKUP($D11,환율,MATCH(K$1,변수H,0),0),"") | L11: =IFERROR(VLOOKUP($D11,환율,MATCH(L$1,변수H,0),0),"") | ... AG11: =IFERROR(VLOOKUP($D11,환율,MATCH(AG$1,변수H,0),0),"")
A12: W/Euro(기말) QoQ | F12: =IFERROR(F11/E11-1,"") | G12: =IFERROR(G11/F11-1,"") | H12: =IFERROR(H11/G11-1,"") | I12: =IFERROR(I11/H11-1,"") | J12: =IFERROR(J11/I11-1,"") | K12: =IFERROR(K11/J11-1,"") | L12: =IFERROR(L11/K11-1,"") | M12: =IFERROR(M11/L11-1,"") | ... AG12: =IFERROR(AG11/AF11-1,"")
D13: 원/100Y(기말) | E13: =IFERROR(VLOOKUP($D13,환율,MATCH(E$1,변수H,0),0),"") | F13: =IFERROR(VLOOKUP($D13,환율,MATCH(F$1,변수H,0),0),"") | G13: =IFERROR(VLOOKUP($D13,환율,MATCH(G$1,변수H,0),0),"") | H13: =IFERROR(VLOOKUP($D13,환율,MATCH(H$1,변수H,0),0),"") | I13: =IFERROR(VLOOKUP($D13,환율,MATCH(I$1,변수H,0),0),"") | J13: =IFERROR(VLOOKUP($D13,환율,MATCH(J$1,변수H,0),0),"") | K13: =IFERROR(VLOOKUP($D13,환율,MATCH(K$1,변수H,0),0),"") | L13: =IFERROR(VLOOKUP($D13,환율,MATCH(L$1,변수H,0),0),"") | ... AG13: =IFERROR(VLOOKUP($D13,환율,MATCH(AG$1,변수H,0),0),"")
A14: 원/100Y(기말) QoQ | F14: =IFERROR(F13/E13-1,"") | G14: =IFERROR(G13/F13-1,"") | H14: =IFERROR(H13/G13-1,"") | I14: =IFERROR(I13/H13-1,"") | J14: =IFERROR(J13/I13-1,"") | K14: =IFERROR(K13/J13-1,"") | L14: =IFERROR(L13/K13-1,"") | M14: =IFERROR(M13/L13-1,"") | ... AG14: =IFERROR(AG13/AF13-1,"")
A16: 외화순노출 | C16: 외화 순노출(백만$) | D16: =변수!D57 | E16: 외화 순노출 × Δ기말환율 (외화 시트 방식)
A17: 환관련손익추정 | C17: 환관련손익 추정(억원) = 순노출 × Δ원/달러(기말) / 100 | F17: =IFERROR($D$16*(F7-E7)/100,"") | G17: =IFERROR($D$16*(G7-F7)/100,"") | H17: =IFERROR($D$16*(H7-G7)/100,"") | I17: =IFERROR($D$16*(I7-H7)/100,"") | J17: =IFERROR($D$16*(J7-I7)/100,"") | K17: =IFERROR($D$16*(K7-J7)/100,"") | L17: =IFERROR($D$16*(L7-K7)/100,"") | M17: =IFERROR($D$16*(M7-L7)/100,"") | ... AG17: =IFERROR($D$16*(AG7-AF7)/100,"")
A18: fx_pnl.by_q | C18: 모델 fx_pnl.by_q(억원, 참고)
C19: 외화 순노출 미공시(face) → 0 + 표기
