Workbook
Name 변수H: 변수!$C$1:$AO$1
Name 환율: 변수!$C$6:$AO$13
Name BS연결H: BS연결!$C$1:$AO$1
Name BS연결: BS연결!$C$5:$AO$100
Name BS별도H: BS별도!$C$1:$AO$1
Name BS별도: BS별도!$C$5:$AO$95
Name SUBQH: subQ!$A$1:$AO$1
Name subQ: subQ!$A$5:$AO$39

Sheet README
A1: 인텔리안테크(189300) 실적 모델 — ARGUS 한국조선
A2: 기준 분기 2026Q2 · 마지막 실적 2026Q2 · 생성 2026-10-11
A3: 모든 수치는 모델 산출값(DART 공개 재무제표 + 우리 추정)이다 — 목표주가·투자 추천 아님. 참고용 · 투자조언 아님.
A5: 시트
A6: 변수 가정 시계열. 환율 8행(ECB via frankfurter — L2 fx.json; 추정 분기 = 노란 가정), 추정 드라이버(노란 셀 = 모델값에서 역산한 가정, 바꾸면 재계산; 연녹 셀 = 3절 스칼라 참조 수식), 3절 스칼라 가정(세율·판관비율·지배주주비중·이자율·종가·PER 밴드·COE·외화 순노출·헤지비율)
A7: BS연결/BS별도 FnGuide 계정명 × 기간 값 덤프(백만원). 행1 분기라벨, 행4 YYYY.MM / YYYY.12A. 이름정의 BS연결H·BS연결(계정명 C열부터)
A8: subQ 분기 서브모델(억원 = 백만원/100). 확정 행: =IFERROR(VLOOKUP($D행,BS연결,MATCH(E$1,BS연결H,0),0)/100,"") 추정 행: 변수 시트 가정 셀 참조 수식. 외환손익·파생상품손익은 BS 계정 합·차, 기타금융손익은 잔차, OPM·EPS·BPS·PER·PBR 은 파생 수식
A9: SLS 선표(조선사만, sls json 있을 때): 요약 행(sls 저장값) + 계약별 스케줄(백만$) × (헤지비율 × 헤지환율 + (1−헤지비율) × 건조시점 환율[변수 원/달러(평균)]) → 원화 수식 블록 → 합계 행이 subQ 매출조선에 연결
A10: 시나리오 신규수주 보수/기준/낙관(forecast_panel 패널, 모델에 scenarios 가 있을 때만): 매출액·영업이익 = subQ 기준값 ± (시나리오 신규 − base 신규) × OPM. base 만 subQ 행에 포함, 나머지는 합산 안 함
A11: 분기/연간예상 subQ 를 이름(A열 key)으로 VLOOKUP 한 보고서 표(억원)
A12: TP PER 밴드 × 12M fwd EPS, PBR = ROE/COE × BPS — 모델 산출값 구간, 목표주가·추천 아님
A13: 외화 환율 QoQ, 외화 순노출 × Δ기말환율 → 환관련손익 추정
... A34: 백테스트: {"freeze": "2025Q2", "horizon": 4, "revenue_wape_pct": 32.8, "op_wape_pct": 137.5, "n": 4, "note": "단일 회사 4분기 — 통계 아님", "driver_at_freeze": "trend_seasonal", "selection_oos_at_freeze": null, "frozen_inputs": "fin(연결/별도)·고객 조선사 모델·지주 자회사 모델은 2025Q2 까지의 분기만; 선표는 체결일 ≤ 2025Q2 말일 계약(원장 최신 금액·코호트 등급, 환산 없음); 잔고는 yards_cache 2025Q2; 시세·환율 forward·prices·forecast_panel 신규수주 미사용. 고객 가중치(suppliers.json 언급 비중)와 합병 체인링크는 현재 지식; 고객 연동 채택은 동결 모델 안에서도 자기 la−4분기 OOS 규칙(selection_oos_at_freeze)", "detail": [{"q": "2025Q3", "rev_pred": 591.46, "rev_act": 772.26, "op_pred": -27.24, "op_act": 23.73}, {"q": "2025Q4", "rev_pred": 730.41, "rev_act": 1243.15, "op_pred": -33.64, "op_act": 198.56}, {"q": "2026Q1", "rev_pred": 411.16, "rev_act": 647.24, "op_pred": -18.93, "op_act": 5.93}, {"q": "2026Q2", "rev_pred": 708.83, "rev_act": 972.46, "op_pred": -32.64, "op_act": 71.36}]}

Sheet 변수
C1: 이름: 변수H | E1: 4Q21 | F1: 2021 | G1: 1Q22 | H1: 2Q22 | I1: 3Q22 | J1: 4Q22 | K1: 2022 | L1: 1Q23 | M1: 2Q23 | N1: 3Q23 | O1: 4Q23 | P1: 2023 | Q1: 1Q24 | R1: 2Q24 | S1: 3Q24 | T1: 4Q24 | U1: 2024 | V1: 1Q25 | W1: 2Q25 | X1: 3Q25 | Y1: 4Q25 | Z1: 2025 | AA1: 1Q26 | AB1: 2Q26 | AC1: 3Q26 | AD1: 4Q26 | AE1: 2026 | AF1: 1Q27 | AG1: 2Q27 | AH1: 3Q27 | AI1: 4Q27 | AJ1: 2027 | AK1: 1Q28 | AL1: 2Q28 | AM1: 3Q28 | AN1: 4Q28 | AO1: 2028
A2: 가정 시계열 — 노란 셀은 추정 가정(모델값에서 역산), 연녹 셀은 3절 스칼라 참조 수식. 바꾸면 subQ·분기·연간예상·TP·시나리오가 재계산됩니다.
E3: 1 | F3: 2 | G3: 3 | H3: 4 | I3: 5 | J3: 6 | K3: 7 | L3: 8 | M3: 9 | N3: 10 | O3: 11 | P3: 12 | Q3: 13 | R3: 14 | S3: 15 | T3: 16 | U3: 17 | V3: 18 | W3: 19 | X3: 20 | Y3: 21 | Z3: 22 | AA3: 23 | AB3: 24 | AC3: 25 | AD3: 26 | AE3: 27 | AF3: 28 | AG3: 29 | AH3: 30 | AI3: 31 | AJ3: 32 | AK3: 33 | AL3: 34 | AM3: 35 | AN3: 36 | AO3: 37
E4: 2021.12 | F4: 2021.12A | G4: 2022.03 | H4: 2022.06 | I4: 2022.09 | J4: 2022.12 | K4: 2022.12A | L4: 2023.03 | M4: 2023.06 | N4: 2023.09 | O4: 2023.12 | P4: 2023.12A | Q4: 2024.03 | R4: 2024.06 | S4: 2024.09 | T4: 2024.12 | U4: 2024.12A | V4: 2025.03 | W4: 2025.06 | X4: 2025.09 | Y4: 2025.12 | Z4: 2025.12A | AA4: 2026.03 | AB4: 2026.06 | AC4: 2026.09 | AD4: 2026.12 | AE4: 2026.12A | AF4: 2027.03 | AG4: 2027.06 | AH4: 2027.09 | AI4: 2027.12 | AJ4: 2027.12A | AK4: 2028.03 | AL4: 2028.06 | AM4: 2028.09 | AN4: 2028.12 | AO4: 2028.12A
B5: 1. FX | C5: 이름: 환율
A6: USDKRW_avg | C6: 원/달러(평균) | E6: 1183.5 | F6: 1145.51 | G6: 1205.78 | H6: 1262.09 | I6: 1341.93 | J6: 1360.12 | K6: 1292.98 | L6: 1276.95 | M6: 1315.69 | N6: 1313.62 | O6: 1322.01 | P6: 1306.85 | Q6: 1330.14 | R6: 1371.28 | S6: 1356.22 | T6: 1396.3 | U6: 1363.53 | V6: 1452.28 | W6: 1398.52 | X6: 1386.95 | Y6: 1449.19 | Z6: 1421.52 | AA6: 1466.12 | AB6: 1501.75 | AC6: 1418.75 | AD6: 1345.14 | AE6: 1457.21 | AF6: 1341.49 | AG6: 1341.49 | AH6: 1341.49 | AI6: 1341.49 | AK6: 1341.49 | AL6: 1341.49 | AM6: 1341.49 | AN6: 1341.49
A7: USDKRW_end | C7: 원/달러(기말) | E7: 1188.75 | F7: 1188.75 | G7: 1213.74 | H7: 1301.24 | I7: 1436.9 | J7: 1260.16 | K7: 1260.16 | L7: 1305.99 | M7: 1321.44 | N7: 1345.35 | O7: 1297.43 | P7: 1297.43 | Q7: 1349.25 | R7: 1377.73 | S7: 1312.17 | T7: 1474.78 | U7: 1474.78 | V7: 1474.54 | W7: 1355.13 | X7: 1403.67 | Y7: 1444.2 | Z7: 1444.2 | AA7: 1524.8 | AB7: 1550.89 | AC7: 1355.4 | AD7: 1341.49 | AE7: 1341.49 | AF7: 1341.49 | AG7: 1341.49 | AH7: 1341.49 | AI7: 1341.49 | AK7: 1341.49 | AL7: 1341.49 | AM7: 1341.49 | AN7: 1341.49
A8: JPY100KRW_avg | C8: 원/100Y(평균) | E8: 1041.02 | F8: 1042.74 | G8: 1036.79 | H8: 972.23 | I8: 970.61 | J8: 961.03 | K8: 985.1 | L8: 964.89 | M8: 957.36 | N8: 909 | O8: 893.22 | P8: 931.11 | Q8: 896.29 | R8: 880.14 | S8: 909.35 | T8: 917.25 | U8: 900.92 | V8: 952.59 | W8: 967.92 | X8: 940.32 | Y8: 940.77 | Z8: 950.17 | AA8: 934.39 | AB8: 942.16 | AC8: 890.41 | AD8: 850.79 | AE8: 919.21 | AF8: 847.7 | AG8: 847.7 | AH8: 847.7 | AI8: 847.7 | AK8: 847.7 | AL8: 847.7 | AM8: 847.7 | AN8: 847.7
A9: JPY100KRW_end | C9: 원/100Y(기말) | E9: 1032.62 | F9: 1032.62 | G9: 996.83 | H9: 954.9 | I9: 993.29 | J9: 955.54 | K9: 955.54 | L9: 980.62 | M9: 913.67 | N9: 901.47 | O9: 917.04 | P9: 917.04 | Q9: 892.42 | R9: 857.76 | S9: 919.21 | T9: 939.65 | U9: 939.65 | V9: 986.84 | W9: 938.85 | X9: 948.49 | Y9: 921.81 | Z9: 921.81 | AA9: 955.99 | AB9: 954.75 | AC9: 863.31 | AD9: 847.7 | AE9: 847.7 | AF9: 847.7 | AG9: 847.7 | AH9: 847.7 | AI9: 847.7 | AK9: 847.7 | AL9: 847.7 | AM9: 847.7 | AN9: 847.7
A10: EURKRW_avg | C10: W/Euro(평균) | E10: 1353.32 | F10: 1354.06 | G10: 1352.29 | H10: 1343.31 | I10: 1350.63 | J10: 1386.07 | K10: 1358.07 | L10: 1369.93 | M10: 1432.41 | N10: 1429.41 | O10: 1420.91 | P10: 1412.88 | Q10: 1444.21 | R10: 1476.42 | S10: 1489.3 | T10: 1490.78 | U10: 1475.4 | V10: 1528.33 | W10: 1585.13 | X10: 1620.04 | Y10: 1686.02 | Z10: 1605.45 | AA10: 1715.47 | AB10: 1746.09 | AC10: 1631.97 | AD10: 1509.74 | AE10: 1689.95 | AF10: 1503.27 | AG10: 1503.27 | AH10: 1503.27 | AI10: 1503.27 | AK10: 1503.27 | AL10: 1503.27 | AM10: 1503.27 | AN10: 1503.27
A11: EURKRW_end | C11: W/Euro(기말) | E11: 1346.38 | F11: 1346.38 | G11: 1347.37 | H11: 1351.6 | I11: 1400.62 | J11: 1344.08 | K11: 1344.08 | L11: 1420.26 | M11: 1435.88 | N11: 1425.26 | O11: 1433.66 | P11: 1433.66 | Q11: 1458.68 | R11: 1474.86 | S11: 1469.1 | T11: 1532.14 | U11: 1532.14 | V11: 1594.72 | W11: 1588.22 | X11: 1648.04 | Y11: 1696.94 | Z11: 1696.94 | AA11: 1753.21 | AB11: 1767.09 | AC11: 1539.06 | AD11: 1503.27 | AE11: 1503.27 | AF11: 1503.27 | AG11: 1503.27 | AH11: 1503.27 | AI11: 1503.27 | AK11: 1503.27 | AL11: 1503.27 | AM11: 1503.27 | AN11: 1503.27
A12: CNYKRW_avg | C12: 원/중국원(평균) | E12: 185.14 | F12: 177.65 | G12: 189.93 | H12: 190.76 | I12: 195.79 | J12: 191.09 | K12: 191.93 | L12: 186.59 | M12: 187.45 | N12: 181.28 | O12: 182.86 | P12: 184.52 | Q12: 185.04 | R12: 189.35 | S12: 189.24 | T12: 194.24 | U12: 189.49 | V12: 199.63 | W12: 193.41 | X12: 193.79 | Y12: 204.38 | Z12: 197.8 | AA12: 211.75 | AB12: 220.8 | AC12: 210.43 | AD12: 200.69 | AE12: 213.75 | AF12: 200.46 | AG12: 200.46 | AH12: 200.46 | AI12: 200.46 | AK12: 200.46 | AL12: 200.46 | AM12: 200.46 | AN12: 200.46
A13: CNYKRW_end | C13: 원/중국원(기말) | E13: 187.13 | F13: 187.13 | G13: 191.38 | H13: 194.13 | I13: 201.92 | J13: 182.67 | K13: 182.67 | L13: 189.97 | M13: 181.8 | N13: 184.26 | O13: 182.61 | P13: 182.61 | Q13: 186.66 | R13: 189.7 | S13: 187.12 | T13: 202.04 | U13: 202.04 | V13: 203.3 | W13: 189.14 | X13: 197.16 | Y13: 206.28 | Z13: 206.28 | AA13: 220.97 | AB13: 228.56 | AC13: 202.16 | AD13: 200.46 | AE13: 200.46 | AF13: 200.46 | AG13: 200.46 | AH13: 200.46 | AI13: 200.46 | AK13: 200.46 | AL13: 200.46 | AM13: 200.46 | AN13: 200.46
B14: 1b. 종가
A15: price_close_end | C15: 종가(기말) | E15: 89064 | G15: 85772 | H15: 57988 | I15: 53051 | J15: 65830 | L15: 90613 | M15: 73400 | N15: 82100 | O15: 72500 | Q15: 59000 | R15: 58900 | S15: 55000 | T15: 37500 | V15: 34850 | W15: 50100 | X15: 47150 | Y15: 59500 | AA15: 110900 | AB15: 77700 | AC15: 66500 | AD15: 63800
A16: price_high | C16: 종가(최고) | E16: 90031 | G16: 92742 | H16: 87902 | I16: 72993 | J16: 74639 | L16: 96324 | M16: 92742 | N16: 92000 | O16: 86700 | Q16: 82400 | R16: 69500 | S16: 60500 | T16: 57400 | V16: 46400 | W16: 54000 | X16: 54900 | Y16: 64600 | AA16: 149400 | AB16: 180200 | AC16: 81400 | AD16: 77300
A17: price_low | C17: 종가(최저) | E17: 64280 | G17: 69992 | H17: 53244 | I17: 51308 | J17: 53728 | L17: 59634 | M17: 63409 | N17: 67400 | O17: 66400 | Q17: 52300 | R17: 53600 | S17: 43000 | T17: 33500 | V17: 33350 | W17: 30800 | X17: 43400 | Y17: 39000 | AA17: 59400 | AB17: 67700 | AC17: 48100 | AD17: 62900
A18: price_avg | C18: 종가(평균) | E18: 74710.1 | G18: 79783.4 | H18: 76683.3 | I18: 64300.9 | J18: 64056 | L18: 74957.9 | M18: 73942.8 | N18: 78641.9 | O18: 74175 | Q18: 61383.6 | R18: 60596.7 | S18: 53920.2 | T18: 45203.3 | V18: 38918.1 | W18: 42007.5 | X18: 48463.1 | Y18: 46804.2 | AA18: 105422 | AB18: 124445.9 | AC18: 66313.7 | AD18: 69920
B20: 2. 추정 드라이버 | C20: 실적 열 = subQ 실현값(수식), 추정 열 = 가정(노란 = 모델값 역산, 연녹 = 3절 스칼라 참조)
A21: drv:매출액 | B21: yoy | C21: 매출액 YoY | J21: =IFERROR(subQ!J5/subQ!E5-1,"") | L21: =IFERROR(subQ!L5/subQ!G5-1,"") | M21: =IFERROR(subQ!M5/subQ!H5-1,"") | N21: =IFERROR(subQ!N5/subQ!I5-1,"") | O21: =IFERROR(subQ!O5/subQ!J5-1,"") | Q21: =IFERROR(subQ!Q5/subQ!L5-1,"") | R21: =IFERROR(subQ!R5/subQ!M5-1,"") | S21: =IFERROR(subQ!S5/subQ!N5-1,"") | T21: =IFERROR(subQ!T5/subQ!O5-1,"") | V21: =IFERROR(subQ!V5/subQ!Q5-1,"") | W21: =IFERROR(subQ!W5/subQ!R5-1,"") | X21: =IFERROR(subQ!X5/subQ!S5-1,"") | Y21: =IFERROR(subQ!Y5/subQ!T5-1,"") | AA21: =IFERROR(subQ!AA5/subQ!V5-1,"") | AB21: =IFERROR(subQ!AB5/subQ!W5-1,"") | AC21: 0.41192503 | AD21: 0.4119246 | AF21: 0.41192768 | AG21: 0.41192178 | AH21: 0.20595572 | AI21: 0.20596044 | AK21: 0.20595284 | AL21: 0.20595904 | AM21: 0.1029849 | AN21: 0.10297862
A22: drv:판관비 | B22: ratio | C22: 판관비율(/매출) | E22: =IFERROR(subQ!E8/subQ!E5,"") | F22: =IFERROR(subQ!F8/subQ!F5,"") | G22: =IFERROR(subQ!G8/subQ!G5,"") | H22: =IFERROR(subQ!H8/subQ!H5,"") | I22: =IFERROR(subQ!I8/subQ!I5,"") | J22: =IFERROR(subQ!J8/subQ!J5,"") | K22: =IFERROR(subQ!K8/subQ!K5,"") | L22: =IFERROR(subQ!L8/subQ!L5,"") | ... AB22: =IFERROR(subQ!AB8/subQ!AB5,"") | AC22: =$D$48 | AD22: =$D$48 | AE22: =IFERROR(subQ!AE8/subQ!AE5,"") | AF22: =$D$48 | AG22: =$D$48 | AH22: =$D$48 | AI22: =$D$48 | AJ22: =IFERROR(subQ!AJ8/subQ!AJ5,"") | AK22: =$D$48 | AL22: =$D$48 | AM22: =$D$48 | AN22: =$D$48 | AO22: =IFERROR(subQ!AO8/subQ!AO5,"")
A23: drv:영업이익 | B23: ratio | C23: 영업이익률(OPM) | E23: =IFERROR(subQ!E9/subQ!E5,"") | F23: =IFERROR(subQ!F9/subQ!F5,"") | G23: =IFERROR(subQ!G9/subQ!G5,"") | H23: =IFERROR(subQ!H9/subQ!H5,"") | I23: =IFERROR(subQ!I9/subQ!I5,"") | J23: =IFERROR(subQ!J9/subQ!J5,"") | K23: =IFERROR(subQ!K9/subQ!K5,"") | L23: =IFERROR(subQ!L9/subQ!L5,"") | ... AB23: =IFERROR(subQ!AB9/subQ!AB5,"") | AC23: 0.016379611 | AD23: 0.016379526 | AE23: =IFERROR(subQ!AE9/subQ!AE5,"") | AF23: 0.016381244 | AG23: 0.016379712 | AH23: 0.016380851 | AI23: 0.016378883 | AJ23: =IFERROR(subQ!AJ9/subQ!AJ5,"") | AK23: 0.016378419 | AL23: 0.016378493 | AM23: 0.016382027 | AN23: 0.016378768 | AO23: =IFERROR(subQ!AO9/subQ!AO5,"")
A24: drv:기타영업외손익 | B24: abs | C24: 기타영업외손익 (가정, 억원) | E24: =subQ!E13 | F24: =subQ!F13 | G24: =subQ!G13 | H24: =subQ!H13 | I24: =subQ!I13 | J24: =subQ!J13 | K24: =subQ!K13 | L24: =subQ!L13 | ... AB24: =subQ!AB13 | AC24: 0 | AD24: 0 | AE24: =subQ!AE13 | AF24: 0 | AG24: 0 | AH24: 0 | AI24: 0 | AJ24: =subQ!AJ13 | AK24: 0 | AL24: 0 | AM24: 0 | AN24: 0 | AO24: =subQ!AO13
A25: drv:법인세비용 | B25: tax | C25: 법인세율(/세전) — 법인세 = MAX(세전,0) × 세율 | E25: =IFERROR(subQ!E15/subQ!E14,"") | F25: =IFERROR(subQ!F15/subQ!F14,"") | G25: =IFERROR(subQ!G15/subQ!G14,"") | H25: =IFERROR(subQ!H15/subQ!H14,"") | I25: =IFERROR(subQ!I15/subQ!I14,"") | J25: =IFERROR(subQ!J15/subQ!J14,"") | K25: =IFERROR(subQ!K15/subQ!K14,"") | L25: =IFERROR(subQ!L15/subQ!L14,"") | ... AB25: =IFERROR(subQ!AB15/subQ!AB14,"") | AC25: =$D$47 | AD25: =$D$47 | AE25: =IFERROR(subQ!AE15/subQ!AE14,"") | AF25: =$D$47 | AG25: =$D$47 | AH25: =$D$47 | AI25: =$D$47 | AJ25: =IFERROR(subQ!AJ15/subQ!AJ14,"") | AK25: =$D$47 | AL25: =$D$47 | AM25: =$D$47 | AN25: =$D$47 | AO25: =IFERROR(subQ!AO15/subQ!AO14,"")
A26: drv:지배주주순이익 | B26: ratio | C26: 지배주주 비중(/당기순이익) | E26: =IFERROR(subQ!E17/subQ!E16,"") | F26: =IFERROR(subQ!F17/subQ!F16,"") | G26: =IFERROR(subQ!G17/subQ!G16,"") | H26: =IFERROR(subQ!H17/subQ!H16,"") | I26: =IFERROR(subQ!I17/subQ!I16,"") | J26: =IFERROR(subQ!J17/subQ!J16,"") | K26: =IFERROR(subQ!K17/subQ!K16,"") | L26: =IFERROR(subQ!L17/subQ!L16,"") | ... AB26: =IFERROR(subQ!AB17/subQ!AB16,"") | AC26: =$D$49 | AD26: =$D$49 | AE26: =IFERROR(subQ!AE17/subQ!AE16,"") | AF26: =$D$49 | AG26: =$D$49 | AH26: =$D$49 | AI26: =$D$49 | AJ26: =IFERROR(subQ!AJ17/subQ!AJ16,"") | AK26: =$D$49 | AL26: =$D$49 | AM26: =$D$49 | AN26: =$D$49 | AO26: =IFERROR(subQ!AO17/subQ!AO16,"")
A27: drv:부채총계 | B27: qoq | C27: 부채총계 QoQ | G27: =IFERROR(subQ!G19/subQ!E19-1,"") | H27: =IFERROR(subQ!H19/subQ!G19-1,"") | I27: =IFERROR(subQ!I19/subQ!H19-1,"") | J27: =IFERROR(subQ!J19/subQ!I19-1,"") | L27: =IFERROR(subQ!L19/subQ!J19-1,"") | M27: =IFERROR(subQ!M19/subQ!L19-1,"") | N27: =IFERROR(subQ!N19/subQ!M19-1,"") | O27: =IFERROR(subQ!O19/subQ!N19-1,"") | Q27: =IFERROR(subQ!Q19/subQ!O19-1,"") | R27: =IFERROR(subQ!R19/subQ!Q19-1,"") | S27: =IFERROR(subQ!S19/subQ!R19-1,"") | T27: =IFERROR(subQ!T19/subQ!S19-1,"") | V27: =IFERROR(subQ!V19/subQ!T19-1,"") | W27: =IFERROR(subQ!W19/subQ!V19-1,"") | X27: =IFERROR(subQ!X19/subQ!W19-1,"") | Y27: =IFERROR(subQ!Y19/subQ!X19-1,"") | AA27: =IFERROR(subQ!AA19/subQ!Y19-1,"") | AB27: =IFERROR(subQ!AB19/subQ!AA19-1,"") | AC27: -8.58e-07 | AD27: 0 | AF27: 0 | AG27: 0 | AH27: 0 | AI27: 0 | AK27: 0 | AL27: 0 | AM27: 0 | AN27: 0
A28: drv:자본총계 | B28: roll | C28: 자본총계 기타변동(배당 등, 억원) | G28: =IFERROR(subQ!E20+subQ!G16-subQ!G20,"") | H28: =IFERROR(subQ!G20+subQ!H16-subQ!H20,"") | I28: =IFERROR(subQ!H20+subQ!I16-subQ!I20,"") | J28: =IFERROR(subQ!I20+subQ!J16-subQ!J20,"") | L28: =IFERROR(subQ!J20+subQ!L16-subQ!L20,"") | M28: =IFERROR(subQ!L20+subQ!M16-subQ!M20,"") | N28: =IFERROR(subQ!M20+subQ!N16-subQ!N20,"") | O28: =IFERROR(subQ!N20+subQ!O16-subQ!O20,"") | Q28: =IFERROR(subQ!O20+subQ!Q16-subQ!Q20,"") | R28: =IFERROR(subQ!Q20+subQ!R16-subQ!R20,"") | S28: =IFERROR(subQ!R20+subQ!S16-subQ!S20,"") | T28: =IFERROR(subQ!S20+subQ!T16-subQ!T20,"") | V28: =IFERROR(subQ!T20+subQ!V16-subQ!V20,"") | W28: =IFERROR(subQ!V20+subQ!W16-subQ!W20,"") | X28: =IFERROR(subQ!W20+subQ!X16-subQ!X20,"") | Y28: =IFERROR(subQ!X20+subQ!Y16-subQ!Y20,"") | AA28: =IFERROR(subQ!Y20+subQ!AA16-subQ!AA20,"") | AB28: =IFERROR(subQ!AA20+subQ!AB16-subQ!AB20,"")
A29: drv:지배주주지분 | B29: roll | C29: 지배주주지분 기타변동(배당 등, 억원) | G29: =IFERROR(subQ!E21+subQ!G17-subQ!G21,"") | H29: =IFERROR(subQ!G21+subQ!H17-subQ!H21,"") | I29: =IFERROR(subQ!H21+subQ!I17-subQ!I21,"") | J29: =IFERROR(subQ!I21+subQ!J17-subQ!J21,"") | L29: =IFERROR(subQ!J21+subQ!L17-subQ!L21,"") | M29: =IFERROR(subQ!L21+subQ!M17-subQ!M21,"") | N29: =IFERROR(subQ!M21+subQ!N17-subQ!N21,"") | O29: =IFERROR(subQ!N21+subQ!O17-subQ!O21,"") | Q29: =IFERROR(subQ!O21+subQ!Q17-subQ!Q21,"") | R29: =IFERROR(subQ!Q21+subQ!R17-subQ!R21,"") | S29: =IFERROR(subQ!R21+subQ!S17-subQ!S21,"") | T29: =IFERROR(subQ!S21+subQ!T17-subQ!T21,"") | V29: =IFERROR(subQ!T21+subQ!V17-subQ!V21,"") | W29: =IFERROR(subQ!V21+subQ!W17-subQ!W21,"") | X29: =IFERROR(subQ!W21+subQ!X17-subQ!X21,"") | Y29: =IFERROR(subQ!X21+subQ!Y17-subQ!Y21,"") | AA29: =IFERROR(subQ!Y21+subQ!AA17-subQ!AA21,"") | AB29: =IFERROR(subQ!AA21+subQ!AB17-subQ!AB21,"") | AC29: -0.000200803 | AD29: -0.001997346 | AF29: 5.8479e-05 | AG29: 20.441998 | AH29: 0.00506408 | AI29: -0.002850513 | AK29: -0.003170288 | AL29: 20.444163 | AM29: 0.001883336 | AN29: -0.004446441
A30: drv:총차입금 | B30: qoq | C30: 총차입금 QoQ | G30: =IFERROR(subQ!G22/subQ!E22-1,"") | H30: =IFERROR(subQ!H22/subQ!G22-1,"") | I30: =IFERROR(subQ!I22/subQ!H22-1,"") | J30: =IFERROR(subQ!J22/subQ!I22-1,"") | L30: =IFERROR(subQ!L22/subQ!J22-1,"") | M30: =IFERROR(subQ!M22/subQ!L22-1,"") | N30: =IFERROR(subQ!N22/subQ!M22-1,"") | O30: =IFERROR(subQ!O22/subQ!N22-1,"") | Q30: =IFERROR(subQ!Q22/subQ!O22-1,"") | R30: =IFERROR(subQ!R22/subQ!Q22-1,"") | S30: =IFERROR(subQ!S22/subQ!R22-1,"") | T30: =IFERROR(subQ!T22/subQ!S22-1,"") | V30: =IFERROR(subQ!V22/subQ!T22-1,"") | W30: =IFERROR(subQ!W22/subQ!V22-1,"") | X30: =IFERROR(subQ!X22/subQ!W22-1,"") | Y30: =IFERROR(subQ!Y22/subQ!X22-1,"") | AA30: =IFERROR(subQ!AA22/subQ!Y22-1,"") | AB30: =IFERROR(subQ!AB22/subQ!AA22-1,"") | AC30: 3.136e-06 | AD30: 0 | AF30: 0 | AG30: 0 | AH30: 0 | AI30: 0 | AK30: 0 | AL30: 0 | AM30: 0 | AN30: 0
A31: drv:순차입금 | B31: qoq | C31: 순차입금 QoQ | G31: =IFERROR(subQ!G23/subQ!E23-1,"") | H31: =IFERROR(subQ!H23/subQ!G23-1,"") | I31: =IFERROR(subQ!I23/subQ!H23-1,"") | J31: =IFERROR(subQ!J23/subQ!I23-1,"") | L31: =IFERROR(subQ!L23/subQ!J23-1,"") | M31: =IFERROR(subQ!M23/subQ!L23-1,"") | N31: =IFERROR(subQ!N23/subQ!M23-1,"") | O31: =IFERROR(subQ!O23/subQ!N23-1,"") | Q31: =IFERROR(subQ!Q23/subQ!O23-1,"") | R31: =IFERROR(subQ!R23/subQ!Q23-1,"") | S31: =IFERROR(subQ!S23/subQ!R23-1,"") | T31: =IFERROR(subQ!T23/subQ!S23-1,"") | V31: =IFERROR(subQ!V23/subQ!T23-1,"") | W31: =IFERROR(subQ!W23/subQ!V23-1,"") | X31: =IFERROR(subQ!X23/subQ!W23-1,"") | Y31: =IFERROR(subQ!Y23/subQ!X23-1,"") | AA31: =IFERROR(subQ!AA23/subQ!Y23-1,"") | AB31: =IFERROR(subQ!AB23/subQ!AA23-1,"") | AC31: -0.003702945 | AD31: -0.012149612 | AF31: -0.001543849 | AG31: 0.01021034 | AH31: -0.006601281 | AI31: -0.016931354 | AK31: -0.004062763 | AL31: 0.006646504 | AM31: -0.008567686 | AN31: -0.020252116
A32: drv:이자발생자산 | B32: qoq | C32: 이자발생자산 QoQ | G32: =IFERROR(subQ!G24/subQ!E24-1,"") | H32: =IFERROR(subQ!H24/subQ!G24-1,"") | I32: =IFERROR(subQ!I24/subQ!H24-1,"") | J32: =IFERROR(subQ!J24/subQ!I24-1,"") | L32: =IFERROR(subQ!L24/subQ!J24-1,"") | M32: =IFERROR(subQ!M24/subQ!L24-1,"") | N32: =IFERROR(subQ!N24/subQ!M24-1,"") | O32: =IFERROR(subQ!O24/subQ!N24-1,"") | Q32: =IFERROR(subQ!Q24/subQ!O24-1,"") | R32: =IFERROR(subQ!R24/subQ!Q24-1,"") | S32: =IFERROR(subQ!S24/subQ!R24-1,"") | T32: =IFERROR(subQ!T24/subQ!S24-1,"") | V32: =IFERROR(subQ!V24/subQ!T24-1,"") | W32: =IFERROR(subQ!W24/subQ!V24-1,"") | X32: =IFERROR(subQ!X24/subQ!W24-1,"") | Y32: =IFERROR(subQ!Y24/subQ!X24-1,"") | AA32: =IFERROR(subQ!AA24/subQ!Y24-1,"") | AB32: =IFERROR(subQ!AB24/subQ!AA24-1,"") | AC32: 0.005555568 | AD32: 0.01807901 | AF32: 0.002229085 | AG32: -0.014686696 | AH32: 0.009747916 | AI32: 0.024565391 | AK32: 0.005643657 | AL32: -0.009151293 | AM32: 0.011988208 | AN32: 0.027790202
A33: drv:현금및현금성자산 | B33: qoq | C33: 현금및현금성자산 QoQ | G33: =IFERROR(subQ!G25/subQ!E25-1,"") | H33: =IFERROR(subQ!H25/subQ!G25-1,"") | I33: =IFERROR(subQ!I25/subQ!H25-1,"") | J33: =IFERROR(subQ!J25/subQ!I25-1,"") | L33: =IFERROR(subQ!L25/subQ!J25-1,"") | M33: =IFERROR(subQ!M25/subQ!L25-1,"") | N33: =IFERROR(subQ!N25/subQ!M25-1,"") | O33: =IFERROR(subQ!O25/subQ!N25-1,"") | Q33: =IFERROR(subQ!Q25/subQ!O25-1,"") | R33: =IFERROR(subQ!R25/subQ!Q25-1,"") | S33: =IFERROR(subQ!S25/subQ!R25-1,"") | T33: =IFERROR(subQ!T25/subQ!S25-1,"") | V33: =IFERROR(subQ!V25/subQ!T25-1,"") | W33: =IFERROR(subQ!W25/subQ!V25-1,"") | X33: =IFERROR(subQ!X25/subQ!W25-1,"") | Y33: =IFERROR(subQ!Y25/subQ!X25-1,"") | AA33: =IFERROR(subQ!AA25/subQ!Y25-1,"") | AB33: =IFERROR(subQ!AB25/subQ!AA25-1,"")
A34: drv:CAPEX | B34: yoy | C34: CAPEX YoY | J34: =IFERROR(subQ!J26/subQ!E26-1,"") | L34: =IFERROR(subQ!L26/subQ!G26-1,"") | M34: =IFERROR(subQ!M26/subQ!H26-1,"") | N34: =IFERROR(subQ!N26/subQ!I26-1,"") | O34: =IFERROR(subQ!O26/subQ!J26-1,"") | Q34: =IFERROR(subQ!Q26/subQ!L26-1,"") | R34: =IFERROR(subQ!R26/subQ!M26-1,"") | S34: =IFERROR(subQ!S26/subQ!N26-1,"") | T34: =IFERROR(subQ!T26/subQ!O26-1,"") | V34: =IFERROR(subQ!V26/subQ!Q26-1,"") | W34: =IFERROR(subQ!W26/subQ!R26-1,"") | X34: =IFERROR(subQ!X26/subQ!S26-1,"") | Y34: =IFERROR(subQ!Y26/subQ!T26-1,"") | AA34: =IFERROR(subQ!AA26/subQ!V26-1,"") | AB34: =IFERROR(subQ!AB26/subQ!W26-1,"") | AC34: -0.19762378 | AD34: 0.37421763 | AF34: -0.10901338 | AG34: 0.13946764 | AH34: 0 | AI34: 0 | AK34: 0 | AL34: 0 | AM34: 0 | AN34: 0
A35: drv:영업활동현금흐름 | B35: yoy | C35: 영업활동현금흐름 YoY | J35: =IFERROR(subQ!J27/subQ!E27-1,"") | L35: =IFERROR(subQ!L27/subQ!G27-1,"") | M35: =IFERROR(subQ!M27/subQ!H27-1,"") | N35: =IFERROR(subQ!N27/subQ!I27-1,"") | O35: =IFERROR(subQ!O27/subQ!J27-1,"") | Q35: =IFERROR(subQ!Q27/subQ!L27-1,"") | R35: =IFERROR(subQ!R27/subQ!M27-1,"") | S35: =IFERROR(subQ!S27/subQ!N27-1,"") | T35: =IFERROR(subQ!T27/subQ!O27-1,"") | V35: =IFERROR(subQ!V27/subQ!Q27-1,"") | W35: =IFERROR(subQ!W27/subQ!R27-1,"") | X35: =IFERROR(subQ!X27/subQ!S27-1,"") | Y35: =IFERROR(subQ!Y27/subQ!T27-1,"") | AA35: =IFERROR(subQ!AA27/subQ!V27-1,"") | AB35: =IFERROR(subQ!AB27/subQ!W27-1,"")
A36: drv:주식수 | B36: qoq | C36: 주식수 QoQ | G36: =IFERROR(subQ!G28/subQ!E28-1,"") | H36: =IFERROR(subQ!H28/subQ!G28-1,"") | I36: =IFERROR(subQ!I28/subQ!H28-1,"") | J36: =IFERROR(subQ!J28/subQ!I28-1,"") | L36: =IFERROR(subQ!L28/subQ!J28-1,"") | M36: =IFERROR(subQ!M28/subQ!L28-1,"") | N36: =IFERROR(subQ!N28/subQ!M28-1,"") | O36: =IFERROR(subQ!O28/subQ!N28-1,"") | Q36: =IFERROR(subQ!Q28/subQ!O28-1,"") | R36: =IFERROR(subQ!R28/subQ!Q28-1,"") | S36: =IFERROR(subQ!S28/subQ!R28-1,"") | T36: =IFERROR(subQ!T28/subQ!S28-1,"") | V36: =IFERROR(subQ!V28/subQ!T28-1,"") | W36: =IFERROR(subQ!W28/subQ!V28-1,"") | X36: =IFERROR(subQ!X28/subQ!W28-1,"") | Y36: =IFERROR(subQ!Y28/subQ!X28-1,"") | AA36: =IFERROR(subQ!AA28/subQ!Y28-1,"") | AB36: =IFERROR(subQ!AB28/subQ!AA28-1,"") | AC36: 0 | AD36: 0 | AF36: 0 | AG36: 0 | AH36: 0 | AI36: 0 | AK36: 0 | AL36: 0 | AM36: 0 | AN36: 0
A37: drv:DPS | B37: abs | C37: DPS (가정, 원) | E37: =subQ!E31 | F37: =subQ!F31 | G37: =subQ!G31 | H37: =subQ!H31 | I37: =subQ!I31 | J37: =subQ!J31 | K37: =subQ!K31 | L37: =subQ!L31 | ... AB37: =subQ!AB31 | AD37: 200 | AE37: =subQ!AE31 | AI37: 200 | AJ37: =subQ!AJ31 | AN37: 200 | AO37: =subQ!AO31
B39: 3. 밸류에이션·스칼라 | C39: 노란 셀 = 가정. '연결' 표시는 추정 전 분기 수식이 이 셀을 참조한다는 뜻
A40: sc:종가 | C40: 종가 | D40: 63800 | E40: 원 — 네이버 정규장 종가(aik 확정종가 대조 · aik 68,500원)
A41: sc:기준일 | C41: 기준일 | D41: 20261008 | E41: 종가 기준일
A42: sc:COE | C42: COE | D42: 0.09 | E42: 자기자본비용(가정) — TP 적정 PBR = ROE/COE
A43: sc:PER_lo | C43: PER_lo | D43: 10 | E43: PER 밴드 하단(배) — sector_default(레퍼런스 TP_PE PB 예시 10/15/20배; 과거 PER 중위 48.9배가 3~40 밖(턴어라운드 왜곡))
A44: sc:PER_mid | C44: PER_mid | D44: 15 | E44: PER 밴드 중단(배)
A45: sc:PER_hi | C45: PER_hi | D45: 20 | E45: PER 밴드 상단(배)
A46: sc:EPS_Y1가중 | C46: EPS_Y1가중 | D46: 0.5 | E46: 12M fwd EPS = FY(last_actual연도)E × w + FY+1E × (1−w) — 기준 분기 2Q 이면 0.5(가정)
A47: sc:세율 | C47: 세율 | D47: 0.09219255 | E47: 연결 — 법인세 = MAX(세전,0) × 세율(역산, 재현 오차 ≤ 0.05억 · 모델 assumptions 0.0922) · 최근 12분기 유효세율 9.2%(5~27% 안 — 그대로)
A48: sc:판관비율 | C48: 판관비율 | D48: 0.35325342 | E48: 연결 — 판관비 = 매출액 × 판관비율(역산, 재현 오차 ≤ 0.05억 · 모델 assumptions 0.3533)
A49: sc:지배주주비중 | C49: 지배주주비중 | D49: 1 | E49: 연결 — 지배주주순이익 = 당기순이익 × 비중(역산, 재현 오차 ≤ 0.05억)
A50: sc:이자율_자산 | C50: 이자율_자산 | D50: 0.012867009 | E50: 연결 — 이자손익 = (전분기 이자발생자산 × 자산이자율 − 전분기 총차입금 × 부채이자율)/4(역산, 재현 오차 ≤ 0.05억 · 모델 assumptions 0.0126)
A51: sc:이자율_부채 | C51: 이자율_부채 | D51: 0.043430593 | E51: 연결 — 같은 수식의 부채 쪽(총차입금 행이 없으면 0)(역산, 재현 오차 ≤ 0.05억 · 모델 assumptions 0.0433)
A52: sc:배당성향 | C52: 배당성향 | D52: 0.2739 | E52: 배당성향(참고 — 모델은 직전 DPS 유지·Q2 지급 가정)
A53: sc:외화순노출_백만$ | C53: 외화순노출_백만$ | E53: 외화 순노출 × Δ기말환율 (외화 시트 방식) — 외화 순노출 미공시(face) → 0 + 표기
A54: sc:헤지비율 | C54: 헤지비율 | E54: sls 없음
A55: sc:헤지환율_약정 | C55: 헤지환율_약정 | E55: sls 없음

Sheet BS연결
B1: (백만원) | C1: 이름: BS연결H | E1: 4Q21 | F1: 2021 | G1: 1Q22 | H1: 2Q22 | I1: 3Q22 | J1: 4Q22 | K1: 2022 | L1: 1Q23 | M1: 2Q23 | N1: 3Q23 | O1: 4Q23 | P1: 2023 | Q1: 1Q24 | R1: 2Q24 | S1: 3Q24 | T1: 4Q24 | U1: 2024 | V1: 1Q25 | W1: 2Q25 | X1: 3Q25 | Y1: 4Q25 | Z1: 2025 | AA1: 1Q26 | AB1: 2Q26 | AC1: 3Q26 | AD1: 4Q26 | AE1: 2026 | AF1: 1Q27 | AG1: 2Q27 | AH1: 3Q27 | AI1: 4Q27 | AJ1: 2027 | AK1: 1Q28 | AL1: 2Q28 | AM1: 3Q28 | AN1: 4Q28 | AO1: 2028
B2: 연결 | D2: fin json(kship_fin.py)
B3: 인텔리안테크(연) | C3: UPDATE: 26-10-11 | E3: 1 | F3: 2 | G3: 3 | H3: 4 | I3: 5 | J3: 6 | K3: 7 | L3: 8 | M3: 9 | N3: 10 | O3: 11 | P3: 12 | Q3: 13 | R3: 14 | S3: 15 | T3: 16 | U3: 17 | V3: 18 | W3: 19 | X3: 20 | Y3: 21 | Z3: 22 | AA3: 23 | AB3: 24 | AC3: 25 | AD3: 26 | AE3: 27 | AF3: 28 | AG3: 29 | AH3: 30 | AI3: 31 | AJ3: 32 | AK3: 33 | AL3: 34 | AM3: 35 | AN3: 36 | AO3: 37
B4: Account Code | C4: AccountNAME | E4: 2021.12 | F4: 2021.12A | G4: 2022.03 | H4: 2022.06 | I4: 2022.09 | J4: 2022.12 | K4: 2022.12A | L4: 2023.03 | M4: 2023.06 | N4: 2023.09 | O4: 2023.12 | P4: 2023.12A | Q4: 2024.03 | R4: 2024.06 | S4: 2024.09 | T4: 2024.12 | U4: 2024.12A | V4: 2025.03 | W4: 2025.06 | X4: 2025.09 | Y4: 2025.12 | Z4: 2025.12A | AA4: 2026.03 | AB4: 2026.06 | AC4: 2026.09 | AD4: 2026.12 | AE4: 2026.12A | AF4: 2027.03 | AG4: 2027.06 | AH4: 2027.09 | AI4: 2027.12 | AJ4: 2027.12A | AK4: 2028.03 | AL4: 2028.06 | AM4: 2028.09 | AN4: 2028.12 | AO4: 2028.12A
A5: 1 | C5: 유동자산 | E5: 155257 | F5: 155257 | G5: 168420.72 | H5: 175170.56 | I5: 202264.03 | J5: 214268.22 | K5: 214268.22 | L5: 213169.3 | M5: 221710.78 | N5: 291151.19 | O5: 283330.11 | P5: 283330.11 | Q5: 254872.26 | R5: 280715.87 | S5: 249812.87 | T5: 225272.82 | U5: 225272.82 | V5: 217246.58 | W5: 237396.12 | X5: 260203.49 | Y5: 276818.59 | Z5: 276818.59 | AA5: 271015.01 | AB5: 291867.65
A6: 1 | C6: 현금및현금성자산 | E6: 22538.5 | F6: 22538.5 | G6: 20133.03 | H6: 19262 | I6: 26906.15 | J6: 24414.57 | K6: 24414.57 | L6: 17940.93 | M6: 26838.97 | N6: 47860.78 | O6: 55948.74 | P6: 55948.74 | Q6: 39907.26 | R6: 30670.91 | S6: 26478.87 | T6: 21486.67 | U6: 21486.67 | V6: 24147.18 | W6: 17215.97 | X6: 23519.4 | Y6: 32845.85 | Z6: 32845.85 | AA6: 31798.82 | AB6: 25099.37
A7: 1 | C7: 단기금융상품 | E7: 35344.38 | F7: 35344.38 | G7: 31965.52 | H7: 19001.27 | I7: 18704.43 | J7: 5896.06 | K7: 5896.06 | M7: 10834.26 | N7: 65030.04 | O7: 66353.66 | P7: 66353.66 | Q7: 78172.43 | R7: 75138.84 | S7: 42642.71 | T7: 37682.92 | U7: 37682.92 | V7: 42166.67 | W7: 15049.2 | X7: 7558.8 | Y7: 500 | Z7: 500 | AA7: 0 | AB7: 598.95
A8: 1 | C8: 단기금융자산 | E8: 35346.69 | F8: 35346.69 | G8: 31965.52 | H8: 19001.27 | I8: 18704.43 | J8: 5896.06 | K8: 5896.06 | M8: 10834.26 | N8: 65030.04 | O8: 66353.66 | P8: 66353.66 | Q8: 78172.43 | R8: 75138.84 | S8: 42642.71 | T8: 37682.92 | U8: 37682.92 | V8: 42166.67 | W8: 15049.2 | X8: 7558.8 | Y8: 500 | Z8: 500 | AA8: 0 | AB8: 598.95
A9: 1 | C9: 매출채권및기타채권 | E9: 43622.87 | F9: 43622.87 | G9: 49846.19 | H9: 52682.95 | I9: 55441.44 | J9: 63639.26 | K9: 63639.26 | L9: 62842.46 | M9: 69482.24 | N9: 66971.91 | O9: 68761.04 | P9: 68761.04 | Q9: 41545.82 | R9: 67405.78 | S9: 61597.96 | T9: 70798.5 | U9: 70798.5 | V9: 49518.75 | W9: 87994.45 | X9: 96730.02 | Y9: 130468.5 | Z9: 130468.5 | AA9: 107536.57 | AB9: 121805.82
A10: 1 | C10: 계약자산 | E10: 77.05 | F10: 77.05 | G10: 116 | H10: 255.99 | I10: 63.42 | J10: 53.4 | K10: 53.4 | L10: 53.4 | Q10: 852.66 | R10: 512.5 | S10: 1274.68
A11: 1 | C11: 유동파생상품자산 | E11: 2.31 | F11: 2.31
A12: 1 | C12: 기타유동자산 | E12: 6434.53 | F12: 6434.53 | G12: 8680.7 | H12: 11014.57 | I12: 11698.09 | J12: 12851.93 | K12: 12851.93 | L12: 13219.99 | M12: 8941.03 | N12: 9241.59 | O12: 9213.85 | P12: 9213.85 | Q12: 8942.13 | R12: 10378.18 | S12: 11577.38 | T12: 6249.1 | U12: 6249.1 | V12: 5304.76 | W12: 6912.37 | X12: 8380.74 | Y12: 11228.48 | Z12: 11228.48 | AA12: 8180.87 | AB12: 9070.62
A13: 1 | C13: 재고자산 | E13: 47140.58 | F13: 47140.58 | G13: 57587.93 | H13: 72870.71 | I13: 88621.32 | J13: 107271.58 | K13: 107271.58 | L13: 118939.89 | M13: 105222.95 | N13: 101641.63 | O13: 82665.42 | P13: 82665.42 | Q13: 84393.99 | R13: 95594.85 | S13: 105177.88 | T13: 87223.09 | U13: 87223.09 | V13: 94913.21 | W13: 108221.33 | X13: 122010.21 | Y13: 100736.64 | Z13: 100736.64 | AA13: 122444.42 | AB13: 134194.48
A14: 1 | C14: 비유동자산 | E14: 106217.93 | F14: 106217.93 | G14: 115824.85 | H14: 127212.67 | I14: 137975.68 | J14: 156108.92 | K14: 156108.92 | L14: 166958.29 | M14: 168902.49 | N14: 168903.97 | O14: 170359.06 | P14: 170359.06 | Q14: 188206.15 | R14: 200516.13 | S14: 204974.79 | T14: 215420.25 | U14: 215420.25 | V14: 212230.22 | W14: 222176.49 | X14: 223884.44 | Y14: 219639.58 | Z14: 219639.58 | AA14: 247014.59 | AB14: 250469.61
A15: 1 | C15: 장기금융자산 | E15: 9092.16 | F15: 9092.16 | G15: 10625.57 | H15: 14862.05 | I15: 14283.48 | J15: 18454.42 | K15: 18454.42 | L15: 17258.75 | M15: 17431.76 | N15: 16953.26 | O15: 15114.96 | P15: 15114.96 | Q15: 22661.82 | R15: 29292.55 | S15: 36585.35 | T15: 48740.17 | U15: 48740.17 | V15: 48628.62 | W15: 60145.56 | X15: 51312.22 | Y15: 47752.82 | Z15: 47752.82 | AA15: 56186.96 | AB15: 52741.9
A16: 1 | C16: 투자자산 | E16: 9092.16 | F16: 9092.16 | G16: 10625.57 | H16: 14862.05 | I16: 14283.48 | J16: 18454.42 | K16: 18454.42 | L16: 17258.75 | M16: 17431.76 | N16: 16953.26 | O16: 15114.96 | P16: 15114.96 | Q16: 22661.82 | R16: 29292.55 | S16: 36585.35 | T16: 48740.17 | U16: 48740.17 | V16: 48628.62 | W16: 60145.56 | X16: 51312.22 | Y16: 47752.82 | Z16: 47752.82 | AA16: 56186.96 | AB16: 52741.9
A17: 1 | C17: 장기매출채권및기타채권 | E17: 3487.81 | F17: 3487.81 | G17: 3160.29 | H17: 2854.93 | I17: 1042.34 | J17: 879.63 | K17: 879.63 | L17: 292.79 | M17: 410.51 | N17: 462.23 | O17: 472.78 | P17: 472.78 | Q17: 712.46 | R17: 832.48 | S17: 910.33 | T17: 722.84 | U17: 722.84 | V17: 786.11 | W17: 804.03 | X17: 1125.12 | Y17: 1001.79 | Z17: 1001.79 | AA17: 989.17 | AB17: 1002.48
A18: 1 | C18: 유형자산 | E18: 64589.43 | F18: 64589.43 | G18: 72341.91 | H18: 78786.34 | I18: 89604.02 | J18: 101649.21 | K18: 101649.21 | L18: 112261.6 | M18: 114673.48 | N18: 114069.75 | O18: 113528.17 | P18: 113528.17 | Q18: 119540.01 | R18: 118510.17 | S18: 114522.89 | T18: 114876.85 | U18: 114876.85 | V18: 111788.47 | W18: 106983.11 | X18: 113538.66 | Y18: 109056.67 | Z18: 109056.67 | AA18: 127286.17 | AB18: 124727.98
A19: 1 | C19: 무형자산 | E19: 17017.54 | F19: 17017.54 | G19: 16960.74 | H19: 17614.25 | I19: 18593.49 | J19: 19660.05 | K19: 19660.05 | L19: 20139.7 | M19: 19288.39 | N19: 22390.12 | O19: 26961.02 | P19: 26961.02 | Q19: 32499.63 | R19: 38655.66 | S19: 39795.79 | T19: 38179.61 | U19: 38179.61 | V19: 37999.2 | W19: 41117.41 | X19: 44024.37 | Y19: 44437.64 | Z19: 44437.64 | AA19: 45627.89 | AB19: 44145.02
A20: 1 | C20: 기타비유동자산 | E20: 1139.5 | F20: 1139.5 | G20: 1355.83 | H20: 1675.43 | I20: 1331.97 | J20: 2426.34 | K20: 2426.34 | L20: 2451.26 | M20: 2510.77 | N20: 2506.14 | O20: 2528.6 | P20: 2528.6 | Q20: 1938.73 | R20: 2052.39 | S20: 1993.62 | T20: 1329.62 | U20: 1329.62 | V20: 1454 | W20: 1328.17 | X20: 1653.24 | Y20: 2922.12 | Z20: 2922.12 | AA20: 2681.92 | AB20: 5790.29
A21: 1 | C21: 이연법인세자산 | E21: 10480.94 | F21: 10480.94 | G21: 10448.36 | H21: 11265.24 | I21: 12187.93 | J21: 11562.58 | K21: 11562.58 | L21: 11099.64 | M21: 10855.35 | N21: 11461.42 | O21: 10952.81 | P21: 10952.81 | Q21: 10853.51 | R21: 11172.87 | S21: 11166.82 | T21: 11571.16 | U21: 11571.16 | V21: 11573.83 | W21: 11798.21 | X21: 12230.82 | Y21: 14468.54 | Z21: 14468.54 | AA21: 14242.48 | AB21: 14284.12
A22: 1 | C22: 자산총계 | E22: 261474.93 | F22: 261474.93 | G22: 284245.57 | H22: 302383.23 | I22: 340239.7 | J22: 370377.14 | K22: 370377.14 | L22: 380127.59 | M22: 390613.27 | N22: 460055.16 | O22: 453689.17 | P22: 453689.17 | Q22: 443078.41 | R22: 481232 | S22: 454787.67 | T22: 440693.07 | U22: 440693.07 | V22: 429476.8 | W22: 459572.61 | X22: 484087.93 | Y22: 496458.17 | Z22: 496458.17 | AA22: 518029.61 | AB22: 542337.27
A23: 1 | C23: 유동부채 | E23: 67404.79 | F23: 67404.79 | G23: 81496.98 | H23: 87762.13 | I23: 109097.67 | J23: 134703.61 | K23: 134703.61 | L23: 128826.8 | M23: 126075.02 | N23: 106247.36 | O23: 101749.21 | P23: 101749.21 | Q23: 93190.43 | R23: 125653.1 | S23: 114721.34 | T23: 91670.41 | U23: 91670.41 | V23: 107974.97 | W23: 145073.28 | X23: 140794.63 | Y23: 147623.21 | Z23: 147623.21 | AA23: 150049.12 | AB23: 169769.49
... A41: 1 | C41: 이익잉여금 | E41: 41398.63 | F41: 41398.63 | G41: 43405.14 | H41: 50191.95 | I41: 56856.67 | J41: 56692.74 | K41: 56692.74 | L41: 56803.97 | M41: 62689.89 | N41: 63209.83 | O41: 61271.07 | P41: 61271.07 | Q41: 55348.37 | R41: 56221.94 | S41: 44103.47 | T41: 55195.96 | U41: 55195.96 | V41: 40025.76 | W41: 35957.94 | X41: 39316.75 | Y41: 62997.43 | Z41: 62997.43 | AA41: 74429 | AB41: 79174.48
A42: 1 | C42: 자본총계 | E42: 161998.34 | F42: 161998.34 | G42: 164374.03 | H42: 172083.95 | I42: 179878.56 | J42: 178704.3 | K42: 178704.3 | L42: 179291.98 | M42: 185897.16 | N42: 276656.86 | O42: 275032.31 | P42: 275032.31 | Q42: 267136.64 | R42: 267360.8 | S42: 254069.81 | T42: 264642.29 | U42: 264642.29 | V42: 248538.99 | W42: 243443.25 | X42: 247072.29 | Y42: 266272.02 | Z42: 266272.02 | AA42: 279643.6
A43: 1 | C43: 부채와자본총계 | E43: 261474.93 | F43: 261474.93 | G43: 284245.57 | H43: 302383.23 | I43: 340239.7 | J43: 370377.14 | K43: 370377.14 | L43: 380127.59 | M43: 390613.27 | N43: 460055.16 | O43: 453689.17 | P43: 453689.17 | Q43: 443078.41 | R43: 481232 | S43: 454787.67 | T43: 440693.07 | U43: 440693.07 | V43: 429476.8 | W43: 459572.61 | X43: 484087.93 | Y43: 496458.17 | Z43: 496458.17 | AA43: 518029.61 | AB43: 542337.27
A44: 1 | C44: 총차입금 | E44: 46941.27 | F44: 46941.27 | G44: 62110.6 | H44: 63084.33 | I44: 84436.03 | J44: 105897.02 | K44: 105897.02 | L44: 118339.99 | M44: 139019.94 | N44: 113107.43 | O44: 109602.76 | P44: 109602.76 | Q44: 108765.16 | R44: 117473.78 | S44: 114225.23 | T44: 108055.68 | U44: 108055.68 | V44: 107397.5 | W44: 125874.97 | X44: 141235.44 | Y44: 136340.8 | Z44: 136340.8 | AA44: 132735.99 | AB44: 143504.55
A45: 1 | C45: 순차입금 | E45: -10943.92 | F45: -10943.92 | G45: 10012.05 | H45: 24821.06 | I45: 38825.45 | J45: 75586.39 | K45: 75586.39 | L45: 100399.06 | M45: 101346.71 | N45: 216.61 | O45: -12699.64 | P45: -12699.64 | Q45: -9314.53 | R45: 11664.03 | S45: 45103.65 | T45: 48886.09 | U45: 48886.09 | V45: 41083.65 | W45: 93609.8 | X45: 110157.24 | Y45: 102994.95 | Z45: 102994.95 | AA45: 100937.17 | AB45: 117806.23
A46: 1 | C46: 이자발생자산 | E46: 66977.35 | F46: 66977.35 | G46: 62724.12 | H46: 53125.32 | I46: 59894.06 | J46: 48765.05 | K46: 48765.05 | L46: 35199.68 | M46: 55104.99 | N46: 129844.08 | O46: 137417.36 | P46: 137417.36 | Q46: 140741.51 | R46: 135102.3 | S46: 105706.93 | T46: 107909.76 | U46: 107909.76 | V46: 114942.47 | W46: 92410.73 | X46: 82390.42 | Y46: 81098.67 | Z46: 81098.67 | AA46: 87985.78 | AB46: 78440.22
A47: 1 | C47: 단기파생상품부채 | G47: 199.85 | H47: 2126.26 | I47: 4487.19 | J47: 746.68 | K47: 746.68
A48: 1 | C48: 단기금융부채 | G48: 199.85 | H48: 2126.26 | I48: 4487.19 | J48: 746.68 | K48: 746.68
A49: 1 | C49: 비지배주주지분 | L49: 0 | X49: 0 | Y49: 0 | Z49: 0 | AA49: 0 | AB49: 0
A50: 1 | C50: 기타비유동부채 | O50: 299.6 | P50: 299.6
A51: 1 | C51: 이연법인세부채 | Q51: 312.94 | R51: 322.79 | S51: 306.62 | T51: 383.94 | U51: 383.94 | V51: 383.03 | W51: 354.27 | X51: 366.24 | Y51: 202.19 | Z51: 202.19 | AA51: 211.51 | AB51: 215.97
A52: 1 | C52: 장기금융부채(face) | S52: 52991.19 | T52: 54051.68 | U52: 54051.68 | V52: 43122.7 | X52: 67212.37
A53: 1 | C53: 당기법인세자산(선급법인세) | W53: 808.68 | X53: 868.48 | Y53: 706.61 | Z53: 706.61 | AA53: 802.34 | AB53: 791.18
A54: 1 | C54: 당기법인세부채(미지급법인세) | W54: 62.59 | X54: 64.07 | Y54: 2419.15 | Z54: 2419.15 | AA54: 1510.68 | AB54: 1198.35
A55: 1 | C55: 사채 | Y55: 20000 | Z55: 20000 | AA55: 20000 | AB55: 20000
A56: 1 | C56: 투자부동산 | AB56: 7777.84
A57: 1 | C57: 매출액(수익) | E57: 48293.36 | G57: 43025.3 | H57: 56984.24 | I57: 57036.79 | J57: 82419.02 | K57: 239465.35 | L57: 64393.46 | M57: 87594.79 | N57: 66774.94 | O57: 86279.65 | P57: 305042.84 | Q57: 46697.93 | R57: 71699.4 | S57: 62360.86 | T57: 77011.25 | U57: 257769.44 | V57: 43350.44 | W57: 74736 | X57: 77226.48 | Y57: 124315.42 | Z57: 319628.34 | AA57: 64723.57 | AB57: 97246.18
A58: 1 | C58: 매출원가 | E58: 27383.29 | G58: 25074.19 | H58: 34559.39 | I58: 35089.85 | J58: 42740.16 | K58: 137463.59 | L58: 39476.26 | M58: 49246.57 | N58: 41672.87 | O58: 52256.6 | P58: 182652.3 | Q58: 29186.15 | R58: 41411.95 | S58: 38188.87 | T58: 49555.35 | U58: 158342.32 | V58: 25409.03 | W58: 46768.67 | X58: 46702.5 | Y58: 75858.46 | Z58: 194738.66 | AA58: 33796.61 | AB58: 56853.9
A59: 1 | C59: 매출총이익 | E59: 20910.07 | G59: 17951.11 | H59: 22424.85 | I59: 21946.94 | J59: 39678.86 | K59: 102001.76 | L59: 24917.2 | M59: 38348.22 | N59: 25102.08 | O59: 34023.05 | P59: 122390.55 | Q59: 17511.79 | R59: 30287.45 | S59: 24171.99 | T59: 27455.9 | U59: 99427.13 | V59: 17941.41 | W59: 27967.34 | X59: 30523.99 | Y59: 48456.97 | Z59: 124889.71 | AA59: 30926.96 | AB59: 40392.29
A60: 1 | C60: 판관비 | E60: 16400.67 | G60: 16391.05 | H60: 18276.08 | I60: 20923.16 | J60: 31068.9 | K60: 86659.19 | L60: 24140.22 | M60: 30577.18 | N60: 26679.92 | O60: 30267.68 | P60: 111665 | Q60: 26857.44 | R60: 29376.99 | S60: 29907.45 | T60: 32728.94 | U60: 118870.82 | V60: 29980.27 | W60: 26204.16 | X60: 28150.94 | Y60: 28600.66 | Z60: 112936.03 | AA60: 30333.57 | AB60: 33256.28
A61: 1 | C61: 영업이익 | E61: 4509.41 | G61: 1560.05 | H61: 4148.77 | I61: 1023.77 | J61: 8609.96 | K61: 15342.55 | L61: 776.98 | M61: 7771.04 | N61: -1577.84 | O61: 3755.37 | P61: 10725.55 | Q61: -9345.66 | R61: 910.46 | S61: -5735.46 | T61: -5273.04 | U61: -19443.7 | V61: -12038.86 | W61: 1763.17 | X61: 2373.05 | Y61: 19856.31 | Z61: 11953.67 | AA61: 593.39 | AB61: 7136
A62: 1 | C62: 기타영업외수익 | E62: 1309.62 | G62: 1902.73 | H62: 7265.92 | I62: 9382.05 | J62: -1101.28 | K62: 17449.42 | L62: 5312.55 | M62: 1980.43 | N62: 4096.94 | O62: -1014.51 | P62: 10375.41 | Q62: 5779.11 | R62: 4126.13 | S62: -790.38 | T62: 11374.71 | U62: 20489.57 | V62: 1231.07 | W62: 1656.71 | X62: 1626.83 | Y62: 6622.49 | Z62: 11137.1 | AA62: 10552.91 | AB62: 5035.14
A63: 1 | C63: 기타영업외비용 | E63: 1594.82 | G63: 422.14 | H63: 2231.61 | I63: 1125.96 | J63: 9157.89 | K63: 12937.6 | L63: 3151.27 | M63: 2013.41 | N63: 1470.05 | O63: 4677.52 | P63: 11312.25 | Q63: 829.23 | R63: 1325.74 | S63: 4655.02 | T63: 707.98 | U63: 7517.97 | V63: 2372.84 | W63: 9556.94 | X63: -2020.17 | Y63: 7562.6 | Z63: 17472.21 | AA63: 2426.9 | AB63: 2253.8
A64: 1 | C64: 금융수익 | E64: 553.68 | G64: 396.06 | H64: 108.72 | I64: 197.77 | J64: 2711.48 | K64: 3414.03 | L64: 457.13 | M64: 156.13 | N64: 721.23 | O64: 2736.76 | P64: 4071.25 | Q64: 1929.61 | R64: 1088.3 | S64: 710.35 | T64: 7634.68 | U64: 11362.94 | V64: 1114.69 | W64: 2532.85 | X64: -164.26 | Y64: 4379.92 | Z64: 7863.2 | AA64: 7435.84 | AB64: -736.71
A65: 1 | C65: 금융비용 | E65: 376.64 | G65: 532.79 | H65: 2971.69 | I65: 3663.37 | J65: -702.01 | K65: 6465.84 | L65: 1457.64 | M65: 1609.98 | N65: 1592.7 | O65: 2043.48 | P65: 6703.8 | Q65: 1583.23 | R65: 1837.32 | S65: 1554.6 | T65: 2153.12 | U65: 7128.27 | V65: 2043.54 | W65: 677.08 | X65: 2927.67 | Y65: 1133.22 | Z65: 6781.51 | AA65: 2325.3 | AB65: 2704.57
A66: 1 | C66: 법인세비용차감전계속사업이익 | E66: 4401.25 | G66: 2903.91 | H66: 6320.1 | I66: 5814.27 | J66: 1764.27 | K66: 16802.55 | L66: 1937.74 | M66: 6284.2 | N66: 177.58 | O66: -1243.38 | P66: 7156.14 | Q66: -4049.4 | R66: 2961.83 | S66: -12025.1 | T66: 10875.24 | U66: -2237.43 | V66: -14109.48 | W66: -4281.29 | X66: 2928.11 | Y66: 22162.9 | Z66: 6700.24 | AA66: 13829.93 | AB66: 6476.06
A67: 1 | C67: 법인세비용 | E67: 864.41 | G67: 5.12 | H67: -345.13 | I67: -850.45 | J67: 1963.82 | K67: 773.36 | L67: 931.99 | M67: 605.15 | N67: -342.36 | O67: 428.93 | P67: 1623.71 | Q67: 822.13 | R67: 306.66 | S67: 93.37 | T67: -448.02 | U67: 774.14 | V67: 22.61 | W67: -213.48 | X67: -430.69 | Y67: -142.13 | Z67: -763.69 | AA67: 358.01 | AB67: 1730.58
A68: 1 | C68: 당기순이익 | E68: 3536.84 | G68: 2898.8 | H68: 6665.24 | I68: 6664.72 | J68: -199.55 | K68: 16029.21 | L68: 1005.74 | M68: 5679.05 | N68: 519.94 | O68: -1672.31 | P68: 5532.42 | Q68: -4871.53 | R68: 2655.17 | S68: -12118.47 | T68: 11323.25 | U68: -3011.58 | V68: -14132.1 | W68: -4067.81 | X68: 3358.8 | Y68: 22305.03 | Z68: 7463.92 | AA68: 13471.92 | AB68: 4745.48
... A73: 1 | C73: 계속사업이익 | E73: 3536.84 | G73: 2898.8 | H73: 6665.24 | I73: 6664.72 | J73: -199.55 | K73: 16029.21 | L73: 1005.74 | M73: 5679.05 | N73: 519.94 | O73: -1672.31 | P73: 5532.42 | Q73: -4871.53 | R73: 2655.17 | S73: -12118.47 | T73: 11323.25 | U73: -3011.58 | V73: -14132.1 | W73: -4067.81 | X73: 3358.8 | Y73: 22305.03 | Z73: 7463.92 | AA73: 13471.92 | AB73: 4745.48
A74: 1 | C74: 이자수익 | G74: 226.85 | H74: 162.08 | I74: 236.84 | J74: 239.11 | K74: 864.88 | L74: 250.21 | M74: 88.04 | N74: 876.57 | O74: 1125.53 | P74: 2340.35 | Q74: 1219.52 | R74: 1043.72 | S74: 784.06 | T74: 481.38 | U74: 3528.68 | V74: 395.36 | W74: 185.36 | X74: 287.02 | Y74: 322.2 | Z74: 1189.94 | AB74: 257.97
A75: 1 | C75: 이자비용 | G75: 298.98 | H75: 406.42 | I75: 178.95 | J75: 673.16 | K75: 1557.51 | L75: 1230.34 | M75: 1605.27 | N75: 1518.14 | O75: 1512.8 | P75: 5866.55 | Q75: 1475.48 | R75: 1466.12 | S75: 1451.62 | T75: 1447.17 | U75: 5840.39 | V75: 1314.93 | W75: 1254.3 | X75: 1397.96 | Y75: 1523.25 | Z75: 5490.44 | AB75: 1742.09
A76: 1 | C76: 파생상품손실 | G76: 215.42 | H76: 1967.65 | I76: 2816.48 | J76: -1857.71 | K76: 3141.84 | L76: 11.72 | M76: 0 | N76: 0 | O76: 0 | P76: 11.72
A77: 1 | C77: 이자손익 | G77: -72.13 | H77: -244.34 | I77: 57.89 | J77: -434.05 | K77: -692.63 | L77: -980.13 | M77: -1517.23 | N77: -641.57 | O77: -387.27 | P77: -3526.2 | Q77: -255.96 | R77: -422.4 | S77: -667.56 | T77: -965.79 | U77: -2311.71 | V77: -919.57 | W77: -1068.94 | X77: -1110.94 | Y77: -1201.05 | Z77: -4300.5 | AB77: -1484.12
A78: 1 | C78: 배당금수익 | I78: 0 | J78: 0 | V78: 382.52 | W78: 133.05 | X78: 88.79 | Y78: -212.64 | Z78: 391.72 | AB78: 82.54
A79: 1 | C79: (비지배주주지분)당기순이익 | AB79: 0
A80: 1 | C80: 영업활동으로인한현금흐름 | E80: 572.6 | G80: -10250.78 | H80: -303.94 | I80: 1158.22 | J80: -16685.78 | K80: -26082.28 | L80: -15921.34 | M80: 7069.53 | N80: 18612.77 | O80: 20057.32 | P80: 29818.28 | Q80: 17964.21 | R80: -2223.68 | S80: -17695.02 | T80: 5911.45 | U80: 3956.96 | V80: 11807.24 | W80: -33423.21 | X80: -7706.54 | Y80: 11083.29 | Z80: -18239.22 | AA80: 17078.09 | AB80: -4214.92
A81: 1 | C81: 이자수취(CF) | E81: 60.86 | G81: 277.57 | H81: 260.07 | I81: 177.87 | J81: 168.76 | K81: 884.27 | L81: 232.8 | M81: 125.83 | N81: 399.25 | O81: 1046.42 | P81: 1804.3 | Q81: 1110.31 | R81: 1106.02 | S81: 1139.32 | T81: 484.46 | U81: 3840.11 | V81: 242.33 | W81: 349.7 | X81: 298.93 | Y81: 338.41 | Z81: 1229.37 | AA81: 294.16 | AB81: 204.1
A82: 1 | C82: 이자지급(CF) | E82: -219.24 | G82: -241.35 | H82: -376.13 | I82: -486.56 | J82: -673.73 | K82: -1777.77 | L82: -1061.27 | M82: -1285.17 | X82: -1253.32 | Y82: -1379.7 | AA82: -1318.4 | AB82: -1424.13
A83: 1 | C83: 배당금수취(CF) | E83: 0 | I83: 0 | J83: 19.58 | L83: 9.79 | T83: 0
A84: 1 | C84: 법인세납부(CF) | E84: -516.3 | G84: -100.78 | H84: -209.65 | I84: -20.22 | J84: -185.44 | K84: -516.09 | L84: -273.41 | M84: -1476.65 | N84: -54.65 | O84: -645.94 | P84: -2450.65 | Q84: -886.81 | R84: -126.38 | S84: -257.21 | T84: 294.56 | U84: -975.84 | V84: -637.63 | W84: 941.97 | X84: -244.62 | Y84: -131.8 | Z84: -72.08 | AA84: -1126 | AB84: -2045.49
A85: 1 | C85: 투자활동으로인한현금흐름 | E85: -2905.39 | G85: -7074.62 | H85: -539.5 | I85: -14168.85 | J85: -5794.54 | K85: -27577.51 | L85: -1735.47 | M85: -17467.06 | N85: -61014.02 | O85: -7337.33 | P85: -87553.88 | Q85: -29623.27 | R85: -12644.71 | S85: 19558.09 | T85: -3825 | U85: -26534.89 | V85: -6387.86 | W85: 10860.28 | X85: -574.42 | Y85: 12248.11 | Z85: 16146.11 | AA85: -14000.62 | AB85: -10221.89
A86: 1 | C86: 유형자산의감소 | E86: -0.71 | G86: 27 | H86: 0 | I86: 69.03 | J86: 0 | K86: 96.03 | L86: 17.87 | N86: 0 | O86: 32.24 | Q86: 1117.11 | R86: 71.64 | S86: 2 | V86: 0.63 | W86: 0 | X86: 0 | Y86: 4806.35 | Z86: 4806.98 | AA86: 0.17 | AB86: 0
A87: 1 | C87: 유형자산의증가 | E87: 6461.63 | G87: 7784.68 | H87: 6647.6 | I87: 11955.85 | J87: 11270.49 | K87: 37658.62 | L87: 6854.3 | M87: 4092.89 | N87: 2945.81 | O87: 2736.43 | P87: 16629.43 | Q87: 5371.59 | R87: 1350.59 | S87: 2152.55 | T87: 1179.42 | U87: 10054.15 | V87: 780.35 | W87: 1037.95 | X87: 9521.31 | Y87: 1197.69 | Z87: 12537.3 | AA87: 9342.39 | AB87: 7886.98
A88: 1 | C88: CAPEX | E88: 7415.08 | G88: 8878.35 | H88: 8345.82 | I88: 13690.39 | J88: 13606.32 | K88: 44520.88 | L88: 8314.23 | M88: 5944.58 | N88: 7201.86 | O88: 8864.24 | P88: 30324.91 | Q88: 11888.35 | R88: 8806.14 | S88: 5558.7 | T88: 3671.45 | U88: 29924.64 | V88: 2626.09 | W88: 6172.2 | X88: 14395.99 | Y88: 8405.51 | Z88: 31599.79 | AA88: 12964.28 | AB88: 10137.19
A89: 1 | C89: 무형자산의증가 | E89: 953.45 | G89: 1093.67 | H89: 1698.22 | I89: 1734.54 | J89: 2335.83 | K89: 6862.26 | L89: 1459.93 | M89: 1851.69 | N89: 4256.05 | O89: 6127.81 | P89: 13695.48 | Q89: 6516.76 | R89: 7455.55 | S89: 3406.15 | T89: 2492.03 | U89: 19870.49 | V89: 1845.74 | W89: 5134.25 | X89: 4874.68 | Y89: 7207.82 | Z89: 19062.49 | AA89: 3621.89 | AB89: 2250.21
A90: 1 | C90: 재무활동으로인한현금흐름 | E90: 4861.65 | G90: 14727.4 | H90: -308.41 | I90: 20160.95 | J90: 21273.46 | K90: 55853.4 | L90: 11149.11 | M90: 19205.63 | N90: 62888.84 | O90: -4269.59 | P90: 88973.99 | Q90: -4887.78 | R90: 5243.04 | S90: -5169.97 | T90: -8646.8 | U90: -13461.51 | V90: -3440.56 | W90: 16064.18 | X90: 14746.44 | Y90: -14297.97 | Z90: 13072.09 | AA90: -4867.03 | AB90: 7456.99
A91: 1 | C91: 단기차입금의증가 | E91: 19500.28 | G91: 19300 | H91: 39337.34 | I91: 13607.98 | J91: 32151.63 | K91: 104396.95 | L91: 47748 | M91: 36771.39 | N91: 38966.42 | O91: 0 | P91: 123485.81 | S91: 45002.67 | T91: 17000 | V91: 261.95 | W91: 24500 | X91: 0 | Y91: 43288.21 | Z91: 68050.16 | AA91: 0 | AB91: 18299.9
A92: 1 | C92: 단기차입금의감소 | E92: 14400.28 | G92: 10143.47 | H92: 36406.57 | I92: 0 | J92: 12905.26 | K92: 59455.3 | L92: 45704.37 | M92: 23638.07 | N92: 64500 | O92: 2981.26 | P92: 136823.7 | Q92: 500 | R92: 540.06 | S92: 47002.47 | T92: 24700 | U92: 72742.53 | V92: 261.95 | W92: 2500 | X92: 7416 | Y92: 44204.21 | Z92: 54382.16 | AA92: 416 | AB92: 6715.9
A93: 1 | C93: 리스부채의상환 | E93: 486.55 | G93: 547.58 | H93: 634.99 | I93: 692.52 | J93: 866.27 | K93: 2741.36 | L93: 811.03 | M93: 842.89 | N93: 857.5 | O93: 863.65 | P93: 3375.07 | Q93: 1091.86 | R93: 1228.2 | S93: 1219.79 | T93: 1333.44 | U93: 4873.29 | V93: 1320.22 | W93: 1290.28 | X93: 1280.38 | Y93: 1320.97 | Z93: 5211.85 | AA93: 1823.8 | AB93: 1642.69
A94: 1 | C94: 유동성장기부채의감소 | E94: 95 | G94: 95 | H94: 6319.1 | I94: 300.92 | J94: 4095 | K94: 10810.02 | L94: 309.44 | M94: 309.28 | N94: 394.38 | O94: 3519.26 | P94: 4532.36 | Q94: 4029.75 | R94: 5506.28 | S94: 1193.71 | T94: 1041.1 | U94: 11770.84 | V94: 1035.89 | W94: 3528.32 | X94: 3699.34 | Y94: 3635.61 | Z94: 11899.16 | AA94: 3472.47 | AB94: 960.57
A95: 1 | C95: 장기차입금의증가 | E95: 0 | G95: 6000 | H95: 4000 | I95: 7500 | J95: 7000 | K95: 24500 | L95: 10000 | M95: 8000 | N95: 0 | O95: 3000 | P95: 21000 | Q95: 3500 | R95: 5000 | S95: 0 | T95: 2200 | U95: 10700 | Y95: 0
A96: 1 | C96: 배당금지급 | E96: 0 | I96: 0 | J96: 0 | N96: 0 | O96: 0 | S96: 0 | T96: 0 | X96: 0 | Y96: 0
A97: 1 | C97: 현금및현금성자산의증감 | E97: 2528.86 | G97: -2598 | H97: -1151.85 | I97: 7150.31 | J97: -1206.84 | K97: 2193.62 | L97: -6507.7 | M97: 8808.1 | N97: 20487.59 | O97: 8450.41 | P97: 31238.4 | Q97: -16546.84 | R97: -9625.35 | S97: -3306.9 | T97: -6560.34 | U97: -36039.43 | V97: 1978.82 | W97: -6498.75 | X97: 6465.48 | Y97: 9033.42 | Z97: 10978.97 | AA97: -1789.57 | AB97: -6979.81
A98: 1 | C98: 기말현금및현금성자산 | E98: 2428.42 | G98: 20133.03 | H98: -871.03 | I98: 7644.15 | J98: -2491.58 | K98: 24414.57 | L98: 17940.93 | M98: 8898.04 | N98: 21021.81 | O98: 8087.96 | P98: 55948.74 | Q98: 39907.26 | R98: -9236.35 | S98: -4192.04 | T98: -4992.2 | U98: 21486.67 | V98: 24147.18 | W98: -6931.21 | X98: 6303.43 | Y98: 9326.45 | Z98: 32845.85 | AA98: 31798.82 | AB98: -6699.45
A99: 1 | C99: 자기주식의취득 | J99: 352.39 | X99: 0 | Y99: 4996.88 | AA99: 0 | AB99: 0
A100: 1 | C100: 사채의증가 | Y100: 0

Sheet BS별도
B1: (백만원) | C1: 이름: BS별도H | E1: 4Q21 | F1: 2021 | G1: 1Q22 | H1: 2Q22 | I1: 3Q22 | J1: 4Q22 | K1: 2022 | L1: 1Q23 | M1: 2Q23 | N1: 3Q23 | O1: 4Q23 | P1: 2023 | Q1: 1Q24 | R1: 2Q24 | S1: 3Q24 | T1: 4Q24 | U1: 2024 | V1: 1Q25 | W1: 2Q25 | X1: 3Q25 | Y1: 4Q25 | Z1: 2025 | AA1: 1Q26 | AB1: 2Q26 | AC1: 3Q26 | AD1: 4Q26 | AE1: 2026 | AF1: 1Q27 | AG1: 2Q27 | AH1: 3Q27 | AI1: 4Q27 | AJ1: 2027 | AK1: 1Q28 | AL1: 2Q28 | AM1: 3Q28 | AN1: 4Q28 | AO1: 2028
B2: 별도 | D2: fin json(kship_fin.py)
B3: 인텔리안테크(별) | C3: UPDATE: 26-10-11 | E3: 1 | F3: 2 | G3: 3 | H3: 4 | I3: 5 | J3: 6 | K3: 7 | L3: 8 | M3: 9 | N3: 10 | O3: 11 | P3: 12 | Q3: 13 | R3: 14 | S3: 15 | T3: 16 | U3: 17 | V3: 18 | W3: 19 | X3: 20 | Y3: 21 | Z3: 22 | AA3: 23 | AB3: 24 | AC3: 25 | AD3: 26 | AE3: 27 | AF3: 28 | AG3: 29 | AH3: 30 | AI3: 31 | AJ3: 32 | AK3: 33 | AL3: 34 | AM3: 35 | AN3: 36 | AO3: 37
B4: Account Code | C4: AccountNAME | E4: 2021.12 | F4: 2021.12A | G4: 2022.03 | H4: 2022.06 | I4: 2022.09 | J4: 2022.12 | K4: 2022.12A | L4: 2023.03 | M4: 2023.06 | N4: 2023.09 | O4: 2023.12 | P4: 2023.12A | Q4: 2024.03 | R4: 2024.06 | S4: 2024.09 | T4: 2024.12 | U4: 2024.12A | V4: 2025.03 | W4: 2025.06 | X4: 2025.09 | Y4: 2025.12 | Z4: 2025.12A | AA4: 2026.03 | AB4: 2026.06 | AC4: 2026.09 | AD4: 2026.12 | AE4: 2026.12A | AF4: 2027.03 | AG4: 2027.06 | AH4: 2027.09 | AI4: 2027.12 | AJ4: 2027.12A | AK4: 2028.03 | AL4: 2028.06 | AM4: 2028.09 | AN4: 2028.12 | AO4: 2028.12A
A5: 1 | C5: 유동자산 | E5: 150245.59 | F5: 150245.59 | G5: 161544.35 | H5: 166391.98 | I5: 189426.26 | J5: 213759.26 | K5: 213759.26 | L5: 209663.09 | M5: 212953.11 | N5: 284836.15 | O5: 282081.26 | P5: 282081.26 | Q5: 260391.19 | R5: 285531.4 | S5: 254468.96 | T5: 221626.85 | U5: 221626.85 | V5: 221161.82 | W5: 239697.61 | X5: 268514.69 | Y5: 280363.82 | Z5: 280363.82 | AA5: 265961.92 | AB5: 299508.88
A6: 1 | C6: 현금및현금성자산 | E6: 15272.86 | F6: 15272.86 | G6: 10716.67 | H6: 11220.52 | I6: 18082.28 | J6: 14470.34 | K6: 14470.34 | L6: 7943.73 | M6: 14470.35 | N6: 30099.79 | O6: 44532.01 | P6: 44532.01 | Q6: 21302.45 | R6: 17584.38 | S6: 12596.01 | T6: 9814.01 | U6: 9814.01 | V6: 9959.15 | W6: 5333.45 | X6: 9780.07 | Y6: 20151.37 | Z6: 20151.37 | AA6: 10562.46 | AB6: 14978.31
A7: 1 | C7: 단기금융상품 | E7: 35344.38 | F7: 35344.38 | G7: 31965.52 | H7: 19001.27 | I7: 18704.43 | J7: 5896.06 | K7: 5896.06 | M7: 10834.26 | N7: 65030.04 | O7: 66353.66 | P7: 66353.66 | Q7: 78172.43 | R7: 75138.84 | S7: 42642.71 | T7: 37682.92 | U7: 37682.92 | V7: 42166.67 | W7: 15049.2 | X7: 7558.8 | Y7: 500 | Z7: 500 | AA7: 0 | AB7: 0
A8: 1 | C8: 단기금융자산 | E8: 35346.69 | F8: 35346.69 | G8: 31965.52 | H8: 19001.27 | I8: 18704.43 | J8: 5896.06 | K8: 5896.06 | M8: 10834.26 | N8: 65030.04 | O8: 66353.66 | P8: 66353.66 | Q8: 78172.43 | R8: 75138.84 | S8: 42642.71 | T8: 37682.92 | U8: 37682.92 | V8: 42166.67 | W8: 15049.2 | X8: 7558.8 | Y8: 500 | Z8: 500 | AA8: 0 | AB8: 0
A9: 1 | C9: 매출채권및기타채권 | E9: 58629.42 | F9: 58629.42 | G9: 67543.39 | H9: 67396.85 | I9: 72297.52 | J9: 96690.69 | K9: 96690.69 | L9: 94392.19 | M9: 92223.7 | N9: 102397.4 | O9: 99788.66 | P9: 99788.66 | Q9: 83787.33 | R9: 103559.32 | S9: 99077.8 | T9: 95504.7 | U9: 95504.7 | V9: 82785.76 | W9: 121787.93 | X9: 147368.75 | Y9: 174031.03 | Z9: 174031.03 | AA9: 148460.54 | AB9: 163858.65
A10: 1 | C10: 계약자산 | E10: 77.05 | F10: 77.05 | G10: 116 | H10: 255.99 | I10: 63.42 | J10: 53.4 | K10: 53.4 | L10: 53.4 | Q10: 852.66 | R10: 512.5 | S10: 1274.68
A11: 1 | C11: 유동파생상품자산 | E11: 2.31 | F11: 2.31
A12: 1 | C12: 기타유동자산 | E12: 5359.41 | F12: 5359.41 | G12: 6282.55 | H12: 9133.24 | I12: 9118.48 | J12: 9646.44 | K12: 9646.44 | L12: 8872.05 | M12: 9023.4 | N12: 6006.97 | O12: 5991.66 | P12: 5991.66 | Q12: 7143.94 | R12: 8704.4 | S12: 9430.28 | T12: 4155.7 | U12: 4155.7 | V12: 4441.33 | W12: 6691.89 | X12: 4350.94 | Y12: 5081.45 | Z12: 5081.45 | AA12: 5040.88 | AB12: 6782.69
A13: 1 | C13: 재고자산 | E13: 35477.19 | F13: 35477.19 | G13: 44839.1 | H13: 59313.54 | I13: 70342.94 | J13: 86864.33 | K13: 86864.33 | L13: 98229.64 | M13: 86010.53 | N13: 80897.29 | O13: 65039.12 | P13: 65039.12 | Q13: 68092.39 | R13: 79029.13 | S13: 88391.27 | T13: 72645.21 | U13: 72645.21 | V13: 80629.35 | W13: 89556.98 | X13: 98201.03 | Y13: 80279.35 | Z13: 80279.35 | AA13: 101633.07 | AB13: 113594.78
A14: 1 | C14: 비유동자산 | E14: 90035.22 | F14: 90035.22 | G14: 101409.96 | H14: 110966.4 | I14: 122547.94 | J14: 136519.24 | K14: 136519.24 | L14: 143995.92 | M14: 143785.4 | N14: 141514.41 | O14: 141281.09 | P14: 141281.09 | Q14: 152728.02 | R14: 164781.78 | S14: 171632.46 | T14: 187019.75 | U14: 187019.75 | V14: 181252.8 | W14: 196044.62 | X14: 194297.69 | Y14: 195975.13 | Z14: 195975.13 | AA14: 206407.32 | AB14: 208009.67
A15: 1 | C15: 종속기업및관계기업투자 | E15: 644.96 | F15: 644.96 | G15: 4071.89 | H15: 3691.01 | I15: 7213.38 | J15: 1750.75 | K15: 1750.75 | L15: 7898.08 | M15: 8034.04 | N15: 7371.56 | O15: 4607.85 | P15: 4607.85 | Q15: 3576.9 | R15: 2954.02 | S15: 2483.63 | T15: 9635.4 | U15: 9635.4 | V15: 5396.83 | W15: 6438.41 | X15: 3506.26 | Y15: 9383.83 | Z15: 9383.83 | AA15: 9678.59 | AB15: 14138.94
A16: 1 | C16: 투자자산 | E16: 9737.12 | F16: 9737.12 | G16: 14697.46 | H16: 18553.06 | I16: 21496.86 | J16: 20205.17 | K16: 20205.17 | L16: 25156.83 | M16: 25465.8 | N16: 24324.82 | O16: 19722.81 | P16: 19722.81 | Q16: 26238.72 | R16: 32246.57 | S16: 39068.98 | T16: 58375.57 | U16: 58375.57 | V16: 54025.45 | W16: 66583.97 | X16: 54818.48 | Y16: 57136.65 | Z16: 57136.65 | AA16: 65865.55 | AB16: 66880.84
A17: 1 | C17: 장기금융자산 | E17: 9092.16 | F17: 9092.16 | G17: 10625.57 | H17: 14862.05 | I17: 14283.48 | J17: 18454.42 | K17: 18454.42 | L17: 17258.75 | M17: 17431.76 | N17: 16953.26 | O17: 15114.96 | P17: 15114.96 | Q17: 22661.82 | R17: 29292.55 | S17: 36585.35 | T17: 48740.17 | U17: 48740.17 | V17: 48628.62 | W17: 60145.56 | X17: 51312.22 | Y17: 47752.82 | Z17: 47752.82 | AA17: 56186.96 | AB17: 52741.9
A18: 1 | C18: 장기매출채권및기타채권 | E18: 2813.44 | F18: 2813.44 | G18: 2589.47 | H18: 2406.76 | I18: 757.67 | J18: 697.89 | K18: 697.89 | L18: 338.27 | M18: 453.92 | N18: 503.23 | O18: 513.93 | P18: 513.93 | Q18: 746.04 | R18: 862.96 | S18: 938.56 | T18: 745.25 | U18: 745.25 | V18: 809.92 | W18: 824.28 | X18: 1142.59 | Y18: 1016.48 | Z18: 1016.48 | AA18: 999.86 | AB18: 1010.97
A19: 1 | C19: 유형자산 | E19: 50821.23 | F19: 50821.23 | G19: 57055.71 | H19: 62750.31 | I19: 72327.9 | J19: 84490.36 | K19: 84490.36 | L19: 84950.66 | M19: 85083.37 | N19: 83468.46 | O19: 83086.51 | P19: 83086.51 | Q19: 83654.86 | R19: 82816.54 | S19: 81590.77 | T19: 80123.4 | U19: 80123.4 | V19: 78672.11 | W19: 77672.06 | X19: 84669.34 | Y19: 80859.6 | Z19: 80859.6 | AA19: 81601.12 | AB19: 72784.95
A20: 1 | C20: 무형자산 | E20: 16999.84 | F20: 16999.84 | G20: 16820.25 | H20: 17377.53 | I20: 18018.77 | J20: 19140.5 | K20: 19140.5 | L20: 19530.63 | M20: 18567.78 | N20: 21660.58 | O20: 26302.72 | P20: 26302.72 | Q20: 31859.11 | R20: 38042.85 | S20: 39256.03 | T20: 37603.34 | U20: 37603.34 | V20: 37445.23 | W20: 40650.73 | X20: 43286.79 | Y20: 43752.24 | Z20: 43752.24 | AA20: 44979.52 | AB20: 43558.83
A21: 1 | C21: 기타비유동자산 | E21: 782.99 | F21: 782.99 | G21: 844.85 | H21: 925.95 | I21: 215.91 | J21: 1322.55 | K21: 1322.55 | L21: 1378.89 | M21: 1376.53 | N21: 1390.5 | O21: 1434.53 | P21: 1434.53 | Q21: 809.41 | R21: 870.65 | S21: 835.91 | T21: 77.17 | U21: 77.17 | V21: 205.05 | W21: 210.11 | X21: 277.02 | Y21: 1410.4 | Z21: 1410.4 | AA21: 1161.53 | AB21: 4196.51
A22: 1 | C22: 이연법인세자산 | E22: 8470.06 | F22: 8470.06 | G22: 8470.06 | H22: 8798.37 | I22: 8798.37 | J22: 9186.08 | K22: 9186.08 | L22: 9186.08 | M22: 9105.77 | N22: 9105.77 | O22: 9419.88 | P22: 9419.88 | Q22: 9419.88 | R22: 9942.21 | S22: 9942.21 | T22: 10095.04 | U22: 10095.04 | V22: 10095.04 | W22: 10103.47 | X22: 10103.47 | Y22: 11799.74 | Z22: 11799.74 | AA22: 11799.74 | AB22: 11799.74
A23: 1 | C23: 자산총계 | E23: 240280.81 | F23: 240280.81 | G23: 262954.31 | H23: 277358.39 | I23: 311974.2 | J23: 350278.5 | K23: 350278.5 | L23: 353659.01 | M23: 356738.51 | N23: 426350.56 | O23: 423362.35 | P23: 423362.35 | Q23: 413119.2 | R23: 450313.18 | S23: 426101.42 | T23: 408646.6 | U23: 408646.6 | V23: 402414.62 | W23: 435742.23 | X23: 462812.38 | Y23: 476338.95 | Z23: 476338.95 | AA23: 472369.24 | AB23: 507518.55
... A41: 1 | C41: 이익잉여금 | E41: 39151.77 | F41: 39151.77 | G41: 39307.42 | H41: 45687.72 | I41: 49995.47 | J41: 51728.33 | K41: 51728.33 | L41: 50275.17 | M41: 55670.62 | N41: 53722.53 | O41: 54651.74 | P41: 54651.74 | Q41: 52479.02 | R41: 50075.91 | S41: 41122.44 | T41: 48714.55 | U41: 48714.55 | V41: 36657.83 | W41: 29022.13 | X41: 35890.85 | Y41: 57069.34 | Z41: 57069.34 | AA41: 68859.16 | AB41: 70973.15
A42: 1 | C42: 자본총계 | E42: 160801.77 | F42: 160801.77 | G42: 161884.44 | H42: 169290.85 | I42: 175442.39 | J42: 174774.87 | K42: 174774.87 | L42: 174858.81 | M42: 180860.57 | N42: 269276.22 | O42: 270184.59 | P42: 270184.59 | Q42: 266173.42 | R42: 263260.34 | S42: 252839.06 | T42: 260456.55 | U42: 260456.55 | V42: 246944.26 | W42: 237568.37 | X42: 245996.6 | Y42: 262061.29 | Z42: 262061.29 | AA42: 276018.61
A43: 1 | C43: 부채와자본총계 | E43: 240280.81 | F43: 240280.81 | G43: 262954.31 | H43: 277358.39 | I43: 311974.2 | J43: 350278.5 | K43: 350278.5 | L43: 353659.01 | M43: 356738.51 | N43: 426350.56 | O43: 423362.35 | P43: 423362.35 | Q43: 413119.2 | R43: 450313.18 | S43: 426101.42 | T43: 408646.6 | U43: 408646.6 | V43: 402414.62 | W43: 435742.23 | X43: 462812.38 | Y43: 476338.95 | Z43: 476338.95 | AA43: 472369.24 | AB43: 507518.55
A44: 1 | C44: 지배주주지분 | E44: 160801.77 | F44: 160801.77 | G44: 161884.44 | H44: 169290.85 | I44: 175442.39 | J44: 174774.87 | K44: 174774.87 | L44: 174858.81 | M44: 180860.57 | N44: 269276.22 | O44: 270184.59 | P44: 270184.59 | Q44: 266173.42 | R44: 263260.34 | S44: 252839.06 | T44: 260456.55 | U44: 260456.55 | V44: 246944.26 | W44: 237568.37 | X44: 245996.6 | Y44: 262061.29 | Z44: 262061.29 | AA44: 276018.61
A45: 1 | C45: 총차입금 | E45: 34720 | F45: 34720 | G45: 50625 | H45: 52760 | I45: 72435 | J45: 95763.05 | K45: 95763.05 | L45: 107678.49 | M45: 128321.28 | N45: 100640.57 | O45: 99331.29 | P45: 99331.29 | Q45: 98522.01 | R45: 107212.53 | S45: 104274.88 | T45: 97965.6 | U45: 97965.6 | V45: 97156.32 | W45: 115847.04 | X45: 131121.76 | Y45: 126226.48 | Z45: 126226.48 | AA45: 122596.2 | AB45: 133465.92
A46: 1 | C46: 순차입금 | E46: -15899.55 | F46: -15899.55 | G46: 7942.81 | H46: 22538.21 | I46: 35648.29 | J46: 75396.65 | K46: 75396.65 | L46: 99734.76 | M46: 103016.67 | N46: 5510.74 | O46: -11554.38 | P46: -11554.38 | Q46: -952.87 | R46: 14489.31 | S46: 49036.16 | T46: 50468.67 | U46: 50468.67 | V46: 45030.5 | W46: 95464.39 | X46: 113782.89 | Y46: 105575.11 | Z46: 105575.11 | AA46: 112033.74 | AB46: 118487.61
A47: 1 | C47: 이자발생자산 | E47: 59711.71 | F47: 59711.71 | G47: 53307.76 | H47: 45083.84 | I47: 51070.19 | J47: 38820.82 | K47: 38820.82 | L47: 25202.48 | M47: 42736.37 | N47: 112083.09 | O47: 126000.63 | P47: 126000.63 | Q47: 122136.7 | R47: 122015.77 | S47: 91824.07 | T47: 96237.1 | U47: 96237.1 | V47: 100754.44 | W47: 80528.21 | X47: 68651.09 | Y47: 68404.19 | Z47: 68404.19 | AA47: 66749.42 | AB47: 67720.21
A48: 1 | C48: 단기파생상품부채 | G48: 199.85 | H48: 2126.26 | I48: 4487.19 | J48: 746.68 | K48: 746.68
A49: 1 | C49: 단기금융부채 | G49: 199.85 | H49: 2126.26 | I49: 4487.19 | J49: 746.68 | K49: 746.68
A50: 1 | C50: 단기금융부채(face) | N50: 45200 | O50: 44200 | P50: 44200 | Q50: 43700 | R50: 52699.8 | S50: 50700 | T50: 43000 | U50: 43000 | V50: 43000
A51: 1 | C51: 장기금융부채(face) | S51: 50337.76 | T51: 51758.48 | U51: 51758.48 | V51: 40979.2
A52: 1 | C52: 당기법인세자산(선급법인세) | W52: 95.23 | X52: 130.91 | Y52: 0 | Z52: 0 | AA52: 25.58
A53: 1 | C53: 당기법인세부채(미지급법인세) | Y53: 1524.42 | Z53: 1524.42 | AA53: 1071.81 | AB53: 1578.9
A54: 1 | C54: 사채 | Y54: 20000 | Z54: 20000 | AA54: 20000 | AB54: 20000
A55: 1 | C55: 투자부동산 | AB55: 7777.84
A56: 1 | C56: 매출액(수익) | E56: 37973.82 | G56: 33141.38 | H56: 49450.78 | I56: 49183.97 | J56: 83818.2 | K56: 215594.33 | L56: 46976.74 | M56: 74811.04 | N56: 61103.01 | O56: 81708.21 | P56: 264599 | Q56: 38646.54 | R56: 57830.18 | S56: 58652.2 | T56: 57547.24 | U56: 212676.16 | V56: 37869.34 | W56: 65481.74 | X56: 78414.36 | Y56: 106044.48 | Z56: 287809.92 | AA56: 55718.72 | AB56: 80065.64
A57: 1 | C57: 매출원가 | E57: 25088.94 | G57: 24820.05 | H57: 32964.67 | I57: 36290.44 | J57: 47170.35 | K57: 141245.51 | L57: 39148.08 | M57: 47449.35 | N57: 43169.84 | O57: 50830.93 | P57: 180598.2 | Q57: 27498.2 | R57: 41377.63 | S57: 39931.54 | T57: 45288.86 | U57: 154096.23 | V57: 25957.65 | W57: 52657.16 | X57: 50662.63 | Y57: 71582.92 | Z57: 200860.36 | AA57: 33714 | AB57: 57762.25
A58: 1 | C58: 매출총이익 | E58: 12884.87 | G58: 8321.33 | H58: 16486.11 | I58: 12893.53 | J58: 36647.84 | K58: 74348.81 | L58: 7828.66 | M58: 27361.69 | N58: 17933.17 | O58: 30877.28 | P58: 84000.8 | Q58: 11148.34 | R58: 16452.55 | S58: 18720.66 | T58: 12258.38 | U58: 58579.93 | V58: 11911.69 | W58: 12824.57 | X58: 27751.73 | Y58: 34461.56 | Z58: 86949.55 | AA58: 22004.71 | AB58: 22303.39
A59: 1 | C59: 판관비 | E59: 10768.77 | G59: 10014.95 | H59: 11138.48 | I59: 14379.45 | J59: 26172.22 | K59: 61705.1 | L59: 14650.18 | M59: 21538.57 | N59: 20146.86 | O59: 23670.22 | P59: 80005.83 | Q59: 15698.57 | R59: 18987.72 | S59: 21654.11 | T59: 27072.64 | U59: 83413.04 | V59: 17060.23 | W59: 17997.17 | X59: 17113.99 | Y59: 25070.29 | Z59: 77241.68 | AA59: 19330.8 | AB59: 22887.59
A60: 1 | C60: 영업이익 | E60: 2116.1 | G60: -1693.63 | H60: 5347.63 | I60: -1485.92 | J60: 10475.63 | K60: 12643.71 | L60: -6821.52 | M60: 5823.12 | N60: -2213.69 | O60: 7207.07 | P60: 3994.98 | Q60: -4550.23 | R60: -2535.17 | S60: -2933.44 | T60: -14814.26 | U60: -24833.1 | V60: -5148.54 | W60: -5172.6 | X60: 10637.74 | Y60: 9391.27 | Z60: 9707.87 | AA60: 2673.91 | AB60: -584.2
A61: 1 | C61: 기타영업외수익 | E61: 522.66 | G61: 3333.9 | H61: 5418.12 | I61: 9894.65 | J61: -3435.61 | K61: 15211.06 | L61: 9551.8 | M61: 1731.31 | N61: 2965.23 | O61: -1689.86 | P61: 12558.48 | Q61: 5892.88 | R61: 4242.15 | S61: -946.04 | T61: 12241.34 | U61: 21430.33 | V61: 1785.04 | W61: 1046.4 | X61: 1489.57 | Y61: 6181.51 | Z61: 10502.52 | AA61: 9823.94 | AB61: 4505.13
A62: 1 | C62: 기타영업외비용 | E62: 1108.23 | G62: 530.6 | H62: 2035.93 | I62: 708.48 | J62: 9402.04 | K62: 12677.05 | L62: 2452.82 | M62: 1692.71 | N62: 2068.04 | O62: 6062.59 | P62: 12276.16 | Q62: 3031.99 | R62: 2523.74 | S62: 4436.71 | T62: -3592.21 | U62: 6400.23 | V62: 6921.71 | W62: 8069.08 | X62: -2080.92 | Y62: 6987.84 | Z62: 19897.71 | AA62: 2123.42 | AB62: 1671.67
A63: 1 | C63: 금융수익 | E63: 1223.98 | G63: 392 | H63: 428.68 | I63: 195.75 | J63: 3165.31 | K63: 4181.74 | L63: 451.17 | M63: 681.01 | N63: 687.99 | O63: 3515.74 | P63: 5335.91 | Q63: 1862.26 | R63: 1730.36 | S63: 667.49 | T63: 8673.26 | U63: 12933.37 | V63: 1053.74 | W63: 3090.84 | X63: -332.24 | Y63: 5589.04 | Z63: 9401.38 | AA63: 7274.92 | AB63: 117.99
A64: 1 | C64: 금융비용 | E64: 299.14 | G64: 453.72 | H64: 2892.55 | I64: 3588.26 | J64: -886.73 | K64: 6047.8 | L64: 1287.27 | M64: 1354.16 | N64: 1319.59 | O64: 1774.69 | P64: 5735.71 | Q64: 1294.48 | R64: 1535.1 | S64: 1304.77 | T64: 1869.65 | U64: 6004 | V64: 1787.15 | W64: 444.03 | X64: 2693.35 | Y64: 912.74 | Z64: 5837.27 | AA64: 1942.3 | AB64: 2316.5
A65: 1 | C65: 법인세비용차감전계속사업이익 | E65: 2455.36 | G65: 1047.94 | H65: 6265.95 | I65: 4307.75 | J65: 1690.03 | K65: 13311.67 | L65: -558.64 | M65: 5188.58 | N65: -1948.1 | O65: 1195.67 | P65: 3877.51 | Q65: -1121.56 | R65: -621.5 | S65: -8953.48 | T65: 7822.88 | U65: -2873.66 | V65: -11018.63 | W65: -7635.69 | X65: 6868.72 | Y65: 16077.07 | Z65: 4291.47 | AA65: 13830.16 | AB65: 3602.47
A66: 1 | C66: 법인세비용 | E66: 81.61 | H66: 7.22 | L66: 0 | AA66: 0 | AB66: 1488.47
A67: 1 | C67: 당기순이익 | E67: 2373.75 | G67: 1047.94 | H67: 6258.73 | I67: 4307.75 | J67: 1697.24 | K67: 13311.66 | L67: -558.64 | M67: 5188.58 | N67: -1948.1 | O67: 1195.67 | P67: 3877.51 | Q67: -1121.56 | R67: -621.5 | S67: -8953.48 | T67: 7822.88 | U67: -2873.66 | V67: -11018.63 | W67: -7635.69 | X67: 6868.72 | Y67: 16416.35 | Z67: 4630.75 | AA67: 13830.16 | AB67: 2113.99
A68: 1 | C68: 총포괄손익 | E68: 2559.31 | G68: 1655.31 | H68: 6689.63 | I68: 6049.31 | J68: -672.72 | K68: 13721.53 | L68: 691.95 | M68: 5458.08 | N68: -1556.92 | O68: 337.74 | P68: 4930.85 | Q68: -598.68 | R68: -2097.33 | S68: -9305.97 | T68: 8886.68 | U68: -3115.3 | V68: -10968.54 | W68: -8643.8 | X68: 7955.75 | Y68: 17308.61 | Z68: 5652.02 | AA68: 14885.22 | AB68: 2593.43
A69: 1 | C69: 금융손익 | E69: 924.84 | G69: -61.72 | H69: -2463.87 | I69: -3392.51 | J69: 4052.04 | K69: -1866.06 | L69: -836.1 | M69: -673.15 | N69: -631.6 | O69: 1741.05 | P69: -399.8 | Q69: 567.78 | R69: 195.26 | S69: -637.28 | T69: 6803.61 | U69: 6929.37 | V69: -733.41 | W69: 2646.81 | X69: -3025.59 | Y69: 4676.3 | Z69: 3564.11 | AA69: 5332.62 | AB69: -2198.51
A70: 1 | C70: 기타영업외손익 | E70: -585.57 | G70: 2803.3 | H70: 3382.19 | I70: 9186.17 | J70: -12837.65 | K70: 2534.01 | L70: 7098.98 | M70: 38.6 | N70: 897.19 | O70: -7752.45 | P70: 282.32 | Q70: 2860.89 | R70: 1718.41 | S70: -5382.75 | T70: 15833.55 | U70: 15030.1 | V70: -5136.67 | W70: -7022.68 | X70: 3570.49 | Y70: -806.33 | Z70: -9395.19 | AA70: 7700.52 | AB70: 2833.46
A71: 1 | C71: (지배주주지분)당기순이익 | E71: 2373.75 | G71: 1047.94 | H71: 6258.73 | I71: 4307.75 | J71: 1697.24 | K71: 13311.66 | L71: -558.64 | M71: 5188.58 | N71: -1948.1 | O71: 1195.67 | P71: 3877.51 | Q71: -1121.56 | R71: -621.5 | S71: -8953.48 | T71: 7822.88 | U71: -2873.66 | V71: -11018.63 | W71: -7635.69 | X71: 6868.72 | Y71: 16416.35 | Z71: 4630.75 | AA71: 13830.16 | AB71: 2113.99
A72: 1 | C72: 계속사업이익 | E72: 2373.75 | G72: 1047.94 | H72: 6258.73 | I72: 4307.75 | J72: 1697.24 | K72: 13311.66 | L72: -558.64 | M72: 5188.58 | N72: -1948.1 | O72: 1195.67 | P72: 3877.51 | Q72: -1121.56 | R72: -621.5 | S72: -8953.48 | T72: 7822.88 | U72: -2873.66 | V72: -11018.63 | W72: -7635.69 | X72: 6868.72 | Y72: 16416.35 | Z72: 4630.75 | AA72: 13830.16 | AB72: 2113.99
A73: 1 | C73: 종속기업,공동지배기업및관계기업관련손익 | W73: 1912.77 | X73: -4313.93 | Y73: 6858.34 | AA73: 1349.43 | AB73: 3551.72
A74: 1 | C74: 지분법관련손익 | W74: 1912.77 | X74: -4313.93 | Y74: 6858.34 | AA74: 1349.43 | AB74: 3551.72
A75: 1 | C75: 영업활동으로인한현금흐름 | E75: 1656.04 | G75: -13471.41 | H75: -1497.64 | I75: 267.45 | J75: -20847.75 | K75: -35549.35 | L75: -18361.01 | M75: 707.68 | N75: 12922.76 | O75: 21405.27 | P75: 16674.7 | Q75: 9080.67 | R75: 2532.96 | S75: -20253.24 | T75: 7650.5 | U75: -989.11 | V75: 8713.66 | W75: -32557.1 | X75: -11907.02 | Y75: 10909.57 | Z75: -24840.89 | AA75: 735.36 | AB75: -2415.12
A76: 1 | C76: 이자수취(CF) | E76: 731.7 | G76: 274.72 | H76: 581.58 | I76: 177.48 | J76: 624.54 | K76: 1658.32 | L76: 229.27 | M76: 654.62 | N76: 370.04 | O76: 1818.92 | P76: 3072.85 | Q76: 1060.15 | R76: 1753.58 | S76: 1101.01 | T76: 1526.9 | U76: 5441.64 | V76: 186.22 | W76: 913.16 | X76: 137.5 | Y76: 1553.61 | Z76: 2790.49 | AA76: 141.21 | AB76: 1067.03
A77: 1 | C77: 이자지급(CF) | E77: -147.69 | G77: -214.63 | H77: -332.13 | I77: -440.55 | J77: -643.73 | K77: -1631.04 | L77: -978.97 | M77: -1263.07 | X77: -1165.68 | Y77: -1294.22 | AA77: -1242.97 | AB77: -1326.32
A78: 1 | C78: 배당금수취(CF) | E78: 0 | I78: 0 | J78: 19.58 | L78: 9.79
A79: 1 | C79: 법인세납부(CF) | E79: -57.54 | G79: -96.18 | H79: -117.97 | I79: -26.92 | J79: -121.15 | K79: -362.22 | L79: -190.88 | M79: -352.4 | N79: -58.3 | O79: -167.95 | P79: -769.53 | Q79: -164.04 | R79: -173.79 | S79: -169.59 | T79: -95.42 | U79: -602.84 | V79: -49.92 | W79: 441.64 | X79: -35.68 | Y79: -103.57 | Z79: 252.47 | AA79: -478.19 | AB79: -955.8
A80: 1 | C80: 투자활동으로인한현금흐름 | E80: -2344.42 | G80: -7043.08 | H80: 271.06 | I80: -13076.82 | J80: -4947.31 | K80: -24796.15 | L80: 231.47 | M80: -13788.32 | N80: -59225.14 | O80: -5163.23 | P80: -77945.22 | Q80: -28367.59 | R80: -12501.07 | S80: 19894.24 | T80: -3618.25 | U80: -24592.67 | V80: -6288.89 | W80: 10861.19 | X80: 273.13 | Y80: 12682.57 | Z80: 17528 | AA80: -7085.49 | AB80: -2130.65
A81: 1 | C81: 유형자산의증가 | E81: 5903.04 | G81: 6764.88 | H81: 6071.91 | I81: 11413.74 | J81: 10516.81 | K81: 34767.34 | L81: 4972.82 | M81: 611.57 | N81: 1160.5 | O81: 530.1 | P81: 7274.99 | Q81: 4127.1 | R81: 1143.84 | S81: 1814.59 | T81: 1001.57 | U81: 8087.1 | V81: 699.88 | W81: 994.94 | X81: 9216.74 | Y81: 860.45 | Z81: 11772.01 | AA81: 1540.85 | AB81: 427.46
A82: 1 | C82: CAPEX | E82: 6856.49 | G82: 7722.7 | H82: 7673.06 | I82: 12823.45 | J82: 12815.9 | K82: 41035.11 | L82: 6327.1 | M82: 2318.59 | N82: 5377.38 | O82: 6657.9 | P82: 20680.97 | Q82: 10643.86 | R82: 8595.24 | S82: 5220.75 | T82: 3463.77 | U82: 27923.62 | V82: 2516.66 | W82: 6129.2 | X82: 13770.69 | Y82: 8068.28 | Z82: 30484.83 | AA82: 5162.74 | AB82: 2677.67
A83: 1 | C83: 무형자산의증가 | E83: 953.45 | G83: 957.82 | H83: 1601.15 | I83: 1409.71 | J83: 2299.09 | K83: 6267.77 | L83: 1354.28 | M83: 1707.02 | N83: 4216.88 | O83: 6127.8 | P83: 13405.98 | Q83: 6516.76 | R83: 7451.4 | S83: 3406.16 | T83: 2462.2 | U83: 19836.52 | V83: 1816.78 | W83: 5134.26 | X83: 4553.95 | Y83: 7207.83 | Z83: 18712.82 | AA83: 3621.89 | AB83: 2250.21
A84: 1 | C84: 재무활동으로인한현금흐름 | E84: 5067.2 | G84: 15836.06 | H84: 1574.11 | I84: 19414 | J84: 23128.67 | K84: 59952.84 | L84: 11602.93 | M84: 19678.08 | N84: 61623.87 | O84: -1584.56 | P84: 91320.32 | Q84: -3995.86 | R84: 6247.01 | S84: -4110.79 | T84: -7493.8 | U84: -9353.44 | V84: -2327.42 | W84: 17151.69 | X84: 15996.74 | Y84: -13170.4 | Z84: 17650.61 | AA84: -3238.78 | AB84: 8890.23
A85: 1 | C85: 단기차입금의증가 | E85: 19500.28 | G85: 19300 | H85: 33230 | I85: 12270 | J85: 32151.63 | K85: 96951.63 | L85: 47748 | M85: 36771.39 | N85: 37000 | O85: 0 | P85: 121519.39 | S85: 45002.67 | T85: 17000 | V85: 261.95 | W85: 24500 | X85: 0 | Y85: 43288.21 | Z85: 68050.16 | AA85: 0 | AB85: 18299.9
A86: 1 | C86: 단기차입금의감소 | E86: 14400.28 | G86: 9300 | H86: 35000 | I86: 0 | J86: 11546 | K86: 55846 | L86: 45704.37 | M86: 23638.07 | N86: 64500 | O86: 1000 | P86: 134842.44 | Q86: 500 | R86: 540.06 | S86: 47002.47 | T86: 24700 | U86: 72742.53 | V86: 261.95 | W86: 2500 | X86: 7416 | Y86: 44204.21 | Z86: 54382.16 | AA86: 416 | AB86: 6715.9
A87: 1 | C87: 리스부채의상환 | E87: 281 | G87: 282.38 | H87: 275.82 | I87: 307.39 | J87: 370.33 | K87: 1235.92 | L87: 357.22 | M87: 370.43 | N87: 369.72 | O87: 369.85 | P87: 1467.22 | Q87: 420.41 | R87: 421.22 | S87: 416.48 | T87: 412.26 | U87: 1670.37 | V87: 433.7 | W87: 421.79 | X87: 420.15 | Y87: 419.72 | Z87: 1695.36 | AA87: 453.73 | AB87: 455.75
A88: 1 | C88: 유동성장기부채의감소 | E88: 95 | G88: 95 | H88: 95 | I88: 95 | J88: 4095 | K88: 4380 | L88: 309.44 | M88: 309.28 | N88: 180.71 | O88: 3309.28 | P88: 4108.71 | Q88: 3809.28 | R88: 5309.28 | S88: 937.85 | T88: 809.28 | U88: 10865.69 | V88: 809.28 | W88: 3309.28 | X88: 3309.28 | Y88: 3409.28 | Z88: 10837.12 | AA88: 3214.28 | AB88: 714.28
A89: 1 | C89: 장기차입금의증가 | E89: 0 | G89: 6000 | H89: 4000 | I89: 7500 | J89: 7000 | K89: 24500 | L89: 10000 | M89: 8000 | N89: 0 | O89: 3000 | P89: 21000 | Q89: 3500 | R89: 5000 | S89: 0 | T89: 2200 | U89: 10700 | Y89: 0
A90: 1 | C90: 배당금지급 | E90: 0 | I90: 0 | J90: 0 | N90: 0 | O90: 0 | S90: 0 | T90: 0 | X90: 0 | Y90: 0
A91: 1 | C91: 현금및현금성자산의증감 | E91: 4378.82 | G91: -4678.43 | H91: 347.53 | I91: 6604.63 | J91: -2666.38 | K91: -392.65 | L91: -6526.62 | M91: 6597.45 | N91: 15321.49 | O91: 14657.48 | P91: 30049.8 | Q91: -23282.77 | R91: -3721.11 | S91: -4469.8 | T91: -3461.54 | U91: -34935.22 | V91: 97.34 | W91: -4544.21 | X91: 4362.85 | Y91: 10421.74 | Z91: 10337.72 | AA91: -9588.91 | AB91: 4344.46
A92: 1 | C92: 기말현금및현금성자산 | E92: 4318.57 | G92: 10716.67 | H92: 503.85 | I92: 6861.76 | J92: -3611.94 | K92: 14470.34 | L92: 7943.73 | M92: 6526.62 | N92: 15629.44 | O92: 14432.22 | P92: 44532.01 | Q92: 21302.45 | R92: -3718.07 | S92: -4988.37 | T92: -2782 | U92: 9814.01 | V92: 9959.15 | W92: -4625.7 | X92: 4446.62 | Y92: 10371.3 | Z92: 20151.37 | AA92: 10562.46 | AB92: 4415.85
A93: 1 | C93: 유형자산의감소 | G93: 27 | H93: 0 | I93: 3.56 | J93: 0 | K93: 30.56 | Q93: 1117.11 | R93: 2 | S93: 2 | T93: 0 | U93: 1121.11 | V93: 0.63 | W93: 0 | X93: 0 | Y93: 4806.35 | Z93: 4806.98 | AA93: 0.17 | AB93: 0
A94: 1 | C94: 자기주식의취득 | J94: 352.39 | X94: 0 | Y94: 4996.88 | AA94: 0 | AB94: 0
A95: 1 | C95: 사채의증가 | Y95: 0

Sheet subQ
A1: YQ | C1: subQ 분기 서브모델(억원, U=100) | E1: 4Q21 | F1: 2021 | G1: 1Q22 | H1: 2Q22 | I1: 3Q22 | J1: 4Q22 | K1: 2022 | L1: 1Q23 | M1: 2Q23 | N1: 3Q23 | O1: 4Q23 | P1: 2023 | Q1: 1Q24 | R1: 2Q24 | S1: 3Q24 | T1: 4Q24 | U1: 2024 | V1: 1Q25 | W1: 2Q25 | X1: 3Q25 | Y1: 4Q25 | Z1: 2025 | AA1: 1Q26 | AB1: 2Q26 | AC1: 3Q26 | AD1: 4Q26 | AE1: 2026 | AF1: 1Q27 | AG1: 2Q27 | AH1: 3Q27 | AI1: 4Q27 | AJ1: 2027 | AK1: 1Q28 | AL1: 2Q28 | AM1: 3Q28 | AN1: 4Q28 | AO1: 2028
A2: A=이름(key) B=그룹 C=단위 D=FnGuide 계정명(VLOOKUP 키). 확정=VLOOKUP(BS), 추정=변수 가정 참조
E3: 1 | F3: 2 | G3: 3 | H3: 4 | I3: 5 | J3: 6 | K3: 7 | L3: 8 | M3: 9 | N3: 10 | O3: 11 | P3: 12 | Q3: 13 | R3: 14 | S3: 15 | T3: 16 | U3: 17 | V3: 18 | W3: 19 | X3: 20 | Y3: 21 | Z3: 22 | AA3: 23 | AB3: 24 | AC3: 25 | AD3: 26 | AE3: 27 | AF3: 28 | AG3: 29 | AH3: 30 | AI3: 31 | AJ3: 32 | AK3: 33 | AL3: 34 | AM3: 35 | AN3: 36 | AO3: 37
E4: 2021.12 | F4: 2021.12A | G4: 2022.03 | H4: 2022.06 | I4: 2022.09 | J4: 2022.12 | K4: 2022.12A | L4: 2023.03 | M4: 2023.06 | N4: 2023.09 | O4: 2023.12 | P4: 2023.12A | Q4: 2024.03 | R4: 2024.06 | S4: 2024.09 | T4: 2024.12 | U4: 2024.12A | V4: 2025.03 | W4: 2025.06 | X4: 2025.09 | Y4: 2025.12 | Z4: 2025.12A | AA4: 2026.03 | AB4: 2026.06 | AC4: 2026.09 | AD4: 2026.12 | AE4: 2026.12A | AF4: 2027.03 | AG4: 2027.06 | AH4: 2027.09 | AI4: 2027.12 | AJ4: 2027.12A | AK4: 2028.03 | AL4: 2028.06 | AM4: 2028.09 | AN4: 2028.12 | AO4: 2028.12A
A5: 매출액 | B5: 손익 | C5: 억원 | D5: 매출액(수익) | E5: =IFERROR(VLOOKUP($D5,BS연결,MATCH(E$1,BS연결H,0),0)/100,"") | G5: =IFERROR(VLOOKUP($D5,BS연결,MATCH(G$1,BS연결H,0),0)/100,"") | H5: =IFERROR(VLOOKUP($D5,BS연결,MATCH(H$1,BS연결H,0),0)/100,"") | I5: =IFERROR(VLOOKUP($D5,BS연결,MATCH(I$1,BS연결H,0),0)/100,"") | J5: =IFERROR(VLOOKUP($D5,BS연결,MATCH(J$1,BS연결H,0),0)/100,"") | K5: =IFERROR(VLOOKUP($D5,BS연결,MATCH(K$1,BS연결H,0),0)/100,"") | L5: =IFERROR(VLOOKUP($D5,BS연결,MATCH(L$1,BS연결H,0),0)/100,"") | M5: =IFERROR(VLOOKUP($D5,BS연결,MATCH(M$1,BS연결H,0),0)/100,"") | N5: =IFERROR(VLOOKUP($D5,BS연결,MATCH(N$1,BS연결H,0),0)/100,"") | ... AB5: =IFERROR(VLOOKUP($D5,BS연결,MATCH(AB$1,BS연결H,0),0)/100,"") | AC5: =IFERROR(X5*(1+변수!AC21),"") | AD5: =IFERROR(Y5*(1+변수!AD21),"") | AE5: =SUM(AA5:AD5) | AF5: =IFERROR(AA5*(1+변수!AF21),"") | AG5: =IFERROR(AB5*(1+변수!AG21),"") | AH5: =IFERROR(AC5*(1+변수!AH21),"") | AI5: =IFERROR(AD5*(1+변수!AI21),"") | AJ5: =SUM(AF5:AI5) | AK5: =IFERROR(AF5*(1+변수!AK21),"") | AL5: =IFERROR(AG5*(1+변수!AL21),"") | AM5: =IFERROR(AH5*(1+변수!AM21),"") | AN5: =IFERROR(AI5*(1+변수!AN21),"") | AO5: =SUM(AK5:AN5)
A6: 매출원가 | B6: 손익 | C6: 억원 | D6: 매출원가 | E6: =IFERROR(VLOOKUP($D6,BS연결,MATCH(E$1,BS연결H,0),0)/100,"") | G6: =IFERROR(VLOOKUP($D6,BS연결,MATCH(G$1,BS연결H,0),0)/100,"") | H6: =IFERROR(VLOOKUP($D6,BS연결,MATCH(H$1,BS연결H,0),0)/100,"") | I6: =IFERROR(VLOOKUP($D6,BS연결,MATCH(I$1,BS연결H,0),0)/100,"") | J6: =IFERROR(VLOOKUP($D6,BS연결,MATCH(J$1,BS연결H,0),0)/100,"") | K6: =IFERROR(VLOOKUP($D6,BS연결,MATCH(K$1,BS연결H,0),0)/100,"") | L6: =IFERROR(VLOOKUP($D6,BS연결,MATCH(L$1,BS연결H,0),0)/100,"") | M6: =IFERROR(VLOOKUP($D6,BS연결,MATCH(M$1,BS연결H,0),0)/100,"") | N6: =IFERROR(VLOOKUP($D6,BS연결,MATCH(N$1,BS연결H,0),0)/100,"") | ... AB6: =IFERROR(VLOOKUP($D6,BS연결,MATCH(AB$1,BS연결H,0),0)/100,"") | AC6: =IFERROR(AC5-AC7,"") | AD6: =IFERROR(AD5-AD7,"") | AE6: =SUM(AA6:AD6) | AF6: =IFERROR(AF5-AF7,"") | AG6: =IFERROR(AG5-AG7,"") | AH6: =IFERROR(AH5-AH7,"") | AI6: =IFERROR(AI5-AI7,"") | AJ6: =SUM(AF6:AI6) | AK6: =IFERROR(AK5-AK7,"") | AL6: =IFERROR(AL5-AL7,"") | AM6: =IFERROR(AM5-AM7,"") | AN6: =IFERROR(AN5-AN7,"") | AO6: =SUM(AK6:AN6)
A7: 매출총이익 | B7: 손익 | C7: 억원 | D7: 매출총이익 | E7: =IFERROR(VLOOKUP($D7,BS연결,MATCH(E$1,BS연결H,0),0)/100,"") | G7: =IFERROR(VLOOKUP($D7,BS연결,MATCH(G$1,BS연결H,0),0)/100,"") | H7: =IFERROR(VLOOKUP($D7,BS연결,MATCH(H$1,BS연결H,0),0)/100,"") | I7: =IFERROR(VLOOKUP($D7,BS연결,MATCH(I$1,BS연결H,0),0)/100,"") | J7: =IFERROR(VLOOKUP($D7,BS연결,MATCH(J$1,BS연결H,0),0)/100,"") | K7: =IFERROR(VLOOKUP($D7,BS연결,MATCH(K$1,BS연결H,0),0)/100,"") | L7: =IFERROR(VLOOKUP($D7,BS연결,MATCH(L$1,BS연결H,0),0)/100,"") | M7: =IFERROR(VLOOKUP($D7,BS연결,MATCH(M$1,BS연결H,0),0)/100,"") | N7: =IFERROR(VLOOKUP($D7,BS연결,MATCH(N$1,BS연결H,0),0)/100,"") | ... AB7: =IFERROR(VLOOKUP($D7,BS연결,MATCH(AB$1,BS연결H,0),0)/100,"") | AC7: =IFERROR(AC9+AC8,"") | AD7: =IFERROR(AD9+AD8,"") | AE7: =SUM(AA7:AD7) | AF7: =IFERROR(AF9+AF8,"") | AG7: =IFERROR(AG9+AG8,"") | AH7: =IFERROR(AH9+AH8,"") | AI7: =IFERROR(AI9+AI8,"") | AJ7: =SUM(AF7:AI7) | AK7: =IFERROR(AK9+AK8,"") | AL7: =IFERROR(AL9+AL8,"") | AM7: =IFERROR(AM9+AM8,"") | AN7: =IFERROR(AN9+AN8,"") | AO7: =SUM(AK7:AN7)
A8: 판관비 | B8: 손익 | C8: 억원 | D8: 판관비 | E8: =IFERROR(VLOOKUP($D8,BS연결,MATCH(E$1,BS연결H,0),0)/100,"") | G8: =IFERROR(VLOOKUP($D8,BS연결,MATCH(G$1,BS연결H,0),0)/100,"") | H8: =IFERROR(VLOOKUP($D8,BS연결,MATCH(H$1,BS연결H,0),0)/100,"") | I8: =IFERROR(VLOOKUP($D8,BS연결,MATCH(I$1,BS연결H,0),0)/100,"") | J8: =IFERROR(VLOOKUP($D8,BS연결,MATCH(J$1,BS연결H,0),0)/100,"") | K8: =IFERROR(VLOOKUP($D8,BS연결,MATCH(K$1,BS연결H,0),0)/100,"") | L8: =IFERROR(VLOOKUP($D8,BS연결,MATCH(L$1,BS연결H,0),0)/100,"") | M8: =IFERROR(VLOOKUP($D8,BS연결,MATCH(M$1,BS연결H,0),0)/100,"") | N8: =IFERROR(VLOOKUP($D8,BS연결,MATCH(N$1,BS연결H,0),0)/100,"") | ... AB8: =IFERROR(VLOOKUP($D8,BS연결,MATCH(AB$1,BS연결H,0),0)/100,"") | AC8: =IFERROR(AC5*변수!AC22,"") | AD8: =IFERROR(AD5*변수!AD22,"") | AE8: =SUM(AA8:AD8) | AF8: =IFERROR(AF5*변수!AF22,"") | AG8: =IFERROR(AG5*변수!AG22,"") | AH8: =IFERROR(AH5*변수!AH22,"") | AI8: =IFERROR(AI5*변수!AI22,"") | AJ8: =SUM(AF8:AI8) | AK8: =IFERROR(AK5*변수!AK22,"") | AL8: =IFERROR(AL5*변수!AL22,"") | AM8: =IFERROR(AM5*변수!AM22,"") | AN8: =IFERROR(AN5*변수!AN22,"") | AO8: =SUM(AK8:AN8)
A9: 영업이익 | B9: 손익 | C9: 억원 | D9: 영업이익 | E9: =IFERROR(VLOOKUP($D9,BS연결,MATCH(E$1,BS연결H,0),0)/100,"") | G9: =IFERROR(VLOOKUP($D9,BS연결,MATCH(G$1,BS연결H,0),0)/100,"") | H9: =IFERROR(VLOOKUP($D9,BS연결,MATCH(H$1,BS연결H,0),0)/100,"") | I9: =IFERROR(VLOOKUP($D9,BS연결,MATCH(I$1,BS연결H,0),0)/100,"") | J9: =IFERROR(VLOOKUP($D9,BS연결,MATCH(J$1,BS연결H,0),0)/100,"") | K9: =IFERROR(VLOOKUP($D9,BS연결,MATCH(K$1,BS연결H,0),0)/100,"") | L9: =IFERROR(VLOOKUP($D9,BS연결,MATCH(L$1,BS연결H,0),0)/100,"") | M9: =IFERROR(VLOOKUP($D9,BS연결,MATCH(M$1,BS연결H,0),0)/100,"") | N9: =IFERROR(VLOOKUP($D9,BS연결,MATCH(N$1,BS연결H,0),0)/100,"") | ... AB9: =IFERROR(VLOOKUP($D9,BS연결,MATCH(AB$1,BS연결H,0),0)/100,"") | AC9: =IFERROR(AC5*변수!AC23,"") | AD9: =IFERROR(AD5*변수!AD23,"") | AE9: =SUM(AA9:AD9) | AF9: =IFERROR(AF5*변수!AF23,"") | AG9: =IFERROR(AG5*변수!AG23,"") | AH9: =IFERROR(AH5*변수!AH23,"") | AI9: =IFERROR(AI5*변수!AI23,"") | AJ9: =SUM(AF9:AI9) | AK9: =IFERROR(AK5*변수!AK23,"") | AL9: =IFERROR(AL5*변수!AL23,"") | AM9: =IFERROR(AM5*변수!AM23,"") | AN9: =IFERROR(AN5*변수!AN23,"") | AO9: =SUM(AK9:AN9)
A10: OPM | B10: 손익 | C10: % | D10: 영업이익률 | E10: =IFERROR(E9/E5,"") | G10: =IFERROR(G9/G5,"") | H10: =IFERROR(H9/H5,"") | I10: =IFERROR(I9/I5,"") | J10: =IFERROR(J9/J5,"") | K10: =IFERROR(K9/K5,"") | L10: =IFERROR(L9/L5,"") | M10: =IFERROR(M9/M5,"") | N10: =IFERROR(N9/N5,"") | ... AO10: =IFERROR(AO9/AO5,"")
A11: 금융손익 | B11: 손익 | C11: 억원 | D11: 금융손익 | E11: =IFERROR(VLOOKUP($D11,BS연결,MATCH(E$1,BS연결H,0),0)/100,"") | G11: =IFERROR(VLOOKUP($D11,BS연결,MATCH(G$1,BS연결H,0),0)/100,"") | H11: =IFERROR(VLOOKUP($D11,BS연결,MATCH(H$1,BS연결H,0),0)/100,"") | I11: =IFERROR(VLOOKUP($D11,BS연결,MATCH(I$1,BS연결H,0),0)/100,"") | J11: =IFERROR(VLOOKUP($D11,BS연결,MATCH(J$1,BS연결H,0),0)/100,"") | K11: =SUM(G11:J11) | L11: =IFERROR(VLOOKUP($D11,BS연결,MATCH(L$1,BS연결H,0),0)/100,"") | M11: =IFERROR(VLOOKUP($D11,BS연결,MATCH(M$1,BS연결H,0),0)/100,"") | N11: =IFERROR(VLOOKUP($D11,BS연결,MATCH(N$1,BS연결H,0),0)/100,"") | O11: =IFERROR(VLOOKUP($D11,BS연결,MATCH(O$1,BS연결H,0),0)/100,"") | P11: =IFERROR(VLOOKUP($D11,BS연결,MATCH(P$1,BS연결H,0),0)/100,"") | Q11: =IFERROR(VLOOKUP($D11,BS연결,MATCH(Q$1,BS연결H,0),0)/100,"") | R11: =IFERROR(VLOOKUP($D11,BS연결,MATCH(R$1,BS연결H,0),0)/100,"") | S11: =IFERROR(VLOOKUP($D11,BS연결,MATCH(S$1,BS연결H,0),0)/100,"") | ... AB11: =IFERROR(VLOOKUP($D11,BS연결,MATCH(AB$1,BS연결H,0),0)/100,"") | AC11: =IFERROR(AC12,"") | AD11: =IFERROR(AD12,"") | AE11: =SUM(AA11:AD11) | AF11: =IFERROR(AF12,"") | AG11: =IFERROR(AG12,"") | AH11: =IFERROR(AH12,"") | AI11: =IFERROR(AI12,"") | AJ11: =SUM(AF11:AI11) | AK11: =IFERROR(AK12,"") | AL11: =IFERROR(AL12,"") | AM11: =IFERROR(AM12,"") | AN11: =IFERROR(AN12,"") | AO11: =SUM(AK11:AN11)
A12: 이자손익 | B12: 손익 | C12: 억원 | D12: 이자손익 | G12: =IFERROR(VLOOKUP($D12,BS연결,MATCH(G$1,BS연결H,0),0)/100,"") | H12: =IFERROR(VLOOKUP($D12,BS연결,MATCH(H$1,BS연결H,0),0)/100,"") | I12: =IFERROR(VLOOKUP($D12,BS연결,MATCH(I$1,BS연결H,0),0)/100,"") | J12: =IFERROR(VLOOKUP($D12,BS연결,MATCH(J$1,BS연결H,0),0)/100,"") | K12: =IFERROR(VLOOKUP($D12,BS연결,MATCH(K$1,BS연결H,0),0)/100,"") | L12: =IFERROR(VLOOKUP($D12,BS연결,MATCH(L$1,BS연결H,0),0)/100,"") | M12: =IFERROR(VLOOKUP($D12,BS연결,MATCH(M$1,BS연결H,0),0)/100,"") | N12: =IFERROR(VLOOKUP($D12,BS연결,MATCH(N$1,BS연결H,0),0)/100,"") | ... Z12: =IFERROR(VLOOKUP($D12,BS연결,MATCH(Z$1,BS연결H,0),0)/100,"") | AB12: =IFERROR(VLOOKUP($D12,BS연결,MATCH(AB$1,BS연결H,0),0)/100,"") | AC12: =IFERROR((AB24*변수!$D$50-AB22*변수!$D$51)/4,"") | AD12: =IFERROR((AC24*변수!$D$50-AC22*변수!$D$51)/4,"") | AE12: =SUM(AA12:AD12) | AF12: =IFERROR((AD24*변수!$D$50-AD22*변수!$D$51)/4,"") | AG12: =IFERROR((AF24*변수!$D$50-AF22*변수!$D$51)/4,"") | AH12: =IFERROR((AG24*변수!$D$50-AG22*변수!$D$51)/4,"") | AI12: =IFERROR((AH24*변수!$D$50-AH22*변수!$D$51)/4,"") | AJ12: =SUM(AF12:AI12) | AK12: =IFERROR((AI24*변수!$D$50-AI22*변수!$D$51)/4,"") | AL12: =IFERROR((AK24*변수!$D$50-AK22*변수!$D$51)/4,"") | AM12: =IFERROR((AL24*변수!$D$50-AL22*변수!$D$51)/4,"") | AN12: =IFERROR((AM24*변수!$D$50-AM22*변수!$D$51)/4,"") | AO12: =SUM(AK12:AN12)
A13: 기타영업외손익 | B13: 손익 | C13: 억원 | D13: 기타영업외손익 | E13: =IFERROR(VLOOKUP($D13,BS연결,MATCH(E$1,BS연결H,0),0)/100,"") | G13: =IFERROR(VLOOKUP($D13,BS연결,MATCH(G$1,BS연결H,0),0)/100,"") | H13: =IFERROR(VLOOKUP($D13,BS연결,MATCH(H$1,BS연결H,0),0)/100,"") | I13: =IFERROR(VLOOKUP($D13,BS연결,MATCH(I$1,BS연결H,0),0)/100,"") | J13: =IFERROR(VLOOKUP($D13,BS연결,MATCH(J$1,BS연결H,0),0)/100,"") | K13: =IFERROR(VLOOKUP($D13,BS연결,MATCH(K$1,BS연결H,0),0)/100,"") | L13: =IFERROR(VLOOKUP($D13,BS연결,MATCH(L$1,BS연결H,0),0)/100,"") | M13: =IFERROR(VLOOKUP($D13,BS연결,MATCH(M$1,BS연결H,0),0)/100,"") | N13: =IFERROR(VLOOKUP($D13,BS연결,MATCH(N$1,BS연결H,0),0)/100,"") | ... AB13: =IFERROR(VLOOKUP($D13,BS연결,MATCH(AB$1,BS연결H,0),0)/100,"") | AC13: =변수!AC24 | AD13: =변수!AD24 | AE13: =SUM(AA13:AD13) | AF13: =변수!AF24 | AG13: =변수!AG24 | AH13: =변수!AH24 | AI13: =변수!AI24 | AJ13: =SUM(AF13:AI13) | AK13: =변수!AK24 | AL13: =변수!AL24 | AM13: =변수!AM24 | AN13: =변수!AN24 | AO13: =SUM(AK13:AN13)
A14: 세전이익 | B14: 손익 | C14: 억원 | D14: 법인세비용차감전계속사업이익 | E14: =IFERROR(VLOOKUP($D14,BS연결,MATCH(E$1,BS연결H,0),0)/100,"") | G14: =IFERROR(VLOOKUP($D14,BS연결,MATCH(G$1,BS연결H,0),0)/100,"") | H14: =IFERROR(VLOOKUP($D14,BS연결,MATCH(H$1,BS연결H,0),0)/100,"") | I14: =IFERROR(VLOOKUP($D14,BS연결,MATCH(I$1,BS연결H,0),0)/100,"") | J14: =IFERROR(VLOOKUP($D14,BS연결,MATCH(J$1,BS연결H,0),0)/100,"") | K14: =IFERROR(VLOOKUP($D14,BS연결,MATCH(K$1,BS연결H,0),0)/100,"") | L14: =IFERROR(VLOOKUP($D14,BS연결,MATCH(L$1,BS연결H,0),0)/100,"") | M14: =IFERROR(VLOOKUP($D14,BS연결,MATCH(M$1,BS연결H,0),0)/100,"") | N14: =IFERROR(VLOOKUP($D14,BS연결,MATCH(N$1,BS연결H,0),0)/100,"") | ... AB14: =IFERROR(VLOOKUP($D14,BS연결,MATCH(AB$1,BS연결H,0),0)/100,"") | AC14: =IFERROR(AC9+AC11+AC13,"") | AD14: =IFERROR(AD9+AD11+AD13,"") | AE14: =SUM(AA14:AD14) | AF14: =IFERROR(AF9+AF11+AF13,"") | AG14: =IFERROR(AG9+AG11+AG13,"") | AH14: =IFERROR(AH9+AH11+AH13,"") | AI14: =IFERROR(AI9+AI11+AI13,"") | AJ14: =SUM(AF14:AI14) | AK14: =IFERROR(AK9+AK11+AK13,"") | AL14: =IFERROR(AL9+AL11+AL13,"") | AM14: =IFERROR(AM9+AM11+AM13,"") | AN14: =IFERROR(AN9+AN11+AN13,"") | AO14: =SUM(AK14:AN14)
A15: 법인세비용 | B15: 손익 | C15: 억원 | D15: 법인세비용 | E15: =IFERROR(VLOOKUP($D15,BS연결,MATCH(E$1,BS연결H,0),0)/100,"") | G15: =IFERROR(VLOOKUP($D15,BS연결,MATCH(G$1,BS연결H,0),0)/100,"") | H15: =IFERROR(VLOOKUP($D15,BS연결,MATCH(H$1,BS연결H,0),0)/100,"") | I15: =IFERROR(VLOOKUP($D15,BS연결,MATCH(I$1,BS연결H,0),0)/100,"") | J15: =IFERROR(VLOOKUP($D15,BS연결,MATCH(J$1,BS연결H,0),0)/100,"") | K15: =IFERROR(VLOOKUP($D15,BS연결,MATCH(K$1,BS연결H,0),0)/100,"") | L15: =IFERROR(VLOOKUP($D15,BS연결,MATCH(L$1,BS연결H,0),0)/100,"") | M15: =IFERROR(VLOOKUP($D15,BS연결,MATCH(M$1,BS연결H,0),0)/100,"") | N15: =IFERROR(VLOOKUP($D15,BS연결,MATCH(N$1,BS연결H,0),0)/100,"") | ... AB15: =IFERROR(VLOOKUP($D15,BS연결,MATCH(AB$1,BS연결H,0),0)/100,"") | AC15: =IFERROR(MAX(AC14,0)*변수!AC25,"") | AD15: =IFERROR(MAX(AD14,0)*변수!AD25,"") | AE15: =SUM(AA15:AD15) | AF15: =IFERROR(MAX(AF14,0)*변수!AF25,"") | AG15: =IFERROR(MAX(AG14,0)*변수!AG25,"") | AH15: =IFERROR(MAX(AH14,0)*변수!AH25,"") | AI15: =IFERROR(MAX(AI14,0)*변수!AI25,"") | AJ15: =SUM(AF15:AI15) | AK15: =IFERROR(MAX(AK14,0)*변수!AK25,"") | AL15: =IFERROR(MAX(AL14,0)*변수!AL25,"") | AM15: =IFERROR(MAX(AM14,0)*변수!AM25,"") | AN15: =IFERROR(MAX(AN14,0)*변수!AN25,"") | AO15: =SUM(AK15:AN15)
A16: 당기순이익 | B16: 손익 | C16: 억원 | D16: 당기순이익 | E16: =IFERROR(VLOOKUP($D16,BS연결,MATCH(E$1,BS연결H,0),0)/100,"") | G16: =IFERROR(VLOOKUP($D16,BS연결,MATCH(G$1,BS연결H,0),0)/100,"") | H16: =IFERROR(VLOOKUP($D16,BS연결,MATCH(H$1,BS연결H,0),0)/100,"") | I16: =IFERROR(VLOOKUP($D16,BS연결,MATCH(I$1,BS연결H,0),0)/100,"") | J16: =IFERROR(VLOOKUP($D16,BS연결,MATCH(J$1,BS연결H,0),0)/100,"") | K16: =IFERROR(VLOOKUP($D16,BS연결,MATCH(K$1,BS연결H,0),0)/100,"") | L16: =IFERROR(VLOOKUP($D16,BS연결,MATCH(L$1,BS연결H,0),0)/100,"") | M16: =IFERROR(VLOOKUP($D16,BS연결,MATCH(M$1,BS연결H,0),0)/100,"") | N16: =IFERROR(VLOOKUP($D16,BS연결,MATCH(N$1,BS연결H,0),0)/100,"") | ... AB16: =IFERROR(VLOOKUP($D16,BS연결,MATCH(AB$1,BS연결H,0),0)/100,"") | AC16: =IFERROR(AC14-AC15,"") | AD16: =IFERROR(AD14-AD15,"") | AE16: =SUM(AA16:AD16) | AF16: =IFERROR(AF14-AF15,"") | AG16: =IFERROR(AG14-AG15,"") | AH16: =IFERROR(AH14-AH15,"") | AI16: =IFERROR(AI14-AI15,"") | AJ16: =SUM(AF16:AI16) | AK16: =IFERROR(AK14-AK15,"") | AL16: =IFERROR(AL14-AL15,"") | AM16: =IFERROR(AM14-AM15,"") | AN16: =IFERROR(AN14-AN15,"") | AO16: =SUM(AK16:AN16)
A17: 지배주주순이익 | B17: 손익 | C17: 억원 | D17: (지배주주지분)당기순이익 | E17: =IFERROR(VLOOKUP($D17,BS연결,MATCH(E$1,BS연결H,0),0)/100,"") | G17: =IFERROR(VLOOKUP($D17,BS연결,MATCH(G$1,BS연결H,0),0)/100,"") | H17: =IFERROR(VLOOKUP($D17,BS연결,MATCH(H$1,BS연결H,0),0)/100,"") | I17: =IFERROR(VLOOKUP($D17,BS연결,MATCH(I$1,BS연결H,0),0)/100,"") | J17: =IFERROR(VLOOKUP($D17,BS연결,MATCH(J$1,BS연결H,0),0)/100,"") | K17: =IFERROR(VLOOKUP($D17,BS연결,MATCH(K$1,BS연결H,0),0)/100,"") | L17: =IFERROR(VLOOKUP($D17,BS연결,MATCH(L$1,BS연결H,0),0)/100,"") | M17: =IFERROR(VLOOKUP($D17,BS연결,MATCH(M$1,BS연결H,0),0)/100,"") | N17: =IFERROR(VLOOKUP($D17,BS연결,MATCH(N$1,BS연결H,0),0)/100,"") | ... AB17: =IFERROR(VLOOKUP($D17,BS연결,MATCH(AB$1,BS연결H,0),0)/100,"") | AC17: =IFERROR(AC16*변수!AC26,"") | AD17: =IFERROR(AD16*변수!AD26,"") | AE17: =SUM(AA17:AD17) | AF17: =IFERROR(AF16*변수!AF26,"") | AG17: =IFERROR(AG16*변수!AG26,"") | AH17: =IFERROR(AH16*변수!AH26,"") | AI17: =IFERROR(AI16*변수!AI26,"") | AJ17: =SUM(AF17:AI17) | AK17: =IFERROR(AK16*변수!AK26,"") | AL17: =IFERROR(AL16*변수!AL26,"") | AM17: =IFERROR(AM16*변수!AM26,"") | AN17: =IFERROR(AN16*변수!AN26,"") | AO17: =SUM(AK17:AN17)
A18: 자산총계 | B18: 재무상태 | C18: 억원 | D18: 자산총계 | E18: =IFERROR(VLOOKUP($D18,BS연결,MATCH(E$1,BS연결H,0),0)/100,"") | F18: =IFERROR(VLOOKUP($D18,BS연결,MATCH(F$1,BS연결H,0),0)/100,"") | G18: =IFERROR(VLOOKUP($D18,BS연결,MATCH(G$1,BS연결H,0),0)/100,"") | H18: =IFERROR(VLOOKUP($D18,BS연결,MATCH(H$1,BS연결H,0),0)/100,"") | I18: =IFERROR(VLOOKUP($D18,BS연결,MATCH(I$1,BS연결H,0),0)/100,"") | J18: =IFERROR(VLOOKUP($D18,BS연결,MATCH(J$1,BS연결H,0),0)/100,"") | K18: =IFERROR(VLOOKUP($D18,BS연결,MATCH(K$1,BS연결H,0),0)/100,"") | L18: =IFERROR(VLOOKUP($D18,BS연결,MATCH(L$1,BS연결H,0),0)/100,"") | ... AB18: =IFERROR(VLOOKUP($D18,BS연결,MATCH(AB$1,BS연결H,0),0)/100,"") | AC18: =IFERROR(AC19+AC20,"") | AD18: =IFERROR(AD19+AD20,"") | AE18: =AD18 | AF18: =IFERROR(AF19+AF20,"") | AG18: =IFERROR(AG19+AG20,"") | AH18: =IFERROR(AH19+AH20,"") | AI18: =IFERROR(AI19+AI20,"") | AJ18: =AI18 | AK18: =IFERROR(AK19+AK20,"") | AL18: =IFERROR(AL19+AL20,"") | AM18: =IFERROR(AM19+AM20,"") | AN18: =IFERROR(AN19+AN20,"") | AO18: =AN18
A19: 부채총계 | B19: 재무상태 | C19: 억원 | D19: 부채총계 | E19: =IFERROR(VLOOKUP($D19,BS연결,MATCH(E$1,BS연결H,0),0)/100,"") | F19: =IFERROR(VLOOKUP($D19,BS연결,MATCH(F$1,BS연결H,0),0)/100,"") | G19: =IFERROR(VLOOKUP($D19,BS연결,MATCH(G$1,BS연결H,0),0)/100,"") | H19: =IFERROR(VLOOKUP($D19,BS연결,MATCH(H$1,BS연결H,0),0)/100,"") | I19: =IFERROR(VLOOKUP($D19,BS연결,MATCH(I$1,BS연결H,0),0)/100,"") | J19: =IFERROR(VLOOKUP($D19,BS연결,MATCH(J$1,BS연결H,0),0)/100,"") | K19: =IFERROR(VLOOKUP($D19,BS연결,MATCH(K$1,BS연결H,0),0)/100,"") | L19: =IFERROR(VLOOKUP($D19,BS연결,MATCH(L$1,BS연결H,0),0)/100,"") | ... AB19: =IFERROR(VLOOKUP($D19,BS연결,MATCH(AB$1,BS연결H,0),0)/100,"") | AC19: =IFERROR(AB19*(1+변수!AC27),"") | AD19: =IFERROR(AC19*(1+변수!AD27),"") | AE19: =AD19 | AF19: =IFERROR(AD19*(1+변수!AF27),"") | AG19: =IFERROR(AF19*(1+변수!AG27),"") | AH19: =IFERROR(AG19*(1+변수!AH27),"") | AI19: =IFERROR(AH19*(1+변수!AI27),"") | AJ19: =AI19 | AK19: =IFERROR(AI19*(1+변수!AK27),"") | AL19: =IFERROR(AK19*(1+변수!AL27),"") | AM19: =IFERROR(AL19*(1+변수!AM27),"") | AN19: =IFERROR(AM19*(1+변수!AN27),"") | AO19: =AN19
A20: 자본총계 | B20: 재무상태 | C20: 억원 | D20: 자본총계 | E20: =IFERROR(VLOOKUP($D20,BS연결,MATCH(E$1,BS연결H,0),0)/100,"") | F20: =IFERROR(VLOOKUP($D20,BS연결,MATCH(F$1,BS연결H,0),0)/100,"") | G20: =IFERROR(VLOOKUP($D20,BS연결,MATCH(G$1,BS연결H,0),0)/100,"") | H20: =IFERROR(VLOOKUP($D20,BS연결,MATCH(H$1,BS연결H,0),0)/100,"") | I20: =IFERROR(VLOOKUP($D20,BS연결,MATCH(I$1,BS연결H,0),0)/100,"") | J20: =IFERROR(VLOOKUP($D20,BS연결,MATCH(J$1,BS연결H,0),0)/100,"") | K20: =IFERROR(VLOOKUP($D20,BS연결,MATCH(K$1,BS연결H,0),0)/100,"") | L20: =IFERROR(VLOOKUP($D20,BS연결,MATCH(L$1,BS연결H,0),0)/100,"") | ... AA20: =IFERROR(VLOOKUP($D20,BS연결,MATCH(AA$1,BS연결H,0),0)/100,"") | AE20: =AD20 | AJ20: =AI20 | AO20: =AN20
A21: 지배주주지분 | B21: 재무상태 | C21: 억원 | D21: 지배주주지분 | E21: =IFERROR(VLOOKUP($D21,BS연결,MATCH(E$1,BS연결H,0),0)/100,"") | F21: =IFERROR(VLOOKUP($D21,BS연결,MATCH(F$1,BS연결H,0),0)/100,"") | G21: =IFERROR(VLOOKUP($D21,BS연결,MATCH(G$1,BS연결H,0),0)/100,"") | H21: =IFERROR(VLOOKUP($D21,BS연결,MATCH(H$1,BS연결H,0),0)/100,"") | I21: =IFERROR(VLOOKUP($D21,BS연결,MATCH(I$1,BS연결H,0),0)/100,"") | J21: =IFERROR(VLOOKUP($D21,BS연결,MATCH(J$1,BS연결H,0),0)/100,"") | K21: =IFERROR(VLOOKUP($D21,BS연결,MATCH(K$1,BS연결H,0),0)/100,"") | L21: =IFERROR(VLOOKUP($D21,BS연결,MATCH(L$1,BS연결H,0),0)/100,"") | ... AB21: =IFERROR(VLOOKUP($D21,BS연결,MATCH(AB$1,BS연결H,0),0)/100,"") | AC21: =IFERROR(AB21+AC17-변수!AC29,"") | AD21: =IFERROR(AC21+AD17-변수!AD29,"") | AE21: =AD21 | AF21: =IFERROR(AD21+AF17-변수!AF29,"") | AG21: =IFERROR(AF21+AG17-변수!AG29,"") | AH21: =IFERROR(AG21+AH17-변수!AH29,"") | AI21: =IFERROR(AH21+AI17-변수!AI29,"") | AJ21: =AI21 | AK21: =IFERROR(AI21+AK17-변수!AK29,"") | AL21: =IFERROR(AK21+AL17-변수!AL29,"") | AM21: =IFERROR(AL21+AM17-변수!AM29,"") | AN21: =IFERROR(AM21+AN17-변수!AN29,"") | AO21: =AN21
A22: 총차입금 | B22: 재무상태 | C22: 억원 | D22: 총차입금 | E22: =IFERROR(VLOOKUP($D22,BS연결,MATCH(E$1,BS연결H,0),0)/100,"") | F22: =IFERROR(VLOOKUP($D22,BS연결,MATCH(F$1,BS연결H,0),0)/100,"") | G22: =IFERROR(VLOOKUP($D22,BS연결,MATCH(G$1,BS연결H,0),0)/100,"") | H22: =IFERROR(VLOOKUP($D22,BS연결,MATCH(H$1,BS연결H,0),0)/100,"") | I22: =IFERROR(VLOOKUP($D22,BS연결,MATCH(I$1,BS연결H,0),0)/100,"") | J22: =IFERROR(VLOOKUP($D22,BS연결,MATCH(J$1,BS연결H,0),0)/100,"") | K22: =IFERROR(VLOOKUP($D22,BS연결,MATCH(K$1,BS연결H,0),0)/100,"") | L22: =IFERROR(VLOOKUP($D22,BS연결,MATCH(L$1,BS연결H,0),0)/100,"") | ... AB22: =IFERROR(VLOOKUP($D22,BS연결,MATCH(AB$1,BS연결H,0),0)/100,"") | AC22: =IFERROR(AB22*(1+변수!AC30),"") | AD22: =IFERROR(AC22*(1+변수!AD30),"") | AE22: =AD22 | AF22: =IFERROR(AD22*(1+변수!AF30),"") | AG22: =IFERROR(AF22*(1+변수!AG30),"") | AH22: =IFERROR(AG22*(1+변수!AH30),"") | AI22: =IFERROR(AH22*(1+변수!AI30),"") | AJ22: =AI22 | AK22: =IFERROR(AI22*(1+변수!AK30),"") | AL22: =IFERROR(AK22*(1+변수!AL30),"") | AM22: =IFERROR(AL22*(1+변수!AM30),"") | AN22: =IFERROR(AM22*(1+변수!AN30),"") | AO22: =AN22
A23: 순차입금 | B23: 재무상태 | C23: 억원 | D23: 순차입금 | E23: =IFERROR(VLOOKUP($D23,BS연결,MATCH(E$1,BS연결H,0),0)/100,"") | F23: =IFERROR(VLOOKUP($D23,BS연결,MATCH(F$1,BS연결H,0),0)/100,"") | G23: =IFERROR(VLOOKUP($D23,BS연결,MATCH(G$1,BS연결H,0),0)/100,"") | H23: =IFERROR(VLOOKUP($D23,BS연결,MATCH(H$1,BS연결H,0),0)/100,"") | I23: =IFERROR(VLOOKUP($D23,BS연결,MATCH(I$1,BS연결H,0),0)/100,"") | J23: =IFERROR(VLOOKUP($D23,BS연결,MATCH(J$1,BS연결H,0),0)/100,"") | K23: =IFERROR(VLOOKUP($D23,BS연결,MATCH(K$1,BS연결H,0),0)/100,"") | L23: =IFERROR(VLOOKUP($D23,BS연결,MATCH(L$1,BS연결H,0),0)/100,"") | ... AB23: =IFERROR(VLOOKUP($D23,BS연결,MATCH(AB$1,BS연결H,0),0)/100,"") | AC23: =IFERROR(AB23*(1+변수!AC31),"") | AD23: =IFERROR(AC23*(1+변수!AD31),"") | AE23: =AD23 | AF23: =IFERROR(AD23*(1+변수!AF31),"") | AG23: =IFERROR(AF23*(1+변수!AG31),"") | AH23: =IFERROR(AG23*(1+변수!AH31),"") | AI23: =IFERROR(AH23*(1+변수!AI31),"") | AJ23: =AI23 | AK23: =IFERROR(AI23*(1+변수!AK31),"") | AL23: =IFERROR(AK23*(1+변수!AL31),"") | AM23: =IFERROR(AL23*(1+변수!AM31),"") | AN23: =IFERROR(AM23*(1+변수!AN31),"") | AO23: =AN23
A24: 이자발생자산 | B24: 재무상태 | C24: 억원 | D24: 이자발생자산 | E24: =IFERROR(VLOOKUP($D24,BS연결,MATCH(E$1,BS연결H,0),0)/100,"") | F24: =IFERROR(VLOOKUP($D24,BS연결,MATCH(F$1,BS연결H,0),0)/100,"") | G24: =IFERROR(VLOOKUP($D24,BS연결,MATCH(G$1,BS연결H,0),0)/100,"") | H24: =IFERROR(VLOOKUP($D24,BS연결,MATCH(H$1,BS연결H,0),0)/100,"") | I24: =IFERROR(VLOOKUP($D24,BS연결,MATCH(I$1,BS연결H,0),0)/100,"") | J24: =IFERROR(VLOOKUP($D24,BS연결,MATCH(J$1,BS연결H,0),0)/100,"") | K24: =IFERROR(VLOOKUP($D24,BS연결,MATCH(K$1,BS연결H,0),0)/100,"") | L24: =IFERROR(VLOOKUP($D24,BS연결,MATCH(L$1,BS연결H,0),0)/100,"") | ... AB24: =IFERROR(VLOOKUP($D24,BS연결,MATCH(AB$1,BS연결H,0),0)/100,"") | AC24: =IFERROR(AB24*(1+변수!AC32),"") | AD24: =IFERROR(AC24*(1+변수!AD32),"") | AE24: =AD24 | AF24: =IFERROR(AD24*(1+변수!AF32),"") | AG24: =IFERROR(AF24*(1+변수!AG32),"") | AH24: =IFERROR(AG24*(1+변수!AH32),"") | AI24: =IFERROR(AH24*(1+변수!AI32),"") | AJ24: =AI24 | AK24: =IFERROR(AI24*(1+변수!AK32),"") | AL24: =IFERROR(AK24*(1+변수!AL32),"") | AM24: =IFERROR(AL24*(1+변수!AM32),"") | AN24: =IFERROR(AM24*(1+변수!AN32),"") | AO24: =AN24
A25: 현금및현금성자산 | B25: 재무상태 | C25: 억원 | D25: 현금및현금성자산 | E25: =IFERROR(VLOOKUP($D25,BS연결,MATCH(E$1,BS연결H,0),0)/100,"") | F25: =IFERROR(VLOOKUP($D25,BS연결,MATCH(F$1,BS연결H,0),0)/100,"") | G25: =IFERROR(VLOOKUP($D25,BS연결,MATCH(G$1,BS연결H,0),0)/100,"") | H25: =IFERROR(VLOOKUP($D25,BS연결,MATCH(H$1,BS연결H,0),0)/100,"") | I25: =IFERROR(VLOOKUP($D25,BS연결,MATCH(I$1,BS연결H,0),0)/100,"") | J25: =IFERROR(VLOOKUP($D25,BS연결,MATCH(J$1,BS연결H,0),0)/100,"") | K25: =IFERROR(VLOOKUP($D25,BS연결,MATCH(K$1,BS연결H,0),0)/100,"") | L25: =IFERROR(VLOOKUP($D25,BS연결,MATCH(L$1,BS연결H,0),0)/100,"") | ... AB25: =IFERROR(VLOOKUP($D25,BS연결,MATCH(AB$1,BS연결H,0),0)/100,"") | AE25: =AD25 | AJ25: =AI25 | AO25: =AN25
A26: CAPEX | B26: 현금흐름 | C26: 억원 | D26: CAPEX | E26: =IFERROR(VLOOKUP($D26,BS연결,MATCH(E$1,BS연결H,0),0)/100,"") | G26: =IFERROR(VLOOKUP($D26,BS연결,MATCH(G$1,BS연결H,0),0)/100,"") | H26: =IFERROR(VLOOKUP($D26,BS연결,MATCH(H$1,BS연결H,0),0)/100,"") | I26: =IFERROR(VLOOKUP($D26,BS연결,MATCH(I$1,BS연결H,0),0)/100,"") | J26: =IFERROR(VLOOKUP($D26,BS연결,MATCH(J$1,BS연결H,0),0)/100,"") | K26: =IFERROR(VLOOKUP($D26,BS연결,MATCH(K$1,BS연결H,0),0)/100,"") | L26: =IFERROR(VLOOKUP($D26,BS연결,MATCH(L$1,BS연결H,0),0)/100,"") | M26: =IFERROR(VLOOKUP($D26,BS연결,MATCH(M$1,BS연결H,0),0)/100,"") | N26: =IFERROR(VLOOKUP($D26,BS연결,MATCH(N$1,BS연결H,0),0)/100,"") | ... AB26: =IFERROR(VLOOKUP($D26,BS연결,MATCH(AB$1,BS연결H,0),0)/100,"") | AC26: =IFERROR(X26*(1+변수!AC34),"") | AD26: =IFERROR(Y26*(1+변수!AD34),"") | AE26: =SUM(AA26:AD26) | AF26: =IFERROR(AA26*(1+변수!AF34),"") | AG26: =IFERROR(AB26*(1+변수!AG34),"") | AH26: =IFERROR(AC26*(1+변수!AH34),"") | AI26: =IFERROR(AD26*(1+변수!AI34),"") | AJ26: =SUM(AF26:AI26) | AK26: =IFERROR(AF26*(1+변수!AK34),"") | AL26: =IFERROR(AG26*(1+변수!AL34),"") | AM26: =IFERROR(AH26*(1+변수!AM34),"") | AN26: =IFERROR(AI26*(1+변수!AN34),"") | AO26: =SUM(AK26:AN26)
A27: 영업활동현금흐름 | B27: 현금흐름 | C27: 억원 | D27: 영업활동으로인한현금흐름 | E27: =IFERROR(VLOOKUP($D27,BS연결,MATCH(E$1,BS연결H,0),0)/100,"") | G27: =IFERROR(VLOOKUP($D27,BS연결,MATCH(G$1,BS연결H,0),0)/100,"") | H27: =IFERROR(VLOOKUP($D27,BS연결,MATCH(H$1,BS연결H,0),0)/100,"") | I27: =IFERROR(VLOOKUP($D27,BS연결,MATCH(I$1,BS연결H,0),0)/100,"") | J27: =IFERROR(VLOOKUP($D27,BS연결,MATCH(J$1,BS연결H,0),0)/100,"") | K27: =IFERROR(VLOOKUP($D27,BS연결,MATCH(K$1,BS연결H,0),0)/100,"") | L27: =IFERROR(VLOOKUP($D27,BS연결,MATCH(L$1,BS연결H,0),0)/100,"") | M27: =IFERROR(VLOOKUP($D27,BS연결,MATCH(M$1,BS연결H,0),0)/100,"") | N27: =IFERROR(VLOOKUP($D27,BS연결,MATCH(N$1,BS연결H,0),0)/100,"") | ... AB27: =IFERROR(VLOOKUP($D27,BS연결,MATCH(AB$1,BS연결H,0),0)/100,"") | AE27: =SUM(AA27:AD27) | AJ27: =SUM(AF27:AI27) | AO27: =SUM(AK27:AN27)
A28: 주식수 | B28: 주당 | C28: 백만주 | D28: 유통주식수 | E28: 8.923 | F28: =E28 | G28: 8.927 | H28: 8.949 | I28: 8.952 | J28: 8.952 | K28: =J28 | L28: 8.947 | M28: 8.949 | N28: 10.504 | O28: 10.512 | P28: =O28 | Q28: 10.513 | R28: 10.448 | S28: 10.428 | T28: 10.381 | U28: =T28 | V28: 10.333 | W28: 10.3 | X28: 10.307 | Y28: 10.202 | Z28: =Y28 | AA28: 10.214 | AB28: 10.221 | AC28: =IFERROR(AB28*(1+변수!AC36),"") | AD28: =IFERROR(AC28*(1+변수!AD36),"") | AE28: =AD28 | AF28: =IFERROR(AD28*(1+변수!AF36),"") | AG28: =IFERROR(AF28*(1+변수!AG36),"") | AH28: =IFERROR(AG28*(1+변수!AH36),"") | AI28: =IFERROR(AH28*(1+변수!AI36),"") | AJ28: =AI28 | AK28: =IFERROR(AI28*(1+변수!AK36),"") | AL28: =IFERROR(AK28*(1+변수!AL36),"") | AM28: =IFERROR(AL28*(1+변수!AM36),"") | AN28: =IFERROR(AM28*(1+변수!AN36),"") | AO28: =AN28
A29: EPS | B29: 주당 | C29: 원 | D29: EPS | E29: =IFERROR(E17*100/E28,"") | G29: =IFERROR(G17*100/G28,"") | H29: =IFERROR(H17*100/H28,"") | I29: =IFERROR(I17*100/I28,"") | J29: =IFERROR(J17*100/J28,"") | K29: =SUM(G29:J29) | L29: =IFERROR(L17*100/L28,"") | M29: =IFERROR(M17*100/M28,"") | N29: =IFERROR(N17*100/N28,"") | O29: =IFERROR(O17*100/O28,"") | P29: =SUM(L29:O29) | Q29: =IFERROR(Q17*100/Q28,"") | R29: =IFERROR(R17*100/R28,"") | S29: =IFERROR(S17*100/S28,"") | T29: =IFERROR(T17*100/T28,"") | U29: =SUM(Q29:T29) | V29: =IFERROR(V17*100/V28,"") | W29: =IFERROR(W17*100/W28,"") | X29: =IFERROR(X17*100/X28,"") | Y29: =IFERROR(Y17*100/Y28,"") | Z29: =SUM(V29:Y29) | AA29: =IFERROR(AA17*100/AA28,"") | AB29: =IFERROR(AB17*100/AB28,"") | AC29: =IFERROR(AC17*100/AC28,"") | AD29: =IFERROR(AD17*100/AD28,"") | AE29: =SUM(AA29:AD29) | AF29: =IFERROR(AF17*100/AF28,"") | AG29: =IFERROR(AG17*100/AG28,"") | AH29: =IFERROR(AH17*100/AH28,"") | AI29: =IFERROR(AI17*100/AI28,"") | AJ29: =SUM(AF29:AI29) | AK29: =IFERROR(AK17*100/AK28,"") | AL29: =IFERROR(AL17*100/AL28,"") | AM29: =IFERROR(AM17*100/AM28,"") | AN29: =IFERROR(AN17*100/AN28,"") | AO29: =SUM(AK29:AN29)
A30: BPS | B30: 주당 | C30: 원 | D30: BPS | E30: =IFERROR(E21*100/E28,"") | F30: =E30 | G30: =IFERROR(G21*100/G28,"") | H30: =IFERROR(H21*100/H28,"") | I30: =IFERROR(I21*100/I28,"") | J30: =IFERROR(J21*100/J28,"") | K30: =J30 | L30: =IFERROR(L21*100/L28,"") | M30: =IFERROR(M21*100/M28,"") | N30: =IFERROR(N21*100/N28,"") | O30: =IFERROR(O21*100/O28,"") | P30: =O30 | Q30: =IFERROR(Q21*100/Q28,"") | R30: =IFERROR(R21*100/R28,"") | S30: =IFERROR(S21*100/S28,"") | T30: =IFERROR(T21*100/T28,"") | U30: =T30 | V30: =IFERROR(V21*100/V28,"") | W30: =IFERROR(W21*100/W28,"") | X30: =IFERROR(X21*100/X28,"") | Y30: =IFERROR(Y21*100/Y28,"") | Z30: =Y30 | AA30: =IFERROR(AA21*100/AA28,"") | AB30: =IFERROR(AB21*100/AB28,"") | AC30: =IFERROR(AC21*100/AC28,"") | AD30: =IFERROR(AD21*100/AD28,"") | AE30: =AD30 | AF30: =IFERROR(AF21*100/AF28,"") | AG30: =IFERROR(AG21*100/AG28,"") | AH30: =IFERROR(AH21*100/AH28,"") | AI30: =IFERROR(AI21*100/AI28,"") | AJ30: =AI30 | AK30: =IFERROR(AK21*100/AK28,"") | AL30: =IFERROR(AL21*100/AL28,"") | AM30: =IFERROR(AM21*100/AM28,"") | AN30: =IFERROR(AN21*100/AN28,"") | AO30: =AN30
A31: DPS | B31: 주당 | C31: 원 | D31: DPS(보통주) | E31: 100 | F31: 100 | J31: 100 | K31: =SUM(G31:J31) | O31: 100 | P31: =SUM(L31:O31) | T31: 100 | U31: =SUM(Q31:T31) | Y31: 200 | Z31: =SUM(V31:Y31) | AD31: =변수!AD37 | AE31: =SUM(AA31:AD31) | AI31: =변수!AI37 | AJ31: =SUM(AF31:AI31) | AN31: =변수!AN37 | AO31: =SUM(AK31:AN31)
A32: PER | B32: 주당 | C32: 배 | D32: PER | F32: =E32 | I32: =IFERROR(변수!I18/(E29+G29+H29+I29),"") | J32: =IFERROR(변수!J18/(G29+H29+I29+J29),"") | K32: =J32 | L32: =IFERROR(변수!L18/(H29+I29+J29+L29),"") | M32: =IFERROR(변수!M18/(I29+J29+L29+M29),"") | N32: =IFERROR(변수!N18/(J29+L29+M29+N29),"") | O32: =IFERROR(변수!O18/(L29+M29+N29+O29),"") | P32: =O32 | Q32: =IFERROR(변수!Q18/(M29+N29+O29+Q29),"") | U32: =T32 | Y32: =IFERROR(변수!Y18/(V29+W29+X29+Y29),"") | Z32: =Y32 | AA32: =IFERROR(변수!AA18/(W29+X29+Y29+AA29),"") | AB32: =IFERROR(변수!AB18/(X29+Y29+AA29+AB29),"") | AC32: =IFERROR(변수!$D$40/(Y29+AA29+AB29+AC29),"") | AD32: =IFERROR(변수!$D$40/(AA29+AB29+AC29+AD29),"") | AE32: =AD32 | AF32: =IFERROR(변수!$D$40/(AB29+AC29+AD29+AF29),"") | AG32: =IFERROR(변수!$D$40/(AC29+AD29+AF29+AG29),"") | AH32: =IFERROR(변수!$D$40/(AD29+AF29+AG29+AH29),"") | AI32: =IFERROR(변수!$D$40/(AF29+AG29+AH29+AI29),"") | AJ32: =AI32 | AK32: =IFERROR(변수!$D$40/(AG29+AH29+AI29+AK29),"") | AL32: =IFERROR(변수!$D$40/(AH29+AI29+AK29+AL29),"") | AM32: =IFERROR(변수!$D$40/(AI29+AK29+AL29+AM29),"") | AN32: =IFERROR(변수!$D$40/(AK29+AL29+AM29+AN29),"") | AO32: =AN32
A33: PBR | B33: 주당 | C33: 배 | D33: PBR | E33: =IFERROR(변수!E18/E30,"") | F33: =E33 | G33: =IFERROR(변수!G18/G30,"") | H33: =IFERROR(변수!H18/H30,"") | I33: =IFERROR(변수!I18/I30,"") | J33: =IFERROR(변수!J18/J30,"") | K33: =J33 | L33: =IFERROR(변수!L18/L30,"") | M33: =IFERROR(변수!M18/M30,"") | N33: =IFERROR(변수!N18/N30,"") | O33: =IFERROR(변수!O18/O30,"") | P33: =O33 | Q33: =IFERROR(변수!Q18/Q30,"") | R33: =IFERROR(변수!R18/R30,"") | S33: =IFERROR(변수!S18/S30,"") | T33: =IFERROR(변수!T18/T30,"") | U33: =T33 | V33: =IFERROR(변수!V18/V30,"") | W33: =IFERROR(변수!W18/W30,"") | X33: =IFERROR(변수!X18/X30,"") | Y33: =IFERROR(변수!Y18/Y30,"") | Z33: =Y33 | AA33: =IFERROR(변수!AA18/AA30,"") | AB33: =IFERROR(변수!AB18/AB30,"") | AC33: =IFERROR(변수!$D$40/AC30,"") | AD33: =IFERROR(변수!$D$40/AD30,"") | AE33: =AD33 | AF33: =IFERROR(변수!$D$40/AF30,"") | AG33: =IFERROR(변수!$D$40/AG30,"") | AH33: =IFERROR(변수!$D$40/AH30,"") | AI33: =IFERROR(변수!$D$40/AI30,"") | AJ33: =AI33 | AK33: =IFERROR(변수!$D$40/AK30,"") | AL33: =IFERROR(변수!$D$40/AL30,"") | AM33: =IFERROR(변수!$D$40/AM30,"") | AN33: =IFERROR(변수!$D$40/AN30,"") | AO33: =AN33
A34: 매출전사 | B34: 사업부 | C34: 억원 | D34: 매출 전사(부문 미분리) | E34: 482.93 | G34: 430.25 | H34: 569.84 | I34: 570.37 | J34: 824.19 | K34: =SUM(G34:J34) | L34: 643.93 | M34: 875.95 | N34: 667.75 | O34: 862.8 | P34: =SUM(L34:O34) | Q34: 466.98 | R34: 716.99 | S34: 623.61 | T34: 770.11 | U34: =SUM(Q34:T34) | V34: 433.5 | W34: 747.36 | X34: 772.26 | Y34: 1243.15 | Z34: =SUM(V34:Y34) | AA34: 647.24 | AB34: 972.46 | AC34: =IFERROR(AC5,"") | AD34: =IFERROR(AD5,"") | AE34: =SUM(AA34:AD34) | AF34: =IFERROR(AF5,"") | AG34: =IFERROR(AG5,"") | AH34: =IFERROR(AH5,"") | AI34: =IFERROR(AI5,"") | AJ34: =SUM(AF34:AI34) | AK34: =IFERROR(AK5,"") | AL34: =IFERROR(AL5,"") | AM34: =IFERROR(AM5,"") | AN34: =IFERROR(AN5,"") | AO34: =SUM(AK34:AN34)
A35: OP전사 | B35: 사업부 | C35: 억원 | D35: OP 전사(부문 미분리) | E35: 45.09 | G35: 15.6 | H35: 41.49 | I35: 10.24 | J35: 86.1 | K35: =SUM(G35:J35) | L35: 7.77 | M35: 77.71 | N35: -15.78 | O35: 37.55 | P35: =SUM(L35:O35) | Q35: -93.46 | R35: 9.1 | S35: -57.35 | T35: -52.73 | U35: =SUM(Q35:T35) | V35: -120.39 | W35: 17.63 | X35: 23.73 | Y35: 198.56 | Z35: =SUM(V35:Y35) | AA35: 5.93 | AB35: 71.36 | AC35: =IFERROR(AC9,"") | AD35: =IFERROR(AD9,"") | AE35: =SUM(AA35:AD35) | AF35: =IFERROR(AF9,"") | AG35: =IFERROR(AG9,"") | AH35: =IFERROR(AH9,"") | AI35: =IFERROR(AI9,"") | AJ35: =SUM(AF35:AI35) | AK35: =IFERROR(AK9,"") | AL35: =IFERROR(AL9,"") | AM35: =IFERROR(AM9,"") | AN35: =IFERROR(AN9,"") | AO35: =SUM(AK35:AN35)
B36: 비율(참고)
A37: NPM | C37: % | D37: 지배주주순이익 / 매출액 | E37: =IFERROR(E17/E5,"") | F37: =IFERROR(F17/F5,"") | G37: =IFERROR(G17/G5,"") | H37: =IFERROR(H17/H5,"") | I37: =IFERROR(I17/I5,"") | J37: =IFERROR(J17/J5,"") | K37: =IFERROR(K17/K5,"") | L37: =IFERROR(L17/L5,"") | ... AO37: =IFERROR(AO17/AO5,"")
A38: 매출원가율 | C38: % | D38: 매출원가 / 매출액 | E38: =IFERROR(E6/E5,"") | F38: =IFERROR(F6/F5,"") | G38: =IFERROR(G6/G5,"") | H38: =IFERROR(H6/H5,"") | I38: =IFERROR(I6/I5,"") | J38: =IFERROR(J6/J5,"") | K38: =IFERROR(K6/K5,"") | L38: =IFERROR(L6/L5,"") | ... AO38: =IFERROR(AO6/AO5,"")
A39: 판관비율 | C39: % | D39: 판관비 / 매출액 | E39: =IFERROR(E8/E5,"") | F39: =IFERROR(F8/F5,"") | G39: =IFERROR(G8/G5,"") | H39: =IFERROR(H8/H5,"") | I39: =IFERROR(I8/I5,"") | J39: =IFERROR(J8/J5,"") | K39: =IFERROR(K8/K5,"") | L39: =IFERROR(L8/L5,"") | ... AO39: =IFERROR(AO8/AO5,"")

Sheet 분기
C1: 이름: 분기H — subQ 를 이름으로 VLOOKUP(억원) | E1: 4Q21 | F1: 1Q22 | G1: 2Q22 | H1: 3Q22 | I1: 4Q22 | J1: 1Q23 | K1: 2Q23 | L1: 3Q23 | M1: 4Q23 | N1: 1Q24 | O1: 2Q24 | P1: 3Q24 | Q1: 4Q24 | R1: 1Q25 | S1: 2Q25 | T1: 3Q25 | U1: 4Q25 | V1: 1Q26 | W1: 2Q26 | X1: 3Q26 | Y1: 4Q26 | Z1: 1Q27 | AA1: 2Q27 | AB1: 3Q27 | AC1: 4Q27 | AD1: 1Q28 | AE1: 2Q28 | AF1: 3Q28 | AG1: 4Q28
C2: 종가: | D2: =변수!D40
C3: 기준일: | D3: 20261008 | E3: 1 | F3: 2 | G3: 3 | H3: 4 | I3: 5 | J3: 6 | K3: 7 | L3: 8 | M3: 9 | N3: 10 | O3: 11 | P3: 12 | Q3: 13 | R3: 14 | S3: 15 | T3: 16 | U3: 17 | V3: 18 | W3: 19 | X3: 20 | Y3: 21 | Z3: 22 | AA3: 23 | AB3: 24 | AC3: 25 | AD3: 26 | AE3: 27 | AF3: 28 | AG3: 29
E4: 2021.12 | F4: 2022.03 | G4: 2022.06 | H4: 2022.09 | I4: 2022.12 | J4: 2023.03 | K4: 2023.06 | L4: 2023.09 | M4: 2023.12 | N4: 2024.03 | O4: 2024.06 | P4: 2024.09 | Q4: 2024.12 | R4: 2025.03 | S4: 2025.06 | T4: 2025.09 | U4: 2025.12 | V4: 2026.03 | W4: 2026.06 | X4: 2026.09 | Y4: 2026.12 | Z4: 2027.03 | AA4: 2027.06 | AB4: 2027.09 | AC4: 2027.12 | AD4: 2028.03 | AE4: 2028.06 | AF4: 2028.09 | AG4: 2028.12
A5: 매출액 | D5: 매출액 | E5: =IFERROR(VLOOKUP($A5,subQ,MATCH(E$1,SUBQH,0),0),"") | F5: =IFERROR(VLOOKUP($A5,subQ,MATCH(F$1,SUBQH,0),0),"") | G5: =IFERROR(VLOOKUP($A5,subQ,MATCH(G$1,SUBQH,0),0),"") | H5: =IFERROR(VLOOKUP($A5,subQ,MATCH(H$1,SUBQH,0),0),"") | I5: =IFERROR(VLOOKUP($A5,subQ,MATCH(I$1,SUBQH,0),0),"") | J5: =IFERROR(VLOOKUP($A5,subQ,MATCH(J$1,SUBQH,0),0),"") | K5: =IFERROR(VLOOKUP($A5,subQ,MATCH(K$1,SUBQH,0),0),"") | L5: =IFERROR(VLOOKUP($A5,subQ,MATCH(L$1,SUBQH,0),0),"") | ... AG5: =IFERROR(VLOOKUP($A5,subQ,MATCH(AG$1,SUBQH,0),0),"")
A6: 매출원가 | D6: 매출원가 | E6: =IFERROR(VLOOKUP($A6,subQ,MATCH(E$1,SUBQH,0),0),"") | F6: =IFERROR(VLOOKUP($A6,subQ,MATCH(F$1,SUBQH,0),0),"") | G6: =IFERROR(VLOOKUP($A6,subQ,MATCH(G$1,SUBQH,0),0),"") | H6: =IFERROR(VLOOKUP($A6,subQ,MATCH(H$1,SUBQH,0),0),"") | I6: =IFERROR(VLOOKUP($A6,subQ,MATCH(I$1,SUBQH,0),0),"") | J6: =IFERROR(VLOOKUP($A6,subQ,MATCH(J$1,SUBQH,0),0),"") | K6: =IFERROR(VLOOKUP($A6,subQ,MATCH(K$1,SUBQH,0),0),"") | L6: =IFERROR(VLOOKUP($A6,subQ,MATCH(L$1,SUBQH,0),0),"") | ... AG6: =IFERROR(VLOOKUP($A6,subQ,MATCH(AG$1,SUBQH,0),0),"")
A7: 매출총이익 | D7: 매출총이익 | E7: =IFERROR(VLOOKUP($A7,subQ,MATCH(E$1,SUBQH,0),0),"") | F7: =IFERROR(VLOOKUP($A7,subQ,MATCH(F$1,SUBQH,0),0),"") | G7: =IFERROR(VLOOKUP($A7,subQ,MATCH(G$1,SUBQH,0),0),"") | H7: =IFERROR(VLOOKUP($A7,subQ,MATCH(H$1,SUBQH,0),0),"") | I7: =IFERROR(VLOOKUP($A7,subQ,MATCH(I$1,SUBQH,0),0),"") | J7: =IFERROR(VLOOKUP($A7,subQ,MATCH(J$1,SUBQH,0),0),"") | K7: =IFERROR(VLOOKUP($A7,subQ,MATCH(K$1,SUBQH,0),0),"") | L7: =IFERROR(VLOOKUP($A7,subQ,MATCH(L$1,SUBQH,0),0),"") | ... AG7: =IFERROR(VLOOKUP($A7,subQ,MATCH(AG$1,SUBQH,0),0),"")
A8: 판관비 | D8: 판매비와관리비 | E8: =IFERROR(VLOOKUP($A8,subQ,MATCH(E$1,SUBQH,0),0),"") | F8: =IFERROR(VLOOKUP($A8,subQ,MATCH(F$1,SUBQH,0),0),"") | G8: =IFERROR(VLOOKUP($A8,subQ,MATCH(G$1,SUBQH,0),0),"") | H8: =IFERROR(VLOOKUP($A8,subQ,MATCH(H$1,SUBQH,0),0),"") | I8: =IFERROR(VLOOKUP($A8,subQ,MATCH(I$1,SUBQH,0),0),"") | J8: =IFERROR(VLOOKUP($A8,subQ,MATCH(J$1,SUBQH,0),0),"") | K8: =IFERROR(VLOOKUP($A8,subQ,MATCH(K$1,SUBQH,0),0),"") | L8: =IFERROR(VLOOKUP($A8,subQ,MATCH(L$1,SUBQH,0),0),"") | ... AG8: =IFERROR(VLOOKUP($A8,subQ,MATCH(AG$1,SUBQH,0),0),"")
A9: 영업이익 | D9: 영업이익 | E9: =IFERROR(VLOOKUP($A9,subQ,MATCH(E$1,SUBQH,0),0),"") | F9: =IFERROR(VLOOKUP($A9,subQ,MATCH(F$1,SUBQH,0),0),"") | G9: =IFERROR(VLOOKUP($A9,subQ,MATCH(G$1,SUBQH,0),0),"") | H9: =IFERROR(VLOOKUP($A9,subQ,MATCH(H$1,SUBQH,0),0),"") | I9: =IFERROR(VLOOKUP($A9,subQ,MATCH(I$1,SUBQH,0),0),"") | J9: =IFERROR(VLOOKUP($A9,subQ,MATCH(J$1,SUBQH,0),0),"") | K9: =IFERROR(VLOOKUP($A9,subQ,MATCH(K$1,SUBQH,0),0),"") | L9: =IFERROR(VLOOKUP($A9,subQ,MATCH(L$1,SUBQH,0),0),"") | ... AG9: =IFERROR(VLOOKUP($A9,subQ,MATCH(AG$1,SUBQH,0),0),"")
A10: OPM | D10: 영업이익률 | E10: =IFERROR(VLOOKUP($A10,subQ,MATCH(E$1,SUBQH,0),0),"") | F10: =IFERROR(VLOOKUP($A10,subQ,MATCH(F$1,SUBQH,0),0),"") | G10: =IFERROR(VLOOKUP($A10,subQ,MATCH(G$1,SUBQH,0),0),"") | H10: =IFERROR(VLOOKUP($A10,subQ,MATCH(H$1,SUBQH,0),0),"") | I10: =IFERROR(VLOOKUP($A10,subQ,MATCH(I$1,SUBQH,0),0),"") | J10: =IFERROR(VLOOKUP($A10,subQ,MATCH(J$1,SUBQH,0),0),"") | K10: =IFERROR(VLOOKUP($A10,subQ,MATCH(K$1,SUBQH,0),0),"") | L10: =IFERROR(VLOOKUP($A10,subQ,MATCH(L$1,SUBQH,0),0),"") | ... AG10: =IFERROR(VLOOKUP($A10,subQ,MATCH(AG$1,SUBQH,0),0),"")
A11: 금융손익 | D11: 금융손익(이자·환 포함) | E11: =IFERROR(VLOOKUP($A11,subQ,MATCH(E$1,SUBQH,0),0),"") | F11: =IFERROR(VLOOKUP($A11,subQ,MATCH(F$1,SUBQH,0),0),"") | G11: =IFERROR(VLOOKUP($A11,subQ,MATCH(G$1,SUBQH,0),0),"") | H11: =IFERROR(VLOOKUP($A11,subQ,MATCH(H$1,SUBQH,0),0),"") | I11: =IFERROR(VLOOKUP($A11,subQ,MATCH(I$1,SUBQH,0),0),"") | J11: =IFERROR(VLOOKUP($A11,subQ,MATCH(J$1,SUBQH,0),0),"") | K11: =IFERROR(VLOOKUP($A11,subQ,MATCH(K$1,SUBQH,0),0),"") | L11: =IFERROR(VLOOKUP($A11,subQ,MATCH(L$1,SUBQH,0),0),"") | ... AG11: =IFERROR(VLOOKUP($A11,subQ,MATCH(AG$1,SUBQH,0),0),"")
A12: 이자손익 | D12: 이자손익(이자수익 − 이자비용) | E12: =IFERROR(VLOOKUP($A12,subQ,MATCH(E$1,SUBQH,0),0),"") | F12: =IFERROR(VLOOKUP($A12,subQ,MATCH(F$1,SUBQH,0),0),"") | G12: =IFERROR(VLOOKUP($A12,subQ,MATCH(G$1,SUBQH,0),0),"") | H12: =IFERROR(VLOOKUP($A12,subQ,MATCH(H$1,SUBQH,0),0),"") | I12: =IFERROR(VLOOKUP($A12,subQ,MATCH(I$1,SUBQH,0),0),"") | J12: =IFERROR(VLOOKUP($A12,subQ,MATCH(J$1,SUBQH,0),0),"") | K12: =IFERROR(VLOOKUP($A12,subQ,MATCH(K$1,SUBQH,0),0),"") | L12: =IFERROR(VLOOKUP($A12,subQ,MATCH(L$1,SUBQH,0),0),"") | ... AG12: =IFERROR(VLOOKUP($A12,subQ,MATCH(AG$1,SUBQH,0),0),"")
A13: 기타영업외손익 | D13: 기타영업외손익 | E13: =IFERROR(VLOOKUP($A13,subQ,MATCH(E$1,SUBQH,0),0),"") | F13: =IFERROR(VLOOKUP($A13,subQ,MATCH(F$1,SUBQH,0),0),"") | G13: =IFERROR(VLOOKUP($A13,subQ,MATCH(G$1,SUBQH,0),0),"") | H13: =IFERROR(VLOOKUP($A13,subQ,MATCH(H$1,SUBQH,0),0),"") | I13: =IFERROR(VLOOKUP($A13,subQ,MATCH(I$1,SUBQH,0),0),"") | J13: =IFERROR(VLOOKUP($A13,subQ,MATCH(J$1,SUBQH,0),0),"") | K13: =IFERROR(VLOOKUP($A13,subQ,MATCH(K$1,SUBQH,0),0),"") | L13: =IFERROR(VLOOKUP($A13,subQ,MATCH(L$1,SUBQH,0),0),"") | ... AG13: =IFERROR(VLOOKUP($A13,subQ,MATCH(AG$1,SUBQH,0),0),"")
A14: 세전이익 | D14: 법인세비용차감전이익 | E14: =IFERROR(VLOOKUP($A14,subQ,MATCH(E$1,SUBQH,0),0),"") | F14: =IFERROR(VLOOKUP($A14,subQ,MATCH(F$1,SUBQH,0),0),"") | G14: =IFERROR(VLOOKUP($A14,subQ,MATCH(G$1,SUBQH,0),0),"") | H14: =IFERROR(VLOOKUP($A14,subQ,MATCH(H$1,SUBQH,0),0),"") | I14: =IFERROR(VLOOKUP($A14,subQ,MATCH(I$1,SUBQH,0),0),"") | J14: =IFERROR(VLOOKUP($A14,subQ,MATCH(J$1,SUBQH,0),0),"") | K14: =IFERROR(VLOOKUP($A14,subQ,MATCH(K$1,SUBQH,0),0),"") | L14: =IFERROR(VLOOKUP($A14,subQ,MATCH(L$1,SUBQH,0),0),"") | ... AG14: =IFERROR(VLOOKUP($A14,subQ,MATCH(AG$1,SUBQH,0),0),"")
A15: 법인세비용 | D15: 법인세비용 | E15: =IFERROR(VLOOKUP($A15,subQ,MATCH(E$1,SUBQH,0),0),"") | F15: =IFERROR(VLOOKUP($A15,subQ,MATCH(F$1,SUBQH,0),0),"") | G15: =IFERROR(VLOOKUP($A15,subQ,MATCH(G$1,SUBQH,0),0),"") | H15: =IFERROR(VLOOKUP($A15,subQ,MATCH(H$1,SUBQH,0),0),"") | I15: =IFERROR(VLOOKUP($A15,subQ,MATCH(I$1,SUBQH,0),0),"") | J15: =IFERROR(VLOOKUP($A15,subQ,MATCH(J$1,SUBQH,0),0),"") | K15: =IFERROR(VLOOKUP($A15,subQ,MATCH(K$1,SUBQH,0),0),"") | L15: =IFERROR(VLOOKUP($A15,subQ,MATCH(L$1,SUBQH,0),0),"") | ... AG15: =IFERROR(VLOOKUP($A15,subQ,MATCH(AG$1,SUBQH,0),0),"")
A16: 당기순이익 | D16: 당기순이익 | E16: =IFERROR(VLOOKUP($A16,subQ,MATCH(E$1,SUBQH,0),0),"") | F16: =IFERROR(VLOOKUP($A16,subQ,MATCH(F$1,SUBQH,0),0),"") | G16: =IFERROR(VLOOKUP($A16,subQ,MATCH(G$1,SUBQH,0),0),"") | H16: =IFERROR(VLOOKUP($A16,subQ,MATCH(H$1,SUBQH,0),0),"") | I16: =IFERROR(VLOOKUP($A16,subQ,MATCH(I$1,SUBQH,0),0),"") | J16: =IFERROR(VLOOKUP($A16,subQ,MATCH(J$1,SUBQH,0),0),"") | K16: =IFERROR(VLOOKUP($A16,subQ,MATCH(K$1,SUBQH,0),0),"") | L16: =IFERROR(VLOOKUP($A16,subQ,MATCH(L$1,SUBQH,0),0),"") | ... AG16: =IFERROR(VLOOKUP($A16,subQ,MATCH(AG$1,SUBQH,0),0),"")
... A36: NPM | D36: NPM | E36: =IFERROR(VLOOKUP($A36,subQ,MATCH(E$1,SUBQH,0),0),"") | F36: =IFERROR(VLOOKUP($A36,subQ,MATCH(F$1,SUBQH,0),0),"") | G36: =IFERROR(VLOOKUP($A36,subQ,MATCH(G$1,SUBQH,0),0),"") | H36: =IFERROR(VLOOKUP($A36,subQ,MATCH(H$1,SUBQH,0),0),"") | I36: =IFERROR(VLOOKUP($A36,subQ,MATCH(I$1,SUBQH,0),0),"") | J36: =IFERROR(VLOOKUP($A36,subQ,MATCH(J$1,SUBQH,0),0),"") | K36: =IFERROR(VLOOKUP($A36,subQ,MATCH(K$1,SUBQH,0),0),"") | L36: =IFERROR(VLOOKUP($A36,subQ,MATCH(L$1,SUBQH,0),0),"") | ... AG36: =IFERROR(VLOOKUP($A36,subQ,MATCH(AG$1,SUBQH,0),0),"")
A37: 매출액 YoY | D37: 매출액 YoY | I37: =IFERROR(I5/E5-1,"") | J37: =IFERROR(J5/F5-1,"") | K37: =IFERROR(K5/G5-1,"") | L37: =IFERROR(L5/H5-1,"") | M37: =IFERROR(M5/I5-1,"") | N37: =IFERROR(N5/J5-1,"") | O37: =IFERROR(O5/K5-1,"") | P37: =IFERROR(P5/L5-1,"") | ... AG37: =IFERROR(AG5/AC5-1,"")
A38: 영업이익 YoY | D38: 영업이익 YoY | I38: =IFERROR(I9/E9-1,"") | J38: =IFERROR(J9/F9-1,"") | K38: =IFERROR(K9/G9-1,"") | L38: =IFERROR(L9/H9-1,"") | M38: =IFERROR(M9/I9-1,"") | N38: =IFERROR(N9/J9-1,"") | O38: =IFERROR(O9/K9-1,"") | P38: =IFERROR(P9/L9-1,"") | ... AG38: =IFERROR(AG9/AC9-1,"")
A39: 지배주주순이익 YoY | D39: 지배주주순이익 YoY | I39: =IFERROR(I17/E17-1,"") | J39: =IFERROR(J17/F17-1,"") | K39: =IFERROR(K17/G17-1,"") | L39: =IFERROR(L17/H17-1,"") | M39: =IFERROR(M17/I17-1,"") | N39: =IFERROR(N17/J17-1,"") | O39: =IFERROR(O17/K17-1,"") | P39: =IFERROR(P17/L17-1,"") | ... AG39: =IFERROR(AG17/AC17-1,"")

Sheet 연간예상
C1: 이름: 연간예상H — subQ 를 이름으로 VLOOKUP(억원) | E1: 2021 | F1: 2022 | G1: 2023 | H1: 2024 | I1: 2025 | J1: 2026 | K1: 2027 | L1: 2028
C2: 종가: | D2: =변수!D40
C3: 기준일: | D3: 20261008 | E3: 1 | F3: 2 | G3: 3 | H3: 4 | I3: 5 | J3: 6 | K3: 7 | L3: 8
E4: 2021.12A | F4: 2022.12A | G4: 2023.12A | H4: 2024.12A | I4: 2025.12A | J4: 2026.12A | K4: 2027.12A | L4: 2028.12A
A5: 매출액 | D5: 매출액 | E5: =IFERROR(VLOOKUP($A5,subQ,MATCH(E$1,SUBQH,0),0),"") | F5: =IFERROR(VLOOKUP($A5,subQ,MATCH(F$1,SUBQH,0),0),"") | G5: =IFERROR(VLOOKUP($A5,subQ,MATCH(G$1,SUBQH,0),0),"") | H5: =IFERROR(VLOOKUP($A5,subQ,MATCH(H$1,SUBQH,0),0),"") | I5: =IFERROR(VLOOKUP($A5,subQ,MATCH(I$1,SUBQH,0),0),"") | J5: =IFERROR(VLOOKUP($A5,subQ,MATCH(J$1,SUBQH,0),0),"") | K5: =IFERROR(VLOOKUP($A5,subQ,MATCH(K$1,SUBQH,0),0),"") | L5: =IFERROR(VLOOKUP($A5,subQ,MATCH(L$1,SUBQH,0),0),"")
A6: 매출원가 | D6: 매출원가 | E6: =IFERROR(VLOOKUP($A6,subQ,MATCH(E$1,SUBQH,0),0),"") | F6: =IFERROR(VLOOKUP($A6,subQ,MATCH(F$1,SUBQH,0),0),"") | G6: =IFERROR(VLOOKUP($A6,subQ,MATCH(G$1,SUBQH,0),0),"") | H6: =IFERROR(VLOOKUP($A6,subQ,MATCH(H$1,SUBQH,0),0),"") | I6: =IFERROR(VLOOKUP($A6,subQ,MATCH(I$1,SUBQH,0),0),"") | J6: =IFERROR(VLOOKUP($A6,subQ,MATCH(J$1,SUBQH,0),0),"") | K6: =IFERROR(VLOOKUP($A6,subQ,MATCH(K$1,SUBQH,0),0),"") | L6: =IFERROR(VLOOKUP($A6,subQ,MATCH(L$1,SUBQH,0),0),"")
A7: 매출총이익 | D7: 매출총이익 | E7: =IFERROR(VLOOKUP($A7,subQ,MATCH(E$1,SUBQH,0),0),"") | F7: =IFERROR(VLOOKUP($A7,subQ,MATCH(F$1,SUBQH,0),0),"") | G7: =IFERROR(VLOOKUP($A7,subQ,MATCH(G$1,SUBQH,0),0),"") | H7: =IFERROR(VLOOKUP($A7,subQ,MATCH(H$1,SUBQH,0),0),"") | I7: =IFERROR(VLOOKUP($A7,subQ,MATCH(I$1,SUBQH,0),0),"") | J7: =IFERROR(VLOOKUP($A7,subQ,MATCH(J$1,SUBQH,0),0),"") | K7: =IFERROR(VLOOKUP($A7,subQ,MATCH(K$1,SUBQH,0),0),"") | L7: =IFERROR(VLOOKUP($A7,subQ,MATCH(L$1,SUBQH,0),0),"")
A8: 판관비 | D8: 판매비와관리비 | E8: =IFERROR(VLOOKUP($A8,subQ,MATCH(E$1,SUBQH,0),0),"") | F8: =IFERROR(VLOOKUP($A8,subQ,MATCH(F$1,SUBQH,0),0),"") | G8: =IFERROR(VLOOKUP($A8,subQ,MATCH(G$1,SUBQH,0),0),"") | H8: =IFERROR(VLOOKUP($A8,subQ,MATCH(H$1,SUBQH,0),0),"") | I8: =IFERROR(VLOOKUP($A8,subQ,MATCH(I$1,SUBQH,0),0),"") | J8: =IFERROR(VLOOKUP($A8,subQ,MATCH(J$1,SUBQH,0),0),"") | K8: =IFERROR(VLOOKUP($A8,subQ,MATCH(K$1,SUBQH,0),0),"") | L8: =IFERROR(VLOOKUP($A8,subQ,MATCH(L$1,SUBQH,0),0),"")
A9: 영업이익 | D9: 영업이익 | E9: =IFERROR(VLOOKUP($A9,subQ,MATCH(E$1,SUBQH,0),0),"") | F9: =IFERROR(VLOOKUP($A9,subQ,MATCH(F$1,SUBQH,0),0),"") | G9: =IFERROR(VLOOKUP($A9,subQ,MATCH(G$1,SUBQH,0),0),"") | H9: =IFERROR(VLOOKUP($A9,subQ,MATCH(H$1,SUBQH,0),0),"") | I9: =IFERROR(VLOOKUP($A9,subQ,MATCH(I$1,SUBQH,0),0),"") | J9: =IFERROR(VLOOKUP($A9,subQ,MATCH(J$1,SUBQH,0),0),"") | K9: =IFERROR(VLOOKUP($A9,subQ,MATCH(K$1,SUBQH,0),0),"") | L9: =IFERROR(VLOOKUP($A9,subQ,MATCH(L$1,SUBQH,0),0),"")
A10: OPM | D10: 영업이익률 | E10: =IFERROR(VLOOKUP($A10,subQ,MATCH(E$1,SUBQH,0),0),"") | F10: =IFERROR(VLOOKUP($A10,subQ,MATCH(F$1,SUBQH,0),0),"") | G10: =IFERROR(VLOOKUP($A10,subQ,MATCH(G$1,SUBQH,0),0),"") | H10: =IFERROR(VLOOKUP($A10,subQ,MATCH(H$1,SUBQH,0),0),"") | I10: =IFERROR(VLOOKUP($A10,subQ,MATCH(I$1,SUBQH,0),0),"") | J10: =IFERROR(VLOOKUP($A10,subQ,MATCH(J$1,SUBQH,0),0),"") | K10: =IFERROR(VLOOKUP($A10,subQ,MATCH(K$1,SUBQH,0),0),"") | L10: =IFERROR(VLOOKUP($A10,subQ,MATCH(L$1,SUBQH,0),0),"")
A11: 금융손익 | D11: 금융손익(이자·환 포함) | E11: =IFERROR(VLOOKUP($A11,subQ,MATCH(E$1,SUBQH,0),0),"") | F11: =IFERROR(VLOOKUP($A11,subQ,MATCH(F$1,SUBQH,0),0),"") | G11: =IFERROR(VLOOKUP($A11,subQ,MATCH(G$1,SUBQH,0),0),"") | H11: =IFERROR(VLOOKUP($A11,subQ,MATCH(H$1,SUBQH,0),0),"") | I11: =IFERROR(VLOOKUP($A11,subQ,MATCH(I$1,SUBQH,0),0),"") | J11: =IFERROR(VLOOKUP($A11,subQ,MATCH(J$1,SUBQH,0),0),"") | K11: =IFERROR(VLOOKUP($A11,subQ,MATCH(K$1,SUBQH,0),0),"") | L11: =IFERROR(VLOOKUP($A11,subQ,MATCH(L$1,SUBQH,0),0),"")
A12: 이자손익 | D12: 이자손익(이자수익 − 이자비용) | E12: =IFERROR(VLOOKUP($A12,subQ,MATCH(E$1,SUBQH,0),0),"") | F12: =IFERROR(VLOOKUP($A12,subQ,MATCH(F$1,SUBQH,0),0),"") | G12: =IFERROR(VLOOKUP($A12,subQ,MATCH(G$1,SUBQH,0),0),"") | H12: =IFERROR(VLOOKUP($A12,subQ,MATCH(H$1,SUBQH,0),0),"") | I12: =IFERROR(VLOOKUP($A12,subQ,MATCH(I$1,SUBQH,0),0),"") | J12: =IFERROR(VLOOKUP($A12,subQ,MATCH(J$1,SUBQH,0),0),"") | K12: =IFERROR(VLOOKUP($A12,subQ,MATCH(K$1,SUBQH,0),0),"") | L12: =IFERROR(VLOOKUP($A12,subQ,MATCH(L$1,SUBQH,0),0),"")
A13: 기타영업외손익 | D13: 기타영업외손익 | E13: =IFERROR(VLOOKUP($A13,subQ,MATCH(E$1,SUBQH,0),0),"") | F13: =IFERROR(VLOOKUP($A13,subQ,MATCH(F$1,SUBQH,0),0),"") | G13: =IFERROR(VLOOKUP($A13,subQ,MATCH(G$1,SUBQH,0),0),"") | H13: =IFERROR(VLOOKUP($A13,subQ,MATCH(H$1,SUBQH,0),0),"") | I13: =IFERROR(VLOOKUP($A13,subQ,MATCH(I$1,SUBQH,0),0),"") | J13: =IFERROR(VLOOKUP($A13,subQ,MATCH(J$1,SUBQH,0),0),"") | K13: =IFERROR(VLOOKUP($A13,subQ,MATCH(K$1,SUBQH,0),0),"") | L13: =IFERROR(VLOOKUP($A13,subQ,MATCH(L$1,SUBQH,0),0),"")
A14: 세전이익 | D14: 법인세비용차감전이익 | E14: =IFERROR(VLOOKUP($A14,subQ,MATCH(E$1,SUBQH,0),0),"") | F14: =IFERROR(VLOOKUP($A14,subQ,MATCH(F$1,SUBQH,0),0),"") | G14: =IFERROR(VLOOKUP($A14,subQ,MATCH(G$1,SUBQH,0),0),"") | H14: =IFERROR(VLOOKUP($A14,subQ,MATCH(H$1,SUBQH,0),0),"") | I14: =IFERROR(VLOOKUP($A14,subQ,MATCH(I$1,SUBQH,0),0),"") | J14: =IFERROR(VLOOKUP($A14,subQ,MATCH(J$1,SUBQH,0),0),"") | K14: =IFERROR(VLOOKUP($A14,subQ,MATCH(K$1,SUBQH,0),0),"") | L14: =IFERROR(VLOOKUP($A14,subQ,MATCH(L$1,SUBQH,0),0),"")
A15: 법인세비용 | D15: 법인세비용 | E15: =IFERROR(VLOOKUP($A15,subQ,MATCH(E$1,SUBQH,0),0),"") | F15: =IFERROR(VLOOKUP($A15,subQ,MATCH(F$1,SUBQH,0),0),"") | G15: =IFERROR(VLOOKUP($A15,subQ,MATCH(G$1,SUBQH,0),0),"") | H15: =IFERROR(VLOOKUP($A15,subQ,MATCH(H$1,SUBQH,0),0),"") | I15: =IFERROR(VLOOKUP($A15,subQ,MATCH(I$1,SUBQH,0),0),"") | J15: =IFERROR(VLOOKUP($A15,subQ,MATCH(J$1,SUBQH,0),0),"") | K15: =IFERROR(VLOOKUP($A15,subQ,MATCH(K$1,SUBQH,0),0),"") | L15: =IFERROR(VLOOKUP($A15,subQ,MATCH(L$1,SUBQH,0),0),"")
A16: 당기순이익 | D16: 당기순이익 | E16: =IFERROR(VLOOKUP($A16,subQ,MATCH(E$1,SUBQH,0),0),"") | F16: =IFERROR(VLOOKUP($A16,subQ,MATCH(F$1,SUBQH,0),0),"") | G16: =IFERROR(VLOOKUP($A16,subQ,MATCH(G$1,SUBQH,0),0),"") | H16: =IFERROR(VLOOKUP($A16,subQ,MATCH(H$1,SUBQH,0),0),"") | I16: =IFERROR(VLOOKUP($A16,subQ,MATCH(I$1,SUBQH,0),0),"") | J16: =IFERROR(VLOOKUP($A16,subQ,MATCH(J$1,SUBQH,0),0),"") | K16: =IFERROR(VLOOKUP($A16,subQ,MATCH(K$1,SUBQH,0),0),"") | L16: =IFERROR(VLOOKUP($A16,subQ,MATCH(L$1,SUBQH,0),0),"")
... A36: NPM | D36: NPM | E36: =IFERROR(VLOOKUP($A36,subQ,MATCH(E$1,SUBQH,0),0),"") | F36: =IFERROR(VLOOKUP($A36,subQ,MATCH(F$1,SUBQH,0),0),"") | G36: =IFERROR(VLOOKUP($A36,subQ,MATCH(G$1,SUBQH,0),0),"") | H36: =IFERROR(VLOOKUP($A36,subQ,MATCH(H$1,SUBQH,0),0),"") | I36: =IFERROR(VLOOKUP($A36,subQ,MATCH(I$1,SUBQH,0),0),"") | J36: =IFERROR(VLOOKUP($A36,subQ,MATCH(J$1,SUBQH,0),0),"") | K36: =IFERROR(VLOOKUP($A36,subQ,MATCH(K$1,SUBQH,0),0),"") | L36: =IFERROR(VLOOKUP($A36,subQ,MATCH(L$1,SUBQH,0),0),"")
A37: 매출액 YoY | D37: 매출액 YoY | F37: =IFERROR(F5/E5-1,"") | G37: =IFERROR(G5/F5-1,"") | H37: =IFERROR(H5/G5-1,"") | I37: =IFERROR(I5/H5-1,"") | J37: =IFERROR(J5/I5-1,"") | K37: =IFERROR(K5/J5-1,"") | L37: =IFERROR(L5/K5-1,"")
A38: 영업이익 YoY | D38: 영업이익 YoY | F38: =IFERROR(F9/E9-1,"") | G38: =IFERROR(G9/F9-1,"") | H38: =IFERROR(H9/G9-1,"") | I38: =IFERROR(I9/H9-1,"") | J38: =IFERROR(J9/I9-1,"") | K38: =IFERROR(K9/J9-1,"") | L38: =IFERROR(L9/K9-1,"")
A39: 지배주주순이익 YoY | D39: 지배주주순이익 YoY | F39: =IFERROR(F17/E17-1,"") | G39: =IFERROR(G17/F17-1,"") | H39: =IFERROR(H17/G17-1,"") | I39: =IFERROR(I17/H17-1,"") | J39: =IFERROR(J17/I17-1,"") | K39: =IFERROR(K17/J17-1,"") | L39: =IFERROR(L17/K17-1,"")

Sheet TP
B1: 종가 | C1: =변수!D40
B2: 기준일 | C2: =변수!D41
B3: 모델 산출값 — 목표주가·추천 아님. 밴드·COE 는 변수 시트 3절의 가정
C5: FY | D5: 2025 | E5: 2026 | F5: 2027 | G5: 2028
D6: A | E6: E | F6: E | G6: E
C7: EPS(원) | D7: =IFERROR(VLOOKUP("EPS",subQ,MATCH(D$5,SUBQH,0),0),"") | E7: =IFERROR(VLOOKUP("EPS",subQ,MATCH(E$5,SUBQH,0),0),"") | F7: =IFERROR(VLOOKUP("EPS",subQ,MATCH(F$5,SUBQH,0),0),"") | G7: =IFERROR(VLOOKUP("EPS",subQ,MATCH(G$5,SUBQH,0),0),"")
C8: BPS(원) | D8: =IFERROR(VLOOKUP("BPS",subQ,MATCH(D$5,SUBQH,0),0),"") | E8: =IFERROR(VLOOKUP("BPS",subQ,MATCH(E$5,SUBQH,0),0),"") | F8: =IFERROR(VLOOKUP("BPS",subQ,MATCH(F$5,SUBQH,0),0),"") | G8: =IFERROR(VLOOKUP("BPS",subQ,MATCH(G$5,SUBQH,0),0),"")
C9: 지배주주순이익(억원) | D9: =IFERROR(VLOOKUP("지배주주순이익",subQ,MATCH(D$5,SUBQH,0),0),"") | E9: =IFERROR(VLOOKUP("지배주주순이익",subQ,MATCH(E$5,SUBQH,0),0),"") | F9: =IFERROR(VLOOKUP("지배주주순이익",subQ,MATCH(F$5,SUBQH,0),0),"") | G9: =IFERROR(VLOOKUP("지배주주순이익",subQ,MATCH(G$5,SUBQH,0),0),"")
C10: 영업이익(억원) | D10: =IFERROR(VLOOKUP("영업이익",subQ,MATCH(D$5,SUBQH,0),0),"") | E10: =IFERROR(VLOOKUP("영업이익",subQ,MATCH(E$5,SUBQH,0),0),"") | F10: =IFERROR(VLOOKUP("영업이익",subQ,MATCH(F$5,SUBQH,0),0),"") | G10: =IFERROR(VLOOKUP("영업이익",subQ,MATCH(G$5,SUBQH,0),0),"")
C11: ROE(EPS/기초BPS) | E11: =IFERROR(E7/D8,"") | F11: =IFERROR(F7/E8,"") | G11: =IFERROR(G7/F8,"")
B13: PER
C14: 12M fwd EPS | D14: =IFERROR(E7*변수!D46+F7*(1-변수!D46),"")
C15: 적정가치 @PER_lo | D15: =변수!D43 | E15: =IFERROR(ROUND($D$14*D15,-2),"") | F15: =IFERROR(E15/$C$1-1,"") | G15: 배 · 원 · 종가 대비
C16: 적정가치 @PER_mid | D16: =변수!D44 | E16: =IFERROR(ROUND($D$14*D16,-2),"") | F16: =IFERROR(E16/$C$1-1,"") | G16: 배 · 원 · 종가 대비
C17: 적정가치 @PER_hi | D17: =변수!D45 | E17: =IFERROR(ROUND($D$14*D17,-2),"") | F17: =IFERROR(E17/$C$1-1,"") | G17: 배 · 원 · 종가 대비
C18: 현재 PER(종가/12M fwd EPS) | D18: =IFERROR($C$1/$D$14,"")
B20: PBR
C21: 최근 BPS(마지막 실적 분기) | D21: =IFERROR(VLOOKUP("BPS",subQ,MATCH("2Q26",SUBQH,0),0),"")
C22: ROE fwd(12M fwd EPS / BPS) | D22: =IFERROR($D$14/$D$21,"")
C23: COE | D23: =변수!D42
C24: 적정 PBR = ROE/COE | D24: =IFERROR(D22/D23,"")
C25: 적정가치(PBR) = BPS × 적정PBR | D25: =IFERROR(ROUND(D21*D24,-2),"") | E25: =IFERROR(D25/$C$1-1,"")
C26: 현재 PBR(종가/BPS) | D26: =IFERROR($C$1/D21,"")
B28: 모델 json valuation(참고)
C29: eps_fwd12m | D29: 284.1
C30: bps_latest | D30: 27981.4
C31: per_now | D31: 224.57
C32: pbr_now | D32: 2.28
C33: roe_fwd | D33: 0.0102
C34: fair_pbr | D34: 0.11
C35: fair_value_pbr | D35: 3100
C36: ev_ebitda
C37: note | D37: 모델 산출값 — 목표주가·추천 아님

Sheet 외화
C1: 이름: 외화QH — 환율 QoQ · 외화 순노출 × Δ기말환율 | E1: 4Q21 | F1: 1Q22 | G1: 2Q22 | H1: 3Q22 | I1: 4Q22 | J1: 1Q23 | K1: 2Q23 | L1: 3Q23 | M1: 4Q23 | N1: 1Q24 | O1: 2Q24 | P1: 3Q24 | Q1: 4Q24 | R1: 1Q25 | S1: 2Q25 | T1: 3Q25 | U1: 4Q25 | V1: 1Q26 | W1: 2Q26 | X1: 3Q26 | Y1: 4Q26 | Z1: 1Q27 | AA1: 2Q27 | AB1: 3Q27 | AC1: 4Q27 | AD1: 1Q28 | AE1: 2Q28 | AF1: 3Q28 | AG1: 4Q28
E3: 1 | F3: 2 | G3: 3 | H3: 4 | I3: 5 | J3: 6 | K3: 7 | L3: 8 | M3: 9 | N3: 10 | O3: 11 | P3: 12 | Q3: 13 | R3: 14 | S3: 15 | T3: 16 | U3: 17 | V3: 18 | W3: 19 | X3: 20 | Y3: 21 | Z3: 22 | AA3: 23 | AB3: 24 | AC3: 25 | AD3: 26 | AE3: 27 | AF3: 28 | AG3: 29
E4: 2021.12 | F4: 2022.03 | G4: 2022.06 | H4: 2022.09 | I4: 2022.12 | J4: 2023.03 | K4: 2023.06 | L4: 2023.09 | M4: 2023.12 | N4: 2024.03 | O4: 2024.06 | P4: 2024.09 | Q4: 2024.12 | R4: 2025.03 | S4: 2025.06 | T4: 2025.09 | U4: 2025.12 | V4: 2026.03 | W4: 2026.06 | X4: 2026.09 | Y4: 2026.12 | Z4: 2027.03 | AA4: 2027.06 | AB4: 2027.09 | AC4: 2027.12 | AD4: 2028.03 | AE4: 2028.06 | AF4: 2028.09 | AG4: 2028.12
D5: 원/달러(평균) | E5: =IFERROR(VLOOKUP($D5,환율,MATCH(E$1,변수H,0),0),"") | F5: =IFERROR(VLOOKUP($D5,환율,MATCH(F$1,변수H,0),0),"") | G5: =IFERROR(VLOOKUP($D5,환율,MATCH(G$1,변수H,0),0),"") | H5: =IFERROR(VLOOKUP($D5,환율,MATCH(H$1,변수H,0),0),"") | I5: =IFERROR(VLOOKUP($D5,환율,MATCH(I$1,변수H,0),0),"") | J5: =IFERROR(VLOOKUP($D5,환율,MATCH(J$1,변수H,0),0),"") | K5: =IFERROR(VLOOKUP($D5,환율,MATCH(K$1,변수H,0),0),"") | L5: =IFERROR(VLOOKUP($D5,환율,MATCH(L$1,변수H,0),0),"") | ... AG5: =IFERROR(VLOOKUP($D5,환율,MATCH(AG$1,변수H,0),0),"")
A6: 원/달러(평균) QoQ | F6: =IFERROR(F5/E5-1,"") | G6: =IFERROR(G5/F5-1,"") | H6: =IFERROR(H5/G5-1,"") | I6: =IFERROR(I5/H5-1,"") | J6: =IFERROR(J5/I5-1,"") | K6: =IFERROR(K5/J5-1,"") | L6: =IFERROR(L5/K5-1,"") | M6: =IFERROR(M5/L5-1,"") | ... AG6: =IFERROR(AG5/AF5-1,"")
D7: 원/달러(기말) | E7: =IFERROR(VLOOKUP($D7,환율,MATCH(E$1,변수H,0),0),"") | F7: =IFERROR(VLOOKUP($D7,환율,MATCH(F$1,변수H,0),0),"") | G7: =IFERROR(VLOOKUP($D7,환율,MATCH(G$1,변수H,0),0),"") | H7: =IFERROR(VLOOKUP($D7,환율,MATCH(H$1,변수H,0),0),"") | I7: =IFERROR(VLOOKUP($D7,환율,MATCH(I$1,변수H,0),0),"") | J7: =IFERROR(VLOOKUP($D7,환율,MATCH(J$1,변수H,0),0),"") | K7: =IFERROR(VLOOKUP($D7,환율,MATCH(K$1,변수H,0),0),"") | L7: =IFERROR(VLOOKUP($D7,환율,MATCH(L$1,변수H,0),0),"") | ... AG7: =IFERROR(VLOOKUP($D7,환율,MATCH(AG$1,변수H,0),0),"")
A8: 원/달러(기말) QoQ | F8: =IFERROR(F7/E7-1,"") | G8: =IFERROR(G7/F7-1,"") | H8: =IFERROR(H7/G7-1,"") | I8: =IFERROR(I7/H7-1,"") | J8: =IFERROR(J7/I7-1,"") | K8: =IFERROR(K7/J7-1,"") | L8: =IFERROR(L7/K7-1,"") | M8: =IFERROR(M7/L7-1,"") | ... AG8: =IFERROR(AG7/AF7-1,"")
D9: W/Euro(평균) | E9: =IFERROR(VLOOKUP($D9,환율,MATCH(E$1,변수H,0),0),"") | F9: =IFERROR(VLOOKUP($D9,환율,MATCH(F$1,변수H,0),0),"") | G9: =IFERROR(VLOOKUP($D9,환율,MATCH(G$1,변수H,0),0),"") | H9: =IFERROR(VLOOKUP($D9,환율,MATCH(H$1,변수H,0),0),"") | I9: =IFERROR(VLOOKUP($D9,환율,MATCH(I$1,변수H,0),0),"") | J9: =IFERROR(VLOOKUP($D9,환율,MATCH(J$1,변수H,0),0),"") | K9: =IFERROR(VLOOKUP($D9,환율,MATCH(K$1,변수H,0),0),"") | L9: =IFERROR(VLOOKUP($D9,환율,MATCH(L$1,변수H,0),0),"") | ... AG9: =IFERROR(VLOOKUP($D9,환율,MATCH(AG$1,변수H,0),0),"")
A10: W/Euro(평균) QoQ | F10: =IFERROR(F9/E9-1,"") | G10: =IFERROR(G9/F9-1,"") | H10: =IFERROR(H9/G9-1,"") | I10: =IFERROR(I9/H9-1,"") | J10: =IFERROR(J9/I9-1,"") | K10: =IFERROR(K9/J9-1,"") | L10: =IFERROR(L9/K9-1,"") | M10: =IFERROR(M9/L9-1,"") | ... AG10: =IFERROR(AG9/AF9-1,"")
D11: W/Euro(기말) | E11: =IFERROR(VLOOKUP($D11,환율,MATCH(E$1,변수H,0),0),"") | F11: =IFERROR(VLOOKUP($D11,환율,MATCH(F$1,변수H,0),0),"") | G11: =IFERROR(VLOOKUP($D11,환율,MATCH(G$1,변수H,0),0),"") | H11: =IFERROR(VLOOKUP($D11,환율,MATCH(H$1,변수H,0),0),"") | I11: =IFERROR(VLOOKUP($D11,환율,MATCH(I$1,변수H,0),0),"") | J11: =IFERROR(VLOOKUP($D11,환율,MATCH(J$1,변수H,0),0),"") | K11: =IFERROR(VLOOKUP($D11,환율,MATCH(K$1,변수H,0),0),"") | L11: =IFERROR(VLOOKUP($D11,환율,MATCH(L$1,변수H,0),0),"") | ... AG11: =IFERROR(VLOOKUP($D11,환율,MATCH(AG$1,변수H,0),0),"")
A12: W/Euro(기말) QoQ | F12: =IFERROR(F11/E11-1,"") | G12: =IFERROR(G11/F11-1,"") | H12: =IFERROR(H11/G11-1,"") | I12: =IFERROR(I11/H11-1,"") | J12: =IFERROR(J11/I11-1,"") | K12: =IFERROR(K11/J11-1,"") | L12: =IFERROR(L11/K11-1,"") | M12: =IFERROR(M11/L11-1,"") | ... AG12: =IFERROR(AG11/AF11-1,"")
D13: 원/100Y(기말) | E13: =IFERROR(VLOOKUP($D13,환율,MATCH(E$1,변수H,0),0),"") | F13: =IFERROR(VLOOKUP($D13,환율,MATCH(F$1,변수H,0),0),"") | G13: =IFERROR(VLOOKUP($D13,환율,MATCH(G$1,변수H,0),0),"") | H13: =IFERROR(VLOOKUP($D13,환율,MATCH(H$1,변수H,0),0),"") | I13: =IFERROR(VLOOKUP($D13,환율,MATCH(I$1,변수H,0),0),"") | J13: =IFERROR(VLOOKUP($D13,환율,MATCH(J$1,변수H,0),0),"") | K13: =IFERROR(VLOOKUP($D13,환율,MATCH(K$1,변수H,0),0),"") | L13: =IFERROR(VLOOKUP($D13,환율,MATCH(L$1,변수H,0),0),"") | ... AG13: =IFERROR(VLOOKUP($D13,환율,MATCH(AG$1,변수H,0),0),"")
A14: 원/100Y(기말) QoQ | F14: =IFERROR(F13/E13-1,"") | G14: =IFERROR(G13/F13-1,"") | H14: =IFERROR(H13/G13-1,"") | I14: =IFERROR(I13/H13-1,"") | J14: =IFERROR(J13/I13-1,"") | K14: =IFERROR(K13/J13-1,"") | L14: =IFERROR(L13/K13-1,"") | M14: =IFERROR(M13/L13-1,"") | ... AG14: =IFERROR(AG13/AF13-1,"")
A16: 외화순노출 | C16: 외화 순노출(백만$) | D16: =변수!D53 | E16: 외화 순노출 × Δ기말환율 (외화 시트 방식)
A17: 환관련손익추정 | C17: 환관련손익 추정(억원) = 순노출 × Δ원/달러(기말) / 100 | F17: =IFERROR($D$16*(F7-E7)/100,"") | G17: =IFERROR($D$16*(G7-F7)/100,"") | H17: =IFERROR($D$16*(H7-G7)/100,"") | I17: =IFERROR($D$16*(I7-H7)/100,"") | J17: =IFERROR($D$16*(J7-I7)/100,"") | K17: =IFERROR($D$16*(K7-J7)/100,"") | L17: =IFERROR($D$16*(L7-K7)/100,"") | M17: =IFERROR($D$16*(M7-L7)/100,"") | ... AG17: =IFERROR($D$16*(AG7-AF7)/100,"")
A18: fx_pnl.by_q | C18: 모델 fx_pnl.by_q(억원, 참고)
C19: 외화 순노출 미공시(face) → 0 + 표기
