Workbook
Name 변수H: 변수!$C$1:$AO$1
Name 환율: 변수!$C$6:$AO$13
Name BS연결H: BS연결!$C$1:$AO$1
Name BS연결: BS연결!$C$5:$AO$108
Name BS별도H: BS별도!$C$1:$AO$1
Name BS별도: BS별도!$C$5:$AO$91
Name SUBQH: subQ!$A$1:$AO$1
Name subQ: subQ!$A$5:$AO$43

Sheet README
A1: 한화시스템(272210) 실적 모델 — ARGUS 한국조선
A2: 기준 분기 2026Q2 · 마지막 실적 2026Q2 · 생성 2026-10-11
A3: 모든 수치는 모델 산출값(DART 공개 재무제표 + 우리 추정)이다 — 목표주가·투자 추천 아님. 참고용 · 투자조언 아님.
A5: 시트
A6: 변수 가정 시계열. 환율 8행(ECB via frankfurter — L2 fx.json; 추정 분기 = 노란 가정), 추정 드라이버(노란 셀 = 모델값에서 역산한 가정, 바꾸면 재계산; 연녹 셀 = 3절 스칼라 참조 수식), 3절 스칼라 가정(세율·판관비율·지배주주비중·이자율·종가·PER 밴드·COE·외화 순노출·헤지비율)
A7: BS연결/BS별도 FnGuide 계정명 × 기간 값 덤프(백만원). 행1 분기라벨, 행4 YYYY.MM / YYYY.12A. 이름정의 BS연결H·BS연결(계정명 C열부터)
A8: subQ 분기 서브모델(억원 = 백만원/100). 확정 행: =IFERROR(VLOOKUP($D행,BS연결,MATCH(E$1,BS연결H,0),0)/100,"") 추정 행: 변수 시트 가정 셀 참조 수식. 외환손익·파생상품손익은 BS 계정 합·차, 기타금융손익은 잔차, OPM·EPS·BPS·PER·PBR 은 파생 수식
A9: SLS 선표(조선사만, sls json 있을 때): 요약 행(sls 저장값) + 계약별 스케줄(백만$) × (헤지비율 × 헤지환율 + (1−헤지비율) × 건조시점 환율[변수 원/달러(평균)]) → 원화 수식 블록 → 합계 행이 subQ 매출조선에 연결
A10: 시나리오 신규수주 보수/기준/낙관(forecast_panel 패널, 모델에 scenarios 가 있을 때만): 매출액·영업이익 = subQ 기준값 ± (시나리오 신규 − base 신규) × OPM. base 만 subQ 행에 포함, 나머지는 합산 안 함
A11: 분기/연간예상 subQ 를 이름(A열 key)으로 VLOOKUP 한 보고서 표(억원)
A12: TP PER 밴드 × 12M fwd EPS, PBR = ROE/COE × BPS — 모델 산출값 구간, 목표주가·추천 아님
A13: 외화 환율 QoQ, 외화 순노출 × Δ기말환율 → 환관련손익 추정
... A34: 백테스트: {"freeze": "2025Q2", "horizon": 4, "revenue_wape_pct": 15.6, "op_wape_pct": 93.1, "n": 4, "note": "단일 회사 4분기 — 통계 아님", "driver_at_freeze": "trend_seasonal", "selection_oos_at_freeze": {"wape_link": null, "wape_trend": null, "adopted": false, "decision": "rejected", "note": "자격 미달 → 격자·OOS 전 기각"}, "frozen_inputs": "fin(연결/별도)·고객 조선사 모델·지주 자회사 모델은 2025Q2 까지의 분기만; 선표는 체결일 ≤ 2025Q2 말일 계약(원장 최신 금액·코호트 등급, 환산 없음); 잔고는 yards_cache 2025Q2; 시세·환율 forward·prices·forecast_panel 신규수주 미사용. 고객 가중치(suppliers.json 언급 비중)와 합병 체인링크는 현재 지식; 고객 연동 채택은 동결 모델 안에서도 자기 la−4분기 OOS 규칙(selection_oos_at_freeze)", "detail": [{"q": "2025Q3", "rev_pred": 7351.79, "rev_act": 8077.37, "op_pred": 486.18, "op_act": 225.21}, {"q": "2025Q4", "rev_pred": 10729.48, "rev_act": 13981.23, "op_pred": 709.56, "op_act": 57.62}, {"q": "2026Q1", "rev_pred": 7937.57, "rev_act": 8070.99, "op_pred": 524.92, "op_act": 342.84}, {"q": "2026Q2", "rev_pred": 8835.77, "rev_act": 11175.52, "op_pred": 584.32, "op_act": 1036.52}]}

Sheet 변수
C1: 이름: 변수H | E1: 4Q21 | F1: 2021 | G1: 1Q22 | H1: 2Q22 | I1: 3Q22 | J1: 4Q22 | K1: 2022 | L1: 1Q23 | M1: 2Q23 | N1: 3Q23 | O1: 4Q23 | P1: 2023 | Q1: 1Q24 | R1: 2Q24 | S1: 3Q24 | T1: 4Q24 | U1: 2024 | V1: 1Q25 | W1: 2Q25 | X1: 3Q25 | Y1: 4Q25 | Z1: 2025 | AA1: 1Q26 | AB1: 2Q26 | AC1: 3Q26 | AD1: 4Q26 | AE1: 2026 | AF1: 1Q27 | AG1: 2Q27 | AH1: 3Q27 | AI1: 4Q27 | AJ1: 2027 | AK1: 1Q28 | AL1: 2Q28 | AM1: 3Q28 | AN1: 4Q28 | AO1: 2028
A2: 가정 시계열 — 노란 셀은 추정 가정(모델값에서 역산), 연녹 셀은 3절 스칼라 참조 수식. 바꾸면 subQ·분기·연간예상·TP·시나리오가 재계산됩니다.
E3: 1 | F3: 2 | G3: 3 | H3: 4 | I3: 5 | J3: 6 | K3: 7 | L3: 8 | M3: 9 | N3: 10 | O3: 11 | P3: 12 | Q3: 13 | R3: 14 | S3: 15 | T3: 16 | U3: 17 | V3: 18 | W3: 19 | X3: 20 | Y3: 21 | Z3: 22 | AA3: 23 | AB3: 24 | AC3: 25 | AD3: 26 | AE3: 27 | AF3: 28 | AG3: 29 | AH3: 30 | AI3: 31 | AJ3: 32 | AK3: 33 | AL3: 34 | AM3: 35 | AN3: 36 | AO3: 37
E4: 2021.12 | F4: 2021.12A | G4: 2022.03 | H4: 2022.06 | I4: 2022.09 | J4: 2022.12 | K4: 2022.12A | L4: 2023.03 | M4: 2023.06 | N4: 2023.09 | O4: 2023.12 | P4: 2023.12A | Q4: 2024.03 | R4: 2024.06 | S4: 2024.09 | T4: 2024.12 | U4: 2024.12A | V4: 2025.03 | W4: 2025.06 | X4: 2025.09 | Y4: 2025.12 | Z4: 2025.12A | AA4: 2026.03 | AB4: 2026.06 | AC4: 2026.09 | AD4: 2026.12 | AE4: 2026.12A | AF4: 2027.03 | AG4: 2027.06 | AH4: 2027.09 | AI4: 2027.12 | AJ4: 2027.12A | AK4: 2028.03 | AL4: 2028.06 | AM4: 2028.09 | AN4: 2028.12 | AO4: 2028.12A
B5: 1. FX | C5: 이름: 환율
A6: USDKRW_avg | C6: 원/달러(평균) | E6: 1183.5 | F6: 1145.51 | G6: 1205.78 | H6: 1262.09 | I6: 1341.93 | J6: 1360.12 | K6: 1292.98 | L6: 1276.95 | M6: 1315.69 | N6: 1313.62 | O6: 1322.01 | P6: 1306.85 | Q6: 1330.14 | R6: 1371.28 | S6: 1356.22 | T6: 1396.3 | U6: 1363.53 | V6: 1452.28 | W6: 1398.52 | X6: 1386.95 | Y6: 1449.19 | Z6: 1421.52 | AA6: 1466.12 | AB6: 1501.75 | AC6: 1418.75 | AD6: 1345.14 | AE6: 1457.21 | AF6: 1341.49 | AG6: 1341.49 | AH6: 1341.49 | AI6: 1341.49 | AK6: 1341.49 | AL6: 1341.49 | AM6: 1341.49 | AN6: 1341.49
A7: USDKRW_end | C7: 원/달러(기말) | E7: 1188.75 | F7: 1188.75 | G7: 1213.74 | H7: 1301.24 | I7: 1436.9 | J7: 1260.16 | K7: 1260.16 | L7: 1305.99 | M7: 1321.44 | N7: 1345.35 | O7: 1297.43 | P7: 1297.43 | Q7: 1349.25 | R7: 1377.73 | S7: 1312.17 | T7: 1474.78 | U7: 1474.78 | V7: 1474.54 | W7: 1355.13 | X7: 1403.67 | Y7: 1444.2 | Z7: 1444.2 | AA7: 1524.8 | AB7: 1550.89 | AC7: 1355.4 | AD7: 1341.49 | AE7: 1341.49 | AF7: 1341.49 | AG7: 1341.49 | AH7: 1341.49 | AI7: 1341.49 | AK7: 1341.49 | AL7: 1341.49 | AM7: 1341.49 | AN7: 1341.49
A8: JPY100KRW_avg | C8: 원/100Y(평균) | E8: 1041.02 | F8: 1042.74 | G8: 1036.79 | H8: 972.23 | I8: 970.61 | J8: 961.03 | K8: 985.1 | L8: 964.89 | M8: 957.36 | N8: 909 | O8: 893.22 | P8: 931.11 | Q8: 896.29 | R8: 880.14 | S8: 909.35 | T8: 917.25 | U8: 900.92 | V8: 952.59 | W8: 967.92 | X8: 940.32 | Y8: 940.77 | Z8: 950.17 | AA8: 934.39 | AB8: 942.16 | AC8: 890.41 | AD8: 850.79 | AE8: 919.21 | AF8: 847.7 | AG8: 847.7 | AH8: 847.7 | AI8: 847.7 | AK8: 847.7 | AL8: 847.7 | AM8: 847.7 | AN8: 847.7
A9: JPY100KRW_end | C9: 원/100Y(기말) | E9: 1032.62 | F9: 1032.62 | G9: 996.83 | H9: 954.9 | I9: 993.29 | J9: 955.54 | K9: 955.54 | L9: 980.62 | M9: 913.67 | N9: 901.47 | O9: 917.04 | P9: 917.04 | Q9: 892.42 | R9: 857.76 | S9: 919.21 | T9: 939.65 | U9: 939.65 | V9: 986.84 | W9: 938.85 | X9: 948.49 | Y9: 921.81 | Z9: 921.81 | AA9: 955.99 | AB9: 954.75 | AC9: 863.31 | AD9: 847.7 | AE9: 847.7 | AF9: 847.7 | AG9: 847.7 | AH9: 847.7 | AI9: 847.7 | AK9: 847.7 | AL9: 847.7 | AM9: 847.7 | AN9: 847.7
A10: EURKRW_avg | C10: W/Euro(평균) | E10: 1353.32 | F10: 1354.06 | G10: 1352.29 | H10: 1343.31 | I10: 1350.63 | J10: 1386.07 | K10: 1358.07 | L10: 1369.93 | M10: 1432.41 | N10: 1429.41 | O10: 1420.91 | P10: 1412.88 | Q10: 1444.21 | R10: 1476.42 | S10: 1489.3 | T10: 1490.78 | U10: 1475.4 | V10: 1528.33 | W10: 1585.13 | X10: 1620.04 | Y10: 1686.02 | Z10: 1605.45 | AA10: 1715.47 | AB10: 1746.09 | AC10: 1631.97 | AD10: 1509.74 | AE10: 1689.95 | AF10: 1503.27 | AG10: 1503.27 | AH10: 1503.27 | AI10: 1503.27 | AK10: 1503.27 | AL10: 1503.27 | AM10: 1503.27 | AN10: 1503.27
A11: EURKRW_end | C11: W/Euro(기말) | E11: 1346.38 | F11: 1346.38 | G11: 1347.37 | H11: 1351.6 | I11: 1400.62 | J11: 1344.08 | K11: 1344.08 | L11: 1420.26 | M11: 1435.88 | N11: 1425.26 | O11: 1433.66 | P11: 1433.66 | Q11: 1458.68 | R11: 1474.86 | S11: 1469.1 | T11: 1532.14 | U11: 1532.14 | V11: 1594.72 | W11: 1588.22 | X11: 1648.04 | Y11: 1696.94 | Z11: 1696.94 | AA11: 1753.21 | AB11: 1767.09 | AC11: 1539.06 | AD11: 1503.27 | AE11: 1503.27 | AF11: 1503.27 | AG11: 1503.27 | AH11: 1503.27 | AI11: 1503.27 | AK11: 1503.27 | AL11: 1503.27 | AM11: 1503.27 | AN11: 1503.27
A12: CNYKRW_avg | C12: 원/중국원(평균) | E12: 185.14 | F12: 177.65 | G12: 189.93 | H12: 190.76 | I12: 195.79 | J12: 191.09 | K12: 191.93 | L12: 186.59 | M12: 187.45 | N12: 181.28 | O12: 182.86 | P12: 184.52 | Q12: 185.04 | R12: 189.35 | S12: 189.24 | T12: 194.24 | U12: 189.49 | V12: 199.63 | W12: 193.41 | X12: 193.79 | Y12: 204.38 | Z12: 197.8 | AA12: 211.75 | AB12: 220.8 | AC12: 210.43 | AD12: 200.69 | AE12: 213.75 | AF12: 200.46 | AG12: 200.46 | AH12: 200.46 | AI12: 200.46 | AK12: 200.46 | AL12: 200.46 | AM12: 200.46 | AN12: 200.46
A13: CNYKRW_end | C13: 원/중국원(기말) | E13: 187.13 | F13: 187.13 | G13: 191.38 | H13: 194.13 | I13: 201.92 | J13: 182.67 | K13: 182.67 | L13: 189.97 | M13: 181.8 | N13: 184.26 | O13: 182.61 | P13: 182.61 | Q13: 186.66 | R13: 189.7 | S13: 187.12 | T13: 202.04 | U13: 202.04 | V13: 203.3 | W13: 189.14 | X13: 197.16 | Y13: 206.28 | Z13: 206.28 | AA13: 220.97 | AB13: 228.56 | AC13: 202.16 | AD13: 200.46 | AE13: 200.46 | AF13: 200.46 | AG13: 200.46 | AH13: 200.46 | AI13: 200.46 | AK13: 200.46 | AL13: 200.46 | AM13: 200.46 | AN13: 200.46
B14: 1b. 종가
A15: price_close_end | C15: 종가(기말) | E15: 16000 | G15: 16400 | H15: 13950 | I15: 11050 | J15: 10550 | L15: 13860 | M15: 14600 | N15: 12270 | O15: 17360 | Q15: 17170 | R15: 18860 | S15: 17880 | T15: 22600 | V15: 32100 | W15: 58000 | X15: 59500 | Y15: 54400 | AA15: 114100 | AB15: 73000 | AC15: 75200 | AD15: 76700
A16: price_high | C16: 종가(최고) | E16: 18100 | G16: 18400 | H16: 17100 | I16: 16200 | J16: 12600 | L16: 14240 | M16: 15700 | N16: 17720 | O16: 17500 | Q16: 19910 | R16: 22450 | S16: 23400 | T16: 30200 | V16: 43400 | W16: 70200 | X16: 62000 | Y16: 65900 | AA16: 184000 | AB16: 138900 | AC16: 87900 | AD16: 89600
A17: price_low | C17: 종가(최저) | E17: 13850 | G17: 14000 | H17: 12750 | I17: 10650 | J17: 10150 | L17: 10200 | M17: 13610 | N17: 12050 | O17: 11530 | Q17: 14950 | R17: 16170 | S17: 16530 | T17: 17460 | V17: 22550 | W17: 30100 | X17: 47550 | Y17: 44750 | AA17: 54400 | AB17: 70700 | AC17: 50700 | AD17: 72500
A18: price_avg | C18: 종가(평균) | E18: 15928.6 | G18: 15916.1 | H18: 15483.9 | I18: 14063.5 | J18: 11266.1 | L18: 12469.4 | M18: 14381.1 | N18: 14105.6 | O18: 14439.7 | Q18: 17156.6 | R18: 18262.5 | S18: 18915 | T18: 21548.7 | V18: 30619 | W18: 45727.5 | X18: 55034.6 | Y18: 52632.2 | AA18: 109610.2 | AB18: 110444.3 | AC18: 70688.7 | AD18: 79380
B20: 2. 추정 드라이버 | C20: 실적 열 = subQ 실현값(수식), 추정 열 = 가정(노란 = 모델값 역산, 연녹 = 3절 스칼라 참조)
A21: drv:매출액 | B21: yoy | C21: 매출액 YoY | J21: =IFERROR(subQ!J5/subQ!E5-1,"") | L21: =IFERROR(subQ!L5/subQ!G5-1,"") | M21: =IFERROR(subQ!M5/subQ!H5-1,"") | N21: =IFERROR(subQ!N5/subQ!I5-1,"") | O21: =IFERROR(subQ!O5/subQ!J5-1,"") | Q21: =IFERROR(subQ!Q5/subQ!L5-1,"") | R21: =IFERROR(subQ!R5/subQ!M5-1,"") | S21: =IFERROR(subQ!S5/subQ!N5-1,"") | T21: =IFERROR(subQ!T5/subQ!O5-1,"") | V21: =IFERROR(subQ!V5/subQ!Q5-1,"") | W21: =IFERROR(subQ!W5/subQ!R5-1,"") | X21: =IFERROR(subQ!X5/subQ!S5-1,"") | Y21: =IFERROR(subQ!Y5/subQ!T5-1,"") | AA21: =IFERROR(subQ!AA5/subQ!V5-1,"") | AB21: =IFERROR(subQ!AB5/subQ!W5-1,"") | AC21: 0.36307186 | AD21: 0.36307204 | AF21: 0.36307162 | AG21: 0.36307166 | AH21: 0.18153629 | AI21: 0.18153612 | AK21: 0.18153607 | AL21: 0.18153644 | AM21: 0.090768137 | AN21: 0.090767743
A22: drv:판관비 | B22: ratio | C22: 판관비율(/매출) | E22: =IFERROR(subQ!E8/subQ!E5,"") | F22: =IFERROR(subQ!F8/subQ!F5,"") | G22: =IFERROR(subQ!G8/subQ!G5,"") | H22: =IFERROR(subQ!H8/subQ!H5,"") | I22: =IFERROR(subQ!I8/subQ!I5,"") | J22: =IFERROR(subQ!J8/subQ!J5,"") | K22: =IFERROR(subQ!K8/subQ!K5,"") | L22: =IFERROR(subQ!L8/subQ!L5,"") | ... AB22: =IFERROR(subQ!AB8/subQ!AB5,"") | AC22: =$D$52 | AD22: =$D$52 | AE22: =IFERROR(subQ!AE8/subQ!AE5,"") | AF22: =$D$52 | AG22: =$D$52 | AH22: =$D$52 | AI22: =$D$52 | AJ22: =IFERROR(subQ!AJ8/subQ!AJ5,"") | AK22: =$D$52 | AL22: =$D$52 | AM22: =$D$52 | AN22: =$D$52 | AO22: =IFERROR(subQ!AO8/subQ!AO5,"")
A23: drv:영업이익 | B23: ratio | C23: 영업이익률(OPM) | E23: =IFERROR(subQ!E9/subQ!E5,"") | F23: =IFERROR(subQ!F9/subQ!F5,"") | G23: =IFERROR(subQ!G9/subQ!G5,"") | H23: =IFERROR(subQ!H9/subQ!H5,"") | I23: =IFERROR(subQ!I9/subQ!I5,"") | J23: =IFERROR(subQ!J9/subQ!J5,"") | K23: =IFERROR(subQ!K9/subQ!K5,"") | L23: =IFERROR(subQ!L9/subQ!L5,"") | ... AB23: =IFERROR(subQ!AB9/subQ!AB5,"") | AC23: 0.044952648 | AD23: 0.044952045 | AE23: =IFERROR(subQ!AE9/subQ!AE5,"") | AF23: 0.044952706 | AG23: 0.044952317 | AH23: 0.044952052 | AI23: 0.044952198 | AJ23: =IFERROR(subQ!AJ9/subQ!AJ5,"") | AK23: 0.044952179 | AL23: 0.044952379 | AM23: 0.044952158 | AN23: 0.044952434 | AO23: =IFERROR(subQ!AO9/subQ!AO5,"")
A24: drv:외환손익 | B24: abs | C24: 외환손익 (가정, 억원) | E24: =subQ!E13 | F24: =subQ!F13 | G24: =subQ!G13 | H24: =subQ!H13 | I24: =subQ!I13 | J24: =subQ!J13 | K24: =subQ!K13 | L24: =subQ!L13 | ... AB24: =subQ!AB13 | AC24: 0 | AD24: 0 | AE24: =subQ!AE13 | AF24: 0 | AG24: 0 | AH24: 0 | AI24: 0 | AJ24: =subQ!AJ13 | AK24: 0 | AL24: 0 | AM24: 0 | AN24: 0 | AO24: =subQ!AO13
A25: drv:기타금융손익 | B25: abs | C25: 기타금융손익 (가정, 억원) | E25: =subQ!E14 | F25: =subQ!F14 | G25: =subQ!G14 | H25: =subQ!H14 | I25: =subQ!I14 | J25: =subQ!J14 | K25: =subQ!K14 | L25: =subQ!L14 | ... AB25: =subQ!AB14 | AC25: 44.45 | AD25: 44.45 | AE25: =subQ!AE14 | AF25: 44.45 | AG25: 44.45 | AH25: 44.45 | AI25: 44.45 | AJ25: =subQ!AJ14 | AK25: 44.45 | AL25: 44.45 | AM25: 44.45 | AN25: 44.45 | AO25: =subQ!AO14
A26: drv:기타영업외손익 | B26: abs | C26: 기타영업외손익 (가정, 억원) | E26: =subQ!E15 | F26: =subQ!F15 | G26: =subQ!G15 | H26: =subQ!H15 | I26: =subQ!I15 | J26: =subQ!J15 | K26: =subQ!K15 | L26: =subQ!L15 | ... AB26: =subQ!AB15 | AC26: 0 | AD26: 0 | AE26: =subQ!AE15 | AF26: 0 | AG26: 0 | AH26: 0 | AI26: 0 | AJ26: =subQ!AJ15 | AK26: 0 | AL26: 0 | AM26: 0 | AN26: 0 | AO26: =subQ!AO15
A27: drv:지분법손익 | B27: abs | C27: 지분법손익 (가정, 억원) | E27: =subQ!E16 | F27: =subQ!F16 | G27: =subQ!G16 | H27: =subQ!H16 | I27: =subQ!I16 | J27: =subQ!J16 | K27: =subQ!K16 | L27: =subQ!L16 | ... AB27: =subQ!AB16 | AC27: -12.11 | AD27: -12.11 | AE27: =subQ!AE16 | AF27: -12.11 | AG27: -12.11 | AH27: -12.11 | AI27: -12.11 | AJ27: =subQ!AJ16 | AK27: -12.11 | AL27: -12.11 | AM27: -12.11 | AN27: -12.11 | AO27: =subQ!AO16
A28: drv:법인세비용 | B28: tax | C28: 법인세율(/세전) — 법인세 = MAX(세전,0) × 세율 | E28: =IFERROR(subQ!E18/subQ!E17,"") | F28: =IFERROR(subQ!F18/subQ!F17,"") | G28: =IFERROR(subQ!G18/subQ!G17,"") | H28: =IFERROR(subQ!H18/subQ!H17,"") | I28: =IFERROR(subQ!I18/subQ!I17,"") | J28: =IFERROR(subQ!J18/subQ!J17,"") | K28: =IFERROR(subQ!K18/subQ!K17,"") | L28: =IFERROR(subQ!L18/subQ!L17,"") | ... AB28: =IFERROR(subQ!AB18/subQ!AB17,"") | AC28: =$D$51 | AD28: =$D$51 | AE28: =IFERROR(subQ!AE18/subQ!AE17,"") | AF28: =$D$51 | AG28: =$D$51 | AH28: =$D$51 | AI28: =$D$51 | AJ28: =IFERROR(subQ!AJ18/subQ!AJ17,"") | AK28: =$D$51 | AL28: =$D$51 | AM28: =$D$51 | AN28: =$D$51 | AO28: =IFERROR(subQ!AO18/subQ!AO17,"")
A29: drv:지배주주순이익 | B29: ratio | C29: 지배주주 비중(/당기순이익) | E29: =IFERROR(subQ!E20/subQ!E19,"") | F29: =IFERROR(subQ!F20/subQ!F19,"") | G29: =IFERROR(subQ!G20/subQ!G19,"") | H29: =IFERROR(subQ!H20/subQ!H19,"") | I29: =IFERROR(subQ!I20/subQ!I19,"") | J29: =IFERROR(subQ!J20/subQ!J19,"") | K29: =IFERROR(subQ!K20/subQ!K19,"") | L29: =IFERROR(subQ!L20/subQ!L19,"") | ... AB29: =IFERROR(subQ!AB20/subQ!AB19,"") | AC29: =$D$53 | AD29: =$D$53 | AE29: =IFERROR(subQ!AE20/subQ!AE19,"") | AF29: =$D$53 | AG29: =$D$53 | AH29: =$D$53 | AI29: =$D$53 | AJ29: =IFERROR(subQ!AJ20/subQ!AJ19,"") | AK29: =$D$53 | AL29: =$D$53 | AM29: =$D$53 | AN29: =$D$53 | AO29: =IFERROR(subQ!AO20/subQ!AO19,"")
A30: drv:중단사업이익 | B30: abs | C30: 중단사업이익 (가정, 억원) | E30: =subQ!E21 | F30: =subQ!F21 | G30: =subQ!G21 | H30: =subQ!H21 | I30: =subQ!I21 | J30: =subQ!J21 | K30: =subQ!K21 | L30: =subQ!L21 | ... AB30: =subQ!AB21 | AE30: =subQ!AE21 | AJ30: =subQ!AJ21 | AO30: =subQ!AO21
A31: drv:부채총계 | B31: qoq | C31: 부채총계 QoQ | G31: =IFERROR(subQ!G23/subQ!E23-1,"") | H31: =IFERROR(subQ!H23/subQ!G23-1,"") | I31: =IFERROR(subQ!I23/subQ!H23-1,"") | J31: =IFERROR(subQ!J23/subQ!I23-1,"") | L31: =IFERROR(subQ!L23/subQ!J23-1,"") | M31: =IFERROR(subQ!M23/subQ!L23-1,"") | N31: =IFERROR(subQ!N23/subQ!M23-1,"") | O31: =IFERROR(subQ!O23/subQ!N23-1,"") | Q31: =IFERROR(subQ!Q23/subQ!O23-1,"") | R31: =IFERROR(subQ!R23/subQ!Q23-1,"") | S31: =IFERROR(subQ!S23/subQ!R23-1,"") | T31: =IFERROR(subQ!T23/subQ!S23-1,"") | V31: =IFERROR(subQ!V23/subQ!T23-1,"") | W31: =IFERROR(subQ!W23/subQ!V23-1,"") | X31: =IFERROR(subQ!X23/subQ!W23-1,"") | Y31: =IFERROR(subQ!Y23/subQ!X23-1,"") | AA31: =IFERROR(subQ!AA23/subQ!Y23-1,"") | AB31: =IFERROR(subQ!AB23/subQ!AA23-1,"") | AC31: -2.3e-08 | AD31: 0 | AF31: 0 | AG31: 0 | AH31: 0 | AI31: 0 | AK31: 0 | AL31: 0 | AM31: 0 | AN31: 0
A32: drv:자본총계 | B32: roll | C32: 자본총계 기타변동(배당 등, 억원) | G32: =IFERROR(subQ!E24+subQ!G19-subQ!G24,"") | H32: =IFERROR(subQ!G24+subQ!H19-subQ!H24,"") | I32: =IFERROR(subQ!H24+subQ!I19-subQ!I24,"") | J32: =IFERROR(subQ!I24+subQ!J19-subQ!J24,"") | L32: =IFERROR(subQ!J24+subQ!L19-subQ!L24,"") | M32: =IFERROR(subQ!L24+subQ!M19-subQ!M24,"") | N32: =IFERROR(subQ!M24+subQ!N19-subQ!N24,"") | O32: =IFERROR(subQ!N24+subQ!O19-subQ!O24,"") | Q32: =IFERROR(subQ!O24+subQ!Q19-subQ!Q24,"") | R32: =IFERROR(subQ!Q24+subQ!R19-subQ!R24,"") | S32: =IFERROR(subQ!R24+subQ!S19-subQ!S24,"") | T32: =IFERROR(subQ!S24+subQ!T19-subQ!T24,"") | V32: =IFERROR(subQ!T24+subQ!V19-subQ!V24,"") | W32: =IFERROR(subQ!V24+subQ!W19-subQ!W24,"") | X32: =IFERROR(subQ!W24+subQ!X19-subQ!X24,"") | Y32: =IFERROR(subQ!X24+subQ!Y19-subQ!Y24,"") | AA32: =IFERROR(subQ!Y24+subQ!AA19-subQ!AA24,"") | AB32: =IFERROR(subQ!AA24+subQ!AB19-subQ!AB24,"") | AC32: 0.006716294 | AD32: -0.005551901 | AF32: 0.005733464 | AG32: 934.96971 | AH32: -0.006163254 | AI32: 0.002632521 | AK32: -0.00466542 | AL32: 934.97461 | AM32: -0.005038271 | AN32: 0.003419515
A33: drv:지배주주지분 | B33: roll | C33: 지배주주지분 기타변동(배당 등, 억원) | G33: =IFERROR(subQ!E25+subQ!G20-subQ!G25,"") | H33: =IFERROR(subQ!G25+subQ!H20-subQ!H25,"") | I33: =IFERROR(subQ!H25+subQ!I20-subQ!I25,"") | J33: =IFERROR(subQ!I25+subQ!J20-subQ!J25,"") | L33: =IFERROR(subQ!J25+subQ!L20-subQ!L25,"") | M33: =IFERROR(subQ!L25+subQ!M20-subQ!M25,"") | N33: =IFERROR(subQ!M25+subQ!N20-subQ!N25,"") | O33: =IFERROR(subQ!N25+subQ!O20-subQ!O25,"") | Q33: =IFERROR(subQ!O25+subQ!Q20-subQ!Q25,"") | R33: =IFERROR(subQ!Q25+subQ!R20-subQ!R25,"") | S33: =IFERROR(subQ!R25+subQ!S20-subQ!S25,"") | T33: =IFERROR(subQ!S25+subQ!T20-subQ!T25,"") | V33: =IFERROR(subQ!T25+subQ!V20-subQ!V25,"") | W33: =IFERROR(subQ!V25+subQ!W20-subQ!W25,"") | X33: =IFERROR(subQ!W25+subQ!X20-subQ!X25,"") | Y33: =IFERROR(subQ!X25+subQ!Y20-subQ!Y25,"") | AA33: =IFERROR(subQ!Y25+subQ!AA20-subQ!AA25,"") | AB33: =IFERROR(subQ!AA25+subQ!AB20-subQ!AB25,"") | AC33: 0.006816294 | AD33: -0.005551901 | AF33: 0.005733464 | AG33: 934.96971 | AH33: -0.006163254 | AI33: 0.002632521 | AK33: -0.00466542 | AL33: 934.97461 | AM33: -0.005038271 | AN33: 0.003419515
A34: drv:총차입금 | B34: qoq | C34: 총차입금 QoQ | G34: =IFERROR(subQ!G26/subQ!E26-1,"") | H34: =IFERROR(subQ!H26/subQ!G26-1,"") | I34: =IFERROR(subQ!I26/subQ!H26-1,"") | J34: =IFERROR(subQ!J26/subQ!I26-1,"") | L34: =IFERROR(subQ!L26/subQ!J26-1,"") | M34: =IFERROR(subQ!M26/subQ!L26-1,"") | N34: =IFERROR(subQ!N26/subQ!M26-1,"") | O34: =IFERROR(subQ!O26/subQ!N26-1,"") | Q34: =IFERROR(subQ!Q26/subQ!O26-1,"") | R34: =IFERROR(subQ!R26/subQ!Q26-1,"") | S34: =IFERROR(subQ!S26/subQ!R26-1,"") | T34: =IFERROR(subQ!T26/subQ!S26-1,"") | V34: =IFERROR(subQ!V26/subQ!T26-1,"") | W34: =IFERROR(subQ!W26/subQ!V26-1,"") | X34: =IFERROR(subQ!X26/subQ!W26-1,"") | Y34: =IFERROR(subQ!Y26/subQ!X26-1,"") | AA34: =IFERROR(subQ!AA26/subQ!Y26-1,"") | AB34: =IFERROR(subQ!AB26/subQ!AA26-1,"") | AC34: 1.07e-07 | AD34: 0 | AF34: 0 | AG34: 0 | AH34: 0 | AI34: 0 | AK34: 0 | AL34: 0 | AM34: 0 | AN34: 0
A35: drv:순차입금 | B35: qoq | C35: 순차입금 QoQ | G35: =IFERROR(subQ!G27/subQ!E27-1,"") | H35: =IFERROR(subQ!H27/subQ!G27-1,"") | I35: =IFERROR(subQ!I27/subQ!H27-1,"") | J35: =IFERROR(subQ!J27/subQ!I27-1,"") | L35: =IFERROR(subQ!L27/subQ!J27-1,"") | M35: =IFERROR(subQ!M27/subQ!L27-1,"") | N35: =IFERROR(subQ!N27/subQ!M27-1,"") | O35: =IFERROR(subQ!O27/subQ!N27-1,"") | Q35: =IFERROR(subQ!Q27/subQ!O27-1,"") | R35: =IFERROR(subQ!R27/subQ!Q27-1,"") | S35: =IFERROR(subQ!S27/subQ!R27-1,"") | T35: =IFERROR(subQ!T27/subQ!S27-1,"") | V35: =IFERROR(subQ!V27/subQ!T27-1,"") | W35: =IFERROR(subQ!W27/subQ!V27-1,"") | X35: =IFERROR(subQ!X27/subQ!W27-1,"") | Y35: =IFERROR(subQ!Y27/subQ!X27-1,"") | AA35: =IFERROR(subQ!AA27/subQ!Y27-1,"") | AB35: =IFERROR(subQ!AB27/subQ!AA27-1,"") | AC35: -0.014903231 | AD35: -0.033179638 | AF35: -0.015863892 | AG35: 0.033617672 | AH35: -0.020075961 | AI35: -0.042626327 | AK35: -0.021686121 | AL35: 0.028336713 | AM35: -0.024394462 | AN35: -0.050709194
A36: drv:이자발생자산 | B36: qoq | C36: 이자발생자산 QoQ | G36: =IFERROR(subQ!G28/subQ!E28-1,"") | H36: =IFERROR(subQ!H28/subQ!G28-1,"") | I36: =IFERROR(subQ!I28/subQ!H28-1,"") | J36: =IFERROR(subQ!J28/subQ!I28-1,"") | L36: =IFERROR(subQ!L28/subQ!J28-1,"") | M36: =IFERROR(subQ!M28/subQ!L28-1,"") | N36: =IFERROR(subQ!N28/subQ!M28-1,"") | O36: =IFERROR(subQ!O28/subQ!N28-1,"") | Q36: =IFERROR(subQ!Q28/subQ!O28-1,"") | R36: =IFERROR(subQ!R28/subQ!Q28-1,"") | S36: =IFERROR(subQ!S28/subQ!R28-1,"") | T36: =IFERROR(subQ!T28/subQ!S28-1,"") | V36: =IFERROR(subQ!V28/subQ!T28-1,"") | W36: =IFERROR(subQ!W28/subQ!V28-1,"") | X36: =IFERROR(subQ!X28/subQ!W28-1,"") | Y36: =IFERROR(subQ!Y28/subQ!X28-1,"") | AA36: =IFERROR(subQ!AA28/subQ!Y28-1,"") | AB36: =IFERROR(subQ!AB28/subQ!AA28-1,"") | AC36: 0.011489923 | AD36: 0.024912798 | AF36: 0.0112362 | AG36: -0.023172876 | AH36: 0.014642576 | AI36: 0.030027431 | AK36: 0.014198263 | AL36: -0.017896208 | AM36: 0.016131673 | AN36: 0.032197086
A37: drv:현금및현금성자산 | B37: qoq | C37: 현금및현금성자산 QoQ | G37: =IFERROR(subQ!G29/subQ!E29-1,"") | H37: =IFERROR(subQ!H29/subQ!G29-1,"") | I37: =IFERROR(subQ!I29/subQ!H29-1,"") | J37: =IFERROR(subQ!J29/subQ!I29-1,"") | L37: =IFERROR(subQ!L29/subQ!J29-1,"") | M37: =IFERROR(subQ!M29/subQ!L29-1,"") | N37: =IFERROR(subQ!N29/subQ!M29-1,"") | O37: =IFERROR(subQ!O29/subQ!N29-1,"") | Q37: =IFERROR(subQ!Q29/subQ!O29-1,"") | R37: =IFERROR(subQ!R29/subQ!Q29-1,"") | S37: =IFERROR(subQ!S29/subQ!R29-1,"") | T37: =IFERROR(subQ!T29/subQ!S29-1,"") | V37: =IFERROR(subQ!V29/subQ!T29-1,"") | W37: =IFERROR(subQ!W29/subQ!V29-1,"") | X37: =IFERROR(subQ!X29/subQ!W29-1,"") | Y37: =IFERROR(subQ!Y29/subQ!X29-1,"") | AA37: =IFERROR(subQ!AA29/subQ!Y29-1,"") | AB37: =IFERROR(subQ!AB29/subQ!AA29-1,"")
A38: drv:CAPEX | B38: yoy | C38: CAPEX YoY | J38: =IFERROR(subQ!J30/subQ!E30-1,"") | L38: =IFERROR(subQ!L30/subQ!G30-1,"") | M38: =IFERROR(subQ!M30/subQ!H30-1,"") | N38: =IFERROR(subQ!N30/subQ!I30-1,"") | O38: =IFERROR(subQ!O30/subQ!J30-1,"") | Q38: =IFERROR(subQ!Q30/subQ!L30-1,"") | R38: =IFERROR(subQ!R30/subQ!M30-1,"") | S38: =IFERROR(subQ!S30/subQ!N30-1,"") | T38: =IFERROR(subQ!T30/subQ!O30-1,"") | V38: =IFERROR(subQ!V30/subQ!Q30-1,"") | W38: =IFERROR(subQ!W30/subQ!R30-1,"") | X38: =IFERROR(subQ!X30/subQ!S30-1,"") | Y38: =IFERROR(subQ!Y30/subQ!T30-1,"") | AA38: =IFERROR(subQ!AA30/subQ!V30-1,"") | AB38: =IFERROR(subQ!AB30/subQ!W30-1,"") | AC38: 0.053712178 | AD38: -0.20586516 | AF38: -0.03220323 | AG38: 0 | AH38: 0 | AI38: 0 | AK38: 0 | AL38: 0 | AM38: 0 | AN38: 0
A39: drv:영업활동현금흐름 | B39: yoy | C39: 영업활동현금흐름 YoY | J39: =IFERROR(subQ!J31/subQ!E31-1,"") | L39: =IFERROR(subQ!L31/subQ!G31-1,"") | M39: =IFERROR(subQ!M31/subQ!H31-1,"") | N39: =IFERROR(subQ!N31/subQ!I31-1,"") | O39: =IFERROR(subQ!O31/subQ!J31-1,"") | Q39: =IFERROR(subQ!Q31/subQ!L31-1,"") | R39: =IFERROR(subQ!R31/subQ!M31-1,"") | S39: =IFERROR(subQ!S31/subQ!N31-1,"") | T39: =IFERROR(subQ!T31/subQ!O31-1,"") | V39: =IFERROR(subQ!V31/subQ!Q31-1,"") | W39: =IFERROR(subQ!W31/subQ!R31-1,"") | X39: =IFERROR(subQ!X31/subQ!S31-1,"") | Y39: =IFERROR(subQ!Y31/subQ!T31-1,"") | AA39: =IFERROR(subQ!AA31/subQ!V31-1,"") | AB39: =IFERROR(subQ!AB31/subQ!W31-1,"")
A40: drv:주식수 | B40: qoq | C40: 주식수 QoQ | G40: =IFERROR(subQ!G32/subQ!E32-1,"") | H40: =IFERROR(subQ!H32/subQ!G32-1,"") | I40: =IFERROR(subQ!I32/subQ!H32-1,"") | J40: =IFERROR(subQ!J32/subQ!I32-1,"") | L40: =IFERROR(subQ!L32/subQ!J32-1,"") | M40: =IFERROR(subQ!M32/subQ!L32-1,"") | N40: =IFERROR(subQ!N32/subQ!M32-1,"") | O40: =IFERROR(subQ!O32/subQ!N32-1,"") | Q40: =IFERROR(subQ!Q32/subQ!O32-1,"") | R40: =IFERROR(subQ!R32/subQ!Q32-1,"") | S40: =IFERROR(subQ!S32/subQ!R32-1,"") | T40: =IFERROR(subQ!T32/subQ!S32-1,"") | V40: =IFERROR(subQ!V32/subQ!T32-1,"") | W40: =IFERROR(subQ!W32/subQ!V32-1,"") | X40: =IFERROR(subQ!X32/subQ!W32-1,"") | Y40: =IFERROR(subQ!Y32/subQ!X32-1,"") | AA40: =IFERROR(subQ!AA32/subQ!Y32-1,"") | AB40: =IFERROR(subQ!AB32/subQ!AA32-1,"") | AC40: 0 | AD40: 0 | AF40: 0 | AG40: 0 | AH40: 0 | AI40: 0 | AK40: 0 | AL40: 0 | AM40: 0 | AN40: 0
A41: drv:DPS | B41: abs | C41: DPS (가정, 원) | E41: =subQ!E35 | F41: =subQ!F35 | G41: =subQ!G35 | H41: =subQ!H35 | I41: =subQ!I35 | J41: =subQ!J35 | K41: =subQ!K35 | L41: =subQ!L35 | ... AB41: =subQ!AB35 | AD41: 500 | AE41: =subQ!AE35 | AI41: 500 | AJ41: =subQ!AJ35 | AN41: 500 | AO41: =subQ!AO35
B43: 3. 밸류에이션·스칼라 | C43: 노란 셀 = 가정. '연결' 표시는 추정 전 분기 수식이 이 셀을 참조한다는 뜻
A44: sc:종가 | C44: 종가 | D44: 76700 | E44: 원 — 네이버 정규장 종가(aik 확정종가 대조 · aik 77,600원)
A45: sc:기준일 | C45: 기준일 | D45: 20261008 | E45: 종가 기준일
A46: sc:COE | C46: COE | D46: 0.09 | E46: 자기자본비용(가정) — TP 적정 PBR = ROE/COE
A47: sc:PER_lo | C47: PER_lo | D47: 12.2 | E47: PER 밴드 하단(배) — hist_quarterly(분기 평균가 ÷ TTM EPS, 14분기, 25/50/75 백분위)
A48: sc:PER_mid | C48: PER_mid | D48: 18.1 | E48: PER 밴드 중단(배)
A49: sc:PER_hi | C49: PER_hi | D49: 26.6 | E49: PER 밴드 상단(배)
A50: sc:EPS_Y1가중 | C50: EPS_Y1가중 | D50: 0.5 | E50: 12M fwd EPS = FY(last_actual연도)E × w + FY+1E × (1−w) — 기준 분기 2Q 이면 0.5(가정)
A51: sc:세율 | C51: 세율 | D51: 0.18262069 | E51: 연결 — 법인세 = MAX(세전,0) × 세율(역산, 재현 오차 ≤ 0.05억 · 모델 assumptions 0.1826) · 최근 12분기 유효세율 -3.1% 가 5~27% 밖 → 클립 대신 최근 8분기 중 세전 > 0 인 6분기(2024Q3~2026Q2)의 법인세/세전 중위 18.3%
A52: sc:판관비율 | C52: 판관비율 | D52: 0.075780734 | E52: 연결 — 판관비 = 매출액 × 판관비율(역산, 재현 오차 ≤ 0.05억 · 모델 assumptions 0.0758)
A53: sc:지배주주비중 | C53: 지배주주비중 | D53: 1 | E53: 연결 — 지배주주순이익 = 당기순이익 × 비중(역산, 재현 오차 ≤ 0.05억)
A54: sc:이자율_자산 | C54: 이자율_자산 | D54: 0.023127736 | E54: 연결 — 이자손익 = (전분기 이자발생자산 × 자산이자율 − 전분기 총차입금 × 부채이자율)/4(역산, 재현 오차 ≤ 0.05억 · 모델 assumptions 0.0231)
A55: sc:이자율_부채 | C55: 이자율_부채 | D55: 0.042698316 | E55: 연결 — 같은 수식의 부채 쪽(총차입금 행이 없으면 0)(역산, 재현 오차 ≤ 0.05억 · 모델 assumptions 0.0427)
A56: sc:배당성향 | C56: 배당성향 | D56: 0.386 | E56: 배당성향(참고 — 모델은 직전 DPS 유지·Q2 지급 가정)
A57: sc:외화순노출_백만$ | C57: 외화순노출_백만$ | E57: 외화 순노출 × Δ기말환율 (외화 시트 방식) — 외화 순노출 미공시(face) → 0 + 표기
A58: sc:헤지비율 | C58: 헤지비율 | E58: sls 없음
A59: sc:헤지환율_약정 | C59: 헤지환율_약정 | E59: sls 없음

Sheet BS연결
B1: (백만원) | C1: 이름: BS연결H | E1: 4Q21 | F1: 2021 | G1: 1Q22 | H1: 2Q22 | I1: 3Q22 | J1: 4Q22 | K1: 2022 | L1: 1Q23 | M1: 2Q23 | N1: 3Q23 | O1: 4Q23 | P1: 2023 | Q1: 1Q24 | R1: 2Q24 | S1: 3Q24 | T1: 4Q24 | U1: 2024 | V1: 1Q25 | W1: 2Q25 | X1: 3Q25 | Y1: 4Q25 | Z1: 2025 | AA1: 1Q26 | AB1: 2Q26 | AC1: 3Q26 | AD1: 4Q26 | AE1: 2026 | AF1: 1Q27 | AG1: 2Q27 | AH1: 3Q27 | AI1: 4Q27 | AJ1: 2027 | AK1: 1Q28 | AL1: 2Q28 | AM1: 3Q28 | AN1: 4Q28 | AO1: 2028
B2: 연결 | D2: fin json(kship_fin.py)
B3: 한화시스템(연) | C3: UPDATE: 26-10-11 | E3: 1 | F3: 2 | G3: 3 | H3: 4 | I3: 5 | J3: 6 | K3: 7 | L3: 8 | M3: 9 | N3: 10 | O3: 11 | P3: 12 | Q3: 13 | R3: 14 | S3: 15 | T3: 16 | U3: 17 | V3: 18 | W3: 19 | X3: 20 | Y3: 21 | Z3: 22 | AA3: 23 | AB3: 24 | AC3: 25 | AD3: 26 | AE3: 27 | AF3: 28 | AG3: 29 | AH3: 30 | AI3: 31 | AJ3: 32 | AK3: 33 | AL3: 34 | AM3: 35 | AN3: 36 | AO3: 37
B4: Account Code | C4: AccountNAME | E4: 2021.12 | F4: 2021.12A | G4: 2022.03 | H4: 2022.06 | I4: 2022.09 | J4: 2022.12 | K4: 2022.12A | L4: 2023.03 | M4: 2023.06 | N4: 2023.09 | O4: 2023.12 | P4: 2023.12A | Q4: 2024.03 | R4: 2024.06 | S4: 2024.09 | T4: 2024.12 | U4: 2024.12A | V4: 2025.03 | W4: 2025.06 | X4: 2025.09 | Y4: 2025.12 | Z4: 2025.12A | AA4: 2026.03 | AB4: 2026.06 | AC4: 2026.09 | AD4: 2026.12 | AE4: 2026.12A | AF4: 2027.03 | AG4: 2027.06 | AH4: 2027.09 | AI4: 2027.12 | AJ4: 2027.12A | AK4: 2028.03 | AL4: 2028.06 | AM4: 2028.09 | AN4: 2028.12 | AO4: 2028.12A
A5: 1 | C5: 유동자산 | E5: 2676109.4 | F5: 2676109.4 | G5: 2071230.8 | H5: 2213495.5 | I5: 2182018.3 | J5: 2326839.8 | K5: 2326839.8 | L5: 2369967.6 | M5: 1786841.5 | N5: 1934736.2 | O5: 1890139.7 | P5: 1890139.7 | Q5: 2063469.5 | R5: 2325690.9 | S5: 2337727.3 | T5: 2286147.3 | U5: 2286147.3 | V5: 2418286.9 | W5: 2699940.2 | X5: 2855518.9 | Y5: 2928529.6 | Z5: 2928529.6 | AA5: 3157609.5 | AB5: 4666192.3
A6: 1 | C6: 현금및현금성자산 | E6: 1636831.2 | F6: 1636831.2 | G6: 958490.4 | H6: 1186796.2 | I6: 1008736 | J6: 1228217.7 | K6: 1228217.7 | L6: 991661.98 | M6: 514881.17 | N6: 541058.32 | O6: 476088.82 | P6: 476088.82 | Q6: 454384.22 | R6: 413662.48 | S6: 246643.66 | T6: 199842.74 | U6: 199842.74 | V6: 240375.74 | W6: 360013.44 | X6: 243848.2 | Y6: 325483.66 | Z6: 325483.66 | AA6: 492567.83 | AB6: 1591309.1
A7: 1 | C7: 매출채권및기타채권 | E7: 181114.56 | F7: 181114.56 | G7: 140859.54 | H7: 111942.26 | I7: 128296.83 | J7: 208560.92 | K7: 208560.92 | L7: 161337.5 | M7: 147970.28 | N7: 169227.01 | O7: 202103.1 | P7: 202103.1 | Q7: 251777.12 | R7: 290811.4 | S7: 264814.67 | T7: 309758.81 | U7: 309758.81 | V7: 251595.8 | W7: 238594.18 | X7: 313499.68 | Y7: 450887.46 | Z7: 450887.46 | AA7: 358037.84 | AB7: 449803.66
A8: 1 | C8: 기타유동금융자산 | E8: 27567.45 | F8: 27567.45 | G8: 25167.73 | H8: 19884.51 | I8: 26502.26 | J8: 25669.19 | K8: 25669.19 | L8: 161613.27 | M8: 19521.76 | N8: 37196.87 | O8: 34748.2 | P8: 34748.2 | Q8: 24160.51 | R8: 137314.71 | S8: 117048.93 | T8: 124138.31 | U8: 124138.31 | V8: 107170.97 | W8: 41973.47 | X8: 40074.41 | Y8: 164123.08 | Z8: 164123.08 | AA8: 162606.91 | AB8: 275220.18
A9: 1 | C9: 기타유동자산 | E9: 424551.09 | F9: 424551.09 | G9: 501934.23 | H9: 497584.55 | I9: 561594.48 | J9: 469952.75 | K9: 469952.75 | L9: 559831.21 | M9: 631304.16 | N9: 698945.67 | O9: 676114.3 | P9: 676114.3 | Q9: 763842.2 | R9: 851096.58 | S9: 1036019.9 | T9: 1025685.1 | U9: 1025685.1 | V9: 1113491.2 | W9: 1226913.5 | X9: 1314803.5 | Y9: 1177292.4 | Z9: 1177292.4 | AA9: 1222536.8 | AB9: 1358830.3
A10: 1 | C10: 재고자산 | E10: 406045.06 | F10: 406045.06 | G10: 444778.89 | H10: 397288.01 | I10: 456888.7 | J10: 372962.72 | K10: 372962.72 | L10: 495523.67 | M10: 473164.17 | N10: 488308.33 | O10: 501085.25 | P10: 501085.25 | Q10: 569305.42 | R10: 632788.84 | S10: 673183.26 | T10: 610096.27 | U10: 610096.27 | V10: 705653.19 | W10: 832445.59 | X10: 943293.2 | Y10: 810743.03 | Z10: 810743.03 | AA10: 921860.15 | AB10: 953529.03
A11: 1 | C11: 비유동자산 | E11: 1218193.3 | F11: 1218193.3 | G11: 1663560.8 | H11: 1713150.2 | I11: 1777753.1 | J11: 1618787.9 | K11: 1618787.9 | L11: 1674767.6 | M11: 2380954.9 | N11: 2460087.8 | O11: 2593071.2 | P11: 2593071.2 | Q11: 2667756.3 | R11: 2685541.7 | S11: 2722679.6 | T11: 3437862.8 | U11: 3437862.8 | V11: 4794326 | W11: 5342920.4 | X11: 6716552 | Y11: 7398735.9 | Z11: 7398735.9 | AA11: 7663054.1 | AB11: 7181132.6
A12: 1 | C12: 장기금융자산 | E12: 167383.88 | F12: 167383.88 | G12: 633442.66 | H12: 665642.73 | I12: 721417.59 | J12: 553749.04 | K12: 553749.04 | L12: 549872.02 | M12: 559925.06 | N12: 548021.68 | O12: 313244.37 | P12: 313244.37 | Q12: 370111.27 | R12: 324802.47 | S12: 324788.49 | T12: 440588.06 | U12: 440588.06 | V12: 470194.7 | W12: 632598.3 | X12: 719196.83 | Y12: 659129.16 | Z12: 659129.16 | AA12: 602052.88 | AB12: 574130.17
A13: 1 | C13: 투자자산 | E13: 195934.2 | F13: 195934.2 | G13: 657228.77 | H13: 682547.1 | I13: 739718.05 | J13: 570182.24 | K13: 570182.24 | L13: 639147.18 | M13: 1369478.4 | N13: 1398313.7 | O13: 1305753.2 | P13: 1305753.2 | Q13: 1363596.4 | R13: 1316986.5 | S13: 1289467.7 | T13: 465139.59 | U13: 465139.59 | V13: 489496.04 | W13: 650260.85 | X13: 829324.17 | Y13: 1207613.2 | Z13: 1207613.2 | AA13: 1220336.3 | AB13: 574130.17
A14: 1 | C14: 종속기업및관계기업투자 | E14: 28550.32 | F14: 28550.32 | G14: 23786.11 | H14: 16904.37 | I14: 18300.46 | J14: 16433.2 | K14: 16433.2 | L14: 89275.16 | M14: 809553.32 | N14: 850292.05 | O14: 992508.82 | P14: 992508.82 | Q14: 993485.13 | R14: 992184.02 | S14: 964679.23 | T14: 24551.53 | U14: 24551.53 | V14: 19301.34 | W14: 17662.55 | X14: 110127.34 | Y14: 548484.06 | Z14: 548484.06 | AA14: 618283.41
A15: 1 | C15: 유형자산 | E15: 256905.96 | F15: 256905.96 | G15: 252637.54 | H15: 274600.35 | I15: 273265.61 | J15: 274368.03 | K15: 274368.03 | L15: 302997.24 | M15: 307580.98 | N15: 335100.92 | O15: 347646.33 | P15: 347646.33 | Q15: 372628.71 | R15: 410190.35 | S15: 434393.19 | T15: 569952.77 | U15: 569952.77 | V15: 607018.91 | W15: 673066.16 | X15: 715329.96 | Y15: 822739.44 | Z15: 822739.44 | AA15: 869841.2 | AB15: 923316.25
A16: 1 | C16: 사용권자산 | E16: 101068.99 | F16: 101068.99 | G16: 95800.75 | H16: 93039.6 | I16: 97212.17 | J16: 100640.33 | K16: 100640.33 | L16: 94602.64 | M16: 88817.05 | N16: 109253.11 | O16: 117782.08 | P16: 117782.08 | Q16: 117358.17 | R16: 110732.6 | S16: 142958.81 | T16: 154215.14 | U16: 154215.14 | V16: 146705.81 | W16: 139745.56 | X16: 132572.46 | Y16: 191329.22 | Z16: 191329.22 | AA16: 189788.54 | AB16: 188868.87
A17: 1 | C17: 기타비유동자산 | E17: 103654.8 | F17: 103654.8 | G17: 99249.37 | H17: 96700.21 | I17: 100855.85 | J17: 105049.47 | K17: 105049.47 | L17: 98539.18 | M17: 92971.72 | N17: 112842.2 | O17: 122398.3 | P17: 122398.3 | Q17: 121612.03 | R17: 114708.65 | S17: 147714.95 | T17: 160954.83 | U17: 160954.83 | V17: 153914.07 | W17: 146606.4 | X17: 152432.73 | Y17: 210721.84 | Z17: 210721.84 | AA17: 211037.73 | AB17: 209466.19
A18: 1 | C18: 무형자산 | E18: 562162.92 | F18: 562162.92 | G18: 559190.23 | H18: 560853.63 | I18: 562774.46 | J18: 557833.98 | K18: 557833.98 | L18: 556422.16 | M18: 555153.48 | N18: 555337.34 | O18: 558922.41 | P18: 558922.41 | Q18: 553061.67 | R18: 562261.41 | S18: 565382.81 | T18: 762189.51 | U18: 762189.51 | V18: 759170.73 | W18: 756130.12 | X18: 750473.69 | Y18: 709755.42 | Z18: 709755.42 | AA18: 709358.13
A19: 1 | C19: 이연법인세자산 | E19: 81719.78 | F19: 81719.78 | G19: 77212.85 | H19: 76372.27 | I19: 77904.25 | J19: 87386.88 | K19: 87386.88 | L19: 54281.9 | M19: 30913.03 | N19: 30695.95 | O19: 77888.32 | P19: 77888.32 | Q19: 80676.72 | R19: 112159.34 | S19: 109599.88 | T19: 41589.41 | U19: 41589.41 | V19: 14077.56 | W19: 8681.79 | X19: 8328.51 | Y19: 16578.71 | Z19: 16578.71 | AA19: 20513.61 | AB19: 27063.24
A20: 1 | C20: 자산총계 | E20: 3894302.6 | F20: 3894302.6 | G20: 3734791.6 | H20: 3926645.7 | I20: 3959771.4 | J20: 3945627.7 | K20: 3945627.7 | L20: 4044735.2 | M20: 4167796.4 | N20: 4394824 | O20: 4483210.8 | P20: 4483210.8 | Q20: 4731225.8 | R20: 5011232.6 | S20: 5060406.9 | T20: 5724010.1 | U20: 5724010.1 | V20: 7212612.8 | W20: 8042860.7 | X20: 9572071 | Y20: 10327266 | Z20: 10327266 | AA20: 10820664 | AB20: 11847325
A21: 1 | C21: 유동부채 | E21: 1363163.3 | F21: 1363163.3 | G21: 1225479.3 | H21: 1452996.4 | I21: 1436892.7 | J21: 1618535.6 | K21: 1618535.6 | L21: 1587063.3 | M21: 1640871.9 | N21: 1781226.5 | O21: 1951414.8 | P21: 1951414.8 | Q21: 2170441.1 | R21: 2167709.4 | S21: 2271473.5 | T21: 2677051.5 | U21: 2677051.5 | V21: 2897194.7 | W21: 2992558.8 | X21: 3192807.5 | Y21: 3334859.8 | Z21: 3334859.8 | AA21: 3514271.4 | AB21: 5354369.3
A22: 1 | C22: 매입채무및기타채무 | E22: 125173.01 | F22: 125173.01 | G22: 125284.93 | H22: 112848.63 | I22: 107061.22 | J22: 160863.44 | K22: 160863.44 | L22: 210002.7 | M22: 116868.83 | N22: 107073.7 | O22: 213095.62 | P22: 213095.62 | Q22: 234773.41 | R22: 215163.82 | S22: 166186.57 | T22: 250001.34 | U22: 250001.34 | V22: 345784.37 | W22: 267463.73 | X22: 365541.88 | Y22: 480878.76 | Z22: 480878.76 | AA22: 536933.02 | AB22: 379114.46
A23: 1 | C23: 단기차입금 | E23: 29986.12 | F23: 29986.12 | G23: 29992.82 | H23: 0 | I23: 50000 | J23: 80000 | K23: 80000 | L23: 80000 | M23: 80000 | N23: 289988.04 | O23: 162334.77 | P23: 162334.77 | Q23: 319996.02 | R23: 209999.79 | S23: 130056.02 | T23: 79955.19 | U23: 79955.19 | V23: 244634.77 | W23: 203864.65 | X23: 389958.29 | Y23: 401210.4 | Z23: 401210.4 | AA23: 546707.92 | AB23: 2163871.5
A24: 1 | C24: 단기금융부채(face) | E24: 29986.12 | F24: 29986.12 | G24: 29992.82 | H24: 0 | I24: 50000 | L24: 80000 | M24: 80000 | N24: 289988.04 | O24: 162334.77 | P24: 162334.77 | Q24: 319996.02 | R24: 209999.79 | S24: 130056.02 | T24: 79955.19 | U24: 79955.19 | V24: 244634.77 | W24: 203864.65 | X24: 389958.29 | Y24: 401210.4 | Z24: 401210.4 | AA24: 546707.92 | AB24: 2163871.5
A25: 1 | C25: 기타유동금융부채 | E25: 70856.03 | F25: 70856.03 | G25: 50838.48 | H25: 51656.58 | I25: 58168.37 | J25: 79617.42 | K25: 79617.42 | L25: 60084.97 | M25: 69779.68 | N25: 69432.29 | O25: 93424.94 | P25: 93424.94 | Q25: 67996.06 | R25: 71334.47 | S25: 83849.04 | T25: 195531.57 | U25: 195531.57 | V25: 124861.04 | W25: 149038.6 | X25: 174229.82 | Y25: 247603.2 | Z25: 247603.2 | AA25: 215824.56 | AB25: 233308.71
A26: 1 | C26: 단기금융부채 | E26: 70856.03 | F26: 70856.03 | G26: 50838.48 | H26: 51656.58 | I26: 58168.37 | J26: 79617.42 | K26: 79617.42 | L26: 60084.97 | M26: 69779.68 | N26: 69432.29 | O26: 93424.94 | P26: 93424.94 | Q26: 67996.06 | R26: 71334.47 | S26: 83849.04 | T26: 195531.57 | U26: 195531.57 | V26: 124861.04 | W26: 149038.6 | X26: 174229.82 | Y26: 247603.2 | Z26: 247603.2 | AA26: 215824.56 | AB26: 233308.71
A27: 1 | C27: 기타유동부채 | E27: 1111361.1 | F27: 1111361.1 | G27: 997671.88 | H27: 1270618.7 | I27: 1197271.1 | J27: 1252876.2 | K27: 1252876.2 | L27: 1203201.1 | M27: 1334719.1 | N27: 1271834.4 | O27: 1432347.3 | P27: 1432347.3 | Q27: 1494639.6 | R27: 1628194.4 | S27: 1849992.3 | T27: 2027772.1 | U27: 2027772.1 | V27: 2090673.8 | W27: 2300085.8 | X27: 2184475.8 | Y27: 2106457.9 | Z27: 2106457.9 | AA27: 2138505.9 | AB27: 2508841.6
A28: 1 | C28: 단기충당부채 | E28: 10475.01 | F28: 10475.01 | G28: 10782.41 | H28: 9174.43 | I28: 15589.43 | J28: 22953.73 | K28: 22953.73 | L28: 19267.13 | M28: 24497.65 | N28: 22914.93 | O28: 31754.6 | P28: 31754.6 | Q28: 28816.23 | R28: 22772.1 | S28: 26263.65 | T28: 83709.54 | U28: 83709.54 | V28: 69394.05 | W28: 61258.61 | X28: 58915.2 | Y28: 63950.21 | Z28: 63950.21 | AA28: 52769.85 | AB28: 39973.75
A29: 1 | C29: 당기법인세부채(미지급법인세) | E29: 15312.02 | F29: 15312.02 | G29: 10908.78 | H29: 8698.08 | I29: 8802.61 | J29: 14839.62 | K29: 14839.62 | L29: 14507.47 | M29: 15006.68 | N29: 19983.24 | O29: 18457.56 | P29: 18457.56 | Q29: 24219.79 | R29: 20244.8 | S29: 15125.9 | T29: 37318.84 | U29: 37318.84 | V29: 21846.7 | W29: 10847.38 | X29: 19686.55 | Y29: 34759.3 | Z29: 34759.3 | AA29: 23530.12 | AB29: 29259.2
A30: 1 | C30: 비유동부채 | E30: 291377.86 | F30: 291377.86 | G30: 290775.72 | H30: 293510.47 | I30: 303533.63 | J30: 308140.1 | K30: 308140.1 | L30: 309593.68 | M30: 310469.31 | N30: 353578.76 | O30: 377669.9 | P30: 377669.9 | Q30: 392965.39 | R30: 645297.99 | S30: 593090.16 | T30: 630541.75 | U30: 630541.75 | V30: 902350.01 | W30: 1244532 | X30: 1519496.8 | Y30: 1991406.7 | Z30: 1991406.7 | AA30: 2263602.3 | AB30: 1921296.9
A31: 1 | C31: 장기차입금 | E31: 0 | F31: 0 | G31: 0 | H31: 0 | I31: 0 | J31: 0 | K31: 0 | L31: 0 | M31: 0 | N31: 0 | O31: 49899.32 | P31: 49899.32 | Q31: 140 | R31: 140 | S31: 249185.35 | T31: 249276.74 | U31: 249276.74 | V31: 290667.02 | W31: 489861.28 | X31: 558310.01 | Y31: 1073225.9 | Z31: 1073225.9 | AA31: 1306257.3 | AB31: 1096911.1
A32: 1 | C32: 기타비유동금융부채 | E32: 80085.85 | F32: 80085.85 | G32: 75456.36 | H32: 72227.29 | I32: 75484.13 | J32: 77868.38 | K32: 77868.38 | L32: 75418.64 | M32: 72037.07 | N32: 89211.63 | O32: 99017.34 | P32: 99017.34 | Q32: 100830.43 | R32: 97406.52 | S32: 131057.96 | T32: 132646.05 | U32: 132646.05 | V32: 136787.94 | W32: 131031.93 | X32: 129607.65 | Y32: 140849.54 | Z32: 140849.54 | AA32: 155383.58 | AB32: 140138.64
A33: 1 | C33: 장기금융부채 | E33: 80085.85 | F33: 80085.85 | G33: 75456.36 | H33: 72227.29 | I33: 75484.13 | J33: 77868.38 | K33: 77868.38 | L33: 75418.64 | M33: 72037.07 | N33: 89211.63 | O33: 99017.34 | P33: 99017.34 | Q33: 100830.43 | R33: 97406.52 | S33: 131057.96 | T33: 132646.05 | U33: 132646.05 | V33: 136787.94 | W33: 131031.93 | X33: 129607.65 | Y33: 140849.54 | Z33: 140849.54 | AA33: 155383.58 | AB33: 140138.64
A34: 1 | C34: 확정급여부채 | E34: 160419.16 | F34: 160419.16 | G34: 164325.31 | H34: 169696.52 | I34: 174978.65 | J34: 180295.29 | K34: 180295.29 | L34: 183662.8 | M34: 187353.93 | N34: 192526.89 | O34: 206769.51 | P34: 206769.51 | Q34: 215215.89 | R34: 222771.94 | S34: 185986.69 | T34: 207330.08 | U34: 207330.08 | V34: 214432 | W34: 226999.46 | X34: 232970.91 | Y34: 151006.05 | Z34: 151006.05 | AA34: 150019.27 | AB34: 156314.24
A35: 1 | C35: 장기충당부채 | E35: 20444.74 | F35: 20444.74 | G35: 21030.68 | H35: 21619.24 | I35: 23099.33 | J35: 19866.57 | K35: 19866.57 | L35: 20398.65 | M35: 20967.31 | N35: 21828.9 | O35: 21983.73 | P35: 21983.73 | Q35: 22365.43 | R35: 23047.55 | S35: 23765.49 | T35: 30505.07 | U35: 30505.07 | V35: 31211.51 | W35: 32308.55 | X35: 33195.88 | Y35: 47254.28 | Z35: 47254.28 | AA35: 48528.7 | AB35: 49835.25
A36: 1 | C36: 이연법인세부채 | E36: 0 | F36: 0 | J36: 7.04 | K36: 7.04 | L36: 6.71 | M36: 0 | N36: 0 | O36: 0 | P36: 0 | Q36: 4500.3 | R36: 2910.09 | S36: 3094.67 | T36: 10783.8 | U36: 10783.8 | V36: 229251.55 | W36: 364330.76 | X36: 565412.35 | Y36: 579070.95 | Z36: 579070.95 | AA36: 603413.39 | AB36: 478097.63
A37: 1 | C37: 부채총계 | E37: 1654541.2 | F37: 1654541.2 | G37: 1516255 | H37: 1746506.9 | I37: 1740426.4 | J37: 1926675.7 | K37: 1926675.7 | L37: 1896657 | M37: 1951341.3 | N37: 2134805.3 | O37: 2329084.7 | P37: 2329084.7 | Q37: 2563406.5 | R37: 2813007.4 | S37: 2864563.6 | T37: 3307593.2 | U37: 3307593.2 | V37: 3799544.7 | W37: 4237090.7 | X37: 4712304.3 | Y37: 5326266.5 | Z37: 5326266.5 | AA37: 5777873.6 | AB37: 7275666.2
A38: 1 | C38: 지배주주지분 | E38: 2222498.1 | F38: 2222498.1 | G38: 2202290.4 | H38: 2164764.1 | I38: 2200040.2 | J38: 2000339 | K38: 2000339 | L38: 2130862.4 | M38: 2200004.1 | N38: 2243378 | O38: 2139817.9 | P38: 2139817.9 | Q38: 2151948.2 | R38: 2183606.2 | S38: 2182511.9 | T38: 2490055 | U38: 2490055 | V38: 3357851.8 | W38: 3721430.3 | X38: 4755342.2 | Y38: 4849228.7 | Z38: 4849228.7 | AA38: 4943895.6 | AB38: 4492709.7
A39: 1 | C39: 자본금 | E39: 944596.94 | F39: 944596.94 | G39: 944596.94 | H39: 944596.94 | I39: 944596.94 | J39: 944596.94 | K39: 944596.94 | L39: 944596.94 | M39: 944596.94 | N39: 944596.94 | O39: 944596.94 | P39: 944596.94 | Q39: 944596.94 | R39: 944596.94 | S39: 944596.94 | T39: 944596.94 | U39: 944596.94 | V39: 944596.94 | W39: 944596.94 | X39: 944596.94 | Y39: 944596.94 | Z39: 944596.94 | AA39: 944596.94 | AB39: 944596.94
A40: 1 | C40: 자본잉여금 | E40: 1084938.9 | F40: 1084938.9 | G40: 1085079.9 | H40: 1085529.2 | I40: 1086220 | J40: 1085520.5 | K40: 1085520.5 | L40: 1086702.8 | M40: 1088049.5 | N40: 1100125.9 | O40: 1100087.1 | P40: 1100087.1 | Q40: 844765.57 | R40: 845562.96 | S40: 846253.93 | T40: 1092001.1 | U40: 1092001.1 | V40: 1092202.3 | W40: 1114239 | X40: 1116579.9 | Y40: 1122977.3 | Z40: 1122977.3 | AA40: 1124166.7 | AB40: 1126777.3
A41: 1 | C41: 기타자본 | E41: -34121.41 | F41: -34121.41 | G41: -34121.41 | H41: -34121.41 | I41: -34121.41 | J41: -34121.41 | K41: -34121.41 | L41: -34121.41 | M41: -34121.41 | N41: -34121.41 | O41: -34121.41 | P41: -34121.41 | Q41: -34121.41 | R41: -34121.41 | S41: -34121.41 | T41: -34121.41 | U41: -34121.41 | V41: -34121.41 | W41: -34121.41 | X41: -34121.41 | Y41: -34121.41 | Z41: -34121.41 | AA41: -34121.41 | AB41: -34121.41
A42: 1 | C42: 기타포괄이익누계액 | E42: 2353.6 | F42: 2353.6 | G42: 309.8 | H42: 7857.64 | I42: 38873.17 | J42: -112582.46 | K42: -112582.46 | L42: -122820.77 | M42: -131350.79 | N42: 21828.54 | O42: -83216.98 | P42: -83216.98 | Q42: -69848.95 | R42: -66719.76 | S42: -77341.52 | T42: -101713.58 | U42: -101713.58 | V42: 793494.78 | W42: 1170967.2 | X42: 2050860.9 | Y42: 2107066.9 | Z42: 2107066.9 | AA42: 2349041.4 | AB42: 1825336
A43: 1 | C43: 이익잉여금 | E43: 224730.05 | F43: 224730.05 | G43: 206425.2 | H43: 160901.66 | I43: 164471.53 | J43: 116925.41 | K43: 116925.41 | L43: 256504.84 | M43: 332829.81 | N43: 210948.11 | O43: 212472.26 | P43: 212472.26 | Q43: 466556.03 | R43: 494287.49 | S43: 503124 | T43: 589291.87 | U43: 589291.87 | V43: 561679.13 | W43: 525748.6 | X43: 677425.91 | Y43: 708708.93 | Z43: 708708.93 | AA43: 560212.07 | AB43: 630120.8
A44: 1 | C44: 비지배주주지분 | E44: 17263.42 | F44: 17263.42 | G44: 16246.18 | H44: 15374.74 | I44: 19304.85 | J44: 18613.06 | K44: 18613.06 | L44: 17215.85 | M44: 16451.07 | N44: 16640.65 | O44: 14308.24 | P44: 14308.24 | Q44: 15871.06 | R44: 14618.93 | S44: 13331.32 | T44: -73638.07 | U44: -73638.07 | V44: 55216.35 | W44: 84339.59 | X44: 104424.43 | Y44: 151770.39 | Z44: 151770.39 | AA44: 98894.34 | AB44: 78948.99
A45: 1 | C45: 자본총계 | E45: 2239761.5 | F45: 2239761.5 | G45: 2218536.6 | H45: 2180138.8 | I45: 2219345.1 | J45: 2018952 | K45: 2018952 | L45: 2148078.3 | M45: 2216455.1 | N45: 2260018.7 | O45: 2154126.2 | P45: 2154126.2 | Q45: 2167819.2 | R45: 2198225.2 | S45: 2195843.3 | T45: 2416416.9 | U45: 2416416.9 | V45: 3413068.1 | W45: 3805769.9 | X45: 4859766.7 | Y45: 5000999.1 | Z45: 5000999.1 | AA45: 5042790 | AB45: 4571658.7
A46: 1 | C46: 부채와자본총계 | E46: 3894302.6 | F46: 3894302.6 | G46: 3734791.6 | H46: 3926645.7 | I46: 3959771.4 | J46: 3945627.7 | K46: 3945627.7 | L46: 4044735.2 | M46: 4167796.4 | N46: 4394824 | O46: 4483210.8 | P46: 4483210.8 | Q46: 4731225.8 | R46: 5011232.6 | S46: 5060406.9 | T46: 5724010.1 | U46: 5724010.1 | V46: 7212612.8 | W46: 8042860.7 | X46: 9572071 | Y46: 10327266 | Z46: 10327266 | AA46: 10820664 | AB46: 11847325
A47: 1 | C47: 총차입금 | E47: 59945.52 | F47: 59945.52 | G47: 59956.19 | H47: 29967.41 | I47: 79971.52 | J47: 109975.65 | K47: 109975.65 | L47: 109979.71 | M47: 109983.84 | N47: 339872.22 | O47: 212234.09 | P47: 212234.09 | Q47: 370049.37 | R47: 509161.67 | S47: 379241.37 | T47: 329231.93 | U47: 329231.93 | V47: 535301.79 | W47: 693725.93 | X47: 948268.3 | Y47: 1474436.2 | Z47: 1474436.2 | AA47: 1852965.2 | AB47: 3260782.6
A48: 1 | C48: 순차입금 | E48: -1576885.7 | F48: -1576885.7 | G48: -898534.21 | H48: -1156828.8 | I48: -928764.51 | J48: -1118242 | K48: -1118242 | L48: -881682.27 | M48: -404897.33 | N48: -201186.1 | O48: -263854.73 | P48: -263854.73 | Q48: -84334.85 | R48: 95499.19 | S48: 132597.71 | T48: 129389.19 | U48: 129389.19 | V48: 294926.05 | W48: 333712.49 | X48: 704420.1 | Y48: 1148952.6 | Z48: 1148952.6 | AA48: 1360397.4 | AB48: 1669473.6
A49: 1 | C49: 이자발생자산 | E49: 1804215.1 | F49: 1804215.1 | G49: 1591933.1 | H49: 1852438.9 | I49: 1730153.6 | J49: 1781966.7 | K49: 1781966.7 | L49: 1541534 | M49: 1074806.2 | N49: 1089080 | O49: 789333.19 | P49: 789333.19 | Q49: 824495.49 | R49: 738464.95 | S49: 571432.15 | T49: 640430.8 | U49: 640430.8 | V49: 710570.44 | W49: 992611.74 | X49: 963045.03 | Y49: 984612.82 | Z49: 984612.82 | AA49: 1094620.7 | AB49: 2165439.3
A50: 1 | C50: 사채 | E50: 29959.4 | F50: 29959.4 | G50: 29963.37 | H50: 29967.41 | I50: 29971.52 | J50: 29975.65 | K50: 29975.65 | L50: 29979.71 | M50: 29983.84 | N50: 49884.18 | Q50: 49913.35 | R50: 299021.88
A51: 1 | C51: 매각예정비유동자산및처분자산 | J51: 21476.55 | K51: 21476.55 | L51: 0 | M51: 0 | N51: 0
A52: 1 | C52: 장기매입채무및기타채무 | L52: 127.17 | M52: 127.17 | N52: 127.17 | O52: 0 | P52: 0 | T52: 0 | U52: 0
A53: 1 | C53: 장기매출채권및기타채권 | O53: 0 | P53: 0
A54: 1 | C54: 매각예정부채 | O54: 0 | P54: 0
A55: 1 | C55: 장기금융부채(face) | O55: 49899.32 | P55: 49899.32 | AB55: 1096911.1
A56: 1 | C56: 단기투자자산(공정가치) | AB56: 37500
A57: 1 | C57: 매출액(수익) | E57: 679524.8 | G57: 429564.43 | H57: 510494.18 | I57: 459399.84 | J57: 788543.91 | K57: 2188002.4 | L57: 439516.49 | M57: 610676.67 | N57: 620823.05 | O57: 782063.33 | P57: 2453079.5 | Q57: 544363.76 | R57: 687318.65 | S57: 639172.02 | T57: 932831.63 | U57: 2803686.1 | V57: 690100.71 | W57: 768190.55 | X57: 807736.58 | Y57: 1398122.7 | Z57: 3664150.6 | AA57: 807099.19 | AB57: 1117551.7
A58: 1 | C58: 매출원가 | E58: 614496.32 | G58: 365999.66 | H58: 438747.17 | I58: 402722.09 | J58: 727219.99 | K58: 1934688.9 | L58: 374825.19 | M58: 526282.88 | N58: 533282.67 | O58: 714379.65 | P58: 2148770.4 | Q58: 458056.49 | R58: 559965.96 | S58: 533232.86 | T58: 836638.23 | U58: 2387893.5 | V58: 578635.67 | W58: 674777.55 | X58: 721119.63 | Y58: 1297885.4 | Z58: 3272418.3 | AA58: 698573.34 | AB58: 933202.56
A59: 1 | C59: 매출총이익 | E59: 65028.49 | G59: 63564.76 | H59: 71747 | I59: 56677.75 | J59: 61323.92 | K59: 253313.43 | L59: 64691.3 | M59: 84393.78 | N59: 87540.38 | O59: 67683.68 | P59: 304309.14 | Q59: 86307.27 | R59: 127352.69 | S59: 105939.17 | T59: 96193.4 | U59: 415792.53 | V59: 111465.04 | W59: 93413 | X59: 86616.96 | Y59: 100237.3 | Z59: 391732.3 | AA59: 108525.85 | AB59: 184349.1
A60: 1 | C60: 판관비 | E60: 57680.09 | G60: 48402.79 | H60: 55320.07 | I60: 56136.4 | J60: 69431.97 | K60: 229291.23 | L60: 56305.61 | M60: 58461.6 | N60: 50207.83 | O60: 46463.38 | P60: 211438.42 | Q60: 47042.89 | R60: 47515.4 | S60: 48940.46 | T60: 52948.47 | U60: 196447.22 | V60: 53300.69 | W60: 59961.53 | X60: 64095.96 | Y60: 94475.39 | Z60: 271833.57 | AA60: 74241.36 | AB60: 80697.21
A61: 1 | C61: 영업이익 | E61: 7348.38 | G61: 15161.97 | H61: 16426.93 | I61: 541.35 | J61: -8108.05 | K61: 24022.2 | L61: 8385.69 | M61: 25932.19 | N61: 37332.55 | O61: 21220.3 | P61: 92870.73 | Q61: 39264.37 | R61: 79837.29 | S61: 56998.7 | T61: 43244.94 | U61: 219345.3 | V61: 58164.35 | W61: 33451.47 | X61: 22520.99 | Y61: 5761.91 | Z61: 119898.72 | AA61: 34284.49 | AB61: 103651.89
A62: 1 | C62: 기타영업외수익 | E62: 26302.88 | G62: 892.7 | H62: 167.1 | I62: 291.49 | J62: 6727.42 | K62: 8078.71 | L62: 214767.76 | M62: 119784.94 | N62: -3436.2 | O62: 51555.05 | P62: 382671.55 | Q62: 43964 | R62: -4703.06 | S62: 5775.49 | T62: 426152.72 | U62: 471189.15 | V62: 39556.43 | W62: 85352.01 | X62: 52533.21 | Y62: -31095.65 | Z62: 146346 | AA62: 8075.17 | AB62: 3518.91
A63: 1 | C63: 기타영업외비용 | E63: 7105.5 | G63: 1643.53 | H63: 54041.65 | I63: 3849.57 | J63: 26084.71 | K63: 85619.46 | L63: 2331.2 | M63: 3127.75 | N63: 3159.15 | O63: 37621.12 | P63: 46239.22 | Q63: 1815.71 | R63: 50429.7 | S63: 4311.36 | T63: 48624.74 | U63: 105181.51 | V63: 62821.42 | W63: 15729.01 | X63: 467.73 | Y63: 73804.65 | Z63: 152822.81 | AA63: 161942.07 | AB63: 30107
A64: 1 | C64: 금융수익 | E64: 3286.11 | G64: 9508.63 | H64: 7999.56 | I64: 22206.52 | J64: -3892.62 | K64: 35822.09 | L64: 14675.94 | M64: 8329.21 | N64: 10329.05 | O64: -1611.54 | P64: 31722.66 | Q64: 8653.79 | R64: 8352.42 | S64: 2103.12 | T64: 28954.28 | U64: 48063.61 | V64: 16395.09 | W64: 12005.64 | X64: 21018.27 | Y64: 3907.33 | Z64: 53326.33 | AA64: 36184.39 | AB64: 26151.87
A65: 1 | C65: 금융비용 | E65: 255.56 | G65: 2039.75 | H65: 1229.43 | I65: 2707.21 | J65: 6638.27 | K65: 12614.66 | L65: 3254.83 | M65: 3200.66 | N65: 4400.08 | O65: 6929.32 | P65: 17784.89 | Q65: 5229.79 | R65: 6397.55 | S65: 24490.67 | T65: 3289.25 | U65: 39407.26 | V65: 10108.29 | W65: 35539.5 | X65: -2472.48 | Y65: 3276.25 | Z65: 46451.56 | AA65: 25285.27 | AB65: 43068.36
A66: 1 | C66: 종속기업,공동지배기업및관계기업관련손익 | E66: -4036.03 | G66: -4649 | H66: -7363.58 | I66: -7269.39 | J66: -7426.34 | K66: -26708.31 | L66: -7617.2 | M66: -38771.44 | N66: 14887.31 | O66: 1706.5 | P66: -29794.83 | Q66: -23995.83 | R66: -18091.53 | S66: -21619.62 | T66: 51110.63 | U66: -12596.35 | V66: -1914.58 | W66: -1150.11 | X66: -977.15 | Y66: -1272.54 | Z66: -5314.38 | AA66: -7018.32
A67: 1 | C67: 지분법관련손익 | E67: -4036.03 | G67: -4649 | H67: -7363.58 | I67: -7269.39 | J67: -7426.34 | K67: -26708.31 | L67: -7617.2 | M67: -38771.44 | N67: 14887.31 | O67: 1706.5 | P67: -29794.83 | Q67: -23995.83 | R67: -18091.53 | S67: -21619.62 | T67: 51110.63 | U67: -12596.35 | V67: -1914.58 | W67: -1150.11 | X67: -977.15 | Y67: -1272.54 | Z67: -5314.38 | AA67: -7018.32
A68: 1 | C68: 법인세비용차감전계속사업이익 | E68: 25540.28 | G68: 17231.01 | H68: -38041.06 | I68: 9213.19 | J68: -45422.58 | K68: -57019.44 | L68: 224626.17 | M68: 108946.49 | N68: 51553.49 | O68: 28319.87 | P68: 413446.02 | Q68: 60840.83 | R68: 8567.88 | S68: 14455.67 | T68: 497548.55 | U68: 581412.93 | V68: 39271.58 | W68: 78390.5 | X68: 97100.08 | Y68: -99779.85 | Z68: 114982.31 | AA68: -115701.62 | AB68: 54367.43
A69: 1 | C69: 법인세비용 | E69: 4681.22 | G69: 6634.18 | H69: 8353.92 | I69: 6633.46 | J69: 2119.19 | K69: 23740.75 | L69: 39687.26 | M69: 34205.2 | N69: 10396.65 | O69: -26894.19 | P69: 57394.92 | Q69: 9132.08 | R69: -18463.74 | S69: 5839.31 | T69: 107750.9 | U69: 104258.55 | V69: 5838.64 | W69: 30941.67 | X69: -54834.78 | Y69: -67683.29 | Z69: -85737.76 | AA69: -26663 | AB69: 2683.28
A70: 1 | C70: 계속사업이익 | E70: 20859.06 | G70: 10596.83 | H70: -46394.98 | I70: 2579.72 | J70: -47541.76 | K70: -80760.19 | L70: 184938.9 | M70: 74741.29 | N70: 41156.85 | O70: 55214.05 | P70: 356051.09 | Q70: 51708.75 | R70: 27031.61 | S70: 8616.36 | T70: 389797.66 | U70: 477154.38 | V70: 33432.94 | W70: 47448.83 | X70: 151934.85 | Y70: -32096.56 | Z70: 200720.06 | AA70: -89038.63 | AB70: 51684.15
A71: 1 | C71: 당기순이익 | E71: 20859.06 | G71: 10596.83 | H71: -46394.98 | I71: 2579.72 | J71: -47541.76 | K71: -80760.19 | L71: 184938.9 | M71: 74741.29 | N71: 41156.85 | O71: 42246.25 | P71: 343083.29 | Q71: 50323.26 | R71: 27036.13 | S71: 8144.57 | T71: 359874.87 | U71: 445378.83 | V71: 40969.85 | W71: 47009.43 | X71: 151796.4 | Y71: -30630.39 | Z71: 209145.29 | AA71: -95751.91 | AB71: 52742.89
A72: 1 | C72: (지배주주지분)당기순이익 | E72: 21295.64 | G72: 11614.07 | H72: -45523.54 | I72: 3569.87 | J72: -46216.2 | K72: -76555.8 | L72: 186368.28 | M72: 76324.97 | N72: 42828.56 | O72: 43699.48 | P72: 349221.29 | Q72: 51805.06 | R72: 28297.24 | S72: 9402.19 | T72: 364795.58 | U72: 454300.07 | V72: 37834.9 | W72: 40905.5 | X72: 151677.31 | Y72: 11814.06 | Z72: 242231.77 | AA72: -54978.69 | AB72: 67081.56
A73: 1 | C73: 총포괄손익 | E73: 18786.23 | G73: 8553.03 | H73: -38847.14 | I73: 33595.26 | J73: -200393.05 | K73: -197091.9 | L73: 174677.15 | M73: 66221.27 | N73: 30276.65 | O73: -104492.34 | P73: 166682.73 | Q73: 63720.92 | R73: 30174.31 | S73: -2507.19 | T73: 319417.28 | U73: 410805.32 | V73: 933551.25 | W73: 370631.17 | X73: 1051655.9 | Y73: 41169.54 | Z73: 2397007.8 | AA73: 134119.67 | AB73: -473761.3
A74: 1 | C74: 금융손익 | E74: 3030.55 | G74: 7468.88 | H74: 6770.13 | I74: 19499.31 | J74: -10530.89 | K74: 23207.43 | L74: 11421.11 | M74: 5128.55 | N74: 5928.97 | O74: -8540.86 | P74: 13937.77 | Q74: 3424 | R74: 1954.87 | S74: -22387.55 | T74: 25665.03 | U74: 8656.35 | V74: 6286.8 | W74: -23533.86 | X74: 23490.75 | Y74: 631.08 | Z74: 6874.77 | AA74: 10899.12 | AB74: -16916.49
A75: 1 | C75: 기타영업외손익 | E75: 19197.38 | G75: -750.83 | H75: -53874.55 | I75: -3558.08 | J75: -19357.29 | K75: -77540.75 | L75: 212436.56 | M75: 116657.19 | N75: -6595.35 | O75: 13933.93 | P75: 336432.33 | Q75: 42148.29 | R75: -55132.76 | S75: 1464.13 | T75: 377527.98 | U75: 366007.64 | V75: -23264.99 | W75: 69623 | X75: 52065.48 | Y75: -104900.3 | Z75: -6476.81 | AA75: -153866.9 | AB75: -26588.09
A76: 1 | C76: (비지배주주지분)당기순이익 | G76: -1017.24 | H76: -871.44 | I76: -990.15 | J76: -1325.57 | K76: -4204.4 | L76: -1429.37 | M76: -1583.68 | N76: -1671.72 | O76: -1453.22 | P76: -6137.99 | Q76: -1481.8 | R76: -1261.1 | S76: -1257.62 | T76: -4920.7 | U76: -8921.22 | V76: 3134.95 | W76: 6103.92 | X76: 119.1 | Y76: -42444.46 | Z76: -33086.49 | AA76: -40773.23 | AB76: -14338.67
A77: 1 | C77: 이자수익 | G77: 4426.86 | H77: 3991.65 | I77: 7082.29 | J77: 9459.07 | K77: 24959.87 | L77: 9697.22 | M77: 6872.36 | N77: 5873.68 | O77: 4335.33 | P77: 26778.59 | Q77: 4009.49 | R77: 2955.41 | S77: 5207.84 | T77: 2457.15 | U77: 14629.89 | V77: 2407.41 | W77: 2147.96 | X77: 4530.32 | Y77: 3845.29 | Z77: 12930.98 | AA77: 4855.52 | AB77: 16873.66
A78: 1 | C78: 이자비용 | G78: 1112.67 | H78: 1021.54 | I78: 1122.26 | J78: 2591.12 | K78: 5847.59 | L78: 2475.9 | M78: 2574.98 | N78: 4018.74 | O78: 5280.04 | P78: 14349.66 | Q78: 4459.84 | R78: 5449.28 | S78: 6789.22 | T78: 5640.29 | U78: 22338.63 | V78: 6626.72 | W78: 8576.06 | X78: 9933.9 | Y78: 12884.89 | Z78: 38021.57 | AA78: 17469.22 | AB78: 40154.43
A79: 1 | C79: 외환차익 | G79: 4258.23 | H79: 954.69 | I79: 1779.43 | J79: 905.04 | K79: 7897.39 | L79: 680.1 | M79: 785.16 | N79: 758.74 | O79: 1694.17 | P79: 3918.17 | Q79: 1520.18 | R79: 1596.84 | S79: 487.9 | T79: 7554.26 | U79: 11159.18 | V79: 1687.75 | W79: 1049.66 | X79: 675.46 | Y79: 4830.01 | Z79: 8242.88 | AA79: 7508.36 | AB79: 772.82
A80: 1 | C80: 외환차손 | G80: 913.79 | H80: 189.08 | I80: 1568.48 | J80: 1605.46 | K80: 4276.81 | L80: 664.49 | M80: 411.13 | N80: 613.1 | O80: 1230.79 | P80: 2919.51 | Q80: 417.4 | R80: 404.19 | S80: 11058.91 | T80: 4666.78 | U80: 16547.28 | V80: 775.89 | W80: 1400.42 | X80: 695.75 | Y80: 430.68 | Z80: 3302.74 | AA80: 2089.77 | AB80: 8031.72
A81: 1 | C81: 외화환산이익 | G81: 823.53 | H81: 3044.72 | I81: 13344.8 | J81: -14256.74 | K81: 2956.31 | L81: 4298.63 | M81: 667.41 | N81: 3696.64 | O81: -7641.04 | P81: 1021.64 | Q81: 3124.12 | R81: 3796.24 | S81: -3592.62 | T81: 18942.86 | U81: 22270.6 | V81: 2523.53 | W81: 8513.47 | X81: -2885.27 | Y81: -4945.3 | Z81: 3206.43 | AA81: 15982.36 | AB81: 7454.21
A82: 1 | C82: 외화환산손실 | G82: 13.28 | H82: 18.81 | I82: 16.48 | J82: 2441.69 | K82: 2490.26 | L82: 114.44 | M82: 214.55 | N82: -231.76 | O82: 418.49 | P82: 515.72 | Q82: 352.55 | R82: 544.08 | S82: 6642.53 | T82: -7017.82 | U82: 521.34 | V82: 2705.68 | W82: 25563.02 | X82: -13102.12 | Y82: -10039.31 | Z82: 5127.27 | AA82: 5726.28 | AB82: -5117.79
A83: 1 | C83: 이자손익 | G83: 3314.19 | H83: 2970.11 | I83: 5960.03 | J83: 6867.95 | K83: 19112.28 | L83: 7221.32 | M83: 4297.38 | N83: 1854.94 | O83: -944.71 | P83: 12428.93 | Q83: -450.35 | R83: -2493.87 | S83: -1581.38 | T83: -3183.14 | U83: -7708.74 | V83: -4219.31 | W83: -6428.1 | X83: -5403.58 | Y83: -9039.6 | Z83: -25090.59 | AA83: -12613.7 | AB83: -23280.77
A84: 1 | C84: 배당금수익 | H84: 8.5 | I84: 0 | J84: 0 | M84: 4.28 | N84: 0 | O84: 0 | AB84: 1051.18
A85: 1 | C85: 중단사업이익 | O85: -12967.81 | Q85: -1385.49 | R85: 4.52 | S85: -471.79 | T85: -29922.79 | U85: -31775.55 | V85: 7536.91 | W85: -439.4 | X85: -138.45 | Y85: 1466.16 | Z85: 8425.22 | AA85: -6713.29 | AB85: 1058.74
A86: 1 | C86: 영업활동으로인한현금흐름 | E86: 287877.58 | G86: -187915.4 | H86: 385340.21 | I86: -177460.38 | J86: 248620.66 | K86: 268585.09 | L86: -182891.08 | M86: 116284.68 | N86: -114754.24 | O86: 264723.88 | P86: 83363.24 | Q86: -103169.89 | R86: 55403.05 | S86: 26043.62 | T86: 154346.91 | U86: 132623.69 | V86: -15776.09 | W86: 41368.9 | X86: -212740.28 | Y86: 265884.29 | Z86: 78736.82 | AA86: -61097.37 | AB86: 152316.42
A87: 1 | C87: 투자활동으로인한현금흐름 | E87: -67692.63 | G87: -486330.15 | H87: -95837.89 | I87: -59796.68 | J87: -37444.39 | K87: -679409.11 | L87: -48540.42 | M87: -539257.31 | N87: -82993.06 | O87: -192894.85 | P87: -863685.64 | Q87: -71508.23 | R87: -175123.82 | S87: -47021.7 | T87: -148361.89 | U87: -442015.64 | V87: -272320.63 | W87: -1354.49 | X87: -154589.7 | Y87: -742179.63 | Z87: -1170444.4 | AA87: -146426.03 | AB87: -361334.12
A88: 1 | C88: 유형자산의증가 | E88: 39507.97 | G88: 11544.71 | H88: 8127.75 | I88: 11963.45 | J88: 16661.43 | K88: 48297.34 | L88: 41861.42 | M88: 15832 | N88: 43168.89 | O88: 31454.02 | P88: 132316.33 | Q88: 49893.05 | R88: 41360.13 | S88: 53673.47 | T88: 94879 | U88: 239805.65 | V88: 67182.21 | W88: 71067.97 | X88: 70871.82 | Y88: 89825 | Z88: 298947 | AA88: 75765.8
A89: 1 | C89: CAPEX | E89: 60754.95 | G89: 18766.99 | H89: 17697.48 | I89: 21192.94 | J89: 23095.05 | K89: 80752.46 | L89: 50447.32 | M89: 21644.63 | N89: 48778.16 | O89: 38428.44 | P89: 159298.55 | Q89: 56572.07 | R89: 57115.73 | S89: 58820.75 | T89: 100404.13 | U89: 272912.68 | V89: 72297.07 | W89: 74907.52 | X89: 73536.21 | Y89: 97572.85 | Z89: 318313.65 | AA89: 80064.33
A90: 1 | C90: 무형자산의감소 | E90: 1600 | J90: 0 | Q90: 85.82 | R90: 7420.53 | S90: 150.22 | T90: 28.58 | U90: 7685.15 | V90: 0 | W90: 70 | X90: 30 | Y90: 0 | Z90: 100 | AA90: 48.22
A91: 1 | C91: 무형자산의증가 | E91: 21246.98 | G91: 7222.28 | H91: 9569.73 | I91: 9229.49 | J91: 6433.62 | K91: 32455.12 | L91: 8585.9 | M91: 5812.63 | N91: 5609.27 | O91: 6974.42 | P91: 26982.22 | Q91: 6679.02 | R91: 15755.6 | S91: 5147.28 | T91: 5525.13 | U91: 33107.03 | V91: 5114.86 | W91: 3839.55 | X91: 2664.39 | Y91: 7747.85 | Z91: 19366.65 | AA91: 4298.53
A92: 1 | C92: 배당금수취(CF) | E92: 0 | I92: 0 | J92: 0 | N92: 0 | O92: 0 | S92: 0 | T92: 0 | V92: 9776.4 | W92: 294.55 | X92: 18697.77 | Y92: 177.32 | Z92: 28946.04 | AA92: 7838.15
A93: 1 | C93: 재무활동으로인한현금흐름 | E93: -18658.86 | G93: -6460.11 | H93: -66715.12 | I93: 47947.99 | J93: 22569.64 | K93: -2657.6 | L93: -7183.1 | M93: -54152.43 | N93: 223558.47 | O93: -135569.62 | P93: 26653.32 | Q93: 151984.58 | R93: 78211.93 | S93: -138467.09 | T93: -56665.87 | U93: 35063.55 | V93: 331000.46 | W93: 86478.14 | X93: 242513.95 | Y93: 577314.02 | Z93: 1237306.6 | AA93: 359716.66 | AB93: 1304090.8
A94: 1 | C94: 단기차입금의증가 | E94: 48000 | G94: 3000 | H94: 10007.11 | I94: 100355.77 | J94: 165000 | K94: 278362.88 | L94: 1361.55 | M94: 170000 | N94: 369000 | O94: 254203.42 | P94: 794564.97 | Q94: 285000 | R94: 310000 | S94: 540115 | T94: 372627.6 | U94: 1507742.6 | V94: 677153.42 | W94: 306015.96 | X94: 795672.42 | Y94: 663912.82 | Z94: 2442754.6 | AA94: 524100 | AB94: 1947813.9
A95: 1 | C95: 단기차입금의감소 | E95: 48000 | G95: 3000 | H95: 10007.11 | I95: 51428.27 | J95: 135000 | K95: 199435.38 | L95: 1361.55 | M95: 170000 | N95: 189000 | O95: 381860.91 | P95: 742222.46 | Q95: 127342.51 | R95: 420000 | S95: 640000 | T95: 421000 | U95: 1608342.5 | V95: 512641.45 | W95: 443642.95 | X95: 562031.8 | Y95: 654187.6 | Z95: 2172503.8 | AA95: 573744.09 | AB95: 338934.2
A96: 1 | C96: 유동성장기부채의감소 | E96: 30000
A97: 1 | C97: 장기차입금의증가 | E97: 0 | Q97: 140 | R97: 0 | S97: 0 | T97: 0 | U97: 140 | V97: 41300 | W97: 0 | X97: 68300 | Y97: 119046 | Z97: 228646 | AA97: 18700
A98: 1 | C98: 사채의감소 | E98: 0 | G98: 0 | H98: 30000 | I98: 0 | J98: 0 | K98: 30000 | N98: 0 | O98: 0 | T98: 0 | Y98: 50000
A99: 1 | C99: 리스부채의상환 | E99: 6358.85 | G99: 6460.11 | H99: 6822.71 | I99: 6590.48 | J99: 7430.37 | K99: 27303.67 | L99: 7183.1 | M99: 7404.12 | N99: 7503
A100: 1 | C100: 자기주식의취득 | E100: 0 | G100: 0 | H100: 0 | I100: 0 | J100: 0 | K100: 0
...

Sheet BS별도
B1: (백만원) | C1: 이름: BS별도H | E1: 4Q21 | F1: 2021 | G1: 1Q22 | H1: 2Q22 | I1: 3Q22 | J1: 4Q22 | K1: 2022 | L1: 1Q23 | M1: 2Q23 | N1: 3Q23 | O1: 4Q23 | P1: 2023 | Q1: 1Q24 | R1: 2Q24 | S1: 3Q24 | T1: 4Q24 | U1: 2024 | V1: 1Q25 | W1: 2Q25 | X1: 3Q25 | Y1: 4Q25 | Z1: 2025 | AA1: 1Q26 | AB1: 2Q26 | AC1: 3Q26 | AD1: 4Q26 | AE1: 2026 | AF1: 1Q27 | AG1: 2Q27 | AH1: 3Q27 | AI1: 4Q27 | AJ1: 2027 | AK1: 1Q28 | AL1: 2Q28 | AM1: 3Q28 | AN1: 4Q28 | AO1: 2028
B2: 별도 | D2: fin json(kship_fin.py)
B3: 한화시스템(별) | C3: UPDATE: 26-10-11 | E3: 1 | F3: 2 | G3: 3 | H3: 4 | I3: 5 | J3: 6 | K3: 7 | L3: 8 | M3: 9 | N3: 10 | O3: 11 | P3: 12 | Q3: 13 | R3: 14 | S3: 15 | T3: 16 | U3: 17 | V3: 18 | W3: 19 | X3: 20 | Y3: 21 | Z3: 22 | AA3: 23 | AB3: 24 | AC3: 25 | AD3: 26 | AE3: 27 | AF3: 28 | AG3: 29 | AH3: 30 | AI3: 31 | AJ3: 32 | AK3: 33 | AL3: 34 | AM3: 35 | AN3: 36 | AO3: 37
B4: Account Code | C4: AccountNAME | E4: 2021.12 | F4: 2021.12A | G4: 2022.03 | H4: 2022.06 | I4: 2022.09 | J4: 2022.12 | K4: 2022.12A | L4: 2023.03 | M4: 2023.06 | N4: 2023.09 | O4: 2023.12 | P4: 2023.12A | Q4: 2024.03 | R4: 2024.06 | S4: 2024.09 | T4: 2024.12 | U4: 2024.12A | V4: 2025.03 | W4: 2025.06 | X4: 2025.09 | Y4: 2025.12 | Z4: 2025.12A | AA4: 2026.03 | AB4: 2026.06 | AC4: 2026.09 | AD4: 2026.12 | AE4: 2026.12A | AF4: 2027.03 | AG4: 2027.06 | AH4: 2027.09 | AI4: 2027.12 | AJ4: 2027.12A | AK4: 2028.03 | AL4: 2028.06 | AM4: 2028.09 | AN4: 2028.12 | AO4: 2028.12A
A5: 1 | C5: 유동자산 | E5: 2652387 | F5: 2652387 | G5: 1929577.4 | H5: 2089907.3 | I5: 2054762.1 | J5: 2208441.8 | K5: 2208441.8 | L5: 2277193.2 | M5: 1715570.3 | N5: 1883371.2 | O5: 1843097 | P5: 1843097 | Q5: 2040114 | R5: 2291067.9 | S5: 2320000.7 | T5: 2069939.6 | U5: 2069939.6 | V5: 2095025.9 | W5: 2367643.5 | X5: 2500441.7 | Y5: 2371127.2 | Z5: 2371127.2 | AA5: 2658703.2 | AB5: 3975405.6
A6: 1 | C6: 현금및현금성자산 | E6: 1621392.8 | F6: 1621392.8 | G6: 822403.09 | H6: 1068259.6 | I6: 892697.8 | J6: 1143568.8 | K6: 1143568.8 | L6: 909441.85 | M6: 449184.23 | N6: 508467.31 | O6: 446939.27 | P6: 446939.27 | Q6: 428557.79 | R6: 387062.02 | S6: 229879.69 | T6: 132154.37 | U6: 132154.37 | V6: 74638.05 | W6: 174659.83 | X6: 36100.21 | Y6: 44175.33 | Z6: 44175.33 | AA6: 287220.28 | AB6: 1333982.7
A7: 1 | C7: 매출채권및기타채권 | E7: 176954.56 | F7: 176954.56 | G7: 138572.02 | H7: 110734.35 | I7: 126965.38 | J7: 207189.74 | K7: 207189.74 | L7: 161082.91 | M7: 146928.7 | N7: 168130.04 | O7: 199620.74 | P7: 199620.74 | Q7: 250610.62 | R7: 287233.18 | S7: 263379.58 | T7: 295774.11 | U7: 295774.11 | V7: 237182.76 | W7: 225171.76 | X7: 298959.56 | Y7: 436993.47 | Z7: 436993.47 | AA7: 346980.34 | AB7: 418524.17
A8: 1 | C8: 기타유동금융자산 | E8: 27413.21 | F8: 27413.21 | G8: 25012.98 | H8: 19575.18 | I8: 20173.55 | J8: 21502.88 | K8: 21502.88 | L8: 160255.79 | M8: 19410.2 | N8: 23111.95 | O8: 21331.2 | P8: 21331.2 | Q8: 21596.06 | R8: 134710.86 | S8: 105620.73 | T8: 104199.69 | U8: 104199.69 | V8: 76980.61 | W8: 22300.75 | X8: 19382.16 | Y8: 27123.43 | Z8: 27123.43 | AA8: 25282.3 | AB8: 27171.8
A9: 1 | C9: 기타유동자산 | E9: 420581.33 | F9: 420581.33 | G9: 498810.43 | H9: 494050.1 | I9: 558251.15 | J9: 463586.64 | K9: 463586.64 | L9: 551258.06 | M9: 627177.26 | N9: 695612.75 | O9: 674308.26 | P9: 674308.26 | Q9: 770159.59 | R9: 849350.27 | S9: 1048014.7 | T9: 930145.01 | U9: 930145.01 | V9: 1002780.4 | W9: 1115694.6 | X9: 1205717.9 | Y9: 1069476.2 | Z9: 1069476.2 | AA9: 1082151.8 | AB9: 1211067.1
A10: 1 | C10: 재고자산 | E10: 406045.06 | F10: 406045.06 | G10: 444778.89 | H10: 397288.01 | I10: 456674.18 | J10: 372593.68 | K10: 372593.68 | L10: 495154.64 | M10: 472869.93 | N10: 488049.14 | O10: 500897.54 | P10: 500897.54 | Q10: 569189.95 | R10: 632711.58 | S10: 673106 | T10: 607666.38 | U10: 607666.38 | V10: 703444.03 | W10: 829816.48 | X10: 940281.92 | Y10: 793358.72 | Z10: 793358.72 | AA10: 917068.5 | AB10: 947159.79
A11: 1 | C11: 비유동자산 | E11: 1262225.9 | F11: 1262225.9 | G11: 1841545.5 | H11: 1939437.2 | I11: 1992426.6 | J11: 1943658.3 | K11: 1943658.3 | L11: 1941812.8 | M11: 2682025.1 | N11: 2737965 | O11: 2712337.4 | P11: 2712337.4 | Q11: 2746738 | R11: 2702637.6 | S11: 2761772.8 | T11: 3149549.9 | U11: 3149549.9 | V11: 4423319.8 | W11: 4917521.1 | X11: 6125241 | Y11: 6972295.6 | Z11: 6972295.6 | AA11: 7297722.8 | AB11: 6792759.8
A12: 1 | C12: 장기금융자산 | E12: 144144.83 | F12: 144144.83 | G12: 158178.4 | H12: 225288.02 | I12: 236641 | J12: 205483.91 | K12: 205483.91 | L12: 208510.12 | M12: 216569.6 | N12: 220522.85 | O12: 194228.39 | P12: 194228.39 | Q12: 203715.87 | R12: 85205.38 | S12: 86486.4 | T12: 76492.07 | U12: 76492.07 | V12: 76971.15 | W12: 81371.11 | X12: 83457.28 | Y12: 86993.09 | Z12: 86993.09 | AA12: 98416.45 | AB12: 101605.4
A13: 1 | C13: 투자자산 | E13: 144144.83 | F13: 144144.83 | G13: 158178.4 | H13: 225288.02 | I13: 236641 | J13: 205483.91 | K13: 205483.91 | L13: 208510.12 | M13: 216569.6 | N13: 220522.85 | O13: 1627449.3 | P13: 1627449.3 | Q13: 1640136.8 | R13: 1524528.1 | S13: 1527407.4 | T13: 580535.58 | U13: 580535.58 | V13: 766368.87 | W13: 770768.83 | X13: 863386.5 | Y13: 1470917.3 | Z13: 1470917.3 | AA13: 1527747.8 | AB13: 101605.4
A14: 1 | C14: 유형자산 | E14: 237584.76 | F14: 237584.76 | G14: 231283.49 | H14: 253532.96 | I14: 252392.3 | J14: 256265.2 | K14: 256265.2 | L14: 285139.81 | M14: 289912.3 | N14: 316982.87 | O14: 329710.04 | P14: 329710.04 | Q14: 355809.56 | R14: 394447.15 | S14: 420470.99 | T14: 508914.03 | U14: 508914.03 | V14: 553254.63 | W14: 621229.48 | X14: 650360.35 | Y14: 710199.09 | Z14: 710199.09 | AA14: 728578.74 | AB14: 769401.94
A15: 1 | C15: 사용권자산 | E15: 96093.13 | F15: 96093.13 | G15: 91105.05 | H15: 86142.84 | I15: 90456.2 | J15: 91379.37 | K15: 91379.37 | L15: 85809.5 | M15: 81788.12 | N15: 102891.4 | O15: 110224.89 | P15: 110224.89 | Q15: 116182.55 | R15: 109863.54 | S15: 142128.05 | T15: 130701.11 | U15: 130701.11 | V15: 123926.27 | W15: 118982.22 | X15: 111334.98 | Y15: 123318.87 | Z15: 123318.87 | AA15: 118914.75 | AB15: 112477.58
A16: 1 | C16: 기타비유동자산 | E16: 98456.28 | F16: 98456.28 | G16: 94323.69 | H16: 89397.7 | I16: 93518.21 | J16: 95489.43 | K16: 95489.43 | L16: 89453.79 | M16: 85683.18 | N16: 106250 | O16: 114650.39 | P16: 114650.39 | Q16: 120311.5 | R16: 113745.64 | S16: 146836.64 | T16: 137319.36 | U16: 137319.36 | V16: 131013.53 | W16: 125731.3 | X16: 131079.87 | Y16: 142593.56 | Z16: 142593.56 | AA16: 140038.89 | AB16: 132947.69
A17: 1 | C17: 무형자산 | E17: 538727.83 | F17: 538727.83 | G17: 536074.61 | H17: 539148.2 | I17: 541358.56 | J17: 544089.39 | K17: 544089.39 | L17: 542690.91 | M17: 541483.88 | N17: 541660.34 | O17: 547331.37 | P17: 547331.37 | Q17: 541950.44 | R17: 551312.09 | S17: 554848.15 | T17: 553167.61 | U17: 553167.61 | V17: 550148.83 | W17: 547108.22 | X17: 541451.79 | Y17: 538159.37 | Z17: 538159.37 | AA17: 530984.52
A18: 1 | C18: 이연법인세자산 | E18: 81719.2 | F18: 81719.2 | G18: 77207.53 | H18: 76362 | I18: 77885.59 | J18: 87386.88 | K18: 87386.88 | L18: 54281.9 | M18: 30891.55 | N18: 30671.17 | O18: 77866.84 | P18: 77866.84 | Q18: 73200.28 | R18: 103275.32 | S18: 96880.25 | T18: 29856.95 | U18: 29856.95 | V18: 0 | W18: 0 | X18: 0 | Y18: 0 | Z18: 0
A19: 1 | C19: 자산총계 | E19: 3914612.9 | F19: 3914612.9 | G19: 3771122.9 | H19: 4029344.5 | I19: 4047188.7 | J19: 4152100.1 | K19: 4152100.1 | L19: 4219006.1 | M19: 4397595.4 | N19: 4621336.2 | O19: 4555434.4 | P19: 4555434.4 | Q19: 4786852 | R19: 4993705.5 | S19: 5081773.5 | T19: 5219489.5 | U19: 5219489.5 | V19: 6518345.7 | W19: 7285164.6 | X19: 8625682.8 | Y19: 9343422.8 | Z19: 9343422.8 | AA19: 9956425.9 | AB19: 10768165
A20: 1 | C20: 유동부채 | E20: 1358175.2 | F20: 1358175.2 | G20: 1219943.9 | H20: 1448190.6 | I20: 1431444.4 | J20: 1605605 | K20: 1605605 | L20: 1581264.5 | M20: 1635652.8 | N20: 1777251.5 | O20: 1941385.8 | P20: 1941385.8 | Q20: 2164973.6 | R20: 2160315 | S20: 2267270.3 | T20: 2176932.2 | U20: 2176932.2 | V20: 2402202.9 | W20: 2493731.6 | X20: 2631721.1 | Y20: 2639692 | Z20: 2639692 | AA20: 2784824.5 | AB20: 4438112
A21: 1 | C21: 매입채무및기타채무 | E21: 124422.77 | F21: 124422.77 | G21: 124106.12 | H21: 111331.13 | I21: 104013.97 | J21: 159257.46 | K21: 159257.46 | L21: 208830.23 | M21: 115098.57 | N21: 105886.55 | O21: 210278.32 | P21: 210278.32 | Q21: 231992.32 | R21: 209988.9 | S21: 164271.76 | T21: 211650.83 | U21: 211650.83 | V21: 311589.43 | W21: 223456.93 | X21: 278142.02 | Y21: 424062.6 | Z21: 424062.6 | AA21: 480886.77 | AB21: 330379.56
A22: 1 | C22: 단기차입금 | E22: 29986.12 | F22: 29986.12 | G22: 29992.82 | H22: 0 | I22: 50000 | J22: 80000 | K22: 80000 | L22: 80000 | M22: 80000 | N22: 289988.04 | O22: 159992.26 | P22: 159992.26 | Q22: 319996.02 | R22: 209999.79 | S22: 129941.02 | T22: 79955.19 | U22: 79955.19 | V22: 229969.77 | W22: 149808.42 | X22: 333870.29 | Y22: 286418.4 | Z22: 286418.4 | AA22: 455903.92 | AB22: 2009721.5
A23: 1 | C23: 단기금융부채(face) | E23: 29986.12 | F23: 29986.12 | G23: 29992.82 | H23: 0 | I23: 50000 | J23: 80000 | K23: 80000 | L23: 80000 | M23: 80000 | N23: 289988.04 | O23: 159992.26 | P23: 159992.26 | Q23: 319996.02 | R23: 209999.79 | S23: 129941.02 | T23: 79955.19 | U23: 79955.19 | V23: 229969.77 | W23: 149808.42 | X23: 333870.29 | Y23: 286418.4 | Z23: 286418.4 | AA23: 455903.92 | AB23: 2009721.5
A24: 1 | C24: 기타유동금융부채 | E24: 67197.46 | F24: 67197.46 | G24: 47633.97 | H24: 49042.48 | I24: 56484.1 | J24: 76906.88 | K24: 76906.88 | L24: 56724.56 | M24: 66855.3 | N24: 67283.39 | O24: 89683.52 | P24: 89683.52 | Q24: 66971.52 | R24: 70600.76 | S24: 83507.1 | T24: 137422.36 | U24: 137422.36 | V24: 75349.2 | W24: 93409.19 | X24: 109650.46 | Y24: 168029.99 | Z24: 168029.99 | AA24: 120411.53 | AB24: 141558.12
A25: 1 | C25: 단기금융부채 | E25: 67197.46 | F25: 67197.46 | G25: 47633.97 | H25: 49042.48 | I25: 56484.1 | J25: 76906.88 | K25: 76906.88 | L25: 56724.56 | M25: 66855.3 | N25: 67283.39 | O25: 89683.52 | P25: 89683.52 | Q25: 66971.52 | R25: 70600.76 | S25: 83507.1 | T25: 137422.36 | U25: 137422.36 | V25: 75349.2 | W25: 93409.19 | X25: 109650.46 | Y25: 168029.99 | Z25: 168029.99 | AA25: 120411.53 | AB25: 141558.12
A26: 1 | C26: 기타유동부채 | E26: 1110781.8 | F26: 1110781.8 | G26: 996519.81 | H26: 1269944.5 | I26: 1196554.3 | J26: 1252282.2 | K26: 1252282.2 | L26: 1202733.3 | M26: 1334313.4 | N26: 1271319.4 | O26: 1431341.5 | P26: 1431341.5 | Q26: 1493112.1 | R26: 1626924.2 | S26: 1848372.9 | T26: 1675436.7 | U26: 1675436.7 | V26: 1733985.2 | W26: 1988516.9 | X26: 1865028.2 | Y26: 1695969.3 | Z26: 1695969.3 | AA26: 1677887.7 | AB26: 1905412.4
A27: 1 | C27: 단기충당부채 | E27: 10475.01 | F27: 10475.01 | G27: 10782.41 | H27: 9174.43 | I27: 15589.43 | J27: 22888.11 | K27: 22888.11 | L27: 19182.69 | M27: 24378.83 | N27: 22790.81 | O27: 31632.6 | P27: 31632.6 | Q27: 28690.2 | R27: 22645.38 | S27: 26139.25 | T27: 35162.4 | U27: 35162.4 | V27: 29518.94 | W27: 27692.82 | X27: 25343.56 | Y27: 30452.43 | Z27: 30452.43 | AA27: 26204.4 | AB27: 23662.57
A28: 1 | C28: 당기법인세부채(미지급법인세) | E28: 15312.02 | F28: 15312.02 | G28: 10908.78 | H28: 8698.08 | I28: 8802.61 | J28: 14270.38 | K28: 14270.38 | L28: 13793.72 | M28: 15006.68 | N28: 19983.24 | O28: 18457.56 | P28: 18457.56 | Q28: 24211.41 | R28: 20155.91 | S28: 15038.21 | T28: 37304.77 | U28: 37304.77 | V28: 21790.37 | W28: 10847.38 | X28: 19686.55 | Y28: 34759.3 | Z28: 34759.3 | AA28: 23530.12 | AB28: 27377.82
A29: 1 | C29: 비유동부채 | E29: 286977.4 | F29: 286977.4 | G29: 286650.41 | H29: 287609.65 | I29: 297747.91 | J29: 299465.71 | K29: 299465.71 | L29: 301136.66 | M29: 303408.4 | N29: 346989.72 | O29: 370401.32 | P29: 370401.32 | Q29: 386344.11 | R29: 640242.57 | S29: 589067.7 | T29: 611522.94 | U29: 611522.94 | V29: 889748.36 | W29: 1188891.4 | X29: 1421260.2 | Y29: 1887466.2 | Z29: 1887466.2 | AA29: 2203873.8 | AB29: 1874425.5
A30: 1 | C30: 장기차입금 | E30: 29959.4 | F30: 29959.4 | G30: 29963.37 | H30: 29967.41 | I30: 29971.52 | J30: 29975.65 | K30: 29975.65 | L30: 29979.71 | M30: 29983.84 | N30: 49884.18 | O30: 49899.32 | P30: 49899.32 | Q30: 49913.35 | R30: 299021.88 | S30: 249185.35 | T30: 249276.74 | U30: 249276.74 | V30: 290667.02 | W30: 489861.28 | X30: 558310.01 | Y30: 1073225.9 | Z30: 1073225.9 | AA30: 1306257.3 | AB30: 1096911.1
... A47: 1 | C47: 이자발생자산 | E47: 1765537.7 | F47: 1765537.7 | G47: 980581.49 | H47: 1293547.6 | I47: 1129338.8 | J47: 1349052.7 | K47: 1349052.7 | L47: 1117952 | M47: 665753.83 | N47: 728990.16 | O47: 641167.66 | P47: 641167.66 | Q47: 632273.66 | R47: 472267.4 | S47: 316366.09 | T47: 208646.44 | U47: 208646.44 | V47: 151609.2 | W47: 256030.94 | X47: 119557.49 | Y47: 131168.42 | Z47: 131168.42 | AA47: 385636.73 | AB47: 1435588.1
A48: 1 | C48: 장기매출채권및기타채권 | O48: 0 | P48: 0
A49: 1 | C49: 종속기업및관계기업투자 | O49: 1433220.9 | P49: 1433220.9 | Q49: 1436420.9 | R49: 1439322.7 | S49: 1440920.9 | T49: 504043.51 | U49: 504043.51 | V49: 689397.72 | W49: 689397.72 | X49: 779929.22 | Y49: 1383924.2 | Z49: 1383924.2 | AA49: 1429331.3
A50: 1 | C50: 장기매입채무및기타채무 | O50: 0 | P50: 0
A51: 1 | C51: 이연법인세부채 | V51: 224521.68 | W51: 315486 | X51: 474993.16 | Y51: 482825.52 | Z51: 482825.52 | AA51: 551472 | AB51: 442888.43
A52: 1 | C52: 단기투자자산(공정가치) | AB52: 37500
A53: 1 | C53: 매출액(수익) | E53: 679521.79 | G53: 429467.46 | H53: 510321.04 | I53: 459131.01 | J53: 788486.16 | K53: 2187405.7 | L53: 439361.13 | M53: 610524.6 | N53: 620671.62 | O53: 780028.04 | P53: 2450585.4 | Q53: 542147.8 | R53: 683326.11 | S53: 637373.3 | T53: 930785.78 | U53: 2793633 | V53: 571805.15 | W53: 617249.03 | X53: 637073.94 | Y53: 1265357.2 | Z53: 3091485.4 | AA53: 643555.8 | AB53: 887824.91
A54: 1 | C54: 매출원가 | E54: 614496.32 | G54: 365999.66 | H54: 438744.36 | I54: 401383.87 | J54: 725983.49 | K54: 1932111.4 | L54: 373861.56 | M54: 525640.22 | N54: 532473.79 | O54: 714661.97 | P54: 2146637.5 | Q54: 456412.06 | R54: 556956.49 | S54: 531967.43 | T54: 834899.54 | U54: 2380235.5 | V54: 462881.37 | W54: 501951.6 | X54: 519999.67 | Y54: 1108883.8 | Z54: 2593716.5 | AA54: 506334.15 | AB54: 708008.58
A55: 1 | C55: 매출총이익 | E55: 65025.47 | G55: 63467.8 | H55: 71576.68 | I55: 57747.14 | J55: 62502.67 | K55: 255294.29 | L55: 65499.57 | M55: 84884.38 | N55: 88197.83 | O55: 65366.08 | P55: 303947.86 | Q55: 85735.74 | R55: 126369.62 | S55: 105405.87 | T55: 95886.24 | U55: 413397.47 | V55: 108923.78 | W55: 115297.43 | X55: 117074.27 | Y55: 156473.42 | Z55: 497768.9 | AA55: 137221.65 | AB55: 179816.32
A56: 1 | C56: 판관비 | E56: 47834.63 | G56: 35599.47 | H56: 39630.22 | I56: 40652.66 | J56: 45732.05 | K56: 161614.4 | L56: 44613.04 | M56: 45630.44 | N56: 42193.89 | O56: 45945.31 | P56: 178382.68 | Q56: 39776.59 | R56: 42227.38 | S56: 44425.58 | T56: 61828.29 | U56: 188257.84 | V56: 47823.95 | W56: 52022.96 | X56: 55207.77 | Y56: 62736.69 | Z56: 217791.37 | AA56: 54870.31 | AB56: 55320.9
A57: 1 | C57: 영업이익 | E57: 17190.85 | G57: 27868.33 | H57: 31946.46 | I57: 17094.48 | J57: 16770.63 | K57: 93679.9 | L57: 20886.54 | M57: 39253.94 | N57: 46003.94 | O57: 19420.76 | P57: 125565.18 | Q57: 45959.15 | R57: 84142.24 | S57: 60980.29 | T57: 34057.96 | U57: 225139.64 | V57: 61099.83 | W57: 63274.47 | X57: 61866.5 | Y57: 93736.74 | Z57: 279977.54 | AA57: 82351.35 | AB57: 124495.42
A58: 1 | C58: 기타영업외수익 | E58: 26341.2 | G58: 908.9 | H58: 181.1 | I58: 279.72 | J58: 6711.39 | K58: 8081.11 | L58: 145225.46 | M58: 113954.25 | N58: 483.07 | O58: 46213.77 | P58: 305876.55 | Q58: 343.56 | R58: 68.28 | S58: 2668.8 | T58: 441126.54 | U58: 444207.18 | V58: 13506.95 | W58: 6693.47 | X58: -2264.3 | Y58: 59676.38 | Z58: 77612.5 | AA58: 8391.36 | AB58: 3984.57
A59: 1 | C59: 기타영업외비용 | E59: 6866.67 | G59: 1059.18 | H59: 1857.29 | I59: 4845.71 | J59: 59807.03 | K59: 67569.21 | L59: 2123.79 | M59: 2950.19 | N59: 2572.97 | O59: 284823.16 | P59: 292470.11 | Q59: 1094.16 | R59: 147916.69 | S59: 1899.31 | T59: 164414.08 | U59: 315324.24 | V59: 8218.31 | W59: 18102.82 | X59: 5086.8 | Y59: 26466.12 | Z59: 57874.05 | AA59: 33591.33 | AB59: -3525.49
A60: 1 | C60: 금융수익 | E60: 3279.13 | G60: 5732.1 | H60: 7910.18 | I60: 21041.12 | J60: -4502.24 | K60: 30181.16 | L60: 13697.39 | M60: 7554.75 | N60: 9441.2 | O60: 795.89 | P60: 31489.23 | Q60: 13438.5 | R60: 11352.05 | S60: 7719.14 | T60: 29741.06 | U60: 62250.75 | V60: 5766.67 | W60: 8709.41 | X60: -2871.17 | Y60: 570.61 | Z60: 12175.52 | AA60: 22094.91 | AB60: 20723.88
A61: 1 | C61: 금융비용 | E61: 204.45 | G61: 1964.98 | H61: 1181.54 | I61: 2475.98 | J61: 5700.62 | K61: 11323.12 | L61: 2913.6 | M61: 3000.18 | N61: 4396 | O61: 6837.7 | P61: 17147.48 | Q61: 5106.32 | R61: 6378.46 | S61: 30109.27 | T61: 4479.11 | U61: 46073.16 | V61: 9518.11 | W61: 34119.82 | X61: -3031.25 | Y61: 213.03 | Z61: 40819.71 | AA61: 23684.67 | AB61: 40457.42
A62: 1 | C62: 법인세비용차감전계속사업이익 | E62: 39740.05 | G62: 31485.17 | H62: 36998.9 | I62: 31093.63 | J62: -46527.88 | K62: 53049.82 | L62: 174772 | M62: 154812.57 | N62: 48959.25 | O62: -225230.44 | P62: 153313.38 | Q62: 53540.74 | R62: -58732.58 | S62: 39359.64 | T62: 336032.35 | U62: 370200.15 | V62: 62637.02 | W62: 26454.7 | X62: 54675.47 | Y62: 127304.57 | Z62: 271071.76 | AA62: 55561.62 | AB62: 112271.93
A63: 1 | C63: 법인세비용 | E63: 5653.44 | G63: 6638.92 | H63: 8432.68 | I63: 6641.5 | J63: 2790.75 | K63: 24503.85 | L63: 39580.28 | M63: 34229.92 | N63: 10398.46 | O63: -26897.9 | P63: 57310.76 | Q63: 11047.56 | R63: -15548.82 | S63: 7765.61 | T63: 103802.5 | U63: 107066.85 | V63: 11512.04 | W63: 3129.16 | X63: -77794.93 | Y63: -32813.89 | Z63: -95967.62 | AA63: 9313.48 | AB63: 19011.67
A64: 1 | C64: 계속사업이익 | E64: 34086.61 | G64: 24846.25 | H64: 28566.22 | I64: 24452.13 | J64: -49318.63 | K64: 28545.97 | L64: 135191.72 | M64: 120582.65 | N64: 38560.78 | O64: -198332.54 | P64: 96002.61 | Q64: 42493.18 | R64: -43183.76 | S64: 31594.03 | T64: 232229.85 | U64: 263133.3 | V64: 51124.98 | W64: 23325.54 | X64: 132470.4 | Y64: 160118.46 | Z64: 367039.38 | AA64: 46248.14 | AB64: 93260.26
A65: 1 | C65: 당기순이익 | E65: 34086.61 | G65: 24846.25 | H65: 28566.22 | I65: 24452.13 | J65: -49318.63 | K65: 28545.97 | L65: 135191.72 | M65: 120582.65 | Q65: 42493.18 | R65: -43183.76 | S65: 31594.03 | T65: 232229.85 | U65: 263133.3 | V65: 51124.98 | W65: 23325.54 | X65: 132470.4 | Y65: 160118.46 | Z65: 367039.38 | AA65: 46248.14 | AB65: 93260.26
A66: 1 | C66: 총포괄손익 | E66: 31660.16 | G66: 24846.25 | H66: 28566.22 | I66: 24452.13 | J66: -70967.06 | K66: 6897.54 | L66: 135126.46 | M66: 120582.65 | N66: 38560.78 | O66: -253512.98 | P66: 40756.91 | Q66: 42493.18 | R66: -43183.76 | S66: 31594.03 | T66: 205118.17 | U66: 236021.62 | V66: 860606.54 | W66: 354110.37 | X66: 967819.15 | Y66: 240877.2 | Z66: 2423413.3 | AA66: 243785.5 | AB66: -514710.44
A67: 1 | C67: 금융손익 | E67: 3074.68 | G67: 3767.12 | H67: 6728.64 | I67: 18565.14 | J67: -10202.86 | K67: 18858.04 | L67: 10783.79 | M67: 4554.57 | N67: 5045.2 | O67: -6041.81 | P67: 14341.75 | Q67: 8332.18 | R67: 4973.59 | S67: -22390.13 | T67: 25261.95 | U67: 16177.59 | V67: -3751.44 | W67: -25410.41 | X67: 160.08 | Y67: 357.58 | Z67: -28644.19 | AA67: -1589.76 | AB67: -19733.54
A68: 1 | C68: 기타영업외손익 | E68: 19474.53 | G68: -150.28 | H68: -1676.19 | I68: -4565.99 | J68: -53095.64 | K68: -59488.1 | L68: 143101.67 | M68: 111004.06 | N68: -2089.9 | O68: -238609.39 | P68: 13406.44 | Q68: -750.6 | R68: -147848.41 | S68: 769.49 | T68: 276712.46 | U68: 128882.94 | V68: 5288.64 | W68: -11409.35 | X68: -7351.1 | Y68: 33210.26 | Z68: 19738.45 | AA68: -25199.97 | AB68: 7510.06
A69: 1 | C69: (지배주주지분)당기순이익 | E69: 34086.61 | G69: 24846.25 | H69: 28566.22 | I69: 24452.13 | J69: -49318.63 | K69: 28545.97 | L69: 135191.72 | M69: 120582.65 | Q69: 42493.18 | R69: -43183.76 | S69: 31594.03 | T69: 232229.85 | U69: 263133.3 | V69: 51124.98 | W69: 23325.54 | X69: 132470.4 | Y69: 160118.46 | Z69: 367039.38 | AA69: 46248.14 | AB69: 93260.26
A70: 1 | C70: 영업활동으로인한현금흐름 | E70: 298301.61 | G70: -182998.52 | H70: 399193.03 | I70: -163751.89 | J70: 271912.55 | K70: 324355.17 | L70: -172186.23 | M70: 122777.04 | N70: -107649.96 | O70: 269927.93 | P70: 112868.78 | Q70: -106570.84 | R70: 67200.75 | S70: 16805.73 | T70: 168859.4 | U70: 146295.04 | V70: 11725.87 | W70: 80057.67 | X70: -230432.11 | Y70: 264277.56 | Z70: 125628.99 | AA70: -40763.67 | AB70: 78248.52
A71: 1 | C71: 투자활동으로인한현금흐름 | E71: -60623.7 | G71: -609885.91 | H71: -87153.63 | I71: -54758.75 | J71: -44040.64 | K71: -795838.93 | L71: -55360.09 | M71: -529362.24 | N71: -55896.64 | O71: -193776.6 | P71: -834395.57 | Q71: -63417.97 | R71: -187078.3 | S71: -29015.32 | T71: -214810.23 | U71: -494321.82 | V71: -251562.38 | W71: -24732.89 | X71: -151667.79 | Y71: -717841.83 | Z71: -1145804.9 | AA71: -105674.41 | AB71: -277279.41
A72: 1 | C72: 유형자산의증가 | E72: 22446.13 | G72: 9859.05 | H72: 7319.47 | I72: 11060.71 | J72: 14917.33 | K72: 43156.56 | L72: 41035.92 | M72: 14994.1 | N72: 41538.29 | O72: 30277.61 | P72: 127845.92 | Q72: 49585.15 | R72: 41166.75 | S72: 53459.59 | T72: 94624.71 | U72: 238836.2 | V72: 71427.31 | W72: 61553.86 | X72: 57036.75 | Y72: 80665.66 | Z72: 270683.58 | AA72: 48232.91
A73: 1 | C73: CAPEX | E73: 29634.87 | G73: 16270.18 | H73: 16756.41 | I73: 20156.99 | J73: 21841.63 | K73: 75025.21 | L73: 49480.27 | M73: 20701.89 | N73: 46973.63 | O73: 37134.14 | P73: 154289.93 | Q73: 56237.41 | R73: 56904.99 | S73: 58606.87 | T73: 100149.84 | U73: 271899.11 | V73: 76542.17 | W73: 65393.41 | X73: 59701.14 | Y73: 88413.51 | Z73: 290050.23 | AA73: 52531.44
A74: 1 | C74: 무형자산의감소 | E74: 1600 | J74: 0 | Q74: 0 | R74: 7320.53 | S74: 141.57 | T74: 28.57 | U74: 7490.67 | X74: 30 | Y74: 0 | AA74: 48.22
A75: 1 | C75: 무형자산의증가 | E75: 7188.74 | G75: 6411.13 | H75: 9436.94 | I75: 9096.28 | J75: 6924.3 | K75: 31868.65 | L75: 8444.35 | M75: 5707.79 | N75: 5435.34 | O75: 6856.53 | P75: 26444.01 | Q75: 6652.26 | R75: 15738.24 | S75: 5147.28 | T75: 5525.13 | U75: 33062.91 | V75: 5114.86 | W75: 3839.55 | X75: 2664.39 | Y75: 7747.85 | Z75: 19366.65 | AA75: 4298.53
A76: 1 | C76: 배당금수취(CF) | E76: 0 | I76: 0 | J76: 0 | N76: 0 | O76: 0 | S76: 0 | T76: 0 | V76: 101.16 | W76: 2.37 | X76: 0 | Y76: 0 | Z76: 103.53 | AA76: 236.92
A77: 1 | C77: 재무활동으로인한현금흐름 | E77: -36020.57 | G77: -6104.82 | H77: -66183.58 | I77: 42904.39 | J77: 23254.12 | K77: -6129.89 | L77: -6663.95 | M77: -53622.22 | N77: 222830.33 | O77: -137519.84 | P77: 25024.32 | Q77: 151568.96 | R77: 78317.4 | S77: -138401.39 | T77: -58252.29 | U77: 33232.68 | V77: 182323.64 | W77: 44720.73 | X77: 243522.25 | Y77: 461636.61 | Z77: 932203.23 | AA77: 389475.68 | AB77: 1245791.9
A78: 1 | C78: 단기차입금의증가 | E78: 39000 | G78: 3000 | H78: 10000 | I78: 100353.5 | J78: 165000 | K78: 278353.5 | L78: 1000 | M78: 170000 | N78: 369000 | O78: 250000 | P78: 790000 | Q78: 285000 | R78: 310000 | S78: 540000 | T78: 371000 | U78: 1506000 | V78: 608000 | W78: 264000 | X78: 796000 | Y78: 606000 | Z78: 2274000 | AA78: 524100 | AB78: 1770000
A79: 1 | C79: 단기차입금의감소 | E79: 39000 | G79: 3000 | H79: 10000 | I79: 51426 | J79: 135000 | K79: 199426 | L79: 1000 | M79: 170000 | N79: 189000 | O79: 380000 | P79: 740000 | Q79: 125000 | R79: 420000 | S79: 640000 | T79: 421000 | U79: 1606000 | V79: 458000 | W79: 444000 | X79: 562000 | Y79: 653500 | Z79: 2117500 | AA79: 544500 | AB79: 220000
A80: 1 | C80: 유동성장기부채의감소 | E80: 30000
A81: 1 | C81: 장기차입금의증가 | E81: 0 | V81: 41300 | W81: 0 | X81: 68300 | Y81: 119046 | Z81: 228646 | AA81: 18700 | AB81: 0
A82: 1 | C82: 사채의감소 | E82: 0 | G82: 0 | H82: 30000 | I82: 0 | J82: 0 | K82: 30000 | N82: 0 | O82: 0 | T82: 0 | Y82: 50000
A83: 1 | C83: 자기주식의취득 | E83: 0 | G83: 0 | J83: 0
A84: 1 | C84: 리스부채의상환 | E84: 6020.57 | G84: 6104.82 | H84: 6291.16 | I84: 6023.11 | J84: 6745.88 | K84: 25164.97 | L84: 6663.95 | M84: 6873.9 | N84: 7051.9
A85: 1 | C85: 배당금지급 | E85: 0 | I85: 0 | J85: 0 | N85: 0 | O85: 0
A86: 1 | C86: 현금및현금성자산의증감 | E86: 201657.33 | G86: -798989.25 | H86: 245855.83 | I86: -175606.25 | J86: 251126.01 | K86: -477613.66 | L86: -234210.27 | M86: -460207.42 | N86: 59283.72 | O86: -61368.5 | P86: -696502.47 | Q86: -18419.85 | R86: -41560.15 | S86: -150610.98 | T86: -104203.12 | U86: -314794.1 | V86: -57512.87 | W86: 100045.52 | X86: -138577.66 | Y86: 8072.33 | Z86: -87972.68 | AA86: 243037.61 | AB86: 1046761
A87: 1 | C87: 기말현금및현금성자산 | E87: 201702.05 | G87: 822403.09 | H87: 245856.52 | I87: -175561.81 | J87: 250871.02 | K87: 1143568.8 | L87: 909441.85 | M87: -460257.62 | N87: 59283.08 | O87: -61528.04 | P87: 446939.27 | Q87: 428557.79 | R87: -41495.77 | S87: -157182.33 | T87: -97725.32 | U87: 132154.37 | V87: 74638.05 | W87: 100021.78 | X87: -138559.62 | Y87: 8075.12 | Z87: 44175.33 | AA87: 287220.28 | AB87: 1046762.4
A88: 1 | C88: 유형자산의감소 | G88: 16.02 | H88: 128.38 | I88: 3.02 | J88: 34.68 | K88: 182.1 | L88: 16 | M88: 8.33 | N88: 5.42 | O88: 46.61 | P88: 76.36 | Q88: 3.12 | R88: 12.76 | S88: 7.48 | T88: 10.74 | U88: 34.1 | V88: 141.67 | W88: 10.49 | X88: 1397 | Y88: 45.16 | Z88: 1594.32 | AA88: 28.49
A89: 1 | C89: 사채의증가 | O89: 0 | S89: 0 | T89: 0 | X89: 0 | Y89: 398622.05 | AA89: 398385.95 | AB89: 16.19
A90: 1 | C90: 이자수취(CF) | S90: 3299.56 | T90: 2522.47 | V90: 1054.25 | W90: 3228.23 | X90: 659.64 | Y90: 1035.95 | Z90: 5978.07 | AA90: 763.51
A91: 1 | C91: 법인세납부(CF) | S91: -6488.24 | T91: -6368.55 | V91: -0.11 | W91: -38280.28 | X91: -3210.5 | Y91: -6426.14 | Z91: -47917.03 | AA91: -406.22

Sheet subQ
A1: YQ | C1: subQ 분기 서브모델(억원, U=100) | E1: 4Q21 | F1: 2021 | G1: 1Q22 | H1: 2Q22 | I1: 3Q22 | J1: 4Q22 | K1: 2022 | L1: 1Q23 | M1: 2Q23 | N1: 3Q23 | O1: 4Q23 | P1: 2023 | Q1: 1Q24 | R1: 2Q24 | S1: 3Q24 | T1: 4Q24 | U1: 2024 | V1: 1Q25 | W1: 2Q25 | X1: 3Q25 | Y1: 4Q25 | Z1: 2025 | AA1: 1Q26 | AB1: 2Q26 | AC1: 3Q26 | AD1: 4Q26 | AE1: 2026 | AF1: 1Q27 | AG1: 2Q27 | AH1: 3Q27 | AI1: 4Q27 | AJ1: 2027 | AK1: 1Q28 | AL1: 2Q28 | AM1: 3Q28 | AN1: 4Q28 | AO1: 2028
A2: A=이름(key) B=그룹 C=단위 D=FnGuide 계정명(VLOOKUP 키). 확정=VLOOKUP(BS), 추정=변수 가정 참조
E3: 1 | F3: 2 | G3: 3 | H3: 4 | I3: 5 | J3: 6 | K3: 7 | L3: 8 | M3: 9 | N3: 10 | O3: 11 | P3: 12 | Q3: 13 | R3: 14 | S3: 15 | T3: 16 | U3: 17 | V3: 18 | W3: 19 | X3: 20 | Y3: 21 | Z3: 22 | AA3: 23 | AB3: 24 | AC3: 25 | AD3: 26 | AE3: 27 | AF3: 28 | AG3: 29 | AH3: 30 | AI3: 31 | AJ3: 32 | AK3: 33 | AL3: 34 | AM3: 35 | AN3: 36 | AO3: 37
E4: 2021.12 | F4: 2021.12A | G4: 2022.03 | H4: 2022.06 | I4: 2022.09 | J4: 2022.12 | K4: 2022.12A | L4: 2023.03 | M4: 2023.06 | N4: 2023.09 | O4: 2023.12 | P4: 2023.12A | Q4: 2024.03 | R4: 2024.06 | S4: 2024.09 | T4: 2024.12 | U4: 2024.12A | V4: 2025.03 | W4: 2025.06 | X4: 2025.09 | Y4: 2025.12 | Z4: 2025.12A | AA4: 2026.03 | AB4: 2026.06 | AC4: 2026.09 | AD4: 2026.12 | AE4: 2026.12A | AF4: 2027.03 | AG4: 2027.06 | AH4: 2027.09 | AI4: 2027.12 | AJ4: 2027.12A | AK4: 2028.03 | AL4: 2028.06 | AM4: 2028.09 | AN4: 2028.12 | AO4: 2028.12A
A5: 매출액 | B5: 손익 | C5: 억원 | D5: 매출액(수익) | E5: =IFERROR(VLOOKUP($D5,BS연결,MATCH(E$1,BS연결H,0),0)/100,"") | G5: =IFERROR(VLOOKUP($D5,BS연결,MATCH(G$1,BS연결H,0),0)/100,"") | H5: =IFERROR(VLOOKUP($D5,BS연결,MATCH(H$1,BS연결H,0),0)/100,"") | I5: =IFERROR(VLOOKUP($D5,BS연결,MATCH(I$1,BS연결H,0),0)/100,"") | J5: =IFERROR(VLOOKUP($D5,BS연결,MATCH(J$1,BS연결H,0),0)/100,"") | K5: =IFERROR(VLOOKUP($D5,BS연결,MATCH(K$1,BS연결H,0),0)/100,"") | L5: =IFERROR(VLOOKUP($D5,BS연결,MATCH(L$1,BS연결H,0),0)/100,"") | M5: =IFERROR(VLOOKUP($D5,BS연결,MATCH(M$1,BS연결H,0),0)/100,"") | N5: =IFERROR(VLOOKUP($D5,BS연결,MATCH(N$1,BS연결H,0),0)/100,"") | ... AB5: =IFERROR(VLOOKUP($D5,BS연결,MATCH(AB$1,BS연결H,0),0)/100,"") | AC5: =IFERROR(X5*(1+변수!AC21),"") | AD5: =IFERROR(Y5*(1+변수!AD21),"") | AE5: =SUM(AA5:AD5) | AF5: =IFERROR(AA5*(1+변수!AF21),"") | AG5: =IFERROR(AB5*(1+변수!AG21),"") | AH5: =IFERROR(AC5*(1+변수!AH21),"") | AI5: =IFERROR(AD5*(1+변수!AI21),"") | AJ5: =SUM(AF5:AI5) | AK5: =IFERROR(AF5*(1+변수!AK21),"") | AL5: =IFERROR(AG5*(1+변수!AL21),"") | AM5: =IFERROR(AH5*(1+변수!AM21),"") | AN5: =IFERROR(AI5*(1+변수!AN21),"") | AO5: =SUM(AK5:AN5)
A6: 매출원가 | B6: 손익 | C6: 억원 | D6: 매출원가 | E6: =IFERROR(VLOOKUP($D6,BS연결,MATCH(E$1,BS연결H,0),0)/100,"") | G6: =IFERROR(VLOOKUP($D6,BS연결,MATCH(G$1,BS연결H,0),0)/100,"") | H6: =IFERROR(VLOOKUP($D6,BS연결,MATCH(H$1,BS연결H,0),0)/100,"") | I6: =IFERROR(VLOOKUP($D6,BS연결,MATCH(I$1,BS연결H,0),0)/100,"") | J6: =IFERROR(VLOOKUP($D6,BS연결,MATCH(J$1,BS연결H,0),0)/100,"") | K6: =IFERROR(VLOOKUP($D6,BS연결,MATCH(K$1,BS연결H,0),0)/100,"") | L6: =IFERROR(VLOOKUP($D6,BS연결,MATCH(L$1,BS연결H,0),0)/100,"") | M6: =IFERROR(VLOOKUP($D6,BS연결,MATCH(M$1,BS연결H,0),0)/100,"") | N6: =IFERROR(VLOOKUP($D6,BS연결,MATCH(N$1,BS연결H,0),0)/100,"") | ... AB6: =IFERROR(VLOOKUP($D6,BS연결,MATCH(AB$1,BS연결H,0),0)/100,"") | AC6: =IFERROR(AC5-AC7,"") | AD6: =IFERROR(AD5-AD7,"") | AE6: =SUM(AA6:AD6) | AF6: =IFERROR(AF5-AF7,"") | AG6: =IFERROR(AG5-AG7,"") | AH6: =IFERROR(AH5-AH7,"") | AI6: =IFERROR(AI5-AI7,"") | AJ6: =SUM(AF6:AI6) | AK6: =IFERROR(AK5-AK7,"") | AL6: =IFERROR(AL5-AL7,"") | AM6: =IFERROR(AM5-AM7,"") | AN6: =IFERROR(AN5-AN7,"") | AO6: =SUM(AK6:AN6)
A7: 매출총이익 | B7: 손익 | C7: 억원 | D7: 매출총이익 | E7: =IFERROR(VLOOKUP($D7,BS연결,MATCH(E$1,BS연결H,0),0)/100,"") | G7: =IFERROR(VLOOKUP($D7,BS연결,MATCH(G$1,BS연결H,0),0)/100,"") | H7: =IFERROR(VLOOKUP($D7,BS연결,MATCH(H$1,BS연결H,0),0)/100,"") | I7: =IFERROR(VLOOKUP($D7,BS연결,MATCH(I$1,BS연결H,0),0)/100,"") | J7: =IFERROR(VLOOKUP($D7,BS연결,MATCH(J$1,BS연결H,0),0)/100,"") | K7: =IFERROR(VLOOKUP($D7,BS연결,MATCH(K$1,BS연결H,0),0)/100,"") | L7: =IFERROR(VLOOKUP($D7,BS연결,MATCH(L$1,BS연결H,0),0)/100,"") | M7: =IFERROR(VLOOKUP($D7,BS연결,MATCH(M$1,BS연결H,0),0)/100,"") | N7: =IFERROR(VLOOKUP($D7,BS연결,MATCH(N$1,BS연결H,0),0)/100,"") | ... AB7: =IFERROR(VLOOKUP($D7,BS연결,MATCH(AB$1,BS연결H,0),0)/100,"") | AC7: =IFERROR(AC9+AC8,"") | AD7: =IFERROR(AD9+AD8,"") | AE7: =SUM(AA7:AD7) | AF7: =IFERROR(AF9+AF8,"") | AG7: =IFERROR(AG9+AG8,"") | AH7: =IFERROR(AH9+AH8,"") | AI7: =IFERROR(AI9+AI8,"") | AJ7: =SUM(AF7:AI7) | AK7: =IFERROR(AK9+AK8,"") | AL7: =IFERROR(AL9+AL8,"") | AM7: =IFERROR(AM9+AM8,"") | AN7: =IFERROR(AN9+AN8,"") | AO7: =SUM(AK7:AN7)
A8: 판관비 | B8: 손익 | C8: 억원 | D8: 판관비 | E8: =IFERROR(VLOOKUP($D8,BS연결,MATCH(E$1,BS연결H,0),0)/100,"") | G8: =IFERROR(VLOOKUP($D8,BS연결,MATCH(G$1,BS연결H,0),0)/100,"") | H8: =IFERROR(VLOOKUP($D8,BS연결,MATCH(H$1,BS연결H,0),0)/100,"") | I8: =IFERROR(VLOOKUP($D8,BS연결,MATCH(I$1,BS연결H,0),0)/100,"") | J8: =IFERROR(VLOOKUP($D8,BS연결,MATCH(J$1,BS연결H,0),0)/100,"") | K8: =IFERROR(VLOOKUP($D8,BS연결,MATCH(K$1,BS연결H,0),0)/100,"") | L8: =IFERROR(VLOOKUP($D8,BS연결,MATCH(L$1,BS연결H,0),0)/100,"") | M8: =IFERROR(VLOOKUP($D8,BS연결,MATCH(M$1,BS연결H,0),0)/100,"") | N8: =IFERROR(VLOOKUP($D8,BS연결,MATCH(N$1,BS연결H,0),0)/100,"") | ... AB8: =IFERROR(VLOOKUP($D8,BS연결,MATCH(AB$1,BS연결H,0),0)/100,"") | AC8: =IFERROR(AC5*변수!AC22,"") | AD8: =IFERROR(AD5*변수!AD22,"") | AE8: =SUM(AA8:AD8) | AF8: =IFERROR(AF5*변수!AF22,"") | AG8: =IFERROR(AG5*변수!AG22,"") | AH8: =IFERROR(AH5*변수!AH22,"") | AI8: =IFERROR(AI5*변수!AI22,"") | AJ8: =SUM(AF8:AI8) | AK8: =IFERROR(AK5*변수!AK22,"") | AL8: =IFERROR(AL5*변수!AL22,"") | AM8: =IFERROR(AM5*변수!AM22,"") | AN8: =IFERROR(AN5*변수!AN22,"") | AO8: =SUM(AK8:AN8)
A9: 영업이익 | B9: 손익 | C9: 억원 | D9: 영업이익 | E9: =IFERROR(VLOOKUP($D9,BS연결,MATCH(E$1,BS연결H,0),0)/100,"") | G9: =IFERROR(VLOOKUP($D9,BS연결,MATCH(G$1,BS연결H,0),0)/100,"") | H9: =IFERROR(VLOOKUP($D9,BS연결,MATCH(H$1,BS연결H,0),0)/100,"") | I9: =IFERROR(VLOOKUP($D9,BS연결,MATCH(I$1,BS연결H,0),0)/100,"") | J9: =IFERROR(VLOOKUP($D9,BS연결,MATCH(J$1,BS연결H,0),0)/100,"") | K9: =IFERROR(VLOOKUP($D9,BS연결,MATCH(K$1,BS연결H,0),0)/100,"") | L9: =IFERROR(VLOOKUP($D9,BS연결,MATCH(L$1,BS연결H,0),0)/100,"") | M9: =IFERROR(VLOOKUP($D9,BS연결,MATCH(M$1,BS연결H,0),0)/100,"") | N9: =IFERROR(VLOOKUP($D9,BS연결,MATCH(N$1,BS연결H,0),0)/100,"") | ... AB9: =IFERROR(VLOOKUP($D9,BS연결,MATCH(AB$1,BS연결H,0),0)/100,"") | AC9: =IFERROR(AC5*변수!AC23,"") | AD9: =IFERROR(AD5*변수!AD23,"") | AE9: =SUM(AA9:AD9) | AF9: =IFERROR(AF5*변수!AF23,"") | AG9: =IFERROR(AG5*변수!AG23,"") | AH9: =IFERROR(AH5*변수!AH23,"") | AI9: =IFERROR(AI5*변수!AI23,"") | AJ9: =SUM(AF9:AI9) | AK9: =IFERROR(AK5*변수!AK23,"") | AL9: =IFERROR(AL5*변수!AL23,"") | AM9: =IFERROR(AM5*변수!AM23,"") | AN9: =IFERROR(AN5*변수!AN23,"") | AO9: =SUM(AK9:AN9)
A10: OPM | B10: 손익 | C10: % | D10: 영업이익률 | E10: =IFERROR(E9/E5,"") | G10: =IFERROR(G9/G5,"") | H10: =IFERROR(H9/H5,"") | I10: =IFERROR(I9/I5,"") | J10: =IFERROR(J9/J5,"") | K10: =IFERROR(K9/K5,"") | L10: =IFERROR(L9/L5,"") | M10: =IFERROR(M9/M5,"") | N10: =IFERROR(N9/N5,"") | ... AO10: =IFERROR(AO9/AO5,"")
A11: 금융손익 | B11: 손익 | C11: 억원 | D11: 금융손익 | E11: =IFERROR(VLOOKUP($D11,BS연결,MATCH(E$1,BS연결H,0),0)/100,"") | G11: =IFERROR(VLOOKUP($D11,BS연결,MATCH(G$1,BS연결H,0),0)/100,"") | H11: =IFERROR(VLOOKUP($D11,BS연결,MATCH(H$1,BS연결H,0),0)/100,"") | I11: =IFERROR(VLOOKUP($D11,BS연결,MATCH(I$1,BS연결H,0),0)/100,"") | J11: =IFERROR(VLOOKUP($D11,BS연결,MATCH(J$1,BS연결H,0),0)/100,"") | K11: =IFERROR(VLOOKUP($D11,BS연결,MATCH(K$1,BS연결H,0),0)/100,"") | L11: =IFERROR(VLOOKUP($D11,BS연결,MATCH(L$1,BS연결H,0),0)/100,"") | M11: =IFERROR(VLOOKUP($D11,BS연결,MATCH(M$1,BS연결H,0),0)/100,"") | N11: =IFERROR(VLOOKUP($D11,BS연결,MATCH(N$1,BS연결H,0),0)/100,"") | ... AB11: =IFERROR(VLOOKUP($D11,BS연결,MATCH(AB$1,BS연결H,0),0)/100,"") | AC11: =IFERROR(AC12+AC13+AC14,"") | AD11: =IFERROR(AD12+AD13+AD14,"") | AE11: =SUM(AA11:AD11) | AF11: =IFERROR(AF12+AF13+AF14,"") | AG11: =IFERROR(AG12+AG13+AG14,"") | AH11: =IFERROR(AH12+AH13+AH14,"") | AI11: =IFERROR(AI12+AI13+AI14,"") | AJ11: =SUM(AF11:AI11) | AK11: =IFERROR(AK12+AK13+AK14,"") | AL11: =IFERROR(AL12+AL13+AL14,"") | AM11: =IFERROR(AM12+AM13+AM14,"") | AN11: =IFERROR(AN12+AN13+AN14,"") | AO11: =SUM(AK11:AN11)
A12: 이자손익 | B12: 손익 | C12: 억원 | D12: 이자손익 | G12: =IFERROR(VLOOKUP($D12,BS연결,MATCH(G$1,BS연결H,0),0)/100,"") | H12: =IFERROR(VLOOKUP($D12,BS연결,MATCH(H$1,BS연결H,0),0)/100,"") | I12: =IFERROR(VLOOKUP($D12,BS연결,MATCH(I$1,BS연결H,0),0)/100,"") | J12: =IFERROR(VLOOKUP($D12,BS연결,MATCH(J$1,BS연결H,0),0)/100,"") | K12: =IFERROR(VLOOKUP($D12,BS연결,MATCH(K$1,BS연결H,0),0)/100,"") | L12: =IFERROR(VLOOKUP($D12,BS연결,MATCH(L$1,BS연결H,0),0)/100,"") | M12: =IFERROR(VLOOKUP($D12,BS연결,MATCH(M$1,BS연결H,0),0)/100,"") | N12: =IFERROR(VLOOKUP($D12,BS연결,MATCH(N$1,BS연결H,0),0)/100,"") | ... AB12: =IFERROR(VLOOKUP($D12,BS연결,MATCH(AB$1,BS연결H,0),0)/100,"") | AC12: =IFERROR((AB28*변수!$D$54-AB26*변수!$D$55)/4,"") | AD12: =IFERROR((AC28*변수!$D$54-AC26*변수!$D$55)/4,"") | AE12: =SUM(AA12:AD12) | AF12: =IFERROR((AD28*변수!$D$54-AD26*변수!$D$55)/4,"") | AG12: =IFERROR((AF28*변수!$D$54-AF26*변수!$D$55)/4,"") | AH12: =IFERROR((AG28*변수!$D$54-AG26*변수!$D$55)/4,"") | AI12: =IFERROR((AH28*변수!$D$54-AH26*변수!$D$55)/4,"") | AJ12: =SUM(AF12:AI12) | AK12: =IFERROR((AI28*변수!$D$54-AI26*변수!$D$55)/4,"") | AL12: =IFERROR((AK28*변수!$D$54-AK26*변수!$D$55)/4,"") | AM12: =IFERROR((AL28*변수!$D$54-AL26*변수!$D$55)/4,"") | AN12: =IFERROR((AM28*변수!$D$54-AM26*변수!$D$55)/4,"") | AO12: =SUM(AK12:AN12)
A13: 외환손익 | B13: 손익 | C13: 억원 | D13: 외환손익(실적만; 추정 환효과는 환관련손익) | G13: =IFERROR((VLOOKUP("외환차익",BS연결,MATCH(G$1,BS연결H,0),0)-VLOOKUP("외환차손",BS연결,MATCH(G$1,BS연결H,0),0)+VLOOKUP("외화환산이익",BS연결,MATCH(G$1,BS연결H,0),0)-VLOOKUP("외화환산손실",BS연결,MATCH(G$1,BS연결H,0),0))/100,"") | H13: =IFERROR((VLOOKUP("외환차익",BS연결,MATCH(H$1,BS연결H,0),0)-VLOOKUP("외환차손",BS연결,MATCH(H$1,BS연결H,0),0)+VLOOKUP("외화환산이익",BS연결,MATCH(H$1,BS연결H,0),0)-VLOOKUP("외화환산손실",BS연결,MATCH(H$1,BS연결H,0),0))/100,"") | I13: =IFERROR((VLOOKUP("외환차익",BS연결,MATCH(I$1,BS연결H,0),0)-VLOOKUP("외환차손",BS연결,MATCH(I$1,BS연결H,0),0)+VLOOKUP("외화환산이익",BS연결,MATCH(I$1,BS연결H,0),0)-VLOOKUP("외화환산손실",BS연결,MATCH(I$1,BS연결H,0),0))/100,"") | J13: =IFERROR((VLOOKUP("외환차익",BS연결,MATCH(J$1,BS연결H,0),0)-VLOOKUP("외환차손",BS연결,MATCH(J$1,BS연결H,0),0)+VLOOKUP("외화환산이익",BS연결,MATCH(J$1,BS연결H,0),0)-VLOOKUP("외화환산손실",BS연결,MATCH(J$1,BS연결H,0),0))/100,"") | K13: =SUM(G13:J13) | L13: =IFERROR((VLOOKUP("외환차익",BS연결,MATCH(L$1,BS연결H,0),0)-VLOOKUP("외환차손",BS연결,MATCH(L$1,BS연결H,0),0)+VLOOKUP("외화환산이익",BS연결,MATCH(L$1,BS연결H,0),0)-VLOOKUP("외화환산손실",BS연결,MATCH(L$1,BS연결H,0),0))/100,"") | M13: =IFERROR((VLOOKUP("외환차익",BS연결,MATCH(M$1,BS연결H,0),0)-VLOOKUP("외환차손",BS연결,MATCH(M$1,BS연결H,0),0)+VLOOKUP("외화환산이익",BS연결,MATCH(M$1,BS연결H,0),0)-VLOOKUP("외화환산손실",BS연결,MATCH(M$1,BS연결H,0),0))/100,"") | N13: =IFERROR((VLOOKUP("외환차익",BS연결,MATCH(N$1,BS연결H,0),0)-VLOOKUP("외환차손",BS연결,MATCH(N$1,BS연결H,0),0)+VLOOKUP("외화환산이익",BS연결,MATCH(N$1,BS연결H,0),0)-VLOOKUP("외화환산손실",BS연결,MATCH(N$1,BS연결H,0),0))/100,"") | O13: =IFERROR((VLOOKUP("외환차익",BS연결,MATCH(O$1,BS연결H,0),0)-VLOOKUP("외환차손",BS연결,MATCH(O$1,BS연결H,0),0)+VLOOKUP("외화환산이익",BS연결,MATCH(O$1,BS연결H,0),0)-VLOOKUP("외화환산손실",BS연결,MATCH(O$1,BS연결H,0),0))/100,"") | P13: =SUM(L13:O13) | Q13: =IFERROR((VLOOKUP("외환차익",BS연결,MATCH(Q$1,BS연결H,0),0)-VLOOKUP("외환차손",BS연결,MATCH(Q$1,BS연결H,0),0)+VLOOKUP("외화환산이익",BS연결,MATCH(Q$1,BS연결H,0),0)-VLOOKUP("외화환산손실",BS연결,MATCH(Q$1,BS연결H,0),0))/100,"") | R13: =IFERROR((VLOOKUP("외환차익",BS연결,MATCH(R$1,BS연결H,0),0)-VLOOKUP("외환차손",BS연결,MATCH(R$1,BS연결H,0),0)+VLOOKUP("외화환산이익",BS연결,MATCH(R$1,BS연결H,0),0)-VLOOKUP("외화환산손실",BS연결,MATCH(R$1,BS연결H,0),0))/100,"") | S13: =IFERROR((VLOOKUP("외환차익",BS연결,MATCH(S$1,BS연결H,0),0)-VLOOKUP("외환차손",BS연결,MATCH(S$1,BS연결H,0),0)+VLOOKUP("외화환산이익",BS연결,MATCH(S$1,BS연결H,0),0)-VLOOKUP("외화환산손실",BS연결,MATCH(S$1,BS연결H,0),0))/100,"") | T13: =IFERROR((VLOOKUP("외환차익",BS연결,MATCH(T$1,BS연결H,0),0)-VLOOKUP("외환차손",BS연결,MATCH(T$1,BS연결H,0),0)+VLOOKUP("외화환산이익",BS연결,MATCH(T$1,BS연결H,0),0)-VLOOKUP("외화환산손실",BS연결,MATCH(T$1,BS연결H,0),0))/100,"") | U13: =SUM(Q13:T13) | V13: =IFERROR((VLOOKUP("외환차익",BS연결,MATCH(V$1,BS연결H,0),0)-VLOOKUP("외환차손",BS연결,MATCH(V$1,BS연결H,0),0)+VLOOKUP("외화환산이익",BS연결,MATCH(V$1,BS연결H,0),0)-VLOOKUP("외화환산손실",BS연결,MATCH(V$1,BS연결H,0),0))/100,"") | W13: =IFERROR((VLOOKUP("외환차익",BS연결,MATCH(W$1,BS연결H,0),0)-VLOOKUP("외환차손",BS연결,MATCH(W$1,BS연결H,0),0)+VLOOKUP("외화환산이익",BS연결,MATCH(W$1,BS연결H,0),0)-VLOOKUP("외화환산손실",BS연결,MATCH(W$1,BS연결H,0),0))/100,"") | X13: =IFERROR((VLOOKUP("외환차익",BS연결,MATCH(X$1,BS연결H,0),0)-VLOOKUP("외환차손",BS연결,MATCH(X$1,BS연결H,0),0)+VLOOKUP("외화환산이익",BS연결,MATCH(X$1,BS연결H,0),0)-VLOOKUP("외화환산손실",BS연결,MATCH(X$1,BS연결H,0),0))/100,"") | Y13: =IFERROR((VLOOKUP("외환차익",BS연결,MATCH(Y$1,BS연결H,0),0)-VLOOKUP("외환차손",BS연결,MATCH(Y$1,BS연결H,0),0)+VLOOKUP("외화환산이익",BS연결,MATCH(Y$1,BS연결H,0),0)-VLOOKUP("외화환산손실",BS연결,MATCH(Y$1,BS연결H,0),0))/100,"") | Z13: =SUM(V13:Y13) | AA13: =IFERROR((VLOOKUP("외환차익",BS연결,MATCH(AA$1,BS연결H,0),0)-VLOOKUP("외환차손",BS연결,MATCH(AA$1,BS연결H,0),0)+VLOOKUP("외화환산이익",BS연결,MATCH(AA$1,BS연결H,0),0)-VLOOKUP("외화환산손실",BS연결,MATCH(AA$1,BS연결H,0),0))/100,"") | AB13: =IFERROR((VLOOKUP("외환차익",BS연결,MATCH(AB$1,BS연결H,0),0)-VLOOKUP("외환차손",BS연결,MATCH(AB$1,BS연결H,0),0)+VLOOKUP("외화환산이익",BS연결,MATCH(AB$1,BS연결H,0),0)-VLOOKUP("외화환산손실",BS연결,MATCH(AB$1,BS연결H,0),0))/100,"") | AC13: =변수!AC24 | AD13: =변수!AD24 | AE13: =SUM(AA13:AD13) | AF13: =변수!AF24 | AG13: =변수!AG24 | AH13: =변수!AH24 | AI13: =변수!AI24 | AJ13: =SUM(AF13:AI13) | AK13: =변수!AK24 | AL13: =변수!AL24 | AM13: =변수!AM24 | AN13: =변수!AN24 | AO13: =SUM(AK13:AN13)
A14: 기타금융손익 | B14: 손익 | C14: 억원 | D14: 기타금융손익(금융손익 잔차) | G14: 0 | H14: 0.08 | I14: 0 | J14: 0 | K14: =SUM(G14:J14) | L14: 0 | M14: 0.05 | N14: 0 | O14: 0 | P14: =SUM(L14:O14) | Q14: 0 | R14: 0.04 | S14: -0.01 | T14: 0 | U14: =SUM(Q14:T14) | V14: 97.76 | W14: 2.94 | X14: 186.98 | Y14: 1.78 | Z14: =SUM(V14:Y14) | AA14: 78.38 | AB14: 10.52 | AC14: =변수!AC25 | AD14: =변수!AD25 | AE14: =SUM(AA14:AD14) | AF14: =변수!AF25 | AG14: =변수!AG25 | AH14: =변수!AH25 | AI14: =변수!AI25 | AJ14: =SUM(AF14:AI14) | AK14: =변수!AK25 | AL14: =변수!AL25 | AM14: =변수!AM25 | AN14: =변수!AN25 | AO14: =SUM(AK14:AN14)
A15: 기타영업외손익 | B15: 손익 | C15: 억원 | D15: 기타영업외손익 | E15: =IFERROR(VLOOKUP($D15,BS연결,MATCH(E$1,BS연결H,0),0)/100,"") | G15: =IFERROR(VLOOKUP($D15,BS연결,MATCH(G$1,BS연결H,0),0)/100,"") | H15: =IFERROR(VLOOKUP($D15,BS연결,MATCH(H$1,BS연결H,0),0)/100,"") | I15: =IFERROR(VLOOKUP($D15,BS연결,MATCH(I$1,BS연결H,0),0)/100,"") | J15: =IFERROR(VLOOKUP($D15,BS연결,MATCH(J$1,BS연결H,0),0)/100,"") | K15: =IFERROR(VLOOKUP($D15,BS연결,MATCH(K$1,BS연결H,0),0)/100,"") | L15: =IFERROR(VLOOKUP($D15,BS연결,MATCH(L$1,BS연결H,0),0)/100,"") | M15: =IFERROR(VLOOKUP($D15,BS연결,MATCH(M$1,BS연결H,0),0)/100,"") | N15: =IFERROR(VLOOKUP($D15,BS연결,MATCH(N$1,BS연결H,0),0)/100,"") | ... AB15: =IFERROR(VLOOKUP($D15,BS연결,MATCH(AB$1,BS연결H,0),0)/100,"") | AC15: =변수!AC26 | AD15: =변수!AD26 | AE15: =SUM(AA15:AD15) | AF15: =변수!AF26 | AG15: =변수!AG26 | AH15: =변수!AH26 | AI15: =변수!AI26 | AJ15: =SUM(AF15:AI15) | AK15: =변수!AK26 | AL15: =변수!AL26 | AM15: =변수!AM26 | AN15: =변수!AN26 | AO15: =SUM(AK15:AN15)
A16: 지분법손익 | B16: 손익 | C16: 억원 | D16: 종속기업,공동지배기업및관계기업관련손익 | E16: =IFERROR(VLOOKUP($D16,BS연결,MATCH(E$1,BS연결H,0),0)/100,"") | G16: =IFERROR(VLOOKUP($D16,BS연결,MATCH(G$1,BS연결H,0),0)/100,"") | H16: =IFERROR(VLOOKUP($D16,BS연결,MATCH(H$1,BS연결H,0),0)/100,"") | I16: =IFERROR(VLOOKUP($D16,BS연결,MATCH(I$1,BS연결H,0),0)/100,"") | J16: =IFERROR(VLOOKUP($D16,BS연결,MATCH(J$1,BS연결H,0),0)/100,"") | K16: =IFERROR(VLOOKUP($D16,BS연결,MATCH(K$1,BS연결H,0),0)/100,"") | L16: =IFERROR(VLOOKUP($D16,BS연결,MATCH(L$1,BS연결H,0),0)/100,"") | M16: =IFERROR(VLOOKUP($D16,BS연결,MATCH(M$1,BS연결H,0),0)/100,"") | N16: =IFERROR(VLOOKUP($D16,BS연결,MATCH(N$1,BS연결H,0),0)/100,"") | ... AA16: =IFERROR(VLOOKUP($D16,BS연결,MATCH(AA$1,BS연결H,0),0)/100,"") | AC16: =변수!AC27 | AD16: =변수!AD27 | AE16: =SUM(AA16:AD16) | AF16: =변수!AF27 | AG16: =변수!AG27 | AH16: =변수!AH27 | AI16: =변수!AI27 | AJ16: =SUM(AF16:AI16) | AK16: =변수!AK27 | AL16: =변수!AL27 | AM16: =변수!AM27 | AN16: =변수!AN27 | AO16: =SUM(AK16:AN16)
A17: 세전이익 | B17: 손익 | C17: 억원 | D17: 법인세비용차감전계속사업이익 | E17: =IFERROR(VLOOKUP($D17,BS연결,MATCH(E$1,BS연결H,0),0)/100,"") | G17: =IFERROR(VLOOKUP($D17,BS연결,MATCH(G$1,BS연결H,0),0)/100,"") | H17: =IFERROR(VLOOKUP($D17,BS연결,MATCH(H$1,BS연결H,0),0)/100,"") | I17: =IFERROR(VLOOKUP($D17,BS연결,MATCH(I$1,BS연결H,0),0)/100,"") | J17: =IFERROR(VLOOKUP($D17,BS연결,MATCH(J$1,BS연결H,0),0)/100,"") | K17: =IFERROR(VLOOKUP($D17,BS연결,MATCH(K$1,BS연결H,0),0)/100,"") | L17: =IFERROR(VLOOKUP($D17,BS연결,MATCH(L$1,BS연결H,0),0)/100,"") | M17: =IFERROR(VLOOKUP($D17,BS연결,MATCH(M$1,BS연결H,0),0)/100,"") | N17: =IFERROR(VLOOKUP($D17,BS연결,MATCH(N$1,BS연결H,0),0)/100,"") | ... AB17: =IFERROR(VLOOKUP($D17,BS연결,MATCH(AB$1,BS연결H,0),0)/100,"") | AC17: =IFERROR(AC9+AC11+AC15+AC16,"") | AD17: =IFERROR(AD9+AD11+AD15+AD16,"") | AE17: =SUM(AA17:AD17) | AF17: =IFERROR(AF9+AF11+AF15+AF16,"") | AG17: =IFERROR(AG9+AG11+AG15+AG16,"") | AH17: =IFERROR(AH9+AH11+AH15+AH16,"") | AI17: =IFERROR(AI9+AI11+AI15+AI16,"") | AJ17: =SUM(AF17:AI17) | AK17: =IFERROR(AK9+AK11+AK15+AK16,"") | AL17: =IFERROR(AL9+AL11+AL15+AL16,"") | AM17: =IFERROR(AM9+AM11+AM15+AM16,"") | AN17: =IFERROR(AN9+AN11+AN15+AN16,"") | AO17: =SUM(AK17:AN17)
A18: 법인세비용 | B18: 손익 | C18: 억원 | D18: 법인세비용 | E18: =IFERROR(VLOOKUP($D18,BS연결,MATCH(E$1,BS연결H,0),0)/100,"") | G18: =IFERROR(VLOOKUP($D18,BS연결,MATCH(G$1,BS연결H,0),0)/100,"") | H18: =IFERROR(VLOOKUP($D18,BS연결,MATCH(H$1,BS연결H,0),0)/100,"") | I18: =IFERROR(VLOOKUP($D18,BS연결,MATCH(I$1,BS연결H,0),0)/100,"") | J18: =IFERROR(VLOOKUP($D18,BS연결,MATCH(J$1,BS연결H,0),0)/100,"") | K18: =IFERROR(VLOOKUP($D18,BS연결,MATCH(K$1,BS연결H,0),0)/100,"") | L18: =IFERROR(VLOOKUP($D18,BS연결,MATCH(L$1,BS연결H,0),0)/100,"") | M18: =IFERROR(VLOOKUP($D18,BS연결,MATCH(M$1,BS연결H,0),0)/100,"") | N18: =IFERROR(VLOOKUP($D18,BS연결,MATCH(N$1,BS연결H,0),0)/100,"") | ... AB18: =IFERROR(VLOOKUP($D18,BS연결,MATCH(AB$1,BS연결H,0),0)/100,"") | AC18: =IFERROR(MAX(AC17,0)*변수!AC28,"") | AD18: =IFERROR(MAX(AD17,0)*변수!AD28,"") | AE18: =SUM(AA18:AD18) | AF18: =IFERROR(MAX(AF17,0)*변수!AF28,"") | AG18: =IFERROR(MAX(AG17,0)*변수!AG28,"") | AH18: =IFERROR(MAX(AH17,0)*변수!AH28,"") | AI18: =IFERROR(MAX(AI17,0)*변수!AI28,"") | AJ18: =SUM(AF18:AI18) | AK18: =IFERROR(MAX(AK17,0)*변수!AK28,"") | AL18: =IFERROR(MAX(AL17,0)*변수!AL28,"") | AM18: =IFERROR(MAX(AM17,0)*변수!AM28,"") | AN18: =IFERROR(MAX(AN17,0)*변수!AN28,"") | AO18: =SUM(AK18:AN18)
A19: 당기순이익 | B19: 손익 | C19: 억원 | D19: 당기순이익 | E19: =IFERROR(VLOOKUP($D19,BS연결,MATCH(E$1,BS연결H,0),0)/100,"") | G19: =IFERROR(VLOOKUP($D19,BS연결,MATCH(G$1,BS연결H,0),0)/100,"") | H19: =IFERROR(VLOOKUP($D19,BS연결,MATCH(H$1,BS연결H,0),0)/100,"") | I19: =IFERROR(VLOOKUP($D19,BS연결,MATCH(I$1,BS연결H,0),0)/100,"") | J19: =IFERROR(VLOOKUP($D19,BS연결,MATCH(J$1,BS연결H,0),0)/100,"") | K19: =IFERROR(VLOOKUP($D19,BS연결,MATCH(K$1,BS연결H,0),0)/100,"") | L19: =IFERROR(VLOOKUP($D19,BS연결,MATCH(L$1,BS연결H,0),0)/100,"") | M19: =IFERROR(VLOOKUP($D19,BS연결,MATCH(M$1,BS연결H,0),0)/100,"") | N19: =IFERROR(VLOOKUP($D19,BS연결,MATCH(N$1,BS연결H,0),0)/100,"") | ... AB19: =IFERROR(VLOOKUP($D19,BS연결,MATCH(AB$1,BS연결H,0),0)/100,"") | AC19: =IFERROR(AC17-AC18,"") | AD19: =IFERROR(AD17-AD18,"") | AE19: =SUM(AA19:AD19) | AF19: =IFERROR(AF17-AF18,"") | AG19: =IFERROR(AG17-AG18,"") | AH19: =IFERROR(AH17-AH18,"") | AI19: =IFERROR(AI17-AI18,"") | AJ19: =SUM(AF19:AI19) | AK19: =IFERROR(AK17-AK18,"") | AL19: =IFERROR(AL17-AL18,"") | AM19: =IFERROR(AM17-AM18,"") | AN19: =IFERROR(AN17-AN18,"") | AO19: =SUM(AK19:AN19)
A20: 지배주주순이익 | B20: 손익 | C20: 억원 | D20: (지배주주지분)당기순이익 | E20: =IFERROR(VLOOKUP($D20,BS연결,MATCH(E$1,BS연결H,0),0)/100,"") | G20: =IFERROR(VLOOKUP($D20,BS연결,MATCH(G$1,BS연결H,0),0)/100,"") | H20: =IFERROR(VLOOKUP($D20,BS연결,MATCH(H$1,BS연결H,0),0)/100,"") | I20: =IFERROR(VLOOKUP($D20,BS연결,MATCH(I$1,BS연결H,0),0)/100,"") | J20: =IFERROR(VLOOKUP($D20,BS연결,MATCH(J$1,BS연결H,0),0)/100,"") | K20: =IFERROR(VLOOKUP($D20,BS연결,MATCH(K$1,BS연결H,0),0)/100,"") | L20: =IFERROR(VLOOKUP($D20,BS연결,MATCH(L$1,BS연결H,0),0)/100,"") | M20: =IFERROR(VLOOKUP($D20,BS연결,MATCH(M$1,BS연결H,0),0)/100,"") | N20: =IFERROR(VLOOKUP($D20,BS연결,MATCH(N$1,BS연결H,0),0)/100,"") | ... AB20: =IFERROR(VLOOKUP($D20,BS연결,MATCH(AB$1,BS연결H,0),0)/100,"") | AC20: =IFERROR(AC19*변수!AC29,"") | AD20: =IFERROR(AD19*변수!AD29,"") | AE20: =SUM(AA20:AD20) | AF20: =IFERROR(AF19*변수!AF29,"") | AG20: =IFERROR(AG19*변수!AG29,"") | AH20: =IFERROR(AH19*변수!AH29,"") | AI20: =IFERROR(AI19*변수!AI29,"") | AJ20: =SUM(AF20:AI20) | AK20: =IFERROR(AK19*변수!AK29,"") | AL20: =IFERROR(AL19*변수!AL29,"") | AM20: =IFERROR(AM19*변수!AM29,"") | AN20: =IFERROR(AN19*변수!AN29,"") | AO20: =SUM(AK20:AN20)
A21: 중단사업이익 | B21: 손익 | C21: 억원 | D21: 중단사업이익 | K21: =SUM(G21:J21) | O21: =IFERROR(VLOOKUP($D21,BS연결,MATCH(O$1,BS연결H,0),0)/100,"") | P21: =SUM(L21:O21) | Q21: =IFERROR(VLOOKUP($D21,BS연결,MATCH(Q$1,BS연결H,0),0)/100,"") | R21: =IFERROR(VLOOKUP($D21,BS연결,MATCH(R$1,BS연결H,0),0)/100,"") | S21: =IFERROR(VLOOKUP($D21,BS연결,MATCH(S$1,BS연결H,0),0)/100,"") | T21: =IFERROR(VLOOKUP($D21,BS연결,MATCH(T$1,BS연결H,0),0)/100,"") | U21: =IFERROR(VLOOKUP($D21,BS연결,MATCH(U$1,BS연결H,0),0)/100,"") | V21: =IFERROR(VLOOKUP($D21,BS연결,MATCH(V$1,BS연결H,0),0)/100,"") | W21: =IFERROR(VLOOKUP($D21,BS연결,MATCH(W$1,BS연결H,0),0)/100,"") | X21: =IFERROR(VLOOKUP($D21,BS연결,MATCH(X$1,BS연결H,0),0)/100,"") | ... AB21: =IFERROR(VLOOKUP($D21,BS연결,MATCH(AB$1,BS연결H,0),0)/100,"") | AE21: =SUM(AA21:AD21) | AJ21: =SUM(AF21:AI21) | AO21: =SUM(AK21:AN21)
A22: 자산총계 | B22: 재무상태 | C22: 억원 | D22: 자산총계 | E22: =IFERROR(VLOOKUP($D22,BS연결,MATCH(E$1,BS연결H,0),0)/100,"") | F22: =IFERROR(VLOOKUP($D22,BS연결,MATCH(F$1,BS연결H,0),0)/100,"") | G22: =IFERROR(VLOOKUP($D22,BS연결,MATCH(G$1,BS연결H,0),0)/100,"") | H22: =IFERROR(VLOOKUP($D22,BS연결,MATCH(H$1,BS연결H,0),0)/100,"") | I22: =IFERROR(VLOOKUP($D22,BS연결,MATCH(I$1,BS연결H,0),0)/100,"") | J22: =IFERROR(VLOOKUP($D22,BS연결,MATCH(J$1,BS연결H,0),0)/100,"") | K22: =IFERROR(VLOOKUP($D22,BS연결,MATCH(K$1,BS연결H,0),0)/100,"") | L22: =IFERROR(VLOOKUP($D22,BS연결,MATCH(L$1,BS연결H,0),0)/100,"") | ... AB22: =IFERROR(VLOOKUP($D22,BS연결,MATCH(AB$1,BS연결H,0),0)/100,"") | AC22: =IFERROR(AC23+AC24,"") | AD22: =IFERROR(AD23+AD24,"") | AE22: =AD22 | AF22: =IFERROR(AF23+AF24,"") | AG22: =IFERROR(AG23+AG24,"") | AH22: =IFERROR(AH23+AH24,"") | AI22: =IFERROR(AI23+AI24,"") | AJ22: =AI22 | AK22: =IFERROR(AK23+AK24,"") | AL22: =IFERROR(AL23+AL24,"") | AM22: =IFERROR(AM23+AM24,"") | AN22: =IFERROR(AN23+AN24,"") | AO22: =AN22
A23: 부채총계 | B23: 재무상태 | C23: 억원 | D23: 부채총계 | E23: =IFERROR(VLOOKUP($D23,BS연결,MATCH(E$1,BS연결H,0),0)/100,"") | F23: =IFERROR(VLOOKUP($D23,BS연결,MATCH(F$1,BS연결H,0),0)/100,"") | G23: =IFERROR(VLOOKUP($D23,BS연결,MATCH(G$1,BS연결H,0),0)/100,"") | H23: =IFERROR(VLOOKUP($D23,BS연결,MATCH(H$1,BS연결H,0),0)/100,"") | I23: =IFERROR(VLOOKUP($D23,BS연결,MATCH(I$1,BS연결H,0),0)/100,"") | J23: =IFERROR(VLOOKUP($D23,BS연결,MATCH(J$1,BS연결H,0),0)/100,"") | K23: =IFERROR(VLOOKUP($D23,BS연결,MATCH(K$1,BS연결H,0),0)/100,"") | L23: =IFERROR(VLOOKUP($D23,BS연결,MATCH(L$1,BS연결H,0),0)/100,"") | ... AB23: =IFERROR(VLOOKUP($D23,BS연결,MATCH(AB$1,BS연결H,0),0)/100,"") | AC23: =IFERROR(AB23*(1+변수!AC31),"") | AD23: =IFERROR(AC23*(1+변수!AD31),"") | AE23: =AD23 | AF23: =IFERROR(AD23*(1+변수!AF31),"") | AG23: =IFERROR(AF23*(1+변수!AG31),"") | AH23: =IFERROR(AG23*(1+변수!AH31),"") | AI23: =IFERROR(AH23*(1+변수!AI31),"") | AJ23: =AI23 | AK23: =IFERROR(AI23*(1+변수!AK31),"") | AL23: =IFERROR(AK23*(1+변수!AL31),"") | AM23: =IFERROR(AL23*(1+변수!AM31),"") | AN23: =IFERROR(AM23*(1+변수!AN31),"") | AO23: =AN23
A24: 자본총계 | B24: 재무상태 | C24: 억원 | D24: 자본총계 | E24: =IFERROR(VLOOKUP($D24,BS연결,MATCH(E$1,BS연결H,0),0)/100,"") | F24: =IFERROR(VLOOKUP($D24,BS연결,MATCH(F$1,BS연결H,0),0)/100,"") | G24: =IFERROR(VLOOKUP($D24,BS연결,MATCH(G$1,BS연결H,0),0)/100,"") | H24: =IFERROR(VLOOKUP($D24,BS연결,MATCH(H$1,BS연결H,0),0)/100,"") | I24: =IFERROR(VLOOKUP($D24,BS연결,MATCH(I$1,BS연결H,0),0)/100,"") | J24: =IFERROR(VLOOKUP($D24,BS연결,MATCH(J$1,BS연결H,0),0)/100,"") | K24: =IFERROR(VLOOKUP($D24,BS연결,MATCH(K$1,BS연결H,0),0)/100,"") | L24: =IFERROR(VLOOKUP($D24,BS연결,MATCH(L$1,BS연결H,0),0)/100,"") | ... AB24: =IFERROR(VLOOKUP($D24,BS연결,MATCH(AB$1,BS연결H,0),0)/100,"") | AC24: =IFERROR(AB24+AC19-변수!AC32,"") | AD24: =IFERROR(AC24+AD19-변수!AD32,"") | AE24: =AD24 | AF24: =IFERROR(AD24+AF19-변수!AF32,"") | AG24: =IFERROR(AF24+AG19-변수!AG32,"") | AH24: =IFERROR(AG24+AH19-변수!AH32,"") | AI24: =IFERROR(AH24+AI19-변수!AI32,"") | AJ24: =AI24 | AK24: =IFERROR(AI24+AK19-변수!AK32,"") | AL24: =IFERROR(AK24+AL19-변수!AL32,"") | AM24: =IFERROR(AL24+AM19-변수!AM32,"") | AN24: =IFERROR(AM24+AN19-변수!AN32,"") | AO24: =AN24
A25: 지배주주지분 | B25: 재무상태 | C25: 억원 | D25: 지배주주지분 | E25: =IFERROR(VLOOKUP($D25,BS연결,MATCH(E$1,BS연결H,0),0)/100,"") | F25: =IFERROR(VLOOKUP($D25,BS연결,MATCH(F$1,BS연결H,0),0)/100,"") | G25: =IFERROR(VLOOKUP($D25,BS연결,MATCH(G$1,BS연결H,0),0)/100,"") | H25: =IFERROR(VLOOKUP($D25,BS연결,MATCH(H$1,BS연결H,0),0)/100,"") | I25: =IFERROR(VLOOKUP($D25,BS연결,MATCH(I$1,BS연결H,0),0)/100,"") | J25: =IFERROR(VLOOKUP($D25,BS연결,MATCH(J$1,BS연결H,0),0)/100,"") | K25: =IFERROR(VLOOKUP($D25,BS연결,MATCH(K$1,BS연결H,0),0)/100,"") | L25: =IFERROR(VLOOKUP($D25,BS연결,MATCH(L$1,BS연결H,0),0)/100,"") | ... AB25: =IFERROR(VLOOKUP($D25,BS연결,MATCH(AB$1,BS연결H,0),0)/100,"") | AC25: =IFERROR(AB25+AC20-변수!AC33,"") | AD25: =IFERROR(AC25+AD20-변수!AD33,"") | AE25: =AD25 | AF25: =IFERROR(AD25+AF20-변수!AF33,"") | AG25: =IFERROR(AF25+AG20-변수!AG33,"") | AH25: =IFERROR(AG25+AH20-변수!AH33,"") | AI25: =IFERROR(AH25+AI20-변수!AI33,"") | AJ25: =AI25 | AK25: =IFERROR(AI25+AK20-변수!AK33,"") | AL25: =IFERROR(AK25+AL20-변수!AL33,"") | AM25: =IFERROR(AL25+AM20-변수!AM33,"") | AN25: =IFERROR(AM25+AN20-변수!AN33,"") | AO25: =AN25
A26: 총차입금 | B26: 재무상태 | C26: 억원 | D26: 총차입금 | E26: =IFERROR(VLOOKUP($D26,BS연결,MATCH(E$1,BS연결H,0),0)/100,"") | F26: =IFERROR(VLOOKUP($D26,BS연결,MATCH(F$1,BS연결H,0),0)/100,"") | G26: =IFERROR(VLOOKUP($D26,BS연결,MATCH(G$1,BS연결H,0),0)/100,"") | H26: =IFERROR(VLOOKUP($D26,BS연결,MATCH(H$1,BS연결H,0),0)/100,"") | I26: =IFERROR(VLOOKUP($D26,BS연결,MATCH(I$1,BS연결H,0),0)/100,"") | J26: =IFERROR(VLOOKUP($D26,BS연결,MATCH(J$1,BS연결H,0),0)/100,"") | K26: =IFERROR(VLOOKUP($D26,BS연결,MATCH(K$1,BS연결H,0),0)/100,"") | L26: =IFERROR(VLOOKUP($D26,BS연결,MATCH(L$1,BS연결H,0),0)/100,"") | ... AB26: =IFERROR(VLOOKUP($D26,BS연결,MATCH(AB$1,BS연결H,0),0)/100,"") | AC26: =IFERROR(AB26*(1+변수!AC34),"") | AD26: =IFERROR(AC26*(1+변수!AD34),"") | AE26: =AD26 | AF26: =IFERROR(AD26*(1+변수!AF34),"") | AG26: =IFERROR(AF26*(1+변수!AG34),"") | AH26: =IFERROR(AG26*(1+변수!AH34),"") | AI26: =IFERROR(AH26*(1+변수!AI34),"") | AJ26: =AI26 | AK26: =IFERROR(AI26*(1+변수!AK34),"") | AL26: =IFERROR(AK26*(1+변수!AL34),"") | AM26: =IFERROR(AL26*(1+변수!AM34),"") | AN26: =IFERROR(AM26*(1+변수!AN34),"") | AO26: =AN26
A27: 순차입금 | B27: 재무상태 | C27: 억원 | D27: 순차입금 | E27: =IFERROR(VLOOKUP($D27,BS연결,MATCH(E$1,BS연결H,0),0)/100,"") | F27: =IFERROR(VLOOKUP($D27,BS연결,MATCH(F$1,BS연결H,0),0)/100,"") | G27: =IFERROR(VLOOKUP($D27,BS연결,MATCH(G$1,BS연결H,0),0)/100,"") | H27: =IFERROR(VLOOKUP($D27,BS연결,MATCH(H$1,BS연결H,0),0)/100,"") | I27: =IFERROR(VLOOKUP($D27,BS연결,MATCH(I$1,BS연결H,0),0)/100,"") | J27: =IFERROR(VLOOKUP($D27,BS연결,MATCH(J$1,BS연결H,0),0)/100,"") | K27: =IFERROR(VLOOKUP($D27,BS연결,MATCH(K$1,BS연결H,0),0)/100,"") | L27: =IFERROR(VLOOKUP($D27,BS연결,MATCH(L$1,BS연결H,0),0)/100,"") | ... AB27: =IFERROR(VLOOKUP($D27,BS연결,MATCH(AB$1,BS연결H,0),0)/100,"") | AC27: =IFERROR(AB27*(1+변수!AC35),"") | AD27: =IFERROR(AC27*(1+변수!AD35),"") | AE27: =AD27 | AF27: =IFERROR(AD27*(1+변수!AF35),"") | AG27: =IFERROR(AF27*(1+변수!AG35),"") | AH27: =IFERROR(AG27*(1+변수!AH35),"") | AI27: =IFERROR(AH27*(1+변수!AI35),"") | AJ27: =AI27 | AK27: =IFERROR(AI27*(1+변수!AK35),"") | AL27: =IFERROR(AK27*(1+변수!AL35),"") | AM27: =IFERROR(AL27*(1+변수!AM35),"") | AN27: =IFERROR(AM27*(1+변수!AN35),"") | AO27: =AN27
A28: 이자발생자산 | B28: 재무상태 | C28: 억원 | D28: 이자발생자산 | E28: =IFERROR(VLOOKUP($D28,BS연결,MATCH(E$1,BS연결H,0),0)/100,"") | F28: =IFERROR(VLOOKUP($D28,BS연결,MATCH(F$1,BS연결H,0),0)/100,"") | G28: =IFERROR(VLOOKUP($D28,BS연결,MATCH(G$1,BS연결H,0),0)/100,"") | H28: =IFERROR(VLOOKUP($D28,BS연결,MATCH(H$1,BS연결H,0),0)/100,"") | I28: =IFERROR(VLOOKUP($D28,BS연결,MATCH(I$1,BS연결H,0),0)/100,"") | J28: =IFERROR(VLOOKUP($D28,BS연결,MATCH(J$1,BS연결H,0),0)/100,"") | K28: =IFERROR(VLOOKUP($D28,BS연결,MATCH(K$1,BS연결H,0),0)/100,"") | L28: =IFERROR(VLOOKUP($D28,BS연결,MATCH(L$1,BS연결H,0),0)/100,"") | ... AB28: =IFERROR(VLOOKUP($D28,BS연결,MATCH(AB$1,BS연결H,0),0)/100,"") | AC28: =IFERROR(AB28*(1+변수!AC36),"") | AD28: =IFERROR(AC28*(1+변수!AD36),"") | AE28: =AD28 | AF28: =IFERROR(AD28*(1+변수!AF36),"") | AG28: =IFERROR(AF28*(1+변수!AG36),"") | AH28: =IFERROR(AG28*(1+변수!AH36),"") | AI28: =IFERROR(AH28*(1+변수!AI36),"") | AJ28: =AI28 | AK28: =IFERROR(AI28*(1+변수!AK36),"") | AL28: =IFERROR(AK28*(1+변수!AL36),"") | AM28: =IFERROR(AL28*(1+변수!AM36),"") | AN28: =IFERROR(AM28*(1+변수!AN36),"") | AO28: =AN28
A29: 현금및현금성자산 | B29: 재무상태 | C29: 억원 | D29: 현금및현금성자산 | E29: =IFERROR(VLOOKUP($D29,BS연결,MATCH(E$1,BS연결H,0),0)/100,"") | F29: =IFERROR(VLOOKUP($D29,BS연결,MATCH(F$1,BS연결H,0),0)/100,"") | G29: =IFERROR(VLOOKUP($D29,BS연결,MATCH(G$1,BS연결H,0),0)/100,"") | H29: =IFERROR(VLOOKUP($D29,BS연결,MATCH(H$1,BS연결H,0),0)/100,"") | I29: =IFERROR(VLOOKUP($D29,BS연결,MATCH(I$1,BS연결H,0),0)/100,"") | J29: =IFERROR(VLOOKUP($D29,BS연결,MATCH(J$1,BS연결H,0),0)/100,"") | K29: =IFERROR(VLOOKUP($D29,BS연결,MATCH(K$1,BS연결H,0),0)/100,"") | L29: =IFERROR(VLOOKUP($D29,BS연결,MATCH(L$1,BS연결H,0),0)/100,"") | ... AB29: =IFERROR(VLOOKUP($D29,BS연결,MATCH(AB$1,BS연결H,0),0)/100,"") | AE29: =AD29 | AJ29: =AI29 | AO29: =AN29
A30: CAPEX | B30: 현금흐름 | C30: 억원 | D30: CAPEX | E30: =IFERROR(VLOOKUP($D30,BS연결,MATCH(E$1,BS연결H,0),0)/100,"") | G30: =IFERROR(VLOOKUP($D30,BS연결,MATCH(G$1,BS연결H,0),0)/100,"") | H30: =IFERROR(VLOOKUP($D30,BS연결,MATCH(H$1,BS연결H,0),0)/100,"") | I30: =IFERROR(VLOOKUP($D30,BS연결,MATCH(I$1,BS연결H,0),0)/100,"") | J30: =IFERROR(VLOOKUP($D30,BS연결,MATCH(J$1,BS연결H,0),0)/100,"") | K30: =IFERROR(VLOOKUP($D30,BS연결,MATCH(K$1,BS연결H,0),0)/100,"") | L30: =IFERROR(VLOOKUP($D30,BS연결,MATCH(L$1,BS연결H,0),0)/100,"") | M30: =IFERROR(VLOOKUP($D30,BS연결,MATCH(M$1,BS연결H,0),0)/100,"") | N30: =IFERROR(VLOOKUP($D30,BS연결,MATCH(N$1,BS연결H,0),0)/100,"") | ... AA30: =IFERROR(VLOOKUP($D30,BS연결,MATCH(AA$1,BS연결H,0),0)/100,"") | AC30: =IFERROR(X30*(1+변수!AC38),"") | AD30: =IFERROR(Y30*(1+변수!AD38),"") | AE30: =SUM(AA30:AD30) | AF30: =IFERROR(AA30*(1+변수!AF38),"") | AG30: =IFERROR(AF30*(1+변수!AG38),"") | AH30: =IFERROR(AC30*(1+변수!AH38),"") | AI30: =IFERROR(AD30*(1+변수!AI38),"") | AJ30: =SUM(AF30:AI30) | AK30: =IFERROR(AF30*(1+변수!AK38),"") | AL30: =IFERROR(AG30*(1+변수!AL38),"") | AM30: =IFERROR(AH30*(1+변수!AM38),"") | AN30: =IFERROR(AI30*(1+변수!AN38),"") | AO30: =SUM(AK30:AN30)
A31: 영업활동현금흐름 | B31: 현금흐름 | C31: 억원 | D31: 영업활동으로인한현금흐름 | E31: =IFERROR(VLOOKUP($D31,BS연결,MATCH(E$1,BS연결H,0),0)/100,"") | G31: =IFERROR(VLOOKUP($D31,BS연결,MATCH(G$1,BS연결H,0),0)/100,"") | H31: =IFERROR(VLOOKUP($D31,BS연결,MATCH(H$1,BS연결H,0),0)/100,"") | I31: =IFERROR(VLOOKUP($D31,BS연결,MATCH(I$1,BS연결H,0),0)/100,"") | J31: =IFERROR(VLOOKUP($D31,BS연결,MATCH(J$1,BS연결H,0),0)/100,"") | K31: =IFERROR(VLOOKUP($D31,BS연결,MATCH(K$1,BS연결H,0),0)/100,"") | L31: =IFERROR(VLOOKUP($D31,BS연결,MATCH(L$1,BS연결H,0),0)/100,"") | M31: =IFERROR(VLOOKUP($D31,BS연결,MATCH(M$1,BS연결H,0),0)/100,"") | N31: =IFERROR(VLOOKUP($D31,BS연결,MATCH(N$1,BS연결H,0),0)/100,"") | ... AB31: =IFERROR(VLOOKUP($D31,BS연결,MATCH(AB$1,BS연결H,0),0)/100,"") | AE31: =SUM(AA31:AD31) | AJ31: =SUM(AF31:AI31) | AO31: =SUM(AK31:AN31)
A32: 주식수 | B32: 주당 | C32: 백만주 | D32: 유통주식수 | E32: 186.993 | F32: =E32 | G32: 186.993 | H32: 186.993 | I32: 186.993 | J32: 186.993 | K32: =J32 | L32: 186.993 | M32: 186.993 | N32: 186.993 | O32: 186.993 | P32: =O32 | Q32: 186.993 | R32: 186.993 | S32: 186.993 | T32: 186.993 | U32: =T32 | V32: 186.993 | W32: 186.993 | X32: 186.993 | Y32: 186.993 | Z32: =Y32 | AA32: 186.993 | AB32: 186.993 | AC32: =IFERROR(AB32*(1+변수!AC40),"") | AD32: =IFERROR(AC32*(1+변수!AD40),"") | AE32: =AD32 | AF32: =IFERROR(AD32*(1+변수!AF40),"") | AG32: =IFERROR(AF32*(1+변수!AG40),"") | AH32: =IFERROR(AG32*(1+변수!AH40),"") | AI32: =IFERROR(AH32*(1+변수!AI40),"") | AJ32: =AI32 | AK32: =IFERROR(AI32*(1+변수!AK40),"") | AL32: =IFERROR(AK32*(1+변수!AL40),"") | AM32: =IFERROR(AL32*(1+변수!AM40),"") | AN32: =IFERROR(AM32*(1+변수!AN40),"") | AO32: =AN32
A33: EPS | B33: 주당 | C33: 원 | D33: EPS | E33: =IFERROR(E20*100/E32,"") | G33: =IFERROR(G20*100/G32,"") | H33: =IFERROR(H20*100/H32,"") | I33: =IFERROR(I20*100/I32,"") | J33: =IFERROR(J20*100/J32,"") | K33: =SUM(G33:J33) | L33: =IFERROR(L20*100/L32,"") | M33: =IFERROR(M20*100/M32,"") | N33: =IFERROR(N20*100/N32,"") | O33: =IFERROR(O20*100/O32,"") | P33: =SUM(L33:O33) | Q33: =IFERROR(Q20*100/Q32,"") | R33: =IFERROR(R20*100/R32,"") | S33: =IFERROR(S20*100/S32,"") | T33: =IFERROR(T20*100/T32,"") | U33: =SUM(Q33:T33) | V33: =IFERROR(V20*100/V32,"") | W33: =IFERROR(W20*100/W32,"") | X33: =IFERROR(X20*100/X32,"") | Y33: =IFERROR(Y20*100/Y32,"") | Z33: =SUM(V33:Y33) | AA33: =IFERROR(AA20*100/AA32,"") | AB33: =IFERROR(AB20*100/AB32,"") | AC33: =IFERROR(AC20*100/AC32,"") | AD33: =IFERROR(AD20*100/AD32,"") | AE33: =SUM(AA33:AD33) | AF33: =IFERROR(AF20*100/AF32,"") | AG33: =IFERROR(AG20*100/AG32,"") | AH33: =IFERROR(AH20*100/AH32,"") | AI33: =IFERROR(AI20*100/AI32,"") | AJ33: =SUM(AF33:AI33) | AK33: =IFERROR(AK20*100/AK32,"") | AL33: =IFERROR(AL20*100/AL32,"") | AM33: =IFERROR(AM20*100/AM32,"") | AN33: =IFERROR(AN20*100/AN32,"") | AO33: =SUM(AK33:AN33)
A34: BPS | B34: 주당 | C34: 원 | D34: BPS | E34: =IFERROR(E25*100/E32,"") | F34: =E34 | G34: =IFERROR(G25*100/G32,"") | H34: =IFERROR(H25*100/H32,"") | I34: =IFERROR(I25*100/I32,"") | J34: =IFERROR(J25*100/J32,"") | K34: =J34 | L34: =IFERROR(L25*100/L32,"") | M34: =IFERROR(M25*100/M32,"") | N34: =IFERROR(N25*100/N32,"") | O34: =IFERROR(O25*100/O32,"") | P34: =O34 | Q34: =IFERROR(Q25*100/Q32,"") | R34: =IFERROR(R25*100/R32,"") | S34: =IFERROR(S25*100/S32,"") | T34: =IFERROR(T25*100/T32,"") | U34: =T34 | V34: =IFERROR(V25*100/V32,"") | W34: =IFERROR(W25*100/W32,"") | X34: =IFERROR(X25*100/X32,"") | Y34: =IFERROR(Y25*100/Y32,"") | Z34: =Y34 | AA34: =IFERROR(AA25*100/AA32,"") | AB34: =IFERROR(AB25*100/AB32,"") | AC34: =IFERROR(AC25*100/AC32,"") | AD34: =IFERROR(AD25*100/AD32,"") | AE34: =AD34 | AF34: =IFERROR(AF25*100/AF32,"") | AG34: =IFERROR(AG25*100/AG32,"") | AH34: =IFERROR(AH25*100/AH32,"") | AI34: =IFERROR(AI25*100/AI32,"") | AJ34: =AI34 | AK34: =IFERROR(AK25*100/AK32,"") | AL34: =IFERROR(AL25*100/AL32,"") | AM34: =IFERROR(AM25*100/AM32,"") | AN34: =IFERROR(AN25*100/AN32,"") | AO34: =AN34
A35: DPS | B35: 주당 | C35: 원 | D35: DPS(보통주) | E35: 160 | F35: 160 | J35: 250 | K35: =SUM(G35:J35) | O35: 280 | P35: =SUM(L35:O35) | T35: 350 | U35: =SUM(Q35:T35) | Y35: 500 | Z35: =SUM(V35:Y35) | AD35: =변수!AD41 | AE35: =SUM(AA35:AD35) | AI35: =변수!AI41 | AJ35: =SUM(AF35:AI35) | AN35: =변수!AN41 | AO35: =SUM(AK35:AN35)
A36: PER | B36: 주당 | C36: 배 | D36: PER | F36: =E36 | K36: =J36 | L36: =IFERROR(변수!L18/(H33+I33+J33+L33),"") | M36: =IFERROR(변수!M18/(I33+J33+L33+M33),"") | N36: =IFERROR(변수!N18/(J33+L33+M33+N33),"") | O36: =IFERROR(변수!O18/(L33+M33+N33+O33),"") | P36: =O36 | Q36: =IFERROR(변수!Q18/(M33+N33+O33+Q33),"") | R36: =IFERROR(변수!R18/(N33+O33+Q33+R33),"") | S36: =IFERROR(변수!S18/(O33+Q33+R33+S33),"") | T36: =IFERROR(변수!T18/(Q33+R33+S33+T33),"") | U36: =T36 | V36: =IFERROR(변수!V18/(R33+S33+T33+V33),"") | W36: =IFERROR(변수!W18/(S33+T33+V33+W33),"") | X36: =IFERROR(변수!X18/(T33+V33+W33+X33),"") | Y36: =IFERROR(변수!Y18/(V33+W33+X33+Y33),"") | Z36: =Y36 | AA36: =IFERROR(변수!AA18/(W33+X33+Y33+AA33),"") | AB36: =IFERROR(변수!AB18/(X33+Y33+AA33+AB33),"") | AC36: =IFERROR(변수!$D$44/(Y33+AA33+AB33+AC33),"") | AD36: =IFERROR(변수!$D$44/(AA33+AB33+AC33+AD33),"") | AE36: =AD36 | AF36: =IFERROR(변수!$D$44/(AB33+AC33+AD33+AF33),"") | AG36: =IFERROR(변수!$D$44/(AC33+AD33+AF33+AG33),"") | AH36: =IFERROR(변수!$D$44/(AD33+AF33+AG33+AH33),"") | AI36: =IFERROR(변수!$D$44/(AF33+AG33+AH33+AI33),"") | AJ36: =AI36 | AK36: =IFERROR(변수!$D$44/(AG33+AH33+AI33+AK33),"") | AL36: =IFERROR(변수!$D$44/(AH33+AI33+AK33+AL33),"") | AM36: =IFERROR(변수!$D$44/(AI33+AK33+AL33+AM33),"") | AN36: =IFERROR(변수!$D$44/(AK33+AL33+AM33+AN33),"") | AO36: =AN36
A37: PBR | B37: 주당 | C37: 배 | D37: PBR | E37: =IFERROR(변수!E18/E34,"") | F37: =E37 | G37: =IFERROR(변수!G18/G34,"") | H37: =IFERROR(변수!H18/H34,"") | I37: =IFERROR(변수!I18/I34,"") | J37: =IFERROR(변수!J18/J34,"") | K37: =J37 | L37: =IFERROR(변수!L18/L34,"") | M37: =IFERROR(변수!M18/M34,"") | N37: =IFERROR(변수!N18/N34,"") | O37: =IFERROR(변수!O18/O34,"") | P37: =O37 | Q37: =IFERROR(변수!Q18/Q34,"") | R37: =IFERROR(변수!R18/R34,"") | S37: =IFERROR(변수!S18/S34,"") | T37: =IFERROR(변수!T18/T34,"") | U37: =T37 | V37: =IFERROR(변수!V18/V34,"") | W37: =IFERROR(변수!W18/W34,"") | X37: =IFERROR(변수!X18/X34,"") | Y37: =IFERROR(변수!Y18/Y34,"") | Z37: =Y37 | AA37: =IFERROR(변수!AA18/AA34,"") | AB37: =IFERROR(변수!AB18/AB34,"") | AC37: =IFERROR(변수!$D$44/AC34,"") | AD37: =IFERROR(변수!$D$44/AD34,"") | AE37: =AD37 | AF37: =IFERROR(변수!$D$44/AF34,"") | AG37: =IFERROR(변수!$D$44/AG34,"") | AH37: =IFERROR(변수!$D$44/AH34,"") | AI37: =IFERROR(변수!$D$44/AI34,"") | AJ37: =AI37 | AK37: =IFERROR(변수!$D$44/AK34,"") | AL37: =IFERROR(변수!$D$44/AL34,"") | AM37: =IFERROR(변수!$D$44/AM34,"") | AN37: =IFERROR(변수!$D$44/AN34,"") | AO37: =AN37
A38: 매출전사 | B38: 사업부 | C38: 억원 | D38: 매출 전사(부문 미분리) | E38: 6795.25 | G38: 4295.64 | H38: 5104.94 | I38: 4594 | J38: 7885.44 | K38: =SUM(G38:J38) | L38: 4395.16 | M38: 6106.77 | N38: 6208.23 | O38: 7820.63 | P38: =SUM(L38:O38) | Q38: 5443.64 | R38: 6873.19 | S38: 6391.72 | T38: 9328.32 | U38: =SUM(Q38:T38) | V38: 6901.01 | W38: 7681.91 | X38: 8077.37 | Y38: 13981.23 | Z38: =SUM(V38:Y38) | AA38: 8070.99 | AB38: 11175.52 | AC38: =IFERROR(AC5,"") | AD38: =IFERROR(AD5,"") | AE38: =SUM(AA38:AD38) | AF38: =IFERROR(AF5,"") | AG38: =IFERROR(AG5,"") | AH38: =IFERROR(AH5,"") | AI38: =IFERROR(AI5,"") | AJ38: =SUM(AF38:AI38) | AK38: =IFERROR(AK5,"") | AL38: =IFERROR(AL5,"") | AM38: =IFERROR(AM5,"") | AN38: =IFERROR(AN5,"") | AO38: =SUM(AK38:AN38)
A39: OP전사 | B39: 사업부 | C39: 억원 | D39: OP 전사(부문 미분리) | E39: 73.48 | G39: 151.62 | H39: 164.27 | I39: 5.41 | J39: -81.08 | K39: =SUM(G39:J39) | L39: 83.86 | M39: 259.32 | N39: 373.33 | O39: 212.2 | P39: =SUM(L39:O39) | Q39: 392.64 | R39: 798.37 | S39: 569.99 | T39: 432.45 | U39: =SUM(Q39:T39) | V39: 581.64 | W39: 334.51 | X39: 225.21 | Y39: 57.62 | Z39: =SUM(V39:Y39) | AA39: 342.84 | AB39: 1036.52 | AC39: =IFERROR(AC9,"") | AD39: =IFERROR(AD9,"") | AE39: =SUM(AA39:AD39) | AF39: =IFERROR(AF9,"") | AG39: =IFERROR(AG9,"") | AH39: =IFERROR(AH9,"") | AI39: =IFERROR(AI9,"") | AJ39: =SUM(AF39:AI39) | AK39: =IFERROR(AK9,"") | AL39: =IFERROR(AL9,"") | AM39: =IFERROR(AM9,"") | AN39: =IFERROR(AN9,"") | AO39: =SUM(AK39:AN39)
B40: 비율(참고)
A41: NPM | C41: % | D41: 지배주주순이익 / 매출액 | E41: =IFERROR(E20/E5,"") | F41: =IFERROR(F20/F5,"") | G41: =IFERROR(G20/G5,"") | H41: =IFERROR(H20/H5,"") | I41: =IFERROR(I20/I5,"") | J41: =IFERROR(J20/J5,"") | K41: =IFERROR(K20/K5,"") | L41: =IFERROR(L20/L5,"") | ... AO41: =IFERROR(AO20/AO5,"")
A42: 매출원가율 | C42: % | D42: 매출원가 / 매출액 | E42: =IFERROR(E6/E5,"") | F42: =IFERROR(F6/F5,"") | G42: =IFERROR(G6/G5,"") | H42: =IFERROR(H6/H5,"") | I42: =IFERROR(I6/I5,"") | J42: =IFERROR(J6/J5,"") | K42: =IFERROR(K6/K5,"") | L42: =IFERROR(L6/L5,"") | ... AO42: =IFERROR(AO6/AO5,"")
A43: 판관비율 | C43: % | D43: 판관비 / 매출액 | E43: =IFERROR(E8/E5,"") | F43: =IFERROR(F8/F5,"") | G43: =IFERROR(G8/G5,"") | H43: =IFERROR(H8/H5,"") | I43: =IFERROR(I8/I5,"") | J43: =IFERROR(J8/J5,"") | K43: =IFERROR(K8/K5,"") | L43: =IFERROR(L8/L5,"") | ... AO43: =IFERROR(AO8/AO5,"")

Sheet 분기
C1: 이름: 분기H — subQ 를 이름으로 VLOOKUP(억원) | E1: 4Q21 | F1: 1Q22 | G1: 2Q22 | H1: 3Q22 | I1: 4Q22 | J1: 1Q23 | K1: 2Q23 | L1: 3Q23 | M1: 4Q23 | N1: 1Q24 | O1: 2Q24 | P1: 3Q24 | Q1: 4Q24 | R1: 1Q25 | S1: 2Q25 | T1: 3Q25 | U1: 4Q25 | V1: 1Q26 | W1: 2Q26 | X1: 3Q26 | Y1: 4Q26 | Z1: 1Q27 | AA1: 2Q27 | AB1: 3Q27 | AC1: 4Q27 | AD1: 1Q28 | AE1: 2Q28 | AF1: 3Q28 | AG1: 4Q28
C2: 종가: | D2: =변수!D44
C3: 기준일: | D3: 20261008 | E3: 1 | F3: 2 | G3: 3 | H3: 4 | I3: 5 | J3: 6 | K3: 7 | L3: 8 | M3: 9 | N3: 10 | O3: 11 | P3: 12 | Q3: 13 | R3: 14 | S3: 15 | T3: 16 | U3: 17 | V3: 18 | W3: 19 | X3: 20 | Y3: 21 | Z3: 22 | AA3: 23 | AB3: 24 | AC3: 25 | AD3: 26 | AE3: 27 | AF3: 28 | AG3: 29
E4: 2021.12 | F4: 2022.03 | G4: 2022.06 | H4: 2022.09 | I4: 2022.12 | J4: 2023.03 | K4: 2023.06 | L4: 2023.09 | M4: 2023.12 | N4: 2024.03 | O4: 2024.06 | P4: 2024.09 | Q4: 2024.12 | R4: 2025.03 | S4: 2025.06 | T4: 2025.09 | U4: 2025.12 | V4: 2026.03 | W4: 2026.06 | X4: 2026.09 | Y4: 2026.12 | Z4: 2027.03 | AA4: 2027.06 | AB4: 2027.09 | AC4: 2027.12 | AD4: 2028.03 | AE4: 2028.06 | AF4: 2028.09 | AG4: 2028.12
A5: 매출액 | D5: 매출액 | E5: =IFERROR(VLOOKUP($A5,subQ,MATCH(E$1,SUBQH,0),0),"") | F5: =IFERROR(VLOOKUP($A5,subQ,MATCH(F$1,SUBQH,0),0),"") | G5: =IFERROR(VLOOKUP($A5,subQ,MATCH(G$1,SUBQH,0),0),"") | H5: =IFERROR(VLOOKUP($A5,subQ,MATCH(H$1,SUBQH,0),0),"") | I5: =IFERROR(VLOOKUP($A5,subQ,MATCH(I$1,SUBQH,0),0),"") | J5: =IFERROR(VLOOKUP($A5,subQ,MATCH(J$1,SUBQH,0),0),"") | K5: =IFERROR(VLOOKUP($A5,subQ,MATCH(K$1,SUBQH,0),0),"") | L5: =IFERROR(VLOOKUP($A5,subQ,MATCH(L$1,SUBQH,0),0),"") | ... AG5: =IFERROR(VLOOKUP($A5,subQ,MATCH(AG$1,SUBQH,0),0),"")
A6: 매출원가 | D6: 매출원가 | E6: =IFERROR(VLOOKUP($A6,subQ,MATCH(E$1,SUBQH,0),0),"") | F6: =IFERROR(VLOOKUP($A6,subQ,MATCH(F$1,SUBQH,0),0),"") | G6: =IFERROR(VLOOKUP($A6,subQ,MATCH(G$1,SUBQH,0),0),"") | H6: =IFERROR(VLOOKUP($A6,subQ,MATCH(H$1,SUBQH,0),0),"") | I6: =IFERROR(VLOOKUP($A6,subQ,MATCH(I$1,SUBQH,0),0),"") | J6: =IFERROR(VLOOKUP($A6,subQ,MATCH(J$1,SUBQH,0),0),"") | K6: =IFERROR(VLOOKUP($A6,subQ,MATCH(K$1,SUBQH,0),0),"") | L6: =IFERROR(VLOOKUP($A6,subQ,MATCH(L$1,SUBQH,0),0),"") | ... AG6: =IFERROR(VLOOKUP($A6,subQ,MATCH(AG$1,SUBQH,0),0),"")
A7: 매출총이익 | D7: 매출총이익 | E7: =IFERROR(VLOOKUP($A7,subQ,MATCH(E$1,SUBQH,0),0),"") | F7: =IFERROR(VLOOKUP($A7,subQ,MATCH(F$1,SUBQH,0),0),"") | G7: =IFERROR(VLOOKUP($A7,subQ,MATCH(G$1,SUBQH,0),0),"") | H7: =IFERROR(VLOOKUP($A7,subQ,MATCH(H$1,SUBQH,0),0),"") | I7: =IFERROR(VLOOKUP($A7,subQ,MATCH(I$1,SUBQH,0),0),"") | J7: =IFERROR(VLOOKUP($A7,subQ,MATCH(J$1,SUBQH,0),0),"") | K7: =IFERROR(VLOOKUP($A7,subQ,MATCH(K$1,SUBQH,0),0),"") | L7: =IFERROR(VLOOKUP($A7,subQ,MATCH(L$1,SUBQH,0),0),"") | ... AG7: =IFERROR(VLOOKUP($A7,subQ,MATCH(AG$1,SUBQH,0),0),"")
A8: 판관비 | D8: 판매비와관리비 | E8: =IFERROR(VLOOKUP($A8,subQ,MATCH(E$1,SUBQH,0),0),"") | F8: =IFERROR(VLOOKUP($A8,subQ,MATCH(F$1,SUBQH,0),0),"") | G8: =IFERROR(VLOOKUP($A8,subQ,MATCH(G$1,SUBQH,0),0),"") | H8: =IFERROR(VLOOKUP($A8,subQ,MATCH(H$1,SUBQH,0),0),"") | I8: =IFERROR(VLOOKUP($A8,subQ,MATCH(I$1,SUBQH,0),0),"") | J8: =IFERROR(VLOOKUP($A8,subQ,MATCH(J$1,SUBQH,0),0),"") | K8: =IFERROR(VLOOKUP($A8,subQ,MATCH(K$1,SUBQH,0),0),"") | L8: =IFERROR(VLOOKUP($A8,subQ,MATCH(L$1,SUBQH,0),0),"") | ... AG8: =IFERROR(VLOOKUP($A8,subQ,MATCH(AG$1,SUBQH,0),0),"")
A9: 영업이익 | D9: 영업이익 | E9: =IFERROR(VLOOKUP($A9,subQ,MATCH(E$1,SUBQH,0),0),"") | F9: =IFERROR(VLOOKUP($A9,subQ,MATCH(F$1,SUBQH,0),0),"") | G9: =IFERROR(VLOOKUP($A9,subQ,MATCH(G$1,SUBQH,0),0),"") | H9: =IFERROR(VLOOKUP($A9,subQ,MATCH(H$1,SUBQH,0),0),"") | I9: =IFERROR(VLOOKUP($A9,subQ,MATCH(I$1,SUBQH,0),0),"") | J9: =IFERROR(VLOOKUP($A9,subQ,MATCH(J$1,SUBQH,0),0),"") | K9: =IFERROR(VLOOKUP($A9,subQ,MATCH(K$1,SUBQH,0),0),"") | L9: =IFERROR(VLOOKUP($A9,subQ,MATCH(L$1,SUBQH,0),0),"") | ... AG9: =IFERROR(VLOOKUP($A9,subQ,MATCH(AG$1,SUBQH,0),0),"")
A10: OPM | D10: 영업이익률 | E10: =IFERROR(VLOOKUP($A10,subQ,MATCH(E$1,SUBQH,0),0),"") | F10: =IFERROR(VLOOKUP($A10,subQ,MATCH(F$1,SUBQH,0),0),"") | G10: =IFERROR(VLOOKUP($A10,subQ,MATCH(G$1,SUBQH,0),0),"") | H10: =IFERROR(VLOOKUP($A10,subQ,MATCH(H$1,SUBQH,0),0),"") | I10: =IFERROR(VLOOKUP($A10,subQ,MATCH(I$1,SUBQH,0),0),"") | J10: =IFERROR(VLOOKUP($A10,subQ,MATCH(J$1,SUBQH,0),0),"") | K10: =IFERROR(VLOOKUP($A10,subQ,MATCH(K$1,SUBQH,0),0),"") | L10: =IFERROR(VLOOKUP($A10,subQ,MATCH(L$1,SUBQH,0),0),"") | ... AG10: =IFERROR(VLOOKUP($A10,subQ,MATCH(AG$1,SUBQH,0),0),"")
A11: 금융손익 | D11: 금융손익(이자·환 포함) | E11: =IFERROR(VLOOKUP($A11,subQ,MATCH(E$1,SUBQH,0),0),"") | F11: =IFERROR(VLOOKUP($A11,subQ,MATCH(F$1,SUBQH,0),0),"") | G11: =IFERROR(VLOOKUP($A11,subQ,MATCH(G$1,SUBQH,0),0),"") | H11: =IFERROR(VLOOKUP($A11,subQ,MATCH(H$1,SUBQH,0),0),"") | I11: =IFERROR(VLOOKUP($A11,subQ,MATCH(I$1,SUBQH,0),0),"") | J11: =IFERROR(VLOOKUP($A11,subQ,MATCH(J$1,SUBQH,0),0),"") | K11: =IFERROR(VLOOKUP($A11,subQ,MATCH(K$1,SUBQH,0),0),"") | L11: =IFERROR(VLOOKUP($A11,subQ,MATCH(L$1,SUBQH,0),0),"") | ... AG11: =IFERROR(VLOOKUP($A11,subQ,MATCH(AG$1,SUBQH,0),0),"")
A12: 이자손익 | D12: 이자손익(이자수익 − 이자비용) | E12: =IFERROR(VLOOKUP($A12,subQ,MATCH(E$1,SUBQH,0),0),"") | F12: =IFERROR(VLOOKUP($A12,subQ,MATCH(F$1,SUBQH,0),0),"") | G12: =IFERROR(VLOOKUP($A12,subQ,MATCH(G$1,SUBQH,0),0),"") | H12: =IFERROR(VLOOKUP($A12,subQ,MATCH(H$1,SUBQH,0),0),"") | I12: =IFERROR(VLOOKUP($A12,subQ,MATCH(I$1,SUBQH,0),0),"") | J12: =IFERROR(VLOOKUP($A12,subQ,MATCH(J$1,SUBQH,0),0),"") | K12: =IFERROR(VLOOKUP($A12,subQ,MATCH(K$1,SUBQH,0),0),"") | L12: =IFERROR(VLOOKUP($A12,subQ,MATCH(L$1,SUBQH,0),0),"") | ... AG12: =IFERROR(VLOOKUP($A12,subQ,MATCH(AG$1,SUBQH,0),0),"")
A13: 외환손익 | D13: 외환손익(실적만; 추정 환효과는 환관련손익) | E13: =IFERROR(VLOOKUP($A13,subQ,MATCH(E$1,SUBQH,0),0),"") | F13: =IFERROR(VLOOKUP($A13,subQ,MATCH(F$1,SUBQH,0),0),"") | G13: =IFERROR(VLOOKUP($A13,subQ,MATCH(G$1,SUBQH,0),0),"") | H13: =IFERROR(VLOOKUP($A13,subQ,MATCH(H$1,SUBQH,0),0),"") | I13: =IFERROR(VLOOKUP($A13,subQ,MATCH(I$1,SUBQH,0),0),"") | J13: =IFERROR(VLOOKUP($A13,subQ,MATCH(J$1,SUBQH,0),0),"") | K13: =IFERROR(VLOOKUP($A13,subQ,MATCH(K$1,SUBQH,0),0),"") | L13: =IFERROR(VLOOKUP($A13,subQ,MATCH(L$1,SUBQH,0),0),"") | ... AG13: =IFERROR(VLOOKUP($A13,subQ,MATCH(AG$1,SUBQH,0),0),"")
A14: 기타금융손익 | D14: 기타금융손익(금융손익 잔차) | E14: =IFERROR(VLOOKUP($A14,subQ,MATCH(E$1,SUBQH,0),0),"") | F14: =IFERROR(VLOOKUP($A14,subQ,MATCH(F$1,SUBQH,0),0),"") | G14: =IFERROR(VLOOKUP($A14,subQ,MATCH(G$1,SUBQH,0),0),"") | H14: =IFERROR(VLOOKUP($A14,subQ,MATCH(H$1,SUBQH,0),0),"") | I14: =IFERROR(VLOOKUP($A14,subQ,MATCH(I$1,SUBQH,0),0),"") | J14: =IFERROR(VLOOKUP($A14,subQ,MATCH(J$1,SUBQH,0),0),"") | K14: =IFERROR(VLOOKUP($A14,subQ,MATCH(K$1,SUBQH,0),0),"") | L14: =IFERROR(VLOOKUP($A14,subQ,MATCH(L$1,SUBQH,0),0),"") | ... AG14: =IFERROR(VLOOKUP($A14,subQ,MATCH(AG$1,SUBQH,0),0),"")
A15: 기타영업외손익 | D15: 기타영업외손익 | E15: =IFERROR(VLOOKUP($A15,subQ,MATCH(E$1,SUBQH,0),0),"") | F15: =IFERROR(VLOOKUP($A15,subQ,MATCH(F$1,SUBQH,0),0),"") | G15: =IFERROR(VLOOKUP($A15,subQ,MATCH(G$1,SUBQH,0),0),"") | H15: =IFERROR(VLOOKUP($A15,subQ,MATCH(H$1,SUBQH,0),0),"") | I15: =IFERROR(VLOOKUP($A15,subQ,MATCH(I$1,SUBQH,0),0),"") | J15: =IFERROR(VLOOKUP($A15,subQ,MATCH(J$1,SUBQH,0),0),"") | K15: =IFERROR(VLOOKUP($A15,subQ,MATCH(K$1,SUBQH,0),0),"") | L15: =IFERROR(VLOOKUP($A15,subQ,MATCH(L$1,SUBQH,0),0),"") | ... AG15: =IFERROR(VLOOKUP($A15,subQ,MATCH(AG$1,SUBQH,0),0),"")
A16: 지분법손익 | D16: 지분법손익 | E16: =IFERROR(VLOOKUP($A16,subQ,MATCH(E$1,SUBQH,0),0),"") | F16: =IFERROR(VLOOKUP($A16,subQ,MATCH(F$1,SUBQH,0),0),"") | G16: =IFERROR(VLOOKUP($A16,subQ,MATCH(G$1,SUBQH,0),0),"") | H16: =IFERROR(VLOOKUP($A16,subQ,MATCH(H$1,SUBQH,0),0),"") | I16: =IFERROR(VLOOKUP($A16,subQ,MATCH(I$1,SUBQH,0),0),"") | J16: =IFERROR(VLOOKUP($A16,subQ,MATCH(J$1,SUBQH,0),0),"") | K16: =IFERROR(VLOOKUP($A16,subQ,MATCH(K$1,SUBQH,0),0),"") | L16: =IFERROR(VLOOKUP($A16,subQ,MATCH(L$1,SUBQH,0),0),"") | ... AG16: =IFERROR(VLOOKUP($A16,subQ,MATCH(AG$1,SUBQH,0),0),"")
... A40: NPM | D40: NPM | E40: =IFERROR(VLOOKUP($A40,subQ,MATCH(E$1,SUBQH,0),0),"") | F40: =IFERROR(VLOOKUP($A40,subQ,MATCH(F$1,SUBQH,0),0),"") | G40: =IFERROR(VLOOKUP($A40,subQ,MATCH(G$1,SUBQH,0),0),"") | H40: =IFERROR(VLOOKUP($A40,subQ,MATCH(H$1,SUBQH,0),0),"") | I40: =IFERROR(VLOOKUP($A40,subQ,MATCH(I$1,SUBQH,0),0),"") | J40: =IFERROR(VLOOKUP($A40,subQ,MATCH(J$1,SUBQH,0),0),"") | K40: =IFERROR(VLOOKUP($A40,subQ,MATCH(K$1,SUBQH,0),0),"") | L40: =IFERROR(VLOOKUP($A40,subQ,MATCH(L$1,SUBQH,0),0),"") | ... AG40: =IFERROR(VLOOKUP($A40,subQ,MATCH(AG$1,SUBQH,0),0),"")
A41: 매출액 YoY | D41: 매출액 YoY | I41: =IFERROR(I5/E5-1,"") | J41: =IFERROR(J5/F5-1,"") | K41: =IFERROR(K5/G5-1,"") | L41: =IFERROR(L5/H5-1,"") | M41: =IFERROR(M5/I5-1,"") | N41: =IFERROR(N5/J5-1,"") | O41: =IFERROR(O5/K5-1,"") | P41: =IFERROR(P5/L5-1,"") | ... AG41: =IFERROR(AG5/AC5-1,"")
A42: 영업이익 YoY | D42: 영업이익 YoY | I42: =IFERROR(I9/E9-1,"") | J42: =IFERROR(J9/F9-1,"") | K42: =IFERROR(K9/G9-1,"") | L42: =IFERROR(L9/H9-1,"") | M42: =IFERROR(M9/I9-1,"") | N42: =IFERROR(N9/J9-1,"") | O42: =IFERROR(O9/K9-1,"") | P42: =IFERROR(P9/L9-1,"") | ... AG42: =IFERROR(AG9/AC9-1,"")
A43: 지배주주순이익 YoY | D43: 지배주주순이익 YoY | I43: =IFERROR(I20/E20-1,"") | J43: =IFERROR(J20/F20-1,"") | K43: =IFERROR(K20/G20-1,"") | L43: =IFERROR(L20/H20-1,"") | M43: =IFERROR(M20/I20-1,"") | N43: =IFERROR(N20/J20-1,"") | O43: =IFERROR(O20/K20-1,"") | P43: =IFERROR(P20/L20-1,"") | ... AG43: =IFERROR(AG20/AC20-1,"")

Sheet 연간예상
C1: 이름: 연간예상H — subQ 를 이름으로 VLOOKUP(억원) | E1: 2021 | F1: 2022 | G1: 2023 | H1: 2024 | I1: 2025 | J1: 2026 | K1: 2027 | L1: 2028
C2: 종가: | D2: =변수!D44
C3: 기준일: | D3: 20261008 | E3: 1 | F3: 2 | G3: 3 | H3: 4 | I3: 5 | J3: 6 | K3: 7 | L3: 8
E4: 2021.12A | F4: 2022.12A | G4: 2023.12A | H4: 2024.12A | I4: 2025.12A | J4: 2026.12A | K4: 2027.12A | L4: 2028.12A
A5: 매출액 | D5: 매출액 | E5: =IFERROR(VLOOKUP($A5,subQ,MATCH(E$1,SUBQH,0),0),"") | F5: =IFERROR(VLOOKUP($A5,subQ,MATCH(F$1,SUBQH,0),0),"") | G5: =IFERROR(VLOOKUP($A5,subQ,MATCH(G$1,SUBQH,0),0),"") | H5: =IFERROR(VLOOKUP($A5,subQ,MATCH(H$1,SUBQH,0),0),"") | I5: =IFERROR(VLOOKUP($A5,subQ,MATCH(I$1,SUBQH,0),0),"") | J5: =IFERROR(VLOOKUP($A5,subQ,MATCH(J$1,SUBQH,0),0),"") | K5: =IFERROR(VLOOKUP($A5,subQ,MATCH(K$1,SUBQH,0),0),"") | L5: =IFERROR(VLOOKUP($A5,subQ,MATCH(L$1,SUBQH,0),0),"")
A6: 매출원가 | D6: 매출원가 | E6: =IFERROR(VLOOKUP($A6,subQ,MATCH(E$1,SUBQH,0),0),"") | F6: =IFERROR(VLOOKUP($A6,subQ,MATCH(F$1,SUBQH,0),0),"") | G6: =IFERROR(VLOOKUP($A6,subQ,MATCH(G$1,SUBQH,0),0),"") | H6: =IFERROR(VLOOKUP($A6,subQ,MATCH(H$1,SUBQH,0),0),"") | I6: =IFERROR(VLOOKUP($A6,subQ,MATCH(I$1,SUBQH,0),0),"") | J6: =IFERROR(VLOOKUP($A6,subQ,MATCH(J$1,SUBQH,0),0),"") | K6: =IFERROR(VLOOKUP($A6,subQ,MATCH(K$1,SUBQH,0),0),"") | L6: =IFERROR(VLOOKUP($A6,subQ,MATCH(L$1,SUBQH,0),0),"")
A7: 매출총이익 | D7: 매출총이익 | E7: =IFERROR(VLOOKUP($A7,subQ,MATCH(E$1,SUBQH,0),0),"") | F7: =IFERROR(VLOOKUP($A7,subQ,MATCH(F$1,SUBQH,0),0),"") | G7: =IFERROR(VLOOKUP($A7,subQ,MATCH(G$1,SUBQH,0),0),"") | H7: =IFERROR(VLOOKUP($A7,subQ,MATCH(H$1,SUBQH,0),0),"") | I7: =IFERROR(VLOOKUP($A7,subQ,MATCH(I$1,SUBQH,0),0),"") | J7: =IFERROR(VLOOKUP($A7,subQ,MATCH(J$1,SUBQH,0),0),"") | K7: =IFERROR(VLOOKUP($A7,subQ,MATCH(K$1,SUBQH,0),0),"") | L7: =IFERROR(VLOOKUP($A7,subQ,MATCH(L$1,SUBQH,0),0),"")
A8: 판관비 | D8: 판매비와관리비 | E8: =IFERROR(VLOOKUP($A8,subQ,MATCH(E$1,SUBQH,0),0),"") | F8: =IFERROR(VLOOKUP($A8,subQ,MATCH(F$1,SUBQH,0),0),"") | G8: =IFERROR(VLOOKUP($A8,subQ,MATCH(G$1,SUBQH,0),0),"") | H8: =IFERROR(VLOOKUP($A8,subQ,MATCH(H$1,SUBQH,0),0),"") | I8: =IFERROR(VLOOKUP($A8,subQ,MATCH(I$1,SUBQH,0),0),"") | J8: =IFERROR(VLOOKUP($A8,subQ,MATCH(J$1,SUBQH,0),0),"") | K8: =IFERROR(VLOOKUP($A8,subQ,MATCH(K$1,SUBQH,0),0),"") | L8: =IFERROR(VLOOKUP($A8,subQ,MATCH(L$1,SUBQH,0),0),"")
A9: 영업이익 | D9: 영업이익 | E9: =IFERROR(VLOOKUP($A9,subQ,MATCH(E$1,SUBQH,0),0),"") | F9: =IFERROR(VLOOKUP($A9,subQ,MATCH(F$1,SUBQH,0),0),"") | G9: =IFERROR(VLOOKUP($A9,subQ,MATCH(G$1,SUBQH,0),0),"") | H9: =IFERROR(VLOOKUP($A9,subQ,MATCH(H$1,SUBQH,0),0),"") | I9: =IFERROR(VLOOKUP($A9,subQ,MATCH(I$1,SUBQH,0),0),"") | J9: =IFERROR(VLOOKUP($A9,subQ,MATCH(J$1,SUBQH,0),0),"") | K9: =IFERROR(VLOOKUP($A9,subQ,MATCH(K$1,SUBQH,0),0),"") | L9: =IFERROR(VLOOKUP($A9,subQ,MATCH(L$1,SUBQH,0),0),"")
A10: OPM | D10: 영업이익률 | E10: =IFERROR(VLOOKUP($A10,subQ,MATCH(E$1,SUBQH,0),0),"") | F10: =IFERROR(VLOOKUP($A10,subQ,MATCH(F$1,SUBQH,0),0),"") | G10: =IFERROR(VLOOKUP($A10,subQ,MATCH(G$1,SUBQH,0),0),"") | H10: =IFERROR(VLOOKUP($A10,subQ,MATCH(H$1,SUBQH,0),0),"") | I10: =IFERROR(VLOOKUP($A10,subQ,MATCH(I$1,SUBQH,0),0),"") | J10: =IFERROR(VLOOKUP($A10,subQ,MATCH(J$1,SUBQH,0),0),"") | K10: =IFERROR(VLOOKUP($A10,subQ,MATCH(K$1,SUBQH,0),0),"") | L10: =IFERROR(VLOOKUP($A10,subQ,MATCH(L$1,SUBQH,0),0),"")
A11: 금융손익 | D11: 금융손익(이자·환 포함) | E11: =IFERROR(VLOOKUP($A11,subQ,MATCH(E$1,SUBQH,0),0),"") | F11: =IFERROR(VLOOKUP($A11,subQ,MATCH(F$1,SUBQH,0),0),"") | G11: =IFERROR(VLOOKUP($A11,subQ,MATCH(G$1,SUBQH,0),0),"") | H11: =IFERROR(VLOOKUP($A11,subQ,MATCH(H$1,SUBQH,0),0),"") | I11: =IFERROR(VLOOKUP($A11,subQ,MATCH(I$1,SUBQH,0),0),"") | J11: =IFERROR(VLOOKUP($A11,subQ,MATCH(J$1,SUBQH,0),0),"") | K11: =IFERROR(VLOOKUP($A11,subQ,MATCH(K$1,SUBQH,0),0),"") | L11: =IFERROR(VLOOKUP($A11,subQ,MATCH(L$1,SUBQH,0),0),"")
A12: 이자손익 | D12: 이자손익(이자수익 − 이자비용) | E12: =IFERROR(VLOOKUP($A12,subQ,MATCH(E$1,SUBQH,0),0),"") | F12: =IFERROR(VLOOKUP($A12,subQ,MATCH(F$1,SUBQH,0),0),"") | G12: =IFERROR(VLOOKUP($A12,subQ,MATCH(G$1,SUBQH,0),0),"") | H12: =IFERROR(VLOOKUP($A12,subQ,MATCH(H$1,SUBQH,0),0),"") | I12: =IFERROR(VLOOKUP($A12,subQ,MATCH(I$1,SUBQH,0),0),"") | J12: =IFERROR(VLOOKUP($A12,subQ,MATCH(J$1,SUBQH,0),0),"") | K12: =IFERROR(VLOOKUP($A12,subQ,MATCH(K$1,SUBQH,0),0),"") | L12: =IFERROR(VLOOKUP($A12,subQ,MATCH(L$1,SUBQH,0),0),"")
A13: 외환손익 | D13: 외환손익(실적만; 추정 환효과는 환관련손익) | E13: =IFERROR(VLOOKUP($A13,subQ,MATCH(E$1,SUBQH,0),0),"") | F13: =IFERROR(VLOOKUP($A13,subQ,MATCH(F$1,SUBQH,0),0),"") | G13: =IFERROR(VLOOKUP($A13,subQ,MATCH(G$1,SUBQH,0),0),"") | H13: =IFERROR(VLOOKUP($A13,subQ,MATCH(H$1,SUBQH,0),0),"") | I13: =IFERROR(VLOOKUP($A13,subQ,MATCH(I$1,SUBQH,0),0),"") | J13: =IFERROR(VLOOKUP($A13,subQ,MATCH(J$1,SUBQH,0),0),"") | K13: =IFERROR(VLOOKUP($A13,subQ,MATCH(K$1,SUBQH,0),0),"") | L13: =IFERROR(VLOOKUP($A13,subQ,MATCH(L$1,SUBQH,0),0),"")
A14: 기타금융손익 | D14: 기타금융손익(금융손익 잔차) | E14: =IFERROR(VLOOKUP($A14,subQ,MATCH(E$1,SUBQH,0),0),"") | F14: =IFERROR(VLOOKUP($A14,subQ,MATCH(F$1,SUBQH,0),0),"") | G14: =IFERROR(VLOOKUP($A14,subQ,MATCH(G$1,SUBQH,0),0),"") | H14: =IFERROR(VLOOKUP($A14,subQ,MATCH(H$1,SUBQH,0),0),"") | I14: =IFERROR(VLOOKUP($A14,subQ,MATCH(I$1,SUBQH,0),0),"") | J14: =IFERROR(VLOOKUP($A14,subQ,MATCH(J$1,SUBQH,0),0),"") | K14: =IFERROR(VLOOKUP($A14,subQ,MATCH(K$1,SUBQH,0),0),"") | L14: =IFERROR(VLOOKUP($A14,subQ,MATCH(L$1,SUBQH,0),0),"")
A15: 기타영업외손익 | D15: 기타영업외손익 | E15: =IFERROR(VLOOKUP($A15,subQ,MATCH(E$1,SUBQH,0),0),"") | F15: =IFERROR(VLOOKUP($A15,subQ,MATCH(F$1,SUBQH,0),0),"") | G15: =IFERROR(VLOOKUP($A15,subQ,MATCH(G$1,SUBQH,0),0),"") | H15: =IFERROR(VLOOKUP($A15,subQ,MATCH(H$1,SUBQH,0),0),"") | I15: =IFERROR(VLOOKUP($A15,subQ,MATCH(I$1,SUBQH,0),0),"") | J15: =IFERROR(VLOOKUP($A15,subQ,MATCH(J$1,SUBQH,0),0),"") | K15: =IFERROR(VLOOKUP($A15,subQ,MATCH(K$1,SUBQH,0),0),"") | L15: =IFERROR(VLOOKUP($A15,subQ,MATCH(L$1,SUBQH,0),0),"")
A16: 지분법손익 | D16: 지분법손익 | E16: =IFERROR(VLOOKUP($A16,subQ,MATCH(E$1,SUBQH,0),0),"") | F16: =IFERROR(VLOOKUP($A16,subQ,MATCH(F$1,SUBQH,0),0),"") | G16: =IFERROR(VLOOKUP($A16,subQ,MATCH(G$1,SUBQH,0),0),"") | H16: =IFERROR(VLOOKUP($A16,subQ,MATCH(H$1,SUBQH,0),0),"") | I16: =IFERROR(VLOOKUP($A16,subQ,MATCH(I$1,SUBQH,0),0),"") | J16: =IFERROR(VLOOKUP($A16,subQ,MATCH(J$1,SUBQH,0),0),"") | K16: =IFERROR(VLOOKUP($A16,subQ,MATCH(K$1,SUBQH,0),0),"") | L16: =IFERROR(VLOOKUP($A16,subQ,MATCH(L$1,SUBQH,0),0),"")
... A40: NPM | D40: NPM | E40: =IFERROR(VLOOKUP($A40,subQ,MATCH(E$1,SUBQH,0),0),"") | F40: =IFERROR(VLOOKUP($A40,subQ,MATCH(F$1,SUBQH,0),0),"") | G40: =IFERROR(VLOOKUP($A40,subQ,MATCH(G$1,SUBQH,0),0),"") | H40: =IFERROR(VLOOKUP($A40,subQ,MATCH(H$1,SUBQH,0),0),"") | I40: =IFERROR(VLOOKUP($A40,subQ,MATCH(I$1,SUBQH,0),0),"") | J40: =IFERROR(VLOOKUP($A40,subQ,MATCH(J$1,SUBQH,0),0),"") | K40: =IFERROR(VLOOKUP($A40,subQ,MATCH(K$1,SUBQH,0),0),"") | L40: =IFERROR(VLOOKUP($A40,subQ,MATCH(L$1,SUBQH,0),0),"")
A41: 매출액 YoY | D41: 매출액 YoY | F41: =IFERROR(F5/E5-1,"") | G41: =IFERROR(G5/F5-1,"") | H41: =IFERROR(H5/G5-1,"") | I41: =IFERROR(I5/H5-1,"") | J41: =IFERROR(J5/I5-1,"") | K41: =IFERROR(K5/J5-1,"") | L41: =IFERROR(L5/K5-1,"")
A42: 영업이익 YoY | D42: 영업이익 YoY | F42: =IFERROR(F9/E9-1,"") | G42: =IFERROR(G9/F9-1,"") | H42: =IFERROR(H9/G9-1,"") | I42: =IFERROR(I9/H9-1,"") | J42: =IFERROR(J9/I9-1,"") | K42: =IFERROR(K9/J9-1,"") | L42: =IFERROR(L9/K9-1,"")
A43: 지배주주순이익 YoY | D43: 지배주주순이익 YoY | F43: =IFERROR(F20/E20-1,"") | G43: =IFERROR(G20/F20-1,"") | H43: =IFERROR(H20/G20-1,"") | I43: =IFERROR(I20/H20-1,"") | J43: =IFERROR(J20/I20-1,"") | K43: =IFERROR(K20/J20-1,"") | L43: =IFERROR(L20/K20-1,"")

Sheet TP
B1: 종가 | C1: =변수!D44
B2: 기준일 | C2: =변수!D45
B3: 모델 산출값 — 목표주가·추천 아님. 밴드·COE 는 변수 시트 3절의 가정
C5: FY | D5: 2025 | E5: 2026 | F5: 2027 | G5: 2028
D6: A | E6: E | F6: E | G6: E
C7: EPS(원) | D7: =IFERROR(VLOOKUP("EPS",subQ,MATCH(D$5,SUBQH,0),0),"") | E7: =IFERROR(VLOOKUP("EPS",subQ,MATCH(E$5,SUBQH,0),0),"") | F7: =IFERROR(VLOOKUP("EPS",subQ,MATCH(F$5,SUBQH,0),0),"") | G7: =IFERROR(VLOOKUP("EPS",subQ,MATCH(G$5,SUBQH,0),0),"")
C8: BPS(원) | D8: =IFERROR(VLOOKUP("BPS",subQ,MATCH(D$5,SUBQH,0),0),"") | E8: =IFERROR(VLOOKUP("BPS",subQ,MATCH(E$5,SUBQH,0),0),"") | F8: =IFERROR(VLOOKUP("BPS",subQ,MATCH(F$5,SUBQH,0),0),"") | G8: =IFERROR(VLOOKUP("BPS",subQ,MATCH(G$5,SUBQH,0),0),"")
C9: 지배주주순이익(억원) | D9: =IFERROR(VLOOKUP("지배주주순이익",subQ,MATCH(D$5,SUBQH,0),0),"") | E9: =IFERROR(VLOOKUP("지배주주순이익",subQ,MATCH(E$5,SUBQH,0),0),"") | F9: =IFERROR(VLOOKUP("지배주주순이익",subQ,MATCH(F$5,SUBQH,0),0),"") | G9: =IFERROR(VLOOKUP("지배주주순이익",subQ,MATCH(G$5,SUBQH,0),0),"")
C10: 영업이익(억원) | D10: =IFERROR(VLOOKUP("영업이익",subQ,MATCH(D$5,SUBQH,0),0),"") | E10: =IFERROR(VLOOKUP("영업이익",subQ,MATCH(E$5,SUBQH,0),0),"") | F10: =IFERROR(VLOOKUP("영업이익",subQ,MATCH(F$5,SUBQH,0),0),"") | G10: =IFERROR(VLOOKUP("영업이익",subQ,MATCH(G$5,SUBQH,0),0),"")
C11: ROE(EPS/기초BPS) | E11: =IFERROR(E7/D8,"") | F11: =IFERROR(F7/E8,"") | G11: =IFERROR(G7/F8,"")
B13: PER
C14: 12M fwd EPS | D14: =IFERROR(E7*변수!D50+F7*(1-변수!D50),"")
C15: 적정가치 @PER_lo | D15: =변수!D47 | E15: =IFERROR(ROUND($D$14*D15,-2),"") | F15: =IFERROR(E15/$C$1-1,"") | G15: 배 · 원 · 종가 대비
C16: 적정가치 @PER_mid | D16: =변수!D48 | E16: =IFERROR(ROUND($D$14*D16,-2),"") | F16: =IFERROR(E16/$C$1-1,"") | G16: 배 · 원 · 종가 대비
C17: 적정가치 @PER_hi | D17: =변수!D49 | E17: =IFERROR(ROUND($D$14*D17,-2),"") | F17: =IFERROR(E17/$C$1-1,"") | G17: 배 · 원 · 종가 대비
C18: 현재 PER(종가/12M fwd EPS) | D18: =IFERROR($C$1/$D$14,"")
B20: PBR
C21: 최근 BPS(마지막 실적 분기) | D21: =IFERROR(VLOOKUP("BPS",subQ,MATCH("2Q26",SUBQH,0),0),"")
C22: ROE fwd(12M fwd EPS / BPS) | D22: =IFERROR($D$14/$D$21,"")
C23: COE | D23: =변수!D46
C24: 적정 PBR = ROE/COE | D24: =IFERROR(D22/D23,"")
C25: 적정가치(PBR) = BPS × 적정PBR | D25: =IFERROR(ROUND(D21*D24,-2),"") | E25: =IFERROR(D25/$C$1-1,"")
C26: 현재 PBR(종가/BPS) | D26: =IFERROR($C$1/D21,"")
B28: 모델 json valuation(참고)
C29: eps_fwd12m | D29: 778.5
C30: bps_latest | D30: 24026.1
C31: per_now | D31: 98.52
C32: pbr_now | D32: 3.19
C33: roe_fwd | D33: 0.0324
C34: fair_pbr | D34: 0.36
C35: fair_value_pbr | D35: 8600
C36: ev_ebitda
C37: note | D37: 모델 산출값 — 목표주가·추천 아님

Sheet 외화
C1: 이름: 외화QH — 환율 QoQ · 외화 순노출 × Δ기말환율 | E1: 4Q21 | F1: 1Q22 | G1: 2Q22 | H1: 3Q22 | I1: 4Q22 | J1: 1Q23 | K1: 2Q23 | L1: 3Q23 | M1: 4Q23 | N1: 1Q24 | O1: 2Q24 | P1: 3Q24 | Q1: 4Q24 | R1: 1Q25 | S1: 2Q25 | T1: 3Q25 | U1: 4Q25 | V1: 1Q26 | W1: 2Q26 | X1: 3Q26 | Y1: 4Q26 | Z1: 1Q27 | AA1: 2Q27 | AB1: 3Q27 | AC1: 4Q27 | AD1: 1Q28 | AE1: 2Q28 | AF1: 3Q28 | AG1: 4Q28
E3: 1 | F3: 2 | G3: 3 | H3: 4 | I3: 5 | J3: 6 | K3: 7 | L3: 8 | M3: 9 | N3: 10 | O3: 11 | P3: 12 | Q3: 13 | R3: 14 | S3: 15 | T3: 16 | U3: 17 | V3: 18 | W3: 19 | X3: 20 | Y3: 21 | Z3: 22 | AA3: 23 | AB3: 24 | AC3: 25 | AD3: 26 | AE3: 27 | AF3: 28 | AG3: 29
E4: 2021.12 | F4: 2022.03 | G4: 2022.06 | H4: 2022.09 | I4: 2022.12 | J4: 2023.03 | K4: 2023.06 | L4: 2023.09 | M4: 2023.12 | N4: 2024.03 | O4: 2024.06 | P4: 2024.09 | Q4: 2024.12 | R4: 2025.03 | S4: 2025.06 | T4: 2025.09 | U4: 2025.12 | V4: 2026.03 | W4: 2026.06 | X4: 2026.09 | Y4: 2026.12 | Z4: 2027.03 | AA4: 2027.06 | AB4: 2027.09 | AC4: 2027.12 | AD4: 2028.03 | AE4: 2028.06 | AF4: 2028.09 | AG4: 2028.12
D5: 원/달러(평균) | E5: =IFERROR(VLOOKUP($D5,환율,MATCH(E$1,변수H,0),0),"") | F5: =IFERROR(VLOOKUP($D5,환율,MATCH(F$1,변수H,0),0),"") | G5: =IFERROR(VLOOKUP($D5,환율,MATCH(G$1,변수H,0),0),"") | H5: =IFERROR(VLOOKUP($D5,환율,MATCH(H$1,변수H,0),0),"") | I5: =IFERROR(VLOOKUP($D5,환율,MATCH(I$1,변수H,0),0),"") | J5: =IFERROR(VLOOKUP($D5,환율,MATCH(J$1,변수H,0),0),"") | K5: =IFERROR(VLOOKUP($D5,환율,MATCH(K$1,변수H,0),0),"") | L5: =IFERROR(VLOOKUP($D5,환율,MATCH(L$1,변수H,0),0),"") | ... AG5: =IFERROR(VLOOKUP($D5,환율,MATCH(AG$1,변수H,0),0),"")
A6: 원/달러(평균) QoQ | F6: =IFERROR(F5/E5-1,"") | G6: =IFERROR(G5/F5-1,"") | H6: =IFERROR(H5/G5-1,"") | I6: =IFERROR(I5/H5-1,"") | J6: =IFERROR(J5/I5-1,"") | K6: =IFERROR(K5/J5-1,"") | L6: =IFERROR(L5/K5-1,"") | M6: =IFERROR(M5/L5-1,"") | ... AG6: =IFERROR(AG5/AF5-1,"")
D7: 원/달러(기말) | E7: =IFERROR(VLOOKUP($D7,환율,MATCH(E$1,변수H,0),0),"") | F7: =IFERROR(VLOOKUP($D7,환율,MATCH(F$1,변수H,0),0),"") | G7: =IFERROR(VLOOKUP($D7,환율,MATCH(G$1,변수H,0),0),"") | H7: =IFERROR(VLOOKUP($D7,환율,MATCH(H$1,변수H,0),0),"") | I7: =IFERROR(VLOOKUP($D7,환율,MATCH(I$1,변수H,0),0),"") | J7: =IFERROR(VLOOKUP($D7,환율,MATCH(J$1,변수H,0),0),"") | K7: =IFERROR(VLOOKUP($D7,환율,MATCH(K$1,변수H,0),0),"") | L7: =IFERROR(VLOOKUP($D7,환율,MATCH(L$1,변수H,0),0),"") | ... AG7: =IFERROR(VLOOKUP($D7,환율,MATCH(AG$1,변수H,0),0),"")
A8: 원/달러(기말) QoQ | F8: =IFERROR(F7/E7-1,"") | G8: =IFERROR(G7/F7-1,"") | H8: =IFERROR(H7/G7-1,"") | I8: =IFERROR(I7/H7-1,"") | J8: =IFERROR(J7/I7-1,"") | K8: =IFERROR(K7/J7-1,"") | L8: =IFERROR(L7/K7-1,"") | M8: =IFERROR(M7/L7-1,"") | ... AG8: =IFERROR(AG7/AF7-1,"")
D9: W/Euro(평균) | E9: =IFERROR(VLOOKUP($D9,환율,MATCH(E$1,변수H,0),0),"") | F9: =IFERROR(VLOOKUP($D9,환율,MATCH(F$1,변수H,0),0),"") | G9: =IFERROR(VLOOKUP($D9,환율,MATCH(G$1,변수H,0),0),"") | H9: =IFERROR(VLOOKUP($D9,환율,MATCH(H$1,변수H,0),0),"") | I9: =IFERROR(VLOOKUP($D9,환율,MATCH(I$1,변수H,0),0),"") | J9: =IFERROR(VLOOKUP($D9,환율,MATCH(J$1,변수H,0),0),"") | K9: =IFERROR(VLOOKUP($D9,환율,MATCH(K$1,변수H,0),0),"") | L9: =IFERROR(VLOOKUP($D9,환율,MATCH(L$1,변수H,0),0),"") | ... AG9: =IFERROR(VLOOKUP($D9,환율,MATCH(AG$1,변수H,0),0),"")
A10: W/Euro(평균) QoQ | F10: =IFERROR(F9/E9-1,"") | G10: =IFERROR(G9/F9-1,"") | H10: =IFERROR(H9/G9-1,"") | I10: =IFERROR(I9/H9-1,"") | J10: =IFERROR(J9/I9-1,"") | K10: =IFERROR(K9/J9-1,"") | L10: =IFERROR(L9/K9-1,"") | M10: =IFERROR(M9/L9-1,"") | ... AG10: =IFERROR(AG9/AF9-1,"")
D11: W/Euro(기말) | E11: =IFERROR(VLOOKUP($D11,환율,MATCH(E$1,변수H,0),0),"") | F11: =IFERROR(VLOOKUP($D11,환율,MATCH(F$1,변수H,0),0),"") | G11: =IFERROR(VLOOKUP($D11,환율,MATCH(G$1,변수H,0),0),"") | H11: =IFERROR(VLOOKUP($D11,환율,MATCH(H$1,변수H,0),0),"") | I11: =IFERROR(VLOOKUP($D11,환율,MATCH(I$1,변수H,0),0),"") | J11: =IFERROR(VLOOKUP($D11,환율,MATCH(J$1,변수H,0),0),"") | K11: =IFERROR(VLOOKUP($D11,환율,MATCH(K$1,변수H,0),0),"") | L11: =IFERROR(VLOOKUP($D11,환율,MATCH(L$1,변수H,0),0),"") | ... AG11: =IFERROR(VLOOKUP($D11,환율,MATCH(AG$1,변수H,0),0),"")
A12: W/Euro(기말) QoQ | F12: =IFERROR(F11/E11-1,"") | G12: =IFERROR(G11/F11-1,"") | H12: =IFERROR(H11/G11-1,"") | I12: =IFERROR(I11/H11-1,"") | J12: =IFERROR(J11/I11-1,"") | K12: =IFERROR(K11/J11-1,"") | L12: =IFERROR(L11/K11-1,"") | M12: =IFERROR(M11/L11-1,"") | ... AG12: =IFERROR(AG11/AF11-1,"")
D13: 원/100Y(기말) | E13: =IFERROR(VLOOKUP($D13,환율,MATCH(E$1,변수H,0),0),"") | F13: =IFERROR(VLOOKUP($D13,환율,MATCH(F$1,변수H,0),0),"") | G13: =IFERROR(VLOOKUP($D13,환율,MATCH(G$1,변수H,0),0),"") | H13: =IFERROR(VLOOKUP($D13,환율,MATCH(H$1,변수H,0),0),"") | I13: =IFERROR(VLOOKUP($D13,환율,MATCH(I$1,변수H,0),0),"") | J13: =IFERROR(VLOOKUP($D13,환율,MATCH(J$1,변수H,0),0),"") | K13: =IFERROR(VLOOKUP($D13,환율,MATCH(K$1,변수H,0),0),"") | L13: =IFERROR(VLOOKUP($D13,환율,MATCH(L$1,변수H,0),0),"") | ... AG13: =IFERROR(VLOOKUP($D13,환율,MATCH(AG$1,변수H,0),0),"")
A14: 원/100Y(기말) QoQ | F14: =IFERROR(F13/E13-1,"") | G14: =IFERROR(G13/F13-1,"") | H14: =IFERROR(H13/G13-1,"") | I14: =IFERROR(I13/H13-1,"") | J14: =IFERROR(J13/I13-1,"") | K14: =IFERROR(K13/J13-1,"") | L14: =IFERROR(L13/K13-1,"") | M14: =IFERROR(M13/L13-1,"") | ... AG14: =IFERROR(AG13/AF13-1,"")
A16: 외화순노출 | C16: 외화 순노출(백만$) | D16: =변수!D57 | E16: 외화 순노출 × Δ기말환율 (외화 시트 방식)
A17: 환관련손익추정 | C17: 환관련손익 추정(억원) = 순노출 × Δ원/달러(기말) / 100 | F17: =IFERROR($D$16*(F7-E7)/100,"") | G17: =IFERROR($D$16*(G7-F7)/100,"") | H17: =IFERROR($D$16*(H7-G7)/100,"") | I17: =IFERROR($D$16*(I7-H7)/100,"") | J17: =IFERROR($D$16*(J7-I7)/100,"") | K17: =IFERROR($D$16*(K7-J7)/100,"") | L17: =IFERROR($D$16*(L7-K7)/100,"") | M17: =IFERROR($D$16*(M7-L7)/100,"") | ... AG17: =IFERROR($D$16*(AG7-AF7)/100,"")
A18: fx_pnl.by_q | C18: 모델 fx_pnl.by_q(억원, 참고)
C19: 외화 순노출 미공시(face) → 0 + 표기
