Workbook
Name 변수H: 변수!$C$1:$AO$1
Name 환율: 변수!$C$6:$AO$13
Name BS연결H: BS연결!$C$1:$AO$1
Name BS연결: BS연결!$C$5:$AO$112
Name BS별도H: BS별도!$C$1:$AO$1
Name BS별도: BS별도!$C$5:$AO$95
Name SUBQH: subQ!$A$1:$AO$1
Name subQ: subQ!$A$5:$AO$48
Name SLS_H: SLS!$A$1:$BE$1

Sheet README
A1: HD현대중공업(329180) 실적 모델 — ARGUS 한국조선
A2: 기준 분기 2026Q2 · 마지막 실적 2026Q2 · 생성 2026-10-14
A3: 모든 수치는 모델 산출값(DART 공개 재무제표 + 우리 추정)이다 — 목표주가·투자 추천 아님. 참고용 · 투자조언 아님.
A5: 시트
A6: 변수 가정 시계열. 환율 8행(ECB via frankfurter — L2 fx.json; 추정 분기 = 노란 가정), 추정 드라이버(노란 셀 = 모델값에서 역산한 가정, 바꾸면 재계산; 연녹 셀 = 3절 스칼라 참조 수식), 3절 스칼라 가정(세율·판관비율·지배주주비중·이자율·종가·PER 밴드·COE·외화 순노출·헤지비율)
A7: BS연결/BS별도 FnGuide 계정명 × 기간 값 덤프(백만원). 행1 분기라벨, 행4 YYYY.MM / YYYY.12A. 이름정의 BS연결H·BS연결(계정명 C열부터)
A8: subQ 분기 서브모델(억원 = 백만원/100). 확정 행: =IFERROR(VLOOKUP($D행,BS연결,MATCH(E$1,BS연결H,0),0)/100,"") 추정 행: 변수 시트 가정 셀 참조 수식. 외환손익·파생상품손익은 BS 계정 합·차, 기타금융손익은 잔차, OPM·EPS·BPS·PER·PBR 은 파생 수식
A9: SLS 선표(조선사만, sls json 있을 때): 요약 행(sls 저장값) + 계약별 스케줄(백만$) × (헤지비율 × 헤지환율 + (1−헤지비율) × 건조시점 환율[변수 원/달러(평균)]) → 원화 수식 블록 → 합계 행이 subQ 매출조선에 연결
A10: 시나리오 신규수주 보수/기준/낙관(forecast_panel 패널, 모델에 scenarios 가 있을 때만): 매출액·영업이익 = subQ 기준값 ± (시나리오 신규 − base 신규) × OPM. base 만 subQ 행에 포함, 나머지는 합산 안 함
A11: 분기/연간예상 subQ 를 이름(A열 key)으로 VLOOKUP 한 보고서 표(억원)
A12: TP PER 밴드 × 12M fwd EPS, PBR = ROE/COE × BPS — 모델 산출값 구간, 목표주가·추천 아님
A13: 외화 환율 QoQ, 외화 순노출 × Δ기말환율 → 환관련손익 추정
... A36: 백테스트: {"freeze": "2025Q2", "horizon": 4, "revenue_wape_pct": 24.0, "op_wape_pct": 50.3, "n": 4, "note": "단일 회사 4분기 — 통계 아님", "driver_at_freeze": "sls_marine_plus_uncovered_backlog_runoff", "selection_oos_at_freeze": null, "frozen_inputs": "fin(연결/별도)·고객 조선사 모델·지주 자회사 모델은 2025Q2 까지의 분기만; 선표는 체결일 ≤ 2025Q2 말일 계약(원장 최신 금액·코호트 등급, 환산 없음); 잔고는 yards_cache 2025Q2; 시세·환율 forward·prices·forecast_panel 신규수주 미사용. 고객 가중치(suppliers.json 언급 비중)와 합병 체인링크는 현재 지식; 고객 연동 채택은 동결 모델 안에서도 자기 la−4분기 OOS 규칙(selection_oos_at_freeze)", "detail": [{"q": "2025Q3", "rev_pred": 41613.18, "rev_act": 44178.98, "op_pred": 3826.68, "op_act": 5572.85}, {"q": "2025Q4", "rev_pred": 41613.18, "rev_act": 51930.94, "op_pred": 3826.68, "op_act": 5750.35}, {"q": "2026Q1", "rev_pred": 41460.55, "rev_act": 59163.32, "op_pred": 3812.64, "op_act": 9053.86}, {"q": "2026Q2", "rev_pred": 41536.85, "rev_act": 63321.55, "op_pred": 3819.66, "op_act": 10399.38}]}

Sheet 변수
C1: 이름: 변수H | E1: 4Q21 | F1: 2021 | G1: 1Q22 | H1: 2Q22 | I1: 3Q22 | J1: 4Q22 | K1: 2022 | L1: 1Q23 | M1: 2Q23 | N1: 3Q23 | O1: 4Q23 | P1: 2023 | Q1: 1Q24 | R1: 2Q24 | S1: 3Q24 | T1: 4Q24 | U1: 2024 | V1: 1Q25 | W1: 2Q25 | X1: 3Q25 | Y1: 4Q25 | Z1: 2025 | AA1: 1Q26 | AB1: 2Q26 | AC1: 3Q26 | AD1: 4Q26 | AE1: 2026 | AF1: 1Q27 | AG1: 2Q27 | AH1: 3Q27 | AI1: 4Q27 | AJ1: 2027 | AK1: 1Q28 | AL1: 2Q28 | AM1: 3Q28 | AN1: 4Q28 | AO1: 2028
A2: 가정 시계열 — 노란 셀은 추정 가정(모델값에서 역산), 연녹 셀은 3절 스칼라 참조 수식. 바꾸면 subQ·분기·연간예상·TP·시나리오가 재계산됩니다.
E3: 1 | F3: 2 | G3: 3 | H3: 4 | I3: 5 | J3: 6 | K3: 7 | L3: 8 | M3: 9 | N3: 10 | O3: 11 | P3: 12 | Q3: 13 | R3: 14 | S3: 15 | T3: 16 | U3: 17 | V3: 18 | W3: 19 | X3: 20 | Y3: 21 | Z3: 22 | AA3: 23 | AB3: 24 | AC3: 25 | AD3: 26 | AE3: 27 | AF3: 28 | AG3: 29 | AH3: 30 | AI3: 31 | AJ3: 32 | AK3: 33 | AL3: 34 | AM3: 35 | AN3: 36 | AO3: 37
E4: 2021.12 | F4: 2021.12A | G4: 2022.03 | H4: 2022.06 | I4: 2022.09 | J4: 2022.12 | K4: 2022.12A | L4: 2023.03 | M4: 2023.06 | N4: 2023.09 | O4: 2023.12 | P4: 2023.12A | Q4: 2024.03 | R4: 2024.06 | S4: 2024.09 | T4: 2024.12 | U4: 2024.12A | V4: 2025.03 | W4: 2025.06 | X4: 2025.09 | Y4: 2025.12 | Z4: 2025.12A | AA4: 2026.03 | AB4: 2026.06 | AC4: 2026.09 | AD4: 2026.12 | AE4: 2026.12A | AF4: 2027.03 | AG4: 2027.06 | AH4: 2027.09 | AI4: 2027.12 | AJ4: 2027.12A | AK4: 2028.03 | AL4: 2028.06 | AM4: 2028.09 | AN4: 2028.12 | AO4: 2028.12A
B5: 1. FX | C5: 이름: 환율
A6: USDKRW_avg | C6: 원/달러(평균) | E6: 1183.5 | F6: 1145.51 | G6: 1205.78 | H6: 1262.09 | I6: 1341.93 | J6: 1360.12 | K6: 1292.98 | L6: 1276.95 | M6: 1315.69 | N6: 1313.62 | O6: 1322.01 | P6: 1306.85 | Q6: 1330.14 | R6: 1371.28 | S6: 1356.22 | T6: 1396.3 | U6: 1363.53 | V6: 1452.28 | W6: 1398.52 | X6: 1386.95 | Y6: 1449.19 | Z6: 1421.52 | AA6: 1466.12 | AB6: 1501.75 | AC6: 1418.75 | AD6: 1343.39 | AE6: 1456.01 | AF6: 1341.45 | AG6: 1341.45 | AH6: 1341.45 | AI6: 1341.45 | AK6: 1341.45 | AL6: 1341.45 | AM6: 1341.45 | AN6: 1341.45
A7: USDKRW_end | C7: 원/달러(기말) | E7: 1188.75 | F7: 1188.75 | G7: 1213.74 | H7: 1301.24 | I7: 1436.9 | J7: 1260.16 | K7: 1260.16 | L7: 1305.99 | M7: 1321.44 | N7: 1345.35 | O7: 1297.43 | P7: 1297.43 | Q7: 1349.25 | R7: 1377.73 | S7: 1312.17 | T7: 1474.78 | U7: 1474.78 | V7: 1474.54 | W7: 1355.13 | X7: 1403.67 | Y7: 1444.2 | Z7: 1444.2 | AA7: 1524.8 | AB7: 1550.89 | AC7: 1355.4 | AD7: 1341.45 | AE7: 1341.45 | AF7: 1341.45 | AG7: 1341.45 | AH7: 1341.45 | AI7: 1341.45 | AK7: 1341.45 | AL7: 1341.45 | AM7: 1341.45 | AN7: 1341.45
A8: JPY100KRW_avg | C8: 원/100Y(평균) | E8: 1041.02 | F8: 1042.74 | G8: 1036.79 | H8: 972.23 | I8: 970.61 | J8: 961.03 | K8: 985.1 | L8: 964.89 | M8: 957.36 | N8: 909 | O8: 893.22 | P8: 931.11 | Q8: 896.29 | R8: 880.14 | S8: 909.35 | T8: 917.25 | U8: 900.92 | V8: 952.59 | W8: 967.92 | X8: 940.32 | Y8: 940.77 | Z8: 950.17 | AA8: 934.39 | AB8: 942.16 | AC8: 890.41 | AD8: 849.39 | AE8: 918.46 | AF8: 848.37 | AG8: 848.37 | AH8: 848.37 | AI8: 848.37 | AK8: 848.37 | AL8: 848.37 | AM8: 848.37 | AN8: 848.37
A9: JPY100KRW_end | C9: 원/100Y(기말) | E9: 1032.62 | F9: 1032.62 | G9: 996.83 | H9: 954.9 | I9: 993.29 | J9: 955.54 | K9: 955.54 | L9: 980.62 | M9: 913.67 | N9: 901.47 | O9: 917.04 | P9: 917.04 | Q9: 892.42 | R9: 857.76 | S9: 919.21 | T9: 939.65 | U9: 939.65 | V9: 986.84 | W9: 938.85 | X9: 948.49 | Y9: 921.81 | Z9: 921.81 | AA9: 955.99 | AB9: 954.75 | AC9: 863.31 | AD9: 848.37 | AE9: 848.37 | AF9: 848.37 | AG9: 848.37 | AH9: 848.37 | AI9: 848.37 | AK9: 848.37 | AL9: 848.37 | AM9: 848.37 | AN9: 848.37
A10: EURKRW_avg | C10: W/Euro(평균) | E10: 1353.32 | F10: 1354.06 | G10: 1352.29 | H10: 1343.31 | I10: 1350.63 | J10: 1386.07 | K10: 1358.07 | L10: 1369.93 | M10: 1432.41 | N10: 1429.41 | O10: 1420.91 | P10: 1412.88 | Q10: 1444.21 | R10: 1476.42 | S10: 1489.3 | T10: 1490.78 | U10: 1475.4 | V10: 1528.33 | W10: 1585.13 | X10: 1620.04 | Y10: 1686.02 | Z10: 1605.45 | AA10: 1715.47 | AB10: 1746.09 | AC10: 1631.97 | AD10: 1506.62 | AE10: 1688.01 | AF10: 1500.82 | AG10: 1500.82 | AH10: 1500.82 | AI10: 1500.82 | AK10: 1500.82 | AL10: 1500.82 | AM10: 1500.82 | AN10: 1500.82
A11: EURKRW_end | C11: W/Euro(기말) | E11: 1346.38 | F11: 1346.38 | G11: 1347.37 | H11: 1351.6 | I11: 1400.62 | J11: 1344.08 | K11: 1344.08 | L11: 1420.26 | M11: 1435.88 | N11: 1425.26 | O11: 1433.66 | P11: 1433.66 | Q11: 1458.68 | R11: 1474.86 | S11: 1469.1 | T11: 1532.14 | U11: 1532.14 | V11: 1594.72 | W11: 1588.22 | X11: 1648.04 | Y11: 1696.94 | Z11: 1696.94 | AA11: 1753.21 | AB11: 1767.09 | AC11: 1539.06 | AD11: 1500.82 | AE11: 1500.82 | AF11: 1500.82 | AG11: 1500.82 | AH11: 1500.82 | AI11: 1500.82 | AK11: 1500.82 | AL11: 1500.82 | AM11: 1500.82 | AN11: 1500.82
A12: CNYKRW_avg | C12: 원/중국원(평균) | E12: 185.14 | F12: 177.65 | G12: 189.93 | H12: 190.76 | I12: 195.79 | J12: 191.09 | K12: 191.93 | L12: 186.59 | M12: 187.45 | N12: 181.28 | O12: 182.86 | P12: 184.52 | Q12: 185.04 | R12: 189.35 | S12: 189.24 | T12: 194.24 | U12: 189.49 | V12: 199.63 | W12: 193.41 | X12: 193.79 | Y12: 204.38 | Z12: 197.8 | AA12: 211.75 | AB12: 220.8 | AC12: 210.43 | AD12: 200.49 | AE12: 213.61 | AF12: 200.4 | AG12: 200.4 | AH12: 200.4 | AI12: 200.4 | AK12: 200.4 | AL12: 200.4 | AM12: 200.4 | AN12: 200.4
A13: CNYKRW_end | C13: 원/중국원(기말) | E13: 187.13 | F13: 187.13 | G13: 191.38 | H13: 194.13 | I13: 201.92 | J13: 182.67 | K13: 182.67 | L13: 189.97 | M13: 181.8 | N13: 184.26 | O13: 182.61 | P13: 182.61 | Q13: 186.66 | R13: 189.7 | S13: 187.12 | T13: 202.04 | U13: 202.04 | V13: 203.3 | W13: 189.14 | X13: 197.16 | Y13: 206.28 | Z13: 206.28 | AA13: 220.97 | AB13: 228.56 | AC13: 202.16 | AD13: 200.4 | AE13: 200.4 | AF13: 200.4 | AG13: 200.4 | AH13: 200.4 | AI13: 200.4 | AK13: 200.4 | AL13: 200.4 | AM13: 200.4 | AN13: 200.4
B14: 1b. 종가
A15: price_close_end | C15: 종가(기말) | E15: 95200 | G15: 119500 | H15: 143000 | I15: 115000 | J15: 116000 | L15: 100000 | M15: 131700 | N15: 121200 | O15: 129000 | Q15: 118000 | R15: 155700 | S15: 184600 | T15: 287500 | V15: 279000 | W15: 428500 | X15: 515000 | Y15: 509000 | AA15: 465000 | AB15: 592000 | AC15: 434500 | AD15: 369000
A16: price_high | C16: 종가(최고) | E16: 119500 | G16: 124000 | H16: 161500 | I16: 151000 | J16: 125500 | L16: 119500 | M16: 131900 | N16: 149700 | O16: 135900 | Q16: 128500 | R16: 158500 | S16: 222500 | T16: 299000 | V16: 371500 | W16: 476000 | X16: 535000 | Y16: 640000 | AA16: 652000 | AB16: 765000 | AC16: 622000 | AD16: 435500
A17: price_low | C17: 종가(최저) | E17: 89700 | G17: 92700 | H17: 111000 | I17: 112500 | J17: 101500 | L17: 91500 | M17: 96900 | N17: 118400 | O17: 101500 | Q17: 107900 | R17: 110800 | S17: 147400 | T17: 168900 | V17: 271500 | W17: 275500 | X17: 370000 | Y17: 489500 | AA17: 460500 | AB17: 428000 | AC17: 411500 | AD17: 347000
A18: price_avg | C18: 종가(평균) | E18: 105952.4 | G18: 106772.9 | H18: 131112.9 | I18: 129166.7 | J18: 115338.7 | L18: 105532.3 | M18: 115295.1 | N18: 131943.5 | O18: 117131.7 | Q18: 116886.9 | R18: 131906.7 | S18: 185524.2 | T18: 214772.1 | V18: 307482.8 | W18: 391666.7 | X18: 463830.8 | Y18: 547372.9 | AA18: 571906.8 | AB18: 616245.9 | AC18: 478298.4 | AD18: 395062.5
B20: 2. 추정 드라이버 | C20: 실적 열 = subQ 실현값(수식), 추정 열 = 가정(노란 = 모델값 역산, 연녹 = 3절 스칼라 참조)
A21: drv:판관비 | B21: ratio | C21: 판관비율(/매출) | E21: =IFERROR(subQ!E8/subQ!E5,"") | F21: =IFERROR(subQ!F8/subQ!F5,"") | G21: =IFERROR(subQ!G8/subQ!G5,"") | H21: =IFERROR(subQ!H8/subQ!H5,"") | I21: =IFERROR(subQ!I8/subQ!I5,"") | J21: =IFERROR(subQ!J8/subQ!J5,"") | K21: =IFERROR(subQ!K8/subQ!K5,"") | L21: =IFERROR(subQ!L8/subQ!L5,"") | ... AB21: =IFERROR(subQ!AB8/subQ!AB5,"") | AC21: =$D$55 | AD21: =$D$55 | AE21: =IFERROR(subQ!AE8/subQ!AE5,"") | AF21: =$D$55 | AG21: =$D$55 | AH21: =$D$55 | AI21: =$D$55 | AJ21: =IFERROR(subQ!AJ8/subQ!AJ5,"") | AK21: =$D$55 | AL21: =$D$55 | AM21: =$D$55 | AN21: =$D$55 | AO21: =IFERROR(subQ!AO8/subQ!AO5,"")
A22: drv:외환손익 | B22: abs | C22: 외환손익 (가정, 억원) | E22: =subQ!E13 | F22: =subQ!F13 | G22: =subQ!G13 | H22: =subQ!H13 | I22: =subQ!I13 | J22: =subQ!J13 | K22: =subQ!K13 | L22: =subQ!L13 | ... AB22: =subQ!AB13 | AC22: 0 | AD22: 0 | AE22: =subQ!AE13 | AF22: 0 | AG22: 0 | AH22: 0 | AI22: 0 | AJ22: =subQ!AJ13 | AK22: 0 | AL22: 0 | AM22: 0 | AN22: 0 | AO22: =subQ!AO13
A23: drv:파생상품손익 | B23: abs | C23: 파생상품손익 (가정, 억원) | E23: =subQ!E14 | F23: =subQ!F14 | G23: =subQ!G14 | H23: =subQ!H14 | I23: =subQ!I14 | J23: =subQ!J14 | K23: =subQ!K14 | L23: =subQ!L14 | ... AB23: =subQ!AB14 | AC23: 0 | AD23: 0 | AE23: =subQ!AE14 | AF23: 0 | AG23: 0 | AH23: 0 | AI23: 0 | AJ23: =subQ!AJ14 | AK23: 0 | AL23: 0 | AM23: 0 | AN23: 0 | AO23: =subQ!AO14
A24: drv:기타금융손익 | B24: abs | C24: 기타금융손익 (가정, 억원) | E24: =subQ!E15 | F24: =subQ!F15 | G24: =subQ!G15 | H24: =subQ!H15 | I24: =subQ!I15 | J24: =subQ!J15 | K24: =subQ!K15 | L24: =subQ!L15 | ... AB24: =subQ!AB15 | AC24: 0 | AD24: 0 | AE24: =subQ!AE15 | AF24: 0 | AG24: 0 | AH24: 0 | AI24: 0 | AJ24: =subQ!AJ15 | AK24: 0 | AL24: 0 | AM24: 0 | AN24: 0 | AO24: =subQ!AO15
A25: drv:기타영업외손익 | B25: abs | C25: 기타영업외손익 (가정, 억원) | E25: =subQ!E16 | F25: =subQ!F16 | G25: =subQ!G16 | H25: =subQ!H16 | I25: =subQ!I16 | J25: =subQ!J16 | K25: =subQ!K16 | L25: =subQ!L16 | ... AB25: =subQ!AB16 | AC25: 0 | AD25: 0 | AE25: =subQ!AE16 | AF25: 0 | AG25: 0 | AH25: 0 | AI25: 0 | AJ25: =subQ!AJ16 | AK25: 0 | AL25: 0 | AM25: 0 | AN25: 0 | AO25: =subQ!AO16
A26: drv:지분법손익 | B26: abs | C26: 지분법손익 (가정, 억원) | E26: =subQ!E17 | F26: =subQ!F17 | G26: =subQ!G17 | H26: =subQ!H17 | I26: =subQ!I17 | J26: =subQ!J17 | K26: =subQ!K17 | L26: =subQ!L17 | ... AB26: =subQ!AB17 | AC26: -0.07 | AD26: -0.07 | AE26: =subQ!AE17 | AF26: -0.07 | AG26: -0.07 | AH26: -0.07 | AI26: -0.07 | AJ26: =subQ!AJ17 | AK26: -0.07 | AL26: -0.07 | AM26: -0.07 | AN26: -0.07 | AO26: =subQ!AO17
A27: drv:법인세비용 | B27: tax | C27: 법인세율(/세전) — 법인세 = MAX(세전,0) × 세율 | E27: =IFERROR(subQ!E20/subQ!E19,"") | F27: =IFERROR(subQ!F20/subQ!F19,"") | G27: =IFERROR(subQ!G20/subQ!G19,"") | H27: =IFERROR(subQ!H20/subQ!H19,"") | I27: =IFERROR(subQ!I20/subQ!I19,"") | J27: =IFERROR(subQ!J20/subQ!J19,"") | K27: =IFERROR(subQ!K20/subQ!K19,"") | L27: =IFERROR(subQ!L20/subQ!L19,"") | ... AB27: =IFERROR(subQ!AB20/subQ!AB19,"") | AC27: =$D$54 | AD27: =$D$54 | AE27: =IFERROR(subQ!AE20/subQ!AE19,"") | AF27: =$D$54 | AG27: =$D$54 | AH27: =$D$54 | AI27: =$D$54 | AJ27: =IFERROR(subQ!AJ20/subQ!AJ19,"") | AK27: =$D$54 | AL27: =$D$54 | AM27: =$D$54 | AN27: =$D$54 | AO27: =IFERROR(subQ!AO20/subQ!AO19,"")
A28: drv:지배주주순이익 | B28: ratio | C28: 지배주주 비중(/당기순이익) | E28: =IFERROR(subQ!E22/subQ!E21,"") | F28: =IFERROR(subQ!F22/subQ!F21,"") | G28: =IFERROR(subQ!G22/subQ!G21,"") | H28: =IFERROR(subQ!H22/subQ!H21,"") | I28: =IFERROR(subQ!I22/subQ!I21,"") | J28: =IFERROR(subQ!J22/subQ!J21,"") | K28: =IFERROR(subQ!K22/subQ!K21,"") | L28: =IFERROR(subQ!L22/subQ!L21,"") | ... AB28: =IFERROR(subQ!AB22/subQ!AB21,"") | AC28: =$D$56 | AD28: =$D$56 | AE28: =IFERROR(subQ!AE22/subQ!AE21,"") | AF28: =$D$56 | AG28: =$D$56 | AH28: =$D$56 | AI28: =$D$56 | AJ28: =IFERROR(subQ!AJ22/subQ!AJ21,"") | AK28: =$D$56 | AL28: =$D$56 | AM28: =$D$56 | AN28: =$D$56 | AO28: =IFERROR(subQ!AO22/subQ!AO21,"")
A29: drv:부채총계 | B29: qoq | C29: 부채총계 QoQ | G29: =IFERROR(subQ!G24/subQ!E24-1,"") | H29: =IFERROR(subQ!H24/subQ!G24-1,"") | I29: =IFERROR(subQ!I24/subQ!H24-1,"") | J29: =IFERROR(subQ!J24/subQ!I24-1,"") | L29: =IFERROR(subQ!L24/subQ!J24-1,"") | M29: =IFERROR(subQ!M24/subQ!L24-1,"") | N29: =IFERROR(subQ!N24/subQ!M24-1,"") | O29: =IFERROR(subQ!O24/subQ!N24-1,"") | Q29: =IFERROR(subQ!Q24/subQ!O24-1,"") | R29: =IFERROR(subQ!R24/subQ!Q24-1,"") | S29: =IFERROR(subQ!S24/subQ!R24-1,"") | T29: =IFERROR(subQ!T24/subQ!S24-1,"") | V29: =IFERROR(subQ!V24/subQ!T24-1,"") | W29: =IFERROR(subQ!W24/subQ!V24-1,"") | X29: =IFERROR(subQ!X24/subQ!W24-1,"") | Y29: =IFERROR(subQ!Y24/subQ!X24-1,"") | AA29: =IFERROR(subQ!AA24/subQ!Y24-1,"") | AB29: =IFERROR(subQ!AB24/subQ!AA24-1,"") | AC29: -2e-09 | AD29: 0 | AF29: 0 | AG29: 0 | AH29: 0 | AI29: 0 | AK29: 0 | AL29: 0 | AM29: 0 | AN29: 0
A30: drv:자본총계 | B30: roll | C30: 자본총계 기타변동(배당 등, 억원) | G30: =IFERROR(subQ!E25+subQ!G21-subQ!G25,"") | H30: =IFERROR(subQ!G25+subQ!H21-subQ!H25,"") | I30: =IFERROR(subQ!H25+subQ!I21-subQ!I25,"") | J30: =IFERROR(subQ!I25+subQ!J21-subQ!J25,"") | L30: =IFERROR(subQ!J25+subQ!L21-subQ!L25,"") | M30: =IFERROR(subQ!L25+subQ!M21-subQ!M25,"") | N30: =IFERROR(subQ!M25+subQ!N21-subQ!N25,"") | O30: =IFERROR(subQ!N25+subQ!O21-subQ!O25,"") | Q30: =IFERROR(subQ!O25+subQ!Q21-subQ!Q25,"") | R30: =IFERROR(subQ!Q25+subQ!R21-subQ!R25,"") | S30: =IFERROR(subQ!R25+subQ!S21-subQ!S25,"") | T30: =IFERROR(subQ!S25+subQ!T21-subQ!T25,"") | V30: =IFERROR(subQ!T25+subQ!V21-subQ!V25,"") | W30: =IFERROR(subQ!V25+subQ!W21-subQ!W25,"") | X30: =IFERROR(subQ!W25+subQ!X21-subQ!X25,"") | Y30: =IFERROR(subQ!X25+subQ!Y21-subQ!Y25,"") | AA30: =IFERROR(subQ!Y25+subQ!AA21-subQ!AA25,"") | AB30: =IFERROR(subQ!AA25+subQ!AB21-subQ!AB25,"") | AC30: 0.001846638 | AD30: -0.003953463 | AF30: 0.000615447 | AG30: 5940.2406 | AH30: 0.009846201 | AI30: -0.003687078 | AK30: 0.00723402 | AL30: 5940.251 | AM30: 0.004250544 | AN30: -0.003765865
A31: drv:지배주주지분 | B31: roll | C31: 지배주주지분 기타변동(배당 등, 억원) | G31: =IFERROR(subQ!E26+subQ!G22-subQ!G26,"") | H31: =IFERROR(subQ!G26+subQ!H22-subQ!H26,"") | I31: =IFERROR(subQ!H26+subQ!I22-subQ!I26,"") | J31: =IFERROR(subQ!I26+subQ!J22-subQ!J26,"") | L31: =IFERROR(subQ!J26+subQ!L22-subQ!L26,"") | M31: =IFERROR(subQ!L26+subQ!M22-subQ!M26,"") | N31: =IFERROR(subQ!M26+subQ!N22-subQ!N26,"") | O31: =IFERROR(subQ!N26+subQ!O22-subQ!O26,"") | Q31: =IFERROR(subQ!O26+subQ!Q22-subQ!Q26,"") | R31: =IFERROR(subQ!Q26+subQ!R22-subQ!R26,"") | S31: =IFERROR(subQ!R26+subQ!S22-subQ!S26,"") | T31: =IFERROR(subQ!S26+subQ!T22-subQ!T26,"") | V31: =IFERROR(subQ!T26+subQ!V22-subQ!V26,"") | W31: =IFERROR(subQ!V26+subQ!W22-subQ!W26,"") | X31: =IFERROR(subQ!W26+subQ!X22-subQ!X26,"") | Y31: =IFERROR(subQ!X26+subQ!Y22-subQ!Y26,"") | AA31: =IFERROR(subQ!Y26+subQ!AA22-subQ!AA26,"") | AB31: =IFERROR(subQ!AA26+subQ!AB22-subQ!AB26,"") | AC31: -0.0015741 | AD31: -0.004779296 | AF31: -0.000234528 | AG31: 5940.2497 | AH31: -0.001099846 | AI31: 0.005304503 | AK31: 0.006160329 | AL31: 5940.2499 | AM31: 0.003054234 | AN31: -0.005005766
A32: drv:총차입금 | B32: qoq | C32: 총차입금 QoQ | G32: =IFERROR(subQ!G27/subQ!E27-1,"") | H32: =IFERROR(subQ!H27/subQ!G27-1,"") | I32: =IFERROR(subQ!I27/subQ!H27-1,"") | J32: =IFERROR(subQ!J27/subQ!I27-1,"") | L32: =IFERROR(subQ!L27/subQ!J27-1,"") | M32: =IFERROR(subQ!M27/subQ!L27-1,"") | N32: =IFERROR(subQ!N27/subQ!M27-1,"") | O32: =IFERROR(subQ!O27/subQ!N27-1,"") | Q32: =IFERROR(subQ!Q27/subQ!O27-1,"") | R32: =IFERROR(subQ!R27/subQ!Q27-1,"") | S32: =IFERROR(subQ!S27/subQ!R27-1,"") | T32: =IFERROR(subQ!T27/subQ!S27-1,"") | V32: =IFERROR(subQ!V27/subQ!T27-1,"") | W32: =IFERROR(subQ!W27/subQ!V27-1,"") | X32: =IFERROR(subQ!X27/subQ!W27-1,"") | Y32: =IFERROR(subQ!Y27/subQ!X27-1,"") | AA32: =IFERROR(subQ!AA27/subQ!Y27-1,"") | AB32: =IFERROR(subQ!AB27/subQ!AA27-1,"") | AC32: 8.22e-07 | AD32: 0 | AF32: 0 | AG32: 0 | AH32: 0 | AI32: 0 | AK32: 0 | AL32: 0 | AM32: 0 | AN32: 0
A33: drv:순차입금 | B33: qoq | C33: 순차입금 QoQ | G33: =IFERROR(subQ!G28/subQ!E28-1,"") | H33: =IFERROR(subQ!H28/subQ!G28-1,"") | I33: =IFERROR(subQ!I28/subQ!H28-1,"") | J33: =IFERROR(subQ!J28/subQ!I28-1,"") | L33: =IFERROR(subQ!L28/subQ!J28-1,"") | M33: =IFERROR(subQ!M28/subQ!L28-1,"") | N33: =IFERROR(subQ!N28/subQ!M28-1,"") | O33: =IFERROR(subQ!O28/subQ!N28-1,"") | Q33: =IFERROR(subQ!Q28/subQ!O28-1,"") | R33: =IFERROR(subQ!R28/subQ!Q28-1,"") | S33: =IFERROR(subQ!S28/subQ!R28-1,"") | T33: =IFERROR(subQ!T28/subQ!S28-1,"") | V33: =IFERROR(subQ!V28/subQ!T28-1,"") | W33: =IFERROR(subQ!W28/subQ!V28-1,"") | X33: =IFERROR(subQ!X28/subQ!W28-1,"") | Y33: =IFERROR(subQ!Y28/subQ!X28-1,"") | AA33: =IFERROR(subQ!AA28/subQ!Y28-1,"") | AB33: =IFERROR(subQ!AB28/subQ!AA28-1,"") | AC33: 0.12000928 | AD33: 0.10781562 | AF33: 0.10016767 | AG33: 0.024233599 | AH33: 0.098940854 | AI33: 0.095968948 | AK33: 0.093233113 | AL33: 0.037486219 | AM33: 0.091588291 | AN33: 0.086960903
A34: drv:이자발생자산 | B34: qoq | C34: 이자발생자산 QoQ | G34: =IFERROR(subQ!G29/subQ!E29-1,"") | H34: =IFERROR(subQ!H29/subQ!G29-1,"") | I34: =IFERROR(subQ!I29/subQ!H29-1,"") | J34: =IFERROR(subQ!J29/subQ!I29-1,"") | L34: =IFERROR(subQ!L29/subQ!J29-1,"") | M34: =IFERROR(subQ!M29/subQ!L29-1,"") | N34: =IFERROR(subQ!N29/subQ!M29-1,"") | O34: =IFERROR(subQ!O29/subQ!N29-1,"") | Q34: =IFERROR(subQ!Q29/subQ!O29-1,"") | R34: =IFERROR(subQ!R29/subQ!Q29-1,"") | S34: =IFERROR(subQ!S29/subQ!R29-1,"") | T34: =IFERROR(subQ!T29/subQ!S29-1,"") | V34: =IFERROR(subQ!V29/subQ!T29-1,"") | W34: =IFERROR(subQ!W29/subQ!V29-1,"") | X34: =IFERROR(subQ!X29/subQ!W29-1,"") | Y34: =IFERROR(subQ!Y29/subQ!X29-1,"") | AA34: =IFERROR(subQ!AA29/subQ!Y29-1,"") | AB34: =IFERROR(subQ!AB29/subQ!AA29-1,"") | AC34: 0.11004074 | AD34: 0.099747731 | AF34: 0.093351937 | AG34: 0.022725454 | AH34: 0.092920226 | AI34: 0.090625663 | AK34: 0.088473495 | AL34: 0.03572807 | AM34: 0.087440869 | AN34: 0.083339668
A35: drv:현금및현금성자산 | B35: qoq | C35: 현금및현금성자산 QoQ | G35: =IFERROR(subQ!G30/subQ!E30-1,"") | H35: =IFERROR(subQ!H30/subQ!G30-1,"") | I35: =IFERROR(subQ!I30/subQ!H30-1,"") | J35: =IFERROR(subQ!J30/subQ!I30-1,"") | L35: =IFERROR(subQ!L30/subQ!J30-1,"") | M35: =IFERROR(subQ!M30/subQ!L30-1,"") | N35: =IFERROR(subQ!N30/subQ!M30-1,"") | O35: =IFERROR(subQ!O30/subQ!N30-1,"") | Q35: =IFERROR(subQ!Q30/subQ!O30-1,"") | R35: =IFERROR(subQ!R30/subQ!Q30-1,"") | S35: =IFERROR(subQ!S30/subQ!R30-1,"") | T35: =IFERROR(subQ!T30/subQ!S30-1,"") | V35: =IFERROR(subQ!V30/subQ!T30-1,"") | W35: =IFERROR(subQ!W30/subQ!V30-1,"") | X35: =IFERROR(subQ!X30/subQ!W30-1,"") | Y35: =IFERROR(subQ!Y30/subQ!X30-1,"") | AA35: =IFERROR(subQ!AA30/subQ!Y30-1,"") | AB35: =IFERROR(subQ!AB30/subQ!AA30-1,"")
A36: drv:CAPEX | B36: yoy | C36: CAPEX YoY | J36: =IFERROR(subQ!J31/subQ!E31-1,"") | L36: =IFERROR(subQ!L31/subQ!G31-1,"") | M36: =IFERROR(subQ!M31/subQ!H31-1,"") | N36: =IFERROR(subQ!N31/subQ!I31-1,"") | O36: =IFERROR(subQ!O31/subQ!J31-1,"") | Q36: =IFERROR(subQ!Q31/subQ!L31-1,"") | R36: =IFERROR(subQ!R31/subQ!M31-1,"") | S36: =IFERROR(subQ!S31/subQ!N31-1,"") | T36: =IFERROR(subQ!T31/subQ!O31-1,"") | V36: =IFERROR(subQ!V31/subQ!Q31-1,"") | W36: =IFERROR(subQ!W31/subQ!R31-1,"") | X36: =IFERROR(subQ!X31/subQ!S31-1,"") | Y36: =IFERROR(subQ!Y31/subQ!T31-1,"") | AA36: =IFERROR(subQ!AA31/subQ!V31-1,"") | AB36: =IFERROR(subQ!AB31/subQ!W31-1,"") | AC36: -0.060772002 | AD36: 0.022962206 | AF36: -0.021958407 | AG36: 0.027331156 | AH36: 0 | AI36: 0 | AK36: 0 | AL36: 0 | AM36: 0 | AN36: 0
A37: drv:영업활동현금흐름 | B37: yoy | C37: 영업활동현금흐름 YoY | J37: =IFERROR(subQ!J32/subQ!E32-1,"") | L37: =IFERROR(subQ!L32/subQ!G32-1,"") | M37: =IFERROR(subQ!M32/subQ!H32-1,"") | N37: =IFERROR(subQ!N32/subQ!I32-1,"") | O37: =IFERROR(subQ!O32/subQ!J32-1,"") | Q37: =IFERROR(subQ!Q32/subQ!L32-1,"") | R37: =IFERROR(subQ!R32/subQ!M32-1,"") | S37: =IFERROR(subQ!S32/subQ!N32-1,"") | T37: =IFERROR(subQ!T32/subQ!O32-1,"") | V37: =IFERROR(subQ!V32/subQ!Q32-1,"") | W37: =IFERROR(subQ!W32/subQ!R32-1,"") | X37: =IFERROR(subQ!X32/subQ!S32-1,"") | Y37: =IFERROR(subQ!Y32/subQ!T32-1,"") | AA37: =IFERROR(subQ!AA32/subQ!V32-1,"") | AB37: =IFERROR(subQ!AB32/subQ!W32-1,"")
A38: drv:주식수 | B38: qoq | C38: 주식수 QoQ | G38: =IFERROR(subQ!G33/subQ!E33-1,"") | H38: =IFERROR(subQ!H33/subQ!G33-1,"") | I38: =IFERROR(subQ!I33/subQ!H33-1,"") | J38: =IFERROR(subQ!J33/subQ!I33-1,"") | L38: =IFERROR(subQ!L33/subQ!J33-1,"") | M38: =IFERROR(subQ!M33/subQ!L33-1,"") | N38: =IFERROR(subQ!N33/subQ!M33-1,"") | O38: =IFERROR(subQ!O33/subQ!N33-1,"") | Q38: =IFERROR(subQ!Q33/subQ!O33-1,"") | R38: =IFERROR(subQ!R33/subQ!Q33-1,"") | S38: =IFERROR(subQ!S33/subQ!R33-1,"") | T38: =IFERROR(subQ!T33/subQ!S33-1,"") | V38: =IFERROR(subQ!V33/subQ!T33-1,"") | W38: =IFERROR(subQ!W33/subQ!V33-1,"") | X38: =IFERROR(subQ!X33/subQ!W33-1,"") | Y38: =IFERROR(subQ!Y33/subQ!X33-1,"") | AA38: =IFERROR(subQ!AA33/subQ!Y33-1,"") | AB38: =IFERROR(subQ!AB33/subQ!AA33-1,"") | AC38: 0 | AD38: 0 | AF38: 0 | AG38: 0 | AH38: 0 | AI38: 0 | AK38: 0 | AL38: 0 | AM38: 0 | AN38: 0
A39: drv:DPS | B39: abs | C39: DPS (가정, 원) | E39: =subQ!E36 | F39: =subQ!F36 | G39: =subQ!G36 | H39: =subQ!H36 | I39: =subQ!I36 | J39: =subQ!J36 | K39: =subQ!K36 | L39: =subQ!L36 | ... AB39: =subQ!AB36 | AD39: 5661 | AE39: =subQ!AE36 | AI39: 5661 | AJ39: =subQ!AJ36 | AN39: 5661 | AO39: =subQ!AO36
A40: drv:매출조선 | B40: sls_link | C40: 원장 밖 잔고 소진(억원) — 매출조선 = SLS 원화/100 + 이 행 + 매출조선신규 | N40: =IFERROR(subQ!N39-SLS!E124/100,"") | O40: =IFERROR(subQ!O39-SLS!F124/100,"") | Q40: =IFERROR(subQ!Q39-SLS!G124/100,"") | R40: =IFERROR(subQ!R39-SLS!H124/100,"") | S40: =IFERROR(subQ!S39-SLS!I124/100,"") | T40: =IFERROR(subQ!T39-SLS!J124/100,"") | V40: =IFERROR(subQ!V39-SLS!K124/100,"") | W40: =IFERROR(subQ!W39-SLS!L124/100,"") | X40: =IFERROR(subQ!X39-SLS!M124/100,"") | Y40: =IFERROR(subQ!Y39-SLS!N124/100,"") | AA40: =IFERROR(subQ!AA39-SLS!O124/100,"") | AB40: =IFERROR(subQ!AB39-SLS!P124/100,"") | AC40: 35378.05 | AD40: 35827.501 | AF40: 35805.243 | AG40: 35816.094 | AH40: 35827.016 | AI40: 35827.091 | AK40: 35816.105 | AL40: 35816.106 | AM40: 35827.09 | AN40: 35827.15
A41: drv:매출조선신규 | B41: abs | C41: 매출조선신규 (forecast_panel base · 공시 상계 신규수주 매출, 억원 — 가정) | E41: =subQ!E40 | F41: =subQ!F40 | G41: =subQ!G40 | H41: =subQ!H40 | I41: =subQ!I40 | J41: =subQ!J40 | K41: =subQ!K40 | L41: =subQ!L40 | ... AB41: =subQ!AB40 | AC41: 0 | AD41: 713.92 | AE41: =subQ!AE40 | AF41: 2954 | AG41: 6661.68 | AH41: 11468.92 | AI41: 17007.63 | AJ41: =subQ!AJ40 | AK41: 22909.76 | AL41: 28807.24 | AM41: 34331.99 | AN41: 39115.96 | AO41: =subQ!AO40
A42: drv:OP조선 | B42: ratio | C42: OP조선 마진(/매출조선) | E42: =IFERROR(subQ!E41/subQ!E39,"") | F42: =IFERROR(subQ!F41/subQ!F39,"") | G42: =IFERROR(subQ!G41/subQ!G39,"") | H42: =IFERROR(subQ!H41/subQ!H39,"") | I42: =IFERROR(subQ!I41/subQ!I39,"") | J42: =IFERROR(subQ!J41/subQ!J39,"") | K42: =IFERROR(subQ!K41/subQ!K39,"") | L42: =IFERROR(subQ!L41/subQ!L39,"") | ... AB42: =IFERROR(subQ!AB41/subQ!AB39,"") | AC42: 0.14060434 | AD42: 0.14090423 | AE42: =IFERROR(subQ!AE41/subQ!AE39,"") | AF42: 0.14090438 | AG42: 0.14093272 | AH42: 0.14101495 | AI42: 0.14107495 | AJ42: =IFERROR(subQ!AJ41/subQ!AJ39,"") | AK42: 0.1411349 | AL42: 0.14119495 | AM42: 0.1413466 | AN42: 0.14156767 | AO42: =IFERROR(subQ!AO41/subQ!AO39,"")
A43: drv:매출기타 | B43: yoy | C43: 매출기타 YoY | J43: =IFERROR(subQ!J43/subQ!E43-1,"") | L43: =IFERROR(subQ!L43/subQ!G43-1,"") | M43: =IFERROR(subQ!M43/subQ!H43-1,"") | N43: =IFERROR(subQ!N43/subQ!I43-1,"") | O43: =IFERROR(subQ!O43/subQ!J43-1,"") | Q43: =IFERROR(subQ!Q43/subQ!L43-1,"") | R43: =IFERROR(subQ!R43/subQ!M43-1,"") | S43: =IFERROR(subQ!S43/subQ!N43-1,"") | T43: =IFERROR(subQ!T43/subQ!O43-1,"") | V43: =IFERROR(subQ!V43/subQ!Q43-1,"") | W43: =IFERROR(subQ!W43/subQ!R43-1,"") | X43: =IFERROR(subQ!X43/subQ!S43-1,"") | Y43: =IFERROR(subQ!Y43/subQ!T43-1,"") | AA43: =IFERROR(subQ!AA43/subQ!V43-1,"") | AB43: =IFERROR(subQ!AB43/subQ!W43-1,"") | AC43: -0.13369879 | AD43: 0.13704943 | AF43: 0.043469212 | AG43: -0.039993324 | AH43: 0 | AI43: 0 | AK43: 0 | AL43: 0 | AM43: 0 | AN43: 0
A44: drv:OP기타 | B44: ratio | C44: OP기타 마진(/매출기타) | E44: =IFERROR(subQ!E44/subQ!E43,"") | F44: =IFERROR(subQ!F44/subQ!F43,"") | G44: =IFERROR(subQ!G44/subQ!G43,"") | H44: =IFERROR(subQ!H44/subQ!H43,"") | I44: =IFERROR(subQ!I44/subQ!I43,"") | J44: =IFERROR(subQ!J44/subQ!J43,"") | K44: =IFERROR(subQ!K44/subQ!K43,"") | L44: =IFERROR(subQ!L44/subQ!L43,"") | ... AB44: =IFERROR(subQ!AB44/subQ!AB43,"") | AC44: 0.14060429 | AD44: 0.14090399 | AE44: =IFERROR(subQ!AE44/subQ!AE43,"") | AF44: 0.14090399 | AG44: 0.14093278 | AH44: 0.14101491 | AI44: 0.14107463 | AJ44: =IFERROR(subQ!AJ44/subQ!AJ43,"") | AK44: 0.14113543 | AL44: 0.14119515 | AM44: 0.1413466 | AN44: 0.14156738 | AO44: =IFERROR(subQ!AO44/subQ!AO43,"")
B46: 3. 밸류에이션·스칼라 | C46: 노란 셀 = 가정. '연결' 표시는 추정 전 분기 수식이 이 셀을 참조한다는 뜻
A47: sc:종가 | C47: 종가 | D47: 369000 | E47: 원 — 네이버 정규장 종가(aik 확정종가 대조 · aik 365,500원)
A48: sc:기준일 | C48: 기준일 | D48: 20261014 | E48: 종가 기준일
A49: sc:COE | C49: COE | D49: 0.09 | E49: 자기자본비용(가정) — TP 적정 PBR = ROE/COE
A50: sc:PER_lo | C50: PER_lo | D50: 10 | E50: PER 밴드 하단(배) — sector_default(레퍼런스 TP_PE PB 예시 10/15/20배; 과거 PER 중위 36.3배가 캡 5~30 밖 — 턴어라운드 초기 TTM EPS 왜곡)
A51: sc:PER_mid | C51: PER_mid | D51: 15 | E51: PER 밴드 중단(배)
A52: sc:PER_hi | C52: PER_hi | D52: 20 | E52: PER 밴드 상단(배)
A53: sc:EPS_Y1가중 | C53: EPS_Y1가중 | D53: 0.5 | E53: 12M fwd EPS = FY(last_actual연도)E × w + FY+1E × (1−w) — 기준 분기 2Q 이면 0.5(가정)
A54: sc:세율 | C54: 세율 | D54: 0.2449402 | E54: 연결 — 법인세 = MAX(세전,0) × 세율(역산, 재현 오차 ≤ 0.05억 · 모델 assumptions 0.2449) · 최근 12분기 유효세율 24.5%(5~27% 안 — 그대로)
A55: sc:판관비율 | C55: 판관비율 | D55: 0.048759368 | E55: 연결 — 판관비 = 매출액 × 판관비율(역산, 재현 오차 ≤ 0.05억 · 모델 assumptions 0.0488)
A56: sc:지배주주비중 | C56: 지배주주비중 | D56: 0.99999989 | E56: 연결 — 지배주주순이익 = 당기순이익 × 비중(역산, 재현 오차 ≤ 0.05억)
A57: sc:이자율_자산 | C57: 이자율_자산 | D57: 0.024728037 | E57: 연결 — 이자손익 = (전분기 이자발생자산 × 자산이자율 − 전분기 총차입금 × 부채이자율)/4(역산, 재현 오차 ≤ 0.05억 · 모델 assumptions 0.0247)
A58: sc:이자율_부채 | C58: 이자율_부채 | D58: 0.13901784 | E58: 연결 — 같은 수식의 부채 쪽(총차입금 행이 없으면 0)(역산, 재현 오차 ≤ 0.05억 · 모델 assumptions 0.139)
A59: sc:배당성향 | C59: 배당성향 | D59: 0.4197 | E59: 배당성향(참고 — 모델은 직전 DPS 유지·Q2 지급 가정)
A60: sc:외화순노출_백만$ | C60: 외화순노출_백만$ | D60: -67.18 | E60: 외화 순노출 × Δ기말환율 (외화 시트 방식) — 연결: subQ 환관련손익 = 노출 × Δ원/달러(기말)/100
A61: sc:헤지비율 | C61: 헤지비율 | D61: 0.7 | E61: SLS 원화 = Σ 스케줄 × (헤지비율 × 헤지환율 + (1−헤지비율) × 건조시점 환율[원/달러(평균)]) — estimate · 약정환율 미공시 → HEDGE 70% 가정(레퍼런스 SLS 시트 HEDGE 행은 미포 65%·삼성重 100% — 그 사이에 둔 설정값). hedge_rate 는 계약별 수주시점 환율로 대체
A62: sc:헤지환율_약정 | C62: 헤지환율_약정 | E62: 정기보고서 평균 약정환율(measured) — 비어 있으면 계약별 수주시점 환율(fx_at_sign)을 쓴다

Sheet BS연결
B1: (백만원) | C1: 이름: BS연결H | E1: 4Q21 | F1: 2021 | G1: 1Q22 | H1: 2Q22 | I1: 3Q22 | J1: 4Q22 | K1: 2022 | L1: 1Q23 | M1: 2Q23 | N1: 3Q23 | O1: 4Q23 | P1: 2023 | Q1: 1Q24 | R1: 2Q24 | S1: 3Q24 | T1: 4Q24 | U1: 2024 | V1: 1Q25 | W1: 2Q25 | X1: 3Q25 | Y1: 4Q25 | Z1: 2025 | AA1: 1Q26 | AB1: 2Q26 | AC1: 3Q26 | AD1: 4Q26 | AE1: 2026 | AF1: 1Q27 | AG1: 2Q27 | AH1: 3Q27 | AI1: 4Q27 | AJ1: 2027 | AK1: 1Q28 | AL1: 2Q28 | AM1: 3Q28 | AN1: 4Q28 | AO1: 2028
B2: 연결 | D2: fin json(kship_fin.py)
B3: HD현대중공업(연) | C3: UPDATE: 26-10-14 | E3: 1 | F3: 2 | G3: 3 | H3: 4 | I3: 5 | J3: 6 | K3: 7 | L3: 8 | M3: 9 | N3: 10 | O3: 11 | P3: 12 | Q3: 13 | R3: 14 | S3: 15 | T3: 16 | U3: 17 | V3: 18 | W3: 19 | X3: 20 | Y3: 21 | Z3: 22 | AA3: 23 | AB3: 24 | AC3: 25 | AD3: 26 | AE3: 27 | AF3: 28 | AG3: 29 | AH3: 30 | AI3: 31 | AJ3: 32 | AK3: 33 | AL3: 34 | AM3: 35 | AN3: 36 | AO3: 37
B4: Account Code | C4: AccountNAME | E4: 2021.12 | F4: 2021.12A | G4: 2022.03 | H4: 2022.06 | I4: 2022.09 | J4: 2022.12 | K4: 2022.12A | L4: 2023.03 | M4: 2023.06 | N4: 2023.09 | O4: 2023.12 | P4: 2023.12A | Q4: 2024.03 | R4: 2024.06 | S4: 2024.09 | T4: 2024.12 | U4: 2024.12A | V4: 2025.03 | W4: 2025.06 | X4: 2025.09 | Y4: 2025.12 | Z4: 2025.12A | AA4: 2026.03 | AB4: 2026.06 | AC4: 2026.09 | AD4: 2026.12 | AE4: 2026.12A | AF4: 2027.03 | AG4: 2027.06 | AH4: 2027.09 | AI4: 2027.12 | AJ4: 2027.12A | AK4: 2028.03 | AL4: 2028.06 | AM4: 2028.09 | AN4: 2028.12 | AO4: 2028.12A
A5: 1 | C5: 유동자산 | E5: 7886064.9 | F5: 7886064.9 | G5: 7731369.7 | H5: 8371718.1 | I5: 9009512.3 | J5: 8000865.9 | K5: 8000865.9 | L5: 8644922.8 | M5: 8900996.9 | N5: 9459114.2 | O5: 8799684.1 | P5: 8799684.1 | Q5: 8984373.7 | R5: 9085824.7 | S5: 8505588.6 | T5: 10403122 | U5: 10403122 | V5: 11956276 | W5: 11299361 | X5: 12293516 | Y5: 14980009 | Z5: 14980009 | AA5: 16185175 | AB5: 17952609
A6: 1 | C6: 현금및현금성자산 | E6: 2137391.4 | F6: 2137391.4 | G6: 1778545.2 | H6: 1647639.9 | I6: 1514079.8 | J6: 744148.12 | K6: 744148.12 | L6: 844743.65 | M6: 763327.15 | N6: 1014008.4 | O6: 928043.11 | P6: 928043.11 | Q6: 728591.78 | R6: 770024.38 | S6: 268526.5 | T6: 1257867.1 | U6: 1257867.1 | V6: 2736801.9 | W6: 2354964.6 | X6: 2355097.9 | Y6: 1869917.7 | Z6: 1869917.7 | AA6: 2975455.8 | AB6: 4550913.2
A7: 1 | C7: 단기금융상품 | E7: 151000 | F7: 151000 | G7: 151000 | H7: 181017.42 | I7: 151026.42 | J7: 161000 | K7: 161000 | L7: 161000 | M7: 131000 | N7: 131000 | O7: 131000 | P7: 131000 | Q7: 131000.01 | R7: 131000 | S7: 131000 | T7: 131000 | U7: 131000 | V7: 131000 | W7: 481000 | X7: 1671000 | Y7: 1702500 | Z7: 1702500 | AA7: 1284000 | AB7: 922000
A8: 1 | C8: 단기금융자산 | E8: 259137.32 | F8: 259137.32 | G8: 314512.06 | H8: 548823.98 | I8: 974210.98 | J8: 485992.28 | K8: 485992.28 | L8: 547844.55 | M8: 526571.39 | N8: 608327.41 | O8: 432686.75 | P8: 432686.75 | Q8: 559683.45 | R8: 673414.52 | S8: 462191.31 | T8: 954876.65 | U8: 954876.65 | V8: 804978.33 | W8: 771947.75 | X8: 2012261.4 | Y8: 2211181.1 | Z8: 2211181.1 | AA8: 2212931.5 | AB8: 2031825.8
A9: 1 | C9: 매출채권및기타채권 | E9: 1032431.2 | F9: 1032431.2 | G9: 873375.34 | H9: 1534385.6 | I9: 1091182.4 | J9: 1135986.6 | K9: 1135986.6 | L9: 1416503.2 | M9: 1391656.7 | N9: 1409062.3 | O9: 1386425.1 | P9: 1386425.1 | Q9: 1380041 | R9: 1552926.9 | S9: 1583631.6 | T9: 1659563 | U9: 1659563 | V9: 1872571.4 | W9: 1713157.5 | X9: 1702043.8 | Y9: 1713176.6 | Z9: 1713176.6 | AA9: 1629663.1 | AB9: 1773669.7
A10: 1 | C10: 계약자산 | E10: 2836711.4 | F10: 2836711.4 | G10: 3073532.6 | H10: 2863561.3 | I10: 3254217.4 | J10: 3180079.7 | K10: 3180079.7 | L10: 3232105.7 | M10: 3494267.8 | N10: 3647358.6 | O10: 3458668.9 | P10: 3458668.9 | Q10: 3515123.4 | R10: 3396531 | S10: 3397567.1 | T10: 3573015.7 | U10: 3573015.7 | V10: 3273711.1 | W10: 3118247.5 | X10: 2988952.8 | Y10: 5131962.9 | Z10: 5131962.9 | AA10: 5344888 | AB10: 5656017.1
A11: 1 | C11: 재고자산 | E11: 898666.74 | F11: 898666.74 | G11: 955114.32 | H11: 1011856.2 | I11: 1289281.2 | J11: 1377137.5 | K11: 1377137.5 | L11: 1453476.1 | M11: 1433760.2 | N11: 1433016.4 | O11: 1309807.3 | P11: 1309807.3 | Q11: 1517713.4 | R11: 1447893.5 | S11: 1544622.2 | T11: 1510905.6 | U11: 1510905.6 | V11: 1662745.5 | W11: 1711077.7 | X11: 1764922.8 | Y11: 2016750.9 | Z11: 2016750.9 | AA11: 1981798.2 | AB11: 2020764.5
A12: 1 | C12: 유동파생상품자산 | E12: 11368.27 | F12: 11368.27 | G12: 39634.66 | H12: 69702.84 | I12: 131045.43 | J12: 106450.66 | K12: 106450.66 | L12: 102084.18 | M12: 104796.3 | N12: 99587.15 | O12: 104488.45 | P12: 104488.45 | Q12: 24628.9 | R12: 3770.28 | S12: 72075.84 | T12: 927.29 | U12: 927.29 | V12: 2644.75 | W12: 66289.1 | X12: 11211.79 | Y12: 8611.82 | Z12: 8611.82 | AA12: 88344.33 | AB12: 99217.49
A13: 1 | C13: 유동확정계약자산 | E13: 96769.05 | F13: 96769.05 | G13: 123877.4 | H13: 298103.72 | I13: 692139.13 | J13: 218541.62 | K13: 218541.62 | L13: 284760.37 | M13: 290775.09 | N13: 377740.26 | O13: 197198.3 | P13: 197198.3 | Q13: 404054.54 | R13: 538644.24 | S13: 259115.47 | T13: 822949.36 | U13: 822949.36 | V13: 671333.58 | W13: 224658.65 | X13: 330049.56 | Y13: 500069.33 | Z13: 500069.33 | AA13: 840587.19 | AB13: 1010608.3
A14: 1 | C14: 당기법인세자산(선급법인세) | E14: 2447.05 | F14: 2447.05 | G14: 3543.2 | H14: 2225.52 | I14: 3567.84 | J14: 5192.93 | K14: 5192.93 | L14: 6561.62 | M14: 2724.72 | N14: 3872.75 | O14: 5481.78 | P14: 5481.78 | Q14: 7337.46 | R14: 140.7 | S14: 66.71 | T14: 45.45 | U14: 45.45 | V14: 71.56 | W14: 0 | X14: 0 | Y14: 0 | Z14: 0
A15: 1 | C15: 매각예정비유동자산및처분자산 | E15: 4719.32 | F15: 4719.32 | O15: 0 | P15: 0
A16: 1 | C16: 기타유동자산 | E16: 714560.46 | F16: 714560.46 | G16: 732746.95 | H16: 763225.7 | I16: 882972.75 | J16: 1072328.8 | K16: 1072328.8 | L16: 1143688 | M16: 1288689.1 | N16: 1343468.3 | O16: 1278571.2 | P16: 1278571.2 | Q16: 1275883.1 | R16: 1244893.7 | S16: 1248983.2 | T16: 1446848.4 | U16: 1446848.4 | V16: 1605395.9 | W16: 1629966.3 | X16: 1470237.5 | Y16: 2037020.3 | Z16: 2037020.3 | AA16: 2040438 | AB16: 1919419.1
A17: 1 | C17: 비유동자산 | E17: 7192606.6 | F17: 7192606.6 | G17: 7326280.2 | H17: 7853155.6 | I17: 8860497.6 | J17: 8288532.1 | K17: 8288532.1 | L17: 8338649.2 | M17: 8340330.3 | N17: 8493865.6 | O17: 8333934 | P17: 8333934 | Q17: 8442535.2 | R17: 8612612.7 | S17: 8350275.5 | T17: 8987824.9 | U17: 8987824.9 | V17: 8948270.4 | W17: 8442078.2 | X17: 8500096.6 | Y17: 11183035 | Z17: 11183035 | AA17: 11392013 | AB17: 11419496
A18: 1 | C18: 종속기업및관계기업투자 | E18: 2789.84 | F18: 2789.84 | G18: 2691.61 | H18: 2502.7 | I18: 2374.96 | J18: 1345.76 | K18: 1345.76 | L18: 1245.92 | M18: 1144.92 | N18: 1057.93 | O18: 1331.63 | P18: 1331.63 | Q18: 1191.87 | R18: 1061.4 | S18: 933.23 | T18: 1132.87 | U18: 1132.87 | V18: 1030.49 | W18: 936.91 | X18: 0 | Y18: 305260.99 | Z18: 305260.99 | AA18: 322053.8 | AB18: 328762.4
A19: 1 | C19: 투자자산 | E19: 201161.17 | F19: 201161.17 | G19: 199975.28 | H19: 604415.13 | I19: 1474644.8 | J19: 494994.5 | K19: 494994.5 | L19: 469291.6 | M19: 399784.34 | N19: 483788.98 | O19: 308240.49 | P19: 308240.49 | Q19: 392144.48 | R19: 556170.77 | S19: 274295.41 | T19: 1070170.8 | U19: 1070170.8 | V19: 1070020.3 | W19: 438371.68 | X19: 590583 | Y19: 1214175.2 | Z19: 1214175.2 | AA19: 1691578.7 | AB19: 1722652.1
A20: 1 | C20: 장기금융자산 | E20: 9560.27 | F20: 9560.27 | G20: 9560.27 | H20: 9554.27 | I20: 9554.27 | J20: 9554.27 | K20: 9554.27 | L20: 9554.27 | M20: 10554.27 | N20: 10554.27 | O20: 10562.23 | P20: 10562.23 | Q20: 10562.23 | R20: 10562.23 | S20: 10562.23 | T20: 10562.23 | U20: 10562.23 | V20: 10562.23 | W20: 10562.23 | X20: 10562.23 | Y20: 25480.06 | Z20: 25480.06 | AA20: 25494.18 | AB20: 25509.37
A21: 1 | C21: 장기매출채권및기타채권 | E21: 38942.19 | F21: 38942.19 | G21: 47787.87 | H21: 97432.15 | I21: 168877.73 | J21: 176766.79 | K21: 176766.79 | L21: 205534.06 | M21: 199004.31 | N21: 216154.11 | O21: 168216.13 | P21: 168216.13 | Q21: 176985.59 | R21: 161036.32 | S21: 137038.47 | T21: 125839.47 | U21: 125839.47 | V21: 100074.38 | W21: 89806.83 | X21: 83283.23 | Y21: 92825.89 | Z21: 92825.89 | AA21: 91716.34 | AB21: 94035.67
A22: 1 | C22: 투자부동산 | E22: 4108.68 | F22: 4108.68 | G22: 1486.97 | H22: 1477.15 | I22: 1467.33 | J22: 1457.52 | K22: 1457.52 | L22: 1447.7 | M22: 1437.88 | N22: 1428.07 | O22: 1418.25 | P22: 1418.25 | Q22: 1408.43 | R22: 1398.61 | S22: 1388.8 | T22: 1378.98 | U22: 1378.98 | V22: 1369.16 | W22: 1359.35 | X22: 1349.53 | Y22: 1339.71 | Z22: 1339.71 | AA22: 1329.89 | AB22: 1320.08
A23: 1 | C23: 유형자산 | E23: 5986254.8 | F23: 5986254.8 | G23: 6034621.2 | H23: 6063618.4 | I23: 6155308.9 | J23: 6237402.6 | K23: 6237402.6 | L23: 6285258.8 | M23: 6345666.1 | N23: 6402169.2 | O23: 6452067.7 | P23: 6452067.7 | Q23: 6476802.9 | R23: 6519937.6 | S23: 6566633.3 | T23: 6609789 | U23: 6609789 | V23: 6709772.4 | W23: 6969670.6 | X23: 7020680.7 | Y23: 8780697.1 | Z23: 8780697.1 | AA23: 8778998.4 | AB23: 8853605.5
A24: 1 | C24: 무형자산 | E24: 79457.82 | F24: 79457.82 | G24: 80867.62 | H24: 82648.44 | I24: 89452.56 | J24: 100465.28 | K24: 100465.28 | L24: 104102.2 | M24: 107161.67 | N24: 111859.43 | O24: 108419.95 | P24: 108419.95 | Q24: 111949.57 | R24: 115445.26 | S24: 118152.46 | T24: 128126.18 | U24: 128126.18 | V24: 127920.59 | W24: 133293.01 | X24: 127612.81 | Y24: 161134.67 | Z24: 161134.67 | AA24: 160918.55 | AB24: 161245.31
A25: 1 | C25: 사용권자산 | E25: 17906.01 | F25: 17906.01 | G25: 21299.24 | H25: 22944.07 | I25: 22153.53 | J25: 43390.37 | K25: 43390.37 | L25: 41511.66 | M25: 41047.61 | N25: 38281.29 | O25: 37417.51 | P25: 37417.51 | Q25: 37699.22 | R25: 35477.32 | S25: 33064.2 | T25: 31509.95 | U25: 31509.95 | V25: 28723.11 | W25: 25667.03 | X25: 25221.9 | Y25: 34922.12 | Z25: 34922.12 | AA25: 36259.92 | AB25: 32815.06
A26: 1 | C26: 기타비유동자산 | E26: 45026.2 | F26: 45026.2 | G26: 73425.54 | H26: 89183.99 | I26: 76374 | J26: 383826.18 | K26: 383826.18 | L26: 371677.17 | M26: 392593.78 | N26: 380910.02 | O26: 372204.41 | P26: 372204.41 | Q26: 360369.53 | R26: 378525.06 | S26: 377579.69 | T26: 243632.3 | U26: 243632.3 | V26: 206745.12 | W26: 185502.49 | X26: 166110.41 | Y26: 461064.31 | Z26: 461064.31 | AA26: 441039.99 | AB26: 414643.67
A27: 1 | C27: 비유동파생상품자산 | E27: 43123.04 | F27: 43123.04 | G27: 59450.95 | H27: 89605.37 | I27: 168106.53 | J27: 293924.05 | K27: 293924.05 | L27: 138341.71 | M27: 158160.86 | N27: 100114.82 | O27: 191895.22 | P27: 191895.22 | Q27: 74200.08 | R27: 52575.75 | S27: 103871.68 | T27: 64055.7 | U27: 64055.7 | V27: 66259.55 | W27: 216190.71 | X27: 90721.64 | Y27: 81469.69 | Z27: 81469.69 | AA27: 2366.41 | AB27: 7453.98
... A59: 1 | C59: 이자발생자산 | E59: 2406089 | F59: 2406089 | G59: 2102617.6 | H59: 2206018.1 | I59: 2497845 | J59: 1239694.7 | K59: 1239694.7 | L59: 1402142.5 | M59: 1300452.8 | N59: 1632890.1 | O59: 1371292.1 | P59: 1371292.1 | Q59: 1298837.5 | R59: 1454001.1 | S59: 741280.04 | T59: 2223306 | U59: 2223306 | V59: 3552342.5 | W59: 3137474.6 | X59: 4377921.5 | Y59: 4106578.9 | Z59: 4106578.9 | AA59: 5213881.5 | AB59: 6608248.4
A60: 1 | C60: 사채 | E60: 536292.31 | F60: 536292.31 | G60: 844823 | H60: 885946 | I60: 956970 | J60: 873294 | K60: 873294 | L60: 391140 | M60: 643175 | N60: 652871
A61: 1 | C61: 유동성장기부채 | E61: 845229.83 | F61: 845229.83 | G61: 1048626.7 | H61: 1514784 | I61: 1577253.8 | J61: 1226167.2 | K61: 1226167.2 | L61: 1143453.2 | M61: 666452.81 | N61: 845029.23 | T61: 371613.31 | U61: 371613.31 | V61: 386666.87 | W61: 332765.09 | X61: 255898.54 | AA61: 599939.45 | AB61: 520403.57
A62: 1 | C62: 비지배주주지분 | L62: 43.5 | M62: 38.62 | N62: 0.63 | O62: 0.23 | P62: 0.23 | Q62: -0.03 | R62: 0.24 | S62: 0.55 | T62: 0.55 | U62: 0.55 | V62: 0.38 | W62: 0.34 | X62: 0.18 | Y62: 0.14 | Z62: 0.14 | AA62: 0.18 | AB62: 0.25
A63: 1 | C63: 당기법인세부채(미지급법인세) | M63: 14.5 | N63: 21.75 | Q63: 4.95 | R63: 307.18 | S63: 9831.55 | T63: 13795.56 | U63: 13795.56 | V63: 24577.83 | W63: 29960.97 | X63: 29065.36 | Y63: 39130.11 | Z63: 39130.11 | AA63: 58633.97 | AB63: 314038.78
A64: 1 | C64: 단기금융부채(face) | O64: 1560030.7 | P64: 1560030.7 | Q64: 1444122.4 | R64: 687243.41 | S64: 655904.62 | Y64: 156966.8 | Z64: 156966.8
A65: 1 | C65: 장기금융부채(face) | O65: 1568942.8 | P65: 1568942.8 | Q65: 1335593.8 | R65: 1215680.3 | S65: 809134.19 | T65: 751605.74 | U65: 751605.74 | V65: 685730.58 | W65: 464790.16 | X65: 478555.37 | Y65: 488384.39 | Z65: 488384.39 | AA65: 0 | AB65: 0
A66: 1 | C66: 이연법인세부채 | Y66: 755.27 | Z66: 755.27 | AA66: 755.27 | AB66: 755.27
A67: 1 | C67: 매출액(수익) | E67: 2475866.7 | G67: 2001636.5 | H67: 2166032.4 | I67: 2203563.7 | J67: 2674247.9 | K67: 9045480.5 | L67: 2632890.3 | M67: 3064397.8 | N67: 2853526.4 | O67: 3413111.5 | P67: 11963926 | Q67: 2987745 | R67: 3883982.5 | S67: 3609175.7 | T67: 4005550.3 | U67: 14486454 | V67: 3822515.7 | W67: 4147124.8 | X67: 4417898.2 | Y67: 5193094.5 | Z67: 17580633 | AA67: 5916331.8 | AB67: 6332155
A68: 1 | C68: 매출원가 | E68: 2727132.9 | G68: 2089477.6 | H68: 2151534.4 | I68: 2067127.5 | J68: 2574480 | K68: 8882619.4 | L68: 2506895.1 | M68: 2866040.5 | N68: 2692363.8 | O68: 3243763.2 | P68: 11309062 | Q68: 2837657.5 | R68: 3443086.3 | S68: 3202405.4 | T68: 3509373.5 | U68: 12992523 | V68: 3193437.9 | W68: 3453431 | X68: 3650707.1 | Y68: 4318841 | Z68: 14616417 | AA68: 4743761.1 | AB68: 4975570.5
A69: 1 | C69: 매출총이익 | E69: -251266.21 | G69: -87841.17 | H69: 14498.03 | I69: 136436.24 | J69: 99767.95 | K69: 162861.05 | L69: 125995.18 | M69: 198357.33 | N69: 161162.62 | O69: 169348.38 | P69: 654863.51 | Q69: 150087.48 | R69: 440896.26 | S69: 406770.28 | T69: 496176.86 | U69: 1493930.9 | V69: 629077.83 | W69: 693693.87 | X69: 767191.13 | Y69: 874253.49 | Z69: 2964216.3 | AA69: 1172570.7 | AB69: 1356584.5
A70: 1 | C70: 판관비 | E70: 229430.52 | G70: 129577.42 | H70: 122749.78 | I70: 122096.1 | J70: 77588.9 | K70: 452012.2 | L70: 167463.91 | M70: 129823.11 | N70: 148254.87 | O70: 30681.66 | P70: 476223.55 | Q70: 128823.57 | R70: 245266.13 | S70: 200625.27 | T70: 213992.42 | U70: 788707.39 | V70: 195343.66 | W70: 222237.89 | X70: 209905.74 | Y70: 299218.92 | Z70: 926706.21 | AA70: 267184.78 | AB70: 316646.91
A71: 1 | C71: 영업이익 | E71: -480696.74 | G71: -217418.59 | H71: -108251.75 | I71: 14340.14 | J71: 22179.05 | K71: -289151.15 | L71: -41468.73 | M71: 68534.23 | N71: 12907.76 | O71: 138666.71 | P71: 178639.97 | Q71: 21263.91 | R71: 195630.12 | S71: 206145 | T71: 282184.44 | U71: 705223.47 | V71: 433734.17 | W71: 471455.98 | X71: 557285.39 | Y71: 575034.55 | Z71: 2037510.1 | AA71: 905385.91 | AB71: 1039937.6
A72: 1 | C72: 금융수익 | E72: 64421.62 | G72: 166207.39 | H72: 379445.01 | I72: 595500.32 | J72: -1798.22 | K72: 1139354.5 | L72: 284345.31 | M72: 225030.58 | N72: 185104.36 | O72: 37012.45 | P72: 731492.7 | Q72: 287572.76 | R72: 219895.85 | S72: 861737.86 | T72: 400396.43 | U72: 1769602.9 | V72: 156428.53 | W72: 1576490.6 | X72: 388797.51 | Y72: -43230.08 | Z72: 2078486.6 | AA72: 547979 | AB72: 321873.67
A73: 1 | C73: 금융비용 | E73: 79456.99 | G73: 199629.38 | H73: 1020739.9 | I73: 1846820 | J73: -1475499 | K73: 1591690.2 | L73: 659565.86 | M73: 298520.23 | N73: 617540.7 | O73: -351128.91 | P73: 1224497.9 | Q73: 918985.28 | R73: 762185.29 | S73: 390887.9 | T73: 1977654.5 | U73: 4049713 | V73: 309801.1 | W73: 517499.37 | X73: 1048267.7 | Y73: 449402.76 | Z73: 2324970.9 | AA73: 1574878.2 | AB73: 751693.09
A74: 1 | C74: 기타영업외수익 | E74: 11020.64 | G74: 67849.4 | H74: 688736.49 | I74: 1398739.5 | J74: -1342235.2 | K74: 813090.25 | L74: 456424.18 | M74: 75969.63 | N74: 423777.48 | O74: -375757.88 | P74: 580413.41 | Q74: 693574.16 | R74: 575022.13 | S74: 9531.84 | T74: 1762567.1 | U74: 3040695.2 | V74: 143086.67 | W74: 34654.73 | X74: 710986.82 | Y74: 276717.84 | Z74: 1165446.1 | AA74: 1238178.4 | AB74: 598442.74
A75: 1 | C75: 기타영업외비용 | E75: 221748.27 | G75: 55092.36 | H75: 32642.91 | I75: 90900.34 | J75: 313007.47 | K75: 491643.08 | L75: 66346.54 | M75: 37463.21 | N75: 17537.84 | O75: 110323.49 | P75: 231671.08 | Q75: 53885.31 | R75: 26234.73 | S75: 599306.41 | T75: -11954.28 | U75: 667472.17 | V75: 47081.21 | W75: 1284823.2 | X75: 37906.37 | Y75: -218657.51 | Z75: 1151153.3 | AA75: 60273.4 | AB75: 52879.79
A76: 1 | C76: 종속기업,공동지배기업및관계기업관련손익 | E76: -146.01 | G76: -98.23 | H76: -188.91 | I76: -127.73 | J76: -1029.21 | K76: -1444.08 | L76: -99.84 | M76: -101 | N76: -86.98 | O76: 273.69 | P76: -14.13 | Q76: -139.75 | R76: -130.47 | S76: -128.17 | T76: 199.64 | U76: -198.75 | V76: -102.38 | W76: -93.58 | X76: -81.64 | Y76: -4124.4 | Z76: -4402 | AA76: 66.79 | AB76: 693.84
A77: 1 | C77: 지분법관련손익 | E77: -146.01 | G77: -98.23 | H77: -188.91 | I77: -127.73 | J77: -1029.21 | K77: -1444.08 | L77: -99.84 | M77: -101 | N77: -86.98 | O77: 273.69 | P77: -14.13 | Q77: -139.75 | R77: -130.47 | S77: -128.17 | T77: 199.64 | U77: -198.75 | V77: -102.38 | W77: -93.58 | X77: -81.64 | Y77: -4124.4 | Z77: -4402 | AA77: 66.79 | AB77: 693.84
A78: 1 | C78: 법인세비용차감전계속사업이익 | E78: -706605.74 | G78: -238181.78 | H78: -93641.98 | I78: 70731.95 | J78: -160391.98 | K78: -421483.79 | L78: -26711.47 | M78: 33449.99 | N78: -13375.92 | O78: 41000.4 | P78: 34363 | Q78: 29400.49 | R78: 201997.62 | S78: 87092.22 | T78: 479647.38 | U78: 798137.71 | V78: 376264.68 | W78: 280185.18 | X78: 570814.02 | Y78: 573652.66 | Z78: 1800916.5 | AA78: 1056458.6 | AB78: 1156375
... A81: 1 | C81: 기타영업외손익 | E81: -210727.63 | G81: 12757.04 | H81: 656093.58 | I81: 1307839.2 | J81: -1655242.6 | K81: 321447.17 | L81: 390077.64 | M81: 38506.42 | N81: 406239.64 | O81: -486081.37 | P81: 348742.33 | Q81: 639688.85 | R81: 548787.4 | S81: -589774.57 | T81: 1774521.4 | U81: 2373223.1 | V81: 96005.46 | W81: -1250168.5 | X81: 673080.45 | Y81: 495375.35 | Z81: 14292.76 | AA81: 1177905 | AB81: 545562.95
A82: 1 | C82: 당기순이익 | G82: -175910.12 | H82: -64729.02 | I82: 50383.25 | J82: -161808.74 | K82: -352064.63 | L82: -20551.75 | M82: 24068.8 | N82: -9828.13 | O82: 31000.29 | P82: 24689.21 | Q82: 28623.73 | R82: 154109.79 | S82: 72198.12 | T82: 366577.77 | U82: 621509.41 | V82: 284230.31 | W82: 210911.34 | X82: 430790.46 | Y82: 489552.45 | Z82: 1415484.6 | AA82: 773812.34 | AB82: 822143.13
A83: 1 | C83: 총포괄손익 | G83: -142842.56 | H83: -65153.97 | I83: 52279.92 | J83: -150256.94 | K83: -305973.55 | L83: -24277.11 | M83: 20566.17 | N83: -12388.83 | O83: -69147.04 | P83: -85246.81 | Q83: 22879.24 | R83: 152720.11 | S83: 78034.52 | T83: 244078.81 | U83: 497712.68 | V83: 287151.53 | W83: 376660.34 | X83: 430613.48 | Y83: 487602.58 | Z83: 1582027.9 | AA83: 790298.68 | AB83: 829639.47
A84: 1 | C84: (지배주주지분)당기순이익 | G84: -175910.12 | H84: -64729.02 | I84: 50383.25 | J84: -161808.74 | K84: -352064.63 | L84: -20551.75 | M84: 24065.96 | N84: -9828.13 | O84: 30999.99 | P84: 24686.07 | Q84: 28623.99 | R84: 154109.51 | S84: 72197.74 | T84: 366577.81 | U84: 621509.05 | V84: 284230.4 | W84: 210911.29 | X84: 430790.6 | Y84: 489552.47 | Z84: 1415484.8 | AA84: 773812.32 | AB84: 822143.05
A85: 1 | C85: 계속사업이익 | G85: -175910.12 | H85: -64729.02 | I85: 50383.25 | J85: -161808.74 | K85: -352064.63 | L85: -20551.75 | M85: 24068.8 | N85: -9828.13 | O85: 31000.29 | P85: 24689.21 | Q85: 28623.73 | R85: 154109.79 | S85: 72198.12 | T85: 366577.77 | U85: 621509.41 | V85: 284230.31 | W85: 210911.34 | X85: 430790.46 | Y85: 489552.45 | Z85: 1415484.6 | AA85: 773812.34 | AB85: 822143.13
A86: 1 | C86: 이자수익 | G86: 8082 | H86: 10390 | I86: 13453 | J86: 13685 | K86: 45610 | L86: 13433 | M86: 9877 | N86: 10921 | O86: 14807 | P86: 49038 | Q86: 14552 | R86: 13406 | S86: 10666 | T86: 15139 | U86: 53763 | V86: 17404 | W86: 26010 | X86: 28636 | Y86: 32807 | Z86: 104857 | AA86: 30279 | AB86: 33814
A87: 1 | C87: 이자비용 | G87: 23822 | H87: 26384 | I87: 28774 | J87: 27161 | K87: 106141 | L87: 30417 | M87: 40611 | N87: 45508 | O87: 15355 | P87: 131891 | Q87: 44943 | R87: 41039 | S87: 29412 | T87: 34275 | U87: 149669 | V87: 24366 | W87: 28626 | X87: 25961 | Y87: 17595 | Z87: 96548 | AA87: 21874 | AB87: 21983
A88: 1 | C88: 외환차익 | G88: 48052 | H88: 132047 | I88: 193513 | J88: 189513 | K88: 563125 | L88: 66962 | M88: 87838 | N88: 82138 | O88: 91325 | P88: 328263 | Q88: 90906 | R88: 146532 | S88: 77110 | T88: 142518 | U88: 457066 | V88: 73119 | W88: 130920 | X88: 84292 | Y88: 110751 | Z88: 399082 | AA88: 216779 | AB88: 245462
A89: 1 | C89: 외환차손 | G89: 39613 | H89: 69170 | I89: 80966 | J89: 171339 | K89: 361088 | L89: 75169 | M89: 46919 | N89: 58434 | O89: 71990 | P89: 252512 | Q89: 57133 | R89: 71926 | S89: 59766 | T89: 66197 | U89: 255022 | V89: 120963 | W89: 249944 | X89: 145602 | Y89: 87186 | Z89: 603695 | AA89: 127228 | AB89: 134033
A90: 1 | C90: 외화환산이익 | G90: 56878 | H90: 141075 | I90: 239912 | J90: -389345 | K90: 48520 | L90: 100387 | M90: 87036 | N90: 69627 | O90: -136860 | P90: 120190 | Q90: 136929 | R90: 37940 | S90: 0 | T90: 295499 | U90: 470368 | V90: 30846 | W90: 31759 | X90: 172774 | Y90: 29305 | Z90: 264684 | AA90: 267689 | AB90: 18513
A91: 1 | C91: 외화환산손실 | G91: 38027 | H91: 127706 | I91: 212312 | J91: -150196 | K91: 227849 | L91: 42797 | M91: 112071 | N91: 36430 | O91: -5584 | P91: 185714 | Q91: 53537 | R91: 17573 | S91: 182698 | T91: 6025 | U91: 259833 | V91: 14850 | W91: 220849 | X91: 4255 | Y91: 20952 | Z91: 260906 | AA91: 67250 | AB91: 14840
A92: 1 | C92: 파생상품이익 | G92: 51902 | H92: 95895 | I92: 148622 | J92: 176516 | K92: 472935 | L92: 64035 | M92: 39816 | N92: 21962 | O92: 67344 | P92: 193157 | Q92: 45000 | R92: 21850 | S92: 773868 | T92: -52784 | U92: 787934 | V92: 34961 | W92: 1381125 | X92: 103084 | Y92: -217856 | Z92: 1301314 | AA92: 33126 | AB92: 24078
A93: 1 | C93: 파생상품손실 | G93: 95249 | H93: 793841 | I93: 1518267 | J93: -1531665 | K93: 875692 | L93: 511183 | M93: 98778 | N93: 475621 | O93: -433947 | P93: 651635 | Q93: 763294 | R93: 631552 | S93: 119012 | T93: 1871157 | U93: 3385015 | V93: 149622 | W93: 8315 | X93: 872431 | Y93: 298542 | Z93: 1328910 | AA93: 1358526 | AB93: 580837
A94: 1 | C94: 이자손익 | G94: -15740 | H94: -15994 | I94: -15321 | J94: -13476 | K94: -60531 | L94: -16984 | M94: -30734 | N94: -34587 | O94: -548 | P94: -82853 | Q94: -30391 | R94: -27633 | S94: -18746 | T94: -19136 | U94: -95906 | V94: -6962 | W94: -2616 | X94: 2675 | Y94: 15212 | Z94: 8309 | AA94: 8405 | AB94: 11831
A95: 1 | C95: 배당금수익 | H95: 38 | I95: 0 | J95: 0 | M95: 21 | N95: 0 | O95: 0 | R95: 17 | S95: 0 | T95: 0 | W95: 0 | X95: 0 | Y95: 0 | AA95: 103 | AB95: 0
A96: 1 | C96: (비지배주주지분)당기순이익 | M96: 2.84 | N96: 0 | O96: 0.3 | Q96: -0.26 | R96: 0.28 | S96: 0.39 | T96: -0.04 | U96: 0.37 | V96: -0.09 | W96: 0.04 | X96: -0.14 | Y96: -0.03 | Z96: -0.22 | AA96: 0.02 | AB96: 0.08
A97: 1 | C97: 영업활동으로인한현금흐름 | E97: 757.66 | G97: -160190.51 | H97: 160687.17 | I97: 128905.84 | J97: -58184.1 | K97: 71218.4 | L97: 67804.62 | M97: -388546.35 | N97: 268396.48 | O97: 221182.43 | P97: 168837.18 | Q97: 310992.26 | R97: 1054495.9 | S97: 45369.8 | T97: 1473024.8 | U97: 2883882.7 | V97: 1704749.7 | W97: 501374.72 | X97: 1575239.7 | Y97: -270971.68 | Z97: 3510392.4 | AA97: 883359.81 | AB97: 1842690.1
A98: 1 | C98: 투자활동으로인한현금흐름 | E98: -20991.58 | G98: -103233.82 | H98: -113097.47 | I98: -125787.35 | J98: -175760.51 | K98: -517879.15 | L98: -108192.29 | M98: -104457.52 | N98: -130448.59 | O98: -134806.21 | P98: -477904.61 | Q98: -118600.37 | R98: -128453.95 | S98: -138038.01 | T98: -114031.64 | U98: -499123.97 | V98: -164264.15 | W98: -459973.87 | X98: -1318710.7 | Y98: -96679.2 | Z98: -2039627.9 | AA98: 293770.24 | AB98: 243632.01
A99: 1 | C99: 유형자산의감소 | E99: 2056.39 | G99: 2480.8 | H99: 5774.82 | I99: 2620.51 | J99: 2013.74 | K99: 12889.87 | L99: 1966.99 | M99: 4265.44 | N99: 1088.89 | O99: 2335.43 | P99: 9656.75 | Q99: 8087.27 | R99: 1546.34 | S99: 1694.02 | T99: 417.8 | U99: 11745.43 | V99: 1048.17 | W99: 1543.59 | X99: 1570.36 | Y99: 10949 | Z99: 15111.12 | AA99: 1100.54 | AB99: 1288.83
A100: 1 | C100: 무형자산의감소 | E100: 0 | I100: 0 | J100: 0 | Y100: 4302.04
A101: 1 | C101: 유형자산의증가 | E101: 62303.9 | G101: 91812.63 | H101: 87305.68 | I101: 149675.38 | J101: 155684.48 | K101: 484478.17 | L101: 105523.96 | M101: 128091.59 | N101: 123215.53 | O101: 121380.71 | P101: 478211.79 | Q101: 120412.83 | R101: 122820.64 | S101: 120123.25 | T101: 100106.31 | U101: 463463.03 | V101: 175237.16 | W101: 104565.74 | X101: 125453.28 | Y101: 106687.51 | Z101: 511943.69 | AA101: 122048.95 | AB101: 111617.78
A102: 1 | C102: CAPEX | E102: 78353.71 | G102: 95114.82 | H102: 91878.3 | I102: 158409.65 | J102: 168749.16 | K102: 514151.93 | L102: 110954.99 | M102: 135877.15 | N102: 132963.25 | O102: 134110.13 | P102: 513905.52 | Q102: 126871.73 | R102: 129210.58 | S102: 126033.36 | T102: 114482.93 | U102: 496598.6 | V102: 179257.14 | W102: 110604.12 | X102: 131183.27 | Y102: 120445.31 | Z102: 541489.84 | AA102: 125977.26 | AB102: 119933.09
A103: 1 | C103: 무형자산의증가 | E103: 16049.81 | G103: 3302.19 | H103: 4572.62 | I103: 8734.27 | J103: 13064.68 | K103: 29673.76 | L103: 5431.03 | M103: 7785.56 | N103: 9747.72 | O103: 12729.42 | P103: 35693.73 | Q103: 6458.9 | R103: 6389.94 | S103: 5910.11 | T103: 14376.62 | U103: 33135.57 | V103: 4019.98 | W103: 6038.38 | X103: 5729.99 | Y103: 13757.8 | Z103: 29546.15 | AA103: 3928.31 | AB103: 8315.31
A104: 1 | C104: 재무활동으로인한현금흐름 | E104: -622870.95 | G104: -95362.07 | H104: -178120.91 | I104: -135820.98 | J104: -523535.82 | K104: -932839.78 | L104: 138322.86 | M104: 414850.68 | N104: 113803.16 | O104: -164215.61 | P104: 502761.09 | Q104: -387471.4 | R104: -887799.77 | S104: -410559.44 | T104: -363002.6 | U104: -2048833.2 | V104: -62114.37 | W104: -425025.23 | X104: -247235.03 | Y104: -125878.4 | Z104: -860253.03 | AA104: -69987.42 | AB104: -513509.12
A105: 1 | C105: 리스부채의상환 | E105: 2453.37 | G105: 1886.57 | H105: 3102.07 | I105: 2332.63 | J105: 2315.67 | K105: 9636.94 | L105: 2931.79 | M105: 4393.52 | N105: 3628.15 | O105: 2847.63 | P105: 13801.09 | Q105: 3290.26 | R105: 4426.5 | S105: 3701.96 | T105: 2871.35 | U105: 14290.07 | V105: 3555.6 | W105: 4558.99 | X105: 3744.14 | Y105: 3381.45 | Z105: 15240.18 | AA105: 4987.42 | AB105: 5827.77
A106: 1 | C106: 현금및현금성자산의증감 | E106: -643001.1 | G106: -358846.18 | H106: -130905.36 | I106: -133560.13 | J106: -769931.63 | K106: -1393243.3 | L106: 100595.53 | M106: -81416.5 | N106: 250681.28 | O106: -85965.32 | P106: 183894.99 | Q106: -199451.33 | R106: 41432.6 | S106: -501497.87 | T106: 989340.64 | U106: 329824.04 | V106: 1478934.8 | W106: -381837.27 | X106: 133.24 | Y106: -485180.19 | Z106: 612050.54 | AA106: 1105538.1 | AB106: 1575457.4
A107: 1 | C107: 기말현금및현금성자산 | E107: -643001.09 | G107: 1778545.2 | H107: -130905.36 | I107: -133560.13 | J107: -769931.63 | K107: 744148.12 | L107: 844743.65 | M107: -81416.5 | N107: 250681.28 | O107: -85965.32 | P107: 928043.11 | Q107: 728591.78 | R107: 41432.6 | S107: -501497.88 | T107: 989340.65 | U107: 1257867.1 | V107: 2736801.9 | W107: -381837.27 | X107: 133.24 | Y107: -485180.18 | Z107: 1869917.7 | AA107: 2975455.8 | AB107: 1575457.4
A108: 1 | C108: 이자수취(CF) | G108: 8594.1 | H108: 7303.85 | I108: 12751.3 | J108: 12732.93 | K108: 41382.18 | L108: 15412.13 | M108: 9332.14 | N108: 5934.15 | O108: 17831.09 | P108: 48509.51 | Q108: 24353.27 | R108: 9311.39 | S108: 13873.98 | T108: 10496.3 | U108: 58034.94 | V108: 19803.26 | W108: 18515.52 | X108: 22576.83 | Y108: 21286.56 | Z108: 82182.17 | AA108: 30770.58 | AB108: 34386.95
A109: 1 | C109: 이자지급(CF) | G109: -20605.67 | H109: -12784.61 | I109: -24186.27 | J109: -19366.21 | K109: -76942.76 | L109: -28830.55 | M109: -20642.24 | N109: -21712.23 | O109: -45460.85 | P109: -116645.87 | Q109: -44786.48 | R109: -26638.68 | S109: -32189.77 | T109: -11149.66 | U109: -114764.59 | V109: -18438.26 | W109: -5623.36 | X109: -14560.83 | Y109: -753.18 | Z109: -39375.63 | AA109: -11493.62 | AB109: 1638.29
A110: 1 | C110: 법인세납부(CF) | G110: -1240.81 | H110: 1222.79 | I110: -2355.24 | J110: -2375.07 | K110: -4748.33 | L110: -1658.95 | M110: 2265.66 | N110: -1210.13 | O110: -1867.94 | P110: -2471.36 | Q110: -928.64 | R110: 2827.82 | S110: -2446.18 | T110: -1677.46 | U110: -2224.46 | V110: -6393.32 | W110: -11760.32 | X110: -28446.78 | Y110: -4265.66 | Z110: -50866.08 | AA110: -17729.77 | AB110: -30995.92
A111: 1 | C111: 배당금수취(CF) | I111: 0 | J111: 0 | N111: 0 | O111: 0 | S111: 0 | T111: 0 | X111: 0 | Y111: 0
A112: 1 | C112: 배당금지급 | X112: 148339.88 | Y112: 0

Sheet BS별도
B1: (백만원) | C1: 이름: BS별도H | E1: 4Q21 | F1: 2021 | G1: 1Q22 | H1: 2Q22 | I1: 3Q22 | J1: 4Q22 | K1: 2022 | L1: 1Q23 | M1: 2Q23 | N1: 3Q23 | O1: 4Q23 | P1: 2023 | Q1: 1Q24 | R1: 2Q24 | S1: 3Q24 | T1: 4Q24 | U1: 2024 | V1: 1Q25 | W1: 2Q25 | X1: 3Q25 | Y1: 4Q25 | Z1: 2025 | AA1: 1Q26 | AB1: 2Q26 | AC1: 3Q26 | AD1: 4Q26 | AE1: 2026 | AF1: 1Q27 | AG1: 2Q27 | AH1: 3Q27 | AI1: 4Q27 | AJ1: 2027 | AK1: 1Q28 | AL1: 2Q28 | AM1: 3Q28 | AN1: 4Q28 | AO1: 2028
B2: 별도 | D2: fin json(kship_fin.py)
B3: HD현대중공업(별) | C3: UPDATE: 26-10-14 | E3: 1 | F3: 2 | G3: 3 | H3: 4 | I3: 5 | J3: 6 | K3: 7 | L3: 8 | M3: 9 | N3: 10 | O3: 11 | P3: 12 | Q3: 13 | R3: 14 | S3: 15 | T3: 16 | U3: 17 | V3: 18 | W3: 19 | X3: 20 | Y3: 21 | Z3: 22 | AA3: 23 | AB3: 24 | AC3: 25 | AD3: 26 | AE3: 27 | AF3: 28 | AG3: 29 | AH3: 30 | AI3: 31 | AJ3: 32 | AK3: 33 | AL3: 34 | AM3: 35 | AN3: 36 | AO3: 37
B4: Account Code | C4: AccountNAME | E4: 2021.12 | F4: 2021.12A | G4: 2022.03 | H4: 2022.06 | I4: 2022.09 | J4: 2022.12 | K4: 2022.12A | L4: 2023.03 | M4: 2023.06 | N4: 2023.09 | O4: 2023.12 | P4: 2023.12A | Q4: 2024.03 | R4: 2024.06 | S4: 2024.09 | T4: 2024.12 | U4: 2024.12A | V4: 2025.03 | W4: 2025.06 | X4: 2025.09 | Y4: 2025.12 | Z4: 2025.12A | AA4: 2026.03 | AB4: 2026.06 | AC4: 2026.09 | AD4: 2026.12 | AE4: 2026.12A | AF4: 2027.03 | AG4: 2027.06 | AH4: 2027.09 | AI4: 2027.12 | AJ4: 2027.12A | AK4: 2028.03 | AL4: 2028.06 | AM4: 2028.09 | AN4: 2028.12 | AO4: 2028.12A
A5: 1 | C5: 유동자산 | E5: 7885398.9 | F5: 7885398.9 | G5: 7716074.5 | H5: 8357606 | I5: 8992402.1 | J5: 7988297 | K5: 7988297 | L5: 8634179.6 | M5: 8896685.2 | N5: 9425959.3 | O5: 8768341.2 | P5: 8768341.2 | Q5: 8966573.2 | R5: 9065484.4 | S5: 8493977.8 | T5: 10398748 | U5: 10398748 | V5: 11918956 | W5: 11283601 | X5: 12277537 | Y5: 14937275 | Z5: 14937275 | AA5: 16145796 | AB5: 17912015
A6: 1 | C6: 현금및현금성자산 | E6: 2137125.6 | F6: 2137125.6 | G6: 1763733.1 | H6: 1634136.9 | I6: 1498890.3 | J6: 723249.2 | K6: 723249.2 | L6: 836315.64 | M6: 760729.54 | N6: 981370.99 | O6: 900193.71 | P6: 900193.71 | Q6: 708556.74 | R6: 748727.8 | S6: 254298.5 | T6: 1242675.6 | U6: 1242675.6 | V6: 2708098.3 | W6: 2338193.9 | X6: 2334257.5 | Y6: 1842183.3 | Z6: 1842183.3 | AA6: 2945633 | AB6: 4513006.2
A7: 1 | C7: 단기금융상품 | E7: 151000 | F7: 151000 | G7: 151000 | H7: 181000 | I7: 151000 | J7: 161000 | K7: 161000 | L7: 161000 | M7: 131000 | N7: 131000 | O7: 131000 | P7: 131000 | Q7: 131000.01 | R7: 131000 | S7: 131000 | T7: 131000 | U7: 131000 | V7: 131000 | W7: 481000 | X7: 1671000 | Y7: 1689000 | Z7: 1689000 | AA7: 1279000 | AB7: 917000
A8: 1 | C8: 단기금융자산 | E8: 259137.32 | F8: 259137.32 | G8: 314512.06 | H8: 548806.56 | I8: 974184.56 | J8: 485992.28 | K8: 485992.28 | L8: 547844.55 | M8: 526571.39 | N8: 608327.41 | O8: 432686.75 | P8: 432686.75 | Q8: 559683.45 | R8: 673414.52 | S8: 462191.31 | T8: 954876.65 | U8: 954876.65 | V8: 804978.33 | W8: 771947.75 | X8: 2012261.4 | Y8: 2197681.1 | Z8: 2197681.1 | AA8: 2207931.5 | AB8: 2026825.8
A9: 1 | C9: 매출채권및기타채권 | E9: 1032383.4 | F9: 1032383.4 | G9: 873302.75 | H9: 1534205.9 | I9: 1101477.2 | J9: 1156122.3 | K9: 1156122.3 | L9: 1420480.3 | M9: 1391097.2 | N9: 1408045.2 | O9: 1383651.2 | P9: 1383651.2 | Q9: 1378783.7 | R9: 1551626.1 | S9: 1581293.3 | T9: 1666695.7 | U9: 1666695.7 | V9: 1865479.1 | W9: 1709653.7 | X9: 1697101.6 | Y9: 1700100.2 | Z9: 1700100.2 | AA9: 1617171.2 | AB9: 1761399.8
A10: 1 | C10: 계약자산 | E10: 2836359.4 | F10: 2836359.4 | G10: 3073176.9 | H10: 2863181.2 | I10: 3253811.6 | J10: 3180079.7 | K10: 3180079.7 | L10: 3232105.7 | M10: 3494267.8 | N10: 3647358.6 | O10: 3458668.9 | P10: 3458668.9 | Q10: 3515123.4 | R10: 3396531 | S10: 3397567.1 | T10: 3573015.7 | U10: 3573015.7 | V10: 3273711.1 | W10: 3118247.5 | X10: 2988952.8 | Y10: 5131962.9 | Z10: 5131962.9 | AA10: 5344888 | AB10: 5656017.1
A11: 1 | C11: 재고자산 | E11: 898666.74 | F11: 898666.74 | G11: 955114.32 | H11: 1011856.2 | I11: 1277538.8 | J11: 1360377.4 | K11: 1360377.4 | L11: 1445702.6 | M11: 1432643.1 | N11: 1432420.2 | O11: 1308520.4 | P11: 1308520.4 | Q11: 1515234.9 | R11: 1445122.4 | S11: 1537922.3 | T11: 1495877.3 | U11: 1495877.3 | V11: 1631668.6 | W11: 1681490.4 | X11: 1730507.7 | Y11: 1979474 | Z11: 1979474 | AA11: 1945915.4 | AB11: 1982548.7
A12: 1 | C12: 유동파생상품자산 | E12: 11368.27 | F12: 11368.27 | G12: 39634.66 | H12: 69702.84 | I12: 131045.43 | J12: 106450.66 | K12: 106450.66 | L12: 102084.18 | M12: 104796.3 | N12: 99587.15 | O12: 104488.45 | P12: 104488.45 | Q12: 24628.9 | R12: 3770.28 | S12: 72075.84 | T12: 927.29 | U12: 927.29 | V12: 2644.75 | W12: 66289.1 | X12: 11211.79 | Y12: 8611.82 | Z12: 8611.82 | AA12: 88344.33 | AB12: 99217.49
A13: 1 | C13: 유동확정계약자산 | E13: 96769.05 | F13: 96769.05 | G13: 123877.4 | H13: 298103.72 | I13: 692139.13 | J13: 218541.62 | K13: 218541.62 | L13: 284760.37 | M13: 290775.09 | N13: 377740.26 | O13: 197198.3 | P13: 197198.3 | Q13: 404054.54 | R13: 538644.24 | S13: 259115.47 | T13: 822949.36 | U13: 822949.36 | V13: 671333.58 | W13: 224658.65 | X13: 330049.56 | Y13: 500069.33 | Z13: 500069.33 | AA13: 840587.19 | AB13: 1010608.3
A14: 1 | C14: 당기법인세자산(선급법인세) | E14: 2447.05 | F14: 2447.05 | G14: 3510.83 | H14: 2208.75 | I14: 3534.69 | J14: 5146.87 | K14: 5146.87 | L14: 6504.98 | M14: 2707.69 | N14: 3779.05 | O14: 5401.22 | P14: 5401.22 | Q14: 7227.15 | R14: 92.27 | S14: 0 | T14: 0 | U14: 0 | Y14: 0 | Z14: 0
A15: 1 | C15: 매각예정비유동자산및처분자산 | E15: 4719.32 | F15: 4719.32 | O15: 0 | P15: 0
A16: 1 | C16: 기타유동자산 | E16: 714559.98 | F16: 714559.98 | G16: 732724.52 | H16: 763210.54 | I16: 882965 | J16: 1077329.3 | K16: 1077329.3 | L16: 1145225.9 | M16: 1288668.6 | N16: 1344657.8 | O16: 1279219.1 | P16: 1279219.1 | Q16: 1281963.8 | R16: 1249970.4 | S16: 1260705.3 | T16: 1465607.2 | U16: 1465607.2 | V16: 1635020.9 | W16: 1664068.2 | X16: 1514456 | Y16: 2085873 | Z16: 2085873 | AA16: 2084257 | AB16: 1972217.4
A17: 1 | C17: 비유동자산 | E17: 7193370.1 | F17: 7193370.1 | G17: 7341258.7 | H17: 7867597.1 | I17: 8870069.1 | J17: 8294797.9 | K17: 8294797.9 | L17: 8344621.5 | M17: 8345253.3 | N17: 8520002.8 | O17: 8355832.9 | P17: 8355832.9 | Q17: 8456151.3 | R17: 8626537.7 | S17: 8364703.7 | T17: 9002546.1 | U17: 9002546.1 | V17: 8987176.1 | W17: 8481259.9 | X17: 8539167.7 | Y17: 11261787 | Z17: 11261787 | AA17: 11455773 | AB17: 11477994
A18: 1 | C18: 종속기업및관계기업투자 | E18: 3556.2 | F18: 3556.2 | G18: 32556.2 | H18: 32556.2 | I18: 32556.2 | J18: 30345.76 | K18: 30345.76 | L18: 30346.4 | M18: 30346.4 | N18: 56498.92 | O18: 68946.32 | P18: 68946.32 | Q18: 57151.27 | R18: 57151.27 | S18: 57151.27 | T18: 56938.38 | U18: 56938.38 | V18: 154385.95 | W18: 154385.95 | X18: 153253.08 | Y18: 513708.18 | Z18: 513708.18 | AA18: 513708.18 | AB18: 513708.18
A19: 1 | C19: 투자자산 | E19: 201927.53 | F19: 201927.53 | G19: 229839.87 | H19: 634468.63 | I19: 1504826.1 | J19: 523994.5 | K19: 523994.5 | L19: 498392.08 | M19: 428985.82 | N19: 539229.97 | O19: 375855.18 | P19: 375855.18 | Q19: 448103.88 | R19: 612260.64 | S19: 330513.45 | T19: 1125976.3 | U19: 1125976.3 | V19: 1223375.8 | W19: 591820.72 | X19: 743836.08 | Y19: 1422423.8 | Z19: 1422423.8 | AA19: 1883020.3 | AB19: 1907370
A20: 1 | C20: 장기금융자산 | E20: 9560.27 | F20: 9560.27 | G20: 9560.27 | H20: 9554.27 | I20: 9554.27 | J20: 9554.27 | K20: 9554.27 | L20: 9554.27 | M20: 10554.27 | N20: 10554.27 | O20: 10562.23 | P20: 10562.23 | Q20: 10562.23 | R20: 10562.23 | S20: 10562.23 | T20: 10562.23 | U20: 10562.23 | V20: 10562.23 | W20: 10562.23 | X20: 10562.23 | Y20: 25281.42 | Z20: 25281.42 | AA20: 25281.42 | AB20: 25281.42
A21: 1 | C21: 장기매출채권및기타채권 | E21: 38942.19 | F21: 38942.19 | G21: 47759.87 | H21: 97404.15 | I21: 168849.73 | J21: 176738.79 | K21: 176738.79 | L21: 205506.06 | M21: 198976.31 | N21: 216126.11 | O21: 168168.13 | P21: 168168.13 | Q21: 176937.59 | R21: 160888.32 | S21: 136890.47 | T21: 125711.47 | U21: 125711.47 | V21: 99946.38 | W21: 89678.83 | X21: 83155.23 | Y21: 91230.79 | Z21: 91230.79 | AA21: 90261.32 | AB21: 92563.73
A22: 1 | C22: 투자부동산 | E22: 4108.68 | F22: 4108.68 | G22: 1486.97 | H22: 1477.15 | I22: 1467.33 | J22: 1457.52 | K22: 1457.52 | L22: 1447.7 | M22: 1437.88 | N22: 1428.07 | O22: 1418.25 | P22: 1418.25 | Q22: 1408.43 | R22: 1398.61 | S22: 1388.8 | T22: 1378.98 | U22: 1378.98 | V22: 1369.16 | W22: 1359.35 | X22: 1349.53 | Y22: 1339.71 | Z22: 1339.71 | AA22: 1329.89 | AB22: 1320.08
A23: 1 | C23: 유형자산 | E23: 5986251.9 | F23: 5986251.9 | G23: 6020784.9 | H23: 6049050.5 | I23: 6135792.8 | J23: 6216100.2 | K23: 6216100.2 | L23: 6264242.7 | M23: 6323567.2 | N23: 6375744 | O23: 6414554.2 | P23: 6414554.2 | Q23: 6437196.5 | R23: 6480780.4 | S23: 6527707.5 | T23: 6571431.6 | U23: 6571431.6 | V23: 6598042.9 | W23: 6858019.6 | X23: 6909098.2 | Y23: 8665345.3 | Z23: 8665345.3 | AA23: 8664445.9 | AB23: 8738314.8
A24: 1 | C24: 무형자산 | E24: 79457.82 | F24: 79457.82 | G24: 80867.62 | H24: 82644.42 | I24: 89389.13 | J24: 100046.84 | K24: 100046.84 | L24: 102981.85 | M24: 105997.21 | N24: 109984.01 | O24: 106633.43 | P24: 106633.43 | Q24: 110283.7 | R24: 113590.25 | S24: 116423.02 | T24: 126522.3 | U24: 126522.3 | V24: 126436.2 | W24: 131928.11 | X24: 126367.39 | Y24: 159207.64 | Z24: 159207.64 | AA24: 159179.91 | AB24: 159638.96
A25: 1 | C25: 사용권자산 | E25: 17906.01 | F25: 17906.01 | G25: 20295.85 | H25: 21950.59 | I25: 21169.95 | J25: 42416.69 | K25: 42416.69 | L25: 40547.88 | M25: 40060.44 | N25: 37306.15 | O25: 36432.63 | P25: 36432.63 | Q25: 36676.19 | R25: 34472.54 | S25: 32077.68 | T25: 30541.67 | U25: 30541.67 | V25: 27630.03 | W25: 24556.85 | X25: 24082.86 | Y25: 33716.29 | Z25: 33716.29 | AA25: 34119.66 | AB25: 30995.03
A26: 1 | C26: 기타비유동자산 | E26: 45026.2 | F26: 45026.2 | G26: 72403.75 | H26: 88171.96 | I26: 75371.77 | J26: 382840.74 | K26: 382840.74 | L26: 370713.39 | M26: 391606.61 | N26: 379934.88 | O26: 366871.99 | P26: 366871.99 | Q26: 359346.5 | R26: 377520.28 | S26: 376593.17 | T26: 242637.37 | U26: 242637.37 | V26: 205652.04 | W26: 184392.31 | X26: 164971.37 | Y26: 450919.57 | Z26: 450919.57 | AA26: 431567.94 | AB26: 407103.37
A27: 1 | C27: 비유동파생상품자산 | E27: 43123.04 | F27: 43123.04 | G27: 59450.95 | H27: 89605.37 | I27: 168106.53 | J27: 293924.05 | K27: 293924.05 | L27: 138341.71 | M27: 158160.86 | N27: 100114.82 | O27: 191895.22 | P27: 191895.22 | Q27: 74200.08 | R27: 52575.75 | S27: 103871.68 | T27: 64055.7 | U27: 64055.7 | V27: 66259.55 | W27: 216190.71 | X27: 90721.64 | Y27: 81469.69 | Z27: 81469.69 | AA27: 2366.41 | AB27: 7453.98
... A41: 1 | C41: 비유동부채 | E41: 2436039.1 | F41: 2436039.1 | G41: 2118819.1 | H41: 2063705.2 | I41: 2926939.7 | J41: 1919430 | K41: 1919430 | L41: 1991644.8 | M41: 2495330.3 | N41: 2389906.6 | O41: 1969554.4 | P41: 1969554.4 | Q41: 1809162.8 | R41: 1845785.2 | S41: 1187834.9 | T41: 1888114.8 | U41: 1888114.8 | V41: 1826089.5 | W41: 996978.52 | X41: 1156625.1 | Y41: 1484222.2 | Z41: 1484222.2 | AA41: 1523370.9 | AB41: 1546209.3
A42: 1 | C42: 장기차입금 | E42: 1958992.3 | F42: 1958992.3 | G42: 1626173.2 | H42: 1197558.8 | I42: 1250450.2 | J42: 1150024.2 | K42: 1150024.2 | L42: 1236710 | M42: 1790094.7 | N42: 1602871 | O42: 1559942.8 | P42: 1559942.8 | Q42: 1326593.8 | R42: 1206680.3 | S42: 809134.19 | V42: 685730.58 | W42: 464790.16 | X42: 478555.37 | Y42: 488384.39 | Z42: 488384.39 | AA42: 0 | AB42: 0
A43: 1 | C43: 장기금융부채(face) | E43: 1958992.3 | F43: 1958992.3 | G43: 1626173.2 | H43: 1197558.8 | I43: 1250450.2 | J43: 1150024.2 | K43: 1150024.2 | L43: 1236710 | M43: 1790094.7 | N43: 1602871 | O43: 1559942.8 | P43: 1559942.8 | Q43: 1326593.8 | R43: 1206680.3 | S43: 809134.19 | V43: 685730.58 | W43: 464790.16 | X43: 478555.37 | Y43: 488384.39 | Z43: 488384.39 | AA43: 0 | AB43: 0
A44: 1 | C44: 비유동리스부채 | E44: 12746.17 | F44: 12746.17 | G44: 13306.69 | H44: 14749.51 | I44: 15167.06 | J44: 30331.12 | K44: 30331.12 | L44: 28628.18 | M44: 27644.11 | N44: 25642.43 | O44: 26059.3 | P44: 26059.3 | Q44: 25218.75 | R44: 22407.1 | S44: 20160.72 | T44: 19194.81 | U44: 19194.81 | V44: 16027.79 | W44: 12612.19 | X44: 11620.04 | Y44: 19495.02 | Z44: 19495.02 | AA44: 19098.16 | AB44: 17703.06
A45: 1 | C45: 장기금융부채 | E45: 163221.98 | F45: 163221.98 | G45: 168609.19 | H45: 525081 | I45: 1309776.1 | J45: 450460.66 | K45: 450460.66 | L45: 469913.87 | M45: 399506.92 | N45: 472943.71 | O45: 314089.53 | P45: 314089.53 | Q45: 381685.29 | R45: 528525.66 | S45: 258153.31 | T45: 1013701.8 | U45: 1013701.8 | V45: 1011282 | W45: 406468.73 | X45: 549200.68 | Y45: 851545.58 | Z45: 851545.58 | AA45: 1373195.6 | AB45: 1393144.6
A46: 1 | C46: 장기매입채무및기타채무 | E46: 248.8 | F46: 248.8 | G46: 249.68 | H46: 253.81 | I46: 329.61 | J46: 381 | K46: 381 | L46: 388.77 | M46: 583.75 | N46: 673.66 | O46: 3790.81 | P46: 3790.81 | Q46: 2967.37 | R46: 4133.22 | S46: 4911.86 | T46: 8835.74 | U46: 8835.74 | V46: 10196.03 | W46: 11351.53 | X46: 12591.07 | Y46: 15699.25 | Z46: 15699.25 | AA46: 18240.03 | AB46: 19448.75
A47: 1 | C47: 확정급여부채 | E47: 33198.09 | F47: 33198.09 | G47: 33198.09 | H47: 33198.09 | I47: 33198.09 | J47: 28462.25 | K47: 28462.25 | L47: 28462.25 | M47: 28462.25 | N47: 28462.25 | O47: 30857.21 | P47: 30857.21 | Q47: 31477.91 | R47: 31477.91 | S47: 31477.91 | T47: 33647.53 | U47: 33647.53 | V47: 25659.51 | W47: 25659.51 | X47: 25659.51 | Y47: 31153.15 | Z47: 31153.15 | AA47: 31153.15 | AB47: 31153.15
A48: 1 | C48: 장기충당부채 | E48: 269562.66 | F48: 269562.66 | G48: 279839.61 | H48: 296930.2 | I48: 322568.42 | J48: 279550.66 | K48: 279550.66 | L48: 245686.94 | M48: 266267.96 | N48: 274609.47 | O48: 50595.84 | P48: 50595.84 | Q48: 56230.86 | R48: 64831.17 | S48: 74091.3 | T48: 70328.19 | U48: 70328.19 | V48: 83298.64 | W48: 78858.93 | X48: 80841.82 | Y48: 87736.3 | Z48: 87736.3 | AA48: 91154.08 | AB48: 92910.3
A49: 1 | C49: 장기파생상품부채 | E49: 150475.81 | F49: 150475.81 | G49: 155302.5 | H49: 510331.49 | I49: 1294609.1 | J49: 420129.54 | K49: 420129.54 | L49: 441285.69 | M49: 371862.81 | N49: 447301.28 | O49: 288030.23 | P49: 288030.23 | Q49: 356466.54 | R49: 506118.56 | S49: 237992.59 | T49: 994507.02 | U49: 994507.02 | V49: 995254.24 | W49: 393856.54 | X49: 537580.64 | Y49: 832050.56 | Z49: 832050.56 | AA49: 1354097.4 | AB49: 1375441.6
A50: 1 | C50: 부채총계 | E50: 9484635.7 | F50: 9484635.7 | G50: 9605667.2 | H50: 10837498 | I50: 12421428 | J50: 10992977 | K50: 10992977 | L50: 11714430 | M50: 11952887 | N50: 12669589 | O50: 11915188 | P50: 11915188 | Q50: 12190594 | R50: 12308927 | S50: 11399303 | T50: 13698694 | U50: 13698694 | V50: 15100871 | W50: 13583891 | X50: 14351971 | Y50: 16816487 | Z50: 16816487 | AA50: 17869552 | AB50: 18838537
A51: 1 | C51: 자본금 | E51: 443865.58 | F51: 443865.58 | G51: 443865.58 | H51: 443865.58 | I51: 443865.58 | J51: 443865.58 | K51: 443865.58 | L51: 443865.58 | M51: 443865.58 | N51: 443865.58 | O51: 443865.58 | P51: 443865.58 | Q51: 443865.58 | R51: 443865.58 | S51: 443865.58 | T51: 443865.58 | U51: 443865.58 | V51: 443865.58 | W51: 443865.58 | X51: 443865.58 | Y51: 524806.12 | Z51: 524806.12 | AA51: 524806.12 | AB51: 524806.12
A52: 1 | C52: 자본잉여금 | E52: 3118365 | F52: 3118365 | G52: 3118365 | H52: 3118365 | I52: 3118365 | J52: 3118365 | K52: 3118365 | L52: 3118365 | M52: 3123097.1 | N52: 3122767.3 | O52: 3120677.5 | P52: 3120677.5 | Q52: 3119482.8 | R52: 3119482.8 | S52: 3119482.8 | T52: 3119482.8 | U52: 3119482.8 | V52: 3119482.8 | W52: 3119482.8 | X52: 3119482.8 | Y52: 5124626.2 | Z52: 5124626.2 | AA52: 5124626.2 | AB52: 5124626.2
A53: 1 | C53: 기타자본 | E53: -1411 | F53: -1411 | G53: -1411 | H53: -1411 | I53: -1411 | J53: -1411 | K53: -1411 | L53: -1411 | M53: -1411 | N53: -1411 | O53: -1411 | P53: -1411 | Q53: -1411 | R53: -1411 | S53: -1411 | T53: -1411 | U53: -1411 | V53: -1411 | W53: -1411 | X53: -1411 | Y53: -16907.95 | Z53: -16907.95 | AA53: -16907.95 | AB53: -16907.95
A54: 1 | C54: 기타포괄이익누계액 | E54: 881517.91 | F54: 881517.91 | G54: 881530.73 | H54: 881850.28 | I54: 883705.15 | J54: 881829.1 | K54: 881829.1 | L54: 877983.16 | M54: 874634.97 | N54: 872415.84 | O54: 871875.07 | P54: 871875.07 | Q54: 854444.87 | R54: 853121.39 | S54: 859307.99 | T54: 854334.96 | U54: 854334.96 | V54: 857410.74 | W54: 1024013.3 | X54: 1024050.9 | Y54: 1347172.2 | Z54: 1347172.2 | AA54: 1346718.9 | AB54: 1348306.5
A55: 1 | C55: 이익잉여금 | E55: 1151795.8 | F55: 1151795.8 | G55: 1009315.7 | H55: 945035.5 | I55: 996518.23 | J55: 847469.64 | K55: 847469.64 | L55: 825568.11 | M55: 848865 | N55: 838735.74 | O55: 773978.61 | P55: 773978.61 | Q55: 815748.34 | R55: 968035.86 | S55: 1038133.1 | T55: 1286327.4 | U55: 1286327.4 | V55: 1385913.4 | W55: 1595019.3 | X55: 1878745.4 | Y55: 2402878.1 | Z55: 2402878.1 | AA55: 2752773.9 | AB55: 3570641.3
... A61: 1 | C61: 이자발생자산 | E61: 2405823.2 | F61: 2405823.2 | G61: 2087805.4 | H61: 2192497.8 | I61: 2482629.1 | J61: 1218795.8 | K61: 1218795.8 | L61: 1393714.5 | M61: 1297855.2 | N61: 1600252.7 | O61: 1343442.7 | P61: 1343442.7 | Q61: 1278802.4 | R61: 1432704.6 | S61: 727052.04 | T61: 2208114.4 | U61: 2208114.4 | V61: 3523638.9 | W61: 3120703.9 | X61: 4357081.1 | Y61: 4065145.9 | Z61: 4065145.9 | AA61: 5178845.9 | AB61: 6565113.4
A62: 1 | C62: 당기법인세부채(미지급법인세) | R62: 297.28 | S62: 9800.49 | T62: 13793.08 | U62: 13793.08 | V62: 24546.08 | W62: 29916.33 | X62: 28989.47 | Y62: 38982.45 | Z62: 38982.45 | AA62: 58402.08 | AB62: 313544.55
A63: 1 | C63: 매출액(수익) | E63: 2471789.6 | G63: 2001656.3 | H63: 2166167.7 | I63: 2214607.6 | J63: 2682916.5 | K63: 9065348.2 | L63: 2633059.5 | M63: 3063545 | N63: 2851666.6 | O63: 3409711.8 | P63: 11957983 | Q63: 2986727.4 | R63: 3882000.1 | S63: 3604180.2 | T63: 4003482.2 | U63: 14476390 | V63: 3819793.4 | W63: 4144984.5 | X63: 4418086.2 | Y63: 5186593.4 | Z63: 17569457 | AA63: 5899214.1 | AB63: 6313579.4
A64: 1 | C64: 매출원가 | E64: 2723466.6 | G64: 2089477.6 | H64: 2151534.4 | I64: 2077837.1 | J64: 2583524.8 | K64: 8902373.9 | L64: 2508843.3 | M64: 2866869.5 | N64: 2691297.9 | O64: 3242458.6 | P64: 11309469 | Q64: 2836058.2 | R64: 3444229.5 | S64: 3201377.2 | T64: 3507952.4 | U64: 12989617 | V64: 3190751.8 | W64: 3455683.4 | X64: 3650262.4 | Y64: 4312369.6 | Z64: 14609067 | AA64: 4735127.2 | AB64: 4964982.2
A65: 1 | C65: 매출총이익 | E65: -251676.97 | G65: -87821.3 | H65: 14633.38 | I65: 136770.57 | J65: 99391.63 | K65: 162974.28 | L65: 124216.21 | M65: 196675.52 | N65: 160368.74 | O65: 167253.18 | P65: 648513.65 | Q65: 150669.18 | R65: 437770.67 | S65: 402803 | T65: 495529.76 | U65: 1486772.6 | V65: 629041.61 | W65: 689301.02 | X65: 767823.87 | Y65: 874223.82 | Z65: 2960390.3 | AA65: 1164086.9 | AB65: 1348597.2
A66: 1 | C66: 판관비 | E66: 229387.11 | G66: 129224.36 | H66: 121798.87 | I66: 121476.4 | J66: 77271.9 | K66: 449771.53 | L66: 166570.59 | M66: 128878.03 | N66: 147567.92 | O66: 27691.14 | P66: 470707.68 | Q66: 127676.26 | R66: 243973.45 | S66: 199283.78 | T66: 213295.73 | U66: 784229.22 | V66: 193601.76 | W66: 220089.78 | X66: 207684.67 | Y66: 296288.17 | Z66: 917664.38 | AA66: 264042.08 | AB66: 312923.3
A67: 1 | C67: 영업이익 | E67: -481064.07 | G67: -217045.66 | H67: -107165.5 | I67: 15294.17 | J67: 22119.74 | K67: -286797.25 | L67: -42354.38 | M67: 67797.49 | N67: 12800.82 | O67: 139562.05 | P67: 177805.98 | Q67: 22992.92 | R67: 193797.22 | S67: 203519.22 | T67: 282234.04 | U67: 702543.4 | V67: 435439.85 | W67: 469211.25 | X67: 560139.2 | Y67: 577935.66 | Z67: 2042726 | AA67: 900044.84 | AB67: 1035673.9
A68: 1 | C68: 금융수익 | E68: 64409.73 | G68: 166154.62 | H68: 379385.34 | I68: 595409.27 | J68: -1897.67 | K68: 1139051.6 | L68: 284268.77 | M68: 224734.72 | N68: 184577.68 | O68: 34542.12 | P68: 728123.29 | Q68: 287027.21 | R68: 219527.46 | S68: 861310.81 | T68: 400081.74 | U68: 1767947.2 | V68: 155908.92 | W68: 1576207.3 | X68: 388407.61 | Y68: -43539.79 | Z68: 2076984.1 | AA68: 547643.43 | AB68: 321473.77
A69: 1 | C69: 금융비용 | E69: 79456.99 | G69: 199622.14 | H69: 1020732.7 | I69: 1846715.6 | J69: -1475616 | K69: 1591454.4 | L69: 659346.13 | M69: 298374.96 | N69: 617394.39 | O69: -351303.2 | P69: 1223812.3 | Q69: 918860.14 | R69: 762033.3 | S69: 390725.83 | T69: 1977417.3 | U69: 4049036.6 | V69: 309602.2 | W69: 517295.17 | X69: 1048092.5 | Y69: 449212.98 | Z69: 2324202.9 | AA69: 1574684.4 | AB69: 751548.2
A70: 1 | C70: 기타영업외수익 | E70: 11020.62 | G70: 67791.74 | H70: 688732.48 | I70: 1398717.4 | J70: -1342260 | K70: 812981.57 | L70: 455596.46 | M70: 75969.52 | N70: 423748.5 | O70: -375845.03 | P70: 579469.45 | Q70: 693569.23 | R70: 575015.13 | S70: 9531.83 | T70: 1762562.9 | U70: 3040679 | V70: 143080.12 | W70: 34599.38 | X70: 710966.29 | Y70: 276700.53 | Z70: 1165346.3 | AA70: 1238147.8 | AB70: 598434.84
A71: 1 | C71: 기타영업외비용 | E71: 221748.15 | G71: 55078.33 | H71: 32628.88 | I71: 90873.83 | J71: 314695.43 | K71: 493276.47 | L71: 66346.55 | M71: 37463.21 | N71: 17417.84 | O71: 110348.7 | P71: 231576.3 | Q71: 53885.31 | R71: 26147.99 | S71: 599306.41 | T71: -11741.38 | U71: 667598.33 | V71: 47075.42 | W71: 1284749.6 | X71: 38171.85 | Y71: -218690.86 | Z71: 1151306 | AA71: 60272.63 | AB71: 52862.41
A72: 1 | C72: 법인세비용차감전계속사업이익 | E72: -706838.86 | G72: -237799.77 | H72: -92409.26 | I72: 71831.43 | J72: -161117.37 | K72: -419494.97 | L72: -28181.83 | M72: 32663.58 | N72: -13685.24 | O72: 39213.63 | P72: 30010.14 | Q72: 30843.91 | R72: 200158.52 | S72: 84329.63 | T72: 479202.7 | U72: 794534.76 | V72: 377751.27 | W72: 277973.23 | X72: 573248.75 | Y72: 580574.29 | Z72: 1809547.5 | AA72: 1050879.1 | AB72: 1151171.9
A73: 1 | C73: 법인세비용 | E73: -186492.22 | G73: -62271.66 | H73: -28912.96 | I73: 20348.7 | J73: 1416.76 | K73: -69419.16 | L73: -6159.72 | M73: 9366.69 | N73: -3555.03 | O73: 9028.75 | P73: 8680.69 | Q73: 771.81 | R73: 47871 | S73: 14232.36 | T73: 113324.95 | U73: 176200.12 | V73: 92629.45 | W73: 68867.32 | X73: 141182.74 | Y73: 84386.77 | Z73: 387066.28 | AA73: 282312.63 | AB73: 333304.47
A74: 1 | C74: 금융손익 | E74: -15047.26 | G74: -33467.52 | H74: -641347.37 | I74: -1251306.3 | J74: 1473718.3 | K74: -452402.83 | L74: -375077.36 | M74: -73640.24 | N74: -432816.71 | O74: 385845.32 | P74: -495688.99 | Q74: -631832.93 | R74: -542505.84 | S74: 470584.98 | T74: -1577335.6 | U74: -2281089.4 | V74: -153693.28 | W74: 1058912.2 | X74: -659684.89 | Y74: -492752.77 | Z74: -247218.77 | AA74: -1027040.9 | AB74: -430074.43
A75: 1 | C75: 기타영업외손익 | E75: -210727.53 | G75: 12713.41 | H75: 656103.6 | I75: 1307843.5 | J75: -1656955.4 | K75: 319705.1 | L75: 389249.91 | M75: 38506.31 | N75: 406330.66 | O75: -486193.73 | P75: 347893.15 | Q75: 639683.92 | R75: 548867.14 | S75: -589774.58 | T75: 1774304.2 | U75: 2373080.7 | V75: 96004.7 | W75: -1250150.2 | X75: 672794.44 | Y75: 495391.39 | Z75: 14040.34 | AA75: 1177875.2 | AB75: 545572.43
A76: 1 | C76: 당기순이익 | G76: -175528.11 | H76: -63496.3 | I76: 51482.73 | J76: -162534.12 | K76: -350075.8 | L76: -22022.11 | M76: 23296.89 | N76: -10130.21 | O76: 30184.89 | P76: 21329.46 | Q76: 30072.1 | R76: 152287.52 | S76: 70097.27 | T76: 365877.75 | U76: 618334.64 | V76: 285121.82 | W76: 209105.91 | X76: 432066.01 | Y76: 496187.53 | Z76: 1422481.3 | AA76: 768566.43 | AB76: 817867.46
A77: 1 | C77: 총포괄손익 | G77: -142467.33 | H77: -63960.64 | I77: 53337.61 | J77: -150924.65 | K77: -304015.01 | L77: -25747.47 | M77: 19948.7 | N77: -12348.4 | O77: -65297.91 | P77: -83445.08 | Q77: 24339.53 | R77: 150964.04 | S77: 76283.87 | T77: 243221.24 | U77: 494808.68 | V77: 288197.59 | W77: 375708.47 | X77: 432103.58 | Y77: 504967.85 | Z77: 1600977.5 | AA77: 768124.19 | AB77: 819455.09
A78: 1 | C78: (지배주주지분)당기순이익 | G78: -175528.11 | H78: -63496.3 | I78: 51482.73 | J78: -162534.12 | K78: -350075.8 | L78: -22022.11 | M78: 23296.89 | N78: -10130.21 | O78: 30184.89 | P78: 21329.46 | Q78: 30072.1 | R78: 152287.52 | S78: 70097.27 | T78: 365877.75 | U78: 618334.64 | V78: 285121.82 | W78: 209105.91 | X78: 432066.01 | Y78: 496187.53 | Z78: 1422481.3 | AA78: 768566.43 | AB78: 817867.46
A79: 1 | C79: 계속사업이익 | G79: -175528.11 | H79: -63496.3 | I79: 51482.73 | J79: -162534.12 | K79: -350075.8 | L79: -22022.11 | M79: 23296.89 | N79: -10130.21 | O79: 30184.89 | P79: 21329.46 | Q79: 30072.1 | R79: 152287.52 | S79: 70097.27 | T79: 365877.75 | U79: 618334.64 | V79: 285121.82 | W79: 209105.91 | X79: 432066.01 | Y79: 496187.53 | Z79: 1422481.3 | AA79: 768566.43 | AB79: 817867.46
A80: 1 | C80: 영업활동으로인한현금흐름 | E80: 1573.97 | G80: -160076.74 | H80: 161027.93 | I80: 130953.82 | J80: -66216.1 | K80: 65688.91 | L80: 80408.49 | M80: -384495.16 | N80: 258535.03 | O80: 226184.76 | P80: 180633.12 | Q80: 310529.44 | R80: 1052308.7 | S80: 51576.64 | T80: 1471966.2 | U80: 2886381 | V80: 1714140.3 | W80: 511994.49 | X80: 1568730.4 | Y80: -265885.04 | Z80: 3528980.2 | AA80: 888566.71 | AB80: 1831450
A81: 1 | C81: 이자수취(CF) | E81: 4098.61 | G81: 8545.23 | H81: 7243.78 | I81: 12668.17 | J81: 12633.49 | K81: 41090.67 | L81: 15335.58 | M81: 9298.11 | N81: 5779.18 | O81: 17518.73 | P81: 47931.6 | Q81: 24174.41 | R81: 9190.09 | S81: 13755.28 | T81: 10369.37 | U81: 57489.15 | V81: 19633.7 | W81: 18409.17 | X81: 22507.23 | Y81: 21101.09 | Z81: 81651.19 | AA81: 30367.15 | AB81: 34175.21
A82: 1 | C82: 이자지급(CF) | E82: -23531.8 | G82: -20598.43 | H82: -12777.41 | I82: -24081.86 | J82: -19249.24 | K82: -76706.94 | L82: -28610.82 | M82: -20496.97 | N82: -21565.93 | O82: -45286.56 | P82: -115960.28 | Q82: -44661.46 | R82: -26492.25 | S82: -32045.35 | T82: -10984.62 | U82: -114183.68 | V82: -18305.45 | W82: -5494.25 | X82: -14448.37 | Y82: -653.11 | Z82: -38901.18 | AA82: -11426.3 | AB82: 1608.53
A83: 1 | C83: 배당금수취(CF) | E83: 0 | I83: 0 | J83: 0 | N83: 0 | O83: 0 | S83: 0 | T83: 0 | X83: 0 | Y83: 0
A84: 1 | C84: 법인세납부(CF) | E84: -1025.21 | G84: -1233.28 | H84: 1207.19 | I84: -2338.87 | J84: -2362.16 | K84: -4727.12 | L84: -1648.37 | M84: 2226.05 | N84: -1133.45 | O84: -1907.29 | P84: -2463.06 | Q84: -898.9 | R84: 2777.83 | S84: -1787.32 | T84: -2147.58 | U84: -2055.97 | V84: -6367.21 | W84: -11569.91 | X84: -28451.08 | Y84: -4245.45 | Z84: -50633.65 | AA84: -17576.28 | AB84: -30907.02
A85: 1 | C85: 투자활동으로인한현금흐름 | E85: -20996.74 | G85: -117911.95 | H85: -112135.67 | I85: -120527.51 | J85: -173402.73 | K85: -523977.86 | L85: -108332.25 | M85: -102685.83 | N85: -151003.64 | O85: -136987.42 | P85: -499009.14 | Q85: -110386.58 | R85: -127618.04 | S85: -137451.8 | T85: -113788.04 | U85: -489244.46 | V85: -187357.93 | W85: -459393.67 | X85: -1317372.5 | Y85: -112736.46 | Z85: -2076860.5 | AA85: 286249.25 | AB85: 245669.33
A86: 1 | C86: 유형자산의감소 | E86: 2056.39 | G86: 2423.13 | H86: 5774.83 | I86: 2584.44 | J86: 2013.74 | K86: 12796.14 | L86: 1966.89 | M86: 4265.44 | N86: 1384.99 | O86: 2335.43 | P86: 9952.75 | Q86: 8087.27 | R86: 1538.64 | S86: 1694.02 | T86: 417.81 | U86: 11737.74 | V86: 970.67 | W86: 1531.16 | X86: 1564.93 | Y86: 10949 | Z86: 15015.76 | AA86: 1074.54 | AB86: 1287.01
A87: 1 | C87: 무형자산의감소 | E87: 0 | I87: 0 | J87: 0 | Y87: 4302.04
A88: 1 | C88: 유형자산의증가 | E88: 62309.07 | G88: 91812.63 | H88: 86365.39 | I88: 144449.09 | J88: 153905.05 | K88: 476532.16 | L88: 104819.95 | M88: 126436.33 | N88: 118594.16 | O88: 111933.74 | P88: 461784.18 | Q88: 115992.08 | R88: 122080.79 | S88: 119537.03 | T88: 99842.71 | U88: 457452.61 | V88: 100805.86 | W88: 103973.13 | X88: 124109.67 | Y88: 105473.35 | Z88: 434362.01 | AA88: 121060.15 | AB88: 109642.63
A89: 1 | C89: CAPEX | E89: 78358.88 | G89: 95114.82 | H89: 90933.92 | I89: 153122.74 | J89: 166599.82 | K89: 505771.3 | L89: 110250.98 | M89: 134111.89 | N89: 127661.88 | O89: 124125.13 | P89: 496149.88 | Q89: 122450.98 | R89: 128466.98 | S89: 125447.14 | T89: 114219.33 | U89: 490584.43 | V89: 104825.84 | W89: 110011.51 | X89: 129839.66 | Y89: 119231.15 | Z89: 463908.16 | AA89: 124986.36 | AB89: 117909.15
A90: 1 | C90: 무형자산의증가 | E90: 16049.81 | G90: 3302.19 | H90: 4568.53 | I90: 8673.65 | J90: 12694.77 | K90: 29239.14 | L90: 5431.03 | M90: 7675.56 | N90: 9067.72 | O90: 12191.39 | P90: 34365.7 | Q90: 6458.9 | R90: 6386.19 | S90: 5910.11 | T90: 14376.62 | U90: 33131.82 | V90: 4019.98 | W90: 6038.38 | X90: 5729.99 | Y90: 13757.8 | Z90: 29546.15 | AA90: 3926.21 | AB90: 8266.52
A91: 1 | C91: 재무활동으로인한현금흐름 | E91: -622870.95 | G91: -95341.23 | H91: -178100.03 | I91: -144800.01 | J91: -523571.02 | K91: -941812.29 | L91: 138329.85 | M91: 414859.12 | N91: 113812.22 | O91: -164205.59 | P91: 502795.6 | Q91: -387458.35 | R91: -887784.62 | S91: -410544.13 | T91: -362987.12 | U91: -2048774.2 | V91: -62067.46 | W91: -425007 | X91: -246214.81 | Y91: -121852.78 | Z91: -855142.05 | AA91: -69748.71 | AB91: -512391.71
A92: 1 | C92: 리스부채의상환 | E92: 2453.37 | G92: 1865.73 | H92: 3081.19 | I92: 2311.65 | J92: 2350.88 | K92: 9609.45 | L92: 2924.79 | M92: 4385.08 | N92: 3619.1 | O92: 2837.6 | P92: 13766.57 | Q92: 3277.2 | R92: 4411.36 | S92: 3686.64 | T92: 2855.88 | U92: 14231.08 | V92: 3508.69 | W92: 4540.76 | X92: 3723.92 | Y92: 3355.83 | Z92: 15129.2 | AA92: 4748.71 | AB92: 5710.36
A93: 1 | C93: 현금및현금성자산의증감 | E93: -642160.02 | G93: -373392.58 | H93: -129596.13 | I93: -135246.67 | J93: -775641.06 | K93: -1413876.4 | L93: 113066.44 | M93: -75586.1 | N93: 220641.45 | O93: -81177.28 | P93: 176944.51 | Q93: -191636.97 | R93: 40171.06 | S93: -494429.3 | T93: 988377.05 | U93: 342481.84 | V93: 1465422.8 | W93: -369904.4 | X93: -3936.45 | Y93: -492074.18 | Z93: 599507.75 | AA93: 1103449.7 | AB93: 1567373.2
A94: 1 | C94: 기말현금및현금성자산 | E94: -642160.02 | G94: 1763733.1 | H94: -129596.13 | I94: -135246.67 | J94: -775641.06 | K94: 723249.2 | L94: 836315.64 | M94: -75586.1 | N94: 220641.45 | O94: -81177.28 | P94: 900193.71 | Q94: 708556.74 | R94: 40171.06 | S94: -494429.3 | T94: 988377.05 | U94: 1242675.6 | V94: 2708098.3 | W94: -369904.4 | X94: -3936.45 | Y94: -492074.18 | Z94: 1842183.3 | AA94: 2945633 | AB94: 1567373.2
A95: 1 | C95: 배당금지급 | X95: 148339.88 | Y95: 0

Sheet subQ
A1: YQ | C1: subQ 분기 서브모델(억원, U=100) | E1: 4Q21 | F1: 2021 | G1: 1Q22 | H1: 2Q22 | I1: 3Q22 | J1: 4Q22 | K1: 2022 | L1: 1Q23 | M1: 2Q23 | N1: 3Q23 | O1: 4Q23 | P1: 2023 | Q1: 1Q24 | R1: 2Q24 | S1: 3Q24 | T1: 4Q24 | U1: 2024 | V1: 1Q25 | W1: 2Q25 | X1: 3Q25 | Y1: 4Q25 | Z1: 2025 | AA1: 1Q26 | AB1: 2Q26 | AC1: 3Q26 | AD1: 4Q26 | AE1: 2026 | AF1: 1Q27 | AG1: 2Q27 | AH1: 3Q27 | AI1: 4Q27 | AJ1: 2027 | AK1: 1Q28 | AL1: 2Q28 | AM1: 3Q28 | AN1: 4Q28 | AO1: 2028
A2: A=이름(key) B=그룹 C=단위 D=FnGuide 계정명(VLOOKUP 키). 확정=VLOOKUP(BS), 추정=변수 가정 참조
E3: 1 | F3: 2 | G3: 3 | H3: 4 | I3: 5 | J3: 6 | K3: 7 | L3: 8 | M3: 9 | N3: 10 | O3: 11 | P3: 12 | Q3: 13 | R3: 14 | S3: 15 | T3: 16 | U3: 17 | V3: 18 | W3: 19 | X3: 20 | Y3: 21 | Z3: 22 | AA3: 23 | AB3: 24 | AC3: 25 | AD3: 26 | AE3: 27 | AF3: 28 | AG3: 29 | AH3: 30 | AI3: 31 | AJ3: 32 | AK3: 33 | AL3: 34 | AM3: 35 | AN3: 36 | AO3: 37
E4: 2021.12 | F4: 2021.12A | G4: 2022.03 | H4: 2022.06 | I4: 2022.09 | J4: 2022.12 | K4: 2022.12A | L4: 2023.03 | M4: 2023.06 | N4: 2023.09 | O4: 2023.12 | P4: 2023.12A | Q4: 2024.03 | R4: 2024.06 | S4: 2024.09 | T4: 2024.12 | U4: 2024.12A | V4: 2025.03 | W4: 2025.06 | X4: 2025.09 | Y4: 2025.12 | Z4: 2025.12A | AA4: 2026.03 | AB4: 2026.06 | AC4: 2026.09 | AD4: 2026.12 | AE4: 2026.12A | AF4: 2027.03 | AG4: 2027.06 | AH4: 2027.09 | AI4: 2027.12 | AJ4: 2027.12A | AK4: 2028.03 | AL4: 2028.06 | AM4: 2028.09 | AN4: 2028.12 | AO4: 2028.12A
A5: 매출액 | B5: 손익 | C5: 억원 | D5: 매출액(수익) | E5: =IFERROR(VLOOKUP($D5,BS연결,MATCH(E$1,BS연결H,0),0)/100,"") | G5: =IFERROR(VLOOKUP($D5,BS연결,MATCH(G$1,BS연결H,0),0)/100,"") | H5: =IFERROR(VLOOKUP($D5,BS연결,MATCH(H$1,BS연결H,0),0)/100,"") | I5: =IFERROR(VLOOKUP($D5,BS연결,MATCH(I$1,BS연결H,0),0)/100,"") | J5: =IFERROR(VLOOKUP($D5,BS연결,MATCH(J$1,BS연결H,0),0)/100,"") | K5: =IFERROR(VLOOKUP($D5,BS연결,MATCH(K$1,BS연결H,0),0)/100,"") | L5: =IFERROR(VLOOKUP($D5,BS연결,MATCH(L$1,BS연결H,0),0)/100,"") | M5: =IFERROR(VLOOKUP($D5,BS연결,MATCH(M$1,BS연결H,0),0)/100,"") | N5: =IFERROR(VLOOKUP($D5,BS연결,MATCH(N$1,BS연결H,0),0)/100,"") | ... AB5: =IFERROR(VLOOKUP($D5,BS연결,MATCH(AB$1,BS연결H,0),0)/100,"") | AC5: =IFERROR(AC39+AC43,"") | AD5: =IFERROR(AD39+AD43,"") | AE5: =SUM(AA5:AD5) | AF5: =IFERROR(AF39+AF43,"") | AG5: =IFERROR(AG39+AG43,"") | AH5: =IFERROR(AH39+AH43,"") | AI5: =IFERROR(AI39+AI43,"") | AJ5: =SUM(AF5:AI5) | AK5: =IFERROR(AK39+AK43,"") | AL5: =IFERROR(AL39+AL43,"") | AM5: =IFERROR(AM39+AM43,"") | AN5: =IFERROR(AN39+AN43,"") | AO5: =SUM(AK5:AN5)
A6: 매출원가 | B6: 손익 | C6: 억원 | D6: 매출원가 | E6: =IFERROR(VLOOKUP($D6,BS연결,MATCH(E$1,BS연결H,0),0)/100,"") | G6: =IFERROR(VLOOKUP($D6,BS연결,MATCH(G$1,BS연결H,0),0)/100,"") | H6: =IFERROR(VLOOKUP($D6,BS연결,MATCH(H$1,BS연결H,0),0)/100,"") | I6: =IFERROR(VLOOKUP($D6,BS연결,MATCH(I$1,BS연결H,0),0)/100,"") | J6: =IFERROR(VLOOKUP($D6,BS연결,MATCH(J$1,BS연결H,0),0)/100,"") | K6: =IFERROR(VLOOKUP($D6,BS연결,MATCH(K$1,BS연결H,0),0)/100,"") | L6: =IFERROR(VLOOKUP($D6,BS연결,MATCH(L$1,BS연결H,0),0)/100,"") | M6: =IFERROR(VLOOKUP($D6,BS연결,MATCH(M$1,BS연결H,0),0)/100,"") | N6: =IFERROR(VLOOKUP($D6,BS연결,MATCH(N$1,BS연결H,0),0)/100,"") | ... AB6: =IFERROR(VLOOKUP($D6,BS연결,MATCH(AB$1,BS연결H,0),0)/100,"") | AC6: =IFERROR(AC5-AC7,"") | AD6: =IFERROR(AD5-AD7,"") | AE6: =SUM(AA6:AD6) | AF6: =IFERROR(AF5-AF7,"") | AG6: =IFERROR(AG5-AG7,"") | AH6: =IFERROR(AH5-AH7,"") | AI6: =IFERROR(AI5-AI7,"") | AJ6: =SUM(AF6:AI6) | AK6: =IFERROR(AK5-AK7,"") | AL6: =IFERROR(AL5-AL7,"") | AM6: =IFERROR(AM5-AM7,"") | AN6: =IFERROR(AN5-AN7,"") | AO6: =SUM(AK6:AN6)
A7: 매출총이익 | B7: 손익 | C7: 억원 | D7: 매출총이익 | E7: =IFERROR(VLOOKUP($D7,BS연결,MATCH(E$1,BS연결H,0),0)/100,"") | G7: =IFERROR(VLOOKUP($D7,BS연결,MATCH(G$1,BS연결H,0),0)/100,"") | H7: =IFERROR(VLOOKUP($D7,BS연결,MATCH(H$1,BS연결H,0),0)/100,"") | I7: =IFERROR(VLOOKUP($D7,BS연결,MATCH(I$1,BS연결H,0),0)/100,"") | J7: =IFERROR(VLOOKUP($D7,BS연결,MATCH(J$1,BS연결H,0),0)/100,"") | K7: =IFERROR(VLOOKUP($D7,BS연결,MATCH(K$1,BS연결H,0),0)/100,"") | L7: =IFERROR(VLOOKUP($D7,BS연결,MATCH(L$1,BS연결H,0),0)/100,"") | M7: =IFERROR(VLOOKUP($D7,BS연결,MATCH(M$1,BS연결H,0),0)/100,"") | N7: =IFERROR(VLOOKUP($D7,BS연결,MATCH(N$1,BS연결H,0),0)/100,"") | ... AB7: =IFERROR(VLOOKUP($D7,BS연결,MATCH(AB$1,BS연결H,0),0)/100,"") | AC7: =IFERROR(AC9+AC8,"") | AD7: =IFERROR(AD9+AD8,"") | AE7: =SUM(AA7:AD7) | AF7: =IFERROR(AF9+AF8,"") | AG7: =IFERROR(AG9+AG8,"") | AH7: =IFERROR(AH9+AH8,"") | AI7: =IFERROR(AI9+AI8,"") | AJ7: =SUM(AF7:AI7) | AK7: =IFERROR(AK9+AK8,"") | AL7: =IFERROR(AL9+AL8,"") | AM7: =IFERROR(AM9+AM8,"") | AN7: =IFERROR(AN9+AN8,"") | AO7: =SUM(AK7:AN7)
A8: 판관비 | B8: 손익 | C8: 억원 | D8: 판관비 | E8: =IFERROR(VLOOKUP($D8,BS연결,MATCH(E$1,BS연결H,0),0)/100,"") | G8: =IFERROR(VLOOKUP($D8,BS연결,MATCH(G$1,BS연결H,0),0)/100,"") | H8: =IFERROR(VLOOKUP($D8,BS연결,MATCH(H$1,BS연결H,0),0)/100,"") | I8: =IFERROR(VLOOKUP($D8,BS연결,MATCH(I$1,BS연결H,0),0)/100,"") | J8: =IFERROR(VLOOKUP($D8,BS연결,MATCH(J$1,BS연결H,0),0)/100,"") | K8: =IFERROR(VLOOKUP($D8,BS연결,MATCH(K$1,BS연결H,0),0)/100,"") | L8: =IFERROR(VLOOKUP($D8,BS연결,MATCH(L$1,BS연결H,0),0)/100,"") | M8: =IFERROR(VLOOKUP($D8,BS연결,MATCH(M$1,BS연결H,0),0)/100,"") | N8: =IFERROR(VLOOKUP($D8,BS연결,MATCH(N$1,BS연결H,0),0)/100,"") | ... AB8: =IFERROR(VLOOKUP($D8,BS연결,MATCH(AB$1,BS연결H,0),0)/100,"") | AC8: =IFERROR(AC5*변수!AC21,"") | AD8: =IFERROR(AD5*변수!AD21,"") | AE8: =SUM(AA8:AD8) | AF8: =IFERROR(AF5*변수!AF21,"") | AG8: =IFERROR(AG5*변수!AG21,"") | AH8: =IFERROR(AH5*변수!AH21,"") | AI8: =IFERROR(AI5*변수!AI21,"") | AJ8: =SUM(AF8:AI8) | AK8: =IFERROR(AK5*변수!AK21,"") | AL8: =IFERROR(AL5*변수!AL21,"") | AM8: =IFERROR(AM5*변수!AM21,"") | AN8: =IFERROR(AN5*변수!AN21,"") | AO8: =SUM(AK8:AN8)
A9: 영업이익 | B9: 손익 | C9: 억원 | D9: 영업이익 | E9: =IFERROR(VLOOKUP($D9,BS연결,MATCH(E$1,BS연결H,0),0)/100,"") | G9: =IFERROR(VLOOKUP($D9,BS연결,MATCH(G$1,BS연결H,0),0)/100,"") | H9: =IFERROR(VLOOKUP($D9,BS연결,MATCH(H$1,BS연결H,0),0)/100,"") | I9: =IFERROR(VLOOKUP($D9,BS연결,MATCH(I$1,BS연결H,0),0)/100,"") | J9: =IFERROR(VLOOKUP($D9,BS연결,MATCH(J$1,BS연결H,0),0)/100,"") | K9: =IFERROR(VLOOKUP($D9,BS연결,MATCH(K$1,BS연결H,0),0)/100,"") | L9: =IFERROR(VLOOKUP($D9,BS연결,MATCH(L$1,BS연결H,0),0)/100,"") | M9: =IFERROR(VLOOKUP($D9,BS연결,MATCH(M$1,BS연결H,0),0)/100,"") | N9: =IFERROR(VLOOKUP($D9,BS연결,MATCH(N$1,BS연결H,0),0)/100,"") | ... AB9: =IFERROR(VLOOKUP($D9,BS연결,MATCH(AB$1,BS연결H,0),0)/100,"") | AC9: =IFERROR(AC41+AC44,"") | AD9: =IFERROR(AD41+AD44,"") | AE9: =SUM(AA9:AD9) | AF9: =IFERROR(AF41+AF44,"") | AG9: =IFERROR(AG41+AG44,"") | AH9: =IFERROR(AH41+AH44,"") | AI9: =IFERROR(AI41+AI44,"") | AJ9: =SUM(AF9:AI9) | AK9: =IFERROR(AK41+AK44,"") | AL9: =IFERROR(AL41+AL44,"") | AM9: =IFERROR(AM41+AM44,"") | AN9: =IFERROR(AN41+AN44,"") | AO9: =SUM(AK9:AN9)
A10: OPM | B10: 손익 | C10: % | D10: 영업이익률 | E10: =IFERROR(E9/E5,"") | G10: =IFERROR(G9/G5,"") | H10: =IFERROR(H9/H5,"") | I10: =IFERROR(I9/I5,"") | J10: =IFERROR(J9/J5,"") | K10: =IFERROR(K9/K5,"") | L10: =IFERROR(L9/L5,"") | M10: =IFERROR(M9/M5,"") | N10: =IFERROR(N9/N5,"") | ... AO10: =IFERROR(AO9/AO5,"")
A11: 금융손익 | B11: 손익 | C11: 억원 | D11: 금융손익 | E11: =IFERROR(VLOOKUP($D11,BS연결,MATCH(E$1,BS연결H,0),0)/100,"") | G11: =IFERROR(VLOOKUP($D11,BS연결,MATCH(G$1,BS연결H,0),0)/100,"") | H11: =IFERROR(VLOOKUP($D11,BS연결,MATCH(H$1,BS연결H,0),0)/100,"") | I11: =IFERROR(VLOOKUP($D11,BS연결,MATCH(I$1,BS연결H,0),0)/100,"") | J11: =IFERROR(VLOOKUP($D11,BS연결,MATCH(J$1,BS연결H,0),0)/100,"") | K11: =IFERROR(VLOOKUP($D11,BS연결,MATCH(K$1,BS연결H,0),0)/100,"") | L11: =IFERROR(VLOOKUP($D11,BS연결,MATCH(L$1,BS연결H,0),0)/100,"") | M11: =IFERROR(VLOOKUP($D11,BS연결,MATCH(M$1,BS연결H,0),0)/100,"") | N11: =IFERROR(VLOOKUP($D11,BS연결,MATCH(N$1,BS연결H,0),0)/100,"") | ... AB11: =IFERROR(VLOOKUP($D11,BS연결,MATCH(AB$1,BS연결H,0),0)/100,"") | AC11: =IFERROR(AC12+AC13+AC14+AC15,"") | AD11: =IFERROR(AD12+AD13+AD14+AD15,"") | AE11: =SUM(AA11:AD11) | AF11: =IFERROR(AF12+AF13+AF14+AF15,"") | AG11: =IFERROR(AG12+AG13+AG14+AG15,"") | AH11: =IFERROR(AH12+AH13+AH14+AH15,"") | AI11: =IFERROR(AI12+AI13+AI14+AI15,"") | AJ11: =SUM(AF11:AI11) | AK11: =IFERROR(AK12+AK13+AK14+AK15,"") | AL11: =IFERROR(AL12+AL13+AL14+AL15,"") | AM11: =IFERROR(AM12+AM13+AM14+AM15,"") | AN11: =IFERROR(AN12+AN13+AN14+AN15,"") | AO11: =SUM(AK11:AN11)
A12: 이자손익 | B12: 손익 | C12: 억원 | D12: 이자손익 | G12: =IFERROR(VLOOKUP($D12,BS연결,MATCH(G$1,BS연결H,0),0)/100,"") | H12: =IFERROR(VLOOKUP($D12,BS연결,MATCH(H$1,BS연결H,0),0)/100,"") | I12: =IFERROR(VLOOKUP($D12,BS연결,MATCH(I$1,BS연결H,0),0)/100,"") | J12: =IFERROR(VLOOKUP($D12,BS연결,MATCH(J$1,BS연결H,0),0)/100,"") | K12: =IFERROR(VLOOKUP($D12,BS연결,MATCH(K$1,BS연결H,0),0)/100,"") | L12: =IFERROR(VLOOKUP($D12,BS연결,MATCH(L$1,BS연결H,0),0)/100,"") | M12: =IFERROR(VLOOKUP($D12,BS연결,MATCH(M$1,BS연결H,0),0)/100,"") | N12: =IFERROR(VLOOKUP($D12,BS연결,MATCH(N$1,BS연결H,0),0)/100,"") | ... AB12: =IFERROR(VLOOKUP($D12,BS연결,MATCH(AB$1,BS연결H,0),0)/100,"") | AC12: =IFERROR((AB29*변수!$D$57-AB27*변수!$D$58)/4,"") | AD12: =IFERROR((AC29*변수!$D$57-AC27*변수!$D$58)/4,"") | AE12: =SUM(AA12:AD12) | AF12: =IFERROR((AD29*변수!$D$57-AD27*변수!$D$58)/4,"") | AG12: =IFERROR((AF29*변수!$D$57-AF27*변수!$D$58)/4,"") | AH12: =IFERROR((AG29*변수!$D$57-AG27*변수!$D$58)/4,"") | AI12: =IFERROR((AH29*변수!$D$57-AH27*변수!$D$58)/4,"") | AJ12: =SUM(AF12:AI12) | AK12: =IFERROR((AI29*변수!$D$57-AI27*변수!$D$58)/4,"") | AL12: =IFERROR((AK29*변수!$D$57-AK27*변수!$D$58)/4,"") | AM12: =IFERROR((AL29*변수!$D$57-AL27*변수!$D$58)/4,"") | AN12: =IFERROR((AM29*변수!$D$57-AM27*변수!$D$58)/4,"") | AO12: =SUM(AK12:AN12)
A13: 외환손익 | B13: 손익 | C13: 억원 | D13: 외환손익(실적만; 추정 환효과는 환관련손익) | G13: =IFERROR((VLOOKUP("외환차익",BS연결,MATCH(G$1,BS연결H,0),0)-VLOOKUP("외환차손",BS연결,MATCH(G$1,BS연결H,0),0)+VLOOKUP("외화환산이익",BS연결,MATCH(G$1,BS연결H,0),0)-VLOOKUP("외화환산손실",BS연결,MATCH(G$1,BS연결H,0),0))/100,"") | H13: =IFERROR((VLOOKUP("외환차익",BS연결,MATCH(H$1,BS연결H,0),0)-VLOOKUP("외환차손",BS연결,MATCH(H$1,BS연결H,0),0)+VLOOKUP("외화환산이익",BS연결,MATCH(H$1,BS연결H,0),0)-VLOOKUP("외화환산손실",BS연결,MATCH(H$1,BS연결H,0),0))/100,"") | I13: =IFERROR((VLOOKUP("외환차익",BS연결,MATCH(I$1,BS연결H,0),0)-VLOOKUP("외환차손",BS연결,MATCH(I$1,BS연결H,0),0)+VLOOKUP("외화환산이익",BS연결,MATCH(I$1,BS연결H,0),0)-VLOOKUP("외화환산손실",BS연결,MATCH(I$1,BS연결H,0),0))/100,"") | J13: =IFERROR((VLOOKUP("외환차익",BS연결,MATCH(J$1,BS연결H,0),0)-VLOOKUP("외환차손",BS연결,MATCH(J$1,BS연결H,0),0)+VLOOKUP("외화환산이익",BS연결,MATCH(J$1,BS연결H,0),0)-VLOOKUP("외화환산손실",BS연결,MATCH(J$1,BS연결H,0),0))/100,"") | K13: =SUM(G13:J13) | L13: =IFERROR((VLOOKUP("외환차익",BS연결,MATCH(L$1,BS연결H,0),0)-VLOOKUP("외환차손",BS연결,MATCH(L$1,BS연결H,0),0)+VLOOKUP("외화환산이익",BS연결,MATCH(L$1,BS연결H,0),0)-VLOOKUP("외화환산손실",BS연결,MATCH(L$1,BS연결H,0),0))/100,"") | M13: =IFERROR((VLOOKUP("외환차익",BS연결,MATCH(M$1,BS연결H,0),0)-VLOOKUP("외환차손",BS연결,MATCH(M$1,BS연결H,0),0)+VLOOKUP("외화환산이익",BS연결,MATCH(M$1,BS연결H,0),0)-VLOOKUP("외화환산손실",BS연결,MATCH(M$1,BS연결H,0),0))/100,"") | N13: =IFERROR((VLOOKUP("외환차익",BS연결,MATCH(N$1,BS연결H,0),0)-VLOOKUP("외환차손",BS연결,MATCH(N$1,BS연결H,0),0)+VLOOKUP("외화환산이익",BS연결,MATCH(N$1,BS연결H,0),0)-VLOOKUP("외화환산손실",BS연결,MATCH(N$1,BS연결H,0),0))/100,"") | O13: =IFERROR((VLOOKUP("외환차익",BS연결,MATCH(O$1,BS연결H,0),0)-VLOOKUP("외환차손",BS연결,MATCH(O$1,BS연결H,0),0)+VLOOKUP("외화환산이익",BS연결,MATCH(O$1,BS연결H,0),0)-VLOOKUP("외화환산손실",BS연결,MATCH(O$1,BS연결H,0),0))/100,"") | P13: =SUM(L13:O13) | Q13: =IFERROR((VLOOKUP("외환차익",BS연결,MATCH(Q$1,BS연결H,0),0)-VLOOKUP("외환차손",BS연결,MATCH(Q$1,BS연결H,0),0)+VLOOKUP("외화환산이익",BS연결,MATCH(Q$1,BS연결H,0),0)-VLOOKUP("외화환산손실",BS연결,MATCH(Q$1,BS연결H,0),0))/100,"") | R13: =IFERROR((VLOOKUP("외환차익",BS연결,MATCH(R$1,BS연결H,0),0)-VLOOKUP("외환차손",BS연결,MATCH(R$1,BS연결H,0),0)+VLOOKUP("외화환산이익",BS연결,MATCH(R$1,BS연결H,0),0)-VLOOKUP("외화환산손실",BS연결,MATCH(R$1,BS연결H,0),0))/100,"") | S13: =IFERROR((VLOOKUP("외환차익",BS연결,MATCH(S$1,BS연결H,0),0)-VLOOKUP("외환차손",BS연결,MATCH(S$1,BS연결H,0),0)+VLOOKUP("외화환산이익",BS연결,MATCH(S$1,BS연결H,0),0)-VLOOKUP("외화환산손실",BS연결,MATCH(S$1,BS연결H,0),0))/100,"") | T13: =IFERROR((VLOOKUP("외환차익",BS연결,MATCH(T$1,BS연결H,0),0)-VLOOKUP("외환차손",BS연결,MATCH(T$1,BS연결H,0),0)+VLOOKUP("외화환산이익",BS연결,MATCH(T$1,BS연결H,0),0)-VLOOKUP("외화환산손실",BS연결,MATCH(T$1,BS연결H,0),0))/100,"") | U13: =SUM(Q13:T13) | V13: =IFERROR((VLOOKUP("외환차익",BS연결,MATCH(V$1,BS연결H,0),0)-VLOOKUP("외환차손",BS연결,MATCH(V$1,BS연결H,0),0)+VLOOKUP("외화환산이익",BS연결,MATCH(V$1,BS연결H,0),0)-VLOOKUP("외화환산손실",BS연결,MATCH(V$1,BS연결H,0),0))/100,"") | W13: =IFERROR((VLOOKUP("외환차익",BS연결,MATCH(W$1,BS연결H,0),0)-VLOOKUP("외환차손",BS연결,MATCH(W$1,BS연결H,0),0)+VLOOKUP("외화환산이익",BS연결,MATCH(W$1,BS연결H,0),0)-VLOOKUP("외화환산손실",BS연결,MATCH(W$1,BS연결H,0),0))/100,"") | X13: =IFERROR((VLOOKUP("외환차익",BS연결,MATCH(X$1,BS연결H,0),0)-VLOOKUP("외환차손",BS연결,MATCH(X$1,BS연결H,0),0)+VLOOKUP("외화환산이익",BS연결,MATCH(X$1,BS연결H,0),0)-VLOOKUP("외화환산손실",BS연결,MATCH(X$1,BS연결H,0),0))/100,"") | Y13: =IFERROR((VLOOKUP("외환차익",BS연결,MATCH(Y$1,BS연결H,0),0)-VLOOKUP("외환차손",BS연결,MATCH(Y$1,BS연결H,0),0)+VLOOKUP("외화환산이익",BS연결,MATCH(Y$1,BS연결H,0),0)-VLOOKUP("외화환산손실",BS연결,MATCH(Y$1,BS연결H,0),0))/100,"") | Z13: =SUM(V13:Y13) | AA13: =IFERROR((VLOOKUP("외환차익",BS연결,MATCH(AA$1,BS연결H,0),0)-VLOOKUP("외환차손",BS연결,MATCH(AA$1,BS연결H,0),0)+VLOOKUP("외화환산이익",BS연결,MATCH(AA$1,BS연결H,0),0)-VLOOKUP("외화환산손실",BS연결,MATCH(AA$1,BS연결H,0),0))/100,"") | AB13: =IFERROR((VLOOKUP("외환차익",BS연결,MATCH(AB$1,BS연결H,0),0)-VLOOKUP("외환차손",BS연결,MATCH(AB$1,BS연결H,0),0)+VLOOKUP("외화환산이익",BS연결,MATCH(AB$1,BS연결H,0),0)-VLOOKUP("외화환산손실",BS연결,MATCH(AB$1,BS연결H,0),0))/100,"") | AC13: =변수!AC22 | AD13: =변수!AD22 | AE13: =SUM(AA13:AD13) | AF13: =변수!AF22 | AG13: =변수!AG22 | AH13: =변수!AH22 | AI13: =변수!AI22 | AJ13: =SUM(AF13:AI13) | AK13: =변수!AK22 | AL13: =변수!AL22 | AM13: =변수!AM22 | AN13: =변수!AN22 | AO13: =SUM(AK13:AN13)
A14: 파생상품손익 | B14: 손익 | C14: 억원 | D14: 파생상품손익 | G14: =IFERROR((VLOOKUP("파생상품이익",BS연결,MATCH(G$1,BS연결H,0),0)-VLOOKUP("파생상품손실",BS연결,MATCH(G$1,BS연결H,0),0))/100,"") | H14: =IFERROR((VLOOKUP("파생상품이익",BS연결,MATCH(H$1,BS연결H,0),0)-VLOOKUP("파생상품손실",BS연결,MATCH(H$1,BS연결H,0),0))/100,"") | I14: =IFERROR((VLOOKUP("파생상품이익",BS연결,MATCH(I$1,BS연결H,0),0)-VLOOKUP("파생상품손실",BS연결,MATCH(I$1,BS연결H,0),0))/100,"") | J14: =IFERROR((VLOOKUP("파생상품이익",BS연결,MATCH(J$1,BS연결H,0),0)-VLOOKUP("파생상품손실",BS연결,MATCH(J$1,BS연결H,0),0))/100,"") | K14: =SUM(G14:J14) | L14: =IFERROR((VLOOKUP("파생상품이익",BS연결,MATCH(L$1,BS연결H,0),0)-VLOOKUP("파생상품손실",BS연결,MATCH(L$1,BS연결H,0),0))/100,"") | M14: =IFERROR((VLOOKUP("파생상품이익",BS연결,MATCH(M$1,BS연결H,0),0)-VLOOKUP("파생상품손실",BS연결,MATCH(M$1,BS연결H,0),0))/100,"") | N14: =IFERROR((VLOOKUP("파생상품이익",BS연결,MATCH(N$1,BS연결H,0),0)-VLOOKUP("파생상품손실",BS연결,MATCH(N$1,BS연결H,0),0))/100,"") | O14: =IFERROR((VLOOKUP("파생상품이익",BS연결,MATCH(O$1,BS연결H,0),0)-VLOOKUP("파생상품손실",BS연결,MATCH(O$1,BS연결H,0),0))/100,"") | P14: =SUM(L14:O14) | Q14: =IFERROR((VLOOKUP("파생상품이익",BS연결,MATCH(Q$1,BS연결H,0),0)-VLOOKUP("파생상품손실",BS연결,MATCH(Q$1,BS연결H,0),0))/100,"") | R14: =IFERROR((VLOOKUP("파생상품이익",BS연결,MATCH(R$1,BS연결H,0),0)-VLOOKUP("파생상품손실",BS연결,MATCH(R$1,BS연결H,0),0))/100,"") | S14: =IFERROR((VLOOKUP("파생상품이익",BS연결,MATCH(S$1,BS연결H,0),0)-VLOOKUP("파생상품손실",BS연결,MATCH(S$1,BS연결H,0),0))/100,"") | T14: =IFERROR((VLOOKUP("파생상품이익",BS연결,MATCH(T$1,BS연결H,0),0)-VLOOKUP("파생상품손실",BS연결,MATCH(T$1,BS연결H,0),0))/100,"") | U14: =SUM(Q14:T14) | V14: =IFERROR((VLOOKUP("파생상품이익",BS연결,MATCH(V$1,BS연결H,0),0)-VLOOKUP("파생상품손실",BS연결,MATCH(V$1,BS연결H,0),0))/100,"") | W14: =IFERROR((VLOOKUP("파생상품이익",BS연결,MATCH(W$1,BS연결H,0),0)-VLOOKUP("파생상품손실",BS연결,MATCH(W$1,BS연결H,0),0))/100,"") | X14: =IFERROR((VLOOKUP("파생상품이익",BS연결,MATCH(X$1,BS연결H,0),0)-VLOOKUP("파생상품손실",BS연결,MATCH(X$1,BS연결H,0),0))/100,"") | Y14: =IFERROR((VLOOKUP("파생상품이익",BS연결,MATCH(Y$1,BS연결H,0),0)-VLOOKUP("파생상품손실",BS연결,MATCH(Y$1,BS연결H,0),0))/100,"") | Z14: =SUM(V14:Y14) | AA14: =IFERROR((VLOOKUP("파생상품이익",BS연결,MATCH(AA$1,BS연결H,0),0)-VLOOKUP("파생상품손실",BS연결,MATCH(AA$1,BS연결H,0),0))/100,"") | AB14: =IFERROR((VLOOKUP("파생상품이익",BS연결,MATCH(AB$1,BS연결H,0),0)-VLOOKUP("파생상품손실",BS연결,MATCH(AB$1,BS연결H,0),0))/100,"") | AC14: =변수!AC23 | AD14: =변수!AD23 | AE14: =SUM(AA14:AD14) | AF14: =변수!AF23 | AG14: =변수!AG23 | AH14: =변수!AH23 | AI14: =변수!AI23 | AJ14: =SUM(AF14:AI14) | AK14: =변수!AK23 | AL14: =변수!AL23 | AM14: =변수!AM23 | AN14: =변수!AN23 | AO14: =SUM(AK14:AN14)
A15: 기타금융손익 | B15: 손익 | C15: 억원 | D15: 기타금융손익(금융손익 잔차) | G15: =IFERROR(G11-G12-G13-G14,"") | H15: =IFERROR(H11-H12-H13-H14,"") | I15: =IFERROR(I11-I12-I13-I14,"") | J15: =IFERROR(J11-J12-J13-J14,"") | K15: =SUM(G15:J15) | L15: =IFERROR(L11-L12-L13-L14,"") | M15: =IFERROR(M11-M12-M13-M14,"") | N15: =IFERROR(N11-N12-N13-N14,"") | O15: =IFERROR(O11-O12-O13-O14,"") | P15: =SUM(L15:O15) | Q15: =IFERROR(Q11-Q12-Q13-Q14,"") | R15: =IFERROR(R11-R12-R13-R14,"") | S15: =IFERROR(S11-S12-S13-S14,"") | T15: =IFERROR(T11-T12-T13-T14,"") | U15: =SUM(Q15:T15) | V15: =IFERROR(V11-V12-V13-V14,"") | W15: =IFERROR(W11-W12-W13-W14,"") | X15: =IFERROR(X11-X12-X13-X14,"") | Y15: =IFERROR(Y11-Y12-Y13-Y14,"") | Z15: =SUM(V15:Y15) | AA15: =IFERROR(AA11-AA12-AA13-AA14,"") | AB15: =IFERROR(AB11-AB12-AB13-AB14,"") | AC15: =변수!AC24 | AD15: =변수!AD24 | AE15: =SUM(AA15:AD15) | AF15: =변수!AF24 | AG15: =변수!AG24 | AH15: =변수!AH24 | AI15: =변수!AI24 | AJ15: =SUM(AF15:AI15) | AK15: =변수!AK24 | AL15: =변수!AL24 | AM15: =변수!AM24 | AN15: =변수!AN24 | AO15: =SUM(AK15:AN15)
A16: 기타영업외손익 | B16: 손익 | C16: 억원 | D16: 기타영업외손익 | E16: =IFERROR(VLOOKUP($D16,BS연결,MATCH(E$1,BS연결H,0),0)/100,"") | G16: =IFERROR(VLOOKUP($D16,BS연결,MATCH(G$1,BS연결H,0),0)/100,"") | H16: =IFERROR(VLOOKUP($D16,BS연결,MATCH(H$1,BS연결H,0),0)/100,"") | I16: =IFERROR(VLOOKUP($D16,BS연결,MATCH(I$1,BS연결H,0),0)/100,"") | J16: =IFERROR(VLOOKUP($D16,BS연결,MATCH(J$1,BS연결H,0),0)/100,"") | K16: =IFERROR(VLOOKUP($D16,BS연결,MATCH(K$1,BS연결H,0),0)/100,"") | L16: =IFERROR(VLOOKUP($D16,BS연결,MATCH(L$1,BS연결H,0),0)/100,"") | M16: =IFERROR(VLOOKUP($D16,BS연결,MATCH(M$1,BS연결H,0),0)/100,"") | N16: =IFERROR(VLOOKUP($D16,BS연결,MATCH(N$1,BS연결H,0),0)/100,"") | ... AB16: =IFERROR(VLOOKUP($D16,BS연결,MATCH(AB$1,BS연결H,0),0)/100,"") | AC16: =변수!AC25 | AD16: =변수!AD25 | AE16: =SUM(AA16:AD16) | AF16: =변수!AF25 | AG16: =변수!AG25 | AH16: =변수!AH25 | AI16: =변수!AI25 | AJ16: =SUM(AF16:AI16) | AK16: =변수!AK25 | AL16: =변수!AL25 | AM16: =변수!AM25 | AN16: =변수!AN25 | AO16: =SUM(AK16:AN16)
A17: 지분법손익 | B17: 손익 | C17: 억원 | D17: 종속기업,공동지배기업및관계기업관련손익 | E17: =IFERROR(VLOOKUP($D17,BS연결,MATCH(E$1,BS연결H,0),0)/100,"") | G17: =IFERROR(VLOOKUP($D17,BS연결,MATCH(G$1,BS연결H,0),0)/100,"") | H17: =IFERROR(VLOOKUP($D17,BS연결,MATCH(H$1,BS연결H,0),0)/100,"") | I17: =IFERROR(VLOOKUP($D17,BS연결,MATCH(I$1,BS연결H,0),0)/100,"") | J17: =IFERROR(VLOOKUP($D17,BS연결,MATCH(J$1,BS연결H,0),0)/100,"") | K17: =IFERROR(VLOOKUP($D17,BS연결,MATCH(K$1,BS연결H,0),0)/100,"") | L17: =IFERROR(VLOOKUP($D17,BS연결,MATCH(L$1,BS연결H,0),0)/100,"") | M17: =IFERROR(VLOOKUP($D17,BS연결,MATCH(M$1,BS연결H,0),0)/100,"") | N17: =IFERROR(VLOOKUP($D17,BS연결,MATCH(N$1,BS연결H,0),0)/100,"") | ... AB17: =IFERROR(VLOOKUP($D17,BS연결,MATCH(AB$1,BS연결H,0),0)/100,"") | AC17: =변수!AC26 | AD17: =변수!AD26 | AE17: =SUM(AA17:AD17) | AF17: =변수!AF26 | AG17: =변수!AG26 | AH17: =변수!AH26 | AI17: =변수!AI26 | AJ17: =SUM(AF17:AI17) | AK17: =변수!AK26 | AL17: =변수!AL26 | AM17: =변수!AM26 | AN17: =변수!AN26 | AO17: =SUM(AK17:AN17)
A18: 환관련손익 | B18: 손익 | C18: 억원 | D18: 환관련손익(모델 추정분) | K18: =SUM(G18:J18) | P18: =SUM(L18:O18) | U18: =SUM(Q18:T18) | Z18: =SUM(V18:Y18) | AC18: =IFERROR(변수!$D$60*(변수!AC7-변수!AB7)/100,"") | AD18: =IFERROR(변수!$D$60*(변수!AD7-변수!AC7)/100,"") | AE18: =SUM(AA18:AD18) | AF18: =IFERROR(변수!$D$60*(변수!AF7-변수!AD7)/100,"") | AG18: =IFERROR(변수!$D$60*(변수!AG7-변수!AF7)/100,"") | AH18: =IFERROR(변수!$D$60*(변수!AH7-변수!AG7)/100,"") | AI18: =IFERROR(변수!$D$60*(변수!AI7-변수!AH7)/100,"") | AJ18: =SUM(AF18:AI18) | AK18: =IFERROR(변수!$D$60*(변수!AK7-변수!AI7)/100,"") | AL18: =IFERROR(변수!$D$60*(변수!AL7-변수!AK7)/100,"") | AM18: =IFERROR(변수!$D$60*(변수!AM7-변수!AL7)/100,"") | AN18: =IFERROR(변수!$D$60*(변수!AN7-변수!AM7)/100,"") | AO18: =SUM(AK18:AN18)
A19: 세전이익 | B19: 손익 | C19: 억원 | D19: 법인세비용차감전계속사업이익 | E19: =IFERROR(VLOOKUP($D19,BS연결,MATCH(E$1,BS연결H,0),0)/100,"") | G19: =IFERROR(VLOOKUP($D19,BS연결,MATCH(G$1,BS연결H,0),0)/100,"") | H19: =IFERROR(VLOOKUP($D19,BS연결,MATCH(H$1,BS연결H,0),0)/100,"") | I19: =IFERROR(VLOOKUP($D19,BS연결,MATCH(I$1,BS연결H,0),0)/100,"") | J19: =IFERROR(VLOOKUP($D19,BS연결,MATCH(J$1,BS연결H,0),0)/100,"") | K19: =IFERROR(VLOOKUP($D19,BS연결,MATCH(K$1,BS연결H,0),0)/100,"") | L19: =IFERROR(VLOOKUP($D19,BS연결,MATCH(L$1,BS연결H,0),0)/100,"") | M19: =IFERROR(VLOOKUP($D19,BS연결,MATCH(M$1,BS연결H,0),0)/100,"") | N19: =IFERROR(VLOOKUP($D19,BS연결,MATCH(N$1,BS연결H,0),0)/100,"") | ... AB19: =IFERROR(VLOOKUP($D19,BS연결,MATCH(AB$1,BS연결H,0),0)/100,"") | AC19: =IFERROR(AC9+AC11+AC16+AC17+AC18,"") | AD19: =IFERROR(AD9+AD11+AD16+AD17+AD18,"") | AE19: =SUM(AA19:AD19) | AF19: =IFERROR(AF9+AF11+AF16+AF17+AF18,"") | AG19: =IFERROR(AG9+AG11+AG16+AG17+AG18,"") | AH19: =IFERROR(AH9+AH11+AH16+AH17+AH18,"") | AI19: =IFERROR(AI9+AI11+AI16+AI17+AI18,"") | AJ19: =SUM(AF19:AI19) | AK19: =IFERROR(AK9+AK11+AK16+AK17+AK18,"") | AL19: =IFERROR(AL9+AL11+AL16+AL17+AL18,"") | AM19: =IFERROR(AM9+AM11+AM16+AM17+AM18,"") | AN19: =IFERROR(AN9+AN11+AN16+AN17+AN18,"") | AO19: =SUM(AK19:AN19)
A20: 법인세비용 | B20: 손익 | C20: 억원 | D20: 법인세비용 | E20: =IFERROR(VLOOKUP($D20,BS연결,MATCH(E$1,BS연결H,0),0)/100,"") | G20: =IFERROR(VLOOKUP($D20,BS연결,MATCH(G$1,BS연결H,0),0)/100,"") | H20: =IFERROR(VLOOKUP($D20,BS연결,MATCH(H$1,BS연결H,0),0)/100,"") | I20: =IFERROR(VLOOKUP($D20,BS연결,MATCH(I$1,BS연결H,0),0)/100,"") | J20: =IFERROR(VLOOKUP($D20,BS연결,MATCH(J$1,BS연결H,0),0)/100,"") | K20: =IFERROR(VLOOKUP($D20,BS연결,MATCH(K$1,BS연결H,0),0)/100,"") | L20: =IFERROR(VLOOKUP($D20,BS연결,MATCH(L$1,BS연결H,0),0)/100,"") | M20: =IFERROR(VLOOKUP($D20,BS연결,MATCH(M$1,BS연결H,0),0)/100,"") | N20: =IFERROR(VLOOKUP($D20,BS연결,MATCH(N$1,BS연결H,0),0)/100,"") | ... AB20: =IFERROR(VLOOKUP($D20,BS연결,MATCH(AB$1,BS연결H,0),0)/100,"") | AC20: =IFERROR(MAX(AC19,0)*변수!AC27,"") | AD20: =IFERROR(MAX(AD19,0)*변수!AD27,"") | AE20: =SUM(AA20:AD20) | AF20: =IFERROR(MAX(AF19,0)*변수!AF27,"") | AG20: =IFERROR(MAX(AG19,0)*변수!AG27,"") | AH20: =IFERROR(MAX(AH19,0)*변수!AH27,"") | AI20: =IFERROR(MAX(AI19,0)*변수!AI27,"") | AJ20: =SUM(AF20:AI20) | AK20: =IFERROR(MAX(AK19,0)*변수!AK27,"") | AL20: =IFERROR(MAX(AL19,0)*변수!AL27,"") | AM20: =IFERROR(MAX(AM19,0)*변수!AM27,"") | AN20: =IFERROR(MAX(AN19,0)*변수!AN27,"") | AO20: =SUM(AK20:AN20)
A21: 당기순이익 | B21: 손익 | C21: 억원 | D21: 당기순이익 | G21: =IFERROR(VLOOKUP($D21,BS연결,MATCH(G$1,BS연결H,0),0)/100,"") | H21: =IFERROR(VLOOKUP($D21,BS연결,MATCH(H$1,BS연결H,0),0)/100,"") | I21: =IFERROR(VLOOKUP($D21,BS연결,MATCH(I$1,BS연결H,0),0)/100,"") | J21: =IFERROR(VLOOKUP($D21,BS연결,MATCH(J$1,BS연결H,0),0)/100,"") | K21: =IFERROR(VLOOKUP($D21,BS연결,MATCH(K$1,BS연결H,0),0)/100,"") | L21: =IFERROR(VLOOKUP($D21,BS연결,MATCH(L$1,BS연결H,0),0)/100,"") | M21: =IFERROR(VLOOKUP($D21,BS연결,MATCH(M$1,BS연결H,0),0)/100,"") | N21: =IFERROR(VLOOKUP($D21,BS연결,MATCH(N$1,BS연결H,0),0)/100,"") | ... AB21: =IFERROR(VLOOKUP($D21,BS연결,MATCH(AB$1,BS연결H,0),0)/100,"") | AC21: =IFERROR(AC19-AC20,"") | AD21: =IFERROR(AD19-AD20,"") | AE21: =SUM(AA21:AD21) | AF21: =IFERROR(AF19-AF20,"") | AG21: =IFERROR(AG19-AG20,"") | AH21: =IFERROR(AH19-AH20,"") | AI21: =IFERROR(AI19-AI20,"") | AJ21: =SUM(AF21:AI21) | AK21: =IFERROR(AK19-AK20,"") | AL21: =IFERROR(AL19-AL20,"") | AM21: =IFERROR(AM19-AM20,"") | AN21: =IFERROR(AN19-AN20,"") | AO21: =SUM(AK21:AN21)
A22: 지배주주순이익 | B22: 손익 | C22: 억원 | D22: (지배주주지분)당기순이익 | G22: =IFERROR(VLOOKUP($D22,BS연결,MATCH(G$1,BS연결H,0),0)/100,"") | H22: =IFERROR(VLOOKUP($D22,BS연결,MATCH(H$1,BS연결H,0),0)/100,"") | I22: =IFERROR(VLOOKUP($D22,BS연결,MATCH(I$1,BS연결H,0),0)/100,"") | J22: =IFERROR(VLOOKUP($D22,BS연결,MATCH(J$1,BS연결H,0),0)/100,"") | K22: =IFERROR(VLOOKUP($D22,BS연결,MATCH(K$1,BS연결H,0),0)/100,"") | L22: =IFERROR(VLOOKUP($D22,BS연결,MATCH(L$1,BS연결H,0),0)/100,"") | M22: =IFERROR(VLOOKUP($D22,BS연결,MATCH(M$1,BS연결H,0),0)/100,"") | N22: =IFERROR(VLOOKUP($D22,BS연결,MATCH(N$1,BS연결H,0),0)/100,"") | ... AB22: =IFERROR(VLOOKUP($D22,BS연결,MATCH(AB$1,BS연결H,0),0)/100,"") | AC22: =IFERROR(AC21*변수!AC28,"") | AD22: =IFERROR(AD21*변수!AD28,"") | AE22: =SUM(AA22:AD22) | AF22: =IFERROR(AF21*변수!AF28,"") | AG22: =IFERROR(AG21*변수!AG28,"") | AH22: =IFERROR(AH21*변수!AH28,"") | AI22: =IFERROR(AI21*변수!AI28,"") | AJ22: =SUM(AF22:AI22) | AK22: =IFERROR(AK21*변수!AK28,"") | AL22: =IFERROR(AL21*변수!AL28,"") | AM22: =IFERROR(AM21*변수!AM28,"") | AN22: =IFERROR(AN21*변수!AN28,"") | AO22: =SUM(AK22:AN22)
A23: 자산총계 | B23: 재무상태 | C23: 억원 | D23: 자산총계 | E23: =IFERROR(VLOOKUP($D23,BS연결,MATCH(E$1,BS연결H,0),0)/100,"") | F23: =IFERROR(VLOOKUP($D23,BS연결,MATCH(F$1,BS연결H,0),0)/100,"") | G23: =IFERROR(VLOOKUP($D23,BS연결,MATCH(G$1,BS연결H,0),0)/100,"") | H23: =IFERROR(VLOOKUP($D23,BS연결,MATCH(H$1,BS연결H,0),0)/100,"") | I23: =IFERROR(VLOOKUP($D23,BS연결,MATCH(I$1,BS연결H,0),0)/100,"") | J23: =IFERROR(VLOOKUP($D23,BS연결,MATCH(J$1,BS연결H,0),0)/100,"") | K23: =IFERROR(VLOOKUP($D23,BS연결,MATCH(K$1,BS연결H,0),0)/100,"") | L23: =IFERROR(VLOOKUP($D23,BS연결,MATCH(L$1,BS연결H,0),0)/100,"") | ... AB23: =IFERROR(VLOOKUP($D23,BS연결,MATCH(AB$1,BS연결H,0),0)/100,"") | AC23: =IFERROR(AC24+AC25,"") | AD23: =IFERROR(AD24+AD25,"") | AE23: =AD23 | AF23: =IFERROR(AF24+AF25,"") | AG23: =IFERROR(AG24+AG25,"") | AH23: =IFERROR(AH24+AH25,"") | AI23: =IFERROR(AI24+AI25,"") | AJ23: =AI23 | AK23: =IFERROR(AK24+AK25,"") | AL23: =IFERROR(AL24+AL25,"") | AM23: =IFERROR(AM24+AM25,"") | AN23: =IFERROR(AN24+AN25,"") | AO23: =AN23
A24: 부채총계 | B24: 재무상태 | C24: 억원 | D24: 부채총계 | E24: =IFERROR(VLOOKUP($D24,BS연결,MATCH(E$1,BS연결H,0),0)/100,"") | F24: =IFERROR(VLOOKUP($D24,BS연결,MATCH(F$1,BS연결H,0),0)/100,"") | G24: =IFERROR(VLOOKUP($D24,BS연결,MATCH(G$1,BS연결H,0),0)/100,"") | H24: =IFERROR(VLOOKUP($D24,BS연결,MATCH(H$1,BS연결H,0),0)/100,"") | I24: =IFERROR(VLOOKUP($D24,BS연결,MATCH(I$1,BS연결H,0),0)/100,"") | J24: =IFERROR(VLOOKUP($D24,BS연결,MATCH(J$1,BS연결H,0),0)/100,"") | K24: =IFERROR(VLOOKUP($D24,BS연결,MATCH(K$1,BS연결H,0),0)/100,"") | L24: =IFERROR(VLOOKUP($D24,BS연결,MATCH(L$1,BS연결H,0),0)/100,"") | ... AB24: =IFERROR(VLOOKUP($D24,BS연결,MATCH(AB$1,BS연결H,0),0)/100,"") | AC24: =IFERROR(AB24*(1+변수!AC29),"") | AD24: =IFERROR(AC24*(1+변수!AD29),"") | AE24: =AD24 | AF24: =IFERROR(AD24*(1+변수!AF29),"") | AG24: =IFERROR(AF24*(1+변수!AG29),"") | AH24: =IFERROR(AG24*(1+변수!AH29),"") | AI24: =IFERROR(AH24*(1+변수!AI29),"") | AJ24: =AI24 | AK24: =IFERROR(AI24*(1+변수!AK29),"") | AL24: =IFERROR(AK24*(1+변수!AL29),"") | AM24: =IFERROR(AL24*(1+변수!AM29),"") | AN24: =IFERROR(AM24*(1+변수!AN29),"") | AO24: =AN24
A25: 자본총계 | B25: 재무상태 | C25: 억원 | D25: 자본총계 | E25: =IFERROR(VLOOKUP($D25,BS연결,MATCH(E$1,BS연결H,0),0)/100,"") | F25: =IFERROR(VLOOKUP($D25,BS연결,MATCH(F$1,BS연결H,0),0)/100,"") | G25: =IFERROR(VLOOKUP($D25,BS연결,MATCH(G$1,BS연결H,0),0)/100,"") | H25: =IFERROR(VLOOKUP($D25,BS연결,MATCH(H$1,BS연결H,0),0)/100,"") | I25: =IFERROR(VLOOKUP($D25,BS연결,MATCH(I$1,BS연결H,0),0)/100,"") | J25: =IFERROR(VLOOKUP($D25,BS연결,MATCH(J$1,BS연결H,0),0)/100,"") | K25: =IFERROR(VLOOKUP($D25,BS연결,MATCH(K$1,BS연결H,0),0)/100,"") | L25: =IFERROR(VLOOKUP($D25,BS연결,MATCH(L$1,BS연결H,0),0)/100,"") | ... AB25: =IFERROR(VLOOKUP($D25,BS연결,MATCH(AB$1,BS연결H,0),0)/100,"") | AC25: =IFERROR(AB25+AC21-변수!AC30,"") | AD25: =IFERROR(AC25+AD21-변수!AD30,"") | AE25: =AD25 | AF25: =IFERROR(AD25+AF21-변수!AF30,"") | AG25: =IFERROR(AF25+AG21-변수!AG30,"") | AH25: =IFERROR(AG25+AH21-변수!AH30,"") | AI25: =IFERROR(AH25+AI21-변수!AI30,"") | AJ25: =AI25 | AK25: =IFERROR(AI25+AK21-변수!AK30,"") | AL25: =IFERROR(AK25+AL21-변수!AL30,"") | AM25: =IFERROR(AL25+AM21-변수!AM30,"") | AN25: =IFERROR(AM25+AN21-변수!AN30,"") | AO25: =AN25
A26: 지배주주지분 | B26: 재무상태 | C26: 억원 | D26: 지배주주지분 | E26: =IFERROR(VLOOKUP($D26,BS연결,MATCH(E$1,BS연결H,0),0)/100,"") | F26: =IFERROR(VLOOKUP($D26,BS연결,MATCH(F$1,BS연결H,0),0)/100,"") | G26: =IFERROR(VLOOKUP($D26,BS연결,MATCH(G$1,BS연결H,0),0)/100,"") | H26: =IFERROR(VLOOKUP($D26,BS연결,MATCH(H$1,BS연결H,0),0)/100,"") | I26: =IFERROR(VLOOKUP($D26,BS연결,MATCH(I$1,BS연결H,0),0)/100,"") | J26: =IFERROR(VLOOKUP($D26,BS연결,MATCH(J$1,BS연결H,0),0)/100,"") | K26: =IFERROR(VLOOKUP($D26,BS연결,MATCH(K$1,BS연결H,0),0)/100,"") | L26: =IFERROR(VLOOKUP($D26,BS연결,MATCH(L$1,BS연결H,0),0)/100,"") | ... AB26: =IFERROR(VLOOKUP($D26,BS연결,MATCH(AB$1,BS연결H,0),0)/100,"") | AC26: =IFERROR(AB26+AC22-변수!AC31,"") | AD26: =IFERROR(AC26+AD22-변수!AD31,"") | AE26: =AD26 | AF26: =IFERROR(AD26+AF22-변수!AF31,"") | AG26: =IFERROR(AF26+AG22-변수!AG31,"") | AH26: =IFERROR(AG26+AH22-변수!AH31,"") | AI26: =IFERROR(AH26+AI22-변수!AI31,"") | AJ26: =AI26 | AK26: =IFERROR(AI26+AK22-변수!AK31,"") | AL26: =IFERROR(AK26+AL22-변수!AL31,"") | AM26: =IFERROR(AL26+AM22-변수!AM31,"") | AN26: =IFERROR(AM26+AN22-변수!AN31,"") | AO26: =AN26
A27: 총차입금 | B27: 재무상태 | C27: 억원 | D27: 총차입금 | E27: =IFERROR(VLOOKUP($D27,BS연결,MATCH(E$1,BS연결H,0),0)/100,"") | F27: =IFERROR(VLOOKUP($D27,BS연결,MATCH(F$1,BS연결H,0),0)/100,"") | G27: =IFERROR(VLOOKUP($D27,BS연결,MATCH(G$1,BS연결H,0),0)/100,"") | H27: =IFERROR(VLOOKUP($D27,BS연결,MATCH(H$1,BS연결H,0),0)/100,"") | I27: =IFERROR(VLOOKUP($D27,BS연결,MATCH(I$1,BS연결H,0),0)/100,"") | J27: =IFERROR(VLOOKUP($D27,BS연결,MATCH(J$1,BS연결H,0),0)/100,"") | K27: =IFERROR(VLOOKUP($D27,BS연결,MATCH(K$1,BS연결H,0),0)/100,"") | L27: =IFERROR(VLOOKUP($D27,BS연결,MATCH(L$1,BS연결H,0),0)/100,"") | ... AB27: =IFERROR(VLOOKUP($D27,BS연결,MATCH(AB$1,BS연결H,0),0)/100,"") | AC27: =IFERROR(AB27*(1+변수!AC32),"") | AD27: =IFERROR(AC27*(1+변수!AD32),"") | AE27: =AD27 | AF27: =IFERROR(AD27*(1+변수!AF32),"") | AG27: =IFERROR(AF27*(1+변수!AG32),"") | AH27: =IFERROR(AG27*(1+변수!AH32),"") | AI27: =IFERROR(AH27*(1+변수!AI32),"") | AJ27: =AI27 | AK27: =IFERROR(AI27*(1+변수!AK32),"") | AL27: =IFERROR(AK27*(1+변수!AL32),"") | AM27: =IFERROR(AL27*(1+변수!AM32),"") | AN27: =IFERROR(AM27*(1+변수!AN32),"") | AO27: =AN27
A28: 순차입금 | B28: 재무상태 | C28: 억원 | D28: 순차입금 | E28: =IFERROR(VLOOKUP($D28,BS연결,MATCH(E$1,BS연결H,0),0)/100,"") | F28: =IFERROR(VLOOKUP($D28,BS연결,MATCH(F$1,BS연결H,0),0)/100,"") | G28: =IFERROR(VLOOKUP($D28,BS연결,MATCH(G$1,BS연결H,0),0)/100,"") | H28: =IFERROR(VLOOKUP($D28,BS연결,MATCH(H$1,BS연결H,0),0)/100,"") | I28: =IFERROR(VLOOKUP($D28,BS연결,MATCH(I$1,BS연결H,0),0)/100,"") | J28: =IFERROR(VLOOKUP($D28,BS연결,MATCH(J$1,BS연결H,0),0)/100,"") | K28: =IFERROR(VLOOKUP($D28,BS연결,MATCH(K$1,BS연결H,0),0)/100,"") | L28: =IFERROR(VLOOKUP($D28,BS연결,MATCH(L$1,BS연결H,0),0)/100,"") | ... AB28: =IFERROR(VLOOKUP($D28,BS연결,MATCH(AB$1,BS연결H,0),0)/100,"") | AC28: =IFERROR(AB28*(1+변수!AC33),"") | AD28: =IFERROR(AC28*(1+변수!AD33),"") | AE28: =AD28 | AF28: =IFERROR(AD28*(1+변수!AF33),"") | AG28: =IFERROR(AF28*(1+변수!AG33),"") | AH28: =IFERROR(AG28*(1+변수!AH33),"") | AI28: =IFERROR(AH28*(1+변수!AI33),"") | AJ28: =AI28 | AK28: =IFERROR(AI28*(1+변수!AK33),"") | AL28: =IFERROR(AK28*(1+변수!AL33),"") | AM28: =IFERROR(AL28*(1+변수!AM33),"") | AN28: =IFERROR(AM28*(1+변수!AN33),"") | AO28: =AN28
A29: 이자발생자산 | B29: 재무상태 | C29: 억원 | D29: 이자발생자산 | E29: =IFERROR(VLOOKUP($D29,BS연결,MATCH(E$1,BS연결H,0),0)/100,"") | F29: =IFERROR(VLOOKUP($D29,BS연결,MATCH(F$1,BS연결H,0),0)/100,"") | G29: =IFERROR(VLOOKUP($D29,BS연결,MATCH(G$1,BS연결H,0),0)/100,"") | H29: =IFERROR(VLOOKUP($D29,BS연결,MATCH(H$1,BS연결H,0),0)/100,"") | I29: =IFERROR(VLOOKUP($D29,BS연결,MATCH(I$1,BS연결H,0),0)/100,"") | J29: =IFERROR(VLOOKUP($D29,BS연결,MATCH(J$1,BS연결H,0),0)/100,"") | K29: =IFERROR(VLOOKUP($D29,BS연결,MATCH(K$1,BS연결H,0),0)/100,"") | L29: =IFERROR(VLOOKUP($D29,BS연결,MATCH(L$1,BS연결H,0),0)/100,"") | ... AB29: =IFERROR(VLOOKUP($D29,BS연결,MATCH(AB$1,BS연결H,0),0)/100,"") | AC29: =IFERROR(AB29*(1+변수!AC34),"") | AD29: =IFERROR(AC29*(1+변수!AD34),"") | AE29: =AD29 | AF29: =IFERROR(AD29*(1+변수!AF34),"") | AG29: =IFERROR(AF29*(1+변수!AG34),"") | AH29: =IFERROR(AG29*(1+변수!AH34),"") | AI29: =IFERROR(AH29*(1+변수!AI34),"") | AJ29: =AI29 | AK29: =IFERROR(AI29*(1+변수!AK34),"") | AL29: =IFERROR(AK29*(1+변수!AL34),"") | AM29: =IFERROR(AL29*(1+변수!AM34),"") | AN29: =IFERROR(AM29*(1+변수!AN34),"") | AO29: =AN29
A30: 현금및현금성자산 | B30: 재무상태 | C30: 억원 | D30: 현금및현금성자산 | E30: =IFERROR(VLOOKUP($D30,BS연결,MATCH(E$1,BS연결H,0),0)/100,"") | F30: =IFERROR(VLOOKUP($D30,BS연결,MATCH(F$1,BS연결H,0),0)/100,"") | G30: =IFERROR(VLOOKUP($D30,BS연결,MATCH(G$1,BS연결H,0),0)/100,"") | H30: =IFERROR(VLOOKUP($D30,BS연결,MATCH(H$1,BS연결H,0),0)/100,"") | I30: =IFERROR(VLOOKUP($D30,BS연결,MATCH(I$1,BS연결H,0),0)/100,"") | J30: =IFERROR(VLOOKUP($D30,BS연결,MATCH(J$1,BS연결H,0),0)/100,"") | K30: =IFERROR(VLOOKUP($D30,BS연결,MATCH(K$1,BS연결H,0),0)/100,"") | L30: =IFERROR(VLOOKUP($D30,BS연결,MATCH(L$1,BS연결H,0),0)/100,"") | ... AB30: =IFERROR(VLOOKUP($D30,BS연결,MATCH(AB$1,BS연결H,0),0)/100,"") | AE30: =AD30 | AJ30: =AI30 | AO30: =AN30
A31: CAPEX | B31: 현금흐름 | C31: 억원 | D31: CAPEX | E31: =IFERROR(VLOOKUP($D31,BS연결,MATCH(E$1,BS연결H,0),0)/100,"") | G31: =IFERROR(VLOOKUP($D31,BS연결,MATCH(G$1,BS연결H,0),0)/100,"") | H31: =IFERROR(VLOOKUP($D31,BS연결,MATCH(H$1,BS연결H,0),0)/100,"") | I31: =IFERROR(VLOOKUP($D31,BS연결,MATCH(I$1,BS연결H,0),0)/100,"") | J31: =IFERROR(VLOOKUP($D31,BS연결,MATCH(J$1,BS연결H,0),0)/100,"") | K31: =IFERROR(VLOOKUP($D31,BS연결,MATCH(K$1,BS연결H,0),0)/100,"") | L31: =IFERROR(VLOOKUP($D31,BS연결,MATCH(L$1,BS연결H,0),0)/100,"") | M31: =IFERROR(VLOOKUP($D31,BS연결,MATCH(M$1,BS연결H,0),0)/100,"") | N31: =IFERROR(VLOOKUP($D31,BS연결,MATCH(N$1,BS연결H,0),0)/100,"") | ... AB31: =IFERROR(VLOOKUP($D31,BS연결,MATCH(AB$1,BS연결H,0),0)/100,"") | AC31: =IFERROR(X31*(1+변수!AC36),"") | AD31: =IFERROR(Y31*(1+변수!AD36),"") | AE31: =SUM(AA31:AD31) | AF31: =IFERROR(AA31*(1+변수!AF36),"") | AG31: =IFERROR(AB31*(1+변수!AG36),"") | AH31: =IFERROR(AC31*(1+변수!AH36),"") | AI31: =IFERROR(AD31*(1+변수!AI36),"") | AJ31: =SUM(AF31:AI31) | AK31: =IFERROR(AF31*(1+변수!AK36),"") | AL31: =IFERROR(AG31*(1+변수!AL36),"") | AM31: =IFERROR(AH31*(1+변수!AM36),"") | AN31: =IFERROR(AI31*(1+변수!AN36),"") | AO31: =SUM(AK31:AN31)
A32: 영업활동현금흐름 | B32: 현금흐름 | C32: 억원 | D32: 영업활동으로인한현금흐름 | E32: =IFERROR(VLOOKUP($D32,BS연결,MATCH(E$1,BS연결H,0),0)/100,"") | G32: =IFERROR(VLOOKUP($D32,BS연결,MATCH(G$1,BS연결H,0),0)/100,"") | H32: =IFERROR(VLOOKUP($D32,BS연결,MATCH(H$1,BS연결H,0),0)/100,"") | I32: =IFERROR(VLOOKUP($D32,BS연결,MATCH(I$1,BS연결H,0),0)/100,"") | J32: =IFERROR(VLOOKUP($D32,BS연결,MATCH(J$1,BS연결H,0),0)/100,"") | K32: =IFERROR(VLOOKUP($D32,BS연결,MATCH(K$1,BS연결H,0),0)/100,"") | L32: =IFERROR(VLOOKUP($D32,BS연결,MATCH(L$1,BS연결H,0),0)/100,"") | M32: =IFERROR(VLOOKUP($D32,BS연결,MATCH(M$1,BS연결H,0),0)/100,"") | N32: =IFERROR(VLOOKUP($D32,BS연결,MATCH(N$1,BS연결H,0),0)/100,"") | ... AB32: =IFERROR(VLOOKUP($D32,BS연결,MATCH(AB$1,BS연결H,0),0)/100,"") | AE32: =SUM(AA32:AD32) | AJ32: =SUM(AF32:AI32) | AO32: =SUM(AK32:AN32)
A33: 주식수 | B33: 주당 | C33: 백만주 | D33: 유통주식수 | E33: 88.773 | F33: =E33 | G33: 88.773 | H33: 88.773 | I33: 88.773 | J33: 88.773 | K33: =J33 | L33: 88.773 | M33: 88.773 | N33: 88.773 | O33: 88.773 | P33: =O33 | Q33: 88.773 | R33: 88.773 | S33: 88.773 | T33: 88.773 | U33: =T33 | V33: 88.773 | W33: 88.773 | X33: 88.773 | Y33: 104.933 | Z33: =Y33 | AA33: 104.933 | AB33: 104.933 | AC33: =IFERROR(AB33*(1+변수!AC38),"") | AD33: =IFERROR(AC33*(1+변수!AD38),"") | AE33: =AD33 | AF33: =IFERROR(AD33*(1+변수!AF38),"") | AG33: =IFERROR(AF33*(1+변수!AG38),"") | AH33: =IFERROR(AG33*(1+변수!AH38),"") | AI33: =IFERROR(AH33*(1+변수!AI38),"") | AJ33: =AI33 | AK33: =IFERROR(AI33*(1+변수!AK38),"") | AL33: =IFERROR(AK33*(1+변수!AL38),"") | AM33: =IFERROR(AL33*(1+변수!AM38),"") | AN33: =IFERROR(AM33*(1+변수!AN38),"") | AO33: =AN33
A34: EPS | B34: 주당 | C34: 원 | D34: EPS | G34: =IFERROR(G22*100/G33,"") | H34: =IFERROR(H22*100/H33,"") | I34: =IFERROR(I22*100/I33,"") | J34: =IFERROR(J22*100/J33,"") | K34: =SUM(G34:J34) | L34: =IFERROR(L22*100/L33,"") | M34: =IFERROR(M22*100/M33,"") | N34: =IFERROR(N22*100/N33,"") | O34: =IFERROR(O22*100/O33,"") | P34: =SUM(L34:O34) | Q34: =IFERROR(Q22*100/Q33,"") | R34: =IFERROR(R22*100/R33,"") | S34: =IFERROR(S22*100/S33,"") | T34: =IFERROR(T22*100/T33,"") | U34: =SUM(Q34:T34) | V34: =IFERROR(V22*100/V33,"") | W34: =IFERROR(W22*100/W33,"") | X34: =IFERROR(X22*100/X33,"") | Y34: =IFERROR(Y22*100/Y33,"") | Z34: =SUM(V34:Y34) | AA34: =IFERROR(AA22*100/AA33,"") | AB34: =IFERROR(AB22*100/AB33,"") | AC34: =IFERROR(AC22*100/AC33,"") | AD34: =IFERROR(AD22*100/AD33,"") | AE34: =SUM(AA34:AD34) | AF34: =IFERROR(AF22*100/AF33,"") | AG34: =IFERROR(AG22*100/AG33,"") | AH34: =IFERROR(AH22*100/AH33,"") | AI34: =IFERROR(AI22*100/AI33,"") | AJ34: =SUM(AF34:AI34) | AK34: =IFERROR(AK22*100/AK33,"") | AL34: =IFERROR(AL22*100/AL33,"") | AM34: =IFERROR(AM22*100/AM33,"") | AN34: =IFERROR(AN22*100/AN33,"") | AO34: =SUM(AK34:AN34)
A35: BPS | B35: 주당 | C35: 원 | D35: BPS | E35: =IFERROR(E26*100/E33,"") | F35: =E35 | G35: =IFERROR(G26*100/G33,"") | H35: =IFERROR(H26*100/H33,"") | I35: =IFERROR(I26*100/I33,"") | J35: =IFERROR(J26*100/J33,"") | K35: =J35 | L35: =IFERROR(L26*100/L33,"") | M35: =IFERROR(M26*100/M33,"") | N35: =IFERROR(N26*100/N33,"") | O35: =IFERROR(O26*100/O33,"") | P35: =O35 | Q35: =IFERROR(Q26*100/Q33,"") | R35: =IFERROR(R26*100/R33,"") | S35: =IFERROR(S26*100/S33,"") | T35: =IFERROR(T26*100/T33,"") | U35: =T35 | V35: =IFERROR(V26*100/V33,"") | W35: =IFERROR(W26*100/W33,"") | X35: =IFERROR(X26*100/X33,"") | Y35: =IFERROR(Y26*100/Y33,"") | Z35: =Y35 | AA35: =IFERROR(AA26*100/AA33,"") | AB35: =IFERROR(AB26*100/AB33,"") | AC35: =IFERROR(AC26*100/AC33,"") | AD35: =IFERROR(AD26*100/AD33,"") | AE35: =AD35 | AF35: =IFERROR(AF26*100/AF33,"") | AG35: =IFERROR(AG26*100/AG33,"") | AH35: =IFERROR(AH26*100/AH33,"") | AI35: =IFERROR(AI26*100/AI33,"") | AJ35: =AI35 | AK35: =IFERROR(AK26*100/AK33,"") | AL35: =IFERROR(AL26*100/AL33,"") | AM35: =IFERROR(AM26*100/AM33,"") | AN35: =IFERROR(AN26*100/AN33,"") | AO35: =AN35
A36: DPS | B36: 주당 | C36: 원 | D36: DPS(보통주) | E36: 0 | F36: 0 | J36: 0 | K36: =SUM(G36:J36) | O36: 0 | P36: =SUM(L36:O36) | T36: 2090 | U36: =SUM(Q36:T36) | Y36: 5661 | Z36: =SUM(V36:Y36) | AD36: =변수!AD39 | AE36: =SUM(AA36:AD36) | AI36: =변수!AI39 | AJ36: =SUM(AF36:AI36) | AN36: =변수!AN39 | AO36: =SUM(AK36:AN36)
A37: PER | B37: 주당 | C37: 배 | D37: PER | F37: =E37 | K37: =J37 | O37: =IFERROR(변수!O18/(L34+M34+N34+O34),"") | P37: =O37 | Q37: =IFERROR(변수!Q18/(M34+N34+O34+Q34),"") | R37: =IFERROR(변수!R18/(N34+O34+Q34+R34),"") | S37: =IFERROR(변수!S18/(O34+Q34+R34+S34),"") | T37: =IFERROR(변수!T18/(Q34+R34+S34+T34),"") | U37: =T37 | V37: =IFERROR(변수!V18/(R34+S34+T34+V34),"") | W37: =IFERROR(변수!W18/(S34+T34+V34+W34),"") | X37: =IFERROR(변수!X18/(T34+V34+W34+X34),"") | Y37: =IFERROR(변수!Y18/(V34+W34+X34+Y34),"") | Z37: =Y37 | AA37: =IFERROR(변수!AA18/(W34+X34+Y34+AA34),"") | AB37: =IFERROR(변수!AB18/(X34+Y34+AA34+AB34),"") | AC37: =IFERROR(변수!$D$47/(Y34+AA34+AB34+AC34),"") | AD37: =IFERROR(변수!$D$47/(AA34+AB34+AC34+AD34),"") | AE37: =AD37 | AF37: =IFERROR(변수!$D$47/(AB34+AC34+AD34+AF34),"") | AG37: =IFERROR(변수!$D$47/(AC34+AD34+AF34+AG34),"") | AH37: =IFERROR(변수!$D$47/(AD34+AF34+AG34+AH34),"") | AI37: =IFERROR(변수!$D$47/(AF34+AG34+AH34+AI34),"") | AJ37: =AI37 | AK37: =IFERROR(변수!$D$47/(AG34+AH34+AI34+AK34),"") | AL37: =IFERROR(변수!$D$47/(AH34+AI34+AK34+AL34),"") | AM37: =IFERROR(변수!$D$47/(AI34+AK34+AL34+AM34),"") | AN37: =IFERROR(변수!$D$47/(AK34+AL34+AM34+AN34),"") | AO37: =AN37
A38: PBR | B38: 주당 | C38: 배 | D38: PBR | E38: =IFERROR(변수!E18/E35,"") | F38: =E38 | G38: =IFERROR(변수!G18/G35,"") | H38: =IFERROR(변수!H18/H35,"") | I38: =IFERROR(변수!I18/I35,"") | J38: =IFERROR(변수!J18/J35,"") | K38: =J38 | L38: =IFERROR(변수!L18/L35,"") | M38: =IFERROR(변수!M18/M35,"") | N38: =IFERROR(변수!N18/N35,"") | O38: =IFERROR(변수!O18/O35,"") | P38: =O38 | Q38: =IFERROR(변수!Q18/Q35,"") | R38: =IFERROR(변수!R18/R35,"") | S38: =IFERROR(변수!S18/S35,"") | T38: =IFERROR(변수!T18/T35,"") | U38: =T38 | V38: =IFERROR(변수!V18/V35,"") | W38: =IFERROR(변수!W18/W35,"") | X38: =IFERROR(변수!X18/X35,"") | Y38: =IFERROR(변수!Y18/Y35,"") | Z38: =Y38 | AA38: =IFERROR(변수!AA18/AA35,"") | AB38: =IFERROR(변수!AB18/AB35,"") | AC38: =IFERROR(변수!$D$47/AC35,"") | AD38: =IFERROR(변수!$D$47/AD35,"") | AE38: =AD38 | AF38: =IFERROR(변수!$D$47/AF35,"") | AG38: =IFERROR(변수!$D$47/AG35,"") | AH38: =IFERROR(변수!$D$47/AH35,"") | AI38: =IFERROR(변수!$D$47/AI35,"") | AJ38: =AI38 | AK38: =IFERROR(변수!$D$47/AK35,"") | AL38: =IFERROR(변수!$D$47/AL35,"") | AM38: =IFERROR(변수!$D$47/AM35,"") | AN38: =IFERROR(변수!$D$47/AN35,"") | AO38: =AN38
A39: 매출조선 | B39: 사업부 | C39: 억원 | D39: 매출 조선·해양(조선·해양플랜트) | K39: =SUM(G39:J39) | N39: 21403.13 | O39: 25569.47 | P39: =SUM(L39:O39) | Q39: 22676 | R39: 29978.88 | S39: 27807.18 | T39: 32262.4 | U39: =SUM(Q39:T39) | V39: 29023.67 | W39: 30956.65 | X39: 33355.92 | Y39: 43685.01 | Z39: =SUM(V39:Y39) | AA39: 50177.88 | AB39: 53554.92 | AC39: =IFERROR(SLS!Q124/100+변수!AC40+AC40,"") | AD39: =IFERROR(SLS!R124/100+변수!AD40+AD40,"") | AE39: =SUM(AA39:AD39) | AF39: =IFERROR(SLS!S124/100+변수!AF40+AF40,"") | AG39: =IFERROR(SLS!T124/100+변수!AG40+AG40,"") | AH39: =IFERROR(SLS!U124/100+변수!AH40+AH40,"") | AI39: =IFERROR(SLS!V124/100+변수!AI40+AI40,"") | AJ39: =SUM(AF39:AI39) | AK39: =IFERROR(SLS!W124/100+변수!AK40+AK40,"") | AL39: =IFERROR(SLS!X124/100+변수!AL40+AL40,"") | AM39: =IFERROR(SLS!Y124/100+변수!AM40+AM40,"") | AN39: =IFERROR(SLS!Z124/100+변수!AN40+AN40,"") | AO39: =SUM(AK39:AN39)
A40: 매출조선신규 | B40: 사업부 | C40: 억원 | D40: 매출 조선·해양(조선·해양플랜트) 신규수주(forecast_panel base(공시 상계) — 매출조선에 포함) | K40: =SUM(G40:J40) | P40: =SUM(L40:O40) | U40: =SUM(Q40:T40) | Z40: =SUM(V40:Y40) | AA40: 0 | AB40: 0 | AC40: =변수!AC41 | AD40: =변수!AD41 | AE40: =SUM(AA40:AD40) | AF40: =변수!AF41 | AG40: =변수!AG41 | AH40: =변수!AH41 | AI40: =변수!AI41 | AJ40: =SUM(AF40:AI40) | AK40: =변수!AK41 | AL40: =변수!AL41 | AM40: =변수!AM41 | AN40: =변수!AN41 | AO40: =SUM(AK40:AN40)
A41: OP조선 | B41: 사업부 | C41: 억원 | D41: OP 조선·해양(조선·해양플랜트) | K41: =SUM(G41:J41) | P41: =SUM(L41:O41) | U41: =SUM(Q41:T41) | Z41: =SUM(V41:Y41) | AC41: =IFERROR(AC39*변수!AC42,"") | AD41: =IFERROR(AD39*변수!AD42,"") | AE41: =SUM(AA41:AD41) | AF41: =IFERROR(AF39*변수!AF42,"") | AG41: =IFERROR(AG39*변수!AG42,"") | AH41: =IFERROR(AH39*변수!AH42,"") | AI41: =IFERROR(AI39*변수!AI42,"") | AJ41: =SUM(AF41:AI41) | AK41: =IFERROR(AK39*변수!AK42,"") | AL41: =IFERROR(AL39*변수!AL42,"") | AM41: =IFERROR(AM39*변수!AM42,"") | AN41: =IFERROR(AN39*변수!AN42,"") | AO41: =SUM(AK41:AN41)
A42: OP조선신규 | B42: 사업부 | C42: 억원 | D42: OP 조선·해양(조선·해양플랜트) 신규수주(매출조선신규 × OPM — OP조선에 포함) | K42: =SUM(G42:J42) | P42: =SUM(L42:O42) | U42: =SUM(Q42:T42) | Z42: =SUM(V42:Y42) | AA42: 0 | AB42: 0 | AC42: =IFERROR(AC40*변수!AC42,"") | AD42: =IFERROR(AD40*변수!AD42,"") | AE42: =SUM(AA42:AD42) | AF42: =IFERROR(AF40*변수!AF42,"") | AG42: =IFERROR(AG40*변수!AG42,"") | AH42: =IFERROR(AH40*변수!AH42,"") | AI42: =IFERROR(AI40*변수!AI42,"") | AJ42: =SUM(AF42:AI42) | AK42: =IFERROR(AK40*변수!AK42,"") | AL42: =IFERROR(AL40*변수!AL42,"") | AM42: =IFERROR(AM40*변수!AM42,"") | AN42: =IFERROR(AN40*변수!AN42,"") | AO42: =SUM(AK42:AN42)
A43: 매출기타 | B43: 사업부 | C43: 억원 | D43: 매출 기타 부문(총매출 − 조선) | K43: =SUM(G43:J43) | N43: 7132.13 | O43: 8561.65 | P43: =SUM(L43:O43) | Q43: 7201.45 | R43: 8860.95 | S43: 8284.58 | T43: 7793.1 | U43: =SUM(Q43:T43) | V43: 9201.49 | W43: 10514.6 | X43: 10823.06 | Y43: 8245.93 | Z43: =SUM(V43:Y43) | AA43: 8985.44 | AB43: 9766.63 | AC43: =IFERROR(X43*(1+변수!AC43),"") | AD43: =IFERROR(Y43*(1+변수!AD43),"") | AE43: =SUM(AA43:AD43) | AF43: =IFERROR(AA43*(1+변수!AF43),"") | AG43: =IFERROR(AB43*(1+변수!AG43),"") | AH43: =IFERROR(AC43*(1+변수!AH43),"") | AI43: =IFERROR(AD43*(1+변수!AI43),"") | AJ43: =SUM(AF43:AI43) | AK43: =IFERROR(AF43*(1+변수!AK43),"") | AL43: =IFERROR(AG43*(1+변수!AL43),"") | AM43: =IFERROR(AH43*(1+변수!AM43),"") | AN43: =IFERROR(AI43*(1+변수!AN43),"") | AO43: =SUM(AK43:AN43)
A44: OP기타 | B44: 사업부 | C44: 억원 | D44: OP 기타 부문(총매출 − 조선) | K44: =SUM(G44:J44) | P44: =SUM(L44:O44) | U44: =SUM(Q44:T44) | Z44: =SUM(V44:Y44) | AC44: =IFERROR(AC43*변수!AC44,"") | AD44: =IFERROR(AD43*변수!AD44,"") | AE44: =SUM(AA44:AD44) | AF44: =IFERROR(AF43*변수!AF44,"") | AG44: =IFERROR(AG43*변수!AG44,"") | AH44: =IFERROR(AH43*변수!AH44,"") | AI44: =IFERROR(AI43*변수!AI44,"") | AJ44: =SUM(AF44:AI44) | AK44: =IFERROR(AK43*변수!AK44,"") | AL44: =IFERROR(AL43*변수!AL44,"") | AM44: =IFERROR(AM43*변수!AM44,"") | AN44: =IFERROR(AN43*변수!AN44,"") | AO44: =SUM(AK44:AN44)
B45: 비율(참고)
A46: NPM | C46: % | D46: 지배주주순이익 / 매출액 | E46: =IFERROR(E22/E5,"") | F46: =IFERROR(F22/F5,"") | G46: =IFERROR(G22/G5,"") | H46: =IFERROR(H22/H5,"") | I46: =IFERROR(I22/I5,"") | J46: =IFERROR(J22/J5,"") | K46: =IFERROR(K22/K5,"") | L46: =IFERROR(L22/L5,"") | ... AO46: =IFERROR(AO22/AO5,"")
A47: 매출원가율 | C47: % | D47: 매출원가 / 매출액 | E47: =IFERROR(E6/E5,"") | F47: =IFERROR(F6/F5,"") | G47: =IFERROR(G6/G5,"") | H47: =IFERROR(H6/H5,"") | I47: =IFERROR(I6/I5,"") | J47: =IFERROR(J6/J5,"") | K47: =IFERROR(K6/K5,"") | L47: =IFERROR(L6/L5,"") | ... AO47: =IFERROR(AO6/AO5,"")
A48: 판관비율 | C48: % | D48: 판관비 / 매출액 | E48: =IFERROR(E8/E5,"") | F48: =IFERROR(F8/F5,"") | G48: =IFERROR(G8/G5,"") | H48: =IFERROR(H8/H5,"") | I48: =IFERROR(I8/I5,"") | J48: =IFERROR(J8/J5,"") | K48: =IFERROR(K8/K5,"") | L48: =IFERROR(L8/L5,"") | ... AO48: =IFERROR(AO8/AO5,"")

Sheet SLS
C1: 이름: SLS_H · 선표 매출인식(백만$) — sls json origin 2026Q2 | E1: 3Q23 | F1: 4Q23 | G1: 1Q24 | H1: 2Q24 | I1: 3Q24 | J1: 4Q24 | K1: 1Q25 | L1: 2Q25 | M1: 3Q25 | N1: 4Q25 | O1: 1Q26 | P1: 2Q26 | Q1: 3Q26 | R1: 4Q26 | S1: 1Q27 | T1: 2Q27 | U1: 3Q27 | V1: 4Q27 | W1: 1Q28 | X1: 2Q28 | Y1: 3Q28 | Z1: 4Q28 | AA1: 1Q29 | AB1: 2Q29 | AC1: 3Q29 | AD1: 4Q29 | AE1: 1Q30 | AF1: 2Q30 | AG1: 3Q30 | AH1: 4Q30 | AI1: 1Q31 | AJ1: 2Q31 | AK1: 3Q31 | AL1: 4Q31 | AM1: 1Q32 | AN1: 2Q32 | AO1: 3Q32 | AP1: 4Q32 | AQ1: 1Q33 | AR1: 2Q33 | AS1: 3Q33 | AT1: 4Q33 | AU1: 2023 | AV1: 2024 | AW1: 2025 | AX1: 2026 | AY1: 2027 | AZ1: 2028 | BA1: 2029 | BB1: 2030 | BC1: 2031 | BD1: 2032 | BE1: 2033
A2: 코호트 표(레퍼런스 실측 캘리브레이션): ①적자 −1.1% ②BEP 1% ③중마진 4.3% ④호황 5.4% ⑤초호황 10.8% — 회사별 캘리브레이션은 target_opm.basis 참조 · 코호트 모드 reference_anchor(대안 ledger_relative) · 잔고 캡 미적용
E3: 1 | F3: 2 | G3: 3 | H3: 4 | I3: 5 | J3: 6 | K3: 7 | L3: 8 | M3: 9 | N3: 10 | O3: 11 | P3: 12 | Q3: 13 | R3: 14 | S3: 15 | T3: 16 | U3: 17 | V3: 18 | W3: 19 | X3: 20 | Y3: 21 | Z3: 22 | AA3: 23 | AB3: 24 | AC3: 25 | AD3: 26 | AE3: 27 | AF3: 28 | AG3: 29 | AH3: 30 | AI3: 31 | AJ3: 32 | AK3: 33 | AL3: 34 | AM3: 35 | AN3: 36 | AO3: 37 | AP3: 38 | AQ3: 39 | AR3: 40 | AS3: 41 | AT3: 42 | AU3: 43 | AV3: 44 | AW3: 45 | AX3: 46 | AY3: 47 | AZ3: 48 | BA3: 49 | BB3: 50 | BC3: 51 | BD3: 52 | BE3: 53
E4: 2023.09 | F4: 2023.12 | G4: 2024.03 | H4: 2024.06 | I4: 2024.09 | J4: 2024.12 | K4: 2025.03 | L4: 2025.06 | M4: 2025.09 | N4: 2025.12 | O4: 2026.03 | P4: 2026.06 | Q4: 2026.09 | R4: 2026.12 | S4: 2027.03 | T4: 2027.06 | U4: 2027.09 | V4: 2027.12 | W4: 2028.03 | X4: 2028.06 | Y4: 2028.09 | Z4: 2028.12 | AA4: 2029.03 | AB4: 2029.06 | AC4: 2029.09 | AD4: 2029.12 | AE4: 2030.03 | AF4: 2030.06 | AG4: 2030.09 | AH4: 2030.12 | AI4: 2031.03 | AJ4: 2031.06 | AK4: 2031.09 | AL4: 2031.12 | AM4: 2032.03 | AN4: 2032.06 | AO4: 2032.09 | AP4: 2032.12 | AQ4: 2033.03 | AR4: 2033.06 | AS4: 2033.09 | AT4: 2033.12 | AU4: 2023.12A | AV4: 2024.12A | AW4: 2025.12A | AX4: 2026.12A | AY4: 2027.12A | AZ4: 2028.12A | BA4: 2029.12A | BB4: 2030.12A | BC4: 2031.12A | BD4: 2032.12A | BE4: 2033.12A
A5: usd_m | D5: 매출인식 합계(백만$) | E5: 95.942 | F5: 95.942 | G5: 108.778 | H5: 126.244 | I5: 130.695 | J5: 153.139 | K5: 291.185 | L5: 380.959 | M5: 536.102 | N5: 640.148 | O5: 887.205 | P5: 1287.171 | Q5: 1560.288 | R5: 1610.261 | S5: 1575.255 | T5: 1562.515 | U5: 1499.817 | V5: 1445.363 | W5: 1380.297 | X5: 1333.678 | Y5: 1241.127 | Z5: 1114.694 | AA5: 733.416 | AB5: 575.381 | AC5: 471.531 | AD5: 300.251 | AE5: 174.161 | AF5: 151.033 | AG5: 65.853 | AH5: 33.927 | AI5: 27.974 | AJ5: 12.524 | AK5: 10.006 | AL5: 10.006 | AM5: 9.897 | AN5: 9.897 | AO5: 10.006 | AP5: 10.006 | AQ5: 9.788 | AR5: 9.897 | AS5: 10.006 | AT5: 8.81 | AU5: 191.884 | AV5: 518.856 | AW5: 1848.394 | AX5: 5344.925 | AY5: 6082.95 | AZ5: 5069.796 | BA5: 2080.579 | BB5: 424.974 | BC5: 60.51 | BD5: 39.806 | BE5: 38.501
A6: marine_usd_m | D6: 해양(type≠OTHER) 합계(백만$) | E6: 95.942 | F6: 95.942 | G6: 108.778 | H6: 126.244 | I6: 130.695 | J6: 153.139 | K6: 291.185 | L6: 380.959 | M6: 536.102 | N6: 640.148 | O6: 887.205 | P6: 1269.147 | Q6: 1511.445 | R6: 1544.271 | S6: 1510.7 | T6: 1497.243 | U6: 1433.827 | V6: 1379.373 | W6: 1315.025 | X6: 1268.405 | Y6: 1175.137 | Z6: 1048.704 | AA6: 668.861 | AB6: 510.109 | AC6: 405.541 | AD6: 234.261 | AE6: 109.605 | AF6: 85.76 | AG6: 28.596 | AH6: 28.596 | AI6: 27.974 | AJ6: 12.524 | AK6: 10.006 | AL6: 10.006 | AM6: 9.897 | AN6: 9.897 | AO6: 10.006 | AP6: 10.006 | AQ6: 9.788 | AR6: 9.897 | AS6: 10.006 | AT6: 8.81 | AU6: 191.884 | AV6: 518.856 | AW6: 1848.394 | AX6: 5212.068 | AY6: 5821.143 | AZ6: 4807.271 | BA6: 1818.772 | BB6: 252.557 | BC6: 60.51 | BD6: 39.806 | BE6: 38.501
A7: type:OFFSH | D7: 선종 OFFSH | E7: 95.942 | F7: 95.942 | G7: 94.899 | H7: 94.899 | I7: 95.942 | J7: 95.942 | K7: 93.856 | L7: 94.899 | M7: 95.942 | N7: 95.942 | O7: 93.856 | P7: 94.899 | Q7: 95.942 | R7: 95.942 | S7: 93.856 | T7: 64.657 | AU7: 191.884 | AV7: 381.682 | AW7: 380.639 | AX7: 380.639 | AY7: 158.513
A8: type:VLGC | D8: 선종 VLGC | G8: 13.879 | H8: 15.987 | I8: 16.163 | J8: 26.193 | K8: 42.224 | L8: 55.898 | M8: 56.513 | N8: 62.085 | O8: 78.079 | P8: 176.553 | Q8: 261.312 | R8: 275.358 | S8: 269.372 | T8: 272.365 | U8: 270.088 | V8: 259.195 | W8: 236.958 | X8: 236.958 | Y8: 206.255 | Z8: 198.404 | AA8: 173.604 | AB8: 155.609 | AC8: 149.054 | AD8: 115.62 | AE8: 81.631 | AF8: 57.475 | AV8: 72.222 | AW8: 216.72 | AX8: 791.302 | AY8: 1071.02 | AZ8: 878.575 | BA8: 593.887 | BB8: 139.106
A9: type:NAVAL | D9: 선종 NAVAL | H9: 15.357 | I9: 18.59 | J9: 18.59 | K9: 18.186 | L9: 18.388 | M9: 18.59 | N9: 27.953 | O9: 64.004 | P9: 84.567 | Q9: 91.15 | R9: 91.15 | S9: 89.169 | T9: 90.159 | U9: 91.15 | V9: 91.15 | W9: 90.159 | X9: 90.159 | Y9: 91.15 | Z9: 91.15 | AA9: 89.169 | AB9: 90.159 | AC9: 81.923 | AD9: 61.023 | AE9: 27.974 | AF9: 28.285 | AG9: 28.596 | AH9: 28.596 | AI9: 27.974 | AJ9: 12.524 | AK9: 10.006 | AL9: 10.006 | AM9: 9.897 | AN9: 9.897 | AO9: 10.006 | AP9: 10.006 | AQ9: 9.788 | AR9: 9.897 | AS9: 10.006 | AT9: 8.81 | AV9: 52.537 | AW9: 83.117 | AX9: 330.871 | AY9: 361.628 | AZ9: 362.618 | BA9: 322.274 | BB9: 113.451 | BC9: 60.51 | BD9: 39.806 | BE9: 38.501
A10: type:VLCC | D10: 선종 VLCC | J10: 12.414 | K10: 14.142 | L10: 20.146 | M10: 42.766 | N10: 75.341 | O10: 104.412 | P10: 110.321 | Q10: 111.533 | R10: 111.533 | S10: 109.108 | T10: 110.321 | U10: 102.302 | V10: 58.74 | W10: 38.584 | X10: 38.584 | Y10: 39.008 | Z10: 29.059 | AA10: 23.482 | AB10: 23.743 | AV10: 12.414 | AW10: 152.395 | AX10: 437.799 | AY10: 380.471 | AZ10: 145.235 | BA10: 47.225
A11: type:CONT | D11: 선종 CONT | K11: 122.777 | L11: 191.627 | M11: 322.291 | N11: 376.381 | O11: 417.709 | P11: 530.909 | Q11: 571.424 | R11: 571.424 | S11: 559.001 | T11: 565.212 | U11: 571.424 | V11: 571.424 | W11: 554.796 | X11: 508.176 | Y11: 456.705 | Z11: 389.139 | AA11: 85.758 | AB11: 86.711 | AC11: 87.664 | AW11: 1013.076 | AX11: 2091.466 | AY11: 2267.061 | AZ11: 1908.816 | BA11: 260.133
A12: type:PC | D12: 선종 PC | N12: 2.446 | O12: 24.463 | P12: 56.447 | Q12: 83.275 | R12: 85.404 | S12: 83.548 | T12: 84.476 | U12: 85.404 | V12: 85.404 | W12: 84.476 | X12: 84.476 | Y12: 68.824 | Z12: 60.398 | AA12: 59.085 | AB12: 49.17 | AW12: 2.446 | AX12: 249.589 | AY12: 338.832 | AZ12: 298.174 | BA12: 108.255
A13: type:LNGC | D13: 선종 LNGC | O13: 104.681 | P13: 194.19 | Q13: 269.375 | R13: 269.375 | S13: 263.519 | T13: 266.447 | U13: 269.375 | V13: 269.375 | W13: 266.447 | X13: 266.447 | Y13: 269.11 | Z13: 245.029 | AA13: 219.488 | AB13: 86.237 | AC13: 68.218 | AD13: 45.232 | AX13: 837.621 | AY13: 1068.716 | AZ13: 1047.033 | BA13: 419.175
A14: type:OTHER | D14: 선종 OTHER | P14: 18.023 | Q14: 48.843 | R14: 65.99 | S14: 64.555 | T14: 65.273 | U14: 65.99 | V14: 65.99 | W14: 65.273 | X14: 65.273 | Y14: 65.99 | Z14: 65.99 | AA14: 64.555 | AB14: 65.273 | AC14: 65.99 | AD14: 65.99 | AE14: 64.555 | AF14: 65.273 | AG14: 37.257 | AH14: 5.331 | AX14: 132.856 | AY14: 261.808 | AZ14: 262.526 | BA14: 261.808 | BB14: 172.416
A15: type:PCTC | D15: 선종 PCTC | P15: 21.262 | Q15: 27.434 | R15: 44.085 | S15: 43.127 | T15: 43.606 | U15: 44.085 | V15: 44.085 | W15: 43.606 | X15: 43.606 | Y15: 44.085 | Z15: 35.525 | AA15: 18.275 | AB15: 18.478 | AC15: 18.681 | AD15: 12.387 | AX15: 92.781 | AY15: 174.903 | AZ15: 166.822 | BA15: 67.821
A16: cohort:⑤초호황 | D16: 코호트 ⑤초호황 | E16: 95.942 | F16: 95.942 | G16: 108.778 | H16: 126.244 | I16: 130.695 | J16: 153.139 | K16: 291.185 | L16: 380.959 | M16: 536.102 | N16: 633.187 | O16: 877.417 | P16: 1259.25 | Q16: 1501.439 | R16: 1534.265 | S16: 1500.912 | T16: 1487.346 | U16: 1423.821 | V16: 1369.367 | W16: 1305.128 | X16: 1258.508 | Y16: 1165.131 | Z16: 1038.699 | AA16: 659.073 | AB16: 500.212 | AC16: 395.535 | AD16: 224.255 | AE16: 99.817 | AF16: 75.863 | AG16: 18.59 | AH16: 18.59 | AI16: 18.186 | AJ16: 2.627 | AU16: 191.884 | AV16: 518.856 | AW16: 1841.433 | AX16: 5172.371 | AY16: 5781.446 | AZ16: 4767.466 | BA16: 1779.075 | BB16: 212.86 | BC16: 20.813
A17: cohort:등급없음 | D17: 코호트 등급없음 | N17: 6.961 | O17: 9.788 | P17: 27.92 | Q17: 58.849 | R17: 75.996 | S17: 74.344 | T17: 75.17 | U17: 75.996 | V17: 75.996 | W17: 75.17 | X17: 75.17 | Y17: 75.996 | Z17: 75.996 | AA17: 74.344 | AB17: 75.17 | AC17: 75.996 | AD17: 75.996 | AE17: 74.344 | AF17: 75.17 | AG17: 47.263 | AH17: 15.337 | AI17: 9.788 | AJ17: 9.897 | AK17: 10.006 | AL17: 10.006 | AM17: 9.897 | AN17: 9.897 | AO17: 10.006 | AP17: 10.006 | AQ17: 9.788 | AR17: 9.897 | AS17: 10.006 | AT17: 8.81 | AW17: 6.961 | AX17: 172.553 | AY17: 301.506 | AZ17: 302.332 | BA17: 301.506 | BB17: 212.114 | BC17: 39.697 | BD17: 39.806 | BE17: 38.501
A18: hedge_ratio | D18: 헤지비율 | E18: 0.7 | F18: 0.7 | G18: 0.7 | H18: 0.7 | I18: 0.7 | J18: 0.7 | K18: 0.7 | L18: 0.7 | M18: 0.7 | N18: 0.7 | O18: 0.7 | P18: 0.7 | Q18: 0.7 | R18: 0.7 | S18: 0.7 | T18: 0.7 | U18: 0.7 | V18: 0.7 | W18: 0.7 | X18: 0.7 | Y18: 0.7 | Z18: 0.7 | AA18: 0.7 | AB18: 0.7 | AC18: 0.7 | AD18: 0.7 | AE18: 0.7 | AF18: 0.7 | AG18: 0.7 | AH18: 0.7 | AI18: 0.7 | AJ18: 0.7 | AK18: 0.7 | AL18: 0.7 | AM18: 0.7 | AN18: 0.7 | AO18: 0.7 | AP18: 0.7 | AQ18: 0.7 | AR18: 0.7 | AS18: 0.7 | AT18: 0.7
A19: hedge_rate | D19: 헤지환율(가중) | E19: 1315.69 | F19: 1315.69 | G19: 1317.53 | H19: 1325.79 | I19: 1327.15 | J19: 1337.29 | K19: 1390.93 | L19: 1399.85 | M19: 1398.73 | N19: 1404.67 | O19: 1420.51 | P19: 1441.66 | Q19: 1448.19 | R19: 1447.28 | S19: 1447.28 | T19: 1449.82 | U19: 1456.41 | V19: 1458.77 | W19: 1460.33 | X19: 1462.89 | Y19: 1462.95 | Z19: 1465.63 | AA19: 1474.84 | AB19: 1471.74 | AC19: 1471.47 | AD19: 1459.43 | AE19: 1454.78 | AF19: 1460.76 | AG19: 1442.92 | AH19: 1421.56 | AI19: 1406.62 | AJ19: 1435.45 | AK19: 1449.19 | AL19: 1449.19 | AM19: 1449.19 | AN19: 1449.19 | AO19: 1449.19 | AP19: 1449.19 | AQ19: 1449.19 | AR19: 1449.19 | AS19: 1449.19 | AT19: 1449.19
A20: spot_assumed | D20: 건조시점 환율(sls 가정) | E20: 1313.62 | F20: 1322.01 | G20: 1330.14 | H20: 1371.28 | I20: 1356.22 | J20: 1396.3 | K20: 1452.28 | L20: 1398.52 | M20: 1386.95 | N20: 1449.19 | O20: 1466.12 | P20: 1501.75 | Q20: 1418.75 | R20: 1343.39 | S20: 1341.45 | T20: 1341.45 | U20: 1341.45 | V20: 1341.45 | W20: 1341.45 | X20: 1341.45 | Y20: 1341.45 | Z20: 1341.45 | AA20: 1341.45 | AB20: 1341.45 | AC20: 1341.45 | AD20: 1341.45 | AE20: 1341.45 | AF20: 1341.45 | AG20: 1341.45 | AH20: 1341.45 | AI20: 1341.45 | AJ20: 1341.45 | AK20: 1341.45 | AL20: 1341.45 | AM20: 1341.45 | AN20: 1341.45 | AO20: 1341.45 | AP20: 1341.45 | AQ20: 1341.45 | AR20: 1341.45 | AS20: 1341.45 | AT20: 1341.45
A21: applied_rate | D21: 적용환율 | E21: 1315.07 | F21: 1317.59 | G21: 1321.32 | H21: 1339.44 | I21: 1335.87 | J21: 1354.99 | K21: 1409.33 | L21: 1399.45 | M21: 1395.2 | N21: 1418.02 | O21: 1434.19 | P21: 1459.68 | Q21: 1439.36 | R21: 1416.11 | S21: 1415.53 | T21: 1417.31 | U21: 1421.92 | V21: 1423.58 | W21: 1424.67 | X21: 1426.46 | Y21: 1426.5 | Z21: 1428.38 | AA21: 1434.82 | AB21: 1432.65 | AC21: 1432.46 | AD21: 1424.04 | AE21: 1420.78 | AF21: 1424.97 | AG21: 1412.48 | AH21: 1397.53 | AI21: 1387.07 | AJ21: 1407.25 | AK21: 1416.87 | AL21: 1416.87 | AM21: 1416.87 | AN21: 1416.87 | AO21: 1416.87 | AP21: 1416.87 | AQ21: 1416.87 | AR21: 1416.87 | AS21: 1416.87 | AT21: 1416.87
A22: hedged_krw_m | D22: 헤지적용 원화매출(백만원) | E22: 126170.6 | F22: 126412.1 | G22: 143730.6 | H22: 169095.8 | I22: 174592.2 | J22: 207502.3 | K22: 410377.2 | L22: 533132.2 | M22: 747967.7 | N22: 907745.3 | O22: 1272424.3 | P22: 1878862.5 | Q22: 2245812.9 | R22: 2280307.6 | S22: 2229818.9 | T22: 2214571 | U22: 2132618.4 | V22: 2057583.3 | W22: 1966462.1 | X22: 1902439.2 | Y22: 1770464 | Z22: 1592202.1 | AA22: 1052321.8 | AB22: 824321.8 | AC22: 675449.6 | AD22: 427568.1 | AE22: 247444.2 | AF22: 215216.4 | AG22: 93015.9 | AH22: 47413.8 | AI22: 38802.4 | AJ22: 17624.4 | AK22: 14177 | AL22: 14177 | AM22: 14022.9 | AN22: 14022.9 | AO22: 14177 | AP22: 14177 | AQ22: 13868.8 | AR22: 14022.9 | AS22: 14177 | AT22: 12481.9 | AU22: 252582.7 | AV22: 694920.9 | AW22: 2599222.4 | AX22: 7677407.3 | AY22: 8634591.6 | AZ22: 7231567.4 | BA22: 2979661.3 | BB22: 603090.3 | BC22: 84780.8 | BD22: 56399.8 | BE22: 54550.6
A23: marine_hedged_krw_m | D23: 해양 원화(백만원) | E23: 126170.6 | F23: 126412.1 | G23: 143730.6 | H23: 169095.8 | I23: 174592.2 | J23: 207502.3 | K23: 410377.2 | L23: 533132.2 | M23: 747967.7 | N23: 907745.3 | O23: 1272424.3 | P23: 1851796.2 | Q23: 2175160.3 | R23: 2186819.5 | S23: 2138400.7 | T23: 2122137 | U23: 2039168.7 | V23: 1964133.6 | W23: 1874028.1 | X23: 1810005.2 | Y23: 1677014.3 | Z23: 1498752.4 | AA23: 960903.6 | AB23: 731887.9 | AC23: 581999.9 | AD23: 334118.4 | AE23: 156026 | AF23: 122782.4 | AG23: 39664.6 | AH23: 39664.6 | AI23: 38802.4 | AJ23: 17624.4 | AK23: 14177 | AL23: 14177 | AM23: 14022.9 | AN23: 14022.9 | AO23: 14177 | AP23: 14177 | AQ23: 13868.8 | AR23: 14022.9 | AS23: 14177 | AT23: 12481.9 | AU23: 252582.7 | AV23: 694920.9 | AW23: 2599222.4 | AX23: 7486200.3 | AY23: 8263840 | AZ23: 6859800 | BA23: 2608909.8 | BB23: 358137.6 | BC23: 84780.8 | BD23: 56399.8 | BE23: 54550.6
A24: marine_hedged_krw_m_signed_by_origin | D24: 해양 원화 — origin 분기말까지 체결분(백만원) | E24: 126170.6 | F24: 126412.1 | G24: 143730.6 | H24: 169095.8 | I24: 174592.2 | J24: 207502.3 | K24: 410377.2 | L24: 533132.2 | M24: 747967.7 | N24: 907745.3 | O24: 1272424.3 | P24: 1851796.2 | Q24: 2119581.4 | R24: 2086296.3 | S24: 2040103.8 | T24: 2022747.9 | U24: 1938687.4 | V24: 1863652.3 | W24: 1774639 | X24: 1710616.2 | Y24: 1576533 | Z24: 1398271.2 | AA24: 862606.7 | AB24: 632498.8 | AC24: 520567.4 | AD24: 281470.7 | AE24: 121433.2 | AF24: 122782.4 | AG24: 39664.6 | AH24: 39664.6 | AI24: 38802.4 | AJ24: 17624.4 | AK24: 14177 | AL24: 14177 | AM24: 14022.9 | AN24: 14022.9 | AO24: 14177 | AP24: 14177 | AQ24: 13868.8 | AR24: 14022.9 | AS24: 14177 | AT24: 12481.9
A25: marine_hedged_krw_m_post_origin | D25: 해양 원화 — origin 이후 체결분(백만원) | E25: 0 | F25: 0 | G25: 0 | H25: 0 | I25: 0 | J25: 0 | K25: 0 | L25: 0 | M25: 0 | N25: 0 | O25: 0 | P25: 0 | Q25: 55578.9 | R25: 100523.2 | S25: 98296.9 | T25: 99389.1 | U25: 100481.3 | V25: 100481.3 | W25: 99389.1 | X25: 99389.1 | Y25: 100481.3 | Z25: 100481.3 | AA25: 98296.9 | AB25: 99389.1 | AC25: 61432.5 | AD25: 52647.7 | AE25: 34592.8 | AF25: 0 | AG25: 0 | AH25: 0 | AI25: 0 | AJ25: 0 | AK25: 0 | AL25: 0 | AM25: 0 | AN25: 0 | AO25: 0 | AP25: 0 | AQ25: 0 | AR25: 0 | AS25: 0 | AT25: 0
A26: target_opm | D26: 타겟 OPM(코호트) | E26: 0.108 | F26: 0.108 | G26: 0.108 | H26: 0.108 | I26: 0.108 | J26: 0.108 | K26: 0.108 | L26: 0.108 | M26: 0.108 | N26: 0.108 | O26: 0.108 | P26: 0.108 | Q26: 0.108 | R26: 0.108 | S26: 0.108 | T26: 0.108 | U26: 0.108 | V26: 0.108 | W26: 0.108 | X26: 0.108 | Y26: 0.108 | Z26: 0.108 | AA26: 0.108 | AB26: 0.108 | AC26: 0.108 | AD26: 0.108 | AE26: 0.108 | AF26: 0.108 | AG26: 0.108 | AH26: 0.108 | AI26: 0.108 | AJ26: 0.108
A28: 선표 연결(수식) — 원화(백만원) = 스케줄(백만$) × 포함 × (1 + (캡배율 − 1) × origin 이후) × (헤지비율 × 헤지환율 + (1 − 헤지비율) × 건조시점 환율) | J28: subQ 매출조선 = 합계/100 + 변수 잔고 소진 + 매출조선신규
A29: 헤지비율 | D29: =변수!$D$61 | E29: 변수 3절 '헤지비율' 참조 — 약정환율 미공시 → HEDGE 70% 가정(레퍼런스 SLS 시트 HEDGE 행은 미포 65%·삼성重 100% — 그 사이에 둔 설정값). hedge_rate 는 계약별 수주시점 환율로 대체
A30: 헤지환율 방식 | D30: 계약별 수주시점 환율(fx_at_sign)
A31: spot_krw | D31: 건조시점 원/달러(평균) — 변수 환율 행 참조, 변수 범위 밖 분기는 sls spot_assumed | E31: =IFERROR(VLOOKUP(" 원/달러(평균)",환율,MATCH(E$1,변수H,0),0),1313.62) | F31: =IFERROR(VLOOKUP(" 원/달러(평균)",환율,MATCH(F$1,변수H,0),0),1322.01) | G31: =IFERROR(VLOOKUP(" 원/달러(평균)",환율,MATCH(G$1,변수H,0),0),1330.14) | H31: =IFERROR(VLOOKUP(" 원/달러(평균)",환율,MATCH(H$1,변수H,0),0),1371.28) | I31: =IFERROR(VLOOKUP(" 원/달러(평균)",환율,MATCH(I$1,변수H,0),0),1356.22) | J31: =IFERROR(VLOOKUP(" 원/달러(평균)",환율,MATCH(J$1,변수H,0),0),1396.3) | K31: =IFERROR(VLOOKUP(" 원/달러(평균)",환율,MATCH(K$1,변수H,0),0),1452.28) | L31: =IFERROR(VLOOKUP(" 원/달러(평균)",환율,MATCH(L$1,변수H,0),0),1398.52) | M31: =IFERROR(VLOOKUP(" 원/달러(평균)",환율,MATCH(M$1,변수H,0),0),1386.95) | N31: =IFERROR(VLOOKUP(" 원/달러(평균)",환율,MATCH(N$1,변수H,0),0),1449.19) | O31: =IFERROR(VLOOKUP(" 원/달러(평균)",환율,MATCH(O$1,변수H,0),0),1466.12) | P31: =IFERROR(VLOOKUP(" 원/달러(평균)",환율,MATCH(P$1,변수H,0),0),1501.75) | Q31: =IFERROR(VLOOKUP(" 원/달러(평균)",환율,MATCH(Q$1,변수H,0),0),1418.75) | R31: =IFERROR(VLOOKUP(" 원/달러(평균)",환율,MATCH(R$1,변수H,0),0),1343.39) | S31: =IFERROR(VLOOKUP(" 원/달러(평균)",환율,MATCH(S$1,변수H,0),0),1341.45) | T31: =IFERROR(VLOOKUP(" 원/달러(평균)",환율,MATCH(T$1,변수H,0),0),1341.45) | U31: =IFERROR(VLOOKUP(" 원/달러(평균)",환율,MATCH(U$1,변수H,0),0),1341.45) | V31: =IFERROR(VLOOKUP(" 원/달러(평균)",환율,MATCH(V$1,변수H,0),0),1341.45) | W31: =IFERROR(VLOOKUP(" 원/달러(평균)",환율,MATCH(W$1,변수H,0),0),1341.45) | X31: =IFERROR(VLOOKUP(" 원/달러(평균)",환율,MATCH(X$1,변수H,0),0),1341.45) | Y31: =IFERROR(VLOOKUP(" 원/달러(평균)",환율,MATCH(Y$1,변수H,0),0),1341.45) | Z31: =IFERROR(VLOOKUP(" 원/달러(평균)",환율,MATCH(Z$1,변수H,0),0),1341.45) | ... AT31: =IFERROR(VLOOKUP(" 원/달러(평균)",환율,MATCH(AT$1,변수H,0),0),1341.45)
A32: after_origin | D32: origin(2026Q2) 이후 분기 = 1 (잔고 캡 배율 적용 구간) | E32: 0 | F32: 0 | G32: 0 | H32: 0 | I32: 0 | J32: 0 | K32: 0 | L32: 0 | M32: 0 | N32: 0 | O32: 0 | P32: 0 | Q32: 1 | R32: 1 | S32: 1 | T32: 1 | U32: 1 | V32: 1 | W32: 1 | X32: 1 | Y32: 1 | Z32: 1 | AA32: 1 | AB32: 1 | AC32: 1 | AD32: 1 | AE32: 1 | AF32: 1 | AG32: 1 | AH32: 1 | AI32: 1 | AJ32: 1 | AK32: 1 | AL32: 1 | AM32: 1 | AN32: 1 | AO32: 1 | AP32: 1 | AQ32: 1 | AR32: 1 | AS32: 1 | AT32: 1
A34: ① 계약별 매출인식 스케줄(백만$, sls 저장값) | B34: type | C34: ships | D34: name | BG34: 포함(1/0) | BH34: 헤지환율 | BI34: 캡배율 | BJ34: 체결일 | BK34: origin이내 | BL34: 코호트 | BM34: 계약액(백만$) | BN34: 종료
A35: 20241118800037 | B35: VLGC | C35: 2 | D35: VLGC 2척 | J35: 10.03 | K35: 19.207 | L35: 19.42 | M35: 19.634 | N35: 19.634 | O35: 19.207 | P35: 19.42 | Q35: 19.634 | R35: 19.634 | S35: 19.207 | T35: 19.42 | U35: 19.634 | V35: 19.635 | BG35: 1 | BH35: 1396.3 | BI35: 1 | BJ35: 2024-11-15 | BK35: 1 | BL35: ⑤초호황 | BM35: 243.716 | BN35: 2027-12-31
A36: 20250123800036 | B36: CONT | C36: 12 | D36: 초대형 컨테이너선 12척 | K36: 122.777 | L36: 161.923 | M36: 163.702 | N36: 163.702 | O36: 160.143 | P36: 161.923 | Q36: 163.702 | R36: 163.702 | S36: 160.143 | T36: 161.923 | U36: 163.702 | V36: 163.702 | W36: 161.923 | X36: 161.923 | Y36: 163.702 | Z36: 160.143 | BG36: 1 | BH36: 1452.28 | BI36: 1 | BJ36: 2025-01-22 | BK36: 1 | BL36: ⑤초호황 | BM36: 2558.735 | BN36: 2028-12-29
A37: 20250213800540 | B37: NAVAL | C37: 4 | D37: 함정 4척 건조용 자재 및 장비 공급 | H37: 15.357 | I37: 18.59 | J37: 18.59 | K37: 18.186 | L37: 18.388 | M37: 18.59 | N37: 18.59 | O37: 18.186 | P37: 18.388 | Q37: 18.59 | R37: 18.59 | S37: 18.186 | T37: 18.388 | U37: 18.59 | V37: 18.59 | W37: 18.388 | X37: 18.388 | Y37: 18.59 | Z37: 18.59 | AA37: 18.186 | AB37: 18.388 | AC37: 18.59 | AD37: 18.59 | AE37: 18.186 | AF37: 18.388 | AG37: 18.59 | AH37: 18.59 | AI37: 18.186 | AJ37: 2.631 | BG37: 1 | BH37: 1383.7 | BI37: 1 | BJ37: 2024-04-16 | BK37: 1 | BL37: ⑤초호황 | BM37: 516.08 | BN37: 2031-04-13
A38: 20250304800166 | B38: VLGC | C38: 2 | D38: VLEC 2척 | K38: 7.206 | L38: 20.491 | M38: 20.716 | N38: 20.716 | O38: 20.266 | P38: 20.491 | Q38: 20.716 | R38: 20.716 | S38: 20.266 | T38: 20.491 | U38: 20.716 | V38: 20.716 | W38: 20.491 | X38: 20.491 | Y38: 20.716 | Z38: 20.712 | BG38: 1 | BH38: 1452.28 | BI38: 1 | BJ38: 2025-02-28 | BK38: 1 | BL38: ⑤초호황 | BM38: 315.917 | BN38: 2028-12-31
A39: 20250422800296 | B39: VLGC | C39: 2 | D39: VLGC 2척 | G39: 13.879 | H39: 15.987 | I39: 16.163 | J39: 16.163 | K39: 15.812 | L39: 15.987 | M39: 16.163 | N39: 16.163 | O39: 15.812 | P39: 15.987 | Q39: 16.163 | R39: 16.163 | S39: 15.812 | T39: 15.987 | U39: 10.892 | BG39: 1 | BH39: 1330.14 | BI39: 1 | BJ39: 2024-01-13 | BK39: 1 | BL39: ⑤초호황 | BM39: 233.133 | BN39: 2027-08-31
A40: 20250521800001 | B40: VLCC | C40: 2 | D40: 157,000 DWT 원유운반선 2척 | J40: 12.414 | K40: 14.142 | L40: 14.299 | M40: 14.456 | N40: 14.456 | O40: 14.142 | P40: 14.299 | Q40: 14.456 | R40: 14.456 | S40: 14.142 | T40: 14.299 | U40: 14.46 | BG40: 1 | BH40: 1396.3 | BI40: 1 | BJ40: 2024-10-14 | BK40: 1 | BL40: ⑤초호황 | BM40: 170.021 | BN40: 2027-09-30
A41: 20250610800109 | B41: CONT | C41: 8 | D41: 컨테이너선 8척 | L41: 29.704 | M41: 124.218 | N41: 124.218 | O41: 121.518 | P41: 122.868 | Q41: 124.218 | R41: 124.218 | S41: 121.518 | T41: 122.868 | U41: 124.218 | V41: 124.218 | W41: 122.868 | X41: 122.868 | Y41: 124.218 | Z41: 82.362 | BG41: 1 | BH41: 1398.52 | BI41: 1 | BJ41: 2025-06-09 | BK41: 1 | BL41: ⑤초호황 | BM41: 1716.1 | BN41: 2028-11-30
A42: 20250613800119 | B42: VLCC | C42: 2 | D42: VLCC 2척 | L42: 5.846 | M42: 28.309 | N42: 28.309 | O42: 27.694 | P42: 28.001 | Q42: 28.309 | R42: 28.309 | S42: 27.694 | T42: 28.001 | U42: 19.078 | BG42: 1 | BH42: 1398.52 | BI42: 1 | BJ42: 2025-06-12 | BK42: 1 | BL42: ⑤초호황 | BM42: 249.55 | BN42: 2027-08-31
A43: 20250708800090 | B43: CONT | C43: 2 | D43: 컨테이너선 2척 | M43: 25.907 | N43: 27.715 | O43: 27.112 | P43: 27.414 | Q43: 27.715 | R43: 27.715 | S43: 27.112 | T43: 27.414 | U43: 27.715 | V43: 27.715 | W43: 27.414 | BG43: 1 | BH43: 1386.95 | BI43: 1 | BJ43: 2025-07-07 | BK43: 1 | BL43: ⑤초호황 | BM43: 300.948 | BN43: 2028-03-31
A44: 20250908800058 | B44: CONT | C44: 2 | D44: 컨테이너선 2척 | M44: 8.464 | N44: 29.948 | O44: 29.297 | P44: 29.623 | Q44: 29.948 | R44: 29.948 | S44: 29.297 | T44: 29.623 | U44: 29.948 | V44: 29.948 | W44: 19.208 | BG44: 1 | BH44: 1386.95 | BI44: 1 | BJ44: 2025-09-05 | BK44: 1 | BL44: ⑤초호황 | BM44: 295.252 | BN44: 2028-02-28
A45: 20251020800152 | B45: VLCC | C45: 2 | D45: VLCC 2척 | N45: 24.584 | O45: 29.113 | P45: 29.436 | Q45: 29.76 | R45: 29.76 | S45: 29.113 | T45: 29.436 | U45: 29.76 | V45: 19.73 | BG45: 1 | BH45: 1449.19 | BI45: 1 | BJ45: 2025-10-17 | BK45: 1 | BL45: ⑤초호황 | BM45: 250.692 | BN45: 2027-11-30
A46: 20251030800164 | B46: NAVAL | D46: KSS-II 성능개량 체계개발사업 | N46: 6.961 | O46: 9.788 | P46: 9.897 | Q46: 10.006 | R46: 10.006 | S46: 9.788 | T46: 9.897 | U46: 10.006 | V46: 10.006 | W46: 9.897 | X46: 9.897 | Y46: 10.006 | Z46: 10.006 | AA46: 9.788 | AB46: 9.897 | AC46: 10.006 | AD46: 10.006 | AE46: 9.788 | AF46: 9.897 | AG46: 10.006 | AH46: 10.006 | AI46: 9.788 | AJ46: 9.897 | AK46: 10.006 | AL46: 10.006 | AM46: 9.897 | AN46: 9.897 | AO46: 10.006 | AP46: 10.006 | AQ46: 9.788 | AR46: 9.897 | AS46: 10.006 | AT46: 8.811 | BG46: 1 | BH46: 1449.19 | BI46: 1 | BJ46: 2025-10-29 | BK46: 1 | BM46: 323.56 | BN46: 2033-12-20
A47: 20251110800036 | B47: CONT | C47: 2 | D47: 컨테이너선 2척 | N47: 15.157 | O47: 24.802 | P47: 25.077 | Q47: 25.353 | R47: 25.353 | S47: 24.802 | T47: 25.077 | U47: 25.353 | V47: 25.353 | W47: 25.077 | X47: 25.077 | Y47: 25.353 | Z47: 8.541 | BG47: 1 | BH47: 1449.19 | BI47: 1 | BJ47: 2025-11-07 | BK47: 1 | BL47: ⑤초호황 | BM47: 300.375 | BN47: 2028-10-31
A48: 20251114800376 | B48: VLCC | C48: 2 | D48: 157,000 DWT 원유운반선 2척 | N48: 7.991 | O48: 14.678 | P48: 14.841 | Q48: 15.004 | R48: 15.004 | S48: 14.678 | T48: 14.841 | U48: 15.004 | V48: 15.004 | W48: 14.841 | X48: 14.841 | Y48: 15.004 | Z48: 5.057 | BG48: 1 | BH48: 1449.19 | BI48: 1 | BJ48: 2025-11-13 | BK48: 1 | BL48: ⑤초호황 | BM48: 176.788 | BN48: 2028-10-31
A49: 20251124800125 | B49: CONT | C49: 2 | D49: 컨테이너선 2척 | N49: 15.641 | O49: 34.334 | P49: 34.715 | Q49: 35.097 | R49: 35.097 | S49: 34.334 | T49: 34.715 | U49: 35.097 | V49: 35.097 | W49: 34.715 | X49: 34.715 | Y49: 5.339 | BG49: 1 | BH49: 1449.19 | BI49: 1 | BJ49: 2025-11-21 | BK49: 1 | BL49: ⑤초호황 | BM49: 368.896 | BN49: 2028-07-14
A50: 20251211800371 | B50: VLGC | C50: 2 | D50: VLAC 2척 | N50: 5.572 | O50: 22.795 | P50: 23.048 | Q50: 23.301 | R50: 23.301 | S50: 22.795 | T50: 23.048 | U50: 23.301 | V50: 23.301 | W50: 23.048 | X50: 23.048 | Y50: 7.854 | BG50: 1 | BH50: 1449.19 | BI50: 1 | BJ50: 2025-12-10 | BK50: 1 | BL50: ⑤초호황 | BM50: 244.412 | BN50: 2028-07-31
A51: 20251224800145 | B51: PC | C51: 5 | D51: P/C선 5척 | N51: 2.446 | O51: 24.463 | P51: 24.735 | Q51: 25.007 | R51: 25.007 | S51: 24.463 | T51: 24.735 | U51: 25.007 | V51: 25.007 | W51: 24.735 | X51: 24.735 | Y51: 8.425 | BG51: 1 | BH51: 1449.19 | BI51: 1 | BJ51: 2025-12-23 | BK51: 1 | BL51: ⑤초호황 | BM51: 258.765 | BN51: 2028-07-31
A52: 20251226800842 | B52: NAVAL | C52: 2 | D52: 수상함 2척 | N52: 2.402 | O52: 36.029 | P52: 36.43 | Q52: 36.83 | R52: 36.83 | S52: 36.029 | T52: 36.43 | U52: 36.83 | V52: 36.83 | W52: 36.43 | X52: 36.43 | Y52: 36.83 | Z52: 36.83 | AA52: 36.029 | AB52: 36.43 | AC52: 36.83 | AD52: 32.428 | BG52: 1 | BH52: 1449.19 | BI52: 1 | BJ52: 2025-12-26 | BK52: 1 | BL52: ⑤초호황 | BM52: 582.877 | BN52: 2029-12-20
A53: 20260106800134 | B53: LNGC | C53: 4 | D53: LNGC 4척 | O53: 74.657 | P53: 78.998 | Q53: 79.866 | R53: 79.866 | S53: 78.13 | T53: 78.998 | U53: 79.866 | V53: 79.866 | W53: 78.998 | X53: 78.998 | Y53: 79.866 | Z53: 79.866 | AA53: 74.656 | BG53: 1 | BH53: 1466.12 | BI53: 1 | BJ53: 2026-01-05 | BK53: 1 | BL53: ⑤초호황 | BM53: 1022.631 | BN53: 2029-03-27
A54: 20260120800200 | B54: VLCC | C54: 2 | D54: 157,000 DWT 원유운반선 2척, 115,000 DWT P/C선 2척 | O54: 18.786 | P54: 23.743 | Q54: 24.004 | R54: 24.004 | S54: 23.482 | T54: 23.743 | U54: 24.004 | V54: 24.004 | W54: 23.743 | X54: 23.743 | Y54: 24.004 | Z54: 24.004 | AA54: 23.482 | AB54: 23.74 | BG54: 1 | BH54: 1466.12 | BI54: 1 | BJ54: 2026-01-19 | BK54: 1 | BL54: ⑤초호황 | BM54: 328.486 | BN54: 2029-06-30
A55: 20260226800192 | B55: LNGC | C55: 1 | D55: LNGC 1척 | O55: 9.262 | P55: 24.081 | Q55: 24.346 | R55: 24.346 | S55: 23.816 | T55: 24.081 | U55: 24.346 | V55: 24.346 | W55: 24.081 | X55: 24.081 | Y55: 24.08 | BG55: 1 | BH55: 1466.12 | BI55: 1 | BJ55: 2026-02-25 | BK55: 1 | BL55: ⑤초호황 | BM55: 250.866 | BN55: 2028-09-29
A56: 20260227800223 | B56: CONT | C56: 6 | D56: 컨테이너선 6척 | O56: 10.089 | P56: 27.003 | Q56: 27.299 | R56: 27.299 | S56: 26.706 | T56: 27.003 | U56: 27.299 | V56: 27.299 | W56: 27.003 | X56: 27.004 | BG56: 1 | BH56: 1466.12 | BI56: 1 | BJ56: 2026-02-26 | BK56: 1 | BL56: ⑤초호황 | BM56: 254.004 | BN56: 2028-06-30
A57: 20260305800836 | B57: LNGC | C57: 4 | D57: LNGC 4척 | O57: 20.762 | P57: 67.477 | Q57: 68.218 | R57: 68.218 | S57: 66.735 | T57: 67.477 | U57: 68.218 | V57: 68.218 | W57: 67.477 | X57: 67.477 | Y57: 68.218 | Z57: 68.218 | AA57: 66.735 | AB57: 67.477 | AC57: 68.218 | AD57: 45.235 | BG57: 1 | BH57: 1466.12 | BI57: 1 | BJ57: 2026-03-04 | BK57: 1 | BL57: ⑤초호황 | BM57: 1014.378 | BN57: 2029-11-30
A58: 20260316800220 | B58: CONT | C58: 10 | D58: 컨테이너선 10척 | O58: 10.414 | P58: 49.879 | Q58: 50.427 | R58: 50.427 | S58: 49.331 | T58: 49.879 | U58: 50.427 | V58: 50.427 | W58: 49.879 | X58: 49.879 | Y58: 50.427 | Z58: 50.427 | BG58: 1 | BH58: 1466.12 | BI58: 1 | BJ58: 2026-03-13 | BK58: 1 | BL58: ⑤초호황 | BM58: 561.823 | BN58: 2028-12-31
A59: 20260403800571 | B59: PC | C59: 8 | D59: P/C선 8척 | P59: 31.712 | Q59: 32.417 | R59: 32.417 | S59: 31.712 | T59: 32.065 | U59: 32.417 | V59: 32.417 | W59: 32.065 | X59: 32.065 | Y59: 32.417 | Z59: 32.417 | AA59: 31.712 | AB59: 21.492 | BG59: 1 | BH59: 1501.75 | BI59: 1 | BJ59: 2026-04-02 | BK59: 1 | BL59: ⑤초호황 | BM59: 407.325 | BN59: 2029-05-31
A60: 20260403800577 | B60: VLGC | C60: 2 | D60: LPGC 2척 | P60: 17.468 | Q60: 17.856 | R60: 17.856 | S60: 17.468 | T60: 17.662 | U60: 17.856 | V60: 17.856 | W60: 17.662 | X60: 17.663 | BG60: 1 | BH60: 1501.75 | BI60: 1 | BJ60: 2026-04-02 | BK60: 1 | BL60: ⑤초호황 | BM60: 159.347 | BN60: 2028-06-30
A61: 20260417800177 | B61: VLGC | C61: 4 | D61: VLGC 4척 | P61: 25.77 | Q61: 31.195 | R61: 31.195 | S61: 30.517 | T61: 30.856 | U61: 31.195 | V61: 31.195 | W61: 30.856 | X61: 30.856 | Y61: 31.195 | Z61: 31.195 | AA61: 30.517 | AB61: 30.856 | AC61: 31.195 | AD61: 20.683 | BG61: 1 | BH61: 1501.75 | BI61: 1 | BJ61: 2026-04-16 | BK61: 1 | BL61: ⑤초호황 | BM61: 449.276 | BN61: 2029-11-30
A62: 20260422800038 | B62: NAVAL | C62: 1 | D62: 쇄빙전용선 1척 | P62: 19.852 | Q62: 25.724 | R62: 25.724 | S62: 25.165 | T62: 25.444 | U62: 25.724 | V62: 25.724 | W62: 25.444 | X62: 25.444 | Y62: 25.724 | Z62: 25.724 | AA62: 25.165 | AB62: 25.444 | AC62: 16.498 | BG62: 1 | BH62: 1501.75 | BI62: 1 | BJ62: 2026-04-21 | BK62: 1 | BL62: ⑤초호황 | BM62: 342.8 | BN62: 2029-08-28
A63: 20260422800175 | B63: OTHER | D63: 엔진발전기 공급 | P63: 18.023 | Q63: 23.354 | R63: 23.354 | S63: 22.846 | T63: 23.1 | U63: 23.354 | V63: 23.354 | W63: 23.1 | X63: 23.1 | Y63: 23.354 | Z63: 23.354 | AA63: 22.846 | AB63: 23.1 | AC63: 23.354 | AD63: 23.354 | AE63: 22.846 | AF63: 23.1 | AG63: 23.354 | AH63: 5.332 | BG63: 0 | BH63: 1501.75 | BI63: 1 | BJ63: 2026-04-21 | BK63: 1 | BM63: 417.579 | BN63: 2030-10-21
A64: 20260504800297 | B64: VLGC | C64: 3 | D64: VLGC 3척 | P64: 17.083 | Q64: 25.348 | R64: 25.348 | S64: 24.797 | T64: 25.073 | U64: 25.348 | V64: 25.348 | W64: 25.073 | X64: 25.073 | Y64: 25.348 | Z64: 25.348 | AA64: 24.797 | AB64: 25.073 | AC64: 17.084 | BG64: 1 | BH64: 1501.75 | BI64: 1 | BJ64: 2026-04-30 | BK64: 1 | BL64: ⑤초호황 | BM64: 336.141 | BN64: 2029-08-31
A65: 20260508800180 | B65: CONT | C65: 6 | D65: 컨테이너선 6척 | P65: 52.408 | Q65: 87.664 | R65: 87.664 | S65: 85.758 | T65: 86.711 | U65: 87.664 | V65: 87.664 | W65: 86.711 | X65: 86.711 | Y65: 87.664 | Z65: 87.664 | AA65: 85.758 | AB65: 86.711 | AC65: 87.666 | BG65: 1 | BH65: 1501.75 | BI65: 1 | BJ65: 2026-05-07 | BK65: 1 | BL65: ⑤초호황 | BM65: 1184.418 | BN65: 2029-09-30
A66: 20260508800181 | B66: VLGC | C66: 2 | D66: VLGC 2척 | P66: 12.177 | Q66: 20.369 | R66: 20.369 | S66: 19.926 | T66: 20.147 | U66: 20.369 | V66: 20.369 | W66: 20.147 | X66: 20.147 | Y66: 20.369 | Z66: 20.369 | AA66: 19.702 | BG66: 1 | BH66: 1501.75 | BI66: 1 | BJ66: 2026-05-07 | BK66: 1 | BL66: ⑤초호황 | BM66: 234.46 | BN66: 2029-03-30
A67: 20260514800315 | B67: LNGC | C67: 2 | D67: LNGC 2척 | P67: 23.051 | Q67: 43.279 | R67: 43.279 | S67: 42.338 | T67: 42.808 | U67: 43.279 | V67: 43.279 | W67: 42.808 | X67: 42.808 | Y67: 43.279 | Z67: 43.279 | AA67: 41.868 | BG67: 1 | BH67: 1501.75 | BI67: 1 | BJ67: 2026-05-13 | BK67: 1 | BL67: ⑤초호황 | BM67: 495.355 | BN67: 2029-03-30
A68: 20260601800384 | B68: VLGC | C68: 8 | D68: VLGC 8척 | P68: 20.211 | Q68: 58.106 | R68: 58.106 | S68: 56.843 | T68: 57.475 | U68: 58.106 | V68: 58.106 | W68: 57.475 | X68: 57.475 | Y68: 58.106 | Z68: 58.106 | AA68: 56.843 | AB68: 57.475 | AC68: 58.106 | AD68: 58.106 | AE68: 56.843 | AF68: 57.479 | BG68: 1 | BH68: 1501.75 | BI68: 1 | BJ68: 2026-05-30 | BK68: 1 | BL68: ⑤초호황 | BM68: 942.967 | BN68: 2030-06-30
A69: 20260608800378 | B69: VLGC | C69: 2 | D69: VLGC 2척 | P69: 4.898 | Q69: 17.331 | R69: 17.331 | S69: 16.954 | T69: 17.143 | U69: 17.331 | V69: 17.331 | W69: 17.143 | X69: 17.143 | Y69: 17.331 | Z69: 17.331 | AA69: 16.954 | AB69: 17.143 | AC69: 17.331 | AD69: 11.491 | BG69: 1 | BH69: 1501.75 | BI69: 1 | BJ69: 2026-06-05 | BK69: 1 | BL69: ⑤초호황 | BM69: 240.186 | BN69: 2029-11-30
A70: 20260701800212 | B70: LNGC | C70: 1 | D70: FSRU 1척 | P70: 0.308 | Q70: 28.294 | R70: 28.294 | S70: 27.679 | T70: 27.987 | U70: 28.294 | V70: 28.294 | W70: 27.987 | X70: 27.987 | Y70: 28.294 | Z70: 28.294 | AA70: 27.679 | AB70: 18.759 | BG70: 1 | BH70: 1501.75 | BI70: 1 | BJ70: 2026-06-30 | BK70: 1 | BL70: ⑤초호황 | BM70: 328.15 | BN70: 2029-05-31
A71: 20260701800215 | B71: LNGC | C71: 1 | D71: LNGC 1척 | P71: 0.276 | Q71: 25.372 | R71: 25.372 | S71: 24.82 | T71: 25.096 | U71: 25.372 | V71: 25.372 | W71: 25.096 | X71: 25.096 | Y71: 25.372 | Z71: 25.372 | AA71: 8.546 | BG71: 1 | BH71: 1501.75 | BI71: 1 | BJ71: 2026-06-30 | BK71: 1 | BL71: ⑤초호황 | BM71: 261.162 | BN71: 2029-01-31
A72: 20260709800137 | B72: PC | C72: 6 | D72: P/C선 6척 | Q72: 25.852 | R72: 27.981 | S72: 27.372 | T72: 27.677 | U72: 27.981 | V72: 27.981 | W72: 27.677 | X72: 27.677 | Y72: 27.981 | Z72: 27.981 | AA72: 27.372 | AB72: 27.675 | BG72: 0 | BH72: 1418.75 | BI72: 1 | BJ72: 2026-07-08 | BK72: 0 | BL72: ⑤초호황 | BM72: 331.207 | BN72: 2029-06-30
A73: 20260714800534 | B73: PCTC | C73: 2 | D73: PCTC 2척 | P73: 21.262 | Q73: 25.404 | R73: 25.404 | S73: 24.851 | T73: 25.127 | U73: 25.404 | V73: 25.404 | W73: 25.127 | X73: 25.127 | Y73: 25.404 | Z73: 16.843 | BG73: 1 | BH73: 1501.75 | BI73: 1 | BJ73: 2026-04-15 | BK73: 1 | BL73: ⑤초호황 | BM73: 265.357 | BN73: 2028-11-30
A74: 20260810800144 | B74: OTHER | D74: 엔진발전기 공급 | Q74: 25.489 | R74: 42.636 | S74: 41.709 | T74: 42.172 | U74: 42.636 | V74: 42.636 | W74: 42.172 | X74: 42.172 | Y74: 42.636 | Z74: 42.636 | AA74: 41.709 | AB74: 42.172 | AC74: 42.636 | AD74: 42.636 | AE74: 41.709 | AF74: 42.172 | AG74: 13.905 | BG74: 0 | BH74: 1418.75 | BI74: 1 | BJ74: 2026-08-07 | BK74: 0 | BM74: 673.833 | BN74: 2030-07-30
A75: 20260824800122 | B75: VLGC | C75: 4 | D75: LPGC 4척 | Q75: 11.292 | R75: 25.339 | S75: 24.788 | T75: 25.063 | U75: 25.339 | V75: 25.339 | W75: 25.063 | X75: 25.063 | Y75: 25.339 | Z75: 25.339 | AA75: 24.788 | AB75: 25.063 | AC75: 25.339 | AD75: 25.339 | AE75: 24.785 | BG75: 0 | BH75: 1418.75 | BI75: 1 | BJ75: 2026-08-21 | BK75: 0 | BL75: ⑤초호황 | BM75: 363.278 | BN75: 2030-03-31
A76: 20260922800219 | B76: PCTC | C76: 2 | D76: RORO선 2척 | Q76: 2.031 | R76: 18.681 | S76: 18.275 | T76: 18.478 | U76: 18.681 | V76: 18.681 | W76: 18.478 | X76: 18.478 | Y76: 18.681 | Z76: 18.681 | AA76: 18.275 | AB76: 18.478 | AC76: 18.681 | AD76: 12.39 | BG76: 0 | BH76: 1418.75 | BI76: 1 | BJ76: 2026-09-21 | BK76: 0 | BL76: ⑤초호황 | BM76: 236.969 | BN76: 2029-11-30
A77: 20261013800234 | B77: OFFSH | C77: 1 | D77: FPU 1기 | E77: 95.942 | F77: 95.942 | G77: 94.899 | H77: 94.899 | I77: 95.942 | J77: 95.942 | K77: 93.856 | L77: 94.899 | M77: 95.942 | N77: 95.942 | O77: 93.856 | P77: 94.899 | Q77: 95.942 | R77: 95.942 | S77: 93.856 | T77: 64.661 | BG77: 1 | BH77: 1315.69 | BI77: 1 | BJ77: 2023-06-30 | BK77: 1 | BL77: ⑤초호황 | BM77: 1493.361 | BN77: 2027-06-01
A79: ② 계약별 원화(백만원, 수식) | B79: type | C79: ships | D79: name
A80: 20241118800037 | B80: VLGC | C80: 2 | D80: VLGC 2척 | J80: =IFERROR(J35*$BG35*(1+($BI35-1)*J$32)*($D$29*$BH35+(1-$D$29)*J$31),"") | K80: =IFERROR(K35*$BG35*(1+($BI35-1)*K$32)*($D$29*$BH35+(1-$D$29)*K$31),"") | L80: =IFERROR(L35*$BG35*(1+($BI35-1)*L$32)*($D$29*$BH35+(1-$D$29)*L$31),"") | M80: =IFERROR(M35*$BG35*(1+($BI35-1)*M$32)*($D$29*$BH35+(1-$D$29)*M$31),"") | N80: =IFERROR(N35*$BG35*(1+($BI35-1)*N$32)*($D$29*$BH35+(1-$D$29)*N$31),"") | O80: =IFERROR(O35*$BG35*(1+($BI35-1)*O$32)*($D$29*$BH35+(1-$D$29)*O$31),"") | P80: =IFERROR(P35*$BG35*(1+($BI35-1)*P$32)*($D$29*$BH35+(1-$D$29)*P$31),"") | Q80: =IFERROR(Q35*$BG35*(1+($BI35-1)*Q$32)*($D$29*$BH35+(1-$D$29)*Q$31),"") | ... V80: =IFERROR(V35*$BG35*(1+($BI35-1)*V$32)*($D$29*$BH35+(1-$D$29)*V$31),"")
A81: 20250123800036 | B81: CONT | C81: 12 | D81: 초대형 컨테이너선 12척 | K81: =IFERROR(K36*$BG36*(1+($BI36-1)*K$32)*($D$29*$BH36+(1-$D$29)*K$31),"") | L81: =IFERROR(L36*$BG36*(1+($BI36-1)*L$32)*($D$29*$BH36+(1-$D$29)*L$31),"") | M81: =IFERROR(M36*$BG36*(1+($BI36-1)*M$32)*($D$29*$BH36+(1-$D$29)*M$31),"") | N81: =IFERROR(N36*$BG36*(1+($BI36-1)*N$32)*($D$29*$BH36+(1-$D$29)*N$31),"") | O81: =IFERROR(O36*$BG36*(1+($BI36-1)*O$32)*($D$29*$BH36+(1-$D$29)*O$31),"") | P81: =IFERROR(P36*$BG36*(1+($BI36-1)*P$32)*($D$29*$BH36+(1-$D$29)*P$31),"") | Q81: =IFERROR(Q36*$BG36*(1+($BI36-1)*Q$32)*($D$29*$BH36+(1-$D$29)*Q$31),"") | R81: =IFERROR(R36*$BG36*(1+($BI36-1)*R$32)*($D$29*$BH36+(1-$D$29)*R$31),"") | ... Z81: =IFERROR(Z36*$BG36*(1+($BI36-1)*Z$32)*($D$29*$BH36+(1-$D$29)*Z$31),"")
A82: 20250213800540 | B82: NAVAL | C82: 4 | D82: 함정 4척 건조용 자재 및 장비 공급 | H82: =IFERROR(H37*$BG37*(1+($BI37-1)*H$32)*($D$29*$BH37+(1-$D$29)*H$31),"") | I82: =IFERROR(I37*$BG37*(1+($BI37-1)*I$32)*($D$29*$BH37+(1-$D$29)*I$31),"") | J82: =IFERROR(J37*$BG37*(1+($BI37-1)*J$32)*($D$29*$BH37+(1-$D$29)*J$31),"") | K82: =IFERROR(K37*$BG37*(1+($BI37-1)*K$32)*($D$29*$BH37+(1-$D$29)*K$31),"") | L82: =IFERROR(L37*$BG37*(1+($BI37-1)*L$32)*($D$29*$BH37+(1-$D$29)*L$31),"") | M82: =IFERROR(M37*$BG37*(1+($BI37-1)*M$32)*($D$29*$BH37+(1-$D$29)*M$31),"") | N82: =IFERROR(N37*$BG37*(1+($BI37-1)*N$32)*($D$29*$BH37+(1-$D$29)*N$31),"") | O82: =IFERROR(O37*$BG37*(1+($BI37-1)*O$32)*($D$29*$BH37+(1-$D$29)*O$31),"") | ... AJ82: =IFERROR(AJ37*$BG37*(1+($BI37-1)*AJ$32)*($D$29*$BH37+(1-$D$29)*AJ$31),"")
A83: 20250304800166 | B83: VLGC | C83: 2 | D83: VLEC 2척 | K83: =IFERROR(K38*$BG38*(1+($BI38-1)*K$32)*($D$29*$BH38+(1-$D$29)*K$31),"") | L83: =IFERROR(L38*$BG38*(1+($BI38-1)*L$32)*($D$29*$BH38+(1-$D$29)*L$31),"") | M83: =IFERROR(M38*$BG38*(1+($BI38-1)*M$32)*($D$29*$BH38+(1-$D$29)*M$31),"") | N83: =IFERROR(N38*$BG38*(1+($BI38-1)*N$32)*($D$29*$BH38+(1-$D$29)*N$31),"") | O83: =IFERROR(O38*$BG38*(1+($BI38-1)*O$32)*($D$29*$BH38+(1-$D$29)*O$31),"") | P83: =IFERROR(P38*$BG38*(1+($BI38-1)*P$32)*($D$29*$BH38+(1-$D$29)*P$31),"") | Q83: =IFERROR(Q38*$BG38*(1+($BI38-1)*Q$32)*($D$29*$BH38+(1-$D$29)*Q$31),"") | R83: =IFERROR(R38*$BG38*(1+($BI38-1)*R$32)*($D$29*$BH38+(1-$D$29)*R$31),"") | ... Z83: =IFERROR(Z38*$BG38*(1+($BI38-1)*Z$32)*($D$29*$BH38+(1-$D$29)*Z$31),"")
A84: 20250422800296 | B84: VLGC | C84: 2 | D84: VLGC 2척 | G84: =IFERROR(G39*$BG39*(1+($BI39-1)*G$32)*($D$29*$BH39+(1-$D$29)*G$31),"") | H84: =IFERROR(H39*$BG39*(1+($BI39-1)*H$32)*($D$29*$BH39+(1-$D$29)*H$31),"") | I84: =IFERROR(I39*$BG39*(1+($BI39-1)*I$32)*($D$29*$BH39+(1-$D$29)*I$31),"") | J84: =IFERROR(J39*$BG39*(1+($BI39-1)*J$32)*($D$29*$BH39+(1-$D$29)*J$31),"") | K84: =IFERROR(K39*$BG39*(1+($BI39-1)*K$32)*($D$29*$BH39+(1-$D$29)*K$31),"") | L84: =IFERROR(L39*$BG39*(1+($BI39-1)*L$32)*($D$29*$BH39+(1-$D$29)*L$31),"") | M84: =IFERROR(M39*$BG39*(1+($BI39-1)*M$32)*($D$29*$BH39+(1-$D$29)*M$31),"") | N84: =IFERROR(N39*$BG39*(1+($BI39-1)*N$32)*($D$29*$BH39+(1-$D$29)*N$31),"") | ... U84: =IFERROR(U39*$BG39*(1+($BI39-1)*U$32)*($D$29*$BH39+(1-$D$29)*U$31),"")
A85: 20250521800001 | B85: VLCC | C85: 2 | D85: 157,000 DWT 원유운반선 2척 | J85: =IFERROR(J40*$BG40*(1+($BI40-1)*J$32)*($D$29*$BH40+(1-$D$29)*J$31),"") | K85: =IFERROR(K40*$BG40*(1+($BI40-1)*K$32)*($D$29*$BH40+(1-$D$29)*K$31),"") | L85: =IFERROR(L40*$BG40*(1+($BI40-1)*L$32)*($D$29*$BH40+(1-$D$29)*L$31),"") | M85: =IFERROR(M40*$BG40*(1+($BI40-1)*M$32)*($D$29*$BH40+(1-$D$29)*M$31),"") | N85: =IFERROR(N40*$BG40*(1+($BI40-1)*N$32)*($D$29*$BH40+(1-$D$29)*N$31),"") | O85: =IFERROR(O40*$BG40*(1+($BI40-1)*O$32)*($D$29*$BH40+(1-$D$29)*O$31),"") | P85: =IFERROR(P40*$BG40*(1+($BI40-1)*P$32)*($D$29*$BH40+(1-$D$29)*P$31),"") | Q85: =IFERROR(Q40*$BG40*(1+($BI40-1)*Q$32)*($D$29*$BH40+(1-$D$29)*Q$31),"") | ... U85: =IFERROR(U40*$BG40*(1+($BI40-1)*U$32)*($D$29*$BH40+(1-$D$29)*U$31),"")
A86: 20250610800109 | B86: CONT | C86: 8 | D86: 컨테이너선 8척 | L86: =IFERROR(L41*$BG41*(1+($BI41-1)*L$32)*($D$29*$BH41+(1-$D$29)*L$31),"") | M86: =IFERROR(M41*$BG41*(1+($BI41-1)*M$32)*($D$29*$BH41+(1-$D$29)*M$31),"") | N86: =IFERROR(N41*$BG41*(1+($BI41-1)*N$32)*($D$29*$BH41+(1-$D$29)*N$31),"") | O86: =IFERROR(O41*$BG41*(1+($BI41-1)*O$32)*($D$29*$BH41+(1-$D$29)*O$31),"") | P86: =IFERROR(P41*$BG41*(1+($BI41-1)*P$32)*($D$29*$BH41+(1-$D$29)*P$31),"") | Q86: =IFERROR(Q41*$BG41*(1+($BI41-1)*Q$32)*($D$29*$BH41+(1-$D$29)*Q$31),"") | R86: =IFERROR(R41*$BG41*(1+($BI41-1)*R$32)*($D$29*$BH41+(1-$D$29)*R$31),"") | S86: =IFERROR(S41*$BG41*(1+($BI41-1)*S$32)*($D$29*$BH41+(1-$D$29)*S$31),"") | ... Z86: =IFERROR(Z41*$BG41*(1+($BI41-1)*Z$32)*($D$29*$BH41+(1-$D$29)*Z$31),"")
A87: 20250613800119 | B87: VLCC | C87: 2 | D87: VLCC 2척 | L87: =IFERROR(L42*$BG42*(1+($BI42-1)*L$32)*($D$29*$BH42+(1-$D$29)*L$31),"") | M87: =IFERROR(M42*$BG42*(1+($BI42-1)*M$32)*($D$29*$BH42+(1-$D$29)*M$31),"") | N87: =IFERROR(N42*$BG42*(1+($BI42-1)*N$32)*($D$29*$BH42+(1-$D$29)*N$31),"") | O87: =IFERROR(O42*$BG42*(1+($BI42-1)*O$32)*($D$29*$BH42+(1-$D$29)*O$31),"") | P87: =IFERROR(P42*$BG42*(1+($BI42-1)*P$32)*($D$29*$BH42+(1-$D$29)*P$31),"") | Q87: =IFERROR(Q42*$BG42*(1+($BI42-1)*Q$32)*($D$29*$BH42+(1-$D$29)*Q$31),"") | R87: =IFERROR(R42*$BG42*(1+($BI42-1)*R$32)*($D$29*$BH42+(1-$D$29)*R$31),"") | S87: =IFERROR(S42*$BG42*(1+($BI42-1)*S$32)*($D$29*$BH42+(1-$D$29)*S$31),"") | ... U87: =IFERROR(U42*$BG42*(1+($BI42-1)*U$32)*($D$29*$BH42+(1-$D$29)*U$31),"")
A88: 20250708800090 | B88: CONT | C88: 2 | D88: 컨테이너선 2척 | M88: =IFERROR(M43*$BG43*(1+($BI43-1)*M$32)*($D$29*$BH43+(1-$D$29)*M$31),"") | N88: =IFERROR(N43*$BG43*(1+($BI43-1)*N$32)*($D$29*$BH43+(1-$D$29)*N$31),"") | O88: =IFERROR(O43*$BG43*(1+($BI43-1)*O$32)*($D$29*$BH43+(1-$D$29)*O$31),"") | P88: =IFERROR(P43*$BG43*(1+($BI43-1)*P$32)*($D$29*$BH43+(1-$D$29)*P$31),"") | Q88: =IFERROR(Q43*$BG43*(1+($BI43-1)*Q$32)*($D$29*$BH43+(1-$D$29)*Q$31),"") | R88: =IFERROR(R43*$BG43*(1+($BI43-1)*R$32)*($D$29*$BH43+(1-$D$29)*R$31),"") | S88: =IFERROR(S43*$BG43*(1+($BI43-1)*S$32)*($D$29*$BH43+(1-$D$29)*S$31),"") | T88: =IFERROR(T43*$BG43*(1+($BI43-1)*T$32)*($D$29*$BH43+(1-$D$29)*T$31),"") | ... W88: =IFERROR(W43*$BG43*(1+($BI43-1)*W$32)*($D$29*$BH43+(1-$D$29)*W$31),"")
A89: 20250908800058 | B89: CONT | C89: 2 | D89: 컨테이너선 2척 | M89: =IFERROR(M44*$BG44*(1+($BI44-1)*M$32)*($D$29*$BH44+(1-$D$29)*M$31),"") | N89: =IFERROR(N44*$BG44*(1+($BI44-1)*N$32)*($D$29*$BH44+(1-$D$29)*N$31),"") | O89: =IFERROR(O44*$BG44*(1+($BI44-1)*O$32)*($D$29*$BH44+(1-$D$29)*O$31),"") | P89: =IFERROR(P44*$BG44*(1+($BI44-1)*P$32)*($D$29*$BH44+(1-$D$29)*P$31),"") | Q89: =IFERROR(Q44*$BG44*(1+($BI44-1)*Q$32)*($D$29*$BH44+(1-$D$29)*Q$31),"") | R89: =IFERROR(R44*$BG44*(1+($BI44-1)*R$32)*($D$29*$BH44+(1-$D$29)*R$31),"") | S89: =IFERROR(S44*$BG44*(1+($BI44-1)*S$32)*($D$29*$BH44+(1-$D$29)*S$31),"") | T89: =IFERROR(T44*$BG44*(1+($BI44-1)*T$32)*($D$29*$BH44+(1-$D$29)*T$31),"") | ... W89: =IFERROR(W44*$BG44*(1+($BI44-1)*W$32)*($D$29*$BH44+(1-$D$29)*W$31),"")
A90: 20251020800152 | B90: VLCC | C90: 2 | D90: VLCC 2척 | N90: =IFERROR(N45*$BG45*(1+($BI45-1)*N$32)*($D$29*$BH45+(1-$D$29)*N$31),"") | O90: =IFERROR(O45*$BG45*(1+($BI45-1)*O$32)*($D$29*$BH45+(1-$D$29)*O$31),"") | P90: =IFERROR(P45*$BG45*(1+($BI45-1)*P$32)*($D$29*$BH45+(1-$D$29)*P$31),"") | Q90: =IFERROR(Q45*$BG45*(1+($BI45-1)*Q$32)*($D$29*$BH45+(1-$D$29)*Q$31),"") | R90: =IFERROR(R45*$BG45*(1+($BI45-1)*R$32)*($D$29*$BH45+(1-$D$29)*R$31),"") | S90: =IFERROR(S45*$BG45*(1+($BI45-1)*S$32)*($D$29*$BH45+(1-$D$29)*S$31),"") | T90: =IFERROR(T45*$BG45*(1+($BI45-1)*T$32)*($D$29*$BH45+(1-$D$29)*T$31),"") | U90: =IFERROR(U45*$BG45*(1+($BI45-1)*U$32)*($D$29*$BH45+(1-$D$29)*U$31),"") | V90: =IFERROR(V45*$BG45*(1+($BI45-1)*V$32)*($D$29*$BH45+(1-$D$29)*V$31),"")
A91: 20251030800164 | B91: NAVAL | D91: KSS-II 성능개량 체계개발사업 | N91: =IFERROR(N46*$BG46*(1+($BI46-1)*N$32)*($D$29*$BH46+(1-$D$29)*N$31),"") | O91: =IFERROR(O46*$BG46*(1+($BI46-1)*O$32)*($D$29*$BH46+(1-$D$29)*O$31),"") | P91: =IFERROR(P46*$BG46*(1+($BI46-1)*P$32)*($D$29*$BH46+(1-$D$29)*P$31),"") | Q91: =IFERROR(Q46*$BG46*(1+($BI46-1)*Q$32)*($D$29*$BH46+(1-$D$29)*Q$31),"") | R91: =IFERROR(R46*$BG46*(1+($BI46-1)*R$32)*($D$29*$BH46+(1-$D$29)*R$31),"") | S91: =IFERROR(S46*$BG46*(1+($BI46-1)*S$32)*($D$29*$BH46+(1-$D$29)*S$31),"") | T91: =IFERROR(T46*$BG46*(1+($BI46-1)*T$32)*($D$29*$BH46+(1-$D$29)*T$31),"") | U91: =IFERROR(U46*$BG46*(1+($BI46-1)*U$32)*($D$29*$BH46+(1-$D$29)*U$31),"") | ... AT91: =IFERROR(AT46*$BG46*(1+($BI46-1)*AT$32)*($D$29*$BH46+(1-$D$29)*AT$31),"")
A92: 20251110800036 | B92: CONT | C92: 2 | D92: 컨테이너선 2척 | N92: =IFERROR(N47*$BG47*(1+($BI47-1)*N$32)*($D$29*$BH47+(1-$D$29)*N$31),"") | O92: =IFERROR(O47*$BG47*(1+($BI47-1)*O$32)*($D$29*$BH47+(1-$D$29)*O$31),"") | P92: =IFERROR(P47*$BG47*(1+($BI47-1)*P$32)*($D$29*$BH47+(1-$D$29)*P$31),"") | Q92: =IFERROR(Q47*$BG47*(1+($BI47-1)*Q$32)*($D$29*$BH47+(1-$D$29)*Q$31),"") | R92: =IFERROR(R47*$BG47*(1+($BI47-1)*R$32)*($D$29*$BH47+(1-$D$29)*R$31),"") | S92: =IFERROR(S47*$BG47*(1+($BI47-1)*S$32)*($D$29*$BH47+(1-$D$29)*S$31),"") | T92: =IFERROR(T47*$BG47*(1+($BI47-1)*T$32)*($D$29*$BH47+(1-$D$29)*T$31),"") | U92: =IFERROR(U47*$BG47*(1+($BI47-1)*U$32)*($D$29*$BH47+(1-$D$29)*U$31),"") | ... Z92: =IFERROR(Z47*$BG47*(1+($BI47-1)*Z$32)*($D$29*$BH47+(1-$D$29)*Z$31),"")
A93: 20251114800376 | B93: VLCC | C93: 2 | D93: 157,000 DWT 원유운반선 2척 | N93: =IFERROR(N48*$BG48*(1+($BI48-1)*N$32)*($D$29*$BH48+(1-$D$29)*N$31),"") | O93: =IFERROR(O48*$BG48*(1+($BI48-1)*O$32)*($D$29*$BH48+(1-$D$29)*O$31),"") | P93: =IFERROR(P48*$BG48*(1+($BI48-1)*P$32)*($D$29*$BH48+(1-$D$29)*P$31),"") | Q93: =IFERROR(Q48*$BG48*(1+($BI48-1)*Q$32)*($D$29*$BH48+(1-$D$29)*Q$31),"") | R93: =IFERROR(R48*$BG48*(1+($BI48-1)*R$32)*($D$29*$BH48+(1-$D$29)*R$31),"") | S93: =IFERROR(S48*$BG48*(1+($BI48-1)*S$32)*($D$29*$BH48+(1-$D$29)*S$31),"") | T93: =IFERROR(T48*$BG48*(1+($BI48-1)*T$32)*($D$29*$BH48+(1-$D$29)*T$31),"") | U93: =IFERROR(U48*$BG48*(1+($BI48-1)*U$32)*($D$29*$BH48+(1-$D$29)*U$31),"") | ... Z93: =IFERROR(Z48*$BG48*(1+($BI48-1)*Z$32)*($D$29*$BH48+(1-$D$29)*Z$31),"")
A94: 20251124800125 | B94: CONT | C94: 2 | D94: 컨테이너선 2척 | N94: =IFERROR(N49*$BG49*(1+($BI49-1)*N$32)*($D$29*$BH49+(1-$D$29)*N$31),"") | O94: =IFERROR(O49*$BG49*(1+($BI49-1)*O$32)*($D$29*$BH49+(1-$D$29)*O$31),"") | P94: =IFERROR(P49*$BG49*(1+($BI49-1)*P$32)*($D$29*$BH49+(1-$D$29)*P$31),"") | Q94: =IFERROR(Q49*$BG49*(1+($BI49-1)*Q$32)*($D$29*$BH49+(1-$D$29)*Q$31),"") | R94: =IFERROR(R49*$BG49*(1+($BI49-1)*R$32)*($D$29*$BH49+(1-$D$29)*R$31),"") | S94: =IFERROR(S49*$BG49*(1+($BI49-1)*S$32)*($D$29*$BH49+(1-$D$29)*S$31),"") | T94: =IFERROR(T49*$BG49*(1+($BI49-1)*T$32)*($D$29*$BH49+(1-$D$29)*T$31),"") | U94: =IFERROR(U49*$BG49*(1+($BI49-1)*U$32)*($D$29*$BH49+(1-$D$29)*U$31),"") | ... Y94: =IFERROR(Y49*$BG49*(1+($BI49-1)*Y$32)*($D$29*$BH49+(1-$D$29)*Y$31),"")
A95: 20251211800371 | B95: VLGC | C95: 2 | D95: VLAC 2척 | N95: =IFERROR(N50*$BG50*(1+($BI50-1)*N$32)*($D$29*$BH50+(1-$D$29)*N$31),"") | O95: =IFERROR(O50*$BG50*(1+($BI50-1)*O$32)*($D$29*$BH50+(1-$D$29)*O$31),"") | P95: =IFERROR(P50*$BG50*(1+($BI50-1)*P$32)*($D$29*$BH50+(1-$D$29)*P$31),"") | Q95: =IFERROR(Q50*$BG50*(1+($BI50-1)*Q$32)*($D$29*$BH50+(1-$D$29)*Q$31),"") | R95: =IFERROR(R50*$BG50*(1+($BI50-1)*R$32)*($D$29*$BH50+(1-$D$29)*R$31),"") | S95: =IFERROR(S50*$BG50*(1+($BI50-1)*S$32)*($D$29*$BH50+(1-$D$29)*S$31),"") | T95: =IFERROR(T50*$BG50*(1+($BI50-1)*T$32)*($D$29*$BH50+(1-$D$29)*T$31),"") | U95: =IFERROR(U50*$BG50*(1+($BI50-1)*U$32)*($D$29*$BH50+(1-$D$29)*U$31),"") | ... Y95: =IFERROR(Y50*$BG50*(1+($BI50-1)*Y$32)*($D$29*$BH50+(1-$D$29)*Y$31),"")
A96: 20251224800145 | B96: PC | C96: 5 | D96: P/C선 5척 | N96: =IFERROR(N51*$BG51*(1+($BI51-1)*N$32)*($D$29*$BH51+(1-$D$29)*N$31),"") | O96: =IFERROR(O51*$BG51*(1+($BI51-1)*O$32)*($D$29*$BH51+(1-$D$29)*O$31),"") | P96: =IFERROR(P51*$BG51*(1+($BI51-1)*P$32)*($D$29*$BH51+(1-$D$29)*P$31),"") | Q96: =IFERROR(Q51*$BG51*(1+($BI51-1)*Q$32)*($D$29*$BH51+(1-$D$29)*Q$31),"") | R96: =IFERROR(R51*$BG51*(1+($BI51-1)*R$32)*($D$29*$BH51+(1-$D$29)*R$31),"") | S96: =IFERROR(S51*$BG51*(1+($BI51-1)*S$32)*($D$29*$BH51+(1-$D$29)*S$31),"") | T96: =IFERROR(T51*$BG51*(1+($BI51-1)*T$32)*($D$29*$BH51+(1-$D$29)*T$31),"") | U96: =IFERROR(U51*$BG51*(1+($BI51-1)*U$32)*($D$29*$BH51+(1-$D$29)*U$31),"") | ... Y96: =IFERROR(Y51*$BG51*(1+($BI51-1)*Y$32)*($D$29*$BH51+(1-$D$29)*Y$31),"")
A97: 20251226800842 | B97: NAVAL | C97: 2 | D97: 수상함 2척 | N97: =IFERROR(N52*$BG52*(1+($BI52-1)*N$32)*($D$29*$BH52+(1-$D$29)*N$31),"") | O97: =IFERROR(O52*$BG52*(1+($BI52-1)*O$32)*($D$29*$BH52+(1-$D$29)*O$31),"") | P97: =IFERROR(P52*$BG52*(1+($BI52-1)*P$32)*($D$29*$BH52+(1-$D$29)*P$31),"") | Q97: =IFERROR(Q52*$BG52*(1+($BI52-1)*Q$32)*($D$29*$BH52+(1-$D$29)*Q$31),"") | R97: =IFERROR(R52*$BG52*(1+($BI52-1)*R$32)*($D$29*$BH52+(1-$D$29)*R$31),"") | S97: =IFERROR(S52*$BG52*(1+($BI52-1)*S$32)*($D$29*$BH52+(1-$D$29)*S$31),"") | T97: =IFERROR(T52*$BG52*(1+($BI52-1)*T$32)*($D$29*$BH52+(1-$D$29)*T$31),"") | U97: =IFERROR(U52*$BG52*(1+($BI52-1)*U$32)*($D$29*$BH52+(1-$D$29)*U$31),"") | ... AD97: =IFERROR(AD52*$BG52*(1+($BI52-1)*AD$32)*($D$29*$BH52+(1-$D$29)*AD$31),"")
A98: 20260106800134 | B98: LNGC | C98: 4 | D98: LNGC 4척 | O98: =IFERROR(O53*$BG53*(1+($BI53-1)*O$32)*($D$29*$BH53+(1-$D$29)*O$31),"") | P98: =IFERROR(P53*$BG53*(1+($BI53-1)*P$32)*($D$29*$BH53+(1-$D$29)*P$31),"") | Q98: =IFERROR(Q53*$BG53*(1+($BI53-1)*Q$32)*($D$29*$BH53+(1-$D$29)*Q$31),"") | R98: =IFERROR(R53*$BG53*(1+($BI53-1)*R$32)*($D$29*$BH53+(1-$D$29)*R$31),"") | S98: =IFERROR(S53*$BG53*(1+($BI53-1)*S$32)*($D$29*$BH53+(1-$D$29)*S$31),"") | T98: =IFERROR(T53*$BG53*(1+($BI53-1)*T$32)*($D$29*$BH53+(1-$D$29)*T$31),"") | U98: =IFERROR(U53*$BG53*(1+($BI53-1)*U$32)*($D$29*$BH53+(1-$D$29)*U$31),"") | V98: =IFERROR(V53*$BG53*(1+($BI53-1)*V$32)*($D$29*$BH53+(1-$D$29)*V$31),"") | ... AA98: =IFERROR(AA53*$BG53*(1+($BI53-1)*AA$32)*($D$29*$BH53+(1-$D$29)*AA$31),"")
A99: 20260120800200 | B99: VLCC | C99: 2 | D99: 157,000 DWT 원유운반선 2척, 115,000 DWT P/C선 2척 | O99: =IFERROR(O54*$BG54*(1+($BI54-1)*O$32)*($D$29*$BH54+(1-$D$29)*O$31),"") | P99: =IFERROR(P54*$BG54*(1+($BI54-1)*P$32)*($D$29*$BH54+(1-$D$29)*P$31),"") | Q99: =IFERROR(Q54*$BG54*(1+($BI54-1)*Q$32)*($D$29*$BH54+(1-$D$29)*Q$31),"") | R99: =IFERROR(R54*$BG54*(1+($BI54-1)*R$32)*($D$29*$BH54+(1-$D$29)*R$31),"") | S99: =IFERROR(S54*$BG54*(1+($BI54-1)*S$32)*($D$29*$BH54+(1-$D$29)*S$31),"") | T99: =IFERROR(T54*$BG54*(1+($BI54-1)*T$32)*($D$29*$BH54+(1-$D$29)*T$31),"") | U99: =IFERROR(U54*$BG54*(1+($BI54-1)*U$32)*($D$29*$BH54+(1-$D$29)*U$31),"") | V99: =IFERROR(V54*$BG54*(1+($BI54-1)*V$32)*($D$29*$BH54+(1-$D$29)*V$31),"") | ... AB99: =IFERROR(AB54*$BG54*(1+($BI54-1)*AB$32)*($D$29*$BH54+(1-$D$29)*AB$31),"")
A100: 20260226800192 | B100: LNGC | C100: 1 | D100: LNGC 1척 | O100: =IFERROR(O55*$BG55*(1+($BI55-1)*O$32)*($D$29*$BH55+(1-$D$29)*O$31),"") | P100: =IFERROR(P55*$BG55*(1+($BI55-1)*P$32)*($D$29*$BH55+(1-$D$29)*P$31),"") | Q100: =IFERROR(Q55*$BG55*(1+($BI55-1)*Q$32)*($D$29*$BH55+(1-$D$29)*Q$31),"") | R100: =IFERROR(R55*$BG55*(1+($BI55-1)*R$32)*($D$29*$BH55+(1-$D$29)*R$31),"") | S100: =IFERROR(S55*$BG55*(1+($BI55-1)*S$32)*($D$29*$BH55+(1-$D$29)*S$31),"") | T100: =IFERROR(T55*$BG55*(1+($BI55-1)*T$32)*($D$29*$BH55+(1-$D$29)*T$31),"") | U100: =IFERROR(U55*$BG55*(1+($BI55-1)*U$32)*($D$29*$BH55+(1-$D$29)*U$31),"") | V100: =IFERROR(V55*$BG55*(1+($BI55-1)*V$32)*($D$29*$BH55+(1-$D$29)*V$31),"") | ... Y100: =IFERROR(Y55*$BG55*(1+($BI55-1)*Y$32)*($D$29*$BH55+(1-$D$29)*Y$31),"")
A101: 20260227800223 | B101: CONT | C101: 6 | D101: 컨테이너선 6척 | O101: =IFERROR(O56*$BG56*(1+($BI56-1)*O$32)*($D$29*$BH56+(1-$D$29)*O$31),"") | P101: =IFERROR(P56*$BG56*(1+($BI56-1)*P$32)*($D$29*$BH56+(1-$D$29)*P$31),"") | Q101: =IFERROR(Q56*$BG56*(1+($BI56-1)*Q$32)*($D$29*$BH56+(1-$D$29)*Q$31),"") | R101: =IFERROR(R56*$BG56*(1+($BI56-1)*R$32)*($D$29*$BH56+(1-$D$29)*R$31),"") | S101: =IFERROR(S56*$BG56*(1+($BI56-1)*S$32)*($D$29*$BH56+(1-$D$29)*S$31),"") | T101: =IFERROR(T56*$BG56*(1+($BI56-1)*T$32)*($D$29*$BH56+(1-$D$29)*T$31),"") | U101: =IFERROR(U56*$BG56*(1+($BI56-1)*U$32)*($D$29*$BH56+(1-$D$29)*U$31),"") | V101: =IFERROR(V56*$BG56*(1+($BI56-1)*V$32)*($D$29*$BH56+(1-$D$29)*V$31),"") | ... X101: =IFERROR(X56*$BG56*(1+($BI56-1)*X$32)*($D$29*$BH56+(1-$D$29)*X$31),"")
A102: 20260305800836 | B102: LNGC | C102: 4 | D102: LNGC 4척 | O102: =IFERROR(O57*$BG57*(1+($BI57-1)*O$32)*($D$29*$BH57+(1-$D$29)*O$31),"") | P102: =IFERROR(P57*$BG57*(1+($BI57-1)*P$32)*($D$29*$BH57+(1-$D$29)*P$31),"") | Q102: =IFERROR(Q57*$BG57*(1+($BI57-1)*Q$32)*($D$29*$BH57+(1-$D$29)*Q$31),"") | R102: =IFERROR(R57*$BG57*(1+($BI57-1)*R$32)*($D$29*$BH57+(1-$D$29)*R$31),"") | S102: =IFERROR(S57*$BG57*(1+($BI57-1)*S$32)*($D$29*$BH57+(1-$D$29)*S$31),"") | T102: =IFERROR(T57*$BG57*(1+($BI57-1)*T$32)*($D$29*$BH57+(1-$D$29)*T$31),"") | U102: =IFERROR(U57*$BG57*(1+($BI57-1)*U$32)*($D$29*$BH57+(1-$D$29)*U$31),"") | V102: =IFERROR(V57*$BG57*(1+($BI57-1)*V$32)*($D$29*$BH57+(1-$D$29)*V$31),"") | ... AD102: =IFERROR(AD57*$BG57*(1+($BI57-1)*AD$32)*($D$29*$BH57+(1-$D$29)*AD$31),"")
A103: 20260316800220 | B103: CONT | C103: 10 | D103: 컨테이너선 10척 | O103: =IFERROR(O58*$BG58*(1+($BI58-1)*O$32)*($D$29*$BH58+(1-$D$29)*O$31),"") | P103: =IFERROR(P58*$BG58*(1+($BI58-1)*P$32)*($D$29*$BH58+(1-$D$29)*P$31),"") | Q103: =IFERROR(Q58*$BG58*(1+($BI58-1)*Q$32)*($D$29*$BH58+(1-$D$29)*Q$31),"") | R103: =IFERROR(R58*$BG58*(1+($BI58-1)*R$32)*($D$29*$BH58+(1-$D$29)*R$31),"") | S103: =IFERROR(S58*$BG58*(1+($BI58-1)*S$32)*($D$29*$BH58+(1-$D$29)*S$31),"") | T103: =IFERROR(T58*$BG58*(1+($BI58-1)*T$32)*($D$29*$BH58+(1-$D$29)*T$31),"") | U103: =IFERROR(U58*$BG58*(1+($BI58-1)*U$32)*($D$29*$BH58+(1-$D$29)*U$31),"") | V103: =IFERROR(V58*$BG58*(1+($BI58-1)*V$32)*($D$29*$BH58+(1-$D$29)*V$31),"") | ... Z103: =IFERROR(Z58*$BG58*(1+($BI58-1)*Z$32)*($D$29*$BH58+(1-$D$29)*Z$31),"")
...

Sheet 시나리오
C1: 신규수주 시나리오(억원) — subQ 기준값 ± (시나리오 신규 − base 신규) × OPM | E1: 3Q26 | F1: 4Q26 | G1: 2026 | H1: 1Q27 | I1: 2Q27 | J1: 3Q27 | K1: 4Q27 | L1: 2027 | M1: 1Q28 | N1: 2Q28 | O1: 3Q28 | P1: 4Q28 | Q1: 2028
A2: 출처: forecast_panel.json.gz scenarios.{conservative,base,optimistic}.quarterly[].new_order_revenue (KRW_million → 억원 ÷100) — 공시 수주 체결 분기별 상계 후(net_panel) · calibrated=False · 행(subQ)에 포함된 시나리오: base. 보수/낙관/기존만 은 합산하지 않는다. 모델 산출값 — 목표주가·추천 아님
A3: 매출 = 기존(선표+잔고 소진+기타) + 시나리오 신규수주 매출; 영업이익 = 행 영업이익 + (시나리오 신규 − base 신규) × base OPM 경로. 보수/낙관·existing_only 는 행에 합산하지 않음(base 는 행과 동일). 모델 산출값 — 목표주가·추천 아님 | E3: 1 | F3: 2 | G3: 3 | H3: 4 | I3: 5 | J3: 6 | K3: 7 | L3: 8 | M3: 9 | N3: 10 | O3: 11 | P3: 12 | Q3: 13
E4: 2026.09 | F4: 2026.12 | G4: 2026.12A | H4: 2027.03 | I4: 2027.06 | J4: 2027.09 | K4: 2027.12 | L4: 2027.12A | M4: 2028.03 | N4: 2028.06 | O4: 2028.09 | P4: 2028.12 | Q4: 2028.12A
A5: base | D5: 기준(base — subQ 행에 포함) — 행에 포함
A6: scn:base:신규수주매출 | C6: 억원 | D6: 신규수주 매출(억원) — subQ 매출조선신규 참조 | E6: =subQ!AC40 | F6: =subQ!AD40 | G6: =SUM(E6:F6) | H6: =subQ!AF40 | I6: =subQ!AG40 | J6: =subQ!AH40 | K6: =subQ!AI40 | L6: =SUM(H6:K6) | M6: =subQ!AK40 | N6: =subQ!AL40 | O6: =subQ!AM40 | P6: =subQ!AN40 | Q6: =SUM(M6:P6)
A7: scn:base:매출액 | C7: 억원 | D7: 매출액 = subQ 매출액 − base 신규 + 이 시나리오 신규 | E7: =IFERROR(subQ!AC5-E6+E6,"") | F7: =IFERROR(subQ!AD5-F6+F6,"") | G7: =IFERROR(SUM(E7:F7)+subQ!AA5+subQ!AB5,"") | H7: =IFERROR(subQ!AF5-H6+H6,"") | I7: =IFERROR(subQ!AG5-I6+I6,"") | J7: =IFERROR(subQ!AH5-J6+J6,"") | K7: =IFERROR(subQ!AI5-K6+K6,"") | L7: =IFERROR(SUM(H7:K7),"") | M7: =IFERROR(subQ!AK5-M6+M6,"") | N7: =IFERROR(subQ!AL5-N6+N6,"") | O7: =IFERROR(subQ!AM5-O6+O6,"") | P7: =IFERROR(subQ!AN5-P6+P6,"") | Q7: =IFERROR(SUM(M7:P7),"")
A8: scn:base:영업이익 | C8: 억원 | D8: 영업이익 = subQ 영업이익 + (이 시나리오 신규 − base 신규) × OPM(변수 드라이버) | E8: =IFERROR(subQ!AC9+(E6-E6)*변수!AC42,"") | F8: =IFERROR(subQ!AD9+(F6-F6)*변수!AD42,"") | G8: =IFERROR(SUM(E8:F8)+subQ!AA9+subQ!AB9,"") | H8: =IFERROR(subQ!AF9+(H6-H6)*변수!AF42,"") | I8: =IFERROR(subQ!AG9+(I6-I6)*변수!AG42,"") | J8: =IFERROR(subQ!AH9+(J6-J6)*변수!AH42,"") | K8: =IFERROR(subQ!AI9+(K6-K6)*변수!AI42,"") | L8: =IFERROR(SUM(H8:K8),"") | M8: =IFERROR(subQ!AK9+(M6-M6)*변수!AK42,"") | N8: =IFERROR(subQ!AL9+(N6-N6)*변수!AL42,"") | O8: =IFERROR(subQ!AM9+(O6-O6)*변수!AM42,"") | P8: =IFERROR(subQ!AN9+(P6-P6)*변수!AN42,"") | Q8: =IFERROR(SUM(M8:P8),"")
A9: scn:base:OPM | C9: % | D9: OPM | E9: =IFERROR(E8/E7,"") | F9: =IFERROR(F8/F7,"") | G9: =IFERROR(G8/G7,"") | H9: =IFERROR(H8/H7,"") | I9: =IFERROR(I8/I7,"") | J9: =IFERROR(J8/J7,"") | K9: =IFERROR(K8/K7,"") | L9: =IFERROR(L8/L7,"") | ... Q9: =IFERROR(Q8/Q7,"")
A11: existing_only | D11: 기존 잔고만(신규수주 0)
A12: scn:existing_only:신규수주매출 | C12: 억원 | D12: 신규수주 매출(억원) — 패널 값(노란, 가정) | E12: 0 | F12: 0 | G12: =SUM(E12:F12) | H12: 0 | I12: 0 | J12: 0 | K12: 0 | L12: =SUM(H12:K12) | M12: 0 | N12: 0 | O12: 0 | P12: 0 | Q12: =SUM(M12:P12)
A13: scn:existing_only:매출액 | C13: 억원 | D13: 매출액 = subQ 매출액 − base 신규 + 이 시나리오 신규 | E13: =IFERROR(subQ!AC5-E6+E12,"") | F13: =IFERROR(subQ!AD5-F6+F12,"") | G13: =IFERROR(SUM(E13:F13)+subQ!AA5+subQ!AB5,"") | H13: =IFERROR(subQ!AF5-H6+H12,"") | I13: =IFERROR(subQ!AG5-I6+I12,"") | J13: =IFERROR(subQ!AH5-J6+J12,"") | K13: =IFERROR(subQ!AI5-K6+K12,"") | L13: =IFERROR(SUM(H13:K13),"") | M13: =IFERROR(subQ!AK5-M6+M12,"") | N13: =IFERROR(subQ!AL5-N6+N12,"") | O13: =IFERROR(subQ!AM5-O6+O12,"") | P13: =IFERROR(subQ!AN5-P6+P12,"") | Q13: =IFERROR(SUM(M13:P13),"")
A14: scn:existing_only:영업이익 | C14: 억원 | D14: 영업이익 = subQ 영업이익 + (이 시나리오 신규 − base 신규) × OPM(변수 드라이버) | E14: =IFERROR(subQ!AC9+(E12-E6)*변수!AC42,"") | F14: =IFERROR(subQ!AD9+(F12-F6)*변수!AD42,"") | G14: =IFERROR(SUM(E14:F14)+subQ!AA9+subQ!AB9,"") | H14: =IFERROR(subQ!AF9+(H12-H6)*변수!AF42,"") | I14: =IFERROR(subQ!AG9+(I12-I6)*변수!AG42,"") | J14: =IFERROR(subQ!AH9+(J12-J6)*변수!AH42,"") | K14: =IFERROR(subQ!AI9+(K12-K6)*변수!AI42,"") | L14: =IFERROR(SUM(H14:K14),"") | M14: =IFERROR(subQ!AK9+(M12-M6)*변수!AK42,"") | N14: =IFERROR(subQ!AL9+(N12-N6)*변수!AL42,"") | O14: =IFERROR(subQ!AM9+(O12-O6)*변수!AM42,"") | P14: =IFERROR(subQ!AN9+(P12-P6)*변수!AN42,"") | Q14: =IFERROR(SUM(M14:P14),"")
A15: scn:existing_only:OPM | C15: % | D15: OPM | E15: =IFERROR(E14/E13,"") | F15: =IFERROR(F14/F13,"") | G15: =IFERROR(G14/G13,"") | H15: =IFERROR(H14/H13,"") | I15: =IFERROR(I14/I13,"") | J15: =IFERROR(J14/J13,"") | K15: =IFERROR(K14/K13,"") | L15: =IFERROR(L14/L13,"") | ... Q15: =IFERROR(Q14/Q13,"")
A17: conservative | D17: 보수
A18: scn:conservative:신규수주매출 | C18: 억원 | D18: 신규수주 매출(억원) — 패널 값(노란, 가정) | E18: 0 | F18: 436.04 | G18: =SUM(E18:F18) | H18: 1912.08 | I18: 4473.45 | J18: 7855.15 | K18: 11792.16 | L18: =SUM(H18:K18) | M18: 16019.47 | N18: 20272.08 | O18: 24284.98 | P18: 27793.15 | Q18: =SUM(M18:P18)
A19: scn:conservative:매출액 | C19: 억원 | D19: 매출액 = subQ 매출액 − base 신규 + 이 시나리오 신규 | E19: =IFERROR(subQ!AC5-E6+E18,"") | F19: =IFERROR(subQ!AD5-F6+F18,"") | G19: =IFERROR(SUM(E19:F19)+subQ!AA5+subQ!AB5,"") | H19: =IFERROR(subQ!AF5-H6+H18,"") | I19: =IFERROR(subQ!AG5-I6+I18,"") | J19: =IFERROR(subQ!AH5-J6+J18,"") | K19: =IFERROR(subQ!AI5-K6+K18,"") | L19: =IFERROR(SUM(H19:K19),"") | M19: =IFERROR(subQ!AK5-M6+M18,"") | N19: =IFERROR(subQ!AL5-N6+N18,"") | O19: =IFERROR(subQ!AM5-O6+O18,"") | P19: =IFERROR(subQ!AN5-P6+P18,"") | Q19: =IFERROR(SUM(M19:P19),"")
A20: scn:conservative:영업이익 | C20: 억원 | D20: 영업이익 = subQ 영업이익 + (이 시나리오 신규 − base 신규) × OPM(변수 드라이버) | E20: =IFERROR(subQ!AC9+(E18-E6)*변수!AC42,"") | F20: =IFERROR(subQ!AD9+(F18-F6)*변수!AD42,"") | G20: =IFERROR(SUM(E20:F20)+subQ!AA9+subQ!AB9,"") | H20: =IFERROR(subQ!AF9+(H18-H6)*변수!AF42,"") | I20: =IFERROR(subQ!AG9+(I18-I6)*변수!AG42,"") | J20: =IFERROR(subQ!AH9+(J18-J6)*변수!AH42,"") | K20: =IFERROR(subQ!AI9+(K18-K6)*변수!AI42,"") | L20: =IFERROR(SUM(H20:K20),"") | M20: =IFERROR(subQ!AK9+(M18-M6)*변수!AK42,"") | N20: =IFERROR(subQ!AL9+(N18-N6)*변수!AL42,"") | O20: =IFERROR(subQ!AM9+(O18-O6)*변수!AM42,"") | P20: =IFERROR(subQ!AN9+(P18-P6)*변수!AN42,"") | Q20: =IFERROR(SUM(M20:P20),"")
A21: scn:conservative:OPM | C21: % | D21: OPM | E21: =IFERROR(E20/E19,"") | F21: =IFERROR(F20/F19,"") | G21: =IFERROR(G20/G19,"") | H21: =IFERROR(H20/H19,"") | I21: =IFERROR(I20/I19,"") | J21: =IFERROR(J20/J19,"") | K21: =IFERROR(K20/K19,"") | L21: =IFERROR(L20/L19,"") | ... Q21: =IFERROR(Q20/Q19,"")
A23: optimistic | D23: 낙관
A24: scn:optimistic:신규수주매출 | C24: 억원 | D24: 신규수주 매출(억원) — 패널 값(노란, 가정) | E24: 0 | F24: 1250.25 | G24: =SUM(E24:F24) | H24: 4965.7 | I24: 10888.12 | J24: 18450.7 | K24: 27086.66 | L24: =SUM(H24:K24) | M24: 36229.2 | N24: 45311.53 | O24: 53766.84 | P24: 61028.36 | Q24: =SUM(M24:P24)
A25: scn:optimistic:매출액 | C25: 억원 | D25: 매출액 = subQ 매출액 − base 신규 + 이 시나리오 신규 | E25: =IFERROR(subQ!AC5-E6+E24,"") | F25: =IFERROR(subQ!AD5-F6+F24,"") | G25: =IFERROR(SUM(E25:F25)+subQ!AA5+subQ!AB5,"") | H25: =IFERROR(subQ!AF5-H6+H24,"") | I25: =IFERROR(subQ!AG5-I6+I24,"") | J25: =IFERROR(subQ!AH5-J6+J24,"") | K25: =IFERROR(subQ!AI5-K6+K24,"") | L25: =IFERROR(SUM(H25:K25),"") | M25: =IFERROR(subQ!AK5-M6+M24,"") | N25: =IFERROR(subQ!AL5-N6+N24,"") | O25: =IFERROR(subQ!AM5-O6+O24,"") | P25: =IFERROR(subQ!AN5-P6+P24,"") | Q25: =IFERROR(SUM(M25:P25),"")
A26: scn:optimistic:영업이익 | C26: 억원 | D26: 영업이익 = subQ 영업이익 + (이 시나리오 신규 − base 신규) × OPM(변수 드라이버) | E26: =IFERROR(subQ!AC9+(E24-E6)*변수!AC42,"") | F26: =IFERROR(subQ!AD9+(F24-F6)*변수!AD42,"") | G26: =IFERROR(SUM(E26:F26)+subQ!AA9+subQ!AB9,"") | H26: =IFERROR(subQ!AF9+(H24-H6)*변수!AF42,"") | I26: =IFERROR(subQ!AG9+(I24-I6)*변수!AG42,"") | J26: =IFERROR(subQ!AH9+(J24-J6)*변수!AH42,"") | K26: =IFERROR(subQ!AI9+(K24-K6)*변수!AI42,"") | L26: =IFERROR(SUM(H26:K26),"") | M26: =IFERROR(subQ!AK9+(M24-M6)*변수!AK42,"") | N26: =IFERROR(subQ!AL9+(N24-N6)*변수!AL42,"") | O26: =IFERROR(subQ!AM9+(O24-O6)*변수!AM42,"") | P26: =IFERROR(subQ!AN9+(P24-P6)*변수!AN42,"") | Q26: =IFERROR(SUM(M26:P26),"")
A27: scn:optimistic:OPM | C27: % | D27: OPM | E27: =IFERROR(E26/E25,"") | F27: =IFERROR(F26/F25,"") | G27: =IFERROR(G26/G25,"") | H27: =IFERROR(H26/H25,"") | I27: =IFERROR(I26/I25,"") | J27: =IFERROR(J26/J25,"") | K27: =IFERROR(K26/K25,"") | L27: =IFERROR(L26/L25,"") | ... Q27: =IFERROR(Q26/Q25,"")

Sheet 분기
C1: 이름: 분기H — subQ 를 이름으로 VLOOKUP(억원) | E1: 4Q21 | F1: 1Q22 | G1: 2Q22 | H1: 3Q22 | I1: 4Q22 | J1: 1Q23 | K1: 2Q23 | L1: 3Q23 | M1: 4Q23 | N1: 1Q24 | O1: 2Q24 | P1: 3Q24 | Q1: 4Q24 | R1: 1Q25 | S1: 2Q25 | T1: 3Q25 | U1: 4Q25 | V1: 1Q26 | W1: 2Q26 | X1: 3Q26 | Y1: 4Q26 | Z1: 1Q27 | AA1: 2Q27 | AB1: 3Q27 | AC1: 4Q27 | AD1: 1Q28 | AE1: 2Q28 | AF1: 3Q28 | AG1: 4Q28
C2: 종가: | D2: =변수!D47
C3: 기준일: | D3: 20261014 | E3: 1 | F3: 2 | G3: 3 | H3: 4 | I3: 5 | J3: 6 | K3: 7 | L3: 8 | M3: 9 | N3: 10 | O3: 11 | P3: 12 | Q3: 13 | R3: 14 | S3: 15 | T3: 16 | U3: 17 | V3: 18 | W3: 19 | X3: 20 | Y3: 21 | Z3: 22 | AA3: 23 | AB3: 24 | AC3: 25 | AD3: 26 | AE3: 27 | AF3: 28 | AG3: 29
E4: 2021.12 | F4: 2022.03 | G4: 2022.06 | H4: 2022.09 | I4: 2022.12 | J4: 2023.03 | K4: 2023.06 | L4: 2023.09 | M4: 2023.12 | N4: 2024.03 | O4: 2024.06 | P4: 2024.09 | Q4: 2024.12 | R4: 2025.03 | S4: 2025.06 | T4: 2025.09 | U4: 2025.12 | V4: 2026.03 | W4: 2026.06 | X4: 2026.09 | Y4: 2026.12 | Z4: 2027.03 | AA4: 2027.06 | AB4: 2027.09 | AC4: 2027.12 | AD4: 2028.03 | AE4: 2028.06 | AF4: 2028.09 | AG4: 2028.12
A5: 매출액 | D5: 매출액 | E5: =IFERROR(VLOOKUP($A5,subQ,MATCH(E$1,SUBQH,0),0),"") | F5: =IFERROR(VLOOKUP($A5,subQ,MATCH(F$1,SUBQH,0),0),"") | G5: =IFERROR(VLOOKUP($A5,subQ,MATCH(G$1,SUBQH,0),0),"") | H5: =IFERROR(VLOOKUP($A5,subQ,MATCH(H$1,SUBQH,0),0),"") | I5: =IFERROR(VLOOKUP($A5,subQ,MATCH(I$1,SUBQH,0),0),"") | J5: =IFERROR(VLOOKUP($A5,subQ,MATCH(J$1,SUBQH,0),0),"") | K5: =IFERROR(VLOOKUP($A5,subQ,MATCH(K$1,SUBQH,0),0),"") | L5: =IFERROR(VLOOKUP($A5,subQ,MATCH(L$1,SUBQH,0),0),"") | ... AG5: =IFERROR(VLOOKUP($A5,subQ,MATCH(AG$1,SUBQH,0),0),"")
A6: 매출원가 | D6: 매출원가 | E6: =IFERROR(VLOOKUP($A6,subQ,MATCH(E$1,SUBQH,0),0),"") | F6: =IFERROR(VLOOKUP($A6,subQ,MATCH(F$1,SUBQH,0),0),"") | G6: =IFERROR(VLOOKUP($A6,subQ,MATCH(G$1,SUBQH,0),0),"") | H6: =IFERROR(VLOOKUP($A6,subQ,MATCH(H$1,SUBQH,0),0),"") | I6: =IFERROR(VLOOKUP($A6,subQ,MATCH(I$1,SUBQH,0),0),"") | J6: =IFERROR(VLOOKUP($A6,subQ,MATCH(J$1,SUBQH,0),0),"") | K6: =IFERROR(VLOOKUP($A6,subQ,MATCH(K$1,SUBQH,0),0),"") | L6: =IFERROR(VLOOKUP($A6,subQ,MATCH(L$1,SUBQH,0),0),"") | ... AG6: =IFERROR(VLOOKUP($A6,subQ,MATCH(AG$1,SUBQH,0),0),"")
A7: 매출총이익 | D7: 매출총이익 | E7: =IFERROR(VLOOKUP($A7,subQ,MATCH(E$1,SUBQH,0),0),"") | F7: =IFERROR(VLOOKUP($A7,subQ,MATCH(F$1,SUBQH,0),0),"") | G7: =IFERROR(VLOOKUP($A7,subQ,MATCH(G$1,SUBQH,0),0),"") | H7: =IFERROR(VLOOKUP($A7,subQ,MATCH(H$1,SUBQH,0),0),"") | I7: =IFERROR(VLOOKUP($A7,subQ,MATCH(I$1,SUBQH,0),0),"") | J7: =IFERROR(VLOOKUP($A7,subQ,MATCH(J$1,SUBQH,0),0),"") | K7: =IFERROR(VLOOKUP($A7,subQ,MATCH(K$1,SUBQH,0),0),"") | L7: =IFERROR(VLOOKUP($A7,subQ,MATCH(L$1,SUBQH,0),0),"") | ... AG7: =IFERROR(VLOOKUP($A7,subQ,MATCH(AG$1,SUBQH,0),0),"")
A8: 판관비 | D8: 판매비와관리비 | E8: =IFERROR(VLOOKUP($A8,subQ,MATCH(E$1,SUBQH,0),0),"") | F8: =IFERROR(VLOOKUP($A8,subQ,MATCH(F$1,SUBQH,0),0),"") | G8: =IFERROR(VLOOKUP($A8,subQ,MATCH(G$1,SUBQH,0),0),"") | H8: =IFERROR(VLOOKUP($A8,subQ,MATCH(H$1,SUBQH,0),0),"") | I8: =IFERROR(VLOOKUP($A8,subQ,MATCH(I$1,SUBQH,0),0),"") | J8: =IFERROR(VLOOKUP($A8,subQ,MATCH(J$1,SUBQH,0),0),"") | K8: =IFERROR(VLOOKUP($A8,subQ,MATCH(K$1,SUBQH,0),0),"") | L8: =IFERROR(VLOOKUP($A8,subQ,MATCH(L$1,SUBQH,0),0),"") | ... AG8: =IFERROR(VLOOKUP($A8,subQ,MATCH(AG$1,SUBQH,0),0),"")
A9: 영업이익 | D9: 영업이익 | E9: =IFERROR(VLOOKUP($A9,subQ,MATCH(E$1,SUBQH,0),0),"") | F9: =IFERROR(VLOOKUP($A9,subQ,MATCH(F$1,SUBQH,0),0),"") | G9: =IFERROR(VLOOKUP($A9,subQ,MATCH(G$1,SUBQH,0),0),"") | H9: =IFERROR(VLOOKUP($A9,subQ,MATCH(H$1,SUBQH,0),0),"") | I9: =IFERROR(VLOOKUP($A9,subQ,MATCH(I$1,SUBQH,0),0),"") | J9: =IFERROR(VLOOKUP($A9,subQ,MATCH(J$1,SUBQH,0),0),"") | K9: =IFERROR(VLOOKUP($A9,subQ,MATCH(K$1,SUBQH,0),0),"") | L9: =IFERROR(VLOOKUP($A9,subQ,MATCH(L$1,SUBQH,0),0),"") | ... AG9: =IFERROR(VLOOKUP($A9,subQ,MATCH(AG$1,SUBQH,0),0),"")
A10: OPM | D10: 영업이익률 | E10: =IFERROR(VLOOKUP($A10,subQ,MATCH(E$1,SUBQH,0),0),"") | F10: =IFERROR(VLOOKUP($A10,subQ,MATCH(F$1,SUBQH,0),0),"") | G10: =IFERROR(VLOOKUP($A10,subQ,MATCH(G$1,SUBQH,0),0),"") | H10: =IFERROR(VLOOKUP($A10,subQ,MATCH(H$1,SUBQH,0),0),"") | I10: =IFERROR(VLOOKUP($A10,subQ,MATCH(I$1,SUBQH,0),0),"") | J10: =IFERROR(VLOOKUP($A10,subQ,MATCH(J$1,SUBQH,0),0),"") | K10: =IFERROR(VLOOKUP($A10,subQ,MATCH(K$1,SUBQH,0),0),"") | L10: =IFERROR(VLOOKUP($A10,subQ,MATCH(L$1,SUBQH,0),0),"") | ... AG10: =IFERROR(VLOOKUP($A10,subQ,MATCH(AG$1,SUBQH,0),0),"")
A11: 금융손익 | D11: 금융손익(이자·환 포함) | E11: =IFERROR(VLOOKUP($A11,subQ,MATCH(E$1,SUBQH,0),0),"") | F11: =IFERROR(VLOOKUP($A11,subQ,MATCH(F$1,SUBQH,0),0),"") | G11: =IFERROR(VLOOKUP($A11,subQ,MATCH(G$1,SUBQH,0),0),"") | H11: =IFERROR(VLOOKUP($A11,subQ,MATCH(H$1,SUBQH,0),0),"") | I11: =IFERROR(VLOOKUP($A11,subQ,MATCH(I$1,SUBQH,0),0),"") | J11: =IFERROR(VLOOKUP($A11,subQ,MATCH(J$1,SUBQH,0),0),"") | K11: =IFERROR(VLOOKUP($A11,subQ,MATCH(K$1,SUBQH,0),0),"") | L11: =IFERROR(VLOOKUP($A11,subQ,MATCH(L$1,SUBQH,0),0),"") | ... AG11: =IFERROR(VLOOKUP($A11,subQ,MATCH(AG$1,SUBQH,0),0),"")
A12: 이자손익 | D12: 이자손익(이자수익 − 이자비용) | E12: =IFERROR(VLOOKUP($A12,subQ,MATCH(E$1,SUBQH,0),0),"") | F12: =IFERROR(VLOOKUP($A12,subQ,MATCH(F$1,SUBQH,0),0),"") | G12: =IFERROR(VLOOKUP($A12,subQ,MATCH(G$1,SUBQH,0),0),"") | H12: =IFERROR(VLOOKUP($A12,subQ,MATCH(H$1,SUBQH,0),0),"") | I12: =IFERROR(VLOOKUP($A12,subQ,MATCH(I$1,SUBQH,0),0),"") | J12: =IFERROR(VLOOKUP($A12,subQ,MATCH(J$1,SUBQH,0),0),"") | K12: =IFERROR(VLOOKUP($A12,subQ,MATCH(K$1,SUBQH,0),0),"") | L12: =IFERROR(VLOOKUP($A12,subQ,MATCH(L$1,SUBQH,0),0),"") | ... AG12: =IFERROR(VLOOKUP($A12,subQ,MATCH(AG$1,SUBQH,0),0),"")
A13: 외환손익 | D13: 외환손익(실적만; 추정 환효과는 환관련손익) | E13: =IFERROR(VLOOKUP($A13,subQ,MATCH(E$1,SUBQH,0),0),"") | F13: =IFERROR(VLOOKUP($A13,subQ,MATCH(F$1,SUBQH,0),0),"") | G13: =IFERROR(VLOOKUP($A13,subQ,MATCH(G$1,SUBQH,0),0),"") | H13: =IFERROR(VLOOKUP($A13,subQ,MATCH(H$1,SUBQH,0),0),"") | I13: =IFERROR(VLOOKUP($A13,subQ,MATCH(I$1,SUBQH,0),0),"") | J13: =IFERROR(VLOOKUP($A13,subQ,MATCH(J$1,SUBQH,0),0),"") | K13: =IFERROR(VLOOKUP($A13,subQ,MATCH(K$1,SUBQH,0),0),"") | L13: =IFERROR(VLOOKUP($A13,subQ,MATCH(L$1,SUBQH,0),0),"") | ... AG13: =IFERROR(VLOOKUP($A13,subQ,MATCH(AG$1,SUBQH,0),0),"")
A14: 파생상품손익 | D14: 파생상품손익 | E14: =IFERROR(VLOOKUP($A14,subQ,MATCH(E$1,SUBQH,0),0),"") | F14: =IFERROR(VLOOKUP($A14,subQ,MATCH(F$1,SUBQH,0),0),"") | G14: =IFERROR(VLOOKUP($A14,subQ,MATCH(G$1,SUBQH,0),0),"") | H14: =IFERROR(VLOOKUP($A14,subQ,MATCH(H$1,SUBQH,0),0),"") | I14: =IFERROR(VLOOKUP($A14,subQ,MATCH(I$1,SUBQH,0),0),"") | J14: =IFERROR(VLOOKUP($A14,subQ,MATCH(J$1,SUBQH,0),0),"") | K14: =IFERROR(VLOOKUP($A14,subQ,MATCH(K$1,SUBQH,0),0),"") | L14: =IFERROR(VLOOKUP($A14,subQ,MATCH(L$1,SUBQH,0),0),"") | ... AG14: =IFERROR(VLOOKUP($A14,subQ,MATCH(AG$1,SUBQH,0),0),"")
A15: 기타금융손익 | D15: 기타금융손익(금융손익 잔차) | E15: =IFERROR(VLOOKUP($A15,subQ,MATCH(E$1,SUBQH,0),0),"") | F15: =IFERROR(VLOOKUP($A15,subQ,MATCH(F$1,SUBQH,0),0),"") | G15: =IFERROR(VLOOKUP($A15,subQ,MATCH(G$1,SUBQH,0),0),"") | H15: =IFERROR(VLOOKUP($A15,subQ,MATCH(H$1,SUBQH,0),0),"") | I15: =IFERROR(VLOOKUP($A15,subQ,MATCH(I$1,SUBQH,0),0),"") | J15: =IFERROR(VLOOKUP($A15,subQ,MATCH(J$1,SUBQH,0),0),"") | K15: =IFERROR(VLOOKUP($A15,subQ,MATCH(K$1,SUBQH,0),0),"") | L15: =IFERROR(VLOOKUP($A15,subQ,MATCH(L$1,SUBQH,0),0),"") | ... AG15: =IFERROR(VLOOKUP($A15,subQ,MATCH(AG$1,SUBQH,0),0),"")
A16: 기타영업외손익 | D16: 기타영업외손익 | E16: =IFERROR(VLOOKUP($A16,subQ,MATCH(E$1,SUBQH,0),0),"") | F16: =IFERROR(VLOOKUP($A16,subQ,MATCH(F$1,SUBQH,0),0),"") | G16: =IFERROR(VLOOKUP($A16,subQ,MATCH(G$1,SUBQH,0),0),"") | H16: =IFERROR(VLOOKUP($A16,subQ,MATCH(H$1,SUBQH,0),0),"") | I16: =IFERROR(VLOOKUP($A16,subQ,MATCH(I$1,SUBQH,0),0),"") | J16: =IFERROR(VLOOKUP($A16,subQ,MATCH(J$1,SUBQH,0),0),"") | K16: =IFERROR(VLOOKUP($A16,subQ,MATCH(K$1,SUBQH,0),0),"") | L16: =IFERROR(VLOOKUP($A16,subQ,MATCH(L$1,SUBQH,0),0),"") | ... AG16: =IFERROR(VLOOKUP($A16,subQ,MATCH(AG$1,SUBQH,0),0),"")
... A45: NPM | D45: NPM | E45: =IFERROR(VLOOKUP($A45,subQ,MATCH(E$1,SUBQH,0),0),"") | F45: =IFERROR(VLOOKUP($A45,subQ,MATCH(F$1,SUBQH,0),0),"") | G45: =IFERROR(VLOOKUP($A45,subQ,MATCH(G$1,SUBQH,0),0),"") | H45: =IFERROR(VLOOKUP($A45,subQ,MATCH(H$1,SUBQH,0),0),"") | I45: =IFERROR(VLOOKUP($A45,subQ,MATCH(I$1,SUBQH,0),0),"") | J45: =IFERROR(VLOOKUP($A45,subQ,MATCH(J$1,SUBQH,0),0),"") | K45: =IFERROR(VLOOKUP($A45,subQ,MATCH(K$1,SUBQH,0),0),"") | L45: =IFERROR(VLOOKUP($A45,subQ,MATCH(L$1,SUBQH,0),0),"") | ... AG45: =IFERROR(VLOOKUP($A45,subQ,MATCH(AG$1,SUBQH,0),0),"")
A46: 매출액 YoY | D46: 매출액 YoY | I46: =IFERROR(I5/E5-1,"") | J46: =IFERROR(J5/F5-1,"") | K46: =IFERROR(K5/G5-1,"") | L46: =IFERROR(L5/H5-1,"") | M46: =IFERROR(M5/I5-1,"") | N46: =IFERROR(N5/J5-1,"") | O46: =IFERROR(O5/K5-1,"") | P46: =IFERROR(P5/L5-1,"") | ... AG46: =IFERROR(AG5/AC5-1,"")
A47: 영업이익 YoY | D47: 영업이익 YoY | I47: =IFERROR(I9/E9-1,"") | J47: =IFERROR(J9/F9-1,"") | K47: =IFERROR(K9/G9-1,"") | L47: =IFERROR(L9/H9-1,"") | M47: =IFERROR(M9/I9-1,"") | N47: =IFERROR(N9/J9-1,"") | O47: =IFERROR(O9/K9-1,"") | P47: =IFERROR(P9/L9-1,"") | ... AG47: =IFERROR(AG9/AC9-1,"")
A48: 지배주주순이익 YoY | D48: 지배주주순이익 YoY | I48: =IFERROR(I22/E22-1,"") | J48: =IFERROR(J22/F22-1,"") | K48: =IFERROR(K22/G22-1,"") | L48: =IFERROR(L22/H22-1,"") | M48: =IFERROR(M22/I22-1,"") | N48: =IFERROR(N22/J22-1,"") | O48: =IFERROR(O22/K22-1,"") | P48: =IFERROR(P22/L22-1,"") | ... AG48: =IFERROR(AG22/AC22-1,"")

Sheet 연간예상
C1: 이름: 연간예상H — subQ 를 이름으로 VLOOKUP(억원) | E1: 2021 | F1: 2022 | G1: 2023 | H1: 2024 | I1: 2025 | J1: 2026 | K1: 2027 | L1: 2028
C2: 종가: | D2: =변수!D47
C3: 기준일: | D3: 20261014 | E3: 1 | F3: 2 | G3: 3 | H3: 4 | I3: 5 | J3: 6 | K3: 7 | L3: 8
E4: 2021.12A | F4: 2022.12A | G4: 2023.12A | H4: 2024.12A | I4: 2025.12A | J4: 2026.12A | K4: 2027.12A | L4: 2028.12A
A5: 매출액 | D5: 매출액 | E5: =IFERROR(VLOOKUP($A5,subQ,MATCH(E$1,SUBQH,0),0),"") | F5: =IFERROR(VLOOKUP($A5,subQ,MATCH(F$1,SUBQH,0),0),"") | G5: =IFERROR(VLOOKUP($A5,subQ,MATCH(G$1,SUBQH,0),0),"") | H5: =IFERROR(VLOOKUP($A5,subQ,MATCH(H$1,SUBQH,0),0),"") | I5: =IFERROR(VLOOKUP($A5,subQ,MATCH(I$1,SUBQH,0),0),"") | J5: =IFERROR(VLOOKUP($A5,subQ,MATCH(J$1,SUBQH,0),0),"") | K5: =IFERROR(VLOOKUP($A5,subQ,MATCH(K$1,SUBQH,0),0),"") | L5: =IFERROR(VLOOKUP($A5,subQ,MATCH(L$1,SUBQH,0),0),"")
A6: 매출원가 | D6: 매출원가 | E6: =IFERROR(VLOOKUP($A6,subQ,MATCH(E$1,SUBQH,0),0),"") | F6: =IFERROR(VLOOKUP($A6,subQ,MATCH(F$1,SUBQH,0),0),"") | G6: =IFERROR(VLOOKUP($A6,subQ,MATCH(G$1,SUBQH,0),0),"") | H6: =IFERROR(VLOOKUP($A6,subQ,MATCH(H$1,SUBQH,0),0),"") | I6: =IFERROR(VLOOKUP($A6,subQ,MATCH(I$1,SUBQH,0),0),"") | J6: =IFERROR(VLOOKUP($A6,subQ,MATCH(J$1,SUBQH,0),0),"") | K6: =IFERROR(VLOOKUP($A6,subQ,MATCH(K$1,SUBQH,0),0),"") | L6: =IFERROR(VLOOKUP($A6,subQ,MATCH(L$1,SUBQH,0),0),"")
