Workbook
Name 변수H: 변수!$C$1:$AO$1
Name 환율: 변수!$C$6:$AO$13
Name BS연결H: BS연결!$C$1:$AO$1
Name BS연결: BS연결!$C$5:$AO$102
Name BS별도H: BS별도!$C$1:$AO$1
Name BS별도: BS별도!$C$5:$AO$92
Name SUBQH: subQ!$A$1:$AO$1
Name subQ: subQ!$A$5:$AO$40

Sheet README
A1: 일승(333430) 실적 모델 — ARGUS 한국조선
A2: 기준 분기 2026Q2 · 마지막 실적 2026Q2 · 생성 2026-10-13
A3: 모든 수치는 모델 산출값(DART 공개 재무제표 + 우리 추정)이다 — 목표주가·투자 추천 아님. 참고용 · 투자조언 아님.
A5: 시트
A6: 변수 가정 시계열. 환율 8행(ECB via frankfurter — L2 fx.json; 추정 분기 = 노란 가정), 추정 드라이버(노란 셀 = 모델값에서 역산한 가정, 바꾸면 재계산; 연녹 셀 = 3절 스칼라 참조 수식), 3절 스칼라 가정(세율·판관비율·지배주주비중·이자율·종가·PER 밴드·COE·외화 순노출·헤지비율)
A7: BS연결/BS별도 FnGuide 계정명 × 기간 값 덤프(백만원). 행1 분기라벨, 행4 YYYY.MM / YYYY.12A. 이름정의 BS연결H·BS연결(계정명 C열부터)
A8: subQ 분기 서브모델(억원 = 백만원/100). 확정 행: =IFERROR(VLOOKUP($D행,BS연결,MATCH(E$1,BS연결H,0),0)/100,"") 추정 행: 변수 시트 가정 셀 참조 수식. 외환손익·파생상품손익은 BS 계정 합·차, 기타금융손익은 잔차, OPM·EPS·BPS·PER·PBR 은 파생 수식
A9: SLS 선표(조선사만, sls json 있을 때): 요약 행(sls 저장값) + 계약별 스케줄(백만$) × (헤지비율 × 헤지환율 + (1−헤지비율) × 건조시점 환율[변수 원/달러(평균)]) → 원화 수식 블록 → 합계 행이 subQ 매출조선에 연결
A10: 시나리오 신규수주 보수/기준/낙관(forecast_panel 패널, 모델에 scenarios 가 있을 때만): 매출액·영업이익 = subQ 기준값 ± (시나리오 신규 − base 신규) × OPM. base 만 subQ 행에 포함, 나머지는 합산 안 함
A11: 분기/연간예상 subQ 를 이름(A열 key)으로 VLOOKUP 한 보고서 표(억원)
A12: TP PER 밴드 × 12M fwd EPS, PBR = ROE/COE × BPS — 모델 산출값 구간, 목표주가·추천 아님
A13: 외화 환율 QoQ, 외화 순노출 × Δ기말환율 → 환관련손익 추정
... A34: 백테스트: {"freeze": "2025Q2", "horizon": 4, "revenue_wape_pct": 11.1, "op_wape_pct": 63.9, "n": 4, "note": "단일 회사 4분기 — 통계 아님", "driver_at_freeze": "customer_yard_revenue_weighted", "selection_oos_at_freeze": {"freeze": "2024Q2", "n": 4, "wape_link": 26.4, "wape_trend": 36.0, "adopted": true, "decision": "adopted"}, "frozen_inputs": "fin(연결/별도)·고객 조선사 모델·지주 자회사 모델은 2025Q2 까지의 분기만; 선표는 체결일 ≤ 2025Q2 말일 계약(원장 최신 금액·코호트 등급, 환산 없음); 잔고는 yards_cache 2025Q2; 시세·환율 forward·prices·forecast_panel 신규수주 미사용. 고객 가중치(suppliers.json 언급 비중)와 합병 체인링크는 현재 지식; 고객 연동 채택은 동결 모델 안에서도 자기 la−4분기 OOS 규칙(selection_oos_at_freeze)", "detail": [{"q": "2025Q3", "rev_pred": 135.46, "rev_act": 137.98, "op_pred": 13.53, "op_act": 33.43}, {"q": "2025Q4", "rev_pred": 178.85, "rev_act": 152.6, "op_pred": 17.86, "op_act": 55.32}, {"q": "2026Q1", "rev_pred": 148.81, "rev_act": 120.79, "op_pred": 14.86, "op_act": 23.04}, {"q": "2026Q2", "rev_pred": 155.17, "rev_act": 162.29, "op_pred": 15.5, "op_act": 59.33}]}

Sheet 변수
C1: 이름: 변수H | E1: 4Q21 | F1: 2021 | G1: 1Q22 | H1: 2Q22 | I1: 3Q22 | J1: 4Q22 | K1: 2022 | L1: 1Q23 | M1: 2Q23 | N1: 3Q23 | O1: 4Q23 | P1: 2023 | Q1: 1Q24 | R1: 2Q24 | S1: 3Q24 | T1: 4Q24 | U1: 2024 | V1: 1Q25 | W1: 2Q25 | X1: 3Q25 | Y1: 4Q25 | Z1: 2025 | AA1: 1Q26 | AB1: 2Q26 | AC1: 3Q26 | AD1: 4Q26 | AE1: 2026 | AF1: 1Q27 | AG1: 2Q27 | AH1: 3Q27 | AI1: 4Q27 | AJ1: 2027 | AK1: 1Q28 | AL1: 2Q28 | AM1: 3Q28 | AN1: 4Q28 | AO1: 2028
A2: 가정 시계열 — 노란 셀은 추정 가정(모델값에서 역산), 연녹 셀은 3절 스칼라 참조 수식. 바꾸면 subQ·분기·연간예상·TP·시나리오가 재계산됩니다.
E3: 1 | F3: 2 | G3: 3 | H3: 4 | I3: 5 | J3: 6 | K3: 7 | L3: 8 | M3: 9 | N3: 10 | O3: 11 | P3: 12 | Q3: 13 | R3: 14 | S3: 15 | T3: 16 | U3: 17 | V3: 18 | W3: 19 | X3: 20 | Y3: 21 | Z3: 22 | AA3: 23 | AB3: 24 | AC3: 25 | AD3: 26 | AE3: 27 | AF3: 28 | AG3: 29 | AH3: 30 | AI3: 31 | AJ3: 32 | AK3: 33 | AL3: 34 | AM3: 35 | AN3: 36 | AO3: 37
E4: 2021.12 | F4: 2021.12A | G4: 2022.03 | H4: 2022.06 | I4: 2022.09 | J4: 2022.12 | K4: 2022.12A | L4: 2023.03 | M4: 2023.06 | N4: 2023.09 | O4: 2023.12 | P4: 2023.12A | Q4: 2024.03 | R4: 2024.06 | S4: 2024.09 | T4: 2024.12 | U4: 2024.12A | V4: 2025.03 | W4: 2025.06 | X4: 2025.09 | Y4: 2025.12 | Z4: 2025.12A | AA4: 2026.03 | AB4: 2026.06 | AC4: 2026.09 | AD4: 2026.12 | AE4: 2026.12A | AF4: 2027.03 | AG4: 2027.06 | AH4: 2027.09 | AI4: 2027.12 | AJ4: 2027.12A | AK4: 2028.03 | AL4: 2028.06 | AM4: 2028.09 | AN4: 2028.12 | AO4: 2028.12A
B5: 1. FX | C5: 이름: 환율
A6: USDKRW_avg | C6: 원/달러(평균) | E6: 1183.5 | F6: 1145.51 | G6: 1205.78 | H6: 1262.09 | I6: 1341.93 | J6: 1360.12 | K6: 1292.98 | L6: 1276.95 | M6: 1315.69 | N6: 1313.62 | O6: 1322.01 | P6: 1306.85 | Q6: 1330.14 | R6: 1371.28 | S6: 1356.22 | T6: 1396.3 | U6: 1363.53 | V6: 1452.28 | W6: 1398.52 | X6: 1386.95 | Y6: 1449.19 | Z6: 1421.52 | AA6: 1466.12 | AB6: 1501.75 | AC6: 1418.75 | AD6: 1343.63 | AE6: 1456.58 | AF6: 1333.09 | AG6: 1333.09 | AH6: 1333.09 | AI6: 1333.09 | AK6: 1333.09 | AL6: 1333.09 | AM6: 1333.09 | AN6: 1333.09
A7: USDKRW_end | C7: 원/달러(기말) | E7: 1188.75 | F7: 1188.75 | G7: 1213.74 | H7: 1301.24 | I7: 1436.9 | J7: 1260.16 | K7: 1260.16 | L7: 1305.99 | M7: 1321.44 | N7: 1345.35 | O7: 1297.43 | P7: 1297.43 | Q7: 1349.25 | R7: 1377.73 | S7: 1312.17 | T7: 1474.78 | U7: 1474.78 | V7: 1474.54 | W7: 1355.13 | X7: 1403.67 | Y7: 1444.2 | Z7: 1444.2 | AA7: 1524.8 | AB7: 1550.89 | AC7: 1355.4 | AD7: 1333.09 | AE7: 1333.09 | AF7: 1333.09 | AG7: 1333.09 | AH7: 1333.09 | AI7: 1333.09 | AK7: 1333.09 | AL7: 1333.09 | AM7: 1333.09 | AN7: 1333.09
A8: JPY100KRW_avg | C8: 원/100Y(평균) | E8: 1041.02 | F8: 1042.74 | G8: 1036.79 | H8: 972.23 | I8: 970.61 | J8: 961.03 | K8: 985.1 | L8: 964.89 | M8: 957.36 | N8: 909 | O8: 893.22 | P8: 931.11 | Q8: 896.29 | R8: 880.14 | S8: 909.35 | T8: 917.25 | U8: 900.92 | V8: 952.59 | W8: 967.92 | X8: 940.32 | Y8: 940.77 | Z8: 950.17 | AA8: 934.39 | AB8: 942.16 | AC8: 890.41 | AD8: 849.51 | AE8: 918.81 | AF8: 840.54 | AG8: 840.54 | AH8: 840.54 | AI8: 840.54 | AK8: 840.54 | AL8: 840.54 | AM8: 840.54 | AN8: 840.54
A9: JPY100KRW_end | C9: 원/100Y(기말) | E9: 1032.62 | F9: 1032.62 | G9: 996.83 | H9: 954.9 | I9: 993.29 | J9: 955.54 | K9: 955.54 | L9: 980.62 | M9: 913.67 | N9: 901.47 | O9: 917.04 | P9: 917.04 | Q9: 892.42 | R9: 857.76 | S9: 919.21 | T9: 939.65 | U9: 939.65 | V9: 986.84 | W9: 938.85 | X9: 948.49 | Y9: 921.81 | Z9: 921.81 | AA9: 955.99 | AB9: 954.75 | AC9: 863.31 | AD9: 840.54 | AE9: 840.54 | AF9: 840.54 | AG9: 840.54 | AH9: 840.54 | AI9: 840.54 | AK9: 840.54 | AL9: 840.54 | AM9: 840.54 | AN9: 840.54
A10: EURKRW_avg | C10: W/Euro(평균) | E10: 1353.32 | F10: 1354.06 | G10: 1352.29 | H10: 1343.31 | I10: 1350.63 | J10: 1386.07 | K10: 1358.07 | L10: 1369.93 | M10: 1432.41 | N10: 1429.41 | O10: 1420.91 | P10: 1412.88 | Q10: 1444.21 | R10: 1476.42 | S10: 1489.3 | T10: 1490.78 | U10: 1475.4 | V10: 1528.33 | W10: 1585.13 | X10: 1620.04 | Y10: 1686.02 | Z10: 1605.45 | AA10: 1715.47 | AB10: 1746.09 | AC10: 1631.97 | AD10: 1507.34 | AE10: 1688.95 | AF10: 1490.54 | AG10: 1490.54 | AH10: 1490.54 | AI10: 1490.54 | AK10: 1490.54 | AL10: 1490.54 | AM10: 1490.54 | AN10: 1490.54
A11: EURKRW_end | C11: W/Euro(기말) | E11: 1346.38 | F11: 1346.38 | G11: 1347.37 | H11: 1351.6 | I11: 1400.62 | J11: 1344.08 | K11: 1344.08 | L11: 1420.26 | M11: 1435.88 | N11: 1425.26 | O11: 1433.66 | P11: 1433.66 | Q11: 1458.68 | R11: 1474.86 | S11: 1469.1 | T11: 1532.14 | U11: 1532.14 | V11: 1594.72 | W11: 1588.22 | X11: 1648.04 | Y11: 1696.94 | Z11: 1696.94 | AA11: 1753.21 | AB11: 1767.09 | AC11: 1539.06 | AD11: 1490.54 | AE11: 1490.54 | AF11: 1490.54 | AG11: 1490.54 | AH11: 1490.54 | AI11: 1490.54 | AK11: 1490.54 | AL11: 1490.54 | AM11: 1490.54 | AN11: 1490.54
A12: CNYKRW_avg | C12: 원/중국원(평균) | E12: 185.14 | F12: 177.65 | G12: 189.93 | H12: 190.76 | I12: 195.79 | J12: 191.09 | K12: 191.93 | L12: 186.59 | M12: 187.45 | N12: 181.28 | O12: 182.86 | P12: 184.52 | Q12: 185.04 | R12: 189.35 | S12: 189.24 | T12: 194.24 | U12: 189.49 | V12: 199.63 | W12: 193.41 | X12: 193.79 | Y12: 204.38 | Z12: 197.8 | AA12: 211.75 | AB12: 220.8 | AC12: 210.43 | AD12: 200.5 | AE12: 213.68 | AF12: 199.18 | AG12: 199.18 | AH12: 199.18 | AI12: 199.18 | AK12: 199.18 | AL12: 199.18 | AM12: 199.18 | AN12: 199.18
A13: CNYKRW_end | C13: 원/중국원(기말) | E13: 187.13 | F13: 187.13 | G13: 191.38 | H13: 194.13 | I13: 201.92 | J13: 182.67 | K13: 182.67 | L13: 189.97 | M13: 181.8 | N13: 184.26 | O13: 182.61 | P13: 182.61 | Q13: 186.66 | R13: 189.7 | S13: 187.12 | T13: 202.04 | U13: 202.04 | V13: 203.3 | W13: 189.14 | X13: 197.16 | Y13: 206.28 | Z13: 206.28 | AA13: 220.97 | AB13: 228.56 | AC13: 202.16 | AD13: 199.18 | AE13: 199.18 | AF13: 199.18 | AG13: 199.18 | AH13: 199.18 | AI13: 199.18 | AK13: 199.18 | AL13: 199.18 | AM13: 199.18 | AN13: 199.18
B14: 1b. 종가
A15: price_close_end | C15: 종가(기말) | E15: 2630 | G15: 2880 | H15: 3515 | I15: 4450 | J15: 3070 | L15: 2890 | M15: 3800 | N15: 3195 | O15: 2780 | Q15: 3075 | R15: 3050 | S15: 2935 | T15: 4280 | V15: 3905 | W15: 4280 | X15: 7700 | Y15: 5960 | AA15: 5070 | AB15: 3390 | AC15: 3790 | AD15: 3405
A16: price_high | C16: 종가(최고) | E16: 3710 | G16: 3185 | H16: 4900 | I16: 7150 | J16: 4925 | L16: 3545 | M16: 4885 | N16: 5540 | O16: 3900 | Q16: 3685 | R16: 3710 | S16: 4050 | T16: 5240 | V16: 5620 | W16: 5860 | X16: 10430 | Y16: 9400 | AA16: 6630 | AB16: 6520 | AC16: 4680 | AD16: 4190
A17: price_low | C17: 종가(최저) | E17: 2205 | G17: 2370 | H17: 2815 | I17: 2885 | J17: 3040 | L17: 2700 | M17: 2810 | N17: 3025 | O17: 2625 | Q17: 2670 | R17: 2800 | S17: 2850 | T17: 2720 | V17: 3905 | W17: 3570 | X17: 3940 | Y17: 5850 | AA17: 4600 | AB17: 3115 | AC17: 2850 | AD17: 3220
A18: price_avg | C18: 종가(평균) | E18: 2719.3 | G18: 2729.7 | H18: 3676 | I18: 4229.1 | J18: 3820.9 | L18: 3144 | M18: 3590.9 | N18: 3887 | O18: 3016.7 | Q18: 2932.4 | R18: 3106.4 | S18: 3314.2 | T18: 3595.9 | V18: 4724 | W18: 4559.7 | X18: 5691.5 | Y18: 6955.6 | AA18: 5853.1 | AB18: 4900.7 | AC18: 3675.7 | AD18: 3717.9
B20: 2. 추정 드라이버 | C20: 실적 열 = subQ 실현값(수식), 추정 열 = 가정(노란 = 모델값 역산, 연녹 = 3절 스칼라 참조)
A21: drv:매출액 | B21: yoy | C21: 매출액 YoY | J21: =IFERROR(subQ!J5/subQ!E5-1,"") | L21: =IFERROR(subQ!L5/subQ!G5-1,"") | M21: =IFERROR(subQ!M5/subQ!H5-1,"") | N21: =IFERROR(subQ!N5/subQ!I5-1,"") | O21: =IFERROR(subQ!O5/subQ!J5-1,"") | Q21: =IFERROR(subQ!Q5/subQ!L5-1,"") | R21: =IFERROR(subQ!R5/subQ!M5-1,"") | S21: =IFERROR(subQ!S5/subQ!N5-1,"") | T21: =IFERROR(subQ!T5/subQ!O5-1,"") | V21: =IFERROR(subQ!V5/subQ!Q5-1,"") | W21: =IFERROR(subQ!W5/subQ!R5-1,"") | X21: =IFERROR(subQ!X5/subQ!S5-1,"") | Y21: =IFERROR(subQ!Y5/subQ!T5-1,"") | AA21: =IFERROR(subQ!AA5/subQ!V5-1,"") | AB21: =IFERROR(subQ!AB5/subQ!W5-1,"") | AC21: 0.02799295 | AD21: 0.31628442 | AF21: 0.22884825 | AG21: 0.007592063 | AH21: 0.17879301 | AI21: 0.16518968 | AK21: 0.18951694 | AL21: 0.22119618 | AM21: 0.24575359 | AN21: 0.2456845
A22: drv:판관비 | B22: ratio | C22: 판관비율(/매출) | E22: =IFERROR(subQ!E8/subQ!E5,"") | F22: =IFERROR(subQ!F8/subQ!F5,"") | G22: =IFERROR(subQ!G8/subQ!G5,"") | H22: =IFERROR(subQ!H8/subQ!H5,"") | I22: =IFERROR(subQ!I8/subQ!I5,"") | J22: =IFERROR(subQ!J8/subQ!J5,"") | K22: =IFERROR(subQ!K8/subQ!K5,"") | L22: =IFERROR(subQ!L8/subQ!L5,"") | ... AB22: =IFERROR(subQ!AB8/subQ!AB5,"") | AC22: =$D$49 | AD22: =$D$49 | AE22: =IFERROR(subQ!AE8/subQ!AE5,"") | AF22: =$D$49 | AG22: =$D$49 | AH22: =$D$49 | AI22: =$D$49 | AJ22: =IFERROR(subQ!AJ8/subQ!AJ5,"") | AK22: =$D$49 | AL22: =$D$49 | AM22: =$D$49 | AN22: =$D$49 | AO22: =IFERROR(subQ!AO8/subQ!AO5,"")
A23: drv:영업이익 | B23: ratio | C23: 영업이익률(OPM) | E23: =IFERROR(subQ!E9/subQ!E5,"") | F23: =IFERROR(subQ!F9/subQ!F5,"") | G23: =IFERROR(subQ!G9/subQ!G5,"") | H23: =IFERROR(subQ!H9/subQ!H5,"") | I23: =IFERROR(subQ!I9/subQ!I5,"") | J23: =IFERROR(subQ!J9/subQ!J5,"") | K23: =IFERROR(subQ!K9/subQ!K5,"") | L23: =IFERROR(subQ!L9/subQ!L5,"") | ... AB23: =IFERROR(subQ!AB9/subQ!AB5,"") | AC23: 0.19564298 | AD23: 0.19565867 | AE23: =IFERROR(subQ!AE9/subQ!AE5,"") | AF23: 0.19564778 | AG23: 0.19563356 | AH23: 0.19563397 | AI23: 0.19565032 | AJ23: =IFERROR(subQ!AJ9/subQ!AJ5,"") | AK23: 0.19562755 | AL23: 0.19565326 | AM23: 0.19564069 | AN23: 0.19565068 | AO23: =IFERROR(subQ!AO9/subQ!AO5,"")
A24: drv:외환손익 | B24: abs | C24: 외환손익 (가정, 억원) | E24: =subQ!E13 | F24: =subQ!F13 | G24: =subQ!G13 | H24: =subQ!H13 | I24: =subQ!I13 | J24: =subQ!J13 | K24: =subQ!K13 | L24: =subQ!L13 | ... AB24: =subQ!AB13 | AC24: 0 | AD24: 0 | AE24: =subQ!AE13 | AF24: 0 | AG24: 0 | AH24: 0 | AI24: 0 | AJ24: =subQ!AJ13 | AK24: 0 | AL24: 0 | AM24: 0 | AN24: 0 | AO24: =subQ!AO13
A25: drv:기타영업외손익 | B25: abs | C25: 기타영업외손익 (가정, 억원) | E25: =subQ!E14 | F25: =subQ!F14 | G25: =subQ!G14 | H25: =subQ!H14 | I25: =subQ!I14 | J25: =subQ!J14 | K25: =subQ!K14 | L25: =subQ!L14 | ... AB25: =subQ!AB14 | AC25: 0 | AD25: 0 | AE25: =subQ!AE14 | AF25: 0 | AG25: 0 | AH25: 0 | AI25: 0 | AJ25: =subQ!AJ14 | AK25: 0 | AL25: 0 | AM25: 0 | AN25: 0 | AO25: =subQ!AO14
A26: drv:법인세비용 | B26: tax | C26: 법인세율(/세전) — 법인세 = MAX(세전,0) × 세율 | E26: =IFERROR(subQ!E16/subQ!E15,"") | F26: =IFERROR(subQ!F16/subQ!F15,"") | G26: =IFERROR(subQ!G16/subQ!G15,"") | H26: =IFERROR(subQ!H16/subQ!H15,"") | I26: =IFERROR(subQ!I16/subQ!I15,"") | J26: =IFERROR(subQ!J16/subQ!J15,"") | K26: =IFERROR(subQ!K16/subQ!K15,"") | L26: =IFERROR(subQ!L16/subQ!L15,"") | ... AB26: =IFERROR(subQ!AB16/subQ!AB15,"") | AC26: =$D$48 | AD26: =$D$48 | AE26: =IFERROR(subQ!AE16/subQ!AE15,"") | AF26: =$D$48 | AG26: =$D$48 | AH26: =$D$48 | AI26: =$D$48 | AJ26: =IFERROR(subQ!AJ16/subQ!AJ15,"") | AK26: =$D$48 | AL26: =$D$48 | AM26: =$D$48 | AN26: =$D$48 | AO26: =IFERROR(subQ!AO16/subQ!AO15,"")
A27: drv:지배주주순이익 | B27: ratio | C27: 지배주주 비중(/당기순이익) | E27: =IFERROR(subQ!E18/subQ!E17,"") | F27: =IFERROR(subQ!F18/subQ!F17,"") | G27: =IFERROR(subQ!G18/subQ!G17,"") | H27: =IFERROR(subQ!H18/subQ!H17,"") | I27: =IFERROR(subQ!I18/subQ!I17,"") | J27: =IFERROR(subQ!J18/subQ!J17,"") | K27: =IFERROR(subQ!K18/subQ!K17,"") | L27: =IFERROR(subQ!L18/subQ!L17,"") | ... AB27: =IFERROR(subQ!AB18/subQ!AB17,"") | AC27: =$D$50 | AD27: =$D$50 | AE27: =IFERROR(subQ!AE18/subQ!AE17,"") | AF27: =$D$50 | AG27: =$D$50 | AH27: =$D$50 | AI27: =$D$50 | AJ27: =IFERROR(subQ!AJ18/subQ!AJ17,"") | AK27: =$D$50 | AL27: =$D$50 | AM27: =$D$50 | AN27: =$D$50 | AO27: =IFERROR(subQ!AO18/subQ!AO17,"")
A28: drv:부채총계 | B28: qoq | C28: 부채총계 QoQ | G28: =IFERROR(subQ!G20/subQ!E20-1,"") | H28: =IFERROR(subQ!H20/subQ!G20-1,"") | I28: =IFERROR(subQ!I20/subQ!H20-1,"") | J28: =IFERROR(subQ!J20/subQ!I20-1,"") | L28: =IFERROR(subQ!L20/subQ!J20-1,"") | M28: =IFERROR(subQ!M20/subQ!L20-1,"") | N28: =IFERROR(subQ!N20/subQ!M20-1,"") | O28: =IFERROR(subQ!O20/subQ!N20-1,"") | Q28: =IFERROR(subQ!Q20/subQ!O20-1,"") | R28: =IFERROR(subQ!R20/subQ!Q20-1,"") | S28: =IFERROR(subQ!S20/subQ!R20-1,"") | T28: =IFERROR(subQ!T20/subQ!S20-1,"") | V28: =IFERROR(subQ!V20/subQ!T20-1,"") | W28: =IFERROR(subQ!W20/subQ!V20-1,"") | X28: =IFERROR(subQ!X20/subQ!W20-1,"") | Y28: =IFERROR(subQ!Y20/subQ!X20-1,"") | AA28: =IFERROR(subQ!AA20/subQ!Y20-1,"") | AB28: =IFERROR(subQ!AB20/subQ!AA20-1,"") | AC28: -7.317e-06 | AD28: 0 | AF28: 0 | AG28: 0 | AH28: 0 | AI28: 0 | AK28: 0 | AL28: 0 | AM28: 0 | AN28: 0
A29: drv:자본총계 | B29: roll | C29: 자본총계 기타변동(배당 등, 억원) | G29: =IFERROR(subQ!E21+subQ!G17-subQ!G21,"") | H29: =IFERROR(subQ!G21+subQ!H17-subQ!H21,"") | I29: =IFERROR(subQ!H21+subQ!I17-subQ!I21,"") | J29: =IFERROR(subQ!I21+subQ!J17-subQ!J21,"") | L29: =IFERROR(subQ!J21+subQ!L17-subQ!L21,"") | M29: =IFERROR(subQ!L21+subQ!M17-subQ!M21,"") | N29: =IFERROR(subQ!M21+subQ!N17-subQ!N21,"") | O29: =IFERROR(subQ!N21+subQ!O17-subQ!O21,"") | Q29: =IFERROR(subQ!O21+subQ!Q17-subQ!Q21,"") | R29: =IFERROR(subQ!Q21+subQ!R17-subQ!R21,"") | S29: =IFERROR(subQ!R21+subQ!S17-subQ!S21,"") | T29: =IFERROR(subQ!S21+subQ!T17-subQ!T21,"") | V29: =IFERROR(subQ!T21+subQ!V17-subQ!V21,"") | W29: =IFERROR(subQ!V21+subQ!W17-subQ!W21,"") | X29: =IFERROR(subQ!W21+subQ!X17-subQ!X21,"") | Y29: =IFERROR(subQ!X21+subQ!Y17-subQ!Y21,"") | AA29: =IFERROR(subQ!Y21+subQ!AA17-subQ!AA21,"") | AB29: =IFERROR(subQ!AA21+subQ!AB17-subQ!AB21,"") | AC29: 0.000360688 | AD29: 0.005267252 | AF29: -0.003322047 | AG29: 0.00276551 | AH29: -0.000706331 | AI29: -0.001235727 | AK29: -0.007279979 | AL29: 0.00641281 | AM29: 0.000887435 | AN29: 0.008437208
A30: drv:지배주주지분 | B30: roll | C30: 지배주주지분 기타변동(배당 등, 억원) | G30: =IFERROR(subQ!E22+subQ!G18-subQ!G22,"") | H30: =IFERROR(subQ!G22+subQ!H18-subQ!H22,"") | I30: =IFERROR(subQ!H22+subQ!I18-subQ!I22,"") | J30: =IFERROR(subQ!I22+subQ!J18-subQ!J22,"") | L30: =IFERROR(subQ!J22+subQ!L18-subQ!L22,"") | M30: =IFERROR(subQ!L22+subQ!M18-subQ!M22,"") | N30: =IFERROR(subQ!M22+subQ!N18-subQ!N22,"") | O30: =IFERROR(subQ!N22+subQ!O18-subQ!O22,"") | Q30: =IFERROR(subQ!O22+subQ!Q18-subQ!Q22,"") | R30: =IFERROR(subQ!Q22+subQ!R18-subQ!R22,"") | S30: =IFERROR(subQ!R22+subQ!S18-subQ!S22,"") | T30: =IFERROR(subQ!S22+subQ!T18-subQ!T22,"") | V30: =IFERROR(subQ!T22+subQ!V18-subQ!V22,"") | W30: =IFERROR(subQ!V22+subQ!W18-subQ!W22,"") | X30: =IFERROR(subQ!W22+subQ!X18-subQ!X22,"") | Y30: =IFERROR(subQ!X22+subQ!Y18-subQ!Y22,"") | AA30: =IFERROR(subQ!Y22+subQ!AA18-subQ!AA22,"") | AB30: =IFERROR(subQ!AA22+subQ!AB18-subQ!AB22,"") | AC30: 0.003551241 | AD30: -0.005594867 | AF30: 0.001084019 | AG30: 0.004216472 | AH30: -0.005396926 | AI30: 0.005208118 | AK30: -0.00181305 | AL30: 0.004735233 | AM30: 0.000517786 | AN30: -0.003285113
A31: drv:총차입금 | B31: qoq | C31: 총차입금 QoQ | G31: =IFERROR(subQ!G23/subQ!E23-1,"") | H31: =IFERROR(subQ!H23/subQ!G23-1,"") | I31: =IFERROR(subQ!I23/subQ!H23-1,"") | J31: =IFERROR(subQ!J23/subQ!I23-1,"") | L31: =IFERROR(subQ!L23/subQ!J23-1,"") | M31: =IFERROR(subQ!M23/subQ!L23-1,"") | N31: =IFERROR(subQ!N23/subQ!M23-1,"") | O31: =IFERROR(subQ!O23/subQ!N23-1,"") | Q31: =IFERROR(subQ!Q23/subQ!O23-1,"") | R31: =IFERROR(subQ!R23/subQ!Q23-1,"") | S31: =IFERROR(subQ!S23/subQ!R23-1,"") | T31: =IFERROR(subQ!T23/subQ!S23-1,"") | V31: =IFERROR(subQ!V23/subQ!T23-1,"") | W31: =IFERROR(subQ!W23/subQ!V23-1,"") | X31: =IFERROR(subQ!X23/subQ!W23-1,"") | Y31: =IFERROR(subQ!Y23/subQ!X23-1,"") | AA31: =IFERROR(subQ!AA23/subQ!Y23-1,"") | AB31: =IFERROR(subQ!AB23/subQ!AA23-1,"") | AC31: 0 | AD31: 0 | AF31: 0 | AG31: 0 | AH31: 0 | AI31: 0 | AK31: 0 | AL31: 0 | AM31: 0 | AN31: 0
A32: drv:순차입금 | B32: qoq | C32: 순차입금 QoQ | G32: =IFERROR(subQ!G24/subQ!E24-1,"") | H32: =IFERROR(subQ!H24/subQ!G24-1,"") | I32: =IFERROR(subQ!I24/subQ!H24-1,"") | J32: =IFERROR(subQ!J24/subQ!I24-1,"") | L32: =IFERROR(subQ!L24/subQ!J24-1,"") | M32: =IFERROR(subQ!M24/subQ!L24-1,"") | N32: =IFERROR(subQ!N24/subQ!M24-1,"") | O32: =IFERROR(subQ!O24/subQ!N24-1,"") | Q32: =IFERROR(subQ!Q24/subQ!O24-1,"") | R32: =IFERROR(subQ!R24/subQ!Q24-1,"") | S32: =IFERROR(subQ!S24/subQ!R24-1,"") | T32: =IFERROR(subQ!T24/subQ!S24-1,"") | V32: =IFERROR(subQ!V24/subQ!T24-1,"") | W32: =IFERROR(subQ!W24/subQ!V24-1,"") | X32: =IFERROR(subQ!X24/subQ!W24-1,"") | Y32: =IFERROR(subQ!Y24/subQ!X24-1,"") | AA32: =IFERROR(subQ!AA24/subQ!Y24-1,"") | AB32: =IFERROR(subQ!AB24/subQ!AA24-1,"") | AC32: 0.098859266 | AD32: 0.12766271 | AF32: 0.084188509 | AG32: 0.085729788 | AH32: 0.081015048 | AI32: 0.10473598 | AK32: 0.072162552 | AL32: 0.076195845 | AM32: 0.074024823 | AN32: 0.096011706
A33: drv:이자발생자산 | B33: qoq | C33: 이자발생자산 QoQ | G33: =IFERROR(subQ!G25/subQ!E25-1,"") | H33: =IFERROR(subQ!H25/subQ!G25-1,"") | I33: =IFERROR(subQ!I25/subQ!H25-1,"") | J33: =IFERROR(subQ!J25/subQ!I25-1,"") | L33: =IFERROR(subQ!L25/subQ!J25-1,"") | M33: =IFERROR(subQ!M25/subQ!L25-1,"") | N33: =IFERROR(subQ!N25/subQ!M25-1,"") | O33: =IFERROR(subQ!O25/subQ!N25-1,"") | Q33: =IFERROR(subQ!Q25/subQ!O25-1,"") | R33: =IFERROR(subQ!R25/subQ!Q25-1,"") | S33: =IFERROR(subQ!S25/subQ!R25-1,"") | T33: =IFERROR(subQ!T25/subQ!S25-1,"") | V33: =IFERROR(subQ!V25/subQ!T25-1,"") | W33: =IFERROR(subQ!W25/subQ!V25-1,"") | X33: =IFERROR(subQ!X25/subQ!W25-1,"") | Y33: =IFERROR(subQ!Y25/subQ!X25-1,"") | AA33: =IFERROR(subQ!AA25/subQ!Y25-1,"") | AB33: =IFERROR(subQ!AB25/subQ!AA25-1,"") | AC33: 0.038180475 | AD33: 0.052183607 | AF33: 0.036867349 | AG33: 0.039284728 | AH33: 0.03876968 | AI33: 0.052159677 | AK33: 0.037733555 | AL33: 0.041164412 | AM33: 0.041325848 | AN33: 0.055309448
A34: drv:현금및현금성자산 | B34: qoq | C34: 현금및현금성자산 QoQ | G34: =IFERROR(subQ!G26/subQ!E26-1,"") | H34: =IFERROR(subQ!H26/subQ!G26-1,"") | I34: =IFERROR(subQ!I26/subQ!H26-1,"") | J34: =IFERROR(subQ!J26/subQ!I26-1,"") | L34: =IFERROR(subQ!L26/subQ!J26-1,"") | M34: =IFERROR(subQ!M26/subQ!L26-1,"") | N34: =IFERROR(subQ!N26/subQ!M26-1,"") | O34: =IFERROR(subQ!O26/subQ!N26-1,"") | Q34: =IFERROR(subQ!Q26/subQ!O26-1,"") | R34: =IFERROR(subQ!R26/subQ!Q26-1,"") | S34: =IFERROR(subQ!S26/subQ!R26-1,"") | T34: =IFERROR(subQ!T26/subQ!S26-1,"") | V34: =IFERROR(subQ!V26/subQ!T26-1,"") | W34: =IFERROR(subQ!W26/subQ!V26-1,"") | X34: =IFERROR(subQ!X26/subQ!W26-1,"") | Y34: =IFERROR(subQ!Y26/subQ!X26-1,"") | AA34: =IFERROR(subQ!AA26/subQ!Y26-1,"") | AB34: =IFERROR(subQ!AB26/subQ!AA26-1,"")
A35: drv:CAPEX | B35: yoy | C35: CAPEX YoY | J35: =IFERROR(subQ!J27/subQ!E27-1,"") | L35: =IFERROR(subQ!L27/subQ!G27-1,"") | M35: =IFERROR(subQ!M27/subQ!H27-1,"") | N35: =IFERROR(subQ!N27/subQ!I27-1,"") | O35: =IFERROR(subQ!O27/subQ!J27-1,"") | Q35: =IFERROR(subQ!Q27/subQ!L27-1,"") | R35: =IFERROR(subQ!R27/subQ!M27-1,"") | S35: =IFERROR(subQ!S27/subQ!N27-1,"") | T35: =IFERROR(subQ!T27/subQ!O27-1,"") | V35: =IFERROR(subQ!V27/subQ!Q27-1,"") | W35: =IFERROR(subQ!W27/subQ!R27-1,"") | X35: =IFERROR(subQ!X27/subQ!S27-1,"") | Y35: =IFERROR(subQ!Y27/subQ!T27-1,"") | AA35: =IFERROR(subQ!AA27/subQ!V27-1,"") | AB35: =IFERROR(subQ!AB27/subQ!W27-1,"") | AC35: 0.28032345 | AD35: -0.38361719 | AF35: -0.1920051 | AG35: 0.9328586 | AH35: 0 | AI35: 0 | AK35: 0 | AL35: 0 | AM35: 0 | AN35: 0
A36: drv:영업활동현금흐름 | B36: yoy | C36: 영업활동현금흐름 YoY | J36: =IFERROR(subQ!J28/subQ!E28-1,"") | L36: =IFERROR(subQ!L28/subQ!G28-1,"") | M36: =IFERROR(subQ!M28/subQ!H28-1,"") | N36: =IFERROR(subQ!N28/subQ!I28-1,"") | O36: =IFERROR(subQ!O28/subQ!J28-1,"") | Q36: =IFERROR(subQ!Q28/subQ!L28-1,"") | R36: =IFERROR(subQ!R28/subQ!M28-1,"") | S36: =IFERROR(subQ!S28/subQ!N28-1,"") | T36: =IFERROR(subQ!T28/subQ!O28-1,"") | V36: =IFERROR(subQ!V28/subQ!Q28-1,"") | W36: =IFERROR(subQ!W28/subQ!R28-1,"") | X36: =IFERROR(subQ!X28/subQ!S28-1,"") | Y36: =IFERROR(subQ!Y28/subQ!T28-1,"") | AA36: =IFERROR(subQ!AA28/subQ!V28-1,"") | AB36: =IFERROR(subQ!AB28/subQ!W28-1,"")
A37: drv:주식수 | B37: qoq | C37: 주식수 QoQ | G37: =IFERROR(subQ!G29/subQ!E29-1,"") | H37: =IFERROR(subQ!H29/subQ!G29-1,"") | I37: =IFERROR(subQ!I29/subQ!H29-1,"") | J37: =IFERROR(subQ!J29/subQ!I29-1,"") | L37: =IFERROR(subQ!L29/subQ!J29-1,"") | M37: =IFERROR(subQ!M29/subQ!L29-1,"") | N37: =IFERROR(subQ!N29/subQ!M29-1,"") | O37: =IFERROR(subQ!O29/subQ!N29-1,"") | Q37: =IFERROR(subQ!Q29/subQ!O29-1,"") | R37: =IFERROR(subQ!R29/subQ!Q29-1,"") | S37: =IFERROR(subQ!S29/subQ!R29-1,"") | T37: =IFERROR(subQ!T29/subQ!S29-1,"") | V37: =IFERROR(subQ!V29/subQ!T29-1,"") | W37: =IFERROR(subQ!W29/subQ!V29-1,"") | X37: =IFERROR(subQ!X29/subQ!W29-1,"") | Y37: =IFERROR(subQ!Y29/subQ!X29-1,"") | AA37: =IFERROR(subQ!AA29/subQ!Y29-1,"") | AB37: =IFERROR(subQ!AB29/subQ!AA29-1,"") | AC37: 0 | AD37: 0 | AF37: 0 | AG37: 0 | AH37: 0 | AI37: 0 | AK37: 0 | AL37: 0 | AM37: 0 | AN37: 0
A38: drv:DPS | B38: abs | C38: DPS (가정, 원) | E38: =subQ!E32 | F38: =subQ!F32 | G38: =subQ!G32 | H38: =subQ!H32 | I38: =subQ!I32 | J38: =subQ!J32 | K38: =subQ!K32 | L38: =subQ!L32 | ... AB38: =subQ!AB32 | AD38: 0 | AE38: =subQ!AE32 | AI38: 0 | AJ38: =subQ!AJ32 | AN38: 0 | AO38: =subQ!AO32
B40: 3. 밸류에이션·스칼라 | C40: 노란 셀 = 가정. '연결' 표시는 추정 전 분기 수식이 이 셀을 참조한다는 뜻
A41: sc:종가 | C41: 종가 | D41: 3405 | E41: 원 — 네이버 정규장 종가(aik 확정종가 대조 · aik 3,710원)
A42: sc:기준일 | C42: 기준일 | D42: 20261013 | E42: 종가 기준일
A43: sc:COE | C43: COE | D43: 0.09 | E43: 자기자본비용(가정) — TP 적정 PBR = ROE/COE
A44: sc:PER_lo | C44: PER_lo | D44: 10 | E44: PER 밴드 하단(배) — sector_default(레퍼런스 TP_PE PB 예시 10/15/20배; 과거 PER 중위 35.0배가 캡 5~30 밖 — 턴어라운드 초기 TTM EPS 왜곡)
A45: sc:PER_mid | C45: PER_mid | D45: 15 | E45: PER 밴드 중단(배)
A46: sc:PER_hi | C46: PER_hi | D46: 20 | E46: PER 밴드 상단(배)
A47: sc:EPS_Y1가중 | C47: EPS_Y1가중 | D47: 0.5 | E47: 12M fwd EPS = FY(last_actual연도)E × w + FY+1E × (1−w) — 기준 분기 2Q 이면 0.5(가정)
A48: sc:세율 | C48: 세율 | D48: 0.12133684 | E48: 연결 — 법인세 = MAX(세전,0) × 세율(역산, 재현 오차 ≤ 0.05억 · 모델 assumptions 0.1213) · 최근 12분기 유효세율 4.3% 가 5~27% 밖 → 클립 대신 최근 8분기 중 세전 > 0 인 8분기(2024Q3~2026Q2)의 법인세/세전 중위 12.1%
A49: sc:판관비율 | C49: 판관비율 | D49: 0.12309715 | E49: 연결 — 판관비 = 매출액 × 판관비율(역산, 재현 오차 ≤ 0.05억 · 모델 assumptions 0.1231)
A50: sc:지배주주비중 | C50: 지배주주비중 | D50: 0.57076786 | E50: 연결 — 지배주주순이익 = 당기순이익 × 비중(역산, 재현 오차 ≤ 0.05억)
A51: sc:이자율_자산 | C51: 이자율_자산 | D51: 0.016623874 | E51: 연결 — 이자손익 = (전분기 이자발생자산 × 자산이자율 − 전분기 총차입금 × 부채이자율)/4(역산, 재현 오차 ≤ 0.05억 · 모델 assumptions 0.0166)
A52: sc:이자율_부채 | C52: 이자율_부채 | D52: 0.036265556 | E52: 연결 — 같은 수식의 부채 쪽(총차입금 행이 없으면 0)(역산, 재현 오차 ≤ 0.05억 · 모델 assumptions 0.0362)
A53: sc:배당성향 | C53: 배당성향 | D53: 0 | E53: 배당성향(참고 — 모델은 직전 DPS 유지·Q2 지급 가정)
A54: sc:외화순노출_백만$ | C54: 외화순노출_백만$ | E54: 외화 순노출 × Δ기말환율 (외화 시트 방식) — 외화 순노출 미공시(face) → 0 + 표기
A55: sc:헤지비율 | C55: 헤지비율 | E55: sls 없음
A56: sc:헤지환율_약정 | C56: 헤지환율_약정 | E56: sls 없음

Sheet BS연결
B1: (백만원) | C1: 이름: BS연결H | E1: 4Q21 | F1: 2021 | G1: 1Q22 | H1: 2Q22 | I1: 3Q22 | J1: 4Q22 | K1: 2022 | L1: 1Q23 | M1: 2Q23 | N1: 3Q23 | O1: 4Q23 | P1: 2023 | Q1: 1Q24 | R1: 2Q24 | S1: 3Q24 | T1: 4Q24 | U1: 2024 | V1: 1Q25 | W1: 2Q25 | X1: 3Q25 | Y1: 4Q25 | Z1: 2025 | AA1: 1Q26 | AB1: 2Q26 | AC1: 3Q26 | AD1: 4Q26 | AE1: 2026 | AF1: 1Q27 | AG1: 2Q27 | AH1: 3Q27 | AI1: 4Q27 | AJ1: 2027 | AK1: 1Q28 | AL1: 2Q28 | AM1: 3Q28 | AN1: 4Q28 | AO1: 2028
B2: 연결 | D2: fin json(kship_fin.py)
B3: 일승(연) | C3: UPDATE: 26-10-13 | E3: 1 | F3: 2 | G3: 3 | H3: 4 | I3: 5 | J3: 6 | K3: 7 | L3: 8 | M3: 9 | N3: 10 | O3: 11 | P3: 12 | Q3: 13 | R3: 14 | S3: 15 | T3: 16 | U3: 17 | V3: 18 | W3: 19 | X3: 20 | Y3: 21 | Z3: 22 | AA3: 23 | AB3: 24 | AC3: 25 | AD3: 26 | AE3: 27 | AF3: 28 | AG3: 29 | AH3: 30 | AI3: 31 | AJ3: 32 | AK3: 33 | AL3: 34 | AM3: 35 | AN3: 36 | AO3: 37
B4: Account Code | C4: AccountNAME | E4: 2021.12 | F4: 2021.12A | G4: 2022.03 | H4: 2022.06 | I4: 2022.09 | J4: 2022.12 | K4: 2022.12A | L4: 2023.03 | M4: 2023.06 | N4: 2023.09 | O4: 2023.12 | P4: 2023.12A | Q4: 2024.03 | R4: 2024.06 | S4: 2024.09 | T4: 2024.12 | U4: 2024.12A | V4: 2025.03 | W4: 2025.06 | X4: 2025.09 | Y4: 2025.12 | Z4: 2025.12A | AA4: 2026.03 | AB4: 2026.06 | AC4: 2026.09 | AD4: 2026.12 | AE4: 2026.12A | AF4: 2027.03 | AG4: 2027.06 | AH4: 2027.09 | AI4: 2027.12 | AJ4: 2027.12A | AK4: 2028.03 | AL4: 2028.06 | AM4: 2028.09 | AN4: 2028.12 | AO4: 2028.12A
A5: 1 | C5: 유동자산 | E5: 34794.77 | F5: 34794.77 | G5: 35852.46 | H5: 31705.66 | I5: 35462.73 | J5: 34265.95 | K5: 34265.95 | L5: 32279.94 | M5: 31587.61 | N5: 31817.98 | O5: 35182.82 | P5: 35182.82 | Q5: 36426.87 | R5: 39871.71 | S5: 43296.67 | T5: 47228.73 | U5: 47228.73 | V5: 45653.13 | W5: 45921.02 | X5: 51181.53 | Y5: 58828.65 | Z5: 58828.65 | AA5: 62470.88 | AB5: 69563.62
A6: 1 | C6: 현금및현금성자산 | E6: 9752.65 | F6: 9752.65 | G6: 10467.24 | H6: 3476.89 | I6: 5267.92 | J6: 6115.72 | K6: 6115.72 | L6: 11195.29 | M6: 13931.35 | N6: 17397.04 | O6: 17864.54 | P6: 17864.54 | Q6: 22469.11 | R6: 24522.44 | S6: 26504.83 | T6: 33157.04 | U6: 33157.04 | V6: 30587.1 | W6: 31290.04 | X6: 29487.02 | Y6: 31124.25 | Z6: 31124.25 | AA6: 29482.06 | AB6: 26581.18
A7: 1 | C7: 단기금융상품 | E7: 3965.43 | F7: 3965.43 | G7: 2000 | H7: 2000 | I7: 2005.2 | J7: 2003.54 | K7: 2003.54 | L7: 2009.17 | M7: 2001.56 | N7: 2000 | O7: 2478.32 | P7: 2478.32 | Q7: 2001.6 | R7: 2000 | S7: 2000 | T7: 1.75 | U7: 1.75 | V7: 0 | W7: 928.86 | X7: 7269.48 | Y7: 12320.39 | Z7: 12320.39 | AA7: 17983.34 | AB7: 27111.7
A8: 1 | C8: 단기금융자산 | E8: 3965.43 | F8: 3965.43 | G8: 2000 | H8: 2000 | I8: 2005.2 | J8: 2003.54 | K8: 2003.54 | L8: 2009.17 | M8: 2001.56 | N8: 2000 | O8: 2478.32 | P8: 2478.32 | Q8: 2001.6 | R8: 2000 | S8: 2000 | T8: 1.75 | U8: 1.75 | V8: 0 | W8: 928.86 | X8: 7269.48 | Y8: 12320.39 | Z8: 12320.39 | AA8: 17983.34 | AB8: 27111.7
A9: 1 | C9: 매출채권및기타채권 | E9: 10759.03 | F9: 10759.03 | G9: 12226.67 | H9: 11669.03 | I9: 11851.67 | J9: 15448.38 | K9: 15448.38 | L9: 10815.39 | M9: 9827.04 | N9: 6664.81 | O9: 10921.37 | P9: 10921.37 | Q9: 6913.16 | R9: 7947.11 | S9: 8861.68 | T9: 10332.43 | U9: 10332.43 | V9: 10016.74 | W9: 8521.25 | X9: 9241.31 | Y9: 9119.3 | Z9: 9119.3 | AA9: 7889.51 | AB9: 7735.61
A10: 1 | C10: 계약자산 | E10: 1962.36 | F10: 1962.36 | G10: 1165.39 | H10: 987.29 | I10: 1265.16 | J10: 391.95 | K10: 391.95 | L10: 403.24 | M10: 406.02 | N10: 0 | O10: 190.13 | P10: 190.13 | Q10: 193.98 | R10: 192.44 | S10: 192.44 | T10: 192.44 | U10: 192.44 | V10: 192.44 | W10: 0 | X10: 0 | Y10: 0 | Z10: 0
A11: 1 | C11: 기타유동자산 | E11: 538.13 | F11: 538.13 | G11: 456.63 | H11: 707.9 | I11: 295.86 | J11: 94.01 | K11: 94.01 | L11: 66.34 | M11: 654.6 | N11: 711.33 | O11: 48.8 | P11: 48.8 | Q11: 131.17 | R11: 117.03 | S11: 67.74 | T11: 19.44 | U11: 19.44 | V11: 19.35 | W11: 14.49 | X11: 55.11 | Y11: 84.72 | Z11: 84.72 | AA11: 12.01 | AB11: 29.96
A12: 1 | C12: 당기법인세자산(선급법인세) | E12: 20.78 | F12: 20.78 | G12: 8.09 | H12: 7.03 | I12: 8.2 | J12: 10 | K12: 10 | L12: 10.95 | M12: 1.93 | N12: 85.58 | O12: 3.94 | P12: 3.94 | Q12: 5.03 | R12: 2.18 | S12: 7.15 | T12: 68.6 | U12: 68.6 | V12: 69.52 | W12: 0 | X12: 0 | Y12: 0 | Z12: 0
A13: 1 | C13: 재고자산 | E13: 7382.14 | F13: 7382.14 | G13: 9092.08 | H13: 12470.61 | I13: 14385.83 | J13: 9807.58 | K13: 9807.58 | L13: 7373.53 | M13: 4349.43 | N13: 4508.58 | O13: 3675.73 | P13: 3675.73 | Q13: 4712.8 | R13: 5090.51 | S13: 5662.84 | T13: 3457.02 | U13: 3457.02 | V13: 4767.97 | W13: 5166.38 | X13: 5128.61 | Y13: 6179.99 | Z13: 6179.99 | AA13: 7103.95 | AB13: 7118.91
A14: 1 | C14: 비유동자산 | E14: 50173.55 | F14: 50173.55 | G14: 67621.52 | H14: 69917.64 | I14: 70751.26 | J14: 69667.96 | K14: 69667.96 | L14: 69351.74 | M14: 70410.3 | N14: 69449.14 | O14: 69432.79 | P14: 69432.79 | Q14: 69068.67 | R14: 68500.84 | S14: 67833.89 | T14: 68314.66 | U14: 68314.66 | V14: 68623.71 | W14: 68774.88 | X14: 68901.33 | Y14: 70311.16 | Z14: 70311.16 | AA14: 70671.54 | AB14: 71245.95
A15: 1 | C15: 장기매출채권및기타채권 | E15: 657.65 | F15: 657.65 | G15: 656.03 | H15: 216.24 | I15: 109.02 | J15: 110.23 | K15: 110.23 | L15: 12.93 | M15: 7.93 | N15: 7.93 | O15: 7.93 | P15: 7.93 | Q15: 19.63 | R15: 19.58 | S15: 19.58 | T15: 6.58 | U15: 6.58 | V15: 3.89 | W15: 3.89 | X15: 3.89 | Y15: 3.89 | Z15: 3.89 | AA15: 1.89 | AB15: 1.89
A16: 1 | C16: 장기금융자산 | E16: 6891.37 | F16: 6891.37 | G16: 7513.3 | H16: 8669.67 | I16: 9361.07 | J16: 8547.32 | K16: 8547.32 | L16: 8738.67 | M16: 9994.94 | N16: 9248.29 | O16: 9178.15 | P16: 9178.15 | Q16: 8986.1 | R16: 8654.07 | S16: 7993.5 | T16: 7187.82 | U16: 7187.82 | V16: 7586.32 | W16: 7922.53 | X16: 8222.13 | Y16: 7918.29 | Z16: 7918.29 | AA16: 8460.57 | AB16: 10246.87
A17: 1 | C17: 투자자산 | E17: 6891.37 | F17: 6891.37 | G17: 7513.3 | H17: 8669.67 | I17: 9361.07 | J17: 8547.32 | K17: 8547.32 | L17: 8738.67 | M17: 9994.94 | N17: 9248.29 | O17: 9178.15 | P17: 9178.15 | Q17: 8986.1 | R17: 8654.07 | S17: 7993.5 | T17: 7187.82 | U17: 7187.82 | V17: 7586.32 | W17: 7922.53 | X17: 8222.13 | Y17: 7918.29 | Z17: 7918.29 | AA17: 8460.57 | AB17: 10246.87
A18: 1 | C18: 유형자산 | E18: 39146.78 | F18: 39146.78 | G18: 55391.95 | H18: 57116.99 | I18: 57581.15 | J18: 57496.87 | K18: 57496.87 | L18: 57287.9 | M18: 57117.33 | N18: 56917.69 | O18: 56783.87 | P18: 56783.87 | Q18: 56611.42 | R18: 56422.93 | S18: 56356.34 | T18: 56171.53 | U18: 56171.53 | V18: 56096.62 | W18: 55915.07 | X18: 55747.49 | Y18: 47396.93 | Z18: 47396.93 | AA18: 47248.23 | AB18: 46088.35
A19: 1 | C19: 사용권자산 | E19: 229.2 | F19: 229.2 | G19: 824.35 | H19: 686.09 | I19: 484.3 | J19: 282.51 | K19: 282.51 | L19: 91.62 | M19: 81.9 | N19: 72.18 | O19: 62.45 | P19: 62.45 | Q19: 59.45 | R19: 48.77 | S19: 54 | T19: 45.21 | U19: 45.21 | V19: 40.5 | W19: 32.37 | X19: 26.92 | Y19: 21.87 | Z19: 21.87 | AA19: 16.82 | AB19: 12.79
A20: 1 | C20: 기타비유동자산 | E20: 229.2 | F20: 229.2 | G20: 824.35 | H20: 686.09 | I20: 484.3 | J20: 282.51 | K20: 282.51 | L20: 91.62 | M20: 81.9 | N20: 72.18 | O20: 62.45 | P20: 62.45 | Q20: 59.45 | R20: 48.77 | S20: 54 | T20: 45.21 | U20: 45.21 | V20: 40.5 | W20: 32.37 | X20: 26.92 | Y20: 21.87 | Z20: 21.87 | AA20: 16.82 | AB20: 12.79
A21: 1 | C21: 무형자산 | E21: 3248.56 | F21: 3248.56 | G21: 3235.9 | H21: 3228.65 | I21: 3215.71 | J21: 3231.03 | K21: 3231.03 | L21: 3220.62 | M21: 3208.2 | N21: 3203.05 | O21: 3189.22 | P21: 3189.22 | Q21: 3180.89 | R21: 3172.87 | S21: 3171.74 | T21: 3164 | U21: 3164 | V21: 3161.16 | W21: 3158.56 | X21: 3156.43 | Y21: 3154.3 | Z21: 3154.3 | AA21: 3152.73 | AB21: 3150.57
A22: 1 | C22: 자산총계 | E22: 84968.32 | F22: 84968.32 | G22: 103473.98 | H22: 101623.3 | I22: 106213.99 | J22: 103933.91 | K22: 103933.91 | L22: 101631.68 | M22: 101997.91 | N22: 101267.12 | O22: 104615.62 | P22: 104615.62 | Q22: 105495.54 | R22: 108372.55 | S22: 111130.57 | T22: 115543.39 | U22: 115543.39 | V22: 114276.84 | W22: 114695.9 | X22: 120082.86 | Y22: 129139.81 | Z22: 129139.81 | AA22: 133142.42 | AB22: 140809.57
A23: 1 | C23: 유동부채 | E23: 15732.29 | F23: 15732.29 | G23: 25328.09 | H23: 23094.64 | I23: 24367.67 | J23: 22604.78 | K23: 22604.78 | L23: 19490.74 | M23: 18461.64 | N23: 18976.96 | O23: 19044.13 | P23: 19044.13 | Q23: 11371.42 | R23: 16637.16 | S23: 11825.75 | T23: 10772.73 | U23: 10772.73 | V23: 8381.41 | W23: 7470.33 | X23: 7371.76 | Y23: 16067.37 | Z23: 16067.37 | AA23: 22335.93 | AB23: 23367.84
A24: 1 | C24: 매입채무및기타채무 | E24: 8309.12 | F24: 8309.12 | G24: 9243.41 | H24: 7357.34 | I24: 7299.16 | J24: 7417.95 | K24: 7417.95 | L24: 6183.7 | M24: 4606.33 | N24: 4820.29 | O24: 4226.27 | P24: 4226.27 | Q24: 4565.14 | R24: 4328.21 | S24: 3931.66 | T24: 5133.15 | U24: 5133.15 | V24: 5168.37 | W24: 4389.43 | X24: 3946.64 | Y24: 4671.49 | Z24: 4671.49 | AA24: 4766.24 | AB24: 3593.94
A25: 1 | C25: 계약부채 | E25: 159.32 | F25: 159.32 | G25: 353.25 | H25: 489.05 | I25: 259.15 | J25: 259.15 | K25: 259.15 | L25: 259.15 | M25: 259.15 | N25: 259.15 | O25: 469.71 | P25: 469.71 | Q25: 469.71 | R25: 469.71 | S25: 469.71 | T25: 0 | U25: 0 | V25: 0 | W25: 0 | Y25: 0 | Z25: 0
A26: 1 | C26: 당기법인세부채(미지급법인세) | E26: 444.92 | F26: 444.92 | G26: 249.06 | H26: 73.5 | I26: 602.61 | J26: 225.92 | K26: 225.92 | L26: 143.21 | M26: 74.44 | N26: 0 | O26: 103.72 | P26: 103.72 | Q26: 136.97 | R26: 2472.11 | S26: 2752.22 | T26: 3000.04 | U26: 3000.04 | V26: 1800.43 | W26: 285.44 | X26: 488.47 | Y26: 655.03 | Z26: 655.03 | AA26: 1142.05 | AB26: 2921.21
A27: 1 | C27: 단기차입금 | E27: 3814.99 | F27: 3814.99 | G27: 11686.21 | H27: 11600 | I27: 12300 | J27: 12300 | K27: 12300 | L27: 12508.41 | M27: 12371.06 | N27: 12933.55 | O27: 13496.04 | P27: 13496.04 | Q27: 5850.12 | R27: 8849.96 | S27: 2600 | T27: 1500 | U27: 1500 | V27: 700 | W27: 2000 | X27: 2000 | Y27: 2000 | Z27: 2000 | AA27: 0 | AB27: 0
A28: 1 | C28: 단기금융부채(face) | E28: 3814.99 | F28: 3814.99 | G28: 11686.21 | H28: 11600 | I28: 12300 | J28: 12300 | K28: 12300 | L28: 12508.41 | M28: 12371.06 | N28: 12933.55 | O28: 13496.04 | P28: 13496.04 | Q28: 5850.12 | R28: 8849.96
A29: 1 | C29: 유동리스부채 | E29: 238.18 | F29: 238.18 | G29: 804.47 | H29: 611.22 | I29: 419.74 | J29: 225.82 | K29: 225.82 | L29: 39.64 | M29: 37.91 | N29: 32.8 | O29: 26.8 | P29: 26.8 | Q29: 27.35 | R29: 22.07 | S29: 29.94 | T29: 25.61 | U29: 25.61 | V29: 25.13 | W29: 19.62 | X29: 19.97 | Y29: 19.29 | Z29: 19.29 | AA29: 17.61 | AB29: 14.83
A30: 1 | C30: 리스부채 | E30: 260.89 | F30: 260.89 | G30: 823.8 | H30: 690.76 | I30: 492.02 | J30: 290.65 | K30: 290.65 | L30: 96.84 | M30: 87.28 | N30: 77.5 | O30: 67.47 | P30: 67.47 | Q30: 63.92 | R30: 54.46 | S30: 58.06 | T30: 49.39 | U30: 49.39 | V30: 44.48 | W30: 35.89 | X30: 30.19 | Y30: 24.82 | Z30: 24.82 | AA30: 19.35 | AB30: 14.83
A31: 1 | C31: 단기금융부채 | E31: 238.18 | F31: 238.18 | G31: 804.47 | H31: 611.22 | I31: 419.74 | J31: 225.82 | K31: 225.82 | L31: 39.64 | M31: 37.91 | N31: 32.8 | O31: 26.8 | P31: 26.8 | Q31: 27.35 | R31: 22.07 | S31: 29.94 | T31: 25.61 | U31: 25.61 | V31: 25.13 | W31: 19.62 | X31: 19.97 | Y31: 19.29 | Z31: 19.29 | AA31: 17.61 | AB31: 14.83
A32: 1 | C32: 기타유동부채 | E32: 2765.75 | F32: 2765.75 | G32: 2991.68 | H32: 2963.52 | I32: 3487.01 | J32: 2175.94 | K32: 2175.94 | L32: 356.63 | M32: 1112.75 | N32: 931.17 | O32: 721.58 | P32: 721.58 | Q32: 322.14 | R32: 495.1 | S32: 625.58 | T32: 1113.92 | U32: 1113.92 | V32: 687.48 | W32: 775.84 | X32: 916.69 | Y32: 1021.56 | Z32: 1021.56 | AA32: 710.04 | AB32: 1137.86
A33: 1 | C33: 비유동부채 | E33: 10172.55 | F33: 10172.55 | G33: 18697.25 | H33: 18540.98 | I33: 18837.35 | J33: 18479.54 | K33: 18479.54 | L33: 18381.09 | M33: 18077.15 | N33: 17350.48 | O33: 14383.22 | P33: 14383.22 | Q33: 21916.25 | R33: 21289.48 | S33: 27058.78 | T33: 28056.69 | U33: 28056.69 | V33: 28161.56 | W33: 28276.44 | X33: 29945.74 | Y33: 22200.09 | Z33: 22200.09 | AA33: 16286.84 | AB33: 16266.45
A34: 1 | C34: 장기차입금 | E34: 5000 | F34: 5000 | G34: 13500 | H34: 13500 | I34: 13500 | J34: 13500 | K34: 13500 | L34: 13291.59 | M34: 12728.94 | N34: 12166.45 | O34: 11603.96 | P34: 11603.96 | Q34: 19041.47 | R34: 18478.98 | S34: 24174.88 | T34: 25500 | U34: 25500 | V34: 25500 | W34: 25500 | X34: 27000 | Y34: 19300 | Z34: 19300 | AA34: 13300 | AB34: 13300
A35: 1 | C35: 비유동리스부채 | E35: 22.71 | F35: 22.71 | G35: 19.33 | H35: 79.54 | I35: 72.28 | J35: 64.83 | K35: 64.83 | L35: 57.2 | M35: 49.37 | N35: 44.7 | O35: 40.67 | P35: 40.67 | Q35: 36.57 | R35: 32.39 | S35: 28.12 | T35: 23.78 | U35: 23.78 | V35: 19.35 | W35: 16.27 | X35: 10.22 | Y35: 5.53 | Z35: 5.53 | AA35: 1.74 | AB35: 0
A36: 1 | C36: 장기금융부채 | E36: 22.71 | F36: 22.71 | G36: 19.33 | H36: 79.54 | I36: 72.28 | J36: 64.83 | K36: 64.83 | L36: 57.2 | M36: 49.37 | N36: 44.7 | O36: 40.67 | P36: 40.67 | Q36: 36.57 | R36: 32.39 | S36: 28.12 | T36: 23.78 | U36: 23.78 | V36: 19.35 | W36: 16.27 | X36: 10.22 | Y36: 5.53 | Z36: 5.53 | AA36: 1.74 | AB36: 0
A37: 1 | C37: 확정급여부채 | E37: 630.95 | F37: 630.95 | G37: 512.56 | H37: 296.88 | I37: 488.56 | J37: 585.95 | K37: 585.95 | L37: 676.79 | M37: 598.76 | N37: 614.64 | O37: 130.51 | P37: 130.51 | Q37: 316.54 | R37: 297.87 | S37: 416.61 | T37: 299.98 | U37: 299.98 | V37: 403.05 | W37: 441.8 | X37: 616.27 | Y37: 340.05 | Z37: 340.05 | AA37: 434.04 | AB37: 475.1
A38: 1 | C38: 이연법인세부채 | E38: 4518.89 | F38: 4518.89 | G38: 4665.37 | H38: 4664.55 | I38: 4776.51 | J38: 4328.76 | K38: 4328.76 | L38: 4355.51 | M38: 4700.07 | N38: 4524.69 | O38: 2608.08 | P38: 2608.08 | Q38: 2521.67 | R38: 2480.24 | S38: 2439.18 | T38: 2174.18 | U38: 2174.18 | V38: 2175.61 | W38: 2251.21 | X38: 2246.71 | Y38: 2473.02 | Z38: 2473.02 | AA38: 2463.75 | AB38: 2413.66
A39: 1 | C39: 부채총계 | E39: 25904.84 | F39: 25904.84 | G39: 44025.35 | H39: 41635.61 | I39: 43205.02 | J39: 41084.32 | K39: 41084.32 | L39: 37871.83 | M39: 36538.79 | N39: 36327.43 | O39: 33427.35 | P39: 33427.35 | Q39: 33287.68 | R39: 37926.64 | S39: 38884.54 | T39: 38829.41 | U39: 38829.41 | V39: 36542.97 | W39: 35746.77 | X39: 37317.51 | Y39: 38267.46 | Z39: 38267.46 | AA39: 38622.78 | AB39: 39634.29
A40: 1 | C40: 지배주주지분 | E40: 30945.35 | F40: 30945.35 | G40: 31581.67 | H40: 31590.6 | I40: 34474.02 | J40: 33515.97 | K40: 33515.97 | L40: 33999.96 | M40: 35551.78 | N40: 34960.55 | O40: 38022.25 | P40: 38022.25 | Q40: 38072 | R40: 35615.84 | S40: 36906.03 | T40: 37955.35 | U40: 37955.35 | V40: 38745.71 | W40: 39613.65 | X40: 41127.73 | Y40: 45836.29 | Z40: 45836.29 | AA40: 48318.94 | AB40: 52710.25
... A51: 1 | C51: 이자발생자산 | E51: 20609.45 | F51: 20609.45 | G51: 19980.54 | H51: 14146.56 | I51: 16634.19 | J51: 16666.58 | K51: 16666.58 | L51: 21943.13 | M51: 25927.85 | N51: 28645.33 | O51: 29521.01 | P51: 29521.01 | Q51: 33456.81 | R51: 35176.51 | S51: 36498.33 | T51: 40346.61 | U51: 40346.61 | V51: 38173.42 | W51: 40141.43 | X51: 44978.63 | Y51: 51362.93 | Z51: 51362.93 | AA51: 55925.97 | AB51: 63939.75
A52: 1 | C52: 장기금융부채(face) | G52: 13500 | H52: 13500 | I52: 13500 | J52: 13500 | K52: 13500 | L52: 13291.59 | M52: 12728.94 | N52: 12166.45 | O52: 11603.96 | P52: 11603.96 | Q52: 19041.47 | R52: 18478.98 | S52: 24174.88 | T52: 25500 | U52: 25500 | V52: 25500 | W52: 25500 | X52: 27000
A53: 1 | C53: 이연법인세자산 | O53: 211.18 | P53: 211.18 | Q53: 211.18 | R53: 182.61 | S53: 238.74 | T53: 1739.52 | U53: 1739.52 | V53: 1735.22 | W53: 1742.46 | X53: 1744.48 | Y53: 3646.58 | Z53: 3646.58 | AA53: 3622.01 | AB53: 3576.19
A54: 1 | C54: 유동성장기부채 | S54: 1416.64 | Y54: 7700 | Z54: 7700 | AA54: 15700 | AB54: 15700
A55: 1 | C55: 기타비유동부채 | T55: 58.75 | U55: 58.75 | V55: 63.56 | W55: 67.15 | X55: 72.54 | Y55: 81.49 | Z55: 81.49 | AA55: 87.31 | AB55: 77.69
A56: 1 | C56: 투자부동산 | Y56: 8169.29 | Z56: 8169.29 | AA56: 8169.29 | AB56: 8169.29
A57: 1 | C57: 매각예정비유동자산및처분자산 | AB57: 986.25
A58: 1 | C58: 매출액(수익) | E58: 21748.81 | G58: 15376.48 | H58: 14025.4 | I58: 17264.06 | J58: 18371.06 | K58: 65037 | L58: 14527.81 | M58: 13672.86 | N58: 9753.72 | O58: 15017.21 | P58: 52971.6 | Q58: 9913.21 | R58: 11442.1 | S58: 12507.9 | T58: 17930.02 | U58: 51793.23 | V58: 10028.74 | W58: 11587.63 | X58: 13797.76 | Y58: 15259.62 | Z58: 50673.75 | AA58: 12078.79 | AB58: 16228.79
A59: 1 | C59: 매출원가 | E59: 17917.43 | G59: 13852.56 | H59: 11854.29 | I59: 12570.9 | J59: 15405.7 | K59: 53683.45 | L59: 12022.23 | M59: 11166.29 | N59: 7708.14 | O59: 9351.67 | P59: 40248.33 | Q59: 8070.84 | R59: 8683.49 | S59: 8177.6 | T59: 12755.75 | U59: 37687.68 | V59: 7653.67 | W59: 8714.77 | X59: 8758.02 | Y59: 7847.02 | Z59: 32973.48 | AA59: 8101.95 | AB59: 8844.89
A60: 1 | C60: 매출총이익 | E60: 3831.37 | G60: 1523.93 | H60: 2171.12 | I60: 4693.16 | J60: 2965.36 | K60: 11353.57 | L60: 2505.58 | M60: 2506.57 | N60: 2045.58 | O60: 5665.55 | P60: 12723.28 | Q60: 1842.37 | R60: 2758.6 | S60: 4330.29 | T60: 5174.27 | U60: 14105.53 | V60: 2375.07 | W60: 2872.87 | X60: 5039.74 | Y60: 7412.6 | Z60: 17700.28 | AA60: 3976.84 | AB60: 7383.9
A61: 1 | C61: 판관비 | E61: 1915.7 | G61: 1969.61 | H61: 1665.36 | I61: 2002.12 | J61: 2487.69 | K61: 8124.78 | L61: 1947.67 | M61: 1536.92 | N61: 2263.27 | O61: 1682.08 | P61: 7429.94 | Q61: 1872.9 | R61: 1742.66 | S61: 1821.76 | T61: 1754.48 | U61: 7191.8 | V61: 1672.7 | W61: 1587.14 | X61: 1696.39 | Y61: 1880.87 | Z61: 6837.1 | AA61: 1673.27 | AB61: 1451.25
A62: 1 | C62: 영업이익 | E62: 1915.67 | G62: -445.69 | H62: 505.76 | I62: 2691.04 | J62: 477.67 | K62: 3228.78 | L62: 557.91 | M62: 969.65 | N62: -217.68 | O62: 3983.47 | P62: 5293.35 | Q62: -30.54 | R62: 1015.94 | S62: 2508.54 | T62: 3419.79 | U62: 6913.73 | V62: 702.37 | W62: 1285.73 | X62: 3343.35 | Y62: 5531.72 | Z62: 10863.17 | AA62: 2303.57 | AB62: 5932.66
A63: 1 | C63: 기타영업외손익 | E63: 44.14 | G63: 54.48 | H63: -10.65 | I63: 35.18 | J63: 33.51 | K63: 112.52 | L63: 30.51 | M63: 14.13 | N63: 21.12 | O63: 331.85 | P63: 397.61 | Q63: 50.33 | R63: 21.5 | S63: 222.35 | T63: 32.43 | U63: 326.61 | V63: 8.64 | W63: 44.04 | X63: 18.81 | Y63: 59.27 | Z63: 130.76 | AA63: 44.82 | AB63: 266.91
A64: 1 | C64: 기타영업외수익 | E64: 49.71 | G64: 54.52 | H64: 64.73 | I64: 36.4 | J64: 35.21 | K64: 190.86 | L64: 34.68 | M64: 25.86 | N64: 18.26 | O64: 333.39 | P64: 412.19 | Q64: 52.17 | R64: 22.26 | S64: 224.67 | T64: 54.04 | U64: 353.14 | V64: 25.19 | W64: 44.5 | X64: 18.44 | Y64: 60.61 | Z64: 148.74 | AA64: 65.09 | AB64: 312.2
A65: 1 | C65: 기타영업외비용 | E65: 5.58 | G65: 0.04 | H65: 75.37 | I65: 1.22 | J65: 1.68 | K65: 78.31 | L65: 4.18 | M65: 11.73 | N65: -2.86 | O65: 1.54 | P65: 14.59 | Q65: 1.84 | R65: 0.76 | S65: 2.32 | T65: 21.61 | U65: 26.53 | V65: 16.55 | W65: 0.46 | X65: -0.37 | Y65: 1.34 | Z65: 17.98 | AA65: 20.27 | AB65: 45.29
A66: 1 | C66: 금융손익 | E66: 453.64 | G66: 280.79 | H66: 36.45 | I66: 702.7 | J66: -792.24 | K66: 227.7 | L66: 118.42 | M66: -183.59 | N66: 80.61 | O66: 190.12 | P66: 205.56 | Q66: 517.72 | R66: -351.08 | S66: -204.31 | T66: 945.26 | U66: 907.59 | V66: 469.26 | W66: -283.78 | X66: 847.38 | Y66: 748.6 | Z66: 1781.46 | AA66: 1994.49 | AB66: 2724.06
A67: 1 | C67: 금융수익 | E67: 689.84 | G67: 453.75 | H67: 314.73 | I67: 959.01 | J67: -288.23 | K67: 1439.26 | L67: 512.32 | M67: 223.33 | N67: 515.31 | O67: 604.74 | P67: 1855.7 | Q67: 812.26 | R67: 323.39 | S67: 414.44 | T67: 1417.13 | U67: 2967.22 | V67: 748.4 | W67: 163.67 | X67: 1046.88 | Y67: 1559.87 | Z67: 3518.82 | AA67: 3963.16 | AB67: 2937.27
A68: 1 | C68: 금융비용 | E68: 236.2 | G68: 172.96 | H68: 278.28 | I68: 256.31 | J68: 504 | K68: 1211.55 | L68: 393.89 | M68: 406.93 | N68: 434.7 | O68: 414.62 | P68: 1650.14 | Q68: 294.54 | R68: 674.47 | S68: 618.75 | T68: 471.87 | U68: 2059.63 | V68: 279.14 | W68: 447.45 | X68: 199.5 | Y68: 811.27 | Z68: 1737.36 | AA68: 1968.67 | AB68: 213.21
A69: 1 | C69: 법인세비용차감전계속사업이익 | E69: 2413.46 | G69: -110.42 | H69: 531.56 | I69: 3428.91 | J69: -281.04 | K69: 3569.01 | L69: 706.84 | M69: 800.19 | N69: -115.95 | O69: 4505.44 | P69: 5896.52 | Q69: 537.51 | R69: 686.36 | S69: 2526.57 | T69: 4397.48 | U69: 8147.92 | V69: 1180.26 | W69: 1045.99 | X69: 4209.55 | Y69: 6339.59 | Z69: 12775.39 | AA69: 4342.89 | AB69: 8923.62
... A82: 1 | C82: 이자손익 | E82: -149.02 | G82: 138.18 | H82: -179.81 | I82: 133.1 | J82: -199.43 | K82: -107.96 | L82: 12.23 | M82: -289.54 | N82: 80.08 | O82: -285.56 | P82: -482.79 | Q82: 97.07 | R82: -263.5 | S82: 110.97 | T82: -188.25 | U82: -243.71 | V82: -37.63 | W82: -2.03 | X82: -87.7 | Y82: 7.81 | Z82: -119.55 | AA82: -37.97 | AB82: -34.59
A83: 1 | C83: 배당금수익 | H83: 0.51 | I83: 31.36 | J83: 0 | M83: 96.4 | N83: 0 | O83: 0 | R83: 57.85 | S83: 0 | T83: 0 | W83: 57.75 | X83: 3.16 | Y83: 9.57 | AB83: 185.46
A84: 1 | C84: 영업활동으로인한현금흐름 | E84: 2457.05 | G84: -1028.77 | H84: -3735.34 | I84: 1831.9 | J84: 1239.42 | K84: -1692.79 | L84: 5112.89 | M84: 3585.61 | N84: 3461.97 | O84: 318.91 | P84: 12479.38 | Q84: 3594 | R84: -230.18 | S84: 1354.48 | T84: 5018.51 | U84: 9736.81 | V84: -1860.32 | W84: 675.48 | X84: 2521.03 | Y84: 5392.73 | Z84: 6728.92 | AA84: 2812.89 | AB84: 5430.92
A85: 1 | C85: 배당금수취(CF) | E85: 0 | G85: 0 | H85: 0.51 | I85: 31.36 | J85: 0 | K85: 31.87 | L85: 0 | M85: 96.4 | N85: 0 | O85: 0 | P85: 96.4 | S85: 0 | T85: 0 | X85: 3.16 | Y85: 9.57
A86: 1 | C86: 법인세납부(CF) | E86: -2.44 | G86: -210.79 | H86: -222.29 | I86: -245.64 | J86: -11.7 | K86: -690.42 | L86: -99.55 | M86: -128.36 | N86: -100.3 | O86: -110.76 | P86: -438.97 | Q86: -39.58 | R86: -63.81 | S86: -83.51 | T86: -155.74 | U86: -342.64 | V86: -1366.89 | W86: -1585.82 | X86: -184.75 | Y86: -6.89 | Z86: -3144.35 | AA86: -158.13 | AB86: -368.97
A87: 1 | C87: 투자활동으로인한현금흐름 | E87: -333.21 | G87: -14413 | H87: -2989.63 | I87: -524.18 | J87: -149.56 | K87: -18076.37 | L87: 18.23 | M87: 10.15 | N87: 17.96 | O87: 409.25 | P87: 455.59 | Q87: 443.36 | R87: -30.35 | S87: 178.75 | T87: 2434.47 | U87: 3026.23 | V87: -120.95 | W87: -882.51 | X87: -5983.97 | Y87: -3743.78 | Z87: -10731.21 | AA87: -4458.81 | AB87: -8322.72
A88: 1 | C88: 유형자산의감소 | E88: 600 | G88: 1.36 | H88: 0 | I88: 0 | J88: 4.25 | K88: 5.61 | L88: 0 | M88: 4 | N88: 0 | O88: 0 | P88: 4 | S88: 2.05 | T88: 6.57 | X88: 0 | Y88: 8.7
A89: 1 | C89: 유형자산의증가 | E89: 1659.14 | G89: 16389.08 | H89: 1931.13 | I89: 673.41 | J89: 126.81 | K89: 19120.43 | L89: 1.8 | M89: 36.57 | N89: 4.88 | O89: 70.25 | P89: 113.5 | Q89: 73.62 | R89: 12.5 | S89: 91.13 | T89: 60.7 | U89: 237.95 | V89: 123.47 | W89: 62.74 | X89: 29.68 | Y89: 61.65 | Z89: 277.54 | AA89: 46.47 | AB89: 19.66
A90: 1 | C90: CAPEX | E90: 1708.64 | G90: 16389.08 | H90: 1936.63 | I90: 673.41 | J90: 155.56 | K90: 19154.68 | L90: 1.8 | M90: 36.57 | N90: 13.29 | O90: 70.25 | P90: 121.91 | Q90: 73.62 | R90: 12.5 | S90: 97.73 | T90: 60.7 | U90: 244.55 | V90: 123.47 | W90: 62.74 | X90: 29.68 | Y90: 61.65 | Z90: 277.54 | AA90: 47.03 | AB90: 19.66
A91: 1 | C91: 무형자산의증가 | E91: 49.5 | G91: 0 | H91: 5.5 | I91: 0 | J91: 28.75 | K91: 34.25 | L91: 0 | M91: 0 | N91: 8.41 | O91: 0 | P91: 8.41 | T91: 0 | Y91: 0 | AA91: 0.56 | AB91: 0
A92: 1 | C92: 재무활동으로인한현금흐름 | E92: 4398.03 | G92: 16160.48 | H92: -288.55 | I92: 501.91 | J92: -233.49 | K92: 16140.35 | L92: -107.59 | M92: -808.55 | N92: -110.39 | O92: -110.44 | P92: -1136.97 | Q92: 552.69 | R92: 2328.26 | S92: 471.08 | T92: -901.2 | U92: 2450.83 | V92: -592.31 | W92: 1077.51 | X92: 1494.3 | Y92: -5.37 | Z92: 1974.13 | AA92: -5.47 | AB92: -4.52
A93: 1 | C93: 장기차입금의증가 | E93: 5000 | G93: 8500 | H93: 0 | I93: 0 | J93: 0 | K93: 8500 | L93: 0 | M93: 0 | N93: 0 | O93: 0 | P93: 0 | Q93: 8000 | R93: 0 | S93: 9800 | T93: 7700 | U93: 25500 | V93: 0 | W93: 0 | X93: 1500 | Y93: 0 | Z93: 1500 | AA93: 2000 | AB93: 0
A94: 1 | C94: 리스부채의상환 | E94: 471.77 | G94: 210.74 | H94: 202.33 | I94: 198.1 | J94: 233.49 | K94: 844.66 | L94: 107.59 | M94: 108.55 | N94: 110.39 | O94: 110.44 | P94: 436.97 | Q94: 108.47 | R94: 109.09 | S94: 109.87 | V94: 8.99 | W94: 5.81 | X94: 5.7 | Y94: 5.37 | Z94: 25.87 | AA94: 5.47 | AB94: 4.52
A95: 1 | C95: 단기차입금의감소 | E95: 0 | G95: 0 | H95: 0 | I95: 0 | J95: 700 | K95: 700 | L95: 0 | M95: 700 | N95: 0 | O95: 0 | P95: 700 | Q95: 8000 | R95: 0 | S95: 4000 | T95: 1100 | U95: 13100 | V95: 800 | W95: 700 | X95: 0 | Y95: 0 | Z95: 1500 | AA95: 2000 | AB95: 0
A96: 1 | C96: 유동성장기부채의감소 | E96: 128.13 | G96: 128.78 | H96: 86.21 | I96: 0 | J96: 0 | K96: 214.99 | L96: 0 | M96: 1600 | N96: 0 | O96: 0 | P96: 1600 | S96: 0 | T96: 1896.04
A97: 1 | C97: 장기차입금의감소 | E97: 0 | G97: 0 | H97: 0 | I97: 0 | J97: 0 | K97: 0 | L97: 0 | M97: 0 | Q97: 208.41 | R97: 562.65 | S97: 4937.42 | T97: 5895.48 | U97: 11603.96 | V97: 0 | W97: 0 | X97: 0 | Y97: 0 | Z97: 0
A98: 1 | C98: 단기차입금의증가 | E98: 0 | G98: 8000 | H98: 0 | I98: 700 | J98: 700 | K98: 9400 | L98: 0 | M98: 1600 | N98: 0 | O98: 0 | P98: 1600 | S98: 0 | T98: 0 | X98: 0 | Y98: 0
A99: 1 | C99: 현금및현금성자산의증감 | E99: 6515.5 | G99: 714.59 | H99: -6990.35 | I99: 1791.02 | J99: 847.81 | K99: -3636.93 | L99: 5079.57 | M99: 2736.06 | N99: 3465.68 | O99: 467.51 | P99: 11748.82 | Q99: 4604.57 | R99: 2053.33 | S99: 1982.39 | T99: 6652.21 | U99: 15292.5 | V99: -2569.93 | W99: 702.93 | X99: -1803.02 | Y99: 1637.24 | Z99: -2032.78 | AA99: -1642.19 | AB99: -2900.88
A100: 1 | C100: 기말현금및현금성자산 | E100: 6515.49 | G100: 10467.24 | H100: -6990.35 | I100: 1791.03 | J100: 847.8 | K100: 6115.72 | L100: 11195.29 | M100: 2736.06 | N100: 3465.69 | O100: 467.5 | P100: 17864.54 | Q100: 22469.11 | R100: 2053.33 | S100: 1982.39 | T100: 6652.21 | U100: 33157.04 | V100: 30587.1 | W100: 702.94 | X100: -1803.02 | Y100: 1637.23 | Z100: 31124.25 | AA100: 29482.06 | AB100: -2900.88
A101: 1 | C101: 이자수취(CF) | Q101: 358.89 | V101: 384.19 | W101: 77.23 | X101: 373.31 | Y101: 44.75 | Z101: 879.48 | AA101: 397.39 | AB101: 22.53
A102: 1 | C102: 자기주식의취득 | Y102: 0

Sheet BS별도
B1: (백만원) | C1: 이름: BS별도H | E1: 4Q21 | F1: 2021 | G1: 1Q22 | H1: 2Q22 | I1: 3Q22 | J1: 4Q22 | K1: 2022 | L1: 1Q23 | M1: 2Q23 | N1: 3Q23 | O1: 4Q23 | P1: 2023 | Q1: 1Q24 | R1: 2Q24 | S1: 3Q24 | T1: 4Q24 | U1: 2024 | V1: 1Q25 | W1: 2Q25 | X1: 3Q25 | Y1: 4Q25 | Z1: 2025 | AA1: 1Q26 | AB1: 2Q26 | AC1: 3Q26 | AD1: 4Q26 | AE1: 2026 | AF1: 1Q27 | AG1: 2Q27 | AH1: 3Q27 | AI1: 4Q27 | AJ1: 2027 | AK1: 1Q28 | AL1: 2Q28 | AM1: 3Q28 | AN1: 4Q28 | AO1: 2028
B2: 별도 | D2: fin json(kship_fin.py)
B3: 일승(별) | C3: UPDATE: 26-10-13 | E3: 1 | F3: 2 | G3: 3 | H3: 4 | I3: 5 | J3: 6 | K3: 7 | L3: 8 | M3: 9 | N3: 10 | O3: 11 | P3: 12 | Q3: 13 | R3: 14 | S3: 15 | T3: 16 | U3: 17 | V3: 18 | W3: 19 | X3: 20 | Y3: 21 | Z3: 22 | AA3: 23 | AB3: 24 | AC3: 25 | AD3: 26 | AE3: 27 | AF3: 28 | AG3: 29 | AH3: 30 | AI3: 31 | AJ3: 32 | AK3: 33 | AL3: 34 | AM3: 35 | AN3: 36 | AO3: 37
B4: Account Code | C4: AccountNAME | E4: 2021.12 | F4: 2021.12A | G4: 2022.03 | H4: 2022.06 | I4: 2022.09 | J4: 2022.12 | K4: 2022.12A | L4: 2023.03 | M4: 2023.06 | N4: 2023.09 | O4: 2023.12 | P4: 2023.12A | Q4: 2024.03 | R4: 2024.06 | S4: 2024.09 | T4: 2024.12 | U4: 2024.12A | V4: 2025.03 | W4: 2025.06 | X4: 2025.09 | Y4: 2025.12 | Z4: 2025.12A | AA4: 2026.03 | AB4: 2026.06 | AC4: 2026.09 | AD4: 2026.12 | AE4: 2026.12A | AF4: 2027.03 | AG4: 2027.06 | AH4: 2027.09 | AI4: 2027.12 | AJ4: 2027.12A | AK4: 2028.03 | AL4: 2028.06 | AM4: 2028.09 | AN4: 2028.12 | AO4: 2028.12A
A5: 1 | C5: 유동자산 | E5: 20121.76 | F5: 20121.76 | G5: 20938.96 | H5: 18646.2 | I5: 22061.71 | J5: 19024.89 | K5: 19024.89 | L5: 16863.73 | M5: 16221.08 | N5: 15984.3 | O5: 17869.75 | P5: 17869.75 | Q5: 17980.43 | R5: 28086.39 | S5: 31014.35 | T5: 31528.22 | U5: 31528.22 | V5: 29908.17 | W5: 30831.2 | X5: 33107.67 | Y5: 34319.97 | Z5: 34319.97 | AA5: 36445.69 | AB5: 40435.75
A6: 1 | C6: 현금및현금성자산 | E6: 5896.77 | F6: 5896.77 | G6: 5308.01 | H6: 1323.66 | I6: 2010.13 | J6: 1852.51 | K6: 1852.51 | L6: 5387.86 | M6: 6606.82 | N6: 8894.3 | O6: 9045.43 | P6: 9045.43 | Q6: 10311.27 | R6: 22206.08 | S6: 23889.05 | T6: 28664.16 | U6: 28664.16 | V6: 26661.87 | W6: 27196.78 | X6: 23491.48 | Y6: 18112.39 | Z6: 18112.39 | AA6: 14592.01 | AB6: 8446.67
A7: 1 | C7: 단기금융상품 | E7: 2001.41 | F7: 2001.41 | G7: 2000 | H7: 2000 | I7: 2005.2 | J7: 2003.54 | K7: 2003.54 | L7: 2009.17 | M7: 2001.56 | N7: 2000 | O7: 2001.53 | P7: 2001.53 | Q7: 2001.6 | R7: 2000 | S7: 2000 | T7: 0 | U7: 0 | V7: 0 | W7: 928.86 | X7: 7269.48 | Y7: 12320.39 | Z7: 12320.39 | AA7: 17982.16 | AB7: 27110.5
A8: 1 | C8: 단기금융자산 | E8: 2001.41 | F8: 2001.41 | G8: 2000 | H8: 2000 | I8: 2005.2 | J8: 2003.54 | K8: 2003.54 | L8: 2009.17 | M8: 2001.56 | N8: 2000 | O8: 2001.53 | P8: 2001.53 | Q8: 2001.6 | R8: 2000 | S8: 2000 | T8: 0 | U8: 0 | V8: 0 | W8: 928.86 | X8: 7269.48 | Y8: 12320.39 | Z8: 12320.39 | AA8: 17982.16 | AB8: 27110.5
A9: 1 | C9: 매출채권및기타채권 | E9: 5555.08 | F9: 5555.08 | G9: 7473.07 | H9: 6053.97 | I9: 7031.84 | J9: 9447.04 | K9: 9447.04 | L9: 5876.04 | M9: 5053.28 | N9: 2575.79 | O9: 4696.64 | P9: 4696.64 | Q9: 2554.34 | R9: 1515.99 | S9: 2632.46 | T9: 1910.85 | U9: 1910.85 | V9: 1789.53 | W9: 1595.96 | X9: 1102.89 | Y9: 1879.98 | Z9: 1879.98 | AA9: 1809.06 | AB9: 1854.05
A10: 1 | C10: 계약자산 | E10: 1962.36 | F10: 1962.36 | G10: 1165.39 | H10: 987.29 | I10: 1265.16 | J10: 391.95 | K10: 391.95 | L10: 403.24 | M10: 406.02 | N10: 0 | O10: 190.13 | P10: 190.13 | Q10: 193.98 | R10: 192.44 | S10: 192.44 | T10: 192.44 | U10: 192.44 | V10: 192.44 | W10: 0 | X10: 0 | Y10: 0 | Z10: 0
A11: 1 | C11: 기타유동자산 | E11: 510.42 | F11: 510.42 | G11: 396.32 | H11: 694.82 | I11: 281.01 | J11: 82.81 | K11: 82.81 | L11: 56.81 | M11: 648.24 | N11: 704.8 | O11: 39.34 | P11: 39.34 | Q11: 122.76 | R11: 106.38 | S11: 55.55 | T11: 2.64 | U11: 2.64 | V11: 7.4 | W11: 3.44 | X11: 40.94 | Y11: 67.98 | Z11: 67.98 | AA11: 1.94 | AB11: 3.48
A12: 1 | C12: 재고자산 | E12: 4195.73 | F12: 4195.73 | G12: 4596.17 | H12: 7586.46 | I12: 9468.37 | J12: 5247.04 | K12: 5247.04 | L12: 3130.61 | M12: 1505.16 | N12: 1726.75 | O12: 1896.69 | P12: 1896.69 | Q12: 2796.48 | R12: 2065.5 | S12: 2244.84 | T12: 758.13 | U12: 758.13 | V12: 1256.93 | W12: 1106.16 | X12: 1202.88 | Y12: 1939.23 | Z12: 1939.23 | AA12: 2060.52 | AB12: 2034.8
A13: 1 | C13: 비유동자산 | E13: 28578.34 | F13: 28578.34 | G13: 38137.48 | H13: 39578.59 | I13: 40327.8 | J13: 39561.82 | K13: 39561.82 | L13: 39469.14 | M13: 40751.38 | N13: 39996.17 | O13: 39942.52 | P13: 39942.52 | Q13: 39581.09 | R13: 35954.91 | S13: 35431.29 | T13: 35027.89 | U13: 35027.89 | V13: 35379.05 | W13: 35667.69 | X13: 35906.01 | Y13: 36051.02 | Z13: 36051.02 | AA13: 36546.47 | AB13: 37323.89
A14: 1 | C14: 장기매출채권및기타채권 | E14: 655.69 | F14: 655.69 | G14: 654.07 | H14: 214.28 | I14: 107.49 | J14: 108.7 | K14: 108.7 | L14: 11.4 | M14: 6.4 | N14: 6.4 | O14: 6.4 | P14: 6.4 | Q14: 5.1 | R14: 4.88 | S14: 4.88 | T14: 4.88 | U14: 4.88 | V14: 2.18 | W14: 2.18 | X14: 2.18 | Y14: 2.18 | Z14: 2.18 | AA14: 0.18 | AB14: 0.18
A15: 1 | C15: 장기금융자산 | E15: 6372.58 | F15: 6372.58 | G15: 6994.51 | H15: 7632.49 | I15: 8184.92 | J15: 7555.39 | K15: 7555.39 | L15: 7807.59 | M15: 9129.1 | N15: 8443.62 | O15: 8457.78 | P15: 8457.78 | Q15: 8147.7 | R15: 7532.95 | S15: 7040.29 | T15: 6677.15 | U15: 6677.15 | V15: 7074.82 | W15: 7410.62 | X15: 7691.98 | Y15: 7885.09 | Z15: 7885.09 | AA15: 8427.37 | AB15: 10213.67
A16: 1 | C16: 투자자산 | E16: 16638.36 | F16: 16638.36 | G16: 17260.29 | H16: 17898.27 | I16: 18450.7 | J16: 17821.17 | K16: 17821.17 | L16: 18073.37 | M16: 19394.88 | N16: 18709.4 | O16: 18723.56 | P16: 18723.56 | Q16: 18413.48 | R16: 17798.73 | S16: 17306.07 | T16: 16942.93 | U16: 16942.93 | V16: 17340.6 | W16: 17676.4 | X16: 17957.76 | Y16: 18150.87 | Z16: 18150.87 | AA16: 18693.15 | AB16: 20479.45
A17: 1 | C17: 종속기업및관계기업투자 | E17: 10265.78 | F17: 10265.78 | G17: 10265.78 | H17: 10265.78 | I17: 10265.78 | J17: 10265.78 | K17: 10265.78 | L17: 10265.78 | M17: 10265.78 | N17: 10265.78 | O17: 10265.78 | P17: 10265.78 | Q17: 10265.78 | R17: 10265.78 | S17: 10265.78 | T17: 10265.78 | U17: 10265.78 | V17: 10265.78 | W17: 10265.78 | X17: 10265.78 | Y17: 10265.78 | Z17: 10265.78 | AA17: 10265.78 | AB17: 10265.78
A18: 1 | C18: 유형자산 | E18: 10974.67 | F18: 10974.67 | G18: 19307.34 | H18: 20703.23 | I18: 21220.18 | J18: 21267.65 | K18: 21267.65 | L18: 21220.05 | M18: 21206.58 | N18: 21158.64 | O18: 21112.63 | P18: 21112.63 | Q18: 21072.16 | R18: 18110.97 | S18: 18070.24 | T18: 18039 | U18: 18039 | V18: 17999.86 | W18: 17959.63 | X18: 17921.29 | Y18: 9708.21 | Z18: 9708.21 | AA18: 9667.68 | AB18: 8661.16
A19: 1 | C19: 사용권자산 | E19: 187.76 | F19: 187.76 | G19: 806.57 | H19: 660.86 | I19: 460.41 | J19: 259.96 | K19: 259.96 | L19: 70.41 | M19: 62.03 | N19: 53.64 | O19: 45.26 | P19: 45.26 | Q19: 43.59 | R19: 36.93 | S19: 41.44 | T19: 33.75 | U19: 33.75 | V19: 30.15 | W19: 24.06 | X19: 19.71 | Y19: 15.77 | Z19: 15.77 | AA19: 11.82 | AB19: 9.82
A20: 1 | C20: 기타비유동자산 | E20: 187.76 | F20: 187.76 | G20: 806.57 | H20: 660.86 | I20: 460.41 | J20: 259.96 | K20: 259.96 | L20: 70.41 | M20: 62.03 | N20: 53.64 | O20: 45.26 | P20: 45.26 | Q20: 43.59 | R20: 36.93 | S20: 41.44 | T20: 33.75 | U20: 33.75 | V20: 30.15 | W20: 24.06 | X20: 19.71 | Y20: 15.77 | Z20: 15.77 | AA20: 11.82 | AB20: 9.82
A21: 1 | C21: 무형자산 | E21: 121.86 | F21: 121.86 | G21: 109.2 | H21: 101.95 | I21: 89.01 | J21: 104.33 | K21: 104.33 | L21: 93.92 | M21: 81.5 | N21: 68.09 | O21: 54.67 | P21: 54.67 | Q21: 46.77 | R21: 3.41 | S21: 8.67 | T21: 7.33 | U21: 7.33 | V21: 6.26 | W21: 5.42 | X21: 5.06 | Y21: 4.7 | Z21: 4.7 | AA21: 4.34 | AB21: 3.98
A22: 1 | C22: 자산총계 | E22: 48700.11 | F22: 48700.11 | G22: 59076.44 | H22: 58224.79 | I22: 62389.51 | J22: 58586.72 | K22: 58586.72 | L22: 56332.87 | M22: 56972.46 | N22: 55980.47 | O22: 57812.27 | P22: 57812.27 | Q22: 57561.52 | R22: 64041.3 | S22: 66445.64 | T22: 66556.11 | U22: 66556.11 | V22: 65287.21 | W22: 66498.89 | X22: 69013.68 | Y22: 70370.99 | Z22: 70370.99 | AA22: 72992.16 | AB22: 77759.64
... A24: 1 | C24: 매입채무및기타채무 | E24: 4872.27 | F24: 4872.27 | G24: 4962.72 | H24: 4501.98 | I24: 4260.2 | J24: 3836.33 | K24: 3836.33 | L24: 3123.29 | M24: 2206.51 | N24: 2117.64 | O24: 2383.09 | P24: 2383.09 | Q24: 2161.33 | R24: 1242.19 | S24: 510.94 | T24: 1338.42 | U24: 1338.42 | V24: 736.52 | W24: 750.92 | X24: 828.7 | Y24: 987.8 | Z24: 987.8 | AA24: 916.54 | AB24: 871.22
A25: 1 | C25: 계약부채 | E25: 159.32 | F25: 159.32 | G25: 353.25 | H25: 489.05 | I25: 259.15 | J25: 259.15 | K25: 259.15 | L25: 259.15 | M25: 259.15 | N25: 259.15 | O25: 469.71 | P25: 469.71 | Q25: 469.71 | R25: 469.71 | S25: 469.71 | T25: 0 | U25: 0 | V25: 0 | W25: 0 | Y25: 0 | Z25: 0
A26: 1 | C26: 당기법인세부채(미지급법인세) | E26: 444.92 | F26: 444.92 | G26: 249.06 | H26: 73.5 | I26: 602.61 | J26: 225.92 | K26: 225.92 | L26: 143.21 | M26: 74.44 | N26: 0 | O26: 103.72 | P26: 103.72 | Q26: 136.97 | R26: 2472.11 | S26: 2752.22 | T26: 3000.04 | U26: 3000.04 | V26: 1800.43 | W26: 258.12 | X26: 363.89 | Y26: 314.43 | Z26: 314.43 | AA26: 891.86 | AB26: 1732.85
A27: 1 | C27: 단기차입금 | E27: 3814.99 | F27: 3814.99 | G27: 3686.21 | H27: 3600 | I27: 4300 | J27: 4300 | K27: 4300 | L27: 4508.41 | M27: 4371.06 | N27: 4933.55 | O27: 5496.04 | P27: 5496.04 | Q27: 5850.12 | R27: 2249.96 | S27: 1416.64 | T27: 0 | U27: 0 | V27: 0 | W27: 2000 | X27: 2000 | Y27: 9700 | Z27: 9700 | AA27: 7700 | AB27: 7700
A28: 1 | C28: 단기금융부채(face) | E28: 3814.99 | F28: 3814.99 | G28: 3686.21 | H28: 3600 | I28: 4300 | J28: 4300 | K28: 4300 | L28: 4508.41 | M28: 4371.06 | N28: 4933.55 | O28: 5496.04 | P28: 5496.04 | Q28: 5850.12 | R28: 2249.96 | S28: 1416.64 | T28: 0 | U28: 0 | V28: 0 | W28: 2000 | X28: 2000 | Y28: 9700 | Z28: 9700 | AA28: 7700 | AB28: 7700
A29: 1 | C29: 유동리스부채 | E29: 196.47 | F29: 196.47 | G29: 786.58 | H29: 606.27 | I29: 414.73 | J29: 220.75 | K29: 220.75 | L29: 34.51 | M29: 32.72 | N29: 27.56 | O29: 21.5 | P29: 21.5 | Q29: 21.99 | R29: 17.5 | S29: 25.08 | T29: 20.45 | U29: 20.45 | V29: 19.67 | W29: 16.24 | X29: 14.85 | Y29: 13.88 | Z29: 13.88 | AA29: 12.89 | AB29: 11.74
A30: 1 | C30: 리스부채 | E30: 219.18 | F30: 219.18 | G30: 805.91 | H30: 665.59 | I30: 468.06 | J30: 267.93 | K30: 267.93 | L30: 75.36 | M30: 67.06 | N30: 58.55 | O30: 49.82 | P30: 49.82 | Q30: 47.57 | R30: 40.27 | S30: 44.99 | T30: 37.42 | U30: 37.42 | V30: 33.64 | W30: 27.13 | X30: 22.6 | Y30: 18.41 | Z30: 18.41 | AA30: 14.12 | AB30: 11.74
A31: 1 | C31: 단기금융부채 | E31: 196.47 | F31: 196.47 | G31: 786.58 | H31: 606.27 | I31: 414.73 | J31: 220.75 | K31: 220.75 | L31: 34.51 | M31: 32.72 | N31: 27.56 | O31: 21.5 | P31: 21.5 | Q31: 21.99 | R31: 17.5 | S31: 25.08 | T31: 20.45 | U31: 20.45 | V31: 19.67 | W31: 16.24 | X31: 14.85 | Y31: 13.88 | Z31: 13.88 | AA31: 12.89 | AB31: 11.74
A32: 1 | C32: 기타유동부채 | E32: 2335.4 | F32: 2335.4 | G32: 2816.24 | H32: 2919.83 | I32: 3474.76 | J32: 1969.5 | K32: 1969.5 | L32: 153.24 | M32: 773.79 | N32: 725.33 | O32: 274.34 | P32: 274.34 | Q32: 212.03 | R32: 47.21 | S32: 225.37 | T32: 144.11 | U32: 144.11 | V32: 34.62 | W32: 32.75 | X32: 19.33 | Y32: 22.78 | Z32: 22.78 | AA32: 37.43 | AB32: 312.52
A33: 1 | C33: 비유동부채 | E33: 6123.15 | F33: 6123.15 | G33: 14766.98 | H33: 14708.05 | I33: 14904.47 | J33: 14855.28 | K33: 14855.28 | L33: 14733.73 | M33: 14364.35 | N33: 13635.44 | O33: 12550.28 | P33: 12550.28 | Q33: 12034.69 | R33: 11221.23 | S33: 13607.78 | T33: 14707.56 | U33: 14707.56 | V33: 14744.05 | W33: 14831.16 | X33: 16363.33 | Y33: 8705.7 | Z33: 8705.7 | AA33: 10715.18 | AB33: 10687.52
A34: 1 | C34: 장기차입금 | E34: 5000 | F34: 5000 | G34: 13500 | H34: 13500 | I34: 13500 | J34: 13500 | K34: 13500 | L34: 13291.59 | M34: 12728.94 | N34: 12166.45 | O34: 11603.96 | P34: 11603.96 | Q34: 11041.47 | R34: 10478.98 | S34: 12874.88 | T34: 14200 | U34: 14200 | V34: 14200 | W34: 14200 | X34: 15700 | Y34: 8000 | Z34: 8000 | AA34: 10000 | AB34: 10000
A35: 1 | C35: 장기금융부채(face) | E35: 5000 | F35: 5000 | G35: 13500 | H35: 13500 | I35: 13500 | J35: 13500 | K35: 13500 | L35: 13291.59 | M35: 12728.94 | N35: 12166.45 | O35: 11603.96 | P35: 11603.96 | Q35: 11041.47 | R35: 10478.98 | S35: 12874.88 | T35: 14200 | U35: 14200 | V35: 14200 | W35: 14200 | X35: 15700
A36: 1 | C36: 비유동리스부채 | E36: 22.71 | F36: 22.71 | G36: 19.33 | H36: 59.32 | I36: 53.33 | J36: 47.18 | K36: 47.18 | L36: 40.85 | M36: 34.34 | N36: 30.99 | O36: 28.32 | P36: 28.32 | Q36: 25.58 | R36: 22.77 | S36: 19.91 | T36: 16.97 | U36: 16.97 | V36: 13.97 | W36: 10.89 | X36: 7.75 | Y36: 4.53 | Z36: 4.53 | AA36: 1.23 | AB36: 0
A37: 1 | C37: 장기금융부채 | E37: 22.71 | F37: 22.71 | G37: 19.33 | H37: 59.32 | I37: 53.33 | J37: 47.18 | K37: 47.18 | L37: 40.85 | M37: 34.34 | N37: 30.99 | O37: 28.32 | P37: 28.32 | Q37: 25.58 | R37: 22.77 | S37: 19.91 | T37: 16.97 | U37: 16.97 | V37: 13.97 | W37: 10.89 | X37: 7.75 | Y37: 4.53 | Z37: 4.53 | AA37: 1.23 | AB37: 0
A38: 1 | C38: 확정급여부채 | E38: 225.15 | F38: 225.15 | G38: 221.68 | H38: 193.02 | I38: 308.8 | J38: 466.97 | K38: 466.97 | L38: 523.57 | M38: 408.56 | N38: 402.9 | O38: 86.92 | P38: 86.92 | Q38: 218.97 | R38: 8.23 | S38: 37.94 | T38: 67.19 | U38: 67.19 | V38: 101.5 | W38: 113.11 | X38: 148.07 | Y38: 58.2 | Z38: 58.2 | AA38: 75.34 | AB38: 96.64
A39: 1 | C39: 이연법인세부채 | E39: 875.28 | F39: 875.28 | G39: 1025.97 | H39: 955.71 | I39: 1042.35 | J39: 841.13 | K39: 841.13 | L39: 877.73 | M39: 1192.51 | N39: 1035.1 | O39: 831.08 | P39: 831.08 | Q39: 748.67 | R39: 711.24 | S39: 675.05 | T39: 413.81 | U39: 413.81 | V39: 418.6 | W39: 498.2 | X39: 497.7 | Y39: 636.16 | Z39: 636.16 | AA39: 631.11 | AB39: 585.23
A40: 1 | C40: 부채총계 | E40: 17946.53 | F40: 17946.53 | G40: 27621.05 | H40: 26898.68 | I40: 28215.93 | J40: 25666.93 | K40: 25666.93 | L40: 22955.54 | M40: 22082.03 | N40: 21698.66 | O40: 21298.68 | P40: 21298.68 | Q40: 20886.82 | R40: 17719.91 | S40: 19007.74 | T40: 19210.59 | U40: 19210.59 | V40: 17335.29 | W40: 17889.19 | X40: 19590.11 | Y40: 19744.59 | Z40: 19744.59 | AA40: 20273.9 | AB40: 21315.85
A41: 1 | C41: 자본금 | E41: 3072.67 | F41: 3072.67 | G41: 3072.67 | H41: 3072.67 | I41: 3072.67 | J41: 3072.67 | K41: 3072.67 | L41: 3072.67 | M41: 3072.67 | N41: 3072.67 | O41: 3072.67 | P41: 3072.67 | Q41: 3072.67 | R41: 3072.67 | S41: 3072.67 | T41: 3072.67 | U41: 3072.67 | V41: 3072.67 | W41: 3072.67 | X41: 3072.67 | Y41: 3072.67 | Z41: 3072.67 | AA41: 3072.67 | AB41: 3072.67
A42: 1 | C42: 자본잉여금 | E42: 22064.38 | F42: 22064.38 | G42: 22064.38 | H42: 22064.38 | I42: 22064.38 | J42: 22064.38 | K42: 22064.38 | L42: 22064.38 | M42: 22064.38 | N42: 22064.38 | O42: 22064.38 | P42: 22064.38 | Q42: 22064.38 | R42: 22064.38 | S42: 22064.38 | T42: 22064.38 | U42: 22064.38 | V42: 22064.38 | W42: 22064.38 | X42: 22064.38 | Y42: 22033.95 | Z42: 22033.95 | AA42: 22033.95 | AB42: 22033.95
A43: 1 | C43: 기타자본 | E43: 0 | F43: 0 | G43: 0 | H43: 0 | I43: 0 | J43: 0 | K43: 0 | L43: 0 | M43: 0 | N43: 0 | O43: 0 | P43: 0 | Q43: 0 | R43: 0 | S43: -141.91 | T43: -141.91 | U43: -141.91 | V43: -141.91 | W43: -141.91 | X43: -141.91 | Y43: -141.91 | Z43: -141.91 | AA43: -141.91 | AB43: -141.91
A44: 1 | C44: 기타포괄이익누계액 | E44: -58.8 | F44: -58.8 | G44: 426.31 | H44: 143.93 | I44: 574.83 | J44: 84.87 | K44: 84.87 | L44: 284.11 | M44: 1328.1 | N44: 830.99 | O44: 694.91 | P44: 694.91 | Q44: 387.93 | R44: 254.48 | S44: 119.21 | T44: -969.72 | U44: -969.72 | V44: -950.04 | W44: -667.19 | X44: -667.23 | Y44: -623.74 | Z44: -623.74 | AA44: -640.07 | AB44: -802.47
A45: 1 | C45: 이익잉여금 | E45: 5675.33 | F45: 5675.33 | G45: 5892.02 | H45: 6045.12 | I45: 8461.7 | J45: 7697.86 | K45: 7697.86 | L45: 7956.17 | M45: 8425.28 | N45: 8313.77 | O45: 10681.63 | P45: 10681.63 | Q45: 11149.72 | R45: 20929.86 | S45: 22323.55 | T45: 23320.1 | U45: 23320.1 | V45: 23906.82 | W45: 24281.74 | X45: 25095.65 | Y45: 26285.42 | Z45: 26285.42 | AA45: 28393.62 | AB45: 32281.56
A46: 1 | C46: 자본총계 | E46: 30753.58 | F46: 30753.58 | G46: 31455.39 | H46: 31326.11 | I46: 34173.58 | J46: 32919.78 | K46: 32919.78 | L46: 33377.33 | M46: 34890.43 | N46: 34281.81 | O46: 36513.59 | P46: 36513.59 | Q46: 36674.7 | R46: 46321.4 | S46: 47437.9 | T46: 47345.52 | U46: 47345.52 | V46: 47951.92 | W46: 48609.69 | X46: 49423.56 | Y46: 50626.4 | Z46: 50626.4 | AA46: 52718.26 | AB46: 56443.79
A47: 1 | C47: 부채와자본총계 | E47: 48700.11 | F47: 48700.11 | G47: 59076.44 | H47: 58224.79 | I47: 62389.51 | J47: 58586.72 | K47: 58586.72 | L47: 56332.87 | M47: 56972.46 | N47: 55980.47 | O47: 57812.27 | P47: 57812.27 | Q47: 57561.52 | R47: 64041.3 | S47: 66445.64 | T47: 66556.11 | U47: 66556.11 | V47: 65287.21 | W47: 66498.89 | X47: 69013.68 | Y47: 70370.99 | Z47: 70370.99 | AA47: 72992.16 | AB47: 77759.64
... A51: 1 | C51: 이자발생자산 | E51: 14270.76 | F51: 14270.76 | G51: 14302.52 | H51: 10956.15 | I51: 12200.25 | J51: 11411.44 | K51: 11411.44 | L51: 15204.62 | M51: 17737.48 | N51: 19337.92 | O51: 19504.74 | P51: 19504.74 | Q51: 20460.57 | R51: 31739.03 | S51: 32929.34 | T51: 35341.31 | U51: 35341.31 | V51: 33736.69 | W51: 35536.26 | X51: 38452.94 | Y51: 38317.87 | Z51: 38317.87 | AA51: 41001.54 | AB51: 45770.84
A52: 1 | C52: 당기법인세자산(선급법인세) | N52: 82.65
A53: 1 | C53: 기타비유동부채 | T53: 9.58 | U53: 9.58 | V53: 9.98 | W53: 8.95 | X53: 9.82 | Y53: 6.81 | Z53: 6.81 | AA53: 7.51 | AB53: 5.65
A54: 1 | C54: 투자부동산 | Y54: 8169.29 | Z54: 8169.29 | AA54: 8169.29 | AB54: 8169.29
A55: 1 | C55: 매각예정비유동자산및처분자산 | AB55: 986.25
A56: 1 | C56: 매출액(수익) | E56: 13028.42 | G56: 9661.41 | H56: 7581.21 | I56: 11424.27 | J56: 12123.76 | K56: 40790.65 | L56: 7648.6 | M56: 6882.17 | N56: 4143.53 | O56: 6989.32 | P56: 25663.62 | Q56: 4256.38 | R56: 2062.35 | S56: 3378.91 | T56: 4838.84 | U56: 14536.48 | V56: 1560 | W56: 2719.07 | X56: 2291.1 | Y56: 2224.94 | Z56: 8795.11 | AA56: 2882.21 | AB56: 4568.32
A57: 1 | C57: 매출원가 | E57: 10701 | G57: 8461.34 | H57: 6482.02 | I57: 7404.42 | J57: 11122.52 | K57: 33470.3 | L57: 6681.99 | M57: 5476.61 | N57: 3173.68 | O57: 4386.04 | P57: 19718.32 | Q57: 3373.95 | R57: 1498.34 | S57: 1436.31 | T57: 3741.01 | U57: 10049.61 | V57: 1065.96 | W57: 1909.47 | X57: 1702.97 | Y57: 1502.82 | Z57: 6181.22 | AA57: 1886.8 | AB57: 2325.04
A58: 1 | C58: 매출총이익 | E58: 2327.4 | G58: 1200.06 | H58: 1099.19 | I58: 4019.85 | J58: 1001.24 | K58: 7320.34 | L58: 966.61 | M58: 1405.56 | N58: 969.84 | O58: 2603.28 | P58: 5945.29 | Q58: 882.43 | R58: 564.01 | S58: 1942.6 | T58: 1097.83 | U58: 4486.87 | V58: 494.05 | W58: 809.6 | X58: 588.13 | Y58: 722.13 | Z58: 2613.91 | AA58: 995.41 | AB58: 2243.27
A59: 1 | C59: 판관비 | E59: 1400.56 | G59: 1303.26 | H59: 1115.73 | I59: 1464.12 | J59: 1559.72 | K59: 5442.83 | L59: 1084.6 | M59: 863.01 | N59: 1485.81 | O59: 959.59 | P59: 4393.01 | Q59: 915.44 | R59: 495.36 | S59: 485.91 | T59: 502.08 | U59: 2398.79 | V59: 420.69 | W59: 420.4 | X59: 477.05 | Y59: 540.51 | Z59: 1858.65 | AA59: 451.59 | AB59: 420.18
A60: 1 | C60: 영업이익 | E60: 926.84 | G60: -103.2 | H60: -16.54 | I60: 2555.73 | J60: -558.49 | K60: 1877.5 | L60: -117.99 | M60: 542.56 | N60: -515.97 | O60: 1643.69 | P60: 1552.29 | Q60: -33 | R60: 68.65 | S60: 1456.69 | T60: 595.75 | U60: 2088.09 | V60: 73.36 | W60: 389.2 | X60: 111.08 | Y60: 181.61 | Z60: 755.25 | AA60: 543.82 | AB60: 1823.09
A61: 1 | C61: 기타영업외손익 | E61: 17.53 | G61: 12.41 | H61: 20.87 | I61: 18.1 | J61: 63.24 | K61: 114.62 | L61: 123.38 | M61: 110.59 | N61: 115.16 | O61: 432.45 | P61: 781.58 | Q61: 144.55 | R61: 112.75 | S61: 312.94 | T61: 121.92 | U61: 692.16 | V61: 89.63 | W61: 101.53 | X61: 104.03 | Y61: 109.46 | Z61: 404.65 | AA61: 99.88 | AB61: 263.32
A62: 1 | C62: 기타영업외수익 | E62: 23.1 | G62: 12.44 | H62: 20.87 | I62: 18.85 | J62: 63.24 | K62: 115.4 | L62: 123.38 | M62: 110.59 | N62: 115.16 | O62: 433.23 | P62: 782.36 | Q62: 144.55 | R62: 113.05 | S62: 313.03 | T62: 121.92 | U62: 692.55 | V62: 103.95 | W62: 101.66 | X62: 104.03 | Y62: 109.46 | Z62: 419.1 | AA62: 99.88 | AB62: 266.23
A63: 1 | C63: 기타영업외비용 | E63: 5.58 | G63: 0.03 | H63: 0 | I63: 0.75 | J63: 0 | K63: 0.78 | L63: 0 | M63: 0 | N63: 0 | O63: 0.78 | P63: 0.78 | Q63: 0 | R63: 0.3 | S63: 0.09 | T63: 0 | U63: 0.39 | V63: 14.32 | W63: 0.13 | X63: 0 | Y63: 0 | Z63: 14.45 | AA63: 0 | AB63: 2.91
A64: 1 | C64: 금융손익 | E64: 396.33 | G64: 291.59 | H64: 127.28 | I64: 594.13 | J64: -565.59 | K64: 447.41 | L64: 252.45 | M64: -69.29 | N64: 205.17 | O64: 340.46 | P64: 728.79 | Q64: 433.18 | R64: -531.83 | S64: -15.58 | T64: 648.67 | U64: 534.44 | V64: 591.63 | W64: -22.99 | X64: 865.05 | Y64: 848.63 | Z64: 2282.32 | AA64: 2047.93 | AB64: 2824.66
A65: 1 | C65: 금융수익 | E65: 619.9 | G65: 422.25 | H65: 280.4 | I65: 768.95 | J65: -110.92 | K65: 1360.68 | L65: 494.41 | M65: 152.45 | N65: 470.51 | O65: 565.97 | P65: 1683.34 | Q65: 634.25 | R65: 32.2 | S65: 419.54 | T65: 972.3 | U65: 2058.29 | V65: 736.9 | W65: 145.79 | X65: 1022.57 | Y65: 1552.65 | Z65: 3457.91 | AA65: 3907.86 | AB65: 2929.37
A66: 1 | C66: 금융비용 | E66: 223.57 | G66: 130.66 | H66: 153.12 | I66: 174.82 | J66: 454.67 | K66: 913.27 | L66: 241.96 | M66: 221.74 | N66: 265.34 | O66: 225.5 | P66: 954.54 | Q66: 201.07 | R66: 564.03 | S66: 435.12 | T66: 323.63 | U66: 1523.85 | V66: 145.27 | W66: 168.78 | X66: 157.52 | Y66: 704.02 | Z66: 1175.59 | AA66: 1859.93 | AB66: 104.71
A67: 1 | C67: 법인세비용차감전계속사업이익 | E67: 1340.7 | G67: 200.8 | H67: 131.6 | I67: 3167.95 | J67: -1060.83 | K67: 2439.52 | L67: 257.84 | M67: 583.86 | N67: -195.63 | O67: 2416.6 | P67: 3062.67 | Q67: 544.73 | R67: -350.44 | S67: 1754.05 | T67: 1366.35 | U67: 3314.69 | V67: 754.63 | W67: 467.74 | X67: 1080.16 | Y67: 1139.7 | Z67: 3442.23 | AA67: 2691.64 | AB67: 4911.07
... A72: 1 | C72: 계속사업이익 | E72: 899.66 | G72: 171.93 | H72: 91.75 | I72: 2468.68 | J72: -655.21 | K72: 2077.15 | L72: 258.32 | M72: 474.94 | N72: -111.51 | O72: 2305.22 | P72: 2926.97 | Q72: 473 | R72: -157.78 | S72: 1395.4 | T72: 997.51 | U72: 2708.13 | V72: 588.27 | W72: 356.52 | X72: 815.77 | Y72: 1103.01 | Z72: 2863.57 | AA72: 2109.8 | AB72: 3888.19
A73: 1 | C73: 중단사업이익 | R73: 9819.26 | S73: 0 | T73: 0 | V73: 0 | W73: 0 | X73: 0 | Y73: 0 | Z73: 0
A74: 1 | C74: 영업활동으로인한현금흐름 | E74: 2321 | G74: -412.48 | H74: -1721.65 | I74: 663.91 | J74: 173.06 | K74: -1297.16 | L74: 3487.06 | M74: 1968.24 | N74: 2172 | O74: -225.58 | P74: 7401.72 | Q74: 1531.45 | R74: 99.58 | S74: 175.05 | T74: 3188.89 | U74: 4994.97 | V74: -1993.48 | W74: -566.69 | X74: 732.96 | Y74: -1156.94 | Z74: -2984.15 | AA74: 893.56 | AB74: 2185.69
A75: 1 | C75: 법인세납부(CF) | E75: 3.47 | G75: -223.48 | H75: -223.35 | I75: -190.36 | J75: -3.89 | K75: -641.08 | L75: -98.6 | M75: -137.38 | N75: -96.91 | O75: -109.66 | P75: -442.55 | Q75: -38.48 | R75: -66.68 | S75: -78.53 | T75: -94.28 | U75: -277.97 | V75: -1365.97 | W75: -1653.54 | X75: -158.62 | Y75: -5.86 | Z75: -3183.99 | AA75: -4.41 | AB75: -181.89
A76: 1 | C76: 투자활동으로인한현금흐름 | E76: -4084.14 | G76: -8356.46 | H76: -2005.49 | I76: -461.31 | J76: -121.99 | K76: -10945.25 | L76: 1.18 | M76: 10.15 | N76: 27.85 | O76: 535.66 | P76: 574.84 | Q76: -62.75 | R76: 12380.62 | S76: 108.33 | T76: 1673.19 | U76: 14099.39 | V76: -3.73 | W76: -870.07 | X76: -5954.62 | Y76: -4217.95 | Z76: -11046.37 | AA76: -4409.66 | AB76: -8327.72
A77: 1 | C77: 유형자산의증가 | E77: 88.58 | G77: 8979.09 | H77: 1440.99 | I77: 564.11 | J77: 96.54 | K77: 11080.73 | L77: 1.8 | M77: 36.57 | N77: 3.4 | O77: 5.37 | P77: 47.14 | Q77: 10.05 | R77: 0.9 | S77: 0 | T77: 9.81 | U77: 20.76 | V77: 1.5 | W77: 3.81 | X77: 2.32 | Y77: 0 | Z77: 7.63
A78: 1 | C78: CAPEX | E78: 138.08 | G78: 8979.09 | H78: 1446.49 | I78: 564.11 | J78: 125.29 | K78: 11114.98 | L78: 1.8 | M78: 36.57 | N78: 3.4 | O78: 5.37 | P78: 47.14 | Q78: 10.05 | R78: 0.9 | S78: 6.6 | T78: 9.81 | U78: 27.36 | V78: 1.5 | W78: 3.81 | X78: 2.32 | Y78: 0 | Z78: 7.63
A79: 1 | C79: 무형자산의증가 | E79: 49.5 | G79: 0 | H79: 5.5 | I79: 0 | J79: 28.75 | K79: 34.25 | L79: 0 | M79: 0 | N79: 0 | O79: 0 | P79: 0 | T79: 0 | Y79: 0
A80: 1 | C80: 재무활동으로인한현금흐름 | E80: 4429.12 | G80: 8184.3 | H80: -280.37 | I80: 502.48 | J80: -200.14 | K80: 8206.27 | L80: -8.92 | M80: -708.3 | N80: -8.51 | O80: -8.74 | P80: -734.47 | Q80: -217.37 | R80: -570.87 | S80: 1413.06 | T80: -99.08 | U80: 525.74 | V80: -7.87 | W80: 1995.35 | X80: 1495.46 | Y80: -4.19 | Z80: 3478.75 | AA80: -4.28 | AB80: -3.31
A81: 1 | C81: 리스부채의상환 | E81: 440.69 | G81: 186.92 | H81: 194.16 | I81: 197.52 | J81: 200.14 | K81: 778.74 | L81: 8.92 | M81: 8.3 | N81: 8.51 | O81: 8.74 | P81: 34.47 | Q81: 8.96 | R81: 8.22 | S81: 7.61 | T81: 7.56 | U81: 32.35 | V81: 7.87 | W81: 4.65 | X81: 4.54 | Y81: 4.19 | Z81: 21.25 | AA81: 4.28 | AB81: 3.31
A82: 1 | C82: 단기차입금의감소 | E82: 0 | G82: 0 | H82: 0 | I82: 0 | J82: 1200 | K82: 1200 | L82: 0 | M82: 700 | N82: 0 | O82: 0 | P82: 700 | S82: 0 | T82: 0 | AA82: 2000 | AB82: 0
A83: 1 | C83: 유동성장기부채의감소 | E83: 128.13 | G83: 128.78 | H83: 86.21 | I83: 0 | J83: 0 | K83: 214.99 | L83: 0 | M83: 1600 | N83: 0 | O83: 0 | P83: 1600 | S83: 0 | T83: 1896.04
A84: 1 | C84: 장기차입금의감소 | E84: 0 | G84: 0 | H84: 0 | I84: 0 | J84: 0 | K84: 0 | L84: 0 | M84: 0 | Q84: 208.41 | R84: 562.65 | S84: 4937.42 | T84: 5895.48 | U84: 11603.96 | V84: 0 | W84: 0 | X84: 0 | Y84: 0 | Z84: 0
A85: 1 | C85: 현금및현금성자산의증감 | E85: 2659.61 | G85: -588.76 | H85: -3984.35 | I85: 686.47 | J85: -157.62 | K85: -4044.26 | L85: 3535.35 | M85: 1218.95 | N85: 2287.49 | O85: 151.12 | P85: 7192.91 | Q85: 1265.84 | R85: 11894.81 | S85: 1682.98 | T85: 4775.1 | U85: 19618.73 | V85: -2002.29 | W85: 534.91 | X85: -3705.3 | Y85: -5379.09 | Z85: -10551.77 | AA85: -3520.38 | AB85: -6145.34
A86: 1 | C86: 기말현금및현금성자산 | E86: 2659.61 | G86: 5308.01 | H86: -3984.35 | I86: 686.47 | J86: -157.62 | K86: 1852.51 | L86: 5387.86 | M86: 1218.96 | N86: 2287.48 | O86: 151.13 | P86: 9045.43 | Q86: 10311.27 | R86: 11894.81 | S86: 1682.97 | T86: 4775.11 | U86: 28664.16 | V86: 26661.87 | W86: 534.91 | X86: -3705.3 | Y86: -5379.09 | Z86: 18112.39 | AA86: 14592.01 | AB86: -6145.34
A87: 1 | C87: 배당금수취(CF) | G87: 0 | H87: 0.51 | I87: 0 | J87: 0 | K87: 0.51 | L87: 0 | M87: 57.81 | N87: 0 | O87: 0 | P87: 57.81 | S87: 0 | T87: 0 | X87: 3.16 | Y87: 9.57
A88: 1 | C88: 유형자산의감소 | G88: 624.43 | H88: 0 | I88: 0 | J88: 1.75 | K88: 626.18 | L88: 0 | M88: 4 | N88: 0 | O88: 0 | P88: 4 | S88: 0 | T88: 1.79 | X88: 0 | Y88: 8.7 | AA88: 0 | AB88: 0
A89: 1 | C89: 단기차입금의증가 | G89: 0 | H89: 0 | I89: 700 | J89: 1200 | K89: 1900 | L89: 0 | M89: 1600 | N89: 0 | O89: 0 | P89: 1600 | S89: 0 | T89: 0 | X89: 0 | Y89: 0
A90: 1 | C90: 장기차입금의증가 | G90: 8500 | H90: 0 | I90: 0 | J90: 0 | K90: 8500 | L90: 0 | M90: 0 | N90: 0 | O90: 0 | P90: 0 | T90: 7700 | Y90: 0 | AA90: 2000 | AB90: 0
A91: 1 | C91: 이자수취(CF) | Q91: 351.33 | V91: 378.24 | W91: 71.48 | X91: 367.67 | Y91: 38.09 | Z91: 855.48 | AA91: 397.06 | AB91: 21.56
A92: 1 | C92: 자기주식의취득 | T92: 0 | Y92: 0

Sheet subQ
A1: YQ | C1: subQ 분기 서브모델(억원, U=100) | E1: 4Q21 | F1: 2021 | G1: 1Q22 | H1: 2Q22 | I1: 3Q22 | J1: 4Q22 | K1: 2022 | L1: 1Q23 | M1: 2Q23 | N1: 3Q23 | O1: 4Q23 | P1: 2023 | Q1: 1Q24 | R1: 2Q24 | S1: 3Q24 | T1: 4Q24 | U1: 2024 | V1: 1Q25 | W1: 2Q25 | X1: 3Q25 | Y1: 4Q25 | Z1: 2025 | AA1: 1Q26 | AB1: 2Q26 | AC1: 3Q26 | AD1: 4Q26 | AE1: 2026 | AF1: 1Q27 | AG1: 2Q27 | AH1: 3Q27 | AI1: 4Q27 | AJ1: 2027 | AK1: 1Q28 | AL1: 2Q28 | AM1: 3Q28 | AN1: 4Q28 | AO1: 2028
A2: A=이름(key) B=그룹 C=단위 D=FnGuide 계정명(VLOOKUP 키). 확정=VLOOKUP(BS), 추정=변수 가정 참조
E3: 1 | F3: 2 | G3: 3 | H3: 4 | I3: 5 | J3: 6 | K3: 7 | L3: 8 | M3: 9 | N3: 10 | O3: 11 | P3: 12 | Q3: 13 | R3: 14 | S3: 15 | T3: 16 | U3: 17 | V3: 18 | W3: 19 | X3: 20 | Y3: 21 | Z3: 22 | AA3: 23 | AB3: 24 | AC3: 25 | AD3: 26 | AE3: 27 | AF3: 28 | AG3: 29 | AH3: 30 | AI3: 31 | AJ3: 32 | AK3: 33 | AL3: 34 | AM3: 35 | AN3: 36 | AO3: 37
E4: 2021.12 | F4: 2021.12A | G4: 2022.03 | H4: 2022.06 | I4: 2022.09 | J4: 2022.12 | K4: 2022.12A | L4: 2023.03 | M4: 2023.06 | N4: 2023.09 | O4: 2023.12 | P4: 2023.12A | Q4: 2024.03 | R4: 2024.06 | S4: 2024.09 | T4: 2024.12 | U4: 2024.12A | V4: 2025.03 | W4: 2025.06 | X4: 2025.09 | Y4: 2025.12 | Z4: 2025.12A | AA4: 2026.03 | AB4: 2026.06 | AC4: 2026.09 | AD4: 2026.12 | AE4: 2026.12A | AF4: 2027.03 | AG4: 2027.06 | AH4: 2027.09 | AI4: 2027.12 | AJ4: 2027.12A | AK4: 2028.03 | AL4: 2028.06 | AM4: 2028.09 | AN4: 2028.12 | AO4: 2028.12A
A5: 매출액 | B5: 손익 | C5: 억원 | D5: 매출액(수익) | E5: =IFERROR(VLOOKUP($D5,BS연결,MATCH(E$1,BS연결H,0),0)/100,"") | G5: =IFERROR(VLOOKUP($D5,BS연결,MATCH(G$1,BS연결H,0),0)/100,"") | H5: =IFERROR(VLOOKUP($D5,BS연결,MATCH(H$1,BS연결H,0),0)/100,"") | I5: =IFERROR(VLOOKUP($D5,BS연결,MATCH(I$1,BS연결H,0),0)/100,"") | J5: =IFERROR(VLOOKUP($D5,BS연결,MATCH(J$1,BS연결H,0),0)/100,"") | K5: =IFERROR(VLOOKUP($D5,BS연결,MATCH(K$1,BS연결H,0),0)/100,"") | L5: =IFERROR(VLOOKUP($D5,BS연결,MATCH(L$1,BS연결H,0),0)/100,"") | M5: =IFERROR(VLOOKUP($D5,BS연결,MATCH(M$1,BS연결H,0),0)/100,"") | N5: =IFERROR(VLOOKUP($D5,BS연결,MATCH(N$1,BS연결H,0),0)/100,"") | ... Y5: =IFERROR(VLOOKUP($D5,BS연결,MATCH(Y$1,BS연결H,0),0)/100,"") | Z5: =SUM(V5:Y5) | AA5: =IFERROR(VLOOKUP($D5,BS연결,MATCH(AA$1,BS연결H,0),0)/100,"") | AB5: =IFERROR(VLOOKUP($D5,BS연결,MATCH(AB$1,BS연결H,0),0)/100,"") | AC5: =IFERROR(X5*(1+변수!AC21),"") | AD5: =IFERROR(Y5*(1+변수!AD21),"") | AE5: =SUM(AA5:AD5) | AF5: =IFERROR(AA5*(1+변수!AF21),"") | AG5: =IFERROR(AB5*(1+변수!AG21),"") | AH5: =IFERROR(AC5*(1+변수!AH21),"") | AI5: =IFERROR(AD5*(1+변수!AI21),"") | AJ5: =SUM(AF5:AI5) | AK5: =IFERROR(AF5*(1+변수!AK21),"") | AL5: =IFERROR(AG5*(1+변수!AL21),"") | AM5: =IFERROR(AH5*(1+변수!AM21),"") | AN5: =IFERROR(AI5*(1+변수!AN21),"") | AO5: =SUM(AK5:AN5)
A6: 매출원가 | B6: 손익 | C6: 억원 | D6: 매출원가 | E6: =IFERROR(VLOOKUP($D6,BS연결,MATCH(E$1,BS연결H,0),0)/100,"") | G6: =IFERROR(VLOOKUP($D6,BS연결,MATCH(G$1,BS연결H,0),0)/100,"") | H6: =IFERROR(VLOOKUP($D6,BS연결,MATCH(H$1,BS연결H,0),0)/100,"") | I6: =IFERROR(VLOOKUP($D6,BS연결,MATCH(I$1,BS연결H,0),0)/100,"") | J6: =IFERROR(VLOOKUP($D6,BS연결,MATCH(J$1,BS연결H,0),0)/100,"") | K6: =IFERROR(VLOOKUP($D6,BS연결,MATCH(K$1,BS연결H,0),0)/100,"") | L6: =IFERROR(VLOOKUP($D6,BS연결,MATCH(L$1,BS연결H,0),0)/100,"") | M6: =IFERROR(VLOOKUP($D6,BS연결,MATCH(M$1,BS연결H,0),0)/100,"") | N6: =IFERROR(VLOOKUP($D6,BS연결,MATCH(N$1,BS연결H,0),0)/100,"") | ... AB6: =IFERROR(VLOOKUP($D6,BS연결,MATCH(AB$1,BS연결H,0),0)/100,"") | AC6: =IFERROR(AC5-AC7,"") | AD6: =IFERROR(AD5-AD7,"") | AE6: =SUM(AA6:AD6) | AF6: =IFERROR(AF5-AF7,"") | AG6: =IFERROR(AG5-AG7,"") | AH6: =IFERROR(AH5-AH7,"") | AI6: =IFERROR(AI5-AI7,"") | AJ6: =SUM(AF6:AI6) | AK6: =IFERROR(AK5-AK7,"") | AL6: =IFERROR(AL5-AL7,"") | AM6: =IFERROR(AM5-AM7,"") | AN6: =IFERROR(AN5-AN7,"") | AO6: =SUM(AK6:AN6)
A7: 매출총이익 | B7: 손익 | C7: 억원 | D7: 매출총이익 | E7: =IFERROR(VLOOKUP($D7,BS연결,MATCH(E$1,BS연결H,0),0)/100,"") | G7: =IFERROR(VLOOKUP($D7,BS연결,MATCH(G$1,BS연결H,0),0)/100,"") | H7: =IFERROR(VLOOKUP($D7,BS연결,MATCH(H$1,BS연결H,0),0)/100,"") | I7: =IFERROR(VLOOKUP($D7,BS연결,MATCH(I$1,BS연결H,0),0)/100,"") | J7: =IFERROR(VLOOKUP($D7,BS연결,MATCH(J$1,BS연결H,0),0)/100,"") | K7: =IFERROR(VLOOKUP($D7,BS연결,MATCH(K$1,BS연결H,0),0)/100,"") | L7: =IFERROR(VLOOKUP($D7,BS연결,MATCH(L$1,BS연결H,0),0)/100,"") | M7: =IFERROR(VLOOKUP($D7,BS연결,MATCH(M$1,BS연결H,0),0)/100,"") | N7: =IFERROR(VLOOKUP($D7,BS연결,MATCH(N$1,BS연결H,0),0)/100,"") | O7: =IFERROR(VLOOKUP($D7,BS연결,MATCH(O$1,BS연결H,0),0)/100,"") | P7: =SUM(L7:O7) | Q7: =IFERROR(VLOOKUP($D7,BS연결,MATCH(Q$1,BS연결H,0),0)/100,"") | R7: =IFERROR(VLOOKUP($D7,BS연결,MATCH(R$1,BS연결H,0),0)/100,"") | S7: =IFERROR(VLOOKUP($D7,BS연결,MATCH(S$1,BS연결H,0),0)/100,"") | T7: =IFERROR(VLOOKUP($D7,BS연결,MATCH(T$1,BS연결H,0),0)/100,"") | U7: =IFERROR(VLOOKUP($D7,BS연결,MATCH(U$1,BS연결H,0),0)/100,"") | V7: =IFERROR(VLOOKUP($D7,BS연결,MATCH(V$1,BS연결H,0),0)/100,"") | W7: =IFERROR(VLOOKUP($D7,BS연결,MATCH(W$1,BS연결H,0),0)/100,"") | X7: =IFERROR(VLOOKUP($D7,BS연결,MATCH(X$1,BS연결H,0),0)/100,"") | ... AB7: =IFERROR(VLOOKUP($D7,BS연결,MATCH(AB$1,BS연결H,0),0)/100,"") | AC7: =IFERROR(AC9+AC8,"") | AD7: =IFERROR(AD9+AD8,"") | AE7: =SUM(AA7:AD7) | AF7: =IFERROR(AF9+AF8,"") | AG7: =IFERROR(AG9+AG8,"") | AH7: =IFERROR(AH9+AH8,"") | AI7: =IFERROR(AI9+AI8,"") | AJ7: =SUM(AF7:AI7) | AK7: =IFERROR(AK9+AK8,"") | AL7: =IFERROR(AL9+AL8,"") | AM7: =IFERROR(AM9+AM8,"") | AN7: =IFERROR(AN9+AN8,"") | AO7: =SUM(AK7:AN7)
A8: 판관비 | B8: 손익 | C8: 억원 | D8: 판관비 | E8: =IFERROR(VLOOKUP($D8,BS연결,MATCH(E$1,BS연결H,0),0)/100,"") | G8: =IFERROR(VLOOKUP($D8,BS연결,MATCH(G$1,BS연결H,0),0)/100,"") | H8: =IFERROR(VLOOKUP($D8,BS연결,MATCH(H$1,BS연결H,0),0)/100,"") | I8: =IFERROR(VLOOKUP($D8,BS연결,MATCH(I$1,BS연결H,0),0)/100,"") | J8: =IFERROR(VLOOKUP($D8,BS연결,MATCH(J$1,BS연결H,0),0)/100,"") | K8: =IFERROR(VLOOKUP($D8,BS연결,MATCH(K$1,BS연결H,0),0)/100,"") | L8: =IFERROR(VLOOKUP($D8,BS연결,MATCH(L$1,BS연결H,0),0)/100,"") | M8: =IFERROR(VLOOKUP($D8,BS연결,MATCH(M$1,BS연결H,0),0)/100,"") | N8: =IFERROR(VLOOKUP($D8,BS연결,MATCH(N$1,BS연결H,0),0)/100,"") | ... AB8: =IFERROR(VLOOKUP($D8,BS연결,MATCH(AB$1,BS연결H,0),0)/100,"") | AC8: =IFERROR(AC5*변수!AC22,"") | AD8: =IFERROR(AD5*변수!AD22,"") | AE8: =SUM(AA8:AD8) | AF8: =IFERROR(AF5*변수!AF22,"") | AG8: =IFERROR(AG5*변수!AG22,"") | AH8: =IFERROR(AH5*변수!AH22,"") | AI8: =IFERROR(AI5*변수!AI22,"") | AJ8: =SUM(AF8:AI8) | AK8: =IFERROR(AK5*변수!AK22,"") | AL8: =IFERROR(AL5*변수!AL22,"") | AM8: =IFERROR(AM5*변수!AM22,"") | AN8: =IFERROR(AN5*변수!AN22,"") | AO8: =SUM(AK8:AN8)
A9: 영업이익 | B9: 손익 | C9: 억원 | D9: 영업이익 | E9: =IFERROR(VLOOKUP($D9,BS연결,MATCH(E$1,BS연결H,0),0)/100,"") | G9: =IFERROR(VLOOKUP($D9,BS연결,MATCH(G$1,BS연결H,0),0)/100,"") | H9: =IFERROR(VLOOKUP($D9,BS연결,MATCH(H$1,BS연결H,0),0)/100,"") | I9: =IFERROR(VLOOKUP($D9,BS연결,MATCH(I$1,BS연결H,0),0)/100,"") | J9: =IFERROR(VLOOKUP($D9,BS연결,MATCH(J$1,BS연결H,0),0)/100,"") | K9: =IFERROR(VLOOKUP($D9,BS연결,MATCH(K$1,BS연결H,0),0)/100,"") | L9: =IFERROR(VLOOKUP($D9,BS연결,MATCH(L$1,BS연결H,0),0)/100,"") | M9: =IFERROR(VLOOKUP($D9,BS연결,MATCH(M$1,BS연결H,0),0)/100,"") | N9: =IFERROR(VLOOKUP($D9,BS연결,MATCH(N$1,BS연결H,0),0)/100,"") | ... AB9: =IFERROR(VLOOKUP($D9,BS연결,MATCH(AB$1,BS연결H,0),0)/100,"") | AC9: =IFERROR(AC5*변수!AC23,"") | AD9: =IFERROR(AD5*변수!AD23,"") | AE9: =SUM(AA9:AD9) | AF9: =IFERROR(AF5*변수!AF23,"") | AG9: =IFERROR(AG5*변수!AG23,"") | AH9: =IFERROR(AH5*변수!AH23,"") | AI9: =IFERROR(AI5*변수!AI23,"") | AJ9: =SUM(AF9:AI9) | AK9: =IFERROR(AK5*변수!AK23,"") | AL9: =IFERROR(AL5*변수!AL23,"") | AM9: =IFERROR(AM5*변수!AM23,"") | AN9: =IFERROR(AN5*변수!AN23,"") | AO9: =SUM(AK9:AN9)
A10: OPM | B10: 손익 | C10: % | D10: 영업이익률 | E10: =IFERROR(E9/E5,"") | G10: =IFERROR(G9/G5,"") | H10: =IFERROR(H9/H5,"") | I10: =IFERROR(I9/I5,"") | J10: =IFERROR(J9/J5,"") | K10: =IFERROR(K9/K5,"") | L10: =IFERROR(L9/L5,"") | M10: =IFERROR(M9/M5,"") | N10: =IFERROR(N9/N5,"") | ... AO10: =IFERROR(AO9/AO5,"")
A11: 금융손익 | B11: 손익 | C11: 억원 | D11: 금융손익 | E11: =IFERROR(VLOOKUP($D11,BS연결,MATCH(E$1,BS연결H,0),0)/100,"") | G11: =IFERROR(VLOOKUP($D11,BS연결,MATCH(G$1,BS연결H,0),0)/100,"") | H11: =IFERROR(VLOOKUP($D11,BS연결,MATCH(H$1,BS연결H,0),0)/100,"") | I11: =IFERROR(VLOOKUP($D11,BS연결,MATCH(I$1,BS연결H,0),0)/100,"") | J11: =IFERROR(VLOOKUP($D11,BS연결,MATCH(J$1,BS연결H,0),0)/100,"") | K11: =IFERROR(VLOOKUP($D11,BS연결,MATCH(K$1,BS연결H,0),0)/100,"") | L11: =IFERROR(VLOOKUP($D11,BS연결,MATCH(L$1,BS연결H,0),0)/100,"") | M11: =IFERROR(VLOOKUP($D11,BS연결,MATCH(M$1,BS연결H,0),0)/100,"") | N11: =IFERROR(VLOOKUP($D11,BS연결,MATCH(N$1,BS연결H,0),0)/100,"") | ... AB11: =IFERROR(VLOOKUP($D11,BS연결,MATCH(AB$1,BS연결H,0),0)/100,"") | AC11: =IFERROR(AC12+AC13,"") | AD11: =IFERROR(AD12+AD13,"") | AE11: =SUM(AA11:AD11) | AF11: =IFERROR(AF12+AF13,"") | AG11: =IFERROR(AG12+AG13,"") | AH11: =IFERROR(AH12+AH13,"") | AI11: =IFERROR(AI12+AI13,"") | AJ11: =SUM(AF11:AI11) | AK11: =IFERROR(AK12+AK13,"") | AL11: =IFERROR(AL12+AL13,"") | AM11: =IFERROR(AM12+AM13,"") | AN11: =IFERROR(AN12+AN13,"") | AO11: =SUM(AK11:AN11)
A12: 이자손익 | B12: 손익 | C12: 억원 | D12: 이자손익 | E12: =IFERROR(VLOOKUP($D12,BS연결,MATCH(E$1,BS연결H,0),0)/100,"") | G12: =IFERROR(VLOOKUP($D12,BS연결,MATCH(G$1,BS연결H,0),0)/100,"") | H12: =IFERROR(VLOOKUP($D12,BS연결,MATCH(H$1,BS연결H,0),0)/100,"") | I12: =IFERROR(VLOOKUP($D12,BS연결,MATCH(I$1,BS연결H,0),0)/100,"") | J12: =IFERROR(VLOOKUP($D12,BS연결,MATCH(J$1,BS연결H,0),0)/100,"") | K12: =IFERROR(VLOOKUP($D12,BS연결,MATCH(K$1,BS연결H,0),0)/100,"") | L12: =IFERROR(VLOOKUP($D12,BS연결,MATCH(L$1,BS연결H,0),0)/100,"") | M12: =IFERROR(VLOOKUP($D12,BS연결,MATCH(M$1,BS연결H,0),0)/100,"") | N12: =IFERROR(VLOOKUP($D12,BS연결,MATCH(N$1,BS연결H,0),0)/100,"") | O12: =IFERROR(VLOOKUP($D12,BS연결,MATCH(O$1,BS연결H,0),0)/100,"") | P12: =SUM(L12:O12) | Q12: =IFERROR(VLOOKUP($D12,BS연결,MATCH(Q$1,BS연결H,0),0)/100,"") | R12: =IFERROR(VLOOKUP($D12,BS연결,MATCH(R$1,BS연결H,0),0)/100,"") | S12: =IFERROR(VLOOKUP($D12,BS연결,MATCH(S$1,BS연결H,0),0)/100,"") | T12: =IFERROR(VLOOKUP($D12,BS연결,MATCH(T$1,BS연결H,0),0)/100,"") | U12: =IFERROR(VLOOKUP($D12,BS연결,MATCH(U$1,BS연결H,0),0)/100,"") | V12: =IFERROR(VLOOKUP($D12,BS연결,MATCH(V$1,BS연결H,0),0)/100,"") | W12: =IFERROR(VLOOKUP($D12,BS연결,MATCH(W$1,BS연결H,0),0)/100,"") | X12: =IFERROR(VLOOKUP($D12,BS연결,MATCH(X$1,BS연결H,0),0)/100,"") | ... AB12: =IFERROR(VLOOKUP($D12,BS연결,MATCH(AB$1,BS연결H,0),0)/100,"") | AC12: =IFERROR((AB25*변수!$D$51-AB23*변수!$D$52)/4,"") | AD12: =IFERROR((AC25*변수!$D$51-AC23*변수!$D$52)/4,"") | AE12: =SUM(AA12:AD12) | AF12: =IFERROR((AD25*변수!$D$51-AD23*변수!$D$52)/4,"") | AG12: =IFERROR((AF25*변수!$D$51-AF23*변수!$D$52)/4,"") | AH12: =IFERROR((AG25*변수!$D$51-AG23*변수!$D$52)/4,"") | AI12: =IFERROR((AH25*변수!$D$51-AH23*변수!$D$52)/4,"") | AJ12: =SUM(AF12:AI12) | AK12: =IFERROR((AI25*변수!$D$51-AI23*변수!$D$52)/4,"") | AL12: =IFERROR((AK25*변수!$D$51-AK23*변수!$D$52)/4,"") | AM12: =IFERROR((AL25*변수!$D$51-AL23*변수!$D$52)/4,"") | AN12: =IFERROR((AM25*변수!$D$51-AM23*변수!$D$52)/4,"") | AO12: =SUM(AK12:AN12)
A13: 외환손익 | B13: 손익 | C13: 억원 | D13: 외환손익(실적만; 추정 환효과는 환관련손익) | E13: =IFERROR((VLOOKUP("외환차익",BS연결,MATCH(E$1,BS연결H,0),0)-VLOOKUP("외환차손",BS연결,MATCH(E$1,BS연결H,0),0)+VLOOKUP("외화환산이익",BS연결,MATCH(E$1,BS연결H,0),0)-VLOOKUP("외화환산손실",BS연결,MATCH(E$1,BS연결H,0),0))/100,"") | G13: =IFERROR((VLOOKUP("외환차익",BS연결,MATCH(G$1,BS연결H,0),0)-VLOOKUP("외환차손",BS연결,MATCH(G$1,BS연결H,0),0)+VLOOKUP("외화환산이익",BS연결,MATCH(G$1,BS연결H,0),0)-VLOOKUP("외화환산손실",BS연결,MATCH(G$1,BS연결H,0),0))/100,"") | H13: =IFERROR((VLOOKUP("외환차익",BS연결,MATCH(H$1,BS연결H,0),0)-VLOOKUP("외환차손",BS연결,MATCH(H$1,BS연결H,0),0)+VLOOKUP("외화환산이익",BS연결,MATCH(H$1,BS연결H,0),0)-VLOOKUP("외화환산손실",BS연결,MATCH(H$1,BS연결H,0),0))/100,"") | I13: =IFERROR((VLOOKUP("외환차익",BS연결,MATCH(I$1,BS연결H,0),0)-VLOOKUP("외환차손",BS연결,MATCH(I$1,BS연결H,0),0)+VLOOKUP("외화환산이익",BS연결,MATCH(I$1,BS연결H,0),0)-VLOOKUP("외화환산손실",BS연결,MATCH(I$1,BS연결H,0),0))/100,"") | J13: =IFERROR((VLOOKUP("외환차익",BS연결,MATCH(J$1,BS연결H,0),0)-VLOOKUP("외환차손",BS연결,MATCH(J$1,BS연결H,0),0)+VLOOKUP("외화환산이익",BS연결,MATCH(J$1,BS연결H,0),0)-VLOOKUP("외화환산손실",BS연결,MATCH(J$1,BS연결H,0),0))/100,"") | K13: =SUM(G13:J13) | L13: =IFERROR((VLOOKUP("외환차익",BS연결,MATCH(L$1,BS연결H,0),0)-VLOOKUP("외환차손",BS연결,MATCH(L$1,BS연결H,0),0)+VLOOKUP("외화환산이익",BS연결,MATCH(L$1,BS연결H,0),0)-VLOOKUP("외화환산손실",BS연결,MATCH(L$1,BS연결H,0),0))/100,"") | M13: =IFERROR((VLOOKUP("외환차익",BS연결,MATCH(M$1,BS연결H,0),0)-VLOOKUP("외환차손",BS연결,MATCH(M$1,BS연결H,0),0)+VLOOKUP("외화환산이익",BS연결,MATCH(M$1,BS연결H,0),0)-VLOOKUP("외화환산손실",BS연결,MATCH(M$1,BS연결H,0),0))/100,"") | N13: =IFERROR((VLOOKUP("외환차익",BS연결,MATCH(N$1,BS연결H,0),0)-VLOOKUP("외환차손",BS연결,MATCH(N$1,BS연결H,0),0)+VLOOKUP("외화환산이익",BS연결,MATCH(N$1,BS연결H,0),0)-VLOOKUP("외화환산손실",BS연결,MATCH(N$1,BS연결H,0),0))/100,"") | O13: =IFERROR((VLOOKUP("외환차익",BS연결,MATCH(O$1,BS연결H,0),0)-VLOOKUP("외환차손",BS연결,MATCH(O$1,BS연결H,0),0)+VLOOKUP("외화환산이익",BS연결,MATCH(O$1,BS연결H,0),0)-VLOOKUP("외화환산손실",BS연결,MATCH(O$1,BS연결H,0),0))/100,"") | P13: =SUM(L13:O13) | Q13: =IFERROR((VLOOKUP("외환차익",BS연결,MATCH(Q$1,BS연결H,0),0)-VLOOKUP("외환차손",BS연결,MATCH(Q$1,BS연결H,0),0)+VLOOKUP("외화환산이익",BS연결,MATCH(Q$1,BS연결H,0),0)-VLOOKUP("외화환산손실",BS연결,MATCH(Q$1,BS연결H,0),0))/100,"") | R13: =IFERROR((VLOOKUP("외환차익",BS연결,MATCH(R$1,BS연결H,0),0)-VLOOKUP("외환차손",BS연결,MATCH(R$1,BS연결H,0),0)+VLOOKUP("외화환산이익",BS연결,MATCH(R$1,BS연결H,0),0)-VLOOKUP("외화환산손실",BS연결,MATCH(R$1,BS연결H,0),0))/100,"") | S13: =IFERROR((VLOOKUP("외환차익",BS연결,MATCH(S$1,BS연결H,0),0)-VLOOKUP("외환차손",BS연결,MATCH(S$1,BS연결H,0),0)+VLOOKUP("외화환산이익",BS연결,MATCH(S$1,BS연결H,0),0)-VLOOKUP("외화환산손실",BS연결,MATCH(S$1,BS연결H,0),0))/100,"") | T13: =IFERROR((VLOOKUP("외환차익",BS연결,MATCH(T$1,BS연결H,0),0)-VLOOKUP("외환차손",BS연결,MATCH(T$1,BS연결H,0),0)+VLOOKUP("외화환산이익",BS연결,MATCH(T$1,BS연결H,0),0)-VLOOKUP("외화환산손실",BS연결,MATCH(T$1,BS연결H,0),0))/100,"") | U13: =SUM(Q13:T13) | V13: =IFERROR((VLOOKUP("외환차익",BS연결,MATCH(V$1,BS연결H,0),0)-VLOOKUP("외환차손",BS연결,MATCH(V$1,BS연결H,0),0)+VLOOKUP("외화환산이익",BS연결,MATCH(V$1,BS연결H,0),0)-VLOOKUP("외화환산손실",BS연결,MATCH(V$1,BS연결H,0),0))/100,"") | W13: =IFERROR((VLOOKUP("외환차익",BS연결,MATCH(W$1,BS연결H,0),0)-VLOOKUP("외환차손",BS연결,MATCH(W$1,BS연결H,0),0)+VLOOKUP("외화환산이익",BS연결,MATCH(W$1,BS연결H,0),0)-VLOOKUP("외화환산손실",BS연결,MATCH(W$1,BS연결H,0),0))/100,"") | X13: =IFERROR((VLOOKUP("외환차익",BS연결,MATCH(X$1,BS연결H,0),0)-VLOOKUP("외환차손",BS연결,MATCH(X$1,BS연결H,0),0)+VLOOKUP("외화환산이익",BS연결,MATCH(X$1,BS연결H,0),0)-VLOOKUP("외화환산손실",BS연결,MATCH(X$1,BS연결H,0),0))/100,"") | Y13: =IFERROR((VLOOKUP("외환차익",BS연결,MATCH(Y$1,BS연결H,0),0)-VLOOKUP("외환차손",BS연결,MATCH(Y$1,BS연결H,0),0)+VLOOKUP("외화환산이익",BS연결,MATCH(Y$1,BS연결H,0),0)-VLOOKUP("외화환산손실",BS연결,MATCH(Y$1,BS연결H,0),0))/100,"") | Z13: =SUM(V13:Y13) | AA13: =IFERROR((VLOOKUP("외환차익",BS연결,MATCH(AA$1,BS연결H,0),0)-VLOOKUP("외환차손",BS연결,MATCH(AA$1,BS연결H,0),0)+VLOOKUP("외화환산이익",BS연결,MATCH(AA$1,BS연결H,0),0)-VLOOKUP("외화환산손실",BS연결,MATCH(AA$1,BS연결H,0),0))/100,"") | AB13: =IFERROR((VLOOKUP("외환차익",BS연결,MATCH(AB$1,BS연결H,0),0)-VLOOKUP("외환차손",BS연결,MATCH(AB$1,BS연결H,0),0)+VLOOKUP("외화환산이익",BS연결,MATCH(AB$1,BS연결H,0),0)-VLOOKUP("외화환산손실",BS연결,MATCH(AB$1,BS연결H,0),0))/100,"") | AC13: =변수!AC24 | AD13: =변수!AD24 | AE13: =SUM(AA13:AD13) | AF13: =변수!AF24 | AG13: =변수!AG24 | AH13: =변수!AH24 | AI13: =변수!AI24 | AJ13: =SUM(AF13:AI13) | AK13: =변수!AK24 | AL13: =변수!AL24 | AM13: =변수!AM24 | AN13: =변수!AN24 | AO13: =SUM(AK13:AN13)
A14: 기타영업외손익 | B14: 손익 | C14: 억원 | D14: 기타영업외손익 | E14: =IFERROR(VLOOKUP($D14,BS연결,MATCH(E$1,BS연결H,0),0)/100,"") | G14: =IFERROR(VLOOKUP($D14,BS연결,MATCH(G$1,BS연결H,0),0)/100,"") | H14: =IFERROR(VLOOKUP($D14,BS연결,MATCH(H$1,BS연결H,0),0)/100,"") | I14: =IFERROR(VLOOKUP($D14,BS연결,MATCH(I$1,BS연결H,0),0)/100,"") | J14: =IFERROR(VLOOKUP($D14,BS연결,MATCH(J$1,BS연결H,0),0)/100,"") | K14: =IFERROR(VLOOKUP($D14,BS연결,MATCH(K$1,BS연결H,0),0)/100,"") | L14: =IFERROR(VLOOKUP($D14,BS연결,MATCH(L$1,BS연결H,0),0)/100,"") | M14: =IFERROR(VLOOKUP($D14,BS연결,MATCH(M$1,BS연결H,0),0)/100,"") | N14: =IFERROR(VLOOKUP($D14,BS연결,MATCH(N$1,BS연결H,0),0)/100,"") | ... T14: =IFERROR(VLOOKUP($D14,BS연결,MATCH(T$1,BS연결H,0),0)/100,"") | U14: =SUM(Q14:T14) | V14: =IFERROR(VLOOKUP($D14,BS연결,MATCH(V$1,BS연결H,0),0)/100,"") | W14: =IFERROR(VLOOKUP($D14,BS연결,MATCH(W$1,BS연결H,0),0)/100,"") | X14: =IFERROR(VLOOKUP($D14,BS연결,MATCH(X$1,BS연결H,0),0)/100,"") | Y14: =IFERROR(VLOOKUP($D14,BS연결,MATCH(Y$1,BS연결H,0),0)/100,"") | Z14: =IFERROR(VLOOKUP($D14,BS연결,MATCH(Z$1,BS연결H,0),0)/100,"") | AA14: =IFERROR(VLOOKUP($D14,BS연결,MATCH(AA$1,BS연결H,0),0)/100,"") | AB14: =IFERROR(VLOOKUP($D14,BS연결,MATCH(AB$1,BS연결H,0),0)/100,"") | AC14: =변수!AC25 | AD14: =변수!AD25 | AE14: =SUM(AA14:AD14) | AF14: =변수!AF25 | AG14: =변수!AG25 | AH14: =변수!AH25 | AI14: =변수!AI25 | AJ14: =SUM(AF14:AI14) | AK14: =변수!AK25 | AL14: =변수!AL25 | AM14: =변수!AM25 | AN14: =변수!AN25 | AO14: =SUM(AK14:AN14)
A15: 세전이익 | B15: 손익 | C15: 억원 | D15: 법인세비용차감전계속사업이익 | E15: =IFERROR(VLOOKUP($D15,BS연결,MATCH(E$1,BS연결H,0),0)/100,"") | G15: =IFERROR(VLOOKUP($D15,BS연결,MATCH(G$1,BS연결H,0),0)/100,"") | H15: =IFERROR(VLOOKUP($D15,BS연결,MATCH(H$1,BS연결H,0),0)/100,"") | I15: =IFERROR(VLOOKUP($D15,BS연결,MATCH(I$1,BS연결H,0),0)/100,"") | J15: =IFERROR(VLOOKUP($D15,BS연결,MATCH(J$1,BS연결H,0),0)/100,"") | K15: =IFERROR(VLOOKUP($D15,BS연결,MATCH(K$1,BS연결H,0),0)/100,"") | L15: =IFERROR(VLOOKUP($D15,BS연결,MATCH(L$1,BS연결H,0),0)/100,"") | M15: =IFERROR(VLOOKUP($D15,BS연결,MATCH(M$1,BS연결H,0),0)/100,"") | N15: =IFERROR(VLOOKUP($D15,BS연결,MATCH(N$1,BS연결H,0),0)/100,"") | ... AB15: =IFERROR(VLOOKUP($D15,BS연결,MATCH(AB$1,BS연결H,0),0)/100,"") | AC15: =IFERROR(AC9+AC11+AC14,"") | AD15: =IFERROR(AD9+AD11+AD14,"") | AE15: =SUM(AA15:AD15) | AF15: =IFERROR(AF9+AF11+AF14,"") | AG15: =IFERROR(AG9+AG11+AG14,"") | AH15: =IFERROR(AH9+AH11+AH14,"") | AI15: =IFERROR(AI9+AI11+AI14,"") | AJ15: =SUM(AF15:AI15) | AK15: =IFERROR(AK9+AK11+AK14,"") | AL15: =IFERROR(AL9+AL11+AL14,"") | AM15: =IFERROR(AM9+AM11+AM14,"") | AN15: =IFERROR(AN9+AN11+AN14,"") | AO15: =SUM(AK15:AN15)
A16: 법인세비용 | B16: 손익 | C16: 억원 | D16: 법인세비용 | E16: =IFERROR(VLOOKUP($D16,BS연결,MATCH(E$1,BS연결H,0),0)/100,"") | G16: =IFERROR(VLOOKUP($D16,BS연결,MATCH(G$1,BS연결H,0),0)/100,"") | H16: =IFERROR(VLOOKUP($D16,BS연결,MATCH(H$1,BS연결H,0),0)/100,"") | I16: =IFERROR(VLOOKUP($D16,BS연결,MATCH(I$1,BS연결H,0),0)/100,"") | J16: =IFERROR(VLOOKUP($D16,BS연결,MATCH(J$1,BS연결H,0),0)/100,"") | K16: =IFERROR(VLOOKUP($D16,BS연결,MATCH(K$1,BS연결H,0),0)/100,"") | L16: =IFERROR(VLOOKUP($D16,BS연결,MATCH(L$1,BS연결H,0),0)/100,"") | M16: =IFERROR(VLOOKUP($D16,BS연결,MATCH(M$1,BS연결H,0),0)/100,"") | N16: =IFERROR(VLOOKUP($D16,BS연결,MATCH(N$1,BS연결H,0),0)/100,"") | ... AB16: =IFERROR(VLOOKUP($D16,BS연결,MATCH(AB$1,BS연결H,0),0)/100,"") | AC16: =IFERROR(MAX(AC15,0)*변수!AC26,"") | AD16: =IFERROR(MAX(AD15,0)*변수!AD26,"") | AE16: =SUM(AA16:AD16) | AF16: =IFERROR(MAX(AF15,0)*변수!AF26,"") | AG16: =IFERROR(MAX(AG15,0)*변수!AG26,"") | AH16: =IFERROR(MAX(AH15,0)*변수!AH26,"") | AI16: =IFERROR(MAX(AI15,0)*변수!AI26,"") | AJ16: =SUM(AF16:AI16) | AK16: =IFERROR(MAX(AK15,0)*변수!AK26,"") | AL16: =IFERROR(MAX(AL15,0)*변수!AL26,"") | AM16: =IFERROR(MAX(AM15,0)*변수!AM26,"") | AN16: =IFERROR(MAX(AN15,0)*변수!AN26,"") | AO16: =SUM(AK16:AN16)
A17: 당기순이익 | B17: 손익 | C17: 억원 | D17: 당기순이익 | E17: =IFERROR(VLOOKUP($D17,BS연결,MATCH(E$1,BS연결H,0),0)/100,"") | G17: =IFERROR(VLOOKUP($D17,BS연결,MATCH(G$1,BS연결H,0),0)/100,"") | H17: =IFERROR(VLOOKUP($D17,BS연결,MATCH(H$1,BS연결H,0),0)/100,"") | I17: =IFERROR(VLOOKUP($D17,BS연결,MATCH(I$1,BS연결H,0),0)/100,"") | J17: =IFERROR(VLOOKUP($D17,BS연결,MATCH(J$1,BS연결H,0),0)/100,"") | K17: =IFERROR(VLOOKUP($D17,BS연결,MATCH(K$1,BS연결H,0),0)/100,"") | L17: =IFERROR(VLOOKUP($D17,BS연결,MATCH(L$1,BS연결H,0),0)/100,"") | M17: =IFERROR(VLOOKUP($D17,BS연결,MATCH(M$1,BS연결H,0),0)/100,"") | N17: =IFERROR(VLOOKUP($D17,BS연결,MATCH(N$1,BS연결H,0),0)/100,"") | ... AB17: =IFERROR(VLOOKUP($D17,BS연결,MATCH(AB$1,BS연결H,0),0)/100,"") | AC17: =IFERROR(AC15-AC16,"") | AD17: =IFERROR(AD15-AD16,"") | AE17: =SUM(AA17:AD17) | AF17: =IFERROR(AF15-AF16,"") | AG17: =IFERROR(AG15-AG16,"") | AH17: =IFERROR(AH15-AH16,"") | AI17: =IFERROR(AI15-AI16,"") | AJ17: =SUM(AF17:AI17) | AK17: =IFERROR(AK15-AK16,"") | AL17: =IFERROR(AL15-AL16,"") | AM17: =IFERROR(AM15-AM16,"") | AN17: =IFERROR(AN15-AN16,"") | AO17: =SUM(AK17:AN17)
A18: 지배주주순이익 | B18: 손익 | C18: 억원 | D18: (지배주주지분)당기순이익 | E18: =IFERROR(VLOOKUP($D18,BS연결,MATCH(E$1,BS연결H,0),0)/100,"") | G18: =IFERROR(VLOOKUP($D18,BS연결,MATCH(G$1,BS연결H,0),0)/100,"") | H18: =IFERROR(VLOOKUP($D18,BS연결,MATCH(H$1,BS연결H,0),0)/100,"") | I18: =IFERROR(VLOOKUP($D18,BS연결,MATCH(I$1,BS연결H,0),0)/100,"") | J18: =IFERROR(VLOOKUP($D18,BS연결,MATCH(J$1,BS연결H,0),0)/100,"") | K18: =SUM(G18:J18) | L18: =IFERROR(VLOOKUP($D18,BS연결,MATCH(L$1,BS연결H,0),0)/100,"") | M18: =IFERROR(VLOOKUP($D18,BS연결,MATCH(M$1,BS연결H,0),0)/100,"") | N18: =IFERROR(VLOOKUP($D18,BS연결,MATCH(N$1,BS연결H,0),0)/100,"") | O18: =IFERROR(VLOOKUP($D18,BS연결,MATCH(O$1,BS연결H,0),0)/100,"") | P18: =IFERROR(VLOOKUP($D18,BS연결,MATCH(P$1,BS연결H,0),0)/100,"") | Q18: =IFERROR(VLOOKUP($D18,BS연결,MATCH(Q$1,BS연결H,0),0)/100,"") | R18: =IFERROR(VLOOKUP($D18,BS연결,MATCH(R$1,BS연결H,0),0)/100,"") | S18: =IFERROR(VLOOKUP($D18,BS연결,MATCH(S$1,BS연결H,0),0)/100,"") | ... AB18: =IFERROR(VLOOKUP($D18,BS연결,MATCH(AB$1,BS연결H,0),0)/100,"") | AC18: =IFERROR(AC17*변수!AC27,"") | AD18: =IFERROR(AD17*변수!AD27,"") | AE18: =SUM(AA18:AD18) | AF18: =IFERROR(AF17*변수!AF27,"") | AG18: =IFERROR(AG17*변수!AG27,"") | AH18: =IFERROR(AH17*변수!AH27,"") | AI18: =IFERROR(AI17*변수!AI27,"") | AJ18: =SUM(AF18:AI18) | AK18: =IFERROR(AK17*변수!AK27,"") | AL18: =IFERROR(AL17*변수!AL27,"") | AM18: =IFERROR(AM17*변수!AM27,"") | AN18: =IFERROR(AN17*변수!AN27,"") | AO18: =SUM(AK18:AN18)
A19: 자산총계 | B19: 재무상태 | C19: 억원 | D19: 자산총계 | E19: =IFERROR(VLOOKUP($D19,BS연결,MATCH(E$1,BS연결H,0),0)/100,"") | F19: =IFERROR(VLOOKUP($D19,BS연결,MATCH(F$1,BS연결H,0),0)/100,"") | G19: =IFERROR(VLOOKUP($D19,BS연결,MATCH(G$1,BS연결H,0),0)/100,"") | H19: =IFERROR(VLOOKUP($D19,BS연결,MATCH(H$1,BS연결H,0),0)/100,"") | I19: =IFERROR(VLOOKUP($D19,BS연결,MATCH(I$1,BS연결H,0),0)/100,"") | J19: =IFERROR(VLOOKUP($D19,BS연결,MATCH(J$1,BS연결H,0),0)/100,"") | K19: =IFERROR(VLOOKUP($D19,BS연결,MATCH(K$1,BS연결H,0),0)/100,"") | L19: =IFERROR(VLOOKUP($D19,BS연결,MATCH(L$1,BS연결H,0),0)/100,"") | ... AB19: =IFERROR(VLOOKUP($D19,BS연결,MATCH(AB$1,BS연결H,0),0)/100,"") | AC19: =IFERROR(AC20+AC21,"") | AD19: =IFERROR(AD20+AD21,"") | AE19: =AD19 | AF19: =IFERROR(AF20+AF21,"") | AG19: =IFERROR(AG20+AG21,"") | AH19: =IFERROR(AH20+AH21,"") | AI19: =IFERROR(AI20+AI21,"") | AJ19: =AI19 | AK19: =IFERROR(AK20+AK21,"") | AL19: =IFERROR(AL20+AL21,"") | AM19: =IFERROR(AM20+AM21,"") | AN19: =IFERROR(AN20+AN21,"") | AO19: =AN19
A20: 부채총계 | B20: 재무상태 | C20: 억원 | D20: 부채총계 | E20: =IFERROR(VLOOKUP($D20,BS연결,MATCH(E$1,BS연결H,0),0)/100,"") | F20: =IFERROR(VLOOKUP($D20,BS연결,MATCH(F$1,BS연결H,0),0)/100,"") | G20: =IFERROR(VLOOKUP($D20,BS연결,MATCH(G$1,BS연결H,0),0)/100,"") | H20: =IFERROR(VLOOKUP($D20,BS연결,MATCH(H$1,BS연결H,0),0)/100,"") | I20: =IFERROR(VLOOKUP($D20,BS연결,MATCH(I$1,BS연결H,0),0)/100,"") | J20: =IFERROR(VLOOKUP($D20,BS연결,MATCH(J$1,BS연결H,0),0)/100,"") | K20: =IFERROR(VLOOKUP($D20,BS연결,MATCH(K$1,BS연결H,0),0)/100,"") | L20: =IFERROR(VLOOKUP($D20,BS연결,MATCH(L$1,BS연결H,0),0)/100,"") | ... AB20: =IFERROR(VLOOKUP($D20,BS연결,MATCH(AB$1,BS연결H,0),0)/100,"") | AC20: =IFERROR(AB20*(1+변수!AC28),"") | AD20: =IFERROR(AC20*(1+변수!AD28),"") | AE20: =AD20 | AF20: =IFERROR(AD20*(1+변수!AF28),"") | AG20: =IFERROR(AF20*(1+변수!AG28),"") | AH20: =IFERROR(AG20*(1+변수!AH28),"") | AI20: =IFERROR(AH20*(1+변수!AI28),"") | AJ20: =AI20 | AK20: =IFERROR(AI20*(1+변수!AK28),"") | AL20: =IFERROR(AK20*(1+변수!AL28),"") | AM20: =IFERROR(AL20*(1+변수!AM28),"") | AN20: =IFERROR(AM20*(1+변수!AN28),"") | AO20: =AN20
A21: 자본총계 | B21: 재무상태 | C21: 억원 | D21: 자본총계 | E21: =IFERROR(VLOOKUP($D21,BS연결,MATCH(E$1,BS연결H,0),0)/100,"") | F21: =IFERROR(VLOOKUP($D21,BS연결,MATCH(F$1,BS연결H,0),0)/100,"") | G21: =IFERROR(VLOOKUP($D21,BS연결,MATCH(G$1,BS연결H,0),0)/100,"") | H21: =IFERROR(VLOOKUP($D21,BS연결,MATCH(H$1,BS연결H,0),0)/100,"") | I21: =IFERROR(VLOOKUP($D21,BS연결,MATCH(I$1,BS연결H,0),0)/100,"") | J21: =IFERROR(VLOOKUP($D21,BS연결,MATCH(J$1,BS연결H,0),0)/100,"") | K21: =IFERROR(VLOOKUP($D21,BS연결,MATCH(K$1,BS연결H,0),0)/100,"") | L21: =IFERROR(VLOOKUP($D21,BS연결,MATCH(L$1,BS연결H,0),0)/100,"") | ... AB21: =IFERROR(VLOOKUP($D21,BS연결,MATCH(AB$1,BS연결H,0),0)/100,"") | AC21: =IFERROR(AB21+AC17-변수!AC29,"") | AD21: =IFERROR(AC21+AD17-변수!AD29,"") | AE21: =AD21 | AF21: =IFERROR(AD21+AF17-변수!AF29,"") | AG21: =IFERROR(AF21+AG17-변수!AG29,"") | AH21: =IFERROR(AG21+AH17-변수!AH29,"") | AI21: =IFERROR(AH21+AI17-변수!AI29,"") | AJ21: =AI21 | AK21: =IFERROR(AI21+AK17-변수!AK29,"") | AL21: =IFERROR(AK21+AL17-변수!AL29,"") | AM21: =IFERROR(AL21+AM17-변수!AM29,"") | AN21: =IFERROR(AM21+AN17-변수!AN29,"") | AO21: =AN21
A22: 지배주주지분 | B22: 재무상태 | C22: 억원 | D22: 지배주주지분 | E22: =IFERROR(VLOOKUP($D22,BS연결,MATCH(E$1,BS연결H,0),0)/100,"") | F22: =IFERROR(VLOOKUP($D22,BS연결,MATCH(F$1,BS연결H,0),0)/100,"") | G22: =IFERROR(VLOOKUP($D22,BS연결,MATCH(G$1,BS연결H,0),0)/100,"") | H22: =IFERROR(VLOOKUP($D22,BS연결,MATCH(H$1,BS연결H,0),0)/100,"") | I22: =IFERROR(VLOOKUP($D22,BS연결,MATCH(I$1,BS연결H,0),0)/100,"") | J22: =IFERROR(VLOOKUP($D22,BS연결,MATCH(J$1,BS연결H,0),0)/100,"") | K22: =IFERROR(VLOOKUP($D22,BS연결,MATCH(K$1,BS연결H,0),0)/100,"") | L22: =IFERROR(VLOOKUP($D22,BS연결,MATCH(L$1,BS연결H,0),0)/100,"") | ... AB22: =IFERROR(VLOOKUP($D22,BS연결,MATCH(AB$1,BS연결H,0),0)/100,"") | AC22: =IFERROR(AB22+AC18-변수!AC30,"") | AD22: =IFERROR(AC22+AD18-변수!AD30,"") | AE22: =AD22 | AF22: =IFERROR(AD22+AF18-변수!AF30,"") | AG22: =IFERROR(AF22+AG18-변수!AG30,"") | AH22: =IFERROR(AG22+AH18-변수!AH30,"") | AI22: =IFERROR(AH22+AI18-변수!AI30,"") | AJ22: =AI22 | AK22: =IFERROR(AI22+AK18-변수!AK30,"") | AL22: =IFERROR(AK22+AL18-변수!AL30,"") | AM22: =IFERROR(AL22+AM18-변수!AM30,"") | AN22: =IFERROR(AM22+AN18-변수!AN30,"") | AO22: =AN22
A23: 총차입금 | B23: 재무상태 | C23: 억원 | D23: 총차입금 | E23: =IFERROR(VLOOKUP($D23,BS연결,MATCH(E$1,BS연결H,0),0)/100,"") | F23: =IFERROR(VLOOKUP($D23,BS연결,MATCH(F$1,BS연결H,0),0)/100,"") | G23: =IFERROR(VLOOKUP($D23,BS연결,MATCH(G$1,BS연결H,0),0)/100,"") | H23: =IFERROR(VLOOKUP($D23,BS연결,MATCH(H$1,BS연결H,0),0)/100,"") | I23: =IFERROR(VLOOKUP($D23,BS연결,MATCH(I$1,BS연결H,0),0)/100,"") | J23: =IFERROR(VLOOKUP($D23,BS연결,MATCH(J$1,BS연결H,0),0)/100,"") | K23: =IFERROR(VLOOKUP($D23,BS연결,MATCH(K$1,BS연결H,0),0)/100,"") | L23: =IFERROR(VLOOKUP($D23,BS연결,MATCH(L$1,BS연결H,0),0)/100,"") | ... AB23: =IFERROR(VLOOKUP($D23,BS연결,MATCH(AB$1,BS연결H,0),0)/100,"") | AC23: =IFERROR(AB23*(1+변수!AC31),"") | AD23: =IFERROR(AC23*(1+변수!AD31),"") | AE23: =AD23 | AF23: =IFERROR(AD23*(1+변수!AF31),"") | AG23: =IFERROR(AF23*(1+변수!AG31),"") | AH23: =IFERROR(AG23*(1+변수!AH31),"") | AI23: =IFERROR(AH23*(1+변수!AI31),"") | AJ23: =AI23 | AK23: =IFERROR(AI23*(1+변수!AK31),"") | AL23: =IFERROR(AK23*(1+변수!AL31),"") | AM23: =IFERROR(AL23*(1+변수!AM31),"") | AN23: =IFERROR(AM23*(1+변수!AN31),"") | AO23: =AN23
A24: 순차입금 | B24: 재무상태 | C24: 억원 | D24: 순차입금 | E24: =IFERROR(VLOOKUP($D24,BS연결,MATCH(E$1,BS연결H,0),0)/100,"") | F24: =IFERROR(VLOOKUP($D24,BS연결,MATCH(F$1,BS연결H,0),0)/100,"") | G24: =IFERROR(VLOOKUP($D24,BS연결,MATCH(G$1,BS연결H,0),0)/100,"") | H24: =IFERROR(VLOOKUP($D24,BS연결,MATCH(H$1,BS연결H,0),0)/100,"") | I24: =IFERROR(VLOOKUP($D24,BS연결,MATCH(I$1,BS연결H,0),0)/100,"") | J24: =IFERROR(VLOOKUP($D24,BS연결,MATCH(J$1,BS연결H,0),0)/100,"") | K24: =IFERROR(VLOOKUP($D24,BS연결,MATCH(K$1,BS연결H,0),0)/100,"") | L24: =IFERROR(VLOOKUP($D24,BS연결,MATCH(L$1,BS연결H,0),0)/100,"") | ... AB24: =IFERROR(VLOOKUP($D24,BS연결,MATCH(AB$1,BS연결H,0),0)/100,"") | AC24: =IFERROR(AB24*(1+변수!AC32),"") | AD24: =IFERROR(AC24*(1+변수!AD32),"") | AE24: =AD24 | AF24: =IFERROR(AD24*(1+변수!AF32),"") | AG24: =IFERROR(AF24*(1+변수!AG32),"") | AH24: =IFERROR(AG24*(1+변수!AH32),"") | AI24: =IFERROR(AH24*(1+변수!AI32),"") | AJ24: =AI24 | AK24: =IFERROR(AI24*(1+변수!AK32),"") | AL24: =IFERROR(AK24*(1+변수!AL32),"") | AM24: =IFERROR(AL24*(1+변수!AM32),"") | AN24: =IFERROR(AM24*(1+변수!AN32),"") | AO24: =AN24
A25: 이자발생자산 | B25: 재무상태 | C25: 억원 | D25: 이자발생자산 | E25: =IFERROR(VLOOKUP($D25,BS연결,MATCH(E$1,BS연결H,0),0)/100,"") | F25: =IFERROR(VLOOKUP($D25,BS연결,MATCH(F$1,BS연결H,0),0)/100,"") | G25: =IFERROR(VLOOKUP($D25,BS연결,MATCH(G$1,BS연결H,0),0)/100,"") | H25: =IFERROR(VLOOKUP($D25,BS연결,MATCH(H$1,BS연결H,0),0)/100,"") | I25: =IFERROR(VLOOKUP($D25,BS연결,MATCH(I$1,BS연결H,0),0)/100,"") | J25: =IFERROR(VLOOKUP($D25,BS연결,MATCH(J$1,BS연결H,0),0)/100,"") | K25: =IFERROR(VLOOKUP($D25,BS연결,MATCH(K$1,BS연결H,0),0)/100,"") | L25: =IFERROR(VLOOKUP($D25,BS연결,MATCH(L$1,BS연결H,0),0)/100,"") | ... AB25: =IFERROR(VLOOKUP($D25,BS연결,MATCH(AB$1,BS연결H,0),0)/100,"") | AC25: =IFERROR(AB25*(1+변수!AC33),"") | AD25: =IFERROR(AC25*(1+변수!AD33),"") | AE25: =AD25 | AF25: =IFERROR(AD25*(1+변수!AF33),"") | AG25: =IFERROR(AF25*(1+변수!AG33),"") | AH25: =IFERROR(AG25*(1+변수!AH33),"") | AI25: =IFERROR(AH25*(1+변수!AI33),"") | AJ25: =AI25 | AK25: =IFERROR(AI25*(1+변수!AK33),"") | AL25: =IFERROR(AK25*(1+변수!AL33),"") | AM25: =IFERROR(AL25*(1+변수!AM33),"") | AN25: =IFERROR(AM25*(1+변수!AN33),"") | AO25: =AN25
A26: 현금및현금성자산 | B26: 재무상태 | C26: 억원 | D26: 현금및현금성자산 | E26: =IFERROR(VLOOKUP($D26,BS연결,MATCH(E$1,BS연결H,0),0)/100,"") | F26: =IFERROR(VLOOKUP($D26,BS연결,MATCH(F$1,BS연결H,0),0)/100,"") | G26: =IFERROR(VLOOKUP($D26,BS연결,MATCH(G$1,BS연결H,0),0)/100,"") | H26: =IFERROR(VLOOKUP($D26,BS연결,MATCH(H$1,BS연결H,0),0)/100,"") | I26: =IFERROR(VLOOKUP($D26,BS연결,MATCH(I$1,BS연결H,0),0)/100,"") | J26: =IFERROR(VLOOKUP($D26,BS연결,MATCH(J$1,BS연결H,0),0)/100,"") | K26: =IFERROR(VLOOKUP($D26,BS연결,MATCH(K$1,BS연결H,0),0)/100,"") | L26: =IFERROR(VLOOKUP($D26,BS연결,MATCH(L$1,BS연결H,0),0)/100,"") | ... AB26: =IFERROR(VLOOKUP($D26,BS연결,MATCH(AB$1,BS연결H,0),0)/100,"") | AE26: =AD26 | AJ26: =AI26 | AO26: =AN26
A27: CAPEX | B27: 현금흐름 | C27: 억원 | D27: CAPEX | E27: =IFERROR(VLOOKUP($D27,BS연결,MATCH(E$1,BS연결H,0),0)/100,"") | G27: =IFERROR(VLOOKUP($D27,BS연결,MATCH(G$1,BS연결H,0),0)/100,"") | H27: =IFERROR(VLOOKUP($D27,BS연결,MATCH(H$1,BS연결H,0),0)/100,"") | I27: =IFERROR(VLOOKUP($D27,BS연결,MATCH(I$1,BS연결H,0),0)/100,"") | J27: =IFERROR(VLOOKUP($D27,BS연결,MATCH(J$1,BS연결H,0),0)/100,"") | K27: =IFERROR(VLOOKUP($D27,BS연결,MATCH(K$1,BS연결H,0),0)/100,"") | L27: =IFERROR(VLOOKUP($D27,BS연결,MATCH(L$1,BS연결H,0),0)/100,"") | M27: =IFERROR(VLOOKUP($D27,BS연결,MATCH(M$1,BS연결H,0),0)/100,"") | N27: =IFERROR(VLOOKUP($D27,BS연결,MATCH(N$1,BS연결H,0),0)/100,"") | ... AB27: =IFERROR(VLOOKUP($D27,BS연결,MATCH(AB$1,BS연결H,0),0)/100,"") | AC27: =IFERROR(X27*(1+변수!AC35),"") | AD27: =IFERROR(Y27*(1+변수!AD35),"") | AE27: =SUM(AA27:AD27) | AF27: =IFERROR(AA27*(1+변수!AF35),"") | AG27: =IFERROR(AB27*(1+변수!AG35),"") | AH27: =IFERROR(AC27*(1+변수!AH35),"") | AI27: =IFERROR(AD27*(1+변수!AI35),"") | AJ27: =SUM(AF27:AI27) | AK27: =IFERROR(AF27*(1+변수!AK35),"") | AL27: =IFERROR(AG27*(1+변수!AL35),"") | AM27: =IFERROR(AH27*(1+변수!AM35),"") | AN27: =IFERROR(AI27*(1+변수!AN35),"") | AO27: =SUM(AK27:AN27)
A28: 영업활동현금흐름 | B28: 현금흐름 | C28: 억원 | D28: 영업활동으로인한현금흐름 | E28: =IFERROR(VLOOKUP($D28,BS연결,MATCH(E$1,BS연결H,0),0)/100,"") | G28: =IFERROR(VLOOKUP($D28,BS연결,MATCH(G$1,BS연결H,0),0)/100,"") | H28: =IFERROR(VLOOKUP($D28,BS연결,MATCH(H$1,BS연결H,0),0)/100,"") | I28: =IFERROR(VLOOKUP($D28,BS연결,MATCH(I$1,BS연결H,0),0)/100,"") | J28: =IFERROR(VLOOKUP($D28,BS연결,MATCH(J$1,BS연결H,0),0)/100,"") | K28: =IFERROR(VLOOKUP($D28,BS연결,MATCH(K$1,BS연결H,0),0)/100,"") | L28: =IFERROR(VLOOKUP($D28,BS연결,MATCH(L$1,BS연결H,0),0)/100,"") | M28: =IFERROR(VLOOKUP($D28,BS연결,MATCH(M$1,BS연결H,0),0)/100,"") | N28: =IFERROR(VLOOKUP($D28,BS연결,MATCH(N$1,BS연결H,0),0)/100,"") | ... AB28: =IFERROR(VLOOKUP($D28,BS연결,MATCH(AB$1,BS연결H,0),0)/100,"") | AE28: =SUM(AA28:AD28) | AJ28: =SUM(AF28:AI28) | AO28: =SUM(AK28:AN28)
A29: 주식수 | B29: 주당 | C29: 백만주 | D29: 유통주식수 | E29: 30.727 | F29: =E29 | G29: 30.727 | H29: 30.727 | I29: 30.727 | J29: 30.727 | K29: =J29 | L29: 30.727 | M29: 30.727 | N29: 30.727 | O29: 30.727 | P29: =O29 | Q29: 30.727 | R29: 30.727 | S29: 30.727 | T29: 30.681 | U29: =T29 | V29: 30.681 | W29: 30.681 | X29: 30.681 | Y29: 30.681 | Z29: =Y29 | AA29: 30.681 | AB29: 30.681 | AC29: =IFERROR(AB29*(1+변수!AC37),"") | AD29: =IFERROR(AC29*(1+변수!AD37),"") | AE29: =AD29 | AF29: =IFERROR(AD29*(1+변수!AF37),"") | AG29: =IFERROR(AF29*(1+변수!AG37),"") | AH29: =IFERROR(AG29*(1+변수!AH37),"") | AI29: =IFERROR(AH29*(1+변수!AI37),"") | AJ29: =AI29 | AK29: =IFERROR(AI29*(1+변수!AK37),"") | AL29: =IFERROR(AK29*(1+변수!AL37),"") | AM29: =IFERROR(AL29*(1+변수!AM37),"") | AN29: =IFERROR(AM29*(1+변수!AN37),"") | AO29: =AN29
A30: EPS | B30: 주당 | C30: 원 | D30: EPS | E30: =IFERROR(E18*100/E29,"") | G30: =IFERROR(G18*100/G29,"") | H30: =IFERROR(H18*100/H29,"") | I30: =IFERROR(I18*100/I29,"") | J30: =IFERROR(J18*100/J29,"") | K30: =SUM(G30:J30) | L30: =IFERROR(L18*100/L29,"") | M30: =IFERROR(M18*100/M29,"") | N30: =IFERROR(N18*100/N29,"") | O30: =IFERROR(O18*100/O29,"") | P30: =SUM(L30:O30) | Q30: =IFERROR(Q18*100/Q29,"") | R30: =IFERROR(R18*100/R29,"") | S30: =IFERROR(S18*100/S29,"") | T30: =IFERROR(T18*100/T29,"") | U30: =SUM(Q30:T30) | V30: =IFERROR(V18*100/V29,"") | W30: =IFERROR(W18*100/W29,"") | X30: =IFERROR(X18*100/X29,"") | Y30: =IFERROR(Y18*100/Y29,"") | Z30: =SUM(V30:Y30) | AA30: =IFERROR(AA18*100/AA29,"") | AB30: =IFERROR(AB18*100/AB29,"") | AC30: =IFERROR(AC18*100/AC29,"") | AD30: =IFERROR(AD18*100/AD29,"") | AE30: =SUM(AA30:AD30) | AF30: =IFERROR(AF18*100/AF29,"") | AG30: =IFERROR(AG18*100/AG29,"") | AH30: =IFERROR(AH18*100/AH29,"") | AI30: =IFERROR(AI18*100/AI29,"") | AJ30: =SUM(AF30:AI30) | AK30: =IFERROR(AK18*100/AK29,"") | AL30: =IFERROR(AL18*100/AL29,"") | AM30: =IFERROR(AM18*100/AM29,"") | AN30: =IFERROR(AN18*100/AN29,"") | AO30: =SUM(AK30:AN30)
A31: BPS | B31: 주당 | C31: 원 | D31: BPS | E31: =IFERROR(E22*100/E29,"") | F31: =E31 | G31: =IFERROR(G22*100/G29,"") | H31: =IFERROR(H22*100/H29,"") | I31: =IFERROR(I22*100/I29,"") | J31: =IFERROR(J22*100/J29,"") | K31: =J31 | L31: =IFERROR(L22*100/L29,"") | M31: =IFERROR(M22*100/M29,"") | N31: =IFERROR(N22*100/N29,"") | O31: =IFERROR(O22*100/O29,"") | P31: =O31 | Q31: =IFERROR(Q22*100/Q29,"") | R31: =IFERROR(R22*100/R29,"") | S31: =IFERROR(S22*100/S29,"") | T31: =IFERROR(T22*100/T29,"") | U31: =T31 | V31: =IFERROR(V22*100/V29,"") | W31: =IFERROR(W22*100/W29,"") | X31: =IFERROR(X22*100/X29,"") | Y31: =IFERROR(Y22*100/Y29,"") | Z31: =Y31 | AA31: =IFERROR(AA22*100/AA29,"") | AB31: =IFERROR(AB22*100/AB29,"") | AC31: =IFERROR(AC22*100/AC29,"") | AD31: =IFERROR(AD22*100/AD29,"") | AE31: =AD31 | AF31: =IFERROR(AF22*100/AF29,"") | AG31: =IFERROR(AG22*100/AG29,"") | AH31: =IFERROR(AH22*100/AH29,"") | AI31: =IFERROR(AI22*100/AI29,"") | AJ31: =AI31 | AK31: =IFERROR(AK22*100/AK29,"") | AL31: =IFERROR(AL22*100/AL29,"") | AM31: =IFERROR(AM22*100/AM29,"") | AN31: =IFERROR(AN22*100/AN29,"") | AO31: =AN31
A32: DPS | B32: 주당 | C32: 원 | D32: DPS(보통주) | E32: 0 | F32: 0 | J32: 0 | K32: =SUM(G32:J32) | O32: 0 | P32: =SUM(L32:O32) | T32: 0 | U32: =SUM(Q32:T32) | Y32: 0 | Z32: =SUM(V32:Y32) | AD32: =변수!AD38 | AE32: =SUM(AA32:AD32) | AI32: =변수!AI38 | AJ32: =SUM(AF32:AI32) | AN32: =변수!AN38 | AO32: =SUM(AK32:AN32)
A33: PER | B33: 주당 | C33: 배 | D33: PER | F33: =E33 | I33: =IFERROR(변수!I18/(E30+G30+H30+I30),"") | J33: =IFERROR(변수!J18/(G30+H30+I30+J30),"") | K33: =J33 | L33: =IFERROR(변수!L18/(H30+I30+J30+L30),"") | M33: =IFERROR(변수!M18/(I30+J30+L30+M30),"") | O33: =IFERROR(변수!O18/(L30+M30+N30+O30),"") | P33: =O33 | Q33: =IFERROR(변수!Q18/(M30+N30+O30+Q30),"") | R33: =IFERROR(변수!R18/(N30+O30+Q30+R30),"") | S33: =IFERROR(변수!S18/(O30+Q30+R30+S30),"") | T33: =IFERROR(변수!T18/(Q30+R30+S30+T30),"") | U33: =T33 | V33: =IFERROR(변수!V18/(R30+S30+T30+V30),"") | W33: =IFERROR(변수!W18/(S30+T30+V30+W30),"") | X33: =IFERROR(변수!X18/(T30+V30+W30+X30),"") | Y33: =IFERROR(변수!Y18/(V30+W30+X30+Y30),"") | Z33: =Y33 | AA33: =IFERROR(변수!AA18/(W30+X30+Y30+AA30),"") | AB33: =IFERROR(변수!AB18/(X30+Y30+AA30+AB30),"") | AC33: =IFERROR(변수!$D$41/(Y30+AA30+AB30+AC30),"") | AD33: =IFERROR(변수!$D$41/(AA30+AB30+AC30+AD30),"") | AE33: =AD33 | AF33: =IFERROR(변수!$D$41/(AB30+AC30+AD30+AF30),"") | AG33: =IFERROR(변수!$D$41/(AC30+AD30+AF30+AG30),"") | AH33: =IFERROR(변수!$D$41/(AD30+AF30+AG30+AH30),"") | AI33: =IFERROR(변수!$D$41/(AF30+AG30+AH30+AI30),"") | AJ33: =AI33 | AK33: =IFERROR(변수!$D$41/(AG30+AH30+AI30+AK30),"") | AL33: =IFERROR(변수!$D$41/(AH30+AI30+AK30+AL30),"") | AM33: =IFERROR(변수!$D$41/(AI30+AK30+AL30+AM30),"") | AN33: =IFERROR(변수!$D$41/(AK30+AL30+AM30+AN30),"") | AO33: =AN33
A34: PBR | B34: 주당 | C34: 배 | D34: PBR | E34: =IFERROR(변수!E18/E31,"") | F34: =E34 | G34: =IFERROR(변수!G18/G31,"") | H34: =IFERROR(변수!H18/H31,"") | I34: =IFERROR(변수!I18/I31,"") | J34: =IFERROR(변수!J18/J31,"") | K34: =J34 | L34: =IFERROR(변수!L18/L31,"") | M34: =IFERROR(변수!M18/M31,"") | N34: =IFERROR(변수!N18/N31,"") | O34: =IFERROR(변수!O18/O31,"") | P34: =O34 | Q34: =IFERROR(변수!Q18/Q31,"") | R34: =IFERROR(변수!R18/R31,"") | S34: =IFERROR(변수!S18/S31,"") | T34: =IFERROR(변수!T18/T31,"") | U34: =T34 | V34: =IFERROR(변수!V18/V31,"") | W34: =IFERROR(변수!W18/W31,"") | X34: =IFERROR(변수!X18/X31,"") | Y34: =IFERROR(변수!Y18/Y31,"") | Z34: =Y34 | AA34: =IFERROR(변수!AA18/AA31,"") | AB34: =IFERROR(변수!AB18/AB31,"") | AC34: =IFERROR(변수!$D$41/AC31,"") | AD34: =IFERROR(변수!$D$41/AD31,"") | AE34: =AD34 | AF34: =IFERROR(변수!$D$41/AF31,"") | AG34: =IFERROR(변수!$D$41/AG31,"") | AH34: =IFERROR(변수!$D$41/AH31,"") | AI34: =IFERROR(변수!$D$41/AI31,"") | AJ34: =AI34 | AK34: =IFERROR(변수!$D$41/AK31,"") | AL34: =IFERROR(변수!$D$41/AL31,"") | AM34: =IFERROR(변수!$D$41/AM31,"") | AN34: =IFERROR(변수!$D$41/AN31,"") | AO34: =AN34
A35: 매출전사 | B35: 사업부 | C35: 억원 | D35: 매출 전사(부문 미분리) | E35: 217.49 | G35: 153.76 | H35: 140.25 | I35: 172.64 | J35: 183.71 | K35: =SUM(G35:J35) | L35: 145.28 | M35: 136.73 | N35: 97.54 | O35: 150.17 | P35: =SUM(L35:O35) | Q35: 99.13 | R35: 114.42 | S35: 125.08 | T35: 179.3 | U35: =SUM(Q35:T35) | V35: 100.29 | W35: 115.88 | X35: 137.98 | Y35: 152.6 | Z35: =SUM(V35:Y35) | AA35: 120.79 | AB35: 162.29 | AC35: =IFERROR(AC5,"") | AD35: =IFERROR(AD5,"") | AE35: =SUM(AA35:AD35) | AF35: =IFERROR(AF5,"") | AG35: =IFERROR(AG5,"") | AH35: =IFERROR(AH5,"") | AI35: =IFERROR(AI5,"") | AJ35: =SUM(AF35:AI35) | AK35: =IFERROR(AK5,"") | AL35: =IFERROR(AL5,"") | AM35: =IFERROR(AM5,"") | AN35: =IFERROR(AN5,"") | AO35: =SUM(AK35:AN35)
A36: OP전사 | B36: 사업부 | C36: 억원 | D36: OP 전사(부문 미분리) | E36: 19.16 | G36: -4.46 | H36: 5.06 | I36: 26.91 | J36: 4.78 | K36: =SUM(G36:J36) | L36: 5.58 | M36: 9.7 | N36: -2.18 | O36: 39.83 | P36: =SUM(L36:O36) | Q36: -0.31 | R36: 10.16 | S36: 25.09 | T36: 34.2 | U36: =SUM(Q36:T36) | V36: 7.02 | W36: 12.86 | X36: 33.43 | Y36: 55.32 | Z36: =SUM(V36:Y36) | AA36: 23.04 | AB36: 59.33 | AC36: =IFERROR(AC9,"") | AD36: =IFERROR(AD9,"") | AE36: =SUM(AA36:AD36) | AF36: =IFERROR(AF9,"") | AG36: =IFERROR(AG9,"") | AH36: =IFERROR(AH9,"") | AI36: =IFERROR(AI9,"") | AJ36: =SUM(AF36:AI36) | AK36: =IFERROR(AK9,"") | AL36: =IFERROR(AL9,"") | AM36: =IFERROR(AM9,"") | AN36: =IFERROR(AN9,"") | AO36: =SUM(AK36:AN36)
B37: 비율(참고)
A38: NPM | C38: % | D38: 지배주주순이익 / 매출액 | E38: =IFERROR(E18/E5,"") | F38: =IFERROR(F18/F5,"") | G38: =IFERROR(G18/G5,"") | H38: =IFERROR(H18/H5,"") | I38: =IFERROR(I18/I5,"") | J38: =IFERROR(J18/J5,"") | K38: =IFERROR(K18/K5,"") | L38: =IFERROR(L18/L5,"") | ... AO38: =IFERROR(AO18/AO5,"")
A39: 매출원가율 | C39: % | D39: 매출원가 / 매출액 | E39: =IFERROR(E6/E5,"") | F39: =IFERROR(F6/F5,"") | G39: =IFERROR(G6/G5,"") | H39: =IFERROR(H6/H5,"") | I39: =IFERROR(I6/I5,"") | J39: =IFERROR(J6/J5,"") | K39: =IFERROR(K6/K5,"") | L39: =IFERROR(L6/L5,"") | ... AO39: =IFERROR(AO6/AO5,"")
A40: 판관비율 | C40: % | D40: 판관비 / 매출액 | E40: =IFERROR(E8/E5,"") | F40: =IFERROR(F8/F5,"") | G40: =IFERROR(G8/G5,"") | H40: =IFERROR(H8/H5,"") | I40: =IFERROR(I8/I5,"") | J40: =IFERROR(J8/J5,"") | K40: =IFERROR(K8/K5,"") | L40: =IFERROR(L8/L5,"") | ... AO40: =IFERROR(AO8/AO5,"")

Sheet 분기
C1: 이름: 분기H — subQ 를 이름으로 VLOOKUP(억원) | E1: 4Q21 | F1: 1Q22 | G1: 2Q22 | H1: 3Q22 | I1: 4Q22 | J1: 1Q23 | K1: 2Q23 | L1: 3Q23 | M1: 4Q23 | N1: 1Q24 | O1: 2Q24 | P1: 3Q24 | Q1: 4Q24 | R1: 1Q25 | S1: 2Q25 | T1: 3Q25 | U1: 4Q25 | V1: 1Q26 | W1: 2Q26 | X1: 3Q26 | Y1: 4Q26 | Z1: 1Q27 | AA1: 2Q27 | AB1: 3Q27 | AC1: 4Q27 | AD1: 1Q28 | AE1: 2Q28 | AF1: 3Q28 | AG1: 4Q28
C2: 종가: | D2: =변수!D41
C3: 기준일: | D3: 20261013 | E3: 1 | F3: 2 | G3: 3 | H3: 4 | I3: 5 | J3: 6 | K3: 7 | L3: 8 | M3: 9 | N3: 10 | O3: 11 | P3: 12 | Q3: 13 | R3: 14 | S3: 15 | T3: 16 | U3: 17 | V3: 18 | W3: 19 | X3: 20 | Y3: 21 | Z3: 22 | AA3: 23 | AB3: 24 | AC3: 25 | AD3: 26 | AE3: 27 | AF3: 28 | AG3: 29
E4: 2021.12 | F4: 2022.03 | G4: 2022.06 | H4: 2022.09 | I4: 2022.12 | J4: 2023.03 | K4: 2023.06 | L4: 2023.09 | M4: 2023.12 | N4: 2024.03 | O4: 2024.06 | P4: 2024.09 | Q4: 2024.12 | R4: 2025.03 | S4: 2025.06 | T4: 2025.09 | U4: 2025.12 | V4: 2026.03 | W4: 2026.06 | X4: 2026.09 | Y4: 2026.12 | Z4: 2027.03 | AA4: 2027.06 | AB4: 2027.09 | AC4: 2027.12 | AD4: 2028.03 | AE4: 2028.06 | AF4: 2028.09 | AG4: 2028.12
A5: 매출액 | D5: 매출액 | E5: =IFERROR(VLOOKUP($A5,subQ,MATCH(E$1,SUBQH,0),0),"") | F5: =IFERROR(VLOOKUP($A5,subQ,MATCH(F$1,SUBQH,0),0),"") | G5: =IFERROR(VLOOKUP($A5,subQ,MATCH(G$1,SUBQH,0),0),"") | H5: =IFERROR(VLOOKUP($A5,subQ,MATCH(H$1,SUBQH,0),0),"") | I5: =IFERROR(VLOOKUP($A5,subQ,MATCH(I$1,SUBQH,0),0),"") | J5: =IFERROR(VLOOKUP($A5,subQ,MATCH(J$1,SUBQH,0),0),"") | K5: =IFERROR(VLOOKUP($A5,subQ,MATCH(K$1,SUBQH,0),0),"") | L5: =IFERROR(VLOOKUP($A5,subQ,MATCH(L$1,SUBQH,0),0),"") | ... AG5: =IFERROR(VLOOKUP($A5,subQ,MATCH(AG$1,SUBQH,0),0),"")
A6: 매출원가 | D6: 매출원가 | E6: =IFERROR(VLOOKUP($A6,subQ,MATCH(E$1,SUBQH,0),0),"") | F6: =IFERROR(VLOOKUP($A6,subQ,MATCH(F$1,SUBQH,0),0),"") | G6: =IFERROR(VLOOKUP($A6,subQ,MATCH(G$1,SUBQH,0),0),"") | H6: =IFERROR(VLOOKUP($A6,subQ,MATCH(H$1,SUBQH,0),0),"") | I6: =IFERROR(VLOOKUP($A6,subQ,MATCH(I$1,SUBQH,0),0),"") | J6: =IFERROR(VLOOKUP($A6,subQ,MATCH(J$1,SUBQH,0),0),"") | K6: =IFERROR(VLOOKUP($A6,subQ,MATCH(K$1,SUBQH,0),0),"") | L6: =IFERROR(VLOOKUP($A6,subQ,MATCH(L$1,SUBQH,0),0),"") | ... AG6: =IFERROR(VLOOKUP($A6,subQ,MATCH(AG$1,SUBQH,0),0),"")
A7: 매출총이익 | D7: 매출총이익 | E7: =IFERROR(VLOOKUP($A7,subQ,MATCH(E$1,SUBQH,0),0),"") | F7: =IFERROR(VLOOKUP($A7,subQ,MATCH(F$1,SUBQH,0),0),"") | G7: =IFERROR(VLOOKUP($A7,subQ,MATCH(G$1,SUBQH,0),0),"") | H7: =IFERROR(VLOOKUP($A7,subQ,MATCH(H$1,SUBQH,0),0),"") | I7: =IFERROR(VLOOKUP($A7,subQ,MATCH(I$1,SUBQH,0),0),"") | J7: =IFERROR(VLOOKUP($A7,subQ,MATCH(J$1,SUBQH,0),0),"") | K7: =IFERROR(VLOOKUP($A7,subQ,MATCH(K$1,SUBQH,0),0),"") | L7: =IFERROR(VLOOKUP($A7,subQ,MATCH(L$1,SUBQH,0),0),"") | ... AG7: =IFERROR(VLOOKUP($A7,subQ,MATCH(AG$1,SUBQH,0),0),"")
A8: 판관비 | D8: 판매비와관리비 | E8: =IFERROR(VLOOKUP($A8,subQ,MATCH(E$1,SUBQH,0),0),"") | F8: =IFERROR(VLOOKUP($A8,subQ,MATCH(F$1,SUBQH,0),0),"") | G8: =IFERROR(VLOOKUP($A8,subQ,MATCH(G$1,SUBQH,0),0),"") | H8: =IFERROR(VLOOKUP($A8,subQ,MATCH(H$1,SUBQH,0),0),"") | I8: =IFERROR(VLOOKUP($A8,subQ,MATCH(I$1,SUBQH,0),0),"") | J8: =IFERROR(VLOOKUP($A8,subQ,MATCH(J$1,SUBQH,0),0),"") | K8: =IFERROR(VLOOKUP($A8,subQ,MATCH(K$1,SUBQH,0),0),"") | L8: =IFERROR(VLOOKUP($A8,subQ,MATCH(L$1,SUBQH,0),0),"") | ... AG8: =IFERROR(VLOOKUP($A8,subQ,MATCH(AG$1,SUBQH,0),0),"")
A9: 영업이익 | D9: 영업이익 | E9: =IFERROR(VLOOKUP($A9,subQ,MATCH(E$1,SUBQH,0),0),"") | F9: =IFERROR(VLOOKUP($A9,subQ,MATCH(F$1,SUBQH,0),0),"") | G9: =IFERROR(VLOOKUP($A9,subQ,MATCH(G$1,SUBQH,0),0),"") | H9: =IFERROR(VLOOKUP($A9,subQ,MATCH(H$1,SUBQH,0),0),"") | I9: =IFERROR(VLOOKUP($A9,subQ,MATCH(I$1,SUBQH,0),0),"") | J9: =IFERROR(VLOOKUP($A9,subQ,MATCH(J$1,SUBQH,0),0),"") | K9: =IFERROR(VLOOKUP($A9,subQ,MATCH(K$1,SUBQH,0),0),"") | L9: =IFERROR(VLOOKUP($A9,subQ,MATCH(L$1,SUBQH,0),0),"") | ... AG9: =IFERROR(VLOOKUP($A9,subQ,MATCH(AG$1,SUBQH,0),0),"")
A10: OPM | D10: 영업이익률 | E10: =IFERROR(VLOOKUP($A10,subQ,MATCH(E$1,SUBQH,0),0),"") | F10: =IFERROR(VLOOKUP($A10,subQ,MATCH(F$1,SUBQH,0),0),"") | G10: =IFERROR(VLOOKUP($A10,subQ,MATCH(G$1,SUBQH,0),0),"") | H10: =IFERROR(VLOOKUP($A10,subQ,MATCH(H$1,SUBQH,0),0),"") | I10: =IFERROR(VLOOKUP($A10,subQ,MATCH(I$1,SUBQH,0),0),"") | J10: =IFERROR(VLOOKUP($A10,subQ,MATCH(J$1,SUBQH,0),0),"") | K10: =IFERROR(VLOOKUP($A10,subQ,MATCH(K$1,SUBQH,0),0),"") | L10: =IFERROR(VLOOKUP($A10,subQ,MATCH(L$1,SUBQH,0),0),"") | ... AG10: =IFERROR(VLOOKUP($A10,subQ,MATCH(AG$1,SUBQH,0),0),"")
A11: 금융손익 | D11: 금융손익(이자·환 포함) | E11: =IFERROR(VLOOKUP($A11,subQ,MATCH(E$1,SUBQH,0),0),"") | F11: =IFERROR(VLOOKUP($A11,subQ,MATCH(F$1,SUBQH,0),0),"") | G11: =IFERROR(VLOOKUP($A11,subQ,MATCH(G$1,SUBQH,0),0),"") | H11: =IFERROR(VLOOKUP($A11,subQ,MATCH(H$1,SUBQH,0),0),"") | I11: =IFERROR(VLOOKUP($A11,subQ,MATCH(I$1,SUBQH,0),0),"") | J11: =IFERROR(VLOOKUP($A11,subQ,MATCH(J$1,SUBQH,0),0),"") | K11: =IFERROR(VLOOKUP($A11,subQ,MATCH(K$1,SUBQH,0),0),"") | L11: =IFERROR(VLOOKUP($A11,subQ,MATCH(L$1,SUBQH,0),0),"") | ... AG11: =IFERROR(VLOOKUP($A11,subQ,MATCH(AG$1,SUBQH,0),0),"")
A12: 이자손익 | D12: 이자손익(이자수익 − 이자비용) | E12: =IFERROR(VLOOKUP($A12,subQ,MATCH(E$1,SUBQH,0),0),"") | F12: =IFERROR(VLOOKUP($A12,subQ,MATCH(F$1,SUBQH,0),0),"") | G12: =IFERROR(VLOOKUP($A12,subQ,MATCH(G$1,SUBQH,0),0),"") | H12: =IFERROR(VLOOKUP($A12,subQ,MATCH(H$1,SUBQH,0),0),"") | I12: =IFERROR(VLOOKUP($A12,subQ,MATCH(I$1,SUBQH,0),0),"") | J12: =IFERROR(VLOOKUP($A12,subQ,MATCH(J$1,SUBQH,0),0),"") | K12: =IFERROR(VLOOKUP($A12,subQ,MATCH(K$1,SUBQH,0),0),"") | L12: =IFERROR(VLOOKUP($A12,subQ,MATCH(L$1,SUBQH,0),0),"") | ... AG12: =IFERROR(VLOOKUP($A12,subQ,MATCH(AG$1,SUBQH,0),0),"")
A13: 외환손익 | D13: 외환손익(실적만; 추정 환효과는 환관련손익) | E13: =IFERROR(VLOOKUP($A13,subQ,MATCH(E$1,SUBQH,0),0),"") | F13: =IFERROR(VLOOKUP($A13,subQ,MATCH(F$1,SUBQH,0),0),"") | G13: =IFERROR(VLOOKUP($A13,subQ,MATCH(G$1,SUBQH,0),0),"") | H13: =IFERROR(VLOOKUP($A13,subQ,MATCH(H$1,SUBQH,0),0),"") | I13: =IFERROR(VLOOKUP($A13,subQ,MATCH(I$1,SUBQH,0),0),"") | J13: =IFERROR(VLOOKUP($A13,subQ,MATCH(J$1,SUBQH,0),0),"") | K13: =IFERROR(VLOOKUP($A13,subQ,MATCH(K$1,SUBQH,0),0),"") | L13: =IFERROR(VLOOKUP($A13,subQ,MATCH(L$1,SUBQH,0),0),"") | ... AG13: =IFERROR(VLOOKUP($A13,subQ,MATCH(AG$1,SUBQH,0),0),"")
A14: 기타영업외손익 | D14: 기타영업외손익 | E14: =IFERROR(VLOOKUP($A14,subQ,MATCH(E$1,SUBQH,0),0),"") | F14: =IFERROR(VLOOKUP($A14,subQ,MATCH(F$1,SUBQH,0),0),"") | G14: =IFERROR(VLOOKUP($A14,subQ,MATCH(G$1,SUBQH,0),0),"") | H14: =IFERROR(VLOOKUP($A14,subQ,MATCH(H$1,SUBQH,0),0),"") | I14: =IFERROR(VLOOKUP($A14,subQ,MATCH(I$1,SUBQH,0),0),"") | J14: =IFERROR(VLOOKUP($A14,subQ,MATCH(J$1,SUBQH,0),0),"") | K14: =IFERROR(VLOOKUP($A14,subQ,MATCH(K$1,SUBQH,0),0),"") | L14: =IFERROR(VLOOKUP($A14,subQ,MATCH(L$1,SUBQH,0),0),"") | ... AG14: =IFERROR(VLOOKUP($A14,subQ,MATCH(AG$1,SUBQH,0),0),"")
A15: 세전이익 | D15: 법인세비용차감전이익 | E15: =IFERROR(VLOOKUP($A15,subQ,MATCH(E$1,SUBQH,0),0),"") | F15: =IFERROR(VLOOKUP($A15,subQ,MATCH(F$1,SUBQH,0),0),"") | G15: =IFERROR(VLOOKUP($A15,subQ,MATCH(G$1,SUBQH,0),0),"") | H15: =IFERROR(VLOOKUP($A15,subQ,MATCH(H$1,SUBQH,0),0),"") | I15: =IFERROR(VLOOKUP($A15,subQ,MATCH(I$1,SUBQH,0),0),"") | J15: =IFERROR(VLOOKUP($A15,subQ,MATCH(J$1,SUBQH,0),0),"") | K15: =IFERROR(VLOOKUP($A15,subQ,MATCH(K$1,SUBQH,0),0),"") | L15: =IFERROR(VLOOKUP($A15,subQ,MATCH(L$1,SUBQH,0),0),"") | ... AG15: =IFERROR(VLOOKUP($A15,subQ,MATCH(AG$1,SUBQH,0),0),"")
A16: 법인세비용 | D16: 법인세비용 | E16: =IFERROR(VLOOKUP($A16,subQ,MATCH(E$1,SUBQH,0),0),"") | F16: =IFERROR(VLOOKUP($A16,subQ,MATCH(F$1,SUBQH,0),0),"") | G16: =IFERROR(VLOOKUP($A16,subQ,MATCH(G$1,SUBQH,0),0),"") | H16: =IFERROR(VLOOKUP($A16,subQ,MATCH(H$1,SUBQH,0),0),"") | I16: =IFERROR(VLOOKUP($A16,subQ,MATCH(I$1,SUBQH,0),0),"") | J16: =IFERROR(VLOOKUP($A16,subQ,MATCH(J$1,SUBQH,0),0),"") | K16: =IFERROR(VLOOKUP($A16,subQ,MATCH(K$1,SUBQH,0),0),"") | L16: =IFERROR(VLOOKUP($A16,subQ,MATCH(L$1,SUBQH,0),0),"") | ... AG16: =IFERROR(VLOOKUP($A16,subQ,MATCH(AG$1,SUBQH,0),0),"")
... A37: NPM | D37: NPM | E37: =IFERROR(VLOOKUP($A37,subQ,MATCH(E$1,SUBQH,0),0),"") | F37: =IFERROR(VLOOKUP($A37,subQ,MATCH(F$1,SUBQH,0),0),"") | G37: =IFERROR(VLOOKUP($A37,subQ,MATCH(G$1,SUBQH,0),0),"") | H37: =IFERROR(VLOOKUP($A37,subQ,MATCH(H$1,SUBQH,0),0),"") | I37: =IFERROR(VLOOKUP($A37,subQ,MATCH(I$1,SUBQH,0),0),"") | J37: =IFERROR(VLOOKUP($A37,subQ,MATCH(J$1,SUBQH,0),0),"") | K37: =IFERROR(VLOOKUP($A37,subQ,MATCH(K$1,SUBQH,0),0),"") | L37: =IFERROR(VLOOKUP($A37,subQ,MATCH(L$1,SUBQH,0),0),"") | ... AG37: =IFERROR(VLOOKUP($A37,subQ,MATCH(AG$1,SUBQH,0),0),"")
A38: 매출액 YoY | D38: 매출액 YoY | I38: =IFERROR(I5/E5-1,"") | J38: =IFERROR(J5/F5-1,"") | K38: =IFERROR(K5/G5-1,"") | L38: =IFERROR(L5/H5-1,"") | M38: =IFERROR(M5/I5-1,"") | N38: =IFERROR(N5/J5-1,"") | O38: =IFERROR(O5/K5-1,"") | P38: =IFERROR(P5/L5-1,"") | ... AG38: =IFERROR(AG5/AC5-1,"")
A39: 영업이익 YoY | D39: 영업이익 YoY | I39: =IFERROR(I9/E9-1,"") | J39: =IFERROR(J9/F9-1,"") | K39: =IFERROR(K9/G9-1,"") | L39: =IFERROR(L9/H9-1,"") | M39: =IFERROR(M9/I9-1,"") | N39: =IFERROR(N9/J9-1,"") | O39: =IFERROR(O9/K9-1,"") | P39: =IFERROR(P9/L9-1,"") | ... AG39: =IFERROR(AG9/AC9-1,"")
A40: 지배주주순이익 YoY | D40: 지배주주순이익 YoY | I40: =IFERROR(I18/E18-1,"") | J40: =IFERROR(J18/F18-1,"") | K40: =IFERROR(K18/G18-1,"") | L40: =IFERROR(L18/H18-1,"") | M40: =IFERROR(M18/I18-1,"") | N40: =IFERROR(N18/J18-1,"") | O40: =IFERROR(O18/K18-1,"") | P40: =IFERROR(P18/L18-1,"") | ... AG40: =IFERROR(AG18/AC18-1,"")

Sheet 연간예상
C1: 이름: 연간예상H — subQ 를 이름으로 VLOOKUP(억원) | E1: 2021 | F1: 2022 | G1: 2023 | H1: 2024 | I1: 2025 | J1: 2026 | K1: 2027 | L1: 2028
C2: 종가: | D2: =변수!D41
C3: 기준일: | D3: 20261013 | E3: 1 | F3: 2 | G3: 3 | H3: 4 | I3: 5 | J3: 6 | K3: 7 | L3: 8
E4: 2021.12A | F4: 2022.12A | G4: 2023.12A | H4: 2024.12A | I4: 2025.12A | J4: 2026.12A | K4: 2027.12A | L4: 2028.12A
A5: 매출액 | D5: 매출액 | E5: =IFERROR(VLOOKUP($A5,subQ,MATCH(E$1,SUBQH,0),0),"") | F5: =IFERROR(VLOOKUP($A5,subQ,MATCH(F$1,SUBQH,0),0),"") | G5: =IFERROR(VLOOKUP($A5,subQ,MATCH(G$1,SUBQH,0),0),"") | H5: =IFERROR(VLOOKUP($A5,subQ,MATCH(H$1,SUBQH,0),0),"") | I5: =IFERROR(VLOOKUP($A5,subQ,MATCH(I$1,SUBQH,0),0),"") | J5: =IFERROR(VLOOKUP($A5,subQ,MATCH(J$1,SUBQH,0),0),"") | K5: =IFERROR(VLOOKUP($A5,subQ,MATCH(K$1,SUBQH,0),0),"") | L5: =IFERROR(VLOOKUP($A5,subQ,MATCH(L$1,SUBQH,0),0),"")
A6: 매출원가 | D6: 매출원가 | E6: =IFERROR(VLOOKUP($A6,subQ,MATCH(E$1,SUBQH,0),0),"") | F6: =IFERROR(VLOOKUP($A6,subQ,MATCH(F$1,SUBQH,0),0),"") | G6: =IFERROR(VLOOKUP($A6,subQ,MATCH(G$1,SUBQH,0),0),"") | H6: =IFERROR(VLOOKUP($A6,subQ,MATCH(H$1,SUBQH,0),0),"") | I6: =IFERROR(VLOOKUP($A6,subQ,MATCH(I$1,SUBQH,0),0),"") | J6: =IFERROR(VLOOKUP($A6,subQ,MATCH(J$1,SUBQH,0),0),"") | K6: =IFERROR(VLOOKUP($A6,subQ,MATCH(K$1,SUBQH,0),0),"") | L6: =IFERROR(VLOOKUP($A6,subQ,MATCH(L$1,SUBQH,0),0),"")
A7: 매출총이익 | D7: 매출총이익 | E7: =IFERROR(VLOOKUP($A7,subQ,MATCH(E$1,SUBQH,0),0),"") | F7: =IFERROR(VLOOKUP($A7,subQ,MATCH(F$1,SUBQH,0),0),"") | G7: =IFERROR(VLOOKUP($A7,subQ,MATCH(G$1,SUBQH,0),0),"") | H7: =IFERROR(VLOOKUP($A7,subQ,MATCH(H$1,SUBQH,0),0),"") | I7: =IFERROR(VLOOKUP($A7,subQ,MATCH(I$1,SUBQH,0),0),"") | J7: =IFERROR(VLOOKUP($A7,subQ,MATCH(J$1,SUBQH,0),0),"") | K7: =IFERROR(VLOOKUP($A7,subQ,MATCH(K$1,SUBQH,0),0),"") | L7: =IFERROR(VLOOKUP($A7,subQ,MATCH(L$1,SUBQH,0),0),"")
A8: 판관비 | D8: 판매비와관리비 | E8: =IFERROR(VLOOKUP($A8,subQ,MATCH(E$1,SUBQH,0),0),"") | F8: =IFERROR(VLOOKUP($A8,subQ,MATCH(F$1,SUBQH,0),0),"") | G8: =IFERROR(VLOOKUP($A8,subQ,MATCH(G$1,SUBQH,0),0),"") | H8: =IFERROR(VLOOKUP($A8,subQ,MATCH(H$1,SUBQH,0),0),"") | I8: =IFERROR(VLOOKUP($A8,subQ,MATCH(I$1,SUBQH,0),0),"") | J8: =IFERROR(VLOOKUP($A8,subQ,MATCH(J$1,SUBQH,0),0),"") | K8: =IFERROR(VLOOKUP($A8,subQ,MATCH(K$1,SUBQH,0),0),"") | L8: =IFERROR(VLOOKUP($A8,subQ,MATCH(L$1,SUBQH,0),0),"")
A9: 영업이익 | D9: 영업이익 | E9: =IFERROR(VLOOKUP($A9,subQ,MATCH(E$1,SUBQH,0),0),"") | F9: =IFERROR(VLOOKUP($A9,subQ,MATCH(F$1,SUBQH,0),0),"") | G9: =IFERROR(VLOOKUP($A9,subQ,MATCH(G$1,SUBQH,0),0),"") | H9: =IFERROR(VLOOKUP($A9,subQ,MATCH(H$1,SUBQH,0),0),"") | I9: =IFERROR(VLOOKUP($A9,subQ,MATCH(I$1,SUBQH,0),0),"") | J9: =IFERROR(VLOOKUP($A9,subQ,MATCH(J$1,SUBQH,0),0),"") | K9: =IFERROR(VLOOKUP($A9,subQ,MATCH(K$1,SUBQH,0),0),"") | L9: =IFERROR(VLOOKUP($A9,subQ,MATCH(L$1,SUBQH,0),0),"")
A10: OPM | D10: 영업이익률 | E10: =IFERROR(VLOOKUP($A10,subQ,MATCH(E$1,SUBQH,0),0),"") | F10: =IFERROR(VLOOKUP($A10,subQ,MATCH(F$1,SUBQH,0),0),"") | G10: =IFERROR(VLOOKUP($A10,subQ,MATCH(G$1,SUBQH,0),0),"") | H10: =IFERROR(VLOOKUP($A10,subQ,MATCH(H$1,SUBQH,0),0),"") | I10: =IFERROR(VLOOKUP($A10,subQ,MATCH(I$1,SUBQH,0),0),"") | J10: =IFERROR(VLOOKUP($A10,subQ,MATCH(J$1,SUBQH,0),0),"") | K10: =IFERROR(VLOOKUP($A10,subQ,MATCH(K$1,SUBQH,0),0),"") | L10: =IFERROR(VLOOKUP($A10,subQ,MATCH(L$1,SUBQH,0),0),"")
A11: 금융손익 | D11: 금융손익(이자·환 포함) | E11: =IFERROR(VLOOKUP($A11,subQ,MATCH(E$1,SUBQH,0),0),"") | F11: =IFERROR(VLOOKUP($A11,subQ,MATCH(F$1,SUBQH,0),0),"") | G11: =IFERROR(VLOOKUP($A11,subQ,MATCH(G$1,SUBQH,0),0),"") | H11: =IFERROR(VLOOKUP($A11,subQ,MATCH(H$1,SUBQH,0),0),"") | I11: =IFERROR(VLOOKUP($A11,subQ,MATCH(I$1,SUBQH,0),0),"") | J11: =IFERROR(VLOOKUP($A11,subQ,MATCH(J$1,SUBQH,0),0),"") | K11: =IFERROR(VLOOKUP($A11,subQ,MATCH(K$1,SUBQH,0),0),"") | L11: =IFERROR(VLOOKUP($A11,subQ,MATCH(L$1,SUBQH,0),0),"")
A12: 이자손익 | D12: 이자손익(이자수익 − 이자비용) | E12: =IFERROR(VLOOKUP($A12,subQ,MATCH(E$1,SUBQH,0),0),"") | F12: =IFERROR(VLOOKUP($A12,subQ,MATCH(F$1,SUBQH,0),0),"") | G12: =IFERROR(VLOOKUP($A12,subQ,MATCH(G$1,SUBQH,0),0),"") | H12: =IFERROR(VLOOKUP($A12,subQ,MATCH(H$1,SUBQH,0),0),"") | I12: =IFERROR(VLOOKUP($A12,subQ,MATCH(I$1,SUBQH,0),0),"") | J12: =IFERROR(VLOOKUP($A12,subQ,MATCH(J$1,SUBQH,0),0),"") | K12: =IFERROR(VLOOKUP($A12,subQ,MATCH(K$1,SUBQH,0),0),"") | L12: =IFERROR(VLOOKUP($A12,subQ,MATCH(L$1,SUBQH,0),0),"")
A13: 외환손익 | D13: 외환손익(실적만; 추정 환효과는 환관련손익) | E13: =IFERROR(VLOOKUP($A13,subQ,MATCH(E$1,SUBQH,0),0),"") | F13: =IFERROR(VLOOKUP($A13,subQ,MATCH(F$1,SUBQH,0),0),"") | G13: =IFERROR(VLOOKUP($A13,subQ,MATCH(G$1,SUBQH,0),0),"") | H13: =IFERROR(VLOOKUP($A13,subQ,MATCH(H$1,SUBQH,0),0),"") | I13: =IFERROR(VLOOKUP($A13,subQ,MATCH(I$1,SUBQH,0),0),"") | J13: =IFERROR(VLOOKUP($A13,subQ,MATCH(J$1,SUBQH,0),0),"") | K13: =IFERROR(VLOOKUP($A13,subQ,MATCH(K$1,SUBQH,0),0),"") | L13: =IFERROR(VLOOKUP($A13,subQ,MATCH(L$1,SUBQH,0),0),"")
A14: 기타영업외손익 | D14: 기타영업외손익 | E14: =IFERROR(VLOOKUP($A14,subQ,MATCH(E$1,SUBQH,0),0),"") | F14: =IFERROR(VLOOKUP($A14,subQ,MATCH(F$1,SUBQH,0),0),"") | G14: =IFERROR(VLOOKUP($A14,subQ,MATCH(G$1,SUBQH,0),0),"") | H14: =IFERROR(VLOOKUP($A14,subQ,MATCH(H$1,SUBQH,0),0),"") | I14: =IFERROR(VLOOKUP($A14,subQ,MATCH(I$1,SUBQH,0),0),"") | J14: =IFERROR(VLOOKUP($A14,subQ,MATCH(J$1,SUBQH,0),0),"") | K14: =IFERROR(VLOOKUP($A14,subQ,MATCH(K$1,SUBQH,0),0),"") | L14: =IFERROR(VLOOKUP($A14,subQ,MATCH(L$1,SUBQH,0),0),"")
A15: 세전이익 | D15: 법인세비용차감전이익 | E15: =IFERROR(VLOOKUP($A15,subQ,MATCH(E$1,SUBQH,0),0),"") | F15: =IFERROR(VLOOKUP($A15,subQ,MATCH(F$1,SUBQH,0),0),"") | G15: =IFERROR(VLOOKUP($A15,subQ,MATCH(G$1,SUBQH,0),0),"") | H15: =IFERROR(VLOOKUP($A15,subQ,MATCH(H$1,SUBQH,0),0),"") | I15: =IFERROR(VLOOKUP($A15,subQ,MATCH(I$1,SUBQH,0),0),"") | J15: =IFERROR(VLOOKUP($A15,subQ,MATCH(J$1,SUBQH,0),0),"") | K15: =IFERROR(VLOOKUP($A15,subQ,MATCH(K$1,SUBQH,0),0),"") | L15: =IFERROR(VLOOKUP($A15,subQ,MATCH(L$1,SUBQH,0),0),"")
A16: 법인세비용 | D16: 법인세비용 | E16: =IFERROR(VLOOKUP($A16,subQ,MATCH(E$1,SUBQH,0),0),"") | F16: =IFERROR(VLOOKUP($A16,subQ,MATCH(F$1,SUBQH,0),0),"") | G16: =IFERROR(VLOOKUP($A16,subQ,MATCH(G$1,SUBQH,0),0),"") | H16: =IFERROR(VLOOKUP($A16,subQ,MATCH(H$1,SUBQH,0),0),"") | I16: =IFERROR(VLOOKUP($A16,subQ,MATCH(I$1,SUBQH,0),0),"") | J16: =IFERROR(VLOOKUP($A16,subQ,MATCH(J$1,SUBQH,0),0),"") | K16: =IFERROR(VLOOKUP($A16,subQ,MATCH(K$1,SUBQH,0),0),"") | L16: =IFERROR(VLOOKUP($A16,subQ,MATCH(L$1,SUBQH,0),0),"")
... A37: NPM | D37: NPM | E37: =IFERROR(VLOOKUP($A37,subQ,MATCH(E$1,SUBQH,0),0),"") | F37: =IFERROR(VLOOKUP($A37,subQ,MATCH(F$1,SUBQH,0),0),"") | G37: =IFERROR(VLOOKUP($A37,subQ,MATCH(G$1,SUBQH,0),0),"") | H37: =IFERROR(VLOOKUP($A37,subQ,MATCH(H$1,SUBQH,0),0),"") | I37: =IFERROR(VLOOKUP($A37,subQ,MATCH(I$1,SUBQH,0),0),"") | J37: =IFERROR(VLOOKUP($A37,subQ,MATCH(J$1,SUBQH,0),0),"") | K37: =IFERROR(VLOOKUP($A37,subQ,MATCH(K$1,SUBQH,0),0),"") | L37: =IFERROR(VLOOKUP($A37,subQ,MATCH(L$1,SUBQH,0),0),"")
A38: 매출액 YoY | D38: 매출액 YoY | F38: =IFERROR(F5/E5-1,"") | G38: =IFERROR(G5/F5-1,"") | H38: =IFERROR(H5/G5-1,"") | I38: =IFERROR(I5/H5-1,"") | J38: =IFERROR(J5/I5-1,"") | K38: =IFERROR(K5/J5-1,"") | L38: =IFERROR(L5/K5-1,"")
A39: 영업이익 YoY | D39: 영업이익 YoY | F39: =IFERROR(F9/E9-1,"") | G39: =IFERROR(G9/F9-1,"") | H39: =IFERROR(H9/G9-1,"") | I39: =IFERROR(I9/H9-1,"") | J39: =IFERROR(J9/I9-1,"") | K39: =IFERROR(K9/J9-1,"") | L39: =IFERROR(L9/K9-1,"")
A40: 지배주주순이익 YoY | D40: 지배주주순이익 YoY | F40: =IFERROR(F18/E18-1,"") | G40: =IFERROR(G18/F18-1,"") | H40: =IFERROR(H18/G18-1,"") | I40: =IFERROR(I18/H18-1,"") | J40: =IFERROR(J18/I18-1,"") | K40: =IFERROR(K18/J18-1,"") | L40: =IFERROR(L18/K18-1,"")

Sheet TP
B1: 종가 | C1: =변수!D41
B2: 기준일 | C2: =변수!D42
B3: 모델 산출값 — 목표주가·추천 아님. 밴드·COE 는 변수 시트 3절의 가정
C5: FY | D5: 2025 | E5: 2026 | F5: 2027 | G5: 2028
D6: A | E6: E | F6: E | G6: E
C7: EPS(원) | D7: =IFERROR(VLOOKUP("EPS",subQ,MATCH(D$5,SUBQH,0),0),"") | E7: =IFERROR(VLOOKUP("EPS",subQ,MATCH(E$5,SUBQH,0),0),"") | F7: =IFERROR(VLOOKUP("EPS",subQ,MATCH(F$5,SUBQH,0),0),"") | G7: =IFERROR(VLOOKUP("EPS",subQ,MATCH(G$5,SUBQH,0),0),"")
C8: BPS(원) | D8: =IFERROR(VLOOKUP("BPS",subQ,MATCH(D$5,SUBQH,0),0),"") | E8: =IFERROR(VLOOKUP("BPS",subQ,MATCH(E$5,SUBQH,0),0),"") | F8: =IFERROR(VLOOKUP("BPS",subQ,MATCH(F$5,SUBQH,0),0),"") | G8: =IFERROR(VLOOKUP("BPS",subQ,MATCH(G$5,SUBQH,0),0),"")
C9: 지배주주순이익(억원) | D9: =IFERROR(VLOOKUP("지배주주순이익",subQ,MATCH(D$5,SUBQH,0),0),"") | E9: =IFERROR(VLOOKUP("지배주주순이익",subQ,MATCH(E$5,SUBQH,0),0),"") | F9: =IFERROR(VLOOKUP("지배주주순이익",subQ,MATCH(F$5,SUBQH,0),0),"") | G9: =IFERROR(VLOOKUP("지배주주순이익",subQ,MATCH(G$5,SUBQH,0),0),"")
C10: 영업이익(억원) | D10: =IFERROR(VLOOKUP("영업이익",subQ,MATCH(D$5,SUBQH,0),0),"") | E10: =IFERROR(VLOOKUP("영업이익",subQ,MATCH(E$5,SUBQH,0),0),"") | F10: =IFERROR(VLOOKUP("영업이익",subQ,MATCH(F$5,SUBQH,0),0),"") | G10: =IFERROR(VLOOKUP("영업이익",subQ,MATCH(G$5,SUBQH,0),0),"")
C11: ROE(EPS/기초BPS) | E11: =IFERROR(E7/D8,"") | F11: =IFERROR(F7/E8,"") | G11: =IFERROR(G7/F8,"")
B13: PER
C14: 12M fwd EPS | D14: =IFERROR(E7*변수!D47+F7*(1-변수!D47),"")
C15: 적정가치 @PER_lo | D15: =변수!D44 | E15: =IFERROR(ROUND($D$14*D15,-2),"") | F15: =IFERROR(E15/$C$1-1,"") | G15: 배 · 원 · 종가 대비
C16: 적정가치 @PER_mid | D16: =변수!D45 | E16: =IFERROR(ROUND($D$14*D16,-2),"") | F16: =IFERROR(E16/$C$1-1,"") | G16: 배 · 원 · 종가 대비
C17: 적정가치 @PER_hi | D17: =변수!D46 | E17: =IFERROR(ROUND($D$14*D17,-2),"") | F17: =IFERROR(E17/$C$1-1,"") | G17: 배 · 원 · 종가 대비
C18: 현재 PER(종가/12M fwd EPS) | D18: =IFERROR($C$1/$D$14,"")
B20: PBR
C21: 최근 BPS(마지막 실적 분기) | D21: =IFERROR(VLOOKUP("BPS",subQ,MATCH("2Q26",SUBQH,0),0),"")
C22: ROE fwd(12M fwd EPS / BPS) | D22: =IFERROR($D$14/$D$21,"")
C23: COE | D23: =변수!D43
C24: 적정 PBR = ROE/COE | D24: =IFERROR(D22/D23,"")
C25: 적정가치(PBR) = BPS × 적정PBR | D25: =IFERROR(ROUND(D21*D24,-2),"") | E25: =IFERROR(D25/$C$1-1,"")
C26: 현재 PBR(종가/BPS) | D26: =IFERROR($C$1/D21,"")
B28: 모델 json valuation(참고)
C29: eps_fwd12m | D29: 210.6
C30: bps_latest | D30: 1718
C31: per_now | D31: 16.17
C32: pbr_now | D32: 1.98
C33: roe_fwd | D33: 0.1226
C34: fair_pbr | D34: 1.36
C35: fair_value_pbr | D35: 2300
C36: ev_ebitda
C37: note | D37: 모델 산출값 — 목표주가·추천 아님

Sheet 외화
C1: 이름: 외화QH — 환율 QoQ · 외화 순노출 × Δ기말환율 | E1: 4Q21 | F1: 1Q22 | G1: 2Q22 | H1: 3Q22 | I1: 4Q22 | J1: 1Q23 | K1: 2Q23 | L1: 3Q23 | M1: 4Q23 | N1: 1Q24 | O1: 2Q24 | P1: 3Q24 | Q1: 4Q24 | R1: 1Q25 | S1: 2Q25 | T1: 3Q25 | U1: 4Q25 | V1: 1Q26 | W1: 2Q26 | X1: 3Q26 | Y1: 4Q26 | Z1: 1Q27 | AA1: 2Q27 | AB1: 3Q27 | AC1: 4Q27 | AD1: 1Q28 | AE1: 2Q28 | AF1: 3Q28 | AG1: 4Q28
E3: 1 | F3: 2 | G3: 3 | H3: 4 | I3: 5 | J3: 6 | K3: 7 | L3: 8 | M3: 9 | N3: 10 | O3: 11 | P3: 12 | Q3: 13 | R3: 14 | S3: 15 | T3: 16 | U3: 17 | V3: 18 | W3: 19 | X3: 20 | Y3: 21 | Z3: 22 | AA3: 23 | AB3: 24 | AC3: 25 | AD3: 26 | AE3: 27 | AF3: 28 | AG3: 29
E4: 2021.12 | F4: 2022.03 | G4: 2022.06 | H4: 2022.09 | I4: 2022.12 | J4: 2023.03 | K4: 2023.06 | L4: 2023.09 | M4: 2023.12 | N4: 2024.03 | O4: 2024.06 | P4: 2024.09 | Q4: 2024.12 | R4: 2025.03 | S4: 2025.06 | T4: 2025.09 | U4: 2025.12 | V4: 2026.03 | W4: 2026.06 | X4: 2026.09 | Y4: 2026.12 | Z4: 2027.03 | AA4: 2027.06 | AB4: 2027.09 | AC4: 2027.12 | AD4: 2028.03 | AE4: 2028.06 | AF4: 2028.09 | AG4: 2028.12
D5: 원/달러(평균) | E5: =IFERROR(VLOOKUP($D5,환율,MATCH(E$1,변수H,0),0),"") | F5: =IFERROR(VLOOKUP($D5,환율,MATCH(F$1,변수H,0),0),"") | G5: =IFERROR(VLOOKUP($D5,환율,MATCH(G$1,변수H,0),0),"") | H5: =IFERROR(VLOOKUP($D5,환율,MATCH(H$1,변수H,0),0),"") | I5: =IFERROR(VLOOKUP($D5,환율,MATCH(I$1,변수H,0),0),"") | J5: =IFERROR(VLOOKUP($D5,환율,MATCH(J$1,변수H,0),0),"") | K5: =IFERROR(VLOOKUP($D5,환율,MATCH(K$1,변수H,0),0),"") | L5: =IFERROR(VLOOKUP($D5,환율,MATCH(L$1,변수H,0),0),"") | ... AG5: =IFERROR(VLOOKUP($D5,환율,MATCH(AG$1,변수H,0),0),"")
A6: 원/달러(평균) QoQ | F6: =IFERROR(F5/E5-1,"") | G6: =IFERROR(G5/F5-1,"") | H6: =IFERROR(H5/G5-1,"") | I6: =IFERROR(I5/H5-1,"") | J6: =IFERROR(J5/I5-1,"") | K6: =IFERROR(K5/J5-1,"") | L6: =IFERROR(L5/K5-1,"") | M6: =IFERROR(M5/L5-1,"") | ... AG6: =IFERROR(AG5/AF5-1,"")
D7: 원/달러(기말) | E7: =IFERROR(VLOOKUP($D7,환율,MATCH(E$1,변수H,0),0),"") | F7: =IFERROR(VLOOKUP($D7,환율,MATCH(F$1,변수H,0),0),"") | G7: =IFERROR(VLOOKUP($D7,환율,MATCH(G$1,변수H,0),0),"") | H7: =IFERROR(VLOOKUP($D7,환율,MATCH(H$1,변수H,0),0),"") | I7: =IFERROR(VLOOKUP($D7,환율,MATCH(I$1,변수H,0),0),"") | J7: =IFERROR(VLOOKUP($D7,환율,MATCH(J$1,변수H,0),0),"") | K7: =IFERROR(VLOOKUP($D7,환율,MATCH(K$1,변수H,0),0),"") | L7: =IFERROR(VLOOKUP($D7,환율,MATCH(L$1,변수H,0),0),"") | ... AG7: =IFERROR(VLOOKUP($D7,환율,MATCH(AG$1,변수H,0),0),"")
A8: 원/달러(기말) QoQ | F8: =IFERROR(F7/E7-1,"") | G8: =IFERROR(G7/F7-1,"") | H8: =IFERROR(H7/G7-1,"") | I8: =IFERROR(I7/H7-1,"") | J8: =IFERROR(J7/I7-1,"") | K8: =IFERROR(K7/J7-1,"") | L8: =IFERROR(L7/K7-1,"") | M8: =IFERROR(M7/L7-1,"") | ... AG8: =IFERROR(AG7/AF7-1,"")
D9: W/Euro(평균) | E9: =IFERROR(VLOOKUP($D9,환율,MATCH(E$1,변수H,0),0),"") | F9: =IFERROR(VLOOKUP($D9,환율,MATCH(F$1,변수H,0),0),"") | G9: =IFERROR(VLOOKUP($D9,환율,MATCH(G$1,변수H,0),0),"") | H9: =IFERROR(VLOOKUP($D9,환율,MATCH(H$1,변수H,0),0),"") | I9: =IFERROR(VLOOKUP($D9,환율,MATCH(I$1,변수H,0),0),"") | J9: =IFERROR(VLOOKUP($D9,환율,MATCH(J$1,변수H,0),0),"") | K9: =IFERROR(VLOOKUP($D9,환율,MATCH(K$1,변수H,0),0),"") | L9: =IFERROR(VLOOKUP($D9,환율,MATCH(L$1,변수H,0),0),"") | ... AG9: =IFERROR(VLOOKUP($D9,환율,MATCH(AG$1,변수H,0),0),"")
A10: W/Euro(평균) QoQ | F10: =IFERROR(F9/E9-1,"") | G10: =IFERROR(G9/F9-1,"") | H10: =IFERROR(H9/G9-1,"") | I10: =IFERROR(I9/H9-1,"") | J10: =IFERROR(J9/I9-1,"") | K10: =IFERROR(K9/J9-1,"") | L10: =IFERROR(L9/K9-1,"") | M10: =IFERROR(M9/L9-1,"") | ... AG10: =IFERROR(AG9/AF9-1,"")
D11: W/Euro(기말) | E11: =IFERROR(VLOOKUP($D11,환율,MATCH(E$1,변수H,0),0),"") | F11: =IFERROR(VLOOKUP($D11,환율,MATCH(F$1,변수H,0),0),"") | G11: =IFERROR(VLOOKUP($D11,환율,MATCH(G$1,변수H,0),0),"") | H11: =IFERROR(VLOOKUP($D11,환율,MATCH(H$1,변수H,0),0),"") | I11: =IFERROR(VLOOKUP($D11,환율,MATCH(I$1,변수H,0),0),"") | J11: =IFERROR(VLOOKUP($D11,환율,MATCH(J$1,변수H,0),0),"") | K11: =IFERROR(VLOOKUP($D11,환율,MATCH(K$1,변수H,0),0),"") | L11: =IFERROR(VLOOKUP($D11,환율,MATCH(L$1,변수H,0),0),"") | ... AG11: =IFERROR(VLOOKUP($D11,환율,MATCH(AG$1,변수H,0),0),"")
A12: W/Euro(기말) QoQ | F12: =IFERROR(F11/E11-1,"") | G12: =IFERROR(G11/F11-1,"") | H12: =IFERROR(H11/G11-1,"") | I12: =IFERROR(I11/H11-1,"") | J12: =IFERROR(J11/I11-1,"") | K12: =IFERROR(K11/J11-1,"") | L12: =IFERROR(L11/K11-1,"") | M12: =IFERROR(M11/L11-1,"") | ... AG12: =IFERROR(AG11/AF11-1,"")
D13: 원/100Y(기말) | E13: =IFERROR(VLOOKUP($D13,환율,MATCH(E$1,변수H,0),0),"") | F13: =IFERROR(VLOOKUP($D13,환율,MATCH(F$1,변수H,0),0),"") | G13: =IFERROR(VLOOKUP($D13,환율,MATCH(G$1,변수H,0),0),"") | H13: =IFERROR(VLOOKUP($D13,환율,MATCH(H$1,변수H,0),0),"") | I13: =IFERROR(VLOOKUP($D13,환율,MATCH(I$1,변수H,0),0),"") | J13: =IFERROR(VLOOKUP($D13,환율,MATCH(J$1,변수H,0),0),"") | K13: =IFERROR(VLOOKUP($D13,환율,MATCH(K$1,변수H,0),0),"") | L13: =IFERROR(VLOOKUP($D13,환율,MATCH(L$1,변수H,0),0),"") | ... AG13: =IFERROR(VLOOKUP($D13,환율,MATCH(AG$1,변수H,0),0),"")
A14: 원/100Y(기말) QoQ | F14: =IFERROR(F13/E13-1,"") | G14: =IFERROR(G13/F13-1,"") | H14: =IFERROR(H13/G13-1,"") | I14: =IFERROR(I13/H13-1,"") | J14: =IFERROR(J13/I13-1,"") | K14: =IFERROR(K13/J13-1,"") | L14: =IFERROR(L13/K13-1,"") | M14: =IFERROR(M13/L13-1,"") | ... AG14: =IFERROR(AG13/AF13-1,"")
A16: 외화순노출 | C16: 외화 순노출(백만$) | D16: =변수!D54 | E16: 외화 순노출 × Δ기말환율 (외화 시트 방식)
A17: 환관련손익추정 | C17: 환관련손익 추정(억원) = 순노출 × Δ원/달러(기말) / 100 | F17: =IFERROR($D$16*(F7-E7)/100,"") | G17: =IFERROR($D$16*(G7-F7)/100,"") | H17: =IFERROR($D$16*(H7-G7)/100,"") | I17: =IFERROR($D$16*(I7-H7)/100,"") | J17: =IFERROR($D$16*(J7-I7)/100,"") | K17: =IFERROR($D$16*(K7-J7)/100,"") | L17: =IFERROR($D$16*(L7-K7)/100,"") | M17: =IFERROR($D$16*(M7-L7)/100,"") | ... AG17: =IFERROR($D$16*(AG7-AF7)/100,"")
A18: fx_pnl.by_q | C18: 모델 fx_pnl.by_q(억원, 참고)
C19: 외화 순노출 미공시(face) → 0 + 표기
