Workbook
Name 변수H: 변수!$C$1:$AL$1
Name 환율: 변수!$C$6:$AL$13
Name BS연결H: BS연결!$C$1:$AL$1
Name BS연결: BS연결!$C$5:$AL$95
Name BS별도H: BS별도!$C$1:$AL$1
Name BS별도: BS별도!$C$5:$AL$95
Name SUBQH: subQ!$A$1:$AL$1
Name subQ: subQ!$A$5:$AL$40

Sheet README
A1: 범한퓨얼셀(382900) 실적 모델 — ARGUS 한국조선
A2: 기준 분기 2026Q2 · 마지막 실적 2026Q2 · 생성 2026-10-11
A3: 모든 수치는 모델 산출값(DART 공개 재무제표 + 우리 추정)이다 — 목표주가·투자 추천 아님. 참고용 · 투자조언 아님.
A5: 시트
A6: 변수 가정 시계열. 환율 8행(ECB via frankfurter — L2 fx.json; 추정 분기 = 노란 가정), 추정 드라이버(노란 셀 = 모델값에서 역산한 가정, 바꾸면 재계산; 연녹 셀 = 3절 스칼라 참조 수식), 3절 스칼라 가정(세율·판관비율·지배주주비중·이자율·종가·PER 밴드·COE·외화 순노출·헤지비율)
A7: BS연결/BS별도 FnGuide 계정명 × 기간 값 덤프(백만원). 행1 분기라벨, 행4 YYYY.MM / YYYY.12A. 이름정의 BS연결H·BS연결(계정명 C열부터)
A8: subQ 분기 서브모델(억원 = 백만원/100). 확정 행: =IFERROR(VLOOKUP($D행,BS연결,MATCH(E$1,BS연결H,0),0)/100,"") 추정 행: 변수 시트 가정 셀 참조 수식. 외환손익·파생상품손익은 BS 계정 합·차, 기타금융손익은 잔차, OPM·EPS·BPS·PER·PBR 은 파생 수식
A9: SLS 선표(조선사만, sls json 있을 때): 요약 행(sls 저장값) + 계약별 스케줄(백만$) × (헤지비율 × 헤지환율 + (1−헤지비율) × 건조시점 환율[변수 원/달러(평균)]) → 원화 수식 블록 → 합계 행이 subQ 매출조선에 연결
A10: 시나리오 신규수주 보수/기준/낙관(forecast_panel 패널, 모델에 scenarios 가 있을 때만): 매출액·영업이익 = subQ 기준값 ± (시나리오 신규 − base 신규) × OPM. base 만 subQ 행에 포함, 나머지는 합산 안 함
A11: 분기/연간예상 subQ 를 이름(A열 key)으로 VLOOKUP 한 보고서 표(억원)
A12: TP PER 밴드 × 12M fwd EPS, PBR = ROE/COE × BPS — 모델 산출값 구간, 목표주가·추천 아님
A13: 외화 환율 QoQ, 외화 순노출 × Δ기말환율 → 환관련손익 추정
... A34: 백테스트: {"freeze": "2025Q2", "horizon": 4, "revenue_wape_pct": 51.1, "op_wape_pct": 104.4, "n": 4, "note": "단일 회사 4분기 — 통계 아님", "driver_at_freeze": "trend_seasonal", "selection_oos_at_freeze": null, "frozen_inputs": "fin(연결/별도)·고객 조선사 모델·지주 자회사 모델은 2025Q2 까지의 분기만; 선표는 체결일 ≤ 2025Q2 말일 계약(원장 최신 금액·코호트 등급, 환산 없음); 잔고는 yards_cache 2025Q2; 시세·환율 forward·prices·forecast_panel 신규수주 미사용. 고객 가중치(suppliers.json 언급 비중)와 합병 체인링크는 현재 지식; 고객 연동 채택은 동결 모델 안에서도 자기 la−4분기 OOS 규칙(selection_oos_at_freeze)", "detail": [{"q": "2025Q3", "rev_pred": 152.12, "rev_act": 103.99, "op_pred": 2.16, "op_act": 8.42}, {"q": "2025Q4", "rev_pred": 128.35, "rev_act": 154.55, "op_pred": 1.82, "op_act": -8.21}, {"q": "2026Q1", "rev_pred": 144.47, "rev_act": 50.54, "op_pred": 2.05, "op_act": -21.45}, {"q": "2026Q2", "rev_pred": 97.65, "rev_act": 178.25, "op_pred": 1.39, "op_act": -32.33}]}

Sheet 변수
C1: 이름: 변수H | E1: 2Q22 | F1: 3Q22 | G1: 4Q22 | H1: 2022 | I1: 1Q23 | J1: 2Q23 | K1: 3Q23 | L1: 4Q23 | M1: 2023 | N1: 1Q24 | O1: 2Q24 | P1: 3Q24 | Q1: 4Q24 | R1: 2024 | S1: 1Q25 | T1: 2Q25 | U1: 3Q25 | V1: 4Q25 | W1: 2025 | X1: 1Q26 | Y1: 2Q26 | Z1: 3Q26 | AA1: 4Q26 | AB1: 2026 | AC1: 1Q27 | AD1: 2Q27 | AE1: 3Q27 | AF1: 4Q27 | AG1: 2027 | AH1: 1Q28 | AI1: 2Q28 | AJ1: 3Q28 | AK1: 4Q28 | AL1: 2028
A2: 가정 시계열 — 노란 셀은 추정 가정(모델값에서 역산), 연녹 셀은 3절 스칼라 참조 수식. 바꾸면 subQ·분기·연간예상·TP·시나리오가 재계산됩니다.
E3: 1 | F3: 2 | G3: 3 | H3: 4 | I3: 5 | J3: 6 | K3: 7 | L3: 8 | M3: 9 | N3: 10 | O3: 11 | P3: 12 | Q3: 13 | R3: 14 | S3: 15 | T3: 16 | U3: 17 | V3: 18 | W3: 19 | X3: 20 | Y3: 21 | Z3: 22 | AA3: 23 | AB3: 24 | AC3: 25 | AD3: 26 | AE3: 27 | AF3: 28 | AG3: 29 | AH3: 30 | AI3: 31 | AJ3: 32 | AK3: 33 | AL3: 34
E4: 2022.06 | F4: 2022.09 | G4: 2022.12 | H4: 2022.12A | I4: 2023.03 | J4: 2023.06 | K4: 2023.09 | L4: 2023.12 | M4: 2023.12A | N4: 2024.03 | O4: 2024.06 | P4: 2024.09 | Q4: 2024.12 | R4: 2024.12A | S4: 2025.03 | T4: 2025.06 | U4: 2025.09 | V4: 2025.12 | W4: 2025.12A | X4: 2026.03 | Y4: 2026.06 | Z4: 2026.09 | AA4: 2026.12 | AB4: 2026.12A | AC4: 2027.03 | AD4: 2027.06 | AE4: 2027.09 | AF4: 2027.12 | AG4: 2027.12A | AH4: 2028.03 | AI4: 2028.06 | AJ4: 2028.09 | AK4: 2028.12 | AL4: 2028.12A
B5: 1. FX | C5: 이름: 환율
A6: USDKRW_avg | C6: 원/달러(평균) | E6: 1262.09 | F6: 1341.93 | G6: 1360.12 | H6: 1292.98 | I6: 1276.95 | J6: 1315.69 | K6: 1313.62 | L6: 1322.01 | M6: 1306.85 | N6: 1330.14 | O6: 1371.28 | P6: 1356.22 | Q6: 1396.3 | R6: 1363.53 | S6: 1452.28 | T6: 1398.52 | U6: 1386.95 | V6: 1449.19 | W6: 1421.52 | X6: 1466.12 | Y6: 1501.75 | Z6: 1418.75 | AA6: 1345.14 | AB6: 1457.21 | AC6: 1341.49 | AD6: 1341.49 | AE6: 1341.49 | AF6: 1341.49 | AH6: 1341.49 | AI6: 1341.49 | AJ6: 1341.49 | AK6: 1341.49
A7: USDKRW_end | C7: 원/달러(기말) | E7: 1301.24 | F7: 1436.9 | G7: 1260.16 | H7: 1260.16 | I7: 1305.99 | J7: 1321.44 | K7: 1345.35 | L7: 1297.43 | M7: 1297.43 | N7: 1349.25 | O7: 1377.73 | P7: 1312.17 | Q7: 1474.78 | R7: 1474.78 | S7: 1474.54 | T7: 1355.13 | U7: 1403.67 | V7: 1444.2 | W7: 1444.2 | X7: 1524.8 | Y7: 1550.89 | Z7: 1355.4 | AA7: 1341.49 | AB7: 1341.49 | AC7: 1341.49 | AD7: 1341.49 | AE7: 1341.49 | AF7: 1341.49 | AH7: 1341.49 | AI7: 1341.49 | AJ7: 1341.49 | AK7: 1341.49
A8: JPY100KRW_avg | C8: 원/100Y(평균) | E8: 972.23 | F8: 970.61 | G8: 961.03 | H8: 985.1 | I8: 964.89 | J8: 957.36 | K8: 909 | L8: 893.22 | M8: 931.11 | N8: 896.29 | O8: 880.14 | P8: 909.35 | Q8: 917.25 | R8: 900.92 | S8: 952.59 | T8: 967.92 | U8: 940.32 | V8: 940.77 | W8: 950.17 | X8: 934.39 | Y8: 942.16 | Z8: 890.41 | AA8: 850.79 | AB8: 919.21 | AC8: 847.7 | AD8: 847.7 | AE8: 847.7 | AF8: 847.7 | AH8: 847.7 | AI8: 847.7 | AJ8: 847.7 | AK8: 847.7
A9: JPY100KRW_end | C9: 원/100Y(기말) | E9: 954.9 | F9: 993.29 | G9: 955.54 | H9: 955.54 | I9: 980.62 | J9: 913.67 | K9: 901.47 | L9: 917.04 | M9: 917.04 | N9: 892.42 | O9: 857.76 | P9: 919.21 | Q9: 939.65 | R9: 939.65 | S9: 986.84 | T9: 938.85 | U9: 948.49 | V9: 921.81 | W9: 921.81 | X9: 955.99 | Y9: 954.75 | Z9: 863.31 | AA9: 847.7 | AB9: 847.7 | AC9: 847.7 | AD9: 847.7 | AE9: 847.7 | AF9: 847.7 | AH9: 847.7 | AI9: 847.7 | AJ9: 847.7 | AK9: 847.7
A10: EURKRW_avg | C10: W/Euro(평균) | E10: 1343.31 | F10: 1350.63 | G10: 1386.07 | H10: 1358.07 | I10: 1369.93 | J10: 1432.41 | K10: 1429.41 | L10: 1420.91 | M10: 1412.88 | N10: 1444.21 | O10: 1476.42 | P10: 1489.3 | Q10: 1490.78 | R10: 1475.4 | S10: 1528.33 | T10: 1585.13 | U10: 1620.04 | V10: 1686.02 | W10: 1605.45 | X10: 1715.47 | Y10: 1746.09 | Z10: 1631.97 | AA10: 1509.74 | AB10: 1689.95 | AC10: 1503.27 | AD10: 1503.27 | AE10: 1503.27 | AF10: 1503.27 | AH10: 1503.27 | AI10: 1503.27 | AJ10: 1503.27 | AK10: 1503.27
A11: EURKRW_end | C11: W/Euro(기말) | E11: 1351.6 | F11: 1400.62 | G11: 1344.08 | H11: 1344.08 | I11: 1420.26 | J11: 1435.88 | K11: 1425.26 | L11: 1433.66 | M11: 1433.66 | N11: 1458.68 | O11: 1474.86 | P11: 1469.1 | Q11: 1532.14 | R11: 1532.14 | S11: 1594.72 | T11: 1588.22 | U11: 1648.04 | V11: 1696.94 | W11: 1696.94 | X11: 1753.21 | Y11: 1767.09 | Z11: 1539.06 | AA11: 1503.27 | AB11: 1503.27 | AC11: 1503.27 | AD11: 1503.27 | AE11: 1503.27 | AF11: 1503.27 | AH11: 1503.27 | AI11: 1503.27 | AJ11: 1503.27 | AK11: 1503.27
A12: CNYKRW_avg | C12: 원/중국원(평균) | E12: 190.76 | F12: 195.79 | G12: 191.09 | H12: 191.93 | I12: 186.59 | J12: 187.45 | K12: 181.28 | L12: 182.86 | M12: 184.52 | N12: 185.04 | O12: 189.35 | P12: 189.24 | Q12: 194.24 | R12: 189.49 | S12: 199.63 | T12: 193.41 | U12: 193.79 | V12: 204.38 | W12: 197.8 | X12: 211.75 | Y12: 220.8 | Z12: 210.43 | AA12: 200.69 | AB12: 213.75 | AC12: 200.46 | AD12: 200.46 | AE12: 200.46 | AF12: 200.46 | AH12: 200.46 | AI12: 200.46 | AJ12: 200.46 | AK12: 200.46
A13: CNYKRW_end | C13: 원/중국원(기말) | E13: 194.13 | F13: 201.92 | G13: 182.67 | H13: 182.67 | I13: 189.97 | J13: 181.8 | K13: 184.26 | L13: 182.61 | M13: 182.61 | N13: 186.66 | O13: 189.7 | P13: 187.12 | Q13: 202.04 | R13: 202.04 | S13: 203.3 | T13: 189.14 | U13: 197.16 | V13: 206.28 | W13: 206.28 | X13: 220.97 | Y13: 228.56 | Z13: 202.16 | AA13: 200.46 | AB13: 200.46 | AC13: 200.46 | AD13: 200.46 | AE13: 200.46 | AF13: 200.46 | AH13: 200.46 | AI13: 200.46 | AJ13: 200.46 | AK13: 200.46
B14: 1b. 종가
A15: price_close_end | C15: 종가(기말) | E15: 35250 | F15: 25600 | G15: 26100 | I15: 27600 | J15: 28450 | K15: 19740 | L15: 20250 | N15: 18530 | O15: 22200 | P15: 15810 | Q15: 12830 | S15: 14170 | T15: 18130 | U15: 28550 | V15: 26200 | X15: 25750 | Y15: 24150 | Z15: 25050 | AA15: 24400
A16: price_high | C16: 종가(최고) | E16: 52400 | F16: 45250 | G16: 33500 | I16: 31450 | J16: 32300 | K16: 28850 | L16: 23100 | N16: 21700 | O16: 29500 | P16: 21950 | Q16: 16090 | S16: 16780 | T16: 21250 | U16: 35950 | V16: 44200 | X16: 36300 | Y16: 43700 | Z16: 28200 | AA16: 26450
A17: price_low | C17: 종가(최저) | E17: 30300 | F17: 25000 | G17: 23600 | I17: 24050 | J17: 25950 | K17: 19400 | L17: 16630 | N17: 17210 | O17: 17300 | P17: 14500 | Q17: 11300 | S17: 12900 | T17: 12590 | U17: 17000 | V17: 26000 | X17: 24350 | Y17: 21100 | Z17: 11810 | AA17: 24050
A18: price_avg | C18: 종가(평균) | E18: 37470 | F18: 32902.4 | G18: 27931.5 | I18: 28058.1 | J18: 28250.8 | K18: 23875 | L18: 18674.3 | N18: 18942.6 | O18: 20921.3 | P18: 17361.5 | Q18: 13716.7 | S18: 14663.8 | T18: 16378.5 | U18: 21695.5 | V18: 30210.2 | X18: 30416.9 | Y18: 29614.8 | Z18: 18741.1 | AA18: 25150
B20: 2. 추정 드라이버 | C20: 실적 열 = subQ 실현값(수식), 추정 열 = 가정(노란 = 모델값 역산, 연녹 = 3절 스칼라 참조)
A21: drv:매출액 | B21: yoy | C21: 매출액 YoY | J21: =IFERROR(subQ!J5/subQ!E5-1,"") | K21: =IFERROR(subQ!K5/subQ!F5-1,"") | L21: =IFERROR(subQ!L5/subQ!G5-1,"") | N21: =IFERROR(subQ!N5/subQ!I5-1,"") | O21: =IFERROR(subQ!O5/subQ!J5-1,"") | P21: =IFERROR(subQ!P5/subQ!K5-1,"") | Q21: =IFERROR(subQ!Q5/subQ!L5-1,"") | S21: =IFERROR(subQ!S5/subQ!N5-1,"") | T21: =IFERROR(subQ!T5/subQ!O5-1,"") | U21: =IFERROR(subQ!U5/subQ!P5-1,"") | V21: =IFERROR(subQ!V5/subQ!Q5-1,"") | X21: =IFERROR(subQ!X5/subQ!S5-1,"") | Y21: =IFERROR(subQ!Y5/subQ!T5-1,"") | Z21: 0.28965316 | AA21: 0.28958786 | AC21: 0.28970217 | AD21: 0.28959399 | AE21: 0.14473194 | AF21: 0.14480682 | AH21: 0.14467628 | AI21: 0.14482099 | AJ21: 0.072433559 | AK21: 0.07240533
A22: drv:판관비 | B22: ratio | C22: 판관비율(/매출) | E22: =IFERROR(subQ!E8/subQ!E5,"") | F22: =IFERROR(subQ!F8/subQ!F5,"") | G22: =IFERROR(subQ!G8/subQ!G5,"") | H22: =IFERROR(subQ!H8/subQ!H5,"") | I22: =IFERROR(subQ!I8/subQ!I5,"") | J22: =IFERROR(subQ!J8/subQ!J5,"") | K22: =IFERROR(subQ!K8/subQ!K5,"") | L22: =IFERROR(subQ!L8/subQ!L5,"") | ... Y22: =IFERROR(subQ!Y8/subQ!Y5,"") | Z22: =$D$48 | AA22: =$D$48 | AB22: =IFERROR(subQ!AB8/subQ!AB5,"") | AC22: =$D$48 | AD22: =$D$48 | AE22: =$D$48 | AF22: =$D$48 | AG22: =IFERROR(subQ!AG8/subQ!AG5,"") | AH22: =$D$48 | AI22: =$D$48 | AJ22: =$D$48 | AK22: =$D$48 | AL22: =IFERROR(subQ!AL8/subQ!AL5,"")
A23: drv:영업이익 | B23: ratio | C23: 영업이익률(OPM) | E23: =IFERROR(subQ!E9/subQ!E5,"") | F23: =IFERROR(subQ!F9/subQ!F5,"") | G23: =IFERROR(subQ!G9/subQ!G5,"") | H23: =IFERROR(subQ!H9/subQ!H5,"") | I23: =IFERROR(subQ!I9/subQ!I5,"") | J23: =IFERROR(subQ!J9/subQ!J5,"") | K23: =IFERROR(subQ!K9/subQ!K5,"") | L23: =IFERROR(subQ!L9/subQ!L5,"") | ... Y23: =IFERROR(subQ!Y9/subQ!Y5,"") | Z23: 0.014167474 | AA23: 0.014199699 | AB23: =IFERROR(subQ!AB9/subQ!AB5,"") | AC23: 0.01426818 | AD23: 0.014181929 | AE23: 0.014200104 | AF23: 0.014200561 | AG23: =IFERROR(subQ!AG9/subQ!AG5,"") | AH23: 0.014207211 | AI23: 0.014211886 | AJ23: 0.014212828 | AK23: 0.014222658 | AL23: =IFERROR(subQ!AL9/subQ!AL5,"")
A24: drv:기타영업외손익 | B24: abs | C24: 기타영업외손익 (가정, 억원) | E24: =subQ!E13 | F24: =subQ!F13 | G24: =subQ!G13 | H24: =subQ!H13 | I24: =subQ!I13 | J24: =subQ!J13 | K24: =subQ!K13 | L24: =subQ!L13 | ... Y24: =subQ!Y13 | Z24: 0 | AA24: 0 | AB24: =subQ!AB13 | AC24: 0 | AD24: 0 | AE24: 0 | AF24: 0 | AG24: =subQ!AG13 | AH24: 0 | AI24: 0 | AJ24: 0 | AK24: 0 | AL24: =subQ!AL13
A25: drv:법인세비용 | B25: ratio | C25: 법인세율(/세전) | E25: =IFERROR(subQ!E15/subQ!E14,"") | F25: =IFERROR(subQ!F15/subQ!F14,"") | G25: =IFERROR(subQ!G15/subQ!G14,"") | H25: =IFERROR(subQ!H15/subQ!H14,"") | I25: =IFERROR(subQ!I15/subQ!I14,"") | J25: =IFERROR(subQ!J15/subQ!J14,"") | K25: =IFERROR(subQ!K15/subQ!K14,"") | L25: =IFERROR(subQ!L15/subQ!L14,"") | ... Y25: =IFERROR(subQ!Y15/subQ!Y14,"") | Z25: 0 | AA25: 0 | AB25: =IFERROR(subQ!AB15/subQ!AB14,"") | AC25: 0 | AD25: 0 | AE25: 0 | AF25: 0 | AG25: =IFERROR(subQ!AG15/subQ!AG14,"") | AH25: 0 | AI25: 0 | AJ25: 0 | AK25: 0 | AL25: =IFERROR(subQ!AL15/subQ!AL14,"")
A26: drv:지배주주순이익 | B26: ratio | C26: 지배주주 비중(/당기순이익) | E26: =IFERROR(subQ!E17/subQ!E16,"") | F26: =IFERROR(subQ!F17/subQ!F16,"") | G26: =IFERROR(subQ!G17/subQ!G16,"") | H26: =IFERROR(subQ!H17/subQ!H16,"") | I26: =IFERROR(subQ!I17/subQ!I16,"") | J26: =IFERROR(subQ!J17/subQ!J16,"") | K26: =IFERROR(subQ!K17/subQ!K16,"") | L26: =IFERROR(subQ!L17/subQ!L16,"") | ... Y26: =IFERROR(subQ!Y17/subQ!Y16,"") | Z26: =$D$49 | AA26: =$D$49 | AB26: =IFERROR(subQ!AB17/subQ!AB16,"") | AC26: =$D$49 | AD26: =$D$49 | AE26: =$D$49 | AF26: =$D$49 | AG26: =IFERROR(subQ!AG17/subQ!AG16,"") | AH26: =$D$49 | AI26: =$D$49 | AJ26: =$D$49 | AK26: =$D$49 | AL26: =IFERROR(subQ!AL17/subQ!AL16,"")
A27: drv:감가상각비 | B27: abs | C27: 감가상각비 (가정, 억원) | E27: =subQ!E18 | F27: =subQ!F18 | G27: =subQ!G18 | H27: =subQ!H18 | I27: =subQ!I18 | J27: =subQ!J18 | K27: =subQ!K18 | L27: =subQ!L18 | ... Y27: =subQ!Y18 | Z27: 5.16 | AA27: 5.16 | AB27: =subQ!AB18 | AC27: 5.16 | AD27: 5.16 | AE27: 5.16 | AF27: 5.16 | AG27: =subQ!AG18 | AH27: 5.16 | AI27: 5.16 | AJ27: 5.16 | AK27: 5.16 | AL27: =subQ!AL18
A28: drv:부채총계 | B28: qoq | C28: 부채총계 QoQ | F28: =IFERROR(subQ!F21/subQ!E21-1,"") | G28: =IFERROR(subQ!G21/subQ!F21-1,"") | I28: =IFERROR(subQ!I21/subQ!G21-1,"") | J28: =IFERROR(subQ!J21/subQ!I21-1,"") | K28: =IFERROR(subQ!K21/subQ!J21-1,"") | L28: =IFERROR(subQ!L21/subQ!K21-1,"") | N28: =IFERROR(subQ!N21/subQ!L21-1,"") | O28: =IFERROR(subQ!O21/subQ!N21-1,"") | P28: =IFERROR(subQ!P21/subQ!O21-1,"") | Q28: =IFERROR(subQ!Q21/subQ!P21-1,"") | S28: =IFERROR(subQ!S21/subQ!Q21-1,"") | T28: =IFERROR(subQ!T21/subQ!S21-1,"") | U28: =IFERROR(subQ!U21/subQ!T21-1,"") | V28: =IFERROR(subQ!V21/subQ!U21-1,"") | X28: =IFERROR(subQ!X21/subQ!V21-1,"") | Y28: =IFERROR(subQ!Y21/subQ!X21-1,"") | Z28: 2.395e-06 | AA28: 0 | AC28: 0 | AD28: 0 | AE28: 0 | AF28: 0 | AH28: 0 | AI28: 0 | AJ28: 0 | AK28: 0
A29: drv:자본총계 | B29: roll | C29: 자본총계 기타변동(배당 등, 억원) | F29: =IFERROR(subQ!E22+subQ!F16-subQ!F22,"") | G29: =IFERROR(subQ!F22+subQ!G16-subQ!G22,"") | I29: =IFERROR(subQ!G22+subQ!I16-subQ!I22,"") | J29: =IFERROR(subQ!I22+subQ!J16-subQ!J22,"") | K29: =IFERROR(subQ!J22+subQ!K16-subQ!K22,"") | L29: =IFERROR(subQ!K22+subQ!L16-subQ!L22,"") | N29: =IFERROR(subQ!L22+subQ!N16-subQ!N22,"") | O29: =IFERROR(subQ!N22+subQ!O16-subQ!O22,"") | P29: =IFERROR(subQ!O22+subQ!P16-subQ!P22,"") | Q29: =IFERROR(subQ!P22+subQ!Q16-subQ!Q22,"") | S29: =IFERROR(subQ!Q22+subQ!S16-subQ!S22,"") | T29: =IFERROR(subQ!S22+subQ!T16-subQ!T22,"") | U29: =IFERROR(subQ!T22+subQ!U16-subQ!U22,"") | V29: =IFERROR(subQ!U22+subQ!V16-subQ!V22,"") | X29: =IFERROR(subQ!V22+subQ!X16-subQ!X22,"") | Y29: =IFERROR(subQ!X22+subQ!Y16-subQ!Y22,"") | Z29: -0.007541919 | AA29: 0.000416409 | AC29: 0.000543429 | AD29: -0.013436241 | AE29: -5.263e-06 | AF29: -0.000646678 | AH29: 0.00070409 | AI29: 0.004521633 | AJ29: -8.934e-05 | AK29: 0.00743363
A30: drv:지배주주지분 | B30: roll | C30: 지배주주지분 기타변동(배당 등, 억원) | F30: =IFERROR(subQ!E23+subQ!F17-subQ!F23,"") | G30: =IFERROR(subQ!F23+subQ!G17-subQ!G23,"") | I30: =IFERROR(subQ!G23+subQ!I17-subQ!I23,"") | J30: =IFERROR(subQ!I23+subQ!J17-subQ!J23,"") | K30: =IFERROR(subQ!J23+subQ!K17-subQ!K23,"") | L30: =IFERROR(subQ!K23+subQ!L17-subQ!L23,"") | N30: =IFERROR(subQ!L23+subQ!N17-subQ!N23,"") | O30: =IFERROR(subQ!N23+subQ!O17-subQ!O23,"") | P30: =IFERROR(subQ!O23+subQ!P17-subQ!P23,"") | Q30: =IFERROR(subQ!P23+subQ!Q17-subQ!Q23,"") | S30: =IFERROR(subQ!Q23+subQ!S17-subQ!S23,"") | T30: =IFERROR(subQ!S23+subQ!T17-subQ!T23,"") | U30: =IFERROR(subQ!T23+subQ!U17-subQ!U23,"") | V30: =IFERROR(subQ!U23+subQ!V17-subQ!V23,"") | X30: =IFERROR(subQ!V23+subQ!X17-subQ!X23,"") | Y30: =IFERROR(subQ!X23+subQ!Y17-subQ!Y23,"") | Z30: -0.009441919 | AA30: 0.000416409 | AC30: 0.000543429 | AD30: -0.003436241 | AE30: -5.263e-06 | AF30: -0.010646678 | AH30: 0.00070409 | AI30: 0.004521633 | AJ30: 0.00991066 | AK30: -0.00256637
A31: drv:총차입금 | B31: qoq | C31: 총차입금 QoQ | F31: =IFERROR(subQ!F24/subQ!E24-1,"") | G31: =IFERROR(subQ!G24/subQ!F24-1,"") | I31: =IFERROR(subQ!I24/subQ!G24-1,"") | J31: =IFERROR(subQ!J24/subQ!I24-1,"") | K31: =IFERROR(subQ!K24/subQ!J24-1,"") | L31: =IFERROR(subQ!L24/subQ!K24-1,"") | N31: =IFERROR(subQ!N24/subQ!L24-1,"") | O31: =IFERROR(subQ!O24/subQ!N24-1,"") | P31: =IFERROR(subQ!P24/subQ!O24-1,"") | Q31: =IFERROR(subQ!Q24/subQ!P24-1,"") | S31: =IFERROR(subQ!S24/subQ!Q24-1,"") | T31: =IFERROR(subQ!T24/subQ!S24-1,"") | U31: =IFERROR(subQ!U24/subQ!T24-1,"") | V31: =IFERROR(subQ!V24/subQ!U24-1,"") | X31: =IFERROR(subQ!X24/subQ!V24-1,"") | Y31: =IFERROR(subQ!Y24/subQ!X24-1,"") | Z31: 1.38e-06 | AA31: 0 | AC31: 0 | AD31: 0 | AE31: 0 | AF31: 0 | AH31: 0 | AI31: 0 | AJ31: 0 | AK31: 0
A32: drv:순차입금 | B32: qoq | C32: 순차입금 QoQ | F32: =IFERROR(subQ!F25/subQ!E25-1,"") | G32: =IFERROR(subQ!G25/subQ!F25-1,"") | I32: =IFERROR(subQ!I25/subQ!G25-1,"") | J32: =IFERROR(subQ!J25/subQ!I25-1,"") | K32: =IFERROR(subQ!K25/subQ!J25-1,"") | L32: =IFERROR(subQ!L25/subQ!K25-1,"") | N32: =IFERROR(subQ!N25/subQ!L25-1,"") | O32: =IFERROR(subQ!O25/subQ!N25-1,"") | P32: =IFERROR(subQ!P25/subQ!O25-1,"") | Q32: =IFERROR(subQ!Q25/subQ!P25-1,"") | S32: =IFERROR(subQ!S25/subQ!Q25-1,"") | T32: =IFERROR(subQ!T25/subQ!S25-1,"") | U32: =IFERROR(subQ!U25/subQ!T25-1,"") | V32: =IFERROR(subQ!V25/subQ!U25-1,"") | X32: =IFERROR(subQ!X25/subQ!V25-1,"") | Y32: =IFERROR(subQ!Y25/subQ!X25-1,"") | Z32: 0.006490235 | AA32: 0.005606263 | AC32: 0.00751159 | AD32: 0.005281041 | AE32: 0.006363829 | AF32: 0.005383206 | AH32: 0.007501861 | AI32: 0.005001895 | AJ32: 0.006353216 | AK32: 0.005329612
A33: drv:이자발생자산 | B33: qoq | C33: 이자발생자산 QoQ | F33: =IFERROR(subQ!F26/subQ!E26-1,"") | G33: =IFERROR(subQ!G26/subQ!F26-1,"") | I33: =IFERROR(subQ!I26/subQ!G26-1,"") | J33: =IFERROR(subQ!J26/subQ!I26-1,"") | K33: =IFERROR(subQ!K26/subQ!J26-1,"") | L33: =IFERROR(subQ!L26/subQ!K26-1,"") | N33: =IFERROR(subQ!N26/subQ!L26-1,"") | O33: =IFERROR(subQ!O26/subQ!N26-1,"") | P33: =IFERROR(subQ!P26/subQ!O26-1,"") | Q33: =IFERROR(subQ!Q26/subQ!P26-1,"") | S33: =IFERROR(subQ!S26/subQ!Q26-1,"") | T33: =IFERROR(subQ!T26/subQ!S26-1,"") | U33: =IFERROR(subQ!U26/subQ!T26-1,"") | V33: =IFERROR(subQ!V26/subQ!U26-1,"") | X33: =IFERROR(subQ!X26/subQ!V26-1,"") | Y33: =IFERROR(subQ!Y26/subQ!X26-1,"") | Z33: -0.02202364 | AA33: -0.01963819 | AC33: -0.026942642 | AD33: -0.019612792 | AE33: -0.024234178 | AF33: -0.021142685 | AH33: -0.030262195 | AI33: -0.020963195 | AJ33: -0.02733282 | AK33: -0.02372316
A34: drv:현금및현금성자산 | B34: qoq | C34: 현금및현금성자산 QoQ | F34: =IFERROR(subQ!F27/subQ!E27-1,"") | G34: =IFERROR(subQ!G27/subQ!F27-1,"") | I34: =IFERROR(subQ!I27/subQ!G27-1,"") | J34: =IFERROR(subQ!J27/subQ!I27-1,"") | K34: =IFERROR(subQ!K27/subQ!J27-1,"") | L34: =IFERROR(subQ!L27/subQ!K27-1,"") | N34: =IFERROR(subQ!N27/subQ!L27-1,"") | O34: =IFERROR(subQ!O27/subQ!N27-1,"") | P34: =IFERROR(subQ!P27/subQ!O27-1,"") | Q34: =IFERROR(subQ!Q27/subQ!P27-1,"") | S34: =IFERROR(subQ!S27/subQ!Q27-1,"") | T34: =IFERROR(subQ!T27/subQ!S27-1,"") | U34: =IFERROR(subQ!U27/subQ!T27-1,"") | V34: =IFERROR(subQ!V27/subQ!U27-1,"") | X34: =IFERROR(subQ!X27/subQ!V27-1,"") | Y34: =IFERROR(subQ!Y27/subQ!X27-1,"")
A35: drv:영업활동현금흐름 | B35: yoy | C35: 영업활동현금흐름 YoY | J35: =IFERROR(subQ!J28/subQ!E28-1,"") | K35: =IFERROR(subQ!K28/subQ!F28-1,"") | L35: =IFERROR(subQ!L28/subQ!G28-1,"") | N35: =IFERROR(subQ!N28/subQ!I28-1,"") | O35: =IFERROR(subQ!O28/subQ!J28-1,"") | P35: =IFERROR(subQ!P28/subQ!K28-1,"") | Q35: =IFERROR(subQ!Q28/subQ!L28-1,"") | S35: =IFERROR(subQ!S28/subQ!N28-1,"") | T35: =IFERROR(subQ!T28/subQ!O28-1,"") | U35: =IFERROR(subQ!U28/subQ!P28-1,"") | V35: =IFERROR(subQ!V28/subQ!Q28-1,"") | X35: =IFERROR(subQ!X28/subQ!S28-1,"") | Y35: =IFERROR(subQ!Y28/subQ!T28-1,"")
A36: drv:주식수 | B36: qoq | C36: 주식수 QoQ | F36: =IFERROR(subQ!F29/subQ!E29-1,"") | G36: =IFERROR(subQ!G29/subQ!F29-1,"") | I36: =IFERROR(subQ!I29/subQ!G29-1,"") | J36: =IFERROR(subQ!J29/subQ!I29-1,"") | K36: =IFERROR(subQ!K29/subQ!J29-1,"") | L36: =IFERROR(subQ!L29/subQ!K29-1,"") | N36: =IFERROR(subQ!N29/subQ!L29-1,"") | O36: =IFERROR(subQ!O29/subQ!N29-1,"") | P36: =IFERROR(subQ!P29/subQ!O29-1,"") | Q36: =IFERROR(subQ!Q29/subQ!P29-1,"") | S36: =IFERROR(subQ!S29/subQ!Q29-1,"") | T36: =IFERROR(subQ!T29/subQ!S29-1,"") | U36: =IFERROR(subQ!U29/subQ!T29-1,"") | V36: =IFERROR(subQ!V29/subQ!U29-1,"") | X36: =IFERROR(subQ!X29/subQ!V29-1,"") | Y36: =IFERROR(subQ!Y29/subQ!X29-1,"") | Z36: 0 | AA36: 0 | AC36: 0 | AD36: 0 | AE36: 0 | AF36: 0 | AH36: 0 | AI36: 0 | AJ36: 0 | AK36: 0
A37: drv:DPS | B37: abs | C37: DPS (가정, 원) | E37: =subQ!E32 | F37: =subQ!F32 | G37: =subQ!G32 | H37: =subQ!H32 | I37: =subQ!I32 | J37: =subQ!J32 | K37: =subQ!K32 | L37: =subQ!L32 | ... Y37: =subQ!Y32 | AA37: 0 | AB37: =subQ!AB32 | AF37: 0 | AG37: =subQ!AG32 | AK37: 0 | AL37: =subQ!AL32
B39: 3. 밸류에이션·스칼라 | C39: 노란 셀 = 가정. '연결' 표시는 추정 전 분기 수식이 이 셀을 참조한다는 뜻
A40: sc:종가 | C40: 종가 | D40: 24400 | E40: 원 — 네이버 정규장 종가(aik 확정종가 대조 · aik 25,150원)
A41: sc:기준일 | C41: 기준일 | D41: 20261008 | E41: 종가 기준일
A42: sc:COE | C42: COE | D42: 0.09 | E42: 자기자본비용(가정) — TP 적정 PBR = ROE/COE
A43: sc:PER_lo | C43: PER_lo | D43: 10 | E43: PER 밴드 하단(배) — sector_default(레퍼런스 TP_PE PB 예시 10/15/20배; 과거 PER 중위 152.1배가 3~40 밖(턴어라운드 왜곡))
A44: sc:PER_mid | C44: PER_mid | D44: 15 | E44: PER 밴드 중단(배)
A45: sc:PER_hi | C45: PER_hi | D45: 20 | E45: PER 밴드 상단(배)
A46: sc:EPS_Y1가중 | C46: EPS_Y1가중 | D46: 0.5 | E46: 12M fwd EPS = FY(last_actual연도)E × w + FY+1E × (1−w) — 기준 분기 2Q 이면 0.5(가정)
A47: sc:세율 | C47: 세율 | D47: 0.22 | E47: 참고(연결 안 됨: MAX(세전,0)×단일 세율로 재현 불가(지주 자회사 합산 등) → 분기별 역산) — 모델 assumptions 값 · 최근 12분기 세전 합 ≤ 0; 세전 > 0 분기 중위 0.0% 도 5~27% 밖 → 법정세율 근사 22% 가정
A48: sc:판관비율 | C48: 판관비율 | D48: 0.093738441 | E48: 연결 — 판관비 = 매출액 × 판관비율(역산, 재현 오차 ≤ 0.05억 · 모델 assumptions 0.0937)
A49: sc:지배주주비중 | C49: 지배주주비중 | D49: 1 | E49: 연결 — 지배주주순이익 = 당기순이익 × 비중(역산, 재현 오차 ≤ 0.05억)
A50: sc:이자율_자산 | C50: 이자율_자산 | D50: 0.048947769 | E50: 연결 — 이자손익 = (전분기 이자발생자산 × 자산이자율 − 전분기 총차입금 × 부채이자율)/4(역산, 재현 오차 ≤ 0.05억 · 모델 assumptions 0.0493)
A51: sc:이자율_부채 | C51: 이자율_부채 | D51: 0.039275362 | E51: 연결 — 같은 수식의 부채 쪽(총차입금 행이 없으면 0)(역산, 재현 오차 ≤ 0.05억 · 모델 assumptions 0.0393)
A52: sc:배당성향 | C52: 배당성향 | D52: 0 | E52: 배당성향(참고 — 모델은 직전 DPS 유지·Q2 지급 가정)
A53: sc:외화순노출_백만$ | C53: 외화순노출_백만$ | E53: 외화 순노출 × Δ기말환율 (외화 시트 방식) — 외화 순노출 미공시(face) → 0 + 표기
A54: sc:헤지비율 | C54: 헤지비율 | E54: sls 없음
A55: sc:헤지환율_약정 | C55: 헤지환율_약정 | E55: sls 없음

Sheet BS연결
B1: (백만원) | C1: 이름: BS연결H | E1: 2Q22 | F1: 3Q22 | G1: 4Q22 | H1: 2022 | I1: 1Q23 | J1: 2Q23 | K1: 3Q23 | L1: 4Q23 | M1: 2023 | N1: 1Q24 | O1: 2Q24 | P1: 3Q24 | Q1: 4Q24 | R1: 2024 | S1: 1Q25 | T1: 2Q25 | U1: 3Q25 | V1: 4Q25 | W1: 2025 | X1: 1Q26 | Y1: 2Q26 | Z1: 3Q26 | AA1: 4Q26 | AB1: 2026 | AC1: 1Q27 | AD1: 2Q27 | AE1: 3Q27 | AF1: 4Q27 | AG1: 2027 | AH1: 1Q28 | AI1: 2Q28 | AJ1: 3Q28 | AK1: 4Q28 | AL1: 2028
B2: 연결 | D2: fin json(kship_fin.py)
B3: 범한퓨얼셀(연) | C3: UPDATE: 26-10-11 | E3: 1 | F3: 2 | G3: 3 | H3: 4 | I3: 5 | J3: 6 | K3: 7 | L3: 8 | M3: 9 | N3: 10 | O3: 11 | P3: 12 | Q3: 13 | R3: 14 | S3: 15 | T3: 16 | U3: 17 | V3: 18 | W3: 19 | X3: 20 | Y3: 21 | Z3: 22 | AA3: 23 | AB3: 24 | AC3: 25 | AD3: 26 | AE3: 27 | AF3: 28 | AG3: 29 | AH3: 30 | AI3: 31 | AJ3: 32 | AK3: 33 | AL3: 34
B4: Account Code | C4: AccountNAME | E4: 2022.06 | F4: 2022.09 | G4: 2022.12 | H4: 2022.12A | I4: 2023.03 | J4: 2023.06 | K4: 2023.09 | L4: 2023.12 | M4: 2023.12A | N4: 2024.03 | O4: 2024.06 | P4: 2024.09 | Q4: 2024.12 | R4: 2024.12A | S4: 2025.03 | T4: 2025.06 | U4: 2025.09 | V4: 2025.12 | W4: 2025.12A | X4: 2026.03 | Y4: 2026.06 | Z4: 2026.09 | AA4: 2026.12 | AB4: 2026.12A | AC4: 2027.03 | AD4: 2027.06 | AE4: 2027.09 | AF4: 2027.12 | AG4: 2027.12A | AH4: 2028.03 | AI4: 2028.06 | AJ4: 2028.09 | AK4: 2028.12 | AL4: 2028.12A
A5: 1 | C5: 유동자산 | L5: 89028.47 | M5: 89028.47 | N5: 78664.34 | O5: 76383.22 | P5: 72699.49 | Q5: 87944.01 | R5: 87944.01 | S5: 88788.95 | T5: 92384.06 | U5: 86456.73 | V5: 129650.83 | W5: 129650.83 | X5: 125052.52 | Y5: 110872.56
A6: 1 | C6: 현금및현금성자산 | L6: 26732.9 | M6: 26732.9 | N6: 2817.92 | O6: 26929.3 | P6: 17192.62 | Q6: 19597.33 | R6: 19597.33 | S6: 25886.48 | T6: 13731.92 | U6: 7986.22 | V6: 45853.97 | W6: 45853.97 | X6: 21114.54 | Y6: 19840.45
A7: 1 | C7: 단기금융상품 | L7: 15540 | M7: 15540 | N7: 5630 | O7: 5360 | P7: 4450 | Q7: 3540 | R7: 3540 | S7: 600 | T7: 2651.36 | U7: 2651.36 | V7: 2651.36 | W7: 2651.36 | X7: 7651.36 | Y7: 2351
A8: 1 | C8: 단기금융자산 | L8: 15540 | M8: 15540 | N8: 5630 | O8: 5360 | P8: 4450 | Q8: 3540 | R8: 3540 | S8: 600 | T8: 2651.36 | U8: 2651.36 | V8: 2651.36 | W8: 2651.36 | X8: 7651.36 | Y8: 2351
A9: 1 | C9: 단기투자자산(공정가치) | L9: 52.09 | M9: 52.09 | N9: 12.35 | O9: 12.45 | P9: 12.55 | Q9: 2699.87 | R9: 2699.87 | S9: 2687.53 | T9: 2687.53 | U9: 2687.53 | V9: 2887.42 | W9: 2887.42 | X9: 2887.42 | Y9: 2887.42
A10: 1 | C10: 매출채권및기타채권 | L10: 19237.51 | M10: 19237.51 | N10: 41826.51 | O10: 14479.48 | P10: 21479.18 | Q10: 39804.81 | R10: 39804.81 | S10: 42172.66 | T10: 48435.93 | U10: 47634.36 | V10: 48702.23 | W10: 48702.23 | X10: 52310.41 | Y10: 52137.88
A11: 1 | C11: 계약자산 | L11: 9255.73 | M11: 9255.73 | N11: 9095.55 | O11: 9620.15 | P11: 10310.92 | Q11: 5907.38 | R11: 5907.38 | S11: 3323.67 | T11: 10175.87 | U11: 9141.36 | V11: 10343.67 | W11: 10343.67 | X11: 9128.41 | Y11: 439.94
A12: 1 | C12: 재고자산 | L12: 16502.04 | M12: 16502.04 | N12: 18140.08 | O12: 19297.2 | P12: 17761.96 | Q12: 15681.99 | R12: 15681.99 | S12: 12869.69 | T12: 12963.13 | U12: 13808.6 | V12: 14059.45 | W12: 14059.45 | X12: 17938.99 | Y12: 21115.81
A13: 1 | C13: 기타유동자산 | L13: 1241.19 | M13: 1241.19 | N13: 633.31 | O13: 558.69 | P13: 1309.71 | Q13: 508.77 | R13: 508.77 | S13: 1016.64 | T13: 1598.68 | U13: 2333.33 | V13: 4840.5 | W13: 4840.5 | X13: 13698.7 | Y13: 11887.62
A14: 1 | C14: 당기법인세자산(선급법인세) | L14: 467.01 | M14: 467.01 | N14: 508.6 | O14: 125.95 | P14: 182.56 | Q14: 203.85 | R14: 203.85 | S14: 232.28 | T14: 139.64 | U14: 213.95 | V14: 312.22 | W14: 312.22 | X14: 322.68 | Y14: 212.44
A15: 1 | C15: 비유동자산 | L15: 34607.2 | M15: 34607.2 | N15: 152692.81 | O15: 151776.8 | P15: 150386.2 | Q15: 224474.91 | R15: 224474.91 | S15: 225062.59 | T15: 217577.27 | U15: 222901.31 | V15: 222709.94 | W15: 222709.94 | X15: 225990.09 | Y15: 225697.2
A16: 1 | C16: 장기금융자산 | L16: 8106.68 | M16: 8106.68 | N16: 8131.12 | O16: 8131.12 | P16: 8131.12 | Q16: 4631.12 | R16: 4631.12 | S16: 4949.61 | T16: 4949.61 | U16: 8959.61 | V16: 7084.61 | W16: 7084.61 | X16: 7539.33 | Y16: 7539.33
... A21: 1 | C21: 무형자산 | L21: 2717.95 | M21: 2717.95 | N21: 2720.25 | O21: 2682.51 | P21: 5458.7 | Q21: 5237.08 | R21: 5237.08 | S21: 5050.91 | T21: 5052.5 | U21: 4843.19 | V21: 4685.33 | W21: 4685.33 | X21: 4521.93 | Y21: 4541
A22: 1 | C22: 이연법인세자산 | L22: 1237.2 | M22: 1237.2 | N22: 1237.2 | O22: 1102.86 | P22: 1102.86 | Q22: 0 | R22: 0 | V22: 0 | W22: 0
A23: 1 | C23: 자산총계 | L23: 123635.67 | M23: 123635.67 | N23: 231357.15 | O23: 228160.02 | P23: 223085.69 | Q23: 312418.93 | R23: 312418.93 | S23: 313851.54 | T23: 309961.34 | U23: 309358.04 | V23: 352360.77 | W23: 352360.77 | X23: 351042.61 | Y23: 336569.76
A24: 1 | C24: 유동부채 | L24: 10647.87 | M24: 10647.87 | N24: 30796.56 | O24: 28173.41 | P24: 23066.24 | Q24: 41752.13 | R24: 41752.13 | S24: 43001.66 | T24: 40009.22 | U24: 40620.34 | V24: 84803.18 | W24: 84803.18 | X24: 165915.11 | Y24: 163667.48
A25: 1 | C25: 매입채무및기타채무 | L25: 4928.09 | M25: 4928.09 | N25: 5266.91 | O25: 5628.93 | P25: 5560.2 | Q25: 5077.61 | R25: 5077.61 | S25: 5026.43 | T25: 5840.4 | U25: 5867.05 | V25: 12248.55 | W25: 12248.55 | X25: 8297.44 | Y25: 10735.1
A26: 1 | C26: 계약부채 | L26: 0 | M26: 0 | N26: 20064.66 | O26: 16090.44 | P26: 10975.58 | Q26: 9347.55 | R26: 9347.55 | S26: 7708.47 | T26: 4316.21 | U26: 3212.12 | V26: 27046.57 | W26: 27046.57 | X26: 26562.04 | Y26: 14957.59
A27: 1 | C27: 단기차입금 | L27: 5000 | M27: 5000 | N27: 5000 | O27: 6000 | P27: 6000 | Q27: 22785.01 | R27: 22785.01 | S27: 25008.92 | T27: 24737.08 | U27: 26809.57 | V27: 35410.7 | W27: 35410.7 | X27: 120338.23 | Y27: 123207.83
A28: 1 | C28: 유동리스부채 | L28: 167.76 | M28: 167.76 | N28: 153.64 | O28: 134.37 | P28: 120.25 | Q28: 120.62 | R28: 120.62 | S28: 119.08 | T28: 116.23 | U28: 168.46 | V28: 163.92 | W28: 163.92 | X28: 154.52 | Y28: 146.75
A29: 1 | C29: 리스부채 | L29: 1217.15 | M29: 1217.15 | N29: 1186.97 | O29: 1136.75 | P29: 1103.64 | Q29: 1080.55 | R29: 1080.55 | S29: 1010.5 | T29: 987.56 | U29: 1448.35 | V29: 1140.94 | W29: 1140.94 | X29: 1108.1 | Y29: 1076.37
A30: 1 | C30: 단기금융부채 | L30: 167.76 | M30: 167.76 | N30: 153.64 | O30: 134.37 | P30: 120.25 | Q30: 4201.66 | R30: 4201.66 | S30: 4200.12 | T30: 4197.27 | U30: 4249.5 | V30: 9718.49 | W30: 9718.49 | X30: 9709.09 | Y30: 13520.55
A31: 1 | C31: 당기법인세부채(미지급법인세) | L31: 0 | M31: 0
A32: 1 | C32: 단기충당부채 | L32: 103.86 | M32: 103.86 | N32: 126.2 | O32: 122.91 | P32: 163.36 | Q32: 106.93 | R32: 106.93 | S32: 841.34 | T32: 712.65 | U32: 291.24 | V32: 246.66 | W32: 246.66 | X32: 835.29 | Y32: 1005.26
A33: 1 | C33: 기타유동부채 | L33: 448.16 | M33: 448.16 | N33: 185.15 | O33: 196.75 | P33: 246.84 | Q33: 233.37 | R33: 233.37 | S33: 216.39 | T33: 205.62 | U33: 190.87 | V33: 132.21 | W33: 132.21 | X33: 173.03 | Y33: 241.16
A34: 1 | C34: 비유동부채 | L34: 7091.18 | M34: 7091.18 | N34: 95286.74 | O34: 93806.17 | P34: 93134.17 | Q34: 104814.39 | R34: 104814.39 | S34: 105070.2 | T34: 104639.26 | U34: 103195.48 | V34: 104864.33 | W34: 104864.33 | X34: 24091.29 | Y34: 15842.09
A35: 1 | C35: 장기차입금 | L35: 3090 | M35: 3090 | N35: 91090 | O35: 90090 | P35: 90090 | Q35: 90090 | R35: 90090 | S35: 90090 | T35: 90090 | U35: 88000 | V35: 88000 | W35: 88000 | X35: 7025.28 | Y35: 0
A36: 1 | C36: 비유동리스부채 | L36: 1049.39 | M36: 1049.39 | N36: 1033.33 | O36: 1002.38 | P36: 983.39 | Q36: 959.93 | R36: 959.93 | S36: 891.42 | T36: 871.33 | U36: 1279.89 | V36: 977.02 | W36: 977.02 | X36: 953.58 | Y36: 929.62
A37: 1 | C37: 장기금융부채 | L37: 1049.39 | M37: 1049.39 | N37: 1033.33 | O37: 1002.38 | P37: 983.39 | Q37: 959.93 | R37: 959.93 | S37: 891.42 | T37: 871.33 | U37: 1279.89 | V37: 977.02 | W37: 977.02 | X37: 953.58 | Y37: 929.62
A38: 1 | C38: 확정급여부채 | L38: 338.53 | M38: 338.53 | N38: 488.6 | O38: 625.52 | P38: 759.51 | Q38: 913.67 | R38: 913.67 | S38: 1093.17 | T38: 1277.01 | U38: 1451.31 | V38: 760 | W38: 760 | X38: 957.75 | Y38: 990.04
A39: 1 | C39: 기타비유동부채 | L39: 30.43 | M39: 30.43 | N39: 31.98 | O39: 33.54 | P39: 35.1 | Q39: 34.93 | R39: 34.93 | S39: 36.59 | T39: 38.39 | U39: 40.12 | V39: 43.77 | W39: 43.77 | X39: 45.65 | Y39: 47.54
A40: 1 | C40: 부채총계 | L40: 17739.06 | M40: 17739.06 | N40: 126083.3 | O40: 121979.57 | P40: 116200.41 | Q40: 146566.52 | R40: 146566.52 | S40: 148071.87 | T40: 144648.48 | U40: 143815.82 | V40: 189667.51 | W40: 189667.51 | X40: 190006.4 | Y40: 179509.57
A41: 1 | C41: 지배주주지분 | L41: 103901.83 | M41: 103901.83 | N41: 103319.43 | O41: 104241.26 | P41: 105016.48 | Q41: 164067.07 | R41: 164067.07 | S41: 164071.91 | T41: 163694.17 | U41: 164030.72 | V41: 161305.57 | W41: 161305.57 | X41: 159659.58 | Y41: 155873
A42: 1 | C42: 자본금 | L42: 4380.5 | M42: 4380.5 | N42: 4380.5 | O42: 4380.5 | P42: 4380.5 | Q42: 4380.5 | R42: 4380.5 | S42: 4380.5 | T42: 4380.5 | U42: 4380.5 | V42: 4380.5 | W42: 4380.5 | X42: 4380.5 | Y42: 4380.5
A43: 1 | C43: 자본잉여금 | L43: 92513.42 | M43: 92513.42 | N43: 92527.79 | O43: 92538.2 | P43: 92538.2 | Q43: 92538.2 | R43: 92538.2 | S43: 92538.2 | T43: 92538.2 | U43: 92538.2 | V43: 92538.2 | W43: 92538.2 | X43: 92538.2 | Y43: 92538.2
... A50: 1 | C50: 이자발생자산 | L50: 50379.58 | M50: 50379.58 | N50: 16579.04 | O50: 40420.42 | P50: 29773.74 | Q50: 27768.45 | R50: 27768.45 | S50: 31436.09 | T50: 21332.89 | U50: 19597.19 | V50: 55589.94 | W50: 55589.94 | X50: 36305.23 | Y50: 29730.78
A51: 1 | C51: 투자부동산 | O51: 116302.65 | P51: 116194.1
A52: 1 | C52: 기타유동금융부채 | Q52: 4081.04 | R52: 4081.04 | S52: 4081.04 | T52: 4081.04 | U52: 4081.04 | V52: 9554.57 | W52: 9554.57 | X52: 9554.57 | Y52: 13373.8
A53: 1 | C53: 이연법인세부채 | Q53: 11480.74 | R53: 11480.74 | S53: 11480.74 | T53: 11555.1 | U53: 11555.1 | V53: 14160.66 | W53: 14160.66 | X53: 14160.66 | Y53: 12939.38
A54: 1 | C54: 기타포괄이익누계액 | Q54: 59696.31 | R54: 59696.31 | S54: 59696.31 | T54: 59696.31 | U54: 59696.31 | V54: 55451.44 | W54: 55451.44 | X54: 55451.44 | Y54: 55451.44
A55: 1 | C55: 사채 | Q55: 11785.01 | R55: 11785.01 | S55: 12008.92 | T55: 12237.08 | U55: 12469.57 | V55: 11320.7 | W55: 11320.7
A56: 1 | C56: 단기금융부채(face) | Y56: 123207.83
A57: 1 | C57: 장기금융부채(face) | Y57: 0
A58: 1 | C58: 매출액(수익) | L58: 7450.42 | N58: 6719.84 | O58: 9194.01 | P58: 11000.03 | Q58: 9280.8 | R58: 36194.68 | S58: 10446.45 | T58: 7061.17 | U58: 10398.92 | V58: 15454.55 | W58: 43361.09 | X58: 5053.88 | Y58: 17824.99
A59: 1 | C59: 매출원가 | L59: 8731.35 | N59: 6447.46 | O59: 6693.01 | P59: 8828.98 | Q59: 7973.61 | R59: 29943.06 | S59: 8736.04 | T59: 5738.35 | U59: 8500.41 | V59: 14952.79 | W59: 37927.59 | X59: 6362.33 | Y59: 19527.47
A60: 1 | C60: 매출총이익 | L60: -1280.93 | N60: 272.38 | O60: 2500.99 | P60: 2171.05 | Q60: 1307.2 | R60: 6251.62 | S60: 1710.41 | T60: 1322.81 | U60: 1898.51 | V60: 501.76 | W60: 5433.49 | X60: -1308.45 | Y60: -1702.47
A61: 1 | C61: 판관비 | L61: 765.54 | N61: 907.81 | O61: 850.81 | P61: 832.69 | Q61: 1249.17 | R61: 3840.48 | S61: 1030.14 | T61: 1166.39 | U61: 1056.59 | V61: 1322.54 | W61: 4575.66 | X61: 836.67 | Y61: 1530.79
A62: 1 | C62: 영업이익 | L62: -2046.47 | N62: -635.43 | O62: 1650.18 | P62: 1338.36 | Q62: 58.03 | R62: 2411.14 | S62: 680.28 | T62: 156.43 | U62: 841.93 | V62: -820.78 | W62: 857.86 | X62: -2145.12 | Y62: -3233.27
A63: 1 | C63: 금융수익 | L63: 513.77 | N63: 387.04 | O63: 333.56 | P63: 353.3 | Q63: 762.24 | R63: 1836.14 | S63: 540.38 | T63: 566.9 | U63: 517.03 | V63: 6312.34 | W63: 7936.65 | X63: 562.11 | Y63: 1106.75
A64: 1 | C64: 금융비용 | L64: 100.24 | N64: 405.09 | O64: 968.38 | P64: 983.92 | Q64: 1709.99 | R64: 4067.38 | S64: 1238.07 | T64: 1156.32 | U64: 1101.3 | V64: 4036.32 | W64: 7532.01 | X64: 1608.56 | Y64: 1885.98
A65: 1 | C65: 기타영업외수익 | L65: 29.37 | N65: 33.33 | O65: 73.16 | P65: 15.09 | Q65: 87.13 | R65: 208.71 | S65: 6.5 | T65: 64.59 | U65: 17.48 | V65: 22.46 | W65: 111.03 | X65: 1611.05 | Y65: -1144.06
A66: 1 | C66: 기타영업외비용 | L66: 84.97 | N66: 16.99 | O66: 59.28 | P66: 18 | Q66: 15.11 | R66: 109.38 | S66: 61.82 | T66: 24.04 | U66: 45.79 | V66: 94.85 | W66: 226.5 | X66: 88.63 | Y66: 30.2
A67: 1 | C67: 법인세비용차감전계속사업이익 | L67: -1688.54 | N67: -637.14 | O67: 1029.24 | P67: 704.83 | Q67: -817.7 | R67: 279.23 | S67: -72.73 | T67: -392.45 | U67: 229.36 | V67: 1382.85 | W67: 1147.03 | X67: -1669.15 | Y67: -5186.75
A68: 1 | C68: 법인세비용 | L68: -542.73 | N68: 0 | O68: 133.04 | P68: 0 | Q68: -478.9 | R68: -345.86 | S68: 0 | T68: 74.37 | U68: 0 | V68: -109.42 | W68: -35.05 | X68: 0 | Y68: -1198.64
A69: 1 | C69: 당기순이익 | L69: -1145.81 | N69: -637.14 | O69: 896.2 | P69: 704.83 | Q69: -338.8 | R69: 625.09 | S69: -72.73 | T69: -466.82 | U69: 229.36 | V69: 1492.27 | W69: 1182.08 | X69: -1669.15 | Y69: -3988.11
... A75: 1 | C75: 계속사업이익 | L75: -1145.81 | N75: -637.14 | O75: 896.2 | P75: 704.83 | Q75: -338.8 | R75: 625.09 | S75: -72.73 | T75: -466.82 | U75: 229.36 | V75: 1492.27 | W75: 1182.08 | X75: -1669.15 | Y75: -3988.11
A76: 1 | C76: 이자수익 | L76: 513.77 | N76: 362.6 | O76: 333.56 | P76: 353.3 | Q76: 389.74 | R76: 1439.2 | S76: 517.98
A77: 1 | C77: 이자비용 | L77: 100.24 | N77: 405.09 | O77: 968.38 | P77: 983.92 | Q77: 1176.78 | R77: 3534.17 | S77: 1238.07
A78: 1 | C78: 이자손익 | L78: 413.53 | N78: -42.49 | O78: -634.82 | P78: -630.62 | Q78: -787.04 | R78: -2094.97 | S78: -720.09
A79: 1 | C79: 영업활동으로인한현금흐름 | L79: 3190.35 | N79: -5439.91 | O79: 18754.8 | P79: -7021.01 | Q79: 2612.06 | R79: 8905.94 | S79: 1393.17 | T79: 367.76 | U79: -1381.07 | V79: 21303.26 | W79: 21683.12 | X79: -15326.48 | Y79: -4061.11
A80: 1 | C80: 감가상각비 | L80: 340.45 | N80: 405.32 | O80: 446.48 | P80: 444.16 | Q80: 437.22 | R80: 1733.18 | S80: 441.4 | T80: 460.01 | U80: 481.48 | V80: 515.94 | W80: 1898.83 | X80: 515.92 | Y80: 537.61
A81: 1 | C81: 무형자산상각비 | L81: 66.12 | N81: 66.39 | O81: 68.03 | P81: 111.05 | Q81: 225.38 | R81: 470.85 | S81: 189.29 | T81: 179.99 | U81: 170.78 | V81: 170.03 | W81: 710.09 | X81: 170.03 | Y81: 169.37
A82: 1 | C82: 이자수취(CF) | L82: 299.44 | N82: 271 | O82: 396 | P82: 362.39 | Q82: 172.35 | R82: 1201.74 | S82: 165.34 | T82: 508.18 | U82: 279.27 | V82: 879.38 | W82: 1832.17 | X82: 69.93 | Y82: 778.64
A83: 1 | C83: 이자지급(CF) | L83: -131.95 | N83: -374.72 | O83: -980.23 | P83: -991.25 | Q83: -1004.01 | R83: -3350.21 | S83: -1013.81 | T83: -945.74 | U83: -870.32 | V83: -877.87 | W83: -3707.74 | X83: -939.94 | Y83: -952.52
A84: 1 | C84: 법인세납부(CF) | L84: -56.89 | N84: -41.59 | O84: 383.95 | P84: -56.61 | Q84: -21.3 | R84: 264.45 | S84: -28.43 | T84: 92.64 | U84: -74.31 | V84: -101.96 | W84: -112.06 | X84: -10.45 | Y84: 87.59
A85: 1 | C85: 투자활동으로인한현금흐름 | L85: -12024.34 | N85: -106453.41 | O85: 5413.59 | P85: -2679.26 | Q85: -18052.02 | R85: -121771.1 | S85: 2915.55 | T85: -11999.52 | U85: -4089.06 | V85: 217.08 | W85: -12955.95 | X85: -12980.04 | Y85: 3592.94
A86: 1 | C86: 재무활동으로인한현금흐름 | L86: -53.46 | N86: 87959.69 | O86: -40.86 | P86: -33.92 | Q86: 17843.86 | R86: 105728.77 | S86: 1978.09 | T86: -522.93 | U86: -277.65 | V86: 16436.37 | W86: 17613.88 | X86: 3231.89 | Y86: -793.08
A87: 1 | C87: 단기차입금의증가 | L87: 0 | P87: 0 | Q87: 5000 | S87: 5000 | T87: 0 | U87: 0 | V87: 10000 | W87: 15000 | X87: 0 | Y87: 0
A88: 1 | C88: 장기차입금의증가 | L88: 0 | N88: 88000 | O88: 0 | P88: 0 | Q88: 0 | R88: 88000 | S88: 0 | T88: 0 | U88: 0 | V88: 0 | W88: 0
A89: 1 | C89: 단기차입금의감소 | L89: 0 | P89: 0 | Q89: 0 | S89: 2000 | T89: 500 | U89: 250 | V89: 250 | W89: 3000 | X89: 3750 | Y89: 750
A90: 1 | C90: 장기차입금의감소 | L90: 0 | Q90: 0
A91: 1 | C91: 유동성장기부채의감소 | L91: 0 | P91: 0 | Q91: 0 | S91: 1000 | T91: 0 | U91: 0 | V91: 0 | W91: 1000 | X91: 0 | Y91: 0
A92: 1 | C92: 리스부채의상환 | L92: 7.71 | N92: 40.31 | O92: 40.86 | P92: 33.92 | Q92: 23.09 | R92: 138.18 | S92: 21.91 | T92: 22.93 | U92: 27.65 | V92: 47.85 | W92: 120.34 | X92: 43.27 | Y92: 43.08
A93: 1 | C93: 현금및현금성자산의증감 | L93: -8904.18 | N93: -23914.98 | O93: 24111.38 | P93: -9736.69 | Q93: 2404.72 | R93: -7135.57 | S93: 6289.14 | T93: -12154.55 | U93: -5745.7 | V93: 37952.16 | W93: 26341.05 | X93: -25074.62
A94: 1 | C94: 기말현금및현금성자산 | L94: -8904.18 | N94: 2817.92 | O94: 24111.38 | P94: -9736.68 | Q94: 2404.71 | R94: 19597.33 | S94: 25886.48 | T94: -12154.56 | U94: -5745.7 | V94: 37867.75 | W94: 45853.97 | X94: 21114.54 | Y94: -1274.09
A95: 1 | C95: 배당금수취(CF) | U95: 0 | V95: 0

Sheet BS별도
B1: (백만원) | C1: 이름: BS별도H | E1: 2Q22 | F1: 3Q22 | G1: 4Q22 | H1: 2022 | I1: 1Q23 | J1: 2Q23 | K1: 3Q23 | L1: 4Q23 | M1: 2023 | N1: 1Q24 | O1: 2Q24 | P1: 3Q24 | Q1: 4Q24 | R1: 2024 | S1: 1Q25 | T1: 2Q25 | U1: 3Q25 | V1: 4Q25 | W1: 2025 | X1: 1Q26 | Y1: 2Q26 | Z1: 3Q26 | AA1: 4Q26 | AB1: 2026 | AC1: 1Q27 | AD1: 2Q27 | AE1: 3Q27 | AF1: 4Q27 | AG1: 2027 | AH1: 1Q28 | AI1: 2Q28 | AJ1: 3Q28 | AK1: 4Q28 | AL1: 2028
B2: 별도 | D2: fin json(kship_fin.py)
B3: 범한퓨얼셀(별) | C3: UPDATE: 26-10-11 | E3: 1 | F3: 2 | G3: 3 | H3: 4 | I3: 5 | J3: 6 | K3: 7 | L3: 8 | M3: 9 | N3: 10 | O3: 11 | P3: 12 | Q3: 13 | R3: 14 | S3: 15 | T3: 16 | U3: 17 | V3: 18 | W3: 19 | X3: 20 | Y3: 21 | Z3: 22 | AA3: 23 | AB3: 24 | AC3: 25 | AD3: 26 | AE3: 27 | AF3: 28 | AG3: 29 | AH3: 30 | AI3: 31 | AJ3: 32 | AK3: 33 | AL3: 34
B4: Account Code | C4: AccountNAME | E4: 2022.06 | F4: 2022.09 | G4: 2022.12 | H4: 2022.12A | I4: 2023.03 | J4: 2023.06 | K4: 2023.09 | L4: 2023.12 | M4: 2023.12A | N4: 2024.03 | O4: 2024.06 | P4: 2024.09 | Q4: 2024.12 | R4: 2024.12A | S4: 2025.03 | T4: 2025.06 | U4: 2025.09 | V4: 2025.12 | W4: 2025.12A | X4: 2026.03 | Y4: 2026.06 | Z4: 2026.09 | AA4: 2026.12 | AB4: 2026.12A | AC4: 2027.03 | AD4: 2027.06 | AE4: 2027.09 | AF4: 2027.12 | AG4: 2027.12A | AH4: 2028.03 | AI4: 2028.06 | AJ4: 2028.09 | AK4: 2028.12 | AL4: 2028.12A
A5: 1 | C5: 유동자산 | E5: 114458.15 | F5: 114290.53 | G5: 103753.55 | H5: 103753.55 | I5: 97022.25 | J5: 102450.84 | K5: 96405.19 | L5: 85052.2 | M5: 85052.2 | N5: 75072.06 | O5: 72705.69 | P5: 69211.78 | Q5: 85624.4 | R5: 85624.4 | S5: 86757.79 | T5: 91089.64 | U5: 85674.93 | V5: 129005.09 | W5: 129005.09 | X5: 124017.58 | Y5: 110998.72
A6: 1 | C6: 현금및현금성자산 | E6: 89978.9 | F6: 16279.67 | G6: 22958.12 | H6: 22958.12 | I6: 30031.84 | J6: 15829.3 | K6: 35637.08 | L6: 26629.85 | M6: 26629.85 | N6: 2750.94 | O6: 26775.18 | P6: 16801.7 | Q6: 19009.47 | R6: 19009.47 | S6: 25416.47 | T6: 13321.65 | U6: 7462.37 | V6: 45601.24 | W6: 45601.24 | X6: 18696.87 | Y6: 19327.03
A7: 1 | C7: 단기금융상품 | E7: 2530 | F7: 73510 | G7: 53600 | H7: 53600 | I7: 33690 | J7: 46622.59 | K7: 19000.14 | L7: 15540 | M7: 15540 | N7: 5630 | O7: 5360 | P7: 4450 | Q7: 3540 | R7: 3540 | S7: 600 | T7: 2651.36 | U7: 2651.36 | V7: 2651.36 | W7: 2651.36 | X7: 7651.36 | Y7: 2351
A8: 1 | C8: 단기금융자산 | E8: 2530 | F8: 73510 | G8: 53600 | H8: 53600 | I8: 33690 | J8: 46622.59 | K8: 19000.14 | L8: 15540 | M8: 15540 | N8: 5630 | O8: 5360 | P8: 4450 | Q8: 3540 | R8: 3540 | S8: 600 | T8: 2651.36 | U8: 2651.36 | V8: 2651.36 | W8: 2651.36 | X8: 7651.36 | Y8: 2351
A9: 1 | C9: 매출채권및기타채권 | E9: 7963.55 | F9: 6898.83 | G9: 4668.59 | H9: 4668.59 | I9: 7346.63 | J9: 6846.83 | K9: 4963.28 | L9: 15418.49 | M9: 15418.49 | N9: 38314.44 | O9: 10969.78 | P9: 19211.56 | Q9: 38107.03 | R9: 38107.03 | S9: 40737.17 | T9: 47588.34 | U9: 47413.09 | V9: 48381.85 | W9: 48381.85 | X9: 51864.52 | Y9: 51330.02
A10: 1 | C10: 재고자산 | E10: 6019.45 | F10: 8289.05 | G10: 10925.5 | H10: 10925.5 | I10: 10319.53 | J10: 14316.07 | K10: 15449.61 | L10: 16502.04 | M10: 16502.04 | N10: 18140.08 | O10: 19297.2 | P10: 17761.96 | Q10: 15681.99 | R10: 15681.99 | S10: 12869.69 | T10: 12963.07 | U10: 13794.35 | V10: 14045.17 | W10: 14045.17 | X10: 17701.26 | Y10: 19485.29
A11: 1 | C11: 계약자산 | E11: 2668.9 | F11: 5073.44 | G11: 8787.73 | H11: 8787.73 | I11: 12948.93 | J11: 17052.45 | K11: 18487.52 | L11: 9255.73 | M11: 9255.73 | N11: 9095.55 | O11: 9620.15 | P11: 10310.92 | Q11: 5907.38 | R11: 5907.38 | S11: 3323.67 | T11: 10175.87 | U11: 9141.36 | V11: 10343.67 | W11: 10343.67 | X11: 9128.41 | Y11: 439.94
A12: 1 | C12: 기타유동자산 | E12: 5297.35 | F12: 4239.54 | G12: 2390.27 | H12: 2390.27 | I12: 2314.49 | J12: 1662.01 | K12: 2462.46 | L12: 1239.64 | M12: 1239.64 | N12: 633.31 | O12: 558.69 | P12: 505.25 | Q12: 507.44 | R12: 507.44 | S12: 918.95 | T12: 1582.36 | U12: 2333.17 | V12: 4804.46 | W12: 4804.46 | X12: 15787.53 | Y12: 14965.98
A13: 1 | C13: 비유동자산 | E13: 23459.25 | F13: 23243.08 | G13: 25948.5 | H13: 25948.5 | I13: 27217.28 | J13: 26935.06 | K13: 26563.91 | L13: 36181.61 | M13: 36181.61 | N13: 154246.03 | O13: 153449.71 | P13: 152018.73 | Q13: 225055.74 | R13: 225055.74 | S13: 225571.54 | T13: 217694.25 | U13: 222594.89 | V13: 222823.24 | W13: 222823.24 | X13: 226254.05 | Y13: 225869.29
A14: 1 | C14: 장기금융자산 | E14: 7635.8 | F14: 7635.8 | G14: 7587.15 | H14: 7587.15 | I14: 7606.68 | J14: 7606.68 | K14: 7606.68 | L14: 8106.68 | M14: 8106.68 | N14: 8131.12 | O14: 8131.12 | P14: 8131.12 | Q14: 4631.12 | R14: 4631.12 | S14: 4949.61 | T14: 4949.61 | U14: 8959.61 | V14: 7084.61 | W14: 7084.61 | X14: 7539.33 | Y14: 7539.33
A15: 1 | C15: 투자자산 | E15: 7635.8 | F15: 7635.8 | G15: 7587.15 | H15: 7587.15 | I15: 7606.68 | J15: 7606.68 | K15: 7606.68 | L15: 13056.68 | M15: 13056.68 | N15: 13081.12 | O15: 13081.12 | P15: 13081.12 | Q15: 9581.12 | R15: 9581.12 | S15: 9899.61 | T15: 9899.61 | U15: 13909.61 | V15: 12034.61 | W15: 12034.61 | X15: 12489.33 | Y15: 12489.33
A16: 1 | C16: 유형자산 | E16: 7538.41 | F16: 7406.52 | G16: 9287.48 | H16: 9287.48 | I16: 10768.03 | J16: 10986.07 | K16: 10783.11 | L16: 10708.3 | M16: 10708.3 | N16: 126989.18 | O16: 10367.06 | P16: 10178.14 | Q16: 203706.51 | R16: 203706.51 | S16: 203384.5 | T16: 202956.06 | U16: 202602.93 | V16: 202895.33 | W16: 202895.33 | X16: 205138.14 | Y16: 205027.75
... A19: 1 | C19: 무형자산 | E19: 2844.95 | F19: 2905.22 | G19: 2835.41 | H19: 2835.41 | I19: 2918.46 | J19: 2855.7 | K19: 2766.29 | L19: 2717.95 | M19: 2717.95 | N19: 2720.25 | O19: 2682.51 | P19: 2628.35 | Q19: 2477.23 | R19: 2477.23 | S19: 2360.85 | T19: 2434.58 | U19: 2297.43 | V19: 2211.72 | W19: 2211.72 | X19: 2120.47 | Y19: 2210.6
A20: 1 | C20: 이연법인세자산 | E20: 417.92 | F20: 417.92 | G20: 305.47 | H20: 305.47 | I20: 305.47 | J20: 695.71 | K20: 695.71 | L20: 1237.2 | M20: 1237.2 | N20: 1237.2 | O20: 1102.86 | P20: 1102.86 | Q20: 0 | R20: 0 | V20: 0 | W20: 0
A21: 1 | C21: 자산총계 | E21: 137917.4 | F21: 137533.61 | G21: 129702.05 | H21: 129702.05 | I21: 124239.54 | J21: 129385.9 | K21: 122969.1 | L21: 121233.81 | M21: 121233.81 | N21: 229318.1 | O21: 226155.41 | P21: 221230.51 | Q21: 310680.14 | R21: 310680.14 | S21: 312329.33 | T21: 308783.88 | U21: 308269.82 | V21: 351828.33 | W21: 351828.33 | X21: 350271.63 | Y21: 336868
A22: 1 | C22: 유동부채 | E22: 20626.58 | F22: 21638.65 | G22: 17042.64 | H22: 17042.64 | I22: 11720.44 | J22: 16205.76 | K22: 10773.4 | L22: 10330.35 | M22: 10330.35 | N22: 30701.84 | O22: 28058.91 | P22: 22858.62 | Q22: 41406.76 | R22: 41406.76 | S22: 42611.35 | T22: 39685.18 | U22: 40446.51 | V22: 84463.64 | W22: 84463.64 | X22: 165250.85 | Y22: 163380.03
A23: 1 | C23: 매입채무및기타채무 | E23: 5004.85 | F23: 8751.2 | G23: 9278.99 | H23: 9278.99 | I23: 6904.36 | J23: 8128.91 | K23: 3602.51 | L23: 4907.27 | M23: 4907.27 | N23: 5218.18 | O23: 5561 | P23: 5461.16 | Q23: 4774.05 | R23: 4774.05 | S23: 4682.6 | T23: 5566.66 | U23: 5797.14 | V23: 12012.39 | W23: 12012.39 | X23: 7737.04 | Y23: 10579.25
A24: 1 | C24: 계약부채 | E24: 11509.15 | F24: 8437.59 | G24: 2943.19 | H24: 2943.19 | I24: 756 | J24: 2034.58 | K24: 1541 | L24: 0 | M24: 0 | N24: 20064.66 | O24: 16090.44 | P24: 10975.58 | Q24: 9347.55 | R24: 9347.55 | S24: 7708.47 | T24: 4316.21 | U24: 3212.12 | V24: 27046.57 | W24: 27046.57 | X24: 26562.04 | Y24: 14957.59
A25: 1 | C25: 단기차입금 | E25: 3110 | F25: 3220 | G25: 3330 | H25: 3330 | I25: 3440 | J25: 5440 | K25: 5000 | L25: 5000 | M25: 5000 | N25: 5000 | O25: 6000 | P25: 6000 | Q25: 22785.01 | R25: 22785.01 | S25: 25008.92 | T25: 24737.08 | U25: 26809.57 | V25: 35410.7 | W25: 35410.7 | X25: 120338.23 | Y25: 123207.83
A26: 1 | C26: 유동리스부채 | E26: 113.54 | F26: 102.03 | G26: 128.34 | H26: 128.34 | I26: 162.31 | J26: 149.71 | K26: 147.05 | L26: 131.65 | M26: 131.65 | N26: 117.53 | O26: 98.25 | P26: 84.13 | Q26: 84.51 | R26: 84.51 | S26: 82.09 | T26: 78.78 | U26: 75.02 | V26: 69.85 | W26: 69.85 | X26: 60.33 | Y26: 52.45
A27: 1 | C27: 리스부채 | E27: 846.67 | F27: 813.06 | G27: 904.86 | H27: 904.86 | I27: 1058.99 | J27: 1019.37 | K27: 992.45 | L27: 957.18 | M27: 957.18 | N27: 929.15 | O27: 881.14 | P27: 850.31 | Q27: 829.57 | R27: 829.57 | S27: 761.94 | T27: 741.49 | U27: 720.82 | V27: 699.93 | W27: 699.93 | X27: 690.53 | Y27: 682.26
A28: 1 | C28: 단기금융부채 | E28: 113.54 | F28: 102.03 | G28: 128.34 | H28: 128.34 | I28: 162.31 | J28: 149.71 | K28: 147.05 | L28: 131.65 | M28: 131.65 | N28: 117.53 | O28: 98.25 | P28: 84.13 | Q28: 4165.55 | R28: 4165.55 | S28: 4163.13 | T28: 4159.82 | U28: 4156.06 | V28: 9624.42 | W28: 9624.42 | X28: 9614.9 | Y28: 13426.25
A29: 1 | C29: 당기법인세부채(미지급법인세) | E29: 320.6 | F29: 634.52 | G29: 0 | H29: 0 | L29: 0 | M29: 0
A30: 1 | C30: 단기충당부채 | E30: 419.89 | F30: 345.39 | G30: 296.95 | H30: 296.95 | I30: 280.74 | J30: 274.26 | K30: 278.63 | L30: 103.86 | M30: 103.86 | N30: 126.2 | O30: 122.91 | P30: 163.36 | Q30: 106.93 | R30: 106.93 | S30: 841.34 | T30: 712.65 | U30: 291.24 | V30: 246.66 | W30: 246.66 | X30: 835.29 | Y30: 1005.26
A31: 1 | C31: 기타유동부채 | E31: 148.55 | F31: 147.92 | G31: 1065.17 | H31: 1065.17 | I31: 177.04 | J31: 178.3 | K31: 204.21 | L31: 187.57 | M31: 187.57 | N31: 175.29 | O31: 186.3 | P31: 174.37 | Q31: 227.68 | R31: 227.68 | S31: 206.9 | T31: 192.77 | U31: 180.4 | V31: 122.89 | W31: 122.89 | X31: 163.35 | Y31: 203.86
A32: 1 | C32: 비유동부채 | E32: 6301.81 | F32: 6553.1 | G32: 6250.5 | H32: 6250.5 | I32: 5545.6 | J32: 6602.5 | K32: 7088.53 | L32: 6867.32 | M32: 6867.32 | N32: 95065.03 | O32: 93586.67 | P32: 92916.96 | Q32: 104566.35 | R32: 104566.35 | S32: 104818.84 | T32: 104362.25 | U32: 102491.53 | V32: 104422.71 | W32: 104422.71 | X32: 23668.37 | Y32: 15435.63
A33: 1 | C33: 장기차입금 | E33: 2090 | F33: 1980 | G33: 1870 | H33: 1870 | I33: 1760 | J33: 2650 | K33: 3090 | L33: 3090 | M33: 3090 | N33: 91090 | O33: 90090 | P33: 90090 | Q33: 90090 | R33: 90090 | S33: 90090 | T33: 90090 | U33: 88000 | V33: 88000 | W33: 88000 | X33: 7025.28 | Y33: 0
A34: 1 | C34: 비유동리스부채 | E34: 733.13 | F34: 711.03 | G34: 776.52 | H34: 776.52 | I34: 896.68 | J34: 869.66 | K34: 845.4 | L34: 825.53 | M34: 825.53 | N34: 811.62 | O34: 782.89 | P34: 766.18 | Q34: 745.06 | R34: 745.06 | S34: 679.85 | T34: 662.71 | U34: 645.8 | V34: 630.08 | W34: 630.08 | X34: 630.2 | Y34: 629.81
A35: 1 | C35: 장기금융부채 | E35: 733.13 | F35: 711.03 | G35: 776.52 | H35: 776.52 | I35: 896.68 | J35: 869.66 | K35: 845.4 | L35: 825.53 | M35: 825.53 | N35: 811.62 | O35: 782.89 | P35: 766.18 | Q35: 745.06 | R35: 745.06 | S35: 679.85 | T35: 662.71 | U35: 645.8 | V35: 630.08 | W35: 630.08 | X35: 630.2 | Y35: 629.81
A36: 1 | C36: 확정급여부채 | E36: 1424.81 | F36: 1562.5 | G36: 1183.55 | H36: 1183.55 | I36: 398.48 | J36: 530.91 | K36: 560.34 | L36: 338.53 | M36: 338.53 | N36: 488.6 | O36: 625.52 | P36: 759.51 | Q36: 880.67 | R36: 880.67 | S36: 1053.55 | T36: 1226.43 | U36: 1399.32 | V36: 683.26 | W36: 683.26 | X36: 876.25 | Y36: 901.5
A37: 1 | C37: 기타비유동부채 | E37: 28.46 | F37: 29.76 | G37: 28.17 | H37: 28.17 | I37: 29.51 | J37: 30.84 | K37: 32.18 | L37: 30.43 | M37: 30.43 | N37: 31.98 | O37: 33.54 | P37: 35.1 | Q37: 34.75 | R37: 34.75 | S37: 36.41 | T37: 38.08 | U37: 39.74 | V37: 43.32 | W37: 43.32 | X37: 45.12 | Y37: 46.92
A38: 1 | C38: 부채총계 | E38: 26928.39 | F38: 28191.75 | G38: 23293.14 | H38: 23293.14 | I38: 17266.04 | J38: 22808.26 | K38: 17861.93 | L38: 17197.67 | M38: 17197.67 | N38: 125766.88 | O38: 121645.59 | P38: 115775.57 | Q38: 145973.11 | R38: 145973.11 | S38: 147430.19 | T38: 144047.44 | U38: 142938.04 | V38: 188886.35 | W38: 188886.35 | X38: 188919.21 | Y38: 178815.67
A39: 1 | C39: 자본금 | E39: 4380.5 | F39: 4380.5 | G39: 4380.5 | H39: 4380.5 | I39: 4380.5 | J39: 4380.5 | K39: 4380.5 | L39: 4380.5 | M39: 4380.5 | N39: 4380.5 | O39: 4380.5 | P39: 4380.5 | Q39: 4380.5 | R39: 4380.5 | S39: 4380.5 | T39: 4380.5 | U39: 4380.5 | V39: 4380.5 | W39: 4380.5 | X39: 4380.5 | Y39: 4380.5
A40: 1 | C40: 자본잉여금 | E40: 98129.17 | F40: 95077.91 | G40: 92602.21 | H40: 92602.21 | I40: 92577.66 | J40: 92581.5 | K40: 92585.34 | L40: 92513.42 | M40: 92513.42 | N40: 92527.79 | O40: 92538.2 | P40: 92538.2 | Q40: 92538.2 | R40: 92538.2 | S40: 92538.2 | T40: 92538.2 | U40: 92538.2 | V40: 92538.2 | W40: 92538.2 | X40: 92538.2 | Y40: 92538.2
A41: 1 | C41: 이익잉여금 | E41: 8479.34 | F41: 9883.45 | G41: 9426.2 | H41: 9426.2 | I41: 10015.34 | J41: 9615.65 | K41: 8141.32 | L41: 7142.22 | M41: 7142.22 | N41: 6642.93 | O41: 7591.12 | P41: 8536.24 | Q41: 8092.02 | R41: 8092.02 | S41: 8284.13 | T41: 8121.44 | U41: 8716.77 | V41: 10571.84 | W41: 10571.84 | X41: 8982.27 | Y41: 5682.2
... A47: 1 | C47: 이자발생자산 | E47: 100144.7 | F47: 97425.47 | G47: 84145.27 | H47: 84145.27 | I47: 71328.52 | J47: 70058.57 | K47: 62243.9 | L47: 50276.53 | M47: 50276.53 | N47: 16512.06 | O47: 40266.3 | P47: 29382.82 | Q47: 27180.59 | R47: 27180.59 | S47: 30966.08 | T47: 20922.62 | U47: 19073.34 | V47: 55337.21 | W47: 55337.21 | X47: 33887.56 | Y47: 29217.36
A48: 1 | C48: 당기법인세자산(선급법인세) | G48: 423.35 | H48: 423.35 | I48: 370.83 | J48: 121.59 | K48: 405.09 | L48: 466.45 | M48: 466.45 | N48: 507.73 | O48: 124.7 | P48: 170.39 | Q48: 183.55 | R48: 183.55 | S48: 204.32 | T48: 119.44 | U48: 191.69 | V48: 289.9 | W48: 289.9 | X48: 300.2 | Y48: 212.04
A49: 1 | C49: 기타유동금융부채 | G49: 0 | H49: 0 | Q49: 4081.04 | R49: 4081.04 | S49: 4081.04 | T49: 4081.04 | U49: 4081.04 | V49: 9554.57 | W49: 9554.57 | X49: 9554.57 | Y49: 13373.8
A50: 1 | C50: 종속기업및관계기업투자 | L50: 4950 | M50: 4950 | N50: 4950 | O50: 4950 | P50: 4950 | Q50: 4950 | R50: 4950 | S50: 4950 | T50: 4950 | U50: 4950 | V50: 4950 | W50: 4950 | X50: 4950 | Y50: 4950
A51: 1 | C51: 투자부동산 | O51: 116302.65 | P51: 116194.1
A52: 1 | C52: 단기투자자산(공정가치) | Q52: 2687.53 | R52: 2687.53 | S52: 2687.53 | T52: 2687.53 | U52: 2687.53 | V52: 2887.42 | W52: 2887.42 | X52: 2887.42 | Y52: 2887.42
A53: 1 | C53: 이연법인세부채 | Q53: 11480.74 | R53: 11480.74 | S53: 11480.74 | T53: 11555.1 | U53: 11555.1 | V53: 14160.66 | W53: 14160.66 | X53: 14160.66 | Y53: 12939.38
A54: 1 | C54: 기타포괄이익누계액 | Q54: 59696.31 | R54: 59696.31 | S54: 59696.31 | T54: 59696.31 | U54: 59696.31 | V54: 55451.44 | W54: 55451.44 | X54: 55451.44 | Y54: 55451.44
A55: 1 | C55: 단기금융부채(face) | Y55: 123207.83
A56: 1 | C56: 장기금융부채(face) | Y56: 0
A57: 1 | C57: 매출액(수익) | E57: 14618.22 | F57: 14250.55 | G57: 13316.03 | I57: 8857.17 | J57: 10247.32 | K57: 3960.77 | L57: 7450.42 | M57: 30515.68 | N57: 6719.84 | O57: 9194.01 | P57: 11000.03 | Q57: 9280.8 | R57: 36194.68 | S57: 10446.45 | T57: 7061.17 | U57: 10398.92 | V57: 15454.55 | W57: 43361.09 | X57: 5053.88 | Y57: 17824.99
A58: 1 | C58: 매출원가 | E58: 12331.31 | F58: 12489.73 | G58: 14102.88 | I58: 8001.8 | J58: 10646.51 | K58: 4815.57 | L58: 8731.35 | M58: 32195.23 | N58: 6447.46 | O58: 6693.01 | P58: 8828.98 | Q58: 7973.61 | R58: 29943.06 | S58: 8736.04 | T58: 5738.35 | U58: 8500.41 | V58: 14952.79 | W58: 37927.59 | X58: 6362.33 | Y58: 19527.47
A59: 1 | C59: 매출총이익 | E59: 2286.91 | F59: 1760.83 | G59: -786.86 | I59: 855.36 | J59: -399.19 | K59: -854.8 | L59: -1280.93 | M59: -1679.56 | N59: 272.38 | O59: 2500.99 | P59: 2171.05 | Q59: 1307.2 | R59: 6251.62 | S59: 1710.41 | T59: 1322.81 | U59: 1898.51 | V59: 501.76 | W59: 5433.49 | X59: -1308.45 | Y59: -1702.47
A60: 1 | C60: 판관비 | E60: 1357.12 | F60: 742.53 | G60: 1004.27 | I60: 755.28 | J60: 986.31 | K60: 1053.68 | L60: 571.29 | M60: 3366.56 | N60: 775.45 | O60: 722.48 | P60: 575.24 | Q60: 921.61 | R60: 2994.78 | S60: 757.99 | T60: 820.71 | U60: 702.8 | V60: 855.32 | W60: 3136.82 | X60: 755.96 | Y60: 851.85
A61: 1 | C61: 영업이익 | E61: 929.79 | F61: 1018.3 | G61: -1791.12 | I61: 100.09 | J61: -1385.5 | K61: -1908.48 | L61: -1852.22 | M61: -5046.11 | N61: -503.08 | O61: 1778.52 | P61: 1595.81 | Q61: 385.58 | R61: 3256.83 | S61: 952.43 | T61: 502.1 | U61: 1195.71 | V61: -353.57 | W61: 2296.67 | X61: -2064.41 | Y61: -2554.32
A62: 1 | C62: 금융수익 | E62: 27.46 | F62: 1164.81 | G62: 264.42 | I62: 829.59 | J62: 577.14 | K62: 502.66 | L62: 501.33 | M62: 2410.72 | N62: 386.53 | O62: 250.95 | P62: 321.1 | Q62: 740.97 | R62: 1699.55 | S62: 525.6 | T62: 559.24 | U62: 515.7 | V62: 6310.63 | W62: 7911.17 | X62: 559.82 | Y62: 1103.7
A63: 1 | C63: 금융비용 | E63: 49.68 | F63: 67.2 | G63: 45.63 | I63: 65.67 | J63: 84.35 | K63: 92.44 | L63: 93.06 | M63: 335.52 | N63: 397.65 | O63: 961 | P63: 976.61 | Q63: 1702.75 | R63: 4038.01 | S63: 1230.89 | T63: 1149.21 | U63: 1089.08 | V63: 4040.45 | W63: 7509.63 | X63: 1607.99 | Y63: 1885.45
A64: 1 | C64: 기타영업외수익 | E64: 10.22 | F64: 86.07 | G64: 125.49 | I64: 33.6 | J64: 52.36 | K64: 68.69 | L64: 29.36 | M64: 184.01 | N64: 31.9 | O64: 72 | P64: 15 | Q64: 64.42 | R64: 183.32 | S64: 6.11 | T64: 22.84 | U64: 18.78 | V64: 19.39 | W64: 67.12 | X64: 1611.55 | Y64: -1144.73
A65: 1 | C65: 기타영업외비용 | E65: 135.28 | F65: 241.17 | G65: 63.92 | I65: 167.14 | J65: 73.74 | K65: 44.75 | L65: 84.42 | M65: 370.05 | N65: 16.99 | O65: 59.23 | P65: 10.19 | Q65: 20.97 | R65: 107.38 | S65: 61.13 | T65: 23.29 | U65: 45.79 | V65: 94.85 | W65: 225.06 | X65: 88.53 | Y65: 17.93
A66: 1 | C66: 법인세비용차감전계속사업이익 | E66: 782.51 | F66: 1960.81 | G66: -1510.76 | I66: 730.48 | J66: -914.1 | K66: -1474.32 | L66: -1499.01 | M66: -3156.95 | N66: -499.29 | O66: 1081.23 | P66: 945.12 | Q66: -532.73 | R66: 994.33 | S66: 192.11 | T66: -88.32 | U66: 595.33 | V66: 1841.14 | W66: 2540.26 | X66: -1589.56 | Y66: -4498.72
A67: 1 | C67: 법인세비용 | E67: 126.12 | F67: 556.69 | G67: -763.98 | I67: 141.34 | J67: -514.41 | K67: 0 | L67: -542.73 | M67: -915.8 | N67: 0 | O67: 133.04 | P67: 0 | Q67: -478.9 | R67: -345.86 | S67: 0 | T67: 74.37 | U67: 0 | V67: -109.42 | W67: -35.05 | X67: 0 | Y67: -1198.64
A68: 1 | C68: 당기순이익 | E68: 656.39 | F68: 1404.11 | G68: -746.78 | I68: 589.14 | J68: -399.69 | K68: -1474.32 | L68: -956.28 | M68: -2241.15 | N68: -499.29 | O68: 948.19 | P68: 945.12 | Q68: -53.83 | R68: 1340.19 | S68: 192.11 | T68: -162.69 | U68: 595.33 | V68: 1950.57 | W68: 2575.32 | X68: -1589.56 | Y68: -3300.08
... A73: 1 | C73: 계속사업이익 | E73: 656.39 | F73: 1404.11 | G73: -746.78 | I73: 589.14 | J73: -399.69 | K73: -1474.32 | L73: -956.28 | M73: -2241.15 | N73: -499.29 | O73: 948.19 | P73: 945.12 | Q73: -53.83 | R73: 1340.19 | S73: 192.11 | T73: -162.69 | U73: 595.33 | V73: 1950.57 | W73: 2575.32 | X73: -1589.56 | Y73: -3300.08
A74: 1 | C74: 이자수익 | E74: 27.46 | F74: 1164.81 | G74: 258.66 | I74: 810.06 | J74: 577.14 | K74: 502.66
A75: 1 | C75: 이자비용 | E75: 49.68 | F75: 67.2 | G75: 28.72 | I75: 65.67 | J75: 84.35 | K75: 92.44
A76: 1 | C76: 이자손익 | E76: -22.22 | F76: 1097.61 | G76: 229.94 | I76: 744.39 | J76: 492.79 | K76: 410.22
A77: 1 | C77: 배당금수익 | E77: 0 | F77: 0 | G77: 0
A78: 1 | C78: 영업활동으로인한현금흐름 | E78: -11070.89 | F78: 847.7 | G78: -9356.34 | I78: -10505.62 | J78: -4060.75 | K78: -7501.56 | L78: 3108.45 | M78: -18959.48 | N78: -5099.81 | O78: 18899.4 | P78: -6049.73 | Q78: 1961.17 | R78: 9711.03 | S78: 1833.13 | T78: 580.72 | U78: -1565.78 | V78: 21575.54 | W78: 22423.61 | X78: -17530.12 | Y78: -2413.17
A79: 1 | C79: 감가상각비 | E79: 215.59 | F79: 212.95 | G79: 272.07 | I79: 284.13 | J79: 349.77 | K79: 327.61 | L79: 329.67 | M79: 1291.18 | N79: 391.33 | O79: 432.22 | P79: 426.13 | Q79: 418.04 | R79: 1667.72 | S79: 415.02 | T79: 408.33 | U79: 397.63 | V79: 421.01 | W79: 1641.99 | X79: 422.63 | Y79: 440.42
A80: 1 | C80: 무형자산상각비 | E80: 71.04 | F80: 80.47 | G80: 81.2 | I80: 81.23 | J80: 81.13 | K80: 70.84 | L80: 66.12 | M80: 299.32 | N80: 66.39 | O80: 68.03 | P80: 63.08 | Q80: 153.28 | R80: 350.78 | S80: 117.2 | T80: 107.84 | U80: 98.63 | V80: 97.88 | W80: 421.55 | X80: 97.88 | Y80: 97.16
A81: 1 | C81: 법인세납부(CF) | E81: -221.82 | F81: -242.77 | G81: -245.64 | I81: -88.82 | J81: 373.42 | K81: -277.87 | L81: -56.34 | M81: -49.61 | N81: -41.28 | O81: 384.34 | P81: -45.69 | Q81: -13.16 | R81: 284.21 | S81: -20.77 | T81: 84.87 | U81: -72.24 | V81: -101.9 | W81: -110.04 | X81: -10.3 | Y81: 65.53
A82: 1 | C82: 투자활동으로인한현금흐름 | E82: -4344.38 | F82: -71443.75 | G82: 18544.86 | I82: 17618.16 | J82: -12972.34 | K82: 27357.36 | L82: -12048.05 | M82: 19955.13 | N82: -106758.16 | O82: 5180.69 | P82: -3892.11 | Q82: -17600.41 | R82: -123069.99 | S82: 2591.03 | T82: -12155.24 | U82: -4024.9 | V82: 187.79 | W82: -13401.32 | X82: -12964.79 | Y82: 3825.8
A83: 1 | C83: 재무활동으로인한현금흐름 | E83: 83709.04 | F83: -3103.18 | G83: -2510.08 | I83: -38.81 | J83: 2830.55 | K83: -48.02 | L83: -51.45 | M83: 2692.27 | N83: 87961.84 | O83: -38.63 | P83: -31.64 | Q83: 17846.2 | R83: 105737.77 | S83: 1980.51 | T83: -520.45 | U83: -270.67 | V83: 16464.5 | W83: 17653.89 | X83: 3255.33 | Y83: -769.63
A84: 1 | C84: 리스부채의상환 | E84: 40.95 | F84: 40.94 | G84: 28.14 | I84: 38.81 | J84: 59.45 | K84: 48.02 | L84: 5.7 | M84: 151.98 | N84: 38.16 | O84: 38.63 | P84: 31.64 | Q84: 20.74 | R84: 129.17 | S84: 19.49 | T84: 20.45 | U84: 20.67 | V84: 19.72 | W84: 80.33 | X84: 19.83 | Y84: 19.63
A85: 1 | C85: 현금및현금성자산의증감 | E85: 68293.76 | F85: -73699.22 | G85: 6678.44 | I85: 7073.73 | J85: -14202.54 | K85: 19807.78 | L85: -9007.24 | M85: 3671.73 | N85: -23878.9 | O85: 24024.23 | P85: -9973.47 | Q85: 2207.77 | R85: -7620.37 | S85: 6406.99 | T85: -12094.81 | U85: -5859.28 | V85: 38223.28 | W85: 26676.18 | X85: -27239.58 | Y85: 965.37
A86: 1 | C86: 기말현금및현금성자산 | E86: 68293.77 | F86: -73699.23 | G86: 6678.45 | I86: 30031.84 | J86: -14202.54 | K86: 19807.78 | L86: -9007.23 | M86: 26629.85 | N86: 2750.94 | O86: 24024.24 | P86: -9973.48 | Q86: 2207.77 | R86: 19009.47 | S86: 25416.47 | T86: -12094.82 | U86: -5859.28 | V86: 38138.87 | W86: 45601.24 | X86: 18696.87 | Y86: 630.16
A87: 1 | C87: 단기차입금의증가 | F87: 0 | G87: 0 | K87: 0 | L87: 0 | P87: 0 | Q87: 5000 | S87: 5000 | T87: 0 | U87: 0 | V87: 10000 | W87: 15000 | X87: 0 | Y87: 0
A88: 1 | C88: 유동성장기부채의감소 | F88: 0 | G88: 0 | K88: 440 | L88: 0 | P88: 0 | Q88: 0 | S88: 1000 | T88: 0 | U88: 0 | V88: 0 | W88: 1000 | X88: 0 | Y88: 0
A89: 1 | C89: 자기주식의취득 | G89: 2481.94 | L89: 45.75
A90: 1 | C90: 장기차입금의증가 | K90: 2090 | L90: 0 | N90: 88000 | O90: 0 | P90: 0 | Q90: 0 | R90: 88000 | S90: 0 | T90: 0 | U90: 0 | V90: 0 | W90: 0
A91: 1 | C91: 단기차입금의감소 | K91: 0 | L91: 0 | P91: 0 | Q91: 0 | S91: 2000 | T91: 500 | U91: 250 | V91: 250 | W91: 3000 | X91: 3750 | Y91: 750
A92: 1 | C92: 이자수취(CF) | L92: 295.85 | N92: 269.72 | O92: 389.12 | P92: 321.08 | Q92: 141.07 | R92: 1120.99 | S92: 135.47 | T92: 460.36 | U92: 270.13 | V92: 877.7 | W92: 1743.66 | X92: 67.66 | Y92: 775.63
A93: 1 | C93: 이자지급(CF) | L93: -124.77 | N93: -367.28 | O93: -722.79 | P93: -1233.99 | Q93: -996.75 | R93: -3320.81 | S93: -1006.62 | T93: -938.64 | U93: -858.09 | V93: -882 | W93: -3685.35 | X93: -939.37 | Y93: -951.98
A94: 1 | C94: 장기차입금의감소 | L94: 0 | Q94: 0
A95: 1 | C95: 배당금수취(CF) | U95: 0 | V95: 0

Sheet subQ
A1: YQ | C1: subQ 분기 서브모델(억원, U=100) | E1: 2Q22 | F1: 3Q22 | G1: 4Q22 | H1: 2022 | I1: 1Q23 | J1: 2Q23 | K1: 3Q23 | L1: 4Q23 | M1: 2023 | N1: 1Q24 | O1: 2Q24 | P1: 3Q24 | Q1: 4Q24 | R1: 2024 | S1: 1Q25 | T1: 2Q25 | U1: 3Q25 | V1: 4Q25 | W1: 2025 | X1: 1Q26 | Y1: 2Q26 | Z1: 3Q26 | AA1: 4Q26 | AB1: 2026 | AC1: 1Q27 | AD1: 2Q27 | AE1: 3Q27 | AF1: 4Q27 | AG1: 2027 | AH1: 1Q28 | AI1: 2Q28 | AJ1: 3Q28 | AK1: 4Q28 | AL1: 2028
A2: A=이름(key) B=그룹 C=단위 D=FnGuide 계정명(VLOOKUP 키). 확정=VLOOKUP(BS), 추정=변수 가정 참조
E3: 1 | F3: 2 | G3: 3 | H3: 4 | I3: 5 | J3: 6 | K3: 7 | L3: 8 | M3: 9 | N3: 10 | O3: 11 | P3: 12 | Q3: 13 | R3: 14 | S3: 15 | T3: 16 | U3: 17 | V3: 18 | W3: 19 | X3: 20 | Y3: 21 | Z3: 22 | AA3: 23 | AB3: 24 | AC3: 25 | AD3: 26 | AE3: 27 | AF3: 28 | AG3: 29 | AH3: 30 | AI3: 31 | AJ3: 32 | AK3: 33 | AL3: 34
E4: 2022.06 | F4: 2022.09 | G4: 2022.12 | H4: 2022.12A | I4: 2023.03 | J4: 2023.06 | K4: 2023.09 | L4: 2023.12 | M4: 2023.12A | N4: 2024.03 | O4: 2024.06 | P4: 2024.09 | Q4: 2024.12 | R4: 2024.12A | S4: 2025.03 | T4: 2025.06 | U4: 2025.09 | V4: 2025.12 | W4: 2025.12A | X4: 2026.03 | Y4: 2026.06 | Z4: 2026.09 | AA4: 2026.12 | AB4: 2026.12A | AC4: 2027.03 | AD4: 2027.06 | AE4: 2027.09 | AF4: 2027.12 | AG4: 2027.12A | AH4: 2028.03 | AI4: 2028.06 | AJ4: 2028.09 | AK4: 2028.12 | AL4: 2028.12A
A5: 매출액 | B5: 손익 | C5: 억원 | D5: 매출액(수익) | E5: =IFERROR(VLOOKUP($D5,BS별도,MATCH(E$1,BS별도H,0),0)/100,"") | F5: =IFERROR(VLOOKUP($D5,BS별도,MATCH(F$1,BS별도H,0),0)/100,"") | G5: =IFERROR(VLOOKUP($D5,BS별도,MATCH(G$1,BS별도H,0),0)/100,"") | I5: =IFERROR(VLOOKUP($D5,BS별도,MATCH(I$1,BS별도H,0),0)/100,"") | J5: =IFERROR(VLOOKUP($D5,BS별도,MATCH(J$1,BS별도H,0),0)/100,"") | K5: =IFERROR(VLOOKUP($D5,BS별도,MATCH(K$1,BS별도H,0),0)/100,"") | L5: =IFERROR(VLOOKUP($D5,BS연결,MATCH(L$1,BS연결H,0),0)/100,"") | M5: =SUM(I5:L5) | N5: =IFERROR(VLOOKUP($D5,BS연결,MATCH(N$1,BS연결H,0),0)/100,"") | O5: =IFERROR(VLOOKUP($D5,BS연결,MATCH(O$1,BS연결H,0),0)/100,"") | P5: =IFERROR(VLOOKUP($D5,BS연결,MATCH(P$1,BS연결H,0),0)/100,"") | Q5: =IFERROR(VLOOKUP($D5,BS연결,MATCH(Q$1,BS연결H,0),0)/100,"") | R5: =IFERROR(VLOOKUP($D5,BS연결,MATCH(R$1,BS연결H,0),0)/100,"") | S5: =IFERROR(VLOOKUP($D5,BS연결,MATCH(S$1,BS연결H,0),0)/100,"") | T5: =IFERROR(VLOOKUP($D5,BS연결,MATCH(T$1,BS연결H,0),0)/100,"") | U5: =IFERROR(VLOOKUP($D5,BS연결,MATCH(U$1,BS연결H,0),0)/100,"") | ... Y5: =IFERROR(VLOOKUP($D5,BS연결,MATCH(Y$1,BS연결H,0),0)/100,"") | Z5: =IFERROR(U5*(1+변수!Z21),"") | AA5: =IFERROR(V5*(1+변수!AA21),"") | AB5: =SUM(X5:AA5) | AC5: =IFERROR(X5*(1+변수!AC21),"") | AD5: =IFERROR(Y5*(1+변수!AD21),"") | AE5: =IFERROR(Z5*(1+변수!AE21),"") | AF5: =IFERROR(AA5*(1+변수!AF21),"") | AG5: =SUM(AC5:AF5) | AH5: =IFERROR(AC5*(1+변수!AH21),"") | AI5: =IFERROR(AD5*(1+변수!AI21),"") | AJ5: =IFERROR(AE5*(1+변수!AJ21),"") | AK5: =IFERROR(AF5*(1+변수!AK21),"") | AL5: =SUM(AH5:AK5)
A6: 매출원가 | B6: 손익 | C6: 억원 | D6: 매출원가 | E6: =IFERROR(VLOOKUP($D6,BS별도,MATCH(E$1,BS별도H,0),0)/100,"") | F6: =IFERROR(VLOOKUP($D6,BS별도,MATCH(F$1,BS별도H,0),0)/100,"") | G6: =IFERROR(VLOOKUP($D6,BS별도,MATCH(G$1,BS별도H,0),0)/100,"") | I6: =IFERROR(VLOOKUP($D6,BS별도,MATCH(I$1,BS별도H,0),0)/100,"") | J6: =IFERROR(VLOOKUP($D6,BS별도,MATCH(J$1,BS별도H,0),0)/100,"") | K6: =IFERROR(VLOOKUP($D6,BS별도,MATCH(K$1,BS별도H,0),0)/100,"") | L6: =IFERROR(VLOOKUP($D6,BS연결,MATCH(L$1,BS연결H,0),0)/100,"") | M6: =SUM(I6:L6) | N6: =IFERROR(VLOOKUP($D6,BS연결,MATCH(N$1,BS연결H,0),0)/100,"") | O6: =IFERROR(VLOOKUP($D6,BS연결,MATCH(O$1,BS연결H,0),0)/100,"") | P6: =IFERROR(VLOOKUP($D6,BS연결,MATCH(P$1,BS연결H,0),0)/100,"") | Q6: =IFERROR(VLOOKUP($D6,BS연결,MATCH(Q$1,BS연결H,0),0)/100,"") | R6: =IFERROR(VLOOKUP($D6,BS연결,MATCH(R$1,BS연결H,0),0)/100,"") | S6: =IFERROR(VLOOKUP($D6,BS연결,MATCH(S$1,BS연결H,0),0)/100,"") | T6: =IFERROR(VLOOKUP($D6,BS연결,MATCH(T$1,BS연결H,0),0)/100,"") | U6: =IFERROR(VLOOKUP($D6,BS연결,MATCH(U$1,BS연결H,0),0)/100,"") | ... Y6: =IFERROR(VLOOKUP($D6,BS연결,MATCH(Y$1,BS연결H,0),0)/100,"") | Z6: =IFERROR(Z5-Z7,"") | AA6: =IFERROR(AA5-AA7,"") | AB6: =SUM(X6:AA6) | AC6: =IFERROR(AC5-AC7,"") | AD6: =IFERROR(AD5-AD7,"") | AE6: =IFERROR(AE5-AE7,"") | AF6: =IFERROR(AF5-AF7,"") | AG6: =SUM(AC6:AF6) | AH6: =IFERROR(AH5-AH7,"") | AI6: =IFERROR(AI5-AI7,"") | AJ6: =IFERROR(AJ5-AJ7,"") | AK6: =IFERROR(AK5-AK7,"") | AL6: =SUM(AH6:AK6)
A7: 매출총이익 | B7: 손익 | C7: 억원 | D7: 매출총이익 | E7: =IFERROR(VLOOKUP($D7,BS별도,MATCH(E$1,BS별도H,0),0)/100,"") | F7: =IFERROR(VLOOKUP($D7,BS별도,MATCH(F$1,BS별도H,0),0)/100,"") | G7: =IFERROR(VLOOKUP($D7,BS별도,MATCH(G$1,BS별도H,0),0)/100,"") | I7: =IFERROR(VLOOKUP($D7,BS별도,MATCH(I$1,BS별도H,0),0)/100,"") | J7: =IFERROR(VLOOKUP($D7,BS별도,MATCH(J$1,BS별도H,0),0)/100,"") | K7: =IFERROR(VLOOKUP($D7,BS별도,MATCH(K$1,BS별도H,0),0)/100,"") | L7: =IFERROR(VLOOKUP($D7,BS연결,MATCH(L$1,BS연결H,0),0)/100,"") | M7: =SUM(I7:L7) | N7: =IFERROR(VLOOKUP($D7,BS연결,MATCH(N$1,BS연결H,0),0)/100,"") | O7: =IFERROR(VLOOKUP($D7,BS연결,MATCH(O$1,BS연결H,0),0)/100,"") | P7: =IFERROR(VLOOKUP($D7,BS연결,MATCH(P$1,BS연결H,0),0)/100,"") | Q7: =IFERROR(VLOOKUP($D7,BS연결,MATCH(Q$1,BS연결H,0),0)/100,"") | R7: =IFERROR(VLOOKUP($D7,BS연결,MATCH(R$1,BS연결H,0),0)/100,"") | S7: =IFERROR(VLOOKUP($D7,BS연결,MATCH(S$1,BS연결H,0),0)/100,"") | T7: =IFERROR(VLOOKUP($D7,BS연결,MATCH(T$1,BS연결H,0),0)/100,"") | U7: =IFERROR(VLOOKUP($D7,BS연결,MATCH(U$1,BS연결H,0),0)/100,"") | ... Y7: =IFERROR(VLOOKUP($D7,BS연결,MATCH(Y$1,BS연결H,0),0)/100,"") | Z7: =IFERROR(Z9+Z8,"") | AA7: =IFERROR(AA9+AA8,"") | AB7: =SUM(X7:AA7) | AC7: =IFERROR(AC9+AC8,"") | AD7: =IFERROR(AD9+AD8,"") | AE7: =IFERROR(AE9+AE8,"") | AF7: =IFERROR(AF9+AF8,"") | AG7: =SUM(AC7:AF7) | AH7: =IFERROR(AH9+AH8,"") | AI7: =IFERROR(AI9+AI8,"") | AJ7: =IFERROR(AJ9+AJ8,"") | AK7: =IFERROR(AK9+AK8,"") | AL7: =SUM(AH7:AK7)
A8: 판관비 | B8: 손익 | C8: 억원 | D8: 판관비 | E8: =IFERROR(VLOOKUP($D8,BS별도,MATCH(E$1,BS별도H,0),0)/100,"") | F8: =IFERROR(VLOOKUP($D8,BS별도,MATCH(F$1,BS별도H,0),0)/100,"") | G8: =IFERROR(VLOOKUP($D8,BS별도,MATCH(G$1,BS별도H,0),0)/100,"") | I8: =IFERROR(VLOOKUP($D8,BS별도,MATCH(I$1,BS별도H,0),0)/100,"") | J8: =IFERROR(VLOOKUP($D8,BS별도,MATCH(J$1,BS별도H,0),0)/100,"") | K8: =IFERROR(VLOOKUP($D8,BS별도,MATCH(K$1,BS별도H,0),0)/100,"") | L8: =IFERROR(VLOOKUP($D8,BS연결,MATCH(L$1,BS연결H,0),0)/100,"") | M8: =SUM(I8:L8) | N8: =IFERROR(VLOOKUP($D8,BS연결,MATCH(N$1,BS연결H,0),0)/100,"") | O8: =IFERROR(VLOOKUP($D8,BS연결,MATCH(O$1,BS연결H,0),0)/100,"") | P8: =IFERROR(VLOOKUP($D8,BS연결,MATCH(P$1,BS연결H,0),0)/100,"") | Q8: =IFERROR(VLOOKUP($D8,BS연결,MATCH(Q$1,BS연결H,0),0)/100,"") | R8: =IFERROR(VLOOKUP($D8,BS연결,MATCH(R$1,BS연결H,0),0)/100,"") | S8: =IFERROR(VLOOKUP($D8,BS연결,MATCH(S$1,BS연결H,0),0)/100,"") | T8: =IFERROR(VLOOKUP($D8,BS연결,MATCH(T$1,BS연결H,0),0)/100,"") | U8: =IFERROR(VLOOKUP($D8,BS연결,MATCH(U$1,BS연결H,0),0)/100,"") | ... Y8: =IFERROR(VLOOKUP($D8,BS연결,MATCH(Y$1,BS연결H,0),0)/100,"") | Z8: =IFERROR(Z5*변수!Z22,"") | AA8: =IFERROR(AA5*변수!AA22,"") | AB8: =SUM(X8:AA8) | AC8: =IFERROR(AC5*변수!AC22,"") | AD8: =IFERROR(AD5*변수!AD22,"") | AE8: =IFERROR(AE5*변수!AE22,"") | AF8: =IFERROR(AF5*변수!AF22,"") | AG8: =SUM(AC8:AF8) | AH8: =IFERROR(AH5*변수!AH22,"") | AI8: =IFERROR(AI5*변수!AI22,"") | AJ8: =IFERROR(AJ5*변수!AJ22,"") | AK8: =IFERROR(AK5*변수!AK22,"") | AL8: =SUM(AH8:AK8)
A9: 영업이익 | B9: 손익 | C9: 억원 | D9: 영업이익 | E9: =IFERROR(VLOOKUP($D9,BS별도,MATCH(E$1,BS별도H,0),0)/100,"") | F9: =IFERROR(VLOOKUP($D9,BS별도,MATCH(F$1,BS별도H,0),0)/100,"") | G9: =IFERROR(VLOOKUP($D9,BS별도,MATCH(G$1,BS별도H,0),0)/100,"") | I9: =IFERROR(VLOOKUP($D9,BS별도,MATCH(I$1,BS별도H,0),0)/100,"") | J9: =IFERROR(VLOOKUP($D9,BS별도,MATCH(J$1,BS별도H,0),0)/100,"") | K9: =IFERROR(VLOOKUP($D9,BS별도,MATCH(K$1,BS별도H,0),0)/100,"") | L9: =IFERROR(VLOOKUP($D9,BS연결,MATCH(L$1,BS연결H,0),0)/100,"") | M9: =SUM(I9:L9) | N9: =IFERROR(VLOOKUP($D9,BS연결,MATCH(N$1,BS연결H,0),0)/100,"") | O9: =IFERROR(VLOOKUP($D9,BS연결,MATCH(O$1,BS연결H,0),0)/100,"") | P9: =IFERROR(VLOOKUP($D9,BS연결,MATCH(P$1,BS연결H,0),0)/100,"") | Q9: =IFERROR(VLOOKUP($D9,BS연결,MATCH(Q$1,BS연결H,0),0)/100,"") | R9: =IFERROR(VLOOKUP($D9,BS연결,MATCH(R$1,BS연결H,0),0)/100,"") | S9: =IFERROR(VLOOKUP($D9,BS연결,MATCH(S$1,BS연결H,0),0)/100,"") | T9: =IFERROR(VLOOKUP($D9,BS연결,MATCH(T$1,BS연결H,0),0)/100,"") | U9: =IFERROR(VLOOKUP($D9,BS연결,MATCH(U$1,BS연결H,0),0)/100,"") | ... Y9: =IFERROR(VLOOKUP($D9,BS연결,MATCH(Y$1,BS연결H,0),0)/100,"") | Z9: =IFERROR(Z5*변수!Z23,"") | AA9: =IFERROR(AA5*변수!AA23,"") | AB9: =SUM(X9:AA9) | AC9: =IFERROR(AC5*변수!AC23,"") | AD9: =IFERROR(AD5*변수!AD23,"") | AE9: =IFERROR(AE5*변수!AE23,"") | AF9: =IFERROR(AF5*변수!AF23,"") | AG9: =SUM(AC9:AF9) | AH9: =IFERROR(AH5*변수!AH23,"") | AI9: =IFERROR(AI5*변수!AI23,"") | AJ9: =IFERROR(AJ5*변수!AJ23,"") | AK9: =IFERROR(AK5*변수!AK23,"") | AL9: =SUM(AH9:AK9)
A10: OPM | B10: 손익 | C10: % | D10: 영업이익률 | E10: =IFERROR(E9/E5,"") | F10: =IFERROR(F9/F5,"") | G10: =IFERROR(G9/G5,"") | I10: =IFERROR(I9/I5,"") | J10: =IFERROR(J9/J5,"") | K10: =IFERROR(K9/K5,"") | L10: =IFERROR(L9/L5,"") | M10: =IFERROR(M9/M5,"") | N10: =IFERROR(N9/N5,"") | O10: =IFERROR(O9/O5,"") | P10: =IFERROR(P9/P5,"") | ... AL10: =IFERROR(AL9/AL5,"")
A11: 금융손익 | B11: 손익 | C11: 억원 | D11: 금융손익 | E11: =IFERROR(VLOOKUP($D11,BS별도,MATCH(E$1,BS별도H,0),0)/100,"") | F11: =IFERROR(VLOOKUP($D11,BS별도,MATCH(F$1,BS별도H,0),0)/100,"") | G11: =IFERROR(VLOOKUP($D11,BS별도,MATCH(G$1,BS별도H,0),0)/100,"") | I11: =IFERROR(VLOOKUP($D11,BS별도,MATCH(I$1,BS별도H,0),0)/100,"") | J11: =IFERROR(VLOOKUP($D11,BS별도,MATCH(J$1,BS별도H,0),0)/100,"") | K11: =IFERROR(VLOOKUP($D11,BS별도,MATCH(K$1,BS별도H,0),0)/100,"") | L11: =IFERROR(VLOOKUP($D11,BS연결,MATCH(L$1,BS연결H,0),0)/100,"") | M11: =SUM(I11:L11) | N11: =IFERROR(VLOOKUP($D11,BS연결,MATCH(N$1,BS연결H,0),0)/100,"") | O11: =IFERROR(VLOOKUP($D11,BS연결,MATCH(O$1,BS연결H,0),0)/100,"") | P11: =IFERROR(VLOOKUP($D11,BS연결,MATCH(P$1,BS연결H,0),0)/100,"") | Q11: =IFERROR(VLOOKUP($D11,BS연결,MATCH(Q$1,BS연결H,0),0)/100,"") | R11: =IFERROR(VLOOKUP($D11,BS연결,MATCH(R$1,BS연결H,0),0)/100,"") | S11: =IFERROR(VLOOKUP($D11,BS연결,MATCH(S$1,BS연결H,0),0)/100,"") | T11: =IFERROR(VLOOKUP($D11,BS연결,MATCH(T$1,BS연결H,0),0)/100,"") | U11: =IFERROR(VLOOKUP($D11,BS연결,MATCH(U$1,BS연결H,0),0)/100,"") | ... Y11: =IFERROR(VLOOKUP($D11,BS연결,MATCH(Y$1,BS연결H,0),0)/100,"") | Z11: =IFERROR(Z12,"") | AA11: =IFERROR(AA12,"") | AB11: =SUM(X11:AA11) | AC11: =IFERROR(AC12,"") | AD11: =IFERROR(AD12,"") | AE11: =IFERROR(AE12,"") | AF11: =IFERROR(AF12,"") | AG11: =SUM(AC11:AF11) | AH11: =IFERROR(AH12,"") | AI11: =IFERROR(AI12,"") | AJ11: =IFERROR(AJ12,"") | AK11: =IFERROR(AK12,"") | AL11: =SUM(AH11:AK11)
A12: 이자손익 | B12: 손익 | C12: 억원 | D12: 이자손익 | E12: =IFERROR(VLOOKUP($D12,BS별도,MATCH(E$1,BS별도H,0),0)/100,"") | F12: =IFERROR(VLOOKUP($D12,BS별도,MATCH(F$1,BS별도H,0),0)/100,"") | G12: =IFERROR(VLOOKUP($D12,BS별도,MATCH(G$1,BS별도H,0),0)/100,"") | I12: =IFERROR(VLOOKUP($D12,BS별도,MATCH(I$1,BS별도H,0),0)/100,"") | J12: =IFERROR(VLOOKUP($D12,BS별도,MATCH(J$1,BS별도H,0),0)/100,"") | K12: =IFERROR(VLOOKUP($D12,BS별도,MATCH(K$1,BS별도H,0),0)/100,"") | L12: =IFERROR(VLOOKUP($D12,BS연결,MATCH(L$1,BS연결H,0),0)/100,"") | M12: =SUM(I12:L12) | N12: =IFERROR(VLOOKUP($D12,BS연결,MATCH(N$1,BS연결H,0),0)/100,"") | O12: =IFERROR(VLOOKUP($D12,BS연결,MATCH(O$1,BS연결H,0),0)/100,"") | P12: =IFERROR(VLOOKUP($D12,BS연결,MATCH(P$1,BS연결H,0),0)/100,"") | Q12: =IFERROR(VLOOKUP($D12,BS연결,MATCH(Q$1,BS연결H,0),0)/100,"") | R12: =IFERROR(VLOOKUP($D12,BS연결,MATCH(R$1,BS연결H,0),0)/100,"") | S12: =IFERROR(VLOOKUP($D12,BS연결,MATCH(S$1,BS연결H,0),0)/100,"") | W12: =SUM(S12:V12) | Z12: =IFERROR((Y26*변수!$D$50-Y24*변수!$D$51)/4,"") | AA12: =IFERROR((Z26*변수!$D$50-Z24*변수!$D$51)/4,"") | AB12: =SUM(X12:AA12) | AC12: =IFERROR((AA26*변수!$D$50-AA24*변수!$D$51)/4,"") | AD12: =IFERROR((AC26*변수!$D$50-AC24*변수!$D$51)/4,"") | AE12: =IFERROR((AD26*변수!$D$50-AD24*변수!$D$51)/4,"") | AF12: =IFERROR((AE26*변수!$D$50-AE24*변수!$D$51)/4,"") | AG12: =SUM(AC12:AF12) | AH12: =IFERROR((AF26*변수!$D$50-AF24*변수!$D$51)/4,"") | AI12: =IFERROR((AH26*변수!$D$50-AH24*변수!$D$51)/4,"") | AJ12: =IFERROR((AI26*변수!$D$50-AI24*변수!$D$51)/4,"") | AK12: =IFERROR((AJ26*변수!$D$50-AJ24*변수!$D$51)/4,"") | AL12: =SUM(AH12:AK12)
A13: 기타영업외손익 | B13: 손익 | C13: 억원 | D13: 기타영업외손익 | E13: =IFERROR(VLOOKUP($D13,BS별도,MATCH(E$1,BS별도H,0),0)/100,"") | F13: =IFERROR(VLOOKUP($D13,BS별도,MATCH(F$1,BS별도H,0),0)/100,"") | G13: =IFERROR(VLOOKUP($D13,BS별도,MATCH(G$1,BS별도H,0),0)/100,"") | I13: =IFERROR(VLOOKUP($D13,BS별도,MATCH(I$1,BS별도H,0),0)/100,"") | J13: =IFERROR(VLOOKUP($D13,BS별도,MATCH(J$1,BS별도H,0),0)/100,"") | K13: =IFERROR(VLOOKUP($D13,BS별도,MATCH(K$1,BS별도H,0),0)/100,"") | L13: =IFERROR(VLOOKUP($D13,BS연결,MATCH(L$1,BS연결H,0),0)/100,"") | M13: =SUM(I13:L13) | N13: =IFERROR(VLOOKUP($D13,BS연결,MATCH(N$1,BS연결H,0),0)/100,"") | O13: =IFERROR(VLOOKUP($D13,BS연결,MATCH(O$1,BS연결H,0),0)/100,"") | P13: =IFERROR(VLOOKUP($D13,BS연결,MATCH(P$1,BS연결H,0),0)/100,"") | Q13: =IFERROR(VLOOKUP($D13,BS연결,MATCH(Q$1,BS연결H,0),0)/100,"") | R13: =IFERROR(VLOOKUP($D13,BS연결,MATCH(R$1,BS연결H,0),0)/100,"") | S13: =IFERROR(VLOOKUP($D13,BS연결,MATCH(S$1,BS연결H,0),0)/100,"") | T13: =IFERROR(VLOOKUP($D13,BS연결,MATCH(T$1,BS연결H,0),0)/100,"") | U13: =IFERROR(VLOOKUP($D13,BS연결,MATCH(U$1,BS연결H,0),0)/100,"") | V13: =IFERROR(VLOOKUP($D13,BS연결,MATCH(V$1,BS연결H,0),0)/100,"") | W13: =SUM(S13:V13) | X13: =IFERROR(VLOOKUP($D13,BS연결,MATCH(X$1,BS연결H,0),0)/100,"") | Y13: =IFERROR(VLOOKUP($D13,BS연결,MATCH(Y$1,BS연결H,0),0)/100,"") | Z13: =변수!Z24 | AA13: =변수!AA24 | AB13: =SUM(X13:AA13) | AC13: =변수!AC24 | AD13: =변수!AD24 | AE13: =변수!AE24 | AF13: =변수!AF24 | AG13: =SUM(AC13:AF13) | AH13: =변수!AH24 | AI13: =변수!AI24 | AJ13: =변수!AJ24 | AK13: =변수!AK24 | AL13: =SUM(AH13:AK13)
A14: 세전이익 | B14: 손익 | C14: 억원 | D14: 법인세비용차감전계속사업이익 | E14: =IFERROR(VLOOKUP($D14,BS별도,MATCH(E$1,BS별도H,0),0)/100,"") | F14: =IFERROR(VLOOKUP($D14,BS별도,MATCH(F$1,BS별도H,0),0)/100,"") | G14: =IFERROR(VLOOKUP($D14,BS별도,MATCH(G$1,BS별도H,0),0)/100,"") | I14: =IFERROR(VLOOKUP($D14,BS별도,MATCH(I$1,BS별도H,0),0)/100,"") | J14: =IFERROR(VLOOKUP($D14,BS별도,MATCH(J$1,BS별도H,0),0)/100,"") | K14: =IFERROR(VLOOKUP($D14,BS별도,MATCH(K$1,BS별도H,0),0)/100,"") | L14: =IFERROR(VLOOKUP($D14,BS연결,MATCH(L$1,BS연결H,0),0)/100,"") | M14: =SUM(I14:L14) | N14: =IFERROR(VLOOKUP($D14,BS연결,MATCH(N$1,BS연결H,0),0)/100,"") | O14: =IFERROR(VLOOKUP($D14,BS연결,MATCH(O$1,BS연결H,0),0)/100,"") | P14: =IFERROR(VLOOKUP($D14,BS연결,MATCH(P$1,BS연결H,0),0)/100,"") | Q14: =IFERROR(VLOOKUP($D14,BS연결,MATCH(Q$1,BS연결H,0),0)/100,"") | R14: =IFERROR(VLOOKUP($D14,BS연결,MATCH(R$1,BS연결H,0),0)/100,"") | S14: =IFERROR(VLOOKUP($D14,BS연결,MATCH(S$1,BS연결H,0),0)/100,"") | T14: =IFERROR(VLOOKUP($D14,BS연결,MATCH(T$1,BS연결H,0),0)/100,"") | U14: =IFERROR(VLOOKUP($D14,BS연결,MATCH(U$1,BS연결H,0),0)/100,"") | ... Y14: =IFERROR(VLOOKUP($D14,BS연결,MATCH(Y$1,BS연결H,0),0)/100,"") | Z14: =IFERROR(Z9+Z11+Z13,"") | AA14: =IFERROR(AA9+AA11+AA13,"") | AB14: =SUM(X14:AA14) | AC14: =IFERROR(AC9+AC11+AC13,"") | AD14: =IFERROR(AD9+AD11+AD13,"") | AE14: =IFERROR(AE9+AE11+AE13,"") | AF14: =IFERROR(AF9+AF11+AF13,"") | AG14: =SUM(AC14:AF14) | AH14: =IFERROR(AH9+AH11+AH13,"") | AI14: =IFERROR(AI9+AI11+AI13,"") | AJ14: =IFERROR(AJ9+AJ11+AJ13,"") | AK14: =IFERROR(AK9+AK11+AK13,"") | AL14: =SUM(AH14:AK14)
A15: 법인세비용 | B15: 손익 | C15: 억원 | D15: 법인세비용 | E15: =IFERROR(VLOOKUP($D15,BS별도,MATCH(E$1,BS별도H,0),0)/100,"") | F15: =IFERROR(VLOOKUP($D15,BS별도,MATCH(F$1,BS별도H,0),0)/100,"") | G15: =IFERROR(VLOOKUP($D15,BS별도,MATCH(G$1,BS별도H,0),0)/100,"") | I15: =IFERROR(VLOOKUP($D15,BS별도,MATCH(I$1,BS별도H,0),0)/100,"") | J15: =IFERROR(VLOOKUP($D15,BS별도,MATCH(J$1,BS별도H,0),0)/100,"") | K15: =IFERROR(VLOOKUP($D15,BS별도,MATCH(K$1,BS별도H,0),0)/100,"") | L15: =IFERROR(VLOOKUP($D15,BS연결,MATCH(L$1,BS연결H,0),0)/100,"") | M15: =SUM(I15:L15) | N15: =IFERROR(VLOOKUP($D15,BS연결,MATCH(N$1,BS연결H,0),0)/100,"") | O15: =IFERROR(VLOOKUP($D15,BS연결,MATCH(O$1,BS연결H,0),0)/100,"") | P15: =IFERROR(VLOOKUP($D15,BS연결,MATCH(P$1,BS연결H,0),0)/100,"") | Q15: =IFERROR(VLOOKUP($D15,BS연결,MATCH(Q$1,BS연결H,0),0)/100,"") | R15: =IFERROR(VLOOKUP($D15,BS연결,MATCH(R$1,BS연결H,0),0)/100,"") | S15: =IFERROR(VLOOKUP($D15,BS연결,MATCH(S$1,BS연결H,0),0)/100,"") | T15: =IFERROR(VLOOKUP($D15,BS연결,MATCH(T$1,BS연결H,0),0)/100,"") | U15: =IFERROR(VLOOKUP($D15,BS연결,MATCH(U$1,BS연결H,0),0)/100,"") | ... Y15: =IFERROR(VLOOKUP($D15,BS연결,MATCH(Y$1,BS연결H,0),0)/100,"") | Z15: =IFERROR(Z14*변수!Z25,"") | AA15: =IFERROR(AA14*변수!AA25,"") | AB15: =SUM(X15:AA15) | AC15: =IFERROR(AC14*변수!AC25,"") | AD15: =IFERROR(AD14*변수!AD25,"") | AE15: =IFERROR(AE14*변수!AE25,"") | AF15: =IFERROR(AF14*변수!AF25,"") | AG15: =SUM(AC15:AF15) | AH15: =IFERROR(AH14*변수!AH25,"") | AI15: =IFERROR(AI14*변수!AI25,"") | AJ15: =IFERROR(AJ14*변수!AJ25,"") | AK15: =IFERROR(AK14*변수!AK25,"") | AL15: =SUM(AH15:AK15)
A16: 당기순이익 | B16: 손익 | C16: 억원 | D16: 당기순이익 | E16: =IFERROR(VLOOKUP($D16,BS별도,MATCH(E$1,BS별도H,0),0)/100,"") | F16: =IFERROR(VLOOKUP($D16,BS별도,MATCH(F$1,BS별도H,0),0)/100,"") | G16: =IFERROR(VLOOKUP($D16,BS별도,MATCH(G$1,BS별도H,0),0)/100,"") | I16: =IFERROR(VLOOKUP($D16,BS별도,MATCH(I$1,BS별도H,0),0)/100,"") | J16: =IFERROR(VLOOKUP($D16,BS별도,MATCH(J$1,BS별도H,0),0)/100,"") | K16: =IFERROR(VLOOKUP($D16,BS별도,MATCH(K$1,BS별도H,0),0)/100,"") | L16: =IFERROR(VLOOKUP($D16,BS연결,MATCH(L$1,BS연결H,0),0)/100,"") | M16: =SUM(I16:L16) | N16: =IFERROR(VLOOKUP($D16,BS연결,MATCH(N$1,BS연결H,0),0)/100,"") | O16: =IFERROR(VLOOKUP($D16,BS연결,MATCH(O$1,BS연결H,0),0)/100,"") | P16: =IFERROR(VLOOKUP($D16,BS연결,MATCH(P$1,BS연결H,0),0)/100,"") | Q16: =IFERROR(VLOOKUP($D16,BS연결,MATCH(Q$1,BS연결H,0),0)/100,"") | R16: =IFERROR(VLOOKUP($D16,BS연결,MATCH(R$1,BS연결H,0),0)/100,"") | S16: =IFERROR(VLOOKUP($D16,BS연결,MATCH(S$1,BS연결H,0),0)/100,"") | T16: =IFERROR(VLOOKUP($D16,BS연결,MATCH(T$1,BS연결H,0),0)/100,"") | U16: =IFERROR(VLOOKUP($D16,BS연결,MATCH(U$1,BS연결H,0),0)/100,"") | ... Y16: =IFERROR(VLOOKUP($D16,BS연결,MATCH(Y$1,BS연결H,0),0)/100,"") | Z16: =IFERROR(Z14-Z15,"") | AA16: =IFERROR(AA14-AA15,"") | AB16: =SUM(X16:AA16) | AC16: =IFERROR(AC14-AC15,"") | AD16: =IFERROR(AD14-AD15,"") | AE16: =IFERROR(AE14-AE15,"") | AF16: =IFERROR(AF14-AF15,"") | AG16: =SUM(AC16:AF16) | AH16: =IFERROR(AH14-AH15,"") | AI16: =IFERROR(AI14-AI15,"") | AJ16: =IFERROR(AJ14-AJ15,"") | AK16: =IFERROR(AK14-AK15,"") | AL16: =SUM(AH16:AK16)
A17: 지배주주순이익 | B17: 손익 | C17: 억원 | D17: (지배주주지분)당기순이익 | E17: =IFERROR(VLOOKUP($D17,BS별도,MATCH(E$1,BS별도H,0),0)/100,"") | F17: =IFERROR(VLOOKUP($D17,BS별도,MATCH(F$1,BS별도H,0),0)/100,"") | G17: =IFERROR(VLOOKUP($D17,BS별도,MATCH(G$1,BS별도H,0),0)/100,"") | I17: =IFERROR(VLOOKUP($D17,BS별도,MATCH(I$1,BS별도H,0),0)/100,"") | J17: =IFERROR(VLOOKUP($D17,BS별도,MATCH(J$1,BS별도H,0),0)/100,"") | K17: =IFERROR(VLOOKUP($D17,BS별도,MATCH(K$1,BS별도H,0),0)/100,"") | L17: =IFERROR(VLOOKUP($D17,BS연결,MATCH(L$1,BS연결H,0),0)/100,"") | M17: =SUM(I17:L17) | N17: =IFERROR(VLOOKUP($D17,BS연결,MATCH(N$1,BS연결H,0),0)/100,"") | O17: =IFERROR(VLOOKUP($D17,BS연결,MATCH(O$1,BS연결H,0),0)/100,"") | P17: =IFERROR(VLOOKUP($D17,BS연결,MATCH(P$1,BS연결H,0),0)/100,"") | Q17: =IFERROR(VLOOKUP($D17,BS연결,MATCH(Q$1,BS연결H,0),0)/100,"") | R17: =IFERROR(VLOOKUP($D17,BS연결,MATCH(R$1,BS연결H,0),0)/100,"") | S17: =IFERROR(VLOOKUP($D17,BS연결,MATCH(S$1,BS연결H,0),0)/100,"") | T17: =IFERROR(VLOOKUP($D17,BS연결,MATCH(T$1,BS연결H,0),0)/100,"") | U17: =IFERROR(VLOOKUP($D17,BS연결,MATCH(U$1,BS연결H,0),0)/100,"") | ... Y17: =IFERROR(VLOOKUP($D17,BS연결,MATCH(Y$1,BS연결H,0),0)/100,"") | Z17: =IFERROR(Z16*변수!Z26,"") | AA17: =IFERROR(AA16*변수!AA26,"") | AB17: =SUM(X17:AA17) | AC17: =IFERROR(AC16*변수!AC26,"") | AD17: =IFERROR(AD16*변수!AD26,"") | AE17: =IFERROR(AE16*변수!AE26,"") | AF17: =IFERROR(AF16*변수!AF26,"") | AG17: =SUM(AC17:AF17) | AH17: =IFERROR(AH16*변수!AH26,"") | AI17: =IFERROR(AI16*변수!AI26,"") | AJ17: =IFERROR(AJ16*변수!AJ26,"") | AK17: =IFERROR(AK16*변수!AK26,"") | AL17: =SUM(AH17:AK17)
A18: 감가상각비 | B18: 손익 | C18: 억원 | D18: 감가상각비 | E18: =IFERROR(VLOOKUP($D18,BS별도,MATCH(E$1,BS별도H,0),0)/100,"") | F18: =IFERROR(VLOOKUP($D18,BS별도,MATCH(F$1,BS별도H,0),0)/100,"") | G18: =IFERROR(VLOOKUP($D18,BS별도,MATCH(G$1,BS별도H,0),0)/100,"") | I18: =IFERROR(VLOOKUP($D18,BS별도,MATCH(I$1,BS별도H,0),0)/100,"") | J18: =IFERROR(VLOOKUP($D18,BS별도,MATCH(J$1,BS별도H,0),0)/100,"") | K18: =IFERROR(VLOOKUP($D18,BS별도,MATCH(K$1,BS별도H,0),0)/100,"") | L18: =IFERROR(VLOOKUP($D18,BS연결,MATCH(L$1,BS연결H,0),0)/100,"") | M18: =SUM(I18:L18) | N18: =IFERROR(VLOOKUP($D18,BS연결,MATCH(N$1,BS연결H,0),0)/100,"") | O18: =IFERROR(VLOOKUP($D18,BS연결,MATCH(O$1,BS연결H,0),0)/100,"") | P18: =IFERROR(VLOOKUP($D18,BS연결,MATCH(P$1,BS연결H,0),0)/100,"") | Q18: =IFERROR(VLOOKUP($D18,BS연결,MATCH(Q$1,BS연결H,0),0)/100,"") | R18: =SUM(N18:Q18) | S18: =IFERROR(VLOOKUP($D18,BS연결,MATCH(S$1,BS연결H,0),0)/100,"") | T18: =IFERROR(VLOOKUP($D18,BS연결,MATCH(T$1,BS연결H,0),0)/100,"") | U18: =IFERROR(VLOOKUP($D18,BS연결,MATCH(U$1,BS연결H,0),0)/100,"") | V18: =IFERROR(VLOOKUP($D18,BS연결,MATCH(V$1,BS연결H,0),0)/100,"") | W18: =IFERROR(VLOOKUP($D18,BS연결,MATCH(W$1,BS연결H,0),0)/100,"") | X18: =IFERROR(VLOOKUP($D18,BS연결,MATCH(X$1,BS연결H,0),0)/100,"") | Y18: =IFERROR(VLOOKUP($D18,BS연결,MATCH(Y$1,BS연결H,0),0)/100,"") | Z18: =변수!Z27 | AA18: =변수!AA27 | AB18: =SUM(X18:AA18) | AC18: =변수!AC27 | AD18: =변수!AD27 | AE18: =변수!AE27 | AF18: =변수!AF27 | AG18: =SUM(AC18:AF18) | AH18: =변수!AH27 | AI18: =변수!AI27 | AJ18: =변수!AJ27 | AK18: =변수!AK27 | AL18: =SUM(AH18:AK18)
A19: EBITDA | B19: 손익 | C19: 억원 | D19: EBITDA | E19: 11.45 | F19: 12.31 | G19: -15.19 | I19: 3.84 | J19: -10.36 | K19: -15.81 | L19: -17.06 | M19: =SUM(I19:L19) | N19: -2.3 | O19: 20.97 | P19: 17.83 | Q19: 4.95 | R19: =SUM(N19:Q19) | S19: 11.22 | T19: 6.16 | U19: 13.23 | V19: -3.05 | W19: =SUM(S19:V19) | X19: -16.29 | Y19: -26.96 | Z19: =IFERROR(Z9+Z18,"") | AA19: =IFERROR(AA9+AA18,"") | AB19: =SUM(X19:AA19) | AC19: =IFERROR(AC9+AC18,"") | AD19: =IFERROR(AD9+AD18,"") | AE19: =IFERROR(AE9+AE18,"") | AF19: =IFERROR(AF9+AF18,"") | AG19: =SUM(AC19:AF19) | AH19: =IFERROR(AH9+AH18,"") | AI19: =IFERROR(AI9+AI18,"") | AJ19: =IFERROR(AJ9+AJ18,"") | AK19: =IFERROR(AK9+AK18,"") | AL19: =SUM(AH19:AK19)
A20: 자산총계 | B20: 재무상태 | C20: 억원 | D20: 자산총계 | E20: =IFERROR(VLOOKUP($D20,BS별도,MATCH(E$1,BS별도H,0),0)/100,"") | F20: =IFERROR(VLOOKUP($D20,BS별도,MATCH(F$1,BS별도H,0),0)/100,"") | G20: =IFERROR(VLOOKUP($D20,BS별도,MATCH(G$1,BS별도H,0),0)/100,"") | H20: 1297.02 | I20: =IFERROR(VLOOKUP($D20,BS별도,MATCH(I$1,BS별도H,0),0)/100,"") | J20: =IFERROR(VLOOKUP($D20,BS별도,MATCH(J$1,BS별도H,0),0)/100,"") | K20: =IFERROR(VLOOKUP($D20,BS별도,MATCH(K$1,BS별도H,0),0)/100,"") | L20: =IFERROR(VLOOKUP($D20,BS연결,MATCH(L$1,BS연결H,0),0)/100,"") | M20: =IFERROR(VLOOKUP($D20,BS연결,MATCH(M$1,BS연결H,0),0)/100,"") | N20: =IFERROR(VLOOKUP($D20,BS연결,MATCH(N$1,BS연결H,0),0)/100,"") | O20: =IFERROR(VLOOKUP($D20,BS연결,MATCH(O$1,BS연결H,0),0)/100,"") | P20: =IFERROR(VLOOKUP($D20,BS연결,MATCH(P$1,BS연결H,0),0)/100,"") | Q20: =IFERROR(VLOOKUP($D20,BS연결,MATCH(Q$1,BS연결H,0),0)/100,"") | R20: =IFERROR(VLOOKUP($D20,BS연결,MATCH(R$1,BS연결H,0),0)/100,"") | S20: =IFERROR(VLOOKUP($D20,BS연결,MATCH(S$1,BS연결H,0),0)/100,"") | ... Y20: =IFERROR(VLOOKUP($D20,BS연결,MATCH(Y$1,BS연결H,0),0)/100,"") | Z20: =IFERROR(Z21+Z22,"") | AA20: =IFERROR(AA21+AA22,"") | AB20: =AA20 | AC20: =IFERROR(AC21+AC22,"") | AD20: =IFERROR(AD21+AD22,"") | AE20: =IFERROR(AE21+AE22,"") | AF20: =IFERROR(AF21+AF22,"") | AG20: =AF20 | AH20: =IFERROR(AH21+AH22,"") | AI20: =IFERROR(AI21+AI22,"") | AJ20: =IFERROR(AJ21+AJ22,"") | AK20: =IFERROR(AK21+AK22,"") | AL20: =AK20
A21: 부채총계 | B21: 재무상태 | C21: 억원 | D21: 부채총계 | E21: =IFERROR(VLOOKUP($D21,BS별도,MATCH(E$1,BS별도H,0),0)/100,"") | F21: =IFERROR(VLOOKUP($D21,BS별도,MATCH(F$1,BS별도H,0),0)/100,"") | G21: =IFERROR(VLOOKUP($D21,BS별도,MATCH(G$1,BS별도H,0),0)/100,"") | H21: 232.93 | I21: =IFERROR(VLOOKUP($D21,BS별도,MATCH(I$1,BS별도H,0),0)/100,"") | J21: =IFERROR(VLOOKUP($D21,BS별도,MATCH(J$1,BS별도H,0),0)/100,"") | K21: =IFERROR(VLOOKUP($D21,BS별도,MATCH(K$1,BS별도H,0),0)/100,"") | L21: =IFERROR(VLOOKUP($D21,BS연결,MATCH(L$1,BS연결H,0),0)/100,"") | M21: =IFERROR(VLOOKUP($D21,BS연결,MATCH(M$1,BS연결H,0),0)/100,"") | N21: =IFERROR(VLOOKUP($D21,BS연결,MATCH(N$1,BS연결H,0),0)/100,"") | O21: =IFERROR(VLOOKUP($D21,BS연결,MATCH(O$1,BS연결H,0),0)/100,"") | P21: =IFERROR(VLOOKUP($D21,BS연결,MATCH(P$1,BS연결H,0),0)/100,"") | Q21: =IFERROR(VLOOKUP($D21,BS연결,MATCH(Q$1,BS연결H,0),0)/100,"") | R21: =IFERROR(VLOOKUP($D21,BS연결,MATCH(R$1,BS연결H,0),0)/100,"") | S21: =IFERROR(VLOOKUP($D21,BS연결,MATCH(S$1,BS연결H,0),0)/100,"") | ... Y21: =IFERROR(VLOOKUP($D21,BS연결,MATCH(Y$1,BS연결H,0),0)/100,"") | Z21: =IFERROR(Y21*(1+변수!Z28),"") | AA21: =IFERROR(Z21*(1+변수!AA28),"") | AB21: =AA21 | AC21: =IFERROR(AA21*(1+변수!AC28),"") | AD21: =IFERROR(AC21*(1+변수!AD28),"") | AE21: =IFERROR(AD21*(1+변수!AE28),"") | AF21: =IFERROR(AE21*(1+변수!AF28),"") | AG21: =AF21 | AH21: =IFERROR(AF21*(1+변수!AH28),"") | AI21: =IFERROR(AH21*(1+변수!AI28),"") | AJ21: =IFERROR(AI21*(1+변수!AJ28),"") | AK21: =IFERROR(AJ21*(1+변수!AK28),"") | AL21: =AK21
A22: 자본총계 | B22: 재무상태 | C22: 억원 | D22: 자본총계 | E22: =IFERROR(VLOOKUP($D22,BS별도,MATCH(E$1,BS별도H,0),0)/100,"") | F22: =IFERROR(VLOOKUP($D22,BS별도,MATCH(F$1,BS별도H,0),0)/100,"") | G22: =IFERROR(VLOOKUP($D22,BS별도,MATCH(G$1,BS별도H,0),0)/100,"") | H22: 1064.09 | I22: =IFERROR(VLOOKUP($D22,BS별도,MATCH(I$1,BS별도H,0),0)/100,"") | J22: =IFERROR(VLOOKUP($D22,BS별도,MATCH(J$1,BS별도H,0),0)/100,"") | K22: =IFERROR(VLOOKUP($D22,BS별도,MATCH(K$1,BS별도H,0),0)/100,"") | L22: =IFERROR(VLOOKUP($D22,BS연결,MATCH(L$1,BS연결H,0),0)/100,"") | M22: =IFERROR(VLOOKUP($D22,BS연결,MATCH(M$1,BS연결H,0),0)/100,"") | N22: =IFERROR(VLOOKUP($D22,BS연결,MATCH(N$1,BS연결H,0),0)/100,"") | O22: =IFERROR(VLOOKUP($D22,BS연결,MATCH(O$1,BS연결H,0),0)/100,"") | P22: =IFERROR(VLOOKUP($D22,BS연결,MATCH(P$1,BS연결H,0),0)/100,"") | Q22: =IFERROR(VLOOKUP($D22,BS연결,MATCH(Q$1,BS연결H,0),0)/100,"") | R22: =IFERROR(VLOOKUP($D22,BS연결,MATCH(R$1,BS연결H,0),0)/100,"") | S22: =IFERROR(VLOOKUP($D22,BS연결,MATCH(S$1,BS연결H,0),0)/100,"") | ... Y22: =IFERROR(VLOOKUP($D22,BS연결,MATCH(Y$1,BS연결H,0),0)/100,"") | Z22: =IFERROR(Y22+Z16-변수!Z29,"") | AA22: =IFERROR(Z22+AA16-변수!AA29,"") | AB22: =AA22 | AC22: =IFERROR(AA22+AC16-변수!AC29,"") | AD22: =IFERROR(AC22+AD16-변수!AD29,"") | AE22: =IFERROR(AD22+AE16-변수!AE29,"") | AF22: =IFERROR(AE22+AF16-변수!AF29,"") | AG22: =AF22 | AH22: =IFERROR(AF22+AH16-변수!AH29,"") | AI22: =IFERROR(AH22+AI16-변수!AI29,"") | AJ22: =IFERROR(AI22+AJ16-변수!AJ29,"") | AK22: =IFERROR(AJ22+AK16-변수!AK29,"") | AL22: =AK22
A23: 지배주주지분 | B23: 재무상태 | C23: 억원 | D23: 지배주주지분 | E23: =IFERROR(VLOOKUP($D23,BS별도,MATCH(E$1,BS별도H,0),0)/100,"") | F23: =IFERROR(VLOOKUP($D23,BS별도,MATCH(F$1,BS별도H,0),0)/100,"") | G23: =IFERROR(VLOOKUP($D23,BS별도,MATCH(G$1,BS별도H,0),0)/100,"") | H23: 1064.09 | I23: =IFERROR(VLOOKUP($D23,BS별도,MATCH(I$1,BS별도H,0),0)/100,"") | J23: =IFERROR(VLOOKUP($D23,BS별도,MATCH(J$1,BS별도H,0),0)/100,"") | K23: =IFERROR(VLOOKUP($D23,BS별도,MATCH(K$1,BS별도H,0),0)/100,"") | L23: =IFERROR(VLOOKUP($D23,BS연결,MATCH(L$1,BS연결H,0),0)/100,"") | M23: =IFERROR(VLOOKUP($D23,BS연결,MATCH(M$1,BS연결H,0),0)/100,"") | N23: =IFERROR(VLOOKUP($D23,BS연결,MATCH(N$1,BS연결H,0),0)/100,"") | O23: =IFERROR(VLOOKUP($D23,BS연결,MATCH(O$1,BS연결H,0),0)/100,"") | P23: =IFERROR(VLOOKUP($D23,BS연결,MATCH(P$1,BS연결H,0),0)/100,"") | Q23: =IFERROR(VLOOKUP($D23,BS연결,MATCH(Q$1,BS연결H,0),0)/100,"") | R23: =IFERROR(VLOOKUP($D23,BS연결,MATCH(R$1,BS연결H,0),0)/100,"") | S23: =IFERROR(VLOOKUP($D23,BS연결,MATCH(S$1,BS연결H,0),0)/100,"") | ... Y23: =IFERROR(VLOOKUP($D23,BS연결,MATCH(Y$1,BS연결H,0),0)/100,"") | Z23: =IFERROR(Y23+Z17-변수!Z30,"") | AA23: =IFERROR(Z23+AA17-변수!AA30,"") | AB23: =AA23 | AC23: =IFERROR(AA23+AC17-변수!AC30,"") | AD23: =IFERROR(AC23+AD17-변수!AD30,"") | AE23: =IFERROR(AD23+AE17-변수!AE30,"") | AF23: =IFERROR(AE23+AF17-변수!AF30,"") | AG23: =AF23 | AH23: =IFERROR(AF23+AH17-변수!AH30,"") | AI23: =IFERROR(AH23+AI17-변수!AI30,"") | AJ23: =IFERROR(AI23+AJ17-변수!AJ30,"") | AK23: =IFERROR(AJ23+AK17-변수!AK30,"") | AL23: =AK23
A24: 총차입금 | B24: 재무상태 | C24: 억원 | D24: 총차입금 | E24: =IFERROR(VLOOKUP($D24,BS별도,MATCH(E$1,BS별도H,0),0)/100,"") | F24: =IFERROR(VLOOKUP($D24,BS별도,MATCH(F$1,BS별도H,0),0)/100,"") | G24: =IFERROR(VLOOKUP($D24,BS별도,MATCH(G$1,BS별도H,0),0)/100,"") | H24: 52 | I24: =IFERROR(VLOOKUP($D24,BS별도,MATCH(I$1,BS별도H,0),0)/100,"") | J24: =IFERROR(VLOOKUP($D24,BS별도,MATCH(J$1,BS별도H,0),0)/100,"") | K24: =IFERROR(VLOOKUP($D24,BS별도,MATCH(K$1,BS별도H,0),0)/100,"") | L24: =IFERROR(VLOOKUP($D24,BS연결,MATCH(L$1,BS연결H,0),0)/100,"") | M24: =IFERROR(VLOOKUP($D24,BS연결,MATCH(M$1,BS연결H,0),0)/100,"") | N24: =IFERROR(VLOOKUP($D24,BS연결,MATCH(N$1,BS연결H,0),0)/100,"") | O24: =IFERROR(VLOOKUP($D24,BS연결,MATCH(O$1,BS연결H,0),0)/100,"") | P24: =IFERROR(VLOOKUP($D24,BS연결,MATCH(P$1,BS연결H,0),0)/100,"") | Q24: =IFERROR(VLOOKUP($D24,BS연결,MATCH(Q$1,BS연결H,0),0)/100,"") | R24: =IFERROR(VLOOKUP($D24,BS연결,MATCH(R$1,BS연결H,0),0)/100,"") | S24: =IFERROR(VLOOKUP($D24,BS연결,MATCH(S$1,BS연결H,0),0)/100,"") | ... Y24: =IFERROR(VLOOKUP($D24,BS연결,MATCH(Y$1,BS연결H,0),0)/100,"") | Z24: =IFERROR(Y24*(1+변수!Z31),"") | AA24: =IFERROR(Z24*(1+변수!AA31),"") | AB24: =AA24 | AC24: =IFERROR(AA24*(1+변수!AC31),"") | AD24: =IFERROR(AC24*(1+변수!AD31),"") | AE24: =IFERROR(AD24*(1+변수!AE31),"") | AF24: =IFERROR(AE24*(1+변수!AF31),"") | AG24: =AF24 | AH24: =IFERROR(AF24*(1+변수!AH31),"") | AI24: =IFERROR(AH24*(1+변수!AI31),"") | AJ24: =IFERROR(AI24*(1+변수!AJ31),"") | AK24: =IFERROR(AJ24*(1+변수!AK31),"") | AL24: =AK24
A25: 순차입금 | B25: 재무상태 | C25: 억원 | D25: 순차입금 | E25: =IFERROR(VLOOKUP($D25,BS별도,MATCH(E$1,BS별도H,0),0)/100,"") | F25: =IFERROR(VLOOKUP($D25,BS별도,MATCH(F$1,BS별도H,0),0)/100,"") | G25: =IFERROR(VLOOKUP($D25,BS별도,MATCH(G$1,BS별도H,0),0)/100,"") | H25: -713.58 | I25: =IFERROR(VLOOKUP($D25,BS별도,MATCH(I$1,BS별도H,0),0)/100,"") | J25: =IFERROR(VLOOKUP($D25,BS별도,MATCH(J$1,BS별도H,0),0)/100,"") | K25: =IFERROR(VLOOKUP($D25,BS별도,MATCH(K$1,BS별도H,0),0)/100,"") | L25: =IFERROR(VLOOKUP($D25,BS연결,MATCH(L$1,BS연결H,0),0)/100,"") | M25: =IFERROR(VLOOKUP($D25,BS연결,MATCH(M$1,BS연결H,0),0)/100,"") | N25: =IFERROR(VLOOKUP($D25,BS연결,MATCH(N$1,BS연결H,0),0)/100,"") | O25: =IFERROR(VLOOKUP($D25,BS연결,MATCH(O$1,BS연결H,0),0)/100,"") | P25: =IFERROR(VLOOKUP($D25,BS연결,MATCH(P$1,BS연결H,0),0)/100,"") | Q25: =IFERROR(VLOOKUP($D25,BS연결,MATCH(Q$1,BS연결H,0),0)/100,"") | R25: =IFERROR(VLOOKUP($D25,BS연결,MATCH(R$1,BS연결H,0),0)/100,"") | S25: =IFERROR(VLOOKUP($D25,BS연결,MATCH(S$1,BS연결H,0),0)/100,"") | ... Y25: =IFERROR(VLOOKUP($D25,BS연결,MATCH(Y$1,BS연결H,0),0)/100,"") | Z25: =IFERROR(Y25*(1+변수!Z32),"") | AA25: =IFERROR(Z25*(1+변수!AA32),"") | AB25: =AA25 | AC25: =IFERROR(AA25*(1+변수!AC32),"") | AD25: =IFERROR(AC25*(1+변수!AD32),"") | AE25: =IFERROR(AD25*(1+변수!AE32),"") | AF25: =IFERROR(AE25*(1+변수!AF32),"") | AG25: =AF25 | AH25: =IFERROR(AF25*(1+변수!AH32),"") | AI25: =IFERROR(AH25*(1+변수!AI32),"") | AJ25: =IFERROR(AI25*(1+변수!AJ32),"") | AK25: =IFERROR(AJ25*(1+변수!AK32),"") | AL25: =AK25
A26: 이자발생자산 | B26: 재무상태 | C26: 억원 | D26: 이자발생자산 | E26: =IFERROR(VLOOKUP($D26,BS별도,MATCH(E$1,BS별도H,0),0)/100,"") | F26: =IFERROR(VLOOKUP($D26,BS별도,MATCH(F$1,BS별도H,0),0)/100,"") | G26: =IFERROR(VLOOKUP($D26,BS별도,MATCH(G$1,BS별도H,0),0)/100,"") | H26: 841.45 | I26: =IFERROR(VLOOKUP($D26,BS별도,MATCH(I$1,BS별도H,0),0)/100,"") | J26: =IFERROR(VLOOKUP($D26,BS별도,MATCH(J$1,BS별도H,0),0)/100,"") | K26: =IFERROR(VLOOKUP($D26,BS별도,MATCH(K$1,BS별도H,0),0)/100,"") | L26: =IFERROR(VLOOKUP($D26,BS연결,MATCH(L$1,BS연결H,0),0)/100,"") | M26: =IFERROR(VLOOKUP($D26,BS연결,MATCH(M$1,BS연결H,0),0)/100,"") | N26: =IFERROR(VLOOKUP($D26,BS연결,MATCH(N$1,BS연결H,0),0)/100,"") | O26: =IFERROR(VLOOKUP($D26,BS연결,MATCH(O$1,BS연결H,0),0)/100,"") | P26: =IFERROR(VLOOKUP($D26,BS연결,MATCH(P$1,BS연결H,0),0)/100,"") | Q26: =IFERROR(VLOOKUP($D26,BS연결,MATCH(Q$1,BS연결H,0),0)/100,"") | R26: =IFERROR(VLOOKUP($D26,BS연결,MATCH(R$1,BS연결H,0),0)/100,"") | S26: =IFERROR(VLOOKUP($D26,BS연결,MATCH(S$1,BS연결H,0),0)/100,"") | ... Y26: =IFERROR(VLOOKUP($D26,BS연결,MATCH(Y$1,BS연결H,0),0)/100,"") | Z26: =IFERROR(Y26*(1+변수!Z33),"") | AA26: =IFERROR(Z26*(1+변수!AA33),"") | AB26: =AA26 | AC26: =IFERROR(AA26*(1+변수!AC33),"") | AD26: =IFERROR(AC26*(1+변수!AD33),"") | AE26: =IFERROR(AD26*(1+변수!AE33),"") | AF26: =IFERROR(AE26*(1+변수!AF33),"") | AG26: =AF26 | AH26: =IFERROR(AF26*(1+변수!AH33),"") | AI26: =IFERROR(AH26*(1+변수!AI33),"") | AJ26: =IFERROR(AI26*(1+변수!AJ33),"") | AK26: =IFERROR(AJ26*(1+변수!AK33),"") | AL26: =AK26
A27: 현금및현금성자산 | B27: 재무상태 | C27: 억원 | D27: 현금및현금성자산 | E27: =IFERROR(VLOOKUP($D27,BS별도,MATCH(E$1,BS별도H,0),0)/100,"") | F27: =IFERROR(VLOOKUP($D27,BS별도,MATCH(F$1,BS별도H,0),0)/100,"") | G27: =IFERROR(VLOOKUP($D27,BS별도,MATCH(G$1,BS별도H,0),0)/100,"") | H27: 229.58 | I27: =IFERROR(VLOOKUP($D27,BS별도,MATCH(I$1,BS별도H,0),0)/100,"") | J27: =IFERROR(VLOOKUP($D27,BS별도,MATCH(J$1,BS별도H,0),0)/100,"") | K27: =IFERROR(VLOOKUP($D27,BS별도,MATCH(K$1,BS별도H,0),0)/100,"") | L27: =IFERROR(VLOOKUP($D27,BS연결,MATCH(L$1,BS연결H,0),0)/100,"") | M27: =IFERROR(VLOOKUP($D27,BS연결,MATCH(M$1,BS연결H,0),0)/100,"") | N27: =IFERROR(VLOOKUP($D27,BS연결,MATCH(N$1,BS연결H,0),0)/100,"") | O27: =IFERROR(VLOOKUP($D27,BS연결,MATCH(O$1,BS연결H,0),0)/100,"") | P27: =IFERROR(VLOOKUP($D27,BS연결,MATCH(P$1,BS연결H,0),0)/100,"") | Q27: =IFERROR(VLOOKUP($D27,BS연결,MATCH(Q$1,BS연결H,0),0)/100,"") | R27: =IFERROR(VLOOKUP($D27,BS연결,MATCH(R$1,BS연결H,0),0)/100,"") | S27: =IFERROR(VLOOKUP($D27,BS연결,MATCH(S$1,BS연결H,0),0)/100,"") | ... Y27: =IFERROR(VLOOKUP($D27,BS연결,MATCH(Y$1,BS연결H,0),0)/100,"") | AB27: =AA27 | AG27: =AF27 | AL27: =AK27
A28: 영업활동현금흐름 | B28: 현금흐름 | C28: 억원 | D28: 영업활동으로인한현금흐름 | E28: =IFERROR(VLOOKUP($D28,BS별도,MATCH(E$1,BS별도H,0),0)/100,"") | F28: =IFERROR(VLOOKUP($D28,BS별도,MATCH(F$1,BS별도H,0),0)/100,"") | G28: =IFERROR(VLOOKUP($D28,BS별도,MATCH(G$1,BS별도H,0),0)/100,"") | I28: =IFERROR(VLOOKUP($D28,BS별도,MATCH(I$1,BS별도H,0),0)/100,"") | J28: =IFERROR(VLOOKUP($D28,BS별도,MATCH(J$1,BS별도H,0),0)/100,"") | K28: =IFERROR(VLOOKUP($D28,BS별도,MATCH(K$1,BS별도H,0),0)/100,"") | L28: =IFERROR(VLOOKUP($D28,BS연결,MATCH(L$1,BS연결H,0),0)/100,"") | M28: =SUM(I28:L28) | N28: =IFERROR(VLOOKUP($D28,BS연결,MATCH(N$1,BS연결H,0),0)/100,"") | O28: =IFERROR(VLOOKUP($D28,BS연결,MATCH(O$1,BS연결H,0),0)/100,"") | P28: =IFERROR(VLOOKUP($D28,BS연결,MATCH(P$1,BS연결H,0),0)/100,"") | Q28: =IFERROR(VLOOKUP($D28,BS연결,MATCH(Q$1,BS연결H,0),0)/100,"") | R28: =IFERROR(VLOOKUP($D28,BS연결,MATCH(R$1,BS연결H,0),0)/100,"") | S28: =IFERROR(VLOOKUP($D28,BS연결,MATCH(S$1,BS연결H,0),0)/100,"") | T28: =IFERROR(VLOOKUP($D28,BS연결,MATCH(T$1,BS연결H,0),0)/100,"") | U28: =IFERROR(VLOOKUP($D28,BS연결,MATCH(U$1,BS연결H,0),0)/100,"") | ... Y28: =IFERROR(VLOOKUP($D28,BS연결,MATCH(Y$1,BS연결H,0),0)/100,"") | AB28: =SUM(X28:AA28) | AG28: =SUM(AC28:AF28) | AL28: =SUM(AH28:AK28)
A29: 주식수 | B29: 주당 | C29: 백만주 | D29: 유통주식수 | E29: 8.761 | F29: 8.673 | G29: 8.585 | H29: =G29 | I29: 8.585 | J29: 8.585 | K29: 8.585 | L29: 8.582 | M29: =L29 | N29: 8.582 | O29: 8.582 | P29: 8.582 | Q29: 8.582 | R29: =Q29 | S29: 8.582 | T29: 8.582 | U29: 8.582 | V29: 8.582 | W29: =V29 | X29: 8.582 | Y29: 8.582 | Z29: =IFERROR(Y29*(1+변수!Z36),"") | AA29: =IFERROR(Z29*(1+변수!AA36),"") | AB29: =AA29 | AC29: =IFERROR(AA29*(1+변수!AC36),"") | AD29: =IFERROR(AC29*(1+변수!AD36),"") | AE29: =IFERROR(AD29*(1+변수!AE36),"") | AF29: =IFERROR(AE29*(1+변수!AF36),"") | AG29: =AF29 | AH29: =IFERROR(AF29*(1+변수!AH36),"") | AI29: =IFERROR(AH29*(1+변수!AI36),"") | AJ29: =IFERROR(AI29*(1+변수!AJ36),"") | AK29: =IFERROR(AJ29*(1+변수!AK36),"") | AL29: =AK29
A30: EPS | B30: 주당 | C30: 원 | D30: EPS | E30: =IFERROR(E17*100/E29,"") | F30: =IFERROR(F17*100/F29,"") | G30: =IFERROR(G17*100/G29,"") | I30: =IFERROR(I17*100/I29,"") | J30: =IFERROR(J17*100/J29,"") | K30: =IFERROR(K17*100/K29,"") | L30: =IFERROR(L17*100/L29,"") | M30: =SUM(I30:L30) | N30: =IFERROR(N17*100/N29,"") | O30: =IFERROR(O17*100/O29,"") | P30: =IFERROR(P17*100/P29,"") | Q30: =IFERROR(Q17*100/Q29,"") | R30: =SUM(N30:Q30) | S30: =IFERROR(S17*100/S29,"") | T30: =IFERROR(T17*100/T29,"") | U30: =IFERROR(U17*100/U29,"") | V30: =IFERROR(V17*100/V29,"") | W30: =SUM(S30:V30) | X30: =IFERROR(X17*100/X29,"") | Y30: =IFERROR(Y17*100/Y29,"") | Z30: =IFERROR(Z17*100/Z29,"") | AA30: =IFERROR(AA17*100/AA29,"") | AB30: =SUM(X30:AA30) | AC30: =IFERROR(AC17*100/AC29,"") | AD30: =IFERROR(AD17*100/AD29,"") | AE30: =IFERROR(AE17*100/AE29,"") | AF30: =IFERROR(AF17*100/AF29,"") | AG30: =SUM(AC30:AF30) | AH30: =IFERROR(AH17*100/AH29,"") | AI30: =IFERROR(AI17*100/AI29,"") | AJ30: =IFERROR(AJ17*100/AJ29,"") | AK30: =IFERROR(AK17*100/AK29,"") | AL30: =SUM(AH30:AK30)
A31: BPS | B31: 주당 | C31: 원 | D31: BPS | E31: =IFERROR(E23*100/E29,"") | F31: =IFERROR(F23*100/F29,"") | G31: =IFERROR(G23*100/G29,"") | H31: =G31 | I31: =IFERROR(I23*100/I29,"") | J31: =IFERROR(J23*100/J29,"") | K31: =IFERROR(K23*100/K29,"") | L31: =IFERROR(L23*100/L29,"") | M31: =L31 | N31: =IFERROR(N23*100/N29,"") | O31: =IFERROR(O23*100/O29,"") | P31: =IFERROR(P23*100/P29,"") | Q31: =IFERROR(Q23*100/Q29,"") | R31: =Q31 | S31: =IFERROR(S23*100/S29,"") | T31: =IFERROR(T23*100/T29,"") | U31: =IFERROR(U23*100/U29,"") | V31: =IFERROR(V23*100/V29,"") | W31: =V31 | X31: =IFERROR(X23*100/X29,"") | Y31: =IFERROR(Y23*100/Y29,"") | Z31: =IFERROR(Z23*100/Z29,"") | AA31: =IFERROR(AA23*100/AA29,"") | AB31: =AA31 | AC31: =IFERROR(AC23*100/AC29,"") | AD31: =IFERROR(AD23*100/AD29,"") | AE31: =IFERROR(AE23*100/AE29,"") | AF31: =IFERROR(AF23*100/AF29,"") | AG31: =AF31 | AH31: =IFERROR(AH23*100/AH29,"") | AI31: =IFERROR(AI23*100/AI29,"") | AJ31: =IFERROR(AJ23*100/AJ29,"") | AK31: =IFERROR(AK23*100/AK29,"") | AL31: =AK31
A32: DPS | B32: 주당 | C32: 원 | D32: DPS(보통주) | G32: 0 | H32: 0 | L32: 0 | M32: =SUM(I32:L32) | Q32: 0 | R32: =SUM(N32:Q32) | V32: 0 | W32: =SUM(S32:V32) | AA32: =변수!AA37 | AB32: =SUM(X32:AA32) | AF32: =변수!AF37 | AG32: =SUM(AC32:AF32) | AK32: =변수!AK37 | AL32: =SUM(AH32:AK32)
A33: PER | B33: 주당 | C33: 배 | D33: PER | H33: =G33 | I33: =IFERROR(변수!I18/(E30+F30+G30+I30),"") | J33: =IFERROR(변수!J18/(F30+G30+I30+J30),"") | M33: =L33 | Q33: =IFERROR(변수!Q18/(N30+O30+P30+Q30),"") | R33: =Q33 | S33: =IFERROR(변수!S18/(O30+P30+Q30+S30),"") | T33: =IFERROR(변수!T18/(P30+Q30+S30+T30),"") | V33: =IFERROR(변수!V18/(S30+T30+U30+V30),"") | W33: =V33 | AB33: =AA33 | AG33: =AF33 | AL33: =AK33
A34: PBR | B34: 주당 | C34: 배 | D34: PBR | E34: =IFERROR(변수!E18/E31,"") | F34: =IFERROR(변수!F18/F31,"") | G34: =IFERROR(변수!G18/G31,"") | H34: =G34 | I34: =IFERROR(변수!I18/I31,"") | J34: =IFERROR(변수!J18/J31,"") | K34: =IFERROR(변수!K18/K31,"") | L34: =IFERROR(변수!L18/L31,"") | M34: =L34 | N34: =IFERROR(변수!N18/N31,"") | O34: =IFERROR(변수!O18/O31,"") | P34: =IFERROR(변수!P18/P31,"") | Q34: =IFERROR(변수!Q18/Q31,"") | R34: =Q34 | S34: =IFERROR(변수!S18/S31,"") | T34: =IFERROR(변수!T18/T31,"") | U34: =IFERROR(변수!U18/U31,"") | V34: =IFERROR(변수!V18/V31,"") | W34: =V34 | X34: =IFERROR(변수!X18/X31,"") | Y34: =IFERROR(변수!Y18/Y31,"") | Z34: =IFERROR(변수!$D$40/Z31,"") | AA34: =IFERROR(변수!$D$40/AA31,"") | AB34: =AA34 | AC34: =IFERROR(변수!$D$40/AC31,"") | AD34: =IFERROR(변수!$D$40/AD31,"") | AE34: =IFERROR(변수!$D$40/AE31,"") | AF34: =IFERROR(변수!$D$40/AF31,"") | AG34: =AF34 | AH34: =IFERROR(변수!$D$40/AH31,"") | AI34: =IFERROR(변수!$D$40/AI31,"") | AJ34: =IFERROR(변수!$D$40/AJ31,"") | AK34: =IFERROR(변수!$D$40/AK31,"") | AL34: =AK34
A35: 매출전사 | B35: 사업부 | C35: 억원 | D35: 매출 전사(부문 미분리) | E35: 146.18 | F35: 142.51 | G35: 133.16 | I35: 88.57 | J35: 102.47 | K35: 39.61 | L35: 74.5 | M35: =SUM(I35:L35) | N35: 67.2 | O35: 91.94 | P35: 110 | Q35: 92.81 | R35: =SUM(N35:Q35) | S35: 104.46 | T35: 70.61 | U35: 103.99 | V35: 154.55 | W35: =SUM(S35:V35) | X35: 50.54 | Y35: 178.25 | Z35: =IFERROR(Z5,"") | AA35: =IFERROR(AA5,"") | AB35: =SUM(X35:AA35) | AC35: =IFERROR(AC5,"") | AD35: =IFERROR(AD5,"") | AE35: =IFERROR(AE5,"") | AF35: =IFERROR(AF5,"") | AG35: =SUM(AC35:AF35) | AH35: =IFERROR(AH5,"") | AI35: =IFERROR(AI5,"") | AJ35: =IFERROR(AJ5,"") | AK35: =IFERROR(AK5,"") | AL35: =SUM(AH35:AK35)
A36: OP전사 | B36: 사업부 | C36: 억원 | D36: OP 전사(부문 미분리) | E36: 9.3 | F36: 10.18 | G36: -17.91 | I36: 1 | J36: -13.86 | K36: -19.08 | L36: -20.46 | M36: =SUM(I36:L36) | N36: -6.35 | O36: 16.5 | P36: 13.38 | Q36: 0.58 | R36: =SUM(N36:Q36) | S36: 6.8 | T36: 1.56 | U36: 8.42 | V36: -8.21 | W36: =SUM(S36:V36) | X36: -21.45 | Y36: -32.33 | Z36: =IFERROR(Z9,"") | AA36: =IFERROR(AA9,"") | AB36: =SUM(X36:AA36) | AC36: =IFERROR(AC9,"") | AD36: =IFERROR(AD9,"") | AE36: =IFERROR(AE9,"") | AF36: =IFERROR(AF9,"") | AG36: =SUM(AC36:AF36) | AH36: =IFERROR(AH9,"") | AI36: =IFERROR(AI9,"") | AJ36: =IFERROR(AJ9,"") | AK36: =IFERROR(AK9,"") | AL36: =SUM(AH36:AK36)
B37: 비율(참고)
A38: NPM | C38: % | D38: 지배주주순이익 / 매출액 | E38: =IFERROR(E17/E5,"") | F38: =IFERROR(F17/F5,"") | G38: =IFERROR(G17/G5,"") | H38: =IFERROR(H17/H5,"") | I38: =IFERROR(I17/I5,"") | J38: =IFERROR(J17/J5,"") | K38: =IFERROR(K17/K5,"") | L38: =IFERROR(L17/L5,"") | ... AL38: =IFERROR(AL17/AL5,"")
A39: 매출원가율 | C39: % | D39: 매출원가 / 매출액 | E39: =IFERROR(E6/E5,"") | F39: =IFERROR(F6/F5,"") | G39: =IFERROR(G6/G5,"") | H39: =IFERROR(H6/H5,"") | I39: =IFERROR(I6/I5,"") | J39: =IFERROR(J6/J5,"") | K39: =IFERROR(K6/K5,"") | L39: =IFERROR(L6/L5,"") | ... AL39: =IFERROR(AL6/AL5,"")
A40: 판관비율 | C40: % | D40: 판관비 / 매출액 | E40: =IFERROR(E8/E5,"") | F40: =IFERROR(F8/F5,"") | G40: =IFERROR(G8/G5,"") | H40: =IFERROR(H8/H5,"") | I40: =IFERROR(I8/I5,"") | J40: =IFERROR(J8/J5,"") | K40: =IFERROR(K8/K5,"") | L40: =IFERROR(L8/L5,"") | ... AL40: =IFERROR(AL8/AL5,"")

Sheet 분기
C1: 이름: 분기H — subQ 를 이름으로 VLOOKUP(억원) | E1: 2Q22 | F1: 3Q22 | G1: 4Q22 | H1: 1Q23 | I1: 2Q23 | J1: 3Q23 | K1: 4Q23 | L1: 1Q24 | M1: 2Q24 | N1: 3Q24 | O1: 4Q24 | P1: 1Q25 | Q1: 2Q25 | R1: 3Q25 | S1: 4Q25 | T1: 1Q26 | U1: 2Q26 | V1: 3Q26 | W1: 4Q26 | X1: 1Q27 | Y1: 2Q27 | Z1: 3Q27 | AA1: 4Q27 | AB1: 1Q28 | AC1: 2Q28 | AD1: 3Q28 | AE1: 4Q28
C2: 종가: | D2: =변수!D40
C3: 기준일: | D3: 20261008 | E3: 1 | F3: 2 | G3: 3 | H3: 4 | I3: 5 | J3: 6 | K3: 7 | L3: 8 | M3: 9 | N3: 10 | O3: 11 | P3: 12 | Q3: 13 | R3: 14 | S3: 15 | T3: 16 | U3: 17 | V3: 18 | W3: 19 | X3: 20 | Y3: 21 | Z3: 22 | AA3: 23 | AB3: 24 | AC3: 25 | AD3: 26 | AE3: 27
E4: 2022.06 | F4: 2022.09 | G4: 2022.12 | H4: 2023.03 | I4: 2023.06 | J4: 2023.09 | K4: 2023.12 | L4: 2024.03 | M4: 2024.06 | N4: 2024.09 | O4: 2024.12 | P4: 2025.03 | Q4: 2025.06 | R4: 2025.09 | S4: 2025.12 | T4: 2026.03 | U4: 2026.06 | V4: 2026.09 | W4: 2026.12 | X4: 2027.03 | Y4: 2027.06 | Z4: 2027.09 | AA4: 2027.12 | AB4: 2028.03 | AC4: 2028.06 | AD4: 2028.09 | AE4: 2028.12
A5: 매출액 | D5: 매출액 | E5: =IFERROR(VLOOKUP($A5,subQ,MATCH(E$1,SUBQH,0),0),"") | F5: =IFERROR(VLOOKUP($A5,subQ,MATCH(F$1,SUBQH,0),0),"") | G5: =IFERROR(VLOOKUP($A5,subQ,MATCH(G$1,SUBQH,0),0),"") | H5: =IFERROR(VLOOKUP($A5,subQ,MATCH(H$1,SUBQH,0),0),"") | I5: =IFERROR(VLOOKUP($A5,subQ,MATCH(I$1,SUBQH,0),0),"") | J5: =IFERROR(VLOOKUP($A5,subQ,MATCH(J$1,SUBQH,0),0),"") | K5: =IFERROR(VLOOKUP($A5,subQ,MATCH(K$1,SUBQH,0),0),"") | L5: =IFERROR(VLOOKUP($A5,subQ,MATCH(L$1,SUBQH,0),0),"") | ... AE5: =IFERROR(VLOOKUP($A5,subQ,MATCH(AE$1,SUBQH,0),0),"")
A6: 매출원가 | D6: 매출원가 | E6: =IFERROR(VLOOKUP($A6,subQ,MATCH(E$1,SUBQH,0),0),"") | F6: =IFERROR(VLOOKUP($A6,subQ,MATCH(F$1,SUBQH,0),0),"") | G6: =IFERROR(VLOOKUP($A6,subQ,MATCH(G$1,SUBQH,0),0),"") | H6: =IFERROR(VLOOKUP($A6,subQ,MATCH(H$1,SUBQH,0),0),"") | I6: =IFERROR(VLOOKUP($A6,subQ,MATCH(I$1,SUBQH,0),0),"") | J6: =IFERROR(VLOOKUP($A6,subQ,MATCH(J$1,SUBQH,0),0),"") | K6: =IFERROR(VLOOKUP($A6,subQ,MATCH(K$1,SUBQH,0),0),"") | L6: =IFERROR(VLOOKUP($A6,subQ,MATCH(L$1,SUBQH,0),0),"") | ... AE6: =IFERROR(VLOOKUP($A6,subQ,MATCH(AE$1,SUBQH,0),0),"")
A7: 매출총이익 | D7: 매출총이익 | E7: =IFERROR(VLOOKUP($A7,subQ,MATCH(E$1,SUBQH,0),0),"") | F7: =IFERROR(VLOOKUP($A7,subQ,MATCH(F$1,SUBQH,0),0),"") | G7: =IFERROR(VLOOKUP($A7,subQ,MATCH(G$1,SUBQH,0),0),"") | H7: =IFERROR(VLOOKUP($A7,subQ,MATCH(H$1,SUBQH,0),0),"") | I7: =IFERROR(VLOOKUP($A7,subQ,MATCH(I$1,SUBQH,0),0),"") | J7: =IFERROR(VLOOKUP($A7,subQ,MATCH(J$1,SUBQH,0),0),"") | K7: =IFERROR(VLOOKUP($A7,subQ,MATCH(K$1,SUBQH,0),0),"") | L7: =IFERROR(VLOOKUP($A7,subQ,MATCH(L$1,SUBQH,0),0),"") | ... AE7: =IFERROR(VLOOKUP($A7,subQ,MATCH(AE$1,SUBQH,0),0),"")
A8: 판관비 | D8: 판매비와관리비 | E8: =IFERROR(VLOOKUP($A8,subQ,MATCH(E$1,SUBQH,0),0),"") | F8: =IFERROR(VLOOKUP($A8,subQ,MATCH(F$1,SUBQH,0),0),"") | G8: =IFERROR(VLOOKUP($A8,subQ,MATCH(G$1,SUBQH,0),0),"") | H8: =IFERROR(VLOOKUP($A8,subQ,MATCH(H$1,SUBQH,0),0),"") | I8: =IFERROR(VLOOKUP($A8,subQ,MATCH(I$1,SUBQH,0),0),"") | J8: =IFERROR(VLOOKUP($A8,subQ,MATCH(J$1,SUBQH,0),0),"") | K8: =IFERROR(VLOOKUP($A8,subQ,MATCH(K$1,SUBQH,0),0),"") | L8: =IFERROR(VLOOKUP($A8,subQ,MATCH(L$1,SUBQH,0),0),"") | ... AE8: =IFERROR(VLOOKUP($A8,subQ,MATCH(AE$1,SUBQH,0),0),"")
A9: 영업이익 | D9: 영업이익 | E9: =IFERROR(VLOOKUP($A9,subQ,MATCH(E$1,SUBQH,0),0),"") | F9: =IFERROR(VLOOKUP($A9,subQ,MATCH(F$1,SUBQH,0),0),"") | G9: =IFERROR(VLOOKUP($A9,subQ,MATCH(G$1,SUBQH,0),0),"") | H9: =IFERROR(VLOOKUP($A9,subQ,MATCH(H$1,SUBQH,0),0),"") | I9: =IFERROR(VLOOKUP($A9,subQ,MATCH(I$1,SUBQH,0),0),"") | J9: =IFERROR(VLOOKUP($A9,subQ,MATCH(J$1,SUBQH,0),0),"") | K9: =IFERROR(VLOOKUP($A9,subQ,MATCH(K$1,SUBQH,0),0),"") | L9: =IFERROR(VLOOKUP($A9,subQ,MATCH(L$1,SUBQH,0),0),"") | ... AE9: =IFERROR(VLOOKUP($A9,subQ,MATCH(AE$1,SUBQH,0),0),"")
A10: OPM | D10: 영업이익률 | E10: =IFERROR(VLOOKUP($A10,subQ,MATCH(E$1,SUBQH,0),0),"") | F10: =IFERROR(VLOOKUP($A10,subQ,MATCH(F$1,SUBQH,0),0),"") | G10: =IFERROR(VLOOKUP($A10,subQ,MATCH(G$1,SUBQH,0),0),"") | H10: =IFERROR(VLOOKUP($A10,subQ,MATCH(H$1,SUBQH,0),0),"") | I10: =IFERROR(VLOOKUP($A10,subQ,MATCH(I$1,SUBQH,0),0),"") | J10: =IFERROR(VLOOKUP($A10,subQ,MATCH(J$1,SUBQH,0),0),"") | K10: =IFERROR(VLOOKUP($A10,subQ,MATCH(K$1,SUBQH,0),0),"") | L10: =IFERROR(VLOOKUP($A10,subQ,MATCH(L$1,SUBQH,0),0),"") | ... AE10: =IFERROR(VLOOKUP($A10,subQ,MATCH(AE$1,SUBQH,0),0),"")
A11: 금융손익 | D11: 금융손익(이자·환 포함) | E11: =IFERROR(VLOOKUP($A11,subQ,MATCH(E$1,SUBQH,0),0),"") | F11: =IFERROR(VLOOKUP($A11,subQ,MATCH(F$1,SUBQH,0),0),"") | G11: =IFERROR(VLOOKUP($A11,subQ,MATCH(G$1,SUBQH,0),0),"") | H11: =IFERROR(VLOOKUP($A11,subQ,MATCH(H$1,SUBQH,0),0),"") | I11: =IFERROR(VLOOKUP($A11,subQ,MATCH(I$1,SUBQH,0),0),"") | J11: =IFERROR(VLOOKUP($A11,subQ,MATCH(J$1,SUBQH,0),0),"") | K11: =IFERROR(VLOOKUP($A11,subQ,MATCH(K$1,SUBQH,0),0),"") | L11: =IFERROR(VLOOKUP($A11,subQ,MATCH(L$1,SUBQH,0),0),"") | ... AE11: =IFERROR(VLOOKUP($A11,subQ,MATCH(AE$1,SUBQH,0),0),"")
A12: 이자손익 | D12: 이자손익(이자수익 − 이자비용) | E12: =IFERROR(VLOOKUP($A12,subQ,MATCH(E$1,SUBQH,0),0),"") | F12: =IFERROR(VLOOKUP($A12,subQ,MATCH(F$1,SUBQH,0),0),"") | G12: =IFERROR(VLOOKUP($A12,subQ,MATCH(G$1,SUBQH,0),0),"") | H12: =IFERROR(VLOOKUP($A12,subQ,MATCH(H$1,SUBQH,0),0),"") | I12: =IFERROR(VLOOKUP($A12,subQ,MATCH(I$1,SUBQH,0),0),"") | J12: =IFERROR(VLOOKUP($A12,subQ,MATCH(J$1,SUBQH,0),0),"") | K12: =IFERROR(VLOOKUP($A12,subQ,MATCH(K$1,SUBQH,0),0),"") | L12: =IFERROR(VLOOKUP($A12,subQ,MATCH(L$1,SUBQH,0),0),"") | ... AE12: =IFERROR(VLOOKUP($A12,subQ,MATCH(AE$1,SUBQH,0),0),"")
A13: 기타영업외손익 | D13: 기타영업외손익 | E13: =IFERROR(VLOOKUP($A13,subQ,MATCH(E$1,SUBQH,0),0),"") | F13: =IFERROR(VLOOKUP($A13,subQ,MATCH(F$1,SUBQH,0),0),"") | G13: =IFERROR(VLOOKUP($A13,subQ,MATCH(G$1,SUBQH,0),0),"") | H13: =IFERROR(VLOOKUP($A13,subQ,MATCH(H$1,SUBQH,0),0),"") | I13: =IFERROR(VLOOKUP($A13,subQ,MATCH(I$1,SUBQH,0),0),"") | J13: =IFERROR(VLOOKUP($A13,subQ,MATCH(J$1,SUBQH,0),0),"") | K13: =IFERROR(VLOOKUP($A13,subQ,MATCH(K$1,SUBQH,0),0),"") | L13: =IFERROR(VLOOKUP($A13,subQ,MATCH(L$1,SUBQH,0),0),"") | ... AE13: =IFERROR(VLOOKUP($A13,subQ,MATCH(AE$1,SUBQH,0),0),"")
A14: 세전이익 | D14: 법인세비용차감전이익 | E14: =IFERROR(VLOOKUP($A14,subQ,MATCH(E$1,SUBQH,0),0),"") | F14: =IFERROR(VLOOKUP($A14,subQ,MATCH(F$1,SUBQH,0),0),"") | G14: =IFERROR(VLOOKUP($A14,subQ,MATCH(G$1,SUBQH,0),0),"") | H14: =IFERROR(VLOOKUP($A14,subQ,MATCH(H$1,SUBQH,0),0),"") | I14: =IFERROR(VLOOKUP($A14,subQ,MATCH(I$1,SUBQH,0),0),"") | J14: =IFERROR(VLOOKUP($A14,subQ,MATCH(J$1,SUBQH,0),0),"") | K14: =IFERROR(VLOOKUP($A14,subQ,MATCH(K$1,SUBQH,0),0),"") | L14: =IFERROR(VLOOKUP($A14,subQ,MATCH(L$1,SUBQH,0),0),"") | ... AE14: =IFERROR(VLOOKUP($A14,subQ,MATCH(AE$1,SUBQH,0),0),"")
A15: 법인세비용 | D15: 법인세비용 | E15: =IFERROR(VLOOKUP($A15,subQ,MATCH(E$1,SUBQH,0),0),"") | F15: =IFERROR(VLOOKUP($A15,subQ,MATCH(F$1,SUBQH,0),0),"") | G15: =IFERROR(VLOOKUP($A15,subQ,MATCH(G$1,SUBQH,0),0),"") | H15: =IFERROR(VLOOKUP($A15,subQ,MATCH(H$1,SUBQH,0),0),"") | I15: =IFERROR(VLOOKUP($A15,subQ,MATCH(I$1,SUBQH,0),0),"") | J15: =IFERROR(VLOOKUP($A15,subQ,MATCH(J$1,SUBQH,0),0),"") | K15: =IFERROR(VLOOKUP($A15,subQ,MATCH(K$1,SUBQH,0),0),"") | L15: =IFERROR(VLOOKUP($A15,subQ,MATCH(L$1,SUBQH,0),0),"") | ... AE15: =IFERROR(VLOOKUP($A15,subQ,MATCH(AE$1,SUBQH,0),0),"")
A16: 당기순이익 | D16: 당기순이익 | E16: =IFERROR(VLOOKUP($A16,subQ,MATCH(E$1,SUBQH,0),0),"") | F16: =IFERROR(VLOOKUP($A16,subQ,MATCH(F$1,SUBQH,0),0),"") | G16: =IFERROR(VLOOKUP($A16,subQ,MATCH(G$1,SUBQH,0),0),"") | H16: =IFERROR(VLOOKUP($A16,subQ,MATCH(H$1,SUBQH,0),0),"") | I16: =IFERROR(VLOOKUP($A16,subQ,MATCH(I$1,SUBQH,0),0),"") | J16: =IFERROR(VLOOKUP($A16,subQ,MATCH(J$1,SUBQH,0),0),"") | K16: =IFERROR(VLOOKUP($A16,subQ,MATCH(K$1,SUBQH,0),0),"") | L16: =IFERROR(VLOOKUP($A16,subQ,MATCH(L$1,SUBQH,0),0),"") | ... AE16: =IFERROR(VLOOKUP($A16,subQ,MATCH(AE$1,SUBQH,0),0),"")
... A37: NPM | D37: NPM | E37: =IFERROR(VLOOKUP($A37,subQ,MATCH(E$1,SUBQH,0),0),"") | F37: =IFERROR(VLOOKUP($A37,subQ,MATCH(F$1,SUBQH,0),0),"") | G37: =IFERROR(VLOOKUP($A37,subQ,MATCH(G$1,SUBQH,0),0),"") | H37: =IFERROR(VLOOKUP($A37,subQ,MATCH(H$1,SUBQH,0),0),"") | I37: =IFERROR(VLOOKUP($A37,subQ,MATCH(I$1,SUBQH,0),0),"") | J37: =IFERROR(VLOOKUP($A37,subQ,MATCH(J$1,SUBQH,0),0),"") | K37: =IFERROR(VLOOKUP($A37,subQ,MATCH(K$1,SUBQH,0),0),"") | L37: =IFERROR(VLOOKUP($A37,subQ,MATCH(L$1,SUBQH,0),0),"") | ... AE37: =IFERROR(VLOOKUP($A37,subQ,MATCH(AE$1,SUBQH,0),0),"")
A38: 매출액 YoY | D38: 매출액 YoY | I38: =IFERROR(I5/E5-1,"") | J38: =IFERROR(J5/F5-1,"") | K38: =IFERROR(K5/G5-1,"") | L38: =IFERROR(L5/H5-1,"") | M38: =IFERROR(M5/I5-1,"") | N38: =IFERROR(N5/J5-1,"") | O38: =IFERROR(O5/K5-1,"") | P38: =IFERROR(P5/L5-1,"") | ... AE38: =IFERROR(AE5/AA5-1,"")
A39: 영업이익 YoY | D39: 영업이익 YoY | I39: =IFERROR(I9/E9-1,"") | J39: =IFERROR(J9/F9-1,"") | K39: =IFERROR(K9/G9-1,"") | L39: =IFERROR(L9/H9-1,"") | M39: =IFERROR(M9/I9-1,"") | N39: =IFERROR(N9/J9-1,"") | O39: =IFERROR(O9/K9-1,"") | P39: =IFERROR(P9/L9-1,"") | ... AE39: =IFERROR(AE9/AA9-1,"")
A40: 지배주주순이익 YoY | D40: 지배주주순이익 YoY | I40: =IFERROR(I17/E17-1,"") | J40: =IFERROR(J17/F17-1,"") | K40: =IFERROR(K17/G17-1,"") | L40: =IFERROR(L17/H17-1,"") | M40: =IFERROR(M17/I17-1,"") | N40: =IFERROR(N17/J17-1,"") | O40: =IFERROR(O17/K17-1,"") | P40: =IFERROR(P17/L17-1,"") | ... AE40: =IFERROR(AE17/AA17-1,"")

Sheet 연간예상
C1: 이름: 연간예상H — subQ 를 이름으로 VLOOKUP(억원) | E1: 2022 | F1: 2023 | G1: 2024 | H1: 2025 | I1: 2026 | J1: 2027 | K1: 2028
C2: 종가: | D2: =변수!D40
C3: 기준일: | D3: 20261008 | E3: 1 | F3: 2 | G3: 3 | H3: 4 | I3: 5 | J3: 6 | K3: 7
E4: 2022.12A | F4: 2023.12A | G4: 2024.12A | H4: 2025.12A | I4: 2026.12A | J4: 2027.12A | K4: 2028.12A
A5: 매출액 | D5: 매출액 | E5: =IFERROR(VLOOKUP($A5,subQ,MATCH(E$1,SUBQH,0),0),"") | F5: =IFERROR(VLOOKUP($A5,subQ,MATCH(F$1,SUBQH,0),0),"") | G5: =IFERROR(VLOOKUP($A5,subQ,MATCH(G$1,SUBQH,0),0),"") | H5: =IFERROR(VLOOKUP($A5,subQ,MATCH(H$1,SUBQH,0),0),"") | I5: =IFERROR(VLOOKUP($A5,subQ,MATCH(I$1,SUBQH,0),0),"") | J5: =IFERROR(VLOOKUP($A5,subQ,MATCH(J$1,SUBQH,0),0),"") | K5: =IFERROR(VLOOKUP($A5,subQ,MATCH(K$1,SUBQH,0),0),"")
A6: 매출원가 | D6: 매출원가 | E6: =IFERROR(VLOOKUP($A6,subQ,MATCH(E$1,SUBQH,0),0),"") | F6: =IFERROR(VLOOKUP($A6,subQ,MATCH(F$1,SUBQH,0),0),"") | G6: =IFERROR(VLOOKUP($A6,subQ,MATCH(G$1,SUBQH,0),0),"") | H6: =IFERROR(VLOOKUP($A6,subQ,MATCH(H$1,SUBQH,0),0),"") | I6: =IFERROR(VLOOKUP($A6,subQ,MATCH(I$1,SUBQH,0),0),"") | J6: =IFERROR(VLOOKUP($A6,subQ,MATCH(J$1,SUBQH,0),0),"") | K6: =IFERROR(VLOOKUP($A6,subQ,MATCH(K$1,SUBQH,0),0),"")
A7: 매출총이익 | D7: 매출총이익 | E7: =IFERROR(VLOOKUP($A7,subQ,MATCH(E$1,SUBQH,0),0),"") | F7: =IFERROR(VLOOKUP($A7,subQ,MATCH(F$1,SUBQH,0),0),"") | G7: =IFERROR(VLOOKUP($A7,subQ,MATCH(G$1,SUBQH,0),0),"") | H7: =IFERROR(VLOOKUP($A7,subQ,MATCH(H$1,SUBQH,0),0),"") | I7: =IFERROR(VLOOKUP($A7,subQ,MATCH(I$1,SUBQH,0),0),"") | J7: =IFERROR(VLOOKUP($A7,subQ,MATCH(J$1,SUBQH,0),0),"") | K7: =IFERROR(VLOOKUP($A7,subQ,MATCH(K$1,SUBQH,0),0),"")
A8: 판관비 | D8: 판매비와관리비 | E8: =IFERROR(VLOOKUP($A8,subQ,MATCH(E$1,SUBQH,0),0),"") | F8: =IFERROR(VLOOKUP($A8,subQ,MATCH(F$1,SUBQH,0),0),"") | G8: =IFERROR(VLOOKUP($A8,subQ,MATCH(G$1,SUBQH,0),0),"") | H8: =IFERROR(VLOOKUP($A8,subQ,MATCH(H$1,SUBQH,0),0),"") | I8: =IFERROR(VLOOKUP($A8,subQ,MATCH(I$1,SUBQH,0),0),"") | J8: =IFERROR(VLOOKUP($A8,subQ,MATCH(J$1,SUBQH,0),0),"") | K8: =IFERROR(VLOOKUP($A8,subQ,MATCH(K$1,SUBQH,0),0),"")
A9: 영업이익 | D9: 영업이익 | E9: =IFERROR(VLOOKUP($A9,subQ,MATCH(E$1,SUBQH,0),0),"") | F9: =IFERROR(VLOOKUP($A9,subQ,MATCH(F$1,SUBQH,0),0),"") | G9: =IFERROR(VLOOKUP($A9,subQ,MATCH(G$1,SUBQH,0),0),"") | H9: =IFERROR(VLOOKUP($A9,subQ,MATCH(H$1,SUBQH,0),0),"") | I9: =IFERROR(VLOOKUP($A9,subQ,MATCH(I$1,SUBQH,0),0),"") | J9: =IFERROR(VLOOKUP($A9,subQ,MATCH(J$1,SUBQH,0),0),"") | K9: =IFERROR(VLOOKUP($A9,subQ,MATCH(K$1,SUBQH,0),0),"")
A10: OPM | D10: 영업이익률 | E10: =IFERROR(VLOOKUP($A10,subQ,MATCH(E$1,SUBQH,0),0),"") | F10: =IFERROR(VLOOKUP($A10,subQ,MATCH(F$1,SUBQH,0),0),"") | G10: =IFERROR(VLOOKUP($A10,subQ,MATCH(G$1,SUBQH,0),0),"") | H10: =IFERROR(VLOOKUP($A10,subQ,MATCH(H$1,SUBQH,0),0),"") | I10: =IFERROR(VLOOKUP($A10,subQ,MATCH(I$1,SUBQH,0),0),"") | J10: =IFERROR(VLOOKUP($A10,subQ,MATCH(J$1,SUBQH,0),0),"") | K10: =IFERROR(VLOOKUP($A10,subQ,MATCH(K$1,SUBQH,0),0),"")
A11: 금융손익 | D11: 금융손익(이자·환 포함) | E11: =IFERROR(VLOOKUP($A11,subQ,MATCH(E$1,SUBQH,0),0),"") | F11: =IFERROR(VLOOKUP($A11,subQ,MATCH(F$1,SUBQH,0),0),"") | G11: =IFERROR(VLOOKUP($A11,subQ,MATCH(G$1,SUBQH,0),0),"") | H11: =IFERROR(VLOOKUP($A11,subQ,MATCH(H$1,SUBQH,0),0),"") | I11: =IFERROR(VLOOKUP($A11,subQ,MATCH(I$1,SUBQH,0),0),"") | J11: =IFERROR(VLOOKUP($A11,subQ,MATCH(J$1,SUBQH,0),0),"") | K11: =IFERROR(VLOOKUP($A11,subQ,MATCH(K$1,SUBQH,0),0),"")
A12: 이자손익 | D12: 이자손익(이자수익 − 이자비용) | E12: =IFERROR(VLOOKUP($A12,subQ,MATCH(E$1,SUBQH,0),0),"") | F12: =IFERROR(VLOOKUP($A12,subQ,MATCH(F$1,SUBQH,0),0),"") | G12: =IFERROR(VLOOKUP($A12,subQ,MATCH(G$1,SUBQH,0),0),"") | H12: =IFERROR(VLOOKUP($A12,subQ,MATCH(H$1,SUBQH,0),0),"") | I12: =IFERROR(VLOOKUP($A12,subQ,MATCH(I$1,SUBQH,0),0),"") | J12: =IFERROR(VLOOKUP($A12,subQ,MATCH(J$1,SUBQH,0),0),"") | K12: =IFERROR(VLOOKUP($A12,subQ,MATCH(K$1,SUBQH,0),0),"")
A13: 기타영업외손익 | D13: 기타영업외손익 | E13: =IFERROR(VLOOKUP($A13,subQ,MATCH(E$1,SUBQH,0),0),"") | F13: =IFERROR(VLOOKUP($A13,subQ,MATCH(F$1,SUBQH,0),0),"") | G13: =IFERROR(VLOOKUP($A13,subQ,MATCH(G$1,SUBQH,0),0),"") | H13: =IFERROR(VLOOKUP($A13,subQ,MATCH(H$1,SUBQH,0),0),"") | I13: =IFERROR(VLOOKUP($A13,subQ,MATCH(I$1,SUBQH,0),0),"") | J13: =IFERROR(VLOOKUP($A13,subQ,MATCH(J$1,SUBQH,0),0),"") | K13: =IFERROR(VLOOKUP($A13,subQ,MATCH(K$1,SUBQH,0),0),"")
A14: 세전이익 | D14: 법인세비용차감전이익 | E14: =IFERROR(VLOOKUP($A14,subQ,MATCH(E$1,SUBQH,0),0),"") | F14: =IFERROR(VLOOKUP($A14,subQ,MATCH(F$1,SUBQH,0),0),"") | G14: =IFERROR(VLOOKUP($A14,subQ,MATCH(G$1,SUBQH,0),0),"") | H14: =IFERROR(VLOOKUP($A14,subQ,MATCH(H$1,SUBQH,0),0),"") | I14: =IFERROR(VLOOKUP($A14,subQ,MATCH(I$1,SUBQH,0),0),"") | J14: =IFERROR(VLOOKUP($A14,subQ,MATCH(J$1,SUBQH,0),0),"") | K14: =IFERROR(VLOOKUP($A14,subQ,MATCH(K$1,SUBQH,0),0),"")
A15: 법인세비용 | D15: 법인세비용 | E15: =IFERROR(VLOOKUP($A15,subQ,MATCH(E$1,SUBQH,0),0),"") | F15: =IFERROR(VLOOKUP($A15,subQ,MATCH(F$1,SUBQH,0),0),"") | G15: =IFERROR(VLOOKUP($A15,subQ,MATCH(G$1,SUBQH,0),0),"") | H15: =IFERROR(VLOOKUP($A15,subQ,MATCH(H$1,SUBQH,0),0),"") | I15: =IFERROR(VLOOKUP($A15,subQ,MATCH(I$1,SUBQH,0),0),"") | J15: =IFERROR(VLOOKUP($A15,subQ,MATCH(J$1,SUBQH,0),0),"") | K15: =IFERROR(VLOOKUP($A15,subQ,MATCH(K$1,SUBQH,0),0),"")
A16: 당기순이익 | D16: 당기순이익 | E16: =IFERROR(VLOOKUP($A16,subQ,MATCH(E$1,SUBQH,0),0),"") | F16: =IFERROR(VLOOKUP($A16,subQ,MATCH(F$1,SUBQH,0),0),"") | G16: =IFERROR(VLOOKUP($A16,subQ,MATCH(G$1,SUBQH,0),0),"") | H16: =IFERROR(VLOOKUP($A16,subQ,MATCH(H$1,SUBQH,0),0),"") | I16: =IFERROR(VLOOKUP($A16,subQ,MATCH(I$1,SUBQH,0),0),"") | J16: =IFERROR(VLOOKUP($A16,subQ,MATCH(J$1,SUBQH,0),0),"") | K16: =IFERROR(VLOOKUP($A16,subQ,MATCH(K$1,SUBQH,0),0),"")
... A37: NPM | D37: NPM | E37: =IFERROR(VLOOKUP($A37,subQ,MATCH(E$1,SUBQH,0),0),"") | F37: =IFERROR(VLOOKUP($A37,subQ,MATCH(F$1,SUBQH,0),0),"") | G37: =IFERROR(VLOOKUP($A37,subQ,MATCH(G$1,SUBQH,0),0),"") | H37: =IFERROR(VLOOKUP($A37,subQ,MATCH(H$1,SUBQH,0),0),"") | I37: =IFERROR(VLOOKUP($A37,subQ,MATCH(I$1,SUBQH,0),0),"") | J37: =IFERROR(VLOOKUP($A37,subQ,MATCH(J$1,SUBQH,0),0),"") | K37: =IFERROR(VLOOKUP($A37,subQ,MATCH(K$1,SUBQH,0),0),"")
A38: 매출액 YoY | D38: 매출액 YoY | F38: =IFERROR(F5/E5-1,"") | G38: =IFERROR(G5/F5-1,"") | H38: =IFERROR(H5/G5-1,"") | I38: =IFERROR(I5/H5-1,"") | J38: =IFERROR(J5/I5-1,"") | K38: =IFERROR(K5/J5-1,"")
A39: 영업이익 YoY | D39: 영업이익 YoY | F39: =IFERROR(F9/E9-1,"") | G39: =IFERROR(G9/F9-1,"") | H39: =IFERROR(H9/G9-1,"") | I39: =IFERROR(I9/H9-1,"") | J39: =IFERROR(J9/I9-1,"") | K39: =IFERROR(K9/J9-1,"")
A40: 지배주주순이익 YoY | D40: 지배주주순이익 YoY | F40: =IFERROR(F17/E17-1,"") | G40: =IFERROR(G17/F17-1,"") | H40: =IFERROR(H17/G17-1,"") | I40: =IFERROR(I17/H17-1,"") | J40: =IFERROR(J17/I17-1,"") | K40: =IFERROR(K17/J17-1,"")

Sheet TP
B1: 종가 | C1: =변수!D40
B2: 기준일 | C2: =변수!D41
B3: 모델 산출값 — 목표주가·추천 아님. 밴드·COE 는 변수 시트 3절의 가정
C5: FY | D5: 2025 | E5: 2026 | F5: 2027 | G5: 2028
D6: A | E6: E | F6: E | G6: E
C7: EPS(원) | D7: =IFERROR(VLOOKUP("EPS",subQ,MATCH(D$5,SUBQH,0),0),"") | E7: =IFERROR(VLOOKUP("EPS",subQ,MATCH(E$5,SUBQH,0),0),"") | F7: =IFERROR(VLOOKUP("EPS",subQ,MATCH(F$5,SUBQH,0),0),"") | G7: =IFERROR(VLOOKUP("EPS",subQ,MATCH(G$5,SUBQH,0),0),"")
C8: BPS(원) | D8: =IFERROR(VLOOKUP("BPS",subQ,MATCH(D$5,SUBQH,0),0),"") | E8: =IFERROR(VLOOKUP("BPS",subQ,MATCH(E$5,SUBQH,0),0),"") | F8: =IFERROR(VLOOKUP("BPS",subQ,MATCH(F$5,SUBQH,0),0),"") | G8: =IFERROR(VLOOKUP("BPS",subQ,MATCH(G$5,SUBQH,0),0),"")
C9: 지배주주순이익(억원) | D9: =IFERROR(VLOOKUP("지배주주순이익",subQ,MATCH(D$5,SUBQH,0),0),"") | E9: =IFERROR(VLOOKUP("지배주주순이익",subQ,MATCH(E$5,SUBQH,0),0),"") | F9: =IFERROR(VLOOKUP("지배주주순이익",subQ,MATCH(F$5,SUBQH,0),0),"") | G9: =IFERROR(VLOOKUP("지배주주순이익",subQ,MATCH(G$5,SUBQH,0),0),"")
C10: 영업이익(억원) | D10: =IFERROR(VLOOKUP("영업이익",subQ,MATCH(D$5,SUBQH,0),0),"") | E10: =IFERROR(VLOOKUP("영업이익",subQ,MATCH(E$5,SUBQH,0),0),"") | F10: =IFERROR(VLOOKUP("영업이익",subQ,MATCH(F$5,SUBQH,0),0),"") | G10: =IFERROR(VLOOKUP("영업이익",subQ,MATCH(G$5,SUBQH,0),0),"")
C11: ROE(EPS/기초BPS) | E11: =IFERROR(E7/D8,"") | F11: =IFERROR(F7/E8,"") | G11: =IFERROR(G7/F8,"")
B13: PER
C14: 12M fwd EPS | D14: =IFERROR(E7*변수!D46+F7*(1-변수!D46),"")
C15: 적정가치 @PER_lo | D15: =변수!D43 | E15: =IFERROR(ROUND($D$14*D15,-2),"") | F15: =IFERROR(E15/$C$1-1,"") | G15: 배 · 원 · 종가 대비
C16: 적정가치 @PER_mid | D16: =변수!D44 | E16: =IFERROR(ROUND($D$14*D16,-2),"") | F16: =IFERROR(E16/$C$1-1,"") | G16: 배 · 원 · 종가 대비
C17: 적정가치 @PER_hi | D17: =변수!D45 | E17: =IFERROR(ROUND($D$14*D17,-2),"") | F17: =IFERROR(E17/$C$1-1,"") | G17: 배 · 원 · 종가 대비
C18: 현재 PER(종가/12M fwd EPS) | D18: =IFERROR($C$1/$D$14,"")
B20: PBR
C21: 최근 BPS(마지막 실적 분기) | D21: =IFERROR(VLOOKUP("BPS",subQ,MATCH("2Q26",SUBQH,0),0),"")
C22: ROE fwd(12M fwd EPS / BPS) | D22: =IFERROR($D$14/$D$21,"")
C23: COE | D23: =변수!D42
C24: 적정 PBR = ROE/COE | D24: =IFERROR(D22/D23,"")
C25: 적정가치(PBR) = BPS × 적정PBR | D25: =IFERROR(ROUND(D21*D24,-2),"") | E25: =IFERROR(D25/$C$1-1,"")
C26: 현재 PBR(종가/BPS) | D26: =IFERROR($C$1/D21,"")
B28: 모델 json valuation(참고)
C29: eps_fwd12m | D29: -295.7
C30: bps_latest | D30: 18161.7
C31: per_now
C32: pbr_now | D32: 1.34
C33: roe_fwd | D33: -0.0163
C34: fair_pbr
C35: fair_value_pbr
C36: ev_ebitda | D36: 105.05
C37: note | D37: 모델 산출값 — 목표주가·추천 아님

Sheet 외화
C1: 이름: 외화QH — 환율 QoQ · 외화 순노출 × Δ기말환율 | E1: 2Q22 | F1: 3Q22 | G1: 4Q22 | H1: 1Q23 | I1: 2Q23 | J1: 3Q23 | K1: 4Q23 | L1: 1Q24 | M1: 2Q24 | N1: 3Q24 | O1: 4Q24 | P1: 1Q25 | Q1: 2Q25 | R1: 3Q25 | S1: 4Q25 | T1: 1Q26 | U1: 2Q26 | V1: 3Q26 | W1: 4Q26 | X1: 1Q27 | Y1: 2Q27 | Z1: 3Q27 | AA1: 4Q27 | AB1: 1Q28 | AC1: 2Q28 | AD1: 3Q28 | AE1: 4Q28
E3: 1 | F3: 2 | G3: 3 | H3: 4 | I3: 5 | J3: 6 | K3: 7 | L3: 8 | M3: 9 | N3: 10 | O3: 11 | P3: 12 | Q3: 13 | R3: 14 | S3: 15 | T3: 16 | U3: 17 | V3: 18 | W3: 19 | X3: 20 | Y3: 21 | Z3: 22 | AA3: 23 | AB3: 24 | AC3: 25 | AD3: 26 | AE3: 27
E4: 2022.06 | F4: 2022.09 | G4: 2022.12 | H4: 2023.03 | I4: 2023.06 | J4: 2023.09 | K4: 2023.12 | L4: 2024.03 | M4: 2024.06 | N4: 2024.09 | O4: 2024.12 | P4: 2025.03 | Q4: 2025.06 | R4: 2025.09 | S4: 2025.12 | T4: 2026.03 | U4: 2026.06 | V4: 2026.09 | W4: 2026.12 | X4: 2027.03 | Y4: 2027.06 | Z4: 2027.09 | AA4: 2027.12 | AB4: 2028.03 | AC4: 2028.06 | AD4: 2028.09 | AE4: 2028.12
D5: 원/달러(평균) | E5: =IFERROR(VLOOKUP($D5,환율,MATCH(E$1,변수H,0),0),"") | F5: =IFERROR(VLOOKUP($D5,환율,MATCH(F$1,변수H,0),0),"") | G5: =IFERROR(VLOOKUP($D5,환율,MATCH(G$1,변수H,0),0),"") | H5: =IFERROR(VLOOKUP($D5,환율,MATCH(H$1,변수H,0),0),"") | I5: =IFERROR(VLOOKUP($D5,환율,MATCH(I$1,변수H,0),0),"") | J5: =IFERROR(VLOOKUP($D5,환율,MATCH(J$1,변수H,0),0),"") | K5: =IFERROR(VLOOKUP($D5,환율,MATCH(K$1,변수H,0),0),"") | L5: =IFERROR(VLOOKUP($D5,환율,MATCH(L$1,변수H,0),0),"") | ... AE5: =IFERROR(VLOOKUP($D5,환율,MATCH(AE$1,변수H,0),0),"")
A6: 원/달러(평균) QoQ | F6: =IFERROR(F5/E5-1,"") | G6: =IFERROR(G5/F5-1,"") | H6: =IFERROR(H5/G5-1,"") | I6: =IFERROR(I5/H5-1,"") | J6: =IFERROR(J5/I5-1,"") | K6: =IFERROR(K5/J5-1,"") | L6: =IFERROR(L5/K5-1,"") | M6: =IFERROR(M5/L5-1,"") | ... AE6: =IFERROR(AE5/AD5-1,"")
D7: 원/달러(기말) | E7: =IFERROR(VLOOKUP($D7,환율,MATCH(E$1,변수H,0),0),"") | F7: =IFERROR(VLOOKUP($D7,환율,MATCH(F$1,변수H,0),0),"") | G7: =IFERROR(VLOOKUP($D7,환율,MATCH(G$1,변수H,0),0),"") | H7: =IFERROR(VLOOKUP($D7,환율,MATCH(H$1,변수H,0),0),"") | I7: =IFERROR(VLOOKUP($D7,환율,MATCH(I$1,변수H,0),0),"") | J7: =IFERROR(VLOOKUP($D7,환율,MATCH(J$1,변수H,0),0),"") | K7: =IFERROR(VLOOKUP($D7,환율,MATCH(K$1,변수H,0),0),"") | L7: =IFERROR(VLOOKUP($D7,환율,MATCH(L$1,변수H,0),0),"") | ... AE7: =IFERROR(VLOOKUP($D7,환율,MATCH(AE$1,변수H,0),0),"")
A8: 원/달러(기말) QoQ | F8: =IFERROR(F7/E7-1,"") | G8: =IFERROR(G7/F7-1,"") | H8: =IFERROR(H7/G7-1,"") | I8: =IFERROR(I7/H7-1,"") | J8: =IFERROR(J7/I7-1,"") | K8: =IFERROR(K7/J7-1,"") | L8: =IFERROR(L7/K7-1,"") | M8: =IFERROR(M7/L7-1,"") | ... AE8: =IFERROR(AE7/AD7-1,"")
D9: W/Euro(평균) | E9: =IFERROR(VLOOKUP($D9,환율,MATCH(E$1,변수H,0),0),"") | F9: =IFERROR(VLOOKUP($D9,환율,MATCH(F$1,변수H,0),0),"") | G9: =IFERROR(VLOOKUP($D9,환율,MATCH(G$1,변수H,0),0),"") | H9: =IFERROR(VLOOKUP($D9,환율,MATCH(H$1,변수H,0),0),"") | I9: =IFERROR(VLOOKUP($D9,환율,MATCH(I$1,변수H,0),0),"") | J9: =IFERROR(VLOOKUP($D9,환율,MATCH(J$1,변수H,0),0),"") | K9: =IFERROR(VLOOKUP($D9,환율,MATCH(K$1,변수H,0),0),"") | L9: =IFERROR(VLOOKUP($D9,환율,MATCH(L$1,변수H,0),0),"") | ... AE9: =IFERROR(VLOOKUP($D9,환율,MATCH(AE$1,변수H,0),0),"")
A10: W/Euro(평균) QoQ | F10: =IFERROR(F9/E9-1,"") | G10: =IFERROR(G9/F9-1,"") | H10: =IFERROR(H9/G9-1,"") | I10: =IFERROR(I9/H9-1,"") | J10: =IFERROR(J9/I9-1,"") | K10: =IFERROR(K9/J9-1,"") | L10: =IFERROR(L9/K9-1,"") | M10: =IFERROR(M9/L9-1,"") | ... AE10: =IFERROR(AE9/AD9-1,"")
D11: W/Euro(기말) | E11: =IFERROR(VLOOKUP($D11,환율,MATCH(E$1,변수H,0),0),"") | F11: =IFERROR(VLOOKUP($D11,환율,MATCH(F$1,변수H,0),0),"") | G11: =IFERROR(VLOOKUP($D11,환율,MATCH(G$1,변수H,0),0),"") | H11: =IFERROR(VLOOKUP($D11,환율,MATCH(H$1,변수H,0),0),"") | I11: =IFERROR(VLOOKUP($D11,환율,MATCH(I$1,변수H,0),0),"") | J11: =IFERROR(VLOOKUP($D11,환율,MATCH(J$1,변수H,0),0),"") | K11: =IFERROR(VLOOKUP($D11,환율,MATCH(K$1,변수H,0),0),"") | L11: =IFERROR(VLOOKUP($D11,환율,MATCH(L$1,변수H,0),0),"") | ... AE11: =IFERROR(VLOOKUP($D11,환율,MATCH(AE$1,변수H,0),0),"")
A12: W/Euro(기말) QoQ | F12: =IFERROR(F11/E11-1,"") | G12: =IFERROR(G11/F11-1,"") | H12: =IFERROR(H11/G11-1,"") | I12: =IFERROR(I11/H11-1,"") | J12: =IFERROR(J11/I11-1,"") | K12: =IFERROR(K11/J11-1,"") | L12: =IFERROR(L11/K11-1,"") | M12: =IFERROR(M11/L11-1,"") | ... AE12: =IFERROR(AE11/AD11-1,"")
D13: 원/100Y(기말) | E13: =IFERROR(VLOOKUP($D13,환율,MATCH(E$1,변수H,0),0),"") | F13: =IFERROR(VLOOKUP($D13,환율,MATCH(F$1,변수H,0),0),"") | G13: =IFERROR(VLOOKUP($D13,환율,MATCH(G$1,변수H,0),0),"") | H13: =IFERROR(VLOOKUP($D13,환율,MATCH(H$1,변수H,0),0),"") | I13: =IFERROR(VLOOKUP($D13,환율,MATCH(I$1,변수H,0),0),"") | J13: =IFERROR(VLOOKUP($D13,환율,MATCH(J$1,변수H,0),0),"") | K13: =IFERROR(VLOOKUP($D13,환율,MATCH(K$1,변수H,0),0),"") | L13: =IFERROR(VLOOKUP($D13,환율,MATCH(L$1,변수H,0),0),"") | ... AE13: =IFERROR(VLOOKUP($D13,환율,MATCH(AE$1,변수H,0),0),"")
A14: 원/100Y(기말) QoQ | F14: =IFERROR(F13/E13-1,"") | G14: =IFERROR(G13/F13-1,"") | H14: =IFERROR(H13/G13-1,"") | I14: =IFERROR(I13/H13-1,"") | J14: =IFERROR(J13/I13-1,"") | K14: =IFERROR(K13/J13-1,"") | L14: =IFERROR(L13/K13-1,"") | M14: =IFERROR(M13/L13-1,"") | ... AE14: =IFERROR(AE13/AD13-1,"")
A16: 외화순노출 | C16: 외화 순노출(백만$) | D16: =변수!D53 | E16: 외화 순노출 × Δ기말환율 (외화 시트 방식)
A17: 환관련손익추정 | C17: 환관련손익 추정(억원) = 순노출 × Δ원/달러(기말) / 100 | F17: =IFERROR($D$16*(F7-E7)/100,"") | G17: =IFERROR($D$16*(G7-F7)/100,"") | H17: =IFERROR($D$16*(H7-G7)/100,"") | I17: =IFERROR($D$16*(I7-H7)/100,"") | J17: =IFERROR($D$16*(J7-I7)/100,"") | K17: =IFERROR($D$16*(K7-J7)/100,"") | L17: =IFERROR($D$16*(L7-K7)/100,"") | M17: =IFERROR($D$16*(M7-L7)/100,"") | ... AE17: =IFERROR($D$16*(AE7-AD7)/100,"")
A18: fx_pnl.by_q | C18: 모델 fx_pnl.by_q(억원, 참고)
C19: 외화 순노출 미공시(face) → 0 + 표기
