Workbook
Name 변수H: 변수!$C$1:$AE$1
Name 환율: 변수!$C$6:$AE$13
Name BS연결H: BS연결!$C$1:$AE$1
Name BS연결: BS연결!$C$5:$AE$5
Name BS별도H: BS별도!$C$1:$AE$1
Name BS별도: BS별도!$C$5:$AE$92
Name SUBQH: subQ!$A$1:$AE$1
Name subQ: subQ!$A$5:$AE$44

Sheet README
A1: 한선엔지니어링(452280) 실적 모델 — ARGUS 한국조선
A2: 기준 분기 2026Q2 · 마지막 실적 2026Q2 · 생성 2026-10-14
A3: 모든 수치는 모델 산출값(DART 공개 재무제표 + 우리 추정)이다 — 목표주가·투자 추천 아님. 참고용 · 투자조언 아님.
A5: 시트
A6: 변수 가정 시계열. 환율 8행(ECB via frankfurter — L2 fx.json; 추정 분기 = 노란 가정), 추정 드라이버(노란 셀 = 모델값에서 역산한 가정, 바꾸면 재계산; 연녹 셀 = 3절 스칼라 참조 수식), 3절 스칼라 가정(세율·판관비율·지배주주비중·이자율·종가·PER 밴드·COE·외화 순노출·헤지비율)
A7: BS연결/BS별도 FnGuide 계정명 × 기간 값 덤프(백만원). 행1 분기라벨, 행4 YYYY.MM / YYYY.12A. 이름정의 BS연결H·BS연결(계정명 C열부터)
A8: subQ 분기 서브모델(억원 = 백만원/100). 확정 행: =IFERROR(VLOOKUP($D행,BS연결,MATCH(E$1,BS연결H,0),0)/100,"") 추정 행: 변수 시트 가정 셀 참조 수식. 외환손익·파생상품손익은 BS 계정 합·차, 기타금융손익은 잔차, OPM·EPS·BPS·PER·PBR 은 파생 수식
A9: SLS 선표(조선사만, sls json 있을 때): 요약 행(sls 저장값) + 계약별 스케줄(백만$) × (헤지비율 × 헤지환율 + (1−헤지비율) × 건조시점 환율[변수 원/달러(평균)]) → 원화 수식 블록 → 합계 행이 subQ 매출조선에 연결
A10: 시나리오 신규수주 보수/기준/낙관(forecast_panel 패널, 모델에 scenarios 가 있을 때만): 매출액·영업이익 = subQ 기준값 ± (시나리오 신규 − base 신규) × OPM. base 만 subQ 행에 포함, 나머지는 합산 안 함
A11: 분기/연간예상 subQ 를 이름(A열 key)으로 VLOOKUP 한 보고서 표(억원)
A12: TP PER 밴드 × 12M fwd EPS, PBR = ROE/COE × BPS — 모델 산출값 구간, 목표주가·추천 아님
A13: 외화 환율 QoQ, 외화 순노출 × Δ기말환율 → 환관련손익 추정
... A34: 백테스트: {"freeze": "2025Q2", "horizon": 4, "revenue_wape_pct": 35.3, "op_wape_pct": 65.0, "n": 4, "note": "단일 회사 4분기 — 통계 아님", "driver_at_freeze": "trend_seasonal", "selection_oos_at_freeze": null, "frozen_inputs": "fin(연결/별도)·고객 조선사 모델·지주 자회사 모델은 2025Q2 까지의 분기만; 선표는 체결일 ≤ 2025Q2 말일 계약(원장 최신 금액·코호트 등급, 환산 없음); 잔고는 yards_cache 2025Q2; 시세·환율 forward·prices·forecast_panel 신규수주 미사용. 고객 가중치(suppliers.json 언급 비중)와 합병 체인링크는 현재 지식; 고객 연동 채택은 동결 모델 안에서도 자기 la−4분기 OOS 규칙(selection_oos_at_freeze)", "detail": [{"q": "2025Q3", "rev_pred": 112.0, "rev_act": 161.96, "op_pred": 12.97, "op_act": 25.93}, {"q": "2025Q4", "rev_pred": 123.37, "rev_act": 184.1, "op_pred": 14.28, "op_act": 28.23}, {"q": "2026Q1", "rev_pred": 131.11, "rev_act": 223.81, "op_pred": 15.18, "op_act": 62.05}, {"q": "2026Q2", "rev_pred": 154.99, "rev_act": 236.45, "op_pred": 17.94, "op_act": 56.03}]}

Sheet 변수
C1: 이름: 변수H | E1: 4Q23 | F1: 2023 | G1: 1Q24 | H1: 2Q24 | I1: 3Q24 | J1: 4Q24 | K1: 2024 | L1: 1Q25 | M1: 2Q25 | N1: 3Q25 | O1: 4Q25 | P1: 2025 | Q1: 1Q26 | R1: 2Q26 | S1: 3Q26 | T1: 4Q26 | U1: 2026 | V1: 1Q27 | W1: 2Q27 | X1: 3Q27 | Y1: 4Q27 | Z1: 2027 | AA1: 1Q28 | AB1: 2Q28 | AC1: 3Q28 | AD1: 4Q28 | AE1: 2028
A2: 가정 시계열 — 노란 셀은 추정 가정(모델값에서 역산), 연녹 셀은 3절 스칼라 참조 수식. 바꾸면 subQ·분기·연간예상·TP·시나리오가 재계산됩니다.
E3: 1 | F3: 2 | G3: 3 | H3: 4 | I3: 5 | J3: 6 | K3: 7 | L3: 8 | M3: 9 | N3: 10 | O3: 11 | P3: 12 | Q3: 13 | R3: 14 | S3: 15 | T3: 16 | U3: 17 | V3: 18 | W3: 19 | X3: 20 | Y3: 21 | Z3: 22 | AA3: 23 | AB3: 24 | AC3: 25 | AD3: 26 | AE3: 27
E4: 2023.12 | F4: 2023.12A | G4: 2024.03 | H4: 2024.06 | I4: 2024.09 | J4: 2024.12 | K4: 2024.12A | L4: 2025.03 | M4: 2025.06 | N4: 2025.09 | O4: 2025.12 | P4: 2025.12A | Q4: 2026.03 | R4: 2026.06 | S4: 2026.09 | T4: 2026.12 | U4: 2026.12A | V4: 2027.03 | W4: 2027.06 | X4: 2027.09 | Y4: 2027.12 | Z4: 2027.12A | AA4: 2028.03 | AB4: 2028.06 | AC4: 2028.09 | AD4: 2028.12 | AE4: 2028.12A
B5: 1. FX | C5: 이름: 환율
A6: USDKRW_avg | C6: 원/달러(평균) | E6: 1322.01 | F6: 1306.85 | G6: 1330.14 | H6: 1371.28 | I6: 1356.22 | J6: 1396.3 | K6: 1363.53 | L6: 1452.28 | M6: 1398.52 | N6: 1386.95 | O6: 1449.19 | P6: 1421.52 | Q6: 1466.12 | R6: 1501.75 | S6: 1418.75 | T6: 1343.39 | U6: 1456.01 | V6: 1341.45 | W6: 1341.45 | X6: 1341.45 | Y6: 1341.45 | AA6: 1341.45 | AB6: 1341.45 | AC6: 1341.45 | AD6: 1341.45
A7: USDKRW_end | C7: 원/달러(기말) | E7: 1297.43 | F7: 1297.43 | G7: 1349.25 | H7: 1377.73 | I7: 1312.17 | J7: 1474.78 | K7: 1474.78 | L7: 1474.54 | M7: 1355.13 | N7: 1403.67 | O7: 1444.2 | P7: 1444.2 | Q7: 1524.8 | R7: 1550.89 | S7: 1355.4 | T7: 1341.45 | U7: 1341.45 | V7: 1341.45 | W7: 1341.45 | X7: 1341.45 | Y7: 1341.45 | AA7: 1341.45 | AB7: 1341.45 | AC7: 1341.45 | AD7: 1341.45
A8: JPY100KRW_avg | C8: 원/100Y(평균) | E8: 893.22 | F8: 931.11 | G8: 896.29 | H8: 880.14 | I8: 909.35 | J8: 917.25 | K8: 900.92 | L8: 952.59 | M8: 967.92 | N8: 940.32 | O8: 940.77 | P8: 950.17 | Q8: 934.39 | R8: 942.16 | S8: 890.41 | T8: 849.39 | U8: 918.46 | V8: 848.37 | W8: 848.37 | X8: 848.37 | Y8: 848.37 | AA8: 848.37 | AB8: 848.37 | AC8: 848.37 | AD8: 848.37
A9: JPY100KRW_end | C9: 원/100Y(기말) | E9: 917.04 | F9: 917.04 | G9: 892.42 | H9: 857.76 | I9: 919.21 | J9: 939.65 | K9: 939.65 | L9: 986.84 | M9: 938.85 | N9: 948.49 | O9: 921.81 | P9: 921.81 | Q9: 955.99 | R9: 954.75 | S9: 863.31 | T9: 848.37 | U9: 848.37 | V9: 848.37 | W9: 848.37 | X9: 848.37 | Y9: 848.37 | AA9: 848.37 | AB9: 848.37 | AC9: 848.37 | AD9: 848.37
A10: EURKRW_avg | C10: W/Euro(평균) | E10: 1420.91 | F10: 1412.88 | G10: 1444.21 | H10: 1476.42 | I10: 1489.3 | J10: 1490.78 | K10: 1475.4 | L10: 1528.33 | M10: 1585.13 | N10: 1620.04 | O10: 1686.02 | P10: 1605.45 | Q10: 1715.47 | R10: 1746.09 | S10: 1631.97 | T10: 1506.62 | U10: 1688.01 | V10: 1500.82 | W10: 1500.82 | X10: 1500.82 | Y10: 1500.82 | AA10: 1500.82 | AB10: 1500.82 | AC10: 1500.82 | AD10: 1500.82
A11: EURKRW_end | C11: W/Euro(기말) | E11: 1433.66 | F11: 1433.66 | G11: 1458.68 | H11: 1474.86 | I11: 1469.1 | J11: 1532.14 | K11: 1532.14 | L11: 1594.72 | M11: 1588.22 | N11: 1648.04 | O11: 1696.94 | P11: 1696.94 | Q11: 1753.21 | R11: 1767.09 | S11: 1539.06 | T11: 1500.82 | U11: 1500.82 | V11: 1500.82 | W11: 1500.82 | X11: 1500.82 | Y11: 1500.82 | AA11: 1500.82 | AB11: 1500.82 | AC11: 1500.82 | AD11: 1500.82
A12: CNYKRW_avg | C12: 원/중국원(평균) | E12: 182.86 | F12: 184.52 | G12: 185.04 | H12: 189.35 | I12: 189.24 | J12: 194.24 | K12: 189.49 | L12: 199.63 | M12: 193.41 | N12: 193.79 | O12: 204.38 | P12: 197.8 | Q12: 211.75 | R12: 220.8 | S12: 210.43 | T12: 200.49 | U12: 213.61 | V12: 200.4 | W12: 200.4 | X12: 200.4 | Y12: 200.4 | AA12: 200.4 | AB12: 200.4 | AC12: 200.4 | AD12: 200.4
A13: CNYKRW_end | C13: 원/중국원(기말) | E13: 182.61 | F13: 182.61 | G13: 186.66 | H13: 189.7 | I13: 187.12 | J13: 202.04 | K13: 202.04 | L13: 203.3 | M13: 189.14 | N13: 197.16 | O13: 206.28 | P13: 206.28 | Q13: 220.97 | R13: 228.56 | S13: 202.16 | T13: 200.4 | U13: 200.4 | V13: 200.4 | W13: 200.4 | X13: 200.4 | Y13: 200.4 | AA13: 200.4 | AB13: 200.4 | AC13: 200.4 | AD13: 200.4
B14: 1b. 종가
A15: price_close_end | C15: 종가(기말) | E15: 9280 | G15: 6590 | H15: 11330 | I15: 11160 | J15: 6180 | L15: 6510 | M15: 6960 | N15: 10970 | O15: 8540 | Q15: 13850 | R15: 14380 | S15: 13730 | T15: 15930
A16: price_high | C16: 종가(최고) | E16: 20650 | G16: 10180 | H16: 14600 | I16: 15750 | J16: 11950 | L16: 9690 | M16: 7720 | N16: 12540 | O16: 12350 | Q16: 17930 | R16: 37300 | S16: 15830 | T16: 16200
A17: price_low | C17: 종가(최저) | E17: 8980 | G17: 6380 | H17: 5410 | I17: 9180 | J17: 5800 | L17: 6070 | M17: 5910 | N17: 6550 | O17: 8380 | Q17: 7840 | R17: 11360 | S17: 8610 | T17: 12160
A18: price_avg | C18: 종가(평균) | E18: 10898.3 | G18: 7657.9 | H18: 8953 | I18: 11694.8 | J18: 8496.9 | L18: 7438.6 | M18: 6972.3 | N18: 8095.5 | O18: 9682.5 | Q18: 11260 | R18: 19949.2 | S18: 11494.2 | T18: 14152.5
B20: 2. 추정 드라이버 | C20: 실적 열 = subQ 실현값(수식), 추정 열 = 가정(노란 = 모델값 역산, 연녹 = 3절 스칼라 참조)
A21: drv:매출액 | B21: yoy | C21: 매출액 YoY | J21: =IFERROR(subQ!J5/subQ!E5-1,"") | L21: =IFERROR(subQ!L5/subQ!G5-1,"") | M21: =IFERROR(subQ!M5/subQ!H5-1,"") | N21: =IFERROR(subQ!N5/subQ!I5-1,"") | O21: =IFERROR(subQ!O5/subQ!J5-1,"") | Q21: =IFERROR(subQ!Q5/subQ!L5-1,"") | R21: =IFERROR(subQ!R5/subQ!M5-1,"") | S21: 0.50001111 | T21: 0.49998045 | V21: 0.50000491 | W21: 0.49999027 | X21: 0.24997942 | Y21: 0.25000905 | AA21: 0.25 | AB21: 0.25000705 | AC21: 0.12500412 | AD21: 0.12500362
A22: drv:판관비 | B22: ratio | C22: 판관비율(/매출) | E22: =IFERROR(subQ!E8/subQ!E5,"") | F22: =IFERROR(subQ!F8/subQ!F5,"") | G22: =IFERROR(subQ!G8/subQ!G5,"") | H22: =IFERROR(subQ!H8/subQ!H5,"") | I22: =IFERROR(subQ!I8/subQ!I5,"") | J22: =IFERROR(subQ!J8/subQ!J5,"") | K22: =IFERROR(subQ!K8/subQ!K5,"") | L22: =IFERROR(subQ!L8/subQ!L5,"") | ... R22: =IFERROR(subQ!R8/subQ!R5,"") | S22: =$D$52 | T22: =$D$52 | U22: =IFERROR(subQ!U8/subQ!U5,"") | V22: =$D$52 | W22: =$D$52 | X22: =$D$52 | Y22: =$D$52 | Z22: =IFERROR(subQ!Z8/subQ!Z5,"") | AA22: =$D$52 | AB22: =$D$52 | AC22: =$D$52 | AD22: =$D$52 | AE22: =IFERROR(subQ!AE8/subQ!AE5,"")
A23: drv:영업이익 | B23: ratio | C23: 영업이익률(OPM) | E23: =IFERROR(subQ!E9/subQ!E5,"") | F23: =IFERROR(subQ!F9/subQ!F5,"") | G23: =IFERROR(subQ!G9/subQ!G5,"") | H23: =IFERROR(subQ!H9/subQ!H5,"") | I23: =IFERROR(subQ!I9/subQ!I5,"") | J23: =IFERROR(subQ!J9/subQ!J5,"") | K23: =IFERROR(subQ!K9/subQ!K5,"") | L23: =IFERROR(subQ!L9/subQ!L5,"") | ... R23: =IFERROR(subQ!R9/subQ!R5,"") | S23: 0.15670536 | T23: 0.1566902 | U23: =IFERROR(subQ!U9/subQ!U5,"") | V23: 0.15667818 | W23: 0.15668086 | X23: 0.15668324 | Y23: 0.15669631 | Z23: =IFERROR(subQ!Z9/subQ!Z5,"") | AA23: 0.15670201 | AB23: 0.15669689 | AC23: 0.15668999 | AD23: 0.15669259 | AE23: =IFERROR(subQ!AE9/subQ!AE5,"")
A24: drv:외환손익 | B24: abs | C24: 외환손익 (가정, 억원) | E24: =subQ!E13 | F24: =subQ!F13 | G24: =subQ!G13 | H24: =subQ!H13 | I24: =subQ!I13 | J24: =subQ!J13 | K24: =subQ!K13 | L24: =subQ!L13 | ... R24: =subQ!R13 | S24: 0 | T24: 0 | U24: =subQ!U13 | V24: 0 | W24: 0 | X24: 0 | Y24: 0 | Z24: =subQ!Z13 | AA24: 0 | AB24: 0 | AC24: 0 | AD24: 0 | AE24: =subQ!AE13
A25: drv:파생상품손익 | B25: abs | C25: 파생상품손익 (가정, 억원) | E25: =subQ!E14 | F25: =subQ!F14 | G25: =subQ!G14 | H25: =subQ!H14 | I25: =subQ!I14 | J25: =subQ!J14 | K25: =subQ!K14 | L25: =subQ!L14 | ... R25: =subQ!R14 | S25: 0 | T25: 0 | U25: =subQ!U14 | V25: 0 | W25: 0 | X25: 0 | Y25: 0 | Z25: =subQ!Z14 | AA25: 0 | AB25: 0 | AC25: 0 | AD25: 0 | AE25: =subQ!AE14
A26: drv:기타금융손익 | B26: abs | C26: 기타금융손익 (가정, 억원) | E26: =subQ!E15 | F26: =subQ!F15 | G26: =subQ!G15 | H26: =subQ!H15 | I26: =subQ!I15 | J26: =subQ!J15 | K26: =subQ!K15 | L26: =subQ!L15 | ... R26: =subQ!R15 | S26: 0 | T26: 0 | U26: =subQ!U15 | V26: 0 | W26: 0 | X26: 0 | Y26: 0 | Z26: =subQ!Z15 | AA26: 0 | AB26: 0 | AC26: 0 | AD26: 0 | AE26: =subQ!AE15
A27: drv:기타영업외손익 | B27: abs | C27: 기타영업외손익 (가정, 억원) | E27: =subQ!E16 | F27: =subQ!F16 | G27: =subQ!G16 | H27: =subQ!H16 | I27: =subQ!I16 | J27: =subQ!J16 | K27: =subQ!K16 | L27: =subQ!L16 | ... R27: =subQ!R16 | S27: 0 | T27: 0 | U27: =subQ!U16 | V27: 0 | W27: 0 | X27: 0 | Y27: 0 | Z27: =subQ!Z16 | AA27: 0 | AB27: 0 | AC27: 0 | AD27: 0 | AE27: =subQ!AE16
A28: drv:법인세비용 | B28: tax | C28: 법인세율(/세전) — 법인세 = MAX(세전,0) × 세율 | E28: =IFERROR(subQ!E18/subQ!E17,"") | F28: =IFERROR(subQ!F18/subQ!F17,"") | G28: =IFERROR(subQ!G18/subQ!G17,"") | H28: =IFERROR(subQ!H18/subQ!H17,"") | I28: =IFERROR(subQ!I18/subQ!I17,"") | J28: =IFERROR(subQ!J18/subQ!J17,"") | K28: =IFERROR(subQ!K18/subQ!K17,"") | L28: =IFERROR(subQ!L18/subQ!L17,"") | ... R28: =IFERROR(subQ!R18/subQ!R17,"") | S28: =$D$51 | T28: =$D$51 | U28: =IFERROR(subQ!U18/subQ!U17,"") | V28: =$D$51 | W28: =$D$51 | X28: =$D$51 | Y28: =$D$51 | Z28: =IFERROR(subQ!Z18/subQ!Z17,"") | AA28: =$D$51 | AB28: =$D$51 | AC28: =$D$51 | AD28: =$D$51 | AE28: =IFERROR(subQ!AE18/subQ!AE17,"")
A29: drv:지배주주순이익 | B29: ratio | C29: 지배주주 비중(/당기순이익) | E29: =IFERROR(subQ!E20/subQ!E19,"") | F29: =IFERROR(subQ!F20/subQ!F19,"") | G29: =IFERROR(subQ!G20/subQ!G19,"") | H29: =IFERROR(subQ!H20/subQ!H19,"") | I29: =IFERROR(subQ!I20/subQ!I19,"") | J29: =IFERROR(subQ!J20/subQ!J19,"") | K29: =IFERROR(subQ!K20/subQ!K19,"") | L29: =IFERROR(subQ!L20/subQ!L19,"") | ... R29: =IFERROR(subQ!R20/subQ!R19,"") | S29: =$D$53 | T29: =$D$53 | U29: =IFERROR(subQ!U20/subQ!U19,"") | V29: =$D$53 | W29: =$D$53 | X29: =$D$53 | Y29: =$D$53 | Z29: =IFERROR(subQ!Z20/subQ!Z19,"") | AA29: =$D$53 | AB29: =$D$53 | AC29: =$D$53 | AD29: =$D$53 | AE29: =IFERROR(subQ!AE20/subQ!AE19,"")
A30: drv:감가상각비 | B30: abs | C30: 감가상각비 (가정, 억원) | E30: =subQ!E21 | F30: =subQ!F21 | G30: =subQ!G21 | H30: =subQ!H21 | I30: =subQ!I21 | J30: =subQ!J21 | K30: =subQ!K21 | L30: =subQ!L21 | ... R30: =subQ!R21 | S30: 5.44 | T30: 5.44 | U30: =subQ!U21 | V30: 5.44 | W30: 5.44 | X30: 5.44 | Y30: 5.44 | Z30: =subQ!Z21 | AA30: 5.44 | AB30: 5.44 | AC30: 5.44 | AD30: 5.44 | AE30: =subQ!AE21
A31: drv:부채총계 | B31: qoq | C31: 부채총계 QoQ | G31: =IFERROR(subQ!G24/subQ!E24-1,"") | H31: =IFERROR(subQ!H24/subQ!G24-1,"") | I31: =IFERROR(subQ!I24/subQ!H24-1,"") | J31: =IFERROR(subQ!J24/subQ!I24-1,"") | L31: =IFERROR(subQ!L24/subQ!J24-1,"") | M31: =IFERROR(subQ!M24/subQ!L24-1,"") | N31: =IFERROR(subQ!N24/subQ!M24-1,"") | O31: =IFERROR(subQ!O24/subQ!N24-1,"") | Q31: =IFERROR(subQ!Q24/subQ!O24-1,"") | R31: =IFERROR(subQ!R24/subQ!Q24-1,"") | S31: 2.152e-06 | T31: 0 | V31: 0 | W31: 0 | X31: 0 | Y31: 0 | AA31: 0 | AB31: 0 | AC31: 0 | AD31: 0
A32: drv:자본총계 | B32: roll | C32: 자본총계 기타변동(배당 등, 억원) | G32: =IFERROR(subQ!E25+subQ!G19-subQ!G25,"") | H32: =IFERROR(subQ!G25+subQ!H19-subQ!H25,"") | I32: =IFERROR(subQ!H25+subQ!I19-subQ!I25,"") | J32: =IFERROR(subQ!I25+subQ!J19-subQ!J25,"") | L32: =IFERROR(subQ!J25+subQ!L19-subQ!L25,"") | M32: =IFERROR(subQ!L25+subQ!M19-subQ!M25,"") | N32: =IFERROR(subQ!M25+subQ!N19-subQ!N25,"") | O32: =IFERROR(subQ!N25+subQ!O19-subQ!O25,"") | Q32: =IFERROR(subQ!O25+subQ!Q19-subQ!Q25,"") | R32: =IFERROR(subQ!Q25+subQ!R19-subQ!R25,"") | S32: 0.008280558 | T32: -0.003454362 | V32: -0.005257215 | W32: 0.000856008 | X32: -0.006339444 | Y32: 0.002822079 | AA32: 0.00471339 | AB32: -0.002390202 | AC32: -0.000648051 | AD32: -0.005174799
A33: drv:지배주주지분 | B33: roll | C33: 지배주주지분 기타변동(배당 등, 억원) | G33: =IFERROR(subQ!E26+subQ!G20-subQ!G26,"") | H33: =IFERROR(subQ!G26+subQ!H20-subQ!H26,"") | I33: =IFERROR(subQ!H26+subQ!I20-subQ!I26,"") | J33: =IFERROR(subQ!I26+subQ!J20-subQ!J26,"") | L33: =IFERROR(subQ!J26+subQ!L20-subQ!L26,"") | M33: =IFERROR(subQ!L26+subQ!M20-subQ!M26,"") | N33: =IFERROR(subQ!M26+subQ!N20-subQ!N26,"") | O33: =IFERROR(subQ!N26+subQ!O20-subQ!O26,"") | Q33: =IFERROR(subQ!O26+subQ!Q20-subQ!Q26,"") | R33: =IFERROR(subQ!Q26+subQ!R20-subQ!R26,"") | S33: 0.008280558 | T33: -0.003454362 | V33: -0.005257215 | W33: 0.000856008 | X33: -0.006339444 | Y33: 0.002822079 | AA33: 0.00471339 | AB33: -0.002390202 | AC33: -0.000648051 | AD33: -0.005174799
A34: drv:총차입금 | B34: qoq | C34: 총차입금 QoQ | G34: =IFERROR(subQ!G27/subQ!E27-1,"") | H34: =IFERROR(subQ!H27/subQ!G27-1,"") | I34: =IFERROR(subQ!I27/subQ!H27-1,"") | J34: =IFERROR(subQ!J27/subQ!I27-1,"") | L34: =IFERROR(subQ!L27/subQ!J27-1,"") | M34: =IFERROR(subQ!M27/subQ!L27-1,"") | N34: =IFERROR(subQ!N27/subQ!M27-1,"") | O34: =IFERROR(subQ!O27/subQ!N27-1,"") | Q34: =IFERROR(subQ!Q27/subQ!O27-1,"") | R34: =IFERROR(subQ!R27/subQ!Q27-1,"") | S34: 3.14e-06 | T34: 0 | V34: 0 | W34: 0 | X34: 0 | Y34: 0 | AA34: 0 | AB34: 0 | AC34: 0 | AD34: 0
A35: drv:순차입금 | B35: qoq | C35: 순차입금 QoQ | G35: =IFERROR(subQ!G28/subQ!E28-1,"") | H35: =IFERROR(subQ!H28/subQ!G28-1,"") | I35: =IFERROR(subQ!I28/subQ!H28-1,"") | J35: =IFERROR(subQ!J28/subQ!I28-1,"") | L35: =IFERROR(subQ!L28/subQ!J28-1,"") | M35: =IFERROR(subQ!M28/subQ!L28-1,"") | N35: =IFERROR(subQ!N28/subQ!M28-1,"") | O35: =IFERROR(subQ!O28/subQ!N28-1,"") | Q35: =IFERROR(subQ!Q28/subQ!O28-1,"") | R35: =IFERROR(subQ!R28/subQ!Q28-1,"") | S35: 0.15210925 | T35: 0.12024226 | V35: 0.08788201 | W35: 0.075355568 | X35: 0.085138062 | Y35: 0.067873626 | AA35: 0.045437859 | AB35: 0.038068028 | AC35: 0.060135925 | AD35: 0.04696361
A36: drv:이자발생자산 | B36: qoq | C36: 이자발생자산 QoQ | G36: =IFERROR(subQ!G29/subQ!E29-1,"") | H36: =IFERROR(subQ!H29/subQ!G29-1,"") | I36: =IFERROR(subQ!I29/subQ!H29-1,"") | J36: =IFERROR(subQ!J29/subQ!I29-1,"") | L36: =IFERROR(subQ!L29/subQ!J29-1,"") | M36: =IFERROR(subQ!M29/subQ!L29-1,"") | N36: =IFERROR(subQ!N29/subQ!M29-1,"") | O36: =IFERROR(subQ!O29/subQ!N29-1,"") | Q36: =IFERROR(subQ!Q29/subQ!O29-1,"") | R36: =IFERROR(subQ!R29/subQ!Q29-1,"") | S36: -0.37748739 | T36: -0.55225791 | V36: -1.0098778 | W36: 95.368421 | X36: 1.2023484 | Y36: 0.47228766 | AA36: 0.22932458 | AB36: 0.16338974 | AC36: 0.23030267 | AD36: 0.15498014
A37: drv:현금및현금성자산 | B37: qoq | C37: 현금및현금성자산 QoQ | G37: =IFERROR(subQ!G30/subQ!E30-1,"") | H37: =IFERROR(subQ!H30/subQ!G30-1,"") | I37: =IFERROR(subQ!I30/subQ!H30-1,"") | J37: =IFERROR(subQ!J30/subQ!I30-1,"") | L37: =IFERROR(subQ!L30/subQ!J30-1,"") | M37: =IFERROR(subQ!M30/subQ!L30-1,"") | N37: =IFERROR(subQ!N30/subQ!M30-1,"") | O37: =IFERROR(subQ!O30/subQ!N30-1,"") | Q37: =IFERROR(subQ!Q30/subQ!O30-1,"") | R37: =IFERROR(subQ!R30/subQ!Q30-1,"")
A38: drv:CAPEX | B38: yoy | C38: CAPEX YoY | J38: =IFERROR(subQ!J31/subQ!E31-1,"") | L38: =IFERROR(subQ!L31/subQ!G31-1,"") | M38: =IFERROR(subQ!M31/subQ!H31-1,"") | N38: =IFERROR(subQ!N31/subQ!I31-1,"") | O38: =IFERROR(subQ!O31/subQ!J31-1,"") | Q38: =IFERROR(subQ!Q31/subQ!L31-1,"") | R38: =IFERROR(subQ!R31/subQ!M31-1,"") | S38: 0.008530378 | T38: -0.12126421 | V38: -0.008295171 | W38: 0.50031741 | X38: 0 | Y38: 0 | AA38: 0 | AB38: 0 | AC38: 0 | AD38: 0
A39: drv:영업활동현금흐름 | B39: yoy | C39: 영업활동현금흐름 YoY | J39: =IFERROR(subQ!J32/subQ!E32-1,"") | L39: =IFERROR(subQ!L32/subQ!G32-1,"") | M39: =IFERROR(subQ!M32/subQ!H32-1,"") | N39: =IFERROR(subQ!N32/subQ!I32-1,"") | O39: =IFERROR(subQ!O32/subQ!J32-1,"") | Q39: =IFERROR(subQ!Q32/subQ!L32-1,"") | R39: =IFERROR(subQ!R32/subQ!M32-1,"")
A40: drv:주식수 | B40: qoq | C40: 주식수 QoQ | G40: =IFERROR(subQ!G33/subQ!E33-1,"") | H40: =IFERROR(subQ!H33/subQ!G33-1,"") | I40: =IFERROR(subQ!I33/subQ!H33-1,"") | J40: =IFERROR(subQ!J33/subQ!I33-1,"") | L40: =IFERROR(subQ!L33/subQ!J33-1,"") | M40: =IFERROR(subQ!M33/subQ!L33-1,"") | N40: =IFERROR(subQ!N33/subQ!M33-1,"") | O40: =IFERROR(subQ!O33/subQ!N33-1,"") | Q40: =IFERROR(subQ!Q33/subQ!O33-1,"") | R40: =IFERROR(subQ!R33/subQ!Q33-1,"") | S40: 0 | T40: 0 | V40: 0 | W40: 0 | X40: 0 | Y40: 0 | AA40: 0 | AB40: 0 | AC40: 0 | AD40: 0
A41: drv:DPS | B41: abs | C41: DPS (가정, 원) | E41: =subQ!E36 | F41: =subQ!F36 | G41: =subQ!G36 | H41: =subQ!H36 | I41: =subQ!I36 | J41: =subQ!J36 | K41: =subQ!K36 | L41: =subQ!L36 | ... R41: =subQ!R36 | T41: 0 | U41: =subQ!U36 | Y41: 0 | Z41: =subQ!Z36 | AD41: 0 | AE41: =subQ!AE36
B43: 3. 밸류에이션·스칼라 | C43: 노란 셀 = 가정. '연결' 표시는 추정 전 분기 수식이 이 셀을 참조한다는 뜻
A44: sc:종가 | C44: 종가 | D44: 15930 | E44: 원 — 네이버 정규장 종가(aik 확정종가 대조 · aik 13,270원)
A45: sc:기준일 | C45: 기준일 | D45: 20261014 | E45: 종가 기준일
A46: sc:COE | C46: COE | D46: 0.09 | E46: 자기자본비용(가정) — TP 적정 PBR = ROE/COE
A47: sc:PER_lo | C47: PER_lo | D47: 10 | E47: PER 밴드 하단(배) — sector_default(레퍼런스 TP_PE PB 예시 10/15/20배; 과거 PER 중위 31.9배가 캡 5~30 밖 — 턴어라운드 초기 TTM EPS 왜곡)
A48: sc:PER_mid | C48: PER_mid | D48: 15 | E48: PER 밴드 중단(배)
A49: sc:PER_hi | C49: PER_hi | D49: 20 | E49: PER 밴드 상단(배)
A50: sc:EPS_Y1가중 | C50: EPS_Y1가중 | D50: 0.5 | E50: 12M fwd EPS = FY(last_actual연도)E × w + FY+1E × (1−w) — 기준 분기 2Q 이면 0.5(가정)
A51: sc:세율 | C51: 세율 | D51: 0.050392281 | E51: 연결 — 법인세 = MAX(세전,0) × 세율(역산, 재현 오차 ≤ 0.05억 · 모델 assumptions 0.0504) · 최근 11분기 유효세율 32.5% 가 5~27% 밖 → 클립 대신 최근 8분기 중 세전 > 0 인 7분기(2024Q3~2026Q2)의 법인세/세전 중위 5.0%
A52: sc:판관비율 | C52: 판관비율 | D52: 0.082331295 | E52: 연결 — 판관비 = 매출액 × 판관비율(역산, 재현 오차 ≤ 0.05억 · 모델 assumptions 0.0823)
A53: sc:지배주주비중 | C53: 지배주주비중 | D53: 1 | E53: 연결 — 지배주주순이익 = 당기순이익 × 비중(역산, 재현 오차 ≤ 0.05억)
A54: sc:이자율_자산 | C54: 이자율_자산 | D54: 0.023226735 | E54: 연결 — 이자손익 = (전분기 이자발생자산 × 자산이자율 − 전분기 총차입금 × 부채이자율)/4(역산, 재현 오차 ≤ 0.05억 · 모델 assumptions 0.0232)
A55: sc:이자율_부채 | C55: 이자율_부채 | D55: 0.013901142 | E55: 연결 — 같은 수식의 부채 쪽(총차입금 행이 없으면 0)(역산, 재현 오차 ≤ 0.05억 · 모델 assumptions 0.0139)
A56: sc:배당성향 | C56: 배당성향 | D56: 0 | E56: 배당성향(참고 — 모델은 직전 DPS 유지·Q2 지급 가정)
A57: sc:외화순노출_백만$ | C57: 외화순노출_백만$ | E57: 외화 순노출 × Δ기말환율 (외화 시트 방식) — 외화 순노출 미공시(face) → 0 + 표기
A58: sc:헤지비율 | C58: 헤지비율 | E58: sls 없음
A59: sc:헤지환율_약정 | C59: 헤지환율_약정 | E59: sls 없음

Sheet BS연결
B1: (백만원) | C1: 이름: BS연결H | E1: 4Q23 | F1: 2023 | G1: 1Q24 | H1: 2Q24 | I1: 3Q24 | J1: 4Q24 | K1: 2024 | L1: 1Q25 | M1: 2Q25 | N1: 3Q25 | O1: 4Q25 | P1: 2025 | Q1: 1Q26 | R1: 2Q26 | S1: 3Q26 | T1: 4Q26 | U1: 2026 | V1: 1Q27 | W1: 2Q27 | X1: 3Q27 | Y1: 4Q27 | Z1: 2027 | AA1: 1Q28 | AB1: 2Q28 | AC1: 3Q28 | AD1: 4Q28 | AE1: 2028
B2: 연결 | D2: fin json(kship_fin.py)
B3: 한선엔지니어링(연) | C3: UPDATE: 26-10-14 | E3: 1 | F3: 2 | G3: 3 | H3: 4 | I3: 5 | J3: 6 | K3: 7 | L3: 8 | M3: 9 | N3: 10 | O3: 11 | P3: 12 | Q3: 13 | R3: 14 | S3: 15 | T3: 16 | U3: 17 | V3: 18 | W3: 19 | X3: 20 | Y3: 21 | Z3: 22 | AA3: 23 | AB3: 24 | AC3: 25 | AD3: 26 | AE3: 27
B4: Account Code | C4: AccountNAME | E4: 2023.12 | F4: 2023.12A | G4: 2024.03 | H4: 2024.06 | I4: 2024.09 | J4: 2024.12 | K4: 2024.12A | L4: 2025.03 | M4: 2025.06 | N4: 2025.09 | O4: 2025.12 | P4: 2025.12A | Q4: 2026.03 | R4: 2026.06 | S4: 2026.09 | T4: 2026.12 | U4: 2026.12A | V4: 2027.03 | W4: 2027.06 | X4: 2027.09 | Y4: 2027.12 | Z4: 2027.12A | AA4: 2028.03 | AB4: 2028.06 | AC4: 2028.09 | AD4: 2028.12 | AE4: 2028.12A

Sheet BS별도
B1: (백만원) | C1: 이름: BS별도H | E1: 4Q23 | F1: 2023 | G1: 1Q24 | H1: 2Q24 | I1: 3Q24 | J1: 4Q24 | K1: 2024 | L1: 1Q25 | M1: 2Q25 | N1: 3Q25 | O1: 4Q25 | P1: 2025 | Q1: 1Q26 | R1: 2Q26 | S1: 3Q26 | T1: 4Q26 | U1: 2026 | V1: 1Q27 | W1: 2Q27 | X1: 3Q27 | Y1: 4Q27 | Z1: 2027 | AA1: 1Q28 | AB1: 2Q28 | AC1: 3Q28 | AD1: 4Q28 | AE1: 2028
B2: 별도 | D2: fin json(kship_fin.py)
B3: 한선엔지니어링(별) | C3: UPDATE: 26-10-14 | E3: 1 | F3: 2 | G3: 3 | H3: 4 | I3: 5 | J3: 6 | K3: 7 | L3: 8 | M3: 9 | N3: 10 | O3: 11 | P3: 12 | Q3: 13 | R3: 14 | S3: 15 | T3: 16 | U3: 17 | V3: 18 | W3: 19 | X3: 20 | Y3: 21 | Z3: 22 | AA3: 23 | AB3: 24 | AC3: 25 | AD3: 26 | AE3: 27
B4: Account Code | C4: AccountNAME | E4: 2023.12 | F4: 2023.12A | G4: 2024.03 | H4: 2024.06 | I4: 2024.09 | J4: 2024.12 | K4: 2024.12A | L4: 2025.03 | M4: 2025.06 | N4: 2025.09 | O4: 2025.12 | P4: 2025.12A | Q4: 2026.03 | R4: 2026.06 | S4: 2026.09 | T4: 2026.12 | U4: 2026.12A | V4: 2027.03 | W4: 2027.06 | X4: 2027.09 | Y4: 2027.12 | Z4: 2027.12A | AA4: 2028.03 | AB4: 2028.06 | AC4: 2028.09 | AD4: 2028.12 | AE4: 2028.12A
A5: 1 | C5: 유동자산 | E5: 37420.47 | F5: 37420.47 | G5: 39916.72 | H5: 41834.15 | I5: 39014.76 | J5: 41256.09 | K5: 41256.09 | L5: 58356.43 | M5: 53826.86 | N5: 47872.7 | O5: 68579.22 | P5: 68579.22 | Q5: 72193.23 | R5: 66912.26
A6: 1 | C6: 현금및현금성자산 | E6: 7248.95 | F6: 7248.95 | G6: 6603.65 | H6: 7760.8 | I6: 5862.74 | J6: 8591.42 | K6: 8591.42 | L6: 6827.96 | M6: 3629.38 | N6: 3488.34 | O6: 22145.69 | P6: 22145.69 | Q6: 6013.5 | R6: 13525.89
A7: 1 | C7: 매출채권및기타채권 | E7: 6082.12 | F7: 6082.12 | G7: 7996.96 | H7: 10394.97 | I7: 9370.53 | J7: 7908.61 | K7: 7908.61 | L7: 9256.01 | M7: 10751.75 | N7: 11816.2 | O7: 12515.79 | P7: 12515.79 | Q7: 16420.85 | R7: 17951.84
A8: 1 | C8: 재고자산 | E8: 24024.37 | F8: 24024.37 | G8: 23776.62 | H8: 23443.4 | I8: 23550.91 | J8: 24042.74 | K8: 24042.74 | L8: 24115.25 | M8: 25951.45 | N8: 28093.56 | O8: 29594.22 | P8: 29594.22 | Q8: 31494.91 | R8: 34117.23
A9: 1 | C9: 기타유동자산 | E9: 65.02 | F9: 65.02 | G9: 196.46 | H9: 234.98 | I9: 230.58 | J9: 713.33 | K9: 713.33 | L9: 1087.47 | M9: 1319.39 | N9: 1375.11 | O9: 1871.5 | P9: 1871.5 | Q9: 1882.36 | R9: 1317.3
A10: 1 | C10: 비유동자산 | E10: 34719.4 | F10: 34719.4 | G10: 34515.45 | H10: 35078.4 | I10: 34946.5 | J10: 37730.84 | K10: 37730.84 | L10: 47447.61 | M10: 53696.89 | N10: 62632.42 | O10: 72017.02 | P10: 72017.02 | Q10: 83844.98 | R10: 87375.85
A11: 1 | C11: 장기금융자산 | E11: 77.3 | F11: 77.3 | G11: 91.3 | H11: 213.98 | I11: 218.4 | J11: 219.84 | K11: 219.84 | L11: 3133.93 | M11: 2073.51 | N11: 2061.66 | O11: 237.5 | P11: 237.5 | Q11: 275.75 | R11: 276.24
A12: 1 | C12: 투자자산 | E12: 77.3 | F12: 77.3 | G12: 91.3 | H12: 213.98 | I12: 218.4 | J12: 219.84 | K12: 219.84 | L12: 3133.93 | M12: 2073.51 | N12: 2061.66 | O12: 237.5 | P12: 237.5 | Q12: 275.75 | R12: 276.24
A13: 1 | C13: 유형자산 | E13: 32577.17 | F13: 32577.17 | G13: 32301.2 | H13: 32285.05 | I13: 32202.91 | J13: 35523.82 | K13: 35523.82 | L13: 42319.38 | M13: 49751.5 | N13: 58844.51 | O13: 69756.37 | P13: 69756.37 | Q13: 81595.15 | R13: 84942.28
A14: 1 | C14: 사용권자산 | E14: 408.89 | F14: 408.89 | G14: 387.21 | H14: 639.26 | I14: 626.17 | J14: 517.07 | K14: 517.07 | L14: 536.02 | M14: 429.44 | N14: 319.66 | O14: 304.19 | P14: 304.19 | Q14: 283.75 | R14: 279.95
A15: 1 | C15: 기타비유동자산 | E15: 408.89 | F15: 408.89 | G15: 387.21 | H15: 639.26 | I15: 626.17 | J15: 517.07 | K15: 517.07 | L15: 536.02 | M15: 429.44 | N15: 319.66 | O15: 304.19 | P15: 304.19 | Q15: 283.75 | R15: 279.95
A16: 1 | C16: 무형자산 | E16: 37.32 | F16: 37.32 | G16: 33.25 | H16: 29.21 | I16: 42.29 | J16: 75.29 | K16: 75.29 | L16: 93.36 | M16: 799.56 | N16: 794.26 | O16: 788.95 | P16: 788.95 | Q16: 791.53 | R16: 785.83
A17: 1 | C17: 장기매출채권및기타채권 | E17: 458.46 | F17: 458.46 | G17: 542.23 | H17: 488.45 | I17: 434.28 | J17: 379.75 | K17: 379.75 | L17: 349.84 | M17: 319.62 | N17: 289.06 | O17: 258.18 | P17: 258.18 | R17: 211.65
A18: 1 | C18: 이연법인세자산 | E18: 1160.26 | F18: 1160.26 | G18: 1160.26 | H18: 1422.45 | I18: 1422.45 | J18: 1015.07 | K18: 1015.07 | L18: 1015.07 | M18: 323.27 | N18: 323.27 | O18: 671.83 | P18: 671.83 | Q18: 671.83 | R18: 879
A19: 1 | C19: 자산총계 | E19: 72139.86 | F19: 72139.86 | G19: 74432.17 | H19: 76912.55 | I19: 73961.26 | J19: 78986.92 | K19: 78986.92 | L19: 105804.05 | M19: 107523.76 | N19: 110505.12 | O19: 140596.24 | P19: 140596.24 | Q19: 156038.21 | R19: 154288.11
A20: 1 | C20: 유동부채 | E20: 8269.11 | F20: 8269.11 | G20: 8741.93 | H20: 9712.72 | I20: 6792.44 | J20: 11750.66 | K20: 11750.66 | L20: 31516.58 | M20: 35948.55 | N20: 36066.78 | O20: 38861.23 | P20: 38861.23 | Q20: 30937.17 | R20: 25281.73
A21: 1 | C21: 매입채무및기타채무 | E21: 4580.61 | F21: 4580.61 | G21: 5227.63 | H21: 5365.41 | I21: 2778.01 | J21: 2350.11 | K21: 2350.11 | L21: 3065.8 | M21: 4050.52 | N21: 4125.69 | O21: 4468.1 | P21: 4468.1 | Q21: 6934.79 | R21: 5812
A22: 1 | C22: 단기차입금 | E22: 2065.54 | F22: 2065.54 | G22: 2006.84 | H22: 2086.52 | I22: 1955.32 | J22: 7214.72 | K22: 7214.72 | L22: 16934.85 | M22: 19259.52 | N22: 19177.32 | O22: 20626.89 | P22: 20626.89 | Q22: 18216.01 | R22: 14644.52
A23: 1 | C23: 단기금융부채(face) | E23: 2065.54 | F23: 2065.54 | G23: 2006.84 | H23: 2086.52 | I23: 1955.32 | J23: 7214.72 | K23: 7214.72 | L23: 16934.85 | M23: 19259.52 | N23: 19177.32 | O23: 20626.89 | P23: 20626.89 | Q23: 18216.01 | R23: 14644.52
A24: 1 | C24: 유동리스부채 | E24: 187.92 | F24: 187.92 | G24: 193.6 | H24: 310.12 | I24: 365.58 | J24: 324.32 | K24: 324.32 | L24: 354.71 | M24: 315.54 | N24: 269.14 | O24: 219.24 | P24: 219.24 | Q24: 172.79 | R24: 190.22
A25: 1 | C25: 리스부채 | E25: 419.63 | F25: 419.63 | G25: 398.95 | H25: 640.97 | I25: 630.47 | J25: 523.96 | K25: 523.96 | L25: 544.45 | M25: 439.74 | N25: 329.08 | O25: 313.86 | P25: 313.86 | Q25: 290.03 | R25: 286.12
A26: 1 | C26: 단기금융부채 | E26: 187.92 | F26: 187.92 | G26: 193.6 | H26: 310.12 | I26: 365.58 | J26: 324.32 | K26: 324.32 | L26: 354.71 | M26: 315.54 | N26: 269.14 | O26: 219.24 | P26: 219.24 | Q26: 172.79 | R26: 190.22
A27: 1 | C27: 기타유동부채 | E27: 1435.04 | F27: 1435.04 | G27: 1313.86 | H27: 1950.67 | I27: 1693.53 | J27: 1861.5 | K27: 1861.5 | L27: 1501.28 | M27: 2264.3 | N27: 2020.78 | O27: 2642.06 | P27: 2642.06 | Q27: 2208.2 | R27: 4634.99
A28: 1 | C28: 비유동부채 | E28: 8953.75 | F28: 8953.75 | G28: 9152.81 | H28: 9711.63 | I28: 9354.11 | J28: 8290.39 | K28: 8290.39 | L28: 13245.79 | M28: 6386.94 | N28: 6496.14 | O28: 33385.96 | P28: 33385.96 | Q28: 33406.38 | R28: 35114.13
A29: 1 | C29: 장기차입금 | E29: 7130 | F29: 7130 | G29: 7170 | H29: 7210 | I29: 6810 | J29: 6200 | K29: 6200 | L29: 6200 | M29: 0 | N29: 0 | O29: 31760.11 | P29: 31760.11 | Q29: 31604.61 | R29: 33133.33
A30: 1 | C30: 확정급여부채 | E30: 1592.04 | F30: 1592.04 | G30: 1777.46 | H30: 2170.79 | I30: 2279.22 | J30: 1890.75 | K30: 1890.75 | L30: 2060.39 | M30: 2480.29 | N30: 2653.75 | O30: 1531.23 | P30: 1531.23 | Q30: 1684.52 | R30: 1884.9
A31: 1 | C31: 장기금융부채(face) | E31: 530 | F31: 530 | G31: 570 | H31: 610 | I31: 6810
A32: 1 | C32: 비유동리스부채 | E32: 231.71 | F32: 231.71 | G32: 205.35 | H32: 330.85 | I32: 264.89 | J32: 199.64 | K32: 199.64 | L32: 189.74 | M32: 124.2 | N32: 59.94 | O32: 94.62 | P32: 94.62 | Q32: 117.24 | R32: 95.9
A33: 1 | C33: 장기금융부채 | E33: 231.71 | F33: 231.71 | G33: 205.35 | H33: 330.85 | I33: 264.89 | J33: 199.64 | K33: 199.64 | L33: 4985.4 | M33: 3906.65 | N33: 3842.39 | O33: 94.62 | P33: 94.62 | Q33: 117.24 | R33: 95.9
A34: 1 | C34: 부채총계 | E34: 17222.86 | F34: 17222.86 | G34: 17894.74 | H34: 19424.35 | I34: 16146.55 | J34: 20041.05 | K34: 20041.05 | L34: 44762.38 | M34: 42335.5 | N34: 42562.93 | O34: 72247.2 | P34: 72247.2 | Q34: 64343.54 | R34: 60395.87
A35: 1 | C35: 자본금 | E35: 8501.25 | F35: 8501.25 | G35: 8501.25 | H35: 8501.25 | I35: 8501.25 | J35: 8568.3 | K35: 8568.3 | L35: 8626.12 | M35: 8632.88 | N35: 8637.07 | O35: 8637.07 | P35: 8637.07 | Q35: 9623.21 | R35: 9623.83
A36: 1 | C36: 자본잉여금 | E36: 27640.78 | F36: 27640.78 | G36: 27640.78 | H36: 27640.78 | I36: 27640.78 | J36: 28025.59 | K36: 28025.59 | L36: 28550.59 | M36: 28607.98 | O36: 28644.45 | P36: 28644.45 | Q36: 56100.24 | R36: 56104.48
A37: 1 | C37: 기타자본 | E37: 778.72 | F37: 778.72 | G37: 854.16 | H37: 1006.54 | I37: 1067.98 | J37: 395.69 | K37: 395.69 | L37: 118.57 | M37: 89.46 | N37: 104.21 | O37: 155.07 | P37: 155.07 | Q37: 184.49 | R37: 346.05
A38: 1 | C38: 이익잉여금 | E38: 17996.25 | F38: 17996.25 | G38: 19541.24 | H38: 20339.62 | I38: 20604.7 | J38: 21956.29 | K38: 21956.29 | L38: 23746.39 | M38: 27857.95 | N38: 30556.46 | O38: 30912.45 | P38: 30912.45 | Q38: 25786.73 | R38: 27817.88
A39: 1 | C39: 자본총계 | E39: 54917 | F39: 54917 | G39: 56537.43 | H39: 57488.2 | I39: 57814.71 | J39: 58945.87 | K39: 58945.87 | L39: 61041.67 | M39: 65188.26 | N39: 67942.19 | O39: 68349.04 | P39: 68349.04 | Q39: 91694.67 | R39: 93892.24
A40: 1 | C40: 부채와자본총계 | E40: 72139.86 | F40: 72139.86 | G40: 74432.17 | H40: 76912.55 | I40: 73961.26 | J40: 78986.92 | K40: 78986.92 | L40: 105804.05 | M40: 107523.76 | N40: 110505.12 | O40: 140596.24 | P40: 140596.24 | Q40: 156038.21 | R40: 154288.11
A41: 1 | C41: 지배주주지분 | E41: 54917 | F41: 54917 | G41: 56537.43 | H41: 57488.2 | I41: 57814.71 | J41: 58945.87 | K41: 58945.87 | L41: 61041.67 | M41: 65188.26 | N41: 67942.19 | O41: 68349.04 | P41: 68349.04 | Q41: 91694.67 | R41: 93892.24
A42: 1 | C42: 총차입금 | E42: 9195.54 | F42: 9195.54 | G42: 9176.84 | H42: 9296.52 | I42: 8765.32 | J42: 13414.72 | K42: 13414.72 | L42: 32794.8 | M42: 29318.2 | N42: 29651.17 | O42: 63291.96 | P42: 63291.96 | Q42: 53226.01 | R42: 47777.85
A43: 1 | C43: 순차입금 | E43: 1946.59 | F43: 1946.59 | G43: 1230.16 | H43: 1535.72 | I43: 2902.58 | J43: 4823.3 | K43: 4823.3 | L43: 25966.84 | M43: 13513.92 | N43: 23063.34 | O43: 41136.23 | P43: 41136.23 | Q43: 39162.32 | R43: 34251.96
A44: 1 | C44: 이자발생자산 | E44: 7326.25 | F44: 7326.25 | G44: 8037.98 | H44: 7974.78 | I44: 6081.14 | J44: 8811.26 | K44: 8811.26 | L44: 9961.89 | M44: 17877.79 | N44: 8649.49 | O44: 22393.23 | P44: 22393.23 | Q44: 14339.44 | R44: 13802.13
A45: 1 | C45: 단기금융자산 | G45: 1343.03 | M45: 12174.9 | N45: 3099.49 | O45: 10.04 | P45: 10.04 | Q45: 8050.19 | R45: 0
A46: 1 | C46: 기타비유동금융부채 | J46: 0 | K46: 0 | L46: 4795.66 | M46: 3782.45 | N46: 3782.45 | O46: 0 | P46: 0
A47: 1 | C47: 단기투자자산(공정가치) | L47: 17069.74
A48: 1 | C48: 유동성장기부채 | L48: 9659.95 | M48: 10058.68 | N48: 10473.85 | O48: 10904.96 | P48: 10904.96 | Q48: 3405.39 | R48: 0
A49: 1 | C49: 단기금융상품 | M49: 12174.9 | N49: 3099.49 | O49: 10.04 | P49: 10.04 | Q49: 8050.19 | R49: 0
A50: 1 | C50: 매출액(수익) | E50: 11270.8 | G50: 11873.71 | H50: 13130.46 | I50: 11200.18 | J50: 12336.77 | K50: 48541.12 | L50: 13111.39 | M50: 15498.77 | N50: 16195.88 | O50: 18410.24 | P50: 63216.28 | Q50: 22381.26 | R50: 23644.82
A51: 1 | C51: 매출원가 | E51: 9838.02 | G51: 9464.28 | H51: 10214.82 | I51: 9128.96 | J51: 9995.53 | K51: 38803.59 | L51: 10289.72 | M51: 11695.23 | N51: 12179.11 | O51: 14175.07 | P51: 48339.13 | Q51: 14568.57 | R51: 15914.41
A52: 1 | C52: 매출총이익 | E52: 1432.77 | G52: 2409.43 | H52: 2915.64 | I52: 2071.23 | J52: 2341.24 | K52: 9737.54 | L52: 2821.67 | M52: 3803.54 | N52: 4016.76 | O52: 4235.18 | P52: 14877.15 | Q52: 7812.69 | R52: 7730.4
A53: 1 | C53: 판관비 | E53: 982.26 | G53: 1034.76 | H53: 1167.96 | I53: 1282.32 | J53: 1329.56 | K53: 4814.6 | L53: 1139.78 | M53: 1150.52 | N53: 1424.24 | O53: 1412.67 | P53: 5127.21 | Q53: 1607.41 | R53: 2127.33
A54: 1 | C54: 영업이익 | E54: 450.51 | G54: 1374.67 | H54: 1747.68 | I54: 788.9 | J54: 1011.68 | K54: 4922.93 | L54: 1681.89 | M54: 2653.02 | N54: 2592.52 | O54: 2822.51 | P54: 9749.94 | Q54: 6205.28 | R54: 5603.07
A55: 1 | C55: 금융수익 | E55: 102.75 | G55: 177.87 | H55: 206.48 | I55: 25.29 | J55: 311.14 | K55: 720.78 | L55: 192.62 | M55: 4699.21 | N55: 185.75 | O55: -2736.79 | P55: 2340.79 | Q55: 6476.05 | R55: 13543.1
A56: 1 | C56: 기타영업외수익 | E56: 47.8 | G56: 128.07 | H56: 24 | I56: 19.86 | J56: 37.82 | K56: 209.75 | L56: 17.87 | M56: 25.36 | N56: 23.51 | O56: 22.06 | P56: 88.8 | Q56: 46.85 | R56: 35.72
A57: 1 | C57: 금융비용 | E57: 472.29 | G57: 117.12 | H57: 146.65 | I57: 280.64 | J57: -76.54 | K57: 467.87 | L57: 99.03 | M57: 1463.05 | N57: 102.96 | O57: -371.63 | P57: 1293.41 | Q57: 18028.06 | R57: 14316.47
A58: 1 | C58: 기타영업외비용 | E58: -7.7 | G58: 18.5 | H58: 0.28 | I58: 288.33 | J58: 18.89 | K58: 326 | L58: 3.26 | M58: -0.13 | N58: 0.32 | O58: 242.97 | P58: 246.42 | Q58: 0.15 | R58: 41.93
A59: 1 | C59: 법인세비용차감전계속사업이익 | E59: 136.47 | G59: 1544.99 | H59: 1831.23 | I59: 265.08 | J59: 1418.28 | K59: 5059.58 | L59: 1790.09 | M59: 5914.66 | N59: 2698.51 | O59: 236.44 | P59: 10639.7 | Q59: -5300.02 | R59: 4823.5
A60: 1 | C60: 법인세비용 | E60: -236.78 | G60: 0 | H60: 830.18 | I60: 0 | J60: 71.48 | K60: 901.66 | L60: 0 | M60: 1593.68 | N60: 0 | O60: 110.58 | P60: 1704.26 | Q60: -174.3 | R60: 2792.35
A61: 1 | C61: 당기순이익 | E61: 373.25 | G61: 1544.99 | H61: 1001.06 | I61: 265.08 | J61: 1346.81 | K61: 4157.94 | L61: 1790.09 | M61: 4320.98 | N61: 2698.51 | O61: 125.87 | P61: 8935.45 | Q61: -5125.72 | R61: 2031.15
... A67: 1 | C67: 이자수익 | E67: 99.22 | G67: 53.26 | H67: 55.73 | I67: 58.56 | J67: 65.69 | K67: 233.24 | L67: 56.65 | M67: 70.64 | N67: -57.28 | O67: 110.02 | P67: 180.03 | Q67: 41.58 | R67: 134.32
A68: 1 | C68: 이자비용 | E68: 373.78 | G68: 92.09 | H68: 91.88 | I68: 85.83 | J68: -7.74 | K68: 262.06 | L68: 39.6 | M68: 59.97 | N68: -99.57 | R68: 285.81
A69: 1 | C69: 외환차익 | E69: 67.6 | G69: 68.6 | H69: 101.73 | I69: 12.15 | J69: 136.12 | K69: 318.6 | L69: 19.11 | M69: 8.58 | N69: 172.83 | O69: 250.71 | P69: 451.23 | Q69: 196.88 | R69: 281.84
A70: 1 | C70: 외환차손 | E70: 70.06 | G70: 25.03 | H70: 29.17 | I70: 80.09 | J70: 46.06 | K70: 180.35 | L70: 59.42 | M70: 211.8 | N70: 85.58 | O70: 20.05 | P70: 376.85 | Q70: 61.3 | R70: 60.34
A71: 1 | C71: 외화환산이익 | E71: -64.07 | G71: 56.01 | H71: 49.01 | I71: -45.41 | J71: 109.34 | K71: 168.95 | L71: 47.13 | M71: -42.3 | N71: 70.2 | O71: -58.16 | P71: 16.87 | Q71: 298.74 | R71: -54.94
A72: 1 | C72: 외화환산손실 | E72: 28.45 | H72: 0.16 | I72: 114.71 | L72: 0.01 | M72: 127.45 | N72: 0.07 | O72: 106.94 | P72: 234.47 | R72: 0.03
A73: 1 | C73: 이자손익 | E73: -274.56 | G73: -38.83 | H73: -36.15 | I73: -27.27 | J73: 73.43 | K73: -28.82 | L73: 17.05 | M73: 10.67 | N73: 42.29 | R73: -151.49
A74: 1 | C74: 파생상품이익 | M74: 4557.25 | N74: 0 | O74: -2981.47 | Q74: 5889.45 | R74: 13231.27
A75: 1 | C75: 파생상품손실 | M75: 1063.84 | N75: 116.88 | O75: -498.62 | Q75: 17966.75 | R75: 12408.05
A76: 1 | C76: 영업활동으로인한현금흐름 | E76: 5371.93 | G76: 880.76 | H76: 509.35 | I76: -968.68 | J76: 1781.89 | K76: 2203.32 | L76: 1109.51 | M76: 281.19 | N76: 129.69 | O76: -92.4 | P76: 1427.99 | Q76: 1025.69 | R76: 4395.66
A77: 1 | C77: 감가상각비 | E77: 586.9 | G77: 565.94 | H77: 568.19 | I77: 585.04 | J77: 580.98 | K77: 2300.15 | L77: 566.04 | M77: 560.7 | N77: 547.75 | O77: 538.68 | P77: 2213.17 | Q77: 540.23 | R77: 697.71
A78: 1 | C78: 무형자산상각비 | E78: 4.56 | G78: 4.07 | H78: 4.03 | I78: 4.93 | J78: 5.82 | K78: 18.85 | L78: 4.93 | M78: 5.3 | N78: 5.31 | O78: 5.31 | P78: 20.85 | Q78: 5.5 | R78: 5.69
A79: 1 | C79: 이자수취(CF) | E79: 95.42 | G79: 46.91 | H79: 49.16 | I79: 51.42 | J79: 58.89 | K79: 206.38 | L79: 50.12 | M79: 64.46 | N79: 222.18 | O79: 106.43 | P79: 443.19 | Q79: 36.58 | R79: 130.25
A80: 1 | C80: 이자지급(CF) | E80: -499.54 | G80: -92.33 | H80: -93.42 | I80: -90.18 | J80: -197.56 | K80: -473.49 | L80: -485.67 | M80: 245.45 | N80: -114.92 | O80: -192.39 | P80: -547.53 | Q80: -217.77 | R80: -255.56
A81: 1 | C81: 법인세납부(CF) | E81: -14.73 | G81: 0 | H81: -317.07 | I81: -329.42 | J81: -14.5 | K81: -660.99 | L81: -253.62 | M81: -346.16 | N81: -386.64 | O81: -44.91 | P81: -1031.33 | Q81: -190.36 | R81: -557.89
A82: 1 | C82: 투자활동으로인한현금흐름 | E82: -5206.49 | G82: -1451.33 | H82: 687.5 | I82: -370.6 | J82: -3684.39 | K82: -4818.82 | L82: -24055.79 | M82: -2991.95 | N82: -164.82 | O82: -7494.85 | P82: -34707.41 | Q82: -17413.94 | R82: 1753.85
A83: 1 | C83: 유형자산의감소 | E83: 0 | G83: 0 | H83: 1.18 | I83: 0 | J83: 57 | K83: 58.18 | L83: 1.2 | M83: 0 | N83: 0 | O83: 0 | P83: 1.2 | Q83: 0 | R83: 0
A84: 1 | C84: 유형자산의증가 | E84: 5288.06 | G84: 166.07 | H84: 546.22 | I84: 408 | J84: 3760.97 | K84: 4881.26 | L84: 6886.75 | M84: 7420.45 | N84: 9209.44 | O84: 10569.73 | P84: 34086.37 | Q84: 9361.98 | R84: 6186.32
A85: 1 | C85: CAPEX | E85: 5288.06 | G85: 166.07 | H85: 546.22 | I85: 426 | J85: 3799.79 | K85: 4938.08 | L85: 6909.75 | M85: 8131.96 | N85: 9209.44 | O85: 10569.73 | P85: 34820.88 | Q85: 9365.69 | R85: 6190.69
A86: 1 | C86: 무형자산의증가 | E86: 0 | G86: 0 | H86: 0 | I86: 18 | J86: 38.82 | K86: 56.82 | L86: 23 | M86: 711.51 | N86: 0 | O86: 0 | P86: 734.51 | Q86: 3.71 | R86: 4.37
A87: 1 | C87: 재무활동으로인한현금흐름 | E87: 4453.73 | G87: -74.88 | H87: -39.55 | I87: -556.5 | J87: 4628.89 | K87: 3957.96 | L87: 21182.82 | M87: -487.81 | N87: -106.68 | O87: 26282.58 | P87: 46870.91 | Q87: 223.78 | R87: 1381.74
A88: 1 | C88: 차입금의증가 | E88: 2600 | G88: 0 | H88: 0 | I88: 0 | J88: 6000 | K88: 6000 | Q88: 0 | R88: 8425.22
A89: 1 | C89: 차입금의감소 | E89: 27600 | I89: 450 | J89: 1400 | N89: 50 | O89: 10800 | Q89: 0 | R89: 166.67
A90: 1 | C90: 리스부채의상환 | E90: 106.41 | G90: 89.68 | H90: 79.55 | I90: 106.5 | J90: 106.51 | K90: 382.24 | L90: 105.84 | M90: 104.71 | N90: 95.1 | O90: 89.92 | P90: 395.57 | Q90: 92.18 | R90: 67.96
A91: 1 | C91: 현금및현금성자산의증감 | E91: 4619.16 | G91: -645.45 | H91: 1157.3 | I91: -1895.78 | J91: 2726.39 | K91: 1342.46 | L91: -1763.46 | M91: -3198.58 | N91: -141.8 | O91: 18695.33 | P91: 13591.49 | Q91: -16164.47
A92: 1 | C92: 기말현금및현금성자산 | E92: 4618.93 | G92: 6603.65 | H92: 1157.15 | I92: -1898.06 | J92: 2728.68 | K92: 8591.42 | L92: 6827.96 | M92: -3198.58 | N92: -141.04 | O92: 18657.35 | P92: 22145.69 | Q92: 6013.5 | R92: 7512.39

Sheet subQ
A1: YQ | C1: subQ 분기 서브모델(억원, U=100) | E1: 4Q23 | F1: 2023 | G1: 1Q24 | H1: 2Q24 | I1: 3Q24 | J1: 4Q24 | K1: 2024 | L1: 1Q25 | M1: 2Q25 | N1: 3Q25 | O1: 4Q25 | P1: 2025 | Q1: 1Q26 | R1: 2Q26 | S1: 3Q26 | T1: 4Q26 | U1: 2026 | V1: 1Q27 | W1: 2Q27 | X1: 3Q27 | Y1: 4Q27 | Z1: 2027 | AA1: 1Q28 | AB1: 2Q28 | AC1: 3Q28 | AD1: 4Q28 | AE1: 2028
A2: A=이름(key) B=그룹 C=단위 D=FnGuide 계정명(VLOOKUP 키). 확정=VLOOKUP(BS), 추정=변수 가정 참조
E3: 1 | F3: 2 | G3: 3 | H3: 4 | I3: 5 | J3: 6 | K3: 7 | L3: 8 | M3: 9 | N3: 10 | O3: 11 | P3: 12 | Q3: 13 | R3: 14 | S3: 15 | T3: 16 | U3: 17 | V3: 18 | W3: 19 | X3: 20 | Y3: 21 | Z3: 22 | AA3: 23 | AB3: 24 | AC3: 25 | AD3: 26 | AE3: 27
E4: 2023.12 | F4: 2023.12A | G4: 2024.03 | H4: 2024.06 | I4: 2024.09 | J4: 2024.12 | K4: 2024.12A | L4: 2025.03 | M4: 2025.06 | N4: 2025.09 | O4: 2025.12 | P4: 2025.12A | Q4: 2026.03 | R4: 2026.06 | S4: 2026.09 | T4: 2026.12 | U4: 2026.12A | V4: 2027.03 | W4: 2027.06 | X4: 2027.09 | Y4: 2027.12 | Z4: 2027.12A | AA4: 2028.03 | AB4: 2028.06 | AC4: 2028.09 | AD4: 2028.12 | AE4: 2028.12A
A5: 매출액 | B5: 손익 | C5: 억원 | D5: 매출액(수익) | E5: =IFERROR(VLOOKUP($D5,BS별도,MATCH(E$1,BS별도H,0),0)/100,"") | G5: =IFERROR(VLOOKUP($D5,BS별도,MATCH(G$1,BS별도H,0),0)/100,"") | H5: =IFERROR(VLOOKUP($D5,BS별도,MATCH(H$1,BS별도H,0),0)/100,"") | I5: =IFERROR(VLOOKUP($D5,BS별도,MATCH(I$1,BS별도H,0),0)/100,"") | J5: =IFERROR(VLOOKUP($D5,BS별도,MATCH(J$1,BS별도H,0),0)/100,"") | K5: =SUM(G5:J5) | L5: =IFERROR(VLOOKUP($D5,BS별도,MATCH(L$1,BS별도H,0),0)/100,"") | M5: =IFERROR(VLOOKUP($D5,BS별도,MATCH(M$1,BS별도H,0),0)/100,"") | N5: =IFERROR(VLOOKUP($D5,BS별도,MATCH(N$1,BS별도H,0),0)/100,"") | O5: =IFERROR(VLOOKUP($D5,BS별도,MATCH(O$1,BS별도H,0),0)/100,"") | P5: =SUM(L5:O5) | Q5: =IFERROR(VLOOKUP($D5,BS별도,MATCH(Q$1,BS별도H,0),0)/100,"") | R5: =IFERROR(VLOOKUP($D5,BS별도,MATCH(R$1,BS별도H,0),0)/100,"") | S5: =IFERROR(N5*(1+변수!S21),"") | T5: =IFERROR(O5*(1+변수!T21),"") | U5: =SUM(Q5:T5) | V5: =IFERROR(Q5*(1+변수!V21),"") | W5: =IFERROR(R5*(1+변수!W21),"") | X5: =IFERROR(S5*(1+변수!X21),"") | Y5: =IFERROR(T5*(1+변수!Y21),"") | Z5: =SUM(V5:Y5) | AA5: =IFERROR(V5*(1+변수!AA21),"") | AB5: =IFERROR(W5*(1+변수!AB21),"") | AC5: =IFERROR(X5*(1+변수!AC21),"") | AD5: =IFERROR(Y5*(1+변수!AD21),"") | AE5: =SUM(AA5:AD5)
A6: 매출원가 | B6: 손익 | C6: 억원 | D6: 매출원가 | E6: =IFERROR(VLOOKUP($D6,BS별도,MATCH(E$1,BS별도H,0),0)/100,"") | G6: =IFERROR(VLOOKUP($D6,BS별도,MATCH(G$1,BS별도H,0),0)/100,"") | H6: =IFERROR(VLOOKUP($D6,BS별도,MATCH(H$1,BS별도H,0),0)/100,"") | I6: =IFERROR(VLOOKUP($D6,BS별도,MATCH(I$1,BS별도H,0),0)/100,"") | J6: =IFERROR(VLOOKUP($D6,BS별도,MATCH(J$1,BS별도H,0),0)/100,"") | K6: =SUM(G6:J6) | L6: =IFERROR(VLOOKUP($D6,BS별도,MATCH(L$1,BS별도H,0),0)/100,"") | M6: =IFERROR(VLOOKUP($D6,BS별도,MATCH(M$1,BS별도H,0),0)/100,"") | N6: =IFERROR(VLOOKUP($D6,BS별도,MATCH(N$1,BS별도H,0),0)/100,"") | O6: =IFERROR(VLOOKUP($D6,BS별도,MATCH(O$1,BS별도H,0),0)/100,"") | P6: =SUM(L6:O6) | Q6: =IFERROR(VLOOKUP($D6,BS별도,MATCH(Q$1,BS별도H,0),0)/100,"") | R6: =IFERROR(VLOOKUP($D6,BS별도,MATCH(R$1,BS별도H,0),0)/100,"") | S6: =IFERROR(S5-S7,"") | T6: =IFERROR(T5-T7,"") | U6: =SUM(Q6:T6) | V6: =IFERROR(V5-V7,"") | W6: =IFERROR(W5-W7,"") | X6: =IFERROR(X5-X7,"") | Y6: =IFERROR(Y5-Y7,"") | Z6: =SUM(V6:Y6) | AA6: =IFERROR(AA5-AA7,"") | AB6: =IFERROR(AB5-AB7,"") | AC6: =IFERROR(AC5-AC7,"") | AD6: =IFERROR(AD5-AD7,"") | AE6: =SUM(AA6:AD6)
A7: 매출총이익 | B7: 손익 | C7: 억원 | D7: 매출총이익 | E7: =IFERROR(VLOOKUP($D7,BS별도,MATCH(E$1,BS별도H,0),0)/100,"") | G7: =IFERROR(VLOOKUP($D7,BS별도,MATCH(G$1,BS별도H,0),0)/100,"") | H7: =IFERROR(VLOOKUP($D7,BS별도,MATCH(H$1,BS별도H,0),0)/100,"") | I7: =IFERROR(VLOOKUP($D7,BS별도,MATCH(I$1,BS별도H,0),0)/100,"") | J7: =IFERROR(VLOOKUP($D7,BS별도,MATCH(J$1,BS별도H,0),0)/100,"") | K7: =SUM(G7:J7) | L7: =IFERROR(VLOOKUP($D7,BS별도,MATCH(L$1,BS별도H,0),0)/100,"") | M7: =IFERROR(VLOOKUP($D7,BS별도,MATCH(M$1,BS별도H,0),0)/100,"") | N7: =IFERROR(VLOOKUP($D7,BS별도,MATCH(N$1,BS별도H,0),0)/100,"") | O7: =IFERROR(VLOOKUP($D7,BS별도,MATCH(O$1,BS별도H,0),0)/100,"") | P7: =SUM(L7:O7) | Q7: =IFERROR(VLOOKUP($D7,BS별도,MATCH(Q$1,BS별도H,0),0)/100,"") | R7: =IFERROR(VLOOKUP($D7,BS별도,MATCH(R$1,BS별도H,0),0)/100,"") | S7: =IFERROR(S9+S8,"") | T7: =IFERROR(T9+T8,"") | U7: =SUM(Q7:T7) | V7: =IFERROR(V9+V8,"") | W7: =IFERROR(W9+W8,"") | X7: =IFERROR(X9+X8,"") | Y7: =IFERROR(Y9+Y8,"") | Z7: =SUM(V7:Y7) | AA7: =IFERROR(AA9+AA8,"") | AB7: =IFERROR(AB9+AB8,"") | AC7: =IFERROR(AC9+AC8,"") | AD7: =IFERROR(AD9+AD8,"") | AE7: =SUM(AA7:AD7)
A8: 판관비 | B8: 손익 | C8: 억원 | D8: 판관비 | E8: =IFERROR(VLOOKUP($D8,BS별도,MATCH(E$1,BS별도H,0),0)/100,"") | G8: =IFERROR(VLOOKUP($D8,BS별도,MATCH(G$1,BS별도H,0),0)/100,"") | H8: =IFERROR(VLOOKUP($D8,BS별도,MATCH(H$1,BS별도H,0),0)/100,"") | I8: =IFERROR(VLOOKUP($D8,BS별도,MATCH(I$1,BS별도H,0),0)/100,"") | J8: =IFERROR(VLOOKUP($D8,BS별도,MATCH(J$1,BS별도H,0),0)/100,"") | K8: =SUM(G8:J8) | L8: =IFERROR(VLOOKUP($D8,BS별도,MATCH(L$1,BS별도H,0),0)/100,"") | M8: =IFERROR(VLOOKUP($D8,BS별도,MATCH(M$1,BS별도H,0),0)/100,"") | N8: =IFERROR(VLOOKUP($D8,BS별도,MATCH(N$1,BS별도H,0),0)/100,"") | O8: =IFERROR(VLOOKUP($D8,BS별도,MATCH(O$1,BS별도H,0),0)/100,"") | P8: =SUM(L8:O8) | Q8: =IFERROR(VLOOKUP($D8,BS별도,MATCH(Q$1,BS별도H,0),0)/100,"") | R8: =IFERROR(VLOOKUP($D8,BS별도,MATCH(R$1,BS별도H,0),0)/100,"") | S8: =IFERROR(S5*변수!S22,"") | T8: =IFERROR(T5*변수!T22,"") | U8: =SUM(Q8:T8) | V8: =IFERROR(V5*변수!V22,"") | W8: =IFERROR(W5*변수!W22,"") | X8: =IFERROR(X5*변수!X22,"") | Y8: =IFERROR(Y5*변수!Y22,"") | Z8: =SUM(V8:Y8) | AA8: =IFERROR(AA5*변수!AA22,"") | AB8: =IFERROR(AB5*변수!AB22,"") | AC8: =IFERROR(AC5*변수!AC22,"") | AD8: =IFERROR(AD5*변수!AD22,"") | AE8: =SUM(AA8:AD8)
A9: 영업이익 | B9: 손익 | C9: 억원 | D9: 영업이익 | E9: =IFERROR(VLOOKUP($D9,BS별도,MATCH(E$1,BS별도H,0),0)/100,"") | G9: =IFERROR(VLOOKUP($D9,BS별도,MATCH(G$1,BS별도H,0),0)/100,"") | H9: =IFERROR(VLOOKUP($D9,BS별도,MATCH(H$1,BS별도H,0),0)/100,"") | I9: =IFERROR(VLOOKUP($D9,BS별도,MATCH(I$1,BS별도H,0),0)/100,"") | J9: =IFERROR(VLOOKUP($D9,BS별도,MATCH(J$1,BS별도H,0),0)/100,"") | K9: =SUM(G9:J9) | L9: =IFERROR(VLOOKUP($D9,BS별도,MATCH(L$1,BS별도H,0),0)/100,"") | M9: =IFERROR(VLOOKUP($D9,BS별도,MATCH(M$1,BS별도H,0),0)/100,"") | N9: =IFERROR(VLOOKUP($D9,BS별도,MATCH(N$1,BS별도H,0),0)/100,"") | O9: =IFERROR(VLOOKUP($D9,BS별도,MATCH(O$1,BS별도H,0),0)/100,"") | P9: =SUM(L9:O9) | Q9: =IFERROR(VLOOKUP($D9,BS별도,MATCH(Q$1,BS별도H,0),0)/100,"") | R9: =IFERROR(VLOOKUP($D9,BS별도,MATCH(R$1,BS별도H,0),0)/100,"") | S9: =IFERROR(S5*변수!S23,"") | T9: =IFERROR(T5*변수!T23,"") | U9: =SUM(Q9:T9) | V9: =IFERROR(V5*변수!V23,"") | W9: =IFERROR(W5*변수!W23,"") | X9: =IFERROR(X5*변수!X23,"") | Y9: =IFERROR(Y5*변수!Y23,"") | Z9: =SUM(V9:Y9) | AA9: =IFERROR(AA5*변수!AA23,"") | AB9: =IFERROR(AB5*변수!AB23,"") | AC9: =IFERROR(AC5*변수!AC23,"") | AD9: =IFERROR(AD5*변수!AD23,"") | AE9: =SUM(AA9:AD9)
A10: OPM | B10: 손익 | C10: % | D10: 영업이익률 | E10: =IFERROR(E9/E5,"") | G10: =IFERROR(G9/G5,"") | H10: =IFERROR(H9/H5,"") | I10: =IFERROR(I9/I5,"") | J10: =IFERROR(J9/J5,"") | K10: =IFERROR(K9/K5,"") | L10: =IFERROR(L9/L5,"") | M10: =IFERROR(M9/M5,"") | N10: =IFERROR(N9/N5,"") | ... AE10: =IFERROR(AE9/AE5,"")
A11: 금융손익 | B11: 손익 | C11: 억원 | D11: 금융손익 | E11: =IFERROR(VLOOKUP($D11,BS별도,MATCH(E$1,BS별도H,0),0)/100,"") | G11: =IFERROR(VLOOKUP($D11,BS별도,MATCH(G$1,BS별도H,0),0)/100,"") | H11: =IFERROR(VLOOKUP($D11,BS별도,MATCH(H$1,BS별도H,0),0)/100,"") | I11: =IFERROR(VLOOKUP($D11,BS별도,MATCH(I$1,BS별도H,0),0)/100,"") | J11: =IFERROR(VLOOKUP($D11,BS별도,MATCH(J$1,BS별도H,0),0)/100,"") | K11: =SUM(G11:J11) | L11: =IFERROR(VLOOKUP($D11,BS별도,MATCH(L$1,BS별도H,0),0)/100,"") | M11: =IFERROR(VLOOKUP($D11,BS별도,MATCH(M$1,BS별도H,0),0)/100,"") | N11: =IFERROR(VLOOKUP($D11,BS별도,MATCH(N$1,BS별도H,0),0)/100,"") | O11: =IFERROR(VLOOKUP($D11,BS별도,MATCH(O$1,BS별도H,0),0)/100,"") | P11: =SUM(L11:O11) | Q11: =IFERROR(VLOOKUP($D11,BS별도,MATCH(Q$1,BS별도H,0),0)/100,"") | R11: =IFERROR(VLOOKUP($D11,BS별도,MATCH(R$1,BS별도H,0),0)/100,"") | S11: =IFERROR(S12+S13+S14+S15,"") | T11: =IFERROR(T12+T13+T14+T15,"") | U11: =SUM(Q11:T11) | V11: =IFERROR(V12+V13+V14+V15,"") | W11: =IFERROR(W12+W13+W14+W15,"") | X11: =IFERROR(X12+X13+X14+X15,"") | Y11: =IFERROR(Y12+Y13+Y14+Y15,"") | Z11: =SUM(V11:Y11) | AA11: =IFERROR(AA12+AA13+AA14+AA15,"") | AB11: =IFERROR(AB12+AB13+AB14+AB15,"") | AC11: =IFERROR(AC12+AC13+AC14+AC15,"") | AD11: =IFERROR(AD12+AD13+AD14+AD15,"") | AE11: =SUM(AA11:AD11)
A12: 이자손익 | B12: 손익 | C12: 억원 | D12: 이자손익 | E12: =IFERROR(VLOOKUP($D12,BS별도,MATCH(E$1,BS별도H,0),0)/100,"") | G12: =IFERROR(VLOOKUP($D12,BS별도,MATCH(G$1,BS별도H,0),0)/100,"") | H12: =IFERROR(VLOOKUP($D12,BS별도,MATCH(H$1,BS별도H,0),0)/100,"") | I12: =IFERROR(VLOOKUP($D12,BS별도,MATCH(I$1,BS별도H,0),0)/100,"") | J12: =IFERROR(VLOOKUP($D12,BS별도,MATCH(J$1,BS별도H,0),0)/100,"") | K12: =SUM(G12:J12) | L12: =IFERROR(VLOOKUP($D12,BS별도,MATCH(L$1,BS별도H,0),0)/100,"") | M12: =IFERROR(VLOOKUP($D12,BS별도,MATCH(M$1,BS별도H,0),0)/100,"") | N12: =IFERROR(VLOOKUP($D12,BS별도,MATCH(N$1,BS별도H,0),0)/100,"") | P12: =SUM(L12:O12) | R12: =IFERROR(VLOOKUP($D12,BS별도,MATCH(R$1,BS별도H,0),0)/100,"") | S12: =IFERROR((R29*변수!$D$54-R27*변수!$D$55)/4,"") | T12: =IFERROR((S29*변수!$D$54-S27*변수!$D$55)/4,"") | U12: =SUM(Q12:T12) | V12: =IFERROR((T29*변수!$D$54-T27*변수!$D$55)/4,"") | W12: =IFERROR((V29*변수!$D$54-V27*변수!$D$55)/4,"") | X12: =IFERROR((W29*변수!$D$54-W27*변수!$D$55)/4,"") | Y12: =IFERROR((X29*변수!$D$54-X27*변수!$D$55)/4,"") | Z12: =SUM(V12:Y12) | AA12: =IFERROR((Y29*변수!$D$54-Y27*변수!$D$55)/4,"") | AB12: =IFERROR((AA29*변수!$D$54-AA27*변수!$D$55)/4,"") | AC12: =IFERROR((AB29*변수!$D$54-AB27*변수!$D$55)/4,"") | AD12: =IFERROR((AC29*변수!$D$54-AC27*변수!$D$55)/4,"") | AE12: =SUM(AA12:AD12)
A13: 외환손익 | B13: 손익 | C13: 억원 | D13: 외환손익(실적만; 추정 환효과는 환관련손익) | E13: =IFERROR((VLOOKUP("외환차익",BS별도,MATCH(E$1,BS별도H,0),0)-VLOOKUP("외환차손",BS별도,MATCH(E$1,BS별도H,0),0)+VLOOKUP("외화환산이익",BS별도,MATCH(E$1,BS별도H,0),0)-VLOOKUP("외화환산손실",BS별도,MATCH(E$1,BS별도H,0),0))/100,"") | H13: =IFERROR((VLOOKUP("외환차익",BS별도,MATCH(H$1,BS별도H,0),0)-VLOOKUP("외환차손",BS별도,MATCH(H$1,BS별도H,0),0)+VLOOKUP("외화환산이익",BS별도,MATCH(H$1,BS별도H,0),0)-VLOOKUP("외화환산손실",BS별도,MATCH(H$1,BS별도H,0),0))/100,"") | I13: =IFERROR((VLOOKUP("외환차익",BS별도,MATCH(I$1,BS별도H,0),0)-VLOOKUP("외환차손",BS별도,MATCH(I$1,BS별도H,0),0)+VLOOKUP("외화환산이익",BS별도,MATCH(I$1,BS별도H,0),0)-VLOOKUP("외화환산손실",BS별도,MATCH(I$1,BS별도H,0),0))/100,"") | K13: =SUM(G13:J13) | L13: =IFERROR((VLOOKUP("외환차익",BS별도,MATCH(L$1,BS별도H,0),0)-VLOOKUP("외환차손",BS별도,MATCH(L$1,BS별도H,0),0)+VLOOKUP("외화환산이익",BS별도,MATCH(L$1,BS별도H,0),0)-VLOOKUP("외화환산손실",BS별도,MATCH(L$1,BS별도H,0),0))/100,"") | M13: =IFERROR((VLOOKUP("외환차익",BS별도,MATCH(M$1,BS별도H,0),0)-VLOOKUP("외환차손",BS별도,MATCH(M$1,BS별도H,0),0)+VLOOKUP("외화환산이익",BS별도,MATCH(M$1,BS별도H,0),0)-VLOOKUP("외화환산손실",BS별도,MATCH(M$1,BS별도H,0),0))/100,"") | N13: =IFERROR((VLOOKUP("외환차익",BS별도,MATCH(N$1,BS별도H,0),0)-VLOOKUP("외환차손",BS별도,MATCH(N$1,BS별도H,0),0)+VLOOKUP("외화환산이익",BS별도,MATCH(N$1,BS별도H,0),0)-VLOOKUP("외화환산손실",BS별도,MATCH(N$1,BS별도H,0),0))/100,"") | O13: =IFERROR((VLOOKUP("외환차익",BS별도,MATCH(O$1,BS별도H,0),0)-VLOOKUP("외환차손",BS별도,MATCH(O$1,BS별도H,0),0)+VLOOKUP("외화환산이익",BS별도,MATCH(O$1,BS별도H,0),0)-VLOOKUP("외화환산손실",BS별도,MATCH(O$1,BS별도H,0),0))/100,"") | P13: =SUM(L13:O13) | R13: =IFERROR((VLOOKUP("외환차익",BS별도,MATCH(R$1,BS별도H,0),0)-VLOOKUP("외환차손",BS별도,MATCH(R$1,BS별도H,0),0)+VLOOKUP("외화환산이익",BS별도,MATCH(R$1,BS별도H,0),0)-VLOOKUP("외화환산손실",BS별도,MATCH(R$1,BS별도H,0),0))/100,"") | S13: =변수!S24 | T13: =변수!T24 | U13: =SUM(Q13:T13) | V13: =변수!V24 | W13: =변수!W24 | X13: =변수!X24 | Y13: =변수!Y24 | Z13: =SUM(V13:Y13) | AA13: =변수!AA24 | AB13: =변수!AB24 | AC13: =변수!AC24 | AD13: =변수!AD24 | AE13: =SUM(AA13:AD13)
A14: 파생상품손익 | B14: 손익 | C14: 억원 | D14: 파생상품손익 | K14: =SUM(G14:J14) | M14: =IFERROR((VLOOKUP("파생상품이익",BS별도,MATCH(M$1,BS별도H,0),0)-VLOOKUP("파생상품손실",BS별도,MATCH(M$1,BS별도H,0),0))/100,"") | N14: =IFERROR((VLOOKUP("파생상품이익",BS별도,MATCH(N$1,BS별도H,0),0)-VLOOKUP("파생상품손실",BS별도,MATCH(N$1,BS별도H,0),0))/100,"") | O14: =IFERROR((VLOOKUP("파생상품이익",BS별도,MATCH(O$1,BS별도H,0),0)-VLOOKUP("파생상품손실",BS별도,MATCH(O$1,BS별도H,0),0))/100,"") | P14: =SUM(L14:O14) | Q14: =IFERROR((VLOOKUP("파생상품이익",BS별도,MATCH(Q$1,BS별도H,0),0)-VLOOKUP("파생상품손실",BS별도,MATCH(Q$1,BS별도H,0),0))/100,"") | R14: =IFERROR((VLOOKUP("파생상품이익",BS별도,MATCH(R$1,BS별도H,0),0)-VLOOKUP("파생상품손실",BS별도,MATCH(R$1,BS별도H,0),0))/100,"") | S14: =변수!S25 | T14: =변수!T25 | U14: =SUM(Q14:T14) | V14: =변수!V25 | W14: =변수!W25 | X14: =변수!X25 | Y14: =변수!Y25 | Z14: =SUM(V14:Y14) | AA14: =변수!AA25 | AB14: =변수!AB25 | AC14: =변수!AC25 | AD14: =변수!AD25 | AE14: =SUM(AA14:AD14)
A15: 기타금융손익 | B15: 손익 | C15: 억원 | D15: 기타금융손익(금융손익 잔차) | K15: =SUM(G15:J15) | M15: =IFERROR(M11-M12-M13-M14,"") | N15: =IFERROR(N11-N12-N13-N14,"") | P15: =SUM(L15:O15) | R15: =IFERROR(R11-R12-R13-R14,"") | S15: =변수!S26 | T15: =변수!T26 | U15: =SUM(Q15:T15) | V15: =변수!V26 | W15: =변수!W26 | X15: =변수!X26 | Y15: =변수!Y26 | Z15: =SUM(V15:Y15) | AA15: =변수!AA26 | AB15: =변수!AB26 | AC15: =변수!AC26 | AD15: =변수!AD26 | AE15: =SUM(AA15:AD15)
A16: 기타영업외손익 | B16: 손익 | C16: 억원 | D16: 기타영업외손익 | E16: =IFERROR(VLOOKUP($D16,BS별도,MATCH(E$1,BS별도H,0),0)/100,"") | G16: =IFERROR(VLOOKUP($D16,BS별도,MATCH(G$1,BS별도H,0),0)/100,"") | H16: =IFERROR(VLOOKUP($D16,BS별도,MATCH(H$1,BS별도H,0),0)/100,"") | I16: =IFERROR(VLOOKUP($D16,BS별도,MATCH(I$1,BS별도H,0),0)/100,"") | J16: =IFERROR(VLOOKUP($D16,BS별도,MATCH(J$1,BS별도H,0),0)/100,"") | K16: =SUM(G16:J16) | L16: =IFERROR(VLOOKUP($D16,BS별도,MATCH(L$1,BS별도H,0),0)/100,"") | M16: =IFERROR(VLOOKUP($D16,BS별도,MATCH(M$1,BS별도H,0),0)/100,"") | N16: =IFERROR(VLOOKUP($D16,BS별도,MATCH(N$1,BS별도H,0),0)/100,"") | O16: =IFERROR(VLOOKUP($D16,BS별도,MATCH(O$1,BS별도H,0),0)/100,"") | P16: =SUM(L16:O16) | Q16: =IFERROR(VLOOKUP($D16,BS별도,MATCH(Q$1,BS별도H,0),0)/100,"") | R16: =IFERROR(VLOOKUP($D16,BS별도,MATCH(R$1,BS별도H,0),0)/100,"") | S16: =변수!S27 | T16: =변수!T27 | U16: =SUM(Q16:T16) | V16: =변수!V27 | W16: =변수!W27 | X16: =변수!X27 | Y16: =변수!Y27 | Z16: =SUM(V16:Y16) | AA16: =변수!AA27 | AB16: =변수!AB27 | AC16: =변수!AC27 | AD16: =변수!AD27 | AE16: =SUM(AA16:AD16)
A17: 세전이익 | B17: 손익 | C17: 억원 | D17: 법인세비용차감전계속사업이익 | E17: =IFERROR(VLOOKUP($D17,BS별도,MATCH(E$1,BS별도H,0),0)/100,"") | G17: =IFERROR(VLOOKUP($D17,BS별도,MATCH(G$1,BS별도H,0),0)/100,"") | H17: =IFERROR(VLOOKUP($D17,BS별도,MATCH(H$1,BS별도H,0),0)/100,"") | I17: =IFERROR(VLOOKUP($D17,BS별도,MATCH(I$1,BS별도H,0),0)/100,"") | J17: =IFERROR(VLOOKUP($D17,BS별도,MATCH(J$1,BS별도H,0),0)/100,"") | K17: =SUM(G17:J17) | L17: =IFERROR(VLOOKUP($D17,BS별도,MATCH(L$1,BS별도H,0),0)/100,"") | M17: =IFERROR(VLOOKUP($D17,BS별도,MATCH(M$1,BS별도H,0),0)/100,"") | N17: =IFERROR(VLOOKUP($D17,BS별도,MATCH(N$1,BS별도H,0),0)/100,"") | O17: =IFERROR(VLOOKUP($D17,BS별도,MATCH(O$1,BS별도H,0),0)/100,"") | P17: =SUM(L17:O17) | Q17: =IFERROR(VLOOKUP($D17,BS별도,MATCH(Q$1,BS별도H,0),0)/100,"") | R17: =IFERROR(VLOOKUP($D17,BS별도,MATCH(R$1,BS별도H,0),0)/100,"") | S17: =IFERROR(S9+S11+S16,"") | T17: =IFERROR(T9+T11+T16,"") | U17: =SUM(Q17:T17) | V17: =IFERROR(V9+V11+V16,"") | W17: =IFERROR(W9+W11+W16,"") | X17: =IFERROR(X9+X11+X16,"") | Y17: =IFERROR(Y9+Y11+Y16,"") | Z17: =SUM(V17:Y17) | AA17: =IFERROR(AA9+AA11+AA16,"") | AB17: =IFERROR(AB9+AB11+AB16,"") | AC17: =IFERROR(AC9+AC11+AC16,"") | AD17: =IFERROR(AD9+AD11+AD16,"") | AE17: =SUM(AA17:AD17)
A18: 법인세비용 | B18: 손익 | C18: 억원 | D18: 법인세비용 | E18: =IFERROR(VLOOKUP($D18,BS별도,MATCH(E$1,BS별도H,0),0)/100,"") | G18: =IFERROR(VLOOKUP($D18,BS별도,MATCH(G$1,BS별도H,0),0)/100,"") | H18: =IFERROR(VLOOKUP($D18,BS별도,MATCH(H$1,BS별도H,0),0)/100,"") | I18: =IFERROR(VLOOKUP($D18,BS별도,MATCH(I$1,BS별도H,0),0)/100,"") | J18: =IFERROR(VLOOKUP($D18,BS별도,MATCH(J$1,BS별도H,0),0)/100,"") | K18: =SUM(G18:J18) | L18: =IFERROR(VLOOKUP($D18,BS별도,MATCH(L$1,BS별도H,0),0)/100,"") | M18: =IFERROR(VLOOKUP($D18,BS별도,MATCH(M$1,BS별도H,0),0)/100,"") | N18: =IFERROR(VLOOKUP($D18,BS별도,MATCH(N$1,BS별도H,0),0)/100,"") | O18: =IFERROR(VLOOKUP($D18,BS별도,MATCH(O$1,BS별도H,0),0)/100,"") | P18: =SUM(L18:O18) | Q18: =IFERROR(VLOOKUP($D18,BS별도,MATCH(Q$1,BS별도H,0),0)/100,"") | R18: =IFERROR(VLOOKUP($D18,BS별도,MATCH(R$1,BS별도H,0),0)/100,"") | S18: =IFERROR(MAX(S17,0)*변수!S28,"") | T18: =IFERROR(MAX(T17,0)*변수!T28,"") | U18: =SUM(Q18:T18) | V18: =IFERROR(MAX(V17,0)*변수!V28,"") | W18: =IFERROR(MAX(W17,0)*변수!W28,"") | X18: =IFERROR(MAX(X17,0)*변수!X28,"") | Y18: =IFERROR(MAX(Y17,0)*변수!Y28,"") | Z18: =SUM(V18:Y18) | AA18: =IFERROR(MAX(AA17,0)*변수!AA28,"") | AB18: =IFERROR(MAX(AB17,0)*변수!AB28,"") | AC18: =IFERROR(MAX(AC17,0)*변수!AC28,"") | AD18: =IFERROR(MAX(AD17,0)*변수!AD28,"") | AE18: =SUM(AA18:AD18)
A19: 당기순이익 | B19: 손익 | C19: 억원 | D19: 당기순이익 | E19: =IFERROR(VLOOKUP($D19,BS별도,MATCH(E$1,BS별도H,0),0)/100,"") | G19: =IFERROR(VLOOKUP($D19,BS별도,MATCH(G$1,BS별도H,0),0)/100,"") | H19: =IFERROR(VLOOKUP($D19,BS별도,MATCH(H$1,BS별도H,0),0)/100,"") | I19: =IFERROR(VLOOKUP($D19,BS별도,MATCH(I$1,BS별도H,0),0)/100,"") | J19: =IFERROR(VLOOKUP($D19,BS별도,MATCH(J$1,BS별도H,0),0)/100,"") | K19: =SUM(G19:J19) | L19: =IFERROR(VLOOKUP($D19,BS별도,MATCH(L$1,BS별도H,0),0)/100,"") | M19: =IFERROR(VLOOKUP($D19,BS별도,MATCH(M$1,BS별도H,0),0)/100,"") | N19: =IFERROR(VLOOKUP($D19,BS별도,MATCH(N$1,BS별도H,0),0)/100,"") | O19: =IFERROR(VLOOKUP($D19,BS별도,MATCH(O$1,BS별도H,0),0)/100,"") | P19: =SUM(L19:O19) | Q19: =IFERROR(VLOOKUP($D19,BS별도,MATCH(Q$1,BS별도H,0),0)/100,"") | R19: =IFERROR(VLOOKUP($D19,BS별도,MATCH(R$1,BS별도H,0),0)/100,"") | S19: =IFERROR(S17-S18,"") | T19: =IFERROR(T17-T18,"") | U19: =SUM(Q19:T19) | V19: =IFERROR(V17-V18,"") | W19: =IFERROR(W17-W18,"") | X19: =IFERROR(X17-X18,"") | Y19: =IFERROR(Y17-Y18,"") | Z19: =SUM(V19:Y19) | AA19: =IFERROR(AA17-AA18,"") | AB19: =IFERROR(AB17-AB18,"") | AC19: =IFERROR(AC17-AC18,"") | AD19: =IFERROR(AD17-AD18,"") | AE19: =SUM(AA19:AD19)
A20: 지배주주순이익 | B20: 손익 | C20: 억원 | D20: (지배주주지분)당기순이익 | E20: =IFERROR(VLOOKUP($D20,BS별도,MATCH(E$1,BS별도H,0),0)/100,"") | G20: =IFERROR(VLOOKUP($D20,BS별도,MATCH(G$1,BS별도H,0),0)/100,"") | H20: =IFERROR(VLOOKUP($D20,BS별도,MATCH(H$1,BS별도H,0),0)/100,"") | I20: =IFERROR(VLOOKUP($D20,BS별도,MATCH(I$1,BS별도H,0),0)/100,"") | J20: =IFERROR(VLOOKUP($D20,BS별도,MATCH(J$1,BS별도H,0),0)/100,"") | K20: =SUM(G20:J20) | L20: =IFERROR(VLOOKUP($D20,BS별도,MATCH(L$1,BS별도H,0),0)/100,"") | M20: =IFERROR(VLOOKUP($D20,BS별도,MATCH(M$1,BS별도H,0),0)/100,"") | N20: =IFERROR(VLOOKUP($D20,BS별도,MATCH(N$1,BS별도H,0),0)/100,"") | O20: =IFERROR(VLOOKUP($D20,BS별도,MATCH(O$1,BS별도H,0),0)/100,"") | P20: =SUM(L20:O20) | Q20: =IFERROR(VLOOKUP($D20,BS별도,MATCH(Q$1,BS별도H,0),0)/100,"") | R20: =IFERROR(VLOOKUP($D20,BS별도,MATCH(R$1,BS별도H,0),0)/100,"") | S20: =IFERROR(S19*변수!S29,"") | T20: =IFERROR(T19*변수!T29,"") | U20: =SUM(Q20:T20) | V20: =IFERROR(V19*변수!V29,"") | W20: =IFERROR(W19*변수!W29,"") | X20: =IFERROR(X19*변수!X29,"") | Y20: =IFERROR(Y19*변수!Y29,"") | Z20: =SUM(V20:Y20) | AA20: =IFERROR(AA19*변수!AA29,"") | AB20: =IFERROR(AB19*변수!AB29,"") | AC20: =IFERROR(AC19*변수!AC29,"") | AD20: =IFERROR(AD19*변수!AD29,"") | AE20: =SUM(AA20:AD20)
A21: 감가상각비 | B21: 손익 | C21: 억원 | D21: 감가상각비 | E21: =IFERROR(VLOOKUP($D21,BS별도,MATCH(E$1,BS별도H,0),0)/100,"") | G21: =IFERROR(VLOOKUP($D21,BS별도,MATCH(G$1,BS별도H,0),0)/100,"") | H21: =IFERROR(VLOOKUP($D21,BS별도,MATCH(H$1,BS별도H,0),0)/100,"") | I21: =IFERROR(VLOOKUP($D21,BS별도,MATCH(I$1,BS별도H,0),0)/100,"") | J21: =IFERROR(VLOOKUP($D21,BS별도,MATCH(J$1,BS별도H,0),0)/100,"") | K21: =SUM(G21:J21) | L21: =IFERROR(VLOOKUP($D21,BS별도,MATCH(L$1,BS별도H,0),0)/100,"") | M21: =IFERROR(VLOOKUP($D21,BS별도,MATCH(M$1,BS별도H,0),0)/100,"") | N21: =IFERROR(VLOOKUP($D21,BS별도,MATCH(N$1,BS별도H,0),0)/100,"") | O21: =IFERROR(VLOOKUP($D21,BS별도,MATCH(O$1,BS별도H,0),0)/100,"") | P21: =SUM(L21:O21) | Q21: =IFERROR(VLOOKUP($D21,BS별도,MATCH(Q$1,BS별도H,0),0)/100,"") | R21: =IFERROR(VLOOKUP($D21,BS별도,MATCH(R$1,BS별도H,0),0)/100,"") | S21: =변수!S30 | T21: =변수!T30 | U21: =SUM(Q21:T21) | V21: =변수!V30 | W21: =변수!W30 | X21: =변수!X30 | Y21: =변수!Y30 | Z21: =SUM(V21:Y21) | AA21: =변수!AA30 | AB21: =변수!AB30 | AC21: =변수!AC30 | AD21: =변수!AD30 | AE21: =SUM(AA21:AD21)
A22: EBITDA | B22: 손익 | C22: 억원 | D22: EBITDA | E22: 10.37 | G22: 19.41 | H22: 23.16 | I22: 13.74 | J22: 15.93 | K22: =SUM(G22:J22) | L22: 22.48 | M22: 32.14 | N22: 31.4 | O22: 33.61 | P22: =SUM(L22:O22) | Q22: 67.46 | R22: 63.01 | S22: =IFERROR(S9+S21,"") | T22: =IFERROR(T9+T21,"") | U22: =SUM(Q22:T22) | V22: =IFERROR(V9+V21,"") | W22: =IFERROR(W9+W21,"") | X22: =IFERROR(X9+X21,"") | Y22: =IFERROR(Y9+Y21,"") | Z22: =SUM(V22:Y22) | AA22: =IFERROR(AA9+AA21,"") | AB22: =IFERROR(AB9+AB21,"") | AC22: =IFERROR(AC9+AC21,"") | AD22: =IFERROR(AD9+AD21,"") | AE22: =SUM(AA22:AD22)
A23: 자산총계 | B23: 재무상태 | C23: 억원 | D23: 자산총계 | E23: =IFERROR(VLOOKUP($D23,BS별도,MATCH(E$1,BS별도H,0),0)/100,"") | F23: 721.4 | G23: =IFERROR(VLOOKUP($D23,BS별도,MATCH(G$1,BS별도H,0),0)/100,"") | H23: =IFERROR(VLOOKUP($D23,BS별도,MATCH(H$1,BS별도H,0),0)/100,"") | I23: =IFERROR(VLOOKUP($D23,BS별도,MATCH(I$1,BS별도H,0),0)/100,"") | J23: =IFERROR(VLOOKUP($D23,BS별도,MATCH(J$1,BS별도H,0),0)/100,"") | K23: =J23 | L23: =IFERROR(VLOOKUP($D23,BS별도,MATCH(L$1,BS별도H,0),0)/100,"") | M23: =IFERROR(VLOOKUP($D23,BS별도,MATCH(M$1,BS별도H,0),0)/100,"") | N23: =IFERROR(VLOOKUP($D23,BS별도,MATCH(N$1,BS별도H,0),0)/100,"") | O23: =IFERROR(VLOOKUP($D23,BS별도,MATCH(O$1,BS별도H,0),0)/100,"") | P23: =O23 | Q23: =IFERROR(VLOOKUP($D23,BS별도,MATCH(Q$1,BS별도H,0),0)/100,"") | R23: =IFERROR(VLOOKUP($D23,BS별도,MATCH(R$1,BS별도H,0),0)/100,"") | S23: =IFERROR(S24+S25,"") | T23: =IFERROR(T24+T25,"") | U23: =T23 | V23: =IFERROR(V24+V25,"") | W23: =IFERROR(W24+W25,"") | X23: =IFERROR(X24+X25,"") | Y23: =IFERROR(Y24+Y25,"") | Z23: =Y23 | AA23: =IFERROR(AA24+AA25,"") | AB23: =IFERROR(AB24+AB25,"") | AC23: =IFERROR(AC24+AC25,"") | AD23: =IFERROR(AD24+AD25,"") | AE23: =AD23
A24: 부채총계 | B24: 재무상태 | C24: 억원 | D24: 부채총계 | E24: =IFERROR(VLOOKUP($D24,BS별도,MATCH(E$1,BS별도H,0),0)/100,"") | F24: 172.23 | G24: =IFERROR(VLOOKUP($D24,BS별도,MATCH(G$1,BS별도H,0),0)/100,"") | H24: =IFERROR(VLOOKUP($D24,BS별도,MATCH(H$1,BS별도H,0),0)/100,"") | I24: =IFERROR(VLOOKUP($D24,BS별도,MATCH(I$1,BS별도H,0),0)/100,"") | J24: =IFERROR(VLOOKUP($D24,BS별도,MATCH(J$1,BS별도H,0),0)/100,"") | K24: =J24 | L24: =IFERROR(VLOOKUP($D24,BS별도,MATCH(L$1,BS별도H,0),0)/100,"") | M24: =IFERROR(VLOOKUP($D24,BS별도,MATCH(M$1,BS별도H,0),0)/100,"") | N24: =IFERROR(VLOOKUP($D24,BS별도,MATCH(N$1,BS별도H,0),0)/100,"") | O24: =IFERROR(VLOOKUP($D24,BS별도,MATCH(O$1,BS별도H,0),0)/100,"") | P24: =O24 | Q24: =IFERROR(VLOOKUP($D24,BS별도,MATCH(Q$1,BS별도H,0),0)/100,"") | R24: =IFERROR(VLOOKUP($D24,BS별도,MATCH(R$1,BS별도H,0),0)/100,"") | S24: =IFERROR(R24*(1+변수!S31),"") | T24: =IFERROR(S24*(1+변수!T31),"") | U24: =T24 | V24: =IFERROR(T24*(1+변수!V31),"") | W24: =IFERROR(V24*(1+변수!W31),"") | X24: =IFERROR(W24*(1+변수!X31),"") | Y24: =IFERROR(X24*(1+변수!Y31),"") | Z24: =Y24 | AA24: =IFERROR(Y24*(1+변수!AA31),"") | AB24: =IFERROR(AA24*(1+변수!AB31),"") | AC24: =IFERROR(AB24*(1+변수!AC31),"") | AD24: =IFERROR(AC24*(1+변수!AD31),"") | AE24: =AD24
A25: 자본총계 | B25: 재무상태 | C25: 억원 | D25: 자본총계 | E25: =IFERROR(VLOOKUP($D25,BS별도,MATCH(E$1,BS별도H,0),0)/100,"") | F25: 549.17 | G25: =IFERROR(VLOOKUP($D25,BS별도,MATCH(G$1,BS별도H,0),0)/100,"") | H25: =IFERROR(VLOOKUP($D25,BS별도,MATCH(H$1,BS별도H,0),0)/100,"") | I25: =IFERROR(VLOOKUP($D25,BS별도,MATCH(I$1,BS별도H,0),0)/100,"") | J25: =IFERROR(VLOOKUP($D25,BS별도,MATCH(J$1,BS별도H,0),0)/100,"") | K25: =J25 | L25: =IFERROR(VLOOKUP($D25,BS별도,MATCH(L$1,BS별도H,0),0)/100,"") | M25: =IFERROR(VLOOKUP($D25,BS별도,MATCH(M$1,BS별도H,0),0)/100,"") | N25: =IFERROR(VLOOKUP($D25,BS별도,MATCH(N$1,BS별도H,0),0)/100,"") | O25: =IFERROR(VLOOKUP($D25,BS별도,MATCH(O$1,BS별도H,0),0)/100,"") | P25: =O25 | Q25: =IFERROR(VLOOKUP($D25,BS별도,MATCH(Q$1,BS별도H,0),0)/100,"") | R25: =IFERROR(VLOOKUP($D25,BS별도,MATCH(R$1,BS별도H,0),0)/100,"") | S25: =IFERROR(R25+S19-변수!S32,"") | T25: =IFERROR(S25+T19-변수!T32,"") | U25: =T25 | V25: =IFERROR(T25+V19-변수!V32,"") | W25: =IFERROR(V25+W19-변수!W32,"") | X25: =IFERROR(W25+X19-변수!X32,"") | Y25: =IFERROR(X25+Y19-변수!Y32,"") | Z25: =Y25 | AA25: =IFERROR(Y25+AA19-변수!AA32,"") | AB25: =IFERROR(AA25+AB19-변수!AB32,"") | AC25: =IFERROR(AB25+AC19-변수!AC32,"") | AD25: =IFERROR(AC25+AD19-변수!AD32,"") | AE25: =AD25
A26: 지배주주지분 | B26: 재무상태 | C26: 억원 | D26: 지배주주지분 | E26: =IFERROR(VLOOKUP($D26,BS별도,MATCH(E$1,BS별도H,0),0)/100,"") | F26: 549.17 | G26: =IFERROR(VLOOKUP($D26,BS별도,MATCH(G$1,BS별도H,0),0)/100,"") | H26: =IFERROR(VLOOKUP($D26,BS별도,MATCH(H$1,BS별도H,0),0)/100,"") | I26: =IFERROR(VLOOKUP($D26,BS별도,MATCH(I$1,BS별도H,0),0)/100,"") | J26: =IFERROR(VLOOKUP($D26,BS별도,MATCH(J$1,BS별도H,0),0)/100,"") | K26: =J26 | L26: =IFERROR(VLOOKUP($D26,BS별도,MATCH(L$1,BS별도H,0),0)/100,"") | M26: =IFERROR(VLOOKUP($D26,BS별도,MATCH(M$1,BS별도H,0),0)/100,"") | N26: =IFERROR(VLOOKUP($D26,BS별도,MATCH(N$1,BS별도H,0),0)/100,"") | O26: =IFERROR(VLOOKUP($D26,BS별도,MATCH(O$1,BS별도H,0),0)/100,"") | P26: =O26 | Q26: =IFERROR(VLOOKUP($D26,BS별도,MATCH(Q$1,BS별도H,0),0)/100,"") | R26: =IFERROR(VLOOKUP($D26,BS별도,MATCH(R$1,BS별도H,0),0)/100,"") | S26: =IFERROR(R26+S20-변수!S33,"") | T26: =IFERROR(S26+T20-변수!T33,"") | U26: =T26 | V26: =IFERROR(T26+V20-변수!V33,"") | W26: =IFERROR(V26+W20-변수!W33,"") | X26: =IFERROR(W26+X20-변수!X33,"") | Y26: =IFERROR(X26+Y20-변수!Y33,"") | Z26: =Y26 | AA26: =IFERROR(Y26+AA20-변수!AA33,"") | AB26: =IFERROR(AA26+AB20-변수!AB33,"") | AC26: =IFERROR(AB26+AC20-변수!AC33,"") | AD26: =IFERROR(AC26+AD20-변수!AD33,"") | AE26: =AD26
A27: 총차입금 | B27: 재무상태 | C27: 억원 | D27: 총차입금 | E27: =IFERROR(VLOOKUP($D27,BS별도,MATCH(E$1,BS별도H,0),0)/100,"") | F27: 91.96 | G27: =IFERROR(VLOOKUP($D27,BS별도,MATCH(G$1,BS별도H,0),0)/100,"") | H27: =IFERROR(VLOOKUP($D27,BS별도,MATCH(H$1,BS별도H,0),0)/100,"") | I27: =IFERROR(VLOOKUP($D27,BS별도,MATCH(I$1,BS별도H,0),0)/100,"") | J27: =IFERROR(VLOOKUP($D27,BS별도,MATCH(J$1,BS별도H,0),0)/100,"") | K27: =J27 | L27: =IFERROR(VLOOKUP($D27,BS별도,MATCH(L$1,BS별도H,0),0)/100,"") | M27: =IFERROR(VLOOKUP($D27,BS별도,MATCH(M$1,BS별도H,0),0)/100,"") | N27: =IFERROR(VLOOKUP($D27,BS별도,MATCH(N$1,BS별도H,0),0)/100,"") | O27: =IFERROR(VLOOKUP($D27,BS별도,MATCH(O$1,BS별도H,0),0)/100,"") | P27: =O27 | Q27: =IFERROR(VLOOKUP($D27,BS별도,MATCH(Q$1,BS별도H,0),0)/100,"") | R27: =IFERROR(VLOOKUP($D27,BS별도,MATCH(R$1,BS별도H,0),0)/100,"") | S27: =IFERROR(R27*(1+변수!S34),"") | T27: =IFERROR(S27*(1+변수!T34),"") | U27: =T27 | V27: =IFERROR(T27*(1+변수!V34),"") | W27: =IFERROR(V27*(1+변수!W34),"") | X27: =IFERROR(W27*(1+변수!X34),"") | Y27: =IFERROR(X27*(1+변수!Y34),"") | Z27: =Y27 | AA27: =IFERROR(Y27*(1+변수!AA34),"") | AB27: =IFERROR(AA27*(1+변수!AB34),"") | AC27: =IFERROR(AB27*(1+변수!AC34),"") | AD27: =IFERROR(AC27*(1+변수!AD34),"") | AE27: =AD27
A28: 순차입금 | B28: 재무상태 | C28: 억원 | D28: 순차입금 | E28: =IFERROR(VLOOKUP($D28,BS별도,MATCH(E$1,BS별도H,0),0)/100,"") | F28: 19.47 | G28: =IFERROR(VLOOKUP($D28,BS별도,MATCH(G$1,BS별도H,0),0)/100,"") | H28: =IFERROR(VLOOKUP($D28,BS별도,MATCH(H$1,BS별도H,0),0)/100,"") | I28: =IFERROR(VLOOKUP($D28,BS별도,MATCH(I$1,BS별도H,0),0)/100,"") | J28: =IFERROR(VLOOKUP($D28,BS별도,MATCH(J$1,BS별도H,0),0)/100,"") | K28: =J28 | L28: =IFERROR(VLOOKUP($D28,BS별도,MATCH(L$1,BS별도H,0),0)/100,"") | M28: =IFERROR(VLOOKUP($D28,BS별도,MATCH(M$1,BS별도H,0),0)/100,"") | N28: =IFERROR(VLOOKUP($D28,BS별도,MATCH(N$1,BS별도H,0),0)/100,"") | O28: =IFERROR(VLOOKUP($D28,BS별도,MATCH(O$1,BS별도H,0),0)/100,"") | P28: =O28 | Q28: =IFERROR(VLOOKUP($D28,BS별도,MATCH(Q$1,BS별도H,0),0)/100,"") | R28: =IFERROR(VLOOKUP($D28,BS별도,MATCH(R$1,BS별도H,0),0)/100,"") | S28: =IFERROR(R28*(1+변수!S35),"") | T28: =IFERROR(S28*(1+변수!T35),"") | U28: =T28 | V28: =IFERROR(T28*(1+변수!V35),"") | W28: =IFERROR(V28*(1+변수!W35),"") | X28: =IFERROR(W28*(1+변수!X35),"") | Y28: =IFERROR(X28*(1+변수!Y35),"") | Z28: =Y28 | AA28: =IFERROR(Y28*(1+변수!AA35),"") | AB28: =IFERROR(AA28*(1+변수!AB35),"") | AC28: =IFERROR(AB28*(1+변수!AC35),"") | AD28: =IFERROR(AC28*(1+변수!AD35),"") | AE28: =AD28
A29: 이자발생자산 | B29: 재무상태 | C29: 억원 | D29: 이자발생자산 | E29: =IFERROR(VLOOKUP($D29,BS별도,MATCH(E$1,BS별도H,0),0)/100,"") | F29: 73.26 | G29: =IFERROR(VLOOKUP($D29,BS별도,MATCH(G$1,BS별도H,0),0)/100,"") | H29: =IFERROR(VLOOKUP($D29,BS별도,MATCH(H$1,BS별도H,0),0)/100,"") | I29: =IFERROR(VLOOKUP($D29,BS별도,MATCH(I$1,BS별도H,0),0)/100,"") | J29: =IFERROR(VLOOKUP($D29,BS별도,MATCH(J$1,BS별도H,0),0)/100,"") | K29: =J29 | L29: =IFERROR(VLOOKUP($D29,BS별도,MATCH(L$1,BS별도H,0),0)/100,"") | M29: =IFERROR(VLOOKUP($D29,BS별도,MATCH(M$1,BS별도H,0),0)/100,"") | N29: =IFERROR(VLOOKUP($D29,BS별도,MATCH(N$1,BS별도H,0),0)/100,"") | O29: =IFERROR(VLOOKUP($D29,BS별도,MATCH(O$1,BS별도H,0),0)/100,"") | P29: =O29 | Q29: =IFERROR(VLOOKUP($D29,BS별도,MATCH(Q$1,BS별도H,0),0)/100,"") | R29: =IFERROR(VLOOKUP($D29,BS별도,MATCH(R$1,BS별도H,0),0)/100,"") | S29: =IFERROR(R29*(1+변수!S36),"") | T29: =IFERROR(S29*(1+변수!T36),"") | U29: =T29 | V29: =IFERROR(T29*(1+변수!V36),"") | W29: =IFERROR(V29*(1+변수!W36),"") | X29: =IFERROR(W29*(1+변수!X36),"") | Y29: =IFERROR(X29*(1+변수!Y36),"") | Z29: =Y29 | AA29: =IFERROR(Y29*(1+변수!AA36),"") | AB29: =IFERROR(AA29*(1+변수!AB36),"") | AC29: =IFERROR(AB29*(1+변수!AC36),"") | AD29: =IFERROR(AC29*(1+변수!AD36),"") | AE29: =AD29
A30: 현금및현금성자산 | B30: 재무상태 | C30: 억원 | D30: 현금및현금성자산 | E30: =IFERROR(VLOOKUP($D30,BS별도,MATCH(E$1,BS별도H,0),0)/100,"") | F30: 72.49 | G30: =IFERROR(VLOOKUP($D30,BS별도,MATCH(G$1,BS별도H,0),0)/100,"") | H30: =IFERROR(VLOOKUP($D30,BS별도,MATCH(H$1,BS별도H,0),0)/100,"") | I30: =IFERROR(VLOOKUP($D30,BS별도,MATCH(I$1,BS별도H,0),0)/100,"") | J30: =IFERROR(VLOOKUP($D30,BS별도,MATCH(J$1,BS별도H,0),0)/100,"") | K30: =J30 | L30: =IFERROR(VLOOKUP($D30,BS별도,MATCH(L$1,BS별도H,0),0)/100,"") | M30: =IFERROR(VLOOKUP($D30,BS별도,MATCH(M$1,BS별도H,0),0)/100,"") | N30: =IFERROR(VLOOKUP($D30,BS별도,MATCH(N$1,BS별도H,0),0)/100,"") | O30: =IFERROR(VLOOKUP($D30,BS별도,MATCH(O$1,BS별도H,0),0)/100,"") | P30: =O30 | Q30: =IFERROR(VLOOKUP($D30,BS별도,MATCH(Q$1,BS별도H,0),0)/100,"") | R30: =IFERROR(VLOOKUP($D30,BS별도,MATCH(R$1,BS별도H,0),0)/100,"") | U30: =T30 | Z30: =Y30 | AE30: =AD30
A31: CAPEX | B31: 현금흐름 | C31: 억원 | D31: CAPEX | E31: =IFERROR(VLOOKUP($D31,BS별도,MATCH(E$1,BS별도H,0),0)/100,"") | G31: =IFERROR(VLOOKUP($D31,BS별도,MATCH(G$1,BS별도H,0),0)/100,"") | H31: =IFERROR(VLOOKUP($D31,BS별도,MATCH(H$1,BS별도H,0),0)/100,"") | I31: =IFERROR(VLOOKUP($D31,BS별도,MATCH(I$1,BS별도H,0),0)/100,"") | J31: =IFERROR(VLOOKUP($D31,BS별도,MATCH(J$1,BS별도H,0),0)/100,"") | K31: =SUM(G31:J31) | L31: =IFERROR(VLOOKUP($D31,BS별도,MATCH(L$1,BS별도H,0),0)/100,"") | M31: =IFERROR(VLOOKUP($D31,BS별도,MATCH(M$1,BS별도H,0),0)/100,"") | N31: =IFERROR(VLOOKUP($D31,BS별도,MATCH(N$1,BS별도H,0),0)/100,"") | O31: =IFERROR(VLOOKUP($D31,BS별도,MATCH(O$1,BS별도H,0),0)/100,"") | P31: =SUM(L31:O31) | Q31: =IFERROR(VLOOKUP($D31,BS별도,MATCH(Q$1,BS별도H,0),0)/100,"") | R31: =IFERROR(VLOOKUP($D31,BS별도,MATCH(R$1,BS별도H,0),0)/100,"") | S31: =IFERROR(N31*(1+변수!S38),"") | T31: =IFERROR(O31*(1+변수!T38),"") | U31: =SUM(Q31:T31) | V31: =IFERROR(Q31*(1+변수!V38),"") | W31: =IFERROR(R31*(1+변수!W38),"") | X31: =IFERROR(S31*(1+변수!X38),"") | Y31: =IFERROR(T31*(1+변수!Y38),"") | Z31: =SUM(V31:Y31) | AA31: =IFERROR(V31*(1+변수!AA38),"") | AB31: =IFERROR(W31*(1+변수!AB38),"") | AC31: =IFERROR(X31*(1+변수!AC38),"") | AD31: =IFERROR(Y31*(1+변수!AD38),"") | AE31: =SUM(AA31:AD31)
A32: 영업활동현금흐름 | B32: 현금흐름 | C32: 억원 | D32: 영업활동으로인한현금흐름 | E32: =IFERROR(VLOOKUP($D32,BS별도,MATCH(E$1,BS별도H,0),0)/100,"") | G32: =IFERROR(VLOOKUP($D32,BS별도,MATCH(G$1,BS별도H,0),0)/100,"") | H32: =IFERROR(VLOOKUP($D32,BS별도,MATCH(H$1,BS별도H,0),0)/100,"") | I32: =IFERROR(VLOOKUP($D32,BS별도,MATCH(I$1,BS별도H,0),0)/100,"") | J32: =IFERROR(VLOOKUP($D32,BS별도,MATCH(J$1,BS별도H,0),0)/100,"") | K32: =SUM(G32:J32) | L32: =IFERROR(VLOOKUP($D32,BS별도,MATCH(L$1,BS별도H,0),0)/100,"") | M32: =IFERROR(VLOOKUP($D32,BS별도,MATCH(M$1,BS별도H,0),0)/100,"") | N32: =IFERROR(VLOOKUP($D32,BS별도,MATCH(N$1,BS별도H,0),0)/100,"") | O32: =IFERROR(VLOOKUP($D32,BS별도,MATCH(O$1,BS별도H,0),0)/100,"") | P32: =SUM(L32:O32) | Q32: =IFERROR(VLOOKUP($D32,BS별도,MATCH(Q$1,BS별도H,0),0)/100,"") | R32: =IFERROR(VLOOKUP($D32,BS별도,MATCH(R$1,BS별도H,0),0)/100,"") | U32: =SUM(Q32:T32) | Z32: =SUM(V32:Y32) | AE32: =SUM(AA32:AD32)
A33: 주식수 | B33: 주당 | C33: 백만주 | D33: 유통주식수 | E33: 17.003 | F33: =E33 | G33: 17.003 | H33: 17.003 | I33: 17.003 | J33: 17.137 | K33: =J33 | L33: 17.252 | M33: 17.266 | N33: 17.274 | O33: 17.274 | P33: =O33 | Q33: 19.246 | R33: 19.248 | S33: =IFERROR(R33*(1+변수!S40),"") | T33: =IFERROR(S33*(1+변수!T40),"") | U33: =T33 | V33: =IFERROR(T33*(1+변수!V40),"") | W33: =IFERROR(V33*(1+변수!W40),"") | X33: =IFERROR(W33*(1+변수!X40),"") | Y33: =IFERROR(X33*(1+변수!Y40),"") | Z33: =Y33 | AA33: =IFERROR(Y33*(1+변수!AA40),"") | AB33: =IFERROR(AA33*(1+변수!AB40),"") | AC33: =IFERROR(AB33*(1+변수!AC40),"") | AD33: =IFERROR(AC33*(1+변수!AD40),"") | AE33: =AD33
A34: EPS | B34: 주당 | C34: 원 | D34: EPS | E34: =IFERROR(E20*100/E33,"") | G34: =IFERROR(G20*100/G33,"") | H34: =IFERROR(H20*100/H33,"") | I34: =IFERROR(I20*100/I33,"") | J34: =IFERROR(J20*100/J33,"") | K34: =SUM(G34:J34) | L34: =IFERROR(L20*100/L33,"") | M34: =IFERROR(M20*100/M33,"") | N34: =IFERROR(N20*100/N33,"") | O34: =IFERROR(O20*100/O33,"") | P34: =SUM(L34:O34) | Q34: =IFERROR(Q20*100/Q33,"") | R34: =IFERROR(R20*100/R33,"") | S34: =IFERROR(S20*100/S33,"") | T34: =IFERROR(T20*100/T33,"") | U34: =SUM(Q34:T34) | V34: =IFERROR(V20*100/V33,"") | W34: =IFERROR(W20*100/W33,"") | X34: =IFERROR(X20*100/X33,"") | Y34: =IFERROR(Y20*100/Y33,"") | Z34: =SUM(V34:Y34) | AA34: =IFERROR(AA20*100/AA33,"") | AB34: =IFERROR(AB20*100/AB33,"") | AC34: =IFERROR(AC20*100/AC33,"") | AD34: =IFERROR(AD20*100/AD33,"") | AE34: =SUM(AA34:AD34)
A35: BPS | B35: 주당 | C35: 원 | D35: BPS | E35: =IFERROR(E26*100/E33,"") | F35: =E35 | G35: =IFERROR(G26*100/G33,"") | H35: =IFERROR(H26*100/H33,"") | I35: =IFERROR(I26*100/I33,"") | J35: =IFERROR(J26*100/J33,"") | K35: =J35 | L35: =IFERROR(L26*100/L33,"") | M35: =IFERROR(M26*100/M33,"") | N35: =IFERROR(N26*100/N33,"") | O35: =IFERROR(O26*100/O33,"") | P35: =O35 | Q35: =IFERROR(Q26*100/Q33,"") | R35: =IFERROR(R26*100/R33,"") | S35: =IFERROR(S26*100/S33,"") | T35: =IFERROR(T26*100/T33,"") | U35: =T35 | V35: =IFERROR(V26*100/V33,"") | W35: =IFERROR(W26*100/W33,"") | X35: =IFERROR(X26*100/X33,"") | Y35: =IFERROR(Y26*100/Y33,"") | Z35: =Y35 | AA35: =IFERROR(AA26*100/AA33,"") | AB35: =IFERROR(AB26*100/AB33,"") | AC35: =IFERROR(AC26*100/AC33,"") | AD35: =IFERROR(AD26*100/AD33,"") | AE35: =AD35
A36: DPS | B36: 주당 | C36: 원 | D36: DPS(보통주) | E36: 0 | F36: 0 | J36: 0 | K36: =SUM(G36:J36) | O36: 0 | P36: =SUM(L36:O36) | T36: =변수!T41 | U36: =SUM(Q36:T36) | Y36: =변수!Y41 | Z36: =SUM(V36:Y36) | AD36: =변수!AD41 | AE36: =SUM(AA36:AD36)
A37: PER | B37: 주당 | C37: 배 | D37: PER | F37: =E37 | I37: =IFERROR(변수!I18/(E34+G34+H34+I34),"") | J37: =IFERROR(변수!J18/(G34+H34+I34+J34),"") | K37: =J37 | L37: =IFERROR(변수!L18/(H34+I34+J34+L34),"") | M37: =IFERROR(변수!M18/(I34+J34+L34+M34),"") | N37: =IFERROR(변수!N18/(J34+L34+M34+N34),"") | O37: =IFERROR(변수!O18/(L34+M34+N34+O34),"") | P37: =O37 | Q37: =IFERROR(변수!Q18/(M34+N34+O34+Q34),"") | R37: =IFERROR(변수!R18/(N34+O34+Q34+R34),"") | S37: =IFERROR(변수!$D$44/(O34+Q34+R34+S34),"") | T37: =IFERROR(변수!$D$44/(Q34+R34+S34+T34),"") | U37: =T37 | V37: =IFERROR(변수!$D$44/(R34+S34+T34+V34),"") | W37: =IFERROR(변수!$D$44/(S34+T34+V34+W34),"") | X37: =IFERROR(변수!$D$44/(T34+V34+W34+X34),"") | Y37: =IFERROR(변수!$D$44/(V34+W34+X34+Y34),"") | Z37: =Y37 | AA37: =IFERROR(변수!$D$44/(W34+X34+Y34+AA34),"") | AB37: =IFERROR(변수!$D$44/(X34+Y34+AA34+AB34),"") | AC37: =IFERROR(변수!$D$44/(Y34+AA34+AB34+AC34),"") | AD37: =IFERROR(변수!$D$44/(AA34+AB34+AC34+AD34),"") | AE37: =AD37
A38: PBR | B38: 주당 | C38: 배 | D38: PBR | E38: =IFERROR(변수!E18/E35,"") | F38: =E38 | G38: =IFERROR(변수!G18/G35,"") | H38: =IFERROR(변수!H18/H35,"") | I38: =IFERROR(변수!I18/I35,"") | J38: =IFERROR(변수!J18/J35,"") | K38: =J38 | L38: =IFERROR(변수!L18/L35,"") | M38: =IFERROR(변수!M18/M35,"") | N38: =IFERROR(변수!N18/N35,"") | O38: =IFERROR(변수!O18/O35,"") | P38: =O38 | Q38: =IFERROR(변수!Q18/Q35,"") | R38: =IFERROR(변수!R18/R35,"") | S38: =IFERROR(변수!$D$44/S35,"") | T38: =IFERROR(변수!$D$44/T35,"") | U38: =T38 | V38: =IFERROR(변수!$D$44/V35,"") | W38: =IFERROR(변수!$D$44/W35,"") | X38: =IFERROR(변수!$D$44/X35,"") | Y38: =IFERROR(변수!$D$44/Y35,"") | Z38: =Y38 | AA38: =IFERROR(변수!$D$44/AA35,"") | AB38: =IFERROR(변수!$D$44/AB35,"") | AC38: =IFERROR(변수!$D$44/AC35,"") | AD38: =IFERROR(변수!$D$44/AD35,"") | AE38: =AD38
A39: 매출전사 | B39: 사업부 | C39: 억원 | D39: 매출 전사(부문 미분리) | E39: 112.71 | G39: 118.74 | H39: 131.3 | I39: 112 | J39: 123.37 | K39: =SUM(G39:J39) | L39: 131.11 | M39: 154.99 | N39: 161.96 | O39: 184.1 | P39: =SUM(L39:O39) | Q39: 223.81 | R39: 236.45 | S39: =IFERROR(S5,"") | T39: =IFERROR(T5,"") | U39: =SUM(Q39:T39) | V39: =IFERROR(V5,"") | W39: =IFERROR(W5,"") | X39: =IFERROR(X5,"") | Y39: =IFERROR(Y5,"") | Z39: =SUM(V39:Y39) | AA39: =IFERROR(AA5,"") | AB39: =IFERROR(AB5,"") | AC39: =IFERROR(AC5,"") | AD39: =IFERROR(AD5,"") | AE39: =SUM(AA39:AD39)
A40: OP전사 | B40: 사업부 | C40: 억원 | D40: OP 전사(부문 미분리) | E40: 4.51 | G40: 13.75 | H40: 17.48 | I40: 7.89 | J40: 10.12 | K40: =SUM(G40:J40) | L40: 16.82 | M40: 26.53 | N40: 25.93 | O40: 28.23 | P40: =SUM(L40:O40) | Q40: 62.05 | R40: 56.03 | S40: =IFERROR(S9,"") | T40: =IFERROR(T9,"") | U40: =SUM(Q40:T40) | V40: =IFERROR(V9,"") | W40: =IFERROR(W9,"") | X40: =IFERROR(X9,"") | Y40: =IFERROR(Y9,"") | Z40: =SUM(V40:Y40) | AA40: =IFERROR(AA9,"") | AB40: =IFERROR(AB9,"") | AC40: =IFERROR(AC9,"") | AD40: =IFERROR(AD9,"") | AE40: =SUM(AA40:AD40)
B41: 비율(참고)
A42: NPM | C42: % | D42: 지배주주순이익 / 매출액 | E42: =IFERROR(E20/E5,"") | F42: =IFERROR(F20/F5,"") | G42: =IFERROR(G20/G5,"") | H42: =IFERROR(H20/H5,"") | I42: =IFERROR(I20/I5,"") | J42: =IFERROR(J20/J5,"") | K42: =IFERROR(K20/K5,"") | L42: =IFERROR(L20/L5,"") | ... AE42: =IFERROR(AE20/AE5,"")
A43: 매출원가율 | C43: % | D43: 매출원가 / 매출액 | E43: =IFERROR(E6/E5,"") | F43: =IFERROR(F6/F5,"") | G43: =IFERROR(G6/G5,"") | H43: =IFERROR(H6/H5,"") | I43: =IFERROR(I6/I5,"") | J43: =IFERROR(J6/J5,"") | K43: =IFERROR(K6/K5,"") | L43: =IFERROR(L6/L5,"") | ... AE43: =IFERROR(AE6/AE5,"")
A44: 판관비율 | C44: % | D44: 판관비 / 매출액 | E44: =IFERROR(E8/E5,"") | F44: =IFERROR(F8/F5,"") | G44: =IFERROR(G8/G5,"") | H44: =IFERROR(H8/H5,"") | I44: =IFERROR(I8/I5,"") | J44: =IFERROR(J8/J5,"") | K44: =IFERROR(K8/K5,"") | L44: =IFERROR(L8/L5,"") | ... AE44: =IFERROR(AE8/AE5,"")

Sheet 분기
C1: 이름: 분기H — subQ 를 이름으로 VLOOKUP(억원) | E1: 4Q23 | F1: 1Q24 | G1: 2Q24 | H1: 3Q24 | I1: 4Q24 | J1: 1Q25 | K1: 2Q25 | L1: 3Q25 | M1: 4Q25 | N1: 1Q26 | O1: 2Q26 | P1: 3Q26 | Q1: 4Q26 | R1: 1Q27 | S1: 2Q27 | T1: 3Q27 | U1: 4Q27 | V1: 1Q28 | W1: 2Q28 | X1: 3Q28 | Y1: 4Q28
C2: 종가: | D2: =변수!D44
C3: 기준일: | D3: 20261014 | E3: 1 | F3: 2 | G3: 3 | H3: 4 | I3: 5 | J3: 6 | K3: 7 | L3: 8 | M3: 9 | N3: 10 | O3: 11 | P3: 12 | Q3: 13 | R3: 14 | S3: 15 | T3: 16 | U3: 17 | V3: 18 | W3: 19 | X3: 20 | Y3: 21
E4: 2023.12 | F4: 2024.03 | G4: 2024.06 | H4: 2024.09 | I4: 2024.12 | J4: 2025.03 | K4: 2025.06 | L4: 2025.09 | M4: 2025.12 | N4: 2026.03 | O4: 2026.06 | P4: 2026.09 | Q4: 2026.12 | R4: 2027.03 | S4: 2027.06 | T4: 2027.09 | U4: 2027.12 | V4: 2028.03 | W4: 2028.06 | X4: 2028.09 | Y4: 2028.12
A5: 매출액 | D5: 매출액 | E5: =IFERROR(VLOOKUP($A5,subQ,MATCH(E$1,SUBQH,0),0),"") | F5: =IFERROR(VLOOKUP($A5,subQ,MATCH(F$1,SUBQH,0),0),"") | G5: =IFERROR(VLOOKUP($A5,subQ,MATCH(G$1,SUBQH,0),0),"") | H5: =IFERROR(VLOOKUP($A5,subQ,MATCH(H$1,SUBQH,0),0),"") | I5: =IFERROR(VLOOKUP($A5,subQ,MATCH(I$1,SUBQH,0),0),"") | J5: =IFERROR(VLOOKUP($A5,subQ,MATCH(J$1,SUBQH,0),0),"") | K5: =IFERROR(VLOOKUP($A5,subQ,MATCH(K$1,SUBQH,0),0),"") | L5: =IFERROR(VLOOKUP($A5,subQ,MATCH(L$1,SUBQH,0),0),"") | ... Y5: =IFERROR(VLOOKUP($A5,subQ,MATCH(Y$1,SUBQH,0),0),"")
A6: 매출원가 | D6: 매출원가 | E6: =IFERROR(VLOOKUP($A6,subQ,MATCH(E$1,SUBQH,0),0),"") | F6: =IFERROR(VLOOKUP($A6,subQ,MATCH(F$1,SUBQH,0),0),"") | G6: =IFERROR(VLOOKUP($A6,subQ,MATCH(G$1,SUBQH,0),0),"") | H6: =IFERROR(VLOOKUP($A6,subQ,MATCH(H$1,SUBQH,0),0),"") | I6: =IFERROR(VLOOKUP($A6,subQ,MATCH(I$1,SUBQH,0),0),"") | J6: =IFERROR(VLOOKUP($A6,subQ,MATCH(J$1,SUBQH,0),0),"") | K6: =IFERROR(VLOOKUP($A6,subQ,MATCH(K$1,SUBQH,0),0),"") | L6: =IFERROR(VLOOKUP($A6,subQ,MATCH(L$1,SUBQH,0),0),"") | ... Y6: =IFERROR(VLOOKUP($A6,subQ,MATCH(Y$1,SUBQH,0),0),"")
A7: 매출총이익 | D7: 매출총이익 | E7: =IFERROR(VLOOKUP($A7,subQ,MATCH(E$1,SUBQH,0),0),"") | F7: =IFERROR(VLOOKUP($A7,subQ,MATCH(F$1,SUBQH,0),0),"") | G7: =IFERROR(VLOOKUP($A7,subQ,MATCH(G$1,SUBQH,0),0),"") | H7: =IFERROR(VLOOKUP($A7,subQ,MATCH(H$1,SUBQH,0),0),"") | I7: =IFERROR(VLOOKUP($A7,subQ,MATCH(I$1,SUBQH,0),0),"") | J7: =IFERROR(VLOOKUP($A7,subQ,MATCH(J$1,SUBQH,0),0),"") | K7: =IFERROR(VLOOKUP($A7,subQ,MATCH(K$1,SUBQH,0),0),"") | L7: =IFERROR(VLOOKUP($A7,subQ,MATCH(L$1,SUBQH,0),0),"") | ... Y7: =IFERROR(VLOOKUP($A7,subQ,MATCH(Y$1,SUBQH,0),0),"")
A8: 판관비 | D8: 판매비와관리비 | E8: =IFERROR(VLOOKUP($A8,subQ,MATCH(E$1,SUBQH,0),0),"") | F8: =IFERROR(VLOOKUP($A8,subQ,MATCH(F$1,SUBQH,0),0),"") | G8: =IFERROR(VLOOKUP($A8,subQ,MATCH(G$1,SUBQH,0),0),"") | H8: =IFERROR(VLOOKUP($A8,subQ,MATCH(H$1,SUBQH,0),0),"") | I8: =IFERROR(VLOOKUP($A8,subQ,MATCH(I$1,SUBQH,0),0),"") | J8: =IFERROR(VLOOKUP($A8,subQ,MATCH(J$1,SUBQH,0),0),"") | K8: =IFERROR(VLOOKUP($A8,subQ,MATCH(K$1,SUBQH,0),0),"") | L8: =IFERROR(VLOOKUP($A8,subQ,MATCH(L$1,SUBQH,0),0),"") | ... Y8: =IFERROR(VLOOKUP($A8,subQ,MATCH(Y$1,SUBQH,0),0),"")
A9: 영업이익 | D9: 영업이익 | E9: =IFERROR(VLOOKUP($A9,subQ,MATCH(E$1,SUBQH,0),0),"") | F9: =IFERROR(VLOOKUP($A9,subQ,MATCH(F$1,SUBQH,0),0),"") | G9: =IFERROR(VLOOKUP($A9,subQ,MATCH(G$1,SUBQH,0),0),"") | H9: =IFERROR(VLOOKUP($A9,subQ,MATCH(H$1,SUBQH,0),0),"") | I9: =IFERROR(VLOOKUP($A9,subQ,MATCH(I$1,SUBQH,0),0),"") | J9: =IFERROR(VLOOKUP($A9,subQ,MATCH(J$1,SUBQH,0),0),"") | K9: =IFERROR(VLOOKUP($A9,subQ,MATCH(K$1,SUBQH,0),0),"") | L9: =IFERROR(VLOOKUP($A9,subQ,MATCH(L$1,SUBQH,0),0),"") | ... Y9: =IFERROR(VLOOKUP($A9,subQ,MATCH(Y$1,SUBQH,0),0),"")
A10: OPM | D10: 영업이익률 | E10: =IFERROR(VLOOKUP($A10,subQ,MATCH(E$1,SUBQH,0),0),"") | F10: =IFERROR(VLOOKUP($A10,subQ,MATCH(F$1,SUBQH,0),0),"") | G10: =IFERROR(VLOOKUP($A10,subQ,MATCH(G$1,SUBQH,0),0),"") | H10: =IFERROR(VLOOKUP($A10,subQ,MATCH(H$1,SUBQH,0),0),"") | I10: =IFERROR(VLOOKUP($A10,subQ,MATCH(I$1,SUBQH,0),0),"") | J10: =IFERROR(VLOOKUP($A10,subQ,MATCH(J$1,SUBQH,0),0),"") | K10: =IFERROR(VLOOKUP($A10,subQ,MATCH(K$1,SUBQH,0),0),"") | L10: =IFERROR(VLOOKUP($A10,subQ,MATCH(L$1,SUBQH,0),0),"") | ... Y10: =IFERROR(VLOOKUP($A10,subQ,MATCH(Y$1,SUBQH,0),0),"")
A11: 금융손익 | D11: 금융손익(이자·환 포함) | E11: =IFERROR(VLOOKUP($A11,subQ,MATCH(E$1,SUBQH,0),0),"") | F11: =IFERROR(VLOOKUP($A11,subQ,MATCH(F$1,SUBQH,0),0),"") | G11: =IFERROR(VLOOKUP($A11,subQ,MATCH(G$1,SUBQH,0),0),"") | H11: =IFERROR(VLOOKUP($A11,subQ,MATCH(H$1,SUBQH,0),0),"") | I11: =IFERROR(VLOOKUP($A11,subQ,MATCH(I$1,SUBQH,0),0),"") | J11: =IFERROR(VLOOKUP($A11,subQ,MATCH(J$1,SUBQH,0),0),"") | K11: =IFERROR(VLOOKUP($A11,subQ,MATCH(K$1,SUBQH,0),0),"") | L11: =IFERROR(VLOOKUP($A11,subQ,MATCH(L$1,SUBQH,0),0),"") | ... Y11: =IFERROR(VLOOKUP($A11,subQ,MATCH(Y$1,SUBQH,0),0),"")
A12: 이자손익 | D12: 이자손익(이자수익 − 이자비용) | E12: =IFERROR(VLOOKUP($A12,subQ,MATCH(E$1,SUBQH,0),0),"") | F12: =IFERROR(VLOOKUP($A12,subQ,MATCH(F$1,SUBQH,0),0),"") | G12: =IFERROR(VLOOKUP($A12,subQ,MATCH(G$1,SUBQH,0),0),"") | H12: =IFERROR(VLOOKUP($A12,subQ,MATCH(H$1,SUBQH,0),0),"") | I12: =IFERROR(VLOOKUP($A12,subQ,MATCH(I$1,SUBQH,0),0),"") | J12: =IFERROR(VLOOKUP($A12,subQ,MATCH(J$1,SUBQH,0),0),"") | K12: =IFERROR(VLOOKUP($A12,subQ,MATCH(K$1,SUBQH,0),0),"") | L12: =IFERROR(VLOOKUP($A12,subQ,MATCH(L$1,SUBQH,0),0),"") | ... Y12: =IFERROR(VLOOKUP($A12,subQ,MATCH(Y$1,SUBQH,0),0),"")
A13: 외환손익 | D13: 외환손익(실적만; 추정 환효과는 환관련손익) | E13: =IFERROR(VLOOKUP($A13,subQ,MATCH(E$1,SUBQH,0),0),"") | F13: =IFERROR(VLOOKUP($A13,subQ,MATCH(F$1,SUBQH,0),0),"") | G13: =IFERROR(VLOOKUP($A13,subQ,MATCH(G$1,SUBQH,0),0),"") | H13: =IFERROR(VLOOKUP($A13,subQ,MATCH(H$1,SUBQH,0),0),"") | I13: =IFERROR(VLOOKUP($A13,subQ,MATCH(I$1,SUBQH,0),0),"") | J13: =IFERROR(VLOOKUP($A13,subQ,MATCH(J$1,SUBQH,0),0),"") | K13: =IFERROR(VLOOKUP($A13,subQ,MATCH(K$1,SUBQH,0),0),"") | L13: =IFERROR(VLOOKUP($A13,subQ,MATCH(L$1,SUBQH,0),0),"") | ... Y13: =IFERROR(VLOOKUP($A13,subQ,MATCH(Y$1,SUBQH,0),0),"")
A14: 파생상품손익 | D14: 파생상품손익 | E14: =IFERROR(VLOOKUP($A14,subQ,MATCH(E$1,SUBQH,0),0),"") | F14: =IFERROR(VLOOKUP($A14,subQ,MATCH(F$1,SUBQH,0),0),"") | G14: =IFERROR(VLOOKUP($A14,subQ,MATCH(G$1,SUBQH,0),0),"") | H14: =IFERROR(VLOOKUP($A14,subQ,MATCH(H$1,SUBQH,0),0),"") | I14: =IFERROR(VLOOKUP($A14,subQ,MATCH(I$1,SUBQH,0),0),"") | J14: =IFERROR(VLOOKUP($A14,subQ,MATCH(J$1,SUBQH,0),0),"") | K14: =IFERROR(VLOOKUP($A14,subQ,MATCH(K$1,SUBQH,0),0),"") | L14: =IFERROR(VLOOKUP($A14,subQ,MATCH(L$1,SUBQH,0),0),"") | ... Y14: =IFERROR(VLOOKUP($A14,subQ,MATCH(Y$1,SUBQH,0),0),"")
A15: 기타금융손익 | D15: 기타금융손익(금융손익 잔차) | E15: =IFERROR(VLOOKUP($A15,subQ,MATCH(E$1,SUBQH,0),0),"") | F15: =IFERROR(VLOOKUP($A15,subQ,MATCH(F$1,SUBQH,0),0),"") | G15: =IFERROR(VLOOKUP($A15,subQ,MATCH(G$1,SUBQH,0),0),"") | H15: =IFERROR(VLOOKUP($A15,subQ,MATCH(H$1,SUBQH,0),0),"") | I15: =IFERROR(VLOOKUP($A15,subQ,MATCH(I$1,SUBQH,0),0),"") | J15: =IFERROR(VLOOKUP($A15,subQ,MATCH(J$1,SUBQH,0),0),"") | K15: =IFERROR(VLOOKUP($A15,subQ,MATCH(K$1,SUBQH,0),0),"") | L15: =IFERROR(VLOOKUP($A15,subQ,MATCH(L$1,SUBQH,0),0),"") | ... Y15: =IFERROR(VLOOKUP($A15,subQ,MATCH(Y$1,SUBQH,0),0),"")
A16: 기타영업외손익 | D16: 기타영업외손익 | E16: =IFERROR(VLOOKUP($A16,subQ,MATCH(E$1,SUBQH,0),0),"") | F16: =IFERROR(VLOOKUP($A16,subQ,MATCH(F$1,SUBQH,0),0),"") | G16: =IFERROR(VLOOKUP($A16,subQ,MATCH(G$1,SUBQH,0),0),"") | H16: =IFERROR(VLOOKUP($A16,subQ,MATCH(H$1,SUBQH,0),0),"") | I16: =IFERROR(VLOOKUP($A16,subQ,MATCH(I$1,SUBQH,0),0),"") | J16: =IFERROR(VLOOKUP($A16,subQ,MATCH(J$1,SUBQH,0),0),"") | K16: =IFERROR(VLOOKUP($A16,subQ,MATCH(K$1,SUBQH,0),0),"") | L16: =IFERROR(VLOOKUP($A16,subQ,MATCH(L$1,SUBQH,0),0),"") | ... Y16: =IFERROR(VLOOKUP($A16,subQ,MATCH(Y$1,SUBQH,0),0),"")
... A41: NPM | D41: NPM | E41: =IFERROR(VLOOKUP($A41,subQ,MATCH(E$1,SUBQH,0),0),"") | F41: =IFERROR(VLOOKUP($A41,subQ,MATCH(F$1,SUBQH,0),0),"") | G41: =IFERROR(VLOOKUP($A41,subQ,MATCH(G$1,SUBQH,0),0),"") | H41: =IFERROR(VLOOKUP($A41,subQ,MATCH(H$1,SUBQH,0),0),"") | I41: =IFERROR(VLOOKUP($A41,subQ,MATCH(I$1,SUBQH,0),0),"") | J41: =IFERROR(VLOOKUP($A41,subQ,MATCH(J$1,SUBQH,0),0),"") | K41: =IFERROR(VLOOKUP($A41,subQ,MATCH(K$1,SUBQH,0),0),"") | L41: =IFERROR(VLOOKUP($A41,subQ,MATCH(L$1,SUBQH,0),0),"") | ... Y41: =IFERROR(VLOOKUP($A41,subQ,MATCH(Y$1,SUBQH,0),0),"")
A42: 매출액 YoY | D42: 매출액 YoY | I42: =IFERROR(I5/E5-1,"") | J42: =IFERROR(J5/F5-1,"") | K42: =IFERROR(K5/G5-1,"") | L42: =IFERROR(L5/H5-1,"") | M42: =IFERROR(M5/I5-1,"") | N42: =IFERROR(N5/J5-1,"") | O42: =IFERROR(O5/K5-1,"") | P42: =IFERROR(P5/L5-1,"") | ... Y42: =IFERROR(Y5/U5-1,"")
A43: 영업이익 YoY | D43: 영업이익 YoY | I43: =IFERROR(I9/E9-1,"") | J43: =IFERROR(J9/F9-1,"") | K43: =IFERROR(K9/G9-1,"") | L43: =IFERROR(L9/H9-1,"") | M43: =IFERROR(M9/I9-1,"") | N43: =IFERROR(N9/J9-1,"") | O43: =IFERROR(O9/K9-1,"") | P43: =IFERROR(P9/L9-1,"") | ... Y43: =IFERROR(Y9/U9-1,"")
A44: 지배주주순이익 YoY | D44: 지배주주순이익 YoY | I44: =IFERROR(I20/E20-1,"") | J44: =IFERROR(J20/F20-1,"") | K44: =IFERROR(K20/G20-1,"") | L44: =IFERROR(L20/H20-1,"") | M44: =IFERROR(M20/I20-1,"") | N44: =IFERROR(N20/J20-1,"") | O44: =IFERROR(O20/K20-1,"") | P44: =IFERROR(P20/L20-1,"") | ... Y44: =IFERROR(Y20/U20-1,"")

Sheet 연간예상
C1: 이름: 연간예상H — subQ 를 이름으로 VLOOKUP(억원) | E1: 2023 | F1: 2024 | G1: 2025 | H1: 2026 | I1: 2027 | J1: 2028
C2: 종가: | D2: =변수!D44
C3: 기준일: | D3: 20261014 | E3: 1 | F3: 2 | G3: 3 | H3: 4 | I3: 5 | J3: 6
E4: 2023.12A | F4: 2024.12A | G4: 2025.12A | H4: 2026.12A | I4: 2027.12A | J4: 2028.12A
A5: 매출액 | D5: 매출액 | E5: =IFERROR(VLOOKUP($A5,subQ,MATCH(E$1,SUBQH,0),0),"") | F5: =IFERROR(VLOOKUP($A5,subQ,MATCH(F$1,SUBQH,0),0),"") | G5: =IFERROR(VLOOKUP($A5,subQ,MATCH(G$1,SUBQH,0),0),"") | H5: =IFERROR(VLOOKUP($A5,subQ,MATCH(H$1,SUBQH,0),0),"") | I5: =IFERROR(VLOOKUP($A5,subQ,MATCH(I$1,SUBQH,0),0),"") | J5: =IFERROR(VLOOKUP($A5,subQ,MATCH(J$1,SUBQH,0),0),"")
A6: 매출원가 | D6: 매출원가 | E6: =IFERROR(VLOOKUP($A6,subQ,MATCH(E$1,SUBQH,0),0),"") | F6: =IFERROR(VLOOKUP($A6,subQ,MATCH(F$1,SUBQH,0),0),"") | G6: =IFERROR(VLOOKUP($A6,subQ,MATCH(G$1,SUBQH,0),0),"") | H6: =IFERROR(VLOOKUP($A6,subQ,MATCH(H$1,SUBQH,0),0),"") | I6: =IFERROR(VLOOKUP($A6,subQ,MATCH(I$1,SUBQH,0),0),"") | J6: =IFERROR(VLOOKUP($A6,subQ,MATCH(J$1,SUBQH,0),0),"")
A7: 매출총이익 | D7: 매출총이익 | E7: =IFERROR(VLOOKUP($A7,subQ,MATCH(E$1,SUBQH,0),0),"") | F7: =IFERROR(VLOOKUP($A7,subQ,MATCH(F$1,SUBQH,0),0),"") | G7: =IFERROR(VLOOKUP($A7,subQ,MATCH(G$1,SUBQH,0),0),"") | H7: =IFERROR(VLOOKUP($A7,subQ,MATCH(H$1,SUBQH,0),0),"") | I7: =IFERROR(VLOOKUP($A7,subQ,MATCH(I$1,SUBQH,0),0),"") | J7: =IFERROR(VLOOKUP($A7,subQ,MATCH(J$1,SUBQH,0),0),"")
A8: 판관비 | D8: 판매비와관리비 | E8: =IFERROR(VLOOKUP($A8,subQ,MATCH(E$1,SUBQH,0),0),"") | F8: =IFERROR(VLOOKUP($A8,subQ,MATCH(F$1,SUBQH,0),0),"") | G8: =IFERROR(VLOOKUP($A8,subQ,MATCH(G$1,SUBQH,0),0),"") | H8: =IFERROR(VLOOKUP($A8,subQ,MATCH(H$1,SUBQH,0),0),"") | I8: =IFERROR(VLOOKUP($A8,subQ,MATCH(I$1,SUBQH,0),0),"") | J8: =IFERROR(VLOOKUP($A8,subQ,MATCH(J$1,SUBQH,0),0),"")
A9: 영업이익 | D9: 영업이익 | E9: =IFERROR(VLOOKUP($A9,subQ,MATCH(E$1,SUBQH,0),0),"") | F9: =IFERROR(VLOOKUP($A9,subQ,MATCH(F$1,SUBQH,0),0),"") | G9: =IFERROR(VLOOKUP($A9,subQ,MATCH(G$1,SUBQH,0),0),"") | H9: =IFERROR(VLOOKUP($A9,subQ,MATCH(H$1,SUBQH,0),0),"") | I9: =IFERROR(VLOOKUP($A9,subQ,MATCH(I$1,SUBQH,0),0),"") | J9: =IFERROR(VLOOKUP($A9,subQ,MATCH(J$1,SUBQH,0),0),"")
A10: OPM | D10: 영업이익률 | E10: =IFERROR(VLOOKUP($A10,subQ,MATCH(E$1,SUBQH,0),0),"") | F10: =IFERROR(VLOOKUP($A10,subQ,MATCH(F$1,SUBQH,0),0),"") | G10: =IFERROR(VLOOKUP($A10,subQ,MATCH(G$1,SUBQH,0),0),"") | H10: =IFERROR(VLOOKUP($A10,subQ,MATCH(H$1,SUBQH,0),0),"") | I10: =IFERROR(VLOOKUP($A10,subQ,MATCH(I$1,SUBQH,0),0),"") | J10: =IFERROR(VLOOKUP($A10,subQ,MATCH(J$1,SUBQH,0),0),"")
A11: 금융손익 | D11: 금융손익(이자·환 포함) | E11: =IFERROR(VLOOKUP($A11,subQ,MATCH(E$1,SUBQH,0),0),"") | F11: =IFERROR(VLOOKUP($A11,subQ,MATCH(F$1,SUBQH,0),0),"") | G11: =IFERROR(VLOOKUP($A11,subQ,MATCH(G$1,SUBQH,0),0),"") | H11: =IFERROR(VLOOKUP($A11,subQ,MATCH(H$1,SUBQH,0),0),"") | I11: =IFERROR(VLOOKUP($A11,subQ,MATCH(I$1,SUBQH,0),0),"") | J11: =IFERROR(VLOOKUP($A11,subQ,MATCH(J$1,SUBQH,0),0),"")
A12: 이자손익 | D12: 이자손익(이자수익 − 이자비용) | E12: =IFERROR(VLOOKUP($A12,subQ,MATCH(E$1,SUBQH,0),0),"") | F12: =IFERROR(VLOOKUP($A12,subQ,MATCH(F$1,SUBQH,0),0),"") | G12: =IFERROR(VLOOKUP($A12,subQ,MATCH(G$1,SUBQH,0),0),"") | H12: =IFERROR(VLOOKUP($A12,subQ,MATCH(H$1,SUBQH,0),0),"") | I12: =IFERROR(VLOOKUP($A12,subQ,MATCH(I$1,SUBQH,0),0),"") | J12: =IFERROR(VLOOKUP($A12,subQ,MATCH(J$1,SUBQH,0),0),"")
A13: 외환손익 | D13: 외환손익(실적만; 추정 환효과는 환관련손익) | E13: =IFERROR(VLOOKUP($A13,subQ,MATCH(E$1,SUBQH,0),0),"") | F13: =IFERROR(VLOOKUP($A13,subQ,MATCH(F$1,SUBQH,0),0),"") | G13: =IFERROR(VLOOKUP($A13,subQ,MATCH(G$1,SUBQH,0),0),"") | H13: =IFERROR(VLOOKUP($A13,subQ,MATCH(H$1,SUBQH,0),0),"") | I13: =IFERROR(VLOOKUP($A13,subQ,MATCH(I$1,SUBQH,0),0),"") | J13: =IFERROR(VLOOKUP($A13,subQ,MATCH(J$1,SUBQH,0),0),"")
A14: 파생상품손익 | D14: 파생상품손익 | E14: =IFERROR(VLOOKUP($A14,subQ,MATCH(E$1,SUBQH,0),0),"") | F14: =IFERROR(VLOOKUP($A14,subQ,MATCH(F$1,SUBQH,0),0),"") | G14: =IFERROR(VLOOKUP($A14,subQ,MATCH(G$1,SUBQH,0),0),"") | H14: =IFERROR(VLOOKUP($A14,subQ,MATCH(H$1,SUBQH,0),0),"") | I14: =IFERROR(VLOOKUP($A14,subQ,MATCH(I$1,SUBQH,0),0),"") | J14: =IFERROR(VLOOKUP($A14,subQ,MATCH(J$1,SUBQH,0),0),"")
A15: 기타금융손익 | D15: 기타금융손익(금융손익 잔차) | E15: =IFERROR(VLOOKUP($A15,subQ,MATCH(E$1,SUBQH,0),0),"") | F15: =IFERROR(VLOOKUP($A15,subQ,MATCH(F$1,SUBQH,0),0),"") | G15: =IFERROR(VLOOKUP($A15,subQ,MATCH(G$1,SUBQH,0),0),"") | H15: =IFERROR(VLOOKUP($A15,subQ,MATCH(H$1,SUBQH,0),0),"") | I15: =IFERROR(VLOOKUP($A15,subQ,MATCH(I$1,SUBQH,0),0),"") | J15: =IFERROR(VLOOKUP($A15,subQ,MATCH(J$1,SUBQH,0),0),"")
A16: 기타영업외손익 | D16: 기타영업외손익 | E16: =IFERROR(VLOOKUP($A16,subQ,MATCH(E$1,SUBQH,0),0),"") | F16: =IFERROR(VLOOKUP($A16,subQ,MATCH(F$1,SUBQH,0),0),"") | G16: =IFERROR(VLOOKUP($A16,subQ,MATCH(G$1,SUBQH,0),0),"") | H16: =IFERROR(VLOOKUP($A16,subQ,MATCH(H$1,SUBQH,0),0),"") | I16: =IFERROR(VLOOKUP($A16,subQ,MATCH(I$1,SUBQH,0),0),"") | J16: =IFERROR(VLOOKUP($A16,subQ,MATCH(J$1,SUBQH,0),0),"")
... A41: NPM | D41: NPM | E41: =IFERROR(VLOOKUP($A41,subQ,MATCH(E$1,SUBQH,0),0),"") | F41: =IFERROR(VLOOKUP($A41,subQ,MATCH(F$1,SUBQH,0),0),"") | G41: =IFERROR(VLOOKUP($A41,subQ,MATCH(G$1,SUBQH,0),0),"") | H41: =IFERROR(VLOOKUP($A41,subQ,MATCH(H$1,SUBQH,0),0),"") | I41: =IFERROR(VLOOKUP($A41,subQ,MATCH(I$1,SUBQH,0),0),"") | J41: =IFERROR(VLOOKUP($A41,subQ,MATCH(J$1,SUBQH,0),0),"")
A42: 매출액 YoY | D42: 매출액 YoY | F42: =IFERROR(F5/E5-1,"") | G42: =IFERROR(G5/F5-1,"") | H42: =IFERROR(H5/G5-1,"") | I42: =IFERROR(I5/H5-1,"") | J42: =IFERROR(J5/I5-1,"")
A43: 영업이익 YoY | D43: 영업이익 YoY | F43: =IFERROR(F9/E9-1,"") | G43: =IFERROR(G9/F9-1,"") | H43: =IFERROR(H9/G9-1,"") | I43: =IFERROR(I9/H9-1,"") | J43: =IFERROR(J9/I9-1,"")
A44: 지배주주순이익 YoY | D44: 지배주주순이익 YoY | F44: =IFERROR(F20/E20-1,"") | G44: =IFERROR(G20/F20-1,"") | H44: =IFERROR(H20/G20-1,"") | I44: =IFERROR(I20/H20-1,"") | J44: =IFERROR(J20/I20-1,"")

Sheet TP
B1: 종가 | C1: =변수!D44
B2: 기준일 | C2: =변수!D45
B3: 모델 산출값 — 목표주가·추천 아님. 밴드·COE 는 변수 시트 3절의 가정
C5: FY | D5: 2025 | E5: 2026 | F5: 2027 | G5: 2028
D6: A | E6: E | F6: E | G6: E
C7: EPS(원) | D7: =IFERROR(VLOOKUP("EPS",subQ,MATCH(D$5,SUBQH,0),0),"") | E7: =IFERROR(VLOOKUP("EPS",subQ,MATCH(E$5,SUBQH,0),0),"") | F7: =IFERROR(VLOOKUP("EPS",subQ,MATCH(F$5,SUBQH,0),0),"") | G7: =IFERROR(VLOOKUP("EPS",subQ,MATCH(G$5,SUBQH,0),0),"")
C8: BPS(원) | D8: =IFERROR(VLOOKUP("BPS",subQ,MATCH(D$5,SUBQH,0),0),"") | E8: =IFERROR(VLOOKUP("BPS",subQ,MATCH(E$5,SUBQH,0),0),"") | F8: =IFERROR(VLOOKUP("BPS",subQ,MATCH(F$5,SUBQH,0),0),"") | G8: =IFERROR(VLOOKUP("BPS",subQ,MATCH(G$5,SUBQH,0),0),"")
C9: 지배주주순이익(억원) | D9: =IFERROR(VLOOKUP("지배주주순이익",subQ,MATCH(D$5,SUBQH,0),0),"") | E9: =IFERROR(VLOOKUP("지배주주순이익",subQ,MATCH(E$5,SUBQH,0),0),"") | F9: =IFERROR(VLOOKUP("지배주주순이익",subQ,MATCH(F$5,SUBQH,0),0),"") | G9: =IFERROR(VLOOKUP("지배주주순이익",subQ,MATCH(G$5,SUBQH,0),0),"")
C10: 영업이익(억원) | D10: =IFERROR(VLOOKUP("영업이익",subQ,MATCH(D$5,SUBQH,0),0),"") | E10: =IFERROR(VLOOKUP("영업이익",subQ,MATCH(E$5,SUBQH,0),0),"") | F10: =IFERROR(VLOOKUP("영업이익",subQ,MATCH(F$5,SUBQH,0),0),"") | G10: =IFERROR(VLOOKUP("영업이익",subQ,MATCH(G$5,SUBQH,0),0),"")
C11: ROE(EPS/기초BPS) | E11: =IFERROR(E7/D8,"") | F11: =IFERROR(F7/E8,"") | G11: =IFERROR(G7/F8,"")
B13: PER
C14: 12M fwd EPS | D14: =IFERROR(E7*변수!D50+F7*(1-변수!D50),"")
C15: 적정가치 @PER_lo | D15: =변수!D47 | E15: =IFERROR(ROUND($D$14*D15,-2),"") | F15: =IFERROR(E15/$C$1-1,"") | G15: 배 · 원 · 종가 대비
C16: 적정가치 @PER_mid | D16: =변수!D48 | E16: =IFERROR(ROUND($D$14*D16,-2),"") | F16: =IFERROR(E16/$C$1-1,"") | G16: 배 · 원 · 종가 대비
C17: 적정가치 @PER_hi | D17: =변수!D49 | E17: =IFERROR(ROUND($D$14*D17,-2),"") | F17: =IFERROR(E17/$C$1-1,"") | G17: 배 · 원 · 종가 대비
C18: 현재 PER(종가/12M fwd EPS) | D18: =IFERROR($C$1/$D$14,"")
B20: PBR
C21: 최근 BPS(마지막 실적 분기) | D21: =IFERROR(VLOOKUP("BPS",subQ,MATCH("2Q26",SUBQH,0),0),"")
C22: ROE fwd(12M fwd EPS / BPS) | D22: =IFERROR($D$14/$D$21,"")
C23: COE | D23: =변수!D46
C24: 적정 PBR = ROE/COE | D24: =IFERROR(D22/D23,"")
C25: 적정가치(PBR) = BPS × 적정PBR | D25: =IFERROR(ROUND(D21*D24,-2),"") | E25: =IFERROR(D25/$C$1-1,"")
C26: 현재 PBR(종가/BPS) | D26: =IFERROR($C$1/D21,"")
B28: 모델 json valuation(참고)
C29: eps_fwd12m | D29: 909.7
C30: bps_latest | D30: 4878.1
C31: per_now | D31: 17.51
C32: pbr_now | D32: 3.27
C33: roe_fwd | D33: 0.1865
C34: fair_pbr | D34: 2.07
C35: fair_value_pbr | D35: 10100
C36: ev_ebitda | D36: 16.13
C37: note | D37: 모델 산출값 — 목표주가·추천 아님

Sheet 외화
C1: 이름: 외화QH — 환율 QoQ · 외화 순노출 × Δ기말환율 | E1: 4Q23 | F1: 1Q24 | G1: 2Q24 | H1: 3Q24 | I1: 4Q24 | J1: 1Q25 | K1: 2Q25 | L1: 3Q25 | M1: 4Q25 | N1: 1Q26 | O1: 2Q26 | P1: 3Q26 | Q1: 4Q26 | R1: 1Q27 | S1: 2Q27 | T1: 3Q27 | U1: 4Q27 | V1: 1Q28 | W1: 2Q28 | X1: 3Q28 | Y1: 4Q28
E3: 1 | F3: 2 | G3: 3 | H3: 4 | I3: 5 | J3: 6 | K3: 7 | L3: 8 | M3: 9 | N3: 10 | O3: 11 | P3: 12 | Q3: 13 | R3: 14 | S3: 15 | T3: 16 | U3: 17 | V3: 18 | W3: 19 | X3: 20 | Y3: 21
E4: 2023.12 | F4: 2024.03 | G4: 2024.06 | H4: 2024.09 | I4: 2024.12 | J4: 2025.03 | K4: 2025.06 | L4: 2025.09 | M4: 2025.12 | N4: 2026.03 | O4: 2026.06 | P4: 2026.09 | Q4: 2026.12 | R4: 2027.03 | S4: 2027.06 | T4: 2027.09 | U4: 2027.12 | V4: 2028.03 | W4: 2028.06 | X4: 2028.09 | Y4: 2028.12
D5: 원/달러(평균) | E5: =IFERROR(VLOOKUP($D5,환율,MATCH(E$1,변수H,0),0),"") | F5: =IFERROR(VLOOKUP($D5,환율,MATCH(F$1,변수H,0),0),"") | G5: =IFERROR(VLOOKUP($D5,환율,MATCH(G$1,변수H,0),0),"") | H5: =IFERROR(VLOOKUP($D5,환율,MATCH(H$1,변수H,0),0),"") | I5: =IFERROR(VLOOKUP($D5,환율,MATCH(I$1,변수H,0),0),"") | J5: =IFERROR(VLOOKUP($D5,환율,MATCH(J$1,변수H,0),0),"") | K5: =IFERROR(VLOOKUP($D5,환율,MATCH(K$1,변수H,0),0),"") | L5: =IFERROR(VLOOKUP($D5,환율,MATCH(L$1,변수H,0),0),"") | ... Y5: =IFERROR(VLOOKUP($D5,환율,MATCH(Y$1,변수H,0),0),"")
A6: 원/달러(평균) QoQ | F6: =IFERROR(F5/E5-1,"") | G6: =IFERROR(G5/F5-1,"") | H6: =IFERROR(H5/G5-1,"") | I6: =IFERROR(I5/H5-1,"") | J6: =IFERROR(J5/I5-1,"") | K6: =IFERROR(K5/J5-1,"") | L6: =IFERROR(L5/K5-1,"") | M6: =IFERROR(M5/L5-1,"") | ... Y6: =IFERROR(Y5/X5-1,"")
D7: 원/달러(기말) | E7: =IFERROR(VLOOKUP($D7,환율,MATCH(E$1,변수H,0),0),"") | F7: =IFERROR(VLOOKUP($D7,환율,MATCH(F$1,변수H,0),0),"") | G7: =IFERROR(VLOOKUP($D7,환율,MATCH(G$1,변수H,0),0),"") | H7: =IFERROR(VLOOKUP($D7,환율,MATCH(H$1,변수H,0),0),"") | I7: =IFERROR(VLOOKUP($D7,환율,MATCH(I$1,변수H,0),0),"") | J7: =IFERROR(VLOOKUP($D7,환율,MATCH(J$1,변수H,0),0),"") | K7: =IFERROR(VLOOKUP($D7,환율,MATCH(K$1,변수H,0),0),"") | L7: =IFERROR(VLOOKUP($D7,환율,MATCH(L$1,변수H,0),0),"") | ... Y7: =IFERROR(VLOOKUP($D7,환율,MATCH(Y$1,변수H,0),0),"")
A8: 원/달러(기말) QoQ | F8: =IFERROR(F7/E7-1,"") | G8: =IFERROR(G7/F7-1,"") | H8: =IFERROR(H7/G7-1,"") | I8: =IFERROR(I7/H7-1,"") | J8: =IFERROR(J7/I7-1,"") | K8: =IFERROR(K7/J7-1,"") | L8: =IFERROR(L7/K7-1,"") | M8: =IFERROR(M7/L7-1,"") | ... Y8: =IFERROR(Y7/X7-1,"")
D9: W/Euro(평균) | E9: =IFERROR(VLOOKUP($D9,환율,MATCH(E$1,변수H,0),0),"") | F9: =IFERROR(VLOOKUP($D9,환율,MATCH(F$1,변수H,0),0),"") | G9: =IFERROR(VLOOKUP($D9,환율,MATCH(G$1,변수H,0),0),"") | H9: =IFERROR(VLOOKUP($D9,환율,MATCH(H$1,변수H,0),0),"") | I9: =IFERROR(VLOOKUP($D9,환율,MATCH(I$1,변수H,0),0),"") | J9: =IFERROR(VLOOKUP($D9,환율,MATCH(J$1,변수H,0),0),"") | K9: =IFERROR(VLOOKUP($D9,환율,MATCH(K$1,변수H,0),0),"") | L9: =IFERROR(VLOOKUP($D9,환율,MATCH(L$1,변수H,0),0),"") | ... Y9: =IFERROR(VLOOKUP($D9,환율,MATCH(Y$1,변수H,0),0),"")
A10: W/Euro(평균) QoQ | F10: =IFERROR(F9/E9-1,"") | G10: =IFERROR(G9/F9-1,"") | H10: =IFERROR(H9/G9-1,"") | I10: =IFERROR(I9/H9-1,"") | J10: =IFERROR(J9/I9-1,"") | K10: =IFERROR(K9/J9-1,"") | L10: =IFERROR(L9/K9-1,"") | M10: =IFERROR(M9/L9-1,"") | ... Y10: =IFERROR(Y9/X9-1,"")
D11: W/Euro(기말) | E11: =IFERROR(VLOOKUP($D11,환율,MATCH(E$1,변수H,0),0),"") | F11: =IFERROR(VLOOKUP($D11,환율,MATCH(F$1,변수H,0),0),"") | G11: =IFERROR(VLOOKUP($D11,환율,MATCH(G$1,변수H,0),0),"") | H11: =IFERROR(VLOOKUP($D11,환율,MATCH(H$1,변수H,0),0),"") | I11: =IFERROR(VLOOKUP($D11,환율,MATCH(I$1,변수H,0),0),"") | J11: =IFERROR(VLOOKUP($D11,환율,MATCH(J$1,변수H,0),0),"") | K11: =IFERROR(VLOOKUP($D11,환율,MATCH(K$1,변수H,0),0),"") | L11: =IFERROR(VLOOKUP($D11,환율,MATCH(L$1,변수H,0),0),"") | ... Y11: =IFERROR(VLOOKUP($D11,환율,MATCH(Y$1,변수H,0),0),"")
A12: W/Euro(기말) QoQ | F12: =IFERROR(F11/E11-1,"") | G12: =IFERROR(G11/F11-1,"") | H12: =IFERROR(H11/G11-1,"") | I12: =IFERROR(I11/H11-1,"") | J12: =IFERROR(J11/I11-1,"") | K12: =IFERROR(K11/J11-1,"") | L12: =IFERROR(L11/K11-1,"") | M12: =IFERROR(M11/L11-1,"") | ... Y12: =IFERROR(Y11/X11-1,"")
D13: 원/100Y(기말) | E13: =IFERROR(VLOOKUP($D13,환율,MATCH(E$1,변수H,0),0),"") | F13: =IFERROR(VLOOKUP($D13,환율,MATCH(F$1,변수H,0),0),"") | G13: =IFERROR(VLOOKUP($D13,환율,MATCH(G$1,변수H,0),0),"") | H13: =IFERROR(VLOOKUP($D13,환율,MATCH(H$1,변수H,0),0),"") | I13: =IFERROR(VLOOKUP($D13,환율,MATCH(I$1,변수H,0),0),"") | J13: =IFERROR(VLOOKUP($D13,환율,MATCH(J$1,변수H,0),0),"") | K13: =IFERROR(VLOOKUP($D13,환율,MATCH(K$1,변수H,0),0),"") | L13: =IFERROR(VLOOKUP($D13,환율,MATCH(L$1,변수H,0),0),"") | ... Y13: =IFERROR(VLOOKUP($D13,환율,MATCH(Y$1,변수H,0),0),"")
A14: 원/100Y(기말) QoQ | F14: =IFERROR(F13/E13-1,"") | G14: =IFERROR(G13/F13-1,"") | H14: =IFERROR(H13/G13-1,"") | I14: =IFERROR(I13/H13-1,"") | J14: =IFERROR(J13/I13-1,"") | K14: =IFERROR(K13/J13-1,"") | L14: =IFERROR(L13/K13-1,"") | M14: =IFERROR(M13/L13-1,"") | ... Y14: =IFERROR(Y13/X13-1,"")
A16: 외화순노출 | C16: 외화 순노출(백만$) | D16: =변수!D57 | E16: 외화 순노출 × Δ기말환율 (외화 시트 방식)
A17: 환관련손익추정 | C17: 환관련손익 추정(억원) = 순노출 × Δ원/달러(기말) / 100 | F17: =IFERROR($D$16*(F7-E7)/100,"") | G17: =IFERROR($D$16*(G7-F7)/100,"") | H17: =IFERROR($D$16*(H7-G7)/100,"") | I17: =IFERROR($D$16*(I7-H7)/100,"") | J17: =IFERROR($D$16*(J7-I7)/100,"") | K17: =IFERROR($D$16*(K7-J7)/100,"") | L17: =IFERROR($D$16*(L7-K7)/100,"") | M17: =IFERROR($D$16*(M7-L7)/100,"") | ... Y17: =IFERROR($D$16*(Y7-X7)/100,"")
A18: fx_pnl.by_q | C18: 모델 fx_pnl.by_q(억원, 참고)
C19: 외화 순노출 미공시(face) → 0 + 표기
